Workbook

Sheet About
A1: Web App Data
A3: This spreadsheet contains data that is used to populate the web application interface
A4: for the Energy Policy Simulator. The data in other tabs in this spreadsheet are used
A5: to establish the policy levers, lever bounds, descriptive text for pop-over
A6: panels, output graphs, and reference scenarios available in the web app.
A8: A live version of the web application interface powered by a copy of this model
A9: can be found at:
A10: https://www.energypolicy.solutions
A12: You are unlikely to need to use or change the contents of this spreadsheet, unless
A13: you are adapting the Energy Policy Simulator to a new country and desire
A14: a web application interface customized for your country-specific model version.
A16: Checks for Policy ID Number Validity
A17: Max policy ID number in use | B17: =MAX(PolicyLevers!H:H) -> 1601
A18: Lowest duplicate ID number | B18: {=IF(MIN(IF(COUNTIF(PolicyLevers!$H$2:$H$1227,PolicyLevers!$H$2:$H$1227)>1,PolicyLevers!$H$2:$H$1227, ""))=0,"No duplicate ID numbers",MIN(IF(COUNTIF(PolicyLevers!$H$2:$H$1227,PolicyLevers!$H$2:$H$1227)>1,PolicyLevers!$H$2:$H$1227, "")))} -> No duplicate ID numbers
A19: Row of first policy missing a valid ID number | B19: {=IF(MIN(IF((NOT(ISNUMBER(PolicyLevers!$H$2:$H$1227)))*(ISTEXT(PolicyLevers!$I$2:$I$1227)),ROW(PolicyLevers!$H$2:$H$1227)))=0,"No missing ID numbers",MIN(IF((NOT(ISNUMBER(PolicyLevers!$H$2:$H$1227)))*(ISTEXT(PolicyLevers!$I$2:$I$1227)),ROW(PolicyLevers!$H$2:$H$1227))))} -> No missing ID numbers
A21: Customizing Policy Levers
A22: Define most policy properties on the "Policy Characteristics" tab.
A23: Specify the subscripted elements of each policy and which are enabled/disabled on the "PolicyLevers" tab.
A24: On the PolicyLevers tab, only manually edit the cells under the green column headers. Simply extend the
A25: existing formulas up or down to fill cells under the red headers on that tab.
A27: Notes on Meaning of Blank Cells on the Policy Characteristics Tab
A28: Leave the "Policy Schedule Subscript" cell blank to deny the ability to edit the implementation
A29: schedule for a lever. This should generally only be done for levers that do not use an
A30: implementation schedule: the toggle to Non-BAU Mandated Capacity Construction
A31: (which has its own schedule built into its input data) and the Nuclear Lifetime Extension
A32: (which simply delays retirements that would occur in the BAU Retirements input data).
A34: Leave the "Policy Group" cell blank to exclude a lever from wedge diagrams and abatement cost curves.
... A53: step size (e.g. 1.5% is not a valid step size, but 1%, 2%, 0.5% and 0.05% are all valid).

Sheet Policy Characteristics
A1: This tab contains information about each policy that does not vary by subscripted element of that policy.
A2: It matches policies to the listing in the "PolicyLevers" tab using the "Vensim Variable Name" column.
A3: Sector | B3: Short Name | C3: Vensim Variable Name | D3: Policy Group | E3: Policy Schedule Subscript | F3: Min Slider Value | G3: Max Slider Value | H3: Slider Step Size | I3: Units | J3: Text for Pop-Over Panel Description | K3: URL for "How the model handles this policy" links | L3: URL for "How to design this policy well" links | M3: Source for Guidance Text (if any) | N3: Source for Max Slider Value (if any)
A4: Transportation | B4: Conventional Pollutant Standards | C4: Percentage Reduction of Separately Regulated Pollutants | D4: Conventional Pollutant Standard | E4: trans reduce regulated pollutants | F4: 0 | G4: 1 | H4: 0.02 | I4: % reduction in emissions | J4: **Description:** This policy represents strengthening standards for the selected pollutant(s) emitted by the selected vehicle type(s). Conventional pollutants' most important, harmful impacts are on human health rather than on climate change. // **Guidance for setting values:** Mexico has multiple regions with serious air quality concerns from fossil fuel combustion. ProAire (local air quality programs) have been deployed in major cities with some strong measures like those deployed for the Mexico City metropolitan area (strengthening air quality standards, re-zoning industrial areas, emissions registry and inventory, semi-annual vehicle inspections and limits to vehicle use). | K4: transportation-sector-main.html#conv-pol-stds | L4: conventional-pollutant-standards.html
A5: Transportation | B5: Electric Vehicle Charger Deployment | C5: EV Charger Deployment | D5: EV Charger Deployment | E5: trans EV charger deployment | F5: 0 | G5: 300 | H5: 5 | I5: chargers / 100k pop | J5: **Description:** This policy represents increasing the deployment of EV charging stations, including DC Fast and Level 2 charging stations. It is set in chargers per 100,000 people (cumulative, not per year), additional to chargers in the Reference case. This policy lever does not have an effect on energy use/emissions/deployment. It is meant to account for the costs of additional charging infrastructure. // **Guidance for setting values:** As of Mar 2019, the U.S. had 63,000 chargers, just under 20 chargers per 100k pop. In 2016, the U.S. had 111,076 gas stations with an average of 8 fuel pumps each, or 275 pumps per 100k pop. Therefore, a lever setting of 255 would cause the population density of EV chargers to equal the 2016 population density of fuel pumps. | L5: ev-charger-deployment.html | M5: Number of EV chargers: https://evadoption.com/ev-charging-stations-statistics/ Number of gas stations: U.S. Census, Statistics of U.S. Businesses, https://www.census.gov/data/tables/2016/econ/susb/2016-susb-annual.html Pumps per station: https://247wallst.com/economy/2014/05/22/why-are-there-115000-or-150000-gas-stations-in-america/
A6: Transportation | B6: Electric Vehicle Range & Charging Time | C6: Reduce EV Range Anxiety and Charging Time | D6: EV Range & Charging Time | E6: trans reduce EV range anxiety and charging time | F6: 0 | G6: 1 | H6: 0.02 | I6: % reduction in concern | J6: **Description:** This policy specifies a percentage reduction in vehicle buyers' aversion to electric vehicles due to concerns over the vehicles' range (how far the EV can travel on a charge) and charging time. A 100% setting implies consumers are no more concerned about EV range and charging time than they are about range and fueling time of gasoline vehicles. It does not imply that range is infinite, nor that charging is instantaneous. This policy only affects passenger LDVs. // **Guidance for setting values:** U.S. model year 2017 all-electric (not hybrid) vehicles had ranges from 58 to 335 miles (median 114 miles), and the typical charging time was 0.5 hours (with a DC Fast charger) or 3.5 hours (with a Level 2 charger). | L6: reduce-range-anxiety-charging-time.html | M6: Ranges: https://www.energy.gov/eere/vehicles/articles/fotw-1010-january-1-2018-all-electric-light-vehicle-ranges-can-exceed-those Charging Times: https://www.chargepoint.com/files/Quick_Guide_to_Fast_Charging.pdf
A7: Transportation | B7: Electric Vehicle Sales Standard | C7: Additional Minimum Required EV Sales Percentage | D7: EV Sales Standard | E7: trans EV minimum | F7: 0 | G7: 1 | H7: 0.01 | I7: % of new vehicles sold | J7: **Description:** This policy requires the specified percentage of newly sold vehicles of the selected type(s) to consist of battery electric vehicles. If that percentage would already be achieved through Reference Case sales plus the effects of other policies, such as an EV subsidy, this policy has no effect. Manufactures may meet a sales standard through techniques such as more heavily marketing electric vehicles, lowering the price of electric vehicles, or raising the price of non-electric vehicles. // **Guidance for setting values:** // **Passenger LDVs:** California's Zero Emission Vehicle (ZEV) program requires automakers to sell ZEVs in California and 10 other states, which will likely require about 7% to 10% new vehicle sales in 2025. California recently passed an executive order to phase out sales of new gas cars by 2035, which would be equivalent to a setting of 100% in 2035. // **Freight Trucks:** Today, the share of electric freight trucks is very low, but electrification is particularly promising for certain types of trucks, such as those used to make deliveries within cities, those involved in port operations, garbage trucks, and others with frequent starts and stops. // **Passenger HDVs:** Electric bus manufacturer Proterra believes all new transit bus sales could be electric as early as 2030, but transit buses make up roughly 15% of the bus fleet. // **Aircraft:** Electricity is commonly used by drones, and small, manned electric aircraft have been developed. However, limited payload and range may complicate the electrification potential of large, long-haul aircraft. Therefore, a low setting of this policy lever may be more realistic than a high setting. // **Passenger Rail:** Today, in the United States, slightly more than half of all energy used for passenger rail consists of electricity, largely for urban metro and commuter rail systems. Electrifying more rail requires installing electric guidewires or an electrified third rail along existing corridors, or the development of new rail corridors. With sufficient investment, most or all passenger rail could potentially be electrified, but many years may be required to complete the associated infrastructure upgrades. // **Freight Rail:** Today, in the United States, little if any freight rail is electrified. However, slightly more than half of all energy used for passenger rail consists of electricity, largely for urban metro and commuter rail systems. It may be possible to use some of the same approaches to electrify freight rail. Electrified rail corridors must have sufficient transformer and other electrical capacity to handle the heavy loads of freight rail. The required infrastructure investments may be substantial and may take many years to complete. // **Passenger Ships:** Although only a small percentage of recreational boats are powered by electricity today, the market for electric recreational boats is growing rapidly and is projected to reach $20 billion / year globally by 2027. Batteries and electric motors are suitable for the typical travel distances and demand cycles of most small pleasure craft, and in some cases, it is possible to retrofit an existing boat with an electric outboard motor and batteries. Accordingly, a high setting of this policy lever may be reasonable. // **Freight Ships:** Today, few freight ships rely solely on electricity for energy. The large loads and long distances traveled by ocean-going vessels (with no opportunity to charge while underway) limit the suitability of electricity for these vessel types. However, there are freight vessels better-suited to electricity, including tug boats (which benefit from the high torque of electric motors) and offshore support vessels (which carry personnel and goods between offshore platforms and the mainland, and perform other support tasks), as these types of vessels travel predictable distances and may easily return to a dock to charge. Accordingly, a modest setting of this policy lever may be reasonable. // **Passenger Motorbikes:** Though electric motorcycles and scooters are popular in Europe and Asia, where motorbikes are commonly used for urban transportation and commuting, electric motorbikes are not yet a significant presence in the U.S., where motorbikes are mostly used for recreation. | K7: transportation-sector-main.html#ev-mandate | L7: ev-mandate.html | M7: https://autoalliance.org/energy-environment/state-electric-vehicle-mandate/ https://www.cnbc.com/2019/08/26/colorado-joins-california-in-requiring-automakers-to-sell-more-evs.html https://www.consumerreports.org/hybrids-evs/california-says-new-cars-sold-in-the-state-must-be-zero-emissions-by-2035/ https://www.greentechmedia.com/articles/read/electric-buses-are-going-to-dominate statistics from FoVObE variable https://www.prnewswire.com/news-releases/electric-boats-and-ships-2017-2027-300561222.html
A8: Transportation | B8: Electric Vehicle Subsidy | C8: Additional EV Subsidy Percentage | D8: EV Subsidy | E8: trans EV subsidy | F8: 0 | G8: 0.5 | H8: 0.01 | I8: % of vehicle cost | J8: **Description:** This policy causes government to pay for the specified percentage of the purchase price of new battery electric passenger LDVs. This is in addition to EV subsidies that exist in the Reference Case case. // **Guidance for setting values:** The U.S. currently offers a federal subsidy for up to $7,500 for qualifying electric vehicles, which represents 20% of the MSRP of a 2017 Chevrolet Bolt EV or 21% of the MSRP of a Tesla Model 3. | K8: transportation-sector-main.html#ev-subsidy | L8: ev-subsidy.html | M8: https://www.fueleconomy.gov/feg/taxevb.shtml plus Chevrolet and Tesla websites
A9: Transportation | B9: Feebate | C9: LDVs Feebate Rate | D9: Feebate | E9: trans LDVs feebate | F9: 0 | G9: 1 | H9: 0.02 | I9: % of global best practice rate | J9: **Description:** This policy implements a fee on sales of inefficient light-duty vehicles (LDVs; namely cars and SUVs) that is rebated to buyers of efficient LDVs. The feebate policy is revenue-neutral, as the pivot point (the efficiency level that incurs neither a rebate nor a fee) is set such that the total of all fees equals the total of all rebates. // **Guidance for setting values:** The feebate is set as a fraction of the global best practice feebate rate. The global best practice feebate rate is $2000 per (hundredth gal/mile), which equates to a $2000 fee on an LDV that gets 20 mpg if the pivot point is 25 mpg. (To see this: 20 mpg is 0.04 gpm. 25 mpg is 0.05 gpm. The difference is -.01 gpm. So in order to levy a $2000 fee on the 20 mpg car when the pivot point is 25 mpg, we need a rate of $2000/.01 gpm.) | K9: transportation-sector-main.html#feebate | L9: feebate.html | M9: Greene et al., 2005, "Feebates, rebates and gas-guzzler taxes: a study of incentives for increased fuel economy", Energy Policy, 33(6), 757-775, http://cta.ornl.gov/cta/Publications/Reports/FeebateEnergyPolicy_FINAL.pdf. | N9: John German and Dan Meszler, 2010, "Best Practices for Feebate Program Design and Implementation", ICCT, http://www.theicct.org/sites/default/files/publications/ICCT_feebates_may2010.pdf, Table 2
A10: Transportation | B10: Fuel Economy Standard | C10: Percentage Additional Improvement of Fuel Economy Std | D10: Vehicle Fuel Economy Standards | E10: trans fuel economy standards | F10: 0 | G10: 1 | H10: 0.01 | I10: % increase in miles/gal | J10: **Description:** This policy specifies a percentage improvement in fuel economy (distance traveled on the same quantity of fuel with the same cargo or passenger loading) due to fuel economy standards for newly sold vehicles of the selected type(s) with fossil fuel-burning engines. // **Guidance for setting values:** // **LDVs:** U.S. combined fuel economy standards for cars and light trucks were 35.5 mpg in 2016 and are scheduled to rise to 54.5 through 2025, then remain constant. The National Research Council has identified a maximum 4.5% annual improvement in LDV fuel economy through 2040, which corresponds to a policy setting of 88%. // **Passenger HDVs:** U.S. fuel economy standards for heavy-duty vehicles vary by vehicle characteristics, but proposed standards for vocational vehicles (the category that includes buses) would reduce GHG emissions by 24% for 2027 model year vehicles relative to the 2018 model year, then remain constant. Extrapolating this trend to 2050 would be an 85% improvement relative to 2018, compared to a 40% improvement relative to 2018 in the Reference Case case. This could be represented by a policy lever setting of 45%. // **Freight HDVs:** U.S. fuel economy standards for heavy-duty vehicles vary by vehicle characteristics, but proposed standards for combination tractor-trailers (which are responsible for roughly 60% of HDV emissions) would reduce GHG emissions by 25% for 2027 model year trucks relative to the 2018 model year, then remain constant. Extrapolating this trend to 2050 would be an 96% improvement relative to 2018, compared to a 40% improvement relative to 2018 in the Reference Case case. This could be represented by a policy lever setting of 56%. // **Passenger Aircraft:** The U.S. currently does not have fuel economy standards for aircraft. In the absence of standards, new passenger aircraft fuel economy is projected to improve roughly 17% from 2018-2050 in the Reference Case case. // **Freight Aircraft:** The U.S. currently does not have fuel economy standards for aircraft. In the absence of standards, new freight aircraft fuel economy is projected to improve roughly 50% from 2018-2050 in the Reference Case case. // **Passenger Rail:** The U.S. currently does not have fuel economy standards for trains. In the absence of standards, new passenger train fuel economy is not projected to change significantly from 2018-2050 in the Reference Case case. // **Freight Rail:** The U.S. currently does not have fuel economy standards for trains. In the absence of standards, new freight train fuel economy is projected to improve roughly 23% from 2018-2050 in the Reference Case case. // **Passenger Ships:** The U.S. currently does not have fuel economy standards for ships. In the absence of standards, new passenger ship fuel economy is not projected to change significantly from 2018-2050 in the Reference Case case. // **Freight Ships:** The U.S. currently does not have fuel economy standards for ships. In the absence of standards, new freight ship fuel economy is projected to improve roughly 21% from 2018-2050 in the Reference Case case. however, the ICCT suggests in-use CO2 intensity of freight ships could fall by roughly 50% by 2040, corresponding to a 100% improvement in fuel economy. // **Passenger Motorbikes:** The U.S. currently does not have fuel economy standards for motorbikes. In the absence of standards, new motorbike fuel economy is not projected to change significantly from 2018-2050 in the Reference Case case. | K10: transportation-sector-main.html#fuel-econ-std | L10: fuel-economy-standard.html | M10: U. S. EPA, 2012, "Fact Sheet: EPA and NHTSA Set Standards to Reduce Greenhouse Gases and Improve Fuel Economy for Model Years 2017-2025 Cars and Light Trucks", https://nepis.epa.gov/Exe/ZyNET.exe/P100EZ7C.txt?ZyActionD=ZyDocument&Client=EPA&Index=2011%20Thru%202015&Docs=&Query=&Time=&EndTime=&SearchMethod=1&TocRestrict=n&Toc=&TocEntry=&QField=&QFieldYear=&QFieldMonth=&QFieldDay=&UseQField=&IntQFieldOp=0&ExtQFieldOp=0&XmlQuery=&File=D%3A%5CZYFILES%5CINDEX%20DATA%5C11THRU15%5CTXT%5C00000005%5CP100EZ7C.txt&User=ANONYMOUS&Password=anonymous&SortMethod=h%7C-&MaximumDocuments=1&FuzzyDegree=0&ImageQuality=r75g8/r75g8/x150y150g16/i425&Display=hpfr&DefSeekPage=x&SearchBack=ZyActionL&Back=ZyActionS&BackDesc=Results%20page&MaximumPages=1&ZyEntry=4, Table 1, Row 4. U.S. EPA, 2015, "EPA and NHTSA Propose Standards to Reduce Greenhouse Gas Emissions and Improve Fuel Efficiency of Medium- and Heavy-Duty Vehicles for Model Year 2018 and Beyond", https://nepis.epa.gov/Exe/ZyNET.exe/P100P7NL.txt?ZyActionD=ZyDocument&Client=EPA&Index=2016%20Thru%202020&Docs=&Query=&Time=&EndTime=&SearchMethod=1&TocRestrict=n&Toc=&TocEntry=&QField=&QFieldYear=&QFieldMonth=&QFieldDay=&UseQField=&IntQFieldOp=0&ExtQFieldOp=0&XmlQuery=&File=D%3A%5CZYFILES%5CINDEX%20DATA%5C16THRU20%5CTXT%5C00000002%5CP100P7NL.txt&User=ANONYMOUS&Password=anonymous&SortMethod=h%7C-&MaximumDocuments=1&FuzzyDegree=0&ImageQuality=r75g8/r75g8/x150y150g16/i425&Display=hpfr&DefSeekPage=x&SearchBack=ZyActionL&Back=ZyActionS&BackDesc=Results%20page&MaximumPages=1&ZyEntry=3, Page 3. https://theicct.org/sites/default/files/publications/ICCT_ShipEfficiency_20130723.pdf Others calculated from model input data. | N10: National Research Council, 2013, "Transitions to Alternative Vehicles and Fuels", https://www.nap.edu/catalog/18264/transitions-to-alternative-vehicles-and-fuels, Table 2.9, Fuel economy test mpg. U.S. DoE, 2013, "Potential for Energy Efficiency Improvement Beyond the Light-Duty-Vehicle Sector," http://www.nrel.gov/docs/fy13osti/55637.pdf, Table 2.2 and Section 3.4.5, Paragraph 1 David McCollum, Gregory Gould, and Davide Greene, 2009, "Greenhouse Gas Emissions from Aviation and Marine Transportation: Mitigation Potential and Policies", Pew Center on Global Climate Change, http://www.c2es.org/docUploads/aviation-and-marine-report-2009.pdf, Table 4 https://theicct.org/sites/default/files/publications/ICCT_ShipEfficiency_20130723.pdf
A11: Transportation | B11: Hydrogen Vehicle Sales Standard | C11: Minimum Required Hydrogen Vehicle Sales Percentage | D11: Hydrogen Veh Sales Standard | E11: trans hydrogen vehicle minimum | F11: 0 | G11: 1 | H11: 0.01 | I11: % of new vehicles sold | J11: **Description:** This policy requires the specified percentage of newly sold vehicles of the selected type(s) to consist of hydrogen vehicles. If that percentage would already be achieved through Reference Case sales plus the effects of other policies, this policy has no effect. Manufactures may meet a sales standard through techniques such as more heavily marketing hydrogen vehicles, lowering the price of hydrogen vehicles, or raising the price of non-hydrogen vehicles. // **Guidance for setting values:** // **Road Vehicles:** No U.S. state has a hydrogen vehicle sales mandate (though hydrogen vehicles are included as a compliance option under zero-emissions vehicle mandates). Only about 5000 hydrogen vehicles are on U.S. roads today (roughly 0.002% of U.S. vehicles). Japan, potentially the country with the greatest commitment to hydrogen vehicles, aims to have 200,000 hydrogen vehicles on its roads by 2025 (which will comprise roughly 0.3% of Japan's vehicles). // **Aircraft:** The use of hydrogen as a fuel for aircraft has been studied, and small prototype aircraft have been built and flown. However, this remains a technology in early stages, and much research and development work would be required to reach commercialization, particularly for large aircraft. // **Rail:** Hydrogen is not commonly used for rail vehicles today, but given trains' ability to carry large fuel tanks, no serious technical barriers exist to more widespread usage. The first hydrogen-powered train, the Coradia iLint, entered service in 2018 (in Germany), and 14 more hydrogen trains are planned for that line. // **Ships:** Hydrogen is not commonly used for ships today, but given ships' ability to carry large fuel tanks, no serious technical barriers exist to more widespread usage. A handful of hydrogen-powered ships have entered service since the mid-2000s, including several passenger ferries. Due to the difficulty of making battery electric, long-haul freight ships, hydrogen is often seen as one of the best options for decarbonizing these types of ships. | L11: hydrogen-vehicle-mandate.html | M11: https://wamu.org/story/19/03/18/japan-is-betting-big-on-the-future-of-hydrogen-cars/
A12: Transportation | B12: Low Carbon Fuel Standard | C12: Additional LCFS Percentage | D12: Low Carbon Fuel Standard | E12: trans LCFS | F12: 0 | G12: 0.2 | H12: 0.01 | I12: % reduction in carbon emissions | J12: **Description:** This policy specifies the percentage reduction in carbon emissions from the transportation sector that must be achieved via fuel switching. This value is in addition to Reference Case requirements. // **Guidance for setting values:** The U.S. National Renewable Fuel Standard equates to a Reference Case LCFS of 2.2% - 4.6% (varying by year). California adopted an LCFS that requires a 10% reduction in carbon intensity of the transportation fuel pool by 2020. | K12: transportation-sector-main.html#lcfs | L12: low-carbon-fuel-standard.html | M12: https://www.arb.ca.gov/fuels/lcfs/background/basics.htm
A13: Transportation | B13: Mode Shifting | C13: Percent of Travel Demand Shifted to Other Modes or Eliminated | D13: Mode Shifting | E13: trans mode shifting | F13: 0 | G13: 0.26 | H13: 0.01 | I13: % of trips shifted | J13: **Description:** This policy represents a set of measures aimed at reducing demand for passenger or freight transportation in the selected vehicle type(s). **Passenger LDV** trips may be shifted to other travel modes, such as buses, rail, walking, biking, or eliminated through technology such as videoconferencing. Example measures include improved public transit systems, more walking and bike paths, zoning for higher density along transit corridors, zoning for mixed-use developments, roadway and congestion pricing, and increased parking fees. **Aircraft** trips may be shifted to inter-city rail or eliminated using technology such as videoconferencing. **Freight Truck** trips can be reduced through improved logistics that avoids backhauls and transporting empty shipping containers. // **Guidance for setting values:** // **Passenger LDVs:** The International Energy Agency's BLUE Shifts scenario (from the 2009 report "Transport, Energy, and CO2: Moving Toward Sustainability") includes a 26% reduction in usage of cars and SUVs in OECD countries by 2050 relative to a Reference Case case. // **Aircraft:** The International Energy Agency's BLUE Shifts scenario (from the 2009 report "Transport, Energy, and CO2: Moving Toward Sustainability") includes a 30% reduction in usage of aircraft in OECD countries by 2050 relative to a Reference Case case. // **Freight Trucks:** The U.S. Federal Highway Administration reports that approximately 25% of mileage for trucks larger than pickups/minivans/other light vans are for empty backhauls and empty shipping containers. | K13: transportation-sector-main.html#tdm | L13: transportation-demand-management.html | M13: International Energy Agency, 2009, "Transport, Energy and CO2: Moving toward Sustainability", http://www.iea.org/publications/freepublications/publication/transport2009.pdf "Freight Facts and Figures", 2013, https://ops.fhwa.dot.gov/freight/freight_analysis/nat_freight_stats/docs/13factsfigures/pdfs/fff2013_highres.pdf
A14: Buildings and Appliances | B14: Building Component Electrification | C14: Fraction of New Bldg Components Shifted to Other Fuels | D14: Building Component Electrification | E14: bldgs new component fuel shifting | F14: 0 | G14: 1 | H14: 0.01 | I14: % of newly sold non-electric building components | J14: **Description:** This policy replaces the specified fraction of newly sold non-electric building components of the selected type(s) in buildings of the selected type(s) with electricity-using components. // **Guidance for setting values: ** // **Mexico:** // In the Reference case for Mexico, the share of electricity among fuels used by urban and rural residential buildings its 28% in Mexico, and in commercial buildings is 50%. // ** ** // **Urban Residential Heating:** // In the Reference Case case, in the United States, the share of electricity among fuels used for heating in urban, residential buildings will fall from 12% to 11% through 2050. // **Urban Residential Appliances:** In the Reference Case case, in the United States, the share of electricity among fuels used by appliances in urban, residential buildings will remain constant at roughly 50% through 2050. // **Urban Residential Other Components:** In the Reference Case case, in the United States, the share of electricity among fuels used by other components in urban, residential buildings will rise from 87% to 88% through 2050. // **Rural Residential Heating:** In the Reference Case case, in the United States, the share of electricity among fuels used for heating in rural, residential buildings will fall from 12% to 11% through 2050. // **Rural Residential Appliances:** In the Reference Case case, in the United States, the share of electricity among fuels used by appliances in rural, residential buildings will remain constant at roughly 50% through 2050. // **Rural Residential Other Components:** In the Reference Case case, in the United States, the share of electricity among fuels used by other components in urban, residential buildings will rise from 87% to 88% through 2050. // **Commercial Heating:** In the Reference Case case, in the United States, the share of electricity among fuels used for heating in commercial buildings will fall from 4% to 3% through 2050. // **Commercial Appliances:** In the Reference Case case, in the United States, the share of electricity among fuels used by appliances in commercial buildings will fall from 45% to 42% through 2050. // **Commercial Other Components:** In the Reference Case case, in the United States, the share of electricity among fuels used by other components in commercial buildings will fall from 68% to 65% through 2050. | K14: buildings-sector-main.html#component-elec | L14: building-component-electrification.html | M14: EIA AEO
A15: Buildings and Appliances | B15: Building Energy Efficiency Standards | C15: Reduction in E Use Allowed by Component Eff Std | D15: Building Energy Efficiency Standards | E15: bldgs efficiency standards | F15: 0 | G15: 0.75 | H15: 0.01 | I15: % reduction in energy use | J15: **Description:** This policy tightens energy efficiency standards for the selected component(s) in the selected building type(s). The policy only applies to newly sold components each year (whether for new buildings or replacement of old components of existing buildings). // **Guidance for setting values:** In "Assessment of Electricity Savings in the U.S. Achievable through New Appliance/Equipment Efficiency Standards and Building Efficiency Codes, 2010-2025" (2011), the Edison Foundation considered a 30% reduction in whole-building energy use (moderate case) and 40-45% (aggressive case) relative to Reference Case from 2010 to 2025. | K15: buildings-sector-main.html#eff-stds | L15: building-energy-efficiency-standards.html | M15: Edison Foundation, 2011, "Assessment of Electricity Savings in the U.S. Achievable through New Appliance/Equipment Efficiency Standards and Building Efficiency Codes (2010 - 2025)", http://www.edisonfoundation.net/iei/Documents/IEE_CodesandStandardsAssessment_2010-2025_UPDATE.pdf, Page B-2, Table B-1. | N15: Itron, 2007, "ASSESSMENT OF LONG-TERM ELECTRIC ENERGY EFFICIENCY POTENTIAL IN CALIFORNIA’S RESIDENTIAL SECTOR," http://www.energy.ca.gov/2007publications/CEC-500-2007-002/CEC-500-2007-002.PDF, p.33, Table 5-1
A16: Buildings and Appliances | B16: Contractor Training | C16: Boolean Improved Contractor Edu and Training | D16: Contractor Training | E16: bldgs contractor training | F16: 0 | G16: 1 | H16: 1 | I16: on/off | J16: **Description:** This policy represents a program to train contractors in energy-efficient products and installation practices. This covers activities such as air sealing, building framing, and choice and application of insulation. This policy affects newly sold building envelope components, which reduce the energy use of heating, cooling, and ventilation systems in buildings by 3.7% (based on a 2006 study from the Energy Center of Wisconsin). | K16: buildings-sector-main.html#contractor-ed | L16: contractor-training.html
A17: Buildings and Appliances | B17: Distributed Solar Carve-Out | C17: Min Fraction of Total Elec Demand to be Met by Distributed Solar PV | D17: Distributed Solar Promotion | E17: bldgs min fraction distributed solar | F17: 0 | G17: 0.24 | H17: 0.005 | I17: minimum % elec from solar | J17: **Description:** This policy requires at least the specified percentage of total retail electricity demand to be generated by residential and commercial buildings' distributed solar systems (typically rooftop PV). // **Guidance for setting values:** Colorado has established a 3% carve-out for 2020 (though it includes non-solar on-site sources). | K17: buildings-sector-main.html#solar-carve-out | L17: solar-carve-out.html | M17: MASSACHUSETTS: http://www.mass.gov/eea/energy-utilities-clean-tech/renewable-energy/solar/rps-solar-carve-out/current-status-of-the-rps-solar-carve-out-program.html COLORADO: http://www.seia.org/research-resources/rps-solar-carve-out-colorado | N17: RMI, 2011, "Reinventing Fire Electricity Sector Methodology," http://www.rmi.org/cms/Download.aspx?id=10765&file=Reinventing+Fire+Electricity+Sector+Methodology.pdf&title=Reinventing+Fire+Electricity+Sector+Methodology, Page 11, 2050 Generation by Case
A18: Buildings and Appliances | B18: Distributed Solar Subsidy | C18: Perc Subsidy for Distributed Solar PV Capacity | D18: Distributed Solar Promotion | E18: bldgs distributed solar subsidy | F18: 0 | G18: 0.5 | H18: 0.01 | I18: % of PV system cost | J18: **Description:** This policy causes the government to reimburse building owners for a percentage of the cost of new distributed solar PV capacity that is installed on or around buildings. // **Guidance for setting values:** The federal Business Energy Investment Tax Credit (ITC) (whose effects are accounted for in the Reference Case case in this simulator) offers a 30% rebate through 2019, with lower values thereafter. Mexico has used similar subsidies in their sustainable housing programs, where efficient components are swapped freely or available at a reduced cost for social-interest housing. | K18: buildings-sector-main.html#distributed-solar-subsidy | L18: distributed-solar-subsidy.html | M18: Department of Energy. Business Energy Investment Tax Credit (ITC). http://energy.gov/savings/business-energy-investment-tax-credit-itc
A19: Buildings and Appliances | B19: Improved Labeling | C19: Boolean Improved Device Labeling | D19: Improved Labeling | E19: bldgs device labeling | F19: 0 | G19: 1 | H19: 1 | I19: on/off | J19: **Description:** This policy represents a program requiring newly sold heating systems, cooling and ventilation systems, and appliances to feature prominent, well-designed labels highlighting their energy efficiencies. The policy reduces energy consumption of newly sold building components of these types by 10%. | K19: buildings-sector-main.html#device-labeling | L19: improved-labeling.html | M19: none
A20: Buildings and Appliances | B20: Retrofit Existing Buildings | C20: Share of Preexisting Buildings Subject to Retrofitting | D20: Increased Retrofitting | E20: bldgs retrofitting | F20: 0 | G20: 0.5 | H20: 0.01 | I20: % of existing buildings | J20: **Description:** Each year, the specified percentage of the selected building type(s) that existed at the start of the model run will be retrofit with more efficient heating, cooling, and envelope components. // **Guidance for setting values:** By 2050, roughly 37% of the preexisting buildings will still survive without major renovations, so a value of 37% will retrofit all such surviving buildings by 2050. Policy settings higher than this will retrofit all eligible buildings sooner than 2050. | K20: buildings-sector-main.html#retrofitting | L20: increased-retrofitting.html | M20: Calculated from model data; see the relevant variable(s) in the InputData folder for source information.
A21: Buildings and Appliances | B21: Rebate for Efficient Products | C21: Boolean Rebate Program for Efficient Components | D21: Rebate for Efficient Products | E21: bldgs rebate | F21: 0 | G21: 1 | H21: 1 | I21: on/off | J21: **Description:** This policy represents a modest rebate paid to customers who purchase energy-efficient building equipment of the selected type(s). Typical rebate amounts represented by this policy are $50-100 for a clothes washer and $25-50 for a dishwasher or refrigerator. Mexico has used similar subsidies in their sustainable housing programs, where old components are swapped freely or at a discount. | K21: buildings-sector-main.html#rebate | L21: rebate-for-efficient-products.html
A22: Electricity Supply | B22: Ban New Power Plants | C22: Boolean Ban New Power Plants | D22: Ban New Power Plants | E22: elec ban new power plants | F22: 0 | G22: 1 | H22: 1 | I22: on/off | J22: **Description:** This policy prevents new capacity of the selected type(s) from being built or deployed. | K22: electricity-sector-main.html#ban | L22: ban-new-capacity.html
A23: Electricity Supply | B23: Carbon Capture and Sequestration | C23: Electricity Sector Fraction of Potential Additional CCS Achieved | D23: Electricity Sector CCS | E23: elec CCS | F23: 0 | G23: 1 | H23: 0.01 | I23: % of CO2 captured | J23: **Description:** This policy specifies the fraction of CO2 emissions from power plants that is captured and stored, above the amount predicted in the business-as-usual scenario. // **Guidance for setting values:** As very few CCS-equipped power plants exist today, a value above 20% or so is likely very optimistic in most policy scenarios. The main exception would be a scenario in which most fossil power plants retire due to other policies, making it feasible to equip a high percentage of the few surviving fossil plants with CCS. | K23: ccs.html#ccs | L23: carbon-capture-and-sequestration.html
A24: Electricity Supply | B24: Clean Electricity Standard | C24: Renewable Portfolio Std Percentage | D24: Clean Electricity Standard | E24: elec renewable portfolio standards | F24: 0 | G24: 1 | H24: 0.01 | I24: % of electricity generation | J24: **Description:** This policy specifies an increase in the fraction of electricity generation that must come from qualifying carbon-free sources (wind, solar, biomass, nuclear, hydro, and geothermal) in 2050. This policy has no effect until the user-set value exceeds the existing fraction of carbon-free electricity and any carbon-free electricity standards which have been enacted at the state level, which in total reaches 51% in 2050 as a generation-weighted national average. In 2020, the value is 36%. To set a carbon-free electricity standard that starts ramping up in 2021, the Customize Implementation Schedule feature below allows users to customize the start year setting. Simply take the 36% value, divide by your chosen policy setting, and enter the resulting value in the "Implementation %" box for 2020. // **Guidance for setting values:** Multiple states have set 100% clean energy or renewable energy laws or goals, including California, Hawaii, New Jersey, New York, Washington, New Mexico, Maine, Wisconsin, Minnesota, Nevada, and Washington DC. The earliest 100% target is Washington DC by 2032, with other states pledging to reach 100% clean or renewable energy by 2040-2050. When setting a high CES with this lever, users should also turn on supporting power sector policies (i.e., Grid-Scale Electricity Storage, Increase Transmission, and Demand Response) to avoid curtailment of renewables. At very high CES values, the associated policy costs are highly uncertain and should be complemented with other modeling. | K24: electricity-sector-main.html#ces | L24: clean-energy-standard.html | M24: White House, 2015, "Fact Sheet: President Obama to Announce Historic Carbon Pollution Standards for Power Plants", https://www.whitehouse.gov/the-press-office/2015/08/03/fact-sheet-president-obama-announce-historic-carbon-pollution-standards.
A25: Electricity Supply | B25: Change Electricity Exports | C25: Percent Change in Electricity Exports | D25: Electricity Imports and Exports | E25: elec change exports | F25: -0.5 | G25: 1 | H25: 0.02 | I25: % change in exports | J25: **Description:** This policy increases or decreases the amount of electricity exported from Mexico to the United States, Belize and Guatemala. It does not cause the construction or removal of transmission lines linking these countries. // **Guidance for setting values:** From 2010 to 2016 electricity exports have grown at 6% p.a. from 22 to 31 PJ. // From 2010-2014, U.S. electricity exports declined by 30%. | K25: electricity-sector-main.html#elec-exports | L25: electricity-imports-exports.html | M25: Energy Information Administation. 2016. Electric Power Annual. Table 2.13.
A26: Electricity Supply | B26: Change Electricity Imports | C26: Percent Change in Electricity Imports | D26: Electricity Imports and Exports | E26: elec change imports | F26: -0.5 | G26: 1 | H26: 0.02 | I26: % change in imports | J26: **Description:** This policy increases or decreases the amount of electricity imported to the United States from Canada and Mexico. It does not cause the construction or removal of transmission lines linking these countries. // **Guidance for setting values:** From 2010 to 2016 electricity imports have grown from what have been a fairly constant 1.5 PJ to 12 PJ by 2016, although electricity imports are still 40% of exports (31 PJ). // From 2010-2014, U.S. electricity imports grew by 48%. | K26: electricity-sector-main.html#elec-imports | L26: electricity-imports-exports.html | M26: Energy Information Administation. 2016. Electric Power Annual. Table 2.13.
A27: Electricity Supply | B27: Non Reference Case Guaranteed Dispatch | C27: Boolean Use Non BAU Guaranteed Dispatch Settings | D27: Non Reference Case Guaranteed Dispatch | E27: elec non BAU guaranteed dispatch | F27: 0 | G27: 1 | H27: 1 | I27: on/off
A28: Electricity Supply | B28: Demand Response | C28: Fraction of Additional Demand Response Potential Achieved | D28: Demand Response | E28: elec demand response | F28: 0 | G28: 1 | H28: 0.01 | I28: % of potential achieved | J28: **Description:** This policy represents regulations that cause more demand response (DR) capacity to be added to the electric grid. Demand response provides flexibility that allows for the integration of more wind and solar PV, if the electricity system is flexibility-constrained. // **Guidance for setting values:** This lever adds additional demand response capacity on top of Reference case values. | K28: electricity-sector-main.html#dr | L28: demand-response.html | M28: Calculated from model data; see the relevant variable(s) in the InputData folder for source information.
A29: Electricity Supply | B29: Early Retirement of Power Plants | C29: Annual Additional Capacity Retired due to Early Retirement Policy | D29: Early Retirement of Power Plants | E29: elec early retirement | F29: 0 | G29: 25000 | H29: 500 | I29: MW/year | J29: **Description:** This policy causes the specified quantity of otherwise non-retiring capacity of the selected type(s) to be retired each year. // **Guidance for setting values:** // **PRODESEN's schedule has 1400 MW of coal capacity retirement in 2029-2030. Additional retirement projects up to 2800 MW retired by 2050 in the reference scenario. An "Accelerated Coal Retirement" policy should not exceed existing coal capacity (5387MW) plus any added by the model. //**Hard Coal:** The EIA Annual Energy Outlook 2015's "Accelerated Coal Retirements" scenario predicts an additional 53.3 GW of coal retirements beyond the reference (Reference Case) scenario by 2030, which is roughly 4,500 MW/year. // **Natural Gas Non-Peaker:** The U.S. has about 255 GW of natural gas non-peaker plants, which is expected to grow somewhat by about 30 GW by 2050. // **Nuclear:** The U.S. has about 100 GW of nuclear reactors, about 20 GW of which are projected to retire by 2050 in the Reference Case case. To retire half of the remainder by 2050 would require about 1200 MW/year of accelerated retirements. // **Natural Gas Peaker:** The U.S. has about 195 GW of natural gas peaker plants, of which 20 GW are projected to retire by 2050. // **Lignite:** The U.S. has about 7,000 MW of lignite power plants, none of which are projected to retire by 2050 in the Reference Case case. | K29: electricity-sector-main.html#early-ret | L29: early-retirement-of-power-plants.html | M29: Energy Information Administration, 2014, "Annual Energy Outlook 2014", http://www.eia.gov/oiaf/aeo/tablebrowser/#release=AEO2014&subject=6-AEO2014&table=9-AEO2014&region=0-0&cases=hccstom-d012314a,ref2014-d102413a, Table Browser. Select Electric Power Sector, Electricity Generating Capacity (and check Reference and Accelerated coal retirements scenarios). | N29: The Brattle Group, 2012, "Potential Coal Plant Retirements: 2012 Update," http://greatlakeslegalfoundation.org/wwcms/wp-content/uploads/documents/regulatory/TrainWreck/12Oct15_BrattleStudy.pdf, Page 8, Table 4
A30: Electricity Supply | B30: Grid-Scale Electricity Storage | C30: Fraction of Additional Grid Battery Storage Potential Achieved | D30: Grid-Scale Electricity Storage | E30: elec storage growth | F30: 0 | G30: 1 | H30: 0.01 | I30: % of potential achieved | J30: **Description:** This policy causes grid-scale electricity storage from chemical batteries to increase above the amount predicted in the Reference Case Scenario. // **Guidance for setting values:** In 2019, the U.S. had about 1,400 MW of grid battery storage. The Reference Case scenario is based on EIA AEO data and sees grid battery capacity reach 17,400 MW by 2050. The additional potential is based on NREL's Renewable Electricity Futures Study (80% RE-ITI (2014) scenario) and suggests the U.S. could reach 120,000 MW of grid battery storage by 2050. | K30: electricity-sector-main.html#storage | L30: grid-scale-electricity-storage.html | M30: National Renewable Energy Laboratory, 2014, Renewable Electricity Futures Scenario Viewer, http://www.nrel.gov/analysis/re_futures/data_viewer/# 80% RE-ITI (2014) scenario
A31: Electricity Supply | B31: Increase Transmission | C31: Percentage Increase in Transmission Capacity vs BAU | D31: Increase Transmission | E31: elec transmission growth | F31: 0 | G31: 1.13 | H31: 0.01 | I31: % increase in transmission capacity | J31: **Description:** This policy causes additional transmission capacity to be built relative to the Reference Case case. Transmission increases the flexibility of the grid, allowing for the integration of more wind and solar PV, if the electricity system is flexibility-constrained. // **Guidance for setting values:** NREL's Renewable Electricity Futures study suggest that the most economical method of achieving 50% renewables penetration involves building roughly 37 million MW-miles of new transmission capacity, an increase of 21% beyond the existing 150-200 million MW-miles. | K31: electricity-sector-main.html#transmission | L31: increase-transmission.html | M31: National Renewable Energy Laboratory, 2014, Renewable Electricity Futures (Vol. 1), http://www.nrel.gov/docs/fy12osti/52409-1.pdf, Page xli, Figure ES-8, 80% RE scenario. | N31: National Renewable Energy Laboratory, 2014, Renewable Electricity Futures (Vol. 1), http://www.nrel.gov/docs/fy12osti/52409-1.pdf, Page 2-10, 90% RE scenario.
A32: Electricity Supply | B32: Non Reference Case Capacity Retirement Schedule | C32: Boolean Use Non BAU Capacity Retirement Schedule | D32: Non Reference Case Capacity Retirement Schedule | F32: 0 | G32: 1 | H32: 1 | I32: on/off | J32: **Description:** This policy uses an alternative retirement schedule for existing capacity of the selected type(s). // **Guidance for setting values:** The Reference Case scenario uses retirements from the Energy Information Administration's Annual Energy Outlook (AEO), which includes some economic retirements. Toggling this policy on will only retire announced, planned retirements and exclude the economic retirements listed in the AEO.
A33: Electricity Supply | B33: Non Reference Case Mandated Capacity Construction | C33: Boolean Use Non BAU Mandated Capacity Construction Schedule | D33: Non Reference Case Mandated Capacity Construction | F33: 0 | G33: 1 | H33: 1 | I33: on/off | J33: **Description:** The business-as-uusal case includes all planned capacity additions (provided by the U.S. Energy Information Administration). This policy blocks all planned additions of the selected type(s) that have not already received regulatory approval. // **Guidance for setting values:** // **Natural Gas Nonpeaker:** This policy levers blocks roughly 15 GW of new natural gas between now and 2025.
A34: Electricity Supply | B34: Non Reference Case RPS Qualifying Resources | C34: Boolean Use Non BAU RPS Qualifying Resource Definitions | D34: Non Reference Case RPS Qualifying Resources | E34: elec non BAU RPS qualifying resources | F34: 0 | G34: 1 | H34: 1 | I34: on/off
A35: Electricity Supply | B35: Nuclear Plant Lifetime Extension | C35: Nuclear Capacity Lifetime Extension | D35: Nuclear Lifetime Extension | F35: 0 | G35: 20 | H35: 1 | I35: year(s) | J35: **Description:** This policy extends the lifetime of all nuclear plants by the specified number of years. Laguna Verde Mexico's only Nuclear Station (1600MW, 2 reactors, 1990) had a 40 year permit, which has already been extended to 60 years (1990-2050). | K35: electricity-sector-main.html#life-ext | L35: nuclear-lifetime-extension.html | M35: El Financiero, 2020, "¿Larga vida a la nuclear Laguna Verde?", https://www.elfinanciero.com.mx/opinion/jonathan-ruiz/2021/09/24/larga-vida-a-la-nuclear-laguna-verde/ U.S. Energy Information Administration, 2014, "Almost all U.S. nuclear plants require life extension past 60 years to operate beyond 2050", http://www.eia.gov/todayinenergy/detail.cfm?id=19091. | N35: El Financiero, 2020, "¿Larga vida a la nuclear Laguna Verde?", https://www.elfinanciero.com.mx/opinion/jonathan-ruiz/2021/09/24/larga-vida-a-la-nuclear-laguna-verde/ U.S. Energy Information Administration, 2014, "Almost all U.S. nuclear plants require life extension past 60 years to operate beyond 2050", http://www.eia.gov/todayinenergy/detail.cfm?id=19091.
A36: Electricity Supply | B36: Reduce Plant Downtime | C36: Percentage Reduction in Plant Downtime | D36: Reduce Plant Downtime | E36: elec reduce plant downtime | F36: 0 | G36: 0.6 | H36: 0.01 | I36: % reduction in downtime | J36: **Description:** This policy specifies the reduction in downtime (time spent not generating power) for plants of the selected type(s) that exist at the start of the model run. This policy increases these plants' target capacity factors, but it does not force them to be dispatched if it would be uneconomical to do so. // **Guidance for setting values:** // **Preexisting Natural Gas Nonpeaker:** Preexisting natural gas nonpeakers have an average capacity factor of 48%. As part of the proposed Clean Power Plan, the EPA assumed that nonpeaking natural gas plants could be reach a 75% capacity factor (ramping up to that value over a number of years). This would represent a 49% reduction in downtime. // **New Wind:** Availability of wind cannot be changed by policy, so the main method of increasing capacity factor is technological improvement of wind turbines. The National Renewable Energy Laboratory estimates that "near-future" wind technology could increase capacity factors by about 10 percentage points in most parts of the country. The average capacity factor of new turbines in the Reference Case case is roughly 47%, so an improvement to 57% might be represented as an 19% setting of this policy lever. // **New Solar PV:** Availability of sunlight cannot be changed by policy, so the main method of improvement is increasing the efficiency of solar cells. Typical crystalline silicon cells today have efficiencies of 20-25%, while today's best multi-junction cells (used primarily in concentrator PV and aerospace applications) have efficiencies of 40-45%. If the typical cells installed in 2050 will have efficiencies similar to today's best multi-junction cells, this might be represented as a 26% setting of this policy lever. | K36: electricity-sector-main.html#red-downtime | L36: reduce-downtime.html | M36: E&E Publishing. The Clean Power Plan - A Summary. http://www.eenews.net/interactive/clean_power_plan/fact_sheets/rule National Renewable Energy Laboratory. United States (48 Contiguous States) Potential Wind Capacity Cumulative Area vs. Gross Capacity Factor. http://apps2.eere.energy.gov/wind/windexchange/pdfs/wind_maps/us_contiguous_wind_potential_chart.pdf See the discussion of multi-junction solar cells on Wikipedia at https://en.wikipedia.org/wiki/Multi-junction_solar_cell. Also NREL has a useful chart at http://www.nrel.gov/ncpv/images/efficiency_chart.jpg.
A37: Electricity Supply | B37: Reduce Soft Costs | C37: Percent Reduction in Soft Costs of Capacity Construction | D37: Reduce Soft Costs | E37: elec reduce soft costs | F37: 0 | G37: 0.9 | H37: 0.01 | I37: % reduction in soft costs | J37: **Description:** This policy specifies a reduction in soft costs (costs for things other than capital equipment) for new plants of the selected type(s), such as the costs of permitting, financing, project management, assembly, etc. // **Guidance for setting values:** Costs of permitting and financing can be reduced by streamlining permitting processes, but some soft costs (such as labor) may be difficult to reduce via policy. A value of 50% would be an aggressive soft cost reduction. | K37: endogenous-learning.html#red-soft-costs | L37: reduce-soft-costs.html
A38: Electricity Supply | B38: Reduce Transmission & Distribution Losses | C38: Percentage TnD Losses Avoided | D38: Reduce T&D Losses | E38: elec avoid TND loss | F38: 0 | G38: 0.4 | H38: 0.01 | I38: % of losses avoided | J38: **Description:** This policy specifies the reduction in transmission and distribution losses that will be achieved by 2050. // **Guidance for setting values:** Mexico's total transmission and distribution losses have fluctuated between 12.5% and 16% according to World Bank. A relevant share of this is due to unenforced illicit use of electricity. As a reference, The U.S. has transmission and distribution losses of about 6%. Germany, Japan, Finland, and the Netherlands have T&D losses of around 4%. Therefore, a 33% policy setting would cause the U.S. to match these countries' current level of T&D losses by 2050. | K38: electricity-sector-main.html#red-tnd-losses | L38: reduce-tnd-losses.html | M38: The World Bank. Electric power transmission and distribution losses (% of output). http://data.worldbank.org/indicator/EG.ELC.LOSS.ZS
A39: Electricity Supply | B39: Subsidy for Capacity Construction | C39: Perc Subsidy for Elec Capacity Construction | D39: Subsidy for Capacity Construction | E39: elec capacity construction subsidy | F39: 0 | G39: 0.95 | H39: 0.01 | I39: % of construction cost | J39: **Description:** This policy is a subsidy paid by the government to electricity suppliers per unit of new capacity constructed. This only applies to utilities, not distributed systems (such as rooftop solar). // **Guidance for setting values:** // **Nuclear:** The U.S. Federal Government has guaranteed billions of dollars of loans for the construction new nuclear plants and has funded billions of dollars of nuclear technology R&D. The construction of two new reactors at the Vogtle power plant, the only advanced nuclear energy project under construction in the U.S., has received $12 billion in loan guarantees as of March 2019. (Loan guarantees are not equivalent to subsidies dollar-for-dollar, but they lower the cost of construction by enabling the plant to access cheaper financing.) // **Onshore Wind:** The U.S. does not have a capacity construction subsidy for onshore wind. However, the Investment Tax Credit, a similar program for solar power, covers 30% of system costs through 2019, with declining amounts thereafter. In the business-as-usual case, we also deduct a third of the ITC value to account for tax credit monetization. // **Solar PV and Solar Thermal:** The U.S. Investment Tax Credit, enacted in 2005, covers 30% of solar system costs through 2019, with declining amounts thereafter. In the business-as-usual case, we also deduct a third of the ITC value to account for tax credit monetization. // **Biomass:** The U.S. Federal Government has collectively guaranteed billions of dollars of loans for the construction new biomass plants. (Loan guarantees are not equivalent to subsidies dollar-for-dollar, but they lower the cost of construction by enabling the plant to access cheaper financing.) // **Offshore Wind:** The Investment Tax Credit covers 30% of system costs through 2025. In the business-as-usual case, we also deduct a third of the ITC value to account for tax credit monetization. | K39: electricity-sector-main.html#subsidies | M39: https://www.energy.gov/articles/secretary-perry-announces-financial-close-additional-loan-guarantees-during-trip-vogtle https://www.energysage.com/solar/cost-benefit/solar-investment-tax-credit/ http://biomassmagazine.com/articles/8185/usda-loan-guarantees-support-3-biomass-power-plants
A40: Electricity Supply | B40: Subsidy for Electricity Production | C40: Subsidy for Elec Production by Fuel | D40: Subsidy for Electricity Production | E40: elec generation subsidy | F40: 0 | G40: 60 | H40: 1 | I40: $/MWh | J40: **Description:** This policy is a subsidy paid by the government to suppliers of electricity per unit of electricity generated from the selected plant type(s). // **Guidance for setting values:** Before its phase-out began, the Renewable Electricity Production Tax Credit (PTC) offered $23/MWh for electricity from wind, geothermal, biomass, and solar systems not claiming the Investment Tax Credit. The current credit level is $25/MWh. State-level tax credits and feed-in tariffs for renewable energy range as high as $54/MWh. Note that while the PTC is currently set to expire in 2022, we assume developers can claim it through 2025 in the business-as-usual case. That is because the model only tracks the year power plants come online, but developers claim the PTC based on when constructions starts rather than when the plant comes online. In the business-as-usual case, we also deduct a third of the PTC value to account for tax credit monetization. // Also note that the Energy Policy Simulator chooses which new power plants to build based on lifetime plant costs, and the PTC is only available for the first 10 years of a project. // **Nuclear:** Because the average lifetime of a nuclear plant is 60 years, a setting of $25/MWh PTC would correspond to a lever setting of approximately $4/MWh. // **Onshore Wind, Solar PV, Solar Thermal, Offshore Wind:** Because the average lifetime of an onshore wind, solar PV, solar thermal, or offshore wind plant is 30 years, a $25/MWh credit would correspond to a lever setting of approximately $8/MWh. Note that where offshore wind developers are eligible for both the PTC and the Investment Tax Credit (ITC) in the business-as-usual case, we assume developers will choose the ITC (see the "Subsidy for Capacity Construction" policy lever). // **Biomass:** Because the average lifetime of a solar thermal plant is 45 years, a setting of $5.50/MWh PTC would correspond to a lever setting of approximately $8/MWh. | K40: electricity-sector-main.html#subsidies | L40: subsidy-for-electricity-production.html | M40: PRODUCTION TAX CREDIT: Database of State Incentives for Renewables & Efficiency, 2013, "Renewable Energy Production Tax Credit (PTC)", http://dsireusa.org/incentives/incentive.cfm?Incentive_Code=US13F. STATE-LEVEL INCENTIVES: Energy Information Administration, 2013, "Feed-In Tariffs and similar programs", http://www.eia.gov/electricity/policies/provider_programs.cfm.
A41: Industry | B41: Buy In-Region Products | C41: Fraction of Imported Industrial Outputs Shifted to In Region Suppliers | D41: Buy In-Region Products | E41: indst buy in region outputs | F41: 0 | G41: 0.5 | H41: 0.01 | I41: % of imports shifted | J41: **Description:** This policy increases the extent to which the selected industry's products are supplied by producers within the modeled region. // **Guidance for setting values:** The lever specifies the percentage of imported products (in the Reference Case case) that are shifted to domestic suppliers (in the policy case). For example, suppose buyers within the modeled region purchase 60% of their road vehicles from domestic automakers and 40% from automakers outside the modeled region. If this policy lever is applied to the "Road Vehicles" industry with a 50% setting, buyers will obtain 80% of their road vehicles from domestic automakers and 20% from automakers outside the modeled region. // **Implementation Note:** This policy reduces imports. In reality, other regions might retaliate by restricting their own purchases of goods produced by the modeled region. However, the EPS only considers policies within the modeled region, so the Buy In-Region Products policy does not affect export levels (i.e., other countries/regions are assumed not to retaliate).
A42: Industry | B42: Carbon Capture and Sequestration | C42: Industry Sector Fraction of Potential Additional CCS Achieved | D42: Industry CCS | E42: indst CCS | F42: 0 | G42: 1 | H42: 0.01 | I42: % of CO2 captured | J42: **Description:** This policy specifies the fraction of CO2 emissions from industry that is captured and stored, above the amount predicted in the business-as-usual scenario. // **Guidance for setting values:** Very few CCS-equipped industrial facilities exist today, so in a scenario where industry does not transition to clean energy, a value over 20% is likely very optimistic. However, in scenarios in which industry mostly or entirely transitions to clean energy (i.e. due to other policies, such as industrial fuel switching and industrial energy efficiency), CCS settings as high as 100% (to capture the small amount of residual CO2 emissions, such as process CO2 from the cement industry) may be very feasible. | K42: ccs.html#ccs | L42: carbon-capture-and-sequestration.html
A43: Industry | B43: Cement Clinker Substitution | C43: Fraction of Cement Measures Achieved | D43: Cement Clinker Substitution | E43: indst cement measures | F43: 0 | G43: 1 | H43: 0.01 | I43: % of potential achieved | J43: **Description:** This policy reduces CO2 emissions from the cement industry by substituting other inputs, such as fly ash, for a portion of the clinker in cement. // **Guidance for setting values:** If this policy is fully implemented, the share of clinker in cement is reduced to 60%. | K43: industry-ag-main.html#clinker | L43: cement-clinker-substitution.html | M43: International Energy Agency and Cement Sustainability Initiative. 2018. Technology Roadmap: Low-Carbon Transition in the Cement Industry. p41. http://www.iea.org/publications/freepublications/publication/TechnologyRoadmapLowCarbonTransitionintheCementIndustry.pdf
A44: Industry | B44: Cogeneration and Waste Heat Recovery | C44: Fraction of Potential Cogeneration and Waste Heat Recovery Adopted | D44: Cogeneration and Waste Heat Recovery | E44: indst CHP | F44: 0 | G44: 1 | H44: 0.01 | I44: % of potential achieved | J44: **Description:** This policy reduces fuel consumption in the industry sector by increasing the use of cogeneration (also known as combined heat and power) and recovery of waste heat (to perform useful work). // **Guidance for setting values:** If this policy is fully implemented, fuel use is reduced by 7.9% for all industries in 2050. | K44: industry-ag-main.html#cogen | L44: cogeneration-and-waste-heat-recovery.html | M44: Calculated from model data; see the relevant variable(s) in the InputData folder for source information.
A45: Industry | B45: Early Retirement of Industrial Facilities | C45: Fraction of Energy Savings from Early Facility Retirement Achieved | D45: Early Retirement of Industrial Facilities | E45: indst early retirement | F45: 0 | G45: 1 | H45: 0.01 | I45: % of potential achieved | J45: **Description:** This policy reduces fuel consumption in the industry sector by retiring older, inefficient industrial facilities sooner than they otherwise would retire. This policy does not affect demand for industrial products, so it is assumed that any facilities retired under this policy are replaced by new facilities or increased output from existing facilities in the same year. // **Guidance for setting values:** If this policy is fully implemented, fuel use is reduced for most industries between 2% and 9% in 2050. | K45: industry-ag-main.html#early-ret | L45: early-retirement-of-industrial-facilities.html | M45: Calculated from model data; see the relevant variable(s) in the InputData folder for source information.
A46: Industry | B46: Industry Energy Efficiency Standards | C46: Percentage Improvement in Eqpt Efficiency Standards above BAU | D46: Industry Energy Efficiency Standards | E46: indst efficiency standards | F46: 0 | G46: 0.25 | H46: 0.01 | I46: % reduction in energy use | J46: **Description:** This policy reduces fuel consumption by the selected industry by increasing the efficiency of industrial equipment through stronger standards. The policy setting refers to overall energy use reduction, not the reduction in energy use of newly sold equipment. // **Guidance for setting values:** As a reference, in 2016, the U.S. Department of Energy developed an industrial energy efficiency potential analysis that suggests the US could double its annual rate of improvement rate through 2030. Extended through 2050, this equates to a maximum potential improvement of 17% by 2050 relative to Reference Case. | K46: industry-ag-main.html#eff-stds | L46: industry-energy-efficiency-standards.html | M46: U.S. DOE, 2016, Industrial Energy Efficiency Potential Analysis, https://energy.gov/sites/prod/files/2017/04/f34/energy-savings-by-state-industrial-methodology.pdf | N46: U.S. DOE, 2016, Industrial Energy Efficiency Potential Analysis, https://energy.gov/sites/prod/files/2017/04/f34/energy-savings-by-state-industrial-methodology.pdf
A47: Industry | B47: Improved System Design | C47: Fraction of Installation and System Integration Issues Remedied | D47: Improved System Design | E47: indst system integration | F47: 0 | G47: 1 | H47: 0.01 | I47: % of potential achieved | J47: **Description:** This policy reduces fuel consumption in the industry sector by improving the way components are put together and the way material or energy flows between them. // **Guidance for setting values:** If this policy is fully implemented, fuel use is reduced by 3.6% for all industries in 2050. | K47: industry-ag-main.html#system-integ | L47: improved-system-design.html | M47: Calculated from model data; see the relevant variable(s) in the InputData folder for source information.
A48: Industry | B48: Electrification + Hydrogen | C48: Fraction of Industrial Fuel Use Shifted to Other Fuels | D48: Electrification + Hydrogen | E48: indst fuel type shifting | F48: 0 | G48: 1 | H48: 0.01 | I48: % of fuel shifted | J48: **Description:** This policy reduces greenhouse gas emissions from the selected industry by switching the fuels used by facilities to electricity and/or hydrogen. Only fuel consumed for energy, not fuel used as a chemical feedstock, is affected by this policy. // **Guidance for setting values:** Separately set the percentages of non-electricity, non-hydrogen fuel used by this industry in the Reference Case case to be shifted to electricity and to hydrogen. (If your settings total more than 100%, the effects will be scaled down proportionately so that the total fuel shifted does not exceed 100%.) Over 90% of thermal fuels (excluding feedstocks) are used to generate process heat or to fuel boilers. Generally, lower-temperature heat is easier to electrify than higher-temperature heat, while hydrogen can meet heat needs of any temprature. In the top-emitting 14 industries in the U.S., just under 50% of heat demand is at tempratures below 250 C, about a third is at temperatures from 350-600 C, and the remainder is at temperatures above 600 C. | K48: industry-ag-main.html#fuel-switching | L48: industry-elec-and-hydrogen.html
A49: Industry | B49: F-Gas Substitution | C49: Fraction of F Gas Substitution Achieved | D49: F-gas Measures | E49: indst f gas substitution | F49: 0 | G49: 1 | H49: 0.01 | I49: % of potential achieved | J49: **Description:** This policy reduces emissions of high-GWP, fluorinated gases (F-gases) from the industry sector by substituting less-harmful chemicals. // **Guidance for setting values:** If this policy is fully implemented, F-gas emissions in 2050 are reduced by 61%. | K49: industry-ag-main.html#avoid-f-gases | L49: avoid-f-gases.html | M49: Calculated from model data; see the relevant variable(s) in the InputData folder for source information.
A50: Industry | B50: F-Gas Destruction | C50: Fraction of F Gas Destruction Achieved | D50: F-gas Measures | E50: indst f gas destruction | F50: 0 | G50: 1 | H50: 0.01 | I50: % of potential achieved | J50: **Description:** This policy reduces emissions of high-GWP, fluorinated gases (F-gases) from the industry sector by destroying F-gases created as byproducts during the creation of desired products. // **Guidance for setting values:** If this policy is fully implemented, F-gas emissions in 2050 are reduced by 1%. | K50: industry-ag-main.html#avoid-f-gases | L50: avoid-f-gases.html
A51: Industry | B51: F-Gas Recovery | C51: Fraction of F Gas Recovery Achieved | D51: F-gas Measures | E51: indst f gas recovery | F51: 0 | G51: 1 | H51: 0.01 | I51: % of potential achieved | J51: **Description:** This policy reduces emissions of high-GWP, fluorinated gases (F-gases) by recovering F-gases from equipment at the end of its service life and destroying or recycling those F-gases. // **Guidance for setting values:** If this policy is fully implemented, F-gas emissions in 2050 are reduced by 4%. | K51: industry-ag-main.html#avoid-f-gases | L51: avoid-f-gases.html
A52: Industry | B52: F-Gas Eqpt. Maintenance & Retrofits | C52: Fraction of F Gas Inspct Maint Retrofit Achieved | D52: F-gas Measures | E52: indst f gas inspct maint retrofit | F52: 0 | G52: 1 | H52: 0.01 | I52: % of potential achieved | J52: **Description:** This policy reduces emissions of high-GWP, fluorinated gases (F-gases) from the industry sector by reducing leakage and losses through improved inspections, maintenance, and retrofitting of equipment. // **Guidance for setting values:** If this policy is fully implemented, F-gas emissions in 2050 are reduced by 1%. | K52: industry-ag-main.html#avoid-f-gases | L52: avoid-f-gases.html
A53: Industry | B53: Material Efficiency, Longevity, & Re-Use | C53: Percent Reduction in Nonenergy Nonagriculture Industry Product Demand | D53: Material Efficiency, Longevity, & Re-Use | E53: indst reduce nonenergy product demand | F53: 0 | G53: 1 | H53: 0.01 | I53: % demand reduction | J53: **Description:** // **Cement and Iron & Steel:** This policy reduces demand for the selected materials through techniques such as material-efficient building codes (using modern designs that require less material per unit floor area), requirements for greater building and infrastructure longevity, greater re-use and re-purposing of buildings (rather than tearing down and building new), etc. // **Guidance for setting values:** In "Sustainable Materials Without the Hot Air: Making Buildings, Vehicles and Products Efficiently and with Less New Material," Allwood and Cullen estimate that concrete use could be reduced by up to 40% using optimized molds, and concrete building longevity could be more than doubled to 200 years. Together, these measures might reduce concrete demand by up to 70%, if demand for building floorspace reaches steady state. They estimate that steel use could be reduced by 30% by optimizing designs and controlling the loads they experience during installation and use. If the lifetime of steel products could be doubled, the resulting material reduction could be up to 65%, if sales reach steady state. // **Water and Waste:** This policy reduces demand for water treatment and waste management services through techniques such as water conservation, reduction in disposable packaging, requirements for greater product longevity, greater repair and re-use of products, and increased recycling and composting. // **Guidance for setting values:** The majority of energy use and emissions from the water and waste sector are a result of water treatment, not solid waste management. The USDA reports that agriculture accounts for 80% of U.S. water consumption, and the U.S. EPA reports that "as much as 50 percent of the water we use outdoors is lost due to wind, evaporation, and runoff caused by inefficient irrigation methods and systems." Non-agriculture uses, including lawn irrigation and in-home use, may be able to achieve similar savings through improved practices and fixtures. | L53: material-efficiency-longevity-reuse.html | M53: Allwood and Cullen, "Sustainable Materials Without the Hot Air: Making Buildings, Vehicles and Products Efficiently and with Less New Material" Allwood and Cullen, "Sustainable Materials With Both Eyes Open" - page 185, http://www.withbotheyesopen.com/read.php?c=12 USDA Irrigation & Water Use: https://www.ers.usda.gov/topics/farm-practices-management/irrigation-water-use.aspx and EPA WaterSense Statistics and Facts: https://www.epa.gov/watersense/statistics-and-facts
A54: Industry | B54: Methane Capture | C54: Fraction of Methane Capture Opportunities Achieved | D54: Methane Capture and Destruction | E54: indst methane capture | F54: 0 | G54: 1 | H54: 0.01 | I54: % of potential achieved | J54: **Description:** This policy reduces methane emissions from the selected industry by increasing the capture of methane that is currently being released into the atmosphere (for example, stopping leaks from wellheads, pipes, coal mines, landfills, etc.). | K54: industry-ag-main.html#methane-capture | L54: methane-capture.html
A55: Industry | B55: Methane Destruction | C55: Fraction of Methane Destruction Opportunities Achieved | D55: Methane Capture and Destruction | E55: indst methane destruction | F55: 0 | G55: 1 | H55: 0.01 | I55: % of potential achieved | J55: **Description:** This policy reduces methane emissions from the selected industry by increasing the burning of methane that is currently being released into the atmosphere (i.e. flaring instead of venting/leaking). | K55: industry-ag-main.html#methane-destr | L55: methane-destruction.html
A56: Industry | B56: N2O Abatement | C56: Fraction of N2O Abatement Achieved | D56: N2O Abatement | E56: indst N2O abatement | F56: 0 | G56: 1 | H56: 0.01 | I56: % of potential achieved | J56: **Description:** This policy reduces nitrous oxide (N2O) process emissions from the chemicals industry (primarily from the production of nitric acid and adipic acid) by destroying the N2O rather than venting it to the atmosphere.
A57: Industry | B57: Reduce Fossil Fuel Exports | C57: Percent Reduction in Fossil Fuel Exports | D57: Percent Reduction in Fossil Fuel Exports | E57: indst reduce fossil fuel exports | F57: 0 | G57: 1 | H57: 0.01 | I57: % reduction in exports | J57: **Description:** This policy reduces production of the selected fuel type(s) for export. This lever may represent a reduction in fuel demand by actors outside the modeled region (i.e., not caused by domestic policy) or a conscious policy within the modeled region to transition its economy away from dependence on fossil fuel exports. // **Guidance for setting values:** According to 2020 Energy Balance for Mexico, exports represent 0% of coal production, 0% of natural gas production, 5.4% of petroleum gasoline production, 7.7% of petroleum diesel production, 0% of jet fuel and kerosene production, 65% of crude oil production, 94% of heavy and residual fuel oil production, and 0.8% of LPG, propane, and butane production. | L57: reduce-fuel-exports.html | M57: National Energy Balance 2020, https://sie.energia.gob.mx/ Calculated from model data; see the relevant variable(s) in the InputData folder for source information.
A58: Agriculture, Land Use, and Forestry | B58: Afforestation and Reforestation | C58: Fraction of Afforestation and Reforestation Achieved | D58: Afforestation and Reforestation | E58: land afforestation and reforestation | F58: 0 | G58: 1 | H58: 0.01 | I58: % of potential achieved | J58: **Description:** This policy increases the sequestration of CO2 by planting forests. Planted forests are assumed to be managed with best practices and are not used for timber harvesting. // **Guidance for setting values:** If this policy is fully implemented, the afforestation/reforestation rate reaches 2 million acres per year in 2050 (roughly equal to 0.1% of the land area of the lower 48 states). | K58: lulucf.html#aff-ref | L58: afforestation-and-reforestation.html | M58: Calculated from model data; see the relevant variable(s) in the InputData folder for source information. | N58: Ross W. Gorte, 2009, "U.S. Tree Planting for Carbon Sequestration," Congressional Research Service, https://www.fas.org/sgp/crs/misc/R40562.pdf, p.3, paragraph 1
A59: Agriculture, Land Use, and Forestry | B59: Avoid Deforestation | C59: Fraction of Avoided Deforestation Achieved | D59: Avoid Deforestation | E59: land avoid deforestation | F59: 0 | G59: 1 | H59: 0.01 | I59: % of potential achieved | K59: lulucf.html#avoid-def | L59: avoid-deforestation.html
A60: Agriculture, Land Use, and Forestry | B60: Forest Restoration | C60: Fraction of Forest Restoration Achieved | D60: Forest Restoration | E60: land forest restoration | F60: 0 | G60: 1 | H60: 0.01 | I60: % of potential achieved | L60: forest-restoration.html
A61: Agriculture, Land Use, and Forestry | B61: Forest Set-Asides | C61: Fraction of Forest Set Asides Achieved | D61: Forest Set-Asides | E61: land forest set asides | F61: 0 | G61: 1 | H61: 0.01 | I61: % of potential achieved | J61: **Description:** This policy avoids the release of CO2 from forests by reducing timber harvesting. // **Guidance for setting values:** A 100% setting of this lever reduces timber harvesting by 2% of the Reference Case amount per year, reaching a roughly 70% reduction in timber harvesting by 2050. | K61: lulucf.html#set-asides | L61: forest-set-asides.html | M61: Calculated from model data; see the relevant variable(s) in the InputData folder for source information.
A62: Agriculture, Land Use, and Forestry | B62: Cropland and Rice Measures | C62: Fraction of Cropland and Rice Measures Achieved | D62: Cropland and Rice Measures | E62: indst cropland and rice measures | F62: 0 | G62: 1 | H62: 0.01 | I62: % of potential achieved | J62: **Description:** This policy reduces greenhouse gas emissions from agriculture through cropland management practices, such as improved crop rotations, reduced soil tillage, and improvements in fertilizer composition and application. Measures particular to rice cultivation include improved flooding practices that avoid anaerobic, methane-forming conditions.. // **Guidance for setting values:** If this policy is fully implemented, agricultural process emissions in 2050 are reduced by 2%. | K62: industry-ag-main.html#cropland | L62: cropland-management.html | M62: Calculated from model data; see the relevant variable(s) in the InputData folder for source information.
A63: Agriculture, Land Use, and Forestry | B63: Improved Forest Management | C63: Fraction of Improved Forest Management Achieved | D63: Improved Forest Management | E63: land forest management | F63: 0 | G63: 1 | H63: 0.01 | I63: % of potential achieved | J63: **Description:** This policy increases CO2 sequestration by forests through improved forest management practices. // **Guidance for setting values:** If this policy is fully implemented, half of the 94 million acres of forest not currently under best management practices will instead be managed with best practices by 2050. | K63: lulucf.html#forest-mgmt | L63: improved-forest-management.html | M63: Calculated from model data; see the relevant variable(s) in the InputData folder for source information.
A64: Agriculture, Land Use, and Forestry | B64: Livestock Measures | C64: Fraction of Livestock Measures Achieved | D64: Livestock Measures | E64: indst livestock measures | F64: 0 | G64: 1 | H64: 0.01 | I64: % of potential achieved | J64: **Description:** This policy reduces greenhouse gas emissions from agriculture through livestock-related measures, such as feed supplements or drugs to prevent enteric methane formation. // **Guidance for setting values:** If this policy is fully implemented, agricultural process emissions in 2050 are reduced by 10%. | K64: industry-ag-main.html#livestock | L64: livestock-measures.html | M64: Calculated from model data; see the relevant variable(s) in the InputData folder for source information.
A65: Agriculture, Land Use, and Forestry | B65: Peatland Restoration | C65: Fraction of Peatland Restoration Achieved | D65: Peatland Restoration | E65: land peatland restoration | F65: 0 | G65: 1 | H65: 0.01 | I65: % of potential achieved | L65: peatland-restoration.html
A66: Agriculture, Land Use, and Forestry | B66: Shift to Non-Animal Products | C66: Percent Animal Products Shifted to Nonanimal Products | D66: Shift to Non-Animal Products | E66: indst shift to nonanimal products | F66: 0 | G66: 1 | H66: 0.01 | I66: % reduction in animal products | J66: **Description:** This policy causes animal products to be substituted for non-animal products, which might be achieved by changes in consumer preferences or by changes in costs of agricultural products (such as by redirecting subsidies currently paid to farmers who raise animals or feed crops to farmers growing fruits, vegetables, and other plant-based foods for human consumption). Moderate settings of this policy lever do not imply a vegan diet: for instance, a 50% setting could represent each individual consuming half as many animal products, rather than half of the population consuming no animal products. // **Guidance for setting values:** According to OECD statistics, the U.S. has the highest per-capita meat consumption in the world, at 99 kg/person/year. If the U.S. were to achieve a rate similar to that in Europe (70 kg/person/yr), Japan (36 kg/person/yr), or India (3 kg/person/yr), this would be a reduction of 29% (Europe), 64% (Japan), or 97% (India) respectively. | L66: shift-to-non-animal-products.html | M66: https://en.wikipedia.org/wiki/List_of_countries_by_meat_consumption_per_capita (article revision 00:12, 22 Feb 2019)
A67: District Heat and Hydrogen | B67: Use CHP for District Heat | C67: Fraction of Non CHP Heat Production Converted to CHP | D67: District Heat CHP | E67: heat convert heat to CHP | F67: 0 | G67: 1 | H67: 0.01 | I67: % non-CHP heat converted | J67: **Description:** This policy causes a percentage of the district heat that would be generated by dedicated heat plants to instead be generated via CHP plants. In this model, this causes them to consume no additional fuel, since it is assumed CHP plants would be run anyway in order to produce electricity. // **Guidance for setting values:** In the Reference Case Scenario, the fraction of heat derived from CHP plants is constant at roughly 50%. Therefore, a policy setting of 50% would increase the CHP fraction to 75% in 2050. | K67: district-heating.html#chp | L67: convert-non-chp-heat-production.html | M67: Calculated from model data; see the relevant variable(s) in the InputData folder for source information.
A68: District Heat and Hydrogen | B68: Produce District Heat with Hydrogen | C68: Fraction of District Heat Fuel Use Shifted to Other Fuels | D68: District Heat Fuel Switching | E68: heat fuel type shifting | F68: 0 | G68: 1 | H68: 0.01 | I68: % of fuel use | J68: **Description:** This policy causes a percentage of the district heat to be generated by burning hydrogen instead of the fuels used in the Reference Case case. // **Guidance for setting values:** In the United States, 64% of district heat is made by burning natural gas, 17% from coal, 16% from biomass, and 3% from petroleum. Hydrogen technologies are still emerging, and it is not yet clear if it will be more economical to electrify end uses of heat (ceasing to use district heat), or if decarbonizing district heat facilities will be an economical pathway. | K68: district-heating.html#convert-coal | L68: district-heat-fuel-switching.html | M68: Calculated from model data; see the relevant variable(s) in the InputData folder for source information.
A69: District Heat and Hydrogen | B69: Shift Hydrogen Production to Electrolysis | C69: Fraction of Hydrogen Production Pathways Shifted | D69: Hydrogen Electrolysis | E69: hydgn shift production pathways | F69: 0 | G69: 1 | H69: 0.01 | I69: % of hydrogen production | J69: **Description:** This policy causes a percentage of merchant hydrogen (i.e. hydrogen produced for sale, not hydrogen produced and consumed on-site within a facility) to be produced via electrolysis rather than via other production pathways. // **Guidance for setting values:** Today, in the United States, roughly 95% of hydrogen is produced via steam reforming of natural gas and 5% is produced via electrolysis. These shares are not projected to change in the Reference Case case. | L69: switch-hydrogen-production-pathway.html
A70: Cross-Sector | B70: Carbon Price | C70: Additional Carbon Tax Rate | D70: Carbon Price | E70: cross carbon tax | F70: 0 | G70: 300 | H70: 5 | I70: $/metric ton CO2e | J70: **Description:** This policy applies a price on fuels used in the selected sector(s) based on their greenhouse gas emissions. It also increases the base cost of capital equipment (e.g., vehicles, power plants, building components) according to their embedded carbon content. When applied to the Industry Sector, the tax **is** levied on greenhouse gas emissions from non-energy industrial and agricultural processes by default, but these emissions sources can be exempted from the tax by enabling the policy lever "Exempt Process Emissions from C Tax." // **Guidance for setting values:** The U.S. government's revised 2015 Social Cost of Carbon estimates for the year 2050 range from $32 to $115 per ton (in inflation-adjusted 2018 dollars), depending on one's choice of discount rate. | K70: fuels.html#carbon-tax | L70: carbon-tax.html | M70: U.S. EPA, 2015, "The Social Cost of Carbon", https://www.epa.gov/climatechange/social-cost-carbon, Row "2050". (For source for adjustment to 2018 dollars, see cpi.xlsx in InputData.) | N70: U.S. EPA, 2016, "Social Cost of CO2, 2015-2020," https://www.epa.gov/climatechange/social-cost-carbon
A71: Cross-Sector | B71: End Existing Subsidies | C71: Percent Reduction in BAU Subsidies | D71: End Existing Subsidies | E71: cross reduce BAU subsidies | F71: 0 | G71: 1 | H71: 0.01 | I71: % reduction in Reference Case subsidies | J71: **Description:** This policy reduces the subsidies paid for the production of the selected energy source(s) in the Reference Case case. // **Guidance for setting values:** A value of 100% eliminates subsidies. For reference, In tghe U.S. model, this would increase the price of coal by 0.3% - 0.5% (varying by sector), natural gas by 0.4% - 0.7% (varying by sector), electricity from nuclear plants by 1.2%, electricity from solar PV plants by 2%, petroleum gasoline by 0.2%, and petroleum diesel by 0.2% - 0.3% (varying by sector) in 2050. | K71: fuels.html#end-subsidies | L71: end-existing-subsidies.html | M71: Calculated from model data; see the relevant variable(s) in the InputData folder for source information.
A72: Cross-Sector | B72: Exempt Non-CO2 Emissions from C Tax | C72: Toggle Whether Carbon Tax Affects Non CO2 Emissions | D72: Carbon Tax Exemptions | E72: cross toggle whether carbon tax affects non CO2 emissions | F72: 0 | G72: 1 | H72: 1 | I72: on/off
A73: Cross-Sector | B73: Exempt Process Emissions from C Tax | C73: Toggle Whether Carbon Tax Affects Process Emissions | D73: Carbon Tax on Process Emissions | E73: cross toggle whether carbon tax affects process emissions | F73: 0 | G73: 1 | H73: 1 | I73: on/off | J73: **Description:** This policy prevents the carbon tax from being levied on process emissions (non-energy greenhouse gas emissions from industrial and agricultural operations). | K73: fuels.html#carbon-tax | L73: carbon-tax.html
A74: Cross-Sector | B74: Fixed Energy Prices | C74: Toggle Whether Policies Affect Energy Prices | D74: Fixed Energy Prices | E74: cross toggle whether policies affect energy prices | F74: 0 | G74: 1 | H74: 1 | I74: on/off
A75: Cross-Sector | B75: Fuel Price Deregulation | C75: Fuel Price Deregulation | D75: Fuel Price Deregulation | E75: cross fuel price deregulation | F75: 0 | G75: 1 | H75: 0.01 | I75: % of price deregulated | J75: **Description:** This policy causes the price of the selected fuel(s) for domestic buyers to approach international market prices. // **Guidance for setting values:** A value of 100% causes domestic fuel prices to equal international market prices, increasing the domestic price by roughly X% in 2050. | K75: fuels.html#fuel-price-deregulation
A76: Cross-Sector | B76: Fuel Taxes | C76: Additional Fuel Tax or Subsidy Rate by Fuel | D76: Fuel Taxes | E76: cross fuel tax | F76: 0 | G76: 0.2 | H76: 0.005 | I76: % of Reference Case price | J76: **Description:** This policy increases the tax rate for the selected fuel type(s). It is expressed as a percentage of the Reference Case Scenario price, which includes sales and excise taxes. // **Guidance for setting values:** In 2012, the national average sales tax rate was 6.8% and the national average tax rate on gasoline was 14%. | K76: fuels.html#fuel-taxes | L76: fuel-taxes.html | M76: AVG SALES TAX: The Sales Tax Clearinghouse, FAQ, https://thestc.com/FAQ.stm, Question "What is the average sales tax nationally?" AVG GASOLINE TAX: Energy Information Administration, 2014, Annual Energy Outlook 2014, http://www.eia.gov/forecasts/aeo/supplement/suptab_130.xlsx, Supplement Table 130.
A77: Research and Development | B77: Capital Cost Reduction | C77: RnD Building Capital Cost Perc Reduction | D77: R&D Capital Cost Reductions | E77: RnD building capital cost reduction | F77: 0 | G77: 0.4 | H77: 0.01 | I77: % reduction in cost | J77: **Description:** This policy causes the capital cost of the selected type(s) of equipment to decline by the set percentage over the course of the model run. The R&D progress caused by this policy is additional to any R&D necessary to comply with other policies, such as tighter fuel economy standards. No costs associated with conducting this additional R&D (such as investments in laboratories or engineers' salaries) are included in the model. // **Guidance for setting values:** This policy should generally be set to zero unless you are exploring a scenario with unusual and unexpected technological advancement. If setting a non-zero value, more mature technologies, such as coal, should have lower values than younger technologies, such as solar. A setting of 30% implies an average of roughly 1% annual improvement, which is very substantial. | K77: architectural-design.html#rnd | L77: research-and-development.html
A78: =A$77 -> Research and Development | B78: =B$77 -> Capital Cost Reduction | C78: RnD CCS Capital Cost Perc Reduction | D78: =D$77 -> R&D Capital Cost Reductions | E78: RnD CCS capital cost reduction | F78: =F$77 -> 0 | G78: =G$77 -> 0.4 | H78: =H$77 -> 0.01 | I78: =I$77 -> % reduction in cost | J78: =J$77 -> **Description:** This policy causes the capital cost of the selected type(s) of equipment to decline by the set percentage over the course of the model run. The R&D progress caused by this policy is additional to any R&D necessary to comply with other policies, such as tighter fuel economy standards. No costs associated with conducting this additional R&D (such as investments in laboratories or engineers' salaries) are included in the model. // **Guidance for setting values:** This policy should generally be set to zero unless you are exploring a scenario with unusual and unexpected technological advancement. If setting a non-zero value, more mature technologies, such as coal, should have lower values than younger technologies, such as solar. A setting of 30% implies an average of roughly 1% annual improvement, which is very substantial. | K78: =K$77 -> architectural-design.html#rnd | L78: =L$77 -> research-and-development.html
A79: =A$77 -> Research and Development | B79: =B$77 -> Capital Cost Reduction | C79: RnD Electricity Capital Cost Perc Reduction | D79: =D$77 -> R&D Capital Cost Reductions | E79: RnD electricity capital cost reduction | F79: =F$77 -> 0 | G79: =G$77 -> 0.4 | H79: =H$77 -> 0.01 | I79: =I$77 -> % reduction in cost | J79: =J$77 -> **Description:** This policy causes the capital cost of the selected type(s) of equipment to decline by the set percentage over the course of the model run. The R&D progress caused by this policy is additional to any R&D necessary to comply with other policies, such as tighter fuel economy standards. No costs associated with conducting this additional R&D (such as investments in laboratories or engineers' salaries) are included in the model. // **Guidance for setting values:** This policy should generally be set to zero unless you are exploring a scenario with unusual and unexpected technological advancement. If setting a non-zero value, more mature technologies, such as coal, should have lower values than younger technologies, such as solar. A setting of 30% implies an average of roughly 1% annual improvement, which is very substantial. | K79: =K$77 -> architectural-design.html#rnd | L79: =L$77 -> research-and-development.html
A80: =A$77 -> Research and Development | B80: =B$77 -> Capital Cost Reduction | C80: RnD Industry Capital Cost Perc Reduction | D80: =D$77 -> R&D Capital Cost Reductions | E80: RnD industry capital cost reduction | F80: =F$77 -> 0 | G80: =G$77 -> 0.4 | H80: =H$77 -> 0.01 | I80: =I$77 -> % reduction in cost | J80: =J$77 -> **Description:** This policy causes the capital cost of the selected type(s) of equipment to decline by the set percentage over the course of the model run. The R&D progress caused by this policy is additional to any R&D necessary to comply with other policies, such as tighter fuel economy standards. No costs associated with conducting this additional R&D (such as investments in laboratories or engineers' salaries) are included in the model. // **Guidance for setting values:** This policy should generally be set to zero unless you are exploring a scenario with unusual and unexpected technological advancement. If setting a non-zero value, more mature technologies, such as coal, should have lower values than younger technologies, such as solar. A setting of 30% implies an average of roughly 1% annual improvement, which is very substantial. | K80: =K$77 -> architectural-design.html#rnd | L80: =L$77 -> research-and-development.html
A81: =A$77 -> Research and Development | B81: =B$77 -> Capital Cost Reduction | C81: RnD Transportation Capital Cost Perc Reduction | D81: =D$77 -> R&D Capital Cost Reductions | E81: RnD transportation capital cost reduction | F81: =F$77 -> 0 | G81: =G$77 -> 0.4 | H81: =H$77 -> 0.01 | I81: =I$77 -> % reduction in cost | J81: =J$77 -> **Description:** This policy causes the capital cost of the selected type(s) of equipment to decline by the set percentage over the course of the model run. The R&D progress caused by this policy is additional to any R&D necessary to comply with other policies, such as tighter fuel economy standards. No costs associated with conducting this additional R&D (such as investments in laboratories or engineers' salaries) are included in the model. // **Guidance for setting values:** This policy should generally be set to zero unless you are exploring a scenario with unusual and unexpected technological advancement. If setting a non-zero value, more mature technologies, such as coal, should have lower values than younger technologies, such as solar. A setting of 30% implies an average of roughly 1% annual improvement, which is very substantial. | K81: =K$77 -> architectural-design.html#rnd | L81: =L$77 -> research-and-development.html
A82: Research and Development | B82: Direct Air Capture | C82: Fraction of Direct Air Capture Potential Achieved | D82: Direct Air Capture | E82: geoeng direct air capture | F82: 0 | G82: 1 | H82: 0.01 | I82: % of potential achieved | J82: **Description:** This policy causes direct air capture (DAC) technology to be used to remove carbon dioxide from the atmosphere. The modeled technology is based on hydroxide sorbents, as this is the most mature DAC technology. Alternatives (such as amine-based technologies) are unlikely to have a perceptible impact by 2050, the last year of the EPS model run. Note that all DAC technologies, even hydroxide sorbents, have their greatest potential effects after 2050, which cannot be seen in a model run that ends in 2050. (DAC refers only to mechanical methods of carbon dioxide removal, not afforestation and other land use measures. For those measures, see the policy levers in the "Agriculture, Land Use, and Forestry" category.) // **Guidance for setting values:** A 100% setting implies large DAC research and development investments starting today, and aggressive deployment in line with a global 1.5-degree-compatible trajectory from a 2019 Nature paper from Realmonte et al. That paper's global deployment rate has been scaled for the U.S. by the U.S.'s share of world GDP in 2017 (about 24%). | K82: direct-air-capture.html#dac | L82: direct-air-capture.html | M82: Realmonte et al., 2019, An inter-model assessment of the role of direct air capture in deep mitigation pathways, https://www.nature.com/articles/s41467-019-10842-5, Table 2, https://static-content.springer.com/esm/art%3A10.1038%2Fs41467-019-10842-5/MediaObjects/41467_2019_10842_MOESM1_ESM.pdf, Supplementary materials, Fig 3
A83: Research and Development | B83: Fuel Use Reduction | C83: RnD Building Fuel Use Perc Reduction | D83: R&D Fuel Use Reductions | E83: RnD building fuel use reduction | F83: 0 | G83: 0.4 | H83: 0.01 | I83: % reduction in fuel use | J83: **Description:** This policy causes the fuel use of the selected type(s) of equipment to decline by the set percentage over the course of the model run. The R&D progress caused by this policy is additional to any R&D necessary to comply with other policies, such as tighter fuel economy standards. No costs associated with conducting this additional R&D (such as investments in laboratories or engineers' salaries) are included in the model. // **Guidance for setting values:** This policy should generally be set to zero unless you are exploring a scenario with unusual and unexpected technological advancement. If setting a non-zero value, more mature technologies, such as coal, should have lower values than younger technologies, such as solar. A setting of 30% implies an average of roughly 1% annual improvement, which is very substantial. | K83: architectural-design.html#rnd | L83: research-and-development.html
A84: =A$83 -> Research and Development | B84: =B$83 -> Fuel Use Reduction | C84: RnD CCS Fuel Use Perc Reduction | D84: =D$83 -> R&D Fuel Use Reductions | E84: RnD CCS fuel use reduction | F84: =F$83 -> 0 | G84: =G$83 -> 0.4 | H84: =H$83 -> 0.01 | I84: =I$83 -> % reduction in fuel use | J84: =J$83 -> **Description:** This policy causes the fuel use of the selected type(s) of equipment to decline by the set percentage over the course of the model run. The R&D progress caused by this policy is additional to any R&D necessary to comply with other policies, such as tighter fuel economy standards. No costs associated with conducting this additional R&D (such as investments in laboratories or engineers' salaries) are included in the model. // **Guidance for setting values:** This policy should generally be set to zero unless you are exploring a scenario with unusual and unexpected technological advancement. If setting a non-zero value, more mature technologies, such as coal, should have lower values than younger technologies, such as solar. A setting of 30% implies an average of roughly 1% annual improvement, which is very substantial. | K84: =K$83 -> architectural-design.html#rnd | L84: =L$83 -> research-and-development.html
A85: =A$83 -> Research and Development | B85: =B$83 -> Fuel Use Reduction | C85: RnD Electricity Fuel Use Perc Reduction | D85: =D$83 -> R&D Fuel Use Reductions | E85: RnD electricity fuel use reduction | F85: =F$83 -> 0 | G85: =G$83 -> 0.4 | H85: =H$83 -> 0.01 | I85: =I$83 -> % reduction in fuel use | J85: =J$83 -> **Description:** This policy causes the fuel use of the selected type(s) of equipment to decline by the set percentage over the course of the model run. The R&D progress caused by this policy is additional to any R&D necessary to comply with other policies, such as tighter fuel economy standards. No costs associated with conducting this additional R&D (such as investments in laboratories or engineers' salaries) are included in the model. // **Guidance for setting values:** This policy should generally be set to zero unless you are exploring a scenario with unusual and unexpected technological advancement. If setting a non-zero value, more mature technologies, such as coal, should have lower values than younger technologies, such as solar. A setting of 30% implies an average of roughly 1% annual improvement, which is very substantial. | K85: =K$83 -> architectural-design.html#rnd | L85: =L$83 -> research-and-development.html
A86: =A$83 -> Research and Development | B86: =B$83 -> Fuel Use Reduction | C86: RnD Industry Fuel Use Perc Reduction | D86: =D$83 -> R&D Fuel Use Reductions | E86: RnD industry fuel use reduction | F86: =F$83 -> 0 | G86: =G$83 -> 0.4 | H86: =H$83 -> 0.01 | I86: =I$83 -> % reduction in fuel use | J86: =J$83 -> **Description:** This policy causes the fuel use of the selected type(s) of equipment to decline by the set percentage over the course of the model run. The R&D progress caused by this policy is additional to any R&D necessary to comply with other policies, such as tighter fuel economy standards. No costs associated with conducting this additional R&D (such as investments in laboratories or engineers' salaries) are included in the model. // **Guidance for setting values:** This policy should generally be set to zero unless you are exploring a scenario with unusual and unexpected technological advancement. If setting a non-zero value, more mature technologies, such as coal, should have lower values than younger technologies, such as solar. A setting of 30% implies an average of roughly 1% annual improvement, which is very substantial. | K86: =K$83 -> architectural-design.html#rnd | L86: =L$83 -> research-and-development.html
A87: =A$83 -> Research and Development | B87: =B$83 -> Fuel Use Reduction | C87: RnD Transportation Fuel Use Perc Reduction | D87: =D$83 -> R&D Fuel Use Reductions | E87: RnD transportation fuel use reduction | F87: =F$83 -> 0 | G87: =G$83 -> 0.4 | H87: =H$83 -> 0.01 | I87: =I$83 -> % reduction in fuel use | J87: =J$83 -> **Description:** This policy causes the fuel use of the selected type(s) of equipment to decline by the set percentage over the course of the model run. The R&D progress caused by this policy is additional to any R&D necessary to comply with other policies, such as tighter fuel economy standards. No costs associated with conducting this additional R&D (such as investments in laboratories or engineers' salaries) are included in the model. // **Guidance for setting values:** This policy should generally be set to zero unless you are exploring a scenario with unusual and unexpected technological advancement. If setting a non-zero value, more mature technologies, such as coal, should have lower values than younger technologies, such as solar. A setting of 30% implies an average of roughly 1% annual improvement, which is very substantial. | K87: =K$83 -> architectural-design.html#rnd | L87: =L$83 -> research-and-development.html
A88: Control Settings | B88: COVID-19 Recession | C88: GDPGR Alternative Base Case GDP Growth Rate | E88: settings exogenous GDP adjustment | F88: -0.08 | G88: 0.02 | H88: 0.001 | I88: GDP growth rate (%) | J88: **Description:** This control setting adjusts the GDP impact of the recession caused by SARS-CoV-2 (COVID-19). It is set in terms of the GDP growth rate for 2020, relative to 2019 (with negative values indicating GDP shrinkage). Recession impacts extend beyond 2020 and can be adjusted using the Implementation Schedule feature for this control setting. // **Guidance for setting values:** The EIA's November 2020 Short-Term Energy Outlook (STEO) expects a 3.6% shrinkage in GDP (versus a counter-factual growth of 2.0% from the January STEO). This is the default setting. | M88: see ctrl-settings/GDPGR
A89: Government Revenue Accounting | B89: Carbon Tax Revenue | C89: GRA for Carbon Tax Revenue | E89: GRA carbon tax revenue | F89: 0 | G89: 10 | H89: 1 | I89: weight | J89: **Description:** This is one of several control settings that help determine how government accounts for policy-driven changes in its cash flow (such as increased or decreased tax revenues or subsidy payments). **Regular Spending** means government will increase or decrease its spending on its normal budget (e.g. activities such as defense, education, and administrative expenses) to spend increased revenue or to make up for a reduction in revenue. **Budget Deficit** means government will grow or shrink the national debt (with associated implications for interest payments) to spend increased revenue or to make up for a reduction in revenue. **Household Taxes** means government will increase or decrease taxes on households (or give households a "climate dividend") to spend increased revenue or to make up for a reduction in revenue. **Payroll Taxes** means government will increase or decrease payroll taxes to spend increased revenue or to make up for a reduction in revenue. **Corporate Taxes** means government will increase or decrease corporate income taxes to spend increased revenue or to make up for a reduction in revenue. // **Guidance for setting values:** This value is set as a weight (1 to 10) to indicate its relative importance among the modeled government revenue accounting modes. The share of the change in government cash flow using this mode is this mode's weight divided by the total of the weights assigned to all modes (or an equal share, if every mode is assigned zero weight). | K89: io-model.html
A90: Government Revenue Accounting | B90: Fuel Tax Revenue | C90: GRA for Fuel Tax Revenue | E90: GRA fuel tax revenue | F90: 0 | G90: 10 | H90: 1 | I90: weight | J90: =J$89 -> **Description:** This is one of several control settings that help determine how government accounts for policy-driven changes in its cash flow (such as increased or decreased tax revenues or subsidy payments). **Regular Spending** means government will increase or decrease its spending on its normal budget (e.g. activities such as defense, education, and administrative expenses) to spend increased revenue or to make up for a reduction in revenue. **Budget Deficit** means government will grow or shrink the national debt (with associated implications for interest payments) to spend increased revenue or to make up for a reduction in revenue. **Household Taxes** means government will increase or decrease taxes on households (or give households a "climate dividend") to spend increased revenue or to make up for a reduction in revenue. **Payroll Taxes** means government will increase or decrease payroll taxes to spend increased revenue or to make up for a reduction in revenue. **Corporate Taxes** means government will increase or decrease corporate income taxes to spend increased revenue or to make up for a reduction in revenue. // **Guidance for setting values:** This value is set as a weight (1 to 10) to indicate its relative importance among the modeled government revenue accounting modes. The share of the change in government cash flow using this mode is this mode's weight divided by the total of the weights assigned to all modes (or an equal share, if every mode is assigned zero weight). | K90: =K$89 -> io-model.html
A91: Government Revenue Accounting | B91: EV Subsidy | C91: GRA for EV Subsidy | E91: GRA EV subsidy | F91: 0 | G91: 10 | H91: 1 | I91: weight | J91: =J$89 -> **Description:** This is one of several control settings that help determine how government accounts for policy-driven changes in its cash flow (such as increased or decreased tax revenues or subsidy payments). **Regular Spending** means government will increase or decrease its spending on its normal budget (e.g. activities such as defense, education, and administrative expenses) to spend increased revenue or to make up for a reduction in revenue. **Budget Deficit** means government will grow or shrink the national debt (with associated implications for interest payments) to spend increased revenue or to make up for a reduction in revenue. **Household Taxes** means government will increase or decrease taxes on households (or give households a "climate dividend") to spend increased revenue or to make up for a reduction in revenue. **Payroll Taxes** means government will increase or decrease payroll taxes to spend increased revenue or to make up for a reduction in revenue. **Corporate Taxes** means government will increase or decrease corporate income taxes to spend increased revenue or to make up for a reduction in revenue. // **Guidance for setting values:** This value is set as a weight (1 to 10) to indicate its relative importance among the modeled government revenue accounting modes. The share of the change in government cash flow using this mode is this mode's weight divided by the total of the weights assigned to all modes (or an equal share, if every mode is assigned zero weight). | K91: =K$89 -> io-model.html
A92: Government Revenue Accounting | B92: Electricity Generation Subsidy | C92: GRA for Electricity Generation Subsidies | E92: GRA elec gen subsidy | F92: 0 | G92: 10 | H92: 1 | I92: weight | J92: =J$89 -> **Description:** This is one of several control settings that help determine how government accounts for policy-driven changes in its cash flow (such as increased or decreased tax revenues or subsidy payments). **Regular Spending** means government will increase or decrease its spending on its normal budget (e.g. activities such as defense, education, and administrative expenses) to spend increased revenue or to make up for a reduction in revenue. **Budget Deficit** means government will grow or shrink the national debt (with associated implications for interest payments) to spend increased revenue or to make up for a reduction in revenue. **Household Taxes** means government will increase or decrease taxes on households (or give households a "climate dividend") to spend increased revenue or to make up for a reduction in revenue. **Payroll Taxes** means government will increase or decrease payroll taxes to spend increased revenue or to make up for a reduction in revenue. **Corporate Taxes** means government will increase or decrease corporate income taxes to spend increased revenue or to make up for a reduction in revenue. // **Guidance for setting values:** This value is set as a weight (1 to 10) to indicate its relative importance among the modeled government revenue accounting modes. The share of the change in government cash flow using this mode is this mode's weight divided by the total of the weights assigned to all modes (or an equal share, if every mode is assigned zero weight). | K92: =K$89 -> io-model.html
A93: Government Revenue Accounting | B93: Electricity Capacity Construction Subsidy | C93: GRA for Electricity Capacity Construction Subsidies | E93: GRA elec cap const subsidy | F93: 0 | G93: 10 | H93: 1 | I93: weight | J93: =J$89 -> **Description:** This is one of several control settings that help determine how government accounts for policy-driven changes in its cash flow (such as increased or decreased tax revenues or subsidy payments). **Regular Spending** means government will increase or decrease its spending on its normal budget (e.g. activities such as defense, education, and administrative expenses) to spend increased revenue or to make up for a reduction in revenue. **Budget Deficit** means government will grow or shrink the national debt (with associated implications for interest payments) to spend increased revenue or to make up for a reduction in revenue. **Household Taxes** means government will increase or decrease taxes on households (or give households a "climate dividend") to spend increased revenue or to make up for a reduction in revenue. **Payroll Taxes** means government will increase or decrease payroll taxes to spend increased revenue or to make up for a reduction in revenue. **Corporate Taxes** means government will increase or decrease corporate income taxes to spend increased revenue or to make up for a reduction in revenue. // **Guidance for setting values:** This value is set as a weight (1 to 10) to indicate its relative importance among the modeled government revenue accounting modes. The share of the change in government cash flow using this mode is this mode's weight divided by the total of the weights assigned to all modes (or an equal share, if every mode is assigned zero weight). | K93: =K$89 -> io-model.html
A94: Government Revenue Accounting | B94: Distributed Solar Subsidy | C94: GRA for Distributed Solar Subsidy | E94: GRA dist solar subsidy | F94: 0 | G94: 10 | H94: 1 | I94: weight | J94: =J$89 -> **Description:** This is one of several control settings that help determine how government accounts for policy-driven changes in its cash flow (such as increased or decreased tax revenues or subsidy payments). **Regular Spending** means government will increase or decrease its spending on its normal budget (e.g. activities such as defense, education, and administrative expenses) to spend increased revenue or to make up for a reduction in revenue. **Budget Deficit** means government will grow or shrink the national debt (with associated implications for interest payments) to spend increased revenue or to make up for a reduction in revenue. **Household Taxes** means government will increase or decrease taxes on households (or give households a "climate dividend") to spend increased revenue or to make up for a reduction in revenue. **Payroll Taxes** means government will increase or decrease payroll taxes to spend increased revenue or to make up for a reduction in revenue. **Corporate Taxes** means government will increase or decrease corporate income taxes to spend increased revenue or to make up for a reduction in revenue. // **Guidance for setting values:** This value is set as a weight (1 to 10) to indicate its relative importance among the modeled government revenue accounting modes. The share of the change in government cash flow using this mode is this mode's weight divided by the total of the weights assigned to all modes (or an equal share, if every mode is assigned zero weight). | K94: =K$89 -> io-model.html
A95: Government Revenue Accounting | B95: Fuel Subsidy | C95: GRA for Fuel Subsidies | E95: GRA fuel subsidy | F95: 0 | G95: 10 | H95: 1 | I95: weight | J95: =J$89 -> **Description:** This is one of several control settings that help determine how government accounts for policy-driven changes in its cash flow (such as increased or decreased tax revenues or subsidy payments). **Regular Spending** means government will increase or decrease its spending on its normal budget (e.g. activities such as defense, education, and administrative expenses) to spend increased revenue or to make up for a reduction in revenue. **Budget Deficit** means government will grow or shrink the national debt (with associated implications for interest payments) to spend increased revenue or to make up for a reduction in revenue. **Household Taxes** means government will increase or decrease taxes on households (or give households a "climate dividend") to spend increased revenue or to make up for a reduction in revenue. **Payroll Taxes** means government will increase or decrease payroll taxes to spend increased revenue or to make up for a reduction in revenue. **Corporate Taxes** means government will increase or decrease corporate income taxes to spend increased revenue or to make up for a reduction in revenue. // **Guidance for setting values:** This value is set as a weight (1 to 10) to indicate its relative importance among the modeled government revenue accounting modes. The share of the change in government cash flow using this mode is this mode's weight divided by the total of the weights assigned to all modes (or an equal share, if every mode is assigned zero weight). | K95: =K$89 -> io-model.html
A96: Government Revenue Accounting | B96: National Debt Interest | C96: GRA for National Debt Interest | E96: GRA national debt interest | F96: 0 | G96: 10 | H96: 1 | I96: weight | J96: =J$89 -> **Description:** This is one of several control settings that help determine how government accounts for policy-driven changes in its cash flow (such as increased or decreased tax revenues or subsidy payments). **Regular Spending** means government will increase or decrease its spending on its normal budget (e.g. activities such as defense, education, and administrative expenses) to spend increased revenue or to make up for a reduction in revenue. **Budget Deficit** means government will grow or shrink the national debt (with associated implications for interest payments) to spend increased revenue or to make up for a reduction in revenue. **Household Taxes** means government will increase or decrease taxes on households (or give households a "climate dividend") to spend increased revenue or to make up for a reduction in revenue. **Payroll Taxes** means government will increase or decrease payroll taxes to spend increased revenue or to make up for a reduction in revenue. **Corporate Taxes** means government will increase or decrease corporate income taxes to spend increased revenue or to make up for a reduction in revenue. // **Guidance for setting values:** This value is set as a weight (1 to 10) to indicate its relative importance among the modeled government revenue accounting modes. The share of the change in government cash flow using this mode is this mode's weight divided by the total of the weights assigned to all modes (or an equal share, if every mode is assigned zero weight). | K96: =K$89 -> io-model.html
A97: Government Revenue Accounting | B97: Remaining Government Cash Flows | C97: GRA for Remaining Government Cash Flow Changes | E97: GRA remaining cash flow changes | F97: 0 | G97: 10 | H97: 1 | I97: weight | J97: =J$89 -> **Description:** This is one of several control settings that help determine how government accounts for policy-driven changes in its cash flow (such as increased or decreased tax revenues or subsidy payments). **Regular Spending** means government will increase or decrease its spending on its normal budget (e.g. activities such as defense, education, and administrative expenses) to spend increased revenue or to make up for a reduction in revenue. **Budget Deficit** means government will grow or shrink the national debt (with associated implications for interest payments) to spend increased revenue or to make up for a reduction in revenue. **Household Taxes** means government will increase or decrease taxes on households (or give households a "climate dividend") to spend increased revenue or to make up for a reduction in revenue. **Payroll Taxes** means government will increase or decrease payroll taxes to spend increased revenue or to make up for a reduction in revenue. **Corporate Taxes** means government will increase or decrease corporate income taxes to spend increased revenue or to make up for a reduction in revenue. // **Guidance for setting values:** This value is set as a weight (1 to 10) to indicate its relative importance among the modeled government revenue accounting modes. The share of the change in government cash flow using this mode is this mode's weight divided by the total of the weights assigned to all modes (or an equal share, if every mode is assigned zero weight). | K97: =K$89 -> io-model.html

Sheet PolicyLevers
A1: Sector | B1: Short Name | C1: Vensim Variable Name | D1: Subscript 1 Value | E1: Subscript 2 Value | F1: Subscript 1 Display Name | G1: Subscript 2 Display Name | H1: Policy ID Number | I1: Include in Web App | J1: Policy Group | K1: Policy Schedule Subscript | L1: Min Slider Value | M1: Max Slider Value | N1: Slider Step Size | O1: Units | P1: Text for Pop-Over Panel Description | Q1: URL for "How the model handles this policy" links | R1: URL for "How to design this policy well" links
A2: =INDEX('Policy Characteristics'!A:A,MATCH($C2,'Policy Characteristics'!$C:$C,0)) -> Transportation | B2: =INDEX('Policy Characteristics'!B:B,MATCH($C2,'Policy Characteristics'!$C:$C,0)) -> Conventional Pollutant Standards | C2: Percentage Reduction of Separately Regulated Pollutants | D2: LDVs | E2: VOC | F2: LDVs | G2: VOCs | H2: 300 | I2: Yes | J2: =INDEX('Policy Characteristics'!D:D,MATCH($C2,'Policy Characteristics'!$C:$C,0)) -> Conventional Pollutant Standard | K2: =INDEX('Policy Characteristics'!E:E,MATCH($C2,'Policy Characteristics'!$C:$C,0)) -> trans reduce regulated pollutants | L2: =INDEX('Policy Characteristics'!F:F,MATCH($C2,'Policy Characteristics'!$C:$C,0)) -> 0 | M2: =INDEX('Policy Characteristics'!G:G,MATCH($C2,'Policy Characteristics'!$C:$C,0)) -> 1 | N2: =INDEX('Policy Characteristics'!H:H,MATCH($C2,'Policy Characteristics'!$C:$C,0)) -> 0.02 | O2: =INDEX('Policy Characteristics'!I:I,MATCH($C2,'Policy Characteristics'!$C:$C,0)) -> % reduction in emissions | P2: =INDEX('Policy Characteristics'!J:J,MATCH($C2,'Policy Characteristics'!$C:$C,0)) -> **Description:** This policy represents strengthening standards for the selected pollutant(s) emitted by the selected vehicle type(s). Conventional pollutants' most important, harmful impacts are on human health rather than on climate change. // **Guidance for setting values:** Mexico has multiple regions with serious air quality concerns from fossil fuel combustion. ProAire (local air quality programs) have been deployed in major cities with some strong measures like those deployed for the Mexico City metropolitan area (strengthening air quality standards, re-zoning industrial areas, emissions registry and inventory, semi-annual vehicle inspections and limits to vehicle use). | Q2: =INDEX('Policy Characteristics'!K:K,MATCH($C2,'Policy Characteristics'!$C:$C,0)) -> transportation-sector-main.html#conv-pol-stds | R2: =INDEX('Policy Characteristics'!L:L,MATCH($C2,'Policy Characteristics'!$C:$C,0)) -> conventional-pollutant-standards.html
A3: =INDEX('Policy Characteristics'!A:A,MATCH($C3,'Policy Characteristics'!$C:$C,0)) -> Transportation | B3: =INDEX('Policy Characteristics'!B:B,MATCH($C3,'Policy Characteristics'!$C:$C,0)) -> Conventional Pollutant Standards | C3: =C$2 -> Percentage Reduction of Separately Regulated Pollutants | D3: LDVs | E3: CO | F3: LDVs | G3: CO | H3: 301 | I3: Yes | J3: =INDEX('Policy Characteristics'!D:D,MATCH($C3,'Policy Characteristics'!$C:$C,0)) -> Conventional Pollutant Standard | K3: =INDEX('Policy Characteristics'!E:E,MATCH($C3,'Policy Characteristics'!$C:$C,0)) -> trans reduce regulated pollutants | L3: =INDEX('Policy Characteristics'!F:F,MATCH($C3,'Policy Characteristics'!$C:$C,0)) -> 0 | M3: =INDEX('Policy Characteristics'!G:G,MATCH($C3,'Policy Characteristics'!$C:$C,0)) -> 1 | N3: =INDEX('Policy Characteristics'!H:H,MATCH($C3,'Policy Characteristics'!$C:$C,0)) -> 0.02 | O3: =INDEX('Policy Characteristics'!I:I,MATCH($C3,'Policy Characteristics'!$C:$C,0)) -> % reduction in emissions | P3: =INDEX('Policy Characteristics'!J:J,MATCH($C3,'Policy Characteristics'!$C:$C,0)) -> **Description:** This policy represents strengthening standards for the selected pollutant(s) emitted by the selected vehicle type(s). Conventional pollutants' most important, harmful impacts are on human health rather than on climate change. // **Guidance for setting values:** Mexico has multiple regions with serious air quality concerns from fossil fuel combustion. ProAire (local air quality programs) have been deployed in major cities with some strong measures like those deployed for the Mexico City metropolitan area (strengthening air quality standards, re-zoning industrial areas, emissions registry and inventory, semi-annual vehicle inspections and limits to vehicle use). | Q3: =INDEX('Policy Characteristics'!K:K,MATCH($C3,'Policy Characteristics'!$C:$C,0)) -> transportation-sector-main.html#conv-pol-stds | R3: =INDEX('Policy Characteristics'!L:L,MATCH($C3,'Policy Characteristics'!$C:$C,0)) -> conventional-pollutant-standards.html
A4: =INDEX('Policy Characteristics'!A:A,MATCH($C4,'Policy Characteristics'!$C:$C,0)) -> Transportation | B4: =INDEX('Policy Characteristics'!B:B,MATCH($C4,'Policy Characteristics'!$C:$C,0)) -> Conventional Pollutant Standards | C4: =C$2 -> Percentage Reduction of Separately Regulated Pollutants | D4: LDVs | E4: NOx | F4: LDVs | G4: NOx | H4: 302 | I4: Yes | J4: =INDEX('Policy Characteristics'!D:D,MATCH($C4,'Policy Characteristics'!$C:$C,0)) -> Conventional Pollutant Standard | K4: =INDEX('Policy Characteristics'!E:E,MATCH($C4,'Policy Characteristics'!$C:$C,0)) -> trans reduce regulated pollutants | L4: =INDEX('Policy Characteristics'!F:F,MATCH($C4,'Policy Characteristics'!$C:$C,0)) -> 0 | M4: =INDEX('Policy Characteristics'!G:G,MATCH($C4,'Policy Characteristics'!$C:$C,0)) -> 1 | N4: =INDEX('Policy Characteristics'!H:H,MATCH($C4,'Policy Characteristics'!$C:$C,0)) -> 0.02 | O4: =INDEX('Policy Characteristics'!I:I,MATCH($C4,'Policy Characteristics'!$C:$C,0)) -> % reduction in emissions | P4: =INDEX('Policy Characteristics'!J:J,MATCH($C4,'Policy Characteristics'!$C:$C,0)) -> **Description:** This policy represents strengthening standards for the selected pollutant(s) emitted by the selected vehicle type(s). Conventional pollutants' most important, harmful impacts are on human health rather than on climate change. // **Guidance for setting values:** Mexico has multiple regions with serious air quality concerns from fossil fuel combustion. ProAire (local air quality programs) have been deployed in major cities with some strong measures like those deployed for the Mexico City metropolitan area (strengthening air quality standards, re-zoning industrial areas, emissions registry and inventory, semi-annual vehicle inspections and limits to vehicle use). | Q4: =INDEX('Policy Characteristics'!K:K,MATCH($C4,'Policy Characteristics'!$C:$C,0)) -> transportation-sector-main.html#conv-pol-stds | R4: =INDEX('Policy Characteristics'!L:L,MATCH($C4,'Policy Characteristics'!$C:$C,0)) -> conventional-pollutant-standards.html
A5: =INDEX('Policy Characteristics'!A:A,MATCH($C5,'Policy Characteristics'!$C:$C,0)) -> Transportation | B5: =INDEX('Policy Characteristics'!B:B,MATCH($C5,'Policy Characteristics'!$C:$C,0)) -> Conventional Pollutant Standards | C5: =C$2 -> Percentage Reduction of Separately Regulated Pollutants | D5: LDVs | E5: PM10 | F5: LDVs | G5: PM10 | H5: 303 | I5: Yes | J5: =INDEX('Policy Characteristics'!D:D,MATCH($C5,'Policy Characteristics'!$C:$C,0)) -> Conventional Pollutant Standard | K5: =INDEX('Policy Characteristics'!E:E,MATCH($C5,'Policy Characteristics'!$C:$C,0)) -> trans reduce regulated pollutants | L5: =INDEX('Policy Characteristics'!F:F,MATCH($C5,'Policy Characteristics'!$C:$C,0)) -> 0 | M5: =INDEX('Policy Characteristics'!G:G,MATCH($C5,'Policy Characteristics'!$C:$C,0)) -> 1 | N5: =INDEX('Policy Characteristics'!H:H,MATCH($C5,'Policy Characteristics'!$C:$C,0)) -> 0.02 | O5: =INDEX('Policy Characteristics'!I:I,MATCH($C5,'Policy Characteristics'!$C:$C,0)) -> % reduction in emissions | P5: =INDEX('Policy Characteristics'!J:J,MATCH($C5,'Policy Characteristics'!$C:$C,0)) -> **Description:** This policy represents strengthening standards for the selected pollutant(s) emitted by the selected vehicle type(s). Conventional pollutants' most important, harmful impacts are on human health rather than on climate change. // **Guidance for setting values:** Mexico has multiple regions with serious air quality concerns from fossil fuel combustion. ProAire (local air quality programs) have been deployed in major cities with some strong measures like those deployed for the Mexico City metropolitan area (strengthening air quality standards, re-zoning industrial areas, emissions registry and inventory, semi-annual vehicle inspections and limits to vehicle use). | Q5: =INDEX('Policy Characteristics'!K:K,MATCH($C5,'Policy Characteristics'!$C:$C,0)) -> transportation-sector-main.html#conv-pol-stds | R5: =INDEX('Policy Characteristics'!L:L,MATCH($C5,'Policy Characteristics'!$C:$C,0)) -> conventional-pollutant-standards.html
A6: =INDEX('Policy Characteristics'!A:A,MATCH($C6,'Policy Characteristics'!$C:$C,0)) -> Transportation | B6: =INDEX('Policy Characteristics'!B:B,MATCH($C6,'Policy Characteristics'!$C:$C,0)) -> Conventional Pollutant Standards | C6: =C$2 -> Percentage Reduction of Separately Regulated Pollutants | D6: LDVs | E6: PM25 | F6: LDVs | G6: PM2.5 | H6: 304 | I6: Yes | J6: =INDEX('Policy Characteristics'!D:D,MATCH($C6,'Policy Characteristics'!$C:$C,0)) -> Conventional Pollutant Standard | K6: =INDEX('Policy Characteristics'!E:E,MATCH($C6,'Policy Characteristics'!$C:$C,0)) -> trans reduce regulated pollutants | L6: =INDEX('Policy Characteristics'!F:F,MATCH($C6,'Policy Characteristics'!$C:$C,0)) -> 0 | M6: =INDEX('Policy Characteristics'!G:G,MATCH($C6,'Policy Characteristics'!$C:$C,0)) -> 1 | N6: =INDEX('Policy Characteristics'!H:H,MATCH($C6,'Policy Characteristics'!$C:$C,0)) -> 0.02 | O6: =INDEX('Policy Characteristics'!I:I,MATCH($C6,'Policy Characteristics'!$C:$C,0)) -> % reduction in emissions | P6: =INDEX('Policy Characteristics'!J:J,MATCH($C6,'Policy Characteristics'!$C:$C,0)) -> **Description:** This policy represents strengthening standards for the selected pollutant(s) emitted by the selected vehicle type(s). Conventional pollutants' most important, harmful impacts are on human health rather than on climate change. // **Guidance for setting values:** Mexico has multiple regions with serious air quality concerns from fossil fuel combustion. ProAire (local air quality programs) have been deployed in major cities with some strong measures like those deployed for the Mexico City metropolitan area (strengthening air quality standards, re-zoning industrial areas, emissions registry and inventory, semi-annual vehicle inspections and limits to vehicle use). | Q6: =INDEX('Policy Characteristics'!K:K,MATCH($C6,'Policy Characteristics'!$C:$C,0)) -> transportation-sector-main.html#conv-pol-stds | R6: =INDEX('Policy Characteristics'!L:L,MATCH($C6,'Policy Characteristics'!$C:$C,0)) -> conventional-pollutant-standards.html
A7: =INDEX('Policy Characteristics'!A:A,MATCH($C7,'Policy Characteristics'!$C:$C,0)) -> Transportation | B7: =INDEX('Policy Characteristics'!B:B,MATCH($C7,'Policy Characteristics'!$C:$C,0)) -> Conventional Pollutant Standards | C7: =C$2 -> Percentage Reduction of Separately Regulated Pollutants | D7: LDVs | E7: SOx | F7: LDVs | G7: SOx | H7: 305 | I7: Yes | J7: =INDEX('Policy Characteristics'!D:D,MATCH($C7,'Policy Characteristics'!$C:$C,0)) -> Conventional Pollutant Standard | K7: =INDEX('Policy Characteristics'!E:E,MATCH($C7,'Policy Characteristics'!$C:$C,0)) -> trans reduce regulated pollutants | L7: =INDEX('Policy Characteristics'!F:F,MATCH($C7,'Policy Characteristics'!$C:$C,0)) -> 0 | M7: =INDEX('Policy Characteristics'!G:G,MATCH($C7,'Policy Characteristics'!$C:$C,0)) -> 1 | N7: =INDEX('Policy Characteristics'!H:H,MATCH($C7,'Policy Characteristics'!$C:$C,0)) -> 0.02 | O7: =INDEX('Policy Characteristics'!I:I,MATCH($C7,'Policy Characteristics'!$C:$C,0)) -> % reduction in emissions | P7: =INDEX('Policy Characteristics'!J:J,MATCH($C7,'Policy Characteristics'!$C:$C,0)) -> **Description:** This policy represents strengthening standards for the selected pollutant(s) emitted by the selected vehicle type(s). Conventional pollutants' most important, harmful impacts are on human health rather than on climate change. // **Guidance for setting values:** Mexico has multiple regions with serious air quality concerns from fossil fuel combustion. ProAire (local air quality programs) have been deployed in major cities with some strong measures like those deployed for the Mexico City metropolitan area (strengthening air quality standards, re-zoning industrial areas, emissions registry and inventory, semi-annual vehicle inspections and limits to vehicle use). | Q7: =INDEX('Policy Characteristics'!K:K,MATCH($C7,'Policy Characteristics'!$C:$C,0)) -> transportation-sector-main.html#conv-pol-stds | R7: =INDEX('Policy Characteristics'!L:L,MATCH($C7,'Policy Characteristics'!$C:$C,0)) -> conventional-pollutant-standards.html
A8: =IF(ISBLANK(INDEX('Policy Characteristics'!A:A,MATCH($C8,'Policy Characteristics'!$C:$C,0))),"",INDEX('Policy Characteristics'!A:A,MATCH($C8,'Policy Characteristics'!$C:$C,0))) -> Transportation | B8: =IF(ISBLANK(INDEX('Policy Characteristics'!B:B,MATCH($C8,'Policy Characteristics'!$C:$C,0))),"",INDEX('Policy Characteristics'!B:B,MATCH($C8,'Policy Characteristics'!$C:$C,0))) -> Conventional Pollutant Standards | C8: =C$2 -> Percentage Reduction of Separately Regulated Pollutants | D8: LDVs | E8: BC | F8: LDVs | G8: BC | H8: 306 | I8: Yes | J8: =INDEX('Policy Characteristics'!D:D,MATCH($C8,'Policy Characteristics'!$C:$C,0)) -> Conventional Pollutant Standard | K8: =INDEX('Policy Characteristics'!E:E,MATCH($C8,'Policy Characteristics'!$C:$C,0)) -> trans reduce regulated pollutants | L8: =INDEX('Policy Characteristics'!F:F,MATCH($C8,'Policy Characteristics'!$C:$C,0)) -> 0 | M8: =INDEX('Policy Characteristics'!G:G,MATCH($C8,'Policy Characteristics'!$C:$C,0)) -> 1 | N8: =INDEX('Policy Characteristics'!H:H,MATCH($C8,'Policy Characteristics'!$C:$C,0)) -> 0.02 | O8: =INDEX('Policy Characteristics'!I:I,MATCH($C8,'Policy Characteristics'!$C:$C,0)) -> % reduction in emissions | P8: =INDEX('Policy Characteristics'!J:J,MATCH($C8,'Policy Characteristics'!$C:$C,0)) -> **Description:** This policy represents strengthening standards for the selected pollutant(s) emitted by the selected vehicle type(s). Conventional pollutants' most important, harmful impacts are on human health rather than on climate change. // **Guidance for setting values:** Mexico has multiple regions with serious air quality concerns from fossil fuel combustion. ProAire (local air quality programs) have been deployed in major cities with some strong measures like those deployed for the Mexico City metropolitan area (strengthening air quality standards, re-zoning industrial areas, emissions registry and inventory, semi-annual vehicle inspections and limits to vehicle use). | Q8: =INDEX('Policy Characteristics'!K:K,MATCH($C8,'Policy Characteristics'!$C:$C,0)) -> transportation-sector-main.html#conv-pol-stds | R8: =INDEX('Policy Characteristics'!L:L,MATCH($C8,'Policy Characteristics'!$C:$C,0)) -> conventional-pollutant-standards.html
A9: =IF(ISBLANK(INDEX('Policy Characteristics'!A:A,MATCH($C9,'Policy Characteristics'!$C:$C,0))),"",INDEX('Policy Characteristics'!A:A,MATCH($C9,'Policy Characteristics'!$C:$C,0))) -> Transportation | B9: =IF(ISBLANK(INDEX('Policy Characteristics'!B:B,MATCH($C9,'Policy Characteristics'!$C:$C,0))),"",INDEX('Policy Characteristics'!B:B,MATCH($C9,'Policy Characteristics'!$C:$C,0))) -> Conventional Pollutant Standards | C9: =C$2 -> Percentage Reduction of Separately Regulated Pollutants | D9: LDVs | E9: OC | F9: LDVs | G9: OC | H9: 307 | I9: Yes | J9: =INDEX('Policy Characteristics'!D:D,MATCH($C9,'Policy Characteristics'!$C:$C,0)) -> Conventional Pollutant Standard | K9: =INDEX('Policy Characteristics'!E:E,MATCH($C9,'Policy Characteristics'!$C:$C,0)) -> trans reduce regulated pollutants | L9: =INDEX('Policy Characteristics'!F:F,MATCH($C9,'Policy Characteristics'!$C:$C,0)) -> 0 | M9: =INDEX('Policy Characteristics'!G:G,MATCH($C9,'Policy Characteristics'!$C:$C,0)) -> 1 | N9: =INDEX('Policy Characteristics'!H:H,MATCH($C9,'Policy Characteristics'!$C:$C,0)) -> 0.02 | O9: =INDEX('Policy Characteristics'!I:I,MATCH($C9,'Policy Characteristics'!$C:$C,0)) -> % reduction in emissions | P9: =INDEX('Policy Characteristics'!J:J,MATCH($C9,'Policy Characteristics'!$C:$C,0)) -> **Description:** This policy represents strengthening standards for the selected pollutant(s) emitted by the selected vehicle type(s). Conventional pollutants' most important, harmful impacts are on human health rather than on climate change. // **Guidance for setting values:** Mexico has multiple regions with serious air quality concerns from fossil fuel combustion. ProAire (local air quality programs) have been deployed in major cities with some strong measures like those deployed for the Mexico City metropolitan area (strengthening air quality standards, re-zoning industrial areas, emissions registry and inventory, semi-annual vehicle inspections and limits to vehicle use). | Q9: =INDEX('Policy Characteristics'!K:K,MATCH($C9,'Policy Characteristics'!$C:$C,0)) -> transportation-sector-main.html#conv-pol-stds | R9: =INDEX('Policy Characteristics'!L:L,MATCH($C9,'Policy Characteristics'!$C:$C,0)) -> conventional-pollutant-standards.html
A10: =IF(ISBLANK(INDEX('Policy Characteristics'!A:A,MATCH($C10,'Policy Characteristics'!$C:$C,0))),"",INDEX('Policy Characteristics'!A:A,MATCH($C10,'Policy Characteristics'!$C:$C,0))) -> Transportation | B10: =IF(ISBLANK(INDEX('Policy Characteristics'!B:B,MATCH($C10,'Policy Characteristics'!$C:$C,0))),"",INDEX('Policy Characteristics'!B:B,MATCH($C10,'Policy Characteristics'!$C:$C,0))) -> Conventional Pollutant Standards | C10: =C$2 -> Percentage Reduction of Separately Regulated Pollutants | D10: LDVs | E10: CH4 | F10: LDVs | G10: CH4 | H10: 308 | I10: No | J10: =INDEX('Policy Characteristics'!D:D,MATCH($C10,'Policy Characteristics'!$C:$C,0)) -> Conventional Pollutant Standard | K10: =INDEX('Policy Characteristics'!E:E,MATCH($C10,'Policy Characteristics'!$C:$C,0)) -> trans reduce regulated pollutants | L10: =INDEX('Policy Characteristics'!F:F,MATCH($C10,'Policy Characteristics'!$C:$C,0)) -> 0 | M10: =INDEX('Policy Characteristics'!G:G,MATCH($C10,'Policy Characteristics'!$C:$C,0)) -> 1 | N10: =INDEX('Policy Characteristics'!H:H,MATCH($C10,'Policy Characteristics'!$C:$C,0)) -> 0.02 | O10: =INDEX('Policy Characteristics'!I:I,MATCH($C10,'Policy Characteristics'!$C:$C,0)) -> % reduction in emissions | P10: =INDEX('Policy Characteristics'!J:J,MATCH($C10,'Policy Characteristics'!$C:$C,0)) -> **Description:** This policy represents strengthening standards for the selected pollutant(s) emitted by the selected vehicle type(s). Conventional pollutants' most important, harmful impacts are on human health rather than on climate change. // **Guidance for setting values:** Mexico has multiple regions with serious air quality concerns from fossil fuel combustion. ProAire (local air quality programs) have been deployed in major cities with some strong measures like those deployed for the Mexico City metropolitan area (strengthening air quality standards, re-zoning industrial areas, emissions registry and inventory, semi-annual vehicle inspections and limits to vehicle use). | Q10: =INDEX('Policy Characteristics'!K:K,MATCH($C10,'Policy Characteristics'!$C:$C,0)) -> transportation-sector-main.html#conv-pol-stds | R10: =INDEX('Policy Characteristics'!L:L,MATCH($C10,'Policy Characteristics'!$C:$C,0)) -> conventional-pollutant-standards.html
A11: =IF(ISBLANK(INDEX('Policy Characteristics'!A:A,MATCH($C11,'Policy Characteristics'!$C:$C,0))),"",INDEX('Policy Characteristics'!A:A,MATCH($C11,'Policy Characteristics'!$C:$C,0))) -> Transportation | B11: =IF(ISBLANK(INDEX('Policy Characteristics'!B:B,MATCH($C11,'Policy Characteristics'!$C:$C,0))),"",INDEX('Policy Characteristics'!B:B,MATCH($C11,'Policy Characteristics'!$C:$C,0))) -> Conventional Pollutant Standards | C11: =C$2 -> Percentage Reduction of Separately Regulated Pollutants | D11: LDVs | E11: N2O | F11: LDVs | G11: N2O | H11: 309 | I11: No | J11: =INDEX('Policy Characteristics'!D:D,MATCH($C11,'Policy Characteristics'!$C:$C,0)) -> Conventional Pollutant Standard | K11: =INDEX('Policy Characteristics'!E:E,MATCH($C11,'Policy Characteristics'!$C:$C,0)) -> trans reduce regulated pollutants | L11: =INDEX('Policy Characteristics'!F:F,MATCH($C11,'Policy Characteristics'!$C:$C,0)) -> 0 | M11: =INDEX('Policy Characteristics'!G:G,MATCH($C11,'Policy Characteristics'!$C:$C,0)) -> 1 | N11: =INDEX('Policy Characteristics'!H:H,MATCH($C11,'Policy Characteristics'!$C:$C,0)) -> 0.02 | O11: =INDEX('Policy Characteristics'!I:I,MATCH($C11,'Policy Characteristics'!$C:$C,0)) -> % reduction in emissions | P11: =INDEX('Policy Characteristics'!J:J,MATCH($C11,'Policy Characteristics'!$C:$C,0)) -> **Description:** This policy represents strengthening standards for the selected pollutant(s) emitted by the selected vehicle type(s). Conventional pollutants' most important, harmful impacts are on human health rather than on climate change. // **Guidance for setting values:** Mexico has multiple regions with serious air quality concerns from fossil fuel combustion. ProAire (local air quality programs) have been deployed in major cities with some strong measures like those deployed for the Mexico City metropolitan area (strengthening air quality standards, re-zoning industrial areas, emissions registry and inventory, semi-annual vehicle inspections and limits to vehicle use). | Q11: =INDEX('Policy Characteristics'!K:K,MATCH($C11,'Policy Characteristics'!$C:$C,0)) -> transportation-sector-main.html#conv-pol-stds | R11: =INDEX('Policy Characteristics'!L:L,MATCH($C11,'Policy Characteristics'!$C:$C,0)) -> conventional-pollutant-standards.html
A12: =IF(ISBLANK(INDEX('Policy Characteristics'!A:A,MATCH($C12,'Policy Characteristics'!$C:$C,0))),"",INDEX('Policy Characteristics'!A:A,MATCH($C12,'Policy Characteristics'!$C:$C,0))) -> Transportation | B12: =IF(ISBLANK(INDEX('Policy Characteristics'!B:B,MATCH($C12,'Policy Characteristics'!$C:$C,0))),"",INDEX('Policy Characteristics'!B:B,MATCH($C12,'Policy Characteristics'!$C:$C,0))) -> Conventional Pollutant Standards | C12: =C$2 -> Percentage Reduction of Separately Regulated Pollutants | D12: HDVs | E12: VOC | F12: HDVs | G12: VOCs | H12: 310 | I12: Yes | J12: =INDEX('Policy Characteristics'!D:D,MATCH($C12,'Policy Characteristics'!$C:$C,0)) -> Conventional Pollutant Standard | K12: =INDEX('Policy Characteristics'!E:E,MATCH($C12,'Policy Characteristics'!$C:$C,0)) -> trans reduce regulated pollutants | L12: =INDEX('Policy Characteristics'!F:F,MATCH($C12,'Policy Characteristics'!$C:$C,0)) -> 0 | M12: =INDEX('Policy Characteristics'!G:G,MATCH($C12,'Policy Characteristics'!$C:$C,0)) -> 1 | N12: =INDEX('Policy Characteristics'!H:H,MATCH($C12,'Policy Characteristics'!$C:$C,0)) -> 0.02 | O12: =INDEX('Policy Characteristics'!I:I,MATCH($C12,'Policy Characteristics'!$C:$C,0)) -> % reduction in emissions | P12: =INDEX('Policy Characteristics'!J:J,MATCH($C12,'Policy Characteristics'!$C:$C,0)) -> **Description:** This policy represents strengthening standards for the selected pollutant(s) emitted by the selected vehicle type(s). Conventional pollutants' most important, harmful impacts are on human health rather than on climate change. // **Guidance for setting values:** Mexico has multiple regions with serious air quality concerns from fossil fuel combustion. ProAire (local air quality programs) have been deployed in major cities with some strong measures like those deployed for the Mexico City metropolitan area (strengthening air quality standards, re-zoning industrial areas, emissions registry and inventory, semi-annual vehicle inspections and limits to vehicle use). | Q12: =INDEX('Policy Characteristics'!K:K,MATCH($C12,'Policy Characteristics'!$C:$C,0)) -> transportation-sector-main.html#conv-pol-stds | R12: =INDEX('Policy Characteristics'!L:L,MATCH($C12,'Policy Characteristics'!$C:$C,0)) -> conventional-pollutant-standards.html
A13: =IF(ISBLANK(INDEX('Policy Characteristics'!A:A,MATCH($C13,'Policy Characteristics'!$C:$C,0))),"",INDEX('Policy Characteristics'!A:A,MATCH($C13,'Policy Characteristics'!$C:$C,0))) -> Transportation | B13: =IF(ISBLANK(INDEX('Policy Characteristics'!B:B,MATCH($C13,'Policy Characteristics'!$C:$C,0))),"",INDEX('Policy Characteristics'!B:B,MATCH($C13,'Policy Characteristics'!$C:$C,0))) -> Conventional Pollutant Standards | C13: =C$2 -> Percentage Reduction of Separately Regulated Pollutants | D13: HDVs | E13: CO | F13: HDVs | G13: CO | H13: 311 | I13: Yes | J13: =INDEX('Policy Characteristics'!D:D,MATCH($C13,'Policy Characteristics'!$C:$C,0)) -> Conventional Pollutant Standard | K13: =INDEX('Policy Characteristics'!E:E,MATCH($C13,'Policy Characteristics'!$C:$C,0)) -> trans reduce regulated pollutants | L13: =INDEX('Policy Characteristics'!F:F,MATCH($C13,'Policy Characteristics'!$C:$C,0)) -> 0 | M13: =INDEX('Policy Characteristics'!G:G,MATCH($C13,'Policy Characteristics'!$C:$C,0)) -> 1 | N13: =INDEX('Policy Characteristics'!H:H,MATCH($C13,'Policy Characteristics'!$C:$C,0)) -> 0.02 | O13: =INDEX('Policy Characteristics'!I:I,MATCH($C13,'Policy Characteristics'!$C:$C,0)) -> % reduction in emissions | P13: =INDEX('Policy Characteristics'!J:J,MATCH($C13,'Policy Characteristics'!$C:$C,0)) -> **Description:** This policy represents strengthening standards for the selected pollutant(s) emitted by the selected vehicle type(s). Conventional pollutants' most important, harmful impacts are on human health rather than on climate change. // **Guidance for setting values:** Mexico has multiple regions with serious air quality concerns from fossil fuel combustion. ProAire (local air quality programs) have been deployed in major cities with some strong measures like those deployed for the Mexico City metropolitan area (strengthening air quality standards, re-zoning industrial areas, emissions registry and inventory, semi-annual vehicle inspections and limits to vehicle use). | Q13: =INDEX('Policy Characteristics'!K:K,MATCH($C13,'Policy Characteristics'!$C:$C,0)) -> transportation-sector-main.html#conv-pol-stds | R13: =INDEX('Policy Characteristics'!L:L,MATCH($C13,'Policy Characteristics'!$C:$C,0)) -> conventional-pollutant-standards.html
A14: =IF(ISBLANK(INDEX('Policy Characteristics'!A:A,MATCH($C14,'Policy Characteristics'!$C:$C,0))),"",INDEX('Policy Characteristics'!A:A,MATCH($C14,'Policy Characteristics'!$C:$C,0))) -> Transportation | B14: =IF(ISBLANK(INDEX('Policy Characteristics'!B:B,MATCH($C14,'Policy Characteristics'!$C:$C,0))),"",INDEX('Policy Characteristics'!B:B,MATCH($C14,'Policy Characteristics'!$C:$C,0))) -> Conventional Pollutant Standards | C14: =C$2 -> Percentage Reduction of Separately Regulated Pollutants | D14: HDVs | E14: NOx | F14: HDVs | G14: NOx | H14: 312 | I14: Yes | J14: =IF(ISBLANK(INDEX('Policy Characteristics'!D:D,MATCH($C14,'Policy Characteristics'!$C:$C,0))),"",INDEX('Policy Characteristics'!D:D,MATCH($C14,'Policy Characteristics'!$C:$C,0))) -> Conventional Pollutant Standard | K14: =IF(ISBLANK(INDEX('Policy Characteristics'!E:E,MATCH($C14,'Policy Characteristics'!$C:$C,0))),"",INDEX('Policy Characteristics'!E:E,MATCH($C14,'Policy Characteristics'!$C:$C,0))) -> trans reduce regulated pollutants | L14: =IF(ISBLANK(INDEX('Policy Characteristics'!F:F,MATCH($C14,'Policy Characteristics'!$C:$C,0))),"",INDEX('Policy Characteristics'!F:F,MATCH($C14,'Policy Characteristics'!$C:$C,0))) -> 0 | M14: =IF(ISBLANK(INDEX('Policy Characteristics'!G:G,MATCH($C14,'Policy Characteristics'!$C:$C,0))),"",INDEX('Policy Characteristics'!G:G,MATCH($C14,'Policy Characteristics'!$C:$C,0))) -> 1 | N14: =IF(ISBLANK(INDEX('Policy Characteristics'!H:H,MATCH($C14,'Policy Characteristics'!$C:$C,0))),"",INDEX('Policy Characteristics'!H:H,MATCH($C14,'Policy Characteristics'!$C:$C,0))) -> 0.02 | O14: =IF(ISBLANK(INDEX('Policy Characteristics'!I:I,MATCH($C14,'Policy Characteristics'!$C:$C,0))),"",INDEX('Policy Characteristics'!I:I,MATCH($C14,'Policy Characteristics'!$C:$C,0))) -> % reduction in emissions | P14: =IF(ISBLANK(INDEX('Policy Characteristics'!J:J,MATCH($C14,'Policy Characteristics'!$C:$C,0))),"",INDEX('Policy Characteristics'!J:J,MATCH($C14,'Policy Characteristics'!$C:$C,0))) -> **Description:** This policy represents strengthening standards for the selected pollutant(s) emitted by the selected vehicle type(s). Conventional pollutants' most important, harmful impacts are on human health rather than on climate change. // **Guidance for setting values:** Mexico has multiple regions with serious air quality concerns from fossil fuel combustion. ProAire (local air quality programs) have been deployed in major cities with some strong measures like those deployed for the Mexico City metropolitan area (strengthening air quality standards, re-zoning industrial areas, emissions registry and inventory, semi-annual vehicle inspections and limits to vehicle use). | Q14: =IF(ISBLANK(INDEX('Policy Characteristics'!K:K,MATCH($C14,'Policy Characteristics'!$C:$C,0))),"",INDEX('Policy Characteristics'!K:K,MATCH($C14,'Policy Characteristics'!$C:$C,0))) -> transportation-sector-main.html#conv-pol-stds | R14: =IF(ISBLANK(INDEX('Policy Characteristics'!L:L,MATCH($C14,'Policy Characteristics'!$C:$C,0))),"",INDEX('Policy Characteristics'!L:L,MATCH($C14,'Policy Characteristics'!$C:$C,0))) -> conventional-pollutant-standards.html
A15: =IF(ISBLANK(INDEX('Policy Characteristics'!A:A,MATCH($C15,'Policy Characteristics'!$C:$C,0))),"",INDEX('Policy Characteristics'!A:A,MATCH($C15,'Policy Characteristics'!$C:$C,0))) -> Transportation | B15: =IF(ISBLANK(INDEX('Policy Characteristics'!B:B,MATCH($C15,'Policy Characteristics'!$C:$C,0))),"",INDEX('Policy Characteristics'!B:B,MATCH($C15,'Policy Characteristics'!$C:$C,0))) -> Conventional Pollutant Standards | C15: =C$2 -> Percentage Reduction of Separately Regulated Pollutants | D15: HDVs | E15: PM10 | F15: HDVs | G15: PM10 | H15: 313 | I15: Yes | J15: =IF(ISBLANK(INDEX('Policy Characteristics'!D:D,MATCH($C15,'Policy Characteristics'!$C:$C,0))),"",INDEX('Policy Characteristics'!D:D,MATCH($C15,'Policy Characteristics'!$C:$C,0))) -> Conventional Pollutant Standard | K15: =IF(ISBLANK(INDEX('Policy Characteristics'!E:E,MATCH($C15,'Policy Characteristics'!$C:$C,0))),"",INDEX('Policy Characteristics'!E:E,MATCH($C15,'Policy Characteristics'!$C:$C,0))) -> trans reduce regulated pollutants | L15: =IF(ISBLANK(INDEX('Policy Characteristics'!F:F,MATCH($C15,'Policy Characteristics'!$C:$C,0))),"",INDEX('Policy Characteristics'!F:F,MATCH($C15,'Policy Characteristics'!$C:$C,0))) -> 0 | M15: =IF(ISBLANK(INDEX('Policy Characteristics'!G:G,MATCH($C15,'Policy Characteristics'!$C:$C,0))),"",INDEX('Policy Characteristics'!G:G,MATCH($C15,'Policy Characteristics'!$C:$C,0))) -> 1 | N15: =IF(ISBLANK(INDEX('Policy Characteristics'!H:H,MATCH($C15,'Policy Characteristics'!$C:$C,0))),"",INDEX('Policy Characteristics'!H:H,MATCH($C15,'Policy Characteristics'!$C:$C,0))) -> 0.02 | O15: =IF(ISBLANK(INDEX('Policy Characteristics'!I:I,MATCH($C15,'Policy Characteristics'!$C:$C,0))),"",INDEX('Policy Characteristics'!I:I,MATCH($C15,'Policy Characteristics'!$C:$C,0))) -> % reduction in emissions | P15: =IF(ISBLANK(INDEX('Policy Characteristics'!J:J,MATCH($C15,'Policy Characteristics'!$C:$C,0))),"",INDEX('Policy Characteristics'!J:J,MATCH($C15,'Policy Characteristics'!$C:$C,0))) -> **Description:** This policy represents strengthening standards for the selected pollutant(s) emitted by the selected vehicle type(s). Conventional pollutants' most important, harmful impacts are on human health rather than on climate change. // **Guidance for setting values:** Mexico has multiple regions with serious air quality concerns from fossil fuel combustion. ProAire (local air quality programs) have been deployed in major cities with some strong measures like those deployed for the Mexico City metropolitan area (strengthening air quality standards, re-zoning industrial areas, emissions registry and inventory, semi-annual vehicle inspections and limits to vehicle use). | Q15: =IF(ISBLANK(INDEX('Policy Characteristics'!K:K,MATCH($C15,'Policy Characteristics'!$C:$C,0))),"",INDEX('Policy Characteristics'!K:K,MATCH($C15,'Policy Characteristics'!$C:$C,0))) -> transportation-sector-main.html#conv-pol-stds | R15: =IF(ISBLANK(INDEX('Policy Characteristics'!L:L,MATCH($C15,'Policy Characteristics'!$C:$C,0))),"",INDEX('Policy Characteristics'!L:L,MATCH($C15,'Policy Characteristics'!$C:$C,0))) -> conventional-pollutant-standards.html
A16: =IF(ISBLANK(INDEX('Policy Characteristics'!A:A,MATCH($C16,'Policy Characteristics'!$C:$C,0))),"",INDEX('Policy Characteristics'!A:A,MATCH($C16,'Policy Characteristics'!$C:$C,0))) -> Transportation | B16: =IF(ISBLANK(INDEX('Policy Characteristics'!B:B,MATCH($C16,'Policy Characteristics'!$C:$C,0))),"",INDEX('Policy Characteristics'!B:B,MATCH($C16,'Policy Characteristics'!$C:$C,0))) -> Conventional Pollutant Standards | C16: =C$2 -> Percentage Reduction of Separately Regulated Pollutants | D16: HDVs | E16: PM25 | F16: HDVs | G16: PM2.5 | H16: 314 | I16: Yes | J16: =IF(ISBLANK(INDEX('Policy Characteristics'!D:D,MATCH($C16,'Policy Characteristics'!$C:$C,0))),"",INDEX('Policy Characteristics'!D:D,MATCH($C16,'Policy Characteristics'!$C:$C,0))) -> Conventional Pollutant Standard | K16: =IF(ISBLANK(INDEX('Policy Characteristics'!E:E,MATCH($C16,'Policy Characteristics'!$C:$C,0))),"",INDEX('Policy Characteristics'!E:E,MATCH($C16,'Policy Characteristics'!$C:$C,0))) -> trans reduce regulated pollutants | L16: =IF(ISBLANK(INDEX('Policy Characteristics'!F:F,MATCH($C16,'Policy Characteristics'!$C:$C,0))),"",INDEX('Policy Characteristics'!F:F,MATCH($C16,'Policy Characteristics'!$C:$C,0))) -> 0 | M16: =IF(ISBLANK(INDEX('Policy Characteristics'!G:G,MATCH($C16,'Policy Characteristics'!$C:$C,0))),"",INDEX('Policy Characteristics'!G:G,MATCH($C16,'Policy Characteristics'!$C:$C,0))) -> 1 | N16: =IF(ISBLANK(INDEX('Policy Characteristics'!H:H,MATCH($C16,'Policy Characteristics'!$C:$C,0))),"",INDEX('Policy Characteristics'!H:H,MATCH($C16,'Policy Characteristics'!$C:$C,0))) -> 0.02 | O16: =IF(ISBLANK(INDEX('Policy Characteristics'!I:I,MATCH($C16,'Policy Characteristics'!$C:$C,0))),"",INDEX('Policy Characteristics'!I:I,MATCH($C16,'Policy Characteristics'!$C:$C,0))) -> % reduction in emissions | P16: =IF(ISBLANK(INDEX('Policy Characteristics'!J:J,MATCH($C16,'Policy Characteristics'!$C:$C,0))),"",INDEX('Policy Characteristics'!J:J,MATCH($C16,'Policy Characteristics'!$C:$C,0))) -> **Description:** This policy represents strengthening standards for the selected pollutant(s) emitted by the selected vehicle type(s). Conventional pollutants' most important, harmful impacts are on human health rather than on climate change. // **Guidance for setting values:** Mexico has multiple regions with serious air quality concerns from fossil fuel combustion. ProAire (local air quality programs) have been deployed in major cities with some strong measures like those deployed for the Mexico City metropolitan area (strengthening air quality standards, re-zoning industrial areas, emissions registry and inventory, semi-annual vehicle inspections and limits to vehicle use). | Q16: =IF(ISBLANK(INDEX('Policy Characteristics'!K:K,MATCH($C16,'Policy Characteristics'!$C:$C,0))),"",INDEX('Policy Characteristics'!K:K,MATCH($C16,'Policy Characteristics'!$C:$C,0))) -> transportation-sector-main.html#conv-pol-stds | R16: =IF(ISBLANK(INDEX('Policy Characteristics'!L:L,MATCH($C16,'Policy Characteristics'!$C:$C,0))),"",INDEX('Policy Characteristics'!L:L,MATCH($C16,'Policy Characteristics'!$C:$C,0))) -> conventional-pollutant-standards.html
A17: =IF(ISBLANK(INDEX('Policy Characteristics'!A:A,MATCH($C17,'Policy Characteristics'!$C:$C,0))),"",INDEX('Policy Characteristics'!A:A,MATCH($C17,'Policy Characteristics'!$C:$C,0))) -> Transportation | B17: =IF(ISBLANK(INDEX('Policy Characteristics'!B:B,MATCH($C17,'Policy Characteristics'!$C:$C,0))),"",INDEX('Policy Characteristics'!B:B,MATCH($C17,'Policy Characteristics'!$C:$C,0))) -> Conventional Pollutant Standards | C17: =C$2 -> Percentage Reduction of Separately Regulated Pollutants | D17: HDVs | E17: SOx | F17: HDVs | G17: SOx | H17: 315 | I17: Yes | J17: =IF(ISBLANK(INDEX('Policy Characteristics'!D:D,MATCH($C17,'Policy Characteristics'!$C:$C,0))),"",INDEX('Policy Characteristics'!D:D,MATCH($C17,'Policy Characteristics'!$C:$C,0))) -> Conventional Pollutant Standard | K17: =IF(ISBLANK(INDEX('Policy Characteristics'!E:E,MATCH($C17,'Policy Characteristics'!$C:$C,0))),"",INDEX('Policy Characteristics'!E:E,MATCH($C17,'Policy Characteristics'!$C:$C,0))) -> trans reduce regulated pollutants | L17: =IF(ISBLANK(INDEX('Policy Characteristics'!F:F,MATCH($C17,'Policy Characteristics'!$C:$C,0))),"",INDEX('Policy Characteristics'!F:F,MATCH($C17,'Policy Characteristics'!$C:$C,0))) -> 0 | M17: =IF(ISBLANK(INDEX('Policy Characteristics'!G:G,MATCH($C17,'Policy Characteristics'!$C:$C,0))),"",INDEX('Policy Characteristics'!G:G,MATCH($C17,'Policy Characteristics'!$C:$C,0))) -> 1 | N17: =IF(ISBLANK(INDEX('Policy Characteristics'!H:H,MATCH($C17,'Policy Characteristics'!$C:$C,0))),"",INDEX('Policy Characteristics'!H:H,MATCH($C17,'Policy Characteristics'!$C:$C,0))) -> 0.02 | O17: =IF(ISBLANK(INDEX('Policy Characteristics'!I:I,MATCH($C17,'Policy Characteristics'!$C:$C,0))),"",INDEX('Policy Characteristics'!I:I,MATCH($C17,'Policy Characteristics'!$C:$C,0))) -> % reduction in emissions | P17: =IF(ISBLANK(INDEX('Policy Characteristics'!J:J,MATCH($C17,'Policy Characteristics'!$C:$C,0))),"",INDEX('Policy Characteristics'!J:J,MATCH($C17,'Policy Characteristics'!$C:$C,0))) -> **Description:** This policy represents strengthening standards for the selected pollutant(s) emitted by the selected vehicle type(s). Conventional pollutants' most important, harmful impacts are on human health rather than on climate change. // **Guidance for setting values:** Mexico has multiple regions with serious air quality concerns from fossil fuel combustion. ProAire (local air quality programs) have been deployed in major cities with some strong measures like those deployed for the Mexico City metropolitan area (strengthening air quality standards, re-zoning industrial areas, emissions registry and inventory, semi-annual vehicle inspections and limits to vehicle use). | Q17: =IF(ISBLANK(INDEX('Policy Characteristics'!K:K,MATCH($C17,'Policy Characteristics'!$C:$C,0))),"",INDEX('Policy Characteristics'!K:K,MATCH($C17,'Policy Characteristics'!$C:$C,0))) -> transportation-sector-main.html#conv-pol-stds | R17: =IF(ISBLANK(INDEX('Policy Characteristics'!L:L,MATCH($C17,'Policy Characteristics'!$C:$C,0))),"",INDEX('Policy Characteristics'!L:L,MATCH($C17,'Policy Characteristics'!$C:$C,0))) -> conventional-pollutant-standards.html
A18: =IF(ISBLANK(INDEX('Policy Characteristics'!A:A,MATCH($C18,'Policy Characteristics'!$C:$C,0))),"",INDEX('Policy Characteristics'!A:A,MATCH($C18,'Policy Characteristics'!$C:$C,0))) -> Transportation | B18: =IF(ISBLANK(INDEX('Policy Characteristics'!B:B,MATCH($C18,'Policy Characteristics'!$C:$C,0))),"",INDEX('Policy Characteristics'!B:B,MATCH($C18,'Policy Characteristics'!$C:$C,0))) -> Conventional Pollutant Standards | C18: =C$2 -> Percentage Reduction of Separately Regulated Pollutants | D18: HDVs | E18: BC | F18: HDVs | G18: BC | H18: 316 | I18: Yes | J18: =IF(ISBLANK(INDEX('Policy Characteristics'!D:D,MATCH($C18,'Policy Characteristics'!$C:$C,0))),"",INDEX('Policy Characteristics'!D:D,MATCH($C18,'Policy Characteristics'!$C:$C,0))) -> Conventional Pollutant Standard | K18: =IF(ISBLANK(INDEX('Policy Characteristics'!E:E,MATCH($C18,'Policy Characteristics'!$C:$C,0))),"",INDEX('Policy Characteristics'!E:E,MATCH($C18,'Policy Characteristics'!$C:$C,0))) -> trans reduce regulated pollutants | L18: =IF(ISBLANK(INDEX('Policy Characteristics'!F:F,MATCH($C18,'Policy Characteristics'!$C:$C,0))),"",INDEX('Policy Characteristics'!F:F,MATCH($C18,'Policy Characteristics'!$C:$C,0))) -> 0 | M18: =IF(ISBLANK(INDEX('Policy Characteristics'!G:G,MATCH($C18,'Policy Characteristics'!$C:$C,0))),"",INDEX('Policy Characteristics'!G:G,MATCH($C18,'Policy Characteristics'!$C:$C,0))) -> 1 | N18: =IF(ISBLANK(INDEX('Policy Characteristics'!H:H,MATCH($C18,'Policy Characteristics'!$C:$C,0))),"",INDEX('Policy Characteristics'!H:H,MATCH($C18,'Policy Characteristics'!$C:$C,0))) -> 0.02 | O18: =IF(ISBLANK(INDEX('Policy Characteristics'!I:I,MATCH($C18,'Policy Characteristics'!$C:$C,0))),"",INDEX('Policy Characteristics'!I:I,MATCH($C18,'Policy Characteristics'!$C:$C,0))) -> % reduction in emissions | P18: =IF(ISBLANK(INDEX('Policy Characteristics'!J:J,MATCH($C18,'Policy Characteristics'!$C:$C,0))),"",INDEX('Policy Characteristics'!J:J,MATCH($C18,'Policy Characteristics'!$C:$C,0))) -> **Description:** This policy represents strengthening standards for the selected pollutant(s) emitted by the selected vehicle type(s). Conventional pollutants' most important, harmful impacts are on human health rather than on climate change. // **Guidance for setting values:** Mexico has multiple regions with serious air quality concerns from fossil fuel combustion. ProAire (local air quality programs) have been deployed in major cities with some strong measures like those deployed for the Mexico City metropolitan area (strengthening air quality standards, re-zoning industrial areas, emissions registry and inventory, semi-annual vehicle inspections and limits to vehicle use). | Q18: =IF(ISBLANK(INDEX('Policy Characteristics'!K:K,MATCH($C18,'Policy Characteristics'!$C:$C,0))),"",INDEX('Policy Characteristics'!K:K,MATCH($C18,'Policy Characteristics'!$C:$C,0))) -> transportation-sector-main.html#conv-pol-stds | R18: =IF(ISBLANK(INDEX('Policy Characteristics'!L:L,MATCH($C18,'Policy Characteristics'!$C:$C,0))),"",INDEX('Policy Characteristics'!L:L,MATCH($C18,'Policy Characteristics'!$C:$C,0))) -> conventional-pollutant-standards.html
A19: =IF(ISBLANK(INDEX('Policy Characteristics'!A:A,MATCH($C19,'Policy Characteristics'!$C:$C,0))),"",INDEX('Policy Characteristics'!A:A,MATCH($C19,'Policy Characteristics'!$C:$C,0))) -> Transportation | B19: =IF(ISBLANK(INDEX('Policy Characteristics'!B:B,MATCH($C19,'Policy Characteristics'!$C:$C,0))),"",INDEX('Policy Characteristics'!B:B,MATCH($C19,'Policy Characteristics'!$C:$C,0))) -> Conventional Pollutant Standards | C19: =C$2 -> Percentage Reduction of Separately Regulated Pollutants | D19: HDVs | E19: OC | F19: HDVs | G19: OC | H19: 317 | I19: Yes | J19: =IF(ISBLANK(INDEX('Policy Characteristics'!D:D,MATCH($C19,'Policy Characteristics'!$C:$C,0))),"",INDEX('Policy Characteristics'!D:D,MATCH($C19,'Policy Characteristics'!$C:$C,0))) -> Conventional Pollutant Standard | K19: =IF(ISBLANK(INDEX('Policy Characteristics'!E:E,MATCH($C19,'Policy Characteristics'!$C:$C,0))),"",INDEX('Policy Characteristics'!E:E,MATCH($C19,'Policy Characteristics'!$C:$C,0))) -> trans reduce regulated pollutants | L19: =IF(ISBLANK(INDEX('Policy Characteristics'!F:F,MATCH($C19,'Policy Characteristics'!$C:$C,0))),"",INDEX('Policy Characteristics'!F:F,MATCH($C19,'Policy Characteristics'!$C:$C,0))) -> 0 | M19: =IF(ISBLANK(INDEX('Policy Characteristics'!G:G,MATCH($C19,'Policy Characteristics'!$C:$C,0))),"",INDEX('Policy Characteristics'!G:G,MATCH($C19,'Policy Characteristics'!$C:$C,0))) -> 1 | N19: =IF(ISBLANK(INDEX('Policy Characteristics'!H:H,MATCH($C19,'Policy Characteristics'!$C:$C,0))),"",INDEX('Policy Characteristics'!H:H,MATCH($C19,'Policy Characteristics'!$C:$C,0))) -> 0.02 | O19: =IF(ISBLANK(INDEX('Policy Characteristics'!I:I,MATCH($C19,'Policy Characteristics'!$C:$C,0))),"",INDEX('Policy Characteristics'!I:I,MATCH($C19,'Policy Characteristics'!$C:$C,0))) -> % reduction in emissions | P19: =IF(ISBLANK(INDEX('Policy Characteristics'!J:J,MATCH($C19,'Policy Characteristics'!$C:$C,0))),"",INDEX('Policy Characteristics'!J:J,MATCH($C19,'Policy Characteristics'!$C:$C,0))) -> **Description:** This policy represents strengthening standards for the selected pollutant(s) emitted by the selected vehicle type(s). Conventional pollutants' most important, harmful impacts are on human health rather than on climate change. // **Guidance for setting values:** Mexico has multiple regions with serious air quality concerns from fossil fuel combustion. ProAire (local air quality programs) have been deployed in major cities with some strong measures like those deployed for the Mexico City metropolitan area (strengthening air quality standards, re-zoning industrial areas, emissions registry and inventory, semi-annual vehicle inspections and limits to vehicle use). | Q19: =IF(ISBLANK(INDEX('Policy Characteristics'!K:K,MATCH($C19,'Policy Characteristics'!$C:$C,0))),"",INDEX('Policy Characteristics'!K:K,MATCH($C19,'Policy Characteristics'!$C:$C,0))) -> transportation-sector-main.html#conv-pol-stds | R19: =IF(ISBLANK(INDEX('Policy Characteristics'!L:L,MATCH($C19,'Policy Characteristics'!$C:$C,0))),"",INDEX('Policy Characteristics'!L:L,MATCH($C19,'Policy Characteristics'!$C:$C,0))) -> conventional-pollutant-standards.html
A20: =IF(ISBLANK(INDEX('Policy Characteristics'!A:A,MATCH($C20,'Policy Characteristics'!$C:$C,0))),"",INDEX('Policy Characteristics'!A:A,MATCH($C20,'Policy Characteristics'!$C:$C,0))) -> Transportation | B20: =IF(ISBLANK(INDEX('Policy Characteristics'!B:B,MATCH($C20,'Policy Characteristics'!$C:$C,0))),"",INDEX('Policy Characteristics'!B:B,MATCH($C20,'Policy Characteristics'!$C:$C,0))) -> Conventional Pollutant Standards | C20: =C$2 -> Percentage Reduction of Separately Regulated Pollutants | D20: HDVs | E20: CH4 | F20: HDVs | G20: CH4 | H20: 318 | I20: No | J20: =IF(ISBLANK(INDEX('Policy Characteristics'!D:D,MATCH($C20,'Policy Characteristics'!$C:$C,0))),"",INDEX('Policy Characteristics'!D:D,MATCH($C20,'Policy Characteristics'!$C:$C,0))) -> Conventional Pollutant Standard | K20: =IF(ISBLANK(INDEX('Policy Characteristics'!E:E,MATCH($C20,'Policy Characteristics'!$C:$C,0))),"",INDEX('Policy Characteristics'!E:E,MATCH($C20,'Policy Characteristics'!$C:$C,0))) -> trans reduce regulated pollutants | L20: =IF(ISBLANK(INDEX('Policy Characteristics'!F:F,MATCH($C20,'Policy Characteristics'!$C:$C,0))),"",INDEX('Policy Characteristics'!F:F,MATCH($C20,'Policy Characteristics'!$C:$C,0))) -> 0 | M20: =IF(ISBLANK(INDEX('Policy Characteristics'!G:G,MATCH($C20,'Policy Characteristics'!$C:$C,0))),"",INDEX('Policy Characteristics'!G:G,MATCH($C20,'Policy Characteristics'!$C:$C,0))) -> 1 | N20: =IF(ISBLANK(INDEX('Policy Characteristics'!H:H,MATCH($C20,'Policy Characteristics'!$C:$C,0))),"",INDEX('Policy Characteristics'!H:H,MATCH($C20,'Policy Characteristics'!$C:$C,0))) -> 0.02 | O20: =IF(ISBLANK(INDEX('Policy Characteristics'!I:I,MATCH($C20,'Policy Characteristics'!$C:$C,0))),"",INDEX('Policy Characteristics'!I:I,MATCH($C20,'Policy Characteristics'!$C:$C,0))) -> % reduction in emissions | P20: =IF(ISBLANK(INDEX('Policy Characteristics'!J:J,MATCH($C20,'Policy Characteristics'!$C:$C,0))),"",INDEX('Policy Characteristics'!J:J,MATCH($C20,'Policy Characteristics'!$C:$C,0))) -> **Description:** This policy represents strengthening standards for the selected pollutant(s) emitted by the selected vehicle type(s). Conventional pollutants' most important, harmful impacts are on human health rather than on climate change. // **Guidance for setting values:** Mexico has multiple regions with serious air quality concerns from fossil fuel combustion. ProAire (local air quality programs) have been deployed in major cities with some strong measures like those deployed for the Mexico City metropolitan area (strengthening air quality standards, re-zoning industrial areas, emissions registry and inventory, semi-annual vehicle inspections and limits to vehicle use). | Q20: =IF(ISBLANK(INDEX('Policy Characteristics'!K:K,MATCH($C20,'Policy Characteristics'!$C:$C,0))),"",INDEX('Policy Characteristics'!K:K,MATCH($C20,'Policy Characteristics'!$C:$C,0))) -> transportation-sector-main.html#conv-pol-stds | R20: =IF(ISBLANK(INDEX('Policy Characteristics'!L:L,MATCH($C20,'Policy Characteristics'!$C:$C,0))),"",INDEX('Policy Characteristics'!L:L,MATCH($C20,'Policy Characteristics'!$C:$C,0))) -> conventional-pollutant-standards.html
A21: =IF(ISBLANK(INDEX('Policy Characteristics'!A:A,MATCH($C21,'Policy Characteristics'!$C:$C,0))),"",INDEX('Policy Characteristics'!A:A,MATCH($C21,'Policy Characteristics'!$C:$C,0))) -> Transportation | B21: =IF(ISBLANK(INDEX('Policy Characteristics'!B:B,MATCH($C21,'Policy Characteristics'!$C:$C,0))),"",INDEX('Policy Characteristics'!B:B,MATCH($C21,'Policy Characteristics'!$C:$C,0))) -> Conventional Pollutant Standards | C21: =C$2 -> Percentage Reduction of Separately Regulated Pollutants | D21: HDVs | E21: N2O | F21: HDVs | G21: N2O | H21: 319 | I21: No | J21: =IF(ISBLANK(INDEX('Policy Characteristics'!D:D,MATCH($C21,'Policy Characteristics'!$C:$C,0))),"",INDEX('Policy Characteristics'!D:D,MATCH($C21,'Policy Characteristics'!$C:$C,0))) -> Conventional Pollutant Standard | K21: =IF(ISBLANK(INDEX('Policy Characteristics'!E:E,MATCH($C21,'Policy Characteristics'!$C:$C,0))),"",INDEX('Policy Characteristics'!E:E,MATCH($C21,'Policy Characteristics'!$C:$C,0))) -> trans reduce regulated pollutants | L21: =IF(ISBLANK(INDEX('Policy Characteristics'!F:F,MATCH($C21,'Policy Characteristics'!$C:$C,0))),"",INDEX('Policy Characteristics'!F:F,MATCH($C21,'Policy Characteristics'!$C:$C,0))) -> 0 | M21: =IF(ISBLANK(INDEX('Policy Characteristics'!G:G,MATCH($C21,'Policy Characteristics'!$C:$C,0))),"",INDEX('Policy Characteristics'!G:G,MATCH($C21,'Policy Characteristics'!$C:$C,0))) -> 1 | N21: =IF(ISBLANK(INDEX('Policy Characteristics'!H:H,MATCH($C21,'Policy Characteristics'!$C:$C,0))),"",INDEX('Policy Characteristics'!H:H,MATCH($C21,'Policy Characteristics'!$C:$C,0))) -> 0.02 | O21: =IF(ISBLANK(INDEX('Policy Characteristics'!I:I,MATCH($C21,'Policy Characteristics'!$C:$C,0))),"",INDEX('Policy Characteristics'!I:I,MATCH($C21,'Policy Characteristics'!$C:$C,0))) -> % reduction in emissions | P21: =IF(ISBLANK(INDEX('Policy Characteristics'!J:J,MATCH($C21,'Policy Characteristics'!$C:$C,0))),"",INDEX('Policy Characteristics'!J:J,MATCH($C21,'Policy Characteristics'!$C:$C,0))) -> **Description:** This policy represents strengthening standards for the selected pollutant(s) emitted by the selected vehicle type(s). Conventional pollutants' most important, harmful impacts are on human health rather than on climate change. // **Guidance for setting values:** Mexico has multiple regions with serious air quality concerns from fossil fuel combustion. ProAire (local air quality programs) have been deployed in major cities with some strong measures like those deployed for the Mexico City metropolitan area (strengthening air quality standards, re-zoning industrial areas, emissions registry and inventory, semi-annual vehicle inspections and limits to vehicle use). | Q21: =IF(ISBLANK(INDEX('Policy Characteristics'!K:K,MATCH($C21,'Policy Characteristics'!$C:$C,0))),"",INDEX('Policy Characteristics'!K:K,MATCH($C21,'Policy Characteristics'!$C:$C,0))) -> transportation-sector-main.html#conv-pol-stds | R21: =IF(ISBLANK(INDEX('Policy Characteristics'!L:L,MATCH($C21,'Policy Characteristics'!$C:$C,0))),"",INDEX('Policy Characteristics'!L:L,MATCH($C21,'Policy Characteristics'!$C:$C,0))) -> conventional-pollutant-standards.html
A22: =IF(ISBLANK(INDEX('Policy Characteristics'!A:A,MATCH($C22,'Policy Characteristics'!$C:$C,0))),"",INDEX('Policy Characteristics'!A:A,MATCH($C22,'Policy Characteristics'!$C:$C,0))) -> Transportation | B22: =IF(ISBLANK(INDEX('Policy Characteristics'!B:B,MATCH($C22,'Policy Characteristics'!$C:$C,0))),"",INDEX('Policy Characteristics'!B:B,MATCH($C22,'Policy Characteristics'!$C:$C,0))) -> Conventional Pollutant Standards | C22: =C$2 -> Percentage Reduction of Separately Regulated Pollutants | D22: aircraft | E22: VOC | F22: aircraft | G22: VOCs | H22: 320 | I22: Yes | J22: =IF(ISBLANK(INDEX('Policy Characteristics'!D:D,MATCH($C22,'Policy Characteristics'!$C:$C,0))),"",INDEX('Policy Characteristics'!D:D,MATCH($C22,'Policy Characteristics'!$C:$C,0))) -> Conventional Pollutant Standard | K22: =IF(ISBLANK(INDEX('Policy Characteristics'!E:E,MATCH($C22,'Policy Characteristics'!$C:$C,0))),"",INDEX('Policy Characteristics'!E:E,MATCH($C22,'Policy Characteristics'!$C:$C,0))) -> trans reduce regulated pollutants | L22: =IF(ISBLANK(INDEX('Policy Characteristics'!F:F,MATCH($C22,'Policy Characteristics'!$C:$C,0))),"",INDEX('Policy Characteristics'!F:F,MATCH($C22,'Policy Characteristics'!$C:$C,0))) -> 0 | M22: =IF(ISBLANK(INDEX('Policy Characteristics'!G:G,MATCH($C22,'Policy Characteristics'!$C:$C,0))),"",INDEX('Policy Characteristics'!G:G,MATCH($C22,'Policy Characteristics'!$C:$C,0))) -> 1 | N22: =IF(ISBLANK(INDEX('Policy Characteristics'!H:H,MATCH($C22,'Policy Characteristics'!$C:$C,0))),"",INDEX('Policy Characteristics'!H:H,MATCH($C22,'Policy Characteristics'!$C:$C,0))) -> 0.02 | O22: =IF(ISBLANK(INDEX('Policy Characteristics'!I:I,MATCH($C22,'Policy Characteristics'!$C:$C,0))),"",INDEX('Policy Characteristics'!I:I,MATCH($C22,'Policy Characteristics'!$C:$C,0))) -> % reduction in emissions | P22: =IF(ISBLANK(INDEX('Policy Characteristics'!J:J,MATCH($C22,'Policy Characteristics'!$C:$C,0))),"",INDEX('Policy Characteristics'!J:J,MATCH($C22,'Policy Characteristics'!$C:$C,0))) -> **Description:** This policy represents strengthening standards for the selected pollutant(s) emitted by the selected vehicle type(s). Conventional pollutants' most important, harmful impacts are on human health rather than on climate change. // **Guidance for setting values:** Mexico has multiple regions with serious air quality concerns from fossil fuel combustion. ProAire (local air quality programs) have been deployed in major cities with some strong measures like those deployed for the Mexico City metropolitan area (strengthening air quality standards, re-zoning industrial areas, emissions registry and inventory, semi-annual vehicle inspections and limits to vehicle use). | Q22: =IF(ISBLANK(INDEX('Policy Characteristics'!K:K,MATCH($C22,'Policy Characteristics'!$C:$C,0))),"",INDEX('Policy Characteristics'!K:K,MATCH($C22,'Policy Characteristics'!$C:$C,0))) -> transportation-sector-main.html#conv-pol-stds | R22: =IF(ISBLANK(INDEX('Policy Characteristics'!L:L,MATCH($C22,'Policy Characteristics'!$C:$C,0))),"",INDEX('Policy Characteristics'!L:L,MATCH($C22,'Policy Characteristics'!$C:$C,0))) -> conventional-pollutant-standards.html
A23: =IF(ISBLANK(INDEX('Policy Characteristics'!A:A,MATCH($C23,'Policy Characteristics'!$C:$C,0))),"",INDEX('Policy Characteristics'!A:A,MATCH($C23,'Policy Characteristics'!$C:$C,0))) -> Transportation | B23: =IF(ISBLANK(INDEX('Policy Characteristics'!B:B,MATCH($C23,'Policy Characteristics'!$C:$C,0))),"",INDEX('Policy Characteristics'!B:B,MATCH($C23,'Policy Characteristics'!$C:$C,0))) -> Conventional Pollutant Standards | C23: =C$2 -> Percentage Reduction of Separately Regulated Pollutants | D23: aircraft | E23: CO | F23: aircraft | G23: CO | H23: 321 | I23: No | J23: =IF(ISBLANK(INDEX('Policy Characteristics'!D:D,MATCH($C23,'Policy Characteristics'!$C:$C,0))),"",INDEX('Policy Characteristics'!D:D,MATCH($C23,'Policy Characteristics'!$C:$C,0))) -> Conventional Pollutant Standard | K23: =IF(ISBLANK(INDEX('Policy Characteristics'!E:E,MATCH($C23,'Policy Characteristics'!$C:$C,0))),"",INDEX('Policy Characteristics'!E:E,MATCH($C23,'Policy Characteristics'!$C:$C,0))) -> trans reduce regulated pollutants | L23: =IF(ISBLANK(INDEX('Policy Characteristics'!F:F,MATCH($C23,'Policy Characteristics'!$C:$C,0))),"",INDEX('Policy Characteristics'!F:F,MATCH($C23,'Policy Characteristics'!$C:$C,0))) -> 0 | M23: =IF(ISBLANK(INDEX('Policy Characteristics'!G:G,MATCH($C23,'Policy Characteristics'!$C:$C,0))),"",INDEX('Policy Characteristics'!G:G,MATCH($C23,'Policy Characteristics'!$C:$C,0))) -> 1 | N23: =IF(ISBLANK(INDEX('Policy Characteristics'!H:H,MATCH($C23,'Policy Characteristics'!$C:$C,0))),"",INDEX('Policy Characteristics'!H:H,MATCH($C23,'Policy Characteristics'!$C:$C,0))) -> 0.02 | O23: =IF(ISBLANK(INDEX('Policy Characteristics'!I:I,MATCH($C23,'Policy Characteristics'!$C:$C,0))),"",INDEX('Policy Characteristics'!I:I,MATCH($C23,'Policy Characteristics'!$C:$C,0))) -> % reduction in emissions | P23: =IF(ISBLANK(INDEX('Policy Characteristics'!J:J,MATCH($C23,'Policy Characteristics'!$C:$C,0))),"",INDEX('Policy Characteristics'!J:J,MATCH($C23,'Policy Characteristics'!$C:$C,0))) -> **Description:** This policy represents strengthening standards for the selected pollutant(s) emitted by the selected vehicle type(s). Conventional pollutants' most important, harmful impacts are on human health rather than on climate change. // **Guidance for setting values:** Mexico has multiple regions with serious air quality concerns from fossil fuel combustion. ProAire (local air quality programs) have been deployed in major cities with some strong measures like those deployed for the Mexico City metropolitan area (strengthening air quality standards, re-zoning industrial areas, emissions registry and inventory, semi-annual vehicle inspections and limits to vehicle use). | Q23: =IF(ISBLANK(INDEX('Policy Characteristics'!K:K,MATCH($C23,'Policy Characteristics'!$C:$C,0))),"",INDEX('Policy Characteristics'!K:K,MATCH($C23,'Policy Characteristics'!$C:$C,0))) -> transportation-sector-main.html#conv-pol-stds | R23: =IF(ISBLANK(INDEX('Policy Characteristics'!L:L,MATCH($C23,'Policy Characteristics'!$C:$C,0))),"",INDEX('Policy Characteristics'!L:L,MATCH($C23,'Policy Characteristics'!$C:$C,0))) -> conventional-pollutant-standards.html
A24: =IF(ISBLANK(INDEX('Policy Characteristics'!A:A,MATCH($C24,'Policy Characteristics'!$C:$C,0))),"",INDEX('Policy Characteristics'!A:A,MATCH($C24,'Policy Characteristics'!$C:$C,0))) -> Transportation | B24: =IF(ISBLANK(INDEX('Policy Characteristics'!B:B,MATCH($C24,'Policy Characteristics'!$C:$C,0))),"",INDEX('Policy Characteristics'!B:B,MATCH($C24,'Policy Characteristics'!$C:$C,0))) -> Conventional Pollutant Standards | C24: =C$2 -> Percentage Reduction of Separately Regulated Pollutants | D24: aircraft | E24: NOx | F24: aircraft | G24: NOx | H24: 322 | I24: Yes | J24: =IF(ISBLANK(INDEX('Policy Characteristics'!D:D,MATCH($C24,'Policy Characteristics'!$C:$C,0))),"",INDEX('Policy Characteristics'!D:D,MATCH($C24,'Policy Characteristics'!$C:$C,0))) -> Conventional Pollutant Standard | K24: =IF(ISBLANK(INDEX('Policy Characteristics'!E:E,MATCH($C24,'Policy Characteristics'!$C:$C,0))),"",INDEX('Policy Characteristics'!E:E,MATCH($C24,'Policy Characteristics'!$C:$C,0))) -> trans reduce regulated pollutants | L24: =IF(ISBLANK(INDEX('Policy Characteristics'!F:F,MATCH($C24,'Policy Characteristics'!$C:$C,0))),"",INDEX('Policy Characteristics'!F:F,MATCH($C24,'Policy Characteristics'!$C:$C,0))) -> 0 | M24: =IF(ISBLANK(INDEX('Policy Characteristics'!G:G,MATCH($C24,'Policy Characteristics'!$C:$C,0))),"",INDEX('Policy Characteristics'!G:G,MATCH($C24,'Policy Characteristics'!$C:$C,0))) -> 1 | N24: =IF(ISBLANK(INDEX('Policy Characteristics'!H:H,MATCH($C24,'Policy Characteristics'!$C:$C,0))),"",INDEX('Policy Characteristics'!H:H,MATCH($C24,'Policy Characteristics'!$C:$C,0))) -> 0.02 | O24: =IF(ISBLANK(INDEX('Policy Characteristics'!I:I,MATCH($C24,'Policy Characteristics'!$C:$C,0))),"",INDEX('Policy Characteristics'!I:I,MATCH($C24,'Policy Characteristics'!$C:$C,0))) -> % reduction in emissions | P24: =IF(ISBLANK(INDEX('Policy Characteristics'!J:J,MATCH($C24,'Policy Characteristics'!$C:$C,0))),"",INDEX('Policy Characteristics'!J:J,MATCH($C24,'Policy Characteristics'!$C:$C,0))) -> **Description:** This policy represents strengthening standards for the selected pollutant(s) emitted by the selected vehicle type(s). Conventional pollutants' most important, harmful impacts are on human health rather than on climate change. // **Guidance for setting values:** Mexico has multiple regions with serious air quality concerns from fossil fuel combustion. ProAire (local air quality programs) have been deployed in major cities with some strong measures like those deployed for the Mexico City metropolitan area (strengthening air quality standards, re-zoning industrial areas, emissions registry and inventory, semi-annual vehicle inspections and limits to vehicle use). | Q24: =IF(ISBLANK(INDEX('Policy Characteristics'!K:K,MATCH($C24,'Policy Characteristics'!$C:$C,0))),"",INDEX('Policy Characteristics'!K:K,MATCH($C24,'Policy Characteristics'!$C:$C,0))) -> transportation-sector-main.html#conv-pol-stds | R24: =IF(ISBLANK(INDEX('Policy Characteristics'!L:L,MATCH($C24,'Policy Characteristics'!$C:$C,0))),"",INDEX('Policy Characteristics'!L:L,MATCH($C24,'Policy Characteristics'!$C:$C,0))) -> conventional-pollutant-standards.html
A25: =IF(ISBLANK(INDEX('Policy Characteristics'!A:A,MATCH($C25,'Policy Characteristics'!$C:$C,0))),"",INDEX('Policy Characteristics'!A:A,MATCH($C25,'Policy Characteristics'!$C:$C,0))) -> Transportation | B25: =IF(ISBLANK(INDEX('Policy Characteristics'!B:B,MATCH($C25,'Policy Characteristics'!$C:$C,0))),"",INDEX('Policy Characteristics'!B:B,MATCH($C25,'Policy Characteristics'!$C:$C,0))) -> Conventional Pollutant Standards | C25: =C$2 -> Percentage Reduction of Separately Regulated Pollutants | D25: aircraft | E25: PM10 | F25: aircraft | G25: PM10 | H25: 323 | I25: No | J25: =IF(ISBLANK(INDEX('Policy Characteristics'!D:D,MATCH($C25,'Policy Characteristics'!$C:$C,0))),"",INDEX('Policy Characteristics'!D:D,MATCH($C25,'Policy Characteristics'!$C:$C,0))) -> Conventional Pollutant Standard | K25: =IF(ISBLANK(INDEX('Policy Characteristics'!E:E,MATCH($C25,'Policy Characteristics'!$C:$C,0))),"",INDEX('Policy Characteristics'!E:E,MATCH($C25,'Policy Characteristics'!$C:$C,0))) -> trans reduce regulated pollutants | L25: =IF(ISBLANK(INDEX('Policy Characteristics'!F:F,MATCH($C25,'Policy Characteristics'!$C:$C,0))),"",INDEX('Policy Characteristics'!F:F,MATCH($C25,'Policy Characteristics'!$C:$C,0))) -> 0 | M25: =IF(ISBLANK(INDEX('Policy Characteristics'!G:G,MATCH($C25,'Policy Characteristics'!$C:$C,0))),"",INDEX('Policy Characteristics'!G:G,MATCH($C25,'Policy Characteristics'!$C:$C,0))) -> 1 | N25: =IF(ISBLANK(INDEX('Policy Characteristics'!H:H,MATCH($C25,'Policy Characteristics'!$C:$C,0))),"",INDEX('Policy Characteristics'!H:H,MATCH($C25,'Policy Characteristics'!$C:$C,0))) -> 0.02 | O25: =IF(ISBLANK(INDEX('Policy Characteristics'!I:I,MATCH($C25,'Policy Characteristics'!$C:$C,0))),"",INDEX('Policy Characteristics'!I:I,MATCH($C25,'Policy Characteristics'!$C:$C,0))) -> % reduction in emissions | P25: =IF(ISBLANK(INDEX('Policy Characteristics'!J:J,MATCH($C25,'Policy Characteristics'!$C:$C,0))),"",INDEX('Policy Characteristics'!J:J,MATCH($C25,'Policy Characteristics'!$C:$C,0))) -> **Description:** This policy represents strengthening standards for the selected pollutant(s) emitted by the selected vehicle type(s). Conventional pollutants' most important, harmful impacts are on human health rather than on climate change. // **Guidance for setting values:** Mexico has multiple regions with serious air quality concerns from fossil fuel combustion. ProAire (local air quality programs) have been deployed in major cities with some strong measures like those deployed for the Mexico City metropolitan area (strengthening air quality standards, re-zoning industrial areas, emissions registry and inventory, semi-annual vehicle inspections and limits to vehicle use). | Q25: =IF(ISBLANK(INDEX('Policy Characteristics'!K:K,MATCH($C25,'Policy Characteristics'!$C:$C,0))),"",INDEX('Policy Characteristics'!K:K,MATCH($C25,'Policy Characteristics'!$C:$C,0))) -> transportation-sector-main.html#conv-pol-stds | R25: =IF(ISBLANK(INDEX('Policy Characteristics'!L:L,MATCH($C25,'Policy Characteristics'!$C:$C,0))),"",INDEX('Policy Characteristics'!L:L,MATCH($C25,'Policy Characteristics'!$C:$C,0))) -> conventional-pollutant-standards.html
... A61: =IF(ISBLANK(INDEX('Policy Characteristics'!A:A,MATCH($C61,'Policy Characteristics'!$C:$C,0))),"",INDEX('Policy Characteristics'!A:A,MATCH($C61,'Policy Characteristics'!$C:$C,0))) -> Transportation | B61: =IF(ISBLANK(INDEX('Policy Characteristics'!B:B,MATCH($C61,'Policy Characteristics'!$C:$C,0))),"",INDEX('Policy Characteristics'!B:B,MATCH($C61,'Policy Characteristics'!$C:$C,0))) -> Conventional Pollutant Standards | C61: =C$2 -> Percentage Reduction of Separately Regulated Pollutants | D61: motorbikes | E61: N2O | F61: motorbikes | G61: N2O | H61: 359 | I61: No | J61: =IF(ISBLANK(INDEX('Policy Characteristics'!D:D,MATCH($C61,'Policy Characteristics'!$C:$C,0))),"",INDEX('Policy Characteristics'!D:D,MATCH($C61,'Policy Characteristics'!$C:$C,0))) -> Conventional Pollutant Standard | K61: =IF(ISBLANK(INDEX('Policy Characteristics'!E:E,MATCH($C61,'Policy Characteristics'!$C:$C,0))),"",INDEX('Policy Characteristics'!E:E,MATCH($C61,'Policy Characteristics'!$C:$C,0))) -> trans reduce regulated pollutants | L61: =IF(ISBLANK(INDEX('Policy Characteristics'!F:F,MATCH($C61,'Policy Characteristics'!$C:$C,0))),"",INDEX('Policy Characteristics'!F:F,MATCH($C61,'Policy Characteristics'!$C:$C,0))) -> 0 | M61: =IF(ISBLANK(INDEX('Policy Characteristics'!G:G,MATCH($C61,'Policy Characteristics'!$C:$C,0))),"",INDEX('Policy Characteristics'!G:G,MATCH($C61,'Policy Characteristics'!$C:$C,0))) -> 1 | N61: =IF(ISBLANK(INDEX('Policy Characteristics'!H:H,MATCH($C61,'Policy Characteristics'!$C:$C,0))),"",INDEX('Policy Characteristics'!H:H,MATCH($C61,'Policy Characteristics'!$C:$C,0))) -> 0.02 | O61: =IF(ISBLANK(INDEX('Policy Characteristics'!I:I,MATCH($C61,'Policy Characteristics'!$C:$C,0))),"",INDEX('Policy Characteristics'!I:I,MATCH($C61,'Policy Characteristics'!$C:$C,0))) -> % reduction in emissions | P61: =IF(ISBLANK(INDEX('Policy Characteristics'!J:J,MATCH($C61,'Policy Characteristics'!$C:$C,0))),"",INDEX('Policy Characteristics'!J:J,MATCH($C61,'Policy Characteristics'!$C:$C,0))) -> **Description:** This policy represents strengthening standards for the selected pollutant(s) emitted by the selected vehicle type(s). Conventional pollutants' most important, harmful impacts are on human health rather than on climate change. // **Guidance for setting values:** Mexico has multiple regions with serious air quality concerns from fossil fuel combustion. ProAire (local air quality programs) have been deployed in major cities with some strong measures like those deployed for the Mexico City metropolitan area (strengthening air quality standards, re-zoning industrial areas, emissions registry and inventory, semi-annual vehicle inspections and limits to vehicle use). | Q61: =IF(ISBLANK(INDEX('Policy Characteristics'!K:K,MATCH($C61,'Policy Characteristics'!$C:$C,0))),"",INDEX('Policy Characteristics'!K:K,MATCH($C61,'Policy Characteristics'!$C:$C,0))) -> transportation-sector-main.html#conv-pol-stds | R61: =IF(ISBLANK(INDEX('Policy Characteristics'!L:L,MATCH($C61,'Policy Characteristics'!$C:$C,0))),"",INDEX('Policy Characteristics'!L:L,MATCH($C61,'Policy Characteristics'!$C:$C,0))) -> conventional-pollutant-standards.html
A62: =IF(ISBLANK(INDEX('Policy Characteristics'!A:A,MATCH($C62,'Policy Characteristics'!$C:$C,0))),"",INDEX('Policy Characteristics'!A:A,MATCH($C62,'Policy Characteristics'!$C:$C,0))) -> Transportation | B62: =IF(ISBLANK(INDEX('Policy Characteristics'!B:B,MATCH($C62,'Policy Characteristics'!$C:$C,0))),"",INDEX('Policy Characteristics'!B:B,MATCH($C62,'Policy Characteristics'!$C:$C,0))) -> Electric Vehicle Charger Deployment | C62: EV Charger Deployment | H62: 360 | I62: Yes | J62: =IF(ISBLANK(INDEX('Policy Characteristics'!D:D,MATCH($C62,'Policy Characteristics'!$C:$C,0))),"",INDEX('Policy Characteristics'!D:D,MATCH($C62,'Policy Characteristics'!$C:$C,0))) -> EV Charger Deployment | K62: =IF(ISBLANK(INDEX('Policy Characteristics'!E:E,MATCH($C62,'Policy Characteristics'!$C:$C,0))),"",INDEX('Policy Characteristics'!E:E,MATCH($C62,'Policy Characteristics'!$C:$C,0))) -> trans EV charger deployment | L62: =IF(ISBLANK(INDEX('Policy Characteristics'!F:F,MATCH($C62,'Policy Characteristics'!$C:$C,0))),"",INDEX('Policy Characteristics'!F:F,MATCH($C62,'Policy Characteristics'!$C:$C,0))) -> 0 | M62: =IF(ISBLANK(INDEX('Policy Characteristics'!G:G,MATCH($C62,'Policy Characteristics'!$C:$C,0))),"",INDEX('Policy Characteristics'!G:G,MATCH($C62,'Policy Characteristics'!$C:$C,0))) -> 300 | N62: =IF(ISBLANK(INDEX('Policy Characteristics'!H:H,MATCH($C62,'Policy Characteristics'!$C:$C,0))),"",INDEX('Policy Characteristics'!H:H,MATCH($C62,'Policy Characteristics'!$C:$C,0))) -> 5 | O62: =IF(ISBLANK(INDEX('Policy Characteristics'!I:I,MATCH($C62,'Policy Characteristics'!$C:$C,0))),"",INDEX('Policy Characteristics'!I:I,MATCH($C62,'Policy Characteristics'!$C:$C,0))) -> chargers / 100k pop | P62: =IF(ISBLANK(INDEX('Policy Characteristics'!J:J,MATCH($C62,'Policy Characteristics'!$C:$C,0))),"",INDEX('Policy Characteristics'!J:J,MATCH($C62,'Policy Characteristics'!$C:$C,0))) -> **Description:** This policy represents increasing the deployment of EV charging stations, including DC Fast and Level 2 charging stations. It is set in chargers per 100,000 people (cumulative, not per year), additional to chargers in the Reference case. This policy lever does not have an effect on energy use/emissions/deployment. It is meant to account for the costs of additional charging infrastructure. // **Guidance for setting values:** As of Mar 2019, the U.S. had 63,000 chargers, just under 20 chargers per 100k pop. In 2016, the U.S. had 111,076 gas stations with an average of 8 fuel pumps each, or 275 pumps per 100k pop. Therefore, a lever setting of 255 would cause the population density of EV chargers to equal the 2016 population density of fuel pumps. | Q62: =IF(ISBLANK(INDEX('Policy Characteristics'!K:K,MATCH($C62,'Policy Characteristics'!$C:$C,0))),"",INDEX('Policy Characteristics'!K:K,MATCH($C62,'Policy Characteristics'!$C:$C,0))) | R62: =IF(ISBLANK(INDEX('Policy Characteristics'!L:L,MATCH($C62,'Policy Characteristics'!$C:$C,0))),"",INDEX('Policy Characteristics'!L:L,MATCH($C62,'Policy Characteristics'!$C:$C,0))) -> ev-charger-deployment.html
A63: =IF(ISBLANK(INDEX('Policy Characteristics'!A:A,MATCH($C63,'Policy Characteristics'!$C:$C,0))),"",INDEX('Policy Characteristics'!A:A,MATCH($C63,'Policy Characteristics'!$C:$C,0))) -> Transportation | B63: =IF(ISBLANK(INDEX('Policy Characteristics'!B:B,MATCH($C63,'Policy Characteristics'!$C:$C,0))),"",INDEX('Policy Characteristics'!B:B,MATCH($C63,'Policy Characteristics'!$C:$C,0))) -> Electric Vehicle Range & Charging Time | C63: Reduce EV Range Anxiety and Charging Time | H63: 361 | I63: Yes | J63: =IF(ISBLANK(INDEX('Policy Characteristics'!D:D,MATCH($C63,'Policy Characteristics'!$C:$C,0))),"",INDEX('Policy Characteristics'!D:D,MATCH($C63,'Policy Characteristics'!$C:$C,0))) -> EV Range & Charging Time | K63: =IF(ISBLANK(INDEX('Policy Characteristics'!E:E,MATCH($C63,'Policy Characteristics'!$C:$C,0))),"",INDEX('Policy Characteristics'!E:E,MATCH($C63,'Policy Characteristics'!$C:$C,0))) -> trans reduce EV range anxiety and charging time | L63: =IF(ISBLANK(INDEX('Policy Characteristics'!F:F,MATCH($C63,'Policy Characteristics'!$C:$C,0))),"",INDEX('Policy Characteristics'!F:F,MATCH($C63,'Policy Characteristics'!$C:$C,0))) -> 0 | M63: =IF(ISBLANK(INDEX('Policy Characteristics'!G:G,MATCH($C63,'Policy Characteristics'!$C:$C,0))),"",INDEX('Policy Characteristics'!G:G,MATCH($C63,'Policy Characteristics'!$C:$C,0))) -> 1 | N63: =IF(ISBLANK(INDEX('Policy Characteristics'!H:H,MATCH($C63,'Policy Characteristics'!$C:$C,0))),"",INDEX('Policy Characteristics'!H:H,MATCH($C63,'Policy Characteristics'!$C:$C,0))) -> 0.02 | O63: =IF(ISBLANK(INDEX('Policy Characteristics'!I:I,MATCH($C63,'Policy Characteristics'!$C:$C,0))),"",INDEX('Policy Characteristics'!I:I,MATCH($C63,'Policy Characteristics'!$C:$C,0))) -> % reduction in concern | P63: =IF(ISBLANK(INDEX('Policy Characteristics'!J:J,MATCH($C63,'Policy Characteristics'!$C:$C,0))),"",INDEX('Policy Characteristics'!J:J,MATCH($C63,'Policy Characteristics'!$C:$C,0))) -> **Description:** This policy specifies a percentage reduction in vehicle buyers' aversion to electric vehicles due to concerns over the vehicles' range (how far the EV can travel on a charge) and charging time. A 100% setting implies consumers are no more concerned about EV range and charging time than they are about range and fueling time of gasoline vehicles. It does not imply that range is infinite, nor that charging is instantaneous. This policy only affects passenger LDVs. // **Guidance for setting values:** U.S. model year 2017 all-electric (not hybrid) vehicles had ranges from 58 to 335 miles (median 114 miles), and the typical charging time was 0.5 hours (with a DC Fast charger) or 3.5 hours (with a Level 2 charger). | Q63: =IF(ISBLANK(INDEX('Policy Characteristics'!K:K,MATCH($C63,'Policy Characteristics'!$C:$C,0))),"",INDEX('Policy Characteristics'!K:K,MATCH($C63,'Policy Characteristics'!$C:$C,0))) | R63: =IF(ISBLANK(INDEX('Policy Characteristics'!L:L,MATCH($C63,'Policy Characteristics'!$C:$C,0))),"",INDEX('Policy Characteristics'!L:L,MATCH($C63,'Policy Characteristics'!$C:$C,0))) -> reduce-range-anxiety-charging-time.html
