Workbook
Name billion: #REF!
Name billion: #REF!
Name Diesel_FE_2024: 'Fuel Economy Stds'!$E$54
Name Diesel_Sales_2024: 'Fuel Economy Stds'!$F$22
Name Eno_TM: #REF!
Name Eno_TM: #REF!
Name Eno_TM: #REF!
Name Eno_TM: #REF!
Name Eno_TM: #REF!
Name Eno_Tons: #REF!
Name Eno_Tons: #REF!
Name Eno_Tons: #REF!
Name Eno_Tons: #REF!
Name Eno_Tons: #REF!
Name EV_FE_2024: 'Fuel Economy Stds'!$E$51
Name EV_Sales_2024: 'Fuel Economy Stds'!$F$19
Name Fuel_Economies: 'Fuel Economy Stds'!$E$51:$J$57
Name Gasoline_FE_2024: 'Fuel Economy Stds'!#REF!
Name Gasoline_Sales_2024: 'Fuel Economy Stds'!$F$21
Name Hydg_FE_2024: 'Fuel Economy Stds'!$E$57
Name Hydg_Sales_2024: 'Fuel Economy Stds'!$F$25
Name LPG_FE_2024: 'Fuel Economy Stds'!$E$56
Name LPG_Sales_2024: 'Fuel Economy Stds'!$F$24
Name NG_FE_2024: 'Fuel Economy Stds'!$E$52
Name NG_Sales_2024: 'Fuel Economy Stds'!$F$20
Name NTS_YR: #REF!
Name NTS_YR: About!$B$105
Name PHEV_FE_2024: 'Fuel Economy Stds'!$E$55
Name PHEV_Sales_2024: 'Fuel Economy Stds'!$F$23
Name Sales: 'Fuel Economy Stds'!$F$19:$K$25
Name Sales_2024: 'Fuel Economy Stds'!$F$19:$F$25
Name Sales_2025: 'Fuel Economy Stds'!$G$19:$G$25
Name Sales_2026: 'Fuel Economy Stds'!$H$19:$H$25
Name Sales_2027: 'Fuel Economy Stds'!$I$19:$I$25
Name Sales_2028: 'Fuel Economy Stds'!$J$19:$J$25
Name Sales_2029: 'Fuel Economy Stds'!$K$19:$K$25
Name Standards: 'Fuel Economy Stds'!$B$5:$G$5
Name Sum_T2: #REF!
Name Sum_T2: #REF!
Name Sum_T2: #REF!
Name Sum_T2: #REF!
Name Sum_T2: #REF!
Name Sum_TTM: #REF!
Name Sum_TTM: #REF!
Name Sum_TTM: #REF!
Name Sum_TTM: #REF!
Name Sum_TTM: #REF!
Name ti_tbl_50: #REF!
Name ti_tbl_50: #REF!
Name ti_tbl_50: #REF!
Name ti_tbl_50: #REF!
Name ti_tbl_50: #REF!
Name ti_tbl_50: #REF!
Name ti_tbl_69: #REF!
Name ti_tbl_69: #REF!
Name ti_tbl_69: #REF!
Name ti_tbl_69: #REF!
Name ti_tbl_69: #REF!
Name ti_tbl_69: #REF!
Name trillion: #REF!

Sheet About
A1: BNVFE BAU New Vehicle Fuel Economy
A3: Sources: | B3: See Notes section for which vehicle types use which sources
B4: EIA
B5: 2021, 2020
B6: Annual Energy Outlook 2021, 2020
B7: https://www.eia.gov/outlooks/aeo/tables_ref.cfm
B8: Tables 7, 35, 36, 38, 40, 47, 48, 49
B10: Bureau of Transportation Statistics
B11: 2017
B12: National Transportation Statistics
B13: https://www.rita.dot.gov/bts/sites/rita.dot.gov.bts/files/publications/national_transportation_statistics/index.html
B14: Table 1-40
B16: U.S. Coast Guard
B17: 2013
B18: National Recreational Boating Survey 2012
B19: http://www.uscgboating.org/library/recreational-boating-servey/2012survey%20report.pdf
B20: Page 63, Table 40
B22: U.S. Department of Energy
B23: 2015
B24: Fuel Cells Fact Sheet
B25: https://www.energy.gov/sites/prod/files/2015/11/f27/fcto_fuel_cells_fact_sheet.pdf
B27: U.S EPA
B28: 2022
B29: Automotive Trends Data
B30: https://www.epa.gov/automotive-trends/explore-automotive-trends-data#DetailedData
B32: Others as noted on "Calculations Etc" tab
B34: Passenger rail diesel vs. electric efficiency
B35: Environmental and Energy Study Institute
B36: 2018
B37: Electrification of U.S. Railways: Pie in the Sky, or Realistic Goal?
B38: https://www.eesi.org/articles/view/electrification-of-u.s.-railways-pie-in-the-sky-or-realistic-goal
B39: Third paragraph
A41: Notes
A42: This variable gives fuel economy for new vehicles in units of cargo distance per BTU.
A44: passenger LDVs
A45: Sources: AEO 7, AEO 40, others as noted on "Calculations Etc" tab
A46: The AEO provides new vehicle fuel economy in mpge terms. For each of the 7 EPS technologies, we take a weighted average of EIA's listed new vehicle
A47: fuel economy for all vehicles that would fall under the given technology. We then adjust by EIA's ratio of onroad:tested fuel economy from Table 7 and
A48: convert to thing-miles/BTU by multiplying by the passenger loading used in the file trans/AVLo and the BTU content of a gallon of gasoline.
A50: EIA's NEMS model has higher efficiency values than reported by the EPA, because it it over-complies on efficiency in order to meet EPA standards (since it doesn't have representation of other options to reduce the equivalent g CO2/mile metric from HFC/advanced tech credits). We calculate the delta between EPA and EIA fuel efficiency
A51: values in 2022 and subtract that value from future years.
A53: freight LDVs and HDVs
A54: Sources: see file trans/SYFAFE, AEO 7, AEO 49
A55: We classify AEO's light commercial trucks category as well as light-medium and medium duty vehicles
... A103: This vehicle type is not used in the U.S. model.
A105: NTS_YR | B105: 2019

Sheet AEO 2023 Table 7
B1: ref2023.d020623a | C1: 2022 | D1: 2023 | E1: 2024 | F1: 2025 | G1: 2026 | H1: 2027 | I1: 2028 | J1: 2029 | K1: 2030 | L1: 2031 | M1: 2032 | N1: 2033 | O1: 2034 | P1: 2035 | Q1: 2036 | R1: 2037 | S1: 2038 | T1: 2039 | U1: 2040 | V1: 2041 | W1: 2042 | X1: 2043 | Y1: 2044 | Z1: 2045 | AA1: 2046 | AB1: 2047 | AC1: 2048 | AD1: 2049 | AE1: 2050
C3: Report | D3: Annual Energy Outlook 2023
C4: Scenario | D4: ref2023 | G4: Reference
C5: Datekey | D5: d020623a
C6: Release Date | E6: March 2023
A10: TKI000 | B10: 7. Transportation Sector Key Indicators and Delivered Energy Consumption | AF10: Average
AF11: Annual
AF12: Change
B13: Key Indicators and Consumption | C13: 2022 | D13: 2023 | E13: 2024 | F13: 2025 | G13: 2026 | H13: 2027 | I13: 2028 | J13: 2029 | K13: 2030 | L13: 2031 | M13: 2032 | N13: 2033 | O13: 2034 | P13: 2035 | Q13: 2036 | R13: 2037 | S13: 2038 | T13: 2039 | U13: 2040 | V13: 2041 | W13: 2042 | X13: 2043 | Y13: 2044 | Z13: 2045 | AA13: 2046 | AB13: 2047 | AC13: 2048 | AD13: 2049 | AE13: 2050 | AF13: 2022–2050
B15: Key Indicators
B16: Travel Indicators
B17: (billion vehicle miles traveled)
A18: TKI000:ba_Light-DutyVeh | B18: Light-Duty Vehicles less than 8,501 pounds | C18: 2843.2981 | D18: 2901.3589 | E18: 2922.5066 | F18: 2933.3601 | G18: 2954.238 | H18: 2981.9343 | I18: 3007.5581 | J18: 3027.573 | K18: 3042.8433 | L18: 3055.7747 | M18: 3066.6516 | N18: 3082.3594 | O18: 3102.4182 | P18: 3120.7375 | Q18: 3135.6208 | R18: 3152.9177 | S18: 3172.4355 | T18: 3192.1006 | U18: 3214.563 | V18: 3237.5806 | W18: 3261.5847 | X18: 3284.8975 | Y18: 3309.0391 | Z18: 3334.7034 | AA18: 3364.5225 | AB18: 3396.5352 | AC18: 3429.5627 | AD18: 3463.0249 | AE18: 3499.543 | AF18: 0.007444
A19: TKI000:ba_CommercialLig | B19: Commercial Light Trucks 1/ | C19: 102.21495 | D19: 103.34346 | E19: 103.55378 | F19: 104.36999 | G19: 105.65627 | H19: 107.00255 | I19: 108.20406 | J19: 109.32984 | K19: 110.21457 | L19: 111.0637 | M19: 112.17591 | N19: 113.26731 | O19: 114.36133 | P19: 115.53986 | Q19: 116.6934 | R19: 117.93478 | S19: 119.26325 | T19: 120.51714 | U19: 121.9657 | V19: 123.54321 | W19: 125.05544 | X19: 126.4902 | Y19: 127.8319 | Z19: 129.14803 | AA19: 130.64792 | AB19: 132.25534 | AC19: 133.71924 | AD19: 135.16911 | AE19: 137.06503 | AF19: 0.010533
A20: TKI000:ba_FreightTrucks | B20: Freight Trucks greater than 10,000 pounds | C20: 321.95499 | D20: 320.72061 | E20: 321.15665 | F20: 324.03918 | G20: 328.45148 | H20: 332.31928 | I20: 335.87875 | J20: 338.621 | K20: 341.15326 | L20: 344.16229 | M20: 348.16583 | N20: 351.54123 | O20: 354.83011 | P20: 358.3447 | Q20: 361.39355 | R20: 364.92679 | S20: 368.38065 | T20: 371.81143 | U20: 375.58807 | V20: 379.58752 | W20: 383.51465 | X20: 387.20883 | Y20: 390.63339 | Z20: 393.83795 | AA20: 397.54263 | AB20: 401.35467 | AC20: 404.65982 | AD20: 408.22446 | AE20: 413.08252 | AF20: 0.008941
B21: (billion passenger miles traveled)
A22: TKI000:buspassmiles | B22: Bus Transportation | C22: 175.47365 | D22: 186.88329 | E22: 193.3692 | F22: 197.39229 | G22: 200.32752 | H22: 202.52968 | I22: 204.21141 | J22: 205.46838 | K22: 206.39357 | L22: 207.0294 | M22: 207.54085 | N22: 207.99565 | O22: 208.43976 | P22: 208.79684 | Q22: 209.10339 | R22: 209.37013 | S22: 209.49379 | T22: 209.54416 | U22: 209.54358 | V22: 209.49118 | W22: 209.41185 | X22: 209.25844 | Y22: 209.10913 | Z22: 208.93102 | AA22: 208.81189 | AB22: 208.60612 | AC22: 208.41769 | AD22: 208.19235 | AE22: 207.99593 | AF22: 0.006091
A23: TKI000:railpassmiles | B23: Passenger Rail | C23: 30.144947 | D23: 32.030231 | E23: 33.06411 | F23: 33.706196 | G23: 34.620327 | H23: 35.443916 | I23: 36.137474 | J23: 36.650322 | K23: 37.00806 | L23: 37.264553 | M23: 37.633518 | N23: 38.06789 | O23: 38.564194 | P23: 38.985653 | Q23: 39.398945 | R23: 39.809189 | S23: 40.237045 | T23: 40.652229 | U23: 41.127975 | V23: 41.567631 | W23: 42.019573 | X23: 42.40731 | Y23: 42.842342 | Z23: 43.266335 | AA23: 43.867863 | AB23: 44.361511 | AC23: 44.905075 | AD23: 45.395485 | AE23: 46.002594 | AF23: 0.01521
B24: (billion seat miles available)
A25: TKI000:ba_Air | B25: Air | C25: 1173.0347 | D25: 1318.6946 | E25: 1361.6111 | F25: 1371.6552 | G25: 1402.928 | H25: 1433.8398 | I25: 1461.4722 | J25: 1484.8291 | K25: 1504.2688 | L25: 1524.7269 | M25: 1552.2568 | N25: 1583.9248 | O25: 1615.3802 | P25: 1647.3462 | Q25: 1682.5896 | R25: 1721.0469 | S25: 1761.139 | T25: 1801.941 | U25: 1848.072 | V25: 1894.2041 | W25: 1941.463 | X25: 1990.3643 | Y25: 2038.4374 | Z25: 2085.6875 | AA25: 2134.0049 | AB25: 2185.897 | AC25: 2238.8362 | AD25: 2292.3555 | AE25: 2350.269 | AF25: 0.02513
B26: (billion ton miles traveled)
A27: TKI000:ba_Rail | B27: Rail | C27: 1620.4949 | D27: 1600.1008 | E27: 1666.9198 | F27: 1628.4084 | G27: 1561.4207 | H27: 1509.6494 | I27: 1489.7312 | J27: 1507.5151 | K27: 1500.1649 | L27: 1506.9524 | M27: 1522.1982 | N27: 1534.7394 | O27: 1543.2374 | P27: 1554.5907 | Q27: 1557.5254 | R27: 1562.4816 | S27: 1568.9661 | T27: 1568.3395 | U27: 1571.7775 | V27: 1585.6112 | W27: 1597.307 | X27: 1600.1909 | Y27: 1601.8328 | Z27: 1602.9988 | AA27: 1608.1294 | AB27: 1618.0824 | AC27: 1630.808 | AD27: 1636.8905 | AE27: 1649.4695 | AF27: 0.000633
A28: TKI000:ba_DomesticShipp | B28: Domestic Shipping | C28: 444.89887 | D28: 450.42761 | E28: 448.61005 | F28: 446.74628 | G28: 445.22772 | H28: 442.84778 | I28: 440.43005 | J28: 437.0246 | K28: 434.03641 | L28: 431.39212 | M28: 429.99737 | N28: 428.16068 | O28: 426.27862 | P28: 424.17816 | Q28: 421.71698 | R28: 419.81464 | S28: 417.56705 | T28: 415.80768 | U28: 414.04514 | V28: 412.52209 | W28: 411.24774 | X28: 409.97736 | Y28: 408.52225 | Z28: 406.63034 | AA28: 405.35852 | AB28: 403.86591 | AC28: 401.97906 | AD28: 400.55664 | AE28: 400.09833 | AF28: -0.003783
B30: Energy Efficiency Indicators | C30: =C41/C38 -> 0.81570903 | D30: =C30/'EPA Auto Trends 2022'!B3 -> 1.0579946
B31: (miles per gallon)
A32: TKI000:ca_AvgCAFEStand | B32: New Light-Duty Vehicle CAFE Standard 2/ | C32: 35.855949 | D32: 36.277985 | E32: 39.337013 | F32: 42.578201 | G32: 47.262627 | H32: 47.227249 | I32: 47.18121 | J32: 47.168774 | K32: 47.163849 | L32: 47.152081 | M32: 47.159279 | N32: 47.152672 | O32: 47.146118 | P32: 47.131687 | Q32: 47.138325 | R32: 47.119869 | S32: 47.100937 | T32: 47.084251 | U32: 47.059879 | V32: 47.032314 | W32: 47.004074 | X32: 46.960155 | Y32: 46.939564 | Z32: 46.91069 | AA32: 46.948238 | AB32: 46.913113 | AC32: 46.90683 | AD32: 46.880138 | AE32: 46.870857 | AF32: 0.009613
A33: TKI000:ca_CarCAFEStand | B33: New Car 2/ | C33: 45.004654 | D33: 45.471119 | E33: 49.460312 | F33: 53.789036 | G33: 59.791531 | H33: 59.80352 | I33: 59.817413 | J33: 59.819332 | K33: 59.821598 | L33: 59.822445 | M33: 59.827473 | N33: 59.828793 | O33: 59.83078 | P33: 59.83112 | Q33: 59.842136 | R33: 59.842136 | S33: 59.842136 | T33: 59.843197 | U33: 59.843197 | V33: 59.843231 | W33: 59.845177 | X33: 59.845177 | Y33: 59.848228 | Z33: 59.848228 | AA33: 59.867775 | AB33: 59.867775 | AC33: 59.867775 | AD33: 59.867775 | AE33: 59.867775 | AF33: 0.010244
A34: TKI000:ca_TwukCAFEStand | B34: New Light Truck 2/ | C34: 32.047302 | D34: 32.608868 | E34: 35.403008 | F34: 38.46349 | G34: 42.755749 | H34: 42.75658 | I34: 42.76173 | J34: 42.76173 | K34: 42.761841 | L34: 42.762085 | M34: 42.762169 | N34: 42.76236 | O34: 42.76239 | P34: 42.76252 | Q34: 42.762554 | R34: 42.762699 | S34: 42.762756 | T34: 42.762825 | U34: 42.762897 | V34: 42.762962 | W34: 42.763016 | X34: 42.763103 | Y34: 42.763103 | Z34: 42.763184 | AA34: 42.763184 | AB34: 42.763294 | AC34: 42.763294 | AD34: 42.763393 | AE34: 42.763393 | AF34: 0.010356
A35: TKI000:ca_NewVehCred | B35: Compliance New Light-Duty Vehicle 3/ | C35: 41.802036 | D35: 43.2672 | E35: 44.448151 | F35: 47.052715 | G35: 48.571758 | H35: 49.79253 | I35: 52.281479 | J35: 53.248959 | K35: 53.962006 | L35: 54.332035 | M35: 54.872646 | N35: 55.329353 | O35: 55.771633 | P35: 56.242725 | Q35: 56.632603 | R35: 56.856194 | S35: 57.030457 | T35: 57.310715 | U35: 57.240421 | V35: 57.306023 | W35: 57.371868 | X35: 57.326744 | Y35: 57.237999 | Z35: 57.125122 | AA35: 57.475964 | AB35: 57.327747 | AC35: 57.273457 | AD35: 57.524818 | AE35: 57.479156 | AF35: 0.011439
A36: TKI000:ca_NewCarCred | B36: New Car 3/ | C36: 56.582645 | D36: 58.322227 | E36: 59.783314 | F36: 64.222374 | G36: 65.997482 | H36: 68.148636 | I36: 72.759445 | J36: 74.876167 | K36: 76.446304 | L36: 77.157303 | M36: 78.145363 | N36: 78.735664 | O36: 79.269257 | P36: 79.864815 | Q36: 80.311752 | R36: 80.510567 | S36: 80.643074 | T36: 81.042244 | U36: 80.790894 | V36: 80.999863 | W36: 81.213394 | X36: 81.251564 | Y36: 81.126785 | Z36: 80.963654 | AA36: 81.962257 | AB36: 81.685669 | AC36: 81.57402 | AD36: 82.338425 | AE36: 82.243484 | AF36: 0.013446
A37: TKI000:ca_NewTwukCred | B37: New Light Truck 3/ | C37: 36.263931 | D37: 37.832123 | E37: 39.014805 | F37: 41.375153 | G37: 42.876762 | H37: 43.911583 | I37: 45.953789 | J37: 46.678478 | K37: 47.207012 | L37: 47.518375 | M37: 47.939487 | N37: 48.362621 | O37: 48.779861 | P37: 49.233047 | Q37: 49.585567 | R37: 49.838345 | S37: 50.048077 | T37: 50.325745 | U37: 50.338009 | V37: 50.426777 | W37: 50.517311 | X37: 50.542614 | Y37: 50.50412 | Z37: 50.459385 | AA37: 50.61805 | AB37: 50.565735 | AC37: 50.535652 | AD37: 50.739391 | AE37: 50.721836 | AF37: 0.012055
A38: TKI000:ca_TestedNewVeh | B38: Tested New Light-Duty Vehicle 4/ | C38: 37.621078 | D38: 38.382416 | E38: 39.075672 | F38: 40.794502 | G38: 41.684994 | H38: 42.387779 | I38: 43.992405 | J38: 44.482399 | K38: 44.828846 | L38: 45.012852 | M38: 45.295109 | N38: 45.54966 | O38: 45.800465 | P38: 46.072914 | Q38: 46.308186 | R38: 46.454895 | S38: 46.573441 | T38: 46.763412 | U38: 46.743324 | V38: 46.781216 | W38: 46.812752 | X38: 46.781078 | Y38: 46.720787 | Z38: 46.649311 | AA38: 46.812588 | AB38: 46.721981 | AC38: 46.686661 | AD38: 46.844208 | AE38: 46.809135 | AF38: 0.007835
A39: TKI000:ca_TestedNewCar | B39: New Car 4/ | C39: 49.658657 | D39: 50.63982 | E39: 51.418789 | F39: 54.041267 | G39: 54.808311 | H39: 55.812794 | I39: 58.414131 | J39: 59.295654 | K39: 59.885937 | L39: 60.128426 | M39: 60.482559 | N39: 60.696911 | O39: 60.896141 | P39: 61.139969 | Q39: 61.34211 | R39: 61.456459 | S39: 61.54549 | T39: 61.791069 | U39: 61.720493 | V39: 61.820892 | W39: 61.909645 | X39: 61.923454 | Y39: 61.848679 | Z39: 61.762375 | AA39: 62.120819 | AB39: 61.989952 | AC39: 61.932671 | AD39: 62.331699 | AE39: 62.272804 | AF39: 0.008117
A40: TKI000:ca_TestedNewTwuk | B40: New Light Truck 4/ | C40: 32.951321 | D40: 33.82571 | E40: 34.570251 | F40: 36.235542 | G40: 37.203815 | H40: 37.859802 | I40: 39.251301 | J40: 39.65464 | K40: 39.942871 | L40: 40.123779 | M40: 40.372108 | N40: 40.635685 | O40: 40.898228 | P40: 41.187042 | Q40: 41.415565 | R40: 41.589336 | S40: 41.735809 | T40: 41.930031 | U40: 41.954327 | V40: 42.014381 | W40: 42.070942 | X40: 42.089371 | Y40: 42.062252 | Z40: 42.034523 | AA40: 42.106945 | AB40: 42.074627 | AC40: 42.053329 | AD40: 42.192116 | AE40: 42.17543 | AF40: 0.008853
A41: TKI000:ca_OnRoadNewVeh | B41: On-Road New Light-Duty Vehicle 5/ | C41: 30.687853 | D41: 31.308468 | E41: 31.873775 | F41: 33.275242 | G41: 34.001518 | H41: 34.574638 | I41: 35.883228 | J41: 36.28281 | K41: 36.56535 | L41: 36.715401 | M41: 36.945652 | N41: 37.153278 | O41: 37.357868 | P41: 37.580082 | Q41: 37.772026 | R41: 37.891651 | S41: 37.988308 | T41: 38.143211 | U41: 38.126759 | V41: 38.157574 | W41: 38.183201 | X41: 38.157219 | Y41: 38.107975 | Z41: 38.049587 | AA41: 38.182838 | AB41: 38.108822 | AC41: 38.080002 | AD41: 38.208389 | AE41: 38.179749 | AF41: 0.007832
A42: TKI000:ca_OnRoadNewCar | B42: New Car 5/ | C42: 40.552002 | D42: 41.353237 | E42: 41.989353 | F42: 44.130909 | G42: 44.75729 | H42: 45.577564 | I42: 47.701855 | J42: 48.421719 | K42: 48.903755 | L42: 49.101772 | M42: 49.390965 | N42: 49.566006 | O42: 49.728703 | P42: 49.927814 | Q42: 50.092888 | R42: 50.186264 | S42: 50.258968 | T42: 50.459515 | U42: 50.401878 | V42: 50.483868 | W42: 50.556343 | X42: 50.567619 | Y42: 50.506557 | Z42: 50.436081 | AA42: 50.72879 | AB42: 50.621925 | AC42: 50.575146 | AD42: 50.901001 | AE42: 50.852905 | AF42: 0.008117
A43: TKI000:ca_OnRoadNewTwuk | B43: New Light Truck 5/ | C43: 26.867123 | D43: 27.580063 | E43: 28.18713 | F43: 29.544939 | G43: 30.334429 | H43: 30.869291 | I43: 32.00386 | J43: 32.332729 | K43: 32.567738 | L43: 32.715244 | M43: 32.917721 | N43: 33.132629 | O43: 33.346695 | P43: 33.582184 | Q43: 33.768513 | R43: 33.910198 | S43: 34.029625 | T43: 34.187984 | U43: 34.207794 | V43: 34.25676 | W43: 34.302879 | X43: 34.317905 | Y43: 34.295792 | Z43: 34.273186 | AA43: 34.332233 | AB43: 34.305882 | AC43: 34.288517 | AD43: 34.40168 | AE43: 34.388073 | AF43: 0.008853
... A47: TKI000:ca_FreightTruck | B47: Freight Truck | C47: 7.472406 | D47: 7.578529 | E47: 7.705323 | F47: 7.84859 | G47: 8.002383 | H47: 8.163677 | I47: 8.321285 | J47: 8.479755 | K47: 8.638294 | L47: 8.79593 | M47: 8.948549 | N47: 9.090997 | O47: 9.222516 | P47: 9.343068 | Q47: 9.453315 | R47: 9.553063 | S47: 9.643444 | T47: 9.72671 | U47: 9.804593 | V47: 9.877275 | W47: 9.942431 | X47: 10.001567 | Y47: 10.055841 | Z47: 10.108454 | AA47: 10.161228 | AB47: 10.213311 | AC47: 10.263764 | AD47: 10.314513 | AE47: 10.365861 | AF47: 0.011758
B48: (seat miles per gallon)
A49: TKI000:ca_Aircraft | B49: Aircraft | C49: 72.717087 | D49: 73.091972 | E49: 73.492531 | F49: 74.018456 | G49: 74.683121 | H49: 75.131767 | I49: 75.59214 | J49: 76.024017 | K49: 76.492363 | L49: 77.014214 | M49: 77.60096 | N49: 78.266678 | O49: 78.981506 | P49: 79.730591 | Q49: 80.48922 | R49: 81.260979 | S49: 82.048454 | T49: 82.814575 | U49: 83.594772 | V49: 84.382309 | W49: 85.171204 | X49: 85.974022 | Y49: 86.764038 | Z49: 87.549927 | AA49: 88.321091 | AB49: 89.091156 | AC49: 89.849762 | AD49: 90.593376 | AE49: 91.328148 | AF49: 0.008172
B50: (ton miles/thousand Btu)
A51: TKI000:ca_Rail | B51: Rail | C51: 3.36634 | D51: 3.369893 | E51: 3.37345 | F51: 3.37701 | G51: 3.380574 | H51: 3.384142 | I51: 3.387713 | J51: 3.391289 | K51: 3.394868 | L51: 3.398451 | M51: 3.402037 | N51: 3.405628 | O51: 3.409222 | P51: 3.41282 | Q51: 3.416422 | R51: 3.420027 | S51: 3.423637 | T51: 3.42725 | U51: 3.430867 | V51: 3.434488 | W51: 3.438113 | X51: 3.441741 | Y51: 3.445373 | Z51: 3.44901 | AA51: 3.452649 | AB51: 3.456293 | AC51: 3.459941 | AD51: 3.463593 | AE51: 3.467248 | AF51: 0.001055
A52: TKI000:ca_DomesticShipp | B52: Domestic Shipping | C52: 4.820226 | D52: 4.838966 | E52: 4.857779 | F52: 4.876665 | G52: 4.895624 | H52: 4.914657 | I52: 4.933764 | J52: 4.952945 | K52: 4.9722 | L52: 4.991531 | M52: 5.010937 | N52: 5.030418 | O52: 5.049975 | P52: 5.069608 | Q52: 5.089317 | R52: 5.109103 | S52: 5.128966 | T52: 5.148906 | U52: 5.168923 | V52: 5.189019 | W52: 5.209192 | X52: 5.229445 | Y52: 5.249775 | Z52: 5.270185 | AA52: 5.290674 | AB52: 5.311243 | AC52: 5.331892 | AD52: 5.352621 | AE52: 5.37343 | AF52: 0.003888
B54: Energy Use by Mode
B55: (quadrillion Btu)
A56: TKI000:da_Light-DutyVeh | B56: Light-Duty Vehicles | C56: 14.541973 | D56: 14.586114 | E56: 14.429692 | F56: 14.201925 | G56: 14.016909 | H56: 13.860763 | I56: 13.679087 | J56: 13.473832 | K56: 13.253083 | L56: 13.044086 | M56: 12.836978 | N56: 12.674039 | O56: 12.534656 | P56: 12.394664 | Q56: 12.251548 | R56: 12.130822 | S56: 12.028416 | T56: 11.933923 | U56: 11.864001 | V56: 11.805396 | W56: 11.762742 | X56: 11.733644 | Y56: 11.725387 | Z56: 11.735775 | AA56: 11.770763 | AB56: 11.824349 | AC56: 11.889715 | AD56: 11.96291 | AE56: 12.054455 | AF56: -0.006678
A57: TKI000:da_CommercialLig | B57: Commercial Light Trucks 1/ | C57: 0.951503 | D57: 0.942558 | E57: 0.92534 | F57: 0.912452 | G57: 0.903111 | H57: 0.894807 | I57: 0.888385 | J57: 0.882995 | K57: 0.877033 | L57: 0.872791 | M57: 0.871791 | N57: 0.871868 | O57: 0.873034 | P57: 0.875074 | Q57: 0.8775 | R57: 0.881023 | S57: 0.885541 | T57: 0.889796 | U57: 0.896146 | V57: 0.903924 | W57: 0.911921 | X57: 0.918675 | Y57: 0.924721 | Z57: 0.93183 | AA57: 0.93994 | AB57: 0.94995 | AC57: 0.95832 | AD57: 0.96721 | AE57: 0.978898 | AF57: 0.001014
A58: TKI000:da_BusTransporta | B58: Bus Transportation | C58: 0.212163 | D58: 0.222312 | E58: 0.226957 | F58: 0.228013 | G58: 0.228798 | H58: 0.229238 | I58: 0.229403 | J58: 0.229156 | K58: 0.228548 | L58: 0.227556 | M58: 0.22653 | N58: 0.226005 | O58: 0.225336 | P58: 0.224473 | Q58: 0.223496 | R58: 0.22194 | S58: 0.220576 | T58: 0.219099 | U58: 0.2175 | V58: 0.215784 | W58: 0.214032 | X58: 0.212017 | Y58: 0.210154 | Z58: 0.208215 | AA58: 0.206535 | AB58: 0.204463 | AC58: 0.20246 | AD58: 0.200282 | AE58: 0.198183 | AF58: -0.002432
A59: TKI000:da_FreightTrucks | B59: Freight Trucks | C59: 5.921126 | D59: 5.815005 | E59: 5.726179 | F59: 5.670887 | G59: 5.636415 | H59: 5.588956 | I59: 5.540693 | J59: 5.48039 | K59: 5.418849 | L59: 5.367491 | M59: 5.336062 | N59: 5.302126 | O59: 5.274123 | P59: 5.25631 | Q59: 5.237802 | R59: 5.232226 | S59: 5.230621 | T59: 5.23229 | U59: 5.241601 | V59: 5.256566 | W59: 5.274461 | X59: 5.292318 | Y59: 5.309026 | Z59: 5.323563 | AA59: 5.344643 | AB59: 5.367305 | AC59: 5.383854 | AD59: 5.403469 | AE59: 5.43954 | AF59: -0.003025
A60: TKI000:da_Rail,Passenge | B60: Rail, Passenger | C60: 0.043913 | D60: 0.045564 | E60: 0.046541 | F60: 0.047205 | G60: 0.0479 | H60: 0.048571 | I60: 0.049133 | J60: 0.049707 | K60: 0.05015 | L60: 0.050599 | M60: 0.05114 | N60: 0.051727 | O60: 0.052369 | P60: 0.052924 | Q60: 0.053457 | R60: 0.053973 | S60: 0.05451 | T60: 0.055034 | U60: 0.055627 | V60: 0.056181 | W60: 0.056754 | X60: 0.057258 | Y60: 0.057816 | Z60: 0.058367 | AA60: 0.059116 | AB60: 0.059751 | AC60: 0.060445 | AD60: 0.061081 | AE60: 0.061848 | AF60: 0.012306
A61: TKI000:da_Rail,Freight | B61: Rail, Freight | C61: 0.481382 | D61: 0.474822 | E61: 0.494129 | F61: 0.482204 | G61: 0.46188 | H61: 0.446095 | I61: 0.439745 | J61: 0.444526 | K61: 0.441892 | L61: 0.443423 | M61: 0.447437 | N61: 0.450648 | O61: 0.452666 | P61: 0.455515 | Q61: 0.455894 | R61: 0.456862 | S61: 0.458275 | T61: 0.457609 | U61: 0.458128 | V61: 0.461673 | W61: 0.464588 | X61: 0.464937 | Y61: 0.464923 | Z61: 0.464771 | AA61: 0.465767 | AB61: 0.468155 | AC61: 0.47134 | AD61: 0.472599 | AE61: 0.475729 | AF61: -0.000422
A62: TKI000:da_Shipping,Dome | B62: Shipping, Domestic | C62: 0.098239 | D62: 0.098921 | E62: 0.098115 | F62: 0.097346 | G62: 0.096686 | H62: 0.095823 | I62: 0.094965 | J62: 0.093891 | K62: 0.092919 | L62: 0.09203 | M62: 0.091401 | N62: 0.090674 | O62: 0.089934 | P62: 0.089169 | Q62: 0.088333 | R62: 0.087615 | S62: 0.086833 | T62: 0.086157 | U62: 0.085474 | V62: 0.084846 | W62: 0.084274 | X62: 0.083705 | Y62: 0.083103 | Z62: 0.082418 | AA62: 0.081856 | AB62: 0.081249 | AC62: 0.080573 | AD62: 0.07999 | AE62: 0.079593 | AF62: -0.007489
A63: TKI000:da_Shipping,Inte | B63: Shipping, International | C63: 0.935028 | D63: 0.88183 | E63: 0.877727 | F63: 0.878604 | G63: 0.87125 | H63: 0.868449 | I63: 0.862689 | J63: 0.859142 | K63: 0.856634 | L63: 0.857136 | M63: 0.857437 | N63: 0.858 | O63: 0.85776 | P63: 0.858218 | Q63: 0.857547 | R63: 0.857614 | S63: 0.857635 | T63: 0.85735 | U63: 0.857245 | V63: 0.857301 | W63: 0.85783 | X63: 0.85782 | Y63: 0.858048 | Z63: 0.858068 | AA63: 0.860633 | AB63: 0.860924 | AC63: 0.859834 | AD63: 0.859122 | AE63: 0.858095 | AF63: -0.003062
A64: TKI000:da_RecreationalB | B64: Recreational Boats | C64: 0.202837 | D64: 0.199163 | E64: 0.195805 | F64: 0.193737 | G64: 0.192813 | H64: 0.191897 | I64: 0.190734 | J64: 0.18921 | K64: 0.187404 | L64: 0.185677 | M64: 0.184467 | N64: 0.18361 | O64: 0.182778 | P64: 0.181998 | Q64: 0.18145 | R64: 0.181106 | S64: 0.180746 | T64: 0.180383 | U64: 0.180295 | V64: 0.180161 | W64: 0.179988 | X64: 0.179814 | Y64: 0.179557 | Z64: 0.179244 | AA64: 0.17895 | AB64: 0.178728 | AC64: 0.178491 | AD64: 0.178228 | AE64: 0.178156 | AF64: -0.004623
A65: TKI000:da_Air | B65: Air | C65: 2.802808 | D65: 3.008168 | E65: 3.051203 | F65: 3.057111 | G65: 3.095898 | H65: 3.134227 | I65: 3.164552 | J65: 3.187108 | K65: 3.202938 | L65: 3.218783 | M65: 3.243937 | N65: 3.270448 | O65: 3.294403 | P65: 3.322924 | Q65: 3.359825 | R65: 3.403895 | S65: 3.450172 | T65: 3.498488 | U65: 3.554644 | V65: 3.608403 | W65: 3.663098 | X65: 3.718625 | Y65: 3.77401 | Z65: 3.827919 | AA65: 3.880434 | AB65: 3.936738 | AC65: 3.993604 | AD65: 4.049651 | AE65: 4.112158 | AF65: 0.013784
A66: TKI000:da_MilitaryUse | B66: Military Use | C66: 0.430832 | D66: 0.433131 | E66: 0.433968 | F66: 0.434628 | G66: 0.435162 | H66: 0.435947 | I66: 0.436506 | J66: 0.436951 | K66: 0.437332 | L66: 0.437576 | M66: 0.437744 | N66: 0.437827 | O66: 0.437858 | P66: 0.437879 | Q66: 0.438004 | R66: 0.438203 | S66: 0.438412 | T66: 0.438631 | U66: 0.438858 | V66: 0.439093 | W66: 0.439335 | X66: 0.439584 | Y66: 0.439839 | Z66: 0.440099 | AA66: 0.440364 | AB66: 0.440633 | AC66: 0.440907 | AD66: 0.441184 | AE66: 0.441465 | AF66: 0.000871
A67: TKI000:da_Lubricants | B67: Lubricants | C67: 0.125945 | D67: 0.125925 | E67: 0.126012 | F67: 0.12605 | G67: 0.126114 | H67: 0.125984 | I67: 0.125853 | J67: 0.125755 | K67: 0.125652 | L67: 0.125546 | M67: 0.125439 | N67: 0.12533 | O67: 0.12525 | P67: 0.125225 | Q67: 0.125255 | R67: 0.125318 | S67: 0.125412 | T67: 0.125527 | U67: 0.125667 | V67: 0.125797 | W67: 0.125925 | X67: 0.126046 | Y67: 0.126166 | Z67: 0.12632 | AA67: 0.126492 | AB67: 0.126661 | AC67: 0.126811 | AD67: 0.126974 | AE67: 0.127159 | AF67: 0.000342
... A70: TKI000:da_Total | B70: Total | C70: 27.986006 | D70: 28.032028 | E70: 27.776655 | F70: 27.4657 | G70: 27.255045 | H70: 27.051918 | I70: 26.819283 | J70: 26.59227 | K70: 26.360722 | L70: 26.162958 | M70: 26.008129 | N70: 25.897749 | O70: 25.802094 | P70: 25.704212 | Q70: 25.598515 | R70: 25.533525 | S70: 25.493338 | T70: 25.449312 | U70: 25.46059 | V70: 25.485914 | W70: 25.531475 | X70: 25.583796 | Y70: 25.657438 | Z70: 25.744152 | AA70: 25.868387 | AB70: 26.019403 | AC70: 26.175444 | AD70: 26.332941 | AE70: 26.540415 | AF70: -0.001892
B72: (million barrels per day oil equivalent)
A73: TKI000:ea_Light-DutyVeh | B73: Light-Duty Vehicles | C73: 7.887402 | D73: 7.912227 | E73: 7.827434 | F73: 7.704175 | G73: 7.603646 | H73: 7.518498 | I73: 7.419035 | J73: 7.306525 | K73: 7.185357 | L73: 7.070691 | M73: 6.957016 | N73: 6.86728 | O73: 6.790267 | P73: 6.712955 | Q73: 6.633772 | R73: 6.566808 | S73: 6.509881 | T73: 6.457382 | U73: 6.418384 | V73: 6.385576 | W73: 6.361585 | X73: 6.345073 | Y73: 6.340106 | Z73: 6.345462 | AA73: 6.36419 | AB73: 6.393152 | AC73: 6.428598 | AD73: 6.468379 | AE73: 6.518199 | AF73: -0.006786
A74: TKI000:ea_CommercialLig | B74: Commercial Light Trucks 1/ | C74: 0.496809 | D74: 0.492193 | E74: 0.483314 | F74: 0.476842 | G74: 0.472221 | H74: 0.467932 | I74: 0.464712 | J74: 0.462053 | K74: 0.459111 | L74: 0.457084 | M74: 0.456754 | N74: 0.456989 | O74: 0.457814 | P74: 0.459091 | Q74: 0.460564 | R74: 0.462619 | S74: 0.465189 | T74: 0.467623 | U74: 0.471176 | V74: 0.475436 | W74: 0.479853 | X74: 0.483793 | Y74: 0.487354 | Z74: 0.491353 | AA74: 0.496003 | AB74: 0.501565 | AC74: 0.506491 | AD74: 0.511462 | AE74: 0.517981 | AF74: 0.001492
A75: TKI000:ea_BusTransporta | B75: Bus Transportation | C75: 0.105213 | D75: 0.110296 | E75: 0.11259 | F75: 0.113083 | G75: 0.113492 | H75: 0.113737 | I75: 0.113843 | J75: 0.113729 | K75: 0.113434 | L75: 0.112917 | M75: 0.112403 | N75: 0.112129 | O75: 0.111806 | P75: 0.111381 | Q75: 0.110915 | R75: 0.110151 | S75: 0.109477 | T75: 0.108762 | U75: 0.107969 | V75: 0.107129 | W75: 0.106288 | X75: 0.105307 | Y75: 0.104391 | Z75: 0.103434 | AA75: 0.102605 | AB75: 0.101578 | AC75: 0.100586 | AD75: 0.099507 | AE75: 0.09846 | AF75: -0.002366
A76: TKI000:ea_FreightTrucks | B76: Freight Trucks | C76: 2.850965 | D76: 2.800434 | E76: 2.758164 | F76: 2.732194 | G76: 2.716136 | H76: 2.693672 | I76: 2.671257 | J76: 2.642962 | K76: 2.614177 | L76: 2.590174 | M76: 2.575932 | N76: 2.560368 | O76: 2.547745 | P76: 2.539845 | Q76: 2.531643 | R76: 2.529634 | S76: 2.5295 | T76: 2.530971 | U76: 2.536117 | V76: 2.544034 | W76: 2.553331 | X76: 2.562598 | Y76: 2.571348 | Z76: 2.579022 | AA76: 2.589984 | AB76: 2.601707 | AC76: 2.610389 | AD76: 2.620612 | AE76: 2.638885 | AF76: -0.002757
A77: TKI000:ea_Rail,Passenge | B77: Rail, Passenger | C77: 0.020781 | D77: 0.021563 | E77: 0.022025 | F77: 0.02234 | G77: 0.022668 | H77: 0.022984 | I77: 0.023251 | J77: 0.023523 | K77: 0.023733 | L77: 0.023945 | M77: 0.024201 | N77: 0.024479 | O77: 0.024783 | P77: 0.025045 | Q77: 0.025298 | R77: 0.025542 | S77: 0.025796 | T77: 0.026044 | U77: 0.026325 | V77: 0.026587 | W77: 0.026858 | X77: 0.027097 | Y77: 0.027361 | Z77: 0.027622 | AA77: 0.027977 | AB77: 0.028278 | AC77: 0.028605 | AD77: 0.028906 | AE77: 0.02927 | AF77: 0.012308
A78: TKI000:ea_Rail,Freight | B78: Rail, Freight | C78: 0.228347 | D78: 0.225234 | E78: 0.234373 | F78: 0.228717 | G78: 0.21906 | H78: 0.211545 | I78: 0.208541 | J78: 0.210806 | K78: 0.209559 | L78: 0.210276 | M78: 0.212178 | N78: 0.213692 | O78: 0.21465 | P78: 0.215989 | Q78: 0.216165 | R78: 0.216616 | S78: 0.21728 | T78: 0.216956 | U78: 0.217194 | V78: 0.218865 | W78: 0.220234 | X78: 0.220387 | Y78: 0.22037 | Z78: 0.220283 | AA78: 0.220747 | AB78: 0.221866 | AC78: 0.223355 | AD78: 0.223935 | AE78: 0.225407 | AF78: -0.000463
A79: TKI000:ea_Shipping,Dome | B79: Shipping, Domestic | C79: 0.046527 | D79: 0.046853 | E79: 0.04647 | F79: 0.04611 | G79: 0.045796 | H79: 0.045385 | I79: 0.044983 | J79: 0.044476 | K79: 0.04402 | L79: 0.0436 | M79: 0.043306 | N79: 0.042963 | O79: 0.042617 | P79: 0.042256 | Q79: 0.041863 | R79: 0.041525 | S79: 0.041158 | T79: 0.04084 | U79: 0.040519 | V79: 0.040222 | W79: 0.03995 | X79: 0.039681 | Y79: 0.039395 | Z79: 0.03907 | AA79: 0.038805 | AB79: 0.038517 | AC79: 0.038196 | AD79: 0.037919 | AE79: 0.037732 | AF79: -0.007455
A80: TKI000:ea_Shipping,Inte | B80: Shipping, International | C80: 0.417032 | D80: 0.39771 | E80: 0.396229 | F80: 0.396613 | G80: 0.393975 | H80: 0.392997 | I80: 0.390956 | J80: 0.389709 | K80: 0.388847 | L80: 0.389075 | M80: 0.389247 | N80: 0.389507 | O80: 0.389481 | P80: 0.389698 | Q80: 0.389505 | R80: 0.389575 | S80: 0.389634 | T80: 0.389581 | U80: 0.389597 | V80: 0.38967 | W80: 0.389917 | X80: 0.389969 | Y80: 0.390113 | Z80: 0.390178 | AA80: 0.391183 | AB80: 0.391349 | AC80: 0.391006 | AD80: 0.3908 | AE80: 0.390489 | AF80: -0.002346
A81: TKI000:ea_RecreationalB | B81: Recreational Boats | C81: 0.110006 | D81: 0.108038 | E81: 0.106242 | F81: 0.105144 | G81: 0.104667 | H81: 0.104195 | I81: 0.103587 | J81: 0.102784 | K81: 0.101827 | L81: 0.100913 | M81: 0.100279 | N81: 0.099838 | O81: 0.099409 | P81: 0.099009 | Q81: 0.098731 | R81: 0.098564 | S81: 0.098387 | T81: 0.098209 | U81: 0.098181 | V81: 0.098125 | W81: 0.098049 | X81: 0.097971 | Y81: 0.097849 | Z81: 0.097695 | AA81: 0.097552 | AB81: 0.097448 | AC81: 0.097337 | AD81: 0.097211 | AE81: 0.097188 | AF81: -0.004415
A82: TKI000:ea_Air | B82: Air | C82: 1.355634 | D82: 1.454865 | E82: 1.475662 | F82: 1.478519 | G82: 1.497263 | H82: 1.515786 | I82: 1.530442 | J82: 1.541344 | K82: 1.548995 | L82: 1.556654 | M82: 1.568811 | N82: 1.581624 | O82: 1.593202 | P82: 1.606986 | Q82: 1.624819 | R82: 1.646116 | S82: 1.668479 | T82: 1.691828 | U82: 1.718965 | V82: 1.744943 | W82: 1.771373 | X82: 1.798206 | Y82: 1.82497 | Z82: 1.851021 | AA82: 1.876398 | AB82: 1.903606 | AC82: 1.931086 | AD82: 1.95817 | AE82: 1.988375 | AF82: 0.013774
A83: TKI000:ea_MilitaryUse | B83: Military Use | C83: 0.207325 | D83: 0.208431 | E83: 0.20883 | F83: 0.209148 | G83: 0.209402 | H83: 0.209774 | I83: 0.210045 | J83: 0.210259 | K83: 0.210443 | L83: 0.21056 | M83: 0.210641 | N83: 0.21068 | O83: 0.210697 | P83: 0.210706 | Q83: 0.210766 | R83: 0.210862 | S83: 0.210964 | T83: 0.211069 | U83: 0.211179 | V83: 0.211292 | W83: 0.211409 | X83: 0.211529 | Y83: 0.211652 | Z83: 0.211777 | AA83: 0.211906 | AB83: 0.212036 | AC83: 0.212167 | AD83: 0.2123 | AE83: 0.212437 | AF83: 0.00087
A84: TKI000:ea_Lubricants | B84: Lubricants | C84: 0.059492 | D84: 0.059483 | E84: 0.059524 | F84: 0.059542 | G84: 0.059572 | H84: 0.059511 | I84: 0.059449 | J84: 0.059403 | K84: 0.059354 | L84: 0.059304 | M84: 0.059253 | N84: 0.059202 | O84: 0.059164 | P84: 0.059152 | Q84: 0.059166 | R84: 0.059196 | S84: 0.05924 | T84: 0.059295 | U84: 0.059361 | V84: 0.059422 | W84: 0.059483 | X84: 0.05954 | Y84: 0.059597 | Z84: 0.059669 | AA84: 0.059751 | AB84: 0.05983 | AC84: 0.059901 | AD84: 0.059978 | AE84: 0.060066 | AF84: 0.000342
... A87: TKI000:ea_Total | B87: Total | C87: 14.370443 | D87: 14.403465 | E87: 14.271711 | F87: 14.108815 | G87: 13.997396 | H87: 13.890337 | I87: 13.767988 | J87: 13.645885 | K87: 13.520164 | L87: 13.411051 | M87: 13.323045 | N87: 13.25902 | O87: 13.203858 | P87: 13.147519 | Q87: 13.087383 | R87: 13.048246 | S87: 13.022289 | T87: 12.995312 | U87: 12.996621 | V87: 13.0055 | W87: 13.025239 | X87: 13.049395 | Y87: 13.085273 | Z87: 13.128707 | AA87: 13.19174 | AB87: 13.269163 | AC87: 13.350009 | AD87: 13.432016 | AE87: 13.539635 | AF87: -0.002125
B89: 1/ Commercial trucks have a 8,501 to 10,000 pound gross vehicle weight rating.
B90: 2/ CAFE standard based on projected new vehicle sales.
B91: 3/ Includes CAFE credits for alternative fueled vehicle sales and credit banking.
B92: 4/ U.S. Environmental Protection Agency rated miles per gallon.
B93: 5/ Tested new vehicle efficiency revised for on-road performance.
B94: 6/ Combined "on-the-road" estimate for all cars and light trucks.
B95: 7/ Fuel used in facilities that liquefy natural gas for export.
B96: CAFE = Corporate average fuel economy.
B97: Btu = British thermal unit.
B98: Note: Totals may not equal sum of components due to independent rounding.
B99: Data source: 2022: U.S. Energy Information Administration (EIA), Short-Term Energy Outlook, November 2022 and EIA, AEO2023
B100: AEO2023 National Energy Modeling System run ref2023.d020623a. Projections: EIA, AEO2023 National Energy Modeling System run ref2023.d020623a.

Sheet AEO 2022 Table 7
B1: highogs.d120120a | C1: 2021 | D1: 2022 | E1: 2023 | F1: 2024 | G1: 2025 | H1: 2026 | I1: 2027 | J1: 2028 | K1: 2029 | L1: 2030 | M1: 2031 | N1: 2032 | O1: 2033 | P1: 2034 | Q1: 2035 | R1: 2036 | S1: 2037 | T1: 2038 | U1: 2039 | V1: 2040 | W1: 2041 | X1: 2042 | Y1: 2043 | Z1: 2044 | AA1: 2045 | AB1: 2046 | AC1: 2047 | AD1: 2048 | AE1: 2049 | AF1: 2050
C3: Annual Energy Outlook 2021
C4: ref2021 | F4: Reference case
C5: d113020a
D6: January 2021
A10: TKI000 | B10: 7. Transportation Sector Key Indicators and Delivered Energy Consumption | AG10: Compound
AG11: Growth
AG12: 2020-2050
B13: Key Indicators and Consumption | C13: 2021 | D13: 2022 | E13: 2023 | F13: 2024 | G13: 2025 | H13: 2026 | I13: 2027 | J13: 2028 | K13: 2029 | L13: 2030 | M13: 2031 | N13: 2032 | O13: 2033 | P13: 2034 | Q13: 2035 | R13: 2036 | S13: 2037 | T13: 2038 | U13: 2039 | V13: 2040 | W13: 2041 | X13: 2042 | Y13: 2043 | Z13: 2044 | AA13: 2045 | AB13: 2046 | AC13: 2047 | AD13: 2048 | AE13: 2049 | AF13: 2050 | AG13: (percent)
B15: Key Indicators
B16: Travel Indicators
B17: (billion vehicle miles traveled)
A18: TKI000:ba_Light-DutyVeh | B18: Light-Duty Vehicles less than 8,501 pounds | C18: 2761.1487 | D18: 2887.3313 | E18: 2986.1375 | F18: 3033.4624 | G18: 3075.9688 | H18: 3112.4636 | I18: 3140.5366 | J18: 3162.593 | K18: 3183.811 | L18: 3206.8018 | M18: 3229.7073 | N18: 3247.4204 | O18: 3266.4207 | P18: 3283.7412 | Q18: 3299.2346 | R18: 3314.6108 | S18: 3331.2617 | T18: 3348.0293 | U18: 3367.125 | V18: 3386.949 | W18: 3405.9556 | X18: 3425.8684 | Y18: 3445.7124 | Z18: 3465.4507 | AA18: 3486.7061 | AB18: 3510.4651 | AC18: 3534.4812 | AD18: 3558.8704 | AE18: 3584.9614 | AF18: 3613.5239 | AG18: 0.009
A19: TKI000:ba_CommercialLig | B19: Commercial Light Trucks 1/ | C19: 100.76003 | D19: 104.34176 | E19: 106.70262 | F19: 108.00214 | G19: 109.34573 | H19: 110.56496 | I19: 111.42751 | J19: 112.36408 | K19: 113.47929 | L19: 114.62598 | M19: 115.78786 | N19: 117.00378 | O19: 118.26071 | P19: 119.48289 | Q19: 120.7066 | R19: 121.99136 | S19: 123.41512 | T19: 124.85188 | U19: 126.28014 | V19: 127.69122 | W19: 129.20485 | X19: 130.79395 | Y19: 132.42688 | Z19: 134.00609 | AA19: 135.59607 | AB19: 137.31485 | AC19: 138.90479 | AD19: 140.36012 | AE19: 142.02193 | AF19: 144.02313 | AG19: 0.012
A20: TKI000:ba_FreightTrucks | B20: Freight Trucks greater than 10,000 pounds | C20: 296.81839 | D20: 304.25449 | E20: 308.97504 | F20: 312.70242 | G20: 316.88568 | H20: 320.48059 | I20: 323.30453 | J20: 326.69177 | K20: 330.38946 | L20: 333.86133 | M20: 337.28406 | N20: 340.79715 | O20: 344.26349 | P20: 347.5257 | Q20: 350.95914 | R20: 354.45807 | S20: 358.38226 | T20: 362.35556 | U20: 366.2616 | V20: 370.20163 | W20: 374.51642 | X20: 379.08896 | Y20: 383.45093 | Z20: 387.78918 | AA20: 392.14526 | AB20: 396.80841 | AC20: 400.81616 | AD20: 404.24228 | AE20: 408.71432 | AF20: 414.21069 | AG20: 0.012
B21: (billion passenger miles traveled)
A22: TKI000:buspassmiles | B22: Bus Transportation | C22: 151.30966 | D22: 173.16789 | E22: 184.76592 | F22: 191.65541 | G22: 196.21399 | H22: 199.3981 | I22: 201.69253 | J22: 203.40639 | K22: 204.7121 | L22: 205.76692 | M22: 206.62942 | N22: 207.27484 | O22: 207.8185 | P22: 208.29555 | Q22: 208.67419 | R22: 209.06363 | S22: 209.5192 | T22: 209.89679 | U22: 210.00269 | V22: 210.10393 | W22: 210.12295 | X22: 210.09636 | Y22: 210.06598 | Z22: 210.01566 | AA22: 209.94398 | AB22: 209.88408 | AC22: 209.77901 | AD22: 209.63933 | AE22: 209.48929 | AF22: 209.347 | AG22: 0.011
A23: TKI000:railpassmiles | B23: Passenger Rail | C23: 29.706352 | D23: 33.420921 | E23: 35.774769 | F23: 37.825356 | G23: 39.433685 | H23: 40.788967 | I23: 41.767357 | J23: 42.560257 | K23: 43.304031 | L23: 44.145664 | M23: 44.963547 | N23: 45.652962 | O23: 46.319397 | P23: 46.919537 | Q23: 47.423344 | R23: 47.944431 | S23: 48.515842 | T23: 49.068516 | U23: 49.548981 | V23: 50.127491 | W23: 50.601322 | X23: 51.080406 | Y23: 51.618813 | Z23: 52.163063 | AA23: 52.755924 | AB23: 53.42416 | AC23: 53.984158 | AD23: 54.50843 | AE23: 55.108772 | AF23: 55.777504 | AG23: 0.022
B24: (billion seat miles available)
A25: TKI000:ba_Air | B25: Air | C25: 884.81805 | D25: 1076.55 | E25: 1230.1667 | F25: 1281.0972 | G25: 1332.4701 | H25: 1370.9828 | I25: 1398.9177 | J25: 1427.2495 | K25: 1459.7749 | L25: 1496.7294 | M25: 1531.1088 | N25: 1567.3237 | O25: 1606.1002 | P25: 1644.3704 | Q25: 1681.6504 | R25: 1717.8458 | S25: 1756.6516 | T25: 1794.5098 | U25: 1835.0491 | V25: 1878.3563 | W25: 1916.7485 | X25: 1957.8833 | Y25: 2001.3043 | Z25: 2045.0242 | AA25: 2092.8052 | AB25: 2142.4402 | AC25: 2188.459 | AD25: 2235.0183 | AE25: 2287.7986 | AF25: 2344.385 | AG25: 0.034
B26: (billion ton miles traveled)
A27: TKI000:ba_Rail | B27: Rail | C27: 1644.4915 | D27: 1665.1613 | E27: 1687.2128 | F27: 1584.5679 | G27: 1618.0447 | H27: 1660.0645 | I27: 1667.3862 | J27: 1673.5901 | K27: 1678.8776 | L27: 1688.5286 | M27: 1699.8828 | N27: 1711.3606 | O27: 1724.6821 | P27: 1718.1174 | Q27: 1722.3843 | R27: 1715.6056 | S27: 1728.4023 | T27: 1737.8145 | U27: 1747.3446 | V27: 1754.1726 | W27: 1763.5247 | X27: 1775.6241 | Y27: 1781.4792 | Z27: 1785.2306 | AA27: 1792.4877 | AB27: 1803.1855 | AC27: 1810.229 | AD27: 1819.6707 | AE27: 1831.4158 | AF27: 1852.35 | AG27: 0.004
A28: TKI000:ba_DomesticShipp | B28: Domestic Shipping | C28: 340.48685 | D28: 355.078 | E28: 354.80612 | F28: 347.34994 | G28: 340.59833 | H28: 332.84692 | I28: 323.82996 | J28: 315.29077 | K28: 306.4082 | L28: 297.53073 | M28: 293.53958 | N28: 289.49127 | O28: 285.82245 | P28: 281.63907 | Q28: 277.23456 | R28: 273.04852 | S28: 269.29669 | T28: 265.319 | U28: 261.74301 | V28: 258.02158 | W28: 257.14194 | X28: 256.13333 | Y28: 254.95567 | Z28: 253.95633 | AA28: 252.95215 | AB28: 252.08273 | AC28: 250.62955 | AD28: 248.75684 | AE28: 247.7997 | AF28: 247.80908 | AG28: -0.011
B30: Energy Efficiency Indicators
B31: (miles per gallon)
A32: TKI000:ca_AvgCAFEStand | B32: New Light-Duty Vehicle CAFE Standard 2/ | C32: 35.285992 | D32: 35.48703 | E32: 35.771912 | F32: 36.135601 | G32: 36.515312 | H32: 37.058449 | I32: 37.01659 | J32: 36.995026 | K32: 36.98127 | L32: 36.99622 | M32: 37.031643 | N32: 37.041542 | O32: 37.047226 | P32: 37.049618 | Q32: 37.040478 | R32: 37.033859 | S32: 37.025627 | T32: 37.023102 | U32: 37.003475 | V32: 36.994915 | W32: 36.983158 | X32: 36.964703 | Y32: 36.957966 | Z32: 36.952953 | AA32: 36.939468 | AB32: 36.932568 | AC32: 36.915142 | AD32: 36.891186 | AE32: 36.867813 | AF32: 36.844318 | AG32: 0.001
A33: TKI000:ca_CarCAFEStand | B33: New Car 2/ | C33: 44.288506 | D33: 44.826138 | E33: 45.45166 | F33: 46.205555 | G33: 46.881027 | H33: 47.673538 | I33: 47.678375 | J33: 47.68045 | K33: 47.684368 | L33: 47.699383 | M33: 47.710827 | N33: 47.710827 | O33: 47.710827 | P33: 47.710827 | Q33: 47.710827 | R33: 47.710827 | S33: 47.711578 | T33: 47.714207 | U33: 47.714207 | V33: 47.715466 | W33: 47.715603 | X33: 47.715603 | Y33: 47.71888 | Z33: 47.719818 | AA33: 47.719818 | AB33: 47.721157 | AC33: 47.721157 | AD33: 47.721157 | AE33: 47.721157 | AF33: 47.721333 | AG33: 0.003
A34: TKI000:ca_TwukCAFEStand | B34: New Light Truck 2/ | C34: 31.772453 | D34: 32.124016 | E34: 32.563663 | F34: 33.014378 | G34: 33.490173 | H34: 34.05373 | I34: 34.053749 | J34: 34.053802 | K34: 34.053837 | L34: 34.053837 | M34: 34.053837 | N34: 34.053913 | O34: 34.053944 | P34: 34.053978 | Q34: 34.054016 | R34: 34.054024 | S34: 34.054043 | T34: 34.054043 | U34: 34.054092 | V34: 34.054092 | W34: 34.054096 | X34: 34.054131 | Y34: 34.054131 | Z34: 34.054131 | AA34: 34.054165 | AB34: 34.054165 | AC34: 34.054195 | AD34: 34.054214 | AE34: 34.054226 | AF34: 34.054241 | AG34: 0.002
A35: TKI000:ca_NewVehCred | B35: Compliance New Light-Duty Vehicle 3/ | C35: 36.320473 | D35: 37.31142 | E35: 37.662174 | F35: 38.010811 | G35: 38.094296 | H35: 38.247921 | I35: 38.293079 | J35: 38.352066 | K35: 38.418518 | L35: 38.54631 | M35: 38.726295 | N35: 38.866302 | O35: 38.983082 | P35: 39.093426 | Q35: 39.1922 | R35: 39.302681 | S35: 39.416943 | T35: 39.533672 | U35: 39.591755 | V35: 39.675838 | W35: 39.750217 | X35: 39.796734 | Y35: 39.879173 | Z35: 39.96608 | AA35: 40.016975 | AB35: 40.087498 | AC35: 40.122173 | AD35: 40.129021 | AE35: 40.139771 | AF35: 40.152401 | AG35: 0.003
A36: TKI000:ca_NewCarCred | B36: New Car 3/ | C36: 45.475075 | D36: 46.463356 | E36: 46.871098 | F36: 47.613346 | G36: 48.15469 | H36: 48.952316 | I36: 49.009914 | J36: 48.983555 | K36: 49.005871 | L36: 49.1185 | M36: 49.276249 | N36: 49.423874 | O36: 49.562927 | P36: 49.715073 | Q36: 49.873493 | R36: 50.02845 | S36: 50.20089 | T36: 50.381207 | U36: 50.512337 | V36: 50.639797 | W36: 50.785503 | X36: 50.896545 | Y36: 51.036186 | Z36: 51.184166 | AA36: 51.303078 | AB36: 51.434132 | AC36: 51.549774 | AD36: 51.631973 | AE36: 51.718174 | AF36: 51.811989 | AG36: 0.005
A37: TKI000:ca_NewTwukCred | B37: New Light Truck 3/ | C37: 32.735344 | D37: 33.951099 | E37: 34.524212 | F37: 34.952869 | G37: 35.098633 | H37: 35.197926 | I37: 35.290627 | J37: 35.391632 | K37: 35.482613 | L37: 35.596081 | M37: 35.737183 | N37: 35.860985 | O37: 35.963947 | P37: 36.060459 | Q37: 36.155796 | R37: 36.262741 | S37: 36.372746 | T37: 36.4776 | U37: 36.543522 | V37: 36.62775 | W37: 36.700649 | X37: 36.755989 | Y37: 36.834328 | Z37: 36.913742 | AA37: 36.966965 | AB37: 37.033054 | AC37: 37.073078 | AD37: 37.095291 | AE37: 37.1208 | AF37: 37.147499 | AG37: 0.004
A38: TKI000:ca_TestedNewVeh | B38: Tested New Light-Duty Vehicle 4/ | C38: 36.097652 | D38: 36.890865 | E38: 37.16309 | F38: 37.471909 | G38: 37.548306 | H38: 37.693558 | I38: 37.730827 | J38: 37.779949 | K38: 37.82983 | L38: 37.92981 | M38: 38.074917 | N38: 38.1805 | O38: 38.265446 | P38: 38.343956 | Q38: 38.411659 | R38: 38.491077 | S38: 38.574333 | T38: 38.658054 | U38: 38.691067 | V38: 38.74736 | W38: 38.795506 | X38: 38.81963 | Y38: 38.873913 | Z38: 38.931656 | AA38: 38.959419 | AB38: 39.003712 | AC38: 39.018578 | AD38: 39.010792 | AE38: 39.006245 | AF38: 39.002537 | AG38: 0.003
A39: TKI000:ca_TestedNewCar | B39: New Car 4/ | C39: 45.096481 | D39: 45.979137 | E39: 46.313679 | F39: 46.990833 | G39: 47.515671 | H39: 48.291649 | I39: 48.344982 | J39: 48.315689 | K39: 48.322018 | L39: 48.394592 | M39: 48.506691 | N39: 48.606041 | O39: 48.697697 | P39: 48.801441 | Q39: 48.908657 | R39: 49.014748 | S39: 49.136864 | T39: 49.263721 | U39: 49.347969 | V39: 49.429173 | W39: 49.526897 | X39: 49.593983 | Y39: 49.683327 | Z39: 49.77837 | AA39: 49.849922 | AB39: 49.930515 | AC39: 50.000229 | AD39: 50.043533 | AE39: 50.089653 | AF39: 50.139729 | AG39: 0.004
A40: TKI000:ca_TestedNewTwuk | B40: New Light Truck 4/ | C40: 32.562687 | D40: 33.557835 | E40: 34.050751 | F40: 34.445057 | G40: 34.584492 | H40: 34.677776 | I40: 34.761444 | J40: 34.851055 | K40: 34.925472 | L40: 35.014309 | M40: 35.12392 | N40: 35.217022 | O40: 35.292133 | P40: 35.36097 | Q40: 35.429878 | R40: 35.509933 | S40: 35.593349 | T40: 35.669994 | U40: 35.715256 | V40: 35.775749 | W40: 35.826942 | X40: 35.864029 | Y40: 35.918907 | Z40: 35.974251 | AA40: 36.00901 | AB40: 36.053822 | AC40: 36.07869 | AD40: 36.090065 | AE40: 36.104107 | AF40: 36.118683 | AG40: 0.004
A41: TKI000:ca_OnRoadNewVeh | B41: On-Road New Light-Duty Vehicle 5/ | C41: 29.44529 | D41: 30.091688 | E41: 30.313065 | F41: 30.564369 | G41: 30.626116 | H41: 30.744225 | I41: 30.774488 | J41: 30.814499 | K41: 30.85515 | L41: 30.93675 | M41: 31.055231 | N41: 31.141388 | O41: 31.210691 | P41: 31.274731 | Q41: 31.329922 | R41: 31.394674 | S41: 31.462549 | T41: 31.530819 | U41: 31.557674 | V41: 31.603556 | W41: 31.642776 | X41: 31.662386 | Y41: 31.706629 | Z41: 31.753708 | AA41: 31.776299 | AB41: 31.812397 | AC41: 31.824455 | AD41: 31.818008 | AE41: 31.814219 | AF41: 31.8111 | AG41: 0.003
A42: TKI000:ca_OnRoadNewCar | B42: New Car 5/ | C42: 36.82645 | D42: 37.547241 | E42: 37.820435 | F42: 38.373409 | G42: 38.801998 | H42: 39.435673 | I42: 39.479225 | J42: 39.455303 | K42: 39.460472 | L42: 39.519737 | M42: 39.611279 | N42: 39.69241 | O42: 39.767258 | P42: 39.851978 | Q42: 39.939529 | R42: 40.026165 | S42: 40.125889 | T42: 40.229481 | U42: 40.298279 | V42: 40.36459 | W42: 40.444393 | X42: 40.499176 | Y42: 40.572136 | Z42: 40.64975 | AA42: 40.708183 | AB42: 40.773994 | AC42: 40.830925 | AD42: 40.866287 | AE42: 40.90395 | AF42: 40.944843 | AG42: 0.004
A43: TKI000:ca_OnRoadNewTwuk | B43: New Light Truck 5/ | C43: 26.550249 | D43: 27.36165 | E43: 27.763554 | F43: 28.085054 | G43: 28.198744 | H43: 28.274803 | I43: 28.343023 | J43: 28.416088 | K43: 28.476765 | L43: 28.549198 | M43: 28.638571 | N43: 28.714481 | O43: 28.775724 | P43: 28.83185 | Q43: 28.888037 | R43: 28.95331 | S43: 29.021324 | T43: 29.083817 | U43: 29.120722 | V43: 29.170044 | W43: 29.211786 | X43: 29.242025 | Y43: 29.28677 | Z43: 29.331894 | AA43: 29.360237 | AB43: 29.396774 | AC43: 29.417049 | AD43: 29.426325 | AE43: 29.437775 | AF43: 29.449659 | AG43: 0.004
... A47: TKI000:ca_FreightTruck | B47: Freight Truck | C47: 7.331892 | D47: 7.410312 | E47: 7.497923 | F47: 7.5963 | G47: 7.70782 | H47: 7.832913 | I47: 7.97052 | J47: 8.109589 | K47: 8.254834 | L47: 8.403061 | M47: 8.551556 | N47: 8.69581 | O47: 8.830752 | P47: 8.955747 | Q47: 9.070722 | R47: 9.177202 | S47: 9.275028 | T47: 9.363853 | U47: 9.444804 | V47: 9.51915 | W47: 9.58819 | X47: 9.649012 | Y47: 9.704254 | Z47: 9.754515 | AA47: 9.801952 | AB47: 9.848245 | AC47: 9.894052 | AD47: 9.940031 | AE47: 9.985973 | AF47: 10.031261 | AG47: 0.011
B48: (seat miles per gallon)
A49: TKI000:ca_Aircraft | B49: Aircraft | C49: 73.643883 | D49: 74.164284 | E49: 74.683517 | F49: 75.120308 | G49: 75.583763 | H49: 75.871498 | I49: 76.308502 | J49: 76.801476 | K49: 77.308174 | L49: 77.856262 | M49: 78.434464 | N49: 79.126999 | O49: 79.792549 | P49: 80.511719 | Q49: 81.242912 | R49: 81.987068 | S49: 82.759789 | T49: 83.544899 | U49: 84.319893 | V49: 85.114548 | W49: 85.926819 | X49: 86.77433 | Y49: 87.609406 | Z49: 88.41713 | AA49: 89.23912 | AB49: 90.056198 | AC49: 90.860878 | AD49: 91.651962 | AE49: 92.4216 | AF49: 93.179382 | AG49: 0.008
B50: (ton miles/thousand Btu)
A51: TKI000:ca_Rail | B51: Rail | C51: 3.512003 | D51: 3.534782 | E51: 3.55771 | F51: 3.580785 | G51: 3.60401 | H51: 3.627386 | I51: 3.650914 | J51: 3.674594 | K51: 3.698428 | L51: 3.722416 | M51: 3.74656 | N51: 3.77086 | O51: 3.795318 | P51: 3.819935 | Q51: 3.844712 | R51: 3.869649 | S51: 3.894748 | T51: 3.920009 | U51: 3.945435 | V51: 3.971025 | W51: 3.996782 | X51: 4.022705 | Y51: 4.048797 | Z51: 4.075058 | AA51: 4.101489 | AB51: 4.128091 | AC51: 4.154866 | AD51: 4.181815 | AE51: 4.208939 | AF51: 4.236238 | AG51: 0.006
A52: TKI000:ca_DomesticShipp | B52: Domestic Shipping | C52: 4.870726 | D52: 4.899663 | E52: 4.928772 | F52: 4.958054 | G52: 4.987509 | H52: 5.01714 | I52: 5.046947 | J52: 5.076931 | K52: 5.107092 | L52: 5.137434 | M52: 5.167955 | N52: 5.198658 | O52: 5.229543 | P52: 5.260611 | Q52: 5.291864 | R52: 5.323303 | S52: 5.354929 | T52: 5.386742 | U52: 5.418745 | V52: 5.450938 | W52: 5.483322 | X52: 5.515898 | Y52: 5.548667 | Z52: 5.581632 | AA52: 5.614792 | AB52: 5.64815 | AC52: 5.681705 | AD52: 5.71546 | AE52: 5.749416 | AF52: 5.783573 | AG52: 0.006
B54: Energy Use by Mode
B55: (quadrillion Btu)
A56: TKI000:da_Light-DutyVeh | B56: Light-Duty Vehicles | C56: 14.274495 | D56: 14.663075 | E56: 14.907382 | F56: 14.888803 | G56: 14.849199 | H56: 14.786862 | I56: 14.699437 | J56: 14.596199 | K56: 14.504814 | L56: 14.439389 | M56: 14.388906 | N56: 14.328156 | O56: 14.293911 | P56: 14.263883 | Q56: 14.229496 | R56: 14.203659 | S56: 14.192496 | T56: 14.188245 | U56: 14.197581 | V56: 14.217714 | W56: 14.239969 | X56: 14.268423 | Y56: 14.301932 | Z56: 14.345214 | AA56: 14.399622 | AB56: 14.468221 | AC56: 14.540375 | AD56: 14.616556 | AE56: 14.701982 | AF56: 14.799429 | AG56: 0.001
A57: TKI000:da_CommercialLig | B57: Commercial Light Trucks 1/ | C57: 0.888323 | D57: 0.90756 | E57: 0.915291 | F57: 0.914746 | G57: 0.917481 | H57: 0.917957 | I57: 0.914716 | J57: 0.913139 | K57: 0.912948 | L57: 0.913619 | M57: 0.914893 | N57: 0.917466 | O57: 0.921147 | P57: 0.925479 | Q57: 0.930151 | R57: 0.935853 | S57: 0.943343 | T57: 0.95109 | U57: 0.959005 | V57: 0.967115 | W57: 0.976328 | X57: 0.985922 | Y57: 0.996503 | Z57: 1.007049 | AA57: 1.017768 | AB57: 1.03064 | AC57: 1.041202 | AD57: 1.05052 | AE57: 1.061403 | AF57: 1.074768 | AG57: 0.007
A58: TKI000:da_BusTransporta | B58: Bus Transportation | C58: 0.175556 | D58: 0.199894 | E58: 0.211877 | F58: 0.218451 | G58: 0.222364 | H58: 0.224934 | I58: 0.226618 | J58: 0.227588 | K58: 0.228099 | L58: 0.228565 | M58: 0.229052 | N58: 0.229042 | O58: 0.228895 | P58: 0.228669 | Q58: 0.228265 | R58: 0.228023 | S58: 0.227888 | T58: 0.22772 | U58: 0.227019 | V58: 0.226432 | W58: 0.225723 | X58: 0.224894 | Y58: 0.224132 | Z58: 0.223359 | AA58: 0.222476 | AB58: 0.221673 | AC58: 0.220744 | AD58: 0.219683 | AE58: 0.218555 | AF58: 0.217454 | AG58: 0.007
A59: TKI000:da_FreightTrucks | B59: Freight Trucks | C59: 5.567438 | D59: 5.647416 | E59: 5.668759 | F59: 5.663161 | G59: 5.655948 | H59: 5.628574 | I59: 5.579707 | J59: 5.540802 | K59: 5.504025 | L59: 5.462724 | M59: 5.421764 | N59: 5.386013 | O59: 5.356112 | P59: 5.329699 | Q59: 5.312141 | R59: 5.300519 | S59: 5.299976 | T59: 5.304958 | U59: 5.312826 | V59: 5.324507 | W59: 5.344189 | X59: 5.371939 | Y59: 5.399783 | Z59: 5.429977 | AA59: 5.461901 | AB59: 5.498568 | AC59: 5.526202 | AD59: 5.545541 | AE59: 5.579021 | AF59: 5.62644 | AG59: 0
A60: TKI000:da_Rail,Passenge | B60: Rail, Passenger | C60: 0.035747 | D60: 0.040344 | E60: 0.043365 | F60: 0.045948 | G60: 0.047975 | H60: 0.049671 | I60: 0.050918 | J60: 0.051924 | K60: 0.052848 | L60: 0.053864 | M60: 0.054847 | N60: 0.05567 | O60: 0.056456 | P60: 0.057163 | Q60: 0.05777 | R60: 0.058395 | S60: 0.059068 | T60: 0.059723 | U60: 0.060305 | V60: 0.060996 | W60: 0.061573 | X60: 0.062161 | Y60: 0.062818 | Z60: 0.063486 | AA60: 0.064212 | AB60: 0.065028 | AC60: 0.065727 | AD60: 0.066388 | AE60: 0.067135 | AF60: 0.067961 | AG60: 0.022
A61: TKI000:da_Rail,Freight | B61: Rail, Freight | C61: 0.468249 | D61: 0.471079 | E61: 0.474241 | F61: 0.44252 | G61: 0.448957 | H61: 0.457648 | I61: 0.456704 | J61: 0.455449 | K61: 0.453944 | L61: 0.453611 | M61: 0.453718 | N61: 0.453838 | O61: 0.454424 | P61: 0.449777 | Q61: 0.447988 | R61: 0.443349 | S61: 0.443778 | T61: 0.443319 | U61: 0.442878 | V61: 0.441743 | W61: 0.441236 | X61: 0.441401 | Y61: 0.440002 | Z61: 0.438087 | AA61: 0.437033 | AB61: 0.436809 | AC61: 0.435689 | AD61: 0.435139 | AE61: 0.435125 | AF61: 0.437263 | AG61: -0.002
A62: TKI000:da_Shipping,Dome | B62: Shipping, Domestic | C62: 0.07517 | D62: 0.077553 | E62: 0.076938 | F62: 0.074884 | G62: 0.073009 | H62: 0.070952 | I62: 0.06864 | J62: 0.06646 | K62: 0.06422 | L62: 0.062007 | M62: 0.060829 | N62: 0.05965 | O62: 0.058555 | P62: 0.057363 | Q62: 0.056156 | R62: 0.054998 | S62: 0.053934 | T62: 0.05284 | U62: 0.051829 | V62: 0.050804 | W62: 0.050346 | X62: 0.04987 | Y62: 0.049359 | Z62: 0.048885 | AA62: 0.048413 | AB62: 0.047972 | AC62: 0.047419 | AD62: 0.046794 | AE62: 0.046349 | AF62: 0.046081 | AG62: -0.017
A63: TKI000:da_Shipping,Inte | B63: Shipping, International | C63: 0.927451 | D63: 0.990021 | E63: 0.88406 | F63: 0.884707 | G63: 0.887061 | H63: 0.885418 | I63: 0.881613 | J63: 0.880343 | K63: 0.880769 | L63: 0.87993 | M63: 0.884786 | N63: 0.884655 | O63: 0.885219 | P63: 0.886289 | Q63: 0.887352 | R63: 0.889095 | S63: 0.891039 | T63: 0.890647 | U63: 0.892274 | V63: 0.887781 | W63: 0.886336 | X63: 0.884984 | Y63: 0.881276 | Z63: 0.879002 | AA63: 0.879116 | AB63: 0.87801 | AC63: 0.877706 | AD63: 0.878744 | AE63: 0.879322 | AF63: 0.880516 | AG63: -0.002
A64: TKI000:da_RecreationalB | B64: Recreational Boats | C64: 0.204097 | D64: 0.207817 | E64: 0.208004 | F64: 0.208627 | G64: 0.208701 | H64: 0.208389 | I64: 0.207107 | J64: 0.205857 | K64: 0.204915 | L64: 0.204265 | M64: 0.203404 | N64: 0.202682 | O64: 0.202113 | P64: 0.201508 | Q64: 0.2008 | R64: 0.200075 | S64: 0.199646 | T64: 0.199111 | U64: 0.198526 | V64: 0.198077 | W64: 0.197288 | X64: 0.196608 | Y64: 0.195989 | Z64: 0.195343 | AA64: 0.194914 | AB64: 0.194549 | AC64: 0.193907 | AD64: 0.193255 | AE64: 0.192858 | AF64: 0.192572 | AG64: -0.002
A65: TKI000:da_Air | B65: Air | C65: 2.296161 | D65: 2.683651 | E65: 2.951118 | F65: 3.03471 | G65: 3.11169 | H65: 3.173993 | I65: 3.213956 | J65: 3.252055 | K65: 3.293846 | L65: 3.340357 | M65: 3.377276 | N65: 3.393485 | O65: 3.431159 | P65: 3.465197 | Q65: 3.501517 | R65: 3.538381 | S65: 3.580709 | T65: 3.619171 | U65: 3.663687 | V65: 3.712987 | W65: 3.753788 | X65: 3.799394 | Y65: 3.8472 | Z65: 3.892524 | AA65: 3.945747 | AB65: 3.999038 | AC65: 4.045661 | AD65: 4.090953 | AE65: 4.144071 | AF65: 4.203216 | AG65: 0.021
A66: TKI000:da_MilitaryUse | B66: Military Use | C66: 0.537703 | D66: 0.545349 | E66: 0.539672 | F66: 0.539224 | G66: 0.542587 | H66: 0.54515 | I66: 0.547037 | J66: 0.549198 | K66: 0.547834 | L66: 0.549644 | M66: 0.549119 | N66: 0.549319 | O66: 0.549484 | P66: 0.549623 | Q66: 0.549738 | R66: 0.549999 | S66: 0.550352 | T66: 0.550702 | U66: 0.55105 | V66: 0.551393 | W66: 0.551735 | X66: 0.552074 | Y66: 0.552409 | Z66: 0.552742 | AA66: 0.553074 | AB66: 0.553403 | AC66: 0.55373 | AD66: 0.554056 | AE66: 0.55438 | AF66: 0.554701 | AG66: 0.001
A67: TKI000:da_Lubricants | B67: Lubricants | C67: 0.125032 | D67: 0.126897 | E67: 0.127926 | F67: 0.1286 | G67: 0.129102 | H67: 0.12965 | I67: 0.129961 | J67: 0.130197 | K67: 0.130404 | L67: 0.130579 | M67: 0.130715 | N67: 0.130834 | O67: 0.130941 | P67: 0.131026 | Q67: 0.131091 | R67: 0.131164 | S67: 0.131261 | T67: 0.131365 | U67: 0.131484 | V67: 0.131631 | W67: 0.131762 | X67: 0.131876 | Y67: 0.131993 | Z67: 0.132102 | AA67: 0.13223 | AB67: 0.132369 | AC67: 0.132482 | AD67: 0.132586 | AE67: 0.132704 | AF67: 0.132831 | AG67: 0.002
... A69: TKI000:da_Total | B69: Total | C69: 26.323486 | D69: 27.261717 | E69: 27.691336 | F69: 27.713699 | G69: 27.751854 | H69: 27.725409 | I69: 27.604784 | J69: 27.501532 | K69: 27.406422 | L69: 27.33799 | M69: 27.28532 | N69: 27.210604 | O69: 27.188005 | P69: 27.162506 | Q69: 27.15077 | R69: 27.155056 | S69: 27.203161 | T69: 27.255516 | U69: 27.329729 | V69: 27.420429 | W69: 27.516987 | X69: 27.629517 | Y69: 27.752115 | Z69: 27.879595 | AA69: 28.032383 | AB69: 28.209902 | AC69: 28.372467 | AD69: 28.5296 | AE69: 28.716095 | AF69: 28.943384 | AG69: 0.003
B71: (million barrels per day oil equivalent)
A72: TKI000:ea_Light-DutyVeh | B72: Light-Duty Vehicles | C72: 7.742116 | D72: 7.952428 | E72: 8.08371 | F72: 8.072867 | G72: 8.052054 | H72: 8.01879 | I72: 7.971849 | J72: 7.916241 | K72: 7.867128 | L72: 7.832047 | M72: 7.804987 | N72: 7.772401 | O72: 7.754267 | P72: 7.738248 | Q72: 7.719971 | R72: 7.706108 | S72: 7.700164 | T72: 7.697928 | U72: 7.703142 | V72: 7.714182 | W72: 7.726223 | X72: 7.741686 | Y72: 7.759839 | Z72: 7.783333 | AA72: 7.812905 | AB72: 7.85021 | AC72: 7.889471 | AD72: 7.930946 | AE72: 7.977459 | AF72: 8.030522 | AG72: 0.001
A73: TKI000:ea_CommercialLig | B73: Commercial Light Trucks 1/ | C73: 0.464147 | D73: 0.474732 | E73: 0.479145 | F73: 0.479204 | G73: 0.481032 | H73: 0.481637 | I73: 0.48007 | J73: 0.479344 | K73: 0.479328 | L73: 0.479732 | M73: 0.480452 | N73: 0.481825 | O73: 0.483756 | P73: 0.486011 | Q73: 0.488466 | R73: 0.491464 | S73: 0.495405 | T73: 0.499485 | U73: 0.503656 | V73: 0.507948 | W73: 0.512819 | X73: 0.517899 | Y73: 0.523457 | Z73: 0.528974 | AA73: 0.534598 | AB73: 0.541335 | AC73: 0.546904 | AD73: 0.55184 | AE73: 0.557638 | AF73: 0.564761 | AG73: 0.007
A74: TKI000:ea_BusTransporta | B74: Bus Transportation | C74: 0.085859 | D74: 0.097947 | E74: 0.103826 | F74: 0.107033 | G74: 0.108947 | H74: 0.110241 | I74: 0.111054 | J74: 0.111527 | K74: 0.11177 | L74: 0.111989 | M74: 0.112246 | N74: 0.112238 | O74: 0.112155 | P74: 0.112047 | Q74: 0.11185 | R74: 0.111726 | S74: 0.111662 | T74: 0.111587 | U74: 0.111251 | V74: 0.110967 | W74: 0.11063 | X74: 0.110224 | Y74: 0.109848 | Z74: 0.109472 | AA74: 0.109043 | AB74: 0.108648 | AC74: 0.108193 | AD74: 0.107667 | AE74: 0.107116 | AF74: 0.106566 | AG74: 0.007
A75: TKI000:ea_FreightTrucks | B75: Freight Trucks | C75: 2.681122 | D75: 2.720326 | E75: 2.730281 | F75: 2.727139 | G75: 2.722948 | H75: 2.71029 | I75: 2.686574 | J75: 2.668368 | K75: 2.65138 | L75: 2.632008 | M75: 2.613121 | N75: 2.596792 | O75: 2.58329 | P75: 2.571543 | Q75: 2.564126 | R75: 2.559471 | S75: 2.560282 | T75: 2.563887 | U75: 2.568771 | V75: 2.575477 | W75: 2.586364 | X75: 2.601004 | Y75: 2.615732 | Z75: 2.631508 | AA75: 2.64829 | AB75: 2.667451 | AC75: 2.682264 | AD75: 2.693123 | AE75: 2.710997 | AF75: 2.735554 | AG75: 0.001
A76: TKI000:ea_Rail,Passenge | B76: Rail, Passenger | C76: 0.01693 | D76: 0.019111 | E76: 0.020543 | F76: 0.021765 | G76: 0.022722 | H76: 0.023527 | I76: 0.024115 | J76: 0.024591 | K76: 0.02503 | L76: 0.02551 | M76: 0.025975 | N76: 0.026365 | O76: 0.026737 | P76: 0.027073 | Q76: 0.02736 | R76: 0.027656 | S76: 0.027975 | T76: 0.028286 | U76: 0.028562 | V76: 0.028889 | W76: 0.029163 | X76: 0.029442 | Y76: 0.029753 | Z76: 0.030069 | AA76: 0.030413 | AB76: 0.030799 | AC76: 0.03113 | AD76: 0.031444 | AE76: 0.031799 | AF76: 0.032191 | AG76: 0.022
A77: TKI000:ea_Rail,Freight | B77: Rail, Freight | C77: 0.222397 | D77: 0.223843 | E77: 0.225339 | F77: 0.210235 | G77: 0.213218 | H77: 0.21736 | I77: 0.216847 | J77: 0.216229 | K77: 0.215496 | L77: 0.215296 | M77: 0.215329 | N77: 0.215365 | O77: 0.215621 | P77: 0.213397 | Q77: 0.212532 | R77: 0.210308 | S77: 0.210492 | T77: 0.210267 | U77: 0.210037 | V77: 0.209478 | W77: 0.209232 | X77: 0.209292 | Y77: 0.208613 | Z77: 0.20768 | AA77: 0.207164 | AB77: 0.207044 | AC77: 0.206499 | AD77: 0.206226 | AE77: 0.206214 | AF77: 0.207218 | AG77: -0.002
A78: TKI000:ea_Shipping,Dome | B78: Shipping, Domestic | C78: 0.035635 | D78: 0.036787 | E78: 0.036501 | F78: 0.035525 | G78: 0.034627 | H78: 0.033658 | I78: 0.032556 | J78: 0.031524 | K78: 0.030465 | L78: 0.029414 | M78: 0.028858 | N78: 0.028301 | O78: 0.027783 | P78: 0.02722 | Q78: 0.02665 | R78: 0.026101 | S78: 0.025598 | T78: 0.025082 | U78: 0.024604 | V78: 0.024118 | W78: 0.023903 | X78: 0.023677 | Y78: 0.023435 | Z78: 0.023208 | AA78: 0.022984 | AB78: 0.022775 | AC78: 0.022513 | AD78: 0.022216 | AE78: 0.022007 | AF78: 0.02188 | AG78: -0.017
A79: TKI000:ea_Shipping,Inte | B79: Shipping, International | C79: 0.4194 | D79: 0.441706 | E79: 0.400143 | F79: 0.400442 | G79: 0.401336 | H79: 0.400814 | I79: 0.399428 | J79: 0.399022 | K79: 0.399253 | L79: 0.398995 | M79: 0.40087 | N79: 0.400882 | O79: 0.401152 | P79: 0.401613 | Q79: 0.402068 | R79: 0.402766 | S79: 0.403541 | T79: 0.403462 | U79: 0.40412 | V79: 0.402499 | W79: 0.402031 | X79: 0.401587 | Y79: 0.400267 | Z79: 0.399465 | AA79: 0.399566 | AB79: 0.399214 | AC79: 0.399164 | AD79: 0.399617 | AE79: 0.399909 | AF79: 0.400431 | AG79: -0.002
A80: TKI000:ea_RecreationalB | B80: Recreational Boats | C80: 0.110663 | D80: 0.112683 | E80: 0.112789 | F80: 0.11313 | G80: 0.113195 | H80: 0.113051 | I80: 0.112379 | J80: 0.111725 | K80: 0.111239 | L80: 0.11091 | M80: 0.110467 | N80: 0.110098 | O80: 0.109813 | P80: 0.109508 | Q80: 0.109147 | R80: 0.108771 | S80: 0.108556 | T80: 0.108284 | U80: 0.107984 | V80: 0.107758 | W80: 0.107344 | X80: 0.10699 | Y80: 0.106669 | Z80: 0.106332 | AA80: 0.106114 | AB80: 0.105931 | AC80: 0.105597 | AD80: 0.105257 | AE80: 0.105056 | AF80: 0.104915 | AG80: -0.002
A81: TKI000:ea_Air | B81: Air | C81: 1.110822 | D81: 1.298055 | E81: 1.427294 | F81: 1.467685 | G81: 1.504884 | H81: 1.534991 | I81: 1.554303 | J81: 1.572715 | K81: 1.59291 | L81: 1.615387 | M81: 1.633229 | N81: 1.641063 | O81: 1.65927 | P81: 1.675719 | Q81: 1.693272 | R81: 1.711086 | S81: 1.731541 | T81: 1.750128 | U81: 1.77164 | V81: 1.795463 | W81: 1.81518 | X81: 1.837219 | Y81: 1.86032 | Z81: 1.882222 | AA81: 1.907941 | AB81: 1.933693 | AC81: 1.956223 | AD81: 1.97811 | AE81: 2.003777 | AF81: 2.032358 | AG81: 0.021
A82: TKI000:ea_MilitaryUse | B82: Military Use | C82: 0.257898 | D82: 0.261636 | E82: 0.258958 | F82: 0.258736 | G82: 0.260333 | H82: 0.26157 | I82: 0.262463 | J82: 0.2635 | K82: 0.262847 | L82: 0.26371 | M82: 0.26346 | N82: 0.263557 | O82: 0.263636 | P82: 0.263704 | Q82: 0.263761 | R82: 0.263885 | S82: 0.264055 | T82: 0.264227 | U82: 0.264394 | V82: 0.264558 | W82: 0.264727 | X82: 0.26489 | Y82: 0.265051 | Z82: 0.265208 | AA82: 0.265368 | AB82: 0.265527 | AC82: 0.265685 | AD82: 0.265843 | AE82: 0.266003 | AF82: 0.26616 | AG82: 0.001
A83: TKI000:ea_Lubricants | B83: Lubricants | C83: 0.059061 | D83: 0.059942 | E83: 0.060428 | F83: 0.060746 | G83: 0.060983 | H83: 0.061242 | I83: 0.061389 | J83: 0.061501 | K83: 0.061598 | L83: 0.061681 | M83: 0.061745 | N83: 0.061802 | O83: 0.061852 | P83: 0.061893 | Q83: 0.061923 | R83: 0.061958 | S83: 0.062003 | T83: 0.062053 | U83: 0.062109 | V83: 0.062178 | W83: 0.06224 | X83: 0.062294 | Y83: 0.062349 | Z83: 0.0624 | AA83: 0.062461 | AB83: 0.062527 | AC83: 0.06258 | AD83: 0.062629 | AE83: 0.062685 | AF83: 0.062745 | AG83: 0.002
... A85: TKI000:ea_Total | B85: Total | C85: 13.559407 | D85: 14.030354 | E85: 14.261442 | F85: 14.270667 | G85: 14.286991 | H85: 14.27242 | I85: 14.20985 | J85: 14.154975 | K85: 14.104977 | L85: 14.069279 | M85: 14.041723 | N85: 14.003458 | O85: 13.992006 | P85: 13.979344 | Q85: 13.973192 | R85: 13.974897 | S85: 13.99871 | T85: 14.025396 | U85: 14.063182 | V85: 14.110198 | W85: 14.160066 | X85: 14.217953 | Y85: 14.281213 | Z85: 14.347218 | AA85: 14.426109 | AB85: 14.518073 | AC85: 14.602921 | AD85: 14.685284 | AE85: 14.782825 | AF85: 14.900753 | AG85: 0.003
B87: 1/ Commercial trucks 8,501 to 10,000 pounds gross vehicle weight rating.
B88: 2/ CAFE standard based on projected new vehicle sales.
B89: 3/ Includes CAFE credits for alternative fueled vehicle sales and credit banking.
B90: 4/ Environmental Protection Agency rated miles per gallon.
B91: 5/ Tested new vehicle efficiency revised for on-road performance.
B92: 6/ Combined "on-the-road" estimate for all cars and light trucks.
B93: CAFE = Corporate average fuel economy.
B94: Btu = British thermal unit.
B95: Note: Totals may not equal sum of components due to independent rounding.
B96: Sources: 2020: U.S. Energy Information Administration (EIA), Short-Term Energy Outlook, October 2020 and EIA,
B97: AEO2021 National Energy Modeling System run highogs.d120120a. Projections: EIA, AEO2021 National Energy Modeling System run highogs.d120120a.

Sheet AEO 2021 Table 7
B1: highogs.d120120a | C1: 2020 | D1: 2021 | E1: 2022 | F1: 2023 | G1: 2024 | H1: 2025 | I1: 2026 | J1: 2027 | K1: 2028 | L1: 2029 | M1: 2030 | N1: 2031 | O1: 2032 | P1: 2033 | Q1: 2034 | R1: 2035 | S1: 2036 | T1: 2037 | U1: 2038 | V1: 2039 | W1: 2040 | X1: 2041 | Y1: 2042 | Z1: 2043 | AA1: 2044 | AB1: 2045 | AC1: 2046 | AD1: 2047 | AE1: 2048 | AF1: 2049 | AG1: 2050
C3: Report | D3: Annual Energy Outlook 2021
C4: Scenario | D4: ref2021 | G4: Reference case
C5: Datekey | D5: d113020a
C6: Release Date | E6: January 2021
A10: TKI000 | B10: 7. Transportation Sector Key Indicators and Delivered Energy Consumption | AH10: Compound
AH11: Growth
AH12: 2020-2050
B13: Key Indicators and Consumption | C13: 2020 | D13: 2021 | E13: 2022 | F13: 2023 | G13: 2024 | H13: 2025 | I13: 2026 | J13: 2027 | K13: 2028 | L13: 2029 | M13: 2030 | N13: 2031 | O13: 2032 | P13: 2033 | Q13: 2034 | R13: 2035 | S13: 2036 | T13: 2037 | U13: 2038 | V13: 2039 | W13: 2040 | X13: 2041 | Y13: 2042 | Z13: 2043 | AA13: 2044 | AB13: 2045 | AC13: 2046 | AD13: 2047 | AE13: 2048 | AF13: 2049 | AG13: 2050 | AH13: (percent)
B15: Key Indicators
B16: Travel Indicators
B17: (billion vehicle miles traveled)
A18: TKI000:ba_Light-DutyVeh | B18: Light-Duty Vehicles less than 8,501 pounds | C18: 2628.8213 | D18: 2807.2766 | E18: 2862.5334 | F18: 2927.623 | G18: 2985.1787 | H18: 3035.5583 | I18: 3076.646 | J18: 3107.3425 | K18: 3133.9348 | L18: 3153.6963 | M18: 3170.1406 | N18: 3182.3604 | O18: 3194.3308 | P18: 3208.3691 | Q18: 3223.0125 | R18: 3240.585 | S18: 3258.4961 | T18: 3274.8767 | U18: 3290.0166 | V18: 3306.9768 | W18: 3326.3066 | X18: 3344.3862 | Y18: 3362.8257 | Z18: 3380.6958 | AA18: 3396.752 | AB18: 3412.0305 | AC18: 3428.1084 | AD18: 3442.5149 | AE18: 3458.3401 | AF18: 3474.7087 | AG18: 3490.9399 | AH18: 0.009499
A19: TKI000:ba_CommercialLig | B19: Commercial Light Trucks 1/ | C19: 89.884674 | D19: 93.705605 | E19: 96.386086 | F19: 98.338295 | G19: 100.59341 | H19: 102.85941 | I19: 104.50481 | J19: 105.69051 | K19: 106.73648 | L19: 107.65262 | M19: 108.58299 | N19: 109.54169 | O19: 110.61884 | P19: 111.70705 | Q19: 112.95861 | R19: 114.4644 | S19: 115.90713 | T19: 117.2149 | U19: 118.58162 | V19: 120.04366 | W19: 121.52813 | X19: 123.15266 | Y19: 124.79562 | Z19: 126.54729 | AA19: 128.13809 | AB19: 129.78653 | AC19: 131.39938 | AD19: 132.81888 | AE19: 134.41592 | AF19: 136.18376 | AG19: 138.01 | AH19: 0.014396
A20: TKI000:ba_FreightTrucks | B20: Freight Trucks greater than 10,000 pounds | C20: 274.54938 | D20: 282.81525 | E20: 293.31253 | F20: 299.26825 | G20: 306.24057 | H20: 313.39252 | I20: 318.20425 | J20: 321.86676 | K20: 325.49912 | L20: 328.91818 | M20: 332.87759 | N20: 337.04804 | O20: 341.41943 | P20: 345.24298 | Q20: 349.75104 | R20: 355.3486 | S20: 360.47449 | T20: 365.30786 | U20: 370.46982 | V20: 375.98251 | W20: 381.01727 | X20: 386.70856 | Y20: 392.7948 | Z20: 399.70087 | AA20: 405.64847 | AB20: 411.79804 | AC20: 417.07053 | AD20: 422.22894 | AE20: 428.00507 | AF20: 434.11798 | AG20: 440.79153 | AH20: 0.015907
B21: (billion passenger miles traveled)
A22: TKI000:buspassmiles | B22: Bus Transportation | C22: 108.32251 | D22: 134.82925 | E22: 154.71742 | F22: 169.65283 | G22: 180.92081 | H22: 189.4493 | I22: 195.91775 | J22: 200.87158 | K22: 204.4294 | L22: 207.17819 | M22: 209.42627 | N22: 211.01544 | O22: 212.35484 | P22: 213.3685 | Q22: 214.16457 | R22: 214.70816 | S22: 215.16942 | T22: 215.53513 | U22: 215.80548 | V22: 215.98587 | W22: 216.16197 | X22: 216.26544 | Y22: 216.33122 | Z22: 216.37845 | AA22: 216.40999 | AB22: 216.44157 | AC22: 216.45151 | AD22: 216.46837 | AE22: 216.483 | AF22: 216.55254 | AG22: 216.64348 | AH22: 0.023374
A23: TKI000:railpassmiles | B23: Passenger Rail | C23: 24.970692 | D23: 29.653244 | E23: 33.486446 | F23: 36.386101 | G23: 38.577961 | H23: 40.222988 | I23: 41.396164 | J23: 42.264778 | K23: 42.515728 | L23: 42.713291 | M23: 43.137005 | N23: 43.343742 | O23: 43.818241 | P23: 44.274139 | Q23: 44.835865 | R23: 45.310886 | S23: 45.831734 | T23: 46.32793 | U23: 46.816154 | V23: 47.317448 | W23: 47.980492 | X23: 48.58215 | Y23: 49.164021 | Z23: 49.763081 | AA23: 50.334721 | AB23: 50.97802 | AC23: 51.558666 | AD23: 52.079247 | AE23: 52.647175 | AF23: 53.282265 | AG23: 53.912506 | AH23: 0.025987
B24: (billion seat miles available)
A25: TKI000:ba_Air | B25: Air | C25: 738.85895 | D25: 1081.6603 | E25: 1215.7373 | F25: 1284.3009 | G25: 1340.2419 | H25: 1397.254 | I25: 1430.9814 | J25: 1455.4497 | K25: 1476.5328 | L25: 1495.9988 | M25: 1516.3666 | N25: 1539.9563 | O25: 1569.8956 | P25: 1600.4498 | Q25: 1634.8596 | R25: 1672.6685 | S25: 1707.1351 | T25: 1738.4458 | U25: 1770.8867 | V25: 1807.5973 | W25: 1848.892 | X25: 1889.7706 | Y25: 1930.5969 | Z25: 1971.072 | AA25: 2010.4889 | AB25: 2052.9485 | AC25: 2092.6599 | AD25: 2129.1379 | AE25: 2171.0725 | AF25: 2213.2192 | AG25: 2256.3169 | AH25: 0.037914
B26: (billion ton miles traveled)
A27: TKI000:ba_Rail | B27: Rail | C27: 1508.557 | D27: 1600.7733 | E27: 1616.5277 | F27: 1618.1086 | G27: 1617.9658 | H27: 1567.8839 | I27: 1587.1537 | J27: 1586.3214 | K27: 1606.0509 | L27: 1623.5897 | M27: 1641.5112 | N27: 1654.2195 | O27: 1664.4609 | P27: 1678.1671 | Q27: 1686.5093 | R27: 1700.8228 | S27: 1714.3484 | T27: 1725.9465 | U27: 1730.047 | V27: 1747.595 | W27: 1753.4669 | X27: 1765.8125 | Y27: 1783.1677 | Z27: 1804.6465 | AA27: 1808.4172 | AB27: 1822.5868 | AC27: 1832.4125 | AD27: 1846.7275 | AE27: 1860.8992 | AF27: 1876.0131 | AG27: 1898.7479 | AH27: 0.007697
A28: TKI000:ba_DomesticShipp | B28: Domestic Shipping | C28: 347.68133 | D28: 359.32346 | E28: 357.10059 | F28: 354.90668 | G28: 352.6954 | H28: 348.07819 | I28: 341.28058 | J28: 333.10046 | K28: 325.25259 | L28: 316.86505 | M28: 308.73145 | N28: 305.11627 | O28: 301.85187 | P28: 298.30835 | Q28: 295.38019 | R28: 292.62634 | S28: 289.63 | T28: 286.27258 | U28: 282.6651 | V28: 279.71716 | W28: 276.01688 | X28: 275.42545 | Y28: 275.00784 | Z28: 275.36859 | AA28: 274.91849 | AB28: 274.56326 | AC28: 273.54471 | AD28: 272.61859 | AE28: 271.43494 | AF28: 270.55728 | AG28: 270.13117 | AH28: -0.008377
B30: Energy Efficiency Indicators
B31: (miles per gallon)
A32: TKI000:ca_AvgCAFEStand | B32: New Light-Duty Vehicle CAFE Standard 2/ | C32: 34.471165 | D32: 35.386478 | E32: 36.015511 | F32: 36.532135 | G32: 36.999756 | H32: 37.485561 | I32: 38.067947 | J32: 38.072563 | K32: 38.080814 | L32: 38.095245 | M32: 38.18074 | N32: 38.191765 | O32: 38.206318 | P32: 38.220623 | Q32: 38.249493 | R32: 38.23008 | S32: 38.209507 | T32: 38.204479 | U32: 38.204224 | V32: 38.187893 | W32: 38.180141 | X32: 38.173969 | Y32: 38.160957 | Z32: 38.151768 | AA32: 38.148342 | AB32: 38.153297 | AC32: 38.143864 | AD32: 38.134365 | AE32: 38.120548 | AF32: 38.116928 | AG32: 38.114223 | AH32: 0.003354
A33: TKI000:ca_CarCAFEStand | B33: New Car 2/ | C33: 42.096588 | D33: 44.275085 | E33: 44.804096 | F33: 45.431927 | G33: 46.163593 | H33: 46.83271 | I33: 47.617275 | J33: 47.640335 | K33: 47.640335 | L33: 47.644814 | M33: 47.681995 | N33: 47.681995 | O33: 47.681995 | P33: 47.681995 | Q33: 47.681995 | R33: 47.681995 | S33: 47.681995 | T33: 47.681995 | U33: 47.681995 | V33: 47.681995 | W33: 47.681995 | X33: 47.681995 | Y33: 47.681995 | Z33: 47.683205 | AA33: 47.684814 | AB33: 47.687138 | AC33: 47.687138 | AD33: 47.687138 | AE33: 47.687138 | AF33: 47.689449 | AG33: 47.689449 | AH33: 0.004167
A34: TKI000:ca_TwukCAFEStand | B34: New Light Truck 2/ | C34: 30.906752 | D34: 31.515783 | E34: 31.942911 | F34: 32.461285 | G34: 32.91795 | H34: 33.400791 | I34: 33.955074 | J34: 33.955074 | K34: 33.955074 | L34: 33.955074 | M34: 33.955074 | N34: 33.955093 | O34: 33.955093 | P34: 33.955093 | Q34: 33.955093 | R34: 33.955128 | S34: 33.955128 | T34: 33.955128 | U34: 33.955128 | V34: 33.955128 | W34: 33.955128 | X34: 33.955128 | Y34: 33.955128 | Z34: 33.955128 | AA34: 33.955128 | AB34: 33.955128 | AC34: 33.955128 | AD34: 33.955128 | AE34: 33.955128 | AF34: 33.955128 | AG34: 33.955128 | AH34: 0.00314
A35: TKI000:ca_NewVehCred | B35: Compliance New Light-Duty Vehicle 3/ | C35: 35.428043 | D35: 36.588161 | E35: 37.27243 | F35: 37.693687 | G35: 38.000156 | H35: 38.414772 | I35: 38.930225 | J35: 39.067493 | K35: 39.131561 | L35: 39.187084 | M35: 39.367001 | N35: 39.458767 | O35: 39.570412 | P35: 39.688381 | Q35: 39.842903 | R35: 39.925739 | S35: 40.007633 | T35: 40.122059 | U35: 40.263226 | V35: 40.363659 | W35: 40.483315 | X35: 40.567554 | Y35: 40.636898 | Z35: 40.715225 | AA35: 40.813824 | AB35: 40.933929 | AC35: 41.032745 | AD35: 41.136253 | AE35: 41.233734 | AF35: 41.366283 | AG35: 41.510693 | AH35: 0.005296
A36: TKI000:ca_NewCarCred | B36: New Car 3/ | C36: 43.264011 | D36: 45.133469 | E36: 45.638382 | F36: 46.329559 | G36: 46.974045 | H36: 47.544498 | I36: 48.288284 | J36: 48.41925 | K36: 48.519196 | L36: 48.602192 | M36: 48.75803 | N36: 48.944359 | O36: 49.116051 | P36: 49.343533 | Q36: 49.588879 | R36: 49.838387 | S36: 50.062164 | T36: 50.324268 | U36: 50.609341 | V36: 50.887779 | W36: 51.161552 | X36: 51.375084 | Y36: 51.577618 | Z36: 51.784939 | AA36: 52.021469 | AB36: 52.278286 | AC36: 52.554256 | AD36: 52.823685 | AE36: 53.105881 | AF36: 53.415283 | AG36: 53.766708 | AH36: 0.007271
A37: TKI000:ca_NewTwukCred | B37: New Light Truck 3/ | C37: 31.76507 | D37: 32.790131 | E37: 33.304337 | F37: 33.675228 | G37: 33.948895 | H37: 34.370636 | I37: 34.850887 | J37: 34.987331 | K37: 35.027725 | L37: 35.055889 | M37: 35.139996 | N37: 35.184067 | O37: 35.253815 | P37: 35.313755 | Q37: 35.395432 | R37: 35.447819 | S37: 35.509632 | T37: 35.58049 | U37: 35.672146 | V37: 35.736599 | W37: 35.81567 | X37: 35.86631 | Y37: 35.911537 | Z37: 35.962078 | AA37: 36.021683 | AB37: 36.09063 | AC37: 36.147751 | AD37: 36.213341 | AE37: 36.274784 | AF37: 36.358318 | AG37: 36.442936 | AH37: 0.00459
A38: TKI000:ca_TestedNewVeh | B38: Tested New Light-Duty Vehicle 4/ | C38: 35.306622 | D38: 36.467899 | E38: 37.145805 | F38: 37.564754 | G38: 37.869587 | H38: 38.261166 | I38: 38.678329 | J38: 38.78212 | K38: 38.833714 | L38: 38.876083 | M38: 39.031017 | N38: 39.097122 | O38: 39.178814 | P38: 39.263397 | Q38: 39.380604 | R38: 39.428646 | S38: 39.476784 | T38: 39.553841 | U38: 39.655148 | V38: 39.718605 | W38: 39.800255 | X38: 39.857685 | Y38: 39.902508 | Z38: 39.954895 | AA38: 40.024872 | AB38: 40.112934 | AC38: 40.181061 | AD38: 40.254047 | AE38: 40.320404 | AF38: 40.416508 | AG38: 40.5215 | AH38: 0.004603
A39: TKI000:ca_TestedNewCar | B39: New Car 4/ | C39: 42.996372 | D39: 44.88583 | E39: 45.388092 | F39: 46.068283 | G39: 46.702301 | H39: 47.265957 | I39: 47.99147 | J39: 48.105293 | K39: 48.179577 | L39: 48.231701 | M39: 48.343479 | N39: 48.473526 | O39: 48.589264 | P39: 48.747791 | Q39: 48.918312 | R39: 49.08532 | S39: 49.232788 | T39: 49.410698 | U39: 49.605431 | V39: 49.791992 | W39: 49.975594 | X39: 50.118858 | Y39: 50.253036 | Z39: 50.390747 | AA39: 50.551331 | AB39: 50.726044 | AC39: 50.913406 | AD39: 51.097149 | AE39: 51.287189 | AF39: 51.498287 | AG39: 51.738174 | AH39: 0.006188
A40: TKI000:ca_TestedNewTwuk | B40: New Light Truck 4/ | C40: 31.69734 | D40: 32.714512 | E40: 33.224262 | F40: 33.594929 | G40: 33.868374 | H40: 34.261593 | I40: 34.620468 | J40: 34.71925 | K40: 34.751755 | L40: 34.772854 | M40: 34.839573 | N40: 34.86882 | O40: 34.918171 | P40: 34.957504 | Q40: 35.015827 | R40: 35.049236 | S40: 35.091114 | T40: 35.140182 | U40: 35.208858 | V40: 35.253445 | W40: 35.311043 | X40: 35.348305 | Y40: 35.381889 | Z40: 35.41943 | AA40: 35.464706 | AB40: 35.517353 | AC40: 35.560341 | AD40: 35.610996 | AE40: 35.657856 | AF40: 35.722626 | AG40: 35.788242 | AH40: 0.004054
A41: TKI000:ca_OnRoadNewVeh | B41: On-Road New Light-Duty Vehicle 5/ | C41: 28.801699 | D41: 29.748508 | E41: 30.302168 | F41: 30.643736 | G41: 30.892097 | H41: 31.211321 | I41: 31.551422 | J41: 31.636091 | K41: 31.678196 | L41: 31.712803 | M41: 31.839462 | N41: 31.893412 | O41: 31.960094 | P41: 32.029114 | Q41: 32.124813 | R41: 32.16391 | S41: 32.203083 | T41: 32.2659 | U41: 32.348515 | V41: 32.400196 | W41: 32.466755 | X41: 32.513561 | Y41: 32.550056 | Z41: 32.592743 | AA41: 32.649788 | AB41: 32.721619 | AC41: 32.77713 | AD41: 32.836617 | AE41: 32.890667 | AF41: 32.969021 | AG41: 33.054626 | AH41: 0.004601
A42: TKI000:ca_OnRoadNewCar | B42: New Car 5/ | C42: 35.111473 | D42: 36.65443 | E42: 37.064587 | F42: 37.620041 | G42: 38.137787 | H42: 38.598076 | I42: 39.190544 | J42: 39.283493 | K42: 39.344154 | L42: 39.386719 | M42: 39.477997 | N42: 39.584198 | O42: 39.678711 | P42: 39.808167 | Q42: 39.947414 | R42: 40.083797 | S42: 40.20422 | T42: 40.349506 | U42: 40.508526 | V42: 40.660873 | W42: 40.810806 | X42: 40.927799 | Y42: 41.037373 | Z42: 41.149826 | AA42: 41.280964 | AB42: 41.423634 | AC42: 41.576637 | AD42: 41.726685 | AE42: 41.881874 | AF42: 42.05426 | AG42: 42.250156 | AH42: 0.006188
A43: TKI000:ca_OnRoadNewTwuk | B43: New Light Truck 5/ | C43: 25.844681 | D43: 26.67404 | E43: 27.08967 | F43: 27.391895 | G43: 27.614851 | H43: 27.935465 | I43: 28.228077 | J43: 28.30862 | K43: 28.335123 | L43: 28.352325 | M43: 28.406727 | N43: 28.430573 | O43: 28.470812 | P43: 28.502882 | Q43: 28.550436 | R43: 28.577677 | S43: 28.611822 | T43: 28.651831 | U43: 28.707827 | V43: 28.744179 | W43: 28.791143 | X43: 28.821524 | Y43: 28.848907 | Z43: 28.879517 | AA43: 28.916433 | AB43: 28.95936 | AC43: 28.99441 | AD43: 29.035711 | AE43: 29.073919 | AF43: 29.12673 | AG43: 29.180231 | AH43: 0.004054
... A47: TKI000:ca_FreightTruck | B47: Freight Truck | C47: 7.238182 | D47: 7.310616 | E47: 7.389947 | F47: 7.476684 | G47: 7.574702 | H47: 7.686319 | I47: 7.80973 | J47: 7.944551 | K47: 8.083447 | L47: 8.230841 | M47: 8.382581 | N47: 8.536425 | O47: 8.686997 | P47: 8.827357 | Q47: 8.956337 | R47: 9.073474 | S47: 9.178899 | T47: 9.273054 | U47: 9.358724 | V47: 9.437573 | W47: 9.508476 | X47: 9.572987 | Y47: 9.62975 | Z47: 9.67997 | AA47: 9.724974 | AB47: 9.767028 | AC47: 9.806892 | AD47: 9.846315 | AE47: 9.885777 | AF47: 9.92395 | AG47: 9.961658 | AH47: 0.010703
B48: (seat miles per gallon)
A49: TKI000:ca_Aircraft | B49: Aircraft | C49: 71.028343 | D49: 72.22039 | E49: 72.564766 | F49: 73.078918 | G49: 73.855469 | H49: 74.440651 | I49: 74.946922 | J49: 75.432518 | K49: 75.920792 | L49: 76.399239 | M49: 76.903839 | N49: 77.42765 | O49: 77.983635 | P49: 78.569893 | Q49: 79.171509 | R49: 79.79718 | S49: 80.421959 | T49: 81.046387 | U49: 81.662766 | V49: 82.260727 | W49: 82.849083 | X49: 83.43293 | Y49: 84.016846 | Z49: 84.607124 | AA49: 85.178467 | AB49: 85.733246 | AC49: 86.278442 | AD49: 86.813042 | AE49: 87.369904 | AF49: 87.921379 | AG49: 88.469986 | AH49: 0.007346
B50: (ton miles/thousand Btu)
A51: TKI000:ca_Rail | B51: Rail | C51: 3.489371 | D51: 3.512003 | E51: 3.534782 | F51: 3.55771 | G51: 3.580785 | H51: 3.60401 | I51: 3.627386 | J51: 3.650914 | K51: 3.674594 | L51: 3.698428 | M51: 3.722416 | N51: 3.74656 | O51: 3.77086 | P51: 3.795318 | Q51: 3.819935 | R51: 3.844712 | S51: 3.869649 | T51: 3.894748 | U51: 3.920009 | V51: 3.945435 | W51: 3.971025 | X51: 3.996782 | Y51: 4.022705 | Z51: 4.048797 | AA51: 4.075058 | AB51: 4.101489 | AC51: 4.128091 | AD51: 4.154866 | AE51: 4.181815 | AF51: 4.208939 | AG51: 4.236238 | AH51: 0.006486
A52: TKI000:ca_DomesticShipp | B52: Domestic Shipping | C52: 4.84196 | D52: 4.870726 | E52: 4.899663 | F52: 4.928772 | G52: 4.958054 | H52: 4.987509 | I52: 5.01714 | J52: 5.046947 | K52: 5.076931 | L52: 5.107092 | M52: 5.137434 | N52: 5.167955 | O52: 5.198658 | P52: 5.229543 | Q52: 5.260611 | R52: 5.291864 | S52: 5.323303 | T52: 5.354929 | U52: 5.386742 | V52: 5.418745 | W52: 5.450938 | X52: 5.483322 | Y52: 5.515898 | Z52: 5.548667 | AA52: 5.581632 | AB52: 5.614792 | AC52: 5.64815 | AD52: 5.681705 | AE52: 5.71546 | AF52: 5.749416 | AG52: 5.783573 | AH52: 0.005941
B54: Energy Use by Mode
B55: (quadrillion Btu)
A56: TKI000:da_Light-DutyVeh | B56: Light-Duty Vehicles | C56: 13.684958 | D56: 14.333231 | E56: 14.327022 | F56: 14.365352 | G56: 14.366455 | H56: 14.341867 | I56: 14.287132 | J56: 14.207239 | K56: 14.125376 | L56: 14.028779 | M56: 13.931946 | N56: 13.831038 | O56: 13.740598 | P56: 13.671222 | Q56: 13.614177 | R56: 13.578903 | S56: 13.555063 | T56: 13.533011 | U56: 13.512934 | V56: 13.507698 | W56: 13.519425 | X56: 13.531686 | Y56: 13.55102 | Z56: 13.573046 | AA56: 13.591692 | AB56: 13.608699 | AC56: 13.631719 | AD56: 13.65046 | AE56: 13.676695 | AF56: 13.70651 | AG56: 13.736445 | AH56: 0.000125
A57: TKI000:da_CommercialLig | B57: Commercial Light Trucks 1/ | C57: 0.800598 | D57: 0.824583 | E57: 0.83718 | F57: 0.842737 | G57: 0.851008 | H57: 0.861964 | I57: 0.867177 | J57: 0.868256 | K57: 0.868721 | L57: 0.868144 | M57: 0.86827 | N57: 0.869091 | O57: 0.871659 | P57: 0.875056 | Q57: 0.880524 | R57: 0.888546 | S57: 0.896605 | T57: 0.904579 | U57: 0.913077 | V57: 0.922396 | W57: 0.932011 | X57: 0.942835 | Y57: 0.95338 | Z57: 0.965235 | AA57: 0.976007 | AB57: 0.987214 | AC57: 0.999347 | AD57: 1.008795 | AE57: 1.01946 | AF57: 1.031487 | AG57: 1.044088 | AH57: 0.008891
A58: TKI000:da_BusTransporta | B58: Bus Transportation | C58: 0.123601 | D58: 0.155229 | E58: 0.178087 | F58: 0.194794 | G58: 0.207087 | H58: 0.215933 | I58: 0.222447 | J58: 0.227387 | K58: 0.229827 | L58: 0.231575 | M58: 0.233385 | N58: 0.233909 | O58: 0.234577 | P58: 0.234898 | Q58: 0.235117 | R58: 0.234732 | S58: 0.234535 | T58: 0.234329 | U58: 0.233979 | V58: 0.23339 | W58: 0.232922 | X58: 0.232252 | Y58: 0.231514 | Z58: 0.230767 | AA58: 0.230025 | AB58: 0.229276 | AC58: 0.228442 | AD58: 0.227697 | AE58: 0.226858 | AF58: 0.226287 | AG58: 0.225795 | AH58: 0.020289
A59: TKI000:da_FreightTrucks | B59: Freight Trucks | C59: 5.215993 | D59: 5.320461 | E59: 5.459595 | F59: 5.506526 | G59: 5.562604 | H59: 5.610408 | I59: 5.606836 | J59: 5.575173 | K59: 5.54105 | L59: 5.498658 | M59: 5.463652 | N59: 5.431874 | O59: 5.406318 | P59: 5.379243 | Q59: 5.370211 | R59: 5.384785 | S59: 5.398619 | T59: 5.414024 | U59: 5.438496 | V59: 5.471154 | W59: 5.50076 | X59: 5.54297 | Y59: 5.59491 | Z59: 5.661906 | AA59: 5.718006 | AB59: 5.778462 | AC59: 5.827639 | AD59: 5.875145 | AE59: 5.930928 | AF59: 5.991611 | AG59: 6.059749 | AH59: 0.00501
A60: TKI000:da_Rail,Passenge | B60: Rail, Passenger | C60: 0.029437 | D60: 0.035251 | E60: 0.039934 | F60: 0.043478 | G60: 0.046156 | H60: 0.048166 | I60: 0.049615 | J60: 0.050695 | K60: 0.051001 | L60: 0.05125 | M60: 0.051752 | N60: 0.052019 | O60: 0.052574 | P60: 0.053111 | Q60: 0.053765 | R60: 0.05433 | S60: 0.054952 | T60: 0.05555 | U60: 0.056141 | V60: 0.056752 | W60: 0.057542 | X60: 0.058268 | Y60: 0.058979 | Z60: 0.059712 | AA60: 0.060418 | AB60: 0.061203 | AC60: 0.061918 | AD60: 0.062563 | AE60: 0.063254 | AF60: 0.064012 | AG60: 0.064756 | AH60: 0.026627
A61: TKI000:da_Rail,Freight | B61: Rail, Freight | C61: 0.432329 | D61: 0.455801 | E61: 0.45732 | F61: 0.454818 | G61: 0.451847 | H61: 0.435039 | I61: 0.437548 | J61: 0.4345 | K61: 0.437069 | L61: 0.438995 | M61: 0.44098 | N61: 0.44153 | O61: 0.441401 | P61: 0.442168 | Q61: 0.441502 | R61: 0.44238 | S61: 0.443024 | T61: 0.443147 | U61: 0.441338 | V61: 0.442941 | W61: 0.441565 | X61: 0.441809 | Y61: 0.443276 | Z61: 0.445724 | AA61: 0.443777 | AB61: 0.444372 | AC61: 0.443889 | AD61: 0.444473 | AE61: 0.444998 | AF61: 0.445721 | AG61: 0.448216 | AH61: 0.001204
A62: TKI000:da_Shipping,Dome | B62: Shipping, Domestic | C62: 0.077343 | D62: 0.079141 | E62: 0.078228 | F62: 0.07735 | G62: 0.076447 | H62: 0.075056 | I62: 0.073205 | J62: 0.071058 | K62: 0.068995 | L62: 0.066834 | M62: 0.064753 | N62: 0.063638 | O62: 0.062605 | P62: 0.061511 | Q62: 0.060562 | R62: 0.059665 | S62: 0.058721 | T62: 0.057711 | U62: 0.056659 | V62: 0.055745 | W62: 0.054692 | X62: 0.054265 | Y62: 0.053874 | Z62: 0.053634 | AA62: 0.05324 | AB62: 0.052873 | AC62: 0.052373 | AD62: 0.051891 | AE62: 0.05137 | AF62: 0.05091 | AG62: 0.050533 | AH62: -0.014087
A63: TKI000:da_Shipping,Inte | B63: Shipping, International | C63: 0.855887 | D63: 0.881465 | E63: 0.973998 | F63: 0.992193 | G63: 0.941402 | H63: 0.944552 | I63: 0.956481 | J63: 0.933812 | K63: 0.934805 | L63: 0.926796 | M63: 0.92926 | N63: 0.946328 | O63: 0.931566 | P63: 0.932016 | Q63: 0.929677 | R63: 0.944409 | S63: 0.930073 | T63: 0.929561 | U63: 0.939661 | V63: 0.926163 | W63: 0.924429 | X63: 0.937035 | Y63: 0.921133 | Z63: 0.92034 | AA63: 0.913829 | AB63: 0.914233 | AC63: 0.910465 | AD63: 0.908206 | AE63: 0.908689 | AF63: 0.907332 | AG63: 0.904865 | AH63: 0.001857
A64: TKI000:da_RecreationalB | B64: Recreational Boats | C64: 0.195878 | D64: 0.196657 | E64: 0.199716 | F64: 0.201514 | G64: 0.202257 | H64: 0.202574 | I64: 0.201854 | J64: 0.200378 | K64: 0.198674 | L64: 0.19683 | M64: 0.195069 | N64: 0.193556 | O64: 0.192489 | P64: 0.191383 | Q64: 0.190484 | R64: 0.189818 | S64: 0.18891 | T64: 0.187759 | U64: 0.186658 | V64: 0.185802 | W64: 0.185223 | X64: 0.184588 | Y64: 0.183882 | Z64: 0.183175 | AA64: 0.182329 | AB64: 0.18168 | AC64: 0.180906 | AD64: 0.17988 | AE64: 0.17914 | AF64: 0.178366 | AG64: 0.177572 | AH64: -0.003265
A65: TKI000:da_Air | B65: Air | C65: 1.860485 | D65: 2.530984 | E65: 2.826346 | F65: 2.963305 | G65: 3.051768 | H65: 3.120219 | I65: 3.144242 | J65: 3.161629 | K65: 3.182792 | L65: 3.201851 | M65: 3.222472 | N65: 3.248707 | O65: 3.287299 | P65: 3.325297 | Q65: 3.36779 | R65: 3.416815 | S65: 3.457473 | T65: 3.492202 | U65: 3.528905 | V65: 3.570296 | W65: 3.622022 | X65: 3.669847 | Y65: 3.719 | Z65: 3.765759 | AA65: 3.814193 | AB65: 3.866814 | AC65: 3.914752 | AD65: 3.951365 | AE65: 3.990626 | AF65: 4.026413 | AG65: 4.062809 | AH65: 0.026376
A66: TKI000:da_MilitaryUse | B66: Military Use | C66: 0.535966 | D66: 0.545011 | E66: 0.545749 | F66: 0.53257 | G66: 0.52388 | H66: 0.523357 | I66: 0.5221 | J66: 0.52193 | K66: 0.524808 | L66: 0.52365 | M66: 0.521666 | N66: 0.521585 | O66: 0.52242 | P66: 0.523287 | Q66: 0.524164 | R66: 0.525042 | S66: 0.525958 | T66: 0.526906 | U66: 0.527867 | V66: 0.528832 | W66: 0.529807 | X66: 0.530791 | Y66: 0.531775 | Z66: 0.532766 | AA66: 0.533758 | AB66: 0.534753 | AC66: 0.535749 | AD66: 0.536745 | AE66: 0.53774 | AF66: 0.538735 | AG66: 0.539727 | AH66: 0.000233
A67: TKI000:da_Lubricants | B67: Lubricants | C67: 0.121224 | D67: 0.1234 | E67: 0.124821 | F67: 0.125915 | G67: 0.126656 | H67: 0.127041 | I67: 0.127207 | J67: 0.126854 | K67: 0.126597 | L67: 0.126378 | M67: 0.126074 | N67: 0.125802 | O67: 0.125585 | P67: 0.125401 | Q67: 0.125289 | R67: 0.125205 | S67: 0.125084 | T67: 0.124934 | U67: 0.12483 | V67: 0.124758 | W67: 0.124673 | X67: 0.124589 | Y67: 0.124522 | Z67: 0.12444 | AA67: 0.124423 | AB67: 0.124498 | AC67: 0.124516 | AD67: 0.124474 | AE67: 0.124496 | AF67: 0.12447 | AG67: 0.124386 | AH67: 0.000858
... A69: TKI000:da_Total | B69: Total | C69: 24.63995 | D69: 26.246357 | E69: 26.803347 | F69: 27.032192 | G69: 27.130775 | H69: 27.230783 | I69: 27.186893 | J69: 27.080057 | K69: 26.990782 | L69: 26.860777 | M69: 26.742741 | N69: 26.653553 | O69: 26.566212 | P69: 26.51256 | Q69: 26.490156 | R69: 26.545183 | S69: 26.577869 | T69: 26.62192 | U69: 26.686522 | V69: 26.75659 | W69: 26.859634 | X69: 26.988043 | Y69: 27.108532 | Z69: 27.264854 | AA69: 27.401077 | AB69: 27.549936 | AC69: 27.685604 | AD69: 27.804758 | AE69: 27.932571 | AF69: 28.069273 | AG69: 28.223778 | AH69: 0.004537
B71: (million barrels per day oil equivalent)
A72: TKI000:ea_Light-DutyVeh | B72: Light-Duty Vehicles | C72: 7.422104 | D72: 7.773714 | E72: 7.769763 | F72: 7.790549 | G72: 7.790876 | H72: 7.778635 | I72: 7.749986 | J72: 7.707629 | K72: 7.66415 | L72: 7.612647 | M72: 7.560986 | N72: 7.507026 | O72: 7.458717 | P72: 7.421792 | Q72: 7.391498 | R72: 7.373047 | S72: 7.360369 | T72: 7.34863 | U72: 7.337916 | V72: 7.33523 | W72: 7.341699 | X72: 7.348314 | Y72: 7.358773 | Z72: 7.37068 | AA72: 7.380744 | AB72: 7.389912 | AC72: 7.40236 | AD72: 7.412508 | AE72: 7.426698 | AF72: 7.442851 | AG72: 7.459049 | AH72: 0.000166
A73: TKI000:ea_CommercialLig | B73: Commercial Light Trucks 1/ | C73: 0.417402 | D73: 0.429752 | E73: 0.4361 | F73: 0.438805 | G73: 0.442896 | H73: 0.448514 | I73: 0.451192 | J73: 0.451773 | K73: 0.452056 | L73: 0.451855 | M73: 0.452067 | N73: 0.452658 | O73: 0.454179 | P73: 0.456158 | Q73: 0.459232 | R73: 0.463664 | S73: 0.46811 | T73: 0.472552 | U73: 0.477285 | V73: 0.48244 | W73: 0.487753 | X73: 0.493671 | Y73: 0.499459 | Z73: 0.505901 | AA73: 0.511755 | AB73: 0.517801 | AC73: 0.524376 | AD73: 0.529585 | AE73: 0.535473 | AF73: 0.542111 | AG73: 0.549078 | AH73: 0.009181
A74: TKI000:ea_BusTransporta | B74: Bus Transportation | C74: 0.059765 | D74: 0.07508 | E74: 0.08616 | F74: 0.094233 | G74: 0.100171 | H74: 0.104438 | I74: 0.107584 | J74: 0.109979 | K74: 0.111142 | L74: 0.111985 | M74: 0.112868 | N74: 0.113118 | O74: 0.113448 | P74: 0.113605 | Q74: 0.113716 | R74: 0.11353 | S74: 0.113436 | T74: 0.113336 | U74: 0.113171 | V74: 0.112886 | W74: 0.112663 | X74: 0.112337 | Y74: 0.11198 | Z74: 0.11162 | AA74: 0.111264 | AB74: 0.110882 | AC74: 0.110487 | AD74: 0.110127 | AE74: 0.109734 | AF74: 0.109462 | AG74: 0.109221 | AH74: 0.020302
A75: TKI000:ea_FreightTrucks | B75: Freight Trucks | C75: 2.511301 | D75: 2.562341 | E75: 2.62972 | F75: 2.651934 | G75: 2.678503 | H75: 2.701084 | I75: 2.699315 | J75: 2.684517 | K75: 2.668267 | L75: 2.648567 | M75: 2.632661 | N75: 2.618124 | O75: 2.60683 | P75: 2.594657 | Q75: 2.591201 | R75: 2.599064 | S75: 2.606463 | T75: 2.614655 | U75: 2.627334 | V75: 2.643946 | W75: 2.65917 | X75: 2.680398 | Y75: 2.706399 | Z75: 2.73978 | AA75: 2.767942 | AB75: 2.797641 | AC75: 2.822753 | AD75: 2.846913 | AE75: 2.875512 | AF75: 2.906283 | AG75: 2.940435 | AH75: 0.005272
A76: TKI000:ea_Rail,Passenge | B76: Rail, Passenger | C76: 0.013936 | D76: 0.016692 | E76: 0.018912 | F76: 0.02059 | G76: 0.021857 | H76: 0.022807 | I76: 0.023493 | J76: 0.024005 | K76: 0.024148 | L76: 0.024265 | M76: 0.024503 | N76: 0.02463 | O76: 0.024893 | P76: 0.025147 | Q76: 0.025457 | R76: 0.025725 | S76: 0.026019 | T76: 0.026302 | U76: 0.026582 | V76: 0.026871 | W76: 0.027246 | X76: 0.027589 | Y76: 0.027926 | Z76: 0.028273 | AA76: 0.028608 | AB76: 0.028976 | AC76: 0.029316 | AD76: 0.029622 | AE76: 0.029951 | AF76: 0.030311 | AG76: 0.030663 | AH76: 0.026634
A77: TKI000:ea_Rail,Freight | B77: Rail, Freight | C77: 0.2052 | D77: 0.216413 | E77: 0.217179 | F77: 0.215971 | G77: 0.214533 | H77: 0.206519 | I77: 0.207688 | J77: 0.206239 | K77: 0.20741 | L77: 0.208304 | M77: 0.209237 | N77: 0.209471 | O77: 0.2094 | P77: 0.209744 | Q77: 0.209412 | R77: 0.20981 | S77: 0.210093 | T77: 0.210129 | U77: 0.209256 | V77: 0.209996 | W77: 0.209331 | X77: 0.209426 | Y77: 0.210104 | Z77: 0.211251 | AA77: 0.210315 | AB77: 0.210549 | AC77: 0.210321 | AD77: 0.210586 | AE77: 0.210842 | AF77: 0.21118 | AG77: 0.212342 | AH77: 0.001141
A78: TKI000:ea_Shipping,Dome | B78: Shipping, Domestic | C78: 0.036641 | D78: 0.037508 | E78: 0.037086 | F78: 0.03667 | G78: 0.03624 | H78: 0.035579 | I78: 0.034701 | J78: 0.033688 | K78: 0.032706 | L78: 0.031683 | M78: 0.030701 | N78: 0.030174 | O78: 0.029688 | P78: 0.029171 | Q78: 0.028723 | R78: 0.0283 | S78: 0.027854 | T78: 0.027376 | U78: 0.026879 | V78: 0.026447 | W78: 0.02595 | X78: 0.025747 | Y78: 0.025561 | Z78: 0.025448 | AA78: 0.025261 | AB78: 0.025081 | AC78: 0.024846 | AD78: 0.024618 | AE78: 0.024375 | AF78: 0.024158 | AG78: 0.023978 | AH78: -0.014035
A79: TKI000:ea_Shipping,Inte | B79: Shipping, International | C79: 0.390127 | D79: 0.399914 | E79: 0.434956 | F79: 0.441884 | G79: 0.422805 | H79: 0.424046 | I79: 0.428597 | J79: 0.420109 | K79: 0.420515 | L79: 0.417549 | M79: 0.418554 | N79: 0.425043 | O79: 0.419537 | P79: 0.41976 | Q79: 0.418936 | R79: 0.424556 | S79: 0.419202 | T79: 0.419055 | U79: 0.422916 | V79: 0.417875 | W79: 0.417271 | X79: 0.422074 | Y79: 0.416121 | Z79: 0.415873 | AA79: 0.413463 | AB79: 0.413624 | AC79: 0.412266 | AD79: 0.41146 | AE79: 0.411718 | AF79: 0.411262 | AG79: 0.410365 | AH79: 0.001687
A80: TKI000:ea_RecreationalB | B80: Recreational Boats | C80: 0.106203 | D80: 0.106628 | E80: 0.108291 | F80: 0.10927 | G80: 0.109676 | H80: 0.109872 | I80: 0.109505 | J80: 0.108728 | K80: 0.107827 | L80: 0.10685 | M80: 0.105917 | N80: 0.105118 | O80: 0.104561 | P80: 0.103983 | Q80: 0.103517 | R80: 0.103178 | S80: 0.102702 | T80: 0.102093 | U80: 0.101512 | V80: 0.101063 | W80: 0.100765 | X80: 0.100435 | Y80: 0.100065 | Z80: 0.099694 | AA80: 0.099248 | AB80: 0.098909 | AC80: 0.098502 | AD80: 0.097958 | AE80: 0.097569 | AF80: 0.097161 | AG80: 0.096743 | AH80: -0.003105
A81: TKI000:ea_Air | B81: Air | C81: 0.900305 | D81: 1.224288 | E81: 1.367005 | F81: 1.433183 | G81: 1.475928 | H81: 1.509005 | I81: 1.520615 | J81: 1.529019 | K81: 1.539247 | L81: 1.548459 | M81: 1.558426 | N81: 1.571105 | O81: 1.589755 | P81: 1.608117 | Q81: 1.628653 | R81: 1.652344 | S81: 1.671992 | T81: 1.688775 | U81: 1.706511 | V81: 1.726514 | W81: 1.75151 | X81: 1.77462 | Y81: 1.798373 | Z81: 1.820968 | AA81: 1.844373 | AB81: 1.869801 | AC81: 1.892966 | AD81: 1.910659 | AE81: 1.929632 | AF81: 1.946926 | AG81: 1.964514 | AH81: 0.02635
A82: TKI000:ea_MilitaryUse | B82: Military Use | C82: 0.257081 | D82: 0.261438 | E82: 0.261803 | F82: 0.255477 | G82: 0.251303 | H82: 0.251044 | I82: 0.250438 | J82: 0.25036 | K82: 0.251731 | L82: 0.251176 | M82: 0.250227 | N82: 0.250187 | O82: 0.250591 | P82: 0.251006 | Q82: 0.251428 | R82: 0.25185 | S82: 0.252288 | T82: 0.252742 | U82: 0.253204 | V82: 0.253666 | W82: 0.254136 | X82: 0.254607 | Y82: 0.255078 | Z82: 0.255554 | AA82: 0.256032 | AB82: 0.256496 | AC82: 0.25698 | AD82: 0.257459 | AE82: 0.257947 | AF82: 0.258428 | AG82: 0.258902 | AH82: 0.000235
A83: TKI000:ea_Lubricants | B83: Lubricants | C83: 0.057262 | D83: 0.05829 | E83: 0.058961 | F83: 0.059478 | G83: 0.059828 | H83: 0.06001 | I83: 0.060088 | J83: 0.059921 | K83: 0.0598 | L83: 0.059697 | M83: 0.059553 | N83: 0.059424 | O83: 0.059322 | P83: 0.059235 | Q83: 0.059183 | R83: 0.059143 | S83: 0.059086 | T83: 0.059015 | U83: 0.058966 | V83: 0.058931 | W83: 0.058892 | X83: 0.058852 | Y83: 0.05882 | Z83: 0.058781 | AA83: 0.058773 | AB83: 0.058809 | AC83: 0.058817 | AD83: 0.058797 | AE83: 0.058808 | AF83: 0.058795 | AG83: 0.058756 | AH83: 0.000858
... A85: TKI000:ea_Total | B85: Total | C85: 12.710937 | D85: 13.523485 | E85: 13.782738 | F85: 13.893643 | G85: 13.946235 | H85: 13.993832 | I85: 13.969633 | J85: 13.917164 | K85: 13.870161 | L85: 13.804184 | M85: 13.743266 | N85: 13.694123 | O85: 13.650218 | P85: 13.62207 | Q85: 13.610144 | R85: 13.63513 | S85: 13.652452 | T85: 13.673915 | U85: 13.704461 | V85: 13.741007 | W85: 13.793367 | X85: 13.856253 | Y85: 13.918808 | Z85: 13.997322 | AA85: 14.066484 | AB85: 14.140247 | AC85: 14.209555 | AD85: 14.270186 | AE85: 14.335911 | AF85: 14.406158 | AG85: 14.484777 | AH85: 0.004364
B87: 1/ Commercial trucks 8,501 to 10,000 pounds gross vehicle weight rating.
B88: 2/ CAFE standard based on projected new vehicle sales.
B89: 3/ Includes CAFE credits for alternative fueled vehicle sales and credit banking.
B90: 4/ Environmental Protection Agency rated miles per gallon.
B91: 5/ Tested new vehicle efficiency revised for on-road performance.
B92: 6/ Combined "on-the-road" estimate for all cars and light trucks.
B93: CAFE = Corporate average fuel economy.
B94: Btu = British thermal unit.
B95: Note: Totals may not equal sum of components due to independent rounding.
B96: Sources: 2020: U.S. Energy Information Administration (EIA), Short-Term Energy Outlook, October 2020 and EIA,
B97: AEO2021 National Energy Modeling System run highogs.d120120a. Projections: EIA, AEO2021 National Energy Modeling System run highogs.d120120a.

Sheet AEO 2020 Table 7
B1: highogs.d112619a | C1: 2019 | D1: 2020 | E1: 2021 | F1: 2022 | G1: 2023 | H1: 2024 | I1: 2025 | J1: 2026 | K1: 2027 | L1: 2028 | M1: 2029 | N1: 2030 | O1: 2031 | P1: 2032 | Q1: 2033 | R1: 2034 | S1: 2035 | T1: 2036 | U1: 2037 | V1: 2038 | W1: 2039 | X1: 2040 | Y1: 2041 | Z1: 2042 | AA1: 2043 | AB1: 2044 | AC1: 2045 | AD1: 2046 | AE1: 2047 | AF1: 2048 | AG1: 2049 | AH1: 2050
C3: Report | D3: Annual Energy Outlook 2020
C4: Scenario | D4: highogs | G4: High oil and gas supply
C5: Datekey | D5: d112619a
C6: Release Date | E6: January 2020
A10: TKI000 | B10: 7. Transportation Sector Key Indicators and Delivered Energy Consumption
AI12: 2019-
B13: Key Indicators and Consumption | C13: 2019 | D13: 2020 | E13: 2021 | F13: 2022 | G13: 2023 | H13: 2024 | I13: 2025 | J13: 2026 | K13: 2027 | L13: 2028 | M13: 2029 | N13: 2030 | O13: 2031 | P13: 2032 | Q13: 2033 | R13: 2034 | S13: 2035 | T13: 2036 | U13: 2037 | V13: 2038 | W13: 2039 | X13: 2040 | Y13: 2041 | Z13: 2042 | AA13: 2043 | AB13: 2044 | AC13: 2045 | AD13: 2046 | AE13: 2047 | AF13: 2048 | AG13: 2049 | AH13: 2050 | AI13: 2050
B15: Key Indicators
B16: Travel Indicators
B17: (billion vehicle miles traveled)
A18: TKI000:ba_Light-DutyVeh | B18: Light-Duty Vehicles less than 8,501 pounds | C18: 2917.2534 | D18: 2975.1255 | E18: 3025.3584 | F18: 3062.7468 | G18: 3083.9775 | H18: 3096.5911 | I18: 3105.9812 | J18: 3125.592 | K18: 3146.8806 | L18: 3167.6331 | M18: 3188.2371 | N18: 3209.8457 | O18: 3233.3459 | P18: 3252.6282 | Q18: 3271.1394 | R18: 3285.1404 | S18: 3295.6909 | T18: 3311.9399 | U18: 3327.9958 | V18: 3344.2627 | W18: 3361.5449 | X18: 3379.7544 | Y18: 3396.2571 | Z18: 3413.8406 | AA18: 3432.0298 | AB18: 3451.1577 | AC18: 3472.0923 | AD18: 3496.9058 | AE18: 3524.3184 | AF18: 3555.4368 | AG18: 3588.8325 | AH18: 3624.4036 | AI18: 0.007026
A19: TKI000:ba_CommercialLig | B19: Commercial Light Trucks 1/ | C19: 99.321114 | D19: 100.61537 | E19: 102.27555 | F19: 103.79449 | G19: 104.99791 | H19: 105.84502 | I19: 106.78965 | J19: 107.83586 | K19: 109.08619 | L19: 110.31479 | M19: 111.61692 | N19: 112.77087 | O19: 114.26243 | P19: 115.52301 | Q19: 116.87927 | R19: 118.14617 | S19: 119.40303 | T19: 120.80527 | U19: 122.15245 | V19: 123.49687 | W19: 124.85643 | X19: 126.2754 | Y19: 127.71654 | Z19: 129.18462 | AA19: 130.707 | AB19: 132.37408 | AC19: 134.19019 | AD19: 136.27534 | AE19: 138.1423 | AF19: 140.20346 | AG19: 142.3405 | AH19: 144.47952 | AI19: 0.012163
A20: TKI000:ba_FreightTrucks | B20: Freight Trucks greater than 10,000 pounds | C20: 299.98956 | D20: 302.9967 | E20: 307.86118 | F20: 312.26749 | G20: 316.85519 | H20: 319.63693 | I20: 322.73798 | J20: 325.80005 | K20: 329.40594 | L20: 332.56686 | M20: 335.87531 | N20: 338.36066 | O20: 342.56183 | P20: 345.99631 | Q20: 349.88959 | R20: 353.1503 | S20: 356.89838 | T20: 360.95453 | U20: 364.40631 | V20: 367.98541 | W20: 371.4613 | X20: 375.17526 | Y20: 378.96576 | Z20: 382.97611 | AA20: 386.86951 | AB20: 391.47946 | AC20: 396.5683 | AD20: 402.70737 | AE20: 407.39862 | AF20: 413.09305 | AG20: 419.04983 | AH20: 425.07648 | AI20: 0.011306
B21: (billion passenger miles traveled)
A22: TKI000:buspassmiles | B22: Bus Transportation | C22: 210.1385 | D22: 211.1262 | E22: 212.11616 | F22: 213.08595 | G22: 214.01353 | H22: 214.96095 | I22: 215.98413 | J22: 216.98978 | K22: 217.98006 | L22: 218.98109 | M22: 219.96805 | N22: 220.90674 | O22: 221.80705 | P22: 222.67883 | Q22: 223.45596 | R22: 224.19052 | S22: 224.88495 | T22: 225.5426 | U22: 226.16771 | V22: 226.76289 | W22: 227.33022 | X22: 227.87238 | Y22: 228.39172 | Z22: 228.89146 | AA22: 229.37672 | AB22: 229.85208 | AC22: 230.32323 | AD22: 230.79691 | AE22: 231.28061 | AF22: 231.78067 | AG22: 232.30583 | AH22: 232.85057 | AI22: 0.003316
A23: TKI000:railpassmiles | B23: Passenger Rail | C23: 41.270718 | D23: 41.874931 | E23: 42.455513 | F23: 42.941441 | G23: 43.403492 | H23: 43.866783 | I23: 44.310471 | J23: 44.75193 | K23: 45.177658 | L23: 45.617382 | M23: 46.05724 | N23: 46.402245 | O23: 46.841446 | P23: 47.267838 | Q23: 47.680485 | R23: 48.055225 | S23: 48.435219 | T23: 48.803921 | U23: 49.166313 | V23: 49.530781 | W23: 49.890511 | X23: 50.244217 | Y23: 50.573273 | Z23: 50.897018 | AA23: 51.222713 | AB23: 51.549355 | AC23: 51.873222 | AD23: 52.227497 | AE23: 52.585468 | AF23: 52.972961 | AG23: 53.355492 | AH23: 53.757782 | AI23: 0.008563
B24: (billion seat miles available)
A25: TKI000:ba_Air | B25: Air | C25: 1222.9934 | D25: 1245.385 | E25: 1270.2579 | F25: 1290.4578 | G25: 1307.1332 | H25: 1325.8835 | I25: 1346.3998 | J25: 1366.3947 | K25: 1386.9773 | L25: 1409.3759 | M25: 1434.0159 | N25: 1459.4762 | O25: 1485.5172 | P25: 1512.3081 | Q25: 1538.871 | R25: 1563.6233 | S25: 1587.829 | T25: 1613.7333 | U25: 1640.1089 | V25: 1667.4398 | W25: 1695.8134 | X25: 1724.8636 | Y25: 1752.9756 | Z25: 1781.3413 | AA25: 1810.3131 | AB25: 1840.631 | AC25: 1874.0067 | AD25: 1909.9596 | AE25: 1947.4512 | AF25: 1987.4026 | AG25: 2028.574 | AH25: 2071.0894 | AI25: 0.017138
B26: (billion ton miles traveled)
A27: TKI000:ba_Rail | B27: Rail | C27: 1807.9623 | D27: 1730.8405 | E27: 1660.0334 | F27: 1651.2594 | G27: 1652.7242 | H27: 1638.4692 | I27: 1604.7769 | J27: 1643.9995 | K27: 1652.7871 | L27: 1662.7437 | M27: 1655.604 | N27: 1648.3021 | O27: 1654.8008 | P27: 1663.8508 | Q27: 1673.921 | R27: 1684.4979 | S27: 1686.808 | T27: 1698.2738 | U27: 1704.6904 | V27: 1701.2555 | W27: 1711.9681 | X27: 1715.1283 | Y27: 1722.2583 | Z27: 1735.2404 | AA27: 1747.2886 | AB27: 1760.9611 | AC27: 1777.2797 | AD27: 1802.0692 | AE27: 1818.0815 | AF27: 1839.249 | AG27: 1861.9969 | AH27: 1888.5421 | AI27: 0.001408
A28: TKI000:ba_DomesticShipp | B28: Domestic Shipping | C28: 416.68076 | D28: 409.15491 | E28: 404.52988 | F28: 396.47797 | G28: 388.98981 | H28: 379.45697 | I28: 370.07324 | J28: 361.44611 | K28: 352.76407 | L28: 343.56067 | M28: 333.81879 | N28: 323.79498 | O28: 320.25205 | P28: 316.14533 | Q28: 312.6521 | R28: 308.38547 | S28: 304.23715 | T28: 300.63773 | U28: 296.55325 | V28: 292.41882 | W28: 288.76395 | X28: 284.95685 | Y28: 283.66168 | Z28: 282.64859 | AA28: 281.33289 | AB28: 280.51184 | AC28: 279.8728 | AD28: 280.18787 | AE28: 279.40164 | AF28: 279.35028 | AG28: 279.69217 | AH28: 280.25092 | AI28: -0.012713
B30: Energy Efficiency Indicators
B31: (miles per gallon)
A32: TKI000:ca_AvgCAFEStand | B32: New Light-Duty Vehicle CAFE Standard 2/ | C32: 34.359936 | D32: 35.284824 | E32: 36.831001 | F32: 38.399506 | G32: 40.110416 | H32: 41.695168 | I32: 43.801582 | J32: 43.785816 | K32: 43.851311 | L32: 43.92421 | M32: 44.014652 | N32: 44.196796 | O32: 44.303349 | P32: 44.390171 | Q32: 44.493732 | R32: 44.60854 | S32: 44.698715 | T32: 44.789574 | U32: 44.882374 | V32: 44.963428 | W32: 45.039089 | X32: 45.11404 | Y32: 45.19231 | Z32: 45.25729 | AA32: 45.303879 | AB32: 45.340485 | AC32: 45.390274 | AD32: 45.422104 | AE32: 45.456978 | AF32: 45.47982 | AG32: 45.506924 | AH32: 45.514236 | AI32: 0.00911
A33: TKI000:ca_CarCAFEStand | B33: New Car 2/ | C33: 40.551155 | D33: 42.338371 | E33: 44.294533 | F33: 46.414017 | G33: 48.711933 | H33: 50.082985 | I33: 52.773457 | J33: 52.773731 | K33: 52.786339 | L33: 52.786339 | M33: 52.798622 | N33: 52.841564 | O33: 52.841564 | P33: 52.841564 | Q33: 52.841564 | R33: 52.841564 | S33: 52.841564 | T33: 52.841564 | U33: 52.841564 | V33: 52.841564 | W33: 52.841564 | X33: 52.842728 | Y33: 52.844788 | Z33: 52.844788 | AA33: 52.844788 | AB33: 52.844788 | AC33: 52.84753 | AD33: 52.84753 | AE33: 52.848724 | AF33: 52.848724 | AG33: 52.84988 | AH33: 52.84988 | AI33: 0.008582
A34: TKI000:ca_TwukCAFEStand | B34: New Light Truck 2/ | C34: 30.2997 | D34: 30.889185 | E34: 32.380001 | F34: 33.7799 | G34: 35.309071 | H34: 36.976479 | I34: 38.765255 | J34: 38.772991 | K34: 38.772991 | L34: 38.772991 | M34: 38.772991 | N34: 38.772991 | O34: 38.772991 | P34: 38.772991 | Q34: 38.772991 | R34: 38.772991 | S34: 38.772991 | T34: 38.772991 | U34: 38.772991 | V34: 38.772991 | W34: 38.772991 | X34: 38.772991 | Y34: 38.772991 | Z34: 38.772991 | AA34: 38.772991 | AB34: 38.772991 | AC34: 38.772991 | AD34: 38.772991 | AE34: 38.772991 | AF34: 38.772991 | AG34: 38.772991 | AH34: 38.773014 | AI34: 0.007986
A35: TKI000:ca_NewVehCred | B35: Compliance New Light-Duty Vehicle 3/ | C35: 35.348213 | D35: 36.238525 | E35: 37.596539 | F35: 39.37933 | G35: 40.901978 | H35: 42.360344 | I35: 44.567291 | J35: 44.831284 | K35: 44.934002 | L35: 45.040806 | M35: 45.183762 | N35: 45.495754 | O35: 45.787571 | P35: 46.034676 | Q35: 46.317448 | R35: 46.60257 | S35: 46.849384 | T35: 47.060444 | U35: 47.280041 | V35: 47.481697 | W35: 47.659729 | X35: 47.83065 | Y35: 47.980515 | Z35: 48.108444 | AA35: 48.197189 | AB35: 48.262737 | AC35: 48.3549 | AD35: 48.425739 | AE35: 48.504185 | AF35: 48.562855 | AG35: 48.634819 | AH35: 48.674248 | AI35: 0.010373
A36: TKI000:ca_NewCarCred | B36: New Car 3/ | C36: 42.356316 | D36: 43.482601 | E36: 45.545635 | F36: 47.835651 | G36: 49.962463 | H36: 51.477432 | I36: 54.131187 | J36: 54.288181 | K36: 54.274036 | L36: 54.345482 | M36: 54.476521 | N36: 54.755726 | O36: 55.19865 | P36: 55.546597 | Q36: 55.91061 | R36: 56.268238 | S36: 56.616009 | T36: 56.875309 | U36: 57.153564 | V36: 57.42186 | W36: 57.643833 | X36: 57.841148 | Y36: 57.984364 | Z36: 58.118862 | AA36: 58.223202 | AB36: 58.303883 | AC36: 58.397022 | AD36: 58.51268 | AE36: 58.621887 | AF36: 58.738182 | AG36: 58.859608 | AH36: 58.987617 | AI36: 0.010741
A37: TKI000:ca_NewTwukCred | B37: New Light Truck 3/ | C37: 30.865908 | D37: 31.724129 | E37: 32.910633 | F37: 34.543072 | G37: 35.889904 | H37: 37.32349 | I37: 39.26572 | J37: 39.595291 | K37: 39.653728 | L37: 39.666462 | M37: 39.683132 | N37: 39.748066 | O37: 39.797894 | P37: 39.852974 | Q37: 39.920296 | R37: 39.970135 | S37: 40.005047 | T37: 40.02647 | U37: 40.043442 | V37: 40.056137 | W37: 40.064693 | X37: 40.075218 | Y37: 40.075615 | Z37: 40.069695 | AA37: 40.055481 | AB37: 40.038029 | AC37: 40.029408 | AD37: 40.008018 | AE37: 39.996075 | AF37: 39.972542 | AG37: 39.958122 | AH37: 39.929474 | AI37: 0.00834
A38: TKI000:ca_TestedNewVeh | B38: Tested New Light-Duty Vehicle 4/ | C38: 34.962322 | D38: 35.991081 | E38: 37.288235 | F38: 39.051094 | G38: 40.553646 | H38: 41.976017 | I38: 44.120575 | J38: 44.336227 | K38: 44.414066 | L38: 44.500385 | M38: 44.615799 | N38: 44.876507 | O38: 45.111603 | P38: 45.306648 | Q38: 45.531082 | R38: 45.75457 | S38: 45.942371 | T38: 46.09964 | U38: 46.263412 | V38: 46.41185 | W38: 46.541386 | X38: 46.666012 | Y38: 46.777721 | Z38: 46.871037 | AA38: 46.931049 | AB38: 46.971848 | AC38: 47.034363 | AD38: 47.077263 | AE38: 47.126358 | AF38: 47.158012 | AG38: 47.200371 | AH38: 47.214767 | AI38: 0.009739
A39: TKI000:ca_TestedNewCar | B39: New Car 4/ | C39: 41.715885 | D39: 42.872379 | E39: 44.733494 | F39: 46.957069 | G39: 49.003487 | H39: 50.41568 | I39: 52.908669 | J39: 53.035347 | K39: 53.002815 | L39: 53.031281 | M39: 53.101597 | N39: 53.283951 | O39: 53.59354 | P39: 53.82737 | Q39: 54.068119 | R39: 54.300163 | S39: 54.521736 | T39: 54.675041 | U39: 54.843937 | V39: 55.006741 | W39: 55.136219 | X39: 55.248566 | Y39: 55.326115 | Z39: 55.397579 | AA39: 55.445976 | AB39: 55.477283 | AC39: 55.516716 | AD39: 55.571735 | AE39: 55.621513 | AF39: 55.67548 | AG39: 55.732971 | AH39: 55.794552 | AI39: 0.009425
A40: TKI000:ca_TestedNewTwuk | B40: New Light Truck 4/ | C40: 30.612513 | D40: 31.651661 | E40: 32.830524 | F40: 34.456524 | G40: 35.799854 | H40: 37.22747 | I40: 39.151051 | J40: 39.426971 | K40: 39.465645 | L40: 39.475208 | M40: 39.488102 | N40: 39.541683 | O40: 39.581787 | P40: 39.624954 | Q40: 39.679688 | R40: 39.716709 | S40: 39.740402 | T40: 39.750675 | U40: 39.756599 | V40: 39.759041 | W40: 39.758137 | X40: 39.759655 | Y40: 39.75499 | Z40: 39.745636 | AA40: 39.729229 | AB40: 39.710049 | AC40: 39.698334 | AD40: 39.675388 | AE40: 39.66048 | AF40: 39.635681 | AG40: 39.61845 | AH40: 39.589142 | AI40: 0.00833
A41: TKI000:ca_OnRoadNewVeh | B41: On-Road New Light-Duty Vehicle 5/ | C41: 28.524006 | D41: 29.363092 | E41: 30.420794 | F41: 31.858644 | G41: 33.084072 | H41: 34.244457 | I41: 35.994076 | J41: 36.169979 | K41: 36.233746 | L41: 36.304462 | M41: 36.398952 | N41: 36.612297 | O41: 36.804462 | P41: 36.963898 | Q41: 37.147385 | R41: 37.330143 | S41: 37.483685 | T41: 37.612339 | U41: 37.7463 | V41: 37.867699 | W41: 37.973671 | X41: 38.075638 | Y41: 38.16708 | Z41: 38.243473 | AA41: 38.292618 | AB41: 38.326035 | AC41: 38.377235 | AD41: 38.412346 | AE41: 38.45253 | AF41: 38.478436 | AG41: 38.513092 | AH41: 38.524834 | AI41: 0.009742
A42: TKI000:ca_OnRoadNewCar | B42: New Car 5/ | C42: 34.065807 | D42: 35.010216 | E42: 36.530029 | F42: 38.345837 | G42: 40.016972 | H42: 41.170189 | I42: 43.205997 | J42: 43.309448 | K42: 43.282879 | L42: 43.306126 | M42: 43.363548 | N42: 43.512459 | O42: 43.765274 | P42: 43.956223 | Q42: 44.152824 | R42: 44.342316 | S42: 44.523254 | T42: 44.648445 | U42: 44.786369 | V42: 44.919315 | W42: 45.025051 | X42: 45.116795 | Y42: 45.180122 | Z42: 45.23848 | AA42: 45.278004 | AB42: 45.303566 | AC42: 45.33577 | AD42: 45.380699 | AE42: 45.421349 | AF42: 45.46542 | AG42: 45.512367 | AH42: 45.562653 | AI42: 0.009425
A43: TKI000:ca_OnRoadNewTwuk | B43: New Light Truck 5/ | C43: 24.960157 | D43: 25.807436 | E43: 26.768633 | F43: 28.094404 | G43: 29.189699 | H43: 30.353718 | I43: 31.922125 | J43: 32.147099 | K43: 32.178631 | L43: 32.186428 | M43: 32.196941 | N43: 32.240631 | O43: 32.273327 | P43: 32.308525 | Q43: 32.353153 | R43: 32.383339 | S43: 32.402657 | T43: 32.411034 | U43: 32.415863 | V43: 32.417854 | W43: 32.417118 | X43: 32.418354 | Y43: 32.414551 | Z43: 32.406925 | AA43: 32.393547 | AB43: 32.377907 | AC43: 32.368355 | AD43: 32.349648 | AE43: 32.33749 | AF43: 32.317272 | AG43: 32.303223 | AH43: 32.279324 | AI43: 0.00833
... A47: TKI000:ca_FreightTruck | B47: Freight Truck | C47: 7.119165 | D47: 7.17094 | E47: 7.235986 | F47: 7.3073 | G47: 7.388516 | H47: 7.48128 | I47: 7.586367 | J47: 7.703835 | K47: 7.834221 | L47: 7.967885 | M47: 8.108215 | N47: 8.251791 | O47: 8.396469 | P47: 8.537745 | Q47: 8.669586 | R47: 8.791187 | S47: 8.902438 | T47: 9.004374 | U47: 9.096915 | V47: 9.181 | W47: 9.258368 | X47: 9.327685 | Y47: 9.391495 | Z47: 9.448672 | AA47: 9.500283 | AB47: 9.547491 | AC47: 9.591628 | AD47: 9.634123 | AE47: 9.675597 | AF47: 9.716289 | AG47: 9.756433 | AH47: 9.797481 | AI47: 0.010354
B48: (seat miles per gallon)
A49: TKI000:ca_Aircraft | B49: Aircraft | C49: 69.061409 | D49: 69.384445 | E49: 69.706734 | F49: 70.035477 | G49: 70.376755 | H49: 70.734436 | I49: 71.082642 | J49: 71.464615 | K49: 71.895363 | L49: 72.350365 | M49: 72.824806 | N49: 73.293343 | O49: 73.757736 | P49: 74.234024 | Q49: 74.700493 | R49: 75.177055 | S49: 75.653641 | T49: 76.137352 | U49: 76.621902 | V49: 77.107964 | W49: 77.601532 | X49: 78.09996 | Y49: 78.56591 | Z49: 79.031158 | AA49: 79.489037 | AB49: 79.918777 | AC49: 80.345123 | AD49: 80.761703 | AE49: 81.17762 | AF49: 81.591446 | AG49: 81.990547 | AH49: 82.372414 | AI49: 0.005702
B50: (ton miles/thousand Btu)
A51: TKI000:ca_Rail | B51: Rail | C51: 3.466884 | D51: 3.489371 | E51: 3.512003 | F51: 3.534782 | G51: 3.55771 | H51: 3.580785 | I51: 3.60401 | J51: 3.627386 | K51: 3.650914 | L51: 3.674594 | M51: 3.698428 | N51: 3.722416 | O51: 3.74656 | P51: 3.77086 | Q51: 3.795318 | R51: 3.819935 | S51: 3.844712 | T51: 3.869649 | U51: 3.894748 | V51: 3.920009 | W51: 3.945435 | X51: 3.971025 | Y51: 3.996782 | Z51: 4.022705 | AA51: 4.048797 | AB51: 4.075058 | AC51: 4.101489 | AD51: 4.128091 | AE51: 4.154866 | AF51: 4.181815 | AG51: 4.208939 | AH51: 4.236238 | AI51: 0.006486
A52: TKI000:ca_DomesticShipp | B52: Domestic Shipping | C52: 4.813365 | D52: 4.84196 | E52: 4.870726 | F52: 4.899663 | G52: 4.928772 | H52: 4.958054 | I52: 4.987509 | J52: 5.01714 | K52: 5.046947 | L52: 5.076931 | M52: 5.107092 | N52: 5.137434 | O52: 5.167955 | P52: 5.198658 | Q52: 5.229543 | R52: 5.260611 | S52: 5.291864 | T52: 5.323303 | U52: 5.354929 | V52: 5.386742 | W52: 5.418745 | X52: 5.450938 | Y52: 5.483322 | Z52: 5.515898 | AA52: 5.548667 | AB52: 5.581632 | AC52: 5.614792 | AD52: 5.64815 | AE52: 5.681705 | AF52: 5.71546 | AG52: 5.749416 | AH52: 5.783573 | AI52: 0.005941
B54: Energy Use by Mode
B55: (quadrillion Btu)
A56: TKI000:da_Light-DutyVeh | B56: Light-Duty Vehicles | C56: 15.312445 | D56: 15.30714 | E56: 15.236718 | F56: 15.068806 | G56: 14.804813 | H56: 14.499307 | I56: 14.167157 | J56: 13.909196 | K56: 13.685458 | L56: 13.482776 | M56: 13.299863 | N56: 13.139069 | O56: 13.002687 | P56: 12.863337 | Q56: 12.735183 | R56: 12.602709 | S56: 12.470579 | T56: 12.372916 | U56: 12.287333 | V56: 12.215109 | W56: 12.15875 | X56: 12.118073 | Y56: 12.081137 | Z56: 12.057517 | AA56: 12.045367 | AB56: 12.044356 | AC56: 12.055041 | AD56: 12.085419 | AE56: 12.129275 | AF56: 12.190246 | AG56: 12.262823 | AH56: 12.346762 | AI56: -0.00692
A57: TKI000:da_CommercialLig | B57: Commercial Light Trucks 1/ | C57: 0.891028 | D57: 0.891903 | E57: 0.895889 | F57: 0.89787 | G57: 0.89709 | H57: 0.89318 | I57: 0.892636 | J57: 0.892015 | K57: 0.892606 | L57: 0.893648 | M57: 0.895486 | N57: 0.896713 | O57: 0.901317 | P57: 0.904846 | Q57: 0.909857 | R57: 0.914968 | S57: 0.920246 | T57: 0.927079 | U57: 0.934283 | V57: 0.94158 | W57: 0.949261 | X57: 0.957789 | Y57: 0.966845 | Z57: 0.975906 | AA57: 0.98611 | AB57: 0.997791 | AC57: 1.010687 | AD57: 1.027074 | AE57: 1.040264 | AF57: 1.054572 | AG57: 1.069246 | AH57: 1.083799 | AI57: 0.006338
A58: TKI000:da_BusTransporta | B58: Bus Transportation | C58: 0.238531 | D58: 0.23989 | E58: 0.241259 | F58: 0.242609 | G58: 0.243913 | H58: 0.245252 | I58: 0.246684 | J58: 0.248104 | K58: 0.249516 | L58: 0.250953 | M58: 0.252383 | N58: 0.253717 | O58: 0.25501 | P58: 0.256269 | Q58: 0.257406 | R58: 0.258486 | S58: 0.259508 | T58: 0.26047 | U58: 0.261377 | V58: 0.262223 | W58: 0.263003 | X58: 0.263714 | Y58: 0.264353 | Z58: 0.264925 | AA58: 0.265439 | AB58: 0.265904 | AC58: 0.266333 | AD58: 0.266748 | AE58: 0.267177 | AF58: 0.267648 | AG58: 0.268208 | AH58: 0.268877 | AI58: 0.00387
A59: TKI000:da_FreightTrucks | B59: Freight Trucks | C59: 5.880958 | D59: 5.904005 | E59: 5.951757 | F59: 5.983958 | G59: 6.010647 | H59: 5.993482 | I59: 5.972905 | J59: 5.942755 | K59: 5.913831 | L59: 5.875737 | M59: 5.836956 | N59: 5.783237 | O59: 5.760028 | P59: 5.727354 | Q59: 5.709549 | R59: 5.688765 | S59: 5.682989 | T59: 5.688041 | U59: 5.689445 | V59: 5.697817 | W59: 5.709255 | X59: 5.729411 | Y59: 5.754163 | Z59: 5.786846 | AA59: 5.821076 | AB59: 5.869198 | AC59: 5.927293 | AD59: 6.001935 | AE59: 6.05612 | AF59: 6.125846 | AG59: 6.200032 | AH59: 6.275017 | AI59: 0.002094
A60: TKI000:da_Rail,Passenge | B60: Rail, Passenger | C60: 0.049125 | D60: 0.050002 | E60: 0.050829 | F60: 0.051513 | G60: 0.052173 | H60: 0.05283 | I60: 0.053461 | J60: 0.054088 | K60: 0.054688 | L60: 0.055315 | M60: 0.05594 | N60: 0.056411 | O60: 0.057057 | P60: 0.057683 | Q60: 0.058288 | R60: 0.058841 | S60: 0.059417 | T60: 0.059977 | U60: 0.060532 | V60: 0.061099 | W60: 0.061667 | X60: 0.062234 | Y60: 0.062772 | Z60: 0.063311 | AA60: 0.063864 | AB60: 0.064422 | AC60: 0.064971 | AD60: 0.065568 | AE60: 0.066151 | AF60: 0.066765 | AG60: 0.067348 | AH60: 0.067945 | AI60: 0.010517
A61: TKI000:da_Rail,Freight | B61: Rail, Freight | C61: 0.521495 | D61: 0.496032 | E61: 0.472674 | F61: 0.467146 | G61: 0.464547 | H61: 0.457573 | I61: 0.445275 | J61: 0.453219 | K61: 0.452705 | L61: 0.452497 | M61: 0.447651 | N61: 0.442804 | O61: 0.441685 | P61: 0.441239 | Q61: 0.441049 | R61: 0.440976 | S61: 0.438735 | T61: 0.43887 | U61: 0.43769 | V61: 0.433993 | W61: 0.433911 | X61: 0.431911 | Y61: 0.430911 | Z61: 0.431362 | AA61: 0.431558 | AB61: 0.432132 | AC61: 0.433326 | AD61: 0.436538 | AE61: 0.437579 | AF61: 0.439821 | AG61: 0.442391 | AH61: 0.445806 | AI61: -0.005046
A62: TKI000:da_Shipping,Dome | B62: Shipping, Domestic | C62: 0.089409 | D62: 0.087947 | E62: 0.085825 | F62: 0.083144 | G62: 0.081043 | H62: 0.07854 | I62: 0.076103 | J62: 0.073851 | K62: 0.071606 | L62: 0.069278 | M62: 0.066865 | N62: 0.064421 | O62: 0.063281 | P62: 0.062044 | Q62: 0.060933 | R62: 0.059681 | S62: 0.058471 | T62: 0.057385 | U62: 0.056209 | V62: 0.055025 | W62: 0.053933 | X62: 0.052831 | Y62: 0.052283 | Z62: 0.051792 | AA62: 0.051248 | AB62: 0.050799 | AC62: 0.050387 | AD62: 0.050149 | AE62: 0.049715 | AF62: 0.049415 | AG62: 0.049187 | AH62: 0.048997 | AI62: -0.019215
A63: TKI000:da_Shipping,Inte | B63: Shipping, International | C63: 0.927327 | D63: 1.008838 | E63: 0.971116 | F63: 0.886972 | G63: 0.891949 | H63: 0.875923 | I63: 0.889297 | J63: 0.864365 | K63: 0.875667 | L63: 0.876735 | M63: 0.862752 | N63: 0.876611 | O63: 0.877461 | P63: 0.865944 | Q63: 0.876064 | R63: 0.876109 | S63: 0.872912 | T63: 0.862727 | U63: 0.869371 | V63: 0.858956 | W63: 0.858436 | X63: 0.864699 | Y63: 0.853751 | Z63: 0.852309 | AA63: 0.849807 | AB63: 0.846604 | AC63: 0.844515 | AD63: 0.843746 | AE63: 0.841557 | AF63: 0.840549 | AG63: 0.839989 | AH63: 0.840091 | AI63: -0.003182
A64: TKI000:da_RecreationalB | B64: Recreational Boats | C64: 0.245487 | D64: 0.246247 | E64: 0.246891 | F64: 0.247228 | G64: 0.247401 | H64: 0.247561 | I64: 0.247747 | J64: 0.247872 | K64: 0.247948 | L64: 0.248034 | M64: 0.248119 | N64: 0.248128 | O64: 0.248119 | P64: 0.248079 | Q64: 0.247943 | R64: 0.247704 | S64: 0.247382 | T64: 0.247051 | U64: 0.246672 | V64: 0.246271 | W64: 0.245845 | X64: 0.245364 | Y64: 0.244837 | Z64: 0.244243 | AA64: 0.243636 | AB64: 0.243037 | AC64: 0.242467 | AD64: 0.241926 | AE64: 0.241387 | AF64: 0.240858 | AG64: 0.240316 | AH64: 0.23976 | AI64: -0.000761
A65: TKI000:da_Air | B65: Air | C65: 2.640944 | D65: 2.673067 | E65: 2.70635 | F65: 2.732191 | G65: 2.752433 | H65: 2.776094 | I65: 2.803131 | J65: 2.82868 | K65: 2.853517 | L65: 2.879811 | M65: 2.908522 | N65: 2.937199 | O65: 2.967398 | P65: 2.997719 | Q65: 3.0276 | R65: 3.053208 | S65: 3.077652 | T65: 3.104426 | U65: 3.132126 | V65: 3.160325 | W65: 3.189834 | X65: 3.220148 | Y65: 3.250173 | Z65: 3.279953 | AA65: 3.310731 | AB65: 3.34457 | AC65: 3.383125 | AD65: 3.426044 | AE65: 3.471181 | AF65: 3.520372 | AG65: 3.571743 | AH65: 3.624813 | AI65: 0.010267
A66: TKI000:da_MilitaryUse | B66: Military Use | C66: 0.512501 | D66: 0.526369 | E66: 0.515977 | F66: 0.504054 | G66: 0.488973 | H66: 0.47893 | I66: 0.47706 | J66: 0.475186 | K66: 0.474613 | L66: 0.477166 | M66: 0.476099 | N66: 0.47539 | O66: 0.475478 | P66: 0.475588 | Q66: 0.475726 | R66: 0.475885 | S66: 0.476065 | T66: 0.476268 | U66: 0.476499 | V66: 0.476747 | W66: 0.477015 | X66: 0.477302 | Y66: 0.4776 | Z66: 0.477913 | AA66: 0.478237 | AB66: 0.478571 | AC66: 0.478915 | AD66: 0.479268 | AE66: 0.479627 | AF66: 0.479993 | AG66: 0.480364 | AH66: 0.480741 | AI66: -0.002062
A67: TKI000:da_Lubricants | B67: Lubricants | C67: 0.131469 | D67: 0.130998 | E67: 0.130617 | F67: 0.130166 | G67: 0.129716 | H67: 0.129236 | I67: 0.128717 | J67: 0.12821 | K67: 0.127738 | L67: 0.127329 | M67: 0.126997 | N67: 0.126676 | O67: 0.126395 | P67: 0.126142 | Q67: 0.125896 | R67: 0.125704 | S67: 0.12555 | T67: 0.12549 | U67: 0.125464 | V67: 0.125469 | W67: 0.125512 | X67: 0.125529 | Y67: 0.125533 | Z67: 0.125612 | AA67: 0.125667 | AB67: 0.125765 | AC67: 0.12594 | AD67: 0.126144 | AE67: 0.126361 | AF67: 0.126627 | AG67: 0.126863 | AH67: 0.127078 | AI67: -0.001095
... A69: TKI000:da_Total | B69: Total | C69: 28.112638 | D69: 28.229656 | E69: 28.207281 | F69: 28.00946 | G69: 27.785589 | H69: 27.463036 | I69: 27.152018 | J69: 26.878296 | K69: 26.655809 | L69: 26.445753 | M69: 26.240934 | N69: 26.065762 | O69: 25.948496 | P69: 25.80217 | Q69: 25.701551 | R69: 25.580608 | S69: 25.470058 | T69: 25.412188 | U69: 25.37376 | V69: 25.339329 | W69: 25.342278 | X69: 25.372105 | Y69: 25.393759 | Z69: 25.455908 | AA69: 25.525803 | AB69: 25.624594 | AC69: 25.752531 | AD69: 25.930012 | AE69: 26.094328 | AF69: 26.300638 | AG69: 26.523647 | AH69: 26.762129 | AI69: -0.001587
B71: (million barrels per day oil equivalent)
A72: TKI000:ea_Light-DutyVeh | B72: Light-Duty Vehicles | C72: 8.299458 | D72: 8.297431 | E72: 8.258867 | F72: 8.167576 | G72: 8.024354 | H72: 7.858614 | I72: 7.680162 | J72: 7.54128 | K72: 7.420378 | L72: 7.311098 | M72: 7.21259 | N72: 7.126847 | O72: 7.05311 | P72: 6.977902 | Q72: 6.908753 | R72: 6.837132 | S72: 6.765776 | T72: 6.712733 | U72: 6.666179 | V72: 6.626825 | W72: 6.595639 | X72: 6.572973 | Y72: 6.552473 | Z72: 6.538953 | AA72: 6.532093 | AB72: 6.531311 | AC72: 6.536314 | AD72: 6.552357 | AE72: 6.575637 | AF72: 6.60852 | AG72: 6.647728 | AH72: 6.693235 | AI72: -0.006914
A73: TKI000:ea_CommercialLig | B73: Commercial Light Trucks 1/ | C73: 0.463645 | D73: 0.463938 | E73: 0.465786 | F73: 0.466659 | G73: 0.466108 | H73: 0.464014 | I73: 0.463842 | J73: 0.463561 | K73: 0.463877 | L73: 0.46449 | M73: 0.465553 | N73: 0.466452 | O73: 0.468995 | P73: 0.470979 | Q73: 0.473754 | R73: 0.476574 | S73: 0.479564 | T73: 0.483356 | U73: 0.487438 | V73: 0.491518 | W73: 0.495649 | X73: 0.500162 | Y73: 0.505092 | Z73: 0.509883 | AA73: 0.515413 | AB73: 0.521692 | AC73: 0.528346 | AD73: 0.53696 | AE73: 0.543866 | AF73: 0.551526 | AG73: 0.559404 | AH73: 0.567315 | AI73: 0.006531
A74: TKI000:ea_BusTransporta | B74: Bus Transportation | C74: 0.115227 | D74: 0.115901 | E74: 0.116581 | F74: 0.117251 | G74: 0.117882 | H74: 0.118551 | I74: 0.11926 | J74: 0.11995 | K74: 0.120641 | L74: 0.12134 | M74: 0.122028 | N74: 0.122645 | O74: 0.12329 | P74: 0.123892 | Q74: 0.124421 | R74: 0.124924 | S74: 0.125429 | T74: 0.125889 | U74: 0.126375 | V74: 0.126791 | W74: 0.127173 | X74: 0.127473 | Y74: 0.127798 | Z74: 0.128063 | AA74: 0.128311 | AB74: 0.128539 | AC74: 0.128753 | AD74: 0.128956 | AE74: 0.12916 | AF74: 0.129386 | AG74: 0.129657 | AH74: 0.129983 | AI74: 0.003895
A75: TKI000:ea_FreightTrucks | B75: Freight Trucks | C75: 2.827296 | D75: 2.838177 | E75: 2.861533 | F75: 2.877479 | G75: 2.89041 | H75: 2.883003 | I75: 2.873901 | J75: 2.859937 | K75: 2.846777 | L75: 2.829164 | M75: 2.811116 | N75: 2.785219 | O75: 2.775341 | P75: 2.760258 | Q75: 2.752032 | R75: 2.742399 | S75: 2.740685 | T75: 2.743816 | U75: 2.746544 | V75: 2.751515 | W75: 2.757982 | X75: 2.767448 | Y75: 2.780638 | Z75: 2.797015 | AA75: 2.814377 | AB75: 2.838605 | AC75: 2.867797 | AD75: 2.904866 | AE75: 2.931931 | AF75: 2.966593 | AG75: 3.003496 | AH75: 3.040895 | AI75: 0.002352
A76: TKI000:ea_Rail,Passenge | B76: Rail, Passenger | C76: 0.023255 | D76: 0.023671 | E76: 0.024065 | F76: 0.02439 | G76: 0.024703 | H76: 0.025016 | I76: 0.025317 | J76: 0.025614 | K76: 0.025899 | L76: 0.026196 | M76: 0.026491 | N76: 0.026709 | O76: 0.027018 | P76: 0.027313 | Q76: 0.027597 | R76: 0.027856 | S76: 0.02813 | T76: 0.028393 | U76: 0.028663 | V76: 0.028932 | W76: 0.029202 | X76: 0.029463 | Y76: 0.02972 | Z76: 0.029973 | AA76: 0.030235 | AB76: 0.030499 | AC76: 0.030761 | AD76: 0.031043 | AE76: 0.031319 | AF76: 0.031609 | AG76: 0.031885 | AH76: 0.032168 | AI76: 0.010521
A77: TKI000:ea_Rail,Freight | B77: Rail, Freight | C77: 0.247425 | D77: 0.235349 | E77: 0.224294 | F77: 0.221703 | G77: 0.220458 | H77: 0.217186 | I77: 0.211368 | J77: 0.215123 | K77: 0.214871 | L77: 0.214751 | M77: 0.212415 | N77: 0.21003 | O77: 0.209515 | P77: 0.209267 | Q77: 0.209119 | R77: 0.209029 | S77: 0.207961 | T77: 0.207993 | U77: 0.207494 | V77: 0.205728 | W77: 0.205676 | X77: 0.20464 | Y77: 0.204172 | Z77: 0.204352 | AA77: 0.204426 | AB77: 0.204688 | AC77: 0.205248 | AD77: 0.206758 | AE77: 0.207232 | AF77: 0.208277 | AG77: 0.209481 | AH77: 0.211086 | AI77: -0.005111
A78: TKI000:ea_Shipping,Dome | B78: Shipping, Domestic | C78: 0.042333 | D78: 0.041603 | E78: 0.040635 | F78: 0.0394 | G78: 0.038405 | H78: 0.037229 | I78: 0.03608 | J78: 0.035014 | K78: 0.033953 | L78: 0.032851 | M78: 0.031707 | N78: 0.030539 | O78: 0.030006 | P78: 0.029419 | Q78: 0.028888 | R78: 0.02829 | S78: 0.02772 | T78: 0.027204 | U78: 0.02666 | V78: 0.026101 | W78: 0.025585 | X78: 0.025052 | Y78: 0.024795 | Z78: 0.024559 | AA78: 0.0243 | AB78: 0.024088 | AC78: 0.023893 | AD78: 0.023781 | AE78: 0.023574 | AF78: 0.02343 | AG78: 0.023322 | AH78: 0.023231 | AI78: -0.019171
A79: TKI000:ea_Shipping,Inte | B79: Shipping, International | C79: 0.419044 | D79: 0.459324 | E79: 0.440255 | F79: 0.398147 | G79: 0.4 | H79: 0.394394 | I79: 0.399222 | J79: 0.390425 | K79: 0.394511 | L79: 0.39495 | M79: 0.390033 | N79: 0.394978 | O79: 0.395364 | P79: 0.391307 | Q79: 0.394931 | R79: 0.394969 | S79: 0.393888 | T79: 0.390292 | U79: 0.392778 | V79: 0.389117 | W79: 0.38898 | X79: 0.391189 | Y79: 0.387353 | Z79: 0.386861 | AA79: 0.386008 | AB79: 0.384915 | AC79: 0.384226 | AD79: 0.384005 | AE79: 0.383269 | AF79: 0.382965 | AG79: 0.382823 | AH79: 0.382909 | AI79: -0.002905
A80: TKI000:ea_RecreationalB | B80: Recreational Boats | C80: 0.13308 | D80: 0.1335 | E80: 0.133858 | F80: 0.134049 | G80: 0.134152 | H80: 0.134247 | I80: 0.134378 | J80: 0.134477 | K80: 0.134548 | L80: 0.134625 | M80: 0.134701 | N80: 0.134737 | O80: 0.134762 | P80: 0.134771 | Q80: 0.134727 | R80: 0.134629 | S80: 0.134484 | T80: 0.134326 | U80: 0.134143 | V80: 0.133947 | W80: 0.133738 | X80: 0.133498 | Y80: 0.13323 | Z80: 0.132925 | AA80: 0.132613 | AB80: 0.132305 | AC80: 0.132013 | AD80: 0.131737 | AE80: 0.131461 | AF80: 0.131191 | AG80: 0.130914 | AH80: 0.130629 | AI80: -0.0006
A81: TKI000:ea_Air | B81: Air | C81: 1.277419 | D81: 1.292941 | E81: 1.309023 | F81: 1.321509 | G81: 1.33129 | H81: 1.342723 | I81: 1.35579 | J81: 1.368137 | K81: 1.380141 | L81: 1.392848 | M81: 1.406724 | N81: 1.420583 | O81: 1.435178 | P81: 1.449832 | Q81: 1.464272 | R81: 1.476649 | S81: 1.488463 | T81: 1.501402 | U81: 1.514789 | V81: 1.528416 | W81: 1.542677 | X81: 1.557327 | Y81: 1.571836 | Z81: 1.586228 | AA81: 1.601101 | AB81: 1.617454 | AC81: 1.636085 | AD81: 1.656825 | AE81: 1.678637 | AF81: 1.702407 | AG81: 1.727231 | AH81: 1.752876 | AI81: 0.010259
A82: TKI000:ea_MilitaryUse | B82: Military Use | C82: 0.245757 | D82: 0.251956 | E82: 0.247274 | F82: 0.241855 | G82: 0.234618 | H82: 0.229808 | I82: 0.228918 | J82: 0.228018 | K82: 0.227745 | L82: 0.22897 | M82: 0.228454 | N82: 0.228098 | O82: 0.228149 | P82: 0.228197 | Q82: 0.228253 | R82: 0.228318 | S82: 0.228408 | T82: 0.228501 | U82: 0.228635 | V82: 0.228755 | W82: 0.228885 | X82: 0.228999 | Y82: 0.229148 | Z82: 0.229291 | AA82: 0.229445 | AB82: 0.229607 | AC82: 0.229775 | AD82: 0.229945 | AE82: 0.230114 | AF82: 0.230288 | AG82: 0.230466 | AH82: 0.230647 | AI82: -0.002045
A83: TKI000:ea_Lubricants | B83: Lubricants | C83: 0.062101 | D83: 0.061879 | E83: 0.061699 | F83: 0.061486 | G83: 0.061273 | H83: 0.061047 | I83: 0.060801 | J83: 0.060562 | K83: 0.060339 | L83: 0.060146 | M83: 0.059989 | N83: 0.059838 | O83: 0.059705 | P83: 0.059585 | Q83: 0.059469 | R83: 0.059378 | S83: 0.059306 | T83: 0.059277 | U83: 0.059265 | V83: 0.059268 | W83: 0.059288 | X83: 0.059296 | Y83: 0.059298 | Z83: 0.059335 | AA83: 0.059361 | AB83: 0.059407 | AC83: 0.05949 | AD83: 0.059586 | AE83: 0.059688 | AF83: 0.059814 | AG83: 0.059926 | AH83: 0.060027 | AI83: -0.001095
... A85: TKI000:ea_Total | B85: Total | C85: 14.473433 | D85: 14.53084 | E85: 14.515177 | F85: 14.408682 | G85: 14.284176 | H85: 14.113085 | I85: 13.944188 | J85: 13.801455 | K85: 13.680749 | L85: 13.568763 | M85: 13.462358 | N85: 13.368217 | O85: 13.305375 | P85: 13.229243 | Q85: 13.172801 | R85: 13.107446 | S85: 13.048519 | T85: 13.017055 | U85: 12.995325 | V85: 12.977034 | W85: 12.975856 | X85: 12.986323 | Y85: 12.997333 | Z85: 13.026218 | AA85: 13.060641 | AB85: 13.110025 | AC85: 13.173438 | AD85: 13.26224 | AE85: 13.34532 | AF85: 13.450161 | AG85: 13.563889 | AH85: 13.686009 | AI85: -0.001803
B87: 1/ Commercial trucks 8,501 to 10,000 pounds gross vehicle weight rating.
B88: 2/ CAFE standard based on projected new vehicle sales.
B89: 3/ Includes CAFE credits for alternative fueled vehicle sales and credit banking.
B90: 4/ Environmental Protection Agency rated miles per gallon.
B91: 5/ Tested new vehicle efficiency revised for on-road performance.
B92: 6/ Combined "on-the-road" estimate for all cars and light trucks.
B93: CAFE = Corporate average fuel economy.
B94: Btu = British thermal unit.
B95: Note: Totals may not equal sum of components due to independent rounding.
B96: Sources: 2019: U.S. Energy Information Administration (EIA), Short-Term Energy Outlook, October 2019 and EIA, AEO2020 National
B97: Energy Modeling System run highogs.d112619a. Projections: EIA, AEO2020 National Energy Modeling System run highogs.d112619a.

Sheet AEO 2023 Table 35
A1: ORIGINAL EIA CODE | F1: 2021 | G1: 2022 | H1: 2023 | I1: 2024 | J1: 2025 | K1: 2026 | L1: 2027 | M1: 2028 | N1: 2029 | O1: 2030 | P1: 2031 | Q1: 2032 | R1: 2033 | S1: 2034 | T1: 2035 | U1: 2036 | V1: 2037 | W1: 2038 | X1: 2039 | Y1: 2040 | Z1: 2041 | AA1: 2042 | AB1: 2043 | AC1: 2044 | AD1: 2045 | AE1: 2046 | AF1: 2047 | AG1: 2048 | AH1: 2049 | AI1: 2050 | AJ1: Growth (2020-2050)
A10: TEU000 | B10: Table 35. Transportation Sector Energy Use by Mode and Type
B11: https://www.eia.gov/outlooks/aeo/data/browser/#/?id=45-AEO2023&sourcekey=0
B12: Tue Apr 18 2023 11:08:48 GMT-0400 (Eastern Daylight Time)
B13: Source: U.S. Energy Information Administration
C14: full name | D14: api key | E14: units | F14: 2021 | G14: 2022 | H14: 2023 | I14: 2024 | J14: 2025 | K14: 2026 | L14: 2027 | M14: 2028 | N14: 2029 | O14: 2030 | P14: 2031 | Q14: 2032 | R14: 2033 | S14: 2034 | T14: 2035 | U14: 2036 | V14: 2037 | W14: 2038 | X14: 2039 | Y14: 2040 | Z14: 2041 | AA14: 2042 | AB14: 2043 | AC14: 2044 | AD14: 2045 | AE14: 2046 | AF14: 2047 | AG14: 2048 | AH14: 2049 | AI14: 2050 | AJ14: Growth (2022-2050)
B15: Energy Use by Mode
B16: Highway
A17: TEU000:ba_Light-DutyVeh | B17: Light-Duty Vehicles | C17: Transportation Energy Use: Highway: Light-Duty Vehicles: Reference case | D17: AEO.2023.REF2023.CNSM_NA_TRN_HWY_LDV_NA_NA_TRLBTU.A | E17: trillion Btu | G17: 14541.974 | H17: 14586.115 | I17: 14429.693 | J17: 14201.927 | K17: 14016.909 | L17: 13860.764 | M17: 13679.089 | N17: 13473.833 | O17: 13253.084 | P17: 13044.087 | Q17: 12836.979 | R17: 12674.041 | S17: 12534.656 | T17: 12394.664 | U17: 12251.55 | V17: 12130.824 | W17: 12028.419 | X17: 11933.924 | Y17: 11864.004 | Z17: 11805.398 | AA17: 11762.744 | AB17: 11733.646 | AC17: 11725.389 | AD17: 11735.777 | AE17: 11770.766 | AF17: 11824.353 | AG17: 11889.718 | AH17: 11962.912 | AI17: 12054.456 | AJ17: -0.007
A18: TEU000:ba_Automobiles | B18: Automobiles | C18: Transportation Energy Use: Highway: Light-Duty Vehicles: Automobiles: Reference case | D18: AEO.2023.REF2023.CNSM_NA_TRN_HWY_LDV_AUTO_NA_TRLBTU.A | E18: trillion Btu | G18: 5654.1606 | H18: 5526.6772 | I18: 5311.813 | J18: 5067.3223 | K18: 4838.1689 | L18: 4619.4316 | M18: 4397.4468 | N18: 4169.8599 | O18: 3944.7561 | P18: 3731.1753 | Q18: 3530.8748 | R18: 3355.2742 | S18: 3201.8225 | T18: 3058.1055 | U18: 2927.6711 | V18: 2817.0913 | W18: 2726.7456 | X18: 2648.3855 | Y18: 2585.8064 | Z18: 2534.5078 | AA18: 2494.8418 | AB18: 2463.2471 | AC18: 2438.6992 | AD18: 2420.9849 | AE18: 2411.0181 | AF18: 2405.7183 | AG18: 2403.655 | AH18: 2402.5029 | AI18: 2405.8833 | AJ18: -0.03
A19: TEU000:ba_LightTrucks | B19: Light Trucks | C19: Transportation Energy Use: Highway: Light-Duty Vehicles: Light Trucks: Reference case | D19: AEO.2023.REF2023.CNSM_NA_TRN_HWY_LDV_LTRT_NA_TRLBTU.A | E19: trillion Btu | G19: 8871.5508 | H19: 9043.541 | I19: 9102.6006 | J19: 9120.0283 | K19: 9164.8242 | L19: 9228.0459 | M19: 9268.9941 | N19: 9291.9814 | O19: 9296.9863 | P19: 9302.1855 | Q19: 9295.9561 | R19: 9309.126 | S19: 9323.6357 | T19: 9327.7764 | U19: 9315.4736 | V19: 9305.6484 | W19: 9293.8496 | X19: 9277.9414 | Y19: 9270.7812 | Z19: 9263.6221 | AA19: 9260.7471 | AB19: 9263.335 | AC19: 9279.6943 | AD19: 9307.8467 | AE19: 9352.8291 | AF19: 9411.7305 | AG19: 9479.1641 | AH19: 9553.5127 | AI19: 9641.666 | AJ19: 0.003
A20: TEU000:ba_Motorcycles | B20: Motorcycles | C20: Transportation Energy Use: Highway: Light-Duty Vehicles: Motorcycles: Reference case | D20: AEO.2023.REF2023.CNSM_NA_TRN_HWY_LDV_MCYCL_NA_TRLBTU.A | E20: trillion Btu | G20: 16.262892 | H20: 15.896933 | I20: 15.278913 | J20: 14.5757 | K20: 13.916059 | L20: 13.285933 | M20: 12.647085 | N20: 11.991311 | O20: 11.342273 | P20: 10.726049 | Q20: 10.148347 | R20: 9.640781 | S20: 9.197762 | T20: 8.782386 | U20: 8.404802 | V20: 8.084402 | W20: 7.823192 | X20: 7.596957 | Y20: 7.416474 | Z20: 7.268723 | AA20: 7.155083 | AB20: 7.064892 | AC20: 6.994964 | AD20: 6.945127 | AE20: 6.917612 | AF20: 6.903515 | AG20: 6.898674 | AH20: 6.896451 | AI20: 6.90719 | AJ20: -0.03
A21: TEU000:ba_CommercialLig | B21: Commercial Light Trucks | C21: Transportation Energy Use: Highway: Commercial Light Trucks: Reference case | D21: AEO.2023.REF2023.CNSM_NA_TRN_HWY_CML_NA_NA_TRLBTU.A | E21: trillion Btu | G21: 951.50293 | H21: 942.55829 | I21: 925.34027 | J21: 912.45172 | K21: 903.11078 | L21: 894.80676 | M21: 888.38452 | N21: 882.99542 | O21: 877.03253 | P21: 872.79089 | Q21: 871.79065 | R21: 871.86749 | S21: 873.03369 | T21: 875.07349 | U21: 877.49945 | V21: 881.02332 | W21: 885.54089 | X21: 889.79602 | Y21: 896.14636 | Z21: 903.92444 | AA21: 911.92096 | AB21: 918.6748 | AC21: 924.72058 | AD21: 931.8302 | AE21: 939.93994 | AF21: 949.95038 | AG21: 958.32001 | AH21: 967.2102 | AI21: 978.89801 | AJ21: 0.001
A22: TEU000:ba_Buses | B22: Buses | C22: Transportation Energy Use: Highway: Buses: Reference case | D22: AEO.2023.REF2023.CNSM_NA_TRN_HWY_BUS_NA_NA_TRLBTU.A | E22: trillion Btu | G22: 212.16301 | H22: 222.31247 | I22: 226.95673 | J22: 228.01268 | K22: 228.79755 | L22: 229.23793 | M22: 229.40265 | N22: 229.15626 | O22: 228.54794 | P22: 227.55568 | Q22: 226.52992 | R22: 226.00464 | S22: 225.33565 | T22: 224.47317 | U22: 223.49628 | V22: 221.94028 | W22: 220.57585 | X22: 219.0985 | Y22: 217.49985 | Z22: 215.78369 | AA22: 214.03241 | AB22: 212.01721 | AC22: 210.15359 | AD22: 208.21464 | AE22: 206.53474 | AF22: 204.46298 | AG22: 202.45996 | AH22: 200.28244 | AI22: 198.18263 | AJ22: -0.002
A23: TEU000:ba_Transit | B23: Transit | C23: Transportation Energy Use: Highway: Buses: Transit: Reference case | D23: AEO.2023.REF2023.CNSM_NA_TRN_HWY_BUS_TNST_NA_TRLBTU.A | E23: trillion Btu | G23: 92.212234 | H23: 95.83783 | I23: 98.320953 | J23: 98.870079 | K23: 99.844643 | L23: 100.61442 | M23: 101.24708 | N23: 101.61662 | O23: 101.72417 | P23: 101.53801 | Q23: 101.31126 | R23: 100.9764 | S23: 100.75687 | T23: 100.29507 | U23: 99.678467 | V23: 98.421806 | W23: 97.683716 | X23: 96.918678 | Y23: 96.071007 | Z23: 95.130722 | AA23: 94.233086 | AB23: 93.123825 | AC23: 92.2043 | AD23: 91.250328 | AE23: 90.65873 | AF23: 89.694473 | AG23: 88.826485 | AH23: 87.819649 | AI23: 86.904648 | AJ23: -0.002
A24: TEU000:ba_Intercity | B24: Intercity | C24: Transportation Energy Use: Highway: Buses: Intercity: Reference case | D24: AEO.2023.REF2023.CNSM_NA_TRN_HWY_BUS_ICYT_NA_TRLBTU.A | E24: trillion Btu | G24: 26.118862 | H24: 28.024412 | I24: 29.477226 | J24: 30.571621 | K24: 31.3964 | L24: 32.010113 | M24: 32.464531 | N24: 32.799759 | O24: 33.046234 | P24: 33.226051 | Q24: 33.352478 | R24: 33.43018 | S24: 33.466476 | T24: 33.46925 | U24: 33.44516 | V24: 33.397396 | W24: 33.349758 | X24: 33.294384 | Y24: 33.234276 | Z24: 33.167286 | AA24: 33.096901 | AB24: 33.025082 | AC24: 32.951077 | AD24: 32.875145 | AE24: 32.799278 | AF24: 32.723492 | AG24: 32.646706 | AH24: 32.56945 | AI24: 32.494362 | AJ24: 0.008
A25: TEU000:ba_School | B25: School | C25: Transportation Energy Use: Highway: Buses: School: Reference case | D25: AEO.2023.REF2023.CNSM_NA_TRN_HWY_BUS_SCBU_NA_TRLBTU.A | E25: trillion Btu | G25: 93.831894 | H25: 98.450195 | I25: 99.158546 | J25: 98.571014 | K25: 97.556511 | L25: 96.613396 | M25: 95.691032 | N25: 94.739861 | O25: 93.77755 | P25: 92.791618 | Q25: 91.866196 | R25: 91.598053 | S25: 91.112289 | T25: 90.70887 | U25: 90.37265 | V25: 90.12104 | W25: 89.542336 | X25: 88.885452 | Y25: 88.194603 | Z25: 87.485649 | AA25: 86.702446 | AB25: 85.868294 | AC25: 84.99823 | AD25: 84.089134 | AE25: 83.076744 | AF25: 82.045021 | AG25: 80.986786 | AH25: 79.893326 | AI25: 78.783607 | AJ25: -0.006
A26: TEU000:ba_FreightTrucks | B26: Freight Trucks | C26: Transportation Energy Use: Highway: Freight Trucks: Reference case | D26: AEO.2023.REF2023.CNSM_NA_TRN_HWY_FGHT_NA_NA_TRLBTU.A | E26: trillion Btu | G26: 5922.792 | H26: 5816.707 | I26: 5728.0947 | J26: 5673.0977 | K26: 5638.8965 | L26: 5591.7075 | M26: 5543.7109 | N26: 5483.6704 | O26: 5422.3882 | P26: 5371.3022 | Q26: 5340.1582 | R26: 5306.5054 | S26: 5278.7798 | T26: 5261.2461 | U26: 5243 | V26: 5237.6978 | W26: 5236.3613 | X26: 5238.3042 | Y26: 5247.9146 | Z26: 5263.2085 | AA26: 5281.4546 | AB26: 5299.6816 | AC26: 5316.7661 | AD26: 5331.6992 | AE26: 5353.2002 | AF26: 5376.3174 | AG26: 5393.3188 | AH26: 5413.416 | AI26: 5450.0127 | AJ26: -0.003
A27: TEU000:ba_LightMedium | B27: Light Medium | C27: Transportation Energy Use: Highway: Freight Trucks: Light Medium: Reference case | D27: AEO.2023.REF2023.CNSM_NA_TRN_HWY_FGHT_LITEMED_NA_TRLBTU.A | E27: trillion Btu | G27: 745.82806 | H27: 731.17401 | I27: 720.99341 | J27: 716.52246 | K27: 715.17627 | L27: 711.7099 | M27: 708.54388 | N27: 705.98785 | O27: 706.4599 | P27: 710.45679 | Q27: 717.79156 | R27: 724.37231 | S27: 731.39038 | T27: 739.17932 | U27: 746.30853 | V27: 754.65619 | W27: 763.13739 | X27: 772.1521 | Y27: 782.66339 | Z27: 794.23718 | AA27: 805.87262 | AB27: 817.30426 | AC27: 829.03217 | AD27: 841.80096 | AE27: 857.07477 | AF27: 873.44006 | AG27: 889.11859 | AH27: 905.95618 | AI27: 926.21399 | AJ27: 0.008
A28: TEU000:ba_Medium | B28: Medium | C28: Transportation Energy Use: Highway: Freight Trucks: Medium: Reference case | D28: AEO.2023.REF2023.CNSM_NA_TRN_HWY_FGHT_MD10T26KLB_NA_TRLBTU.A | E28: trillion Btu | G28: 969.69183 | H28: 947.22809 | I28: 929.37402 | J28: 917.57544 | K28: 910.67749 | L28: 903.25037 | M28: 897.46631 | N28: 890.09558 | O28: 882.57385 | P28: 876.55035 | Q28: 874.65271 | R28: 871.91071 | S28: 869.98096 | T28: 869.72485 | U28: 869.34759 | V28: 871.61865 | W28: 873.72833 | X28: 877.64197 | Y28: 882.78259 | Z28: 889.237 | AA28: 896.04053 | AB28: 903.72443 | AC28: 911.77496 | AD28: 919.3786 | AE28: 928.10925 | AF28: 937.41211 | AG28: 945.94012 | AH28: 955.21368 | AI28: 967.38184 | AJ28: 0
A29: TEU000:ba_Large(>26000p | B29: Large (more than 26000 pounds) | C29: Transportation Energy Use: Highway: Freight Trucks: Large: Reference case | D29: AEO.2023.REF2023.#N/A.A | E29: trillion Btu | G29: 4207.2715 | H29: 4138.3047 | I29: 4077.7268 | J29: 4039 | K29: 4013.0432 | L29: 3976.7476 | M29: 3937.7007 | N29: 3887.5867 | O29: 3833.355 | P29: 3784.2954 | Q29: 3747.7139 | R29: 3710.2224 | S29: 3677.4087 | T29: 3652.342 | U29: 3627.3435 | V29: 3611.4229 | W29: 3599.4961 | X29: 3588.51 | Y29: 3582.4688 | Z29: 3579.7341 | AA29: 3579.5413 | AB29: 3578.6533 | AC29: 3575.9597 | AD29: 3570.5195 | AE29: 3568.0156 | AF29: 3565.4651 | AG29: 3558.26 | AH29: 3552.2463 | AI29: 3556.4165 | AJ29: -0.006
B30: Non-Highway
A31: TEU000:ca_Air | B31: Air | C31: Transportation Energy Use: Non-Highway: Air: Reference case | D31: AEO.2023.REF2023.CNSM_NA_TRN_AIR_NA_NA_NA_TRLBTU.A | E31: trillion Btu | G31: 2802.8074 | H31: 3008.168 | I31: 3051.2026 | J31: 3057.1106 | K31: 3095.8982 | L31: 3134.2271 | M31: 3164.5515 | N31: 3187.1079 | O31: 3202.9382 | P31: 3218.7827 | Q31: 3243.9365 | R31: 3270.4482 | S31: 3294.4031 | T31: 3322.9241 | U31: 3359.825 | V31: 3403.8945 | W31: 3450.1719 | X31: 3498.4883 | Y31: 3554.6438 | Z31: 3608.4036 | AA31: 3663.0974 | AB31: 3718.6248 | AC31: 3774.01 | AD31: 3827.9189 | AE31: 3880.4333 | AF31: 3936.7383 | AG31: 3993.604 | AH31: 4049.6506 | AI31: 4112.1577 | AJ31: 0.014
A32: TEU000:ca_GeneralAviati | B32: General Aviation | C32: Transportation Energy Use: Non-Highway: Air: General Aviation: Reference case | D32: AEO.2023.REF2023.CNSM_NA_TRN_AIR_GAV_NA_NA_TRLBTU.A | E32: trillion Btu | G32: 154.82079 | H32: 164.58934 | I32: 166.63007 | J32: 166.90428 | K32: 168.74524 | L32: 170.56552 | M32: 172.0056 | N32: 173.07629 | O32: 173.82729 | P32: 174.57951 | Q32: 175.77553 | R32: 177.03632 | S32: 178.17583 | T32: 179.53285 | U32: 181.289 | V32: 183.38686 | W32: 185.59007 | X32: 187.89032 | Y32: 190.56396 | Z32: 193.12366 | AA32: 195.72784 | AB32: 198.37164 | AC32: 201.00888 | AD32: 203.57585 | AE32: 206.07645 | AF32: 208.75748 | AG32: 211.46515 | AH32: 214.13402 | AI32: 217.1105 | AJ32: 0.012
A33: TEU000:ca_DomesticAirCa | B33: Domestic Passenger | C33: Transportation Energy Use: Non-Highway: Air: Domestic Passenger: Reference case | D33: AEO.2023.REF2023.CNSM_NA_TRN_AIR_DAC_NA_NA_TRLBTU.A | E33: trillion Btu | G33: 1525.3719 | H33: 1568.4963 | I33: 1545.2438 | J33: 1539.9454 | K33: 1560.0005 | L33: 1578.9973 | M33: 1593.6608 | N33: 1603.7645 | O33: 1608.9692 | P33: 1613.8066 | Q33: 1624.1025 | R33: 1638.2094 | S33: 1651.6223 | T33: 1665.2513 | U33: 1681.9424 | V33: 1701.5503 | W33: 1722.4525 | X33: 1743.975 | Y33: 1770.0122 | Z33: 1794.5861 | AA33: 1819.5831 | AB33: 1845.8711 | AC33: 1871.9424 | AD33: 1896.6277 | AE33: 1920.9094 | AF33: 1947.4875 | AG33: 1974.0907 | AH33: 2000.766 | AI33: 2030.3903 | AJ33: 0.01
A34: TEU000:ca_International | B34: International Passenger | C34: Transportation Energy Use: Non-Highway: Air: International Passenger: Reference case | D34: AEO.2023.REF2023.CNSM_NA_TRN_AIR_IAC_NA_NA_TRLBTU.A | E34: trillion Btu | G34: 586.70477 | H34: 755.09033 | I34: 825.08246 | J34: 835.10657 | K34: 847.74762 | L34: 860.41785 | M34: 870.67084 | N34: 878.74676 | O34: 885.43268 | P34: 892.21881 | Q34: 901.3352 | R34: 909.30804 | S34: 916.19775 | T34: 925.32129 | U34: 937.39001 | V34: 951.84992 | W34: 966.82947 | X34: 982.55957 | Y34: 1000.3361 | Z34: 1017.5378 | AA34: 1035.0142 | AB34: 1052.2997 | AC34: 1069.5682 | AD34: 1086.702 | AE34: 1103.2957 | AF34: 1120.8325 | AG34: 1138.662 | AH34: 1156.0013 | AI34: 1175.4172 | AJ34: 0.025
A35: TEU000:ca_FreightCarrie | B35: Dedicated Freight | C35: Transportation Energy Use: Non-Highway: Air: Dedicated Freight: Reference case | D35: AEO.2023.REF2023.CNSM_NA_TRN_AIR_DFT_NA_NA_TRLBTU.A | E35: trillion Btu | G35: 535.90997 | H35: 519.99194 | I35: 514.24634 | J35: 515.1543 | K35: 519.40478 | L35: 524.24622 | M35: 528.21435 | N35: 531.52032 | O35: 534.70904 | P35: 538.17767 | Q35: 542.72302 | R35: 545.89441 | S35: 548.40717 | T35: 552.81854 | U35: 559.20331 | V35: 567.1073 | W35: 575.29974 | X35: 584.06348 | Y35: 593.73175 | Z35: 603.15594 | AA35: 612.77222 | AB35: 622.08221 | AC35: 631.49048 | AD35: 641.01318 | AE35: 650.15185 | AF35: 659.66058 | AG35: 669.38611 | AH35: 678.74933 | AI35: 689.23981 | AJ35: 0.009
A36: TEU000:ca_Water | B36: Water | C36: Transportation Energy Use: Non-Highway: Water: Reference case | D36: AEO.2023.REF2023.CNSM_NA_TRN_WTR_NA_NA_NA_TRLBTU.A | E36: trillion Btu | G36: 1236.1034 | H36: 1179.9142 | I36: 1171.6475 | J36: 1169.6875 | K36: 1160.7493 | L36: 1156.1696 | M36: 1148.3876 | N36: 1142.2429 | O36: 1136.957 | P36: 1134.8431 | Q36: 1133.3051 | R36: 1132.2845 | S36: 1130.4717 | T36: 1129.385 | U36: 1127.3304 | V36: 1126.3339 | W36: 1125.2139 | X36: 1123.8895 | Y36: 1123.0144 | Z36: 1122.3082 | AA36: 1122.0916 | AB36: 1121.3387 | AC36: 1120.708 | AD36: 1119.7297 | AE36: 1121.4393 | AF36: 1120.9009 | AG36: 1118.8984 | AH36: 1117.3406 | AI36: 1115.843 | AJ36: -0.004
A37: TEU000:ca_Freight | B37: Freight | C37: Transportation Energy Use: Non-Highway: Water: Freight: Reference case | D37: AEO.2023.REF2023.CNSM_NA_TRN_WTR_FGT_NA_NA_TRLBTU.A | E37: trillion Btu | G37: 1033.2667 | H37: 980.75116 | I37: 975.84198 | J37: 975.9502 | K37: 967.93616 | L37: 964.27222 | M37: 957.65405 | N37: 953.03247 | O37: 949.55359 | P37: 949.16626 | Q37: 948.83813 | R37: 948.67444 | S37: 947.69421 | T37: 947.38678 | U37: 945.88025 | V37: 945.22846 | W37: 944.46802 | X37: 943.50647 | Y37: 942.71899 | Z37: 942.1471 | AA37: 942.10346 | AB37: 941.52521 | AC37: 941.15137 | AD37: 940.48584 | AE37: 942.48962 | AF37: 942.17328 | AG37: 940.40753 | AH37: 939.11212 | AI37: 937.68744 | AJ37: -0.003
A38: TEU000:ca_DomesticShipp | B38: Domestic Shipping | C38: Transportation Energy Use: Non-Highway: Water: Freight: Domestic Shipping: Reference case | D38: AEO.2023.REF2023.CNSM_NA_TRN_WTR_DMT_NA_NA_TRLBTU.A | E38: trillion Btu | G38: 98.239021 | H38: 98.920753 | I38: 98.114662 | J38: 97.346069 | K38: 96.685867 | L38: 95.823471 | M38: 94.964699 | N38: 93.890503 | O38: 92.919189 | P38: 92.029816 | Q38: 91.401108 | R38: 90.674225 | S38: 89.934029 | T38: 89.168869 | U38: 88.333008 | V38: 87.614967 | W38: 86.833351 | X38: 86.156693 | Y38: 85.473595 | Z38: 84.846123 | AA38: 84.273766 | AB38: 83.705399 | AC38: 83.103455 | AD38: 82.418205 | AE38: 81.856209 | AF38: 81.249023 | AG38: 80.57312 | AH38: 79.990395 | AI38: 79.59285 | AJ38: -0.007
A39: TEU000:da_International | B39: International Shipping | C39: Transportation Energy Use: Non-Highway: Water: Freight: International Shipping: Reference case | D39: AEO.2023.REF2023.CNSM_NA_TRN_WTR_INTS_NA_NA_TRLBTU.A | E39: trillion Btu | G39: 935.02771 | H39: 881.83038 | I39: 877.7273 | J39: 878.60413 | K39: 871.25031 | L39: 868.44873 | M39: 862.68933 | N39: 859.14197 | O39: 856.6344 | P39: 857.13648 | Q39: 857.43701 | R39: 858.00024 | S39: 857.76019 | T39: 858.2179 | U39: 857.54724 | V39: 857.61346 | W39: 857.63464 | X39: 857.34979 | Y39: 857.24542 | Z39: 857.30096 | AA39: 857.82971 | AB39: 857.81982 | AC39: 858.04791 | AD39: 858.06763 | AE39: 860.63342 | AF39: 860.92426 | AG39: 859.83441 | AH39: 859.1217 | AI39: 858.0946 | AJ39: -0.003
A40: TEU000:da_RecreationalB | B40: Recreational Boats | C40: Transportation Energy Use: Non-Highway: Water: Recreational Boats: Reference case | D40: AEO.2023.REF2023.CNSM_NA_TRN_WTR_RBT_NA_NA_TRLBTU.A | E40: trillion Btu | G40: 202.83664 | H40: 199.16296 | I40: 195.80548 | J40: 193.73721 | K40: 192.81314 | L40: 191.8974 | M40: 190.73351 | N40: 189.21046 | O40: 187.40353 | P40: 185.67694 | Q40: 184.46689 | R40: 183.61003 | S40: 182.77757 | T40: 181.99818 | U40: 181.45029 | V40: 181.10551 | W40: 180.74588 | X40: 180.38298 | Y40: 180.29542 | Z40: 180.16119 | AA40: 179.98802 | AB40: 179.81351 | AC40: 179.55652 | AD40: 179.24385 | AE40: 178.94971 | AF40: 178.72766 | AG40: 178.49087 | AH40: 178.22836 | AI40: 178.15555 | AJ40: -0.005
A41: TEU000:da_Rail | B41: Rail | C41: Transportation Energy Use: Non-Highway: Rail: Reference case | D41: AEO.2023.REF2023.CNSM_NA_TRN_RAIL_RAIL_NA_NA_TRLBTU.A | E41: trillion Btu | G41: 525.29517 | H41: 520.38635 | I41: 540.67011 | J41: 529.40961 | K41: 509.78037 | L41: 494.66577 | M41: 488.8783 | N41: 494.23297 | O41: 492.04196 | P41: 494.02197 | Q41: 498.57672 | R41: 502.37463 | S41: 505.03482 | T41: 508.43884 | U41: 509.35068 | V41: 510.83496 | W41: 512.78436 | X41: 512.64246 | Y41: 513.75494 | Z41: 517.85437 | AA41: 521.3421 | AB41: 522.19409 | AC41: 522.73846 | AD41: 523.13727 | AE41: 524.88281 | AF41: 527.90674 | AG41: 531.78455 | AH41: 533.67975 | AI41: 537.57678 | AJ41: 0.001
A42: TEU000:da_Freight | B42: Freight | C42: Transportation Energy Use: Non-Highway: Rail: Freight: Reference case | D42: AEO.2023.REF2023.CNSM_NA_TRN_RAIL_FGT_NA_NA_TRLBTU.A | E42: trillion Btu | G42: 481.38171 | H42: 474.82239 | I42: 494.12915 | J42: 482.20422 | K42: 461.88034 | L42: 446.09524 | M42: 439.74536 | N42: 444.5257 | O42: 441.89194 | P42: 443.42331 | Q42: 447.43723 | R42: 450.64798 | S42: 452.66559 | T42: 455.51504 | U42: 455.89371 | V42: 456.86227 | W42: 458.27463 | X42: 457.60877 | Y42: 458.12836 | Z42: 461.67325 | AA42: 464.58835 | AB42: 464.93649 | AC42: 464.92282 | AD42: 464.77069 | AE42: 465.76679 | AF42: 468.15533 | AG42: 471.33984 | AH42: 472.59906 | AI42: 475.72867 | AJ42: 0
... A51: TEU000:ea_ResidualFuelU | B51: Jet Fuel and Aviation Gasoline | C51: Transportation Energy Use: Military Use: Aviation: Reference case | D51: AEO.2023.REF2023.CNSM_NA_TRN_MLU_AVI_NA_NA_TRLBTU.A | E51: trillion Btu | G51: 334.44891 | H51: 336.23386 | I51: 336.88306 | J51: 337.39594 | K51: 337.81006 | L51: 338.4198 | M51: 338.85339 | N51: 339.19925 | O51: 339.4949 | P51: 339.68457 | Q51: 339.81464 | R51: 339.87894 | S51: 339.90338 | T51: 339.91986 | U51: 340.01639 | V51: 340.17093 | W51: 340.33325 | X51: 340.50293 | Y51: 340.67941 | Z51: 340.86197 | AA51: 341.05005 | AB51: 341.24316 | AC51: 341.44086 | AD51: 341.64276 | AE51: 341.84848 | AF51: 342.05759 | AG51: 342.26984 | AH51: 342.48502 | AI51: 342.70288 | AJ51: 0.001
A52: TEU000:ea_DistillateFue | B52: Residual Fuel Oil | C52: Transportation Energy Use: Military Use: Residual Fuel Oil: Reference case | D52: AEO.2023.REF2023.CNSM_NA_TRN_MLU_RFO_NA_NA_TRLBTU.A | E52: trillion Btu | G52: 0 | H52: 0 | I52: 0 | J52: 0 | K52: 0 | L52: 0 | M52: 0 | N52: 0 | O52: 0 | P52: 0 | Q52: 0 | R52: 0 | S52: 0 | T52: 0 | U52: 0 | V52: 0 | W52: 0 | X52: 0 | Y52: 0 | Z52: 0 | AA52: 0 | AB52: 0 | AC52: 0 | AD52: 0 | AE52: 0 | AF52: 0 | AG52: 0 | AH52: 0 | AI52: 0 | AJ52: - -
A53: TEU000:fa_Total | B53: Distillates and Diesel | C53: Transportation Energy Use: Military Use: Distillate Fuel Oil: Reference case | D53: AEO.2023.REF2023.CNSM_NA_TRN_MLU_DFO_NA_NA_TRLBTU.A | E53: trillion Btu | G53: 96.382973 | H53: 96.897369 | I53: 97.084457 | J53: 97.232269 | K53: 97.351608 | L53: 97.527321 | M53: 97.652275 | N53: 97.751961 | O53: 97.837143 | P53: 97.891815 | Q53: 97.929291 | R53: 97.947815 | S53: 97.954857 | T53: 97.959595 | U53: 97.987419 | V53: 98.031967 | W53: 98.078743 | X53: 98.12764 | Y53: 98.178513 | Z53: 98.231117 | AA53: 98.285309 | AB53: 98.340965 | AC53: 98.397942 | AD53: 98.456131 | AE53: 98.515411 | AF53: 98.575668 | AG53: 98.636826 | AH53: 98.698837 | AI53: 98.761627 | AJ53: 0.001
B54: Total | C54: Transportation Energy Use: Total: Reference case | D54: AEO.2023.REF2023.CNSM_NA_TRN_NA_TOT_NA_NA_TRLBTU.A | E54: trillion Btu | G54: 27655.148 | H54: 27655.762 | I54: 27394.568 | J54: 27059.129 | K54: 26811.27 | L54: 26577.496 | M54: 26318.691 | N54: 26067.979 | O54: 25786.289 | P54: 25538.402 | Q54: 25332.225 | R54: 25172.969 | S54: 25035.588 | T54: 24912.785 | U54: 24789.316 | V54: 24709.041 | W54: 24660.725 | X54: 24616.969 | Y54: 24627.309 | Z54: 24654.197 | AA54: 24700.111 | AB54: 24752.801 | AC54: 24825.584 | AD54: 24913.93 | AE54: 25038.584 | AF54: 25190.057 | AG54: 25345.311 | AH54: 25504.531 | AI54: 25712.529 | AJ54: -0.003
A55: TEU000:ga_MotorGasoline | B55: Energy Use by Type
A56: TEU000:ga_Ethanol | B56: Motor Gasoline excluding E85 | C56: Transportation Energy Use: Petroleum: Motor Gasoline: Reference case | D56: AEO.2023.REF2023.CNSM_NA_TRN_NA_PET_MGS_NA_TRLBTU.A | E56: trillion Btu | G56: 15874.355 | H56: 15889.633 | I56: 15703.889 | J56: 15449.35 | K56: 15240.682 | L56: 15053.521 | M56: 14839.349 | N56: 14597.918 | O56: 14338.503 | P56: 14096.112 | Q56: 13861.302 | R56: 13670.039 | S56: 13502.24 | T56: 13335.431 | U56: 13166.213 | V56: 13022.09 | W56: 12897.387 | X56: 12783.024 | Y56: 12697.221 | Z56: 12626.134 | AA56: 12573.058 | AB56: 12533.43 | AC56: 12516.672 | AD56: 12520.883 | AE56: 12551.513 | AF56: 12603.282 | AG56: 12665.79 | AH56: 12737.466 | AI56: 12832.444 | AJ56: -0.008
A57: TEU000:ga_Distillate(di | B57: E85 | C57: Transportation Energy Use: E85: Reference case | D57: AEO.2023.REF2023.CNSM_NA_TRN_NA_E85_NA_NA_TRLBTU.A | E57: trillion Btu | G57: 34.631935 | H57: 35.037319 | I57: 32.552341 | J57: 32.353249 | K57: 31.504307 | L57: 30.668486 | M57: 29.69116 | N57: 28.651995 | O57: 27.562658 | P57: 26.514359 | Q57: 25.50803 | R57: 24.634333 | S57: 23.871559 | T57: 23.224663 | U57: 22.621021 | V57: 22.23918 | W57: 22.006664 | X57: 21.907352 | Y57: 21.950138 | Z57: 22.073862 | AA57: 22.260597 | AB57: 22.542372 | AC57: 22.813953 | AD57: 23.132349 | AE57: 23.431681 | AF57: 23.847071 | AG57: 24.21563 | AH57: 24.654547 | AI57: 25.077648 | AJ57: -0.011
A58: TEU000:ga_JetFuel(keros | B58: Diesel | C58: Transportation Energy Use: Petroleum: Diesel: Reference case | D58: AEO.2023.REF2023.CNSM_NA_TRN_NA_PET_DSL_NA_TRLBTU.A | E58: trillion Btu | G58: 6710.395 | H58: 6706.5205 | I58: 6636.6934 | J58: 6567.0239 | K58: 6510.3555 | L58: 6449.8804 | M58: 6399.6875 | N58: 6345.397 | O58: 6280.8228 | P58: 6224.6582 | Q58: 6188.4878 | R58: 6150.8975 | S58: 6117.8203 | T58: 6092.3511 | U58: 6064.7573 | V58: 6047.6304 | W58: 6036.644 | X58: 6023.3477 | Y58: 6019.6016 | Z58: 6021.7837 | AA58: 6024.8711 | AB58: 6025.457 | AC58: 6023.2671 | AD58: 6018.6934 | AE58: 6019.314 | AF58: 6021.1924 | AG58: 6019.1113 | AH58: 6015.7207 | AI58: 6030.272 | AJ58: -0.004
A59: TEU000:ga_ResidualOil | B59: Jet Fuel (kerosene & naphtha) | C59: Transportation Energy Use: Petroleum: Jet Fuel: Reference case | D59: AEO.2023.REF2023.UNC_NA_TRN_NA_PET_JFL_NA_TRLBTU.A | E59: trillion Btu | G59: 3114.8347 | H59: 3321.9912 | I59: 3365.6841 | J59: 3372.1125 | K59: 3411.3206 | L59: 3450.2642 | M59: 3481.0264 | N59: 3503.9324 | O59: 3520.061 | P59: 3536.0977 | Q59: 3561.3833 | R59: 3587.9609 | S59: 3611.9419 | T59: 3640.4805 | U59: 3677.4785 | V59: 3721.7036 | W59: 3768.144 | X59: 3816.6306 | Y59: 3872.9631 | Z59: 3926.9058 | AA59: 3981.7881 | AB59: 4037.5085 | AC59: 4093.0918 | AD59: 4147.2026 | AE59: 4199.9233 | AF59: 4256.437 | AG59: 4313.5156 | AH59: 4369.7773 | AI59: 4432.502 | AJ59: 0.013
A60: TEU000:ga_AviationGasol | B60: Residual Fuel Oil | C60: Transportation Energy Use: Petroleum: Residual Fuel Oil: Reference case | D60: AEO.2023.REF2023.CNSM_NA_TRN_NA_PET_RFO_NA_TRLBTU.A | E60: trillion Btu | G60: 687.54108 | H60: 533.95758 | I60: 521.0669 | J60: 521.9704 | K60: 499.00574 | L60: 489.2088 | M60: 471.12759 | N60: 459.55618 | O60: 451.02731 | P60: 451.06888 | Q60: 450.30673 | R60: 450.39215 | S60: 448.21356 | T60: 448.02866 | U60: 444.74847 | V60: 443.62381 | W60: 442.39099 | X60: 440.1236 | Y60: 438.39453 | Z60: 437.18234 | AA60: 437.22125 | AB60: 435.65289 | AC60: 434.69913 | AD60: 433.13565 | AE60: 438.8573 | AF60: 438.0972 | AG60: 433.31424 | AH60: 429.63794 | AI60: 424.94931 | AJ60: -0.017
A61: TEU000:ga_LiquefiedPetr | B61: Aviation Gasoline | C61: Transportation Energy Use: Petroleum: Aviation Gasoline: Reference case | D61: AEO.2023.REF2023.CNSM_NA_TRN_NA_PET_AVGA_NA_TRLBTU.A | E61: trillion Btu | G61: 22.421618 | H61: 22.410635 | I61: 22.401548 | J61: 22.394032 | K61: 22.387812 | L61: 22.382666 | M61: 22.378407 | N61: 22.374884 | O61: 22.371969 | P61: 22.369558 | Q61: 22.367563 | R61: 22.365911 | S61: 22.364546 | T61: 22.363417 | U61: 22.36248 | V61: 22.361708 | W61: 22.361067 | X61: 22.360538 | Y61: 22.3601 | Z61: 22.359737 | AA61: 22.359438 | AB61: 22.35919 | AC61: 22.358984 | AD61: 22.358814 | AE61: 22.358673 | AF61: 22.358557 | AG61: 22.358461 | AH61: 22.358381 | AI61: 22.358315 | AJ61: 0
A62: TEU000:ga_Lubricants | B62: Propane | C62: Transportation Energy Use: Petroleum: Propane: Reference case | D62: AEO.2023.REF2023.CNSM_NA_TRN_NA_PET_PROP_NA_TRLBTU.A | E62: trillion Btu | G62: 11.141157 | H62: 11.729122 | I62: 11.853459 | J62: 12.01076 | K62: 12.154844 | L62: 12.287197 | M62: 12.139218 | N62: 12.24054 | O62: 12.351296 | P62: 12.459235 | Q62: 12.585068 | R62: 12.731653 | S62: 12.905529 | T62: 13.095903 | U62: 13.307463 | V62: 13.546154 | W62: 13.805359 | X62: 14.093753 | Y62: 14.423079 | Z62: 14.799322 | AA62: 15.214664 | AB62: 15.662395 | AC62: 16.14922 | AD62: 16.675133 | AE62: 17.265896 | AF62: 17.89559 | AG62: 18.551962 | AH62: 19.225891 | AI62: 19.960386 | AJ62: 0.021
A63: TEU000:ga_PetroleumSubt | B63: Lubricants | C63: Transportation Energy Use: Petroleum: Lubricants: Reference case | D63: AEO.2023.REF2023.CNSM_NA_TRN_NA_PET_LBC_NA_TRLBTU.A | E63: trillion Btu | G63: 125.94522 | H63: 125.92506 | I63: 126.01238 | J63: 126.04986 | K63: 126.11367 | L63: 125.98441 | M63: 125.853 | N63: 125.75523 | O63: 125.65207 | P63: 125.54579 | Q63: 125.43918 | R63: 125.33015 | S63: 125.25038 | T63: 125.22502 | U63: 125.25526 | V63: 125.31821 | W63: 125.4119 | X63: 125.52669 | Y63: 125.66653 | Z63: 125.79737 | AA63: 125.92503 | AB63: 126.04557 | AC63: 126.16628 | AD63: 126.32028 | AE63: 126.49239 | AF63: 126.66081 | AG63: 126.81145 | AH63: 126.97429 | AI63: 127.15868 | AJ63: 0
A64: TEU000:ga_Methanol | B64: Petroleum and Other Liquids Subtotal | C64: Transportation Energy Use: Petroleum Subtotal: Reference case | D64: AEO.2023.REF2023.CNSM_NA_TRN_NA_PET_NA_NA_TRLBTU.A | E64: trillion Btu | G64: 26581.266 | H64: 26647.203 | I64: 26420.152 | J64: 26103.268 | K64: 25853.523 | L64: 25634.197 | M64: 25381.252 | N64: 25095.826 | O64: 24778.352 | P64: 24494.822 | Q64: 24247.379 | R64: 24044.354 | S64: 23864.607 | T64: 23700.199 | U64: 23536.744 | V64: 23418.512 | W64: 23328.15 | X64: 23247.016 | Y64: 23212.578 | Z64: 23197.035 | AA64: 23202.699 | AB64: 23218.656 | AC64: 23255.219 | AD64: 23308.402 | AE64: 23399.156 | AF64: 23509.773 | AG64: 23623.67 | AH64: 23745.816 | AI64: 23914.723 | AJ64: -0.004
A65: TEU000:ga_Electricity | B65: Electricity | C65: Transportation Energy Use: Electricity: Reference case | D65: AEO.2023.REF2023.CNSM_NA_TRN_NA_ELC_NA_NA_TRLBTU.A | E65: trillion Btu | G65: 58.271488 | H65: 70.924744 | I65: 86.151306 | J65: 103.80544 | K65: 124.94299 | L65: 150.04829 | M65: 178.72939 | N65: 211.36607 | O65: 247.30803 | P65: 280.38351 | Q65: 314.45035 | R65: 348.6257 | S65: 383.96487 | T65: 418.87405 | U65: 452.58807 | V65: 485.43649 | W65: 517.22076 | X65: 547.37634 | Y65: 575.67041 | Z65: 602.42621 | AA65: 627.3949 | AB65: 650.20367 | AC65: 671.55237 | AD65: 690.80652 | AE65: 710.45508 | AF65: 729.02063 | AG65: 747.0238 | AH65: 764.70154 | AI65: 781.67743 | AJ65: 0.097
A66: TEU000:ga_CompressedNat | B66: Compressed/Liquefied Natural Gas | C66: Transportation Energy Use: Natural Gas: Reference case | D66: AEO.2023.REF2023.CNSM_NA_TRN_NA_NG_NA_NA_TRLBTU.A | E66: trillion Btu | G66: 107.76208 | H66: 114.84132 | I66: 124.74314 | J66: 122.40164 | K66: 133.70236 | L66: 135.6781 | M66: 140.85495 | N66: 144.49738 | O66: 145.72705 | P66: 146.36429 | Q66: 147.34078 | R66: 148.05913 | S66: 150.25818 | T66: 153.89322 | U66: 159.30589 | V66: 165.10998 | W66: 170.17973 | X66: 178.24515 | Y66: 185.24722 | Z66: 193.94168 | AA66: 203.10612 | AB66: 214.17357 | AC66: 224.93594 | AD66: 236.52026 | AE66: 245.41003 | AF66: 259.84387 | AG66: 276.02594 | AH66: 292.71753 | AI66: 309.737 | AJ66: 0.038
A67: TEU000:ga_LiquidHydroge | B67: Hydrogen | C67: Transportation Energy Use: Hydrogen: Reference case | D67: AEO.2023.REF2023.CNSM_NA_TRN_NA_HDG_NA_NA_TRLBTU.A | E67: trillion Btu | G67: 0.449255 | H67: 0.542217 | I67: 0.620706 | J67: 0.690218 | K67: 0.763191 | L67: 0.832262 | M67: 0.905294 | N67: 0.974009 | O67: 1.046211 | P67: 1.119019 | Q67: 1.19111 | R67: 1.262406 | S67: 1.334878 | T67: 1.405921 | U67: 1.472262 | V67: 1.536677 | W67: 1.594822 | X67: 1.646765 | Y67: 1.689135 | Z67: 1.72306 | AA67: 1.754586 | AB67: 1.776198 | AC67: 1.792174 | AD67: 1.801144 | AE67: 1.81132 | AF67: 1.821694 | AG67: 1.828998 | AH67: 1.834284 | AI67: 1.8375 | AJ67: 0.052
... A69: TEU000:ha_TotalConsumpt | B69: Natural Gas Liquefaction for Export | C69: Transportation Energy Use: Natural Gas for Liquefaction: Reference case | D69: AEO.2023.REF2023.CNSM_NA_NMFG_LQFCT_DELE_NA_NA_TRLBTU.A | E69: trillion Btu | G69: 332.5231 | H69: 377.97052 | I69: 384.00461 | J69: 408.78293 | K69: 446.26065 | L69: 477.17264 | M69: 503.61008 | N69: 527.57086 | O69: 577.96906 | P69: 628.36725 | Q69: 680.00372 | R69: 729.16363 | S69: 771.16211 | T69: 796.36121 | U69: 814.39893 | V69: 829.96002 | W69: 838.35974 | X69: 838.35974 | Y69: 839.59802 | Z69: 838.35974 | AA69: 838.35974 | AB69: 838.35974 | AC69: 839.59802 | AD69: 838.35974 | AE69: 838.35974 | AF69: 838.35974 | AG69: 839.59802 | AH69: 838.35974 | AI69: 838.35974 | AJ69: 0.034
B70: Total Consumption | C70: Transportation: Total Energy Use: Reference case | D70: AEO.2023.REF2023.CNSM_NA_TRN_NA_NA_NA_NA_TRLBTU.A | E70: trillion Btu | G70: 27986.004 | H70: 28032.025 | I70: 27776.652 | J70: 27465.699 | K70: 27255.043 | L70: 27051.914 | M70: 26819.279 | N70: 26592.268 | O70: 26360.719 | P70: 26162.953 | Q70: 26008.129 | R70: 25897.748 | S70: 25802.094 | T70: 25704.211 | U70: 25598.514 | V70: 25533.523 | W70: 25493.338 | X70: 25449.312 | Y70: 25460.59 | Z70: 25485.91 | AA70: 25531.479 | AB70: 25584.162 | AC70: 25658.191 | AD70: 25745.092 | AE70: 25869.725 | AF70: 26020.955 | AG70: 26177.635 | AH70: 26335.311 | AI70: 26543.111 | AJ70: -0.002

Sheet AEO 2022 Table 35
A1: ORIGINAL EIA CODE | F1: 2020 | G1: 2021 | H1: 2022 | I1: 2023 | J1: 2024 | K1: 2025 | L1: 2026 | M1: 2027 | N1: 2028 | O1: 2029 | P1: 2030 | Q1: 2031 | R1: 2032 | S1: 2033 | T1: 2034 | U1: 2035 | V1: 2036 | W1: 2037 | X1: 2038 | Y1: 2039 | Z1: 2040 | AA1: 2041 | AB1: 2042 | AC1: 2043 | AD1: 2044 | AE1: 2045 | AF1: 2046 | AG1: 2047 | AH1: 2048 | AI1: 2049 | AJ1: 2050 | AK1: Growth (2020-2050)
A10: TEU000 | B10: Table 35. Transportation Sector Energy Use by Mode and Type
B11: https://www.eia.gov/outlooks/aeo/data/browser/#/?id=45-AEO2022&cases=ref2022&sourcekey=0
B12: Tue Apr 18 2023 11:05:52 GMT-0400 (Eastern Daylight Time)
B13: Source: U.S. Energy Information Administration
C14: full name | D14: api key | E14: units | F14: 2020 | G14: 2021 | H14: 2022 | I14: 2023 | J14: 2024 | K14: 2025 | L14: 2026 | M14: 2027 | N14: 2028 | O14: 2029 | P14: 2030 | Q14: 2031 | R14: 2032 | S14: 2033 | T14: 2034 | U14: 2035 | V14: 2036 | W14: 2037 | X14: 2038 | Y14: 2039 | Z14: 2040 | AA14: 2041 | AB14: 2042 | AC14: 2043 | AD14: 2044 | AE14: 2045 | AF14: 2046 | AG14: 2047 | AH14: 2048 | AI14: 2049 | AJ14: 2050 | AK14: Growth (2021-2050)
B15: Energy Use by Mode
B16: Highway
A17: TEU000:ba_Light-DutyVeh | B17: Light-Duty Vehicles | C17: Transportation Energy Use: Highway: Light-Duty Vehicles: Reference case | D17: AEO.2022.REF2022.CNSM_NA_TRN_HWY_LDV_NA_NA_TRLBTU.A | E17: trillion Btu | G17: 14274.495 | H17: 14663.076 | I17: 14907.381 | J17: 14888.804 | K17: 14849.199 | L17: 14786.863 | M17: 14699.438 | N17: 14596.2 | O17: 14504.817 | P17: 14439.393 | Q17: 14388.909 | R17: 14328.159 | S17: 14293.913 | T17: 14263.885 | U17: 14229.5 | V17: 14203.662 | W17: 14192.501 | X17: 14188.249 | Y17: 14197.587 | Z17: 14217.721 | AA17: 14239.975 | AB17: 14268.429 | AC17: 14301.938 | AD17: 14345.219 | AE17: 14399.628 | AF17: 14468.228 | AG17: 14540.382 | AH17: 14616.563 | AI17: 14701.988 | AJ17: 14799.438 | AK17: 0.001
A18: TEU000:ba_Automobiles | B18: Automobiles | C18: Transportation Energy Use: Highway: Light-Duty Vehicles: Automobiles: Reference case | D18: AEO.2022.REF2022.CNSM_NA_TRN_HWY_LDV_AUTO_NA_TRLBTU.A | E18: trillion Btu | G18: 5662.5596 | H18: 5661.311 | I18: 5580.3618 | J18: 5385.1548 | K18: 5173.79 | L18: 4944.5249 | M18: 4705.0459 | N18: 4466.2534 | O18: 4235.5903 | P18: 4021.8137 | Q18: 3824.6455 | R18: 3639.2983 | S18: 3475.322 | T18: 3329.1929 | U18: 3195.6604 | V18: 3080.0759 | W18: 2983.6606 | X18: 2905.9729 | Y18: 2842.6824 | Z18: 2793.7925 | AA18: 2754.2856 | AB18: 2724.7661 | AC18: 2703.5164 | AD18: 2687.7588 | AE18: 2676.7239 | AF18: 2670.7747 | AG18: 2666.4004 | AH18: 2662.6792 | AI18: 2660.4133 | AJ18: 2659.7957 | AK18: -0.026
A19: TEU000:ba_LightTrucks | B19: Light Trucks | C19: Transportation Energy Use: Highway: Light-Duty Vehicles: Light Trucks: Reference case | D19: AEO.2022.REF2022.CNSM_NA_TRN_HWY_LDV_LTRT_NA_TRLBTU.A | E19: trillion Btu | G19: 8595.6504 | H19: 8985.4844 | I19: 9310.9707 | J19: 9488.1611 | K19: 9660.5303 | L19: 9828.1191 | M19: 9980.8643 | N19: 10117.106 | O19: 10257.05 | P19: 10406.019 | Q19: 10553.271 | R19: 10678.402 | S19: 10808.606 | T19: 10925.13 | U19: 11024.663 | V19: 11114.743 | W19: 11200.276 | X19: 11273.938 | Y19: 11346.748 | Z19: 11415.912 | AA19: 11477.786 | AB19: 11535.846 | AC19: 11590.665 | AD19: 11649.747 | AE19: 11715.222 | AF19: 11789.787 | AG19: 11866.326 | AH19: 11946.238 | AI19: 12033.935 | AJ19: 12132.002 | AK19: 0.012
A20: TEU000:ba_Motorcycles | B20: Motorcycles | C20: Transportation Energy Use: Highway: Light-Duty Vehicles: Motorcycles: Reference case | D20: AEO.2022.REF2022.CNSM_NA_TRN_HWY_LDV_MCYCL_NA_TRLBTU.A | E20: trillion Btu | G20: 16.285139 | H20: 16.281631 | I20: 16.048916 | J20: 15.486917 | K20: 14.87859 | L20: 14.21839 | M20: 13.528482 | N20: 12.841229 | O20: 12.176816 | P20: 11.560631 | Q20: 10.991937 | R20: 10.457605 | S20: 9.983936 | T20: 9.562394 | U20: 9.176792 | V20: 8.842463 | W20: 8.563345 | X20: 8.33895 | Y20: 8.156423 | Z20: 8.015568 | AA20: 7.901921 | AB20: 7.817563 | AC20: 7.757262 | AD20: 7.712647 | AE20: 7.68225 | AF20: 7.666448 | AG20: 7.655192 | AH20: 7.645787 | AI20: 7.640529 | AJ20: 7.639924 | AK20: -0.026
A21: TEU000:ba_CommercialLig | B21: Commercial Light Trucks | C21: Transportation Energy Use: Highway: Commercial Light Trucks: Reference case | D21: AEO.2022.REF2022.CNSM_NA_TRN_HWY_CML_NA_NA_TRLBTU.A | E21: trillion Btu | G21: 888.32336 | H21: 907.56 | I21: 915.29089 | J21: 914.74591 | K21: 917.48145 | L21: 917.95685 | M21: 914.71551 | N21: 913.13898 | O21: 912.94818 | P21: 913.61938 | Q21: 914.8927 | R21: 917.46625 | S21: 921.14691 | T21: 925.47858 | U21: 930.15088 | V21: 935.85309 | W21: 943.34344 | X21: 951.09039 | Y21: 959.00452 | Z21: 967.11505 | AA21: 976.32758 | AB21: 985.92194 | AC21: 996.50336 | AD21: 1007.0494 | AE21: 1017.7682 | AF21: 1030.6398 | AG21: 1041.2024 | AH21: 1050.5197 | AI21: 1061.4025 | AJ21: 1074.7678 | AK21: 0.007
A22: TEU000:ba_Buses | B22: Buses | C22: Transportation Energy Use: Highway: Buses: Reference case | D22: AEO.2022.REF2022.CNSM_NA_TRN_HWY_BUS_NA_NA_TRLBTU.A | E22: trillion Btu | G22: 175.5564 | H22: 199.89397 | I22: 211.87677 | J22: 218.45087 | K22: 222.36423 | L22: 224.93424 | M22: 226.61833 | N22: 227.5876 | O22: 228.09912 | P22: 228.56531 | Q22: 229.05199 | R22: 229.04248 | S22: 228.89539 | T22: 228.66852 | U22: 228.26529 | V22: 228.0228 | W22: 227.88759 | X22: 227.71959 | Y22: 227.01889 | Z22: 226.43184 | AA22: 225.72267 | AB22: 224.89371 | AC22: 224.13243 | AD22: 223.35878 | AE22: 222.4761 | AF22: 221.67345 | AG22: 220.74408 | AH22: 219.68259 | AI22: 218.55473 | AJ22: 217.45403 | AK22: 0.007
A23: TEU000:ba_Transit | B23: Transit | C23: Transportation Energy Use: Highway: Buses: Transit: Reference case | D23: AEO.2022.REF2022.CNSM_NA_TRN_HWY_BUS_TNST_NA_TRLBTU.A | E23: trillion Btu | G23: 75.313232 | H23: 82.089531 | I23: 86.692978 | J23: 90.06427 | K23: 92.38768 | L23: 94.193466 | M23: 95.518471 | N23: 96.276382 | O23: 96.685287 | P23: 97.144073 | Q23: 97.692047 | R23: 97.729561 | S23: 97.570175 | T23: 97.256912 | U23: 96.751549 | V23: 96.316826 | W23: 95.774391 | X23: 95.265297 | Y23: 94.57637 | Z23: 94.018852 | AA23: 93.417526 | AB23: 92.731255 | AC23: 92.131393 | AD23: 91.537315 | AE23: 90.839287 | AF23: 90.224251 | AG23: 89.512222 | AH23: 88.689476 | AI23: 87.816879 | AJ23: 86.980957 | AK23: 0.005
A24: TEU000:ba_Intercity | B24: Intercity | C24: Transportation Energy Use: Highway: Buses: Intercity: Reference case | D24: AEO.2022.REF2022.CNSM_NA_TRN_HWY_BUS_ICYT_NA_TRLBTU.A | E24: trillion Btu | G24: 24.198652 | H24: 27.012306 | I24: 29.212631 | J24: 30.957491 | K24: 32.341728 | L24: 33.455864 | M24: 34.358208 | N24: 35.101486 | O24: 35.729759 | P24: 36.272858 | Q24: 36.745235 | R24: 37.157917 | S24: 37.51918 | T24: 37.836521 | U24: 38.120975 | V24: 38.371075 | W24: 38.58268 | X24: 38.780827 | Y24: 38.998051 | Z24: 39.207397 | AA24: 39.410442 | AB24: 39.611862 | AC24: 39.810284 | AD24: 40.004852 | AE24: 40.19912 | AF24: 40.391823 | AG24: 40.58147 | AH24: 40.771324 | AI24: 40.965553 | AJ24: 41.161907 | AK24: 0.018
A25: TEU000:ba_School | B25: School | C25: Transportation Energy Use: Highway: Buses: School: Reference case | D25: AEO.2022.REF2022.CNSM_NA_TRN_HWY_BUS_SCBU_NA_TRLBTU.A | E25: trillion Btu | G25: 76.044502 | H25: 90.79213 | I25: 95.971184 | J25: 97.429085 | K25: 97.634796 | L25: 97.284904 | M25: 96.741661 | N25: 96.209747 | O25: 95.684082 | P25: 95.148361 | Q25: 94.614685 | R25: 94.155014 | S25: 93.806 | T25: 93.575081 | U25: 93.392754 | V25: 93.334915 | W25: 93.530533 | X25: 93.673462 | Y25: 93.444473 | Z25: 93.205589 | AA25: 92.894691 | AB25: 92.550583 | AC25: 92.190781 | AD25: 91.816612 | AE25: 91.437714 | AF25: 91.057373 | AG25: 90.650406 | AH25: 90.221802 | AI25: 89.772278 | AJ25: 89.311195 | AK25: 0.006
A26: TEU000:ba_FreightTrucks | B26: Freight Trucks | C26: Transportation Energy Use: Highway: Freight Trucks: Reference case | D26: AEO.2022.REF2022.CNSM_NA_TRN_HWY_FGHT_NA_NA_TRLBTU.A | E26: trillion Btu | G26: 5569.2725 | H26: 5649.5093 | I26: 5670.957 | J26: 5665.5723 | K26: 5658.5767 | L26: 5631.4033 | M26: 5582.7314 | N26: 5544.0293 | O26: 5507.4678 | P26: 5466.3779 | Q26: 5425.623 | R26: 5390.0801 | S26: 5360.416 | T26: 5334.1699 | U26: 5316.8242 | V26: 5305.4541 | W26: 5305.1641 | X26: 5310.3726 | Y26: 5318.4966 | Z26: 5330.4346 | AA26: 5350.3921 | AB26: 5378.4546 | AC26: 5406.6211 | AD26: 5437.1548 | AE26: 5469.4419 | AF26: 5506.4971 | AG26: 5534.5332 | AH26: 5554.2827 | AI26: 5588.2158 | AJ26: 5636.1416 | AK26: 0
A27: TEU000:ba_LightMedium | B27: Light Medium | C27: Transportation Energy Use: Highway: Freight Trucks: Light Medium: Reference case | D27: AEO.2022.REF2022.CNSM_NA_TRN_HWY_FGHT_LITEMED_NA_TRLBTU.A | E27: trillion Btu | G27: 665.52826 | H27: 675.73755 | I27: 679.8396 | J27: 681.52075 | K27: 684.33227 | L27: 686.01068 | M27: 687.45282 | N27: 692.34375 | O27: 699.59143 | P27: 707.82782 | Q27: 717.18683 | R27: 727.90259 | S27: 739.33038 | T27: 750.91937 | U27: 763.32794 | V27: 776.34619 | W27: 790.17847 | X27: 803.79956 | Y27: 816.99597 | Z27: 830.3631 | AA27: 845.23755 | AB27: 860.96057 | AC27: 876.38196 | AD27: 892.18866 | AE27: 908.6637 | AF27: 926.35846 | AG27: 943.28998 | AH27: 959.7348 | AI27: 978.50696 | AJ27: 998.97797 | AK27: 0.014
A28: TEU000:ba_Medium | B28: Medium | C28: Transportation Energy Use: Highway: Freight Trucks: Medium: Reference case | D28: AEO.2022.REF2022.CNSM_NA_TRN_HWY_FGHT_MD10T26KLB_NA_TRLBTU.A | E28: trillion Btu | G28: 902.79663 | H28: 910.2464 | I28: 910.66998 | J28: 909.3277 | K28: 909.06567 | L28: 907.93683 | M28: 905.51746 | N28: 906.89618 | O28: 909.27698 | P28: 910.73279 | Q28: 911.58612 | R28: 913.62244 | S28: 916.13269 | T28: 919.15588 | U28: 923.95441 | V28: 930.21252 | W28: 939.30548 | X28: 948.96307 | Y28: 960.3493 | Z28: 972.2785 | AA28: 986.07507 | AB28: 1001.3968 | AC28: 1017.738 | AD28: 1035.2705 | AE28: 1053.4392 | AF28: 1073.0015 | AG28: 1091.3892 | AH28: 1108.6449 | AI28: 1129.6066 | AJ28: 1154.2745 | AK28: 0.009
A29: TEU000:ba_Large(>26000p | B29: Large (> 26000 pounds) | C29: Transportation Energy Use: Highway: Freight Trucks: Large: Reference case | D29: AEO.2022.REF2022.CNSM_NA_TRN_HWY_FGHT_LGT26KLBS_NA_TRLBTU.A | E29: trillion Btu | G29: 4000.948 | H29: 4063.5254 | I29: 4080.448 | J29: 4074.7239 | K29: 4065.1785 | L29: 4037.4561 | M29: 3989.7615 | N29: 3944.7896 | O29: 3898.5999 | P29: 3847.8169 | Q29: 3796.8501 | R29: 3748.5549 | S29: 3704.9529 | T29: 3664.0952 | U29: 3629.542 | V29: 3598.895 | W29: 3575.6804 | X29: 3557.6096 | Y29: 3541.1516 | Z29: 3527.7937 | AA29: 3519.0796 | AB29: 3516.0967 | AC29: 3512.5005 | AD29: 3509.696 | AE29: 3507.3398 | AF29: 3507.1375 | AG29: 3499.8545 | AH29: 3485.9036 | AI29: 3480.1028 | AJ29: 3482.8892 | AK29: -0.005
B30: Non-Highway
A31: TEU000:ca_Air | B31: Air | C31: Transportation Energy Use: Non-Highway: Air: Reference case | D31: AEO.2022.REF2022.CNSM_NA_TRN_AIR_NA_NA_NA_TRLBTU.A | E31: trillion Btu | G31: 2296.1614 | H31: 2683.6514 | I31: 2951.1182 | J31: 3034.7092 | K31: 3111.6895 | L31: 3173.9924 | M31: 3213.9558 | N31: 3252.0549 | O31: 3293.8452 | P31: 3340.3574 | Q31: 3377.2759 | R31: 3393.4851 | S31: 3431.1587 | T31: 3465.1965 | U31: 3501.5168 | V31: 3538.3806 | W31: 3580.7085 | X31: 3619.1714 | Y31: 3663.6863 | Z31: 3712.9866 | AA31: 3753.7881 | AB31: 3799.394 | AC31: 3847.1995 | AD31: 3892.5247 | AE31: 3945.7466 | AF31: 3999.0381 | AG31: 4045.6616 | AH31: 4090.9534 | AI31: 4144.0703 | AJ31: 4203.2158 | AK31: 0.021
A32: TEU000:ca_GeneralAviati | B32: General Aviation | C32: Transportation Energy Use: Non-Highway: Air: General Aviation: Reference case | D32: AEO.2022.REF2022.CNSM_NA_TRN_AIR_GAV_NA_NA_TRLBTU.A | E32: trillion Btu | G32: 130.7076 | H32: 149.14671 | I32: 161.87279 | J32: 165.84467 | K32: 169.50316 | L32: 172.46399 | M32: 174.36215 | N32: 176.17235 | O32: 178.15906 | P32: 180.37123 | Q32: 182.12688 | R32: 182.89687 | S32: 184.68915 | T32: 186.30888 | U32: 188.03725 | V32: 189.79169 | W32: 191.80653 | X32: 193.63768 | Y32: 195.75678 | Z32: 198.104 | AA32: 200.04675 | AB32: 202.21808 | AC32: 204.4942 | AD32: 206.65243 | AE32: 209.18669 | AF32: 211.72415 | AG32: 213.94424 | AH32: 216.10089 | AI32: 218.63011 | AJ32: 221.44669 | AK32: 0.018
A33: TEU000:ca_DomesticAirCa | B33: Domestic Passenger | C33: Transportation Energy Use: Non-Highway: Air: Domestic Passenger: Reference case | D33: AEO.2022.REF2022.CNSM_NA_TRN_AIR_DAC_NA_NA_TRLBTU.A | E33: trillion Btu | G33: 1263.8523 | H33: 1453.1924 | I33: 1523.4235 | J33: 1555.9927 | K33: 1584.8278 | L33: 1613.559 | M33: 1629.1897 | N33: 1643.9263 | O33: 1663.1897 | P33: 1685.9615 | Q33: 1704.4103 | R33: 1720.7582 | S33: 1740.0422 | T33: 1758.0646 | U33: 1774.988 | V33: 1790.6195 | W33: 1807.5457 | X33: 1823.1907 | Y33: 1841.5996 | Z33: 1863.0444 | AA33: 1880.1101 | AB33: 1899.6366 | AC33: 1920.4456 | AD33: 1941.0343 | AE33: 1965.2957 | AF33: 1989.9406 | AG33: 2010.5398 | AH33: 2030.6146 | AI33: 2056.1877 | AJ33: 2084.3064 | AK33: 0.017
A34: TEU000:ca_International | B34: International Passenger | C34: Transportation Energy Use: Non-Highway: Air: International Passenger: Reference case | D34: AEO.2022.REF2022.CNSM_NA_TRN_AIR_IAC_NA_NA_TRLBTU.A | E34: trillion Btu | G34: 340.6817 | H34: 524.7478 | I34: 707.83893 | J34: 747.83081 | K34: 781.49011 | L34: 799.26135 | M34: 811.74396 | N34: 823.71448 | O34: 835.72552 | P34: 848.61224 | Q34: 858.83679 | R34: 860.69806 | S34: 871.02942 | T34: 880.22705 | U34: 890.82617 | V34: 902.13117 | W34: 915.50384 | X34: 927.63263 | Y34: 941.47199 | Z34: 956.38739 | AA34: 969.11621 | AB34: 983.104 | AC34: 997.63446 | AD34: 1011.1772 | AE34: 1026.936 | AF34: 1042.6157 | AG34: 1056.7582 | AH34: 1070.5103 | AI34: 1085.8558 | AJ34: 1102.9905 | AK34: 0.041
A35: TEU000:ca_FreightCarrie | B35: Dedicated Freight | C35: Transportation Energy Use: Non-Highway: Air: Dedicated Freight: Reference case | D35: AEO.2022.REF2022.CNSM_NA_TRN_AIR_DFT_NA_NA_TRLBTU.A | E35: trillion Btu | G35: 560.91974 | H35: 556.56439 | I35: 557.98291 | J35: 565.04108 | K35: 575.86847 | L35: 588.70831 | M35: 598.65997 | N35: 608.242 | O35: 616.77112 | P35: 625.41242 | Q35: 631.90198 | R35: 629.13214 | S35: 635.39783 | T35: 640.59595 | U35: 647.66528 | V35: 655.83844 | W35: 665.85242 | X35: 674.71033 | Y35: 684.85791 | Z35: 695.45062 | AA35: 704.51508 | AB35: 714.43536 | AC35: 724.62524 | AD35: 733.66071 | AE35: 744.32819 | AF35: 754.75763 | AG35: 764.41937 | AH35: 773.72754 | AI35: 783.39673 | AJ35: 794.47205 | AK35: 0.012
A36: TEU000:ca_Water | B36: Water | C36: Transportation Energy Use: Non-Highway: Water: Reference case | D36: AEO.2022.REF2022.CNSM_NA_TRN_WTR_NA_NA_NA_TRLBTU.A | E36: trillion Btu | G36: 1206.7181 | H36: 1275.3909 | I36: 1169.0016 | J36: 1168.2175 | K36: 1168.7708 | L36: 1164.7593 | M36: 1157.3593 | N36: 1152.6595 | O36: 1149.9052 | P36: 1146.202 | Q36: 1149.0189 | R36: 1146.9872 | S36: 1145.8867 | T36: 1145.1604 | U36: 1144.3082 | V36: 1144.1683 | W36: 1144.6188 | X36: 1142.5975 | Y36: 1142.6291 | Z36: 1136.6624 | AA36: 1133.9694 | AB36: 1131.4615 | AC36: 1126.6243 | AD36: 1123.2292 | AE36: 1122.4425 | AF36: 1120.5319 | AG36: 1119.0326 | AH36: 1118.793 | AI36: 1118.5291 | AJ36: 1119.1694 | AK36: -0.003
A37: TEU000:ca_Freight | B37: Freight | C37: Transportation Energy Use: Non-Highway: Water: Freight: Reference case | D37: AEO.2022.REF2022.CNSM_NA_TRN_WTR_FGT_NA_NA_TRLBTU.A | E37: trillion Btu | G37: 1002.621 | H37: 1067.5742 | I37: 960.99731 | J37: 959.59088 | K37: 960.06995 | L37: 956.36987 | M37: 950.25226 | N37: 946.80273 | O37: 944.98975 | P37: 941.93701 | Q37: 945.6145 | R37: 944.3053 | S37: 943.77332 | T37: 943.65192 | U37: 943.50806 | V37: 944.09314 | W37: 944.97284 | X37: 943.48682 | Y37: 944.10333 | Z37: 938.5849 | AA37: 936.68176 | AB37: 934.8537 | AC37: 930.63519 | AD37: 927.88641 | AE37: 927.52887 | AF37: 925.98273 | AG37: 925.12524 | AH37: 925.53802 | AI37: 925.67102 | AJ37: 926.59729 | AK37: -0.003
A38: TEU000:ca_DomesticShipp | B38: Domestic Shipping | C38: Transportation Energy Use: Non-Highway: Water: Freight: Domestic Shipping: Reference case | D38: AEO.2022.REF2022.CNSM_NA_TRN_WTR_DMT_NA_NA_TRLBTU.A | E38: trillion Btu | G38: 75.169693 | H38: 77.553368 | I38: 76.937828 | J38: 74.883781 | K38: 73.008736 | L38: 70.952271 | M38: 68.639519 | N38: 66.460136 | O38: 64.220459 | P38: 62.007294 | Q38: 60.828522 | R38: 59.650131 | S38: 58.55489 | T38: 57.362953 | U38: 56.156143 | V38: 54.998363 | W38: 53.933727 | X38: 52.840008 | Y38: 51.828865 | Z38: 50.803616 | AA38: 50.346043 | AB38: 49.869534 | AC38: 49.358772 | AD38: 48.884739 | AE38: 48.413406 | AF38: 47.972458 | AG38: 47.419342 | AH38: 46.793991 | AI38: 46.348915 | AJ38: 46.08128 | AK38: -0.017
A39: TEU000:da_International | B39: International Shipping | C39: Transportation Energy Use: Non-Highway: Water: Freight: International Shipping: Reference case | D39: AEO.2022.REF2022.CNSM_NA_TRN_WTR_INTS_NA_NA_TRLBTU.A | E39: trillion Btu | G39: 927.45136 | H39: 990.02081 | I39: 884.05951 | J39: 884.70709 | K39: 887.06122 | L39: 885.4176 | M39: 881.61273 | N39: 880.34259 | O39: 880.76929 | P39: 879.92975 | Q39: 884.78595 | R39: 884.65515 | S39: 885.21844 | T39: 886.28894 | U39: 887.35193 | V39: 889.09479 | W39: 891.03912 | X39: 890.64679 | Y39: 892.27448 | Z39: 887.78131 | AA39: 886.33569 | AB39: 884.98419 | AC39: 881.27643 | AD39: 879.00165 | AE39: 879.11548 | AF39: 878.01025 | AG39: 877.70593 | AH39: 878.74402 | AI39: 879.32208 | AJ39: 880.51599 | AK39: -0.002
A40: TEU000:da_RecreationalB | B40: Recreational Boats | C40: Transportation Energy Use: Non-Highway: Water: Recreational Boats: Reference case | D40: AEO.2022.REF2022.CNSM_NA_TRN_WTR_RBT_NA_NA_TRLBTU.A | E40: trillion Btu | G40: 204.09703 | H40: 207.81659 | I40: 208.00427 | J40: 208.62669 | K40: 208.70084 | L40: 208.38937 | M40: 207.10693 | N40: 205.85677 | O40: 204.91547 | P40: 204.265 | Q40: 203.40439 | R40: 202.68185 | S40: 202.11337 | T40: 201.50842 | U40: 200.80013 | V40: 200.07523 | W40: 199.64594 | X40: 199.11072 | Y40: 198.52576 | Z40: 198.07747 | AA40: 197.2876 | AB40: 196.6079 | AC40: 195.98908 | AD40: 195.3428 | AE40: 194.91363 | AF40: 194.54913 | AG40: 193.90735 | AH40: 193.25499 | AI40: 192.858 | AJ40: 192.57214 | AK40: -0.002
A41: TEU000:da_Rail | B41: Rail | C41: Transportation Energy Use: Non-Highway: Rail: Reference case | D41: AEO.2022.REF2022.CNSM_NA_TRN_RAIL_RAIL_NA_NA_TRLBTU.A | E41: trillion Btu | G41: 503.99615 | H41: 511.423 | I41: 517.60669 | J41: 488.4679 | K41: 496.9314 | L41: 507.31833 | M41: 507.62198 | N41: 507.37274 | O41: 506.79187 | P41: 507.47492 | Q41: 508.56488 | R41: 509.50793 | S41: 510.87939 | T41: 506.93988 | U41: 505.75772 | V41: 501.74429 | W41: 502.8458 | X41: 503.04224 | Y41: 503.18256 | Z41: 502.73898 | AA41: 502.80948 | AB41: 503.56192 | AC41: 502.82043 | AD41: 501.57358 | AE41: 501.24579 | AF41: 501.83624 | AG41: 501.41541 | AH41: 501.52655 | AI41: 502.2605 | AJ41: 505.22388 | AK41: 0
A42: TEU000:da_Freight | B42: Freight | C42: Transportation Energy Use: Non-Highway: Rail: Freight: Reference case | D42: AEO.2022.REF2022.CNSM_NA_TRN_RAIL_FGT_NA_NA_TRLBTU.A | E42: trillion Btu | G42: 468.24884 | H42: 471.07889 | I42: 474.2413 | J42: 442.51971 | K42: 448.95673 | L42: 457.64755 | M42: 456.7038 | N42: 455.44904 | O42: 453.94357 | P42: 453.6109 | Q42: 453.71829 | R42: 453.83826 | S42: 454.42358 | T42: 449.77661 | U42: 447.98791 | V42: 443.34918 | W42: 443.77777 | X42: 443.31897 | Y42: 442.87756 | Z42: 441.74304 | AA42: 441.23618 | AB42: 441.40057 | AC42: 440.0022 | AD42: 438.08722 | AE42: 437.03345 | AF42: 436.8085 | AG42: 435.68884 | AH42: 435.13898 | AI42: 435.12531 | AJ42: 437.26294 | AK42: -0.002
... A53: TEU000:fa_Total | B53: Total | C53: Transportation Energy Use: Total: Reference case | D53: AEO.2022.REF2022.CNSM_NA_TRN_NA_TOT_NA_NA_TRLBTU.A | E53: trillion Btu | G53: 26325.32 | H53: 27263.812 | I53: 27693.533 | J53: 27716.109 | K53: 27754.48 | L53: 27728.242 | M53: 27607.809 | N53: 27504.758 | O53: 27409.863 | P53: 27341.646 | Q53: 27289.184 | R53: 27214.672 | S53: 27192.307 | T53: 27166.979 | U53: 27155.459 | V53: 27159.99 | W53: 27208.355 | X53: 27260.936 | Y53: 27335.404 | Z53: 27426.359 | AA53: 27523.195 | AB53: 27636.037 | AC53: 27758.959 | AD53: 27886.777 | AE53: 28039.932 | AF53: 28217.84 | AG53: 28380.809 | AH53: 28538.352 | AI53: 28725.297 | AJ53: 28953.096 | AK53: 0.003
B54: Energy Use by Type
A55: TEU000:ga_MotorGasoline | B55: Motor Gasoline excluding E85 | C55: Transportation Energy Use: Petroleum: Motor Gasoline: Reference case | D55: AEO.2022.REF2022.CNSM_NA_TRN_NA_PET_MGS_NA_TRLBTU.A | E55: trillion Btu | G55: 15498.281 | H55: 15897.141 | I55: 16137.845 | J55: 16107.379 | K55: 16058.004 | L55: 15983.128 | M55: 15877.661 | N55: 15760.836 | O55: 15658.563 | P55: 15583.214 | Q55: 15522.64 | R55: 15454.544 | S55: 15413.687 | T55: 15378.898 | U55: 15340.438 | V55: 15311.306 | W55: 15300.468 | X55: 15296.752 | Y55: 15307.189 | Z55: 15328.766 | AA55: 15355.349 | AB55: 15389.863 | AC55: 15429.481 | AD55: 15479.829 | AE55: 15542.129 | AF55: 15621.055 | AG55: 15701.366 | AH55: 15784.323 | AI55: 15880.244 | AJ55: 15991.699 | AK55: 0.001
A56: TEU000:ga_Ethanol | B56: E85 | C56: Transportation Energy Use: E85: Reference case | D56: AEO.2022.REF2022.CNSM_NA_TRN_NA_E85_NA_NA_TRLBTU.A | E56: trillion Btu | G56: 37.409657 | H56: 38.440613 | I56: 36.00972 | J56: 35.717388 | K56: 35.547005 | L56: 34.855843 | M56: 34.025654 | N56: 33.089924 | O56: 32.310158 | P56: 31.427309 | Q56: 30.473276 | R56: 29.687052 | S56: 29.405977 | T56: 28.303238 | U56: 27.885773 | V56: 28.294489 | W56: 28.540981 | X56: 28.545448 | Y56: 29.029167 | Z56: 29.517008 | AA56: 30.01403 | AB56: 30.768532 | AC56: 31.439165 | AD56: 32.125431 | AE56: 32.923443 | AF56: 33.740028 | AG56: 34.665287 | AH56: 35.671249 | AI56: 36.730343 | AJ56: 37.897232 | AK56: 0
A57: TEU000:ga_Distillate(di | B57: Diesel | C57: Transportation Energy Use: Petroleum: Diesel: Reference case | D57: AEO.2022.REF2022.CNSM_NA_TRN_NA_PET_DSL_NA_TRLBTU.A | E57: trillion Btu | G57: 6496.4019 | H57: 6492.2397 | I57: 6629.9468 | J57: 6591.0215 | K57: 6583.6763 | L57: 6560.2617 | M57: 6507.6304 | N57: 6459.8799 | O57: 6408.2275 | P57: 6355.5161 | Q57: 6300.0869 | R57: 6250.1699 | S57: 6206.5898 | T57: 6160.2949 | U57: 6123.2441 | V57: 6088.3584 | W57: 6066.2617 | X57: 6051.5781 | Y57: 6037.0952 | Z57: 6029.3486 | AA57: 6026.0874 | AB57: 6030.0229 | AC57: 6033.2744 | AD57: 6034.8154 | AE57: 6038.0742 | AF57: 6045.7715 | AG57: 6043.999 | AH57: 6033.9683 | AI57: 6035.5244 | AJ57: 6050.2021 | AK57: -0.002
A58: TEU000:ga_JetFuel(keros | B58: Jet Fuel (kerosene & naphtha) | C58: Transportation Energy Use: Petroleum: Jet Fuel: Reference case | D58: AEO.2022.REF2022.UNC_NA_TRN_NA_PET_JFL_NA_TRLBTU.A | E58: trillion Btu | G58: 2675.8489 | H58: 3069.8179 | I58: 3333.825 | J58: 3417.0884 | K58: 3496.6003 | L58: 3560.8337 | M58: 3602.2207 | N58: 3641.9473 | O58: 3682.7163 | P58: 3730.5896 | Q58: 3767.1147 | R58: 3783.4758 | S58: 3821.2751 | T58: 3855.418 | U58: 3891.8242 | V58: 3928.884 | W58: 3971.4771 | X58: 4010.2026 | Y58: 4054.9788 | Z58: 4104.5386 | AA58: 4145.5972 | AB58: 4191.458 | AC58: 4239.5171 | AD58: 4285.0933 | AE58: 4338.5649 | AF58: 4392.104 | AG58: 4438.9731 | AH58: 4484.5098 | AI58: 4537.8691 | AJ58: 4597.2559 | AK58: 0.019
A59: TEU000:ga_ResidualOil | B59: Residual Fuel Oil | C59: Transportation Energy Use: Petroleum: Residual Fuel Oil: Reference case | D59: AEO.2022.REF2022.CNSM_NA_TRN_NA_PET_RFO_NA_TRLBTU.A | E59: trillion Btu | G59: 558.12335 | H59: 748.90198 | I59: 523.45557 | J59: 522.68378 | K59: 526.93713 | L59: 520.56867 | M59: 508.53278 | N59: 503.42752 | O59: 502.67056 | P59: 498.65405 | Q59: 509.99155 | R59: 507.99564 | S59: 507.87897 | T59: 509.09653 | U59: 510.3884 | V59: 513.55164 | W59: 517.25079 | X59: 514.66571 | Y59: 517.55798 | Z59: 503.91544 | AA59: 498.49164 | AB59: 493.30075 | AC59: 481.63867 | AD59: 473.86624 | AE59: 472.55453 | AF59: 467.90671 | AG59: 465.41754 | AH59: 466.60858 | AI59: 466.47327 | AJ59: 467.89331 | AK59: -0.006
A60: TEU000:ga_AviationGasol | B60: Aviation Gasoline | C60: Transportation Energy Use: Petroleum: Aviation Gasoline: Reference case | D60: AEO.2022.REF2022.CNSM_NA_TRN_NA_PET_AVGA_NA_TRLBTU.A | E60: trillion Btu | G60: 22.434891 | H60: 22.421618 | I60: 22.410635 | J60: 22.401548 | K60: 22.394032 | L60: 22.387812 | M60: 22.382666 | N60: 22.378407 | O60: 22.374884 | P60: 22.371969 | Q60: 22.369558 | R60: 22.367563 | S60: 22.365911 | T60: 22.364546 | U60: 22.363417 | V60: 22.36248 | W60: 22.361708 | X60: 22.361067 | Y60: 22.360538 | Z60: 22.3601 | AA60: 22.359737 | AB60: 22.359438 | AC60: 22.35919 | AD60: 22.358984 | AE60: 22.358814 | AF60: 22.358673 | AG60: 22.358557 | AH60: 22.358461 | AI60: 22.358381 | AJ60: 22.358315 | AK60: 0
A61: TEU000:ga_LiquefiedPetr | B61: Propane | C61: Transportation Energy Use: Petroleum: Propane: Reference case | D61: AEO.2022.REF2022.CNSM_NA_TRN_NA_PET_PROP_NA_TRLBTU.A | E61: trillion Btu | G61: 6.906717 | H61: 8.07742 | I61: 8.739411 | J61: 9.05189 | K61: 9.425159 | L61: 9.759268 | M61: 10.047401 | N61: 10.104795 | O61: 10.347483 | P61: 10.614594 | Q61: 10.879387 | R61: 11.138477 | S61: 11.407876 | T61: 11.687796 | U61: 11.969448 | V61: 12.265259 | W61: 12.585253 | X61: 12.911563 | Y61: 13.225584 | Z61: 13.556355 | AA61: 13.90135 | AB61: 14.255974 | AC61: 14.617752 | AD61: 14.986189 | AE61: 15.371302 | AF61: 15.784579 | AG61: 16.19943 | AH61: 16.617161 | AI61: 17.068151 | AJ61: 17.569765 | AK61: 0.033
A62: TEU000:ga_Lubricants | B62: Lubricants | C62: Transportation Energy Use: Petroleum: Lubricants: Reference case | D62: AEO.2022.REF2022.CNSM_NA_TRN_NA_PET_LBC_NA_TRLBTU.A | E62: trillion Btu | G62: 125.03158 | H62: 126.89674 | I62: 127.92604 | J62: 128.60027 | K62: 129.1019 | L62: 129.64999 | M62: 129.96121 | N62: 130.19676 | O62: 130.40361 | P62: 130.57878 | Q62: 130.71516 | R62: 130.83389 | S62: 130.94083 | T62: 131.02644 | U62: 131.09085 | V62: 131.16414 | W62: 131.26132 | X62: 131.36519 | Y62: 131.48392 | Z62: 131.63141 | AA62: 131.76234 | AB62: 131.87556 | AC62: 131.99271 | AD62: 132.1015 | AE62: 132.23047 | AF62: 132.3692 | AG62: 132.48219 | AH62: 132.58585 | AI62: 132.70448 | AJ62: 132.83112 | AK62: 0.002
A63: TEU000:ga_PetroleumSubt | B63: Petroleum and Other Liquids Subtotal | C63: Transportation Energy Use: Petroleum Subtotal: Reference case | D63: AEO.2022.REF2022.CNSM_NA_TRN_NA_PET_NA_NA_TRLBTU.A | E63: trillion Btu | G63: 25420.439 | H63: 26403.939 | I63: 26820.156 | J63: 26833.943 | K63: 26861.686 | L63: 26821.447 | M63: 26692.461 | N63: 26561.861 | O63: 26447.615 | P63: 26362.967 | Q63: 26294.27 | R63: 26190.215 | S63: 26143.553 | T63: 26097.09 | U63: 26059.205 | V63: 26036.188 | W63: 26050.207 | X63: 26068.383 | Y63: 26112.922 | Z63: 26163.633 | AA63: 26223.561 | AB63: 26303.902 | AC63: 26384.32 | AD63: 26475.178 | AE63: 26594.207 | AF63: 26731.09 | AG63: 26855.463 | AH63: 26976.645 | AI63: 27128.973 | AJ63: 27317.707 | AK63: 0.002
A64: TEU000:ga_Methanol | B64: M85 | C64: Transportation Energy Use: M85: Reference case | D64: AEO.2022.REF2022.CNSM_NA_TRN_NA_M85_NA_NA_TRLBTU.A | E64: trillion Btu | G64: 0 | H64: 0 | I64: 0 | J64: 0 | K64: 0 | L64: 0 | M64: 0 | N64: 0 | O64: 0 | P64: 0 | Q64: 0 | R64: 0 | S64: 0 | T64: 0 | U64: 0 | V64: 0 | W64: 0 | X64: 0 | Y64: 0 | Z64: 0 | AA64: 0 | AB64: 0 | AC64: 0 | AD64: 0 | AE64: 0 | AF64: 0 | AG64: 0 | AH64: 0 | AI64: 0 | AJ64: 0 | AK64: - -
A65: TEU000:ga_Electricity | B65: Electricity | C65: Transportation Energy Use: Electricity: Reference case | D65: AEO.2022.REF2022.CNSM_NA_TRN_NA_ELC_NA_NA_TRLBTU.A | E65: trillion Btu | G65: 44.104729 | H65: 56.240578 | I65: 69.13517 | J65: 82.721107 | K65: 96.866806 | L65: 111.51833 | M65: 126.12091 | N65: 140.47661 | O65: 154.8988 | P65: 169.65961 | Q65: 184.7235 | R65: 199.69844 | S65: 214.91594 | T65: 230.29071 | U65: 245.68015 | V65: 261.23288 | W65: 277.05438 | X65: 293.02951 | Y65: 309.18445 | Z65: 325.5415 | AA65: 341.8157 | AB65: 358.086 | AC65: 374.72705 | AD65: 391.70364 | AE65: 408.88974 | AF65: 426.02393 | AG65: 443.20725 | AH65: 460.47812 | AI65: 478.19519 | AJ65: 496.65753 | AK65: 0.087
A66: TEU000:ga_CompressedNat | B66: Compressed/Liquefied Natural Gas | C66: Transportation Energy Use: Natural Gas: Reference case | D66: AEO.2022.REF2022.CNSM_NA_TRN_NA_NG_NA_NA_TRLBTU.A | E66: trillion Btu | G66: 110.50194 | H66: 99.974213 | I66: 118.70307 | J66: 126.95818 | K66: 134.62819 | L66: 145.19629 | M66: 156.64154 | N66: 165.51674 | O66: 174.62009 | P66: 184.20355 | Q66: 188.38626 | R66: 198.76137 | S66: 207.59207 | T66: 215.71481 | U66: 224.78955 | V66: 233.09135 | W66: 243.02911 | X66: 254.08615 | Y66: 262.77145 | Z66: 278.23254 | AA66: 290.93896 | AB66: 303.42172 | AC66: 320.04666 | AD66: 336.42462 | AE66: 348.77939 | AF66: 364.37189 | AG66: 377.22821 | AH66: 387.99915 | AI66: 400.49878 | AJ66: 413.50238 | AK66: 0.047
A67: TEU000:ga_LiquidHydroge | B67: Hydrogen | C67: Transportation Energy Use: Hydrogen: Reference case | D67: AEO.2022.REF2022.CNSM_NA_TRN_NA_HDG_NA_NA_TRLBTU.A | E67: trillion Btu | G67: 0.379081 | H67: 0.504824 | I67: 0.634451 | J67: 0.75851 | K67: 0.891351 | L67: 1.03494 | M67: 1.188964 | N67: 1.354496 | O67: 1.532376 | P67: 1.723086 | Q67: 1.926877 | R67: 2.138948 | S67: 2.356639 | T67: 2.576108 | U67: 2.791301 | V67: 2.999512 | W67: 3.198714 | X67: 3.392779 | Y67: 3.585047 | Z67: 3.774554 | AA67: 3.955084 | AB67: 4.132504 | AC67: 4.302669 | AD67: 4.465927 | AE67: 4.631506 | AF67: 4.793143 | AG67: 4.948122 | AH67: 5.094355 | AI67: 5.233084 | AJ67: 5.365827 | AK67: 0.096
A68: TEU000:ga_PipelineFuelN | B68: Pipeline Fuel Natural Gas | C68: Transportation Energy Use: Pipeline Fuel Natural Gas: Reference case | D68: AEO.2022.REF2022.CNSM_NA_TRN_PIPL_NG_NA_NA_TRLBTU.A | E68: trillion Btu | G68: 748.06146 | H68: 701.06183 | I68: 682.70349 | J68: 669.31574 | K68: 657.77765 | L68: 646.21258 | M68: 628.37183 | N68: 632.31946 | O68: 627.75476 | P68: 619.43811 | Q68: 616.01282 | R68: 619.79211 | S68: 619.58685 | T68: 616.83026 | U68: 618.30475 | V68: 621.5434 | W68: 629.67157 | X68: 636.62567 | Y68: 641.26691 | Z68: 649.24738 | AA68: 656.71551 | AB68: 659.97137 | AC68: 668.71802 | AD68: 671.82458 | AE68: 675.8764 | AF68: 683.62018 | AG68: 691.62048 | AH68: 699.38654 | AI68: 703.1933 | AJ68: 710.15021 | AK68: -0.002
A69: TEU000:ha_TotalConsumpt | B69: Total Consumption | C69: Transportation: Total Energy Use: Reference case | D69: AEO.2022.REF2022.CNSM_NA_TRN_NA_NA_NA_NA_TRLBTU.A | E69: trillion Btu | G69: 26323.486 | H69: 27261.721 | I69: 27691.332 | J69: 27713.697 | K69: 27751.85 | L69: 27725.408 | M69: 27604.783 | N69: 27501.531 | O69: 27406.42 | P69: 27337.99 | Q69: 27285.32 | R69: 27210.607 | S69: 27188.004 | T69: 27162.502 | U69: 27150.77 | V69: 27155.055 | W69: 27203.162 | X69: 27255.516 | Y69: 27329.73 | Z69: 27420.43 | AA69: 27516.986 | AB69: 27629.514 | AC69: 27752.115 | AD69: 27879.596 | AE69: 28032.385 | AF69: 28209.898 | AG69: 28372.467 | AH69: 28529.604 | AI69: 28716.092 | AJ69: 28943.383 | AK69: 0.003

Sheet AEO 2021 Table 35
A1: ORIGINAL EIA CODE | F1: 2020 | G1: 2021 | H1: 2022 | I1: 2023 | J1: 2024 | K1: 2025 | L1: 2026 | M1: 2027 | N1: 2028 | O1: 2029 | P1: 2030 | Q1: 2031 | R1: 2032 | S1: 2033 | T1: 2034 | U1: 2035 | V1: 2036 | W1: 2037 | X1: 2038 | Y1: 2039 | Z1: 2040 | AA1: 2041 | AB1: 2042 | AC1: 2043 | AD1: 2044 | AE1: 2045 | AF1: 2046 | AG1: 2047 | AH1: 2048 | AI1: 2049 | AJ1: 2050 | AK1: Growth (2020-2050)
A10: TEU000 | B10: Table 35. Transportation Sector Energy Use by Mode and Type
B11: https://www.eia.gov/outlooks/aeo/data/browser/#/?id=45-AEO2021&region=0-0&cases=highogs&start=2019&end=2050&f=A&sourcekey=0
B12: Tue Mar 09 2021 10:51:32 GMT-0800 (Pacific Standard Time)
B13: Source: U.S. Energy Information Administration
C14: full name | D14: api key | E14: units | F14: 2020 | G14: 2021 | H14: 2022 | I14: 2023 | J14: 2024 | K14: 2025 | L14: 2026 | M14: 2027 | N14: 2028 | O14: 2029 | P14: 2030 | Q14: 2031 | R14: 2032 | S14: 2033 | T14: 2034 | U14: 2035 | V14: 2036 | W14: 2037 | X14: 2038 | Y14: 2039 | Z14: 2040 | AA14: 2041 | AB14: 2042 | AC14: 2043 | AD14: 2044 | AE14: 2045 | AF14: 2046 | AG14: 2047 | AH14: 2048 | AI14: 2049 | AJ14: 2050 | AK14: Growth (2020-2050)
B15: Energy Use by Mode | D15: 45-AEO2021.2.
B16: Highway | D16: 45-AEO2021.3.
A17: TEU000:ba_Light-DutyVeh | B17: Light-Duty Vehicles | C17: Transportation Energy Use: Highway: Light-Duty Vehicles: High oil and gas supply | D17: 45-AEO2021.4.highogs-d120120a | E17: trillion Btu | F17: 13684.959 | G17: 14333.232 | H17: 14327.021 | I17: 14365.353 | J17: 14366.454 | K17: 14341.867 | L17: 14287.134 | M17: 14207.24 | N17: 14125.377 | O17: 14028.782 | P17: 13931.946 | Q17: 13831.038 | R17: 13740.6 | S17: 13671.223 | T17: 13614.178 | U17: 13578.905 | V17: 13555.065 | W17: 13533.014 | X17: 13512.937 | Y17: 13507.699 | Z17: 13519.428 | AA17: 13531.689 | AB17: 13551.022 | AC17: 13573.049 | AD17: 13591.697 | AE17: 13608.703 | AF17: 13631.723 | AG17: 13650.464 | AH17: 13676.699 | AI17: 13706.515 | AJ17: 13736.45 | AK17: 0
A18: TEU000:ba_Automobiles | B18: Automobiles | C18: Transportation Energy Use: Highway: Light-Duty Vehicles: Automobiles: High oil and gas supply | D18: 45-AEO2021.5.highogs-d120120a | E18: trillion Btu | F18: 5675.0977 | G18: 5849.8979 | H18: 5755.2529 | I18: 5674.1973 | J18: 5571.2588 | K18: 5452.5518 | L18: 5322.6035 | M18: 5185.96 | N18: 5050.46 | O18: 4913.0923 | P18: 4785.4287 | Q18: 4662.6523 | R18: 4550.6763 | S18: 4453.6479 | T18: 4370.249 | U18: 4301.7231 | V18: 4245.416 | W18: 4198.5293 | X18: 4159.6685 | Y18: 4129.9312 | Z18: 4109.8428 | AA18: 4093.1614 | AB18: 4081.1697 | AC18: 4071.9587 | AD18: 4063.4624 | AE18: 4055.2773 | AF18: 4048.9263 | AG18: 4041.3586 | AH18: 4035.5654 | AI18: 4031.2227 | AJ18: 4027.0671 | AK18: -0.011
A19: TEU000:ba_LightTrucks | B19: Light Trucks | C19: Transportation Energy Use: Highway: Light-Duty Vehicles: Light Trucks: High oil and gas supply | D19: 45-AEO2021.6.highogs-d120120a | E19: trillion Btu | F19: 7993.563 | G19: 8466.5332 | H19: 8555.2402 | I19: 8674.8594 | J19: 8779.1953 | K19: 8873.6572 | L19: 8949.2451 | M19: 9006.3877 | N19: 9060.4141 | O19: 9101.5811 | P19: 9132.7764 | Q19: 9154.9971 | R19: 9176.8564 | S19: 9204.7871 | T19: 9231.3809 | U19: 9264.832 | V19: 9297.46 | W19: 9322.4297 | X19: 9341.3252 | Y19: 9365.9111 | Z19: 9397.7852 | AA19: 9426.7773 | AB19: 9458.1357 | AC19: 9489.3994 | AD19: 9516.5684 | AE19: 9541.7832 | AF19: 9571.1719 | AG19: 9597.5029 | AH19: 9629.5479 | AI19: 9663.7188 | AJ19: 9697.8213 | AK19: 0.006
A20: TEU000:ba_Motorcycles | B20: Motorcycles | C20: Transportation Energy Use: Highway: Light-Duty Vehicles: Motorcycles: High oil and gas supply | D20: 45-AEO2021.7.highogs-d120120a | E20: trillion Btu | F20: 16.299149 | G20: 16.800869 | H20: 16.528765 | I20: 16.295639 | J20: 15.999691 | K20: 15.658419 | L20: 15.284882 | M20: 14.89215 | N20: 14.502714 | O20: 14.107929 | P20: 13.741054 | Q20: 13.388216 | R20: 13.066401 | S20: 12.787572 | T20: 12.547906 | U20: 12.350933 | V20: 12.189022 | W20: 12.054244 | X20: 11.942542 | Y20: 11.85706 | Z20: 11.799364 | AA20: 11.751442 | AB20: 11.71702 | AC20: 11.690611 | AD20: 11.666224 | AE20: 11.642757 | AF20: 11.624537 | AG20: 11.602818 | AH20: 11.586204 | AI20: 11.573715 | AJ20: 11.561806 | AK20: -0.011
A21: TEU000:ba_CommercialLig | B21: Commercial Light Trucks | C21: Transportation Energy Use: Highway: Commercial Light Trucks: High oil and gas supply | D21: 45-AEO2021.8.highogs-d120120a | E21: trillion Btu | F21: 800.59766 | G21: 824.58264 | H21: 837.18012 | I21: 842.73663 | J21: 851.00818 | K21: 861.96362 | L21: 867.17664 | M21: 868.25635 | N21: 868.72144 | O21: 868.14349 | P21: 868.26971 | Q21: 869.091 | R21: 871.65924 | S21: 875.05597 | T21: 880.52374 | U21: 888.54584 | V21: 896.60486 | W21: 904.57898 | X21: 913.07678 | Y21: 922.39557 | Z21: 932.01129 | AA21: 942.83514 | AB21: 953.38037 | AC21: 965.23499 | AD21: 976.00677 | AE21: 987.21423 | AF21: 999.34717 | AG21: 1008.7945 | AH21: 1019.4604 | AI21: 1031.4871 | AJ21: 1044.0883 | AK21: 0.009
A22: TEU000:ba_Buses | B22: Buses | C22: Transportation Energy Use: Highway: Buses: High oil and gas supply | D22: 45-AEO2021.9.highogs-d120120a | E22: trillion Btu | F22: 123.60058 | G22: 155.22908 | H22: 178.08673 | I22: 194.79402 | J22: 207.08707 | K22: 215.93285 | L22: 222.4467 | M22: 227.38673 | N22: 229.82677 | O22: 231.57542 | P22: 233.38449 | Q22: 233.90918 | R22: 234.57722 | S22: 234.89816 | T22: 235.11737 | U22: 234.73181 | V22: 234.535 | W22: 234.32896 | X22: 233.97902 | Y22: 233.39026 | Z22: 232.92192 | AA22: 232.25186 | AB22: 231.51384 | AC22: 230.76698 | AD22: 230.02493 | AE22: 229.27586 | AF22: 228.442 | AG22: 227.6967 | AH22: 226.85817 | AI22: 226.28667 | AJ22: 225.79506 | AK22: 0.02
A23: TEU000:ba_Transit | B23: Transit | C23: Transportation Energy Use: Highway: Buses: Transit: High oil and gas supply | D23: 45-AEO2021.10.highogs-d120120a | E23: trillion Btu | F23: 65.868385 | G23: 77.343925 | H23: 85.037193 | I23: 90.397377 | J23: 94.148392 | K23: 96.454201 | L23: 98.028534 | M23: 99.228485 | N23: 98.787506 | O23: 98.326218 | P23: 98.456612 | Q23: 97.730179 | R23: 97.429573 | S23: 97.078491 | T23: 96.865768 | U23: 96.19072 | V23: 95.827606 | W23: 95.546768 | X23: 95.188217 | Y23: 94.635986 | Z23: 94.23497 | AA23: 93.65612 | AB23: 93.025208 | AC23: 92.393784 | AD23: 91.770996 | AE23: 91.134651 | AF23: 90.408363 | AG23: 89.765427 | AH23: 89.013596 | AI23: 88.517876 | AJ23: 88.092033 | AK23: 0.01
A24: TEU000:ba_Intercity | B24: Intercity | C24: Transportation Energy Use: Highway: Buses: Intercity: High oil and gas supply | D24: 45-AEO2021.11.highogs-d120120a | E24: trillion Btu | F24: 21.389296 | G24: 24.819853 | H24: 27.510082 | I24: 29.622658 | J24: 31.287823 | K24: 32.605827 | L24: 33.663296 | M24: 34.520813 | N24: 35.224197 | O24: 35.81303 | P24: 36.317593 | Q24: 36.759636 | R24: 37.152344 | S24: 37.510296 | T24: 37.844872 | U24: 38.157986 | V24: 38.449917 | W24: 38.72361 | X24: 38.985104 | Y24: 39.238808 | Z24: 39.486942 | AA24: 39.72662 | AB24: 39.958668 | AC24: 40.184944 | AD24: 40.404293 | AE24: 40.622166 | AF24: 40.834713 | AG24: 41.040451 | AH24: 41.248081 | AI24: 41.453495 | AJ24: 41.657665 | AK24: 0.022
A25: TEU000:ba_School | B25: School | C25: Transportation Energy Use: Highway: Buses: School: High oil and gas supply | D25: 45-AEO2021.12.highogs-d120120a | E25: trillion Btu | F25: 36.342903 | G25: 53.065319 | H25: 65.539474 | I25: 74.77401 | J25: 81.650841 | K25: 86.872803 | L25: 90.754913 | M25: 93.637444 | N25: 95.815033 | O25: 97.436134 | P25: 98.610291 | Q25: 99.419357 | R25: 99.995285 | S25: 100.30936 | T25: 100.40678 | U25: 100.38309 | V25: 100.25748 | W25: 100.05856 | X25: 99.805702 | Y25: 99.51545 | Z25: 99.200005 | AA25: 98.869118 | AB25: 98.529976 | AC25: 98.188255 | AD25: 97.849648 | AE25: 97.519051 | AF25: 97.198906 | AG25: 96.890816 | AH25: 96.596497 | AI25: 96.315292 | AJ25: 96.04538 | AK25: 0.033
