Workbook
Name a: [1]ISICrev3.1!$E:$F
Name Calculated_Relationship_HS12___HS07: '[2]Correlation HS2012-HS2007'!#REF!
Name CAP_CT: #REF!
Name CAP_CT: #REF!
Name CAP_CT: #REF!
Name CAP_CT: #REF!
Name CAP_GFCF: #REF!
Name CAP_GFCF: #REF!
Name CAP_GFCF: #REF!
Name CAP_GFCF: #REF!
Name CAP_IT: #REF!
Name CAP_IT: #REF!
Name CAP_IT: #REF!
Name CAP_IT: #REF!
Name CAP_OCon: #REF!
Name CAP_OCon: #REF!
Name CAP_OCon: #REF!
Name CAP_OCon: #REF!
Name CAP_OMach: #REF!
Name CAP_OMach: #REF!
Name CAP_OMach: #REF!
Name CAP_OMach: #REF!
Name CAP_Other: #REF!
Name CAP_Other: #REF!
Name CAP_Other: #REF!
Name CAP_Other: #REF!
Name CAP_QI: #REF!
Name CAP_QI: #REF!
Name CAP_QI: #REF!
Name CAP_QI: #REF!
Name CAP_RStruc: #REF!
Name CAP_RStruc: #REF!
Name CAP_RStruc: #REF!
Name CAP_RStruc: #REF!
Name CAP_Soft: #REF!
Name CAP_Soft: #REF!
Name CAP_Soft: #REF!
Name CAP_Soft: #REF!
Name CAP_TraEq: #REF!
Name CAP_TraEq: #REF!
Name CAP_TraEq: #REF!
Name CAP_TraEq: #REF!
Name CAPIT: #REF!
Name CAPIT: #REF!
Name CAPIT: #REF!
Name CAPIT: #REF!
Name CAPIT_QI: #REF!
Name CAPIT_QI: #REF!
Name CAPIT_QI: #REF!
Name CAPIT_QI: #REF!
Name capit_qph: #REF!
Name capit_qph: #REF!
Name capit_qph: #REF!
Name capit_qph: #REF!
Name CAPNIT: #REF!
Name CAPNIT: #REF!
Name CAPNIT: #REF!
Name CAPNIT: #REF!
Name CAPNIT_QI: #REF!
Name CAPNIT_QI: #REF!

Sheet About
A1: FoGPbEaIC Fraction of Goods Purchased by Entity and ISIC Code
A3: Source: | B3: All Industries
B4: see variable io-model/DLIM
B5: see variable io-model/BOibC
B6: see variable io-model/GAaHEbIC-government
B7: see variable io-model/GaHEbIC-household
B9: Split for Chemicals/Pharmaceuticals
B10: World Input-Output Database
B11: 2016
B12: National IO Tables
B13: http://www.wiod.org/database/niots16
B14: Mexico NIOT, 2014
B16: Split for All Other ISIC Codes
B17: Exiobase
B18: 2019
B19: Exiobase 3rx, 2016
B20: https://zenodo.org/record/2654460#.YEFjHmhKg2w
B21: MEX, exports
A23: Notes
A25: Data Source
A26: The OECD input-output tables use ISIC codes that do not map well onto EPS industry categories.
A27: The following industry categories are particularly problematic for mapping onto OECD:
B28: chemicals (OECD doesn't split out pharmaceuticals)
B29: natural gas and petroleum systems
B30: coal mining
B31: waste management (water + waste)
A33: Also, even the industries that are mappable to OECD (such as iron and steel) can be improved by
A34: using a more disaggregated data source that (for example) breaks out iron and steel from other metals.
A36: Accordingly, we use the variables DLIM and BOIbC to break out the OECD data in several places. See the file io-model/DLIM
A37: for more information on the steps to transform a DLIM table into a standard input-output matrix. Ideally, we would use
A38: a Total Leontief Inverse matrix rather than a Domestic Leontief Inverse matrix for this step, but our source data does not provide
A39: that information.
A41: Procedure
A42: We calculate the share of each industry's output purchased by each ISIC code, disregarding
A43: the cash flow entities that are not assigned ISIC codes, such that the shares assigned to all
A44: ISIC codes sum to 100%. Note that this requires dividing by the total output from each industry
A45: to all ISIC codes in the denominator ourselves, since using the "Total Intermediate" column (col OS)
A46: from the BEA table introduces too much rounding error, and this is visible in EPS outputs.
... A66: the five energy supplier entities, does not introduce error.

Sheet ISIC Crosswalk
I1: OECD Version | J1: OECD ISIC
A2: ISIC 05 | B2: 05 | C2: Mining of coal and lignite | I2: 2021 | J2: CONS_ABR: Direct purchases abroad by residents (imports)
B3: 051 | C3: Mining of hard coal | I3: 2021 | J3: CONS_NONRES: Direct purchases by non-residents (exports)
B4: 052 | C4: Mining of lignite | I4: 2021 | J4: D01T02: Agriculture, hunting, forestry
A5: ISIC 06 | B5: 06 | C5: Extraction of crude petroleum & natural gas | I5: 2018 | J5: D01T03: Agriculture, forestry and fishing | K5: ISIC 01T03
B6: 061 | C6: Extraction of crude petroleum | I6: 2021 | J6: D03: Fishing and aquaculture
B7: 062 | C7: Extraction of natural gas | I7: 2018 | J7: D05T06: Mining and extraction of energy producing products
A8: ISIC 07T08 | B8: 07 | C8: Mining of metal ores | I8: 2021 | J8: D05T06: Mining and quarrying, energy producing products
B9: 071 | C9: Mining of iron ores | I9: 2018 | J9: D07T08: Mining and quarrying of non-energy producing products
B10: 072 | C10: Mining of non-ferrous metal ores | I10: 2021 | J10: D07T08: Mining and quarrying, non-energy producing products | K10: ISIC 07T08
A11: ISIC 07T08 | B11: 08 | C11: Other mining and quarrying | I11: 2021 | J11: D09: Mining support service activities | K11: ISIC 09
B12: 081 | C12: Quarrying of stone, sand and clay | I12: 2021 | J12: D10T12: Food products, beverages and tobacco | K12: ISIC 10T12
B13: 089 | C13: Mining and quarrying n.e.c. | I13: 2021 | J13: D13T15: Textiles, textile products, leather and footwear | K13: ISIC 13T15
A14: ISIC 09 | B14: 09 | C14: Mining support service activities | I14: 2018 | J14: D13T15: Textiles, wearing apparel, leather and related products
B15: 091 | C15: Support activities for petroleum | I15: 2021 | J15: D16: Wood and products of wood and cork | K15: ISIC 16
B16: 099 | C16: Support activities for other mining, quarrying | I16: 2021 | J16: D17T18: Paper products and printing | K16: ISIC 17T18
B17: 0B | C17: Mining and quarrying | I17: 2021 | J17: D19: Coke and refined petroleum products | K17: ISIC 19
B18: 35 | C18: Electricity, gas, steam & air conditioning | I18: 2021 | J18: D20: Chemical and chemical products | K18: ISIC 20
A19: ISIC 351 | B19: 351 | C19: Electric power generation, transmission | I19: 2018 | J19: D20T21: Chemicals and pharmaceutical products
A20: ISIC 352T353 | B20: 352 | C20: Manufacture of gas | I20: 2021 | J20: D21: Pharmaceuticals, medicinal chemical and botanical products | K20: ISIC 21
A21: ISIC 352T353 | B21: 353 | C21: Steam and air conditioning supply | I21: 2018 | J21: D22: Rubber and plastic products | K21: ISIC 22
B22: 35D | C22: Electricity, gas, steam & air conditioning | I22: 2021 | J22: D22: Rubber and plastics products
A23: ISIC 36T39 | B23: 36 | C23: Water collection, treatment and supply | I23: 2021 | J23: D23: Other non-metallic mineral products
B24: 360 | C24: Water collection, treatment and supply | I24: 2021 | J24: D24: Basic metals
A25: ISIC 36T39 | B25: 37 | C25: Sewerage | I25: 2021 | J25: D25: Fabricated metal products | K25: ISIC 25
B26: 370 | C26: Sewerage | I26: 2021 | J26: D26: Computer, electronic and optical equipment | K26: ISIC 26
A27: ISIC 36T39 | B27: 38 | C27: Waste collection,treatment,disposal activities | I27: 2018 | J27: D26: Computer, electronic and optical products
B28: 381 | C28: Waste collection | I28: 2021 | J28: D27: Electrical equipment | K28: ISIC 27
B29: 382 | C29: Waste treatment and disposal | I29: 2021 | J29: D28: Machinery and equipment, nec | K29: ISIC 28
B30: 383 | C30: Materials recovery | I30: 2021 | J30: D29: Motor vehicles, trailers and semi-trailers | K30: ISIC 29
A31: ISIC 36T39 | B31: 39 | C31: Remediation activities | I31: 2021 | J31: D30: Other transport equipment | K31: ISIC 30
B32: 390 | C32: Remediation activities | I32: 2021 | J32: D31T33: Manufacturing nec; repair and installation of machinery and equipment | K32: ISIC 31T33
A33: ISIC 36T39 | B33: 39E | C33: Water supply;sewerage,waste management | I33: 2018 | J33: D31T33: Other manufacturing; repair and installation of machinery and equipment
A34: ISIC 10T12 | B34: 1010 | C34: Processing/preserving of meat | I34: 2021 | J34: D35: Electricity, gas, steam and air conditioning supply
A35: ISIC 10T12 | B35: 1020 | C35: Processing/preserving of fish, etc. | I35: 2018 | J35: D35T39: Electricity, gas, water supply, sewerage, waste and remediation services
A36: ISIC 10T12 | B36: 1030 | C36: Processing/preserving of fruit,vegetables | I36: 2021 | J36: D36T39: Water supply; sewerage, waste management and remediation activities | K36: ISIC 36T39
A37: ISIC 10T12 | B37: 1040 | C37: Vegetable and animal oils and fats | I37: 2021 | J37: D41T43: Construction | K37: ISIC 41T43
A38: ISIC 10T12 | B38: 1050 | C38: Dairy products | I38: 2021 | J38: D45T47: Wholesale and retail trade; repair of motor vehicles | K38: ISIC 45T47
A39: ISIC 10T12 | B39: 106 | C39: Grain mill products,starches and starch products | I39: 2021 | J39: D49: Land transport and transport via pipelines
B40: 1061 | C40: Grain mill products | I40: 2018 | J40: D49T53: Transportation and storage | K40: ISIC 49T53
B41: 1062 | C41: Starches and starch products | I41: 2021 | J41: D50: Water transport
A42: ISIC 10T12 | B42: 107 | C42: Other food products | I42: 2021 | J42: D51: Air transport
B43: 1071 | C43: Bakery products | I43: 2021 | J43: D52: Warehousing and support activities for transportation
B44: 1072 | C44: Sugar | I44: 2021 | J44: D53: Postal and courier activities
B45: 1073 | C45: Cocoa, chocolate and sugar confectionery | I45: 2021 | J45: D55T56: Accommodation and food service activities | K45: ISIC 55T56
B46: 1074 | C46: Macaroni, noodles, couscous, etc. | I46: 2018 | J46: D55T56: Accomodation and food services
B47: 1075 | C47: Prepared meals and dishes | I47: 2021 | J47: D58T60: Publishing, audiovisual and broadcasting activities | K47: ISIC 58T60
B48: 1079 | C48: Other food products n.e.c. | I48: 2021 | J48: D61: Telecommunications | K48: ISIC 61
A49: ISIC 10T12 | B49: 1080 | C49: Prepared animal feeds | I49: 2021 | J49: D62T63: IT and other information services | K49: ISIC 62T63
A50: ISIC 10T12 | B50: 110 | C50: Beverages | I50: 2021 | J50: D64T66: Financial and insurance activities | K50: ISIC 64T66
B51: 1101 | C51: Distilling, rectifying and blending of spirits | I51: 2021 | J51: D68: Real estate activities | K51: ISIC 68
B52: 1102 | C52: Wines | I52: 2021 | J52: D69T75: Professional, scientific and technical activities
B53: 1103 | C53: Malt liquors and malt | I53: 2018 | J53: D69T82: Other business sector services | K53: ISIC 69T82
B54: 1104 | C54: Soft drinks,mineral waters,other bottled waters | I54: 2021 | J54: D77T82: Administrative and support services
A55: ISIC 10T12 | B55: 1200 | C55: Tobacco products | I55: 2018 | J55: D84: Public admin. and defence; compulsory social security
A56: ISIC 13T15 | B56: 131 | C56: Spinning, weaving and finishing of textiles | I56: 2021 | J56: D84: Public administration and defence; compulsory social security | K56: ISIC 84
B57: 1311 | C57: Preparation and spinning of textile fibres | I57: 2021 | J57: D85: Education | K57: ISIC 85
B58: 1312 | C58: Weaving of textiles | I58: 2018 | J58: D86T88: Human health and social work
B59: 1313 | C59: Finishing of textiles | I59: 2021 | J59: D86T88: Human health and social work activities | K59: ISIC 86T88
A60: ISIC 13T15 | B60: 139 | C60: Other textiles | I60: 2021 | J60: D90T93: Arts, entertainment and recreation
B61: 1391 | C61: Knitted and crocheted fabrics | I61: 2018 | J61: D90T96: Arts, entertainment, recreation and other service activities | K61: ISIC 90T96
B62: 1392 | C62: Made-up textile articles, except apparel | I62: 2021 | J62: D94T96: Other service activities
B63: 1393 | C63: Carpets and rugs | I63: 2021 | J63: D97T98: Activities of households as employers; undifferentiated goods- and services-producing activities of households for own use | K63: ISIC 97T98
B64: 1394 | C64: Cordage, rope, twine and netting | I64: 2018 | J64: D97T98: Private households with employed persons
B65: 1399 | C65: Other textiles n.e.c. | I65: 2021 | J65: EXPO: Exports (cross border)
A66: ISIC 13T15 | B66: 1410 | C66: Wearing apparel, except fur apparel | I66: 2021 | J66: GFCF: Gross Fixed Capital Formation
A67: ISIC 13T15 | B67: 1420 | C67: Articles of fur | I67: 2021 | J67: GGFC: Final consumption expenditure of general government
A68: ISIC 13T15 | B68: 1430 | C68: Knitted and crocheted apparel | I68: 2021 | J68: HFCE: Final consumption expenditure of households
A69: ISIC 13T15 | B69: 151 | C69: Leather;luggage,handbags,saddlery,harness;fur | I69: 2021 | J69: IMPO: Imports (cross border)
B70: 1511 | C70: Tanning/dressing of leather; dressing of fur | I70: 2021 | J70: INVNT: Changes in inventories
B71: 1512 | C71: Luggage,handbags,etc.;saddlery/harness | I71: 2021 | J71: NPISH: Final consumption expenditure of non-profit institutions serving households
A72: ISIC 13T15 | B72: 1520 | C72: Footwear
A73: ISIC 16 | B73: 1610 | C73: Sawmilling and planing of wood
A74: ISIC 16 | B74: 162 | C74: Wood products, cork, straw, plaiting materials
B75: 1621 | C75: Veneer sheets and wood-based panels
B76: 1622 | C76: Builders' carpentry and joinery
B77: 1623 | C77: Wooden containers
B78: 1629 | C78: Other wood products;articles of cork,straw
A79: ISIC 17T18 | B79: 170 | C79: Paper and paper products
B80: 1701 | C80: Pulp, paper and paperboard
B81: 1702 | C81: Corrugated paper and paperboard
B82: 1709 | C82: Other articles of paper and paperboard
A83: ISIC 17T18 | B83: 181 | C83: Printing and service activities related to printing
B84: 1811 | C84: Printing
B85: 1812 | C85: Service activities related to printing
A86: ISIC 17T18 | B86: 1820 | C86: Reproduction of recorded media
A87: ISIC 19 | B87: 1910 | C87: Coke oven products
A88: ISIC 19 | B88: 1920 | C88: Refined petroleum products
A89: ISIC 20 | B89: 201 | C89: Basic chemicals,fertilizers, etc.
B90: 2011 | C90: Basic chemicals
B91: 2012 | C91: Fertilizers and nitrogen compounds
B92: 2013 | C92: Plastics and synthetic rubber in primary forms
A93: ISIC 20 | B93: 202 | C93: Other chemical products
B94: 2021 | C94: Pesticides and other agrochemical products
B95: 2022 | C95: Paints,varnishes;printing ink and mastics
B96: 2023 | C96: Soap,cleaning and cosmetic preparations
B97: 2029 | C97: Other chemical products n.e.c.
B98: 2030 | C98: Man-made fibres
A99: ISIC 21 | B99: 2100 | C99: Pharmaceuticals,medicinal chemicals, etc.
A100: ISIC 22 | B100: 221 | C100: Rubber products
...

Sheet Pre ISIC Split DLIM
B1: ISIC 01T03 | C1: ISIC 05 | D1: ISIC 06 | E1: ISIC 07T08 | F1: ISIC 09 | G1: ISIC 10T12 | H1: ISIC 13T15 | I1: ISIC 16 | J1: ISIC 17T18 | K1: ISIC 19 | L1: ISIC 20 | M1: ISIC 21 | N1: ISIC 22 | O1: ISIC 231 | P1: ISIC 239 | Q1: ISIC 241 | R1: ISIC 242 | S1: ISIC 25 | T1: ISIC 26 | U1: ISIC 27 | V1: ISIC 28 | W1: ISIC 29 | X1: ISIC 30 | Y1: ISIC 31T33 | Z1: ISIC 351 | AA1: ISIC 352T353 | AB1: ISIC 36T39 | AC1: ISIC 41T43 | AD1: ISIC 45T47 | AE1: ISIC 49T53 | AF1: ISIC 55T56 | AG1: ISIC 58T60 | AH1: ISIC 61 | AI1: ISIC 62T63 | AJ1: ISIC 64T66 | AK1: ISIC 68 | AL1: ISIC 69T82 | AM1: ISIC 84 | AN1: ISIC 85 | AO1: ISIC 86T88 | AP1: ISIC 90T96 | AQ1: ISIC 97T98
A2: ISIC 01T03 | B2: 1.093 | C2: 8.3969505e-05 | D2: 2.6080841e-06 | E2: 0.003 | F2: 0.002 | G2: 0.233 | H2: 0.026 | I2: 0.132 | J2: 0.03 | K2: 0.003 | L2: 0.0060866294 | M2: 0.0064984597 | N2: 0.011 | O2: 0.00015007949 | P2: 4.4392202e-05 | Q2: 0.00017323838 | R2: 4.6852676e-05 | S2: 0.002 | T2: 0.001 | U2: 0.002 | V2: 0.002 | W2: 0.002 | X2: 0.002 | Y2: 0.015 | Z2: 0.00014546665 | AA2: 0.00013813121 | AB2: 0.00011991853 | AC2: 0.004 | AD2: 0.004 | AE2: 0.002 | AF2: 0.046 | AG2: 0.005 | AH2: 0.001 | AI2: 0.002 | AJ2: 0.002 | AK2: 0.001 | AL2: 0.003 | AM2: 0.008 | AN2: 0.003 | AO2: 0.007 | AP2: 0.006 | AQ2: 0
A3: ISIC 05 | B3: 0.00013876065 | C3: 1.0001866 | D3: 9.9524146e-06 | E3: 9.274934e-07 | F3: 0 | G3: 8.356304e-05 | H3: 2.6823783e-05 | I3: 2.0067892e-05 | J3: 9.6552656e-05 | K3: 4.4514085e-05 | L3: 0.16235409 | M3: 0.017733337 | N3: 0.0019951756 | O3: 3.9354235e-05 | P3: 2.681869e-07 | Q3: 0.00026688022 | R3: 2.6281428e-05 | S3: 0.0001372281 | T3: 0.00014480334 | U3: 8.2811004e-05 | V3: 8.9411695e-05 | W3: 7.2987642e-05 | X3: 3.2362951e-05 | Y3: 0.0023669661 | Z3: 0.0016261951 | AA3: 5.4910283e-05 | AB3: 2.7983939e-05 | AC3: 7.8745665e-06 | AD3: 4.9253684e-07 | AE3: 9.489812e-08 | AF3: 2.110407e-06 | AG3: 0 | AH3: 3.2483714e-06 | AI3: 2.2372152e-06 | AJ3: 2.2660878e-05 | AK3: 2.295248e-05 | AL3: 8.262152e-06 | AM3: 0.00016150026 | AN3: 8.2770245e-05 | AO3: 5.6143825e-05 | AP3: 3.9919059e-05 | AQ3: 0.00014562739
A4: ISIC 06 | B4: 9.7181737e-05 | C4: 8.6218445e-07 | D4: 1.0000043 | E4: 4.7772262e-06 | F4: 0 | G4: 0.00010328004 | H4: 0.00013743446 | I4: 0.00016208523 | J4: 0.00012270031 | K4: 0.57343054 | L4: 0.16235409 | M4: 0.017733337 | N4: 0.0020914809 | O4: 1.3941107e-05 | P4: 3.2291581e-07 | Q4: 4.7753979e-05 | R4: 2.4145145e-05 | S4: 0.00018970189 | T4: 0.0001798993 | U4: 7.4577449e-05 | V4: 0.0001581329 | W4: 0.00012252767 | X4: 2.8041447e-05 | Y4: 0.00045073823 | Z4: 0.0024276532 | AA4: 2.8745616e-06 | AB4: 3.1688793e-05 | AC4: 3.8214303e-06 | AD4: 3.3766234e-07 | AE4: 1.9226182e-08 | AF4: 3.9450503e-07 | AG4: 0 | AH4: 4.7460969e-07 | AI4: 3.4867421e-07 | AJ4: 0.00031605219 | AK4: 0.0025064542 | AL4: 2.2830113e-06 | AM4: 0.0077373031 | AN4: 0.00053065108 | AO4: 5.4136947e-05 | AP4: 0.00012200624 | AQ4: 7.8228207e-09
A5: ISIC 07T08 | B5: 0.003 | C5: 0.0025483117 | D5: 6.083748e-05 | E5: 1.016 | F5: 0.005 | G5: 0.005 | H5: 0.002 | I5: 0.002 | J5: 0.003 | K5: 0.001 | L5: 0.02 | M5: 0.003 | N5: 0.006 | O5: 0.0021423114 | P5: 0.16026496 | Q5: 0.0029841508 | R5: 0.33477604 | S5: 0.035 | T5: 0.003 | U5: 0.02 | V5: 0.017 | W5: 0.013 | X5: 0.012 | Y5: 0.007 | Z5: 0.00048920078 | AA5: 0.00097120228 | AB5: 0.004 | AC5: 0.023 | AD5: 0.001 | AE5: 0.004 | AF5: 0.002 | AG5: 0.001 | AH5: 0 | AI5: 0.002 | AJ5: 0 | AK5: 0 | AL5: 0.001 | AM5: 0.001 | AN5: 0 | AO5: 0.001 | AP5: 0.002 | AQ5: 0
A6: ISIC 09 | B6: 0.017 | C6: 0 | D6: 0 | E6: 0.003 | F6: 1.018 | G6: 0 | H6: 0 | I6: 0 | J6: 0 | K6: 0.007 | L6: 0.003 | M6: 0.002 | N6: 0.007 | O6: 0 | P6: 0 | Q6: 0 | R6: 0 | S6: 0 | T6: 0 | U6: 0 | V6: 0 | W6: 0 | X6: 0 | Y6: 0 | Z6: 0 | AA6: 0 | AB6: 0 | AC6: 0 | AD6: 0 | AE6: 0.006 | AF6: 0 | AG6: 0.001 | AH6: 0 | AI6: 0.001 | AJ6: 0 | AK6: 0 | AL6: 0.001 | AM6: 0 | AN6: 0 | AO6: 0 | AP6: 0.001 | AQ6: 0
A7: ISIC 10T12 | B7: 0.062 | C7: 7.6404479e-05 | D7: 2.5099902e-06 | E7: 0.001 | F7: 0.001 | G7: 1.084 | H7: 0.014 | I7: 0.014 | J7: 0.007 | K7: 0.001 | L7: 0.005 | M7: 0.01 | N7: 0.006 | O7: 0.00022668919 | P7: 3.516024e-05 | Q7: 0.00019165883 | R7: 4.8621767e-05 | S7: 0.002 | T7: 0.001 | U7: 0.001 | V7: 0.001 | W7: 0.001 | X7: 0.001 | Y7: 0.002 | Z7: 0.00016695917 | AA7: 0.00020572359 | AB7: 0.001 | AC7: 0.001 | AD7: 0.001 | AE7: 0.002 | AF7: 0.063 | AG7: 0.002 | AH7: 0.001 | AI7: 0.002 | AJ7: 0.001 | AK7: 0 | AL7: 0.002 | AM7: 0.009 | AN7: 0.002 | AO7: 0.004 | AP7: 0.009 | AQ7: 0
A8: ISIC 13T15 | B8: 0.002 | C8: 8.9127488e-05 | D8: 2.7077664e-06 | E8: 0.005 | F8: 0.01 | G8: 0.002 | H8: 0.007 | I8: 0.004 | J8: 0.005 | K8: 0.001 | L8: 0.002 | M8: 0.002 | N8: 0.009 | O8: 0.00039265603 | P8: 7.5778652e-05 | Q8: 0.00029333523 | R8: 0.00011363244 | S8: 0.005 | T8: 0.006 | U8: 0.005 | V8: 0.004 | W8: 0.004 | X8: 0.004 | Y8: 1.013 | Z8: 0.00082703972 | AA8: 0.00016655856 | AB8: 0.002 | AC8: 0.003 | AD8: 0.001 | AE8: 0.002 | AF8: 0.002 | AG8: 0.006 | AH8: 0.002 | AI8: 0.002 | AJ8: 0.002 | AK8: 0 | AL8: 0.002 | AM8: 0.003 | AN8: 0.002 | AO8: 0.007 | AP8: 0.005 | AQ8: 0
A9: ISIC 16 | B9: 0.001 | C9: 0.00084144085 | D9: 1.1794331e-06 | E9: 0.005 | F9: 0.01 | G9: 0.002 | H9: 0.007 | I9: 0.004 | J9: 0.005 | K9: 0.001 | L9: 0.002 | M9: 0.002 | N9: 0.002 | O9: 0.0043697259 | P9: 0.001016003 | Q9: 0.0010514986 | R9: 0.00040414828 | S9: 0.005 | T9: 0.006 | U9: 0.005 | V9: 0.004 | W9: 0.004 | X9: 0.004 | Y9: 1.013 | Z9: 0.0001101571 | AA9: 0.00023239194 | AB9: 0.002 | AC9: 0.003 | AD9: 0.001 | AE9: 0.001 | AF9: 0.002 | AG9: 0.006 | AH9: 0.002 | AI9: 0.002 | AJ9: 0.002 | AK9: 0 | AL9: 0.001 | AM9: 0.003 | AN9: 0.002 | AO9: 0.007 | AP9: 0.002 | AQ9: 0
A10: ISIC 17T18 | B10: 0.003 | C10: 7.0831409e-05 | D10: 1.0593472e-05 | E10: 0.002 | F10: 0.016 | G10: 0.01 | H10: 0.016 | I10: 0.011 | J10: 1.19 | K10: 0.002 | L10: 0.006 | M10: 0.012 | N10: 0.012 | O10: 0.0071278247 | P10: 3.7463566e-05 | Q10: 0.00033613438 | R10: 0.00010902981 | S10: 0.01 | T10: 0.007 | U10: 0.008 | V10: 0.005 | W10: 0.005 | X10: 0.003 | Y10: 0.021 | Z10: 0.00057549979 | AA10: 0.0015836685 | AB10: 0.004 | AC10: 0.002 | AD10: 0.007 | AE10: 0.004 | AF10: 0.01 | AG10: 0.004 | AH10: 0.002 | AI10: 0.008 | AJ10: 0.009 | AK10: 0.003 | AL10: 0.008 | AM10: 0.012 | AN10: 0.007 | AO10: 0.006 | AP10: 0.011 | AQ10: 0
A11: ISIC 19 | B11: 0.027 | C11: 5.3489112e-08 | D11: 5.1685294e-09 | E11: 0.035 | F11: 0.06 | G11: 0.016 | H11: 0.012 | I11: 0.027 | J11: 0.018 | K11: 1.155 | L11: 0.045 | M11: 0.014 | N11: 0.021 | O11: 2.1211268e-06 | P11: 1.5000553e-08 | Q11: 2.3819679e-05 | R11: 6.3670694e-06 | S11: 0.02 | T11: 0.006 | U11: 0.013 | V11: 0.01 | W11: 0.009 | X11: 0.01 | Y11: 0.014 | Z11: 0.00052951316 | AA11: 3.3758267e-07 | AB11: 0.026 | AC11: 0.015 | AD11: 0.008 | AE11: 0.11 | AF11: 0.008 | AG11: 0.009 | AH11: 0.003 | AI11: 0.006 | AJ11: 0.004 | AK11: 0.002 | AL11: 0.008 | AM11: 0.017 | AN11: 0.004 | AO11: 0.01 | AP11: 0.012 | AQ11: 0
A12: ISIC 20 | B12: 0.040781031 | C12: 0.024202007 | D12: 0.024202007 | E12: 0.017 | F12: 0.01 | G12: 0.02 | H12: 0.028 | I12: 0.022 | J12: 0.041 | K12: 0.032 | L12: 1.118 | M12: 0.076 | N12: 0.23670861 | O12: 0.048965334 | P12: 0.048965334 | Q12: 0.023497274 | R12: 0.023497274 | S12: 0.015 | T12: 0.007 | U12: 0.02 | V12: 0.009 | W12: 0.015 | X12: 0.005 | Y12: 0.027 | Z12: 0.092141332 | AA12: 0.069288717 | AB12: 0.015 | AC12: 0.006 | AD12: 0.003 | AE12: 0.017465322 | AF12: 0.011 | AG12: 0.011 | AH12: 0.002 | AI12: 0.004 | AJ12: 0.002 | AK12: 0.002 | AL12: 0.0073353336 | AM12: 0.007 | AN12: 0.003 | AO12: 0.017 | AP12: 0 | AQ12: 0
A13: ISIC 21 | B13: 0.00076978746 | C13: 1.4632139e-05 | D13: 1.4632139e-05 | E13: 0 | F13: 0 | G13: 0.001 | H13: 0 | I13: 0.001 | J13: 0 | K13: 0 | L13: 0.001 | M13: 1.083 | N13: 0.00017271509 | O13: 6.8304542e-05 | P13: 6.8304542e-05 | Q13: 3.2743993e-05 | R13: 3.2743993e-05 | S13: 0 | T13: 0 | U13: 0 | V13: 0 | W13: 0 | X13: 0 | Y13: 0.004 | Z13: 4.7870518e-05 | AA13: 4.0663545e-05 | AB13: 0 | AC13: 0 | AD13: 0 | AE13: 4.8955228e-05 | AF13: 0 | AG13: 0 | AH13: 0 | AI13: 0 | AJ13: 0 | AK13: 0 | AL13: 0.0050553872 | AM13: 0.002 | AN13: 0 | AO13: 0.046 | AP13: 0 | AQ13: 0
... A43: ISIC 97T98 | B43: 0 | C43: 0 | D43: 0 | E43: 0 | F43: 0 | G43: 0 | H43: 0 | I43: 0 | J43: 0 | K43: 0 | L43: 0 | M43: 0 | N43: 0 | O43: 0 | P43: 0 | Q43: 0 | R43: 0 | S43: 0 | T43: 0 | U43: 0 | V43: 0 | W43: 0 | X43: 0 | Y43: 0 | Z43: 0 | AA43: 0 | AB43: 0 | AC43: 0 | AD43: 0 | AE43: 0 | AF43: 0 | AG43: 0 | AH43: 0 | AI43: 0 | AJ43: 0 | AK43: 0 | AL43: 0 | AM43: 0 | AN43: 0 | AO43: 0 | AP43: 0 | AQ43: 1

Sheet DLIM ISIC alignment
A1: ='Pre ISIC Split DLIM'!A1 -> 0 | B1: ='Pre ISIC Split DLIM'!B1 -> ISIC 01T03 | C1: ='Pre ISIC Split DLIM'!C1 -> ISIC 05 | D1: ='Pre ISIC Split DLIM'!D1 -> ISIC 06 | E1: ='Pre ISIC Split DLIM'!E1 -> ISIC 07T08 | F1: ='Pre ISIC Split DLIM'!F1 -> ISIC 09 | G1: ='Pre ISIC Split DLIM'!G1 -> ISIC 10T12 | H1: ='Pre ISIC Split DLIM'!H1 -> ISIC 13T15 | ... AQ1: ='Pre ISIC Split DLIM'!AQ1 -> ISIC 97T98
A2: ='Pre ISIC Split DLIM'!A2 -> ISIC 01T03 | B2: ='Pre ISIC Split DLIM'!B2 -> 1.093 | C2: ='Pre ISIC Split DLIM'!C2 -> 8.3969505e-05 | D2: ='Pre ISIC Split DLIM'!D2 -> 2.6080841e-06 | E2: ='Pre ISIC Split DLIM'!E2 -> 0.003 | F2: ='Pre ISIC Split DLIM'!F2 -> 0.002 | G2: ='Pre ISIC Split DLIM'!G2 -> 0.233 | H2: ='Pre ISIC Split DLIM'!H2 -> 0.026 | ... AQ2: ='Pre ISIC Split DLIM'!AQ2 -> 0
A3: ='Pre ISIC Split DLIM'!A3 -> ISIC 05 | B3: ='Pre ISIC Split DLIM'!B3 -> 0.00013876065 | C3: ='Pre ISIC Split DLIM'!C3 -> 1.0001866 | D3: ='Pre ISIC Split DLIM'!D3 -> 9.9524146e-06 | E3: ='Pre ISIC Split DLIM'!E3 -> 9.274934e-07 | F3: ='Pre ISIC Split DLIM'!F3 -> 0 | G3: ='Pre ISIC Split DLIM'!G3 -> 8.356304e-05 | H3: ='Pre ISIC Split DLIM'!H3 -> 2.6823783e-05 | ... AQ3: ='Pre ISIC Split DLIM'!AQ3 -> 0.00014562739
A4: ='Pre ISIC Split DLIM'!A4 -> ISIC 06 | B4: ='Pre ISIC Split DLIM'!B4 -> 9.7181737e-05 | C4: ='Pre ISIC Split DLIM'!C4 -> 8.6218445e-07 | D4: ='Pre ISIC Split DLIM'!D4 -> 1.0000043 | E4: ='Pre ISIC Split DLIM'!E4 -> 4.7772262e-06 | F4: ='Pre ISIC Split DLIM'!F4 -> 0 | G4: ='Pre ISIC Split DLIM'!G4 -> 0.00010328004 | H4: ='Pre ISIC Split DLIM'!H4 -> 0.00013743446 | ... AQ4: ='Pre ISIC Split DLIM'!AQ4 -> 7.8228207e-09
A5: ='Pre ISIC Split DLIM'!A5 -> ISIC 07T08 | B5: ='Pre ISIC Split DLIM'!B5 -> 0.003 | C5: ='Pre ISIC Split DLIM'!C5 -> 0.0025483117 | D5: ='Pre ISIC Split DLIM'!D5 -> 6.083748e-05 | E5: ='Pre ISIC Split DLIM'!E5 -> 1.016 | F5: ='Pre ISIC Split DLIM'!F5 -> 0.005 | G5: ='Pre ISIC Split DLIM'!G5 -> 0.005 | H5: ='Pre ISIC Split DLIM'!H5 -> 0.002 | ... AQ5: ='Pre ISIC Split DLIM'!AQ5 -> 0
A6: ='Pre ISIC Split DLIM'!A6 -> ISIC 09 | B6: ='Pre ISIC Split DLIM'!B6 -> 0.017 | C6: ='Pre ISIC Split DLIM'!C6 -> 0 | D6: ='Pre ISIC Split DLIM'!D6 -> 0 | E6: ='Pre ISIC Split DLIM'!E6 -> 0.003 | F6: ='Pre ISIC Split DLIM'!F6 -> 1.018 | G6: ='Pre ISIC Split DLIM'!G6 -> 0 | H6: ='Pre ISIC Split DLIM'!H6 -> 0 | ... AQ6: ='Pre ISIC Split DLIM'!AQ6 -> 0
A7: ='Pre ISIC Split DLIM'!A7 -> ISIC 10T12 | B7: ='Pre ISIC Split DLIM'!B7 -> 0.062 | C7: ='Pre ISIC Split DLIM'!C7 -> 7.6404479e-05 | D7: ='Pre ISIC Split DLIM'!D7 -> 2.5099902e-06 | E7: ='Pre ISIC Split DLIM'!E7 -> 0.001 | F7: ='Pre ISIC Split DLIM'!F7 -> 0.001 | G7: ='Pre ISIC Split DLIM'!G7 -> 1.084 | H7: ='Pre ISIC Split DLIM'!H7 -> 0.014 | ... AQ7: ='Pre ISIC Split DLIM'!AQ7 -> 0
A8: ='Pre ISIC Split DLIM'!A8 -> ISIC 13T15 | B8: ='Pre ISIC Split DLIM'!B8 -> 0.002 | C8: ='Pre ISIC Split DLIM'!C8 -> 8.9127488e-05 | D8: ='Pre ISIC Split DLIM'!D8 -> 2.7077664e-06 | E8: ='Pre ISIC Split DLIM'!E8 -> 0.005 | F8: ='Pre ISIC Split DLIM'!F8 -> 0.01 | G8: ='Pre ISIC Split DLIM'!G8 -> 0.002 | H8: ='Pre ISIC Split DLIM'!H8 -> 0.007 | ... AQ8: ='Pre ISIC Split DLIM'!AQ8 -> 0
A9: ='Pre ISIC Split DLIM'!A9 -> ISIC 16 | B9: ='Pre ISIC Split DLIM'!B9 -> 0.001 | C9: ='Pre ISIC Split DLIM'!C9 -> 0.00084144085 | D9: ='Pre ISIC Split DLIM'!D9 -> 1.1794331e-06 | E9: ='Pre ISIC Split DLIM'!E9 -> 0.005 | F9: ='Pre ISIC Split DLIM'!F9 -> 0.01 | G9: ='Pre ISIC Split DLIM'!G9 -> 0.002 | H9: ='Pre ISIC Split DLIM'!H9 -> 0.007 | ... AQ9: ='Pre ISIC Split DLIM'!AQ9 -> 0
A10: ='Pre ISIC Split DLIM'!A10 -> ISIC 17T18 | B10: ='Pre ISIC Split DLIM'!B10 -> 0.003 | C10: ='Pre ISIC Split DLIM'!C10 -> 7.0831409e-05 | D10: ='Pre ISIC Split DLIM'!D10 -> 1.0593472e-05 | E10: ='Pre ISIC Split DLIM'!E10 -> 0.002 | F10: ='Pre ISIC Split DLIM'!F10 -> 0.016 | G10: ='Pre ISIC Split DLIM'!G10 -> 0.01 | H10: ='Pre ISIC Split DLIM'!H10 -> 0.016 | ... AQ10: ='Pre ISIC Split DLIM'!AQ10 -> 0
A11: ='Pre ISIC Split DLIM'!A11 -> ISIC 19 | B11: ='Pre ISIC Split DLIM'!B11 -> 0.027 | C11: ='Pre ISIC Split DLIM'!C11 -> 5.3489112e-08 | D11: ='Pre ISIC Split DLIM'!D11 -> 5.1685294e-09 | E11: ='Pre ISIC Split DLIM'!E11 -> 0.035 | F11: ='Pre ISIC Split DLIM'!F11 -> 0.06 | G11: ='Pre ISIC Split DLIM'!G11 -> 0.016 | H11: ='Pre ISIC Split DLIM'!H11 -> 0.012 | ... AQ11: ='Pre ISIC Split DLIM'!AQ11 -> 0
A12: ='Pre ISIC Split DLIM'!A12 -> ISIC 20 | B12: ='Pre ISIC Split DLIM'!B12 -> 0.040781031 | C12: ='Pre ISIC Split DLIM'!C12 -> 0.024202007 | D12: ='Pre ISIC Split DLIM'!D12 -> 0.024202007 | E12: ='Pre ISIC Split DLIM'!E12 -> 0.017 | F12: ='Pre ISIC Split DLIM'!F12 -> 0.01 | G12: ='Pre ISIC Split DLIM'!G12 -> 0.02 | H12: ='Pre ISIC Split DLIM'!H12 -> 0.028 | ... AQ12: ='Pre ISIC Split DLIM'!AQ12 -> 0
... A43: ='Pre ISIC Split DLIM'!A43 -> ISIC 97T98 | B43: ='Pre ISIC Split DLIM'!B43 -> 0 | C43: ='Pre ISIC Split DLIM'!C43 -> 0 | D43: ='Pre ISIC Split DLIM'!D43 -> 0 | E43: ='Pre ISIC Split DLIM'!E43 -> 0 | F43: ='Pre ISIC Split DLIM'!F43 -> 0 | G43: ='Pre ISIC Split DLIM'!G43 -> 0 | H43: ='Pre ISIC Split DLIM'!H43 -> 0 | ... AQ43: ='Pre ISIC Split DLIM'!AQ43 -> 1

Sheet Pre ISIC Split BObIC
A1: Unit: USD | B1: ISIC 01T03 | C1: ISIC 05 | D1: ISIC 06 | E1: ISIC 07T08 | F1: ISIC 09 | G1: ISIC 10T12 | H1: ISIC 13T15 | I1: ISIC 16 | J1: ISIC 17T18 | K1: ISIC 19 | L1: ISIC 20 | M1: ISIC 21 | N1: ISIC 22 | O1: ISIC 231 | P1: ISIC 239 | Q1: ISIC 241 | R1: ISIC 242 | S1: ISIC 25 | T1: ISIC 26 | U1: ISIC 27 | V1: ISIC 28 | W1: ISIC 29 | X1: ISIC 30 | Y1: ISIC 31T33 | Z1: ISIC 351 | AA1: ISIC 352T353 | AB1: ISIC 36T39 | AC1: ISIC 41T43 | AD1: ISIC 45T47 | AE1: ISIC 49T53 | AF1: ISIC 55T56 | AG1: ISIC 58T60 | AH1: ISIC 61 | AI1: ISIC 62T63 | AJ1: ISIC 64T66 | AK1: ISIC 68 | AL1: ISIC 69T82 | AM1: ISIC 84 | AN1: ISIC 85 | AO1: ISIC 86T88 | AP1: ISIC 90T96 | AQ1: ISIC 97T98
A2: Output | B2: 52329376000 | C2: 4.8858285e+08 | D2: 4.2147738e+10 | E2: 16974139000 | F2: 7200739000 | G2: 129043369000 | H2: 19568731000 | I2: 3939845000 | J2: 16184623000 | K2: 45756620000 | L2: 39707304000 | M2: 12745551000 | N2: 18376336000 | O2: 6.5339221e+09 | P2: 1.1263403e+10 | Q2: 1.3105774e+10 | R2: 2.6453837e+10 | S2: 24117730000 | T2: 78553930000 | U2: 25144483000 | V2: 23016903000 | W2: 161627466000 | X2: 9838556000 | Y2: 20414667000 | Z2: 2.6767267e+10 | AA2: 8.2743506e+08 | AB2: 6815263000 | AC2: 139088313000 | AD2: 261044875000 | AE2: 110265848000 | AF2: 37828973000 | AG2: 8906261000 | AH2: 21265426000 | AI2: 2554643000 | AJ2: 68018132000 | AK2: 115551527000 | AL2: 82725720000 | AM2: 63878360000 | AN2: 46365228000 | AO2: 38002328000 | AP2: 19889936000 | AQ2: 4731727000

Sheet SIOM from DLIM
A1: Inverse of DLIM
B3: ISIC 01T03 | C3: ISIC 05 | D3: ISIC 06 | E3: ISIC 07T08 | F3: ISIC 09 | G3: ISIC 10T12 | H3: ISIC 13T15 | I3: ISIC 16 | J3: ISIC 17T18 | K3: ISIC 19 | L3: ISIC 20 | M3: ISIC 21 | N3: ISIC 22 | O3: ISIC 231 | P3: ISIC 239 | Q3: ISIC 241 | R3: ISIC 242 | S3: ISIC 25 | T3: ISIC 26 | U3: ISIC 27 | V3: ISIC 28 | W3: ISIC 29 | X3: ISIC 30 | Y3: ISIC 31T33 | Z3: ISIC 351 | AA3: ISIC 352T353 | AB3: ISIC 36T39 | AC3: ISIC 41T43 | AD3: ISIC 45T47 | AE3: ISIC 49T53 | AF3: ISIC 55T56 | AG3: ISIC 58T60 | AH3: ISIC 61 | AI3: ISIC 62T63 | AJ3: ISIC 64T66 | AK3: ISIC 68 | AL3: ISIC 69T82 | AM3: ISIC 84 | AN3: ISIC 85 | AO3: ISIC 86T88 | AP3: ISIC 90T96 | AQ3: ISIC 97T98
A4: ISIC 01T03 | B4: {=MINVERSE('Pre ISIC Split DLIM'!B2:AQ43)} -> 2.9432153 | C4: -25.977206 | D4: 8.4242198 | E4: 0.14111685 | F4: 0.2231858 | G4: 0.23918731 | H4: -690215.88 | I4: 76433.089 | J4: -1.7668661 | K4: -4.2530586 | L4: -7.6898321 | M4: -4.0770411 | N4: 12.216443 | O4: -86.322387 | P4: -24.735576 | Q4: -10.37495 | R4: 11.416637 | S4: -1729.6564 | T4: 1011240.3 | U4: -112657.88 | V4: -4511.554 | W4: -0.082069038 | X4: -692122.67 | Y4: 413564.26 | Z4: 653.0532 | AA4: 96.772714 | AB4: 0.18481286 | AC4: 0.30676107 | AD4: 0.036298251 | AE4: 1.9605806 | AF4: -0.1629405 | AG4: -0.1516697 | AH4: 0.032354226 | AI4: 0.072915896 | AJ4: -1.354409 | AK4: -1.7652872 | AL4: -0.25156157 | AM4: -3.8857408 | AN4: -5.6219522 | AO4: -2.2855595 | AP4: 83.268144 | AQ4: 0.0037622831
A5: ISIC 05 | B5: -3.095982 | C5: 29.566052 | D5: -9.4289327 | E5: -0.14864601 | F5: -0.24412955 | G5: -0.25780952 | H5: 781502.98 | I5: -85587.253 | J5: 1.9802566 | K5: 4.7943148 | L5: 8.5863108 | M5: 4.5852259 | N5: -10.012217 | O5: 95.294416 | P5: 27.088243 | Q5: 12.324758 | R5: -13.026493 | S5: 2833.7576 | T5: -1150740.2 | U5: 126132.49 | V5: 741.58509 | W5: 0.050267688 | X5: 784502.46 | Y5: -459385.92 | Z5: -734.89936 | AA5: -109.67379 | AB5: -0.22269845 | AC5: -0.32960477 | AD5: -0.051547298 | AE5: -3.1117579 | AF5: 0.16537728 | AG5: 0.14074002 | AH5: -0.038835608 | AI5: -0.086607588 | AJ5: 1.5279922 | AK5: 1.992866 | AL5: 0.24361484 | AM5: 4.3746834 | AN5: 6.3329056 | AO5: 2.5544745 | AP5: -83.279211 | AQ5: -0.0042813162
A6: ISIC 06 | B6: -4.8276352 | C6: 45.062724 | D6: -13.836501 | E6: -0.22046797 | F6: -0.35778411 | G6: -0.42348027 | H6: 1229525.2 | I6: -134808.89 | J6: 3.1161512 | K6: 7.0406753 | L6: 13.59324 | M6: 7.2195442 | N6: -15.915634 | O6: 150.42652 | P6: 42.762966 | Q6: 19.416445 | R6: -20.517695 | S6: 4416.7736 | T6: -1810237.9 | U6: 198436.46 | V6: 1443.7047 | W6: 0.077406708 | X6: 1234205.2 | Y6: -722980.68 | Z6: -1156.1901 | AA6: -172.52643 | AB6: -0.33895159 | AC6: -0.51674326 | AD6: -0.077635303 | AE6: -4.8022267 | AF6: 0.26096929 | AG6: 0.22325042 | AH6: -0.060643381 | AI6: -0.13527157 | AJ6: 2.4037282 | AK6: 3.1325902 | AL6: 0.38806164 | AM6: 6.8809198 | AN6: 9.9637876 | AO6: 4.0207959 | AP6: -131.21463 | AQ6: -0.0065243613
A7: ISIC 07T08 | B7: 6.7837163 | C7: -61.900136 | D7: 20.598079 | E7: 1.3168467 | F7: 0.53523704 | G7: 0.51544062 | H7: -1707451.1 | I7: 186315.25 | J7: -4.3232438 | K7: -10.460138 | L7: -19.172924 | M7: -10.043944 | N7: 23.508433 | O7: -206.14978 | P7: -58.653279 | Q7: -27.382913 | R7: 27.83657 | S7: -6440.1185 | T7: 2514018.2 | U7: -275414.24 | V7: 134.13307 | W7: -0.13253056 | X7: -1714478.8 | Y7: 1003317 | Z7: 1605.1681 | AA7: 239.76525 | AB7: 0.48272337 | AC7: 0.69561697 | AD7: 0.10991443 | AE7: 6.8227253 | AF7: -0.35563696 | AG7: -0.28700918 | AH7: 0.095309057 | AI7: 0.21806493 | AJ7: -3.3196862 | AK7: -4.3505616 | AL7: -0.74009502 | AM7: -9.546017 | AN7: -13.826308 | AO7: -5.5676896 | AP7: 182.79846 | AQ7: 0.0089605983
A8: ISIC 09 | B8: -0.24970382 | C8: 2.2863379 | D8: -0.7547337 | E8: -0.014827919 | F8: 0.96297156 | G8: -0.020297226 | H8: 62410.952 | I8: -6839.2495 | J8: 0.15839842 | K8: 0.37714778 | L8: 0.69580867 | M8: 0.3656662 | N8: -0.87147535 | O8: 7.617196 | P8: 2.1672665 | Q8: 0.97983398 | R8: -1.0333814 | S8: 217.56439 | T8: -91817.829 | U8: 10093.261 | V8: 95.008057 | W8: 0.0049395532 | X8: 62647.41 | Y8: -36807.124 | Z8: -58.754511 | AA8: -8.7592919 | AB8: -0.017499739 | AC8: -0.026325414 | AD8: -0.0039305484 | AE8: -0.23963676 | AF8: 0.01334374 | AG8: 0.010390198 | AH8: -0.003239351 | AI8: -0.0083596167 | AJ8: 0.1218211 | AK8: 0.1592096 | AL8: 0.023917074 | AM8: 0.34967382 | AN8: 0.50614658 | AO8: 0.20433582 | AP8: -6.8133319 | AQ8: -0.00033101252
A9: ISIC 10T12 | B9: 12.347012 | C9: -113.92568 | D9: 37.668823 | E9: 0.60265601 | F9: 0.97984486 | G9: 1.9494023 | H9: -3122107.7 | I9: 341691.25 | J9: -7.8984427 | K9: -19.137511 | L9: -34.911068 | M9: -18.352487 | N9: 40.576432 | O9: -379.92206 | P9: -107.96499 | Q9: -49.233258 | R9: 52.085413 | S9: -11404.136 | T9: 4597206.5 | U9: -503690.24 | V9: -2533.8916 | W9: -0.20796272 | X9: -3134238.9 | Y9: 1835077.4 | Z9: 2935.292 | AA9: 438.23316 | AB9: 0.89457296 | AC9: 1.3129442 | AD9: 0.20521354 | AE9: 12.455072 | AF9: -0.71161119 | AG9: -0.55197958 | AH9: 0.15829329 | AI9: 0.35497341 | AJ9: -6.0982685 | AK9: -7.95854 | AL9: -1.0314207 | AM9: -17.475949 | AN9: -25.29373 | AO9: -10.194046 | AP9: 332.74513 | AQ9: 0.016493225
A10: ISIC 13T15 | B10: -1320.624 | C10: 12093.935 | D10: -4002.6535 | E10: -64.070627 | F10: -104.17606 | G10: -106.17066 | H10: 3.317302e+08 | I10: -36290703 | J10: 839.06826 | K10: 2033.5461 | L10: 3711.0228 | M10: 1949.539 | N10: -4327.7727 | O10: 40326.029 | P10: 11457.12 | Q10: 5232.1526 | R10: -5525.9828 | S10: 1218388.4 | T10: -4.884739e+08 | U10: 53522292 | V10: 222087.21 | W10: 22.520962 | X10: 3.330288e+08 | Y10: -1.949572e+08 | Z10: -311896.06 | AA10: -46565.535 | AB10: -95.086667 | AC10: -139.29211 | AD10: -21.821664 | AE10: -1327.1706 | AF10: 69.674322 | AG10: 58.345231 | AH10: -16.971567 | AI10: -38.186644 | AJ10: 647.75401 | AK10: 845.68063 | AL10: 112.18622 | AM10: 1856.1387 | AN10: 2687.4387 | AO10: 1082.8413 | AP10: -35355.307 | AQ10: -1.7508317
A11: ISIC 16 | B11: 225.66685 | C11: -2002.28 | D11: 664.55301 | E11: 10.572838 | F11: 17.266746 | G11: 15.727699 | H11: -55137115 | I11: 6022676.7 | J11: -139.48864 | K11: -337.85184 | L11: -617.34843 | M11: -323.9364 | N11: 696.11204 | O11: -6678.2387 | P11: -1895.3158 | Q11: -873.96391 | R11: 917.97036 | S11: -209853.7 | T11: 81231690 | U11: -8886170.9 | V11: 1854.8652 | W11: -3.5207823 | X11: -55360740 | Y11: 32337664 | Z11: 51809.7 | AA11: 7740.9118 | AB11: 15.909774 | AC11: 22.969369 | AD11: 3.6727436 | AE11: 227.36746 | AF11: -11.667473 | AG11: -9.4346673 | AH11: 2.866926 | AI11: 6.4661364 | AJ11: -107.58362 | AK11: -140.52505 | AL11: -18.99816 | AM11: -308.35104 | AN11: -446.46204 | AO11: -179.74529 | AP11: 5799.033 | AQ11: 0.28985269
A12: ISIC 17T18 | B12: -5.9621381 | C12: 53.620326 | D12: -17.986784 | E12: -0.29101749 | F12: -0.48489238 | G12: -0.4137812 | H12: 1487155.4 | I12: -161813.6 | J12: 4.6279813 | K12: 9.1312242 | L12: 16.780781 | M12: 8.7672399 | N12: -22.822373 | O12: 178.47492 | P12: 50.498585 | Q12: 23.364007 | R12: -23.996334 | S12: 5906.1687 | T12: -2189118.3 | U12: 240561.84 | V12: -2402.6785 | W12: 0.16322542 | X12: 1493802.4 | Y12: -874091.41 | Z12: -1400.4028 | AA12: -208.89442 | AB12: -0.41880214 | AC12: -0.61051055 | AD12: -0.096210799 | AE12: -6.011878 | AF12: 0.30366573 | AG12: 0.23598896 | AH12: -0.092191851 | AI12: -0.22427121 | AJ12: 2.8741663 | AK12: 3.7911157 | AL12: 0.85310666 | AM12: 8.3127536 | AN12: 12.051554 | AO12: 4.8517815 | AP12: -161.50431 | AQ12: -0.0077608907
A13: ISIC 19 | B13: 2.6144883 | C13: -25.082377 | D13: 8.2098226 | E13: 0.10569536 | F13: 0.16635108 | G13: 0.25719064 | H13: -680203.09 | I13: 74779.357 | J13: -1.7245833 | K13: -3.2973315 | L13: -7.5996625 | M13: -3.9993549 | N13: 8.9082085 | O13: -83.842693 | P13: -23.84545 | Q13: -10.776849 | R13: 11.394046 | S13: -2378.2399 | T13: 1001223.6 | U13: -109769.86 | V13: -1228.8803 | W13: -0.039309483 | X13: -682718.94 | Y13: 400296.15 | Z13: 639.59691 | AA13: 95.417663 | AB13: 0.17395284 | AC13: 0.28403242 | AD13: 0.039080986 | AE13: 2.5405438 | AF13: -0.14531163 | AG13: -0.12643316 | AH13: 0.03274371 | AI13: 0.072514032 | AJ13: -1.3306334 | AK13: -1.7340614 | AL13: -0.21029588 | AM13: -3.8180502 | AN13: -5.5134713 | AO13: -2.2270829 | AP13: 72.805063 | AQ13: 0.003631945
A14: ISIC 20 | B14: 15.433423 | C14: -142.729 | D14: 47.05198 | E14: 0.73878956 | F14: 1.2161894 | G14: 1.3024782 | H14: -3900606.7 | I14: 427388.3 | J14: -9.8838976 | K14: -23.930546 | L14: -42.652363 | M14: -22.971797 | N14: 49.144982 | O14: -476.20157 | P14: -135.41462 | Q14: -61.536505 | R14: 65.15879 | S14: -14037.326 | T14: 5743666 | U14: -629474.11 | V14: -4462.1464 | W14: -0.23691105 | X14: -3915383 | Y14: 2292909.5 | Z14: 3667.7077 | AA14: 547.35312 | AB14: 1.1117183 | AC14: 1.648601 | AD14: 0.2588141 | AE14: 15.511747 | AF14: -0.82684491 | AG14: -0.7098026 | AH14: 0.19007411 | AI14: 0.42070062 | AJ14: -7.6325416 | AK14: -9.9471312 | AL14: -1.1343003 | AM14: -21.837133 | AN14: -31.6089 | AO14: -12.748798 | AP14: 415.08682 | AQ14: 0.020664201
A15: ISIC 21 | B15: -0.099735843 | C15: 0.85773994 | D15: -0.28429274 | E15: -0.0044725948 | F15: -0.0073174605 | G15: -0.0070119827 | H15: 23672.115 | I15: -2584.5437 | J15: 0.059691063 | K15: 0.14470644 | L15: 0.26349232 | M15: 1.06213 | N15: -0.26030777 | O15: 2.8655362 | P15: 0.81260956 | Q15: 0.37773712 | R15: -0.39927611 | S15: 94.096825 | T15: -34911.93 | U15: 3801.1709 | V15: -13.749256 | W15: 0.00092641854 | X15: 23773.605 | Y15: -13830.772 | Z15: -22.19773 | AA15: -3.3232304 | AB15: -0.0069380329 | AC15: -0.009828069 | AD15: -0.0016435113 | AE15: -0.10001162 | AF15: 0.0051096995 | AG15: 0.0040576131 | AH15: -0.001131404 | AI15: -0.0024494941 | AJ15: 0.0463225 | AK15: 0.06027153 | AL15: 0.0052627068 | AM15: 0.13038747 | AN15: 0.19140071 | AO15: 0.034744738 | AP15: -2.4064462 | AQ15: -0.00012416729
A16: ISIC 22 | B16: -3.513646 | C16: 32.121051 | D16: -10.64784 | E16: -0.17019431 | F16: -0.27748898 | G16: -0.27748652 | H16: 882275.74 | I16: -96432.093 | J16: 2.235509 | K16: 5.4081914 | L16: 9.8820571 | M16: 5.1885642 | N16: -12.111256 | O16: 107.08464 | P16: 30.385914 | Q16: 13.884685 | R16: -14.574427 | S16: 3319.6496 | T16: -1298567.4 | U16: 142379.22 | V16: 30.901812 | W16: 0.070070302 | X16: 885885.06 | Y16: -518891.17 | Z16: -829.65763 | AA16: -123.85598 | AB16: -0.25102328 | AC16: -0.36932214 | AD16: -0.057048747 | AE16: -3.5316465 | AF16: 0.18552989 | AG16: 0.1536891 | AH16: -0.047648102 | AI16: -0.10992747 | AJ16: 1.7177629 | AK16: 2.2483905 | AL16: 0.37016618 | AM16: 4.9353815 | AN16: 7.1467938 | AO16: 2.8803404 | AP16: -95.321404 | AQ16: -0.0046500229
... A45: ISIC 97T98 | B45: 0 | C45: 0 | D45: 0 | E45: 0 | F45: 0 | G45: 0 | H45: 0 | I45: 0 | J45: 0 | K45: 0 | L45: 0 | M45: 0 | N45: 0 | O45: 0 | P45: 0 | Q45: 0 | R45: 0 | S45: 0 | T45: 0 | U45: 0 | V45: 0 | W45: 0 | X45: 0 | Y45: 0 | Z45: 0 | AA45: 0 | AB45: 0 | AC45: 0 | AD45: 0 | AE45: 0 | AF45: 0 | AG45: 0 | AH45: 0 | AI45: 0 | AJ45: 0 | AK45: 0 | AL45: 0 | AM45: 0 | AN45: 0 | AO45: 0 | AP45: 0 | AQ45: 1
A47: I Matrix
B49: ISIC 01T03 | C49: ISIC 05 | D49: ISIC 06 | E49: ISIC 07T08 | F49: ISIC 09 | G49: ISIC 10T12 | H49: ISIC 13T15 | I49: ISIC 16 | J49: ISIC 17T18 | K49: ISIC 19 | L49: ISIC 20 | M49: ISIC 21 | N49: ISIC 22 | O49: ISIC 231 | P49: ISIC 239 | Q49: ISIC 241 | R49: ISIC 242 | S49: ISIC 25 | T49: ISIC 26 | U49: ISIC 27 | V49: ISIC 28 | W49: ISIC 29 | X49: ISIC 30 | Y49: ISIC 31T33 | Z49: ISIC 351 | AA49: ISIC 352T353 | AB49: ISIC 36T39 | AC49: ISIC 41T43 | AD49: ISIC 45T47 | AE49: ISIC 49T53 | AF49: ISIC 55T56 | AG49: ISIC 58T60 | AH49: ISIC 61 | AI49: ISIC 62T63 | AJ49: ISIC 64T66 | AK49: ISIC 68 | AL49: ISIC 69T82 | AM49: ISIC 84 | AN49: ISIC 85 | AO49: ISIC 86T88 | AP49: ISIC 90T96 | AQ49: ISIC 97T98
A50: ISIC 01T03 | B50: 1 | C50: 0 | D50: 0 | E50: 0 | F50: 0 | G50: 0 | H50: 0 | I50: 0 | J50: 0 | K50: 0 | L50: 0 | M50: 0 | N50: 0 | O50: 0 | P50: 0 | Q50: 0 | R50: 0 | S50: 0 | T50: 0 | U50: 0 | V50: 0 | W50: 0 | X50: 0 | Y50: 0 | Z50: 0 | AA50: 0 | AB50: 0 | AC50: 0 | AD50: 0 | AE50: 0 | AF50: 0 | AG50: 0 | AH50: 0 | AI50: 0 | AJ50: 0 | AK50: 0 | AL50: 0 | AM50: 0 | AN50: 0 | AO50: 0 | AP50: 0 | AQ50: 0
A51: ISIC 05 | B51: 0 | C51: 1 | D51: 0 | E51: 0 | F51: 0 | G51: 0 | H51: 0 | I51: 0 | J51: 0 | K51: 0 | L51: 0 | M51: 0 | N51: 0 | O51: 0 | P51: 0 | Q51: 0 | R51: 0 | S51: 0 | T51: 0 | U51: 0 | V51: 0 | W51: 0 | X51: 0 | Y51: 0 | Z51: 0 | AA51: 0 | AB51: 0 | AC51: 0 | AD51: 0 | AE51: 0 | AF51: 0 | AG51: 0 | AH51: 0 | AI51: 0 | AJ51: 0 | AK51: 0 | AL51: 0 | AM51: 0 | AN51: 0 | AO51: 0 | AP51: 0 | AQ51: 0
A52: ISIC 06 | B52: 0 | C52: 0 | D52: 1 | E52: 0 | F52: 0 | G52: 0 | H52: 0 | I52: 0 | J52: 0 | K52: 0 | L52: 0 | M52: 0 | N52: 0 | O52: 0 | P52: 0 | Q52: 0 | R52: 0 | S52: 0 | T52: 0 | U52: 0 | V52: 0 | W52: 0 | X52: 0 | Y52: 0 | Z52: 0 | AA52: 0 | AB52: 0 | AC52: 0 | AD52: 0 | AE52: 0 | AF52: 0 | AG52: 0 | AH52: 0 | AI52: 0 | AJ52: 0 | AK52: 0 | AL52: 0 | AM52: 0 | AN52: 0 | AO52: 0 | AP52: 0 | AQ52: 0
A53: ISIC 07T08 | B53: 0 | C53: 0 | D53: 0 | E53: 1 | F53: 0 | G53: 0 | H53: 0 | I53: 0 | J53: 0 | K53: 0 | L53: 0 | M53: 0 | N53: 0 | O53: 0 | P53: 0 | Q53: 0 | R53: 0 | S53: 0 | T53: 0 | U53: 0 | V53: 0 | W53: 0 | X53: 0 | Y53: 0 | Z53: 0 | AA53: 0 | AB53: 0 | AC53: 0 | AD53: 0 | AE53: 0 | AF53: 0 | AG53: 0 | AH53: 0 | AI53: 0 | AJ53: 0 | AK53: 0 | AL53: 0 | AM53: 0 | AN53: 0 | AO53: 0 | AP53: 0 | AQ53: 0
A54: ISIC 09 | B54: 0 | C54: 0 | D54: 0 | E54: 0 | F54: 1 | G54: 0 | H54: 0 | I54: 0 | J54: 0 | K54: 0 | L54: 0 | M54: 0 | N54: 0 | O54: 0 | P54: 0 | Q54: 0 | R54: 0 | S54: 0 | T54: 0 | U54: 0 | V54: 0 | W54: 0 | X54: 0 | Y54: 0 | Z54: 0 | AA54: 0 | AB54: 0 | AC54: 0 | AD54: 0 | AE54: 0 | AF54: 0 | AG54: 0 | AH54: 0 | AI54: 0 | AJ54: 0 | AK54: 0 | AL54: 0 | AM54: 0 | AN54: 0 | AO54: 0 | AP54: 0 | AQ54: 0
A55: ISIC 10T12 | B55: 0 | C55: 0 | D55: 0 | E55: 0 | F55: 0 | G55: 1 | H55: 0 | I55: 0 | J55: 0 | K55: 0 | L55: 0 | M55: 0 | N55: 0 | O55: 0 | P55: 0 | Q55: 0 | R55: 0 | S55: 0 | T55: 0 | U55: 0 | V55: 0 | W55: 0 | X55: 0 | Y55: 0 | Z55: 0 | AA55: 0 | AB55: 0 | AC55: 0 | AD55: 0 | AE55: 0 | AF55: 0 | AG55: 0 | AH55: 0 | AI55: 0 | AJ55: 0 | AK55: 0 | AL55: 0 | AM55: 0 | AN55: 0 | AO55: 0 | AP55: 0 | AQ55: 0
A56: ISIC 13T15 | B56: 0 | C56: 0 | D56: 0 | E56: 0 | F56: 0 | G56: 0 | H56: 1 | I56: 0 | J56: 0 | K56: 0 | L56: 0 | M56: 0 | N56: 0 | O56: 0 | P56: 0 | Q56: 0 | R56: 0 | S56: 0 | T56: 0 | U56: 0 | V56: 0 | W56: 0 | X56: 0 | Y56: 0 | Z56: 0 | AA56: 0 | AB56: 0 | AC56: 0 | AD56: 0 | AE56: 0 | AF56: 0 | AG56: 0 | AH56: 0 | AI56: 0 | AJ56: 0 | AK56: 0 | AL56: 0 | AM56: 0 | AN56: 0 | AO56: 0 | AP56: 0 | AQ56: 0
A57: ISIC 16 | B57: 0 | C57: 0 | D57: 0 | E57: 0 | F57: 0 | G57: 0 | H57: 0 | I57: 1 | J57: 0 | K57: 0 | L57: 0 | M57: 0 | N57: 0 | O57: 0 | P57: 0 | Q57: 0 | R57: 0 | S57: 0 | T57: 0 | U57: 0 | V57: 0 | W57: 0 | X57: 0 | Y57: 0 | Z57: 0 | AA57: 0 | AB57: 0 | AC57: 0 | AD57: 0 | AE57: 0 | AF57: 0 | AG57: 0 | AH57: 0 | AI57: 0 | AJ57: 0 | AK57: 0 | AL57: 0 | AM57: 0 | AN57: 0 | AO57: 0 | AP57: 0 | AQ57: 0
A58: ISIC 17T18 | B58: 0 | C58: 0 | D58: 0 | E58: 0 | F58: 0 | G58: 0 | H58: 0 | I58: 0 | J58: 1 | K58: 0 | L58: 0 | M58: 0 | N58: 0 | O58: 0 | P58: 0 | Q58: 0 | R58: 0 | S58: 0 | T58: 0 | U58: 0 | V58: 0 | W58: 0 | X58: 0 | Y58: 0 | Z58: 0 | AA58: 0 | AB58: 0 | AC58: 0 | AD58: 0 | AE58: 0 | AF58: 0 | AG58: 0 | AH58: 0 | AI58: 0 | AJ58: 0 | AK58: 0 | AL58: 0 | AM58: 0 | AN58: 0 | AO58: 0 | AP58: 0 | AQ58: 0
A59: ISIC 19 | B59: 0 | C59: 0 | D59: 0 | E59: 0 | F59: 0 | G59: 0 | H59: 0 | I59: 0 | J59: 0 | K59: 1 | L59: 0 | M59: 0 | N59: 0 | O59: 0 | P59: 0 | Q59: 0 | R59: 0 | S59: 0 | T59: 0 | U59: 0 | V59: 0 | W59: 0 | X59: 0 | Y59: 0 | Z59: 0 | AA59: 0 | AB59: 0 | AC59: 0 | AD59: 0 | AE59: 0 | AF59: 0 | AG59: 0 | AH59: 0 | AI59: 0 | AJ59: 0 | AK59: 0 | AL59: 0 | AM59: 0 | AN59: 0 | AO59: 0 | AP59: 0 | AQ59: 0
A60: ISIC 20 | B60: 0 | C60: 0 | D60: 0 | E60: 0 | F60: 0 | G60: 0 | H60: 0 | I60: 0 | J60: 0 | K60: 0 | L60: 1 | M60: 0 | N60: 0 | O60: 0 | P60: 0 | Q60: 0 | R60: 0 | S60: 0 | T60: 0 | U60: 0 | V60: 0 | W60: 0 | X60: 0 | Y60: 0 | Z60: 0 | AA60: 0 | AB60: 0 | AC60: 0 | AD60: 0 | AE60: 0 | AF60: 0 | AG60: 0 | AH60: 0 | AI60: 0 | AJ60: 0 | AK60: 0 | AL60: 0 | AM60: 0 | AN60: 0 | AO60: 0 | AP60: 0 | AQ60: 0
A61: ISIC 21 | B61: 0 | C61: 0 | D61: 0 | E61: 0 | F61: 0 | G61: 0 | H61: 0 | I61: 0 | J61: 0 | K61: 0 | L61: 0 | M61: 1 | N61: 0 | O61: 0 | P61: 0 | Q61: 0 | R61: 0 | S61: 0 | T61: 0 | U61: 0 | V61: 0 | W61: 0 | X61: 0 | Y61: 0 | Z61: 0 | AA61: 0 | AB61: 0 | AC61: 0 | AD61: 0 | AE61: 0 | AF61: 0 | AG61: 0 | AH61: 0 | AI61: 0 | AJ61: 0 | AK61: 0 | AL61: 0 | AM61: 0 | AN61: 0 | AO61: 0 | AP61: 0 | AQ61: 0
... A91: ISIC 97T98 | B91: 0 | C91: 0 | D91: 0 | E91: 0 | F91: 0 | G91: 0 | H91: 0 | I91: 0 | J91: 0 | K91: 0 | L91: 0 | M91: 0 | N91: 0 | O91: 0 | P91: 0 | Q91: 0 | R91: 0 | S91: 0 | T91: 0 | U91: 0 | V91: 0 | W91: 0 | X91: 0 | Y91: 0 | Z91: 0 | AA91: 0 | AB91: 0 | AC91: 0 | AD91: 0 | AE91: 0 | AF91: 0 | AG91: 0 | AH91: 0 | AI91: 0 | AJ91: 0 | AK91: 0 | AL91: 0 | AM91: 0 | AN91: 0 | AO91: 0 | AP91: 0 | AQ91: 1
A93: A Matrix
B95: ISIC 01T03 | C95: ISIC 05 | D95: ISIC 06 | E95: ISIC 07T08 | F95: ISIC 09 | G95: ISIC 10T12 | H95: ISIC 13T15 | I95: ISIC 16 | J95: ISIC 17T18 | K95: ISIC 19 | L95: ISIC 20 | M95: ISIC 21 | N95: ISIC 22 | O95: ISIC 231 | P95: ISIC 239 | Q95: ISIC 241 | R95: ISIC 242 | S95: ISIC 25 | T95: ISIC 26 | U95: ISIC 27 | V95: ISIC 28 | W95: ISIC 29 | X95: ISIC 30 | Y95: ISIC 31T33 | Z95: ISIC 351 | AA95: ISIC 352T353 | AB95: ISIC 36T39 | AC95: ISIC 41T43 | AD95: ISIC 45T47 | AE95: ISIC 49T53 | AF95: ISIC 55T56 | AG95: ISIC 58T60 | AH95: ISIC 61 | AI95: ISIC 62T63 | AJ95: ISIC 64T66 | AK95: ISIC 68 | AL95: ISIC 69T82 | AM95: ISIC 84 | AN95: ISIC 85 | AO95: ISIC 86T88 | AP95: ISIC 90T96 | AQ95: ISIC 97T98
A96: ISIC 01T03 | B96: =B50-B4 -> -1.9432153 | C96: =C50-C4 -> 25.977206 | D96: =D50-D4 -> -8.4242198 | E96: =E50-E4 -> -0.14111685 | F96: =F50-F4 -> -0.2231858 | G96: =G50-G4 -> -0.23918731 | H96: =H50-H4 -> 690215.88 | I96: =I50-I4 -> -76433.089 | ... AQ96: =AQ50-AQ4 -> -0.0037622831
A97: ISIC 05 | B97: =B51-B5 -> 3.095982 | C97: =C51-C5 -> -28.566052 | D97: =D51-D5 -> 9.4289327 | E97: =E51-E5 -> 0.14864601 | F97: =F51-F5 -> 0.24412955 | G97: =G51-G5 -> 0.25780952 | H97: =H51-H5 -> -781502.98 | I97: =I51-I5 -> 85587.253 | ... AQ97: =AQ51-AQ5 -> 0.0042813162
A98: ISIC 06 | B98: =B52-B6 -> 4.8276352 | C98: =C52-C6 -> -45.062724 | D98: =D52-D6 -> 14.836501 | E98: =E52-E6 -> 0.22046797 | F98: =F52-F6 -> 0.35778411 | G98: =G52-G6 -> 0.42348027 | H98: =H52-H6 -> -1229525.2 | I98: =I52-I6 -> 134808.89 | ... AQ98: =AQ52-AQ6 -> 0.0065243613
A99: ISIC 07T08 | B99: =B53-B7 -> -6.7837163 | C99: =C53-C7 -> 61.900136 | D99: =D53-D7 -> -20.598079 | E99: =E53-E7 -> -0.31684674 | F99: =F53-F7 -> -0.53523704 | G99: =G53-G7 -> -0.51544062 | H99: =H53-H7 -> 1707451.1 | I99: =I53-I7 -> -186315.25 | ... AQ99: =AQ53-AQ7 -> -0.0089605983
A100: ISIC 09 | B100: =B54-B8 -> 0.24970382 | C100: =C54-C8 -> -2.2863379 | D100: =D54-D8 -> 0.7547337 | E100: =E54-E8 -> 0.014827919 | F100: =F54-F8 -> 0.037028436 | G100: =G54-G8 -> 0.020297226 | H100: =H54-H8 -> -62410.952 | I100: =I54-I8 -> 6839.2495 | ... AQ100: =AQ54-AQ8 -> 0.00033101252
A101: ISIC 10T12 | B101: =B55-B9 -> -12.347012 | C101: =C55-C9 -> 113.92568 | D101: =D55-D9 -> -37.668823 | E101: =E55-E9 -> -0.60265601 | F101: =F55-F9 -> -0.97984486 | G101: =G55-G9 -> -0.94940228 | H101: =H55-H9 -> 3122107.7 | I101: =I55-I9 -> -341691.25 | ... AQ101: =AQ55-AQ9 -> -0.016493225
A102: ISIC 13T15 | B102: =B56-B10 -> 1320.624 | C102: =C56-C10 -> -12093.935 | D102: =D56-D10 -> 4002.6535 | E102: =E56-E10 -> 64.070627 | F102: =F56-F10 -> 104.17606 | G102: =G56-G10 -> 106.17066 | H102: =H56-H10 -> -3.317302e+08 | I102: =I56-I10 -> 36290703 | ... AQ102: =AQ56-AQ10 -> 1.7508317
A103: ISIC 16 | B103: =B57-B11 -> -225.66685 | C103: =C57-C11 -> 2002.28 | D103: =D57-D11 -> -664.55301 | E103: =E57-E11 -> -10.572838 | F103: =F57-F11 -> -17.266746 | G103: =G57-G11 -> -15.727699 | H103: =H57-H11 -> 55137115 | I103: =I57-I11 -> -6022675.7 | ... AQ103: =AQ57-AQ11 -> -0.28985269
A104: ISIC 17T18 | B104: =B58-B12 -> 5.9621381 | C104: =C58-C12 -> -53.620326 | D104: =D58-D12 -> 17.986784 | E104: =E58-E12 -> 0.29101749 | F104: =F58-F12 -> 0.48489238 | G104: =G58-G12 -> 0.4137812 | H104: =H58-H12 -> -1487155.4 | I104: =I58-I12 -> 161813.6 | ... AQ104: =AQ58-AQ12 -> 0.0077608907
A105: ISIC 19 | B105: =B59-B13 -> -2.6144883 | C105: =C59-C13 -> 25.082377 | D105: =D59-D13 -> -8.2098226 | E105: =E59-E13 -> -0.10569536 | F105: =F59-F13 -> -0.16635108 | G105: =G59-G13 -> -0.25719064 | H105: =H59-H13 -> 680203.09 | I105: =I59-I13 -> -74779.357 | ... AQ105: =AQ59-AQ13 -> -0.003631945
A106: ISIC 20 | B106: =B60-B14 -> -15.433423 | C106: =C60-C14 -> 142.729 | D106: =D60-D14 -> -47.05198 | E106: =E60-E14 -> -0.73878956 | F106: =F60-F14 -> -1.2161894 | G106: =G60-G14 -> -1.3024782 | H106: =H60-H14 -> 3900606.7 | I106: =I60-I14 -> -427388.3 | ... AQ106: =AQ60-AQ14 -> -0.020664201
A107: ISIC 21 | B107: =B61-B15 -> 0.099735843 | C107: =C61-C15 -> -0.85773994 | D107: =D61-D15 -> 0.28429274 | E107: =E61-E15 -> 0.0044725948 | F107: =F61-F15 -> 0.0073174605 | G107: =G61-G15 -> 0.0070119827 | H107: =H61-H15 -> -23672.115 | I107: =I61-I15 -> 2584.5437 | ... AQ107: =AQ61-AQ15 -> 0.00012416729
... A137: ISIC 97T98 | B137: =B91-B45 -> 0 | C137: =C91-C45 -> 0 | D137: =D91-D45 -> 0 | E137: =E91-E45 -> 0 | F137: =F91-F45 -> 0 | G137: =G91-G45 -> 0 | H137: =H91-H45 -> 0 | I137: =I91-I45 -> 0 | ... AQ137: =AQ91-AQ45 -> 0
A139: Standard Input Output Matrix
B141: ISIC 01T03 | C141: ISIC 05 | D141: ISIC 06 | E141: ISIC 07T08 | F141: ISIC 09 | G141: ISIC 10T12 | H141: ISIC 13T15 | I141: ISIC 16 | J141: ISIC 17T18 | K141: ISIC 19 | L141: ISIC 20 | M141: ISIC 21 | N141: ISIC 22 | O141: ISIC 231 | P141: ISIC 239 | Q141: ISIC 241 | R141: ISIC 242 | S141: ISIC 25 | T141: ISIC 26 | U141: ISIC 27 | V141: ISIC 28 | W141: ISIC 29 | X141: ISIC 30 | Y141: ISIC 31T33 | Z141: ISIC 351 | AA141: ISIC 352T353 | AB141: ISIC 36T39 | AC141: ISIC 41T43 | AD141: ISIC 45T47 | AE141: ISIC 49T53 | AF141: ISIC 55T56 | AG141: ISIC 58T60 | AH141: ISIC 61 | AI141: ISIC 62T63 | AJ141: ISIC 64T66 | AK141: ISIC 68 | AL141: ISIC 69T82 | AM141: ISIC 84 | AN141: ISIC 85 | AO141: ISIC 86T88 | AP141: ISIC 90T96 | AQ141: ISIC 97T98
A142: ISIC 01T03 | B142: =IF(B96*'Pre ISIC Split BObIC'!B$2>0,B96*'Pre ISIC Split BObIC'!B$2,0) -> 0 | C142: =IF(C96*'Pre ISIC Split BObIC'!C$2>0,C96*'Pre ISIC Split BObIC'!C$2,0) -> 1.2692018e+10 | D142: =IF(D96*'Pre ISIC Split BObIC'!D$2>0,D96*'Pre ISIC Split BObIC'!D$2,0) -> 0 | E142: =IF(E96*'Pre ISIC Split BObIC'!E$2>0,E96*'Pre ISIC Split BObIC'!E$2,0) -> 0 | F142: =IF(F96*'Pre ISIC Split BObIC'!F$2>0,F96*'Pre ISIC Split BObIC'!F$2,0) -> 0 | G142: =IF(G96*'Pre ISIC Split BObIC'!G$2>0,G96*'Pre ISIC Split BObIC'!G$2,0) -> 0 | H142: =IF(H96*'Pre ISIC Split BObIC'!H$2>0,H96*'Pre ISIC Split BObIC'!H$2,0) -> 1.3506649e+16 | I142: =IF(I96*'Pre ISIC Split BObIC'!I$2>0,I96*'Pre ISIC Split BObIC'!I$2,0) -> 0 | ... AQ142: =IF(AQ96*'Pre ISIC Split BObIC'!AQ$2>0,AQ96*'Pre ISIC Split BObIC'!AQ$2,0) -> 0
A143: ISIC 05 | B143: =IF(B97*'Pre ISIC Split BObIC'!B$2>0,B97*'Pre ISIC Split BObIC'!B$2,0) -> 1.620108e+11 | C143: =IF(C97*'Pre ISIC Split BObIC'!C$2>0,C97*'Pre ISIC Split BObIC'!C$2,0) -> 0 | D143: =IF(D97*'Pre ISIC Split BObIC'!D$2>0,D97*'Pre ISIC Split BObIC'!D$2,0) -> 3.9740819e+11 | E143: =IF(E97*'Pre ISIC Split BObIC'!E$2>0,E97*'Pre ISIC Split BObIC'!E$2,0) -> 2.5231381e+09 | F143: =IF(F97*'Pre ISIC Split BObIC'!F$2>0,F97*'Pre ISIC Split BObIC'!F$2,0) -> 1.7579132e+09 | G143: =IF(G97*'Pre ISIC Split BObIC'!G$2>0,G97*'Pre ISIC Split BObIC'!G$2,0) -> 3.3268609e+10 | H143: =IF(H97*'Pre ISIC Split BObIC'!H$2>0,H97*'Pre ISIC Split BObIC'!H$2,0) -> 0 | I143: =IF(I97*'Pre ISIC Split BObIC'!I$2>0,I97*'Pre ISIC Split BObIC'!I$2,0) -> 3.3720051e+14 | ... AQ143: =IF(AQ97*'Pre ISIC Split BObIC'!AQ$2>0,AQ97*'Pre ISIC Split BObIC'!AQ$2,0) -> 20258019
A144: ISIC 06 | B144: =IF(B98*'Pre ISIC Split BObIC'!B$2>0,B98*'Pre ISIC Split BObIC'!B$2,0) -> 2.5262714e+11 | C144: =IF(C98*'Pre ISIC Split BObIC'!C$2>0,C98*'Pre ISIC Split BObIC'!C$2,0) -> 0 | D144: =IF(D98*'Pre ISIC Split BObIC'!D$2>0,D98*'Pre ISIC Split BObIC'!D$2,0) -> 6.2532497e+11 | E144: =IF(E98*'Pre ISIC Split BObIC'!E$2>0,E98*'Pre ISIC Split BObIC'!E$2,0) -> 3.7422539e+09 | F144: =IF(F98*'Pre ISIC Split BObIC'!F$2>0,F98*'Pre ISIC Split BObIC'!F$2,0) -> 2.57631e+09 | G144: =IF(G98*'Pre ISIC Split BObIC'!G$2>0,G98*'Pre ISIC Split BObIC'!G$2,0) -> 5.4647321e+10 | H144: =IF(H98*'Pre ISIC Split BObIC'!H$2>0,H98*'Pre ISIC Split BObIC'!H$2,0) -> 0 | I144: =IF(I98*'Pre ISIC Split BObIC'!I$2>0,I98*'Pre ISIC Split BObIC'!I$2,0) -> 5.3112611e+14 | ... AQ144: =IF(AQ98*'Pre ISIC Split BObIC'!AQ$2>0,AQ98*'Pre ISIC Split BObIC'!AQ$2,0) -> 30871497
A145: ISIC 07T08 | B145: =IF(B99*'Pre ISIC Split BObIC'!B$2>0,B99*'Pre ISIC Split BObIC'!B$2,0) -> 0 | C145: =IF(C99*'Pre ISIC Split BObIC'!C$2>0,C99*'Pre ISIC Split BObIC'!C$2,0) -> 3.0243345e+10 | D145: =IF(D99*'Pre ISIC Split BObIC'!D$2>0,D99*'Pre ISIC Split BObIC'!D$2,0) -> 0 | E145: =IF(E99*'Pre ISIC Split BObIC'!E$2>0,E99*'Pre ISIC Split BObIC'!E$2,0) -> 0 | F145: =IF(F99*'Pre ISIC Split BObIC'!F$2>0,F99*'Pre ISIC Split BObIC'!F$2,0) -> 0 | G145: =IF(G99*'Pre ISIC Split BObIC'!G$2>0,G99*'Pre ISIC Split BObIC'!G$2,0) -> 0 | H145: =IF(H99*'Pre ISIC Split BObIC'!H$2>0,H99*'Pre ISIC Split BObIC'!H$2,0) -> 3.3412652e+16 | I145: =IF(I99*'Pre ISIC Split BObIC'!I$2>0,I99*'Pre ISIC Split BObIC'!I$2,0) -> 0 | ... AQ145: =IF(AQ99*'Pre ISIC Split BObIC'!AQ$2>0,AQ99*'Pre ISIC Split BObIC'!AQ$2,0) -> 0
A146: ISIC 09 | B146: =IF(B100*'Pre ISIC Split BObIC'!B$2>0,B100*'Pre ISIC Split BObIC'!B$2,0) -> 1.3066845e+10 | C146: =IF(C100*'Pre ISIC Split BObIC'!C$2>0,C100*'Pre ISIC Split BObIC'!C$2,0) -> 0 | D146: =IF(D100*'Pre ISIC Split BObIC'!D$2>0,D100*'Pre ISIC Split BObIC'!D$2,0) -> 3.1810319e+10 | E146: =IF(E100*'Pre ISIC Split BObIC'!E$2>0,E100*'Pre ISIC Split BObIC'!E$2,0) -> 2.5169116e+08 | F146: =IF(F100*'Pre ISIC Split BObIC'!F$2>0,F100*'Pre ISIC Split BObIC'!F$2,0) -> 2.666321e+08 | G146: =IF(G100*'Pre ISIC Split BObIC'!G$2>0,G100*'Pre ISIC Split BObIC'!G$2,0) -> 2.6192224e+09 | H146: =IF(H100*'Pre ISIC Split BObIC'!H$2>0,H100*'Pre ISIC Split BObIC'!H$2,0) -> 0 | I146: =IF(I100*'Pre ISIC Split BObIC'!I$2>0,I100*'Pre ISIC Split BObIC'!I$2,0) -> 2.6945583e+13 | ... AQ146: =IF(AQ100*'Pre ISIC Split BObIC'!AQ$2>0,AQ100*'Pre ISIC Split BObIC'!AQ$2,0) -> 1566260.9
A147: ISIC 10T12 | B147: =IF(B101*'Pre ISIC Split BObIC'!B$2>0,B101*'Pre ISIC Split BObIC'!B$2,0) -> 0 | C147: =IF(C101*'Pre ISIC Split BObIC'!C$2>0,C101*'Pre ISIC Split BObIC'!C$2,0) -> 5.5662132e+10 | D147: =IF(D101*'Pre ISIC Split BObIC'!D$2>0,D101*'Pre ISIC Split BObIC'!D$2,0) -> 0 | E147: =IF(E101*'Pre ISIC Split BObIC'!E$2>0,E101*'Pre ISIC Split BObIC'!E$2,0) -> 0 | F147: =IF(F101*'Pre ISIC Split BObIC'!F$2>0,F101*'Pre ISIC Split BObIC'!F$2,0) -> 0 | G147: =IF(G101*'Pre ISIC Split BObIC'!G$2>0,G101*'Pre ISIC Split BObIC'!G$2,0) -> 0 | H147: =IF(H101*'Pre ISIC Split BObIC'!H$2>0,H101*'Pre ISIC Split BObIC'!H$2,0) -> 6.1095685e+16 | I147: =IF(I101*'Pre ISIC Split BObIC'!I$2>0,I101*'Pre ISIC Split BObIC'!I$2,0) -> 0 | ... AQ147: =IF(AQ101*'Pre ISIC Split BObIC'!AQ$2>0,AQ101*'Pre ISIC Split BObIC'!AQ$2,0) -> 0
A148: ISIC 13T15 | B148: =IF(B102*'Pre ISIC Split BObIC'!B$2>0,B102*'Pre ISIC Split BObIC'!B$2,0) -> 6.9107432e+13 | C148: =IF(C102*'Pre ISIC Split BObIC'!C$2>0,C102*'Pre ISIC Split BObIC'!C$2,0) -> 0 | D148: =IF(D102*'Pre ISIC Split BObIC'!D$2>0,D102*'Pre ISIC Split BObIC'!D$2,0) -> 1.6870279e+14 | E148: =IF(E102*'Pre ISIC Split BObIC'!E$2>0,E102*'Pre ISIC Split BObIC'!E$2,0) -> 1.0875437e+12 | F148: =IF(F102*'Pre ISIC Split BObIC'!F$2>0,F102*'Pre ISIC Split BObIC'!F$2,0) -> 7.5014462e+11 | G148: =IF(G102*'Pre ISIC Split BObIC'!G$2>0,G102*'Pre ISIC Split BObIC'!G$2,0) -> 1.3700619e+13 | H148: =IF(H102*'Pre ISIC Split BObIC'!H$2>0,H102*'Pre ISIC Split BObIC'!H$2,0) -> 0 | I148: =IF(I102*'Pre ISIC Split BObIC'!I$2>0,I102*'Pre ISIC Split BObIC'!I$2,0) -> 1.4297975e+17 | ... AQ148: =IF(AQ102*'Pre ISIC Split BObIC'!AQ$2>0,AQ102*'Pre ISIC Split BObIC'!AQ$2,0) -> 8.2844576e+09
A149: ISIC 16 | B149: =IF(B103*'Pre ISIC Split BObIC'!B$2>0,B103*'Pre ISIC Split BObIC'!B$2,0) -> 0 | C149: =IF(C103*'Pre ISIC Split BObIC'!C$2>0,C103*'Pre ISIC Split BObIC'!C$2,0) -> 9.7827968e+11 | D149: =IF(D103*'Pre ISIC Split BObIC'!D$2>0,D103*'Pre ISIC Split BObIC'!D$2,0) -> 0 | E149: =IF(E103*'Pre ISIC Split BObIC'!E$2>0,E103*'Pre ISIC Split BObIC'!E$2,0) -> 0 | F149: =IF(F103*'Pre ISIC Split BObIC'!F$2>0,F103*'Pre ISIC Split BObIC'!F$2,0) -> 0 | G149: =IF(G103*'Pre ISIC Split BObIC'!G$2>0,G103*'Pre ISIC Split BObIC'!G$2,0) -> 0 | H149: =IF(H103*'Pre ISIC Split BObIC'!H$2>0,H103*'Pre ISIC Split BObIC'!H$2,0) -> 1.0789634e+18 | I149: =IF(I103*'Pre ISIC Split BObIC'!I$2>0,I103*'Pre ISIC Split BObIC'!I$2,0) -> 0 | ... AQ149: =IF(AQ103*'Pre ISIC Split BObIC'!AQ$2>0,AQ103*'Pre ISIC Split BObIC'!AQ$2,0) -> 0
A150: ISIC 17T18 | B150: =IF(B104*'Pre ISIC Split BObIC'!B$2>0,B104*'Pre ISIC Split BObIC'!B$2,0) -> 3.1199497e+11 | C150: =IF(C104*'Pre ISIC Split BObIC'!C$2>0,C104*'Pre ISIC Split BObIC'!C$2,0) -> 0 | D150: =IF(D104*'Pre ISIC Split BObIC'!D$2>0,D104*'Pre ISIC Split BObIC'!D$2,0) -> 7.5810226e+11 | E150: =IF(E104*'Pre ISIC Split BObIC'!E$2>0,E104*'Pre ISIC Split BObIC'!E$2,0) -> 4.9397714e+09 | F150: =IF(F104*'Pre ISIC Split BObIC'!F$2>0,F104*'Pre ISIC Split BObIC'!F$2,0) -> 3.4915835e+09 | G150: =IF(G104*'Pre ISIC Split BObIC'!G$2>0,G104*'Pre ISIC Split BObIC'!G$2,0) -> 5.339572e+10 | H150: =IF(H104*'Pre ISIC Split BObIC'!H$2>0,H104*'Pre ISIC Split BObIC'!H$2,0) -> 0 | I150: =IF(I104*'Pre ISIC Split BObIC'!I$2>0,I104*'Pre ISIC Split BObIC'!I$2,0) -> 637520491489868 | ... AQ150: =IF(AQ104*'Pre ISIC Split BObIC'!AQ$2>0,AQ104*'Pre ISIC Split BObIC'!AQ$2,0) -> 36722416
A151: ISIC 19 | B151: =IF(B105*'Pre ISIC Split BObIC'!B$2>0,B105*'Pre ISIC Split BObIC'!B$2,0) -> 0 | C151: =IF(C105*'Pre ISIC Split BObIC'!C$2>0,C105*'Pre ISIC Split BObIC'!C$2,0) -> 1.2254819e+10 | D151: =IF(D105*'Pre ISIC Split BObIC'!D$2>0,D105*'Pre ISIC Split BObIC'!D$2,0) -> 0 | E151: =IF(E105*'Pre ISIC Split BObIC'!E$2>0,E105*'Pre ISIC Split BObIC'!E$2,0) -> 0 | F151: =IF(F105*'Pre ISIC Split BObIC'!F$2>0,F105*'Pre ISIC Split BObIC'!F$2,0) -> 0 | G151: =IF(G105*'Pre ISIC Split BObIC'!G$2>0,G105*'Pre ISIC Split BObIC'!G$2,0) -> 0 | H151: =IF(H105*'Pre ISIC Split BObIC'!H$2>0,H105*'Pre ISIC Split BObIC'!H$2,0) -> 1.3310711e+16 | I151: =IF(I105*'Pre ISIC Split BObIC'!I$2>0,I105*'Pre ISIC Split BObIC'!I$2,0) -> 0 | ... AQ151: =IF(AQ105*'Pre ISIC Split BObIC'!AQ$2>0,AQ105*'Pre ISIC Split BObIC'!AQ$2,0) -> 0
A152: ISIC 20 | B152: =IF(B106*'Pre ISIC Split BObIC'!B$2>0,B106*'Pre ISIC Split BObIC'!B$2,0) -> 0 | C152: =IF(C106*'Pre ISIC Split BObIC'!C$2>0,C106*'Pre ISIC Split BObIC'!C$2,0) -> 6.9734943e+10 | D152: =IF(D106*'Pre ISIC Split BObIC'!D$2>0,D106*'Pre ISIC Split BObIC'!D$2,0) -> 0 | E152: =IF(E106*'Pre ISIC Split BObIC'!E$2>0,E106*'Pre ISIC Split BObIC'!E$2,0) -> 0 | F152: =IF(F106*'Pre ISIC Split BObIC'!F$2>0,F106*'Pre ISIC Split BObIC'!F$2,0) -> 0 | G152: =IF(G106*'Pre ISIC Split BObIC'!G$2>0,G106*'Pre ISIC Split BObIC'!G$2,0) -> 0 | H152: =IF(H106*'Pre ISIC Split BObIC'!H$2>0,H106*'Pre ISIC Split BObIC'!H$2,0) -> 7.6329922e+16 | I152: =IF(I106*'Pre ISIC Split BObIC'!I$2>0,I106*'Pre ISIC Split BObIC'!I$2,0) -> 0 | ... AQ152: =IF(AQ106*'Pre ISIC Split BObIC'!AQ$2>0,AQ106*'Pre ISIC Split BObIC'!AQ$2,0) -> 0
A153: ISIC 21 | B153: =IF(B107*'Pre ISIC Split BObIC'!B$2>0,B107*'Pre ISIC Split BObIC'!B$2,0) -> 5.2191144e+09 | C153: =IF(C107*'Pre ISIC Split BObIC'!C$2>0,C107*'Pre ISIC Split BObIC'!C$2,0) -> 0 | D153: =IF(D107*'Pre ISIC Split BObIC'!D$2>0,D107*'Pre ISIC Split BObIC'!D$2,0) -> 1.1982296e+10 | E153: =IF(E107*'Pre ISIC Split BObIC'!E$2>0,E107*'Pre ISIC Split BObIC'!E$2,0) -> 75918446 | F153: =IF(F107*'Pre ISIC Split BObIC'!F$2>0,F107*'Pre ISIC Split BObIC'!F$2,0) -> 52691123 | G153: =IF(G107*'Pre ISIC Split BObIC'!G$2>0,G107*'Pre ISIC Split BObIC'!G$2,0) -> 9.0484987e+08 | H153: =IF(H107*'Pre ISIC Split BObIC'!H$2>0,H107*'Pre ISIC Split BObIC'!H$2,0) -> 0 | I153: =IF(I107*'Pre ISIC Split BObIC'!I$2>0,I107*'Pre ISIC Split BObIC'!I$2,0) -> 1.0182701e+13 | ... AQ153: =IF(AQ107*'Pre ISIC Split BObIC'!AQ$2>0,AQ107*'Pre ISIC Split BObIC'!AQ$2,0) -> 587525.72
... A183: ISIC 97T98 | B183: =IF(B137*'Pre ISIC Split BObIC'!B$2>0,B137*'Pre ISIC Split BObIC'!B$2,0) -> 0 | C183: =IF(C137*'Pre ISIC Split BObIC'!C$2>0,C137*'Pre ISIC Split BObIC'!C$2,0) -> 0 | D183: =IF(D137*'Pre ISIC Split BObIC'!D$2>0,D137*'Pre ISIC Split BObIC'!D$2,0) -> 0 | E183: =IF(E137*'Pre ISIC Split BObIC'!E$2>0,E137*'Pre ISIC Split BObIC'!E$2,0) -> 0 | F183: =IF(F137*'Pre ISIC Split BObIC'!F$2>0,F137*'Pre ISIC Split BObIC'!F$2,0) -> 0 | G183: =IF(G137*'Pre ISIC Split BObIC'!G$2>0,G137*'Pre ISIC Split BObIC'!G$2,0) -> 0 | H183: =IF(H137*'Pre ISIC Split BObIC'!H$2>0,H137*'Pre ISIC Split BObIC'!H$2,0) -> 0 | I183: =IF(I137*'Pre ISIC Split BObIC'!I$2>0,I137*'Pre ISIC Split BObIC'!I$2,0) -> 0 | ... AQ183: =IF(AQ137*'Pre ISIC Split BObIC'!AQ$2>0,AQ137*'Pre ISIC Split BObIC'!AQ$2,0) -> 0

Sheet SIOM
A1: *Note for CEA: This table is mostly complete, but is just missing values for some of the orange highlighted boxes. You can copy the method used in the first orange box (cells D4:E5) to fill out the others. Once you've done that, the FoGPbEaIC-isic tab will correctly reflect the share by entity.
B2: Matching EPS Industry | C2: D01T03: Agriculture, forestry and fishing | D2: coal mining 05 | E2: oil and gas extraction 06 | F2: D07T08: Mining and quarrying of non-energy producing products | G2: D09: Mining support service activities | H2: D10T12: Food products, beverages and tobacco | I2: D13T15: Textiles, wearing apparel, leather and related products | J2: D16: Wood and products of wood and cork | K2: D17T18: Paper products and printing | L2: D19: Coke and refined petroleum products | M2: chemicals 20 | N2: pharmaceuticals | O2: D22: Rubber and plastic products | P2: glass and glass products 231 | Q2: cement and other nonmetallic minerals 239 | R2: iron and steel 241 | S2: other metals 242 | T2: D25: Fabricated metal products | U2: D26: Computer, electronic and optical products | V2: D27: Electrical equipment | W2: D28: Machinery and equipment, nec | X2: D29: Motor vehicles, trailers and semi-trailers | Y2: D30: Other transport equipment | Z2: D31T33: Other manufacturing; repair and installation of machinery and equipment | AA2: electricity | AB2: energy pipelines and gas processing 352T353 | AC2: water and waste 36T39 | AD2: D41T43: Construction | AE2: D45T47: Wholesale and retail trade; repair of motor vehicles | AF2: D49T53: Transportation and storage | AG2: D55T56: Accomodation and food services | AH2: D58T60: Publishing, audiovisual and broadcasting activities | AI2: D61: Telecommunications | AJ2: D62T63: IT and other information services | AK2: D64T66: Financial and insurance activities | AL2: D68: Real estate activities | AM2: D69T82: Other business sector services | AN2: D84: Public admin. and defence; compulsory social security | AO2: D85: Education | AP2: D86T88: Human health and social work | AQ2: D90T96: Arts, entertainment, recreation and other service activities | AR2: D97T98: Private households with employed persons
A3: D01T03: Agriculture, forestry and fishing | B3: agriculture and forestry 01T03 | C3: ='OECD TTL - 2018'!C9 -> 5034.6 | D3: ='OECD TTL - 2018'!$D9*'SIOM from DLIM'!C142/SUM('SIOM from DLIM'!$C142:$D142) -> 8.1 | E3: ='OECD TTL - 2018'!$D9*'SIOM from DLIM'!D142/SUM('SIOM from DLIM'!$C142:$D142) -> 0 | F3: ='OECD TTL - 2018'!E9 -> 22.4 | G3: ='OECD TTL - 2018'!F9 -> 8.2 | H3: ='OECD TTL - 2018'!G9 -> 30244.9 | I3: ='OECD TTL - 2018'!H9 -> 425.8 | J3: ='OECD TTL - 2018'!I9 -> 494.3 | K3: ='OECD TTL - 2018'!J9 -> 325.3 | L3: ='OECD TTL - 2018'!K9 -> 39.8 | M3: ='OECD TTL - 2018'!$L9*'SIOM from DLIM'!L142/SUM('SIOM from DLIM'!$L142:$M142) -> 461.12441 | N3: ='OECD TTL - 2018'!$L9*'SIOM from DLIM'!M142/SUM('SIOM from DLIM'!$L142:$M142) -> 78.475586 | O3: ='OECD TTL - 2018'!M9 -> 153.5 | P3: ='OECD TTL - 2018'!$N9*'SIOM from DLIM'!O142/SUM('SIOM from DLIM'!$O142:$P142) -> 5.8903742 | Q3: ='OECD TTL - 2018'!$N9*'SIOM from DLIM'!P142/SUM('SIOM from DLIM'!$O142:$P142) -> 2.9096258 | R3: ='OECD TTL - 2018'!$O9*'SIOM from DLIM'!Q142/SUM('SIOM from DLIM'!$Q142:$R142) -> 19.5 | S3: ='OECD TTL - 2018'!$O9*'SIOM from DLIM'!R142/SUM('SIOM from DLIM'!$Q142:$R142) -> 0 | T3: ='OECD TTL - 2018'!P9 -> 9.7 | U3: ='OECD TTL - 2018'!Q9 -> 7.4 | V3: ='OECD TTL - 2018'!R9 -> 6.9 | W3: ='OECD TTL - 2018'!S9 -> 6.8 | X3: ='OECD TTL - 2018'!T9 -> 25.1 | Y3: ='OECD TTL - 2018'!U9 -> 0.5 | Z3: ='OECD TTL - 2018'!V9 -> 132.5 | AA3: ='OECD TTL - 2018'!$W9*'SIOM from DLIM'!Z142/SUM('SIOM from DLIM'!$Z142:$AB142) -> #DIV/0! | AB3: ='OECD TTL - 2018'!$W9*'SIOM from DLIM'!AA142/SUM('SIOM from DLIM'!$Z142:$AB142) -> #DIV/0! | AC3: ='OECD TTL - 2018'!$W9*'SIOM from DLIM'!AB142/SUM('SIOM from DLIM'!$Z142:$AB142) -> #DIV/0! | AD3: ='OECD TTL - 2018'!X9 -> 177.3 | AE3: ='OECD TTL - 2018'!Y9 -> 643.1 | AF3: ='OECD TTL - 2018'!Z9 -> 45 | AG3: ='OECD TTL - 2018'!AA9 -> 1104.2 | AH3: ='OECD TTL - 2018'!AB9 -> 11.6 | AI3: ='OECD TTL - 2018'!AC9 -> 0.9 | AJ3: ='OECD TTL - 2018'!AD9 -> 0.9 | AK3: ='OECD TTL - 2018'!AE9 -> 12.9 | ... AR3: ='OECD TTL - 2018'!AL9 -> 0
A4: coal mining 05 | B4: coal mining 05 | C4: ='OECD TTL - 2018'!C$10*'SIOM from DLIM'!B143/SUM('SIOM from DLIM'!B$143:B$144) -> 18.87218 | D4: ='OECD TTL - 2018'!$D$10*'SIOM from DLIM'!C143/SUM('SIOM from DLIM'!$C$143:$D$144) -> 0 | E4: ='OECD TTL - 2018'!$D$10*'SIOM from DLIM'!D143/SUM('SIOM from DLIM'!$C$143:$D$144) -> 110.86035 | F4: ='OECD TTL - 2018'!E$10*'SIOM from DLIM'!D143/SUM('SIOM from DLIM'!D$143:D$144) -> 7.1109162 | G4: ='OECD TTL - 2018'!F$10*'SIOM from DLIM'!E143/SUM('SIOM from DLIM'!E$143:E$144) -> 89.603048 | H4: ='OECD TTL - 2018'!G$10*'SIOM from DLIM'!F143/SUM('SIOM from DLIM'!F$143:F$144) -> 41.694548 | I4: ='OECD TTL - 2018'!H$10*'SIOM from DLIM'!G143/SUM('SIOM from DLIM'!G$143:G$144) -> 3.1029939 | J4: ='OECD TTL - 2018'!I$10*'SIOM from DLIM'!H143/SUM('SIOM from DLIM'!H$143:H$144) -> #DIV/0! | K4: ='OECD TTL - 2018'!J$10*'SIOM from DLIM'!I143/SUM('SIOM from DLIM'!I$143:I$144) -> 14.174181 | L4: ='OECD TTL - 2018'!K$10*'SIOM from DLIM'!J143/SUM('SIOM from DLIM'!J$143:J$144) -> #DIV/0! | M4: ='OECD TTL - 2018'!$L$10*'SIOM from DLIM'!L143/SUM('SIOM from DLIM'!$L$143:$M$144) -> #DIV/0! | N4: ='OECD TTL - 2018'!$L$10*'SIOM from DLIM'!M143/SUM('SIOM from DLIM'!$L$143:$M$144) -> #DIV/0! | O4: ='OECD TTL - 2018'!M$10*'SIOM from DLIM'!L143/SUM('SIOM from DLIM'!L$143:L$144) -> #DIV/0! | P4: ='OECD TTL - 2018'!$N$10*'SIOM from DLIM'!O143/SUM('SIOM from DLIM'!$O$143:$P$144) -> #DIV/0! | Q4: ='OECD TTL - 2018'!$N$10*'SIOM from DLIM'!P143/SUM('SIOM from DLIM'!$O$143:$P$144) -> #DIV/0! | R4: ='OECD TTL - 2018'!$O$10*'SIOM from DLIM'!Q143/SUM('SIOM from DLIM'!$Q$143:$R$144) -> 0 | S4: ='OECD TTL - 2018'!$O$10*'SIOM from DLIM'!R143/SUM('SIOM from DLIM'!$Q$143:$R$144) -> 153.97614 | T4: ='OECD TTL - 2018'!P$10*'SIOM from DLIM'!O143/SUM('SIOM from DLIM'!O$143:O$144) -> #DIV/0! | U4: ='OECD TTL - 2018'!Q$10*'SIOM from DLIM'!P143/SUM('SIOM from DLIM'!P$143:P$144) -> #DIV/0! | V4: ='OECD TTL - 2018'!R$10*'SIOM from DLIM'!Q143/SUM('SIOM from DLIM'!Q$143:Q$144) -> #DIV/0! | W4: ='OECD TTL - 2018'!S$10*'SIOM from DLIM'!R143/SUM('SIOM from DLIM'!R$143:R$144) -> 5.1260655 | X4: ='OECD TTL - 2018'!T$10*'SIOM from DLIM'!S143/SUM('SIOM from DLIM'!S$143:S$144) -> #DIV/0! | Y4: ='OECD TTL - 2018'!U$10*'SIOM from DLIM'!T143/SUM('SIOM from DLIM'!T$143:T$144) -> 1.9043123 | Z4: ='OECD TTL - 2018'!V$10*'SIOM from DLIM'!U143/SUM('SIOM from DLIM'!U$143:U$144) -> #DIV/0! | AA4: ='OECD TTL - 2018'!$W$10*'SIOM from DLIM'!Z143/SUM('SIOM from DLIM'!$Z$143:$AB$144) -> 627.03844 | AB4: ='OECD TTL - 2018'!$W$10*'SIOM from DLIM'!AA143/SUM('SIOM from DLIM'!$Z$143:$AB$144) -> 2.892671 | AC4: ='OECD TTL - 2018'!$W$10*'SIOM from DLIM'!AB143/SUM('SIOM from DLIM'!$Z$143:$AB$144) -> 0.048379579 | AD4: ='OECD TTL - 2018'!X$10*'SIOM from DLIM'!W143/SUM('SIOM from DLIM'!W$143:W$144) -> #DIV/0! | AE4: ='OECD TTL - 2018'!Y$10*'SIOM from DLIM'!X143/SUM('SIOM from DLIM'!X$143:X$144) -> #DIV/0! | AF4: ='OECD TTL - 2018'!Z$10*'SIOM from DLIM'!Y143/SUM('SIOM from DLIM'!Y$143:Y$144) -> 104.04857 | AG4: ='OECD TTL - 2018'!AA$10*'SIOM from DLIM'!Z143/SUM('SIOM from DLIM'!Z$143:Z$144) -> 22.69492 | AH4: ='OECD TTL - 2018'!AB$10*'SIOM from DLIM'!AA143/SUM('SIOM from DLIM'!AA$143:AA$144) -> 1.4379614 | AI4: ='OECD TTL - 2018'!AC$10*'SIOM from DLIM'!AB143/SUM('SIOM from DLIM'!AB$143:AB$144) -> 2.1807912 | AJ4: ='OECD TTL - 2018'!AD$10*'SIOM from DLIM'!AC143/SUM('SIOM from DLIM'!AC$143:AC$144) -> 0.11683306 | AK4: ='OECD TTL - 2018'!AE$10*'SIOM from DLIM'!AD143/SUM('SIOM from DLIM'!AD$143:AD$144) -> 6.1450101 | ... AR4: ='OECD TTL - 2018'!AL$10*'SIOM from DLIM'!AK143/SUM('SIOM from DLIM'!AK$143:AK$144) -> #DIV/0!
A5: oil and gas extraction 06 | B5: oil and gas extraction 06 | C5: ='OECD TTL - 2018'!C$10*'SIOM from DLIM'!B144/SUM('SIOM from DLIM'!B$143:B$144) -> 29.42782 | D5: ='OECD TTL - 2018'!$D$10*'SIOM from DLIM'!C144/SUM('SIOM from DLIM'!$C$143:$D$144) -> 0 | E5: ='OECD TTL - 2018'!$D$10*'SIOM from DLIM'!D144/SUM('SIOM from DLIM'!$C$143:$D$144) -> 174.43965 | F5: ='OECD TTL - 2018'!E$10*'SIOM from DLIM'!D144/SUM('SIOM from DLIM'!D$143:D$144) -> 11.189084 | G5: ='OECD TTL - 2018'!F$10*'SIOM from DLIM'!E144/SUM('SIOM from DLIM'!E$143:E$144) -> 132.89695 | H5: ='OECD TTL - 2018'!G$10*'SIOM from DLIM'!F144/SUM('SIOM from DLIM'!F$143:F$144) -> 61.105452 | I5: ='OECD TTL - 2018'!H$10*'SIOM from DLIM'!G144/SUM('SIOM from DLIM'!G$143:G$144) -> 5.0970061 | J5: ='OECD TTL - 2018'!I$10*'SIOM from DLIM'!H144/SUM('SIOM from DLIM'!H$143:H$144) -> #DIV/0! | K5: ='OECD TTL - 2018'!J$10*'SIOM from DLIM'!I144/SUM('SIOM from DLIM'!I$143:I$144) -> 22.325819 | L5: ='OECD TTL - 2018'!K$10*'SIOM from DLIM'!J144/SUM('SIOM from DLIM'!J$143:J$144) -> #DIV/0! | M5: ='OECD TTL - 2018'!$L$10*'SIOM from DLIM'!L144/SUM('SIOM from DLIM'!$L$143:$M$144) -> #DIV/0! | N5: ='OECD TTL - 2018'!$L$10*'SIOM from DLIM'!M144/SUM('SIOM from DLIM'!$L$143:$M$144) -> #DIV/0! | O5: ='OECD TTL - 2018'!M$10*'SIOM from DLIM'!L144/SUM('SIOM from DLIM'!L$143:L$144) -> #DIV/0! | P5: ='OECD TTL - 2018'!$N$10*'SIOM from DLIM'!O144/SUM('SIOM from DLIM'!$O$143:$P$144) -> #DIV/0! | Q5: ='OECD TTL - 2018'!$N$10*'SIOM from DLIM'!P144/SUM('SIOM from DLIM'!$O$143:$P$144) -> #DIV/0! | R5: ='OECD TTL - 2018'!$O$10*'SIOM from DLIM'!Q144/SUM('SIOM from DLIM'!$Q$143:$R$144) -> 0 | S5: ='OECD TTL - 2018'!$O$10*'SIOM from DLIM'!R144/SUM('SIOM from DLIM'!$Q$143:$R$144) -> 242.52386 | T5: ='OECD TTL - 2018'!P$10*'SIOM from DLIM'!O144/SUM('SIOM from DLIM'!O$143:O$144) -> #DIV/0! | U5: ='OECD TTL - 2018'!Q$10*'SIOM from DLIM'!P144/SUM('SIOM from DLIM'!P$143:P$144) -> #DIV/0! | V5: ='OECD TTL - 2018'!R$10*'SIOM from DLIM'!Q144/SUM('SIOM from DLIM'!Q$143:Q$144) -> #DIV/0! | W5: ='OECD TTL - 2018'!S$10*'SIOM from DLIM'!R144/SUM('SIOM from DLIM'!R$143:R$144) -> 8.0739345 | X5: ='OECD TTL - 2018'!T$10*'SIOM from DLIM'!S144/SUM('SIOM from DLIM'!S$143:S$144) -> #DIV/0! | Y5: ='OECD TTL - 2018'!U$10*'SIOM from DLIM'!T144/SUM('SIOM from DLIM'!T$143:T$144) -> 2.9956877 | Z5: ='OECD TTL - 2018'!V$10*'SIOM from DLIM'!U144/SUM('SIOM from DLIM'!U$143:U$144) -> #DIV/0! | AA5: ='OECD TTL - 2018'!$W$10*'SIOM from DLIM'!Z144/SUM('SIOM from DLIM'!$Z$143:$AB$144) -> 986.49646 | AB5: ='OECD TTL - 2018'!$W$10*'SIOM from DLIM'!AA144/SUM('SIOM from DLIM'!$Z$143:$AB$144) -> 4.5504234 | AC5: ='OECD TTL - 2018'!$W$10*'SIOM from DLIM'!AB144/SUM('SIOM from DLIM'!$Z$143:$AB$144) -> 0.073634706 | AD5: ='OECD TTL - 2018'!X$10*'SIOM from DLIM'!W144/SUM('SIOM from DLIM'!W$143:W$144) -> #DIV/0! | AE5: ='OECD TTL - 2018'!Y$10*'SIOM from DLIM'!X144/SUM('SIOM from DLIM'!X$143:X$144) -> #DIV/0! | AF5: ='OECD TTL - 2018'!Z$10*'SIOM from DLIM'!Y144/SUM('SIOM from DLIM'!Y$143:Y$144) -> 163.75143 | AG5: ='OECD TTL - 2018'!AA$10*'SIOM from DLIM'!Z144/SUM('SIOM from DLIM'!Z$143:Z$144) -> 35.70508 | AH5: ='OECD TTL - 2018'!AB$10*'SIOM from DLIM'!AA144/SUM('SIOM from DLIM'!AA$143:AA$144) -> 2.2620386 | AI5: ='OECD TTL - 2018'!AC$10*'SIOM from DLIM'!AB144/SUM('SIOM from DLIM'!AB$143:AB$144) -> 3.3192088 | AJ5: ='OECD TTL - 2018'!AD$10*'SIOM from DLIM'!AC144/SUM('SIOM from DLIM'!AC$143:AC$144) -> 0.18316694 | AK5: ='OECD TTL - 2018'!AE$10*'SIOM from DLIM'!AD144/SUM('SIOM from DLIM'!AD$143:AD$144) -> 9.2549899 | ... AR5: ='OECD TTL - 2018'!AL$10*'SIOM from DLIM'!AK144/SUM('SIOM from DLIM'!AK$143:AK$144) -> #DIV/0!
A6: D07T08: Mining and quarrying of non-energy producing products | B6: other mining and quarrying 07T08 | C6: ='OECD TTL - 2018'!C11 -> 56.1 | D6: ='OECD TTL - 2018'!$D11*'SIOM from DLIM'!C145/SUM('SIOM from DLIM'!$C145:$D145) -> 19.8 | E6: ='OECD TTL - 2018'!$D11*'SIOM from DLIM'!D145/SUM('SIOM from DLIM'!$C145:$D145) -> 0 | F6: ='OECD TTL - 2018'!E11 -> 613.3 | G6: ='OECD TTL - 2018'!F11 -> 59.5 | H6: ='OECD TTL - 2018'!G11 -> 40.7 | I6: ='OECD TTL - 2018'!H11 -> 6.9 | J6: ='OECD TTL - 2018'!I11 -> 2.6 | K6: ='OECD TTL - 2018'!J11 -> 46.4 | L6: ='OECD TTL - 2018'!K11 -> 970.2 | M6: ='OECD TTL - 2018'!$L11*'SIOM from DLIM'!L145/SUM('SIOM from DLIM'!$L145:$M145) -> 655.99294 | N6: ='OECD TTL - 2018'!$L11*'SIOM from DLIM'!M145/SUM('SIOM from DLIM'!$L145:$M145) -> 110.30706 | O6: ='OECD TTL - 2018'!M11 -> 13.4 | P6: ='OECD TTL - 2018'!$N11*'SIOM from DLIM'!O145/SUM('SIOM from DLIM'!$O145:$P145) -> 1143.8738 | Q6: ='OECD TTL - 2018'!$N11*'SIOM from DLIM'!P145/SUM('SIOM from DLIM'!$O145:$P145) -> 561.02624 | R6: ='OECD TTL - 2018'!$O11*'SIOM from DLIM'!Q145/SUM('SIOM from DLIM'!$Q145:$R145) -> 6761.2 | S6: ='OECD TTL - 2018'!$O11*'SIOM from DLIM'!R145/SUM('SIOM from DLIM'!$Q145:$R145) -> 0 | T6: ='OECD TTL - 2018'!P11 -> 235.1 | U6: ='OECD TTL - 2018'!Q11 -> 38.7 | V6: ='OECD TTL - 2018'!R11 -> 64 | W6: ='OECD TTL - 2018'!S11 -> 45.8 | X6: ='OECD TTL - 2018'!T11 -> 55.1 | Y6: ='OECD TTL - 2018'!U11 -> 3.4 | Z6: ='OECD TTL - 2018'!V11 -> 145.9 | AA6: ='OECD TTL - 2018'!$W11*'SIOM from DLIM'!Z145/SUM('SIOM from DLIM'!$Z145:$AB145) -> #DIV/0! | AB6: ='OECD TTL - 2018'!$W11*'SIOM from DLIM'!AA145/SUM('SIOM from DLIM'!$Z145:$AB145) -> #DIV/0! | AC6: ='OECD TTL - 2018'!$W11*'SIOM from DLIM'!AB145/SUM('SIOM from DLIM'!$Z145:$AB145) -> #DIV/0! | AD6: ='OECD TTL - 2018'!X11 -> 1805.4 | AE6: ='OECD TTL - 2018'!Y11 -> 47.5 | AF6: ='OECD TTL - 2018'!Z11 -> 62.5 | AG6: ='OECD TTL - 2018'!AA11 -> 4.6 | AH6: ='OECD TTL - 2018'!AB11 -> 0.5 | AI6: ='OECD TTL - 2018'!AC11 -> 0.5 | AJ6: ='OECD TTL - 2018'!AD11 -> 0.1 | AK6: ='OECD TTL - 2018'!AE11 -> 3 | ... AR6: ='OECD TTL - 2018'!AL11 -> 0
A7: D09: Mining support service activities | C7: ='OECD TTL - 2018'!C12 -> 665.7 | D7: ='OECD TTL - 2018'!$D12*'SIOM from DLIM'!C146/SUM('SIOM from DLIM'!$C146:$D146) -> 0 | E7: ='OECD TTL - 2018'!$D12*'SIOM from DLIM'!D146/SUM('SIOM from DLIM'!$C146:$D146) -> 3004.1 | F7: ='OECD TTL - 2018'!E12 -> 870.4 | G7: ='OECD TTL - 2018'!F12 -> 2312.7 | H7: ='OECD TTL - 2018'!G12 -> 171.5 | I7: ='OECD TTL - 2018'!H12 -> 0.4 | J7: ='OECD TTL - 2018'!I12 -> 7.1 | K7: ='OECD TTL - 2018'!J12 -> 55.1 | L7: ='OECD TTL - 2018'!K12 -> 162.9 | M7: ='OECD TTL - 2018'!$L12*'SIOM from DLIM'!L146/SUM('SIOM from DLIM'!$L146:$M146) -> #DIV/0! | N7: ='OECD TTL - 2018'!$L12*'SIOM from DLIM'!M146/SUM('SIOM from DLIM'!$L146:$M146) -> #DIV/0! | O7: ='OECD TTL - 2018'!M12 -> 74.2 | P7: ='OECD TTL - 2018'!$N12*'SIOM from DLIM'!O146/SUM('SIOM from DLIM'!$O146:$P146) -> #DIV/0! | Q7: ='OECD TTL - 2018'!$N12*'SIOM from DLIM'!P146/SUM('SIOM from DLIM'!$O146:$P146) -> #DIV/0! | R7: ='OECD TTL - 2018'!$O12*'SIOM from DLIM'!Q146/SUM('SIOM from DLIM'!$Q146:$R146) -> 0 | S7: ='OECD TTL - 2018'!$O12*'SIOM from DLIM'!R146/SUM('SIOM from DLIM'!$Q146:$R146) -> 26.3 | T7: ='OECD TTL - 2018'!P12 -> 3.9 | U7: ='OECD TTL - 2018'!Q12 -> 1.1 | V7: ='OECD TTL - 2018'!R12 -> 0.6 | W7: ='OECD TTL - 2018'!S12 -> 37.9 | X7: ='OECD TTL - 2018'!T12 -> 7.6 | Y7: ='OECD TTL - 2018'!U12 -> 1 | Z7: ='OECD TTL - 2018'!V12 -> 34 | AA7: ='OECD TTL - 2018'!$W12*'SIOM from DLIM'!Z146/SUM('SIOM from DLIM'!$Z146:$AB146) -> 399.82708 | AB7: ='OECD TTL - 2018'!$W12*'SIOM from DLIM'!AA146/SUM('SIOM from DLIM'!$Z146:$AB146) -> 1.842595 | AC7: ='OECD TTL - 2018'!$W12*'SIOM from DLIM'!AB146/SUM('SIOM from DLIM'!$Z146:$AB146) -> 0.030320835 | AD7: ='OECD TTL - 2018'!X12 -> 1271 | AE7: ='OECD TTL - 2018'!Y12 -> 8.8 | AF7: ='OECD TTL - 2018'!Z12 -> 54.6 | AG7: ='OECD TTL - 2018'!AA12 -> 1.9 | AH7: ='OECD TTL - 2018'!AB12 -> 0.4 | AI7: ='OECD TTL - 2018'!AC12 -> 0.7 | AJ7: ='OECD TTL - 2018'!AD12 -> 0.1 | AK7: ='OECD TTL - 2018'!AE12 -> 5.3 | ... AR7: ='OECD TTL - 2018'!AL12 -> 0
A8: D10T12: Food products, beverages and tobacco | B8: food beverage and tobacco 10T12 | C8: ='OECD TTL - 2018'!C13 -> 3366 | D8: ='OECD TTL - 2018'!$D13*'SIOM from DLIM'!C147/SUM('SIOM from DLIM'!$C147:$D147) -> 6.6 | E8: ='OECD TTL - 2018'!$D13*'SIOM from DLIM'!D147/SUM('SIOM from DLIM'!$C147:$D147) -> 0 | F8: ='OECD TTL - 2018'!E13 -> 12.3 | G8: ='OECD TTL - 2018'!F13 -> 7.3 | H8: ='OECD TTL - 2018'!G13 -> 14358.9 | I8: ='OECD TTL - 2018'!H13 -> 395.2 | J8: ='OECD TTL - 2018'!I13 -> 12.6 | K8: ='OECD TTL - 2018'!J13 -> 106.7 | L8: ='OECD TTL - 2018'!K13 -> 105.9 | M8: ='OECD TTL - 2018'!$L13*'SIOM from DLIM'!L147/SUM('SIOM from DLIM'!$L147:$M147) -> 956.07173 | N8: ='OECD TTL - 2018'!$L13*'SIOM from DLIM'!M147/SUM('SIOM from DLIM'!$L147:$M147) -> 161.32827 | O8: ='OECD TTL - 2018'!M13 -> 103.5 | P8: ='OECD TTL - 2018'!$N13*'SIOM from DLIM'!O147/SUM('SIOM from DLIM'!$O147:$P147) -> 33.895491 | Q8: ='OECD TTL - 2018'!$N13*'SIOM from DLIM'!P147/SUM('SIOM from DLIM'!$O147:$P147) -> 16.604509 | R8: ='OECD TTL - 2018'!$O13*'SIOM from DLIM'!Q147/SUM('SIOM from DLIM'!$Q147:$R147) -> 48.5 | S8: ='OECD TTL - 2018'!$O13*'SIOM from DLIM'!R147/SUM('SIOM from DLIM'!$Q147:$R147) -> 0 | T8: ='OECD TTL - 2018'!P13 -> 32.8 | U8: ='OECD TTL - 2018'!Q13 -> 72.8 | V8: ='OECD TTL - 2018'!R13 -> 34.3 | W8: ='OECD TTL - 2018'!S13 -> 26.2 | X8: ='OECD TTL - 2018'!T13 -> 168.3 | Y8: ='OECD TTL - 2018'!U13 -> 15.6 | Z8: ='OECD TTL - 2018'!V13 -> 60.8 | AA8: ='OECD TTL - 2018'!$W13*'SIOM from DLIM'!Z147/SUM('SIOM from DLIM'!$Z147:$AB147) -> #DIV/0! | AB8: ='OECD TTL - 2018'!$W13*'SIOM from DLIM'!AA147/SUM('SIOM from DLIM'!$Z147:$AB147) -> #DIV/0! | AC8: ='OECD TTL - 2018'!$W13*'SIOM from DLIM'!AB147/SUM('SIOM from DLIM'!$Z147:$AB147) -> #DIV/0! | AD8: ='OECD TTL - 2018'!X13 -> 177.2 | AE8: ='OECD TTL - 2018'!Y13 -> 747.3 | AF8: ='OECD TTL - 2018'!Z13 -> 106.7 | AG8: ='OECD TTL - 2018'!AA13 -> 3483.3 | AH8: ='OECD TTL - 2018'!AB13 -> 25.6 | AI8: ='OECD TTL - 2018'!AC13 -> 9.9 | AJ8: ='OECD TTL - 2018'!AD13 -> 2.9 | AK8: ='OECD TTL - 2018'!AE13 -> 41.8 | ... AR8: ='OECD TTL - 2018'!AL13 -> 0
A9: D13T15: Textiles, wearing apparel, leather and related products | B9: textiles apparel and leather 13T15 | C9: ='OECD TTL - 2018'!C14 -> 99.8 | D9: ='OECD TTL - 2018'!$D14*'SIOM from DLIM'!C148/SUM('SIOM from DLIM'!$C148:$D148) -> 0 | E9: ='OECD TTL - 2018'!$D14*'SIOM from DLIM'!D148/SUM('SIOM from DLIM'!$C148:$D148) -> 19 | F9: ='OECD TTL - 2018'!E14 -> 29.3 | G9: ='OECD TTL - 2018'!F14 -> 23.5 | H9: ='OECD TTL - 2018'!G14 -> 121.2 | I9: ='OECD TTL - 2018'!H14 -> 5021 | J9: ='OECD TTL - 2018'!I14 -> 20.4 | K9: ='OECD TTL - 2018'!J14 -> 131.4 | L9: ='OECD TTL - 2018'!K14 -> 35.7 | M9: ='OECD TTL - 2018'!$L14*'SIOM from DLIM'!L148/SUM('SIOM from DLIM'!$L148:$M148) -> #DIV/0! | N9: ='OECD TTL - 2018'!$L14*'SIOM from DLIM'!M148/SUM('SIOM from DLIM'!$L148:$M148) -> #DIV/0! | O9: ='OECD TTL - 2018'!M14 -> 246.3 | P9: ='OECD TTL - 2018'!$N14*'SIOM from DLIM'!O148/SUM('SIOM from DLIM'!$O148:$P148) -> #DIV/0! | Q9: ='OECD TTL - 2018'!$N14*'SIOM from DLIM'!P148/SUM('SIOM from DLIM'!$O148:$P148) -> #DIV/0! | R9: ='OECD TTL - 2018'!$O14*'SIOM from DLIM'!Q148/SUM('SIOM from DLIM'!$Q148:$R148) -> 0 | S9: ='OECD TTL - 2018'!$O14*'SIOM from DLIM'!R148/SUM('SIOM from DLIM'!$Q148:$R148) -> 20.2 | T9: ='OECD TTL - 2018'!P14 -> 53.5 | U9: ='OECD TTL - 2018'!Q14 -> 126.2 | V9: ='OECD TTL - 2018'!R14 -> 52.9 | W9: ='OECD TTL - 2018'!S14 -> 45.1 | X9: ='OECD TTL - 2018'!T14 -> 1292.1 | Y9: ='OECD TTL - 2018'!U14 -> 51.2 | Z9: ='OECD TTL - 2018'!V14 -> 815 | AA9: ='OECD TTL - 2018'!$W14*'SIOM from DLIM'!Z148/SUM('SIOM from DLIM'!$Z148:$AB148) -> 40.708963 | AB9: ='OECD TTL - 2018'!$W14*'SIOM from DLIM'!AA148/SUM('SIOM from DLIM'!$Z148:$AB148) -> 0.18787744 | AC9: ='OECD TTL - 2018'!$W14*'SIOM from DLIM'!AB148/SUM('SIOM from DLIM'!$Z148:$AB148) -> 0.0031599365 | AD9: ='OECD TTL - 2018'!X14 -> 284.4 | AE9: ='OECD TTL - 2018'!Y14 -> 512.8 | AF9: ='OECD TTL - 2018'!Z14 -> 200.4 | AG9: ='OECD TTL - 2018'!AA14 -> 217.5 | AH9: ='OECD TTL - 2018'!AB14 -> 67.6 | AI9: ='OECD TTL - 2018'!AC14 -> 12.1 | AJ9: ='OECD TTL - 2018'!AD14 -> 3 | AK9: ='OECD TTL - 2018'!AE14 -> 124.3 | ... AR9: ='OECD TTL - 2018'!AL14 -> 0
A10: D16: Wood and products of wood and cork | B10: wood products 16 | C10: ='OECD TTL - 2018'!C15 -> 39.9 | D10: ='OECD TTL - 2018'!$D15*'SIOM from DLIM'!C149/SUM('SIOM from DLIM'!$C149:$D149) -> 12.1 | E10: ='OECD TTL - 2018'!$D15*'SIOM from DLIM'!D149/SUM('SIOM from DLIM'!$C149:$D149) -> 0 | F10: ='OECD TTL - 2018'!E15 -> 30 | G10: ='OECD TTL - 2018'!F15 -> 8.6 | H10: ='OECD TTL - 2018'!G15 -> 65.2 | I10: ='OECD TTL - 2018'!H15 -> 20 | J10: ='OECD TTL - 2018'!I15 -> 586.7 | K10: ='OECD TTL - 2018'!J15 -> 124.3 | L10: ='OECD TTL - 2018'!K15 -> 15 | M10: ='OECD TTL - 2018'!$L15*'SIOM from DLIM'!L149/SUM('SIOM from DLIM'!$L149:$M149) -> 54.089709 | N10: ='OECD TTL - 2018'!$L15*'SIOM from DLIM'!M149/SUM('SIOM from DLIM'!$L149:$M149) -> 9.1102912 | O10: ='OECD TTL - 2018'!M15 -> 32 | P10: ='OECD TTL - 2018'!$N15*'SIOM from DLIM'!O149/SUM('SIOM from DLIM'!$O149:$P149) -> 44.385279 | Q10: ='OECD TTL - 2018'!$N15*'SIOM from DLIM'!P149/SUM('SIOM from DLIM'!$O149:$P149) -> 21.714721 | R10: ='OECD TTL - 2018'!$O15*'SIOM from DLIM'!Q149/SUM('SIOM from DLIM'!$Q149:$R149) -> 9.9 | S10: ='OECD TTL - 2018'!$O15*'SIOM from DLIM'!R149/SUM('SIOM from DLIM'!$Q149:$R149) -> 0 | T10: ='OECD TTL - 2018'!P15 -> 60 | U10: ='OECD TTL - 2018'!Q15 -> 55.9 | V10: ='OECD TTL - 2018'!R15 -> 29.4 | W10: ='OECD TTL - 2018'!S15 -> 31.2 | X10: ='OECD TTL - 2018'!T15 -> 320.5 | Y10: ='OECD TTL - 2018'!U15 -> 15 | Z10: ='OECD TTL - 2018'!V15 -> 1225 | AA10: ='OECD TTL - 2018'!$W15*'SIOM from DLIM'!Z149/SUM('SIOM from DLIM'!$Z149:$AB149) -> #DIV/0! | AB10: ='OECD TTL - 2018'!$W15*'SIOM from DLIM'!AA149/SUM('SIOM from DLIM'!$Z149:$AB149) -> #DIV/0! | AC10: ='OECD TTL - 2018'!$W15*'SIOM from DLIM'!AB149/SUM('SIOM from DLIM'!$Z149:$AB149) -> #DIV/0! | AD10: ='OECD TTL - 2018'!X15 -> 1711.9 | AE10: ='OECD TTL - 2018'!Y15 -> 107.4 | AF10: ='OECD TTL - 2018'!Z15 -> 50.5 | AG10: ='OECD TTL - 2018'!AA15 -> 25.2 | AH10: ='OECD TTL - 2018'!AB15 -> 16.5 | AI10: ='OECD TTL - 2018'!AC15 -> 3.8 | AJ10: ='OECD TTL - 2018'!AD15 -> 1.3 | AK10: ='OECD TTL - 2018'!AE15 -> 9.9 | ... AR10: ='OECD TTL - 2018'!AL15 -> 0
A11: D17T18: Paper products and printing | B11: pulp paper and printing 17T18 | C11: ='OECD TTL - 2018'!C16 -> 95.1 | D11: ='OECD TTL - 2018'!$D16*'SIOM from DLIM'!C150/SUM('SIOM from DLIM'!$C150:$D150) -> 0 | E11: ='OECD TTL - 2018'!$D16*'SIOM from DLIM'!D150/SUM('SIOM from DLIM'!$C150:$D150) -> 12.6 | F11: ='OECD TTL - 2018'!E16 -> 39.6 | G11: ='OECD TTL - 2018'!F16 -> 11.6 | H11: ='OECD TTL - 2018'!G16 -> 1611 | I11: ='OECD TTL - 2018'!H16 -> 372.5 | J11: ='OECD TTL - 2018'!I16 -> 61.1 | K11: ='OECD TTL - 2018'!J16 -> 4351.7 | L11: ='OECD TTL - 2018'!K16 -> 77.8 | M11: ='OECD TTL - 2018'!$L16*'SIOM from DLIM'!L150/SUM('SIOM from DLIM'!$L150:$M150) -> #DIV/0! | N11: ='OECD TTL - 2018'!$L16*'SIOM from DLIM'!M150/SUM('SIOM from DLIM'!$L150:$M150) -> #DIV/0! | O11: ='OECD TTL - 2018'!M16 -> 237.2 | P11: ='OECD TTL - 2018'!$N16*'SIOM from DLIM'!O150/SUM('SIOM from DLIM'!$O150:$P150) -> #DIV/0! | Q11: ='OECD TTL - 2018'!$N16*'SIOM from DLIM'!P150/SUM('SIOM from DLIM'!$O150:$P150) -> #DIV/0! | R11: ='OECD TTL - 2018'!$O16*'SIOM from DLIM'!Q150/SUM('SIOM from DLIM'!$Q150:$R150) -> 0 | S11: ='OECD TTL - 2018'!$O16*'SIOM from DLIM'!R150/SUM('SIOM from DLIM'!$Q150:$R150) -> 62.6 | T11: ='OECD TTL - 2018'!P16 -> 120.9 | U11: ='OECD TTL - 2018'!Q16 -> 367.2 | V11: ='OECD TTL - 2018'!R16 -> 155 | W11: ='OECD TTL - 2018'!S16 -> 112.1 | X11: ='OECD TTL - 2018'!T16 -> 726.8 | Y11: ='OECD TTL - 2018'!U16 -> 46 | Z11: ='OECD TTL - 2018'!V16 -> 356.7 | AA11: ='OECD TTL - 2018'!$W16*'SIOM from DLIM'!Z150/SUM('SIOM from DLIM'!$Z150:$AB150) -> 75.147765 | AB11: ='OECD TTL - 2018'!$W16*'SIOM from DLIM'!AA150/SUM('SIOM from DLIM'!$Z150:$AB150) -> 0.34651323 | AC11: ='OECD TTL - 2018'!$W16*'SIOM from DLIM'!AB150/SUM('SIOM from DLIM'!$Z150:$AB150) -> 0.0057220359 | AD11: ='OECD TTL - 2018'!X16 -> 271.7 | AE11: ='OECD TTL - 2018'!Y16 -> 1072 | AF11: ='OECD TTL - 2018'!Z16 -> 323.6 | AG11: ='OECD TTL - 2018'!AA16 -> 280.5 | AH11: ='OECD TTL - 2018'!AB16 -> 466.3 | AI11: ='OECD TTL - 2018'!AC16 -> 102 | AJ11: ='OECD TTL - 2018'!AD16 -> 37 | AK11: ='OECD TTL - 2018'!AE16 -> 798.1 | ... AR11: ='OECD TTL - 2018'!AL16 -> 0
A12: D19: Coke and refined petroleum products | B12: refined petroleum and coke 19 | C12: ='OECD TTL - 2018'!C17 -> 1384.2 | D12: ='OECD TTL - 2018'!$D17*'SIOM from DLIM'!C151/SUM('SIOM from DLIM'!$C151:$D151) -> 308.8 | E12: ='OECD TTL - 2018'!$D17*'SIOM from DLIM'!D151/SUM('SIOM from DLIM'!$C151:$D151) -> 0 | F12: ='OECD TTL - 2018'!E17 -> 659.8 | G12: ='OECD TTL - 2018'!F17 -> 340.1 | H12: ='OECD TTL - 2018'!G17 -> 777.3 | I12: ='OECD TTL - 2018'!H17 -> 152.9 | J12: ='OECD TTL - 2018'!I17 -> 62.7 | K12: ='OECD TTL - 2018'!J17 -> 195.6 | L12: ='OECD TTL - 2018'!K17 -> 5785.3 | M12: ='OECD TTL - 2018'!$L17*'SIOM from DLIM'!L151/SUM('SIOM from DLIM'!$L151:$M151) -> 2346.4373 | N12: ='OECD TTL - 2018'!$L17*'SIOM from DLIM'!M151/SUM('SIOM from DLIM'!$L151:$M151) -> 396.36273 | O12: ='OECD TTL - 2018'!M17 -> 202.3 | P12: ='OECD TTL - 2018'!$N17*'SIOM from DLIM'!O151/SUM('SIOM from DLIM'!$O151:$P151) -> 527.01833 | Q12: ='OECD TTL - 2018'!$N17*'SIOM from DLIM'!P151/SUM('SIOM from DLIM'!$O151:$P151) -> 258.38167 | R12: ='OECD TTL - 2018'!$O17*'SIOM from DLIM'!Q151/SUM('SIOM from DLIM'!$Q151:$R151) -> 1021.3 | S12: ='OECD TTL - 2018'!$O17*'SIOM from DLIM'!R151/SUM('SIOM from DLIM'!$Q151:$R151) -> 0 | T12: ='OECD TTL - 2018'!P17 -> 220.1 | U12: ='OECD TTL - 2018'!Q17 -> 258.1 | V12: ='OECD TTL - 2018'!R17 -> 172.3 | W12: ='OECD TTL - 2018'!S17 -> 155.7 | X12: ='OECD TTL - 2018'!T17 -> 750 | Y12: ='OECD TTL - 2018'!U17 -> 163.1 | Z12: ='OECD TTL - 2018'!V17 -> 272.2 | AA12: ='OECD TTL - 2018'!$W17*'SIOM from DLIM'!Z151/SUM('SIOM from DLIM'!$Z151:$AB151) -> #DIV/0! | AB12: ='OECD TTL - 2018'!$W17*'SIOM from DLIM'!AA151/SUM('SIOM from DLIM'!$Z151:$AB151) -> #DIV/0! | AC12: ='OECD TTL - 2018'!$W17*'SIOM from DLIM'!AB151/SUM('SIOM from DLIM'!$Z151:$AB151) -> #DIV/0! | AD12: ='OECD TTL - 2018'!X17 -> 2124.1 | AE12: ='OECD TTL - 2018'!Y17 -> 1619 | AF12: ='OECD TTL - 2018'!Z17 -> 15421.1 | AG12: ='OECD TTL - 2018'!AA17 -> 277.8 | AH12: ='OECD TTL - 2018'!AB17 -> 81.9 | AI12: ='OECD TTL - 2018'!AC17 -> 109.4 | AJ12: ='OECD TTL - 2018'!AD17 -> 24.5 | AK12: ='OECD TTL - 2018'!AE17 -> 579 | ... AR12: ='OECD TTL - 2018'!AL17 -> 0
A13: chemicals 20 | B13: chemicals 20 | C13: ='OECD TTL - 2018'!C$18*'SIOM from DLIM'!B152/SUM('SIOM from DLIM'!B$152:B$153) -> 0 | D13: ='OECD TTL - 2018'!$D$18*'SIOM from DLIM'!C152/SUM('SIOM from DLIM'!$C$152:$D$153) -> 189.61855 | E13: ='OECD TTL - 2018'!$D$18*'SIOM from DLIM'!D152/SUM('SIOM from DLIM'!$C$152:$D$153) -> 0 | F13: ='OECD TTL - 2018'!E$18*'SIOM from DLIM'!D152/SUM('SIOM from DLIM'!D$152:D$153) -> 0 | G13: ='OECD TTL - 2018'!F$18*'SIOM from DLIM'!E152/SUM('SIOM from DLIM'!E$152:E$153) -> 0 | H13: ='OECD TTL - 2018'!G$18*'SIOM from DLIM'!F152/SUM('SIOM from DLIM'!F$152:F$153) -> 0 | I13: ='OECD TTL - 2018'!H$18*'SIOM from DLIM'!G152/SUM('SIOM from DLIM'!G$152:G$153) -> 0 | J13: ='OECD TTL - 2018'!I$18*'SIOM from DLIM'!H152/SUM('SIOM from DLIM'!H$152:H$153) -> 242.6 | K13: ='OECD TTL - 2018'!J$18*'SIOM from DLIM'!I152/SUM('SIOM from DLIM'!I$152:I$153) -> 0 | L13: ='OECD TTL - 2018'!K$18*'SIOM from DLIM'!J152/SUM('SIOM from DLIM'!J$152:J$153) -> 3280.1 | M13: ='OECD TTL - 2018'!$L$18*'SIOM from DLIM'!L152/SUM('SIOM from DLIM'!$L$152:$M$153) -> 15040.151 | N13: ='OECD TTL - 2018'!$L$18*'SIOM from DLIM'!M152/SUM('SIOM from DLIM'!$L$152:$M$153) -> 2540.5492 | O13: ='OECD TTL - 2018'!M$18*'SIOM from DLIM'!L152/SUM('SIOM from DLIM'!L$152:L$153) -> 5481.4 | P13: ='OECD TTL - 2018'!$N$18*'SIOM from DLIM'!O152/SUM('SIOM from DLIM'!$O$152:$P$153) -> 778.62204 | Q13: ='OECD TTL - 2018'!$N$18*'SIOM from DLIM'!P152/SUM('SIOM from DLIM'!$O$152:$P$153) -> 381.67796 | R13: ='OECD TTL - 2018'!$O$18*'SIOM from DLIM'!Q152/SUM('SIOM from DLIM'!$Q$152:$R$153) -> 1334.6207 | S13: ='OECD TTL - 2018'!$O$18*'SIOM from DLIM'!R152/SUM('SIOM from DLIM'!$Q$152:$R$153) -> 0 | T13: ='OECD TTL - 2018'!P$18*'SIOM from DLIM'!O152/SUM('SIOM from DLIM'!O$152:O$153) -> 762.6 | U13: ='OECD TTL - 2018'!Q$18*'SIOM from DLIM'!P152/SUM('SIOM from DLIM'!P$152:P$153) -> 1826 | V13: ='OECD TTL - 2018'!R$18*'SIOM from DLIM'!Q152/SUM('SIOM from DLIM'!Q$152:Q$153) -> 932.7 | W13: ='OECD TTL - 2018'!S$18*'SIOM from DLIM'!R152/SUM('SIOM from DLIM'!R$152:R$153) -> 0 | X13: ='OECD TTL - 2018'!T$18*'SIOM from DLIM'!S152/SUM('SIOM from DLIM'!S$152:S$153) -> 3417.9 | Y13: ='OECD TTL - 2018'!U$18*'SIOM from DLIM'!T152/SUM('SIOM from DLIM'!T$152:T$153) -> 0 | Z13: ='OECD TTL - 2018'!V$18*'SIOM from DLIM'!U152/SUM('SIOM from DLIM'!U$152:U$153) -> 1145.7 | AA13: ='OECD TTL - 2018'!$W$18*'SIOM from DLIM'!Z152/SUM('SIOM from DLIM'!$Z$152:$AB$153) -> 0 | AB13: ='OECD TTL - 2018'!$W$18*'SIOM from DLIM'!AA152/SUM('SIOM from DLIM'!$Z$152:$AB$153) -> 0 | AC13: ='OECD TTL - 2018'!$W$18*'SIOM from DLIM'!AB152/SUM('SIOM from DLIM'!$Z$152:$AB$153) -> 0 | AD13: ='OECD TTL - 2018'!X$18*'SIOM from DLIM'!W152/SUM('SIOM from DLIM'!W$152:W$153) -> 1802.3 | AE13: ='OECD TTL - 2018'!Y$18*'SIOM from DLIM'!X152/SUM('SIOM from DLIM'!X$152:X$153) -> 714.3 | AF13: ='OECD TTL - 2018'!Z$18*'SIOM from DLIM'!Y152/SUM('SIOM from DLIM'!Y$152:Y$153) -> 0 | AG13: ='OECD TTL - 2018'!AA$18*'SIOM from DLIM'!Z152/SUM('SIOM from DLIM'!Z$152:Z$153) -> 0 | AH13: ='OECD TTL - 2018'!AB$18*'SIOM from DLIM'!AA152/SUM('SIOM from DLIM'!AA$152:AA$153) -> 0 | AI13: ='OECD TTL - 2018'!AC$18*'SIOM from DLIM'!AB152/SUM('SIOM from DLIM'!AB$152:AB$153) -> 0 | AJ13: ='OECD TTL - 2018'!AD$18*'SIOM from DLIM'!AC152/SUM('SIOM from DLIM'!AC$152:AC$153) -> 0 | AK13: ='OECD TTL - 2018'!AE$18*'SIOM from DLIM'!AD152/SUM('SIOM from DLIM'!AD$152:AD$153) -> 0 | ... AR13: ='OECD TTL - 2018'!AL$18*'SIOM from DLIM'!AK152/SUM('SIOM from DLIM'!AK$152:AK$153) -> 0
A14: pharmaceuticals | B14: chemicals 20 | C14: ='OECD TTL - 2018'!C$18*'SIOM from DLIM'!B153/SUM('SIOM from DLIM'!B$152:B$153) -> 2698.2 | D14: ='OECD TTL - 2018'!$D$18*'SIOM from DLIM'!C153/SUM('SIOM from DLIM'!$C$152:$D$153) -> 0 | E14: ='OECD TTL - 2018'!$D$18*'SIOM from DLIM'!D153/SUM('SIOM from DLIM'!$C$152:$D$153) -> 32.58145 | F14: ='OECD TTL - 2018'!E$18*'SIOM from DLIM'!D153/SUM('SIOM from DLIM'!D$152:D$153) -> 415 | G14: ='OECD TTL - 2018'!F$18*'SIOM from DLIM'!E153/SUM('SIOM from DLIM'!E$152:E$153) -> 159.5 | H14: ='OECD TTL - 2018'!G$18*'SIOM from DLIM'!F153/SUM('SIOM from DLIM'!F$152:F$153) -> 1414.1 | I14: ='OECD TTL - 2018'!H$18*'SIOM from DLIM'!G153/SUM('SIOM from DLIM'!G$152:G$153) -> 1437.5 | J14: ='OECD TTL - 2018'!I$18*'SIOM from DLIM'!H153/SUM('SIOM from DLIM'!H$152:H$153) -> 0 | K14: ='OECD TTL - 2018'!J$18*'SIOM from DLIM'!I153/SUM('SIOM from DLIM'!I$152:I$153) -> 1264.4 | L14: ='OECD TTL - 2018'!K$18*'SIOM from DLIM'!J153/SUM('SIOM from DLIM'!J$152:J$153) -> 0 | M14: ='OECD TTL - 2018'!$L$18*'SIOM from DLIM'!L153/SUM('SIOM from DLIM'!$L$152:$M$153) -> 0 | N14: ='OECD TTL - 2018'!$L$18*'SIOM from DLIM'!M153/SUM('SIOM from DLIM'!$L$152:$M$153) -> 0 | O14: ='OECD TTL - 2018'!M$18*'SIOM from DLIM'!L153/SUM('SIOM from DLIM'!L$152:L$153) -> 0 | P14: ='OECD TTL - 2018'!$N$18*'SIOM from DLIM'!O153/SUM('SIOM from DLIM'!$O$152:$P$153) -> 0 | Q14: ='OECD TTL - 2018'!$N$18*'SIOM from DLIM'!P153/SUM('SIOM from DLIM'!$O$152:$P$153) -> 0 | R14: ='OECD TTL - 2018'!$O$18*'SIOM from DLIM'!Q153/SUM('SIOM from DLIM'!$Q$152:$R$153) -> 0 | S14: ='OECD TTL - 2018'!$O$18*'SIOM from DLIM'!R153/SUM('SIOM from DLIM'!$Q$152:$R$153) -> 17.479312 | T14: ='OECD TTL - 2018'!P$18*'SIOM from DLIM'!O153/SUM('SIOM from DLIM'!O$152:O$153) -> 0 | U14: ='OECD TTL - 2018'!Q$18*'SIOM from DLIM'!P153/SUM('SIOM from DLIM'!P$152:P$153) -> 0 | V14: ='OECD TTL - 2018'!R$18*'SIOM from DLIM'!Q153/SUM('SIOM from DLIM'!Q$152:Q$153) -> 0 | W14: ='OECD TTL - 2018'!S$18*'SIOM from DLIM'!R153/SUM('SIOM from DLIM'!R$152:R$153) -> 424.6 | X14: ='OECD TTL - 2018'!T$18*'SIOM from DLIM'!S153/SUM('SIOM from DLIM'!S$152:S$153) -> 0 | Y14: ='OECD TTL - 2018'!U$18*'SIOM from DLIM'!T153/SUM('SIOM from DLIM'!T$152:T$153) -> 296.1 | Z14: ='OECD TTL - 2018'!V$18*'SIOM from DLIM'!U153/SUM('SIOM from DLIM'!U$152:U$153) -> 0 | AA14: ='OECD TTL - 2018'!$W$18*'SIOM from DLIM'!Z153/SUM('SIOM from DLIM'!$Z$152:$AB$153) -> 481.8318 | AB14: ='OECD TTL - 2018'!$W$18*'SIOM from DLIM'!AA153/SUM('SIOM from DLIM'!$Z$152:$AB$153) -> 2.2298581 | AC14: ='OECD TTL - 2018'!$W$18*'SIOM from DLIM'!AB153/SUM('SIOM from DLIM'!$Z$152:$AB$153) -> 0.038344391 | AD14: ='OECD TTL - 2018'!X$18*'SIOM from DLIM'!W153/SUM('SIOM from DLIM'!W$152:W$153) -> 0 | AE14: ='OECD TTL - 2018'!Y$18*'SIOM from DLIM'!X153/SUM('SIOM from DLIM'!X$152:X$153) -> 0 | AF14: ='OECD TTL - 2018'!Z$18*'SIOM from DLIM'!Y153/SUM('SIOM from DLIM'!Y$152:Y$153) -> 745.4 | AG14: ='OECD TTL - 2018'!AA$18*'SIOM from DLIM'!Z153/SUM('SIOM from DLIM'!Z$152:Z$153) -> 229.2 | AH14: ='OECD TTL - 2018'!AB$18*'SIOM from DLIM'!AA153/SUM('SIOM from DLIM'!AA$152:AA$153) -> 143 | AI14: ='OECD TTL - 2018'!AC$18*'SIOM from DLIM'!AB153/SUM('SIOM from DLIM'!AB$152:AB$153) -> 31.8 | AJ14: ='OECD TTL - 2018'!AD$18*'SIOM from DLIM'!AC153/SUM('SIOM from DLIM'!AC$152:AC$153) -> 8.6 | AK14: ='OECD TTL - 2018'!AE$18*'SIOM from DLIM'!AD153/SUM('SIOM from DLIM'!AD$152:AD$153) -> 146.1 | ... AR14: ='OECD TTL - 2018'!AL$18*'SIOM from DLIM'!AK153/SUM('SIOM from DLIM'!AK$152:AK$153) -> 0
A15: D22: Rubber and plastic products | B15: rubber and plastic products 22 | C15: ='OECD TTL - 2018'!C19 -> 164.5 | D15: ='OECD TTL - 2018'!$D19*'SIOM from DLIM'!C154/SUM('SIOM from DLIM'!$C154:$D154) -> 0 | E15: ='OECD TTL - 2018'!$D19*'SIOM from DLIM'!D154/SUM('SIOM from DLIM'!$C154:$D154) -> 77 | F15: ='OECD TTL - 2018'!E19 -> 139.9 | G15: ='OECD TTL - 2018'!F19 -> 73.7 | H15: ='OECD TTL - 2018'!G19 -> 1869.2 | I15: ='OECD TTL - 2018'!H19 -> 399.1 | J15: ='OECD TTL - 2018'!I19 -> 56.9 | K15: ='OECD TTL - 2018'!J19 -> 289 | L15: ='OECD TTL - 2018'!K19 -> 152.1 | M15: ='OECD TTL - 2018'!$L19*'SIOM from DLIM'!L154/SUM('SIOM from DLIM'!$L154:$M154) -> #DIV/0! | N15: ='OECD TTL - 2018'!$L19*'SIOM from DLIM'!M154/SUM('SIOM from DLIM'!$L154:$M154) -> #DIV/0! | O15: ='OECD TTL - 2018'!M19 -> 1899.1 | P15: ='OECD TTL - 2018'!$N19*'SIOM from DLIM'!O154/SUM('SIOM from DLIM'!$O154:$P154) -> #DIV/0! | Q15: ='OECD TTL - 2018'!$N19*'SIOM from DLIM'!P154/SUM('SIOM from DLIM'!$O154:$P154) -> #DIV/0! | R15: ='OECD TTL - 2018'!$O19*'SIOM from DLIM'!Q154/SUM('SIOM from DLIM'!$Q154:$R154) -> 0 | S15: ='OECD TTL - 2018'!$O19*'SIOM from DLIM'!R154/SUM('SIOM from DLIM'!$Q154:$R154) -> 229 | T15: ='OECD TTL - 2018'!P19 -> 362.7 | U15: ='OECD TTL - 2018'!Q19 -> 1474.7 | V15: ='OECD TTL - 2018'!R19 -> 740.7 | W15: ='OECD TTL - 2018'!S19 -> 535.9 | X15: ='OECD TTL - 2018'!T19 -> 6469.1 | Y15: ='OECD TTL - 2018'!U19 -> 361.6 | Z15: ='OECD TTL - 2018'!V19 -> 811.8 | AA15: ='OECD TTL - 2018'!$W19*'SIOM from DLIM'!Z154/SUM('SIOM from DLIM'!$Z154:$AB154) -> 121.62934 | AB15: ='OECD TTL - 2018'!$W19*'SIOM from DLIM'!AA154/SUM('SIOM from DLIM'!$Z154:$AB154) -> 0.5612887 | AC15: ='OECD TTL - 2018'!$W19*'SIOM from DLIM'!AB154/SUM('SIOM from DLIM'!$Z154:$AB154) -> 0.009369837 | AD15: ='OECD TTL - 2018'!X19 -> 2479.8 | AE15: ='OECD TTL - 2018'!Y19 -> 975 | AF15: ='OECD TTL - 2018'!Z19 -> 1247.6 | AG15: ='OECD TTL - 2018'!AA19 -> 153.3 | AH15: ='OECD TTL - 2018'!AB19 -> 41.2 | AI15: ='OECD TTL - 2018'!AC19 -> 83.4 | AJ15: ='OECD TTL - 2018'!AD19 -> 8.4 | AK15: ='OECD TTL - 2018'!AE19 -> 109.1 | ... AR15: ='OECD TTL - 2018'!AL19 -> 0
A16: glass and glass products 231 | B16: glass and glass products 231 | C16: ='OECD TTL - 2018'!C$20*'SIOM from DLIM'!B155/SUM('SIOM from DLIM'!B$155:B$156) -> 48.051096 | D16: ='OECD TTL - 2018'!$D$20*'SIOM from DLIM'!C155/SUM('SIOM from DLIM'!$C$155:$D$156) -> 0 | E16: ='OECD TTL - 2018'!$D$20*'SIOM from DLIM'!D155/SUM('SIOM from DLIM'!$C$155:$D$156) -> 16.637674 | F16: ='OECD TTL - 2018'!E$20*'SIOM from DLIM'!D155/SUM('SIOM from DLIM'!D$155:D$156) -> 69.068238 | G16: ='OECD TTL - 2018'!F$20*'SIOM from DLIM'!E155/SUM('SIOM from DLIM'!E$155:E$156) -> 25.829702 | H16: ='OECD TTL - 2018'!G$20*'SIOM from DLIM'!F155/SUM('SIOM from DLIM'!F$155:F$156) -> 378.45733 | I16: ='OECD TTL - 2018'!H$20*'SIOM from DLIM'!G155/SUM('SIOM from DLIM'!G$155:G$156) -> 22.166527 | J16: ='OECD TTL - 2018'!I$20*'SIOM from DLIM'!H155/SUM('SIOM from DLIM'!H$155:H$156) -> #DIV/0! | K16: ='OECD TTL - 2018'!J$20*'SIOM from DLIM'!I155/SUM('SIOM from DLIM'!I$155:I$156) -> 13.872928 | L16: ='OECD TTL - 2018'!K$20*'SIOM from DLIM'!J155/SUM('SIOM from DLIM'!J$155:J$156) -> #DIV/0! | M16: ='OECD TTL - 2018'!$L$20*'SIOM from DLIM'!L155/SUM('SIOM from DLIM'!$L$155:$M$156) -> #DIV/0! | N16: ='OECD TTL - 2018'!$L$20*'SIOM from DLIM'!M155/SUM('SIOM from DLIM'!$L$155:$M$156) -> #DIV/0! | O16: ='OECD TTL - 2018'!M$20*'SIOM from DLIM'!L155/SUM('SIOM from DLIM'!L$155:L$156) -> #DIV/0! | P16: ='OECD TTL - 2018'!$N$20*'SIOM from DLIM'!O155/SUM('SIOM from DLIM'!$O$155:$P$156) -> #DIV/0! | Q16: ='OECD TTL - 2018'!$N$20*'SIOM from DLIM'!P155/SUM('SIOM from DLIM'!$O$155:$P$156) -> #DIV/0! | R16: ='OECD TTL - 2018'!$O$20*'SIOM from DLIM'!Q155/SUM('SIOM from DLIM'!$Q$155:$R$156) -> 0 | S16: ='OECD TTL - 2018'!$O$20*'SIOM from DLIM'!R155/SUM('SIOM from DLIM'!$Q$155:$R$156) -> 104.41577 | T16: ='OECD TTL - 2018'!P$20*'SIOM from DLIM'!O155/SUM('SIOM from DLIM'!O$155:O$156) -> #DIV/0! | U16: ='OECD TTL - 2018'!Q$20*'SIOM from DLIM'!P155/SUM('SIOM from DLIM'!P$155:P$156) -> #DIV/0! | V16: ='OECD TTL - 2018'!R$20*'SIOM from DLIM'!Q155/SUM('SIOM from DLIM'!Q$155:Q$156) -> #DIV/0! | W16: ='OECD TTL - 2018'!S$20*'SIOM from DLIM'!R155/SUM('SIOM from DLIM'!R$155:R$156) -> 67.704123 | X16: ='OECD TTL - 2018'!T$20*'SIOM from DLIM'!S155/SUM('SIOM from DLIM'!S$155:S$156) -> #DIV/0! | Y16: ='OECD TTL - 2018'!U$20*'SIOM from DLIM'!T155/SUM('SIOM from DLIM'!T$155:T$156) -> 31.672218 | Z16: ='OECD TTL - 2018'!V$20*'SIOM from DLIM'!U155/SUM('SIOM from DLIM'!U$155:U$156) -> #DIV/0! | AA16: ='OECD TTL - 2018'!$W$20*'SIOM from DLIM'!Z155/SUM('SIOM from DLIM'!$Z$155:$AB$156) -> 45.148009 | AB16: ='OECD TTL - 2018'!$W$20*'SIOM from DLIM'!AA155/SUM('SIOM from DLIM'!$Z$155:$AB$156) -> 0.20871702 | AC16: ='OECD TTL - 2018'!$W$20*'SIOM from DLIM'!AB155/SUM('SIOM from DLIM'!$Z$155:$AB$156) -> 0.0034780046 | AD16: ='OECD TTL - 2018'!X$20*'SIOM from DLIM'!W155/SUM('SIOM from DLIM'!W$155:W$156) -> #DIV/0! | AE16: ='OECD TTL - 2018'!Y$20*'SIOM from DLIM'!X155/SUM('SIOM from DLIM'!X$155:X$156) -> #DIV/0! | AF16: ='OECD TTL - 2018'!Z$20*'SIOM from DLIM'!Y155/SUM('SIOM from DLIM'!Y$155:Y$156) -> 74.782665 | AG16: ='OECD TTL - 2018'!AA$20*'SIOM from DLIM'!Z155/SUM('SIOM from DLIM'!Z$155:Z$156) -> 43.499682 | AH16: ='OECD TTL - 2018'!AB$20*'SIOM from DLIM'!AA155/SUM('SIOM from DLIM'!AA$155:AA$156) -> 4.7638073 | AI16: ='OECD TTL - 2018'!AC$20*'SIOM from DLIM'!AB155/SUM('SIOM from DLIM'!AB$155:AB$156) -> 8.2247955 | AJ16: ='OECD TTL - 2018'!AD$20*'SIOM from DLIM'!AC155/SUM('SIOM from DLIM'!AC$155:AC$156) -> 0.95027598 | AK16: ='OECD TTL - 2018'!AE$20*'SIOM from DLIM'!AD155/SUM('SIOM from DLIM'!AD$155:AD$156) -> 17.616467 | ... AR16: ='OECD TTL - 2018'!AL$20*'SIOM from DLIM'!AK155/SUM('SIOM from DLIM'!AK$155:AK$156) -> #DIV/0!
A17: cement and other nonmetallic minerals 239 | B17: cement and other nonmetallic minerals 239 | C17: ='OECD TTL - 2018'!C$20*'SIOM from DLIM'!B156/SUM('SIOM from DLIM'!B$155:B$156) -> 39.548904 | D17: ='OECD TTL - 2018'!$D$20*'SIOM from DLIM'!C156/SUM('SIOM from DLIM'!$C$155:$D$156) -> 0 | E17: ='OECD TTL - 2018'!$D$20*'SIOM from DLIM'!D156/SUM('SIOM from DLIM'!$C$155:$D$156) -> 13.762326 | F17: ='OECD TTL - 2018'!E$20*'SIOM from DLIM'!D156/SUM('SIOM from DLIM'!D$155:D$156) -> 57.131762 | G17: ='OECD TTL - 2018'!F$20*'SIOM from DLIM'!E156/SUM('SIOM from DLIM'!E$155:E$156) -> 21.170298 | H17: ='OECD TTL - 2018'!G$20*'SIOM from DLIM'!F156/SUM('SIOM from DLIM'!F$155:F$156) -> 310.24267 | I17: ='OECD TTL - 2018'!H$20*'SIOM from DLIM'!G156/SUM('SIOM from DLIM'!G$155:G$156) -> 18.933473 | J17: ='OECD TTL - 2018'!I$20*'SIOM from DLIM'!H156/SUM('SIOM from DLIM'!H$155:H$156) -> #DIV/0! | K17: ='OECD TTL - 2018'!J$20*'SIOM from DLIM'!I156/SUM('SIOM from DLIM'!I$155:I$156) -> 11.627072 | L17: ='OECD TTL - 2018'!K$20*'SIOM from DLIM'!J156/SUM('SIOM from DLIM'!J$155:J$156) -> #DIV/0! | M17: ='OECD TTL - 2018'!$L$20*'SIOM from DLIM'!L156/SUM('SIOM from DLIM'!$L$155:$M$156) -> #DIV/0! | N17: ='OECD TTL - 2018'!$L$20*'SIOM from DLIM'!M156/SUM('SIOM from DLIM'!$L$155:$M$156) -> #DIV/0! | O17: ='OECD TTL - 2018'!M$20*'SIOM from DLIM'!L156/SUM('SIOM from DLIM'!L$155:L$156) -> #DIV/0! | P17: ='OECD TTL - 2018'!$N$20*'SIOM from DLIM'!O156/SUM('SIOM from DLIM'!$O$155:$P$156) -> #DIV/0! | Q17: ='OECD TTL - 2018'!$N$20*'SIOM from DLIM'!P156/SUM('SIOM from DLIM'!$O$155:$P$156) -> #DIV/0! | R17: ='OECD TTL - 2018'!$O$20*'SIOM from DLIM'!Q156/SUM('SIOM from DLIM'!$Q$155:$R$156) -> 0 | S17: ='OECD TTL - 2018'!$O$20*'SIOM from DLIM'!R156/SUM('SIOM from DLIM'!$Q$155:$R$156) -> 87.284229 | T17: ='OECD TTL - 2018'!P$20*'SIOM from DLIM'!O156/SUM('SIOM from DLIM'!O$155:O$156) -> #DIV/0! | U17: ='OECD TTL - 2018'!Q$20*'SIOM from DLIM'!P156/SUM('SIOM from DLIM'!P$155:P$156) -> #DIV/0! | V17: ='OECD TTL - 2018'!R$20*'SIOM from DLIM'!Q156/SUM('SIOM from DLIM'!Q$155:Q$156) -> #DIV/0! | W17: ='OECD TTL - 2018'!S$20*'SIOM from DLIM'!R156/SUM('SIOM from DLIM'!R$155:R$156) -> 56.595877 | X17: ='OECD TTL - 2018'!T$20*'SIOM from DLIM'!S156/SUM('SIOM from DLIM'!S$155:S$156) -> #DIV/0! | Y17: ='OECD TTL - 2018'!U$20*'SIOM from DLIM'!T156/SUM('SIOM from DLIM'!T$155:T$156) -> 26.227782 | Z17: ='OECD TTL - 2018'!V$20*'SIOM from DLIM'!U156/SUM('SIOM from DLIM'!U$155:U$156) -> #DIV/0! | AA17: ='OECD TTL - 2018'!$W$20*'SIOM from DLIM'!Z156/SUM('SIOM from DLIM'!$Z$155:$AB$156) -> 37.364474 | AB17: ='OECD TTL - 2018'!$W$20*'SIOM from DLIM'!AA156/SUM('SIOM from DLIM'!$Z$155:$AB$156) -> 0.17245668 | AC17: ='OECD TTL - 2018'!$W$20*'SIOM from DLIM'!AB156/SUM('SIOM from DLIM'!$Z$155:$AB$156) -> 0.0028650187 | AD17: ='OECD TTL - 2018'!X$20*'SIOM from DLIM'!W156/SUM('SIOM from DLIM'!W$155:W$156) -> #DIV/0! | AE17: ='OECD TTL - 2018'!Y$20*'SIOM from DLIM'!X156/SUM('SIOM from DLIM'!X$155:X$156) -> #DIV/0! | AF17: ='OECD TTL - 2018'!Z$20*'SIOM from DLIM'!Y156/SUM('SIOM from DLIM'!Y$155:Y$156) -> 61.817335 | AG17: ='OECD TTL - 2018'!AA$20*'SIOM from DLIM'!Z156/SUM('SIOM from DLIM'!Z$155:Z$156) -> 36.000318 | AH17: ='OECD TTL - 2018'!AB$20*'SIOM from DLIM'!AA156/SUM('SIOM from DLIM'!AA$155:AA$156) -> 3.9361927 | AI17: ='OECD TTL - 2018'!AC$20*'SIOM from DLIM'!AB156/SUM('SIOM from DLIM'!AB$155:AB$156) -> 6.7752045 | AJ17: ='OECD TTL - 2018'!AD$20*'SIOM from DLIM'!AC156/SUM('SIOM from DLIM'!AC$155:AC$156) -> 0.94972402 | AK17: ='OECD TTL - 2018'!AE$20*'SIOM from DLIM'!AD156/SUM('SIOM from DLIM'!AD$155:AD$156) -> 14.683533 | ... AR17: ='OECD TTL - 2018'!AL$20*'SIOM from DLIM'!AK156/SUM('SIOM from DLIM'!AK$155:AK$156) -> #DIV/0!
A18: iron and steel 241 | B18: iron and steel 241 | C18: ='OECD TTL - 2018'!C$21*'SIOM from DLIM'!B157/SUM('SIOM from DLIM'!B$157:B$158) -> 48.6 | D18: ='OECD TTL - 2018'!$D$21*'SIOM from DLIM'!C157/SUM('SIOM from DLIM'!$C$157:$D$158) -> 0 | E18: ='OECD TTL - 2018'!$D$21*'SIOM from DLIM'!D157/SUM('SIOM from DLIM'!$C$157:$D$158) -> 102.60654 | F18: ='OECD TTL - 2018'!E$21*'SIOM from DLIM'!D157/SUM('SIOM from DLIM'!D$157:D$158) -> 126.3 | G18: ='OECD TTL - 2018'!F$21*'SIOM from DLIM'!E157/SUM('SIOM from DLIM'!E$157:E$158) -> 192.1 | H18: ='OECD TTL - 2018'!G$21*'SIOM from DLIM'!F157/SUM('SIOM from DLIM'!F$157:F$158) -> 246.9 | I18: ='OECD TTL - 2018'!H$21*'SIOM from DLIM'!G157/SUM('SIOM from DLIM'!G$157:G$158) -> 15.5 | J18: ='OECD TTL - 2018'!I$21*'SIOM from DLIM'!H157/SUM('SIOM from DLIM'!H$157:H$158) -> 0 | K18: ='OECD TTL - 2018'!J$21*'SIOM from DLIM'!I157/SUM('SIOM from DLIM'!I$157:I$158) -> 115 | L18: ='OECD TTL - 2018'!K$21*'SIOM from DLIM'!J157/SUM('SIOM from DLIM'!J$157:J$158) -> 0 | M18: ='OECD TTL - 2018'!$L$21*'SIOM from DLIM'!L157/SUM('SIOM from DLIM'!$L$157:$M$158) -> 0 | N18: ='OECD TTL - 2018'!$L$21*'SIOM from DLIM'!M157/SUM('SIOM from DLIM'!$L$157:$M$158) -> 0 | O18: ='OECD TTL - 2018'!M$21*'SIOM from DLIM'!L157/SUM('SIOM from DLIM'!L$157:L$158) -> 0 | P18: ='OECD TTL - 2018'!$N$21*'SIOM from DLIM'!O157/SUM('SIOM from DLIM'!$O$157:$P$158) -> 0 | Q18: ='OECD TTL - 2018'!$N$21*'SIOM from DLIM'!P157/SUM('SIOM from DLIM'!$O$157:$P$158) -> 0 | R18: ='OECD TTL - 2018'!$O$21*'SIOM from DLIM'!Q157/SUM('SIOM from DLIM'!$Q$157:$R$158) -> 0 | S18: ='OECD TTL - 2018'!$O$21*'SIOM from DLIM'!R157/SUM('SIOM from DLIM'!$Q$157:$R$158) -> 3984.9138 | T18: ='OECD TTL - 2018'!P$21*'SIOM from DLIM'!O157/SUM('SIOM from DLIM'!O$157:O$158) -> 0 | U18: ='OECD TTL - 2018'!Q$21*'SIOM from DLIM'!P157/SUM('SIOM from DLIM'!P$157:P$158) -> 0 | V18: ='OECD TTL - 2018'!R$21*'SIOM from DLIM'!Q157/SUM('SIOM from DLIM'!Q$157:Q$158) -> 0 | W18: ='OECD TTL - 2018'!S$21*'SIOM from DLIM'!R157/SUM('SIOM from DLIM'!R$157:R$158) -> 2521.4 | X18: ='OECD TTL - 2018'!T$21*'SIOM from DLIM'!S157/SUM('SIOM from DLIM'!S$157:S$158) -> 0 | Y18: ='OECD TTL - 2018'!U$21*'SIOM from DLIM'!T157/SUM('SIOM from DLIM'!T$157:T$158) -> 1024.2 | Z18: ='OECD TTL - 2018'!V$21*'SIOM from DLIM'!U157/SUM('SIOM from DLIM'!U$157:U$158) -> 0 | AA18: ='OECD TTL - 2018'!$W$21*'SIOM from DLIM'!Z157/SUM('SIOM from DLIM'!$Z$157:$AB$158) -> 156.56787 | AB18: ='OECD TTL - 2018'!$W$21*'SIOM from DLIM'!AA157/SUM('SIOM from DLIM'!$Z$157:$AB$158) -> 0.72006125 | AC18: ='OECD TTL - 2018'!$W$21*'SIOM from DLIM'!AB157/SUM('SIOM from DLIM'!$Z$157:$AB$158) -> 0.012070196 | AD18: ='OECD TTL - 2018'!X$21*'SIOM from DLIM'!W157/SUM('SIOM from DLIM'!W$157:W$158) -> 0 | AE18: ='OECD TTL - 2018'!Y$21*'SIOM from DLIM'!X157/SUM('SIOM from DLIM'!X$157:X$158) -> 0 | AF18: ='OECD TTL - 2018'!Z$21*'SIOM from DLIM'!Y157/SUM('SIOM from DLIM'!Y$157:Y$158) -> 204.8 | AG18: ='OECD TTL - 2018'!AA$21*'SIOM from DLIM'!Z157/SUM('SIOM from DLIM'!Z$157:Z$158) -> 8.6 | AH18: ='OECD TTL - 2018'!AB$21*'SIOM from DLIM'!AA157/SUM('SIOM from DLIM'!AA$157:AA$158) -> 3.8 | AI18: ='OECD TTL - 2018'!AC$21*'SIOM from DLIM'!AB157/SUM('SIOM from DLIM'!AB$157:AB$158) -> 21.5 | AJ18: ='OECD TTL - 2018'!AD$21*'SIOM from DLIM'!AC157/SUM('SIOM from DLIM'!AC$157:AC$158) -> 1 | AK18: ='OECD TTL - 2018'!AE$21*'SIOM from DLIM'!AD157/SUM('SIOM from DLIM'!AD$157:AD$158) -> 16.8 | ... AR18: ='OECD TTL - 2018'!AL$21*'SIOM from DLIM'!AK157/SUM('SIOM from DLIM'!AK$157:AK$158) -> 0
A19: other metals 242 | B19: other metals 242 | C19: ='OECD TTL - 2018'!C$21*'SIOM from DLIM'!B158/SUM('SIOM from DLIM'!B$157:B$158) -> 0 | D19: ='OECD TTL - 2018'!$D$21*'SIOM from DLIM'!C158/SUM('SIOM from DLIM'!$C$157:$D$158) -> 5.7934608 | E19: ='OECD TTL - 2018'!$D$21*'SIOM from DLIM'!D158/SUM('SIOM from DLIM'!$C$157:$D$158) -> 0 | F19: ='OECD TTL - 2018'!E$21*'SIOM from DLIM'!D158/SUM('SIOM from DLIM'!D$157:D$158) -> 0 | G19: ='OECD TTL - 2018'!F$21*'SIOM from DLIM'!E158/SUM('SIOM from DLIM'!E$157:E$158) -> 0 | H19: ='OECD TTL - 2018'!G$21*'SIOM from DLIM'!F158/SUM('SIOM from DLIM'!F$157:F$158) -> 0 | I19: ='OECD TTL - 2018'!H$21*'SIOM from DLIM'!G158/SUM('SIOM from DLIM'!G$157:G$158) -> 0 | J19: ='OECD TTL - 2018'!I$21*'SIOM from DLIM'!H158/SUM('SIOM from DLIM'!H$157:H$158) -> 11.3 | K19: ='OECD TTL - 2018'!J$21*'SIOM from DLIM'!I158/SUM('SIOM from DLIM'!I$157:I$158) -> 0 | L19: ='OECD TTL - 2018'!K$21*'SIOM from DLIM'!J158/SUM('SIOM from DLIM'!J$157:J$158) -> 93.2 | M19: ='OECD TTL - 2018'!$L$21*'SIOM from DLIM'!L158/SUM('SIOM from DLIM'!$L$157:$M$158) -> 175.13348 | N19: ='OECD TTL - 2018'!$L$21*'SIOM from DLIM'!M158/SUM('SIOM from DLIM'!$L$157:$M$158) -> 29.466515 | O19: ='OECD TTL - 2018'!M$21*'SIOM from DLIM'!L158/SUM('SIOM from DLIM'!L$157:L$158) -> 129 | P19: ='OECD TTL - 2018'!$N$21*'SIOM from DLIM'!O158/SUM('SIOM from DLIM'!$O$157:$P$158) -> 173.41927 | Q19: ='OECD TTL - 2018'!$N$21*'SIOM from DLIM'!P158/SUM('SIOM from DLIM'!$O$157:$P$158) -> 84.48073 | R19: ='OECD TTL - 2018'!$O$21*'SIOM from DLIM'!Q158/SUM('SIOM from DLIM'!$Q$157:$R$158) -> 3053.2862 | S19: ='OECD TTL - 2018'!$O$21*'SIOM from DLIM'!R158/SUM('SIOM from DLIM'!$Q$157:$R$158) -> 0 | T19: ='OECD TTL - 2018'!P$21*'SIOM from DLIM'!O158/SUM('SIOM from DLIM'!O$157:O$158) -> 5574.9 | U19: ='OECD TTL - 2018'!Q$21*'SIOM from DLIM'!P158/SUM('SIOM from DLIM'!P$157:P$158) -> 1879.2 | V19: ='OECD TTL - 2018'!R$21*'SIOM from DLIM'!Q158/SUM('SIOM from DLIM'!Q$157:Q$158) -> 3061.2 | W19: ='OECD TTL - 2018'!S$21*'SIOM from DLIM'!R158/SUM('SIOM from DLIM'!R$157:R$158) -> 0 | X19: ='OECD TTL - 2018'!T$21*'SIOM from DLIM'!S158/SUM('SIOM from DLIM'!S$157:S$158) -> 9049.2 | Y19: ='OECD TTL - 2018'!U$21*'SIOM from DLIM'!T158/SUM('SIOM from DLIM'!T$157:T$158) -> 0 | Z19: ='OECD TTL - 2018'!V$21*'SIOM from DLIM'!U158/SUM('SIOM from DLIM'!U$157:U$158) -> 1863.8 | AA19: ='OECD TTL - 2018'!$W$21*'SIOM from DLIM'!Z158/SUM('SIOM from DLIM'!$Z$157:$AB$158) -> 0 | AB19: ='OECD TTL - 2018'!$W$21*'SIOM from DLIM'!AA158/SUM('SIOM from DLIM'!$Z$157:$AB$158) -> 0 | AC19: ='OECD TTL - 2018'!$W$21*'SIOM from DLIM'!AB158/SUM('SIOM from DLIM'!$Z$157:$AB$158) -> 0 | AD19: ='OECD TTL - 2018'!X$21*'SIOM from DLIM'!W158/SUM('SIOM from DLIM'!W$157:W$158) -> 4965 | AE19: ='OECD TTL - 2018'!Y$21*'SIOM from DLIM'!X158/SUM('SIOM from DLIM'!X$157:X$158) -> 128.3 | AF19: ='OECD TTL - 2018'!Z$21*'SIOM from DLIM'!Y158/SUM('SIOM from DLIM'!Y$157:Y$158) -> 0 | AG19: ='OECD TTL - 2018'!AA$21*'SIOM from DLIM'!Z158/SUM('SIOM from DLIM'!Z$157:Z$158) -> 0 | AH19: ='OECD TTL - 2018'!AB$21*'SIOM from DLIM'!AA158/SUM('SIOM from DLIM'!AA$157:AA$158) -> 0 | AI19: ='OECD TTL - 2018'!AC$21*'SIOM from DLIM'!AB158/SUM('SIOM from DLIM'!AB$157:AB$158) -> 0 | AJ19: ='OECD TTL - 2018'!AD$21*'SIOM from DLIM'!AC158/SUM('SIOM from DLIM'!AC$157:AC$158) -> 0 | AK19: ='OECD TTL - 2018'!AE$21*'SIOM from DLIM'!AD158/SUM('SIOM from DLIM'!AD$157:AD$158) -> 0 | ... AR19: ='OECD TTL - 2018'!AL$21*'SIOM from DLIM'!AK158/SUM('SIOM from DLIM'!AK$157:AK$158) -> 0
A20: D25: Fabricated metal products | B20: metal products except machinery and vehicles 25 | C20: ='OECD TTL - 2018'!C22 -> 195 | D20: ='OECD TTL - 2018'!$D22*'SIOM from DLIM'!C159/SUM('SIOM from DLIM'!$C159:$D159) -> 209.1 | E20: ='OECD TTL - 2018'!$D22*'SIOM from DLIM'!D159/SUM('SIOM from DLIM'!$C159:$D159) -> 0 | F20: ='OECD TTL - 2018'!E22 -> 159.5 | G20: ='OECD TTL - 2018'!F22 -> 135.7 | H20: ='OECD TTL - 2018'!G22 -> 1332.3 | I20: ='OECD TTL - 2018'!H22 -> 127.9 | J20: ='OECD TTL - 2018'!I22 -> 95.2 | K20: ='OECD TTL - 2018'!J22 -> 105.5 | L20: ='OECD TTL - 2018'!K22 -> 238.2 | M20: ='OECD TTL - 2018'!$L22*'SIOM from DLIM'!L159/SUM('SIOM from DLIM'!$L159:$M159) -> 348.20397 | N20: ='OECD TTL - 2018'!$L22*'SIOM from DLIM'!M159/SUM('SIOM from DLIM'!$L159:$M159) -> 58.296033 | O20: ='OECD TTL - 2018'!M22 -> 260 | P20: ='OECD TTL - 2018'!$N22*'SIOM from DLIM'!O159/SUM('SIOM from DLIM'!$O159:$P159) -> 192.05389 | Q20: ='OECD TTL - 2018'!$N22*'SIOM from DLIM'!P159/SUM('SIOM from DLIM'!$O159:$P159) -> 93.746113 | R20: ='OECD TTL - 2018'!$O22*'SIOM from DLIM'!Q159/SUM('SIOM from DLIM'!$Q159:$R159) -> 1123.9 | S20: ='OECD TTL - 2018'!$O22*'SIOM from DLIM'!R159/SUM('SIOM from DLIM'!$Q159:$R159) -> 0 | T20: ='OECD TTL - 2018'!P22 -> 3016.5 | U20: ='OECD TTL - 2018'!Q22 -> 1291.9 | V20: ='OECD TTL - 2018'!R22 -> 854.7 | W20: ='OECD TTL - 2018'!S22 -> 1655.5 | X20: ='OECD TTL - 2018'!T22 -> 6838.9 | Y20: ='OECD TTL - 2018'!U22 -> 490.7 | Z20: ='OECD TTL - 2018'!V22 -> 830.6 | AA20: ='OECD TTL - 2018'!$W22*'SIOM from DLIM'!Z159/SUM('SIOM from DLIM'!$Z159:$AB159) -> #DIV/0! | AB20: ='OECD TTL - 2018'!$W22*'SIOM from DLIM'!AA159/SUM('SIOM from DLIM'!$Z159:$AB159) -> #DIV/0! | AC20: ='OECD TTL - 2018'!$W22*'SIOM from DLIM'!AB159/SUM('SIOM from DLIM'!$Z159:$AB159) -> #DIV/0! | AD20: ='OECD TTL - 2018'!X22 -> 4952.9 | AE20: ='OECD TTL - 2018'!Y22 -> 468.2 | AF20: ='OECD TTL - 2018'!Z22 -> 387.8 | AG20: ='OECD TTL - 2018'!AA22 -> 97.9 | AH20: ='OECD TTL - 2018'!AB22 -> 22.1 | AI20: ='OECD TTL - 2018'!AC22 -> 38.5 | AJ20: ='OECD TTL - 2018'!AD22 -> 9.3 | AK20: ='OECD TTL - 2018'!AE22 -> 80.2 | ... AR20: ='OECD TTL - 2018'!AL22 -> 0
A21: D26: Computer, electronic and optical products | B21: computers and electronics 26 | C21: ='OECD TTL - 2018'!C23 -> 56.6 | D21: ='OECD TTL - 2018'!$D23*'SIOM from DLIM'!C160/SUM('SIOM from DLIM'!$C160:$D160) -> 46.3 | E21: ='OECD TTL - 2018'!$D23*'SIOM from DLIM'!D160/SUM('SIOM from DLIM'!$C160:$D160) -> 0 | F21: ='OECD TTL - 2018'!E23 -> 57.7 | G21: ='OECD TTL - 2018'!F23 -> 55 | H21: ='OECD TTL - 2018'!G23 -> 169.9 | I21: ='OECD TTL - 2018'!H23 -> 126.8 | J21: ='OECD TTL - 2018'!I23 -> 14.8 | K21: ='OECD TTL - 2018'!J23 -> 115.5 | L21: ='OECD TTL - 2018'!K23 -> 103.1 | M21: ='OECD TTL - 2018'!$L23*'SIOM from DLIM'!L160/SUM('SIOM from DLIM'!$L160:$M160) -> 215.76303 | N21: ='OECD TTL - 2018'!$L23*'SIOM from DLIM'!M160/SUM('SIOM from DLIM'!$L160:$M160) -> 36.336969 | O21: ='OECD TTL - 2018'!M23 -> 150 | P21: ='OECD TTL - 2018'!$N23*'SIOM from DLIM'!O160/SUM('SIOM from DLIM'!$O160:$P160) -> 74.469384 | Q21: ='OECD TTL - 2018'!$N23*'SIOM from DLIM'!P160/SUM('SIOM from DLIM'!$O160:$P160) -> 36.430616 | R21: ='OECD TTL - 2018'!$O23*'SIOM from DLIM'!Q160/SUM('SIOM from DLIM'!$Q160:$R160) -> 111.9 | S21: ='OECD TTL - 2018'!$O23*'SIOM from DLIM'!R160/SUM('SIOM from DLIM'!$Q160:$R160) -> 0 | T21: ='OECD TTL - 2018'!P23 -> 238.3 | U21: ='OECD TTL - 2018'!Q23 -> 28944.1 | V21: ='OECD TTL - 2018'!R23 -> 1581.5 | W21: ='OECD TTL - 2018'!S23 -> 716.5 | X21: ='OECD TTL - 2018'!T23 -> 3911.8 | Y21: ='OECD TTL - 2018'!U23 -> 292.6 | Z21: ='OECD TTL - 2018'!V23 -> 468.4 | AA21: ='OECD TTL - 2018'!$W23*'SIOM from DLIM'!Z160/SUM('SIOM from DLIM'!$Z160:$AB160) -> #DIV/0! | AB21: ='OECD TTL - 2018'!$W23*'SIOM from DLIM'!AA160/SUM('SIOM from DLIM'!$Z160:$AB160) -> #DIV/0! | AC21: ='OECD TTL - 2018'!$W23*'SIOM from DLIM'!AB160/SUM('SIOM from DLIM'!$Z160:$AB160) -> #DIV/0! | AD21: ='OECD TTL - 2018'!X23 -> 1217.9 | AE21: ='OECD TTL - 2018'!Y23 -> 798.6 | AF21: ='OECD TTL - 2018'!Z23 -> 454.1 | AG21: ='OECD TTL - 2018'!AA23 -> 121.4 | AH21: ='OECD TTL - 2018'!AB23 -> 254.3 | AI21: ='OECD TTL - 2018'!AC23 -> 1470.9 | AJ21: ='OECD TTL - 2018'!AD23 -> 167.6 | AK21: ='OECD TTL - 2018'!AE23 -> 564.7 | ... AR21: ='OECD TTL - 2018'!AL23 -> 0
A22: D27: Electrical equipment | B22: appliances and electrical equipment 27 | C22: ='OECD TTL - 2018'!C24 -> 60.8 | D22: ='OECD TTL - 2018'!$D24*'SIOM from DLIM'!C161/SUM('SIOM from DLIM'!$C161:$D161) -> 0 | E22: ='OECD TTL - 2018'!$D24*'SIOM from DLIM'!D161/SUM('SIOM from DLIM'!$C161:$D161) -> 66.3 | F22: ='OECD TTL - 2018'!E24 -> 73.7 | G22: ='OECD TTL - 2018'!F24 -> 46.1 | H22: ='OECD TTL - 2018'!G24 -> 168.1 | I22: ='OECD TTL - 2018'!H24 -> 52.2 | J22: ='OECD TTL - 2018'!I24 -> 14 | K22: ='OECD TTL - 2018'!J24 -> 53.6 | L22: ='OECD TTL - 2018'!K24 -> 77.3 | M22: ='OECD TTL - 2018'!$L24*'SIOM from DLIM'!L161/SUM('SIOM from DLIM'!$L161:$M161) -> #DIV/0! | N22: ='OECD TTL - 2018'!$L24*'SIOM from DLIM'!M161/SUM('SIOM from DLIM'!$L161:$M161) -> #DIV/0! | O22: ='OECD TTL - 2018'!M24 -> 93.5 | P22: ='OECD TTL - 2018'!$N24*'SIOM from DLIM'!O161/SUM('SIOM from DLIM'!$O161:$P161) -> #DIV/0! | Q22: ='OECD TTL - 2018'!$N24*'SIOM from DLIM'!P161/SUM('SIOM from DLIM'!$O161:$P161) -> #DIV/0! | R22: ='OECD TTL - 2018'!$O24*'SIOM from DLIM'!Q161/SUM('SIOM from DLIM'!$Q161:$R161) -> 0 | S22: ='OECD TTL - 2018'!$O24*'SIOM from DLIM'!R161/SUM('SIOM from DLIM'!$Q161:$R161) -> 309 | T22: ='OECD TTL - 2018'!P24 -> 328 | U22: ='OECD TTL - 2018'!Q24 -> 4636.2 | V22: ='OECD TTL - 2018'!R24 -> 4772.4 | W22: ='OECD TTL - 2018'!S24 -> 1057 | X22: ='OECD TTL - 2018'!T24 -> 5944.2 | Y22: ='OECD TTL - 2018'!U24 -> 415.6 | Z22: ='OECD TTL - 2018'!V24 -> 338.6 | AA22: ='OECD TTL - 2018'!$W24*'SIOM from DLIM'!Z161/SUM('SIOM from DLIM'!$Z161:$AB161) -> 535.48994 | AB22: ='OECD TTL - 2018'!$W24*'SIOM from DLIM'!AA161/SUM('SIOM from DLIM'!$Z161:$AB161) -> 2.4686948 | AC22: ='OECD TTL - 2018'!$W24*'SIOM from DLIM'!AB161/SUM('SIOM from DLIM'!$Z161:$AB161) -> 0.041363277 | AD22: ='OECD TTL - 2018'!X24 -> 3352 | AE22: ='OECD TTL - 2018'!Y24 -> 506.4 | AF22: ='OECD TTL - 2018'!Z24 -> 535.2 | AG22: ='OECD TTL - 2018'!AA24 -> 101.6 | AH22: ='OECD TTL - 2018'!AB24 -> 67.6 | AI22: ='OECD TTL - 2018'!AC24 -> 326.2 | AJ22: ='OECD TTL - 2018'!AD24 -> 28.5 | AK22: ='OECD TTL - 2018'!AE24 -> 120 | ... AR22: ='OECD TTL - 2018'!AL24 -> 0
A23: D28: Machinery and equipment, nec | B23: other machinery 28 | C23: ='OECD TTL - 2018'!C25 -> 243.1 | D23: ='OECD TTL - 2018'!$D25*'SIOM from DLIM'!C162/SUM('SIOM from DLIM'!$C162:$D162) -> 237.4 | E23: ='OECD TTL - 2018'!$D25*'SIOM from DLIM'!D162/SUM('SIOM from DLIM'!$C162:$D162) -> 0 | F23: ='OECD TTL - 2018'!E25 -> 269.5 | G23: ='OECD TTL - 2018'!F25 -> 243 | H23: ='OECD TTL - 2018'!G25 -> 274 | I23: ='OECD TTL - 2018'!H25 -> 90.8 | J23: ='OECD TTL - 2018'!I25 -> 30.5 | K23: ='OECD TTL - 2018'!J25 -> 126.3 | L23: ='OECD TTL - 2018'!K25 -> 180.2 | M23: ='OECD TTL - 2018'!$L25*'SIOM from DLIM'!L162/SUM('SIOM from DLIM'!$L162:$M162) -> 174.49498 | N23: ='OECD TTL - 2018'!$L25*'SIOM from DLIM'!M162/SUM('SIOM from DLIM'!$L162:$M162) -> 29.505024 | O23: ='OECD TTL - 2018'!M25 -> 123.1 | P23: ='OECD TTL - 2018'!$N25*'SIOM from DLIM'!O162/SUM('SIOM from DLIM'!$O162:$P162) -> 129.57161 | Q23: ='OECD TTL - 2018'!$N25*'SIOM from DLIM'!P162/SUM('SIOM from DLIM'!$O162:$P162) -> 63.428389 | R23: ='OECD TTL - 2018'!$O25*'SIOM from DLIM'!Q162/SUM('SIOM from DLIM'!$Q162:$R162) -> 317.7 | S23: ='OECD TTL - 2018'!$O25*'SIOM from DLIM'!R162/SUM('SIOM from DLIM'!$Q162:$R162) -> 0 | T23: ='OECD TTL - 2018'!P25 -> 387.4 | U23: ='OECD TTL - 2018'!Q25 -> 1242.9 | V23: ='OECD TTL - 2018'!R25 -> 419.6 | W23: ='OECD TTL - 2018'!S25 -> 1863.9 | X23: ='OECD TTL - 2018'!T25 -> 4597.6 | Y23: ='OECD TTL - 2018'!U25 -> 383.2 | Z23: ='OECD TTL - 2018'!V25 -> 269.2 | AA23: ='OECD TTL - 2018'!$W25*'SIOM from DLIM'!Z162/SUM('SIOM from DLIM'!$Z162:$AB162) -> #DIV/0! | AB23: ='OECD TTL - 2018'!$W25*'SIOM from DLIM'!AA162/SUM('SIOM from DLIM'!$Z162:$AB162) -> #DIV/0! | AC23: ='OECD TTL - 2018'!$W25*'SIOM from DLIM'!AB162/SUM('SIOM from DLIM'!$Z162:$AB162) -> #DIV/0! | AD23: ='OECD TTL - 2018'!X25 -> 1386.5 | AE23: ='OECD TTL - 2018'!Y25 -> 358.6 | AF23: ='OECD TTL - 2018'!Z25 -> 404.9 | AG23: ='OECD TTL - 2018'!AA25 -> 33.7 | AH23: ='OECD TTL - 2018'!AB25 -> 28.5 | AI23: ='OECD TTL - 2018'!AC25 -> 73.3 | AJ23: ='OECD TTL - 2018'!AD25 -> 12.1 | AK23: ='OECD TTL - 2018'!AE25 -> 88.2 | ... AR23: ='OECD TTL - 2018'!AL25 -> 0
A24: D29: Motor vehicles, trailers and semi-trailers | B24: road vehicles 29 | C24: ='OECD TTL - 2018'!C26 -> 69.2 | D24: ='OECD TTL - 2018'!$D26*'SIOM from DLIM'!C163/SUM('SIOM from DLIM'!$C163:$D163) -> 32.4 | E24: ='OECD TTL - 2018'!$D26*'SIOM from DLIM'!D163/SUM('SIOM from DLIM'!$C163:$D163) -> 0 | F24: ='OECD TTL - 2018'!E26 -> 48.1 | G24: ='OECD TTL - 2018'!F26 -> 41.1 | H24: ='OECD TTL - 2018'!G26 -> 159.5 | I24: ='OECD TTL - 2018'!H26 -> 95.2 | J24: ='OECD TTL - 2018'!I26 -> 16 | K24: ='OECD TTL - 2018'!J26 -> 43.3 | L24: ='OECD TTL - 2018'!K26 -> 47 | M24: ='OECD TTL - 2018'!$L26*'SIOM from DLIM'!L163/SUM('SIOM from DLIM'!$L163:$M163) -> 96.049125 | N24: ='OECD TTL - 2018'!$L26*'SIOM from DLIM'!M163/SUM('SIOM from DLIM'!$L163:$M163) -> 16.150875 | O24: ='OECD TTL - 2018'!M26 -> 125.4 | P24: ='OECD TTL - 2018'!$N26*'SIOM from DLIM'!O163/SUM('SIOM from DLIM'!$O163:$P163) -> 51.583208 | Q24: ='OECD TTL - 2018'!$N26*'SIOM from DLIM'!P163/SUM('SIOM from DLIM'!$O163:$P163) -> 25.216792 | R24: ='OECD TTL - 2018'!$O26*'SIOM from DLIM'!Q163/SUM('SIOM from DLIM'!$Q163:$R163) -> 129.1 | S24: ='OECD TTL - 2018'!$O26*'SIOM from DLIM'!R163/SUM('SIOM from DLIM'!$Q163:$R163) -> 0 | T24: ='OECD TTL - 2018'!P26 -> 214.6 | U24: ='OECD TTL - 2018'!Q26 -> 590.2 | V24: ='OECD TTL - 2018'!R26 -> 344.8 | W24: ='OECD TTL - 2018'!S26 -> 358.4 | X24: ='OECD TTL - 2018'!T26 -> 34144.5 | Y24: ='OECD TTL - 2018'!U26 -> 225.3 | Z24: ='OECD TTL - 2018'!V26 -> 175.9 | AA24: ='OECD TTL - 2018'!$W26*'SIOM from DLIM'!Z163/SUM('SIOM from DLIM'!$Z163:$AB163) -> #DIV/0! | AB24: ='OECD TTL - 2018'!$W26*'SIOM from DLIM'!AA163/SUM('SIOM from DLIM'!$Z163:$AB163) -> #DIV/0! | AC24: ='OECD TTL - 2018'!$W26*'SIOM from DLIM'!AB163/SUM('SIOM from DLIM'!$Z163:$AB163) -> #DIV/0! | AD24: ='OECD TTL - 2018'!X26 -> 608.2 | AE24: ='OECD TTL - 2018'!Y26 -> 693.3 | AF24: ='OECD TTL - 2018'!Z26 -> 1381.9 | AG24: ='OECD TTL - 2018'!AA26 -> 30.9 | AH24: ='OECD TTL - 2018'!AB26 -> 19.6 | AI24: ='OECD TTL - 2018'!AC26 -> 64.7 | AJ24: ='OECD TTL - 2018'!AD26 -> 7.3 | AK24: ='OECD TTL - 2018'!AE26 -> 67.7 | ... AR24: ='OECD TTL - 2018'!AL26 -> 0
A25: D30: Other transport equipment | B25: nonroad vehicles 30 | C25: ='OECD TTL - 2018'!C27 -> 9.4 | D25: ='OECD TTL - 2018'!$D27*'SIOM from DLIM'!C164/SUM('SIOM from DLIM'!$C164:$D164) -> 0 | E25: ='OECD TTL - 2018'!$D27*'SIOM from DLIM'!D164/SUM('SIOM from DLIM'!$C164:$D164) -> 7.6 | F25: ='OECD TTL - 2018'!E27 -> 9.4 | G25: ='OECD TTL - 2018'!F27 -> 6.7 | H25: ='OECD TTL - 2018'!G27 -> 23.8 | I25: ='OECD TTL - 2018'!H27 -> 20.9 | J25: ='OECD TTL - 2018'!I27 -> 1.9 | K25: ='OECD TTL - 2018'!J27 -> 5.3 | L25: ='OECD TTL - 2018'!K27 -> 7.1 | M25: ='OECD TTL - 2018'!$L27*'SIOM from DLIM'!L164/SUM('SIOM from DLIM'!$L164:$M164) -> #DIV/0! | N25: ='OECD TTL - 2018'!$L27*'SIOM from DLIM'!M164/SUM('SIOM from DLIM'!$L164:$M164) -> #DIV/0! | O25: ='OECD TTL - 2018'!M27 -> 9.6 | P25: ='OECD TTL - 2018'!$N27*'SIOM from DLIM'!O164/SUM('SIOM from DLIM'!$O164:$P164) -> #DIV/0! | Q25: ='OECD TTL - 2018'!$N27*'SIOM from DLIM'!P164/SUM('SIOM from DLIM'!$O164:$P164) -> #DIV/0! | R25: ='OECD TTL - 2018'!$O27*'SIOM from DLIM'!Q164/SUM('SIOM from DLIM'!$Q164:$R164) -> 0 | S25: ='OECD TTL - 2018'!$O27*'SIOM from DLIM'!R164/SUM('SIOM from DLIM'!$Q164:$R164) -> 46.9 | T25: ='OECD TTL - 2018'!P27 -> 47 | U25: ='OECD TTL - 2018'!Q27 -> 104.7 | V25: ='OECD TTL - 2018'!R27 -> 79.4 | W25: ='OECD TTL - 2018'!S27 -> 71.2 | X25: ='OECD TTL - 2018'!T27 -> 456.6 | Y25: ='OECD TTL - 2018'!U27 -> 275.1 | Z25: ='OECD TTL - 2018'!V27 -> 27 | AA25: ='OECD TTL - 2018'!$W27*'SIOM from DLIM'!Z164/SUM('SIOM from DLIM'!$Z164:$AB164) -> 12.242567 | AB25: ='OECD TTL - 2018'!$W27*'SIOM from DLIM'!AA164/SUM('SIOM from DLIM'!$Z164:$AB164) -> 0.056489071 | AC25: ='OECD TTL - 2018'!$W27*'SIOM from DLIM'!AB164/SUM('SIOM from DLIM'!$Z164:$AB164) -> 0.00094398225 | AD25: ='OECD TTL - 2018'!X27 -> 153 | AE25: ='OECD TTL - 2018'!Y27 -> 25.6 | AF25: ='OECD TTL - 2018'!Z27 -> 68.9 | AG25: ='OECD TTL - 2018'!AA27 -> 3.7 | AH25: ='OECD TTL - 2018'!AB27 -> 1.7 | AI25: ='OECD TTL - 2018'!AC27 -> 7.1 | AJ25: ='OECD TTL - 2018'!AD27 -> 0.8 | AK25: ='OECD TTL - 2018'!AE27 -> 4.7 | ... AR25: ='OECD TTL - 2018'!AL27 -> 0
A26: D31T33: Other manufacturing; repair and installation of machinery and equipment | B26: other manufacturing 31T33 | C26: ='OECD TTL - 2018'!C28 -> 44.9 | D26: ='OECD TTL - 2018'!$D28*'SIOM from DLIM'!C165/SUM('SIOM from DLIM'!$C165:$D165) -> 0 | E26: ='OECD TTL - 2018'!$D28*'SIOM from DLIM'!D165/SUM('SIOM from DLIM'!$C165:$D165) -> 19.8 | F26: ='OECD TTL - 2018'!E28 -> 21.2 | G26: ='OECD TTL - 2018'!F28 -> 15.2 | H26: ='OECD TTL - 2018'!G28 -> 121.7 | I26: ='OECD TTL - 2018'!H28 -> 173.5 | J26: ='OECD TTL - 2018'!I28 -> 23 | K26: ='OECD TTL - 2018'!J28 -> 53.3 | L26: ='OECD TTL - 2018'!K28 -> 39.3 | M26: ='OECD TTL - 2018'!$L28*'SIOM from DLIM'!L165/SUM('SIOM from DLIM'!$L165:$M165) -> #DIV/0! | N26: ='OECD TTL - 2018'!$L28*'SIOM from DLIM'!M165/SUM('SIOM from DLIM'!$L165:$M165) -> #DIV/0! | O26: ='OECD TTL - 2018'!M28 -> 60.9 | P26: ='OECD TTL - 2018'!$N28*'SIOM from DLIM'!O165/SUM('SIOM from DLIM'!$O165:$P165) -> #DIV/0! | Q26: ='OECD TTL - 2018'!$N28*'SIOM from DLIM'!P165/SUM('SIOM from DLIM'!$O165:$P165) -> #DIV/0! | R26: ='OECD TTL - 2018'!$O28*'SIOM from DLIM'!Q165/SUM('SIOM from DLIM'!$Q165:$R165) -> 0 | S26: ='OECD TTL - 2018'!$O28*'SIOM from DLIM'!R165/SUM('SIOM from DLIM'!$Q165:$R165) -> 120.1 | T26: ='OECD TTL - 2018'!P28 -> 101.6 | U26: ='OECD TTL - 2018'!Q28 -> 207.2 | V26: ='OECD TTL - 2018'!R28 -> 95.2 | W26: ='OECD TTL - 2018'!S28 -> 91 | X26: ='OECD TTL - 2018'!T28 -> 478.8 | Y26: ='OECD TTL - 2018'!U28 -> 32.7 | Z26: ='OECD TTL - 2018'!V28 -> 131 | AA26: ='OECD TTL - 2018'!$W28*'SIOM from DLIM'!Z165/SUM('SIOM from DLIM'!$Z165:$AB165) -> 41.405869 | AB26: ='OECD TTL - 2018'!$W28*'SIOM from DLIM'!AA165/SUM('SIOM from DLIM'!$Z165:$AB165) -> 0.19095744 | AC26: ='OECD TTL - 2018'!$W28*'SIOM from DLIM'!AB165/SUM('SIOM from DLIM'!$Z165:$AB165) -> 0.0031735274 | AD26: ='OECD TTL - 2018'!X28 -> 327.4 | AE26: ='OECD TTL - 2018'!Y28 -> 89.3 | AF26: ='OECD TTL - 2018'!Z28 -> 146.4 | AG26: ='OECD TTL - 2018'!AA28 -> 25.1 | AH26: ='OECD TTL - 2018'!AB28 -> 13.1 | AI26: ='OECD TTL - 2018'!AC28 -> 25.6 | AJ26: ='OECD TTL - 2018'!AD28 -> 2.9 | AK26: ='OECD TTL - 2018'!AE28 -> 31.7 | ... AR26: ='OECD TTL - 2018'!AL28 -> 0
A27: electricity | C27: ='OECD TTL - 2018'!C$29*'SIOM from DLIM'!B166/SUM('SIOM from DLIM'!B$166:B$168) -> 37.648904 | D27: ='OECD TTL - 2018'!$D$29*'SIOM from DLIM'!C166/SUM('SIOM from DLIM'!$C$166:$D$168) -> 0 | E27: ='OECD TTL - 2018'!$D$29*'SIOM from DLIM'!D166/SUM('SIOM from DLIM'!$C$166:$D$168) -> 28.03999 | F27: ='OECD TTL - 2018'!E$29*'SIOM from DLIM'!D166/SUM('SIOM from DLIM'!D$166:D$168) -> 56.629334 | G27: ='OECD TTL - 2018'!F$29*'SIOM from DLIM'!E166/SUM('SIOM from DLIM'!E$166:E$168) -> 12.851086 | H27: ='OECD TTL - 2018'!G$29*'SIOM from DLIM'!F166/SUM('SIOM from DLIM'!F$166:F$168) -> 96.804761 | I27: ='OECD TTL - 2018'!H$29*'SIOM from DLIM'!G166/SUM('SIOM from DLIM'!G$166:G$168) -> 25.79275 | J27: ='OECD TTL - 2018'!I$29*'SIOM from DLIM'!H166/SUM('SIOM from DLIM'!H$166:H$168) -> #DIV/0! | K27: ='OECD TTL - 2018'!J$29*'SIOM from DLIM'!I166/SUM('SIOM from DLIM'!I$166:I$168) -> 47.914245 | L27: ='OECD TTL - 2018'!K$29*'SIOM from DLIM'!J166/SUM('SIOM from DLIM'!J$166:J$168) -> #DIV/0! | M27: ='OECD TTL - 2018'!$L$29*'SIOM from DLIM'!L166/SUM('SIOM from DLIM'!$L$166:$M$168) -> #DIV/0! | N27: ='OECD TTL - 2018'!$L$29*'SIOM from DLIM'!M166/SUM('SIOM from DLIM'!$L$166:$M$168) -> #DIV/0! | O27: ='OECD TTL - 2018'!M$29*'SIOM from DLIM'!L166/SUM('SIOM from DLIM'!L$166:L$168) -> #DIV/0! | P27: ='OECD TTL - 2018'!$N$29*'SIOM from DLIM'!O166/SUM('SIOM from DLIM'!$O$166:$P$168) -> #DIV/0! | Q27: ='OECD TTL - 2018'!$N$29*'SIOM from DLIM'!P166/SUM('SIOM from DLIM'!$O$166:$P$168) -> #DIV/0! | R27: ='OECD TTL - 2018'!$O$29*'SIOM from DLIM'!Q166/SUM('SIOM from DLIM'!$Q$166:$R$168) -> 0 | S27: ='OECD TTL - 2018'!$O$29*'SIOM from DLIM'!R166/SUM('SIOM from DLIM'!$Q$166:$R$168) -> 129.02127 | T27: ='OECD TTL - 2018'!P$29*'SIOM from DLIM'!O166/SUM('SIOM from DLIM'!O$166:O$168) -> #DIV/0! | U27: ='OECD TTL - 2018'!Q$29*'SIOM from DLIM'!P166/SUM('SIOM from DLIM'!P$166:P$168) -> #DIV/0! | V27: ='OECD TTL - 2018'!R$29*'SIOM from DLIM'!Q166/SUM('SIOM from DLIM'!Q$166:Q$168) -> #DIV/0! | W27: ='OECD TTL - 2018'!S$29*'SIOM from DLIM'!R166/SUM('SIOM from DLIM'!R$166:R$168) -> 23.001649 | X27: ='OECD TTL - 2018'!T$29*'SIOM from DLIM'!S166/SUM('SIOM from DLIM'!S$166:S$168) -> #DIV/0! | Y27: ='OECD TTL - 2018'!U$29*'SIOM from DLIM'!T166/SUM('SIOM from DLIM'!T$166:T$168) -> 10.990299 | Z27: ='OECD TTL - 2018'!V$29*'SIOM from DLIM'!U166/SUM('SIOM from DLIM'!U$166:U$168) -> #DIV/0! | AA27: ='OECD TTL - 2018'!$W$29*'SIOM from DLIM'!Z166/SUM('SIOM from DLIM'!$Z$166:$AB$168) -> 349.44581 | AB27: ='OECD TTL - 2018'!$W$29*'SIOM from DLIM'!AA166/SUM('SIOM from DLIM'!$Z$166:$AB$168) -> 1.6115447 | AC27: ='OECD TTL - 2018'!$W$29*'SIOM from DLIM'!AB166/SUM('SIOM from DLIM'!$Z$166:$AB$168) -> 0.026857977 | AD27: ='OECD TTL - 2018'!X$29*'SIOM from DLIM'!W166/SUM('SIOM from DLIM'!W$166:W$168) -> #DIV/0! | AE27: ='OECD TTL - 2018'!Y$29*'SIOM from DLIM'!X166/SUM('SIOM from DLIM'!X$166:X$168) -> #DIV/0! | AF27: ='OECD TTL - 2018'!Z$29*'SIOM from DLIM'!Y166/SUM('SIOM from DLIM'!Y$166:Y$168) -> 110.94966 | AG27: ='OECD TTL - 2018'!AA$29*'SIOM from DLIM'!Z166/SUM('SIOM from DLIM'!Z$166:Z$168) -> 64.673063 | AH27: ='OECD TTL - 2018'!AB$29*'SIOM from DLIM'!AA166/SUM('SIOM from DLIM'!AA$166:AA$168) -> 13.501454 | AI27: ='OECD TTL - 2018'!AC$29*'SIOM from DLIM'!AB166/SUM('SIOM from DLIM'!AB$166:AB$168) -> 16.63241 | AJ27: ='OECD TTL - 2018'!AD$29*'SIOM from DLIM'!AC166/SUM('SIOM from DLIM'!AC$166:AC$168) -> 2.1238345 | AK27: ='OECD TTL - 2018'!AE$29*'SIOM from DLIM'!AD166/SUM('SIOM from DLIM'!AD$166:AD$168) -> 50.315152 | ... AR27: ='OECD TTL - 2018'!AL$29*'SIOM from DLIM'!AK166/SUM('SIOM from DLIM'!AK$166:AK$168) -> #DIV/0!
A28: energy pipelines and gas processing 352T353 | B28: energy pipelines and gas processing 352T353 | C28: ='OECD TTL - 2018'!C$29*'SIOM from DLIM'!B167/SUM('SIOM from DLIM'!B$166:B$168) -> 3.3055627 | D28: ='OECD TTL - 2018'!$D$29*'SIOM from DLIM'!C167/SUM('SIOM from DLIM'!$C$166:$D$168) -> 0 | E28: ='OECD TTL - 2018'!$D$29*'SIOM from DLIM'!D167/SUM('SIOM from DLIM'!$C$166:$D$168) -> 2.4611409 | F28: ='OECD TTL - 2018'!E$29*'SIOM from DLIM'!D167/SUM('SIOM from DLIM'!D$166:D$168) -> 4.9705001 | G28: ='OECD TTL - 2018'!F$29*'SIOM from DLIM'!E167/SUM('SIOM from DLIM'!E$166:E$168) -> 1.1302086 | H28: ='OECD TTL - 2018'!G$29*'SIOM from DLIM'!F167/SUM('SIOM from DLIM'!F$166:F$168) -> 8.5353462 | I28: ='OECD TTL - 2018'!H$29*'SIOM from DLIM'!G167/SUM('SIOM from DLIM'!G$166:G$168) -> 2.2106184 | J28: ='OECD TTL - 2018'!I$29*'SIOM from DLIM'!H167/SUM('SIOM from DLIM'!H$166:H$168) -> #DIV/0! | K28: ='OECD TTL - 2018'!J$29*'SIOM from DLIM'!I167/SUM('SIOM from DLIM'!I$166:I$168) -> 4.1718391 | L28: ='OECD TTL - 2018'!K$29*'SIOM from DLIM'!J167/SUM('SIOM from DLIM'!J$166:J$168) -> #DIV/0! | M28: ='OECD TTL - 2018'!$L$29*'SIOM from DLIM'!L167/SUM('SIOM from DLIM'!$L$166:$M$168) -> #DIV/0! | N28: ='OECD TTL - 2018'!$L$29*'SIOM from DLIM'!M167/SUM('SIOM from DLIM'!$L$166:$M$168) -> #DIV/0! | O28: ='OECD TTL - 2018'!M$29*'SIOM from DLIM'!L167/SUM('SIOM from DLIM'!L$166:L$168) -> #DIV/0! | P28: ='OECD TTL - 2018'!$N$29*'SIOM from DLIM'!O167/SUM('SIOM from DLIM'!$O$166:$P$168) -> #DIV/0! | Q28: ='OECD TTL - 2018'!$N$29*'SIOM from DLIM'!P167/SUM('SIOM from DLIM'!$O$166:$P$168) -> #DIV/0! | R28: ='OECD TTL - 2018'!$O$29*'SIOM from DLIM'!Q167/SUM('SIOM from DLIM'!$Q$166:$R$168) -> 0 | S28: ='OECD TTL - 2018'!$O$29*'SIOM from DLIM'!R167/SUM('SIOM from DLIM'!$Q$166:$R$168) -> 10.96849 | T28: ='OECD TTL - 2018'!P$29*'SIOM from DLIM'!O167/SUM('SIOM from DLIM'!O$166:O$168) -> #DIV/0! | U28: ='OECD TTL - 2018'!Q$29*'SIOM from DLIM'!P167/SUM('SIOM from DLIM'!P$166:P$168) -> #DIV/0! | V28: ='OECD TTL - 2018'!R$29*'SIOM from DLIM'!Q167/SUM('SIOM from DLIM'!Q$166:Q$168) -> #DIV/0! | W28: ='OECD TTL - 2018'!S$29*'SIOM from DLIM'!R167/SUM('SIOM from DLIM'!R$166:R$168) -> 1.9554399 | X28: ='OECD TTL - 2018'!T$29*'SIOM from DLIM'!S167/SUM('SIOM from DLIM'!S$166:S$168) -> #DIV/0! | Y28: ='OECD TTL - 2018'!U$29*'SIOM from DLIM'!T167/SUM('SIOM from DLIM'!T$166:T$168) -> 0.96168623 | Z28: ='OECD TTL - 2018'!V$29*'SIOM from DLIM'!U167/SUM('SIOM from DLIM'!U$166:U$168) -> #DIV/0! | AA28: ='OECD TTL - 2018'!$W$29*'SIOM from DLIM'!Z167/SUM('SIOM from DLIM'!$Z$166:$AB$168) -> 30.64423 | AB28: ='OECD TTL - 2018'!$W$29*'SIOM from DLIM'!AA167/SUM('SIOM from DLIM'!$Z$166:$AB$168) -> 0.14114507 | AC28: ='OECD TTL - 2018'!$W$29*'SIOM from DLIM'!AB167/SUM('SIOM from DLIM'!$Z$166:$AB$168) -> 0.0023105782 | AD28: ='OECD TTL - 2018'!X$29*'SIOM from DLIM'!W167/SUM('SIOM from DLIM'!W$166:W$168) -> #DIV/0! | AE28: ='OECD TTL - 2018'!Y$29*'SIOM from DLIM'!X167/SUM('SIOM from DLIM'!X$166:X$168) -> #DIV/0! | AF28: ='OECD TTL - 2018'!Z$29*'SIOM from DLIM'!Y167/SUM('SIOM from DLIM'!Y$166:Y$168) -> 9.716955 | AG28: ='OECD TTL - 2018'!AA$29*'SIOM from DLIM'!Z167/SUM('SIOM from DLIM'!Z$166:Z$168) -> 5.6714263 | AH28: ='OECD TTL - 2018'!AB$29*'SIOM from DLIM'!AA167/SUM('SIOM from DLIM'!AA$166:AA$168) -> 1.1825074 | AI28: ='OECD TTL - 2018'!AC$29*'SIOM from DLIM'!AB167/SUM('SIOM from DLIM'!AB$166:AB$168) -> 1.4308778 | AJ28: ='OECD TTL - 2018'!AD$29*'SIOM from DLIM'!AC167/SUM('SIOM from DLIM'!AC$166:AC$168) -> 0.182862 | AK28: ='OECD TTL - 2018'!AE$29*'SIOM from DLIM'!AD167/SUM('SIOM from DLIM'!AD$166:AD$168) -> 4.2766073 | ... AR28: ='OECD TTL - 2018'!AL$29*'SIOM from DLIM'!AK167/SUM('SIOM from DLIM'!AK$166:AK$168) -> #DIV/0!
A29: water and waste 36T39 | B29: water and waste 36T39 | C29: ='OECD TTL - 2018'!C$29*'SIOM from DLIM'!B168/SUM('SIOM from DLIM'!B$166:B$168) -> 123.74553 | D29: ='OECD TTL - 2018'!$D$29*'SIOM from DLIM'!C168/SUM('SIOM from DLIM'!$C$166:$D$168) -> 0 | E29: ='OECD TTL - 2018'!$D$29*'SIOM from DLIM'!D168/SUM('SIOM from DLIM'!$C$166:$D$168) -> 91.998869 | F29: ='OECD TTL - 2018'!E$29*'SIOM from DLIM'!D168/SUM('SIOM from DLIM'!D$166:D$168) -> 185.80017 | G29: ='OECD TTL - 2018'!F$29*'SIOM from DLIM'!E168/SUM('SIOM from DLIM'!E$166:E$168) -> 43.718705 | H29: ='OECD TTL - 2018'!G$29*'SIOM from DLIM'!F168/SUM('SIOM from DLIM'!F$166:F$168) -> 321.75989 | I29: ='OECD TTL - 2018'!H$29*'SIOM from DLIM'!G168/SUM('SIOM from DLIM'!G$166:G$168) -> 75.996631 | J29: ='OECD TTL - 2018'!I$29*'SIOM from DLIM'!H168/SUM('SIOM from DLIM'!H$166:H$168) -> #DIV/0! | K29: ='OECD TTL - 2018'!J$29*'SIOM from DLIM'!I168/SUM('SIOM from DLIM'!I$166:I$168) -> 156.61392 | L29: ='OECD TTL - 2018'!K$29*'SIOM from DLIM'!J168/SUM('SIOM from DLIM'!J$166:J$168) -> #DIV/0! | M29: ='OECD TTL - 2018'!$L$29*'SIOM from DLIM'!L168/SUM('SIOM from DLIM'!$L$166:$M$168) -> #DIV/0! | N29: ='OECD TTL - 2018'!$L$29*'SIOM from DLIM'!M168/SUM('SIOM from DLIM'!$L$166:$M$168) -> #DIV/0! | O29: ='OECD TTL - 2018'!M$29*'SIOM from DLIM'!L168/SUM('SIOM from DLIM'!L$166:L$168) -> #DIV/0! | P29: ='OECD TTL - 2018'!$N$29*'SIOM from DLIM'!O168/SUM('SIOM from DLIM'!$O$166:$P$168) -> #DIV/0! | Q29: ='OECD TTL - 2018'!$N$29*'SIOM from DLIM'!P168/SUM('SIOM from DLIM'!$O$166:$P$168) -> #DIV/0! | R29: ='OECD TTL - 2018'!$O$29*'SIOM from DLIM'!Q168/SUM('SIOM from DLIM'!$Q$166:$R$168) -> 0 | S29: ='OECD TTL - 2018'!$O$29*'SIOM from DLIM'!R168/SUM('SIOM from DLIM'!$Q$166:$R$168) -> 419.81024 | T29: ='OECD TTL - 2018'!P$29*'SIOM from DLIM'!O168/SUM('SIOM from DLIM'!O$166:O$168) -> #DIV/0! | U29: ='OECD TTL - 2018'!Q$29*'SIOM from DLIM'!P168/SUM('SIOM from DLIM'!P$166:P$168) -> #DIV/0! | V29: ='OECD TTL - 2018'!R$29*'SIOM from DLIM'!Q168/SUM('SIOM from DLIM'!Q$166:Q$168) -> #DIV/0! | W29: ='OECD TTL - 2018'!S$29*'SIOM from DLIM'!R168/SUM('SIOM from DLIM'!R$166:R$168) -> 74.842911 | X29: ='OECD TTL - 2018'!T$29*'SIOM from DLIM'!S168/SUM('SIOM from DLIM'!S$166:S$168) -> #DIV/0! | Y29: ='OECD TTL - 2018'!U$29*'SIOM from DLIM'!T168/SUM('SIOM from DLIM'!T$166:T$168) -> 36.048014 | Z29: ='OECD TTL - 2018'!V$29*'SIOM from DLIM'!U168/SUM('SIOM from DLIM'!U$166:U$168) -> #DIV/0! | AA29: ='OECD TTL - 2018'!$W$29*'SIOM from DLIM'!Z168/SUM('SIOM from DLIM'!$Z$166:$AB$168) -> 1146.3328 | AB29: ='OECD TTL - 2018'!$W$29*'SIOM from DLIM'!AA168/SUM('SIOM from DLIM'!$Z$166:$AB$168) -> 5.2895991 | AC29: ='OECD TTL - 2018'!$W$29*'SIOM from DLIM'!AB168/SUM('SIOM from DLIM'!$Z$166:$AB$168) -> 0.10566705 | AD29: ='OECD TTL - 2018'!X$29*'SIOM from DLIM'!W168/SUM('SIOM from DLIM'!W$166:W$168) -> #DIV/0! | AE29: ='OECD TTL - 2018'!Y$29*'SIOM from DLIM'!X168/SUM('SIOM from DLIM'!X$166:X$168) -> #DIV/0! | AF29: ='OECD TTL - 2018'!Z$29*'SIOM from DLIM'!Y168/SUM('SIOM from DLIM'!Y$166:Y$168) -> 364.03339 | AG29: ='OECD TTL - 2018'!AA$29*'SIOM from DLIM'!Z168/SUM('SIOM from DLIM'!Z$166:Z$168) -> 212.15551 | AH29: ='OECD TTL - 2018'!AB$29*'SIOM from DLIM'!AA168/SUM('SIOM from DLIM'!AA$166:AA$168) -> 44.316039 | AI29: ='OECD TTL - 2018'!AC$29*'SIOM from DLIM'!AB168/SUM('SIOM from DLIM'!AB$166:AB$168) -> 65.436712 | AJ29: ='OECD TTL - 2018'!AD$29*'SIOM from DLIM'!AC168/SUM('SIOM from DLIM'!AC$166:AC$168) -> 6.8933035 | AK29: ='OECD TTL - 2018'!AE$29*'SIOM from DLIM'!AD168/SUM('SIOM from DLIM'!AD$166:AD$168) -> 168.70824 | ... AR29: ='OECD TTL - 2018'!AL$29*'SIOM from DLIM'!AK168/SUM('SIOM from DLIM'!AK$166:AK$168) -> #DIV/0!
A30: D41T43: Construction | B30: construction 41T43 | C30: ='OECD TTL - 2018'!C30 -> 67.9 | D30: ='OECD TTL - 2018'!$D30*'SIOM from DLIM'!C169/SUM('SIOM from DLIM'!$C169:$D169) -> 216.1 | E30: ='OECD TTL - 2018'!$D30*'SIOM from DLIM'!D169/SUM('SIOM from DLIM'!$C169:$D169) -> 0 | F30: ='OECD TTL - 2018'!E30 -> 99.2 | G30: ='OECD TTL - 2018'!F30 -> 167.5 | H30: ='OECD TTL - 2018'!G30 -> 26.6 | I30: ='OECD TTL - 2018'!H30 -> 4.8 | J30: ='OECD TTL - 2018'!I30 -> 2.7 | K30: ='OECD TTL - 2018'!J30 -> 10.8 | L30: ='OECD TTL - 2018'!K30 -> 28 | M30: ='OECD TTL - 2018'!$L30*'SIOM from DLIM'!L169/SUM('SIOM from DLIM'!$L169:$M169) -> 26.780161 | N30: ='OECD TTL - 2018'!$L30*'SIOM from DLIM'!M169/SUM('SIOM from DLIM'!$L169:$M169) -> 4.5198387 | O30: ='OECD TTL - 2018'!M30 -> 11.2 | P30: ='OECD TTL - 2018'!$N30*'SIOM from DLIM'!O169/SUM('SIOM from DLIM'!$O169:$P169) -> 14.433452 | Q30: ='OECD TTL - 2018'!$N30*'SIOM from DLIM'!P169/SUM('SIOM from DLIM'!$O169:$P169) -> 7.0665482 | R30: ='OECD TTL - 2018'!$O30*'SIOM from DLIM'!Q169/SUM('SIOM from DLIM'!$Q169:$R169) -> 17.8 | S30: ='OECD TTL - 2018'!$O30*'SIOM from DLIM'!R169/SUM('SIOM from DLIM'!$Q169:$R169) -> 0 | T30: ='OECD TTL - 2018'!P30 -> 14.7 | U30: ='OECD TTL - 2018'!Q30 -> 29.1 | V30: ='OECD TTL - 2018'!R30 -> 10.8 | W30: ='OECD TTL - 2018'!S30 -> 13.6 | X30: ='OECD TTL - 2018'!T30 -> 46.9 | Y30: ='OECD TTL - 2018'!U30 -> 4.1 | Z30: ='OECD TTL - 2018'!V30 -> 15.7 | AA30: ='OECD TTL - 2018'!$W30*'SIOM from DLIM'!Z169/SUM('SIOM from DLIM'!$Z169:$AB169) -> #DIV/0! | AB30: ='OECD TTL - 2018'!$W30*'SIOM from DLIM'!AA169/SUM('SIOM from DLIM'!$Z169:$AB169) -> #DIV/0! | AC30: ='OECD TTL - 2018'!$W30*'SIOM from DLIM'!AB169/SUM('SIOM from DLIM'!$Z169:$AB169) -> #DIV/0! | AD30: ='OECD TTL - 2018'!X30 -> 1128.9 | AE30: ='OECD TTL - 2018'!Y30 -> 101.3 | AF30: ='OECD TTL - 2018'!Z30 -> 130 | AG30: ='OECD TTL - 2018'!AA30 -> 25.2 | AH30: ='OECD TTL - 2018'!AB30 -> 9.4 | AI30: ='OECD TTL - 2018'!AC30 -> 26 | AJ30: ='OECD TTL - 2018'!AD30 -> 1.9 | AK30: ='OECD TTL - 2018'!AE30 -> 66.1 | ... AR30: ='OECD TTL - 2018'!AL30 -> 0
A31: D45T47: Wholesale and retail trade; repair of motor vehicles | C31: ='OECD TTL - 2018'!C31 -> 4729.5 | D31: ='OECD TTL - 2018'!$D31*'SIOM from DLIM'!C170/SUM('SIOM from DLIM'!$C170:$D170) -> 475 | E31: ='OECD TTL - 2018'!$D31*'SIOM from DLIM'!D170/SUM('SIOM from DLIM'!$C170:$D170) -> 0 | F31: ='OECD TTL - 2018'!E31 -> 783.9 | G31: ='OECD TTL - 2018'!F31 -> 429.4 | H31: ='OECD TTL - 2018'!G31 -> 20136.8 | I31: ='OECD TTL - 2018'!H31 -> 3266.7 | J31: ='OECD TTL - 2018'!I31 -> 525.2 | K31: ='OECD TTL - 2018'!J31 -> 2660.6 | L31: ='OECD TTL - 2018'!K31 -> 4350.3 | M31: ='OECD TTL - 2018'!$L31*'SIOM from DLIM'!L170/SUM('SIOM from DLIM'!$L170:$M170) -> 9121.6635 | N31: ='OECD TTL - 2018'!$L31*'SIOM from DLIM'!M170/SUM('SIOM from DLIM'!$L170:$M170) -> 1537.2365 | O31: ='OECD TTL - 2018'!M31 -> 3526.8 | P31: ='OECD TTL - 2018'!$N31*'SIOM from DLIM'!O170/SUM('SIOM from DLIM'!$O170:$P170) -> 1540.9374 | Q31: ='OECD TTL - 2018'!$N31*'SIOM from DLIM'!P170/SUM('SIOM from DLIM'!$O170:$P170) -> 753.8626 | R31: ='OECD TTL - 2018'!$O31*'SIOM from DLIM'!Q170/SUM('SIOM from DLIM'!$Q170:$R170) -> 3644 | S31: ='OECD TTL - 2018'!$O31*'SIOM from DLIM'!R170/SUM('SIOM from DLIM'!$Q170:$R170) -> 0 | T31: ='OECD TTL - 2018'!P31 -> 2833.5 | U31: ='OECD TTL - 2018'!Q31 -> 9371.3 | V31: ='OECD TTL - 2018'!R31 -> 3552.8 | W31: ='OECD TTL - 2018'!S31 -> 2672.6 | X31: ='OECD TTL - 2018'!T31 -> 15658.3 | Y31: ='OECD TTL - 2018'!U31 -> 1189 | Z31: ='OECD TTL - 2018'!V31 -> 2722.9 | AA31: ='OECD TTL - 2018'!$W31*'SIOM from DLIM'!Z170/SUM('SIOM from DLIM'!$Z170:$AB170) -> #DIV/0! | AB31: ='OECD TTL - 2018'!$W31*'SIOM from DLIM'!AA170/SUM('SIOM from DLIM'!$Z170:$AB170) -> #DIV/0! | AC31: ='OECD TTL - 2018'!$W31*'SIOM from DLIM'!AB170/SUM('SIOM from DLIM'!$Z170:$AB170) -> #DIV/0! | AD31: ='OECD TTL - 2018'!X31 -> 11208.3 | AE31: ='OECD TTL - 2018'!Y31 -> 22740.8 | AF31: ='OECD TTL - 2018'!Z31 -> 8601 | AG31: ='OECD TTL - 2018'!AA31 -> 2740.7 | AH31: ='OECD TTL - 2018'!AB31 -> 1450.8 | AI31: ='OECD TTL - 2018'!AC31 -> 1923.4 | AJ31: ='OECD TTL - 2018'!AD31 -> 435 | AK31: ='OECD TTL - 2018'!AE31 -> 2495.7 | ... AR31: ='OECD TTL - 2018'!AL31 -> 0
A32: D49T53: Transportation and storage | C32: ='OECD TTL - 2018'!C32 -> 1250.6 | D32: ='OECD TTL - 2018'!$D32*'SIOM from DLIM'!C171/SUM('SIOM from DLIM'!$C171:$D171) -> 258 | E32: ='OECD TTL - 2018'!$D32*'SIOM from DLIM'!D171/SUM('SIOM from DLIM'!$C171:$D171) -> 0 | F32: ='OECD TTL - 2018'!E32 -> 410.3 | G32: ='OECD TTL - 2018'!F32 -> 196.9 | H32: ='OECD TTL - 2018'!G32 -> 4910.7 | I32: ='OECD TTL - 2018'!H32 -> 700.5 | J32: ='OECD TTL - 2018'!I32 -> 158.6 | K32: ='OECD TTL - 2018'!J32 -> 686.1 | L32: ='OECD TTL - 2018'!K32 -> 2002.9 | M32: ='OECD TTL - 2018'!$L32*'SIOM from DLIM'!L171/SUM('SIOM from DLIM'!$L171:$M171) -> 2165.6702 | N32: ='OECD TTL - 2018'!$L32*'SIOM from DLIM'!M171/SUM('SIOM from DLIM'!$L171:$M171) -> 364.72984 | O32: ='OECD TTL - 2018'!M32 -> 758.8 | P32: ='OECD TTL - 2018'!$N32*'SIOM from DLIM'!O171/SUM('SIOM from DLIM'!$O171:$P171) -> 678.70243 | Q32: ='OECD TTL - 2018'!$N32*'SIOM from DLIM'!P171/SUM('SIOM from DLIM'!$O171:$P171) -> 332.09757 | R32: ='OECD TTL - 2018'!$O32*'SIOM from DLIM'!Q171/SUM('SIOM from DLIM'!$Q171:$R171) -> 1802.5 | S32: ='OECD TTL - 2018'!$O32*'SIOM from DLIM'!R171/SUM('SIOM from DLIM'!$Q171:$R171) -> 0 | T32: ='OECD TTL - 2018'!P32 -> 881.1 | U32: ='OECD TTL - 2018'!Q32 -> 2286.4 | V32: ='OECD TTL - 2018'!R32 -> 860.7 | W32: ='OECD TTL - 2018'!S32 -> 725.3 | X32: ='OECD TTL - 2018'!T32 -> 6933.9 | Y32: ='OECD TTL - 2018'!U32 -> 359.5 | Z32: ='OECD TTL - 2018'!V32 -> 742.2 | AA32: ='OECD TTL - 2018'!$W32*'SIOM from DLIM'!Z171/SUM('SIOM from DLIM'!$Z171:$AB171) -> #DIV/0! | AB32: ='OECD TTL - 2018'!$W32*'SIOM from DLIM'!AA171/SUM('SIOM from DLIM'!$Z171:$AB171) -> #DIV/0! | AC32: ='OECD TTL - 2018'!$W32*'SIOM from DLIM'!AB171/SUM('SIOM from DLIM'!$Z171:$AB171) -> #DIV/0! | AD32: ='OECD TTL - 2018'!X32 -> 3175.2 | AE32: ='OECD TTL - 2018'!Y32 -> 2524.7 | AF32: ='OECD TTL - 2018'!Z32 -> 8040.3 | AG32: ='OECD TTL - 2018'!AA32 -> 578 | AH32: ='OECD TTL - 2018'!AB32 -> 172.3 | AI32: ='OECD TTL - 2018'!AC32 -> 255.9 | AJ32: ='OECD TTL - 2018'!AD32 -> 35.8 | AK32: ='OECD TTL - 2018'!AE32 -> 746 | ... AR32: ='OECD TTL - 2018'!AL32 -> 0
A33: D55T56: Accomodation and food services | C33: ='OECD TTL - 2018'!C33 -> 8.1 | D33: ='OECD TTL - 2018'!$D33*'SIOM from DLIM'!C172/SUM('SIOM from DLIM'!$C172:$D172) -> 0 | E33: ='OECD TTL - 2018'!$D33*'SIOM from DLIM'!D172/SUM('SIOM from DLIM'!$C172:$D172) -> 3.8 | F33: ='OECD TTL - 2018'!E33 -> 2.9 | G33: ='OECD TTL - 2018'!F33 -> 5.9 | H33: ='OECD TTL - 2018'!G33 -> 33.4 | I33: ='OECD TTL - 2018'!H33 -> 7.1 | J33: ='OECD TTL - 2018'!I33 -> 1.7 | K33: ='OECD TTL - 2018'!J33 -> 6.6 | L33: ='OECD TTL - 2018'!K33 -> 6.6 | M33: ='OECD TTL - 2018'!$L33*'SIOM from DLIM'!L172/SUM('SIOM from DLIM'!$L172:$M172) -> #DIV/0! | N33: ='OECD TTL - 2018'!$L33*'SIOM from DLIM'!M172/SUM('SIOM from DLIM'!$L172:$M172) -> #DIV/0! | O33: ='OECD TTL - 2018'!M33 -> 6.9 | P33: ='OECD TTL - 2018'!$N33*'SIOM from DLIM'!O172/SUM('SIOM from DLIM'!$O172:$P172) -> #DIV/0! | Q33: ='OECD TTL - 2018'!$N33*'SIOM from DLIM'!P172/SUM('SIOM from DLIM'!$O172:$P172) -> #DIV/0! | R33: ='OECD TTL - 2018'!$O33*'SIOM from DLIM'!Q172/SUM('SIOM from DLIM'!$Q172:$R172) -> 0 | S33: ='OECD TTL - 2018'!$O33*'SIOM from DLIM'!R172/SUM('SIOM from DLIM'!$Q172:$R172) -> 9 | T33: ='OECD TTL - 2018'!P33 -> 10.2 | U33: ='OECD TTL - 2018'!Q33 -> 18.2 | V33: ='OECD TTL - 2018'!R33 -> 7 | W33: ='OECD TTL - 2018'!S33 -> 8.3 | X33: ='OECD TTL - 2018'!T33 -> 45.1 | Y33: ='OECD TTL - 2018'!U33 -> 7.6 | Z33: ='OECD TTL - 2018'!V33 -> 10.7 | AA33: ='OECD TTL - 2018'!$W33*'SIOM from DLIM'!Z172/SUM('SIOM from DLIM'!$Z172:$AB172) -> 13.138358 | AB33: ='OECD TTL - 2018'!$W33*'SIOM from DLIM'!AA172/SUM('SIOM from DLIM'!$Z172:$AB172) -> 0.060622941 | AC33: ='OECD TTL - 2018'!$W33*'SIOM from DLIM'!AB172/SUM('SIOM from DLIM'!$Z172:$AB172) -> 0.0010192594 | AD33: ='OECD TTL - 2018'!X33 -> 45.8 | AE33: ='OECD TTL - 2018'!Y33 -> 105.2 | AF33: ='OECD TTL - 2018'!Z33 -> 115.9 | AG33: ='OECD TTL - 2018'!AA33 -> 38.6 | AH33: ='OECD TTL - 2018'!AB33 -> 15.3 | AI33: ='OECD TTL - 2018'!AC33 -> 8.8 | AJ33: ='OECD TTL - 2018'!AD33 -> 5.5 | AK33: ='OECD TTL - 2018'!AE33 -> 89.8 | ... AR33: ='OECD TTL - 2018'!AL33 -> 0
A34: D58T60: Publishing, audiovisual and broadcasting activities | C34: ='OECD TTL - 2018'!C34 -> 12.6 | D34: ='OECD TTL - 2018'!$D34*'SIOM from DLIM'!C173/SUM('SIOM from DLIM'!$C173:$D173) -> 0 | E34: ='OECD TTL - 2018'!$D34*'SIOM from DLIM'!D173/SUM('SIOM from DLIM'!$C173:$D173) -> 6.8 | F34: ='OECD TTL - 2018'!E34 -> 4.9 | G34: ='OECD TTL - 2018'!F34 -> 4.9 | H34: ='OECD TTL - 2018'!G34 -> 153.5 | I34: ='OECD TTL - 2018'!H34 -> 8.7 | J34: ='OECD TTL - 2018'!I34 -> 2.6 | K34: ='OECD TTL - 2018'!J34 -> 45.2 | L34: ='OECD TTL - 2018'!K34 -> 23.6 | M34: ='OECD TTL - 2018'!$L34*'SIOM from DLIM'!L173/SUM('SIOM from DLIM'!$L173:$M173) -> #DIV/0! | N34: ='OECD TTL - 2018'!$L34*'SIOM from DLIM'!M173/SUM('SIOM from DLIM'!$L173:$M173) -> #DIV/0! | O34: ='OECD TTL - 2018'!M34 -> 11.4 | P34: ='OECD TTL - 2018'!$N34*'SIOM from DLIM'!O173/SUM('SIOM from DLIM'!$O173:$P173) -> #DIV/0! | Q34: ='OECD TTL - 2018'!$N34*'SIOM from DLIM'!P173/SUM('SIOM from DLIM'!$O173:$P173) -> #DIV/0! | R34: ='OECD TTL - 2018'!$O34*'SIOM from DLIM'!Q173/SUM('SIOM from DLIM'!$Q173:$R173) -> 0 | S34: ='OECD TTL - 2018'!$O34*'SIOM from DLIM'!R173/SUM('SIOM from DLIM'!$Q173:$R173) -> 5.6 | T34: ='OECD TTL - 2018'!P34 -> 14.6 | U34: ='OECD TTL - 2018'!Q34 -> 77.3 | V34: ='OECD TTL - 2018'!R34 -> 14.6 | W34: ='OECD TTL - 2018'!S34 -> 15.2 | X34: ='OECD TTL - 2018'!T34 -> 82.7 | Y34: ='OECD TTL - 2018'!U34 -> 11.3 | Z34: ='OECD TTL - 2018'!V34 -> 23.5 | AA34: ='OECD TTL - 2018'!$W34*'SIOM from DLIM'!Z173/SUM('SIOM from DLIM'!$Z173:$AB173) -> 24.584424 | AB34: ='OECD TTL - 2018'!$W34*'SIOM from DLIM'!AA173/SUM('SIOM from DLIM'!$Z173:$AB173) -> 0.11360726 | AC34: ='OECD TTL - 2018'!$W34*'SIOM from DLIM'!AB173/SUM('SIOM from DLIM'!$Z173:$AB173) -> 0.0019686689 | AD34: ='OECD TTL - 2018'!X34 -> 62.4 | AE34: ='OECD TTL - 2018'!Y34 -> 302.5 | AF34: ='OECD TTL - 2018'!Z34 -> 126.6 | AG34: ='OECD TTL - 2018'!AA34 -> 46.4 | AH34: ='OECD TTL - 2018'!AB34 -> 768.4 | AI34: ='OECD TTL - 2018'!AC34 -> 117.8 | AJ34: ='OECD TTL - 2018'!AD34 -> 22.6 | AK34: ='OECD TTL - 2018'!AE34 -> 208.9 | ... AR34: ='OECD TTL - 2018'!AL34 -> 0
A35: D61: Telecommunications | C35: ='OECD TTL - 2018'!C35 -> 36.4 | D35: ='OECD TTL - 2018'!$D35*'SIOM from DLIM'!C174/SUM('SIOM from DLIM'!$C174:$D174) -> 0 | E35: ='OECD TTL - 2018'!$D35*'SIOM from DLIM'!D174/SUM('SIOM from DLIM'!$C174:$D174) -> 8.9 | F35: ='OECD TTL - 2018'!E35 -> 20.4 | G35: ='OECD TTL - 2018'!F35 -> 15.6 | H35: ='OECD TTL - 2018'!G35 -> 86.8 | I35: ='OECD TTL - 2018'!H35 -> 30.3 | J35: ='OECD TTL - 2018'!I35 -> 5.6 | K35: ='OECD TTL - 2018'!J35 -> 21.8 | L35: ='OECD TTL - 2018'!K35 -> 37.4 | M35: ='OECD TTL - 2018'!$L35*'SIOM from DLIM'!L174/SUM('SIOM from DLIM'!$L174:$M174) -> #DIV/0! | N35: ='OECD TTL - 2018'!$L35*'SIOM from DLIM'!M174/SUM('SIOM from DLIM'!$L174:$M174) -> #DIV/0! | O35: ='OECD TTL - 2018'!M35 -> 20.5 | P35: ='OECD TTL - 2018'!$N35*'SIOM from DLIM'!O174/SUM('SIOM from DLIM'!$O174:$P174) -> #DIV/0! | Q35: ='OECD TTL - 2018'!$N35*'SIOM from DLIM'!P174/SUM('SIOM from DLIM'!$O174:$P174) -> #DIV/0! | R35: ='OECD TTL - 2018'!$O35*'SIOM from DLIM'!Q174/SUM('SIOM from DLIM'!$Q174:$R174) -> 0 | S35: ='OECD TTL - 2018'!$O35*'SIOM from DLIM'!R174/SUM('SIOM from DLIM'!$Q174:$R174) -> 19.3 | T35: ='OECD TTL - 2018'!P35 -> 37 | U35: ='OECD TTL - 2018'!Q35 -> 127.3 | V35: ='OECD TTL - 2018'!R35 -> 26.9 | W35: ='OECD TTL - 2018'!S35 -> 36.8 | X35: ='OECD TTL - 2018'!T35 -> 159.2 | Y35: ='OECD TTL - 2018'!U35 -> 21.6 | Z35: ='OECD TTL - 2018'!V35 -> 40.6 | AA35: ='OECD TTL - 2018'!$W35*'SIOM from DLIM'!Z174/SUM('SIOM from DLIM'!$Z174:$AB174) -> 66.388609 | AB35: ='OECD TTL - 2018'!$W35*'SIOM from DLIM'!AA174/SUM('SIOM from DLIM'!$Z174:$AB174) -> 0.30626903 | AC35: ='OECD TTL - 2018'!$W35*'SIOM from DLIM'!AB174/SUM('SIOM from DLIM'!$Z174:$AB174) -> 0.0051218157 | AD35: ='OECD TTL - 2018'!X35 -> 125 | AE35: ='OECD TTL - 2018'!Y35 -> 419.9 | AF35: ='OECD TTL - 2018'!Z35 -> 378.2 | AG35: ='OECD TTL - 2018'!AA35 -> 85.2 | AH35: ='OECD TTL - 2018'!AB35 -> 234.3 | AI35: ='OECD TTL - 2018'!AC35 -> 1996.9 | AJ35: ='OECD TTL - 2018'!AD35 -> 46.6 | AK35: ='OECD TTL - 2018'!AE35 -> 700.9 | ... AR35: ='OECD TTL - 2018'!AL35 -> 0
A36: D62T63: IT and other information services | C36: ='OECD TTL - 2018'!C36 -> 7.8 | D36: ='OECD TTL - 2018'!$D36*'SIOM from DLIM'!C175/SUM('SIOM from DLIM'!$C175:$D175) -> 0 | E36: ='OECD TTL - 2018'!$D36*'SIOM from DLIM'!D175/SUM('SIOM from DLIM'!$C175:$D175) -> 2.8 | F36: ='OECD TTL - 2018'!E36 -> 2.6 | G36: ='OECD TTL - 2018'!F36 -> 1.7 | H36: ='OECD TTL - 2018'!G36 -> 33.2 | I36: ='OECD TTL - 2018'!H36 -> 10.6 | J36: ='OECD TTL - 2018'!I36 -> 1.3 | K36: ='OECD TTL - 2018'!J36 -> 9.9 | L36: ='OECD TTL - 2018'!K36 -> 11.6 | M36: ='OECD TTL - 2018'!$L36*'SIOM from DLIM'!L175/SUM('SIOM from DLIM'!$L175:$M175) -> #DIV/0! | N36: ='OECD TTL - 2018'!$L36*'SIOM from DLIM'!M175/SUM('SIOM from DLIM'!$L175:$M175) -> #DIV/0! | O36: ='OECD TTL - 2018'!M36 -> 11.7 | P36: ='OECD TTL - 2018'!$N36*'SIOM from DLIM'!O175/SUM('SIOM from DLIM'!$O175:$P175) -> #DIV/0! | Q36: ='OECD TTL - 2018'!$N36*'SIOM from DLIM'!P175/SUM('SIOM from DLIM'!$O175:$P175) -> #DIV/0! | R36: ='OECD TTL - 2018'!$O36*'SIOM from DLIM'!Q175/SUM('SIOM from DLIM'!$Q175:$R175) -> 0 | S36: ='OECD TTL - 2018'!$O36*'SIOM from DLIM'!R175/SUM('SIOM from DLIM'!$Q175:$R175) -> 8.5 | T36: ='OECD TTL - 2018'!P36 -> 10.3 | U36: ='OECD TTL - 2018'!Q36 -> 60.5 | V36: ='OECD TTL - 2018'!R36 -> 14.3 | W36: ='OECD TTL - 2018'!S36 -> 12.3 | X36: ='OECD TTL - 2018'!T36 -> 59.7 | Y36: ='OECD TTL - 2018'!U36 -> 4.9 | Z36: ='OECD TTL - 2018'!V36 -> 10.7 | AA36: ='OECD TTL - 2018'!$W36*'SIOM from DLIM'!Z175/SUM('SIOM from DLIM'!$Z175:$AB175) -> 9.057495 | AB36: ='OECD TTL - 2018'!$W36*'SIOM from DLIM'!AA175/SUM('SIOM from DLIM'!$Z175:$AB175) -> 0.041798751 | AC36: ='OECD TTL - 2018'!$W36*'SIOM from DLIM'!AB175/SUM('SIOM from DLIM'!$Z175:$AB175) -> 0.00070620409 | AD36: ='OECD TTL - 2018'!X36 -> 34.1 | AE36: ='OECD TTL - 2018'!Y36 -> 43.8 | AF36: ='OECD TTL - 2018'!Z36 -> 38.4 | AG36: ='OECD TTL - 2018'!AA36 -> 8.1 | AH36: ='OECD TTL - 2018'!AB36 -> 13.5 | AI36: ='OECD TTL - 2018'!AC36 -> 18.6 | AJ36: ='OECD TTL - 2018'!AD36 -> 11.7 | AK36: ='OECD TTL - 2018'!AE36 -> 72.1 | ... AR36: ='OECD TTL - 2018'!AL36 -> 0
A37: D64T66: Financial and insurance activities | C37: ='OECD TTL - 2018'!C37 -> 209.5 | D37: ='OECD TTL - 2018'!$D37*'SIOM from DLIM'!C176/SUM('SIOM from DLIM'!$C176:$D176) -> 92.9 | E37: ='OECD TTL - 2018'!$D37*'SIOM from DLIM'!D176/SUM('SIOM from DLIM'!$C176:$D176) -> 0 | F37: ='OECD TTL - 2018'!E37 -> 75.4 | G37: ='OECD TTL - 2018'!F37 -> 41.1 | H37: ='OECD TTL - 2018'!G37 -> 284.7 | I37: ='OECD TTL - 2018'!H37 -> 84.1 | J37: ='OECD TTL - 2018'!I37 -> 21.7 | K37: ='OECD TTL - 2018'!J37 -> 77 | L37: ='OECD TTL - 2018'!K37 -> 155.7 | M37: ='OECD TTL - 2018'!$L37*'SIOM from DLIM'!L176/SUM('SIOM from DLIM'!$L176:$M176) -> 212.30288 | N37: ='OECD TTL - 2018'!$L37*'SIOM from DLIM'!M176/SUM('SIOM from DLIM'!$L176:$M176) -> 35.697124 | O37: ='OECD TTL - 2018'!M37 -> 66.2 | P37: ='OECD TTL - 2018'!$N37*'SIOM from DLIM'!O176/SUM('SIOM from DLIM'!$O176:$P176) -> 65.505947 | Q37: ='OECD TTL - 2018'!$N37*'SIOM from DLIM'!P176/SUM('SIOM from DLIM'!$O176:$P176) -> 32.094053 | R37: ='OECD TTL - 2018'!$O37*'SIOM from DLIM'!Q176/SUM('SIOM from DLIM'!$Q176:$R176) -> 197.5 | S37: ='OECD TTL - 2018'!$O37*'SIOM from DLIM'!R176/SUM('SIOM from DLIM'!$Q176:$R176) -> 0 | T37: ='OECD TTL - 2018'!P37 -> 107.3 | U37: ='OECD TTL - 2018'!Q37 -> 237 | V37: ='OECD TTL - 2018'!R37 -> 79.8 | W37: ='OECD TTL - 2018'!S37 -> 92.5 | X37: ='OECD TTL - 2018'!T37 -> 509 | Y37: ='OECD TTL - 2018'!U37 -> 79.3 | Z37: ='OECD TTL - 2018'!V37 -> 112.4 | AA37: ='OECD TTL - 2018'!$W37*'SIOM from DLIM'!Z176/SUM('SIOM from DLIM'!$Z176:$AB176) -> #DIV/0! | AB37: ='OECD TTL - 2018'!$W37*'SIOM from DLIM'!AA176/SUM('SIOM from DLIM'!$Z176:$AB176) -> #DIV/0! | AC37: ='OECD TTL - 2018'!$W37*'SIOM from DLIM'!AB176/SUM('SIOM from DLIM'!$Z176:$AB176) -> #DIV/0! | AD37: ='OECD TTL - 2018'!X37 -> 490.8 | AE37: ='OECD TTL - 2018'!Y37 -> 884.8 | AF37: ='OECD TTL - 2018'!Z37 -> 902.9 | AG37: ='OECD TTL - 2018'!AA37 -> 158.7 | AH37: ='OECD TTL - 2018'!AB37 -> 78.1 | AI37: ='OECD TTL - 2018'!AC37 -> 108.9 | AJ37: ='OECD TTL - 2018'!AD37 -> 24.8 | AK37: ='OECD TTL - 2018'!AE37 -> 7397.6 | ... AR37: ='OECD TTL - 2018'!AL37 -> 0
A38: D68: Real estate activities | C38: ='OECD TTL - 2018'!C38 -> 95.5 | D38: ='OECD TTL - 2018'!$D38*'SIOM from DLIM'!C177/SUM('SIOM from DLIM'!$C177:$D177) -> 0 | E38: ='OECD TTL - 2018'!$D38*'SIOM from DLIM'!D177/SUM('SIOM from DLIM'!$C177:$D177) -> 76.7 | F38: ='OECD TTL - 2018'!E38 -> 19.7 | G38: ='OECD TTL - 2018'!F38 -> 13.7 | H38: ='OECD TTL - 2018'!G38 -> 396.8 | I38: ='OECD TTL - 2018'!H38 -> 159.9 | J38: ='OECD TTL - 2018'!I38 -> 22.8 | K38: ='OECD TTL - 2018'!J38 -> 106 | L38: ='OECD TTL - 2018'!K38 -> 118.8 | M38: ='OECD TTL - 2018'!$L38*'SIOM from DLIM'!L177/SUM('SIOM from DLIM'!$L177:$M177) -> #DIV/0! | N38: ='OECD TTL - 2018'!$L38*'SIOM from DLIM'!M177/SUM('SIOM from DLIM'!$L177:$M177) -> #DIV/0! | O38: ='OECD TTL - 2018'!M38 -> 101.7 | P38: ='OECD TTL - 2018'!$N38*'SIOM from DLIM'!O177/SUM('SIOM from DLIM'!$O177:$P177) -> #DIV/0! | Q38: ='OECD TTL - 2018'!$N38*'SIOM from DLIM'!P177/SUM('SIOM from DLIM'!$O177:$P177) -> #DIV/0! | R38: ='OECD TTL - 2018'!$O38*'SIOM from DLIM'!Q177/SUM('SIOM from DLIM'!$Q177:$R177) -> 0 | S38: ='OECD TTL - 2018'!$O38*'SIOM from DLIM'!R177/SUM('SIOM from DLIM'!$Q177:$R177) -> 49 | T38: ='OECD TTL - 2018'!P38 -> 160.5 | U38: ='OECD TTL - 2018'!Q38 -> 299 | V38: ='OECD TTL - 2018'!R38 -> 98.5 | W38: ='OECD TTL - 2018'!S38 -> 99 | X38: ='OECD TTL - 2018'!T38 -> 902.5 | Y38: ='OECD TTL - 2018'!U38 -> 88.7 | Z38: ='OECD TTL - 2018'!V38 -> 205.9 | AA38: ='OECD TTL - 2018'!$W38*'SIOM from DLIM'!Z177/SUM('SIOM from DLIM'!$Z177:$AB177) -> 202.652 | AB38: ='OECD TTL - 2018'!$W38*'SIOM from DLIM'!AA177/SUM('SIOM from DLIM'!$Z177:$AB177) -> 0.93299032 | AC38: ='OECD TTL - 2018'!$W38*'SIOM from DLIM'!AB177/SUM('SIOM from DLIM'!$Z177:$AB177) -> 0.01500798 | AD38: ='OECD TTL - 2018'!X38 -> 885.3 | AE38: ='OECD TTL - 2018'!Y38 -> 5765.1 | AF38: ='OECD TTL - 2018'!Z38 -> 1378.1 | AG38: ='OECD TTL - 2018'!AA38 -> 1163.8 | AH38: ='OECD TTL - 2018'!AB38 -> 269.6 | AI38: ='OECD TTL - 2018'!AC38 -> 468.7 | AJ38: ='OECD TTL - 2018'!AD38 -> 84.3 | AK38: ='OECD TTL - 2018'!AE38 -> 1813.2 | ... AR38: ='OECD TTL - 2018'!AL38 -> 0
A39: D69T82: Other business sector services | C39: ='OECD TTL - 2018'!C39 -> 544.1 | D39: ='OECD TTL - 2018'!$D39*'SIOM from DLIM'!C178/SUM('SIOM from DLIM'!$C178:$D178) -> 0 | E39: ='OECD TTL - 2018'!$D39*'SIOM from DLIM'!D178/SUM('SIOM from DLIM'!$C178:$D178) -> 494.5 | F39: ='OECD TTL - 2018'!E39 -> 153.9 | G39: ='OECD TTL - 2018'!F39 -> 241.2 | H39: ='OECD TTL - 2018'!G39 -> 3271.1 | I39: ='OECD TTL - 2018'!H39 -> 228.7 | J39: ='OECD TTL - 2018'!I39 -> 129.3 | K39: ='OECD TTL - 2018'!J39 -> 461 | L39: ='OECD TTL - 2018'!K39 -> 569.3 | M39: ='OECD TTL - 2018'!$L39*'SIOM from DLIM'!L178/SUM('SIOM from DLIM'!$L178:$M178) -> #DIV/0! | N39: ='OECD TTL - 2018'!$L39*'SIOM from DLIM'!M178/SUM('SIOM from DLIM'!$L178:$M178) -> #DIV/0! | O39: ='OECD TTL - 2018'!M39 -> 478.9 | P39: ='OECD TTL - 2018'!$N39*'SIOM from DLIM'!O178/SUM('SIOM from DLIM'!$O178:$P178) -> #DIV/0! | Q39: ='OECD TTL - 2018'!$N39*'SIOM from DLIM'!P178/SUM('SIOM from DLIM'!$O178:$P178) -> #DIV/0! | R39: ='OECD TTL - 2018'!$O39*'SIOM from DLIM'!Q178/SUM('SIOM from DLIM'!$Q178:$R178) -> 0 | S39: ='OECD TTL - 2018'!$O39*'SIOM from DLIM'!R178/SUM('SIOM from DLIM'!$Q178:$R178) -> 336.3 | T39: ='OECD TTL - 2018'!P39 -> 820.8 | U39: ='OECD TTL - 2018'!Q39 -> 3264 | V39: ='OECD TTL - 2018'!R39 -> 721.5 | W39: ='OECD TTL - 2018'!S39 -> 718.8 | X39: ='OECD TTL - 2018'!T39 -> 4589.8 | Y39: ='OECD TTL - 2018'!U39 -> 474.3 | Z39: ='OECD TTL - 2018'!V39 -> 1041.3 | AA39: ='OECD TTL - 2018'!$W39*'SIOM from DLIM'!Z178/SUM('SIOM from DLIM'!$Z178:$AB178) -> 1120.0497 | AB39: ='OECD TTL - 2018'!$W39*'SIOM from DLIM'!AA178/SUM('SIOM from DLIM'!$Z178:$AB178) -> 5.1639593 | AC39: ='OECD TTL - 2018'!$W39*'SIOM from DLIM'!AB178/SUM('SIOM from DLIM'!$Z178:$AB178) -> 0.086307316 | AD39: ='OECD TTL - 2018'!X39 -> 3646.4 | AE39: ='OECD TTL - 2018'!Y39 -> 5624.7 | AF39: ='OECD TTL - 2018'!Z39 -> 4866.9 | AG39: ='OECD TTL - 2018'!AA39 -> 1541.9 | AH39: ='OECD TTL - 2018'!AB39 -> 889.7 | AI39: ='OECD TTL - 2018'!AC39 -> 1229.2 | AJ39: ='OECD TTL - 2018'!AD39 -> 361.4 | AK39: ='OECD TTL - 2018'!AE39 -> 5270 | ... AR39: ='OECD TTL - 2018'!AL39 -> 0
A40: D84: Public admin. and defence; compulsory social security | C40: ='OECD TTL - 2018'!C40 -> 6.5 | D40: ='OECD TTL - 2018'!$D40*'SIOM from DLIM'!C179/SUM('SIOM from DLIM'!$C179:$D179) -> 0 | E40: ='OECD TTL - 2018'!$D40*'SIOM from DLIM'!D179/SUM('SIOM from DLIM'!$C179:$D179) -> 3.8 | F40: ='OECD TTL - 2018'!E40 -> 4.1 | G40: ='OECD TTL - 2018'!F40 -> 2.5 | H40: ='OECD TTL - 2018'!G40 -> 10.7 | I40: ='OECD TTL - 2018'!H40 -> 4.9 | J40: ='OECD TTL - 2018'!I40 -> 1.1 | K40: ='OECD TTL - 2018'!J40 -> 4.1 | L40: ='OECD TTL - 2018'!K40 -> 11.6 | M40: ='OECD TTL - 2018'!$L40*'SIOM from DLIM'!L179/SUM('SIOM from DLIM'!$L179:$M179) -> #DIV/0! | N40: ='OECD TTL - 2018'!$L40*'SIOM from DLIM'!M179/SUM('SIOM from DLIM'!$L179:$M179) -> #DIV/0! | O40: ='OECD TTL - 2018'!M40 -> 4 | P40: ='OECD TTL - 2018'!$N40*'SIOM from DLIM'!O179/SUM('SIOM from DLIM'!$O179:$P179) -> #DIV/0! | Q40: ='OECD TTL - 2018'!$N40*'SIOM from DLIM'!P179/SUM('SIOM from DLIM'!$O179:$P179) -> #DIV/0! | R40: ='OECD TTL - 2018'!$O40*'SIOM from DLIM'!Q179/SUM('SIOM from DLIM'!$Q179:$R179) -> 0 | S40: ='OECD TTL - 2018'!$O40*'SIOM from DLIM'!R179/SUM('SIOM from DLIM'!$Q179:$R179) -> 4.2 | T40: ='OECD TTL - 2018'!P40 -> 5.9 | U40: ='OECD TTL - 2018'!Q40 -> 12.4 | V40: ='OECD TTL - 2018'!R40 -> 4.2 | W40: ='OECD TTL - 2018'!S40 -> 4.9 | X40: ='OECD TTL - 2018'!T40 -> 26.1 | Y40: ='OECD TTL - 2018'!U40 -> 3.3 | Z40: ='OECD TTL - 2018'!V40 -> 6 | AA40: ='OECD TTL - 2018'!$W40*'SIOM from DLIM'!Z179/SUM('SIOM from DLIM'!$Z179:$AB179) -> 17.915921 | AB40: ='OECD TTL - 2018'!$W40*'SIOM from DLIM'!AA179/SUM('SIOM from DLIM'!$Z179:$AB179) -> 0.082697542 | AC40: ='OECD TTL - 2018'!$W40*'SIOM from DLIM'!AB179/SUM('SIOM from DLIM'!$Z179:$AB179) -> 0.0013812851 | AD40: ='OECD TTL - 2018'!X40 -> 28.1 | AE40: ='OECD TTL - 2018'!Y40 -> 42.2 | AF40: ='OECD TTL - 2018'!Z40 -> 76.2 | AG40: ='OECD TTL - 2018'!AA40 -> 6.8 | AH40: ='OECD TTL - 2018'!AB40 -> 9.9 | AI40: ='OECD TTL - 2018'!AC40 -> 9.6 | AJ40: ='OECD TTL - 2018'!AD40 -> 1.5 | AK40: ='OECD TTL - 2018'!AE40 -> 37.1 | ... AR40: ='OECD TTL - 2018'!AL40 -> 0
A41: D85: Education | C41: ='OECD TTL - 2018'!C41 -> 3.1 | D41: ='OECD TTL - 2018'!$D41*'SIOM from DLIM'!C180/SUM('SIOM from DLIM'!$C180:$D180) -> 7.5 | E41: ='OECD TTL - 2018'!$D41*'SIOM from DLIM'!D180/SUM('SIOM from DLIM'!$C180:$D180) -> 0 | F41: ='OECD TTL - 2018'!E41 -> 5.7 | G41: ='OECD TTL - 2018'!F41 -> 0.9 | H41: ='OECD TTL - 2018'!G41 -> 12.1 | I41: ='OECD TTL - 2018'!H41 -> 3.8 | J41: ='OECD TTL - 2018'!I41 -> 0.7 | K41: ='OECD TTL - 2018'!J41 -> 4.3 | L41: ='OECD TTL - 2018'!K41 -> 7.6 | M41: ='OECD TTL - 2018'!$L41*'SIOM from DLIM'!L180/SUM('SIOM from DLIM'!$L180:$M180) -> 15.31774 | N41: ='OECD TTL - 2018'!$L41*'SIOM from DLIM'!M180/SUM('SIOM from DLIM'!$L180:$M180) -> 2.5822603 | O41: ='OECD TTL - 2018'!M41 -> 3.4 | P41: ='OECD TTL - 2018'!$N41*'SIOM from DLIM'!O180/SUM('SIOM from DLIM'!$O180:$P180) -> 3.0199906 | Q41: ='OECD TTL - 2018'!$N41*'SIOM from DLIM'!P180/SUM('SIOM from DLIM'!$O180:$P180) -> 1.4800094 | R41: ='OECD TTL - 2018'!$O41*'SIOM from DLIM'!Q180/SUM('SIOM from DLIM'!$Q180:$R180) -> 2.4 | S41: ='OECD TTL - 2018'!$O41*'SIOM from DLIM'!R180/SUM('SIOM from DLIM'!$Q180:$R180) -> 0 | T41: ='OECD TTL - 2018'!P41 -> 5.2 | U41: ='OECD TTL - 2018'!Q41 -> 22.3 | V41: ='OECD TTL - 2018'!R41 -> 5.1 | W41: ='OECD TTL - 2018'!S41 -> 5.3 | X41: ='OECD TTL - 2018'!T41 -> 31.6 | Y41: ='OECD TTL - 2018'!U41 -> 1.8 | Z41: ='OECD TTL - 2018'!V41 -> 5.5 | AA41: ='OECD TTL - 2018'!$W41*'SIOM from DLIM'!Z180/SUM('SIOM from DLIM'!$Z180:$AB180) -> #DIV/0! | AB41: ='OECD TTL - 2018'!$W41*'SIOM from DLIM'!AA180/SUM('SIOM from DLIM'!$Z180:$AB180) -> #DIV/0! | AC41: ='OECD TTL - 2018'!$W41*'SIOM from DLIM'!AB180/SUM('SIOM from DLIM'!$Z180:$AB180) -> #DIV/0! | AD41: ='OECD TTL - 2018'!X41 -> 12.9 | AE41: ='OECD TTL - 2018'!Y41 -> 40.9 | AF41: ='OECD TTL - 2018'!Z41 -> 45.5 | AG41: ='OECD TTL - 2018'!AA41 -> 2.6 | AH41: ='OECD TTL - 2018'!AB41 -> 11.6 | AI41: ='OECD TTL - 2018'!AC41 -> 11.6 | AJ41: ='OECD TTL - 2018'!AD41 -> 4.5 | AK41: ='OECD TTL - 2018'!AE41 -> 91.4 | ... AR41: ='OECD TTL - 2018'!AL41 -> 0
A42: D86T88: Human health and social work | C42: ='OECD TTL - 2018'!C42 -> 30 | D42: ='OECD TTL - 2018'!$D42*'SIOM from DLIM'!C181/SUM('SIOM from DLIM'!$C181:$D181) -> 0 | E42: ='OECD TTL - 2018'!$D42*'SIOM from DLIM'!D181/SUM('SIOM from DLIM'!$C181:$D181) -> 2.6 | F42: ='OECD TTL - 2018'!E42 -> 0.6 | G42: ='OECD TTL - 2018'!F42 -> 0.3 | H42: ='OECD TTL - 2018'!G42 -> 126.3 | I42: ='OECD TTL - 2018'!H42 -> 3.4 | J42: ='OECD TTL - 2018'!I42 -> 4.5 | K42: ='OECD TTL - 2018'!J42 -> 17.1 | L42: ='OECD TTL - 2018'!K42 -> 19.1 | M42: ='OECD TTL - 2018'!$L42*'SIOM from DLIM'!L181/SUM('SIOM from DLIM'!$L181:$M181) -> #DIV/0! | N42: ='OECD TTL - 2018'!$L42*'SIOM from DLIM'!M181/SUM('SIOM from DLIM'!$L181:$M181) -> #DIV/0! | O42: ='OECD TTL - 2018'!M42 -> 17.1 | P42: ='OECD TTL - 2018'!$N42*'SIOM from DLIM'!O181/SUM('SIOM from DLIM'!$O181:$P181) -> #DIV/0! | Q42: ='OECD TTL - 2018'!$N42*'SIOM from DLIM'!P181/SUM('SIOM from DLIM'!$O181:$P181) -> #DIV/0! | R42: ='OECD TTL - 2018'!$O42*'SIOM from DLIM'!Q181/SUM('SIOM from DLIM'!$Q181:$R181) -> 0 | S42: ='OECD TTL - 2018'!$O42*'SIOM from DLIM'!R181/SUM('SIOM from DLIM'!$Q181:$R181) -> 7.2 | T42: ='OECD TTL - 2018'!P42 -> 24 | U42: ='OECD TTL - 2018'!Q42 -> 49.4 | V42: ='OECD TTL - 2018'!R42 -> 20.7 | W42: ='OECD TTL - 2018'!S42 -> 19.6 | X42: ='OECD TTL - 2018'!T42 -> 119.5 | Y42: ='OECD TTL - 2018'!U42 -> 6.2 | Z42: ='OECD TTL - 2018'!V42 -> 38.2 | AA42: ='OECD TTL - 2018'!$W42*'SIOM from DLIM'!Z181/SUM('SIOM from DLIM'!$Z181:$AB181) -> 43.5952 | AB42: ='OECD TTL - 2018'!$W42*'SIOM from DLIM'!AA181/SUM('SIOM from DLIM'!$Z181:$AB181) -> 0.20140698 | AC42: ='OECD TTL - 2018'!$W42*'SIOM from DLIM'!AB181/SUM('SIOM from DLIM'!$Z181:$AB181) -> 0.0033925861 | AD42: ='OECD TTL - 2018'!X42 -> 75 | AE42: ='OECD TTL - 2018'!Y42 -> 225.5 | AF42: ='OECD TTL - 2018'!Z42 -> 314.5 | AG42: ='OECD TTL - 2018'!AA42 -> 42.5 | AH42: ='OECD TTL - 2018'!AB42 -> 35.3 | AI42: ='OECD TTL - 2018'!AC42 -> 42.5 | AJ42: ='OECD TTL - 2018'!AD42 -> 12.6 | AK42: ='OECD TTL - 2018'!AE42 -> 575.7 | ... AR42: ='OECD TTL - 2018'!AL42 -> 0
... A44: D97T98: Private households with employed persons | C44: ='OECD TTL - 2018'!C44 -> 0 | D44: ='OECD TTL - 2018'!$D44*'SIOM from DLIM'!C183/SUM('SIOM from DLIM'!$C183:$D183) -> #DIV/0! | E44: ='OECD TTL - 2018'!$D44*'SIOM from DLIM'!D183/SUM('SIOM from DLIM'!$C183:$D183) -> #DIV/0! | F44: ='OECD TTL - 2018'!E44 -> 0 | G44: ='OECD TTL - 2018'!F44 -> 0 | H44: ='OECD TTL - 2018'!G44 -> 0 | I44: ='OECD TTL - 2018'!H44 -> 0 | J44: ='OECD TTL - 2018'!I44 -> 0 | K44: ='OECD TTL - 2018'!J44 -> 0 | L44: ='OECD TTL - 2018'!K44 -> 0 | M44: ='OECD TTL - 2018'!$L44*'SIOM from DLIM'!L183/SUM('SIOM from DLIM'!$L183:$M183) -> #DIV/0! | N44: ='OECD TTL - 2018'!$L44*'SIOM from DLIM'!M183/SUM('SIOM from DLIM'!$L183:$M183) -> #DIV/0! | O44: ='OECD TTL - 2018'!M44 -> 0 | P44: ='OECD TTL - 2018'!$N44*'SIOM from DLIM'!O183/SUM('SIOM from DLIM'!$O183:$P183) -> #DIV/0! | Q44: ='OECD TTL - 2018'!$N44*'SIOM from DLIM'!P183/SUM('SIOM from DLIM'!$O183:$P183) -> #DIV/0! | R44: ='OECD TTL - 2018'!$O44*'SIOM from DLIM'!Q183/SUM('SIOM from DLIM'!$Q183:$R183) -> #DIV/0! | S44: ='OECD TTL - 2018'!$O44*'SIOM from DLIM'!R183/SUM('SIOM from DLIM'!$Q183:$R183) -> #DIV/0! | T44: ='OECD TTL - 2018'!P44 -> 0 | U44: ='OECD TTL - 2018'!Q44 -> 0 | V44: ='OECD TTL - 2018'!R44 -> 0 | W44: ='OECD TTL - 2018'!S44 -> 0 | X44: ='OECD TTL - 2018'!T44 -> 0 | Y44: ='OECD TTL - 2018'!U44 -> 0 | Z44: ='OECD TTL - 2018'!V44 -> 0 | AA44: ='OECD TTL - 2018'!$W44*'SIOM from DLIM'!Z183/SUM('SIOM from DLIM'!$Z183:$AB183) -> #DIV/0! | AB44: ='OECD TTL - 2018'!$W44*'SIOM from DLIM'!AA183/SUM('SIOM from DLIM'!$Z183:$AB183) -> #DIV/0! | AC44: ='OECD TTL - 2018'!$W44*'SIOM from DLIM'!AB183/SUM('SIOM from DLIM'!$Z183:$AB183) -> #DIV/0! | AD44: ='OECD TTL - 2018'!X44 -> 0 | AE44: ='OECD TTL - 2018'!Y44 -> 0 | AF44: ='OECD TTL - 2018'!Z44 -> 0 | AG44: ='OECD TTL - 2018'!AA44 -> 0 | AH44: ='OECD TTL - 2018'!AB44 -> 0 | AI44: ='OECD TTL - 2018'!AC44 -> 0 | AJ44: ='OECD TTL - 2018'!AD44 -> 0 | AK44: ='OECD TTL - 2018'!AE44 -> 0 | ... AR44: ='OECD TTL - 2018'!AL44 -> 0
A46: SIOM, without errors
B47: Matching EPS Industry | C47: ISIC 01T03 | D47: ISIC 05 | E47: ISIC 06 | F47: ISIC 07T08 | G47: ISIC 09 | H47: ISIC 10T12 | I47: ISIC 13T15 | J47: ISIC 16 | K47: ISIC 17T18 | L47: ISIC 19 | M47: ISIC 20 | N47: ISIC 21 | O47: ISIC 22 | P47: ISIC 231 | Q47: ISIC 239 | R47: ISIC 241 | S47: ISIC 242 | T47: ISIC 25 | U47: ISIC 26 | V47: ISIC 27 | W47: ISIC 28 | X47: ISIC 29 | Y47: ISIC 30 | Z47: ISIC 31T33 | AA47: ISIC 351 | AB47: ISIC 352T353 | AC47: ISIC 36T39 | AD47: ISIC 41T43 | AE47: ISIC 45T47 | AF47: ISIC 49T53 | AG47: ISIC 55T56 | AH47: ISIC 58T60 | AI47: ISIC 61 | AJ47: ISIC 62T63 | AK47: ISIC 64T66 | AL47: ISIC 68 | AM47: ISIC 69T82 | AN47: ISIC 84 | AO47: ISIC 85 | AP47: ISIC 86T88 | AQ47: ISIC 90T96 | AR47: ISIC 97T98 | AS47: 0
A48: D01T03: Agriculture, forestry and fishing | B48: agriculture and forestry 01T03 | C48: =IFERROR(C3,0) -> 5034.6 | D48: =IFERROR(D3,0) -> 8.1 | E48: =IFERROR(E3,0) -> 0 | F48: =IFERROR(F3,0) -> 22.4 | G48: =IFERROR(G3,0) -> 8.2 | H48: =IFERROR(H3,0) -> 30244.9 | I48: =IFERROR(I3,0) -> 425.8 | J48: =IFERROR(J3,0) -> 494.3 | ... AR48: =IFERROR(AR3,0) -> 0
A49: coal mining 05 | B49: coal mining 05 | C49: =IFERROR(C4,0) -> 18.87218 | D49: =IFERROR(D4,0) -> 0 | E49: =IFERROR(E4,0) -> 110.86035 | F49: =IFERROR(F4,0) -> 7.1109162 | G49: =IFERROR(G4,0) -> 89.603048 | H49: =IFERROR(H4,0) -> 41.694548 | I49: =IFERROR(I4,0) -> 3.1029939 | J49: =IFERROR(J4,0) -> 0 | ... L49: =IFERROR(L4,0) -> 0 | M49: =IFERROR(M13,0) -> 15040.151 | N49: =IFERROR(N13,0) -> 2540.5492 | O49: =IFERROR(O4,0) -> 0 | P49: =IFERROR(P4,0) -> 0 | Q49: =IFERROR(Q4,0) -> 0 | R49: =IFERROR(R4,0) -> 0 | S49: =IFERROR(S4,0) -> 153.97614 | T49: =IFERROR(T4,0) -> 0 | U49: =IFERROR(U4,0) -> 0 | V49: =IFERROR(V4,0) -> 0 | ... AR49: =IFERROR(AR4,0) -> 0
A50: oil and gas extraction 06 | B50: oil and gas extraction 06 | C50: =IFERROR(C5,0) -> 29.42782 | D50: =IFERROR(D5,0) -> 0 | E50: =IFERROR(E5,0) -> 174.43965 | F50: =IFERROR(F5,0) -> 11.189084 | G50: =IFERROR(G5,0) -> 132.89695 | H50: =IFERROR(H5,0) -> 61.105452 | I50: =IFERROR(I5,0) -> 5.0970061 | J50: =IFERROR(J5,0) -> 0 | ... L50: =IFERROR(L5,0) -> 0 | M50: =IFERROR(M14,0) -> 0 | N50: =IFERROR(N14,0) -> 0 | O50: =IFERROR(O5,0) -> 0 | P50: =IFERROR(P5,0) -> 0 | Q50: =IFERROR(Q5,0) -> 0 | R50: =IFERROR(R5,0) -> 0 | S50: =IFERROR(S5,0) -> 242.52386 | T50: =IFERROR(T5,0) -> 0 | U50: =IFERROR(U5,0) -> 0 | V50: =IFERROR(V5,0) -> 0 | ... AR50: =IFERROR(AR5,0) -> 0
A51: D07T08: Mining and quarrying of non-energy producing products | B51: other mining and quarrying 07T08 | C51: =IFERROR(C6,0) -> 56.1 | D51: =IFERROR(D6,0) -> 19.8 | E51: =IFERROR(E6,0) -> 0 | F51: =IFERROR(F6,0) -> 613.3 | G51: =IFERROR(G6,0) -> 59.5 | H51: =IFERROR(H6,0) -> 40.7 | I51: =IFERROR(I6,0) -> 6.9 | J51: =IFERROR(J6,0) -> 2.6 | ... AR51: =IFERROR(AR6,0) -> 0
A52: D09: Mining support service activities | C52: =IFERROR(C7,0) -> 665.7 | D52: =IFERROR(D7,0) -> 0 | E52: =IFERROR(E7,0) -> 3004.1 | F52: =IFERROR(F7,0) -> 870.4 | G52: =IFERROR(G7,0) -> 2312.7 | H52: =IFERROR(H7,0) -> 171.5 | I52: =IFERROR(I7,0) -> 0.4 | J52: =IFERROR(J7,0) -> 7.1 | ... AR52: =IFERROR(AR7,0) -> 0
A53: D10T12: Food products, beverages and tobacco | B53: food beverage and tobacco 10T12 | C53: =IFERROR(C8,0) -> 3366 | D53: =IFERROR(D8,0) -> 6.6 | E53: =IFERROR(E8,0) -> 0 | F53: =IFERROR(F8,0) -> 12.3 | G53: =IFERROR(G8,0) -> 7.3 | H53: =IFERROR(H8,0) -> 14358.9 | I53: =IFERROR(I8,0) -> 395.2 | J53: =IFERROR(J8,0) -> 12.6 | ... AR53: =IFERROR(AR8,0) -> 0
A54: D13T15: Textiles, wearing apparel, leather and related products | B54: textiles apparel and leather 13T15 | C54: =IFERROR(C9,0) -> 99.8 | D54: =IFERROR(D9,0) -> 0 | E54: =IFERROR(E9,0) -> 19 | F54: =IFERROR(F9,0) -> 29.3 | G54: =IFERROR(G9,0) -> 23.5 | H54: =IFERROR(H9,0) -> 121.2 | I54: =IFERROR(I9,0) -> 5021 | J54: =IFERROR(J9,0) -> 20.4 | ... AR54: =IFERROR(AR9,0) -> 0
A55: D16: Wood and products of wood and cork | B55: wood products 16 | C55: =IFERROR(C10,0) -> 39.9 | D55: =IFERROR(D10,0) -> 12.1 | E55: =IFERROR(E10,0) -> 0 | F55: =IFERROR(F10,0) -> 30 | G55: =IFERROR(G10,0) -> 8.6 | H55: =IFERROR(H10,0) -> 65.2 | I55: =IFERROR(I10,0) -> 20 | J55: =IFERROR(J10,0) -> 586.7 | ... AR55: =IFERROR(AR10,0) -> 0
A56: D17T18: Paper products and printing | B56: pulp paper and printing 17T18 | C56: =IFERROR(C11,0) -> 95.1 | D56: =IFERROR(D11,0) -> 0 | E56: =IFERROR(E11,0) -> 12.6 | F56: =IFERROR(F11,0) -> 39.6 | G56: =IFERROR(G11,0) -> 11.6 | H56: =IFERROR(H11,0) -> 1611 | I56: =IFERROR(I11,0) -> 372.5 | J56: =IFERROR(J11,0) -> 61.1 | ... AR56: =IFERROR(AR11,0) -> 0
A57: D19: Coke and refined petroleum products | B57: refined petroleum and coke 19 | C57: =IFERROR(C12,0) -> 1384.2 | D57: =IFERROR(D12,0) -> 308.8 | E57: =IFERROR(E12,0) -> 0 | F57: =IFERROR(F12,0) -> 659.8 | G57: =IFERROR(G12,0) -> 340.1 | H57: =IFERROR(H12,0) -> 777.3 | I57: =IFERROR(I12,0) -> 152.9 | J57: =IFERROR(J12,0) -> 62.7 | ... AR57: =IFERROR(AR12,0) -> 0
A58: chemicals 20 | B58: chemicals 20 | C58: =IFERROR(C13,0) -> 0 | D58: =IFERROR(D13,0) -> 189.61855 | E58: =IFERROR(E13,0) -> 0 | F58: =IFERROR(F13,0) -> 0 | G58: =IFERROR(G13,0) -> 0 | H58: =IFERROR(H13,0) -> 0 | I58: =IFERROR(I13,0) -> 0 | J58: =IFERROR(J13,0) -> 242.6 | ... L58: =IFERROR(L13,0) -> 3280.1 | M58: =IFERROR(#REF!,0) -> 0 | N58: =IFERROR(#REF!,0) -> 0 | O58: =IFERROR(O13,0) -> 5481.4 | P58: =IFERROR(P13,0) -> 778.62204 | Q58: =IFERROR(Q13,0) -> 381.67796 | R58: =IFERROR(R13,0) -> 1334.6207 | S58: =IFERROR(S13,0) -> 0 | T58: =IFERROR(T13,0) -> 762.6 | U58: =IFERROR(U13,0) -> 1826 | V58: =IFERROR(V13,0) -> 932.7 | ... AR58: =IFERROR(AR13,0) -> 0
A59: pharmaceuticals | B59: chemicals 20 | C59: =IFERROR(C14,0) -> 2698.2 | D59: =IFERROR(D14,0) -> 0 | E59: =IFERROR(E14,0) -> 32.58145 | F59: =IFERROR(F14,0) -> 415 | G59: =IFERROR(G14,0) -> 159.5 | H59: =IFERROR(H14,0) -> 1414.1 | I59: =IFERROR(I14,0) -> 1437.5 | J59: =IFERROR(J14,0) -> 0 | ... L59: =IFERROR(L14,0) -> 0 | M59: =IFERROR(#REF!,0) -> 0 | N59: =IFERROR(#REF!,0) -> 0 | O59: =IFERROR(O14,0) -> 0 | P59: =IFERROR(P14,0) -> 0 | Q59: =IFERROR(Q14,0) -> 0 | R59: =IFERROR(R14,0) -> 0 | S59: =IFERROR(S14,0) -> 17.479312 | T59: =IFERROR(T14,0) -> 0 | U59: =IFERROR(U14,0) -> 0 | V59: =IFERROR(V14,0) -> 0 | ... AR59: =IFERROR(AR14,0) -> 0
A60: D22: Rubber and plastic products | B60: rubber and plastic products 22 | C60: =IFERROR(C15,0) -> 164.5 | D60: =IFERROR(D15,0) -> 0 | E60: =IFERROR(E15,0) -> 77 | F60: =IFERROR(F15,0) -> 139.9 | G60: =IFERROR(G15,0) -> 73.7 | H60: =IFERROR(H15,0) -> 1869.2 | I60: =IFERROR(I15,0) -> 399.1 | J60: =IFERROR(J15,0) -> 56.9 | ... AR60: =IFERROR(AR15,0) -> 0
A61: glass and glass products 231 | B61: glass and glass products 231 | C61: =IFERROR(C16,0) -> 48.051096 | D61: =IFERROR(D16,0) -> 0 | E61: =IFERROR(E16,0) -> 16.637674 | F61: =IFERROR(F16,0) -> 69.068238 | G61: =IFERROR(G16,0) -> 25.829702 | H61: =IFERROR(H16,0) -> 378.45733 | I61: =IFERROR(I16,0) -> 22.166527 | J61: =IFERROR(J16,0) -> 0 | ... AR61: =IFERROR(AR16,0) -> 0
A62: cement and other nonmetallic minerals 239 | B62: cement and other nonmetallic minerals 239 | C62: =IFERROR(C17,0) -> 39.548904 | D62: =IFERROR(D17,0) -> 0 | E62: =IFERROR(E17,0) -> 13.762326 | F62: =IFERROR(F17,0) -> 57.131762 | G62: =IFERROR(G17,0) -> 21.170298 | H62: =IFERROR(H17,0) -> 310.24267 | I62: =IFERROR(I17,0) -> 18.933473 | J62: =IFERROR(J17,0) -> 0 | ... AR62: =IFERROR(AR17,0) -> 0
A63: iron and steel 241 | B63: iron and steel 241 | C63: =IFERROR(C18,0) -> 48.6 | D63: =IFERROR(D18,0) -> 0 | E63: =IFERROR(E18,0) -> 102.60654 | F63: =IFERROR(F18,0) -> 126.3 | G63: =IFERROR(G18,0) -> 192.1 | H63: =IFERROR(H18,0) -> 246.9 | I63: =IFERROR(I18,0) -> 15.5 | J63: =IFERROR(J18,0) -> 0 | ... AR63: =IFERROR(AR18,0) -> 0
A64: other metals 242 | B64: other metals 242 | C64: =IFERROR(C19,0) -> 0 | D64: =IFERROR(D19,0) -> 5.7934608 | E64: =IFERROR(E19,0) -> 0 | F64: =IFERROR(F19,0) -> 0 | G64: =IFERROR(G19,0) -> 0 | H64: =IFERROR(H19,0) -> 0 | I64: =IFERROR(I19,0) -> 0 | J64: =IFERROR(J19,0) -> 11.3 | ... AR64: =IFERROR(AR19,0) -> 0
A65: D25: Fabricated metal products | B65: metal products except machinery and vehicles 25 | C65: =IFERROR(C20,0) -> 195 | D65: =IFERROR(D20,0) -> 209.1 | E65: =IFERROR(E20,0) -> 0 | F65: =IFERROR(F20,0) -> 159.5 | G65: =IFERROR(G20,0) -> 135.7 | H65: =IFERROR(H20,0) -> 1332.3 | I65: =IFERROR(I20,0) -> 127.9 | J65: =IFERROR(J20,0) -> 95.2 | ... AR65: =IFERROR(AR20,0) -> 0
A66: D26: Computer, electronic and optical products | B66: computers and electronics 26 | C66: =IFERROR(C21,0) -> 56.6 | D66: =IFERROR(D21,0) -> 46.3 | E66: =IFERROR(E21,0) -> 0 | F66: =IFERROR(F21,0) -> 57.7 | G66: =IFERROR(G21,0) -> 55 | H66: =IFERROR(H21,0) -> 169.9 | I66: =IFERROR(I21,0) -> 126.8 | J66: =IFERROR(J21,0) -> 14.8 | ... AR66: =IFERROR(AR21,0) -> 0
A67: D27: Electrical equipment | B67: appliances and electrical equipment 27 | C67: =IFERROR(C22,0) -> 60.8 | D67: =IFERROR(D22,0) -> 0 | E67: =IFERROR(E22,0) -> 66.3 | F67: =IFERROR(F22,0) -> 73.7 | G67: =IFERROR(G22,0) -> 46.1 | H67: =IFERROR(H22,0) -> 168.1 | I67: =IFERROR(I22,0) -> 52.2 | J67: =IFERROR(J22,0) -> 14 | ... AR67: =IFERROR(AR22,0) -> 0
A68: D28: Machinery and equipment, nec | B68: other machinery 28 | C68: =IFERROR(C23,0) -> 243.1 | D68: =IFERROR(D23,0) -> 237.4 | E68: =IFERROR(E23,0) -> 0 | F68: =IFERROR(F23,0) -> 269.5 | G68: =IFERROR(G23,0) -> 243 | H68: =IFERROR(H23,0) -> 274 | I68: =IFERROR(I23,0) -> 90.8 | J68: =IFERROR(J23,0) -> 30.5 | ... AR68: =IFERROR(AR23,0) -> 0
A69: D29: Motor vehicles, trailers and semi-trailers | B69: road vehicles 29 | C69: =IFERROR(C24,0) -> 69.2 | D69: =IFERROR(D24,0) -> 32.4 | E69: =IFERROR(E24,0) -> 0 | F69: =IFERROR(F24,0) -> 48.1 | G69: =IFERROR(G24,0) -> 41.1 | H69: =IFERROR(H24,0) -> 159.5 | I69: =IFERROR(I24,0) -> 95.2 | J69: =IFERROR(J24,0) -> 16 | ... AR69: =IFERROR(AR24,0) -> 0
A70: D30: Other transport equipment | B70: nonroad vehicles 30 | C70: =IFERROR(C25,0) -> 9.4 | D70: =IFERROR(D25,0) -> 0 | E70: =IFERROR(E25,0) -> 7.6 | F70: =IFERROR(F25,0) -> 9.4 | G70: =IFERROR(G25,0) -> 6.7 | H70: =IFERROR(H25,0) -> 23.8 | I70: =IFERROR(I25,0) -> 20.9 | J70: =IFERROR(J25,0) -> 1.9 | ... AR70: =IFERROR(AR25,0) -> 0
A71: D31T33: Other manufacturing; repair and installation of machinery and equipment | B71: other manufacturing 31T33 | C71: =IFERROR(C26,0) -> 44.9 | D71: =IFERROR(D26,0) -> 0 | E71: =IFERROR(E26,0) -> 19.8 | F71: =IFERROR(F26,0) -> 21.2 | G71: =IFERROR(G26,0) -> 15.2 | H71: =IFERROR(H26,0) -> 121.7 | I71: =IFERROR(I26,0) -> 173.5 | J71: =IFERROR(J26,0) -> 23 | ... AR71: =IFERROR(AR26,0) -> 0
A72: electricity | C72: =IFERROR(C27,0) -> 37.648904 | D72: =IFERROR(D27,0) -> 0 | E72: =IFERROR(E27,0) -> 28.03999 | F72: =IFERROR(F27,0) -> 56.629334 | G72: =IFERROR(G27,0) -> 12.851086 | H72: =IFERROR(H27,0) -> 96.804761 | I72: =IFERROR(I27,0) -> 25.79275 | J72: =IFERROR(J27,0) -> 0 | ... AR72: =IFERROR(AR27,0) -> 0
A73: energy pipelines and gas processing 352T353 | B73: energy pipelines and gas processing 352T353 | C73: =IFERROR(C28,0) -> 3.3055627 | D73: =IFERROR(D28,0) -> 0 | E73: =IFERROR(E28,0) -> 2.4611409 | F73: =IFERROR(F28,0) -> 4.9705001 | G73: =IFERROR(G28,0) -> 1.1302086 | H73: =IFERROR(H28,0) -> 8.5353462 | I73: =IFERROR(I28,0) -> 2.2106184 | J73: =IFERROR(J28,0) -> 0 | ... AR73: =IFERROR(AR28,0) -> 0
A74: water and waste 36T39 | B74: water and waste 36T39 | C74: =IFERROR(C29,0) -> 123.74553 | D74: =IFERROR(D29,0) -> 0 | E74: =IFERROR(E29,0) -> 91.998869 | F74: =IFERROR(F29,0) -> 185.80017 | G74: =IFERROR(G29,0) -> 43.718705 | H74: =IFERROR(H29,0) -> 321.75989 | I74: =IFERROR(I29,0) -> 75.996631 | J74: =IFERROR(J29,0) -> 0 | ... AR74: =IFERROR(AR29,0) -> 0
A75: D41T43: Construction | B75: construction 41T43 | C75: =IFERROR(C30,0) -> 67.9 | D75: =IFERROR(D30,0) -> 216.1 | E75: =IFERROR(E30,0) -> 0 | F75: =IFERROR(F30,0) -> 99.2 | G75: =IFERROR(G30,0) -> 167.5 | H75: =IFERROR(H30,0) -> 26.6 | I75: =IFERROR(I30,0) -> 4.8 | J75: =IFERROR(J30,0) -> 2.7 | ... AR75: =IFERROR(AR30,0) -> 0
A76: D45T47: Wholesale and retail trade; repair of motor vehicles | C76: =IFERROR(C31,0) -> 4729.5 | D76: =IFERROR(D31,0) -> 475 | E76: =IFERROR(E31,0) -> 0 | F76: =IFERROR(F31,0) -> 783.9 | G76: =IFERROR(G31,0) -> 429.4 | H76: =IFERROR(H31,0) -> 20136.8 | I76: =IFERROR(I31,0) -> 3266.7 | J76: =IFERROR(J31,0) -> 525.2 | ... AR76: =IFERROR(AR31,0) -> 0
A77: D49T53: Transportation and storage | C77: =IFERROR(C32,0) -> 1250.6 | D77: =IFERROR(D32,0) -> 258 | E77: =IFERROR(E32,0) -> 0 | F77: =IFERROR(F32,0) -> 410.3 | G77: =IFERROR(G32,0) -> 196.9 | H77: =IFERROR(H32,0) -> 4910.7 | I77: =IFERROR(I32,0) -> 700.5 | J77: =IFERROR(J32,0) -> 158.6 | ... AR77: =IFERROR(AR32,0) -> 0
A78: D55T56: Accomodation and food services | C78: =IFERROR(C33,0) -> 8.1 | D78: =IFERROR(D33,0) -> 0 | E78: =IFERROR(E33,0) -> 3.8 | F78: =IFERROR(F33,0) -> 2.9 | G78: =IFERROR(G33,0) -> 5.9 | H78: =IFERROR(H33,0) -> 33.4 | I78: =IFERROR(I33,0) -> 7.1 | J78: =IFERROR(J33,0) -> 1.7 | ... AR78: =IFERROR(AR33,0) -> 0
A79: D58T60: Publishing, audiovisual and broadcasting activities | C79: =IFERROR(C34,0) -> 12.6 | D79: =IFERROR(D34,0) -> 0 | E79: =IFERROR(E34,0) -> 6.8 | F79: =IFERROR(F34,0) -> 4.9 | G79: =IFERROR(G34,0) -> 4.9 | H79: =IFERROR(H34,0) -> 153.5 | I79: =IFERROR(I34,0) -> 8.7 | J79: =IFERROR(J34,0) -> 2.6 | ... AR79: =IFERROR(AR34,0) -> 0
A80: D61: Telecommunications | C80: =IFERROR(C35,0) -> 36.4 | D80: =IFERROR(D35,0) -> 0 | E80: =IFERROR(E35,0) -> 8.9 | F80: =IFERROR(F35,0) -> 20.4 | G80: =IFERROR(G35,0) -> 15.6 | H80: =IFERROR(H35,0) -> 86.8 | I80: =IFERROR(I35,0) -> 30.3 | J80: =IFERROR(J35,0) -> 5.6 | ... AR80: =IFERROR(AR35,0) -> 0
A81: D62T63: IT and other information services | C81: =IFERROR(C36,0) -> 7.8 | D81: =IFERROR(D36,0) -> 0 | E81: =IFERROR(E36,0) -> 2.8 | F81: =IFERROR(F36,0) -> 2.6 | G81: =IFERROR(G36,0) -> 1.7 | H81: =IFERROR(H36,0) -> 33.2 | I81: =IFERROR(I36,0) -> 10.6 | J81: =IFERROR(J36,0) -> 1.3 | ... AR81: =IFERROR(AR36,0) -> 0
A82: D64T66: Financial and insurance activities | C82: =IFERROR(C37,0) -> 209.5 | D82: =IFERROR(D37,0) -> 92.9 | E82: =IFERROR(E37,0) -> 0 | F82: =IFERROR(F37,0) -> 75.4 | G82: =IFERROR(G37,0) -> 41.1 | H82: =IFERROR(H37,0) -> 284.7 | I82: =IFERROR(I37,0) -> 84.1 | J82: =IFERROR(J37,0) -> 21.7 | ... AR82: =IFERROR(AR37,0) -> 0
A83: D68: Real estate activities | C83: =IFERROR(C38,0) -> 95.5 | D83: =IFERROR(D38,0) -> 0 | E83: =IFERROR(E38,0) -> 76.7 | F83: =IFERROR(F38,0) -> 19.7 | G83: =IFERROR(G38,0) -> 13.7 | H83: =IFERROR(H38,0) -> 396.8 | I83: =IFERROR(I38,0) -> 159.9 | J83: =IFERROR(J38,0) -> 22.8 | ... AR83: =IFERROR(AR38,0) -> 0
A84: D69T82: Other business sector services | C84: =IFERROR(C39,0) -> 544.1 | D84: =IFERROR(D39,0) -> 0 | E84: =IFERROR(E39,0) -> 494.5 | F84: =IFERROR(F39,0) -> 153.9 | G84: =IFERROR(G39,0) -> 241.2 | H84: =IFERROR(H39,0) -> 3271.1 | I84: =IFERROR(I39,0) -> 228.7 | J84: =IFERROR(J39,0) -> 129.3 | ... AR84: =IFERROR(AR39,0) -> 0
A85: D84: Public admin. and defence; compulsory social security | C85: =IFERROR(C40,0) -> 6.5 | D85: =IFERROR(D40,0) -> 0 | E85: =IFERROR(E40,0) -> 3.8 | F85: =IFERROR(F40,0) -> 4.1 | G85: =IFERROR(G40,0) -> 2.5 | H85: =IFERROR(H40,0) -> 10.7 | I85: =IFERROR(I40,0) -> 4.9 | J85: =IFERROR(J40,0) -> 1.1 | ... AR85: =IFERROR(AR40,0) -> 0
A86: D85: Education | C86: =IFERROR(C41,0) -> 3.1 | D86: =IFERROR(D41,0) -> 7.5 | E86: =IFERROR(E41,0) -> 0 | F86: =IFERROR(F41,0) -> 5.7 | G86: =IFERROR(G41,0) -> 0.9 | H86: =IFERROR(H41,0) -> 12.1 | I86: =IFERROR(I41,0) -> 3.8 | J86: =IFERROR(J41,0) -> 0.7 | ... AR86: =IFERROR(AR41,0) -> 0
A87: D86T88: Human health and social work | C87: =IFERROR(C42,0) -> 30 | D87: =IFERROR(D42,0) -> 0 | E87: =IFERROR(E42,0) -> 2.6 | F87: =IFERROR(F42,0) -> 0.6 | G87: =IFERROR(G42,0) -> 0.3 | H87: =IFERROR(H42,0) -> 126.3 | I87: =IFERROR(I42,0) -> 3.4 | J87: =IFERROR(J42,0) -> 4.5 | ... AR87: =IFERROR(AR42,0) -> 0
... A89: D97T98: Private households with employed persons | C89: =IFERROR(C44,0) -> 0 | D89: =IFERROR(D44,0) -> 0 | E89: =IFERROR(E44,0) -> 0 | F89: =IFERROR(F44,0) -> 0 | G89: =IFERROR(G44,0) -> 0 | H89: =IFERROR(H44,0) -> 0 | I89: =IFERROR(I44,0) -> 0 | J89: =IFERROR(J44,0) -> 0 | ... AR89: =IFERROR(AR44,0) -> 0

Sheet Pre ISIC Consolidation
D1: ISIC 01T03 | E1: ISIC 05 | F1: ISIC 06 | G1: ISIC 07T08 | H1: ISIC 09 | I1: ISIC 10T12 | J1: ISIC 13T15 | K1: ISIC 16 | L1: ISIC 17T18 | M1: ISIC 19 | N1: ISIC 20 | O1: ISIC 21 | P1: ISIC 22 | Q1: ISIC 231 | R1: ISIC 239 | S1: ISIC 241 | T1: ISIC 242 | U1: ISIC 25 | V1: ISIC 26 | W1: ISIC 27 | X1: ISIC 28 | Y1: ISIC 29 | Z1: ISIC 30 | AA1: ISIC 31T33 | AB1: ISIC 351 | AC1: ISIC 352T353 | AD1: ISIC 36T39 | AE1: ISIC 41T43 | AF1: ISIC 45T47 | AG1: ISIC 49T53 | AH1: ISIC 55T56 | AI1: ISIC 58T60 | AJ1: ISIC 61 | AK1: ISIC 62T63 | AL1: ISIC 64T66 | AM1: ISIC 68 | AN1: ISIC 69T82 | AO1: ISIC 84 | AP1: ISIC 85 | AQ1: ISIC 86T88 | AR1: ISIC 90T96 | AS1: ISIC 97T98 | AT1: 0
D2: =B51 -> ISIC 01T03 | E2: =D51 -> ISIC 05 | F2: =E51 -> ISIC 06 | G2: =F51 -> ISIC 07T08 | H2: =G51 -> ISIC 09 | I2: =H51 -> ISIC 10T12 | J2: =I51 -> ISIC 31T33 | K2: =J51 -> ISIC 31T33 | L2: =K51 -> ISIC 17T18 | ... AT2: =AS51 -> 0
A3: ISIC 01T03 | B3: agriculture and forestry 01T03 | C3: =IFERROR(INDEX($B$54:$Z$54,MATCH(B3,$B$53:$Z$53,0)),"") -> agriculture and forestry 01T03 | D3: =SIOM!C48 -> 5034.6 | E3: =SIOM!D48 -> 8.1 | F3: =SIOM!E48 -> 0 | G3: =SIOM!F48 -> 22.4 | H3: =SIOM!G48 -> 8.2 | I3: =SIOM!H48 -> 30244.9 | J3: =SIOM!I48 -> 425.8 | K3: =SIOM!J48 -> 494.3 | ... AT3: =SIOM!AS48 -> 0
A4: ISIC 05 | B4: coal mining 05 | C4: =IFERROR(INDEX($B$54:$Z$54,MATCH(B4,$B$53:$Z$53,0)),"") -> coal mining 05 | D4: =SIOM!C49 -> 18.87218 | E4: =SIOM!D49 -> 0 | F4: =SIOM!E49 -> 110.86035 | G4: =SIOM!F49 -> 7.1109162 | H4: =SIOM!G49 -> 89.603048 | I4: =SIOM!H49 -> 41.694548 | J4: =SIOM!I49 -> 3.1029939 | K4: =SIOM!J49 -> 0 | ... AT4: =SIOM!AS49 -> 0
A5: ISIC 06 | B5: oil and gas extraction 06 | C5: =IFERROR(INDEX($B$54:$Z$54,MATCH(B5,$B$53:$Z$53,0)),"") -> oil and gas extraction 06 | D5: =SIOM!C50 -> 29.42782 | E5: =SIOM!D50 -> 0 | F5: =SIOM!E50 -> 174.43965 | G5: =SIOM!F50 -> 11.189084 | H5: =SIOM!G50 -> 132.89695 | I5: =SIOM!H50 -> 61.105452 | J5: =SIOM!I50 -> 5.0970061 | K5: =SIOM!J50 -> 0 | ... AT5: =SIOM!AS50 -> 0
A6: ISIC 07T08 | B6: other mining and quarrying 07T08 | C6: =IFERROR(INDEX($B$54:$Z$54,MATCH(B6,$B$53:$Z$53,0)),"") -> other mining and quarrying 07T08 | D6: =SIOM!C51 -> 56.1 | E6: =SIOM!D51 -> 19.8 | F6: =SIOM!E51 -> 0 | G6: =SIOM!F51 -> 613.3 | H6: =SIOM!G51 -> 59.5 | I6: =SIOM!H51 -> 40.7 | J6: =SIOM!I51 -> 6.9 | K6: =SIOM!J51 -> 2.6 | ... AT6: =SIOM!AS51 -> 0
A7: ISIC 09 | B7: 0 | C7: =IFERROR(INDEX($B$54:$Z$54,MATCH(B7,$B$53:$Z$53,0)),"") | D7: =SIOM!C52 -> 665.7 | E7: =SIOM!D52 -> 0 | F7: =SIOM!E52 -> 3004.1 | G7: =SIOM!F52 -> 870.4 | H7: =SIOM!G52 -> 2312.7 | I7: =SIOM!H52 -> 171.5 | J7: =SIOM!I52 -> 0.4 | K7: =SIOM!J52 -> 7.1 | ... AT7: =SIOM!AS52 -> 0
A8: ISIC 10T12 | B8: food beverage and tobacco 10T12 | C8: =IFERROR(INDEX($B$54:$Z$54,MATCH(B8,$B$53:$Z$53,0)),"") -> food beverage and tobacco 10T12 | D8: =SIOM!C53 -> 3366 | E8: =SIOM!D53 -> 6.6 | F8: =SIOM!E53 -> 0 | G8: =SIOM!F53 -> 12.3 | H8: =SIOM!G53 -> 7.3 | I8: =SIOM!H53 -> 14358.9 | J8: =SIOM!I53 -> 395.2 | K8: =SIOM!J53 -> 12.6 | ... AT8: =SIOM!AS53 -> 0
A9: ISIC 13T15 | B9: textiles apparel and leather 13T15 | C9: =IFERROR(INDEX($B$54:$Z$54,MATCH(B9,$B$53:$Z$53,0)),"") -> other manufacturing 31T33 | D9: =SIOM!C54 -> 99.8 | E9: =SIOM!D54 -> 0 | F9: =SIOM!E54 -> 19 | G9: =SIOM!F54 -> 29.3 | H9: =SIOM!G54 -> 23.5 | I9: =SIOM!H54 -> 121.2 | J9: =SIOM!I54 -> 5021 | K9: =SIOM!J54 -> 20.4 | ... AT9: =SIOM!AS54 -> 0
A10: ISIC 16 | B10: wood products 16 | C10: =IFERROR(INDEX($B$54:$Z$54,MATCH(B10,$B$53:$Z$53,0)),"") -> other manufacturing 31T33 | D10: =SIOM!C55 -> 39.9 | E10: =SIOM!D55 -> 12.1 | F10: =SIOM!E55 -> 0 | G10: =SIOM!F55 -> 30 | H10: =SIOM!G55 -> 8.6 | I10: =SIOM!H55 -> 65.2 | J10: =SIOM!I55 -> 20 | K10: =SIOM!J55 -> 586.7 | ... AT10: =SIOM!AS55 -> 0
A11: ISIC 17T18 | B11: pulp paper and printing 17T18 | C11: =IFERROR(INDEX($B$54:$Z$54,MATCH(B11,$B$53:$Z$53,0)),"") -> pulp paper and printing 17T18 | D11: =SIOM!C56 -> 95.1 | E11: =SIOM!D56 -> 0 | F11: =SIOM!E56 -> 12.6 | G11: =SIOM!F56 -> 39.6 | H11: =SIOM!G56 -> 11.6 | I11: =SIOM!H56 -> 1611 | J11: =SIOM!I56 -> 372.5 | K11: =SIOM!J56 -> 61.1 | ... AT11: =SIOM!AS56 -> 0
A12: ISIC 19 | B12: refined petroleum and coke 19 | C12: =IFERROR(INDEX($B$54:$Z$54,MATCH(B12,$B$53:$Z$53,0)),"") -> refined petroleum and coke 19 | D12: =SIOM!C57 -> 1384.2 | E12: =SIOM!D57 -> 308.8 | F12: =SIOM!E57 -> 0 | G12: =SIOM!F57 -> 659.8 | H12: =SIOM!G57 -> 340.1 | I12: =SIOM!H57 -> 777.3 | J12: =SIOM!I57 -> 152.9 | K12: =SIOM!J57 -> 62.7 | ... AT12: =SIOM!AS57 -> 0
A13: ISIC 20 | B13: chemicals 20 | C13: =IFERROR(INDEX($B$54:$Z$54,MATCH(B13,$B$53:$Z$53,0)),"") -> chemicals 20 | D13: =SIOM!C58 -> 0 | E13: =SIOM!D58 -> 189.61855 | F13: =SIOM!E58 -> 0 | G13: =SIOM!F58 -> 0 | H13: =SIOM!G58 -> 0 | I13: =SIOM!H58 -> 0 | J13: =SIOM!I58 -> 0 | K13: =SIOM!J58 -> 242.6 | ... AT13: =SIOM!AS58 -> 0
A14: ISIC 21 | B14: chemicals 20 | C14: =IFERROR(INDEX($B$54:$Z$54,MATCH(B14,$B$53:$Z$53,0)),"") -> chemicals 20 | D14: =SIOM!C59 -> 2698.2 | E14: =SIOM!D59 -> 0 | F14: =SIOM!E59 -> 32.58145 | G14: =SIOM!F59 -> 415 | H14: =SIOM!G59 -> 159.5 | I14: =SIOM!H59 -> 1414.1 | J14: =SIOM!I59 -> 1437.5 | K14: =SIOM!J59 -> 0 | ... AT14: =SIOM!AS59 -> 0
A15: ISIC 22 | B15: rubber and plastic products 22 | C15: =IFERROR(INDEX($B$54:$Z$54,MATCH(B15,$B$53:$Z$53,0)),"") -> rubber and plastic products 22 | D15: =SIOM!C60 -> 164.5 | E15: =SIOM!D60 -> 0 | F15: =SIOM!E60 -> 77 | G15: =SIOM!F60 -> 139.9 | H15: =SIOM!G60 -> 73.7 | I15: =SIOM!H60 -> 1869.2 | J15: =SIOM!I60 -> 399.1 | K15: =SIOM!J60 -> 56.9 | ... AT15: =SIOM!AS60 -> 0
A16: ISIC 231 | B16: glass and glass products 231 | C16: =IFERROR(INDEX($B$54:$Z$54,MATCH(B16,$B$53:$Z$53,0)),"") -> glass and glass products 231 | D16: =SIOM!C61 -> 48.051096 | E16: =SIOM!D61 -> 0 | F16: =SIOM!E61 -> 16.637674 | G16: =SIOM!F61 -> 69.068238 | H16: =SIOM!G61 -> 25.829702 | I16: =SIOM!H61 -> 378.45733 | J16: =SIOM!I61 -> 22.166527 | K16: =SIOM!J61 -> 0 | ... AT16: =SIOM!AS61 -> 0
A17: ISIC 239 | B17: cement and other nonmetallic minerals 239 | C17: =IFERROR(INDEX($B$54:$Z$54,MATCH(B17,$B$53:$Z$53,0)),"") -> cement and other nonmetallic minerals 239 | D17: =SIOM!C62 -> 39.548904 | E17: =SIOM!D62 -> 0 | F17: =SIOM!E62 -> 13.762326 | G17: =SIOM!F62 -> 57.131762 | H17: =SIOM!G62 -> 21.170298 | I17: =SIOM!H62 -> 310.24267 | J17: =SIOM!I62 -> 18.933473 | K17: =SIOM!J62 -> 0 | ... AT17: =SIOM!AS62 -> 0
A18: ISIC 241 | B18: iron and steel 241 | C18: =IFERROR(INDEX($B$54:$Z$54,MATCH(B18,$B$53:$Z$53,0)),"") -> iron and steel 241 | D18: =SIOM!C63 -> 48.6 | E18: =SIOM!D63 -> 0 | F18: =SIOM!E63 -> 102.60654 | G18: =SIOM!F63 -> 126.3 | H18: =SIOM!G63 -> 192.1 | I18: =SIOM!H63 -> 246.9 | J18: =SIOM!I63 -> 15.5 | K18: =SIOM!J63 -> 0 | ... AT18: =SIOM!AS63 -> 0
A19: ISIC 242 | B19: other metals 242 | C19: =IFERROR(INDEX($B$54:$Z$54,MATCH(B19,$B$53:$Z$53,0)),"") -> other metals 242 | D19: =SIOM!C64 -> 0 | E19: =SIOM!D64 -> 5.7934608 | F19: =SIOM!E64 -> 0 | G19: =SIOM!F64 -> 0 | H19: =SIOM!G64 -> 0 | I19: =SIOM!H64 -> 0 | J19: =SIOM!I64 -> 0 | K19: =SIOM!J64 -> 11.3 | ... AT19: =SIOM!AS64 -> 0
... A26: ISIC 31T33 | B26: other manufacturing 31T33 | C26: =IFERROR(INDEX($B$54:$Z$54,MATCH(B26,$B$53:$Z$53,0)),"") -> other manufacturing 31T33 | D26: =SIOM!C71 -> 44.9 | E26: =SIOM!D71 -> 0 | F26: =SIOM!E71 -> 19.8 | G26: =SIOM!F71 -> 21.2 | H26: =SIOM!G71 -> 15.2 | I26: =SIOM!H71 -> 121.7 | J26: =SIOM!I71 -> 173.5 | K26: =SIOM!J71 -> 23 | ... AT26: =SIOM!AS71 -> 0
A27: ISIC 351 | B27: 0 | C27: =IFERROR(INDEX($B$54:$Z$54,MATCH(B27,$B$53:$Z$53,0)),"") | D27: =SIOM!C72 -> 37.648904 | E27: =SIOM!D72 -> 0 | F27: =SIOM!E72 -> 28.03999 | G27: =SIOM!F72 -> 56.629334 | H27: =SIOM!G72 -> 12.851086 | I27: =SIOM!H72 -> 96.804761 | J27: =SIOM!I72 -> 25.79275 | K27: =SIOM!J72 -> 0 | ... AT27: =SIOM!AS72 -> 0
A28: ISIC 352T353 | B28: energy pipelines and gas processing 352T353 | C28: =IFERROR(INDEX($B$54:$Z$54,MATCH(B28,$B$53:$Z$53,0)),"") -> energy pipelines and gas processing 352T353 | D28: =SIOM!C73 -> 3.3055627 | E28: =SIOM!D73 -> 0 | F28: =SIOM!E73 -> 2.4611409 | G28: =SIOM!F73 -> 4.9705001 | H28: =SIOM!G73 -> 1.1302086 | I28: =SIOM!H73 -> 8.5353462 | J28: =SIOM!I73 -> 2.2106184 | K28: =SIOM!J73 -> 0 | ... AT28: =SIOM!AS73 -> 0
A29: ISIC 36T39 | B29: water and waste 36T39 | C29: =IFERROR(INDEX($B$54:$Z$54,MATCH(B29,$B$53:$Z$53,0)),"") -> water and waste 36T39 | D29: =SIOM!C74 -> 123.74553 | E29: =SIOM!D74 -> 0 | F29: =SIOM!E74 -> 91.998869 | G29: =SIOM!F74 -> 185.80017 | H29: =SIOM!G74 -> 43.718705 | I29: =SIOM!H74 -> 321.75989 | J29: =SIOM!I74 -> 75.996631 | K29: =SIOM!J74 -> 0 | ... AT29: =SIOM!AS74 -> 0
A30: ISIC 41T43 | B30: construction 41T43 | C30: =IFERROR(INDEX($B$54:$Z$54,MATCH(B30,$B$53:$Z$53,0)),"") -> construction 41T43 | D30: =SIOM!C75 -> 67.9 | E30: =SIOM!D75 -> 216.1 | F30: =SIOM!E75 -> 0 | G30: =SIOM!F75 -> 99.2 | H30: =SIOM!G75 -> 167.5 | I30: =SIOM!H75 -> 26.6 | J30: =SIOM!I75 -> 4.8 | K30: =SIOM!J75 -> 2.7 | ... AT30: =SIOM!AS75 -> 0
A31: ISIC 45T47 | B31: 0 | C31: =IFERROR(INDEX($B$54:$Z$54,MATCH(B31,$B$53:$Z$53,0)),"") | D31: =SIOM!C76 -> 4729.5 | E31: =SIOM!D76 -> 475 | F31: =SIOM!E76 -> 0 | G31: =SIOM!F76 -> 783.9 | H31: =SIOM!G76 -> 429.4 | I31: =SIOM!H76 -> 20136.8 | J31: =SIOM!I76 -> 3266.7 | K31: =SIOM!J76 -> 525.2 | ... AT31: =SIOM!AS76 -> 0
A32: ISIC 49T53 | B32: 0 | C32: =IFERROR(INDEX($B$54:$Z$54,MATCH(B32,$B$53:$Z$53,0)),"") | D32: =SIOM!C77 -> 1250.6 | E32: =SIOM!D77 -> 258 | F32: =SIOM!E77 -> 0 | G32: =SIOM!F77 -> 410.3 | H32: =SIOM!G77 -> 196.9 | I32: =SIOM!H77 -> 4910.7 | J32: =SIOM!I77 -> 700.5 | K32: =SIOM!J77 -> 158.6 | ... AT32: =SIOM!AS77 -> 0
A33: ISIC 55T56 | B33: 0 | C33: =IFERROR(INDEX($B$54:$Z$54,MATCH(B33,$B$53:$Z$53,0)),"") | D33: =SIOM!C78 -> 8.1 | E33: =SIOM!D78 -> 0 | F33: =SIOM!E78 -> 3.8 | G33: =SIOM!F78 -> 2.9 | H33: =SIOM!G78 -> 5.9 | I33: =SIOM!H78 -> 33.4 | J33: =SIOM!I78 -> 7.1 | K33: =SIOM!J78 -> 1.7 | ... AT33: =SIOM!AS78 -> 0
A34: ISIC 58T60 | B34: 0 | C34: =IFERROR(INDEX($B$54:$Z$54,MATCH(B34,$B$53:$Z$53,0)),"") | D34: =SIOM!C79 -> 12.6 | E34: =SIOM!D79 -> 0 | F34: =SIOM!E79 -> 6.8 | G34: =SIOM!F79 -> 4.9 | H34: =SIOM!G79 -> 4.9 | I34: =SIOM!H79 -> 153.5 | J34: =SIOM!I79 -> 8.7 | K34: =SIOM!J79 -> 2.6 | ... AT34: =SIOM!AS79 -> 0
A35: ISIC 61 | B35: 0 | C35: =IFERROR(INDEX($B$54:$Z$54,MATCH(B35,$B$53:$Z$53,0)),"") | D35: =SIOM!C80 -> 36.4 | E35: =SIOM!D80 -> 0 | F35: =SIOM!E80 -> 8.9 | G35: =SIOM!F80 -> 20.4 | H35: =SIOM!G80 -> 15.6 | I35: =SIOM!H80 -> 86.8 | J35: =SIOM!I80 -> 30.3 | K35: =SIOM!J80 -> 5.6 | ... AT35: =SIOM!AS80 -> 0
A36: ISIC 62T63 | B36: 0 | C36: =IFERROR(INDEX($B$54:$Z$54,MATCH(B36,$B$53:$Z$53,0)),"") | D36: =SIOM!C81 -> 7.8 | E36: =SIOM!D81 -> 0 | F36: =SIOM!E81 -> 2.8 | G36: =SIOM!F81 -> 2.6 | H36: =SIOM!G81 -> 1.7 | I36: =SIOM!H81 -> 33.2 | J36: =SIOM!I81 -> 10.6 | K36: =SIOM!J81 -> 1.3 | ... AT36: =SIOM!AS81 -> 0
A37: ISIC 64T66 | B37: 0 | C37: =IFERROR(INDEX($B$54:$Z$54,MATCH(B37,$B$53:$Z$53,0)),"") | D37: =SIOM!C82 -> 209.5 | E37: =SIOM!D82 -> 92.9 | F37: =SIOM!E82 -> 0 | G37: =SIOM!F82 -> 75.4 | H37: =SIOM!G82 -> 41.1 | I37: =SIOM!H82 -> 284.7 | J37: =SIOM!I82 -> 84.1 | K37: =SIOM!J82 -> 21.7 | ... AT37: =SIOM!AS82 -> 0
A38: ISIC 68 | B38: 0 | C38: =IFERROR(INDEX($B$54:$Z$54,MATCH(B38,$B$53:$Z$53,0)),"") | D38: =SIOM!C83 -> 95.5 | E38: =SIOM!D83 -> 0 | F38: =SIOM!E83 -> 76.7 | G38: =SIOM!F83 -> 19.7 | H38: =SIOM!G83 -> 13.7 | I38: =SIOM!H83 -> 396.8 | J38: =SIOM!I83 -> 159.9 | K38: =SIOM!J83 -> 22.8 | ... AT38: =SIOM!AS83 -> 0
A39: ISIC 69T82 | B39: 0 | C39: =IFERROR(INDEX($B$54:$Z$54,MATCH(B39,$B$53:$Z$53,0)),"") | D39: =SIOM!C84 -> 544.1 | E39: =SIOM!D84 -> 0 | F39: =SIOM!E84 -> 494.5 | G39: =SIOM!F84 -> 153.9 | H39: =SIOM!G84 -> 241.2 | I39: =SIOM!H84 -> 3271.1 | J39: =SIOM!I84 -> 228.7 | K39: =SIOM!J84 -> 129.3 | ... AT39: =SIOM!AS84 -> 0
A40: ISIC 84 | B40: 0 | C40: =IFERROR(INDEX($B$54:$Z$54,MATCH(B40,$B$53:$Z$53,0)),"") | D40: =SIOM!C85 -> 6.5 | E40: =SIOM!D85 -> 0 | F40: =SIOM!E85 -> 3.8 | G40: =SIOM!F85 -> 4.1 | H40: =SIOM!G85 -> 2.5 | I40: =SIOM!H85 -> 10.7 | J40: =SIOM!I85 -> 4.9 | K40: =SIOM!J85 -> 1.1 | ... AT40: =SIOM!AS85 -> 0
A41: ISIC 85 | B41: 0 | C41: =IFERROR(INDEX($B$54:$Z$54,MATCH(B41,$B$53:$Z$53,0)),"") | D41: =SIOM!C86 -> 3.1 | E41: =SIOM!D86 -> 7.5 | F41: =SIOM!E86 -> 0 | G41: =SIOM!F86 -> 5.7 | H41: =SIOM!G86 -> 0.9 | I41: =SIOM!H86 -> 12.1 | J41: =SIOM!I86 -> 3.8 | K41: =SIOM!J86 -> 0.7 | ... AT41: =SIOM!AS86 -> 0
A42: ISIC 86T88 | B42: 0 | C42: =IFERROR(INDEX($B$54:$Z$54,MATCH(B42,$B$53:$Z$53,0)),"") | D42: =SIOM!C87 -> 30 | E42: =SIOM!D87 -> 0 | F42: =SIOM!E87 -> 2.6 | G42: =SIOM!F87 -> 0.6 | H42: =SIOM!G87 -> 0.3 | I42: =SIOM!H87 -> 126.3 | J42: =SIOM!I87 -> 3.4 | K42: =SIOM!J87 -> 4.5 | ... AT42: =SIOM!AS87 -> 0
... A44: ISIC 97T98 | B44: 0 | C44: =IFERROR(INDEX($B$54:$Z$54,MATCH(B44,$B$53:$Z$53,0)),"") | D44: =SIOM!C89 -> 0 | E44: =SIOM!D89 -> 0 | F44: =SIOM!E89 -> 0 | G44: =SIOM!F89 -> 0 | H44: =SIOM!G89 -> 0 | I44: =SIOM!H89 -> 0 | J44: =SIOM!I89 -> 0 | K44: =SIOM!J89 -> 0 | ... AT44: =SIOM!AS89 -> 0
A49: EU ISIC Consolidation
A50: Default EPS ISIC Groupings | B50: ISIC 01T03 | D50: ISIC 05 | E50: ISIC 06 | F50: ISIC 07T08 | G50: ISIC 09 | H50: ISIC 10T12 | I50: ISIC 13T15 | J50: ISIC 16 | K50: ISIC 17T18 | L50: ISIC 19 | M50: ISIC 20 | N50: ISIC 21 | O50: ISIC 22 | P50: ISIC 231 | Q50: ISIC 239 | R50: ISIC 241 | S50: ISIC 242 | T50: ISIC 25 | U50: ISIC 26 | V50: ISIC 27 | W50: ISIC 28 | X50: ISIC 29 | Y50: ISIC 30 | Z50: ISIC 31T33 | AA50: ISIC 351 | AB50: ISIC 352T353 | AC50: ISIC 36T39 | AD50: ISIC 41T43 | AE50: ISIC 45T47 | AF50: ISIC 49T53 | AG50: ISIC 55T56 | AH50: ISIC 58T60 | AI50: ISIC 61 | AJ50: ISIC 62T63 | AK50: ISIC 64T66 | AL50: ISIC 68 | AM50: ISIC 69T82 | AN50: ISIC 84 | AO50: ISIC 85 | AP50: ISIC 86T88 | AQ50: ISIC 90T96 | AR50: ISIC 97T98
A51: Mexico ISIC Groupings | B51: ISIC 01T03 | D51: ISIC 05 | E51: ISIC 06 | F51: ISIC 07T08 | G51: ISIC 09 | H51: ISIC 10T12 | I51: ISIC 31T33 | J51: ISIC 31T33 | K51: ISIC 17T18 | L51: ISIC 19 | M51: ISIC 20 | N51: ISIC 21 | O51: ISIC 22 | P51: ISIC 231 | Q51: ISIC 239 | R51: ISIC 241 | S51: ISIC 242 | T51: ISIC 31T33 | U51: ISIC 31T33 | V51: ISIC 31T33 | W51: ISIC 31T33 | X51: ISIC 29 | Y51: ISIC 31T33 | Z51: ISIC 31T33 | AA51: ISIC 351 | AB51: ISIC 352T353 | AC51: ISIC 36T39 | AD51: ISIC 41T43 | AE51: ISIC 45T47 | AF51: ISIC 49T53 | AG51: ISIC 55T56 | AH51: ISIC 58T60 | AI51: ISIC 61 | AJ51: ISIC 62T63 | AK51: ISIC 64T66 | AL51: ISIC 68 | AM51: ISIC 69T82 | AN51: ISIC 84 | AO51: ISIC 85 | AP51: ISIC 86T88 | AQ51: ISIC 90T96 | AR51: ISIC 97T98
A53: Default EPS Industry Groupings | B53: agriculture and forestry 01T03 | C53: coal mining 05 | D53: oil and gas extraction 06 | E53: other mining and quarrying 07T08 | F53: food beverage and tobacco 10T12 | G53: textiles apparel and leather 13T15 | H53: wood products 16 | I53: pulp paper and printing 17T18 | J53: refined petroleum and coke 19 | K53: chemicals 20 | L53: rubber and plastic products 22 | M53: glass and glass products 231 | N53: cement and other nonmetallic minerals 239 | O53: iron and steel 241 | P53: other metals 242 | Q53: metal products except machinery and vehicles 25 | R53: computers and electronics 26 | S53: appliances and electrical equipment 27 | T53: other machinery 28 | U53: road vehicles 29 | V53: nonroad vehicles 30 | W53: other manufacturing 31T33 | X53: energy pipelines and gas processing 352T353 | Y53: water and waste 36T39 | Z53: construction 41T43
