Workbook
Name Fraction_coal: [1]About!#REF!
Name gal_per_barrel: [2]About!$A$63
Name Percent_rural: [1]About!#REF!
Name Percent_urban: [1]About!#REF!
Name quadrillion: [1]About!$B$62
Name Table4: #REF!
Name Table4_1: #REF!
Name Table4_A: #REF!
Name Table5: #REF!
Name Table5_1: #REF!
Name Table5_A: #REF!
Name UrbFrac: '[3]MX urban Rural'!$B$3

Sheet About
A1: BFPIaE BAU Fuel Production
A2: BFPIaE BAU Fuel Imports
A3: BFPIaE BAU Fuel Exports
A5: Source: | B5: Petroleum-based fuels, biofuels | F5: National Energy Balance
B6: U.S. Energy Information Administration | F6: Sistema de Información Energética
B7: 2019 | F7: Secretaría de Energía
B8: Petroleum & Other Liquids: Supply and Disposition | F8: Dirección General de Planeación e Información Energéticas
B9: https://www.eia.gov/dnav/pet/pet_sum_snd_d_nus_mbbl_a_cur.htm | F9: Balance Nacional de Energía: Origen y destino de la energía
B10: Area: US, Period: Annual 2017 | F10: (petajoules)
F11: REALES 2019
B12: Nuclear Fuel (Uranium) | F12: https://www.gob.mx/sener/articulos/balance-nacional-de-energia-296106
B13: U.S. Energy Information Administration
B14: 2018
B15: U.S. uranium imports continue as domestic production remains at historical lows
B16: https://www.eia.gov/todayinenergy/detail.php?id=37192
B17: Paragraph 1
B19: Hard Coal, Lignite
B20: U.S. Energy Information Administration
B21: 2019
B22: Coal Explained: Where Our Coal Comes From
B23: https://www.eia.gov/energyexplained/index.php?page=coal_where
B24: https://www.eia.gov/energyexplained/index.php?page=coal_imports
B25: https://www.eia.gov/energyexplained/index.php?page=coal_prices
B27: Biomass Production and Exports
B28: U.S. Energy Information Administration
B29: 2017
B30: Monthly Densified Biomass Fuel Report
B31: https://www.eia.gov/biofuels/biomass/?year=2016&month=13#table_data
B32: Tables 4 and 8
B34: Biomass Imports and Exports (for Import to Export Ratio)
B35: U.S. International Trade Administration
B36: 2017
B37: 2016 Top Markets Report Renewable Fuels Sector Snapshot: Biomass Wood Pellets
B38: https://www.trade.gov/topmarkets/pdf/Renewable_Fuels_Biomass_Wood_Pellets.pdf
B39: Tables 2 and 3a
B41: Natural Gas, Time Series Scaling Factors
B42: U.S. Energy Information Administration
B43: 2019
B44: Annual Energy Outlook 2019
B45: https://www.eia.gov/outlooks/aeo/tables_ref.php
B46: Table 1
B48: Municipal Solid Waste
B49: U.S. Environmental Protection Agency
B50: 2016
B51: National Overview: Facts and Figures on Materials, Wastes and Recycling
B52: https://www.epa.gov/facts-and-figures-about-materials-waste-and-recycling/national-overview-facts-and-figures-materials
B54: Hydrogen
B55: U.S. Department of Energy
B56: 2018
B57: Fact of the Month May 2018: 10 Million Metric Tons of Hydrogen Produced Annually in the United States
B58: https://www.energy.gov/eere/fuelcells/fact-month-may-2018-10-million-metric-tons-hydrogen-produced-annually-united-states
B60: Unit Conversions for hard coal, natural gas, petroleum fuels, liquid biofuels
B61: Energy Information Administration
B62: 2020
B63: Annual Energy Outlook 2020
B64: http://www.eia.gov/forecasts/aeo/supplement/excel/suptab_73.xlsx
B65: Table 73
B67: Unit Conversions for Lignite, Biomass, LPG, municipal solid waste, hydrogen
B68: Argonne National Laboratory
B69: 2019
B70: GREET1 2019
B71: https://greet.es.anl.gov/
B72: Tab "Fuel_Specs"
B74: Unit Conversion for Uranium (U3O8)
B75: TradeTech
B76: 2019
B77: Uranium Primer - Price & Unit Conversion Calculator & Table
B78: https://www.uranium.info/unit_conversion_table.php
A80: Notes
A82: Collect Export, Import, and Production Data for Each Fuel
A83: The consolidated data in this variable (production, imports, exports, and domestic use of each fuel)
A84: is used in the variable fuels/CiFIaEpUDFS. Therefore, even though this variable only outputs
A85: production and exports, you should also collect data on fuel imports. (Domestic use data
A86: can be calculated from production, imports, and exports. We ignore changes in fuel stocks,
A87: which should average to zero over multi-year timeframes.)
A89: Time Series
A90: This variable contains time series data.
A91: However, only data from the first year are used in variable fuels/CiFIaEpUDFS.
A92: In the future, fuels/CiFIaEpUDFS may be replaced with internal Vensim calculations,
A93: making those values sensitive to changes over time.
... A107: or exported in bulk, so is included here.

Sheet Petroleum and Biofuel Data
A1: Area: US | B1: Period: 2017 (Annual) | D1: Unit: Thousand Barrels
B2: Supply | H2: Disposition | L2: Ending Stocks
B3: Field Production | C3: Renewable Fuels & Oxygenate Plant Net Production | D3: Refinery & Blender Net Production | E3: Imports | F3: Net Receipts | G3: Adjust- ments | H3: Stock Change | I3: Refinery & Blender Net Inputs | J3: Exports | K3: Products Supplied
A4: Crude Oil & Petroleum Products | B4: 4794078 | C4: 437131 | D4: 7408771 | E4: 3702640 | G4: 137262 | H4: -135002 | I4: 7003159 | J4: 2327156 | K4: 7284569 | L4: 1894570
A5: Crude Oil | B5: 3413376 | C5: - - | D5: - - | E5: 2908670 | G5: 60486 | H5: -95227 | I5: 6055241 | J5: 422518 | K5: 0 | L5: 1084477
A6: Hydrocarbon Gas Liquids | B6: 1380702 | C6: -7942 | D6: 229391 | E6: 71427 | G6: - - | H6: -10191 | I6: 206629 | J6: 512495 | K6: 964645 | L6: 190004
A7: Natural Gas Liquids | B7: 1380702 | C7: -7942 | D7: 127270 | E7: 60585 | G7: - - | H7: -6640 | I7: 206629 | J7: 512495 | K7: 848131 | L7: 184131
A8: Ethane | B8: 520504 | C8: - - | D8: 1958 | E8: - | G8: - - | H8: 4925 | J8: 64822 | K8: 452715 | L8: 55616
A9: Propane | B9: 451133 | C9: - - | D9: 111964 | E9: 48606 | G9: - - | H9: -14864 | J9: 333544 | K9: 293023 | L9: 62183
A10: Normal Butane | B10: 115086 | C10: - - | D10: 15710 | E10: 5504 | G10: - - | H10: 7939 | I10: 64779 | J10: 49568 | K10: 14014 | L10: 37821
A11: Isobutane | B11: 128589 | C11: - - | D11: -2362 | E11: 3735 | G11: - - | H11: 292 | I11: 77360 | J11: 1321 | K11: 50989 | L11: 8398
A12: Natural Gasoline | B12: 165390 | C12: -7942 | E12: 2740 | G12: - - | H12: -4932 | I12: 64490 | J12: 63240 | K12: 37390 | L12: 20113
A13: Refinery Olefins | B13: - - | C13: - - | D13: 102121 | E13: 10842 | G13: - - | H13: -3551 | I13: - - | J13: - - | K13: 116514 | L13: 5873
A14: Ethylene | B14: - - | C14: - - | D14: 270 | E14: - | G14: - - | H14: 0 | I14: - - | J14: - - | K14: 270 | L14: 0
A15: Propylene | B15: - - | C15: - - | D15: 103962 | E15: 8409 | G15: - - | H15: -2392 | I15: - - | J15: - - | K15: 114763 | L15: 4639
A16: Normal Butylene | B16: - - | C16: - - | D16: -2397 | E16: 2433 | G16: - - | H16: -1165 | I16: - - | J16: - - | K16: 1201 | L16: 1204
A17: Isobutylene | B17: - - | C17: - - | D17: 286 | E17: - | G17: - - | H17: 6 | I17: - - | J17: - - | K17: 280 | L17: 30
A18: Other Liquids | B18: - - | C18: 443737 | D18: - - | E18: 471784 | G18: 19117 | H18: 8685 | I18: 741289 | J18: 171592 | K18: 13072 | L18: 328230
A19: Hydrogen/Oxygenates/Renewables/Other Hydrocarbons | B19: - - | C19: 443788 | D19: - - | E19: 19778 | G19: 36824 | H19: 577 | I19: 439078 | J19: 60735 | K19: 0 | L19: 29585
A20: Hydrogen | B20: - - | C20: - - | D20: - - | G20: 81091 | H20: - - | I20: 81091 | K20: 0 | L20: - -
A21: Oxygenates (excl. Fuel Ethanol) | B21: - - | C21: 26360 | D21: - - | E21: 3835 | G21: -4811 | H21: -31 | I21: - | J21: 25415 | K21: 0 | L21: 1446
A22: Renewable Fuels (incl. Fuel Ethanol) | B22: - - | C22: 417428 | D22: - - | E22: 15707 | G22: -39640 | H22: 578 | I22: 357597 | J22: 35320 | K22: 0 | L22: 28092
A23: Fuel Ethanol | B23: - - | C23: 379435 | D23: - - | E23: 1824 | G23: -9859 | H23: 3285 | I23: 335023 | J23: 33092 | K23: 0 | L23: 23043
A24: Renewable Fuels Except Fuel Ethanol | B24: - - | C24: 37993 | D24: - - | E24: 13883 | G24: -29781 | H24: -2707 | I24: 22574 | J24: 2228 | K24: 0 | L24: 5049
A25: Other Hydrocarbons | B25: - - | C25: - - | D25: - - | E25: 236 | G25: 184 | H25: 30 | I25: 390 | K25: 0 | L25: 47
A26: Unfinished Oils | B26: - - | C26: - - | D26: - - | E26: 231478 | G26: - - | H26: 6013 | I26: 129406 | J26: 82949 | K26: 13110 | L26: 86337
A27: Motor Gasoline Blend. Comp. | B27: - - | C27: -51 | D27: - - | E27: 220528 | G27: -17707 | H27: 2089 | I27: 172773 | J27: 27908 | K27: 0 | L27: 212293
A28: Reformulated | B28: - - | C28: -3 | D28: - - | E28: 76948 | G28: 65150 | H28: 1299 | I28: 140697 | J28: 99 | K28: 0 | L28: 53447
A29: Conventional | B29: - - | C29: -48 | D29: - - | E29: 143580 | G29: -82856 | H29: 790 | I29: 32076 | J29: 27810 | K29: 0 | L29: 158846
A30: Aviation Gasoline Blend. Comp. | B30: - - | C30: - - | D30: - - | E30: - | G30: - - | H30: 6 | I30: 32 | J30: - | K30: -38 | L30: 15
A31: Finished Petroleum Products | B31: - - | C31: 1336 | D31: 7179380 | E31: 250759 | G31: 57659 | H31: -38269 | I31: - - | J31: 1220551 | K31: 6306852 | L31: 291859
A32: Finished Motor Gasoline | B32: - - | C32: 1336 | D32: 3633123 | E32: 11784 | G32: 27566 | H32: -3860 | I32: - - | J32: 273483 | K32: 3404186 | L32: 24523
A33: Reformulated | B33: - - | D33: 1187104 | E33: - | G33: -59342 | H33: -7 | I33: - - | J33: - | K33: 1127769 | L33: 40
A34: Conventional | B34: - - | C34: 1336 | D34: 2446019 | E34: 11784 | G34: 86908 | H34: -3853 | I34: - - | J34: 273483 | K34: 2276417 | L34: 24483
A35: Finished Aviation Gasoline | B35: - - | C35: - - | D35: 4032 | E35: 165 | G35: - - | H35: 47 | I35: - - | J35: - | K35: 4150 | L35: 1041
A36: Kerosene-Type Jet Fuel | B36: - - | C36: - - | D36: 621176 | E36: 58273 | G36: - - | H36: -1706 | I36: - - | J36: 67161 | K36: 613994 | L36: 41304
A37: Kerosene | B37: - - | C37: - - | D37: 2738 | E37: 1429 | G37: - - | H37: 10 | I37: - - | J37: 2267 | K37: 1890 | L37: 2138
A38: Distillate Fuel Oil | B38: - - | C38: - - | D38: 1833879 | E38: 54975 | G38: 30093 | H38: -20457 | I38: - - | J38: 504155 | K38: 1435249 | L38: 145638
A39: 15 ppm Sulfur and Under | B39: - - | C39: - - | D39: 1713652 | E39: 37012 | G39: 30093 | H39: -16256 | I39: - - | J39: 423862 | K39: 1373151 | L39: 128016
A40: Greater than 15 to 500 ppm Sulfur | B40: - - | C40: - - | D40: 42167 | E40: 759 | G40: - | H40: -929 | I40: - - | J40: 41645 | K40: 2210 | L40: 7480
A41: Greater than 500 ppm Sulfur | B41: - - | C41: - - | D41: 78060 | E41: 17204 | G41: - - | H41: -3272 | I41: - - | J41: 38648 | K41: 59888 | L41: 10142
A42: Residual Fuel Oil | B42: - - | C42: - - | D42: 155851 | E42: 69015 | G42: - - | H42: -12098 | I42: - - | J42: 112240 | K42: 124724 | L42: 29377
A43: Less than 0.31% Sulfur | B43: - - | C43: - - | D43: 18946 | E43: 4112 | G43: - - | H43: -2600 | I43: - - | J43: NA | K43: NA | L43: 1928
A44: 0.31 to 1.00% Sulfur | B44: - - | C44: - - | D44: 19577 | E44: 7295 | G44: - - | H44: -1119 | I44: - - | J44: NA | K44: NA | L44: 6822
A45: Greater than 1.00% Sulfur | B45: - - | C45: - - | D45: 117328 | E45: 57608 | G45: - - | H45: -8379 | I45: - - | J45: NA | K45: NA | L45: 20621
A46: Petrochemical Feedstocks | B46: - - | C46: - - | D46: 112198 | E46: 15696 | G46: - - | H46: -357 | I46: - - | J46: - | K46: 128251 | L46: 2883
A47: Naphtha for Petro. Feed. Use | B47: - - | C47: - - | D47: 71578 | E47: 11373 | G47: - - | H47: -162 | I47: - - | J47: - | K47: 83113 | L47: 1849
A48: Other Oils for Petro. Feed. Use | B48: - - | C48: - - | D48: 40620 | E48: 4323 | G48: - - | H48: -195 | I48: - - | J48: - | K48: 45138 | L48: 1034
A49: Special Naphthas | B49: - - | C49: - - | D49: 13688 | E49: 5405 | G49: - - | H49: -26 | I49: - - | J49: - | K49: 19119 | L49: 1192
A50: Lubricants | B50: - - | C50: - - | D50: 64970 | E50: 14901 | G50: - - | H50: -347 | I50: - - | J50: 36215 | K50: 44003 | L50: 12021
A51: Waxes | B51: - - | C51: - - | D51: 1774 | E51: 1724 | G51: - - | H51: 184 | I51: - - | J51: 1479 | K51: 1835 | L51: 855
A52: Petroleum Coke | B52: - - | C52: - - | D52: 329170 | E52: 3662 | G52: - - | H52: 1536 | I52: - - | J52: 215873 | K52: 115423 | L52: 8519
A53: Marketable | B53: - - | C53: - - | D53: 245213 | E53: 3662 | G53: - - | H53: 1536 | I53: - - | J53: 215873 | K53: 31466 | L53: 8519
A54: Catalyst | B54: - - | C54: - - | D54: 83957 | E54: - - | F54: - - | G54: - - | H54: - - | I54: - - | J54: - - | K54: 83957 | L54: - -
A55: Asphalt and Road Oil | B55: - - | C55: - - | D55: 120515 | E55: 13666 | G55: - - | H55: -1184 | I55: - - | J55: 7399 | K55: 127966 | L55: 21697
A56: Still Gas | B56: - - | C56: - - | D56: 251761 | E56: - - | F56: - - | G56: - - | H56: - - | I56: - - | J56: - - | K56: 251761 | L56: - -
A57: Miscellaneous Products | B57: - - | C57: - - | D57: 34505 | E57: 64 | G57: - - | H57: -11 | I57: - - | J57: 279 | K57: 34301 | L57: 671

Sheet Biomass Data
A1: Table 4. Production of densified biomass fuel, 2016 (tons)
A2: Region | B2: Month | C2: Wood Pellets, PFI Certified | D2: Wood Pellets, Not Certified | E2: Wood Pellets Utility | F2: Compressed Bricks/Logs
A3: U.S. Total
B4: 1 | C4: 95844 | D4: 79371 | E4: 421133 | F4: 1659
B5: 2 | C5: 65410 | D5: 63962 | E5: 388199 | F5: 1748
B6: 3 | C6: 60828 | D6: 49392 | E6: 413882 | F6: 1705
B7: 4 | C7: 63815 | D7: 45622 | E7: 419029 | F7: 1660
B8: 5 | C8: 72872 | D8: 62962 | E8: 447352 | F8: 1371
B9: 6 | C9: 63971 | D9: 69622 | E9: 425459 | F9: 2299
B10: 7 | C10: 66862 | D10: 56530 | E10: 473065 | F10: 2052
B11: 8 | C11: 81078 | D11: 77052 | E11: 427549 | F11: 2080
B12: 9 | C12: 78422 | D12: 77769 | E12: 425587 | F12: 1552
B13: 10 | C13: 78390 | D13: 70137 | E13: 445045 | F13: 1484
B14: 11 | C14: 59704 | D14: 69068 | E14: 470151 | F14: 992
B15: 12 | C15: 58607 | D15: 58819 | E15: 509468 | F15: 1208
A17: Table 8. Export sales and average price of densified biomass fuel, 2016
A18: Month | B18: Quantity (tons) | C18: Average Price (USD per ton)
A19: 1 | B19: 318480 | C19: 151.07
A20: 2 | B20: 432018 | C20: 145.75
A21: 3 | B21: 459937 | C21: 148.58
A22: 4 | B22: 317594 | C22: 155.75
A23: 5 | B23: 417765 | C23: 148.33
A24: 6 | B24: 538584 | C24: 147.9
A25: 7 | B25: 257482 | C25: 166.17
A26: 8 | B26: 391653 | C26: 149.42
A27: 9 | B27: 457496 | C27: 153.16
A28: 10 | B28: 400054 | C28: 129.94
A29: 11 | B29: 340954 | C29: 144.92
A30: 12 | B30: 495630 | C30: 144.99
A32: Total wood pellet production
A33: =SUM(C4:E15) -> 6892028 | B33: tons
A35: Total wood pellet exports
A36: =SUM(B19:B30) -> 4827647 | B36: tons
A38: We don't have biomass import data from EIA, but we do have some from the International Trade Administration (trade.gov).
A39: It uses different units and shows much higher wood pellet quantities than the EIA data, and it lacks production data.
A40: Accordingly, we only use it to establish a ratio of exports to imports, and apply that ratio to the EIA export data to
A41: estimate wood pellet imports (which are small compared to exports).
B43: Imports | C43: Exports | D43: Unit
A44: 2015 | B44: 207171527 | C44: 4668774792 | D44: kg
A46: Import to Export Ratio
A47: =B44/C44 -> 0.044373853
A49: Total wood pellet imports
A50: =A36*A47 -> 214221.3 | B50: tons

Sheet Uranium, Coal, MSW, Hydrogen
A1: Uranium
B2: Production | C2: Imports | D2: Exports | E2: Unit
A3: 2017 | B3: 3 | C3: 40 | D3: 0 | E3: million pounds U3O8
A5: Hard Coal and Lignite
A6: 0.09 | B6: of U.S. coal production was lignite in 2017
A7: 775 | B7: million short tons of coal produced (of all types) in 2017
A8: 97 | B8: million short tons of coal exported in 2017
A9: 6 | B9: million short tons of coal imported in 2017
A10: We assume that all imported and exported coal was hard coal, while all lignite produced was used domestically.
B12: Production | C12: Imports | D12: Exports | E12: Unit
A13: Hard Coal | B13: =A7*(1-A6) -> 705.25 | C13: =A9 -> 6 | D13: =A8 -> 97 | E13: million short tons
A14: Lignite | B14: =A6*A7 -> 69.75 | C14: 0 | D14: 0 | E14: million short tons
A16: Municipal Solid Waste
A17: MSW Tonnage Data for Year 2015
A18: 262.4 | B18: U.S. MSW generated (million tons)
A19: 33.57 | B19: U.S. MSW burned with energy recovery (million tons)
A20: 67.8 | B20: U.S. MSW recycled (million tons)
A21: 23.4 | B21: U.S. MSW composted (million tons)
A22: 137.7 | B22: U.S. MSW landfilled (million tons)
A24: Although the U.S. exports waste to other countries,
A25: it is difficult to find statistics for waste exports other than plastic waste.
A26: (Plastic waste exports to other countries in 2018 were
A27: 1.07 million metric tons in 2018.) | D27: https://www.plasticpollutioncoalition.org/pft/2019/3/6/157000-shipping-containers-of-us-plastic-waste-exported-to-countries-with-poor-waste-management-in-2018
A30: In this model, we are only concerned about MSW that is burned as a
A31: fuel. We will assume that a negligible amount of exported waste
A32: is used as a fuel.
A34: Hydrogen
A35: 10 | B35: million metric tons
A36: produced in 2018
A38: We assume none was imported or exported.

Sheet AEO Table 1
B1: highogs.d112619a | C1: 2019 | D1: 2020 | E1: 2021 | F1: 2022 | G1: 2023 | H1: 2024 | I1: 2025 | J1: 2026 | K1: 2027 | L1: 2028 | M1: 2029 | N1: 2030 | O1: 2031 | P1: 2032 | Q1: 2033 | R1: 2034 | S1: 2035 | T1: 2036 | U1: 2037 | V1: 2038 | W1: 2039 | X1: 2040 | Y1: 2041 | Z1: 2042 | AA1: 2043 | AB1: 2044 | AC1: 2045 | AD1: 2046 | AE1: 2047 | AF1: 2048 | AG1: 2049 | AH1: 2050
C3: Report | D3: Annual Energy Outlook 2020
C4: Scenario | D4: highogs | G4: High oil and gas supply
C5: Datekey | D5: d112619a
C6: Release Date | E6: January 2020
A10: SUP000 | B10: 1. Total Energy Supply, Disposition, and Price Summary
B11: (quadrillion Btu, unless otherwise noted)
AI12: 2019-
B13: Supply, Disposition, and Prices | C13: 2019 | D13: 2020 | E13: 2021 | F13: 2022 | G13: 2023 | H13: 2024 | I13: 2025 | J13: 2026 | K13: 2027 | L13: 2028 | M13: 2029 | N13: 2030 | O13: 2031 | P13: 2032 | Q13: 2033 | R13: 2034 | S13: 2035 | T13: 2036 | U13: 2037 | V13: 2038 | W13: 2039 | X13: 2040 | Y13: 2041 | Z13: 2042 | AA13: 2043 | AB13: 2044 | AC13: 2045 | AD13: 2046 | AE13: 2047 | AF13: 2048 | AG13: 2049 | AH13: 2050 | AI13: 2050
B15: Production
A16: SUP000:ba_CrudeOilLease | B16: Crude Oil and Lease Condensate | C16: 25.609802 | D16: 29.02322 | E16: 32.153172 | F16: 34.069309 | G16: 34.946575 | H16: 35.786289 | I16: 36.260719 | J16: 36.787514 | K16: 37.048611 | L16: 37.295334 | M16: 37.478222 | N16: 37.728161 | O16: 38.161762 | P16: 38.435223 | Q16: 38.808941 | R16: 38.440941 | S16: 38.606178 | T16: 38.570507 | U16: 38.509876 | V16: 38.289101 | W16: 38.237984 | X16: 38.24062 | Y16: 38.236805 | Z16: 38.273491 | AA16: 38.000069 | AB16: 37.980083 | AC16: 38.048946 | AD16: 38.124599 | AE16: 38.372814 | AF16: 38.755627 | AG16: 39.242901 | AH16: 39.56263 | AI16: 0.014128
A17: SUP000:ba_NaturalGasPla | B17: Natural Gas Plant Liquids | C17: 6.601902 | D17: 7.687216 | E17: 8.268795 | F17: 9.085635 | G17: 9.154001 | H17: 9.280481 | I17: 9.382998 | J17: 9.632951 | K17: 9.888704 | L17: 10.018386 | M17: 10.108791 | N17: 10.070297 | O17: 10.089097 | P17: 10.12474 | Q17: 10.179479 | R17: 10.167198 | S17: 10.201029 | T17: 10.205934 | U17: 10.177264 | V17: 10.230554 | W17: 10.229934 | X17: 10.224058 | Y17: 10.182619 | Z17: 10.205435 | AA17: 10.201748 | AB17: 10.166046 | AC17: 10.195329 | AD17: 10.23309 | AE17: 10.288787 | AF17: 10.369956 | AG17: 10.475321 | AH17: 10.553595 | AI17: 0.015248
A18: SUP000:ba_DryNaturalGas | B18: Dry Natural Gas | C18: 35.698853 | D18: 36.461613 | E18: 38.399319 | F18: 39.064152 | G18: 39.540783 | H18: 40.186932 | I18: 41.594856 | J18: 42.991825 | K18: 43.837154 | L18: 44.673092 | M18: 45.265652 | N18: 45.577869 | O18: 46.066223 | P18: 46.707607 | Q18: 47.376926 | R18: 47.925549 | S18: 48.427116 | T18: 49.248726 | U18: 49.617588 | V18: 50.274464 | W18: 50.788734 | X18: 51.329384 | Y18: 51.800266 | Z18: 52.29541 | AA18: 52.754333 | AB18: 53.282814 | AC18: 53.71896 | AD18: 54.344379 | AE18: 54.812981 | AF18: 55.301308 | AG18: 55.799816 | AH18: 56.345497 | AI18: 0.014831
A19: SUP000:ba_Coal | B19: Coal 1/ | C19: 13.570377 | D19: 12.323533 | E19: 11.59661 | F19: 11.398017 | G19: 10.785779 | H19: 10.465207 | I19: 9.428184 | J19: 9.61118 | K19: 9.565367 | L19: 9.448417 | M19: 9.282607 | N19: 9.118553 | O19: 9.030849 | P19: 9.008224 | Q19: 8.995221 | R19: 8.990909 | S19: 8.880076 | T19: 8.872306 | U19: 8.865554 | V19: 8.824455 | W19: 8.782435 | X19: 8.69428 | Y19: 8.630263 | Z19: 8.598111 | AA19: 8.579282 | AB19: 8.54311 | AC19: 8.502932 | AD19: 8.50601 | AE19: 8.48208 | AF19: 8.45368 | AG19: 8.459153 | AH19: 8.432384 | AI19: -0.015231
A20: SUP000:ba_NuclearPower | B20: Nuclear / Uranium 2/ | C20: 8.444346 | D20: 8.293446 | E20: 8.156399 | F20: 8.00432 | G20: 8.028068 | H20: 8.059065 | I20: 7.91081 | J20: 6.578477 | K20: 6.110461 | L20: 6.114827 | M20: 6.119108 | N20: 5.934624 | O20: 5.842663 | P20: 5.775915 | Q20: 5.617176 | R20: 5.362936 | S20: 5.377634 | T20: 4.883077 | U20: 4.885286 | V20: 4.510839 | W20: 4.330963 | X20: 4.33457 | Y20: 4.347668 | Z20: 4.273965 | AA20: 4.200269 | AB20: 4.048344 | AC20: 3.984968 | AD20: 3.918423 | AE20: 3.922881 | AF20: 3.925656 | AG20: 3.929009 | AH20: 3.933857 | AI20: -0.02434
A21: SUP000:ba_Hydropower | B21: Conventional Hydroelectric Power | C21: 2.62724 | D21: 2.630024 | E21: 2.608772 | F21: 2.555373 | G21: 2.500631 | H21: 2.447045 | I21: 2.414509 | J21: 2.335763 | K21: 2.301766 | L21: 2.286823 | M21: 2.274183 | N21: 2.265188 | O21: 2.258272 | P21: 2.247759 | Q21: 2.242433 | R21: 2.237327 | S21: 2.234227 | T21: 2.225456 | U21: 2.210283 | V21: 2.210092 | W21: 2.194727 | X21: 2.188682 | Y21: 2.171035 | Z21: 2.163268 | AA21: 2.149309 | AB21: 2.155904 | AC21: 2.147812 | AD21: 2.14894 | AE21: 2.147149 | AF21: 2.149729 | AG21: 2.138394 | AH21: 2.13362 | AI21: -0.006691
A22: SUP000:ba_Biomass | B22: Biomass 3/ | C22: 4.82518 | D22: 4.766847 | E22: 4.82663 | F22: 4.891224 | G22: 4.918721 | H22: 4.950122 | I22: 4.980151 | J22: 5.007463 | K22: 5.044035 | L22: 5.080586 | M22: 5.106367 | N22: 5.128502 | O22: 5.144773 | P22: 5.152127 | Q22: 5.16701 | R22: 5.174049 | S22: 5.189386 | T22: 5.204069 | U22: 5.213857 | V22: 5.227988 | W22: 5.239909 | X22: 5.257756 | Y22: 5.283101 | Z22: 5.29576 | AA22: 5.319311 | AB22: 5.350887 | AC22: 5.378565 | AD22: 5.424164 | AE22: 5.462148 | AF22: 5.500999 | AG22: 5.546075 | AH22: 5.598709 | AI22: 0.004808
A23: SUP000:ba_RenewableEner | B23: Other Renewable Energy 4/ | C23: 3.98661 | D23: 4.494395 | E23: 5.065486 | F23: 5.872777 | G23: 6.29326 | H23: 6.385596 | I23: 6.742633 | J23: 6.775188 | K23: 6.839761 | L23: 6.913706 | M23: 7.030445 | N23: 7.305614 | O23: 7.369681 | P23: 7.379068 | Q23: 7.407632 | R23: 7.451074 | S23: 7.710938 | T23: 7.802966 | U23: 7.833769 | V23: 7.879764 | W23: 7.930049 | X23: 7.981818 | Y23: 8.045572 | Z23: 8.143557 | AA23: 8.303351 | AB23: 8.493343 | AC23: 8.690237 | AD23: 8.881924 | AE23: 9.096939 | AF23: 9.320292 | AG23: 9.595012 | AH23: 9.894312 | AI23: 0.029757
A24: SUP000:ba_Other | B24: Other 5/ | C24: 1.418818 | D24: 0.77089 | E24: 0.736356 | F24: 0.77303 | G24: 0.854863 | H24: 0.881459 | I24: 0.815687 | J24: 0.66516 | K24: 0.622542 | L24: 0.637312 | M24: 0.628271 | N24: 0.584811 | O24: 0.578334 | P24: 0.588707 | Q24: 0.567073 | R24: 0.580399 | S24: 0.578376 | T24: 0.572439 | U24: 0.595171 | V24: 0.595104 | W24: 0.595701 | X24: 0.590376 | Y24: 0.600907 | Z24: 0.597535 | AA24: 0.601193 | AB24: 0.603373 | AC24: 0.607764 | AD24: 0.608229 | AE24: 0.612571 | AF24: 0.614231 | AG24: 0.617509 | AH24: 0.612761 | AI24: -0.026721
A25: SUP000:ba_Total | B25: Total | C25: 102.78312 | D25: 106.45117 | E25: 111.81154 | F25: 115.71384 | G25: 117.02268 | H25: 118.44222 | I25: 119.53055 | J25: 120.38552 | K25: 121.25841 | L25: 122.46849 | M25: 123.29364 | N25: 123.71362 | O25: 124.54166 | P25: 125.41937 | Q25: 126.36188 | R25: 126.33038 | S25: 127.20496 | T25: 127.58548 | U25: 127.90865 | V25: 128.04236 | W25: 128.33043 | X25: 128.84155 | Y25: 129.29825 | Z25: 129.84653 | AA25: 130.10887 | AB25: 130.6239 | AC25: 131.27551 | AD25: 132.18977 | AE25: 133.19835 | AF25: 134.39149 | AG25: 135.80318 | AH25: 137.06737 | AI25: 0.009329
B27: Imports
A28: SUP000:ca_CrudeOil | B28: Crude Oil | C28: 15.557913 | D28: 14.53161 | E28: 10.839822 | F28: 9.283045 | G28: 9.711083 | H28: 9.396487 | I28: 8.376527 | J28: 8.779516 | K28: 8.26525 | L28: 7.740358 | M28: 7.331103 | N28: 5.658647 | O28: 5.515424 | P28: 5.242305 | Q28: 4.703898 | R28: 5.036331 | S28: 5.039837 | T28: 4.886359 | U28: 5.357675 | V28: 5.245924 | W28: 5.107249 | X28: 5.233577 | Y28: 5.783911 | Z28: 5.680748 | AA28: 5.922231 | AB28: 5.976051 | AC28: 5.866432 | AD28: 5.936519 | AE28: 5.963267 | AF28: 5.832415 | AG28: 6.03104 | AH28: 5.868403 | AI28: -0.030962
A29: SUP000:ca_PetroleumProd | B29: Petroleum and Other Liquids 6/ | C29: 4.818967 | D29: 4.202692 | E29: 4.255038 | F29: 4.344409 | G29: 4.310221 | H29: 4.204672 | I29: 4.051309 | J29: 3.73584 | K29: 3.758186 | L29: 3.626599 | M29: 3.472314 | N29: 3.533805 | O29: 3.499255 | P29: 3.403134 | Q29: 3.427885 | R29: 3.436105 | S29: 3.391357 | T29: 3.327733 | U29: 3.427994 | V29: 3.385025 | W29: 3.394435 | X29: 3.420483 | Y29: 3.419091 | Z29: 3.424332 | AA29: 3.42945 | AB29: 3.433667 | AC29: 3.463475 | AD29: 3.521511 | AE29: 3.534636 | AF29: 3.576368 | AG29: 3.644244 | AH29: 3.693158 | AI29: -0.008546
A30: SUP000:ca_NaturalGas | B30: Natural Gas | C30: 2.79107 | D30: 2.72174 | E30: 2.397942 | F30: 2.310857 | G30: 2.205464 | H30: 2.171041 | I30: 2.251062 | J30: 2.344378 | K30: 2.18932 | L30: 1.897442 | M30: 1.81331 | N30: 1.769985 | O30: 1.839804 | P30: 1.766449 | Q30: 1.596209 | R30: 1.557857 | S30: 1.522343 | T30: 1.501905 | U30: 1.505041 | V30: 1.486304 | W30: 1.46496 | X30: 1.443362 | Y30: 1.435708 | Z30: 1.394784 | AA30: 1.341333 | AB30: 1.28926 | AC30: 1.263642 | AD30: 1.222849 | AE30: 1.183778 | AF30: 1.151181 | AG30: 1.138505 | AH30: 1.106201 | AI30: -0.029413
A31: SUP000:ca_OtherImports | B31: Other 7/ | C31: 0.291597 | D31: 0.311465 | E31: 0.198491 | F31: 0.188917 | G31: 0.184921 | H31: 0.188236 | I31: 0.177557 | J31: 0.183053 | K31: 0.197399 | L31: 0.203696 | M31: 0.201345 | N31: 0.209987 | O31: 0.201656 | P31: 0.210156 | Q31: 0.210358 | R31: 0.21874 | S31: 0.21698 | T31: 0.212136 | U31: 0.210972 | V31: 0.209018 | W31: 0.209871 | X31: 0.208984 | Y31: 0.210388 | Z31: 0.208157 | AA31: 0.206515 | AB31: 0.203912 | AC31: 0.201447 | AD31: 0.199199 | AE31: 0.19695 | AF31: 0.196395 | AG31: 0.194942 | AH31: 0.191452 | AI31: -0.01348
A32: SUP000:ca_Total | B32: Total | C32: 23.459549 | D32: 21.767506 | E32: 17.691294 | F32: 16.127226 | G32: 16.41169 | H32: 15.960435 | I32: 14.856455 | J32: 15.042787 | K32: 14.410155 | L32: 13.468095 | M32: 12.818072 | N32: 11.172423 | O32: 11.056138 | P32: 10.622044 | Q32: 9.938349 | R32: 10.249033 | S32: 10.170517 | T32: 9.928134 | U32: 10.501682 | V32: 10.326272 | W32: 10.176515 | X32: 10.306406 | Y32: 10.849097 | Z32: 10.70802 | AA32: 10.899529 | AB32: 10.902891 | AC32: 10.794995 | AD32: 10.880077 | AE32: 10.878632 | AF32: 10.756359 | AG32: 11.00873 | AH32: 10.859214 | AI32: -0.024541
B34: Exports
A35: SUP000:da_Petroleum | B35: Petroleum and Other Liquids 8/ | C35: 16.699137 | D35: 19.67774 | E35: 19.813248 | F35: 21.186703 | G35: 22.677301 | H35: 23.574001 | I35: 23.217295 | J35: 24.092285 | K35: 24.293886 | L35: 24.191198 | M35: 24.077267 | N35: 22.821302 | O35: 23.160934 | P35: 23.184769 | Q35: 23.166058 | R35: 23.190947 | S35: 23.408087 | T35: 23.194202 | U35: 23.611103 | V35: 23.30299 | W35: 23.079035 | X35: 23.200663 | Y35: 23.616289 | Z35: 23.485144 | AA35: 23.346128 | AB35: 23.194836 | AC35: 23.039408 | AD35: 22.963045 | AE35: 23.076998 | AF35: 23.139055 | AG35: 23.632502 | AH35: 23.532877 | AI35: 0.011127
A36: SUP000:da_NaturalGas | B36: Natural Gas | C36: 4.483331 | D36: 5.390441 | E36: 6.29525 | F36: 6.659064 | G36: 6.864997 | H36: 7.378416 | I36: 8.329083 | J36: 9.202188 | K36: 9.561375 | L36: 9.921309 | M36: 10.159161 | N36: 10.409156 | O36: 10.643183 | P36: 10.902959 | Q36: 11.031044 | R36: 11.16286 | S36: 11.386827 | T36: 11.532694 | U36: 11.53221 | V36: 11.555552 | W36: 11.577884 | X36: 11.721876 | Y36: 11.812589 | Z36: 11.835786 | AA36: 11.857625 | AB36: 11.900509 | AC36: 11.898772 | AD36: 11.921367 | AE36: 11.949547 | AF36: 12.009178 | AG36: 12.025288 | AH36: 12.043931 | AI36: 0.032391
A37: SUP000:da_Coal | B37: Coal | C37: 2.384845 | D37: 2.087335 | E37: 2.21891 | F37: 2.73313 | G37: 2.749026 | H37: 2.765525 | I37: 2.784021 | J37: 2.799102 | K37: 2.796579 | L37: 2.754004 | M37: 2.701591 | N37: 2.662022 | O37: 2.659713 | P37: 2.660605 | Q37: 2.658387 | R37: 2.657806 | S37: 2.707269 | T37: 2.700574 | U37: 2.700053 | V37: 2.699575 | W37: 2.699134 | X37: 2.69873 | Y37: 2.698362 | Z37: 2.698028 | AA37: 2.697726 | AB37: 2.705911 | AC37: 2.705754 | AD37: 2.705624 | AE37: 2.705523 | AF37: 2.696648 | AG37: 2.705398 | AH37: 2.705374 | AI37: 0.004076
A38: SUP000:da_Total | B38: Total | C38: 23.567314 | D38: 27.155516 | E38: 28.327408 | F38: 30.578896 | G38: 32.291325 | H38: 33.717941 | I38: 34.330399 | J38: 36.093575 | K38: 36.65184 | L38: 36.866508 | M38: 36.938019 | N38: 35.892479 | O38: 36.463829 | P38: 36.748333 | Q38: 36.855488 | R38: 37.011612 | S38: 37.502182 | T38: 37.427471 | U38: 37.843369 | V38: 37.558117 | W38: 37.356052 | X38: 37.621269 | Y38: 38.127239 | Z38: 38.018959 | AA38: 37.901482 | AB38: 37.801254 | AC38: 37.643932 | AD38: 37.590034 | AE38: 37.732067 | AF38: 37.844879 | AG38: 38.36319 | AH38: 38.282185 | AI38: 0.015772
A40: SUP000:ea_Discrepancy | B40: Discrepancy 9/ | C40: 2.669487 | D40: 0.957136 | E40: 0.29143 | F40: 0.221487 | G40: 0.189823 | H40: 0.076195 | I40: 0.048325 | J40: 0.102432 | K40: 0.048897 | L40: 0.081345 | M40: 0.069302 | N40: 0.093658 | O40: 0.043777 | P40: 0.034935 | Q40: 0.018368 | R40: 0.023247 | S40: 0.037964 | T40: 0.013191 | U40: 0.09399 | V40: 0.109951 | W40: 0.113277 | X40: 0.077209 | Y40: 0.088421 | Z40: 0.078701 | AA40: 0.11026 | AB40: 0.098335 | AC40: 0.067657 | AD40: 0.048908 | AE40: 0.092388 | AF40: 0.042515 | AG40: 0.015648 | AH40: -0.014767 | AI40: - -
B42: Consumption
A43: SUP000:fa_PetroleumProd | B43: Petroleum and Other Liquids 10/ | C43: 38.036598 | D43: 38.249081 | E43: 38.338688 | F43: 38.386181 | G43: 38.289234 | H43: 38.002949 | I43: 37.750813 | J43: 37.561947 | K43: 37.416737 | L43: 37.273754 | M43: 37.124798 | N43: 36.995697 | O43: 36.933586 | P43: 36.857891 | Q43: 36.808525 | R43: 36.746334 | S43: 36.693485 | T43: 36.683826 | U43: 36.740818 | V43: 36.744766 | W43: 36.804943 | X43: 36.866257 | Y43: 36.954792 | Z43: 37.06773 | AA43: 37.188457 | AB43: 37.365673 | AC43: 37.576744 | AD43: 37.924442 | AE43: 38.174854 | AF43: 38.506775 | AG43: 38.902462 | AH43: 39.312489 | AI43: 0.001065
A44: SUP000:fa_NaturalGas | B44: Natural Gas | C44: 32.145264 | D44: 32.737129 | E44: 33.949142 | F44: 34.150421 | G44: 34.379078 | H44: 34.568253 | I44: 35.093334 | J44: 35.69463 | K44: 36.01915 | L44: 36.170952 | M44: 36.428425 | N44: 36.37265 | O44: 36.745525 | P44: 37.066868 | Q44: 37.421097 | R44: 37.808136 | S44: 38.033005 | T44: 38.68364 | U44: 39.013336 | V44: 39.599762 | W44: 40.054459 | X44: 40.432426 | Y44: 40.813301 | Z44: 41.232796 | AA44: 41.579891 | AB44: 42.008537 | AC44: 42.425045 | AD44: 42.982323 | AE44: 43.330105 | AF44: 43.763386 | AG44: 44.238911 | AH44: 44.742081 | AI44: 0.010723
A45: SUP000:fa_Coal | B45: Coal 11/ | C45: 11.259031 | D45: 10.280395 | E45: 9.333065 | F45: 8.622534 | G45: 8.002261 | H45: 7.662528 | I45: 6.605392 | J45: 6.773781 | K45: 6.734324 | L45: 6.658014 | M45: 6.544596 | N45: 6.423348 | O45: 6.334036 | P45: 6.312187 | Q45: 6.300232 | R45: 6.297875 | S45: 6.135948 | T45: 6.138631 | U45: 6.129973 | V45: 6.088452 | W45: 6.047576 | X45: 5.958601 | Y45: 5.893947 | Z45: 5.861347 | AA45: 5.84467 | AB45: 5.801578 | AC45: 5.760871 | AD45: 5.764395 | AE45: 5.739917 | AF45: 5.721745 | AG45: 5.718521 | AH45: 5.689028 | AI45: -0.02178
A46: SUP000:fa_NuclearPower | B46: Nuclear / Uranium 2/ | C46: 8.444346 | D46: 8.293446 | E46: 8.156399 | F46: 8.00432 | G46: 8.028068 | H46: 8.059065 | I46: 7.91081 | J46: 6.578477 | K46: 6.110461 | L46: 6.114827 | M46: 6.119108 | N46: 5.934624 | O46: 5.842663 | P46: 5.775915 | Q46: 5.617176 | R46: 5.362936 | S46: 5.377634 | T46: 4.883077 | U46: 4.885286 | V46: 4.510839 | W46: 4.330963 | X46: 4.33457 | Y46: 4.347668 | Z46: 4.273965 | AA46: 4.200269 | AB46: 4.048344 | AC46: 3.984968 | AD46: 3.918423 | AE46: 3.922881 | AF46: 3.925656 | AG46: 3.929009 | AH46: 3.933857 | AI46: -0.02434
A47: SUP000:fa_Hydropower | B47: Conventional Hydroelectric Power | C47: 2.62724 | D47: 2.630024 | E47: 2.608772 | F47: 2.555373 | G47: 2.500631 | H47: 2.447045 | I47: 2.414509 | J47: 2.335763 | K47: 2.301766 | L47: 2.286823 | M47: 2.274183 | N47: 2.265188 | O47: 2.258272 | P47: 2.247759 | Q47: 2.242433 | R47: 2.237327 | S47: 2.234227 | T47: 2.225456 | U47: 2.210283 | V47: 2.210092 | W47: 2.194727 | X47: 2.188682 | Y47: 2.171035 | Z47: 2.163268 | AA47: 2.149309 | AB47: 2.155904 | AC47: 2.147812 | AD47: 2.14894 | AE47: 2.147149 | AF47: 2.149729 | AG47: 2.138394 | AH47: 2.13362 | AI47: -0.006691
A48: SUP000:fa_Biomass | B48: Biomass 12/ | C48: 3.225383 | D48: 3.098976 | E48: 3.124981 | F48: 3.156809 | G48: 3.174736 | H48: 3.189423 | I48: 3.20948 | J48: 3.226856 | K48: 3.24636 | L48: 3.264666 | M48: 3.279681 | N48: 3.290752 | O48: 3.303107 | P48: 3.306364 | Q48: 3.317096 | R48: 3.319901 | S48: 3.330778 | T48: 3.340802 | U48: 3.345825 | V48: 3.355098 | W48: 3.362056 | X48: 3.374875 | Y48: 3.39137 | Z48: 3.402288 | AA48: 3.420014 | AB48: 3.445644 | AC48: 3.467393 | AD48: 3.507087 | AE48: 3.538946 | AF48: 3.571927 | AG48: 3.61107 | AH48: 3.65761 | AI48: 0.004065
A49: SUP000:fa_RenewableEner | B49: Other Renewable Energy 4/ | C49: 3.98661 | D49: 4.494395 | E49: 5.065486 | F49: 5.872777 | G49: 6.29326 | H49: 6.385596 | I49: 6.742633 | J49: 6.775188 | K49: 6.839761 | L49: 6.913706 | M49: 7.030445 | N49: 7.305614 | O49: 7.369681 | P49: 7.379068 | Q49: 7.407632 | R49: 7.451074 | S49: 7.710938 | T49: 7.802966 | U49: 7.833769 | V49: 7.879764 | W49: 7.930049 | X49: 7.981818 | Y49: 8.045572 | Z49: 8.143557 | AA49: 8.303351 | AB49: 8.493343 | AC49: 8.690237 | AD49: 8.881924 | AE49: 9.096939 | AF49: 9.320292 | AG49: 9.595012 | AH49: 9.894312 | AI49: 0.029757
A50: SUP000:fa_Other | B50: Other 13/ | C50: 0.281393 | D50: 0.322586 | E50: 0.307465 | F50: 0.292266 | G50: 0.28596 | H50: 0.293659 | I50: 0.281313 | J50: 0.285669 | K50: 0.299279 | L50: 0.306001 | M50: 0.303153 | N50: 0.312035 | O50: 0.303321 | P50: 0.312092 | Q50: 0.312183 | R50: 0.32097 | S50: 0.319317 | T50: 0.314555 | U50: 0.313688 | V50: 0.311789 | W50: 0.312841 | X50: 0.312244 | Y50: 0.313997 | Z50: 0.311941 | AA50: 0.310691 | AB50: 0.308189 | AC50: 0.30585 | AD50: 0.303366 | AE50: 0.301738 | AF50: 0.300947 | AG50: 0.29969 | AH50: 0.29617 | AI50: 0.001652
A51: SUP000:fa_Total | B51: Total | C51: 100.00587 | D51: 100.10603 | E51: 100.88399 | F51: 101.04069 | G51: 100.95322 | H51: 100.60851 | I51: 100.00828 | J51: 99.2323 | K51: 98.967827 | L51: 98.988731 | M51: 99.104393 | N51: 98.899902 | O51: 99.090187 | P51: 99.258148 | Q51: 99.426369 | R51: 99.544556 | S51: 99.835327 | T51: 100.07295 | U51: 100.47298 | V51: 100.70056 | W51: 101.03761 | X51: 101.44948 | Y51: 101.93169 | Z51: 102.45689 | AA51: 102.99666 | AB51: 103.62721 | AC51: 104.35892 | AD51: 105.43091 | AE51: 106.25253 | AF51: 107.26046 | AG51: 108.43307 | AH51: 109.65916 | AI51: 0.002977
B53: Prices (2019 dollars per unit)
A54: SUP000:ha_WorldOilPrice | B54: Brent Spot Price (dollars per barrel) | C54: 63.371998 | D54: 57.724522 | E54: 58.922596 | F54: 60.425056 | G54: 61.430351 | H54: 62.38113 | I54: 63.533955 | J54: 64.565697 | K54: 65.742775 | L54: 66.727455 | M54: 67.963661 | N54: 69.20668 | O54: 70.411636 | P54: 71.622894 | Q54: 72.731606 | R54: 74.266747 | S54: 75.43338 | T54: 76.704254 | U54: 77.701996 | V54: 78.906395 | W54: 80.181808 | X54: 81.759392 | Y54: 83.171791 | Z54: 84.555916 | AA54: 85.999214 | AB54: 87.05336 | AC54: 88.038773 | AD54: 89.02108 | AE54: 89.703667 | AF54: 90.323441 | AG54: 90.755264 | AH54: 91.386757 | AI54: 0.011879
A55: SUP000:ha_ForLowSulfLit | B55: West Texas Intermediate Spot Price (dollars per barrel) | C55: 56.261002 | D55: 54.319656 | E55: 53.787861 | F55: 54.445362 | G55: 55.377003 | H55: 56.431797 | I55: 57.670925 | J55: 58.112759 | K55: 59.152477 | L55: 59.626846 | M55: 61.200031 | N55: 61.784191 | O55: 63.240383 | P55: 63.937023 | Q55: 65.294266 | R55: 67.102943 | S55: 68.327972 | T55: 69.380417 | U55: 71.079979 | V55: 72.109207 | W55: 73.262459 | X55: 74.774445 | Y55: 76.13427 | Z55: 77.891747 | AA55: 79.440323 | AB55: 80.294273 | AC55: 81.265411 | AD55: 82.265564 | AE55: 82.930176 | AF55: 83.169044 | AG55: 83.461624 | AH55: 84.412727 | AI55: 0.013174
A56: SUP000:ha_GasPriceHenry | B56: Natural Gas at Henry Hub (dollars per mmBtu) | C56: 2.566947 | D56: 2.46114 | E56: 2.378542 | F56: 2.267594 | G56: 2.217039 | H56: 2.232104 | I56: 2.39129 | J56: 2.593056 | K56: 2.682391 | L56: 2.68209 | M56: 2.635443 | N56: 2.587787 | O56: 2.580512 | P56: 2.596762 | Q56: 2.612083 | R56: 2.616543 | S56: 2.6054 | T56: 2.614558 | U56: 2.636981 | V56: 2.647321 | W56: 2.649715 | X56: 2.645178 | Y56: 2.638018 | Z56: 2.63495 | AA56: 2.607855 | AB56: 2.58515 | AC56: 2.571348 | AD56: 2.570073 | AE56: 2.560807 | AF56: 2.551662 | AG56: 2.544252 | AH56: 2.537284 | AI56: -0.000375
A57: SUP000:ha_CoalMinemouth | B57: Coal, Minemouth (dollars per ton) 14/ | C57: 34.280701 | D57: 32.949497 | E57: 35.14888 | F57: 35.36496 | G57: 34.924271 | H57: 35.077209 | I57: 36.054295 | J57: 34.973942 | K57: 35.137032 | L57: 34.781273 | M57: 35.045933 | N57: 35.215336 | O57: 35.304592 | P57: 35.364494 | Q57: 35.47826 | R57: 35.483234 | S57: 35.92905 | T57: 36.205711 | U57: 36.589981 | V57: 37.444744 | W57: 37.581074 | X57: 38.080601 | Y57: 38.290585 | Z57: 38.386753 | AA57: 38.492985 | AB57: 38.673492 | AC57: 38.84779 | AD57: 38.99995 | AE57: 39.092632 | AF57: 39.182384 | AG57: 39.428085 | AH57: 39.576504 | AI57: 0.004645
A58: SUP000:ha_CoalMineBtu | B58: Coal, Minemouth (dollars per million Btu) 14/ | C58: 1.70453 | D58: 1.620796 | E58: 1.678334 | F58: 1.67366 | G58: 1.65489 | H58: 1.654235 | I58: 1.682514 | J58: 1.648252 | K58: 1.655163 | L58: 1.642343 | M58: 1.651438 | N58: 1.656681 | O58: 1.660526 | P58: 1.664496 | Q58: 1.670135 | R58: 1.672572 | S58: 1.689753 | T58: 1.700725 | U58: 1.714757 | V58: 1.740343 | W58: 1.746328 | X58: 1.764323 | Y58: 1.77129 | Z58: 1.77659 | AA58: 1.781166 | AB58: 1.788302 | AC58: 1.796736 | AD58: 1.804658 | AE58: 1.809374 | AF58: 1.813902 | AG58: 1.822453 | AH58: 1.829362 | AI58: 0.002283
A59: SUP000:ha_CoalDelivered | B59: Coal, Delivered (dollars per million Btu) 15/ | C59: 2.18719 | D59: 2.17905 | E59: 2.135298 | F59: 2.081176 | G59: 2.061861 | H59: 2.046628 | I59: 2.035747 | J59: 2.022008 | K59: 2.035451 | L59: 2.031131 | M59: 2.03477 | N59: 2.028044 | O59: 2.025258 | P59: 2.022873 | Q59: 2.024446 | R59: 2.026966 | S59: 2.028592 | T59: 2.032047 | U59: 2.035839 | V59: 2.039702 | W59: 2.039401 | X59: 2.04244 | Y59: 2.039507 | Z59: 2.040875 | AA59: 2.041382 | AB59: 2.041337 | AC59: 2.041541 | AD59: 2.045588 | AE59: 2.044852 | AF59: 2.045883 | AG59: 2.045835 | AH59: 2.047916 | AI59: -0.00212
A60: SUP000:ha_Electricity(c | B60: Electricity (cents per kilowatthour) | C60: 10.388245 | D60: 10.218346 | E60: 10.115773 | F60: 10.047506 | G60: 9.989574 | H60: 10.004821 | I60: 10.077984 | J60: 10.158848 | K60: 10.150057 | L60: 10.111455 | M60: 10.010123 | N60: 9.969799 | O60: 9.940785 | P60: 9.931937 | Q60: 9.925848 | R60: 9.909852 | S60: 9.864488 | T60: 9.843067 | U60: 9.827897 | V60: 9.799759 | W60: 9.771208 | X60: 9.754768 | Y60: 9.731934 | Z60: 9.714381 | AA60: 9.67724 | AB60: 9.632534 | AC60: 9.606205 | AD60: 9.553829 | AE60: 9.518396 | AF60: 9.514969 | AG60: 9.457655 | AH60: 9.393082 | AI60: -0.003243
B63: Prices (nominal dollars per unit)
A64: SUP000:nom_ImportRACost | B64: Brent Spot Price (dollars per barrel) | C64: 63.371998 | D64: 59.077347 | E64: 61.818974 | F64: 65.025085 | G64: 67.779213 | H64: 70.536018 | I64: 73.65358 | J64: 76.803391 | K64: 80.309258 | L64: 83.701019 | M64: 87.53875 | N64: 91.495277 | O64: 95.484993 | P64: 99.574181 | Q64: 103.62965 | R64: 108.38433 | S64: 112.70813 | T64: 117.32385 | U64: 121.64743 | V64: 126.40358 | W64: 131.39116 | X64: 137.06885 | Y64: 142.62617 | Z64: 148.32709 | AA64: 154.26851 | AB64: 159.64691 | AC64: 165.05809 | AD64: 170.62506 | AE64: 175.80865 | AF64: 181.11958 | AG64: 186.33601 | AH64: 192.18858 | AI64: 0.036437
A65: SUP000:nom_ForLowSulfLi | B65: West Texas Intermediate Spot Price (dollars per barrel) | C65: 56.261002 | D65: 55.592682 | E65: 56.431839 | F65: 58.590172 | G65: 61.100246 | H65: 63.808952 | I65: 66.856689 | J65: 69.127373 | K65: 72.258759 | L65: 74.794212 | M65: 78.827042 | N65: 81.682312 | O65: 85.760078 | P65: 88.888847 | Q65: 93.032761 | R65: 97.929527 | S65: 102.09164 | T65: 106.12159 | U65: 111.28025 | V65: 115.51488 | W65: 120.05265 | X65: 125.35865 | Y65: 130.55797 | Z65: 136.63687 | AA65: 142.50293 | AB65: 147.25143 | AC65: 152.35916 | AD65: 157.67688 | AE65: 162.53342 | AF65: 166.77336 | AG65: 171.36093 | AH65: 177.52203 | AI65: 0.037763
A66: SUP000:nom_Gas@HenryHub | B66: Natural Gas at Henry Hub (dollars per mmBtu) | C66: 2.566947 | D66: 2.518819 | E66: 2.495461 | F66: 2.440222 | G66: 2.446171 | H66: 2.5239 | I66: 2.772172 | J66: 3.084541 | K66: 3.276722 | L66: 3.364337 | M66: 3.394511 | N66: 3.421206 | O66: 3.499424 | P66: 3.610165 | Q66: 3.721756 | R66: 3.818563 | S66: 3.892835 | T66: 3.999126 | U66: 4.128361 | V66: 4.240859 | W66: 4.341996 | X66: 4.434616 | Y66: 4.523775 | Z66: 4.622201 | AA66: 4.678064 | AB66: 4.740899 | AC66: 4.820851 | AD66: 4.926012 | AE66: 5.018882 | AF66: 5.116679 | AG66: 5.223783 | AH66: 5.335969 | AI66: 0.023886
A67: SUP000:nom_CoalMinemout | B67: Coal, Minemouth (dollars per ton) 14/ | C67: 34.280701 | D67: 33.721695 | E67: 36.876648 | F67: 38.057217 | G67: 38.53371 | H67: 39.662743 | I67: 41.796986 | J67: 41.602856 | K67: 42.922264 | L67: 43.628635 | M67: 45.139965 | N67: 46.556732 | O67: 47.876442 | P67: 49.165707 | Q67: 50.550236 | R67: 51.783966 | S67: 53.683079 | T67: 55.378853 | U67: 57.283947 | V67: 59.98436 | W67: 61.582802 | X67: 63.84177 | Y67: 65.662163 | Z67: 67.337631 | AA67: 69.05011 | AB67: 70.92321 | AC67: 72.83316 | AD67: 74.750488 | AE67: 76.616974 | AF67: 78.569832 | AG67: 80.952568 | AH67: 83.230347 | AI67: 0.029027
A68: SUP000:nom_CoalMineBtu | B68: Coal, Minemouth (dollars per million Btu) 14/ | C68: 1.70453 | D68: 1.658781 | E68: 1.760834 | F68: 1.801072 | G68: 1.825924 | H68: 1.870488 | I68: 1.950503 | J68: 1.96066 | K68: 2.021894 | L68: 2.060108 | M68: 2.12709 | N68: 2.19023 | O68: 2.251833 | P68: 2.314076 | Q68: 2.379647 | R68: 2.440938 | S68: 2.524729 | T68: 2.601362 | U68: 2.684562 | V68: 2.787931 | W68: 2.861648 | X68: 2.957871 | Y68: 3.037475 | Z68: 3.116475 | AA68: 3.19512 | AB68: 3.279562 | AC68: 3.368582 | AD68: 3.458954 | AE68: 3.546162 | AF68: 3.637297 | AG68: 3.741806 | AH68: 3.847193 | AI68: 0.026608
A69: SUP000:nom_CoalDeliverd | B69: Coal, Delivered (dollars per million Btu) 15/ | C69: 2.18719 | D69: 2.230118 | E69: 2.24026 | F69: 2.239611 | G69: 2.274955 | H69: 2.314178 | I69: 2.359999 | J69: 2.405256 | K69: 2.486441 | L69: 2.547793 | M69: 2.62083 | N69: 2.681193 | O69: 2.746446 | P69: 2.812312 | Q69: 2.884476 | R69: 2.958139 | S69: 3.031003 | T69: 3.10814 | U69: 3.187235 | V69: 3.267488 | W69: 3.341895 | X69: 3.424131 | Y69: 3.497426 | Z69: 3.580082 | AA69: 3.661905 | AB69: 3.743601 | AC69: 3.82755 | AD69: 3.920741 | AE69: 4.00767 | AF69: 4.102472 | AG69: 4.200447 | AH69: 4.306817 | AI69: 0.022098
A70: SUP000:nom_Electricity | B70: Electricity (cents per kilowatthour) | C70: 10.388245 | D70: 10.457822 | E70: 10.61302 | F70: 10.812402 | G70: 11.022003 | H70: 11.312719 | I70: 11.683195 | J70: 12.084341 | K70: 12.398981 | L70: 12.68352 | M70: 12.893268 | N70: 13.180657 | O70: 13.480666 | P70: 13.807938 | Q70: 14.142575 | R70: 14.462362 | S70: 14.738938 | T70: 15.055573 | U70: 15.386201 | V70: 15.698659 | W70: 16.011738 | X70: 16.353779 | Y70: 16.688692 | Z70: 17.040863 | AA70: 17.359383 | AB70: 17.665077 | AC70: 18.01004 | AD70: 18.311647 | AE70: 18.65494 | AF70: 19.079733 | AG70: 19.418175 | AH70: 19.75388 | AI70: 0.020948
B72: 1/ Includes waste coal.
B73: 2/ These values represent the energy obtained from uranium when it is used in light water reactors. The total energy content of uranium
B74: is much larger, but alternative processes are required to take advantage of it.
B75: 3/ Includes grid-connected electricity from wood and wood waste; biomass, such as corn, used for liquid fuels production; and non-electric
B76: energy demand from wood. Refer to Table 17 for details.
B77: 4/ Includes grid-connected electricity from landfill gas; biogenic municipal waste; wind; photovoltaic and solar thermal sources; and
B78: non-electric energy from renewable sources, such as active and passive solar systems. Excludes electricity imports using renewable sources
B79: and nonmarketed renewable energy. See Table 17 for selected nonmarketed residential and commercial renewable energy data.
B80: 5/ Includes non-biogenic municipal waste, hydrogen, methanol, and some domestic inputs to refineries.
B81: 6/ Includes imports of finished petroleum products, unfinished oils, alcohols, ethers, blending components, and renewable fuels such as ethanol.
B82: 7/ Includes coal, coal coke (net), and electricity (net). Excludes imports of fuel used in nuclear power plants.
B83: 8/ Includes crude oil, petroleum products, ethanol, and biodiesel.
... B100: Energy Modeling System run highogs.d112619a. Projections: EIA, AEO2020 National Energy Modeling System run highogs.d112619a.

Sheet AEO Table 73
B1: ref2021.d113020a | C1: 2020 | D1: 2021 | E1: 2022 | F1: 2023 | G1: 2024 | H1: 2025 | I1: 2026 | J1: 2027 | K1: 2028 | L1: 2029 | M1: 2030 | N1: 2031 | O1: 2032 | P1: 2033 | Q1: 2034 | R1: 2035 | S1: 2036 | T1: 2037 | U1: 2038 | V1: 2039 | W1: 2040 | X1: 2041 | Y1: 2042 | Z1: 2043 | AA1: 2044 | AB1: 2045 | AC1: 2046 | AD1: 2047 | AE1: 2048 | AF1: 2049 | AG1: 2050
C3: Report | D3: Annual Energy Outlook 2021
C4: Scenario | D4: ref2021 | G4: Reference case
C5: Datekey | D5: d113020a
C6: Release Date | E6: January 2021
A10: CNV000 | B10: 71. Conversion Factors | AH10: Compound
B11: (from physical units to million Btu) | AH11: Growth
AH12: 2020-2050
C13: 2020 | D13: 2021 | E13: 2022 | F13: 2023 | G13: 2024 | H13: 2025 | I13: 2026 | J13: 2027 | K13: 2028 | L13: 2029 | M13: 2030 | N13: 2031 | O13: 2032 | P13: 2033 | Q13: 2034 | R13: 2035 | S13: 2036 | T13: 2037 | U13: 2038 | V13: 2039 | W13: 2040 | X13: 2041 | Y13: 2042 | Z13: 2043 | AA13: 2044 | AB13: 2045 | AC13: 2046 | AD13: 2047 | AE13: 2048 | AF13: 2049 | AG13: 2050 | AH13: (percent)
B14: Petroleum and Other Liquids
B15: (million Btu per barrel)
A16: CNV000:aa_AsphaltandRoa | B16: Asphalt and Road Oil | C16: 6.636 | D16: 6.636 | E16: 6.636 | F16: 6.636 | G16: 6.636 | H16: 6.636 | I16: 6.636 | J16: 6.636 | K16: 6.636 | L16: 6.636 | M16: 6.636 | N16: 6.636 | O16: 6.636 | P16: 6.636 | Q16: 6.636 | R16: 6.636 | S16: 6.636 | T16: 6.636 | U16: 6.636 | V16: 6.636 | W16: 6.636 | X16: 6.636 | Y16: 6.636 | Z16: 6.636 | AA16: 6.636 | AB16: 6.636 | AC16: 6.636 | AD16: 6.636 | AE16: 6.636 | AF16: 6.636 | AG16: 6.636 | AH16: 0
A17: CNV000:aa_AviationGasol | B17: Aviation Gasoline | C17: 5.048 | D17: 5.048 | E17: 5.048 | F17: 5.048 | G17: 5.048 | H17: 5.048 | I17: 5.048 | J17: 5.048 | K17: 5.048 | L17: 5.048 | M17: 5.048 | N17: 5.048 | O17: 5.048 | P17: 5.048 | Q17: 5.048 | R17: 5.048 | S17: 5.048 | T17: 5.048 | U17: 5.048 | V17: 5.048 | W17: 5.048 | X17: 5.048 | Y17: 5.048 | Z17: 5.048 | AA17: 5.048 | AB17: 5.048 | AC17: 5.048 | AD17: 5.048 | AE17: 5.048 | AF17: 5.048 | AG17: 5.048 | AH17: 0
A18: CNV000:ea_Biodiesel | B18: Biodiesel | C18: 5.359 | D18: 5.359 | E18: 5.359 | F18: 5.359 | G18: 5.359 | H18: 5.359 | I18: 5.359 | J18: 5.359 | K18: 5.359 | L18: 5.359 | M18: 5.359 | N18: 5.359 | O18: 5.359 | P18: 5.359 | Q18: 5.359 | R18: 5.359 | S18: 5.359 | T18: 5.359 | U18: 5.359 | V18: 5.359 | W18: 5.359 | X18: 5.359 | Y18: 5.359 | Z18: 5.359 | AA18: 5.359 | AB18: 5.359 | AC18: 5.359 | AD18: 5.359 | AE18: 5.359 | AF18: 5.359 | AG18: 5.359 | AH18: 0
A19: CNV000:aa_Distillate | B19: Distillate Fuel Oil | C19: 5.825 | D19: 5.825 | E19: 5.825 | F19: 5.825 | G19: 5.825 | H19: 5.825 | I19: 5.825 | J19: 5.825 | K19: 5.825 | L19: 5.825 | M19: 5.825 | N19: 5.825 | O19: 5.825 | P19: 5.825 | Q19: 5.825 | R19: 5.825 | S19: 5.825 | T19: 5.825 | U19: 5.825 | V19: 5.825 | W19: 5.825 | X19: 5.825 | Y19: 5.825 | Z19: 5.825 | AA19: 5.825 | AB19: 5.825 | AC19: 5.825 | AD19: 5.825 | AE19: 5.825 | AF19: 5.825 | AG19: 5.825 | AH19: 0
A20: CNV000:aa_Residential | B20: Residential | C20: 5.772225 | D20: 5.770434 | E20: 5.769468 | F20: 5.769597 | G20: 5.770083 | H20: 5.769742 | I20: 5.769996 | J20: 5.770608 | K20: 5.769846 | L20: 5.770197 | M20: 5.76971 | N20: 5.7698 | O20: 5.769487 | P20: 5.769598 | Q20: 5.769436 | R20: 5.769614 | S20: 5.770103 | T20: 5.769971 | U20: 5.770141 | V20: 5.769869 | W20: 5.770143 | X20: 5.770298 | Y20: 5.770511 | Z20: 5.770051 | AA20: 5.769538 | AB20: 5.769256 | AC20: 5.770041 | AD20: 5.769023 | AE20: 5.768785 | AF20: 5.768611 | AG20: 5.768018 | AH20: -2.4e-05
A21: CNV000:aa_Commercial | B21: Commercial | C21: 5.772225 | D21: 5.770434 | E21: 5.769468 | F21: 5.769597 | G21: 5.770083 | H21: 5.769742 | I21: 5.769996 | J21: 5.770608 | K21: 5.769846 | L21: 5.770197 | M21: 5.76971 | N21: 5.7698 | O21: 5.769487 | P21: 5.769598 | Q21: 5.769436 | R21: 5.769614 | S21: 5.770103 | T21: 5.769971 | U21: 5.770141 | V21: 5.769869 | W21: 5.770143 | X21: 5.770298 | Y21: 5.770511 | Z21: 5.770051 | AA21: 5.769538 | AB21: 5.769256 | AC21: 5.770041 | AD21: 5.769023 | AE21: 5.768785 | AF21: 5.768611 | AG21: 5.768018 | AH21: -2.4e-05
A22: CNV000:aa_Transportatio | B22: Transportation | C22: 5.772225 | D22: 5.770434 | E22: 5.769468 | F22: 5.769597 | G22: 5.770083 | H22: 5.769742 | I22: 5.769996 | J22: 5.770608 | K22: 5.769846 | L22: 5.770197 | M22: 5.76971 | N22: 5.7698 | O22: 5.769487 | P22: 5.769598 | Q22: 5.769436 | R22: 5.769614 | S22: 5.770103 | T22: 5.769971 | U22: 5.770141 | V22: 5.769869 | W22: 5.770143 | X22: 5.770298 | Y22: 5.770511 | Z22: 5.770051 | AA22: 5.769538 | AB22: 5.769256 | AC22: 5.770041 | AD22: 5.769023 | AE22: 5.768785 | AF22: 5.768611 | AG22: 5.768018 | AH22: -2.4e-05
A23: CNV000:aa_Industrial | B23: Industrial | C23: 5.772225 | D23: 5.770434 | E23: 5.769468 | F23: 5.769597 | G23: 5.770083 | H23: 5.769742 | I23: 5.769996 | J23: 5.770608 | K23: 5.769846 | L23: 5.770197 | M23: 5.76971 | N23: 5.7698 | O23: 5.769487 | P23: 5.769598 | Q23: 5.769436 | R23: 5.769614 | S23: 5.770103 | T23: 5.769971 | U23: 5.770141 | V23: 5.769869 | W23: 5.770143 | X23: 5.770298 | Y23: 5.770511 | Z23: 5.770051 | AA23: 5.769538 | AB23: 5.769256 | AC23: 5.770041 | AD23: 5.769023 | AE23: 5.768785 | AF23: 5.768611 | AG23: 5.768018 | AH23: -2.4e-05
A24: CNV000:aa_ElectricPower | B24: Electric Power | C24: 5.772225 | D24: 5.770434 | E24: 5.769468 | F24: 5.769597 | G24: 5.770083 | H24: 5.769742 | I24: 5.769996 | J24: 5.770608 | K24: 5.769846 | L24: 5.770197 | M24: 5.76971 | N24: 5.7698 | O24: 5.769487 | P24: 5.769598 | Q24: 5.769436 | R24: 5.769614 | S24: 5.770103 | T24: 5.769971 | U24: 5.770141 | V24: 5.769869 | W24: 5.770143 | X24: 5.770298 | Y24: 5.770511 | Z24: 5.770051 | AA24: 5.769538 | AB24: 5.769256 | AC24: 5.770041 | AD24: 5.769023 | AE24: 5.768785 | AF24: 5.768611 | AG24: 5.768018 | AH24: -2.4e-05
A25: CNV000:aa_TotalDistilla | B25: Total Distillate | C25: 5.772226 | D25: 5.770434 | E25: 5.769468 | F25: 5.769597 | G25: 5.770083 | H25: 5.769742 | I25: 5.769997 | J25: 5.770607 | K25: 5.769845 | L25: 5.770196 | M25: 5.76971 | N25: 5.7698 | O25: 5.769487 | P25: 5.769598 | Q25: 5.769436 | R25: 5.769614 | S25: 5.770103 | T25: 5.769971 | U25: 5.770141 | V25: 5.769869 | W25: 5.770143 | X25: 5.770298 | Y25: 5.770511 | Z25: 5.770051 | AA25: 5.769537 | AB25: 5.769256 | AC25: 5.770042 | AD25: 5.769023 | AE25: 5.768785 | AF25: 5.768611 | AG25: 5.768018 | AH25: -2.4e-05
A26: CNV000:aa_DistLowSulf | B26: Distillate Fuel Oil - Low Sulfur Diesel | C26: 5.817 | D26: 5.817 | E26: 5.817 | F26: 5.817 | G26: 5.817 | H26: 5.817 | I26: 5.817 | J26: 5.817 | K26: 5.817 | L26: 5.817 | M26: 5.817 | N26: 5.817 | O26: 5.817 | P26: 5.817 | Q26: 5.817 | R26: 5.817 | S26: 5.817 | T26: 5.817 | U26: 5.817 | V26: 5.817 | W26: 5.817 | X26: 5.817 | Y26: 5.817 | Z26: 5.817 | AA26: 5.817 | AB26: 5.817 | AC26: 5.817 | AD26: 5.817 | AE26: 5.817 | AF26: 5.817 | AG26: 5.817 | AH26: 0
A27: CNV000:aa_DistUltraLow | B27: Distillate Fuel Oil - Ultra Low Sulfur Diesel | C27: 5.77 | D27: 5.77 | E27: 5.77 | F27: 5.77 | G27: 5.77 | H27: 5.77 | I27: 5.77 | J27: 5.77 | K27: 5.77 | L27: 5.77 | M27: 5.77 | N27: 5.77 | O27: 5.77 | P27: 5.77 | Q27: 5.77 | R27: 5.77 | S27: 5.77 | T27: 5.77 | U27: 5.77 | V27: 5.77 | W27: 5.77 | X27: 5.77 | Y27: 5.77 | Z27: 5.77 | AA27: 5.77 | AB27: 5.77 | AC27: 5.77 | AD27: 5.77 | AE27: 5.77 | AF27: 5.77 | AG27: 5.77 | AH27: 0
... A46: CNV000:aa_Exports | B46: Petroleum Product Exports | C46: 5.208902 | D46: 5.233259 | E46: 5.248022 | F46: 5.255337 | G46: 5.284336 | H46: 5.284585 | I46: 5.293683 | J46: 5.295779 | K46: 5.304686 | L46: 5.305382 | M46: 5.288252 | N46: 5.307133 | O46: 5.317582 | P46: 5.324971 | Q46: 5.329218 | R46: 5.340077 | S46: 5.341102 | T46: 5.350363 | U46: 5.351419 | V46: 5.347663 | W46: 5.341086 | X46: 5.342655 | Y46: 5.341298 | Z46: 5.333441 | AA46: 5.32583 | AB46: 5.325848 | AC46: 5.324336 | AD46: 5.331812 | AE46: 5.337536 | AF46: 5.337165 | AG46: 5.341957 | AH46: 0.000841
B47: Crude Oil
A48: CNV000:aa_CrudeOilProdu | B48: Production | C48: 5.701258 | D48: 5.705287 | E48: 5.698242 | F48: 5.690741 | G48: 5.686217 | H48: 5.680397 | I48: 5.679482 | J48: 5.680235 | K48: 5.682467 | L48: 5.683152 | M48: 5.685532 | N48: 5.686835 | O48: 5.686281 | P48: 5.688497 | Q48: 5.689099 | R48: 5.687949 | S48: 5.684894 | T48: 5.68398 | U48: 5.68161 | V48: 5.680455 | W48: 5.678696 | X48: 5.677988 | Y48: 5.678402 | Z48: 5.678963 | AA48: 5.678901 | AB48: 5.675479 | AC48: 5.677872 | AD48: 5.678594 | AE48: 5.676446 | AF48: 5.673857 | AG48: 5.669861 | AH48: -0.000184
A49: CNV000:aa_CrudeOilImpor | B49: Imports | C49: 6.085091 | D49: 6.066456 | E49: 6.068346 | F49: 6.068904 | G49: 6.068149 | H49: 6.070602 | I49: 6.087798 | J49: 6.087098 | K49: 6.09395 | L49: 6.091728 | M49: 6.087254 | N49: 6.093457 | O49: 6.103011 | P49: 6.10403 | Q49: 6.110426 | R49: 6.110364 | S49: 6.113935 | T49: 6.127923 | U49: 6.126749 | V49: 6.126231 | W49: 6.121337 | X49: 6.12137 | Y49: 6.118534 | Z49: 6.108738 | AA49: 6.108547 | AB49: 6.110272 | AC49: 6.10705 | AD49: 6.107703 | AE49: 6.109305 | AF49: 6.10804 | AG49: 6.116878 | AH49: 0.000174
A50: CNV000:aa_CrudeOilExpor | B50: Exports | C50: 5.586683 | D50: 5.596693 | E50: 5.596242 | F50: 5.595907 | G50: 5.595245 | H50: 5.595181 | I50: 5.584603 | J50: 5.587386 | K50: 5.595116 | L50: 5.586189 | M50: 5.59499 | N50: 5.585876 | O50: 5.594877 | P50: 5.59394 | Q50: 5.590277 | R50: 5.591412 | S50: 5.590872 | T50: 5.594198 | U50: 5.594143 | V50: 5.588477 | W50: 5.593933 | X50: 5.593874 | Y50: 5.593719 | Z50: 5.593579 | AA50: 5.597045 | AB50: 5.59432 | AC50: 5.593446 | AD50: 5.593292 | AE50: 5.593154 | AF50: 5.593037 | AG50: 5.592913 | AH50: 3.7e-05
A51: CNV000:aa_NaturalGasPla | B51: Natural Gas Plant Liquids | C51: 3.588495 | D51: 3.53136 | E51: 3.523382 | F51: 3.549014 | G51: 3.544739 | H51: 3.540329 | I51: 3.539303 | J51: 3.538394 | K51: 3.537459 | L51: 3.535216 | M51: 3.533556 | N51: 3.532846 | O51: 3.532958 | P51: 3.533101 | Q51: 3.532566 | R51: 3.531256 | S51: 3.530272 | T51: 3.529652 | U51: 3.528985 | V51: 3.52799 | W51: 3.527618 | X51: 3.528339 | Y51: 3.528407 | Z51: 3.529173 | AA51: 3.529438 | AB51: 3.528521 | AC51: 3.529552 | AD51: 3.529862 | AE51: 3.52899 | AF51: 3.527624 | AG51: 3.525624 | AH51: -0.000589
B53: Natural Gas (thousand Btu per cubic foot)
A54: CNV000:ba_Consumption | B54: Consumption | C54: 1.037 | D54: 1.037 | E54: 1.037 | F54: 1.037 | G54: 1.037 | H54: 1.037 | I54: 1.037 | J54: 1.037 | K54: 1.037 | L54: 1.037 | M54: 1.037 | N54: 1.037 | O54: 1.037 | P54: 1.037 | Q54: 1.037 | R54: 1.037 | S54: 1.037 | T54: 1.037 | U54: 1.037 | V54: 1.037 | W54: 1.037 | X54: 1.037 | Y54: 1.037 | Z54: 1.037 | AA54: 1.037 | AB54: 1.037 | AC54: 1.037 | AD54: 1.037 | AE54: 1.037 | AF54: 1.037 | AG54: 1.037 | AH54: 0
A55: CNV000:ba_Utility | B55: Electric Power Sector 2/ | C55: 1.034 | D55: 1.034 | E55: 1.034 | F55: 1.034 | G55: 1.034 | H55: 1.034 | I55: 1.034 | J55: 1.034 | K55: 1.034 | L55: 1.034 | M55: 1.034 | N55: 1.034 | O55: 1.034 | P55: 1.034 | Q55: 1.034 | R55: 1.034 | S55: 1.034 | T55: 1.034 | U55: 1.034 | V55: 1.034 | W55: 1.034 | X55: 1.034 | Y55: 1.034 | Z55: 1.034 | AA55: 1.034 | AB55: 1.034 | AC55: 1.034 | AD55: 1.034 | AE55: 1.034 | AF55: 1.034 | AG55: 1.034 | AH55: 0
A56: CNV000:ba_Nonutility | B56: End-use Sector | C56: 1.039 | D56: 1.039 | E56: 1.039 | F56: 1.039 | G56: 1.039 | H56: 1.039 | I56: 1.039 | J56: 1.039 | K56: 1.039 | L56: 1.039 | M56: 1.039 | N56: 1.039 | O56: 1.039 | P56: 1.039 | Q56: 1.039 | R56: 1.039 | S56: 1.039 | T56: 1.039 | U56: 1.039 | V56: 1.039 | W56: 1.039 | X56: 1.039 | Y56: 1.039 | Z56: 1.039 | AA56: 1.039 | AB56: 1.039 | AC56: 1.039 | AD56: 1.039 | AE56: 1.039 | AF56: 1.039 | AG56: 1.039 | AH56: 0
A57: CNV000:ba_Production | B57: Production | C57: 1.037 | D57: 1.037 | E57: 1.037 | F57: 1.037 | G57: 1.037 | H57: 1.037 | I57: 1.037 | J57: 1.037 | K57: 1.037 | L57: 1.037 | M57: 1.037 | N57: 1.037 | O57: 1.037 | P57: 1.037 | Q57: 1.037 | R57: 1.037 | S57: 1.037 | T57: 1.037 | U57: 1.037 | V57: 1.037 | W57: 1.037 | X57: 1.037 | Y57: 1.037 | Z57: 1.037 | AA57: 1.037 | AB57: 1.037 | AC57: 1.037 | AD57: 1.037 | AE57: 1.037 | AF57: 1.037 | AG57: 1.037 | AH57: 0
A58: CNV000:ba_Imports | B58: Imports | C58: 1.025 | D58: 1.025 | E58: 1.025 | F58: 1.025 | G58: 1.025 | H58: 1.025 | I58: 1.025 | J58: 1.025 | K58: 1.025 | L58: 1.025 | M58: 1.025 | N58: 1.025 | O58: 1.025 | P58: 1.025 | Q58: 1.025 | R58: 1.025 | S58: 1.025 | T58: 1.025 | U58: 1.025 | V58: 1.025 | W58: 1.025 | X58: 1.025 | Y58: 1.025 | Z58: 1.025 | AA58: 1.025 | AB58: 1.025 | AC58: 1.025 | AD58: 1.025 | AE58: 1.025 | AF58: 1.025 | AG58: 1.025 | AH58: 0
A59: CNV000:ba_Exports | B59: Exports | C59: 1.009 | D59: 1.009 | E59: 1.009 | F59: 1.009 | G59: 1.009 | H59: 1.009 | I59: 1.009 | J59: 1.009 | K59: 1.009 | L59: 1.009 | M59: 1.009 | N59: 1.009 | O59: 1.009 | P59: 1.009 | Q59: 1.009 | R59: 1.009 | S59: 1.009 | T59: 1.009 | U59: 1.009 | V59: 1.009 | W59: 1.009 | X59: 1.009 | Y59: 1.009 | Z59: 1.009 | AA59: 1.009 | AB59: 1.009 | AC59: 1.009 | AD59: 1.009 | AE59: 1.009 | AF59: 1.009 | AG59: 1.009 | AH59: 0
A60: CNV000:ba_CompressedNat | B60: Compressed/Liquefied Natural Gas | C60: 0.96 | D60: 0.96 | E60: 0.96 | F60: 0.96 | G60: 0.96 | H60: 0.96 | I60: 0.96 | J60: 0.96 | K60: 0.96 | L60: 0.96 | M60: 0.96 | N60: 0.96 | O60: 0.96 | P60: 0.96 | Q60: 0.96 | R60: 0.96 | S60: 0.96 | T60: 0.96 | U60: 0.96 | V60: 0.96 | W60: 0.96 | X60: 0.96 | Y60: 0.96 | Z60: 0.96 | AA60: 0.96 | AB60: 0.96 | AC60: 0.96 | AD60: 0.96 | AE60: 0.96 | AF60: 0.96 | AG60: 0.96 | AH60: 0
B62: Coal (million Btu per short ton)
A63: CNV000:ca_Production | B63: Production | C63: 20.313612 | D63: 20.251499 | E63: 20.463696 | F63: 20.630898 | G63: 20.58532 | H63: 20.620371 | I63: 20.558367 | J63: 20.551445 | K63: 20.452055 | L63: 20.355701 | M63: 20.289701 | N63: 20.316072 | O63: 20.341093 | P63: 20.369787 | Q63: 20.349621 | R63: 20.382479 | S63: 20.405159 | T63: 20.455118 | U63: 20.57431 | V63: 20.58498 | W63: 20.617809 | X63: 20.606735 | Y63: 20.642296 | Z63: 20.684587 | AA63: 20.690783 | AB63: 20.781717 | AC63: 20.824453 | AD63: 20.813873 | AE63: 20.786306 | AF63: 20.831282 | AG63: 20.832466 | AH63: 0.000841
A64: CNV000:ca_EastoftheMiss | B64: East of the Mississippi | C64: 25.162447 | D64: 25.061907 | E64: 24.844831 | F64: 25.003353 | G64: 25.014917 | H64: 25.161196 | I64: 25.144636 | J64: 25.18247 | K64: 25.190441 | L64: 25.210474 | M64: 25.271479 | N64: 25.263571 | O64: 25.235905 | P64: 25.426609 | Q64: 25.42605 | R64: 25.406256 | S64: 25.35174 | T64: 25.317278 | U64: 25.262371 | V64: 25.204082 | W64: 25.170408 | X64: 25.136366 | Y64: 25.124195 | Z64: 25.10177 | AA64: 25.08288 | AB64: 25.03639 | AC64: 25.004837 | AD64: 24.996422 | AE64: 24.994413 | AF64: 25.032789 | AG64: 25.018826 | AH64: -0.000191
A65: CNV000:ca_WestoftheMiss | B65: West of the Mississippi | C65: 17.310602 | D65: 17.309647 | E65: 17.211004 | F65: 17.263588 | G65: 17.337936 | H65: 17.308016 | I65: 17.259657 | J65: 17.224226 | K65: 17.166725 | L65: 17.176584 | M65: 17.131996 | N65: 17.134941 | O65: 17.114252 | P65: 17.09199 | Q65: 17.09087 | R65: 17.088018 | S65: 17.077797 | T65: 17.051991 | U65: 17.025953 | V65: 17.01372 | W65: 16.977299 | X65: 16.978853 | Y65: 17.006622 | Z65: 17.016672 | AA65: 17.028193 | AB65: 17.032866 | AC65: 17.039537 | AD65: 17.015118 | AE65: 16.990679 | AF65: 16.993908 | AG65: 16.98835 | AH65: -0.000626
A66: CNV000:ca_Consumption | B66: Consumption | C66: 19.465235 | D66: 19.47703 | E66: 19.633654 | F66: 19.748119 | G66: 19.604624 | H66: 19.514042 | I66: 19.460508 | J66: 19.416695 | K66: 19.301138 | L66: 19.199217 | M66: 19.119923 | N66: 19.131233 | O66: 19.13302 | P66: 19.181492 | Q66: 19.162058 | R66: 19.166834 | S66: 19.206079 | T66: 19.242796 | U66: 19.352158 | V66: 19.394049 | W66: 19.422735 | X66: 19.419495 | Y66: 19.465462 | Z66: 19.508917 | AA66: 19.511177 | AB66: 19.602798 | AC66: 19.653093 | AD66: 19.640366 | AE66: 19.61727 | AF66: 19.648813 | AG66: 19.641287 | AH66: 0.0003
A67: CNV000:ca_Residentialan | B67: Commercial and Institutional | C67: 19.07375 | D67: 19.023113 | E67: 19.023102 | F67: 19.320454 | G67: 19.262178 | H67: 19.226744 | I67: 19.203001 | J67: 19.198051 | K67: 19.173183 | L67: 19.142059 | M67: 19.111967 | N67: 19.063097 | O67: 19.027267 | P67: 18.988686 | Q67: 18.945419 | R67: 18.899261 | S67: 18.854065 | T67: 18.823059 | U67: 18.801371 | V67: 18.77677 | W67: 18.747007 | X67: 18.720158 | Y67: 18.696239 | Z67: 18.664991 | AA67: 18.637045 | AB67: 18.618738 | AC67: 18.595921 | AD67: 18.562662 | AE67: 18.520023 | AF67: 18.478739 | AG67: 18.440039 | AH67: -0.001126
A68: CNV000:ca_Industrial | B68: Industrial 3/ | C68: 19.047443 | D68: 19.29319 | E68: 19.406574 | F68: 19.401604 | G68: 19.396521 | H68: 19.387011 | I68: 19.386452 | J68: 19.379221 | K68: 19.369596 | L68: 19.360327 | M68: 19.351662 | N68: 19.3437 | O68: 19.335772 | P68: 19.328518 | Q68: 19.320198 | R68: 19.320457 | S68: 19.30393 | T68: 19.276167 | U68: 19.278488 | V68: 19.280405 | W68: 19.310587 | X68: 19.309147 | Y68: 19.301651 | Z68: 19.294476 | AA68: 19.266329 | AB68: 19.271349 | AC68: 19.274885 | AD68: 19.282909 | AE68: 19.308189 | AF68: 19.31518 | AG68: 19.319613 | AH68: 0.000473
A69: CNV000:ca_Coking | B69: Coking | C69: 28.46183 | D69: 28.444407 | E69: 28.425611 | F69: 28.430611 | G69: 28.426397 | H69: 28.410816 | I69: 28.410643 | J69: 28.404917 | K69: 28.393972 | L69: 28.382809 | M69: 28.384378 | N69: 28.385469 | O69: 28.383551 | P69: 28.379475 | Q69: 28.381683 | R69: 28.384056 | S69: 28.383585 | T69: 28.384052 | U69: 28.38829 | V69: 28.391367 | W69: 28.388498 | X69: 28.391012 | Y69: 28.398878 | Z69: 28.404837 | AA69: 28.404747 | AB69: 28.404837 | AC69: 28.405666 | AD69: 28.405745 | AE69: 28.408457 | AF69: 28.40884 | AG69: 28.414181 | AH69: -5.6e-05
A70: CNV000:ca_ElectricPower | B70: Electric Power 2/ | C70: 18.96517 | D70: 19.123833 | E70: 19.29612 | F70: 19.282087 | G70: 19.073906 | H70: 18.931747 | I70: 18.8878 | J70: 18.832237 | K70: 18.730505 | L70: 18.639585 | M70: 18.542288 | N70: 18.545713 | O70: 18.545574 | P70: 18.609898 | Q70: 18.586058 | R70: 18.576267 | S70: 18.626122 | T70: 18.661646 | U70: 18.765039 | V70: 18.805761 | W70: 18.843643 | X70: 18.834778 | Y70: 18.874973 | Z70: 18.909355 | AA70: 18.914787 | AB70: 19.009039 | AC70: 19.066225 | AD70: 19.052853 | AE70: 19.023752 | AF70: 19.06444 | AG70: 19.044859 | AH70: 0.00014
A71: CNV000:ca_Imports | B71: Imports | C71: 21.803574 | D71: 23.877344 | E71: 24.519646 | F71: 24.553909 | G71: 24.555077 | H71: 24.556545 | I71: 24.558163 | J71: 24.560095 | K71: 24.562294 | L71: 24.564135 | M71: 24.566006 | N71: 24.567417 | O71: 24.569372 | P71: 24.571028 | Q71: 24.572569 | R71: 24.572277 | S71: 24.416414 | T71: 24.415298 | U71: 24.413433 | V71: 24.411963 | W71: 24.410923 | X71: 24.409023 | Y71: 24.406759 | Z71: 24.364962 | AA71: 24.290007 | AB71: 24.287508 | AC71: 24.284723 | AD71: 24.282084 | AE71: 24.279228 | AF71: 24.275148 | AG71: 24.271727 | AH71: 0.003581
A72: CNV000:ca_Exports | B72: Exports | C72: 26.459833 | D72: 26.347706 | E72: 26.128981 | F72: 25.58699 | G72: 25.522665 | H72: 25.523605 | I72: 25.521624 | J72: 25.518833 | K72: 25.515526 | L72: 25.523022 | M72: 25.52689 | N72: 25.522734 | O72: 25.498999 | P72: 25.49938 | Q72: 25.492809 | R72: 25.47209 | S72: 25.474277 | T72: 25.513758 | U72: 25.504108 | V72: 25.435743 | W72: 25.415844 | X72: 25.386637 | Y72: 25.381466 | Z72: 25.371529 | AA72: 25.363153 | AB72: 25.322754 | AC72: 25.289442 | AD72: 25.279551 | AE72: 25.278866 | AF72: 25.38624 | AG72: 25.345205 | AH72: -0.001434
A73: CNV000:ca_CoaltoLiquids | B73: Coal to Liquids | C73: - - | D73: - - | E73: - - | F73: - - | G73: - - | H73: - - | I73: - - | J73: - - | K73: - - | L73: - - | M73: - - | N73: - - | O73: - - | P73: - - | Q73: - - | R73: - - | S73: - - | T73: - - | U73: - - | V73: - - | W73: - - | X73: - - | Y73: - - | Z73: - - | AA73: - - | AB73: - - | AC73: - - | AD73: - - | AE73: - - | AF73: - - | AG73: - - | AH73: - -
A74: CNV000:ca_WasteCoal | B74: Waste Coal | C74: 13.506 | D74: 13.506 | E74: 13.506001 | F74: 13.506001 | G74: 13.506001 | H74: 13.506001 | I74: 13.506001 | J74: 13.506 | K74: 13.506 | L74: 13.506001 | M74: 13.506001 | N74: 13.506001 | O74: 13.506 | P74: 13.506001 | Q74: 13.506001 | R74: 13.506001 | S74: 13.506 | T74: 13.506 | U74: 13.506001 | V74: 13.506001 | W74: 13.506 | X74: 13.506001 | Y74: 13.506001 | Z74: 13.506001 | AA74: 13.506001 | AB74: 13.506 | AC74: 13.506 | AD74: 13.506 | AE74: 13.506 | AF74: 13.506001 | AG74: 13.506 | AH74: 0
B76: Approximate Heat Rates and Heat Content
B77: (Btu per kilowatthour)
A78: CNV000:da_Electricity | B78: Electricity Heat Content | C78: 3412 | D78: 3412 | E78: 3412 | F78: 3412 | G78: 3412 | H78: 3412 | I78: 3412 | J78: 3412 | K78: 3412 | L78: 3412 | M78: 3412 | N78: 3412 | O78: 3412 | P78: 3412 | Q78: 3412 | R78: 3412 | S78: 3412 | T78: 3412 | U78: 3412 | V78: 3412 | W78: 3412 | X78: 3412 | Y78: 3412 | Z78: 3412 | AA78: 3412 | AB78: 3412 | AC78: 3412 | AD78: 3412 | AE78: 3412 | AF78: 3412 | AG78: 3412 | AH78: 0
A79: CNV000:fossil_hr_us | B79: Fossil Fuel Heat Rate | C79: 8813.9736 | D79: 8888.75 | E79: 8900.5576 | F79: 8681.874 | G79: 8583.335 | H79: 8331.1445 | I79: 8270.6992 | J79: 8207.6904 | K79: 8195.6641 | L79: 8180.2568 | M79: 8174.5835 | N79: 8143.1289 | O79: 8114.2529 | P79: 8096.6523 | Q79: 8080.8423 | R79: 8058.7603 | S79: 8044.7466 | T79: 8019.1504 | U79: 7976.832 | V79: 7954.623 | W79: 7933.0767 | X79: 7915.2524 | Y79: 7900.6011 | Z79: 7871.0732 | AA79: 7850.0557 | AB79: 7821.7222 | AC79: 7808.6509 | AD79: 7797.0405 | AE79: 7788.7275 | AF79: 7768.7769 | AG79: 7750.7515 | AH79: -0.004276
B80: 1/ Includes ethane, natural gasoline, and refinery olefins.
B81: 2/ Includes all electricity-only and combined heat and power plants that have a regulatory status.
B82: 3/ Includes combined heat and power plants that have a non-regulatory status, and small on-site generating systems.
B83: - - = Not applicable.
B84: Sources: 2020: U.S. Energy Information Administration (EIA), Short-Term Energy Outlook, October 2020 and EIA,
B85: AEO2021 National Energy Modeling System run ref2021.d113020a. Projections: EIA, AEO2021 National Energy Modeling System run ref2021.d113020a.

Sheet GREET1 Fuel_Specs
A1: Specifications of Fuels, Global Warming Potentials of Greenhouse Gases, and Carbon and Sulfur Ratios of Pollutants
A2: 1) Specifications of Fuels
A3: Fuel | B3: Heating Value | E3: Density | F3: C ratio | G3: S ratio | H3: S ratio
B4: Calculation: LHV | C4: LHV | D4: HHV | F4: (% by wt) | G4: (ppm by wt) | H4: Actual ratio by wt | I4: LHV/HHV
A5: Use LHV or HHV in calculations? | B5: 1 | C5: 1 -- LHV; 2 -- HHV
A6: Liquid Fuels: | B6: Btu/gal | C6: Btu/gal | D6: Btu/gal | E6: grams/gal
A7: Crude oil | B7: 129670 | C7: 129670 | D7: 138350 | E7: 3205 | F7: 0.853 | G7: 16000 | H7: 0.016 | I7: 0.93726057
A8: Synthetic crude oil (SCO) | B8: 135084.91 | C8: 135084.91 | D8: 144475.84 | E8: 3266 | F8: 0.85562069 | G8: 1800 | H8: 0.0018 | I8: 0.935
A9: Bitumen | B9: 152370.9 | C9: 152370.9 | D9: 162963.53 | E9: 3839.6821 | F9: 0.83 | G9: 48000 | H9: 0.048 | I9: 0.935
A10: Dilbit (After Recovery) | B10: 152370.9 | C10: 152370.9 | D10: 162963.53 | E10: 3839.6821 | F10: 0.83 | G10: 48000 | H10: 0.048 | I10: 0.935
A11: Dilbit (Before Recovery) | B11: 145194.19 | C11: 145194.19 | D11: 155287.9 | E11: 3500.4775 | F11: 0.83245886 | G11: 37227.39 | H11: 0.03722739 | I11: 0.935
A12: Diluent | B12: 128448.53 | C12: 128448.53 | D12: 137378.1 | E12: 2709 | F12: 0.84059084 | G12: 1600 | H12: 0.0016 | I12: 0.935
A13: Shale Oil (Bakken) | B13: 125600.91 | C13: 125600.91 | D13: 134008.53 | E13: 3087.2372 | F13: 0.853 | G13: 16000 | H13: 0.016 | I13: 0.93726057
A14: Shale Oil (Eagle Ford) | B14: 122492.61 | C14: 122492.61 | D14: 130692.16 | E14: 2984.0427 | F14: 0.853 | G14: 16000 | H14: 0.016 | I14: 0.93726057
A15: Gasoline blendstock | B15: 116090 | C15: 116090 | D15: 124340 | E15: 2819 | F15: 0.863 | G15: 10 | H15: 1e-05 | I15: 0.93364967
A16: Gasoline | B16: 112193.52 | C16: 112193.52 | D16: 120438.62 | E16: 2835.562 | F16: 0.82778547 | G16: 9.0261788 | H16: 9.0261788e-06 | I16: 0.93154106
A17: CA gasoline | B17: 112193.52 | C17: 112193.52 | D17: 120438.62 | E17: 2835.562 | F17: 0.82778547 | G17: 9.0261788 | H17: 9.0261788e-06 | I17: 0.93154106
A18: High Octane Fuel (E25) | B18: 106150 | C18: 106150 | D18: 114387.5 | E18: 2861.25 | F18: 0.77775 | G18: 7.6425 | H18: 7.6425e-06 | I18: 0.92798601
... A20: U.S. conventional diesel | B20: 128450 | C20: 128450 | D20: 137380 | E20: 3167 | F20: 0.865 | G20: 200 | H20: 0.0002 | I20: 0.93499782
A21: CA diesel | B21: 129487.85 | C21: 129487.85 | D21: 138490 | E21: 3206 | F21: 0.871 | G21: 11 | H21: 1.1e-05
A22: Diesel for non-road engines | B22: 128450 | C22: 128450 | D22: 137380 | E22: 3167 | F22: 0.865 | G22: 11 | H22: 1.1e-05 | I22: 0.93499782
A23: Low-sulfur diesel | B23: 129487.85 | C23: 129487.85 | D23: 138490 | E23: 3206 | F23: 0.871 | G23: 11 | H23: 1.1e-05 | I23: 0.93499782
A24: Petroleum naphtha | B24: 116920 | C24: 116920 | D24: 125080 | E24: 2745 | F24: 0.85 | G24: 1 | H24: 1e-06 | I24: 0.93476175
A25: Low Octane Gasoline-Like Fuel (LOF) | B25: 118237.43 | C25: 118237.43 | D25: 126586.16 | E25: 2833.857 | F25: 0.85315639 | G25: 10 | H25: 1e-05 | I25: 0.93404711
A26: Conventional Jet Fuel | B26: 124307.03 | C26: 124307.03 | D26: 132948.69 | E26: 3035.8996 | F26: 0.862 | G26: 700 | H26: 0.0007 | I26: 0.93500004
A27: ULS Jet Fuel | B27: 123041.23 | C27: 123041.23 | D27: 131594.89 | E27: 2998.0455 | F27: 0.86 | G27: 11 | H27: 1.1e-05 | I27: 0.93500004
A28: NG-based FT naphtha | B28: 111520 | C28: 111520 | D28: 119740 | E28: 2651 | F28: 0.842 | G28: 0 | H28: 0 | I28: 0.93135126
A29: Residual oil | B29: 140352.52 | C29: 140352.52 | D29: 150110 | E29: 3752 | F29: 0.868 | G29: 5000 | H29: 0.005 | I29: 0.93499782
A30: Bunker fuel for ocean tanker | B30: 140352.52 | C30: 140352.52 | D30: 150110 | E30: 3752 | F30: 0.868 | G30: 27000 | H30: 0.027 | I30: 0.93499782
A31: Methanol | B31: 57250 | C31: 57250 | D31: 65200 | E31: 3006 | F31: 0.375 | G31: 0 | H31: 0 | I31: 0.87806748
A32: Ethanol | B32: 76330 | C32: 76330 | D32: 84530 | E32: 2988 | F32: 0.522 | G32: 0.57000011 | H32: 5.7000011e-07 | I32: 0.90299302
A33: Butanol | B33: 99837 | C33: 99837 | D33: 108458 | E33: 3065 | F33: 0.6486 | G33: 0 | H33: 0 | I33: 0.92051301
... A56: Propane | B56: 84250 | C56: 84250 | D56: 91420 | E56: 1920 | F56: 0.818 | G56: 0 | H56: 0 | I56: 0.92157077
A57: Natural gas liquids | B57: 83686.112 | C57: 83686.112 | D57: 90050 | E57: 2532 | G57: 0 | H57: 0 | I57: 0.9293294
A58: n-Hexane | B58: 105124.8 | C58: 105124.8 | D58: 112166.3 | E58: 2478.7 | F58: 0.836251 | G58: 0 | H58: 0 | I58: 0.93722268
A59: Gaseous Fuels (at 32F and 1atm): | B59: Btu/ft3 | C59: Btu/ft3 | D59: Btu/ft3 | E59: gms/ft3 | I59: LHV/HHV
A60: Natural gas | B60: 983 | C60: 983 | D60: 1089 | E60: 22 | F60: 0.724 | G60: 6 | H60: 6e-06 | I60: 0.90266299
A61: Pure Methane | B61: 962.18505 | C61: 962.18505 | D61: 1068.0254 | E61: 20.303179 | F61: 0.75 | G61: 0 | H61: 0 | I61: 0.9009009
A62: Gaseous hydrogen | B62: 290 | C62: 290 | D62: 343 | E62: 2.55 | F62: 0 | G62: 0 | H62: 0 | I62: 0.84548105
A63: Carbon Dioxide | E63: 55.97783 | F63: 0.27272727 | G63: 0 | H63: 0
A64: Still gas (in refineries) | B64: 1159.2737 | C64: 1159.2737 | D64: 1279.7381 | E64: 25.019852 | F64: 0.76981386 | G64: 6 | H64: 6e-06 | I64: 0.9058679
A65: Solid Fuels: | B65: Btu/ton | C65: Btu/ton | D65: Btu/ton | I65: LHV/HHV
A66: Coal Mix for Electricity Generation | B66: 19474169 | C66: 19474169 | D66: 20673610 | F66: 0.5857111 | G66: 10455.988 | H66: 0.010455988
A67: Bituminous coal | B67: 22639320 | C67: 22639320 | D67: 23633493 | F67: 0.612 | G67: 15352.093 | H67: 0.015352093 | I67: 0.95793373
A68: Subbituminous coal | B68: 16085444 | C68: 16085444 | D68: 17449320 | F68: 0.537 | G68: 3568.2537 | H68: 0.0035682537 | I68: 0.92183789
A69: Lignite coal | B69: 10805183 | C69: 10805183 | D69: 12992302 | F69: 0.491 | G69: 9064.2347 | H69: 0.0090642347 | I69: 0.83166038
A70: Synthetic coal | B70: 22639320 | C70: 22639320 | D70: 23633493 | F70: 0.8064205 | G70: 16142.739 | H70: 0.016142739 | I70: 0.95793373
A71: Waste coal | B71: 9945646.3 | C71: 9945646.3 | D71: 11958783 | F71: 0.32642858 | G71: 9064.2347 | H71: 0.0090642347 | I71: 0.83166038
A72: Pet Coke | B72: 26949429 | C72: 26949429 | D72: 28595925 | F72: 0.8667 | G72: 45137.714 | H72: 0.045137714 | I72: 0.94242199
A73: Tire Derived Fuel | B73: 26664354 | C73: 26664354 | D73: 28293434 | F73: 0.48798697 | G73: 45137.714 | H73: 0.045137714 | I73: 0.94242199
A74: Coking coal | B74: 24599422 | C74: 24599422 | D74: 25679670 | F74: 0.747 | G74: 11800 | H74: 0.0118 | I74: 0.95793373
A75: Catalyst Coke | B75: 28385750 | C75: 28385750 | D75: 30120000 | F75: 0.86413234 | G75: 45137.714 | H75: 0.045137714 | I75: 0.94242199
A76: Willow | B76: 15396000 | C76: 15396000 | D76: 16524000 | F76: 0.487 | G76: 500 | H76: 0.0005 | I76: 0.93173566
A77: Poplar | B77: 15929000 | C77: 15929000 | D77: 17062000 | F77: 0.501 | G77: 200 | H77: 0.0002 | I77: 0.93359512
A78: Switchgrass | B78: 14447000 | C78: 14447000 | D78: 15583000 | F78: 0.466 | G78: 1100 | H78: 0.0011 | I78: 0.92710004
... A82: Clean Pine | B82: 15929000 | C82: 15929000 | D82: 17062000 | F82: 0.501 | G82: 200 | H82: 0.0002 | I82: 0.93359512
A83: Yard trimming waste | B83: 15000000 | C83: 15000000 | F83: 0.478 | G83: 400 | H83: 0.0004
A84: Sugarcane straw | B84: 13454049 | C84: 13454049 | D84: 15774000 | F84: 0.5 | I84: 0.85292563
A85: Sugarcane bagasse | B85: 12381771 | C85: 12381771 | D85: 14062678 | F85: 0.463 | I85: 0.88047037
A86: Bio-char | B86: 18916911 | C86: 18916911 | D86: 18916911 | F86: 0.512 | G86: 0 | H86: 0 | I86: 1
A87: Grain sorghum bagasse | B87: 12781599 | C87: 12781599 | D87: 14131556 | F87: 0.3934 | G87: 0 | H87: 0 | I87: 0.90447216
A88: Sweet sorghum bagasse | B88: 14409931 | C88: 14409931 | D88: 15305245 | F88: 0.41985 | G88: 0 | H88: 0 | I88: 0.94150281
A89: Forage sorghum bagasse | B89: 14409931 | C89: 14409931 | D89: 15305245 | F89: 0.41985 | G89: 0 | H89: 0 | I89: 0.94150281
A90: Municipal solid waste (defined by EISA) | B90: 11209639 | C90: 11209639 | D90: 13583445 | F90: 0.49161518 | G90: 1765.2251 | H90: 0.0017652251 | I90: 0.82524272
A91: Convertible municipal solid waste | B91: 14155275 | C91: 14155275 | D91: 16144033 | F91: 0.5049151 | G91: 1787.3101 | H91: 0.0017873101 | I91: 0.87681159
A92: Asphalt | B92: 152370.9 | C92: 152370.9 | D92: 162963.53 | E92: 3839.6821 | F92: 0.83 | G92: 48000 | H92: 0.048 | I92: 0.935
A93: Lubricants | B93: 144230 | E93: 3785.411 | F93: 0.80800504 | G93: 3510
A95: 2) Global Warming Potentials of Greenhouse Gases: relative to CO2
A96: Metrics for Carbon Dioxide, Methane, Nitrous Oxide
A97: AR Edition/Type | B97: AR5/GWP | C97: AR5/GWP | D97: AR5/GWP | E97: AR5/GTP | F97: AR5/GTP | G97: AR4/GWP | H97: AR4/GWP | I97: AR3/GWP | J97: AR3/GWP | K97: AR2/GWP | L97: AR2/GWP | M97: AR1/GWP | N97: AR1/GWP
A98: Time Horizon (YR) | B98: 100 | C98: 100 | D98: 20 | E98: 100 | F98: 20 | G98: 100 | H98: 20 | I98: 100 | J98: 20 | K98: 100 | L98: 20 | M98: 100 | N98: 20
A99: CO2 | B99: 1 | C99: 1 | D99: 1 | E99: 1 | F99: 1 | G99: 1 | H99: 1 | I99: 1 | J99: 1 | K99: 1 | L99: 1 | M99: 1 | N99: 1
A100: CH4 | B100: 30 | C100: 30 | D100: 85 | E100: 6 | F100: 68 | G100: 25 | H100: 72 | I100: 23 | J100: 62 | K100: 21 | L100: 56 | M100: 21 | N100: 63
A101: N2O | B101: 265 | C101: 265 | D101: 264 | E101: 234 | F101: 277 | G101: 298 | H101: 289 | I101: 296 | J101: 275 | K101: 310 | L101: 280 | M101: 290 | N101: 270
A103: Metrics for Near Term Climate Forcers
A104: Type | B104: None | C104: None | D104: GWP | E104: GWP | F104: GTP | G104: GTP
A105: Time Horizon (YR) | B105: 100 | D105: 100 | E105: 20 | F105: 100 | G105: 20
A106: VOC | B106: 0 | C106: 0 | D106: 4.5 | E106: 14 | F106: 0.66 | G106: 7.5
A107: CO | B107: 0 | C107: 0 | D107: 2.65 | E107: 7.65 | F107: 0.42 | G107: 4.9
A108: NOx | B108: 0 | C108: 0 | D108: -11 | E108: 19 | F108: -2.9 | G108: -87
A109: BC | B109: 0 | C109: 0 | D109: 900 | E109: 3200 | F109: 130 | G109: 920
A110: OC | B110: 0 | C110: 0 | D110: -69 | E110: -240 | F110: -10 | G110: -71
A112: 3) Carbon and Sulfur Ratios of Pollutants
A113: Carbon ratio of VOC | B113: 0.85
A114: Carbon ratio of CO | B114: 0.42857143
A115: Carbon ratio of CH4 | B115: 0.75
A116: Carbon ratio of CO2 | B116: 0.27272727
A117: Sulfur ratio of SO2 | B117: 0.5
A119: 4) Regulated Sulfur Content in Gasoline Blendstock and Conventional Diesel over Time
B121: 10 | F121: 200 | J121: 11 | N121: 11 | R121: 27000 | V121: 1000
B122: 10 | F122: 200 | J122: 11 | N122: 11 | R122: 27000 | V122: 1000
B123: 5-year period | C123: Sulfur Content in Gasoline Blendstock (ppm) | D123: Relative Change (to yr 2010) | F123: 5-year period | G123: Sulfur Content in Conventional Diesel (ppm) | H123: Relative Change (to yr 2010) | J123: 5-year period | K123: Sulfur Content in California Diesel (ppm) | L123: Relative Change (to yr 2010) | N123: 5-year period | O123: Sulfur Content in non-Road Diesel (ppm) | P123: Relative Change (to yr 2010) | R123: 5-year period | S123: Sulfur Content in Residual Oil (ppm) | T123: Relative Change (to yr 2010) | V123: 5-year period | W123: Sulfur Content in Marine Disttillate (ppm) | X123: Relative Change (to yr 2010)
B124: 1990 | C124: 500 | D124: 19.607843 | F124: 1990 | G124: 600 | H124: 3 | J124: 1990 | K124: 350 | L124: 31.818182 | N124: 1990 | O124: 2283 | P124: 14.006135 | R124: 1990 | S124: 27000 | T124: 1 | V124: 1990 | W124: 2000 | X124: 1
B125: 1995 | C125: 340 | D125: 13.333333 | F125: 1995 | G125: 350 | H125: 1.75 | J125: 1995 | K125: 200 | L125: 18.181818 | N125: 1995 | O125: 2283 | P125: 14.006135 | R125: 1995 | S125: 27000 | T125: 1 | V125: 1995 | W125: 2000 | X125: 1
B126: 2000 | C126: 200 | D126: 7.8431373 | F126: 2000 | G126: 200 | H126: 1 | J126: 2000 | K126: 120 | L126: 10.909091 | N126: 2000 | O126: 2283 | P126: 14.006135 | R126: 2000 | S126: 27000 | T126: 1 | V126: 2000 | W126: 2000 | X126: 1
B127: 2005 | C127: 25.5 | D127: 1 | F127: 2005 | G127: 200 | H127: 1 | J127: 2005 | K127: 120 | L127: 10.909091 | N127: 2005 | O127: 2283 | P127: 14.006135 | R127: 2005 | S127: 27000 | T127: 1 | V127: 2005 | W127: 2000 | X127: 1
B128: 2010 | C128: 25.5 | D128: 1 | F128: 2010 | G128: 200 | H128: 1 | J128: 2010 | K128: 11 | L128: 1 | N128: 2010 | O128: 163 | P128: 1 | R128: 2010 | S128: 27000 | T128: 1 | V128: 2010 | W128: 2000 | X128: 1
B129: 2015 | C129: 25.5 | D129: 1 | F129: 2015 | G129: 200 | H129: 1 | J129: 2015 | K129: 11 | L129: 1 | N129: 2015 | O129: 11 | P129: 0.067484663 | R129: 2015 | S129: 27000 | T129: 1 | V129: 2015 | W129: 1000 | X129: 0.5
B130: 2017 | C130: 10 | D130: 0.39215686 | F130: 2020 | G130: 200 | H130: 1 | J130: 2020 | K130: 11 | L130: 1 | N130: 2020 | O130: 11 | P130: 0.067484663 | R130: 2020 | S130: 5000 | T130: 0.185 | V130: 2020 | W130: 1000 | X130: 0.5
B131: 2020 | C131: 10 | D131: 0.39215686
...

Sheet energeticos
A1: Sistema de Información Energética
A2: Secretaría de Energía
A3: Dirección General de Planeación e Información Energéticas
A4: Balance Nacional de Energía: Oferta interna bruta total por energético
A5: (petajoules)
B7: REALES
A8: PRODUCCION | B8: 2005 | C8: 2006 | D8: 2007 | E8: 2008 | F8: 2009 | G8: 2010 | H8: 2011 | I8: 2012 | J8: 2013 | K8: 2014 | L8: 2015 | M8: 2016 | N8: 2017 | O8: 2018 | P8: 2019
A10: Total | B10: 7957.4425 | C10: 8056.0255 | D10: 8092.2401 | E10: 8337.7937 | F10: 8315.1592 | G10: 8271.0447 | H10: 8638.2634 | I10: 8814.8054 | J10: 8988.4304 | K10: 8650.6894 | L10: 8528.8669 | M10: 9140.096 | N10: 9249.7458 | O10: 9236.858 | P10: 8811.0536
A11: Carbón y coque de carbón | B11: 480.34629 | C11: 515.51383 | D11: 473.7015 | E11: 423.16308 | F11: 431.08722 | G11: 533.22752 | H11: 616.77734 | I11: 537.35764 | J11: 533.6158 | K11: 532.57986 | L11: 531.54163 | M11: 520.67992 | N11: 636.31004 | O11: 567.16367 | P11: 541.49341
A12: Crudo y petrolíferos | B12: 3810.5241 | C12: 3668.0553 | D12: 3814.1232 | E12: 4016.4307 | F12: 3807.6383 | G12: 3662.0643 | H12: 3755.621 | I12: 3954.8035 | J12: 3905.5825 | K12: 3505.8766 | L12: 3462.1818 | M12: 3592.9419 | N12: 3520.6184 | O12: 3508.2583 | P12: 3261.1419
A13: Gas natural y condensados | B13: 2936.5748 | C13: 3154.6768 | D13: 3084.0401 | E13: 3154.1639 | F13: 3385.3809 | G13: 3390.0961 | H13: 3538.5164 | I13: 3626.0582 | J13: 3812.4531 | K13: 3870.5824 | L13: 3791.0102 | M13: 4281.1098 | N13: 4335.6791 | O13: 4344.1563 | P13: 4227.1734
A14: Nuclear | B14: 117.88 | C14: 119.419 | D14: 114.486 | E14: 106.635 | F14: 112.745 | G14: 63.942774 | H14: 106.39494 | I14: 91.317 | J14: 122.598 | K14: 100.596 | L14: 120.407 | M14: 109.95428 | N14: 113.21871 | O14: 156.00289 | P14: 124.82
A15: Renovables | B15: 638.20057 | C15: 625.8113 | D15: 632.25558 | E15: 666.21994 | F15: 605.14064 | G15: 641.96217 | H15: 640.84781 | I15: 620.53108 | J15: 634.71908 | K15: 665.76647 | L15: 647.90824 | M15: 653.95183 | N15: 663.87645 | O15: 673.74244 | P15: 661.12485
A16: Biogás | B16: 0.688518 | C16: 0.675775 | D16: 0.651122 | E16: 0.808913 | F16: 1.067139 | G16: 1.298023 | H16: 1.507667 | I16: 1.823098 | J16: 1.972003 | K16: 1.925703 | L16: 1.867721 | M16: 1.912172 | N16: 2.51994 | O16: 2.843916 | P16: 2.799
A17: Hidro | B17: 99.754004 | C17: 109.60731 | D17: 98.422827 | E17: 141.20607 | F17: 96.19922 | G17: 133.76877 | H17: 130.57351 | I17: 114.87848 | J17: 100.87676 | K17: 140.01397 | L17: 111.20955 | M17: 110.51047 | N17: 114.65156 | O17: 116.9475 | P17: 84.99
A18: Geo, eólica, solar | B18: 167.54291 | C18: 153.96991 | D18: 171.46978 | E18: 164.11173 | F18: 158.93915 | G18: 159.35707 | H18: 161.03846 | I18: 153.05186 | J18: 153.97625 | K18: 161.74767 | L18: 176.16514 | M18: 181.04483 | N18: 180.81332 | O18: 184.28175 | P18: 213.42
A19: Biomasa | B19: 370.21514 | C19: 361.55831 | D19: 361.71185 | E19: 360.09323 | F19: 348.93514 | G19: 347.53832 | H19: 347.72818 | I19: 350.77764 | J19: 377.89407 | K19: 362.07913 | L19: 358.66583 | M19: 360.48435 | N19: 365.89163 | O19: 369.66927 | P19: 359.92
A20: Comercio neto de electricidad | B20: -26.083201 | C20: -27.450698 | D20: -26.366262 | E20: -28.81887 | F20: -26.832849 | G20: -20.248171 | H20: -19.894091 | I20: -15.262 | J20: -20.538 | K20: -24.712 | L20: -24.182 | M20: -18.541693 | N20: -19.956901 | O20: -12.465634 | P20: -4.7
A22: Nota:
A23: La suma de los parciales puede no coincidir con los totales, debido al redondeo de las cifras.
A24: Los datos del a&ntilde;o 2018 son preliminares y están sujetos a cambios sin previo aviso.
A26: Fuente: Sistema de Información Energética, SENER.
A28: Sistema de Información Energética
A29: Secretaría de Energía
A30: Dirección General de Planeación e Información Energéticas
A31: Balance Nacional de Energía: Importación de energía
A32: (petajoules)
B34: REALES
A35: IMPORTACION | B35: 2005 | C35: 2006 | D35: 2007 | E35: 2008 | F35: 2009 | G35: 2010 | H35: 2011 | I35: 2012 | J35: 2013 | K35: 2014 | L35: 2015 | M35: 2016 | N35: 2017 | O35: 2018 | P35: 2019
A37: Total | B37: 1175.0891 | C37: 1312.3561 | D37: 1563.285 | E37: 1780.0249 | F37: 1690.4806 | G37: 2063.1866 | H37: 2307.5298 | I37: 2449.6146 | J37: 2401.159 | K37: 2560.9862 | L37: 2904.2855 | M37: 3994.254 | N37: 4417.6104 | O37: 5032.193 | P37: 4803.342
A39: Energía primaria | B39: 214.63649 | C39: 225.28817 | D39: 157.07036 | E39: 131.82857 | F39: 173.82363 | G39: 222.89887 | H39: 219.49365 | I39: 215.30875 | J39: 216.96667 | K39: 210.82794 | L39: 223.23036 | M39: 239.84802 | N39: 301.22066 | O39: 277.237 | P39: 275.146
A40: Carbón | B40: 214.63649 | C40: 225.28817 | D40: 157.07036 | E40: 131.82857 | F40: 173.82363 | G40: 222.89887 | H40: 219.49365 | I40: 215.30875 | J40: 216.96667 | K40: 210.82794 | L40: 223.23036 | M40: 239.84802 | N40: 301.22066 | O40: 268.665 | P40: 275.146
A41: Petróleo crudo | B41: 0 | C41: 0 | D41: 0 | E41: 0 | F41: 0 | G41: 0 | H41: 0 | I41: 0 | J41: 0 | K41: 0 | L41: 0 | M41: 0 | N41: 0 | O41: 8.572 | P41: 0
A43: Energía secundaria | B43: 960.45259 | C43: 1087.0679 | D43: 1406.2146 | E43: 1648.1963 | F43: 1516.6569 | G43: 1840.2877 | H43: 2088.0361 | I43: 2234.3058 | J43: 2184.1923 | K43: 2350.1583 | L43: 2681.0551 | M43: 3754.4059 | N43: 4116.3898 | O43: 4754.956 | P43: 4528.196
A44: Coque | B44: 80.811661 | C44: 105.59073 | D44: 119.66027 | E44: 117.76023 | F44: 75.729024 | G44: 93.548424 | H44: 103.09529 | I44: 113.58223 | J44: 95.548637 | K44: 89.063171 | L44: 104.41035 | M44: 139.8685 | N44: 171.72484 | O44: 170.734 | P44: 149.518
A45: Coque de carbón | B45: 10.34776 | C45: 8.569837 | D45: 7.217706 | E45: 9.237363 | F45: 5.517239 | G45: 10.366608 | H45: 8.90816 | I45: 10.366377 | J45: 9.894612 | K45: 13.286949 | L45: 13.869203 | M45: 29.413607 | N45: 31.52665 | O45: 19.178 | P45: 32.333
A46: Coque de petróleo | B46: 70.4639 | C46: 97.020891 | D46: 112.44256 | E46: 108.52287 | F46: 70.211785 | G46: 83.181816 | H46: 94.187132 | I46: 103.21585 | J46: 85.654025 | K46: 75.776222 | L46: 90.541153 | M46: 110.45489 | N46: 140.19819 | O46: 151.556 | P46: 117.185
A47: Gas licuado | B47: 100.22508 | C47: 103.91974 | D47: 126.37883 | E47: 138.04281 | F47: 124.11815 | G47: 122.37296 | H47: 126.42366 | I47: 130.83708 | J47: 119.61333 | K47: 127.88249 | L47: 158.39708 | M47: 206.48342 | N47: 224.86509 | O47: 248.94 | P47: 233.628
A48: Gasolinas y naftas | B48: 354.59955 | C48: 399.0066 | D48: 587.25496 | E48: 645.37498 | F48: 624.14022 | G48: 761.69667 | H48: 815.73267 | I48: 755.48205 | J48: 713.79389 | K48: 711.47402 | L48: 810.81735 | M48: 978.83989 | N48: 1061.0026 | O48: 1262.578 | P48: 1128.085
A49: Querosenos | B49: 0 | C49: 0.260609 | D49: 6.815569 | E49: 9.697214 | F49: 2.168061 | G49: 8.053136 | H49: 1.839684 | I49: 6.614373 | J49: 6.557259 | K49: 24.126674 | L49: 50.347961 | M49: 72.325782 | N49: 91.191092 | O49: 121.7 | P49: 114.693
... A54: Electricidad | B54: 0.507 | C54: 2.179 | D54: 1.204 | E54: 1.425 | F54: 1.388 | G54: 1.571 | H54: 2.359 | I54: 8.432 | J54: 5.942 | K54: 9.141 | L54: 8.795 | M54: 12.463 | N54: 8.394832 | O54: 14.185 | P54: 14.067
A56: Notas:
A57: Las importaciones de gas seco incluyen importaciones de gas natural licuado.
A58: La suma de los parciales puede no coincidir con los totales, debido al redondeo de las cifras.
A59: Los datos del a&ntilde;o 2018 son preliminares y están sujetos a cambios sin previo aviso.
A62: Sistema de Información Energética
A63: Secretaría de Energía
A64: Dirección General de Planeación e Información Energéticas
A65: Balance Nacional de Energía: Exportación de energía
A66: (petajoules)
A68: EXPORTACION | B68: REALES
B69: 2005 | C69: 2006 | D69: 2007 | E69: 2008 | F69: 2009 | G69: 2010 | H69: 2011 | I69: 2012 | J69: 2013 | K69: 2014 | L69: 2015 | M69: 2016 | N69: 2017 | O69: 2018 | P69: 2019
A71: Total | B71: 4363.4643 | C71: 4342.1227 | D71: 4120.8671 | E71: 3654.3374 | F71: 3381.5952 | G71: 3644.3493 | H71: 3565.606 | I71: 3311.6611 | J71: 3183.6151 | K71: 3120.716 | L71: 3104.8854 | M71: 3100.9289 | N71: 2974.8899 | O71: 3030.586 | P71: 2747.441
A73: Energía primaria | B73: 4152.95 | C73: 4033.232 | D73: 3788.285 | E73: 3288.935 | F73: 2877.632 | G73: 3170.949 | H73: 3137.065 | I73: 2962.365 | J73: 2756.588 | K73: 2650.786 | L73: 2634.239 | M73: 2685.715 | N73: 2609.339 | O73: 2681.844 | P73: 2465.454
A74: Carbón | B74: 0.09796 | C74: 0.074824 | D74: 0.187884 | E74: 2.64619 | F74: 1.234903 | G74: 3.224433 | H74: 7.096278 | I74: 6.345785 | J74: 0.137706 | K74: 0.10382 | L74: 0.084318 | M74: 0.075295 | N74: 0.077518 | O74: 0.142 | P74: 0.135
A75: Petróleo crudo | B75: 4149.8001 | C75: 4031.6661 | D75: 3788.0968 | E75: 3286.2891 | F75: 2876.3971 | G75: 3167.7244 | H75: 3128.6874 | I75: 2946.2128 | J75: 2744.4456 | K75: 2646.0545 | L75: 2631.4904 | M75: 2685.6401 | N75: 2609.2615 | O75: 2681.702 | P75: 2465.319
A76: Condensados | B76: 3.051736 | C76: 1.491546 | D76: 0 | E76: 0 | F76: 0 | G76: 0 | H76: 1.281691 | I76: 9.806507 | J76: 12.005027 | K76: 4.627808 | L76: 2.66384 | M76: 0 | N76: 0 | O76: 0 | P76: 0
A78: Energía secundaria | B78: 210.51451 | C78: 308.89027 | D78: 332.58244 | E78: 365.40213 | F78: 503.9632 | G78: 473.40048 | H78: 428.54063 | I78: 349.29594 | J78: 427.02676 | K78: 469.92987 | L78: 470.64683 | M78: 415.2135 | N78: 365.55087 | O78: 348.742 | P78: 281.987
A79: Coque | B79: 4.54636 | C79: 3.671646 | D79: 1.44476 | E79: 1.662126 | F79: 3.058645 | G79: 1.424067 | H79: 0.106811 | I79: 22.314572 | J79: 20.58146 | K79: 2.055261 | L79: 0.003841 | M79: 0.014793 | N79: 0.094232 | O79: 1.279 | P79: 0.098
A80: Coque de carbón | B80: 0.04063 | C80: 0.067942 | D80: 0.076318 | E80: 0.091393 | F80: 0.008094 | G80: 0.019071 | H80: 0.052751 | I80: 0.0302 | J80: 0.020737 | K80: 0.015575 | L80: 0.003283 | M80: 0.004357 | N80: 0.068796 | O80: 1.179 | P80: 0.006
A81: Coque de petróleo | B81: 4.50573 | C81: 3.603704 | D81: 1.368442 | E81: 1.570733 | F81: 3.050551 | G81: 1.404996 | H81: 0.05406 | I81: 22.284371 | J81: 20.560723 | K81: 2.039686 | L81: 0.000558 | M81: 0.010437 | N81: 0.025436 | O81: 0.099 | P81: 0.092
A82: Gas licuado | B82: 2.434862 | C82: 2.867986 | D82: 1.553391 | E82: 0.175483 | F82: 1.684108 | G82: 0.143305 | H82: 2.280211 | I82: 0.173251 | J82: 0.266531 | K82: 1.959765 | L82: 0.031356 | M82: 6.759627 | N82: 8.596408 | O82: 2.878 | P82: 1.396
A83: Gasolinas y naftas | B83: 146.89079 | C83: 161.07125 | D83: 148.17284 | E83: 128.28439 | F83: 132.88814 | G83: 125.94856 | H83: 141.22593 | I83: 130.0717 | J83: 124.79505 | K83: 123.61946 | L83: 118.81371 | M83: 103.40388 | N83: 84.740105 | O83: 77.043 | P83: 64.678
A84: Querosenos | B84: 13.245928 | C84: 11.988546 | D84: 6.671132 | E84: 11.406276 | F84: 8.444385 | G84: 2.663987 | H84: 3.578424 | I84: 0 | J84: 0 | K84: 0 | L84: 0 | M84: 0 | N84: 0 | O84: 0 | P84: 0
... A89: Electricidad | B89: 26.59 | C89: 29.63 | D89: 27.57 | E89: 30.244 | F89: 28.221 | G89: 21.82 | H89: 22.253 | I89: 23.694 | J89: 26.48 | K89: 33.853 | L89: 32.977 | M89: 31.004 | N89: 28.351733 | O89: 26.651 | P89: 18.762
A91: Nota:
A92: La suma de los parciales puede no coincidir con los totales debido al redondeo de las cifras.
A93: Los datos del a&ntilde;o 2018 son preliminares y están sujetos a cambios sin previo aviso.

Sheet OrigenDestino_2019
A1: Sistema de Información Energética
A2: Secretaría de Energía
A3: Dirección General de Planeación e Información Energéticas
A4: Balance Nacional de Energía: Origen y destino de la energía
A5: (petajoules)
A6: REALES 2019
B9: Carbón | C9: Petróleo crudo | D9: Condensados | E9: Gas natural | F9: Nucleoenergía | G9: Hidroenergía | H9: Geoenergía | I9: Energía solar | J9: Energía eólica | K9: Bagazo de ca&ntilde;a | L9: Le&ntilde;a | M9: Biogás | N9: Total de energía primaria | O9: Coque de carbón | P9: Coque de petróleo | Q9: Gas LP | R9: Gasolinas y naftas | S9: Querosenos | T9: Diesel | U9: Combustóleo | V9: Productos no energéticos | W9: Gas seco | X9: Otros autogeneración | Y9: Electricidad | Z9: Total de energía secundaria | AA9: Total
A11: Producción | B11: 230.461 | C11: 3788.641 | D11: 60.487 | E11: 1466.036 | F11: 124.817 | G11: 84.989 | H11: 112.883 | I11: 40.315 | J11: 60.216 | K11: 113.249 | L11: 247.919 | M11: 2.799 | N11: 6332.812 | O11: 0 | P11: 0 | Q11: 0 | R11: 0 | S11: 0 | T11: 0 | U11: 0 | V11: 0 | W11: 0 | X11: 0 | Y11: 0 | Z11: 0 | AA11: 6332.812
A12: De otras fuentes | E12: 684.327 | N12: 684.327 | O12: 0 | P12: 0 | Q12: 0 | R12: 0 | S12: 0 | T12: 0 | U12: 0 | V12: 0 | W12: 0 | X12: 0 | Y12: 0 | Z12: 0 | AA12: 684.327
A13: Importación | B13: 275.146 | C13: 0 | N13: 275.146 | O13: 32.333 | P13: 117.185 | Q13: 233.628 | R13: 1128.085 | S13: 114.693 | T13: 572.06 | U13: 103.143 | V13: 0 | W13: 2213.002 | X13: 0 | Y13: 14.067 | Z13: 4528.196 | AA13: 4803.342
A14: Variación de inventarios | B14: 3.693 | C14: 41.625 | D14: 5.886 | E14: 21.153 | N14: 72.357 | O14: 0 | P14: -6.525 | Q14: -0.691 | R14: -91.919 | S14: 16.157 | T14: -41.723 | U14: 15.889 | V14: -1.096 | W14: -0.29 | X14: 0 | Z14: -110.196 | AA14: -37.838
A15: Oferta total | B15: 509.3 | C15: 3830.266 | D15: 66.373 | E15: 2171.516 | F15: 124.817 | G15: 84.989 | H15: 112.883 | I15: 40.315 | J15: 60.216 | K15: 113.249 | L15: 247.919 | M15: 2.799 | N15: 7364.642 | O15: 32.333 | P15: 110.66 | Q15: 232.937 | R15: 1036.166 | S15: 130.85 | T15: 530.337 | U15: 119.032 | V15: -1.096 | W15: 2212.712 | X15: 0 | Y15: 14.067 | Z15: 4417.998 | AA15: 11782.641
A16: Exportación | B16: -0.135 | C16: -2465.319 | D16: 0 | N16: -2465.454 | O16: -0.006 | P16: -0.092 | Q16: -1.396 | R16: -64.678 | S16: 0 | T16: -27.128 | U16: -168.521 | V16: 0 | W16: -1.403 | X16: 0 | Y16: -18.762 | Z16: -281.986 | AA16: -2747.44
A17: No aprovechada | C17: -0.878 | E17: -222.025 | K17: -1.246 | N17: -224.149 | X17: 0 | Y17: 0 | Z17: 0 | AA17: -224.148
A18: Maquila-intercambio neto | C18: 0 | N18: 0 | Q18: 0 | R18: 0 | S18: 0 | T18: 0 | U18: 0 | V18: 0 | X18: 0 | Y18: 0 | Z18: 0 | AA18: 0
A19: Oferta interna bruta | B19: 509.165 | C19: 1364.069 | D19: 66.373 | E19: 1949.491 | F19: 124.817 | G19: 84.989 | H19: 112.883 | I19: 40.315 | J19: 60.216 | K19: 112.003 | L19: 247.919 | M19: 2.799 | N19: 4675.039 | O19: 32.327 | P19: 110.568 | Q19: 231.541 | R19: 971.488 | S19: 130.85 | T19: 503.209 | U19: -49.489 | V19: -1.096 | W19: 2211.309 | X19: 0 | Y19: -4.695 | Z19: 4136.012 | AA19: 8811.053
A20: Total transformación | B20: -387.477 | C20: -1287.501 | D20: -66.372 | E20: -1311.252 | F20: -124.817 | G20: -84.989 | H20: -112.883 | I20: -26.519018 | J20: -60.216 | K20: -75.569 | L20: 0 | M20: -2.799136 | N20: -3540.3942 | O20: 26.282 | P20: 6.199 | Q20: 162.217 | R20: 475.974 | S20: 60.903 | T20: 169.406 | U20: 102.172 | V20: 118.697 | W20: -758.513 | X20: 0 | Y20: 1240.487 | Z20: 1603.824 | AA20: -1936.5702
A21: Coquizadoras | B21: -37.048 | N21: -37.048 | O21: 26.282 | X21: 1.555 | Y21: 0 | Z21: 27.837 | AA21: -9.211
A22: Refinerías y despuntadoras | C22: -1287.501 | D22: -33.369 | N22: -1320.87 | P22: 40.529 | Q22: 10.509 | R22: 391.414 | S22: 60.903 | T22: 219.889 | U22: 354.177 | V22: 36.172 | W22: 92.064 | X22: 0 | Y22: 0 | Z22: 1205.657 | AA22: -115.213
A23: Plantas de gas y fraccionadoras | D23: -33.003 | E23: -1311.252 | N23: -1344.255 | Q23: 152.068 | R23: 84.56 | S23: 0 | T23: 0 | U23: 0 | V23: 82.525 | W23: 908.869 | X23: 0 | Y23: 0 | Z23: 1228.022 | AA23: -116.233
A24: Centrales eléctricas públicas | B24: -284.193 | F24: -124.817 | G24: -79.45 | H24: -110.704 | I24: -0.036 | J24: -0.264 | N24: -599.463 | T24: -32.784 | U24: -227.928 | W24: -577.527 | X24: 0 | Y24: 542.415 | Z24: -295.824 | AA24: -895.287
A25: Centrales eléctricas PIE | J25: -8.4 | N25: -8.4 | T25: -8.904 | W25: -604.643 | X25: 0 | Y25: 339.96 | Z25: -273.587 | AA25: -281.987
A26: Centrales eléctricas de autogeneración | B26: -66.236 | G26: -2.69 | H26: -2.179 | I26: -4.94 | J26: -43.42 | K26: -67.774 | M26: -2.096 | N26: -189.335 | P26: -34.33 | Q26: -0.36 | T26: -7.638 | U26: -24.077 | W26: -462.463 | X26: -1.555 | Y26: 278.929 | Z26: -251.494 | AA26: -440.829
A27: Centrales eléctricas con modalidad de Generación | G27: -2.849 | I27: -21.543018 | J27: -8.132 | K27: -7.795 | M27: -0.703136 | N27: -41.022154 | T27: -1.157 | W27: -114.813 | Y27: 79.183 | Z27: -36.787 | AA27: -77.809154
A28: Consumo propio del sector | B28: 0 | C28: 0 | D28: 0 | E28: -228.382 | N28: -228.382 | O28: -1.577 | Q28: -2.376 | R28: -3.413 | S28: -0.006 | T28: -42.847 | U28: -30.701 | V28: 0 | W28: -786.839 | X28: 0 | Y28: -50.434 | Z28: -918.193 | AA28: -1146.575
A29: Transferencias interproductos | E29: -94.74 | N29: -94.74 | W29: 94.011 | X29: 0 | Y29: 0 | Z29: 94.011 | AA29: -0.729
A30: Recirculaciones | E30: -315.118 | N30: -315.118 | W30: -196.71 | X30: 0 | Y30: 0 | Z30: -196.71 | AA30: -511.828
A31: Diferencia estadística | B31: 0.001 | C31: -73.352 | D31: -0.001 | E31: 0.001 | F31: 0 | G31: 0 | H31: 0 | I31: 1.8e-05 | J31: 0 | K31: -0.001 | L31: 0 | N31: -73.352982 | O31: 0 | P31: -7.10543e-15 | Q31: -0.001 | R31: -50.003 | S31: -16.791 | T31: -0.001 | U31: -6.024 | V31: -52.209 | W31: -1.42109e-14 | X31: 0 | Y31: 32.981 | Z31: -119.003 | AA31: -192.35598
A32: Pérdidas (transp.,dist. y almac) | C32: -3.216 | N32: -3.216 | X32: 0 | Y32: -195.165 | Z32: -195.165 | AA32: -198.381
A33: Consumo final total | B33: 121.689 | C33: 0 | I33: 13.796 | K33: 36.433 | L33: 247.919 | N33: 419.838 | O33: 57.032 | P33: 116.767 | Q33: 391.381 | R33: 1394.046 | S33: 174.956 | T33: 629.767 | U33: 15.958 | V33: 65.392 | W33: 563.258 | X33: 0 | Y33: 1023.174 | Z33: 4431.731 | AA33: 4851.569
A34: Consumo final no energético | K34: 0.077 | N34: 0.077 | P34: 0 | Q34: 4.542 | R34: 6.674 | S34: 0 | U34: 0 | V34: 65.392 | W34: 13.91 | X34: 0 | Z34: 90.518 | AA34: 90.595
A35: Petroquímica de Pemex | Q35: 0 | R35: 6.674 | S35: 0 | V35: 27.351 | W35: 13.91 | X35: 0 | Z35: 47.935 | AA35: 47.935
A36: Otras ramas económicas | K36: 0.077 | N36: 0.077 | P36: 0 | Q36: 4.542 | R36: 0 | S36: 0 | U36: 0 | V36: 38.041 | W36: 0 | X36: 0 | Z36: 42.583 | AA36: 42.66
A37: Consumo final energético | B37: 121.689 | I37: 13.796 | K37: 36.357 | L37: 247.919 | N37: 419.761 | O37: 57.032 | P37: 116.767 | Q37: 386.84 | R37: 1387.372 | S37: 174.956 | T37: 629.767 | U37: 15.958 | W37: 549.348 | X37: 0 | Y37: 1023.174 | Z37: 4341.214 | AA37: 4760.975
A38: Residencial, comercial y público | I38: 13.059 | L38: 247.919 | N38: 260.978 | Q38: 292.932 | S38: 0 | T38: 0 | U38: 0 | W38: 40.902 | X38: 0 | Y38: 357.774 | Z38: 691.609 | AA38: 952.587
A39: Transporte | Q39: 61.085 | R39: 1386.08 | S39: 174.956 | T39: 428.116 | U39: 2.382 | W39: 2.086 | X39: 0 | Y39: 3.981 | Z39: 2058.686 | AA39: 2058.686
A40: Agropecuario | Q40: 3.529 | R40: 0 | S40: 0 | T40: 141.099 | U40: 0 | X40: 0 | Y40: 47.267 | Z40: 191.895 | AA40: 191.895
A41: Industrial | B41: 121.689 | I41: 0.737 | K41: 36.357 | N41: 158.783 | O41: 57.032 | P41: 116.767 | Q41: 29.293 | R41: 1.292 | S41: 0 | T41: 60.553 | U41: 13.577 | W41: 506.36 | X41: 0 | Y41: 614.153 | Z41: 1399.027 | AA41: 1557.81
A42: Producción bruta de energía secundaria | O42: 26.282 | P42: 40.529 | Q42: 162.577 | R42: 475.974 | S42: 60.903 | T42: 219.889 | U42: 354.177 | V42: 118.697 | W42: 1000.933 | X42: 1.555 | Y42: 1240.487 | Z42: 3702.003 | AA42: 3702.003
A44: Nota(s):
A45: La suma de los parciales puede no coincidir con los totales debido al redondeo de las cifras.
A46: La generación de electricidad mediante módulos fotovoltáicos se consideró como centrales eléctricas autogeneración.
A47: Los datos del a&ntilde;o 2018 son preliminares y están sujetos a cambios sin previo aviso.
A48: A partir de 2016 se incluye información de las centrales eléctricas con permiso de generación otorgado por la CRE.
A49: Fuente: Sistema de Información Energética, SENER.

Sheet Start Year Data
A1: Fuel | B1: Production | C1: Imports | D1: Exports | E1: Domestic Use | F1: Unit | G1: Domestic use also includes change in domestic inventories, which should average to zero over multi-year timeframes.
A2: electricity (not used in this variable)
A3: hard coal | B3: =OrigenDestino_2019!B11+OrigenDestino_2019!O42+OrigenDestino_2019!P42 -> 297.272 | C3: =OrigenDestino_2019!B13+OrigenDestino_2019!O13+OrigenDestino_2019!P13 -> 424.664 | D3: =-(OrigenDestino_2019!B16+OrigenDestino_2019!O16+OrigenDestino_2019!P16) -> 0.233 | E3: =B3+C3-D3 -> 721.703 | F3: PJ
A4: natural gas | B4: =OrigenDestino_2019!E11 -> 1466.036 | C4: =OrigenDestino_2019!E13 -> 0 | D4: =-(OrigenDestino_2019!E16) -> 0 | E4: =B4+C4-D4 -> 1466.036 | F4: PJ
A5: uranium | B5: =OrigenDestino_2019!F11 -> 124.817 | C5: =OrigenDestino_2019!F13 -> 0 | D5: =-OrigenDestino_2019!F16 -> 0 | E5: =B5+C5-D5 -> 124.817 | F5: million pounds U3O8
A6: hydro (is not a fuel)
A7: wind (is not a fuel)
A8: solar (is not a fuel)
A9: biomass | B9: =OrigenDestino_2019!K11+OrigenDestino_2019!L11 -> 361.168 | C9: =OrigenDestino_2019!K13+OrigenDestino_2019!L13 -> 0 | D9: =-(OrigenDestino_2019!K16+OrigenDestino_2019!L16) -> 0 | E9: =B9+C9-D9 -> 361.168 | F9: PJ
A10: petroleum gasoline | B10: =OrigenDestino_2019!R42 -> 475.974 | C10: =OrigenDestino_2019!R13 -> 1128.085 | D10: =-OrigenDestino_2019!R16 -> 64.678 | E10: =B10+C10-D10 -> 1539.381 | F10: PJ
A11: petroleum diesel | B11: =OrigenDestino_2019!T42 -> 219.889 | C11: =OrigenDestino_2019!T13 -> 572.06 | D11: =-OrigenDestino_2019!T16 -> 27.128 | E11: =B11+C11-D11 -> 764.821 | F11: PJ
A12: biofuel gasoline | B12: 0 | C12: 0 | D12: 0 | E12: =B12+C12-D12 -> 0 | F12: PJ
A13: biofuel diesel | B13: 0 | C13: 0 | D13: 0 | E13: =B13+C13-D13 -> 0 | F13: PJ
A14: jet fuel or kerosene | B14: =OrigenDestino_2019!S42 -> 60.903 | C14: =OrigenDestino_2019!S13 -> 114.693 | D14: =OrigenDestino_2019!S16 -> 0 | E14: =B14+C14-D14 -> 175.596 | F14: PJ
A15: heat (not used in this variable)
A16: geothermal (is not a fuel)
A17: lignite | B17: 0 | C17: 0 | D17: 0 | E17: =B17+C17-D17 -> 0 | F17: PJ
A18: crude oil | B18: =OrigenDestino_2019!C11 -> 3788.641 | C18: =OrigenDestino_2019!C13 -> 0 | D18: =-OrigenDestino_2019!C16 -> 2465.319 | E18: =B18+C18-D18 -> 1323.322 | F18: PJ
A19: heavy fuel oil | B19: =OrigenDestino_2019!$U$42 -> 354.177 | C19: =OrigenDestino_2019!U13 -> 103.143 | D19: =-OrigenDestino_2019!U16 -> 168.521 | E19: =B19+C19-D19 -> 288.799 | F19: PJ
A20: LPG propane or butane | B20: =OrigenDestino_2019!Q42 -> 162.577 | C20: =OrigenDestino_2019!Q13 -> 233.628 | D20: =-OrigenDestino_2019!Q16 -> 1.396 | E20: =B20+C20-D20 -> 394.809 | F20: PJ
A21: municipal solid waste | B21: 0 | C21: 0 | D21: 0 | E21: =B21+C21-D21 -> 0 | F21: PJ
A22: hydrogen | B22: 0 | C22: 0 | D22: 0 | E22: =B22+C22-D22 -> 0 | F22: PJ
A24: Converted to BTU
A25: Fuel | B25: Production | C25: Imports | D25: Exports | E25: Domestic Use | F25: Unit | H25: Conversion Factors
A26: electricity (not used in this variable) | K26: SENER | L26: https://sie.energia.gob.mx/bdiController.do?action=convertidor
A27: hard coal | B27: =B3*$H27 -> 281759490896640 | C27: =C3*$H27 -> 4.0250381e+14 | D27: =D3*$H27 -> 220841388960 | E27: =E3*$H27 -> 6.8404246e+14 | F27: BTU | H27: =K27 -> 947817120000 | I27: BTU per | J27: PJ | K27: 947817120000 | L27: BTU/PJ
A28: natural gas | B28: =B4*$H28 -> 1.389534e+15 | C28: =C4*$H28 -> 0 | D28: =D4*$H28 -> 0 | E28: =E4*$H28 -> 1.389534e+15 | F28: BTU | H28: =$H$27 -> 947817120000 | I28: =I27 -> BTU per | J28: =J27 -> PJ
A29: uranium | B29: =B5*$H29 -> 118303689467040 | C29: =C5*$H29 -> 0 | D29: =D5*$H29 -> 0 | E29: =E5*$H29 -> 118303689467040 | F29: BTU | H29: =$H$27 -> 947817120000 | I29: =I28 -> BTU per | J29: =J28 -> PJ
A30: hydro (is not a fuel) | H30: =$H$27 -> 947817120000 | I30: =I29 -> BTU per | J30: =J29 -> PJ
A31: wind (is not a fuel) | H31: =$H$27 -> 947817120000 | I31: =I30 -> BTU per | J31: =J30 -> PJ
A32: solar (is not a fuel) | H32: =$H$27 -> 947817120000 | I32: =I31 -> BTU per | J32: =J31 -> PJ
A33: biomass | B33: =B9*$H33 -> 342321213596160 | C33: =C9*$H33 -> 0 | D33: =D9*$H33 -> 0 | E33: =E9*$H33 -> 342321213596160 | F33: BTU | H33: =$H$27 -> 947817120000 | I33: =I32 -> BTU per | J33: =J32 -> PJ
A34: petroleum gasoline | B34: =B10*$H34 -> 451136305874880 | C34: =C10*$H34 -> 1.0692183e+15 | D34: =D10*$H34 -> 61302915687360 | E34: =E10*$H34 -> 1.4590517e+15 | F34: BTU | H34: =$H$27 -> 947817120000 | I34: =I33 -> BTU per | J34: =J33 -> PJ
A35: petroleum diesel | B35: =B11*$H35 -> 208414558699680 | C35: =C11*$H35 -> 5.4220826e+14 | D35: =D11*$H35 -> 25712382831360 | E35: =E11*$H35 -> 7.2491044e+14 | F35: BTU | H35: =$H$27 -> 947817120000 | I35: =I34 -> BTU per | J35: =J34 -> PJ
A36: biofuel gasoline | B36: =B12*$H36 -> 0 | C36: =C12*$H36 -> 0 | D36: =D12*$H36 -> 0 | E36: =E12*$H36 -> 0 | F36: BTU | H36: =$H$27 -> 947817120000 | I36: =I35 -> BTU per | J36: =J35 -> PJ
A37: biofuel diesel | B37: =B13*$H37 -> 0 | C37: =C13*$H37 -> 0 | D37: =D13*$H37 -> 0 | E37: =E13*$H37 -> 0 | F37: BTU | H37: =$H$27 -> 947817120000 | I37: =I36 -> BTU per | J37: =J36 -> PJ
A38: jet fuel or kerosene | B38: =B14*$H38 -> 57724906059360 | C38: =C14*$H38 -> 108707988944160 | D38: =D14*$H38 -> 0 | E38: =E14*$H38 -> 166432895003520 | F38: BTU | H38: =$H$27 -> 947817120000 | I38: =I37 -> BTU per | J38: =J37 -> PJ
A39: heat (not used in this variable) | H39: =$H$27 -> 947817120000 | I39: =I38 -> BTU per | J39: =J38 -> PJ
A40: geothermal (is not a fuel) | H40: =$H$27 -> 947817120000 | I40: =I39 -> BTU per | J40: =J39 -> PJ
A41: lignite | B41: =B17*$H41 -> 0 | C41: =C17*$H41 -> 0 | D41: =D17*$H41 -> 0 | E41: =E17*$H41 -> 0 | F41: BTU | H41: =$H$27 -> 947817120000 | I41: =I40 -> BTU per | J41: =J40 -> PJ
A42: crude oil | B42: =B18*$H42 -> 3.5909388e+15 | C42: =C18*$H42 -> 0 | D42: =D18*$H42 -> 2.3366716e+15 | E42: =E18*$H42 -> 1.2542672e+15 | F42: BTU | H42: =$H$27 -> 947817120000 | I42: =I41 -> BTU per | J42: =J41 -> PJ
A43: heavy fuel oil | B43: =B19*$H43 -> 335695024110240 | C43: =C19*$H43 -> 97760701208160 | D43: =D19*$H43 -> 159727088879520 | E43: =E19*$H43 -> 2.7372864e+14 | F43: BTU | H43: =$H$27 -> 947817120000 | I43: =I42 -> BTU per | J43: =J42 -> PJ
A44: LPG propane or butane | B44: =B20*$H44 -> 154093263918240 | C44: =C20*$H44 -> 221436618111360 | D44: =D20*$H44 -> 1323152699520 | E44: =E20*$H44 -> 374206729330080 | F44: BTU | H44: =$H$27 -> 947817120000 | I44: =I43 -> BTU per | J44: =J43 -> PJ
A45: municipal solid waste | B45: =B21*$H45 -> 0 | C45: =C21*$H45 -> 0 | D45: =D21*$H45 -> 0 | E45: =E21*$H45 -> 0 | F45: BTU | H45: =$H$27 -> 947817120000 | I45: =I44 -> BTU per | J45: =J44 -> PJ
A46: hydrogen | B46: =B22*$H46 -> 0 | C46: =C22*$H46 -> 0 | D46: =D22*$H46 -> 0 | E46: =E22*$H46 -> 0 | F46: BTU | H46: =$H$27 -> 947817120000 | I46: =I45 -> BTU per | J46: =J45 -> PJ

Sheet Time Series Scaling Factors
A1: Production Scaling Factors
B2: 2019 | C2: 2020 | D2: 2021 | E2: 2022 | F2: 2023 | G2: 2024 | H2: 2025 | I2: 2026 | J2: 2027 | K2: 2028 | L2: 2029 | M2: 2030 | N2: 2031 | O2: 2032 | P2: 2033 | Q2: 2034 | R2: 2035 | S2: 2036 | T2: 2037 | U2: 2038 | V2: 2039 | W2: 2040 | X2: 2041 | Y2: 2042 | Z2: 2043 | AA2: 2044 | AB2: 2045 | AC2: 2046 | AD2: 2047 | AE2: 2048 | AF2: 2049 | AG2: 2050
A3: electricity (not used in this variable) | B3: 0 | C3: 0 | D3: 0 | E3: 0 | F3: 0 | G3: 0 | H3: 0 | I3: 0 | J3: 0 | K3: 0 | L3: 0 | M3: 0 | N3: 0 | O3: 0 | P3: 0 | Q3: 0 | R3: 0 | S3: 0 | T3: 0 | U3: 0 | V3: 0 | W3: 0 | X3: 0 | Y3: 0 | Z3: 0 | AA3: 0 | AB3: 0 | AC3: 0 | AD3: 0 | AE3: 0 | AF3: 0 | AG3: 0
A4: hard coal | B4: ='AEO Table 1'!C$19/'AEO Table 1'!$C$19 -> 1 | C4: ='AEO Table 1'!D$19/'AEO Table 1'!$C$19 -> 0.90812016 | D4: ='AEO Table 1'!E$19/'AEO Table 1'!$C$19 -> 0.85455327 | E4: ='AEO Table 1'!F$19/'AEO Table 1'!$C$19 -> 0.83991896 | F4: ='AEO Table 1'!G$19/'AEO Table 1'!$C$19 -> 0.7948032 | G4: ='AEO Table 1'!H$19/'AEO Table 1'!$C$19 -> 0.77118027 | H4: ='AEO Table 1'!I$19/'AEO Table 1'!$C$19 -> 0.69476213 | I4: ='AEO Table 1'!J$19/'AEO Table 1'!$C$19 -> 0.70824709 | ... AG4: ='AEO Table 1'!AH$19/'AEO Table 1'!$C$19 -> 0.62138171
A5: natural gas | B5: ='AEO Table 1'!C$18/'AEO Table 1'!$C$18 -> 1 | C5: ='AEO Table 1'!D$18/'AEO Table 1'!$C$18 -> 1.0213665 | D5: ='AEO Table 1'!E$18/'AEO Table 1'!$C$18 -> 1.0756457 | E5: ='AEO Table 1'!F$18/'AEO Table 1'!$C$18 -> 1.0942691 | F5: ='AEO Table 1'!G$18/'AEO Table 1'!$C$18 -> 1.1076205 | G5: ='AEO Table 1'!H$18/'AEO Table 1'!$C$18 -> 1.1257205 | H5: ='AEO Table 1'!I$18/'AEO Table 1'!$C$18 -> 1.1651595 | I5: ='AEO Table 1'!J$18/'AEO Table 1'!$C$18 -> 1.2042915 | ... AG5: ='AEO Table 1'!AH$18/'AEO Table 1'!$C$18 -> 1.5783559
A6: uranium | B6: ='AEO Table 1'!C$20/'AEO Table 1'!$C$20 -> 1 | C6: ='AEO Table 1'!D$20/'AEO Table 1'!$C$20 -> 0.98213005 | D6: ='AEO Table 1'!E$20/'AEO Table 1'!$C$20 -> 0.96590062 | E6: ='AEO Table 1'!F$20/'AEO Table 1'!$C$20 -> 0.94789105 | F6: ='AEO Table 1'!G$20/'AEO Table 1'!$C$20 -> 0.95070335 | G6: ='AEO Table 1'!H$20/'AEO Table 1'!$C$20 -> 0.95437409 | H6: ='AEO Table 1'!I$20/'AEO Table 1'!$C$20 -> 0.93681737 | I6: ='AEO Table 1'!J$20/'AEO Table 1'!$C$20 -> 0.77903925 | ... AG6: ='AEO Table 1'!AH$20/'AEO Table 1'!$C$20 -> 0.46585692
A7: hydro (is not a fuel) | B7: 0 | C7: 0 | D7: 0 | E7: 0 | F7: 0 | G7: 0 | H7: 0 | I7: 0 | J7: 0 | K7: 0 | L7: 0 | M7: 0 | N7: 0 | O7: 0 | P7: 0 | Q7: 0 | R7: 0 | S7: 0 | T7: 0 | U7: 0 | V7: 0 | W7: 0 | X7: 0 | Y7: 0 | Z7: 0 | AA7: 0 | AB7: 0 | AC7: 0 | AD7: 0 | AE7: 0 | AF7: 0 | AG7: 0
A8: wind (is not a fuel) | B8: 0 | C8: 0 | D8: 0 | E8: 0 | F8: 0 | G8: 0 | H8: 0 | I8: 0 | J8: 0 | K8: 0 | L8: 0 | M8: 0 | N8: 0 | O8: 0 | P8: 0 | Q8: 0 | R8: 0 | S8: 0 | T8: 0 | U8: 0 | V8: 0 | W8: 0 | X8: 0 | Y8: 0 | Z8: 0 | AA8: 0 | AB8: 0 | AC8: 0 | AD8: 0 | AE8: 0 | AF8: 0 | AG8: 0
A9: solar (is not a fuel) | B9: 0 | C9: 0 | D9: 0 | E9: 0 | F9: 0 | G9: 0 | H9: 0 | I9: 0 | J9: 0 | K9: 0 | L9: 0 | M9: 0 | N9: 0 | O9: 0 | P9: 0 | Q9: 0 | R9: 0 | S9: 0 | T9: 0 | U9: 0 | V9: 0 | W9: 0 | X9: 0 | Y9: 0 | Z9: 0 | AA9: 0 | AB9: 0 | AC9: 0 | AD9: 0 | AE9: 0 | AF9: 0 | AG9: 0
A10: biomass | B10: ='AEO Table 1'!C$22/'AEO Table 1'!$C$22 -> 1 | C10: ='AEO Table 1'!D$22/'AEO Table 1'!$C$22 -> 0.98791071 | D10: ='AEO Table 1'!E$22/'AEO Table 1'!$C$22 -> 1.0003005 | E10: ='AEO Table 1'!F$22/'AEO Table 1'!$C$22 -> 1.0136874 | F10: ='AEO Table 1'!G$22/'AEO Table 1'!$C$22 -> 1.019386 | G10: ='AEO Table 1'!H$22/'AEO Table 1'!$C$22 -> 1.0258937 | H10: ='AEO Table 1'!I$22/'AEO Table 1'!$C$22 -> 1.0321171 | I10: ='AEO Table 1'!J$22/'AEO Table 1'!$C$22 -> 1.0377775 | ... AG10: ='AEO Table 1'!AH$22/'AEO Table 1'!$C$22 -> 1.1603109
A11: petroleum gasoline | B11: ='AEO Table 1'!C$16/'AEO Table 1'!$C$16 -> 1 | C11: ='AEO Table 1'!D$16/'AEO Table 1'!$C$16 -> 1.1332856 | D11: ='AEO Table 1'!E$16/'AEO Table 1'!$C$16 -> 1.2555026 | E11: ='AEO Table 1'!F$16/'AEO Table 1'!$C$16 -> 1.330323 | F11: ='AEO Table 1'!G$16/'AEO Table 1'!$C$16 -> 1.3645781 | G11: ='AEO Table 1'!H$16/'AEO Table 1'!$C$16 -> 1.3973669 | H11: ='AEO Table 1'!I$16/'AEO Table 1'!$C$16 -> 1.4158922 | I11: ='AEO Table 1'!J$16/'AEO Table 1'!$C$16 -> 1.4364623 | ... AG11: ='AEO Table 1'!AH$16/'AEO Table 1'!$C$16 -> 1.5448237
A12: petroleum diesel | B12: ='AEO Table 1'!C$16/'AEO Table 1'!$C$16 -> 1 | C12: ='AEO Table 1'!D$16/'AEO Table 1'!$C$16 -> 1.1332856 | D12: ='AEO Table 1'!E$16/'AEO Table 1'!$C$16 -> 1.2555026 | E12: ='AEO Table 1'!F$16/'AEO Table 1'!$C$16 -> 1.330323 | F12: ='AEO Table 1'!G$16/'AEO Table 1'!$C$16 -> 1.3645781 | G12: ='AEO Table 1'!H$16/'AEO Table 1'!$C$16 -> 1.3973669 | H12: ='AEO Table 1'!I$16/'AEO Table 1'!$C$16 -> 1.4158922 | I12: ='AEO Table 1'!J$16/'AEO Table 1'!$C$16 -> 1.4364623 | ... AG12: ='AEO Table 1'!AH$16/'AEO Table 1'!$C$16 -> 1.5448237
A13: biofuel gasoline | B13: ='AEO Table 1'!C$22/'AEO Table 1'!$C$22 -> 1 | C13: ='AEO Table 1'!D$22/'AEO Table 1'!$C$22 -> 0.98791071 | D13: ='AEO Table 1'!E$22/'AEO Table 1'!$C$22 -> 1.0003005 | E13: ='AEO Table 1'!F$22/'AEO Table 1'!$C$22 -> 1.0136874 | F13: ='AEO Table 1'!G$22/'AEO Table 1'!$C$22 -> 1.019386 | G13: ='AEO Table 1'!H$22/'AEO Table 1'!$C$22 -> 1.0258937 | H13: ='AEO Table 1'!I$22/'AEO Table 1'!$C$22 -> 1.0321171 | I13: ='AEO Table 1'!J$22/'AEO Table 1'!$C$22 -> 1.0377775 | ... AG13: ='AEO Table 1'!AH$22/'AEO Table 1'!$C$22 -> 1.1603109
A14: biofuel diesel | B14: ='AEO Table 1'!C$22/'AEO Table 1'!$C$22 -> 1 | C14: ='AEO Table 1'!D$22/'AEO Table 1'!$C$22 -> 0.98791071 | D14: ='AEO Table 1'!E$22/'AEO Table 1'!$C$22 -> 1.0003005 | E14: ='AEO Table 1'!F$22/'AEO Table 1'!$C$22 -> 1.0136874 | F14: ='AEO Table 1'!G$22/'AEO Table 1'!$C$22 -> 1.019386 | G14: ='AEO Table 1'!H$22/'AEO Table 1'!$C$22 -> 1.0258937 | H14: ='AEO Table 1'!I$22/'AEO Table 1'!$C$22 -> 1.0321171 | I14: ='AEO Table 1'!J$22/'AEO Table 1'!$C$22 -> 1.0377775 | ... AG14: ='AEO Table 1'!AH$22/'AEO Table 1'!$C$22 -> 1.1603109
A15: jet fuel or kerosene | B15: ='AEO Table 1'!C$16/'AEO Table 1'!$C$16 -> 1 | C15: ='AEO Table 1'!D$16/'AEO Table 1'!$C$16 -> 1.1332856 | D15: ='AEO Table 1'!E$16/'AEO Table 1'!$C$16 -> 1.2555026 | E15: ='AEO Table 1'!F$16/'AEO Table 1'!$C$16 -> 1.330323 | F15: ='AEO Table 1'!G$16/'AEO Table 1'!$C$16 -> 1.3645781 | G15: ='AEO Table 1'!H$16/'AEO Table 1'!$C$16 -> 1.3973669 | H15: ='AEO Table 1'!I$16/'AEO Table 1'!$C$16 -> 1.4158922 | I15: ='AEO Table 1'!J$16/'AEO Table 1'!$C$16 -> 1.4364623 | ... AG15: ='AEO Table 1'!AH$16/'AEO Table 1'!$C$16 -> 1.5448237
A16: heat (not used in this variable) | B16: 0 | C16: 0 | D16: 0 | E16: 0 | F16: 0 | G16: 0 | H16: 0 | I16: 0 | J16: 0 | K16: 0 | L16: 0 | M16: 0 | N16: 0 | O16: 0 | P16: 0 | Q16: 0 | R16: 0 | S16: 0 | T16: 0 | U16: 0 | V16: 0 | W16: 0 | X16: 0 | Y16: 0 | Z16: 0 | AA16: 0 | AB16: 0 | AC16: 0 | AD16: 0 | AE16: 0 | AF16: 0 | AG16: 0
A17: geothermal (is not a fuel) | B17: 0 | C17: 0 | D17: 0 | E17: 0 | F17: 0 | G17: 0 | H17: 0 | I17: 0 | J17: 0 | K17: 0 | L17: 0 | M17: 0 | N17: 0 | O17: 0 | P17: 0 | Q17: 0 | R17: 0 | S17: 0 | T17: 0 | U17: 0 | V17: 0 | W17: 0 | X17: 0 | Y17: 0 | Z17: 0 | AA17: 0 | AB17: 0 | AC17: 0 | AD17: 0 | AE17: 0 | AF17: 0 | AG17: 0
A18: lignite | B18: ='AEO Table 1'!C$19/'AEO Table 1'!$C$19 -> 1 | C18: ='AEO Table 1'!D$19/'AEO Table 1'!$C$19 -> 0.90812016 | D18: ='AEO Table 1'!E$19/'AEO Table 1'!$C$19 -> 0.85455327 | E18: ='AEO Table 1'!F$19/'AEO Table 1'!$C$19 -> 0.83991896 | F18: ='AEO Table 1'!G$19/'AEO Table 1'!$C$19 -> 0.7948032 | G18: ='AEO Table 1'!H$19/'AEO Table 1'!$C$19 -> 0.77118027 | H18: ='AEO Table 1'!I$19/'AEO Table 1'!$C$19 -> 0.69476213 | I18: ='AEO Table 1'!J$19/'AEO Table 1'!$C$19 -> 0.70824709 | ... AG18: ='AEO Table 1'!AH$19/'AEO Table 1'!$C$19 -> 0.62138171
A19: crude oil | B19: ='AEO Table 1'!C$16/'AEO Table 1'!$C$16 -> 1 | C19: ='AEO Table 1'!D$16/'AEO Table 1'!$C$16 -> 1.1332856 | D19: ='AEO Table 1'!E$16/'AEO Table 1'!$C$16 -> 1.2555026 | E19: ='AEO Table 1'!F$16/'AEO Table 1'!$C$16 -> 1.330323 | F19: ='AEO Table 1'!G$16/'AEO Table 1'!$C$16 -> 1.3645781 | G19: ='AEO Table 1'!H$16/'AEO Table 1'!$C$16 -> 1.3973669 | H19: ='AEO Table 1'!I$16/'AEO Table 1'!$C$16 -> 1.4158922 | I19: ='AEO Table 1'!J$16/'AEO Table 1'!$C$16 -> 1.4364623 | ... AG19: ='AEO Table 1'!AH$16/'AEO Table 1'!$C$16 -> 1.5448237
A20: heavy fuel oil | B20: ='AEO Table 1'!C$16/'AEO Table 1'!$C$16 -> 1 | C20: ='AEO Table 1'!D$16/'AEO Table 1'!$C$16 -> 1.1332856 | D20: ='AEO Table 1'!E$16/'AEO Table 1'!$C$16 -> 1.2555026 | E20: ='AEO Table 1'!F$16/'AEO Table 1'!$C$16 -> 1.330323 | F20: ='AEO Table 1'!G$16/'AEO Table 1'!$C$16 -> 1.3645781 | G20: ='AEO Table 1'!H$16/'AEO Table 1'!$C$16 -> 1.3973669 | H20: ='AEO Table 1'!I$16/'AEO Table 1'!$C$16 -> 1.4158922 | I20: ='AEO Table 1'!J$16/'AEO Table 1'!$C$16 -> 1.4364623 | ... AG20: ='AEO Table 1'!AH$16/'AEO Table 1'!$C$16 -> 1.5448237
A21: LPG propane or butane | B21: ='AEO Table 1'!C$17/'AEO Table 1'!$C$17 -> 1 | C21: ='AEO Table 1'!D$17/'AEO Table 1'!$C$17 -> 1.1643941 | D21: ='AEO Table 1'!E$17/'AEO Table 1'!$C$17 -> 1.2524868 | E21: ='AEO Table 1'!F$17/'AEO Table 1'!$C$17 -> 1.3762148 | F21: ='AEO Table 1'!G$17/'AEO Table 1'!$C$17 -> 1.3865703 | G21: ='AEO Table 1'!H$17/'AEO Table 1'!$C$17 -> 1.4057284 | H21: ='AEO Table 1'!I$17/'AEO Table 1'!$C$17 -> 1.4212568 | I21: ='AEO Table 1'!J$17/'AEO Table 1'!$C$17 -> 1.4591175 | ... AG21: ='AEO Table 1'!AH$17/'AEO Table 1'!$C$17 -> 1.5985689
A22: municipal solid waste | B22: ='AEO Table 1'!C$24/'AEO Table 1'!$C$24 -> 1 | C22: ='AEO Table 1'!D$24/'AEO Table 1'!$C$24 -> 0.54333255 | D22: ='AEO Table 1'!E$24/'AEO Table 1'!$C$24 -> 0.51899257 | E22: ='AEO Table 1'!F$24/'AEO Table 1'!$C$24 -> 0.54484085 | F22: ='AEO Table 1'!G$24/'AEO Table 1'!$C$24 -> 0.60251773 | G22: ='AEO Table 1'!H$24/'AEO Table 1'!$C$24 -> 0.62126291 | H22: ='AEO Table 1'!I$24/'AEO Table 1'!$C$24 -> 0.57490601 | I22: ='AEO Table 1'!J$24/'AEO Table 1'!$C$24 -> 0.46881277 | ... AG22: ='AEO Table 1'!AH$24/'AEO Table 1'!$C$24 -> 0.43188133
A23: hydrogen | B23: 1 | C23: 1 | D23: 1 | E23: 1 | F23: 1 | G23: 1 | H23: 1 | I23: 1 | J23: 1 | K23: 1 | L23: 1 | M23: 1 | N23: 1 | O23: 1 | P23: 1 | Q23: 1 | R23: 1 | S23: 1 | T23: 1 | U23: 1 | V23: 1 | W23: 1 | X23: 1 | Y23: 1 | Z23: 1 | AA23: 1 | AB23: 1 | AC23: 1 | AD23: 1 | AE23: 1 | AF23: 1 | AG23: 1
A26: Imports Scaling Factors
B27: =B2 -> 2019 | C27: =C2 -> 2020 | D27: =D2 -> 2021 | E27: =E2 -> 2022 | F27: =F2 -> 2023 | G27: =G2 -> 2024 | H27: =H2 -> 2025 | I27: =I2 -> 2026 | ... AG27: =AG2 -> 2050
A28: electricity (not used in this variable) | B28: 0 | C28: 0 | D28: 0 | E28: 0 | F28: 0 | G28: 0 | H28: 0 | I28: 0 | J28: 0 | K28: 0 | L28: 0 | M28: 0 | N28: 0 | O28: 0 | P28: 0 | Q28: 0 | R28: 0 | S28: 0 | T28: 0 | U28: 0 | V28: 0 | W28: 0 | X28: 0 | Y28: 0 | Z28: 0 | AA28: 0 | AB28: 0 | AC28: 0 | AD28: 0 | AE28: 0 | AF28: 0 | AG28: 0
A29: hard coal | B29: ='AEO Table 1'!C$31/'AEO Table 1'!$C$31 -> 1 | C29: ='AEO Table 1'!D$31/'AEO Table 1'!$C$31 -> 1.0681351 | D29: ='AEO Table 1'!E$31/'AEO Table 1'!$C$31 -> 0.68070316 | E29: ='AEO Table 1'!F$31/'AEO Table 1'!$C$31 -> 0.64787018 | F29: ='AEO Table 1'!G$31/'AEO Table 1'!$C$31 -> 0.63416633 | G29: ='AEO Table 1'!H$31/'AEO Table 1'!$C$31 -> 0.64553476 | H29: ='AEO Table 1'!I$31/'AEO Table 1'!$C$31 -> 0.6089123 | I29: ='AEO Table 1'!J$31/'AEO Table 1'!$C$31 -> 0.62776023 | ... AG29: ='AEO Table 1'!AH$31/'AEO Table 1'!$C$31 -> 0.65656368
A30: natural gas | B30: ='AEO Table 1'!C$30/'AEO Table 1'!$C$30 -> 1 | C30: ='AEO Table 1'!D$30/'AEO Table 1'!$C$30 -> 0.97516006 | D30: ='AEO Table 1'!E$30/'AEO Table 1'!$C$30 -> 0.85914793 | E30: ='AEO Table 1'!F$30/'AEO Table 1'!$C$30 -> 0.82794663 | F30: ='AEO Table 1'!G$30/'AEO Table 1'!$C$30 -> 0.79018584 | G30: ='AEO Table 1'!H$30/'AEO Table 1'!$C$30 -> 0.77785258 | H30: ='AEO Table 1'!I$30/'AEO Table 1'!$C$30 -> 0.80652295 | I30: ='AEO Table 1'!J$30/'AEO Table 1'!$C$30 -> 0.83995672 | ... AG30: ='AEO Table 1'!AH$30/'AEO Table 1'!$C$30 -> 0.39633581
A31: uranium | B31: 1 | C31: 1 | D31: 1 | E31: 1 | F31: 1 | G31: 1 | H31: 1 | I31: 1 | J31: 1 | K31: 1 | L31: 1 | M31: 1 | N31: 1 | O31: 1 | P31: 1 | Q31: 1 | R31: 1 | S31: 1 | T31: 1 | U31: 1 | V31: 1 | W31: 1 | X31: 1 | Y31: 1 | Z31: 1 | AA31: 1 | AB31: 1 | AC31: 1 | AD31: 1 | AE31: 1 | AF31: 1 | AG31: 1
A32: hydro (is not a fuel) | B32: 0 | C32: 0 | D32: 0 | E32: 0 | F32: 0 | G32: 0 | H32: 0 | I32: 0 | J32: 0 | K32: 0 | L32: 0 | M32: 0 | N32: 0 | O32: 0 | P32: 0 | Q32: 0 | R32: 0 | S32: 0 | T32: 0 | U32: 0 | V32: 0 | W32: 0 | X32: 0 | Y32: 0 | Z32: 0 | AA32: 0 | AB32: 0 | AC32: 0 | AD32: 0 | AE32: 0 | AF32: 0 | AG32: 0
A33: wind (is not a fuel) | B33: 0 | C33: 0 | D33: 0 | E33: 0 | F33: 0 | G33: 0 | H33: 0 | I33: 0 | J33: 0 | K33: 0 | L33: 0 | M33: 0 | N33: 0 | O33: 0 | P33: 0 | Q33: 0 | R33: 0 | S33: 0 | T33: 0 | U33: 0 | V33: 0 | W33: 0 | X33: 0 | Y33: 0 | Z33: 0 | AA33: 0 | AB33: 0 | AC33: 0 | AD33: 0 | AE33: 0 | AF33: 0 | AG33: 0
A34: solar (is not a fuel) | B34: 0 | C34: 0 | D34: 0 | E34: 0 | F34: 0 | G34: 0 | H34: 0 | I34: 0 | J34: 0 | K34: 0 | L34: 0 | M34: 0 | N34: 0 | O34: 0 | P34: 0 | Q34: 0 | R34: 0 | S34: 0 | T34: 0 | U34: 0 | V34: 0 | W34: 0 | X34: 0 | Y34: 0 | Z34: 0 | AA34: 0 | AB34: 0 | AC34: 0 | AD34: 0 | AE34: 0 | AF34: 0 | AG34: 0
A35: biomass | B35: 1 | C35: 1 | D35: 1 | E35: 1 | F35: 1 | G35: 1 | H35: 1 | I35: 1 | J35: 1 | K35: 1 | L35: 1 | M35: 1 | N35: 1 | O35: 1 | P35: 1 | Q35: 1 | R35: 1 | S35: 1 | T35: 1 | U35: 1 | V35: 1 | W35: 1 | X35: 1 | Y35: 1 | Z35: 1 | AA35: 1 | AB35: 1 | AC35: 1 | AD35: 1 | AE35: 1 | AF35: 1 | AG35: 1
A36: petroleum gasoline | B36: ='AEO Table 1'!C$29/'AEO Table 1'!$C$29 -> 1 | C36: ='AEO Table 1'!D$29/'AEO Table 1'!$C$29 -> 0.87211471 | D36: ='AEO Table 1'!E$29/'AEO Table 1'!$C$29 -> 0.8829772 | E36: ='AEO Table 1'!F$29/'AEO Table 1'!$C$29 -> 0.90152288 | F36: ='AEO Table 1'!G$29/'AEO Table 1'!$C$29 -> 0.89442841 | G36: ='AEO Table 1'!H$29/'AEO Table 1'!$C$29 -> 0.87252558 | H36: ='AEO Table 1'!I$29/'AEO Table 1'!$C$29 -> 0.84070071 | I36: ='AEO Table 1'!J$29/'AEO Table 1'!$C$29 -> 0.77523668 | ... AG36: ='AEO Table 1'!AH$29/'AEO Table 1'!$C$29 -> 0.7663796
A37: petroleum diesel | B37: ='AEO Table 1'!C$29/'AEO Table 1'!$C$29 -> 1 | C37: ='AEO Table 1'!D$29/'AEO Table 1'!$C$29 -> 0.87211471 | D37: ='AEO Table 1'!E$29/'AEO Table 1'!$C$29 -> 0.8829772 | E37: ='AEO Table 1'!F$29/'AEO Table 1'!$C$29 -> 0.90152288 | F37: ='AEO Table 1'!G$29/'AEO Table 1'!$C$29 -> 0.89442841 | G37: ='AEO Table 1'!H$29/'AEO Table 1'!$C$29 -> 0.87252558 | H37: ='AEO Table 1'!I$29/'AEO Table 1'!$C$29 -> 0.84070071 | I37: ='AEO Table 1'!J$29/'AEO Table 1'!$C$29 -> 0.77523668 | ... AG37: ='AEO Table 1'!AH$29/'AEO Table 1'!$C$29 -> 0.7663796
A38: biofuel gasoline | B38: ='AEO Table 1'!C$29/'AEO Table 1'!$C$29 -> 1 | C38: ='AEO Table 1'!D$29/'AEO Table 1'!$C$29 -> 0.87211471 | D38: ='AEO Table 1'!E$29/'AEO Table 1'!$C$29 -> 0.8829772 | E38: ='AEO Table 1'!F$29/'AEO Table 1'!$C$29 -> 0.90152288 | F38: ='AEO Table 1'!G$29/'AEO Table 1'!$C$29 -> 0.89442841 | G38: ='AEO Table 1'!H$29/'AEO Table 1'!$C$29 -> 0.87252558 | H38: ='AEO Table 1'!I$29/'AEO Table 1'!$C$29 -> 0.84070071 | I38: ='AEO Table 1'!J$29/'AEO Table 1'!$C$29 -> 0.77523668 | ... AG38: ='AEO Table 1'!AH$29/'AEO Table 1'!$C$29 -> 0.7663796
A39: biofuel diesel | B39: ='AEO Table 1'!C$29/'AEO Table 1'!$C$29 -> 1 | C39: ='AEO Table 1'!D$29/'AEO Table 1'!$C$29 -> 0.87211471 | D39: ='AEO Table 1'!E$29/'AEO Table 1'!$C$29 -> 0.8829772 | E39: ='AEO Table 1'!F$29/'AEO Table 1'!$C$29 -> 0.90152288 | F39: ='AEO Table 1'!G$29/'AEO Table 1'!$C$29 -> 0.89442841 | G39: ='AEO Table 1'!H$29/'AEO Table 1'!$C$29 -> 0.87252558 | H39: ='AEO Table 1'!I$29/'AEO Table 1'!$C$29 -> 0.84070071 | I39: ='AEO Table 1'!J$29/'AEO Table 1'!$C$29 -> 0.77523668 | ... AG39: ='AEO Table 1'!AH$29/'AEO Table 1'!$C$29 -> 0.7663796
A40: jet fuel or kerosene | B40: ='AEO Table 1'!C$29/'AEO Table 1'!$C$29 -> 1 | C40: ='AEO Table 1'!D$29/'AEO Table 1'!$C$29 -> 0.87211471 | D40: ='AEO Table 1'!E$29/'AEO Table 1'!$C$29 -> 0.8829772 | E40: ='AEO Table 1'!F$29/'AEO Table 1'!$C$29 -> 0.90152288 | F40: ='AEO Table 1'!G$29/'AEO Table 1'!$C$29 -> 0.89442841 | G40: ='AEO Table 1'!H$29/'AEO Table 1'!$C$29 -> 0.87252558 | H40: ='AEO Table 1'!I$29/'AEO Table 1'!$C$29 -> 0.84070071 | I40: ='AEO Table 1'!J$29/'AEO Table 1'!$C$29 -> 0.77523668 | ... AG40: ='AEO Table 1'!AH$29/'AEO Table 1'!$C$29 -> 0.7663796
A41: heat (not used in this variable) | B41: 0 | C41: 0 | D41: 0 | E41: 0 | F41: 0 | G41: 0 | H41: 0 | I41: 0 | J41: 0 | K41: 0 | L41: 0 | M41: 0 | N41: 0 | O41: 0 | P41: 0 | Q41: 0 | R41: 0 | S41: 0 | T41: 0 | U41: 0 | V41: 0 | W41: 0 | X41: 0 | Y41: 0 | Z41: 0 | AA41: 0 | AB41: 0 | AC41: 0 | AD41: 0 | AE41: 0 | AF41: 0 | AG41: 0
A42: geothermal (is not a fuel) | B42: 0 | C42: 0 | D42: 0 | E42: 0 | F42: 0 | G42: 0 | H42: 0 | I42: 0 | J42: 0 | K42: 0 | L42: 0 | M42: 0 | N42: 0 | O42: 0 | P42: 0 | Q42: 0 | R42: 0 | S42: 0 | T42: 0 | U42: 0 | V42: 0 | W42: 0 | X42: 0 | Y42: 0 | Z42: 0 | AA42: 0 | AB42: 0 | AC42: 0 | AD42: 0 | AE42: 0 | AF42: 0 | AG42: 0
A43: lignite | B43: ='AEO Table 1'!C$31/'AEO Table 1'!$C$31 -> 1 | C43: ='AEO Table 1'!D$31/'AEO Table 1'!$C$31 -> 1.0681351 | D43: ='AEO Table 1'!E$31/'AEO Table 1'!$C$31 -> 0.68070316 | E43: ='AEO Table 1'!F$31/'AEO Table 1'!$C$31 -> 0.64787018 | F43: ='AEO Table 1'!G$31/'AEO Table 1'!$C$31 -> 0.63416633 | G43: ='AEO Table 1'!H$31/'AEO Table 1'!$C$31 -> 0.64553476 | H43: ='AEO Table 1'!I$31/'AEO Table 1'!$C$31 -> 0.6089123 | I43: ='AEO Table 1'!J$31/'AEO Table 1'!$C$31 -> 0.62776023 | ... AG43: ='AEO Table 1'!AH$31/'AEO Table 1'!$C$31 -> 0.65656368
A44: crude oil | B44: ='AEO Table 1'!C$28/'AEO Table 1'!$C$28 -> 1 | C44: ='AEO Table 1'!D$28/'AEO Table 1'!$C$28 -> 0.93403338 | D44: ='AEO Table 1'!E$28/'AEO Table 1'!$C$28 -> 0.69674011 | E44: ='AEO Table 1'!F$28/'AEO Table 1'!$C$28 -> 0.59667675 | F44: ='AEO Table 1'!G$28/'AEO Table 1'!$C$28 -> 0.62418931 | G44: ='AEO Table 1'!H$28/'AEO Table 1'!$C$28 -> 0.60396835 | H44: ='AEO Table 1'!I$28/'AEO Table 1'!$C$28 -> 0.53840943 | I44: ='AEO Table 1'!J$28/'AEO Table 1'!$C$28 -> 0.56431194 | ... AG44: ='AEO Table 1'!AH$28/'AEO Table 1'!$C$28 -> 0.37719731
A45: heavy fuel oil | B45: ='AEO Table 1'!C$29/'AEO Table 1'!$C$29 -> 1 | C45: ='AEO Table 1'!D$29/'AEO Table 1'!$C$29 -> 0.87211471 | D45: ='AEO Table 1'!E$29/'AEO Table 1'!$C$29 -> 0.8829772 | E45: ='AEO Table 1'!F$29/'AEO Table 1'!$C$29 -> 0.90152288 | F45: ='AEO Table 1'!G$29/'AEO Table 1'!$C$29 -> 0.89442841 | G45: ='AEO Table 1'!H$29/'AEO Table 1'!$C$29 -> 0.87252558 | H45: ='AEO Table 1'!I$29/'AEO Table 1'!$C$29 -> 0.84070071 | I45: ='AEO Table 1'!J$29/'AEO Table 1'!$C$29 -> 0.77523668 | ... AG45: ='AEO Table 1'!AH$29/'AEO Table 1'!$C$29 -> 0.7663796
A46: LPG propane or butane | B46: ='AEO Table 1'!C$29/'AEO Table 1'!$C$29 -> 1 | C46: ='AEO Table 1'!D$29/'AEO Table 1'!$C$29 -> 0.87211471 | D46: ='AEO Table 1'!E$29/'AEO Table 1'!$C$29 -> 0.8829772 | E46: ='AEO Table 1'!F$29/'AEO Table 1'!$C$29 -> 0.90152288 | F46: ='AEO Table 1'!G$29/'AEO Table 1'!$C$29 -> 0.89442841 | G46: ='AEO Table 1'!H$29/'AEO Table 1'!$C$29 -> 0.87252558 | H46: ='AEO Table 1'!I$29/'AEO Table 1'!$C$29 -> 0.84070071 | I46: ='AEO Table 1'!J$29/'AEO Table 1'!$C$29 -> 0.77523668 | ... AG46: ='AEO Table 1'!AH$29/'AEO Table 1'!$C$29 -> 0.7663796
A47: municipal solid waste | B47: 1 | C47: 1 | D47: 1 | E47: 1 | F47: 1 | G47: 1 | H47: 1 | I47: 1 | J47: 1 | K47: 1 | L47: 1 | M47: 1 | N47: 1 | O47: 1 | P47: 1 | Q47: 1 | R47: 1 | S47: 1 | T47: 1 | U47: 1 | V47: 1 | W47: 1 | X47: 1 | Y47: 1 | Z47: 1 | AA47: 1 | AB47: 1 | AC47: 1 | AD47: 1 | AE47: 1 | AF47: 1 | AG47: 1
A48: hydrogen | B48: 1 | C48: 1 | D48: 1 | E48: 1 | F48: 1 | G48: 1 | H48: 1 | I48: 1 | J48: 1 | K48: 1 | L48: 1 | M48: 1 | N48: 1 | O48: 1 | P48: 1 | Q48: 1 | R48: 1 | S48: 1 | T48: 1 | U48: 1 | V48: 1 | W48: 1 | X48: 1 | Y48: 1 | Z48: 1 | AA48: 1 | AB48: 1 | AC48: 1 | AD48: 1 | AE48: 1 | AF48: 1 | AG48: 1
A51: Exports Scaling Factors
B52: =B2 -> 2019 | C52: =C2 -> 2020 | D52: =D2 -> 2021 | E52: =E2 -> 2022 | F52: =F2 -> 2023 | G52: =G2 -> 2024 | H52: =H2 -> 2025 | I52: =I2 -> 2026 | ... AG52: =AG2 -> 2050
A53: electricity (not used in this variable) | B53: 0 | C53: 0 | D53: 0 | E53: 0 | F53: 0 | G53: 0 | H53: 0 | I53: 0 | J53: 0 | K53: 0 | L53: 0 | M53: 0 | N53: 0 | O53: 0 | P53: 0 | Q53: 0 | R53: 0 | S53: 0 | T53: 0 | U53: 0 | V53: 0 | W53: 0 | X53: 0 | Y53: 0 | Z53: 0 | AA53: 0 | AB53: 0 | AC53: 0 | AD53: 0 | AE53: 0 | AF53: 0 | AG53: 0
A54: hard coal | B54: ='AEO Table 1'!C$37/'AEO Table 1'!$C$37 -> 1 | C54: ='AEO Table 1'!D$37/'AEO Table 1'!$C$37 -> 0.87524975 | D54: ='AEO Table 1'!E$37/'AEO Table 1'!$C$37 -> 0.93042105 | E54: ='AEO Table 1'!F$37/'AEO Table 1'!$C$37 -> 1.1460409 | F54: ='AEO Table 1'!G$37/'AEO Table 1'!$C$37 -> 1.1527064 | G54: ='AEO Table 1'!H$37/'AEO Table 1'!$C$37 -> 1.1596246 | H54: ='AEO Table 1'!I$37/'AEO Table 1'!$C$37 -> 1.1673803 | I54: ='AEO Table 1'!J$37/'AEO Table 1'!$C$37 -> 1.173704 | ... AG54: ='AEO Table 1'!AH$37/'AEO Table 1'!$C$37 -> 1.1344024
A55: natural gas | B55: ='AEO Table 1'!C$36/'AEO Table 1'!$C$36 -> 1 | C55: ='AEO Table 1'!D$36/'AEO Table 1'!$C$36 -> 1.2023295 | D55: ='AEO Table 1'!E$36/'AEO Table 1'!$C$36 -> 1.4041457 | E55: ='AEO Table 1'!F$36/'AEO Table 1'!$C$36 -> 1.4852939 | F55: ='AEO Table 1'!G$36/'AEO Table 1'!$C$36 -> 1.5312269 | G55: ='AEO Table 1'!H$36/'AEO Table 1'!$C$36 -> 1.6457442 | H55: ='AEO Table 1'!I$36/'AEO Table 1'!$C$36 -> 1.857789 | I55: ='AEO Table 1'!J$36/'AEO Table 1'!$C$36 -> 2.0525337 | ... AG55: ='AEO Table 1'!AH$36/'AEO Table 1'!$C$36 -> 2.6863801
A56: uranium | B56: 1 | C56: 1 | D56: 1 | E56: 1 | F56: 1 | G56: 1 | H56: 1 | I56: 1 | J56: 1 | K56: 1 | L56: 1 | M56: 1 | N56: 1 | O56: 1 | P56: 1 | Q56: 1 | R56: 1 | S56: 1 | T56: 1 | U56: 1 | V56: 1 | W56: 1 | X56: 1 | Y56: 1 | Z56: 1 | AA56: 1 | AB56: 1 | AC56: 1 | AD56: 1 | AE56: 1 | AF56: 1 | AG56: 1
A57: hydro (is not a fuel) | B57: 0 | C57: 0 | D57: 0 | E57: 0 | F57: 0 | G57: 0 | H57: 0 | I57: 0 | J57: 0 | K57: 0 | L57: 0 | M57: 0 | N57: 0 | O57: 0 | P57: 0 | Q57: 0 | R57: 0 | S57: 0 | T57: 0 | U57: 0 | V57: 0 | W57: 0 | X57: 0 | Y57: 0 | Z57: 0 | AA57: 0 | AB57: 0 | AC57: 0 | AD57: 0 | AE57: 0 | AF57: 0 | AG57: 0
A58: wind (is not a fuel) | B58: 0 | C58: 0 | D58: 0 | E58: 0 | F58: 0 | G58: 0 | H58: 0 | I58: 0 | J58: 0 | K58: 0 | L58: 0 | M58: 0 | N58: 0 | O58: 0 | P58: 0 | Q58: 0 | R58: 0 | S58: 0 | T58: 0 | U58: 0 | V58: 0 | W58: 0 | X58: 0 | Y58: 0 | Z58: 0 | AA58: 0 | AB58: 0 | AC58: 0 | AD58: 0 | AE58: 0 | AF58: 0 | AG58: 0
A59: solar (is not a fuel) | B59: 0 | C59: 0 | D59: 0 | E59: 0 | F59: 0 | G59: 0 | H59: 0 | I59: 0 | J59: 0 | K59: 0 | L59: 0 | M59: 0 | N59: 0 | O59: 0 | P59: 0 | Q59: 0 | R59: 0 | S59: 0 | T59: 0 | U59: 0 | V59: 0 | W59: 0 | X59: 0 | Y59: 0 | Z59: 0 | AA59: 0 | AB59: 0 | AC59: 0 | AD59: 0 | AE59: 0 | AF59: 0 | AG59: 0
A60: biomass | B60: 1 | C60: 1 | D60: 1 | E60: 1 | F60: 1 | G60: 1 | H60: 1 | I60: 1 | J60: 1 | K60: 1 | L60: 1 | M60: 1 | N60: 1 | O60: 1 | P60: 1 | Q60: 1 | R60: 1 | S60: 1 | T60: 1 | U60: 1 | V60: 1 | W60: 1 | X60: 1 | Y60: 1 | Z60: 1 | AA60: 1 | AB60: 1 | AC60: 1 | AD60: 1 | AE60: 1 | AF60: 1 | AG60: 1
A61: petroleum gasoline | B61: ='AEO Table 1'!C$35/'AEO Table 1'!$C$35 -> 1 | C61: ='AEO Table 1'!D$35/'AEO Table 1'!$C$35 -> 1.1783687 | D61: ='AEO Table 1'!E$35/'AEO Table 1'!$C$35 -> 1.1864833 | E61: ='AEO Table 1'!F$35/'AEO Table 1'!$C$35 -> 1.2687304 | F61: ='AEO Table 1'!G$35/'AEO Table 1'!$C$35 -> 1.3579924 | G61: ='AEO Table 1'!H$35/'AEO Table 1'!$C$35 -> 1.4116898 | H61: ='AEO Table 1'!I$35/'AEO Table 1'!$C$35 -> 1.390329 | I61: ='AEO Table 1'!J$35/'AEO Table 1'!$C$35 -> 1.4427264 | ... AG61: ='AEO Table 1'!AH$35/'AEO Table 1'!$C$35 -> 1.4092271
A62: petroleum diesel | B62: ='AEO Table 1'!C$35/'AEO Table 1'!$C$35 -> 1 | C62: ='AEO Table 1'!D$35/'AEO Table 1'!$C$35 -> 1.1783687 | D62: ='AEO Table 1'!E$35/'AEO Table 1'!$C$35 -> 1.1864833 | E62: ='AEO Table 1'!F$35/'AEO Table 1'!$C$35 -> 1.2687304 | F62: ='AEO Table 1'!G$35/'AEO Table 1'!$C$35 -> 1.3579924 | G62: ='AEO Table 1'!H$35/'AEO Table 1'!$C$35 -> 1.4116898 | H62: ='AEO Table 1'!I$35/'AEO Table 1'!$C$35 -> 1.390329 | I62: ='AEO Table 1'!J$35/'AEO Table 1'!$C$35 -> 1.4427264 | ... AG62: ='AEO Table 1'!AH$35/'AEO Table 1'!$C$35 -> 1.4092271
A63: biofuel gasoline | B63: ='AEO Table 1'!C$35/'AEO Table 1'!$C$35 -> 1 | C63: ='AEO Table 1'!D$35/'AEO Table 1'!$C$35 -> 1.1783687 | D63: ='AEO Table 1'!E$35/'AEO Table 1'!$C$35 -> 1.1864833 | E63: ='AEO Table 1'!F$35/'AEO Table 1'!$C$35 -> 1.2687304 | F63: ='AEO Table 1'!G$35/'AEO Table 1'!$C$35 -> 1.3579924 | G63: ='AEO Table 1'!H$35/'AEO Table 1'!$C$35 -> 1.4116898 | H63: ='AEO Table 1'!I$35/'AEO Table 1'!$C$35 -> 1.390329 | I63: ='AEO Table 1'!J$35/'AEO Table 1'!$C$35 -> 1.4427264 | ... AG63: ='AEO Table 1'!AH$35/'AEO Table 1'!$C$35 -> 1.4092271
A64: biofuel diesel | B64: ='AEO Table 1'!C$35/'AEO Table 1'!$C$35 -> 1 | C64: ='AEO Table 1'!D$35/'AEO Table 1'!$C$35 -> 1.1783687 | D64: ='AEO Table 1'!E$35/'AEO Table 1'!$C$35 -> 1.1864833 | E64: ='AEO Table 1'!F$35/'AEO Table 1'!$C$35 -> 1.2687304 | F64: ='AEO Table 1'!G$35/'AEO Table 1'!$C$35 -> 1.3579924 | G64: ='AEO Table 1'!H$35/'AEO Table 1'!$C$35 -> 1.4116898 | H64: ='AEO Table 1'!I$35/'AEO Table 1'!$C$35 -> 1.390329 | I64: ='AEO Table 1'!J$35/'AEO Table 1'!$C$35 -> 1.4427264 | ... AG64: ='AEO Table 1'!AH$35/'AEO Table 1'!$C$35 -> 1.4092271
A65: jet fuel or kerosene | B65: ='AEO Table 1'!C$35/'AEO Table 1'!$C$35 -> 1 | C65: ='AEO Table 1'!D$35/'AEO Table 1'!$C$35 -> 1.1783687 | D65: ='AEO Table 1'!E$35/'AEO Table 1'!$C$35 -> 1.1864833 | E65: ='AEO Table 1'!F$35/'AEO Table 1'!$C$35 -> 1.2687304 | F65: ='AEO Table 1'!G$35/'AEO Table 1'!$C$35 -> 1.3579924 | G65: ='AEO Table 1'!H$35/'AEO Table 1'!$C$35 -> 1.4116898 | H65: ='AEO Table 1'!I$35/'AEO Table 1'!$C$35 -> 1.390329 | I65: ='AEO Table 1'!J$35/'AEO Table 1'!$C$35 -> 1.4427264 | ... AG65: ='AEO Table 1'!AH$35/'AEO Table 1'!$C$35 -> 1.4092271
A66: heat (not used in this variable) | B66: 0 | C66: 0 | D66: 0 | E66: 0 | F66: 0 | G66: 0 | H66: 0 | I66: 0 | J66: 0 | K66: 0 | L66: 0 | M66: 0 | N66: 0 | O66: 0 | P66: 0 | Q66: 0 | R66: 0 | S66: 0 | T66: 0 | U66: 0 | V66: 0 | W66: 0 | X66: 0 | Y66: 0 | Z66: 0 | AA66: 0 | AB66: 0 | AC66: 0 | AD66: 0 | AE66: 0 | AF66: 0 | AG66: 0
A67: geothermal (is not a fuel) | B67: 0 | C67: 0 | D67: 0 | E67: 0 | F67: 0 | G67: 0 | H67: 0 | I67: 0 | J67: 0 | K67: 0 | L67: 0 | M67: 0 | N67: 0 | O67: 0 | P67: 0 | Q67: 0 | R67: 0 | S67: 0 | T67: 0 | U67: 0 | V67: 0 | W67: 0 | X67: 0 | Y67: 0 | Z67: 0 | AA67: 0 | AB67: 0 | AC67: 0 | AD67: 0 | AE67: 0 | AF67: 0 | AG67: 0
A68: lignite | B68: ='AEO Table 1'!C$37/'AEO Table 1'!$C$37 -> 1 | C68: ='AEO Table 1'!D$37/'AEO Table 1'!$C$37 -> 0.87524975 | D68: ='AEO Table 1'!E$37/'AEO Table 1'!$C$37 -> 0.93042105 | E68: ='AEO Table 1'!F$37/'AEO Table 1'!$C$37 -> 1.1460409 | F68: ='AEO Table 1'!G$37/'AEO Table 1'!$C$37 -> 1.1527064 | G68: ='AEO Table 1'!H$37/'AEO Table 1'!$C$37 -> 1.1596246 | H68: ='AEO Table 1'!I$37/'AEO Table 1'!$C$37 -> 1.1673803 | I68: ='AEO Table 1'!J$37/'AEO Table 1'!$C$37 -> 1.173704 | ... AG68: ='AEO Table 1'!AH$37/'AEO Table 1'!$C$37 -> 1.1344024
A69: crude oil | B69: ='AEO Table 1'!C$35/'AEO Table 1'!$C$35 -> 1 | C69: ='AEO Table 1'!D$35/'AEO Table 1'!$C$35 -> 1.1783687 | D69: ='AEO Table 1'!E$35/'AEO Table 1'!$C$35 -> 1.1864833 | E69: ='AEO Table 1'!F$35/'AEO Table 1'!$C$35 -> 1.2687304 | F69: ='AEO Table 1'!G$35/'AEO Table 1'!$C$35 -> 1.3579924 | G69: ='AEO Table 1'!H$35/'AEO Table 1'!$C$35 -> 1.4116898 | H69: ='AEO Table 1'!I$35/'AEO Table 1'!$C$35 -> 1.390329 | I69: ='AEO Table 1'!J$35/'AEO Table 1'!$C$35 -> 1.4427264 | ... AG69: ='AEO Table 1'!AH$35/'AEO Table 1'!$C$35 -> 1.4092271
A70: heavy fuel oil | B70: ='AEO Table 1'!C$35/'AEO Table 1'!$C$35 -> 1 | C70: ='AEO Table 1'!D$35/'AEO Table 1'!$C$35 -> 1.1783687 | D70: ='AEO Table 1'!E$35/'AEO Table 1'!$C$35 -> 1.1864833 | E70: ='AEO Table 1'!F$35/'AEO Table 1'!$C$35 -> 1.2687304 | F70: ='AEO Table 1'!G$35/'AEO Table 1'!$C$35 -> 1.3579924 | G70: ='AEO Table 1'!H$35/'AEO Table 1'!$C$35 -> 1.4116898 | H70: ='AEO Table 1'!I$35/'AEO Table 1'!$C$35 -> 1.390329 | I70: ='AEO Table 1'!J$35/'AEO Table 1'!$C$35 -> 1.4427264 | ... AG70: ='AEO Table 1'!AH$35/'AEO Table 1'!$C$35 -> 1.4092271
A71: LPG propane or butane | B71: ='AEO Table 1'!C$35/'AEO Table 1'!$C$35 -> 1 | C71: ='AEO Table 1'!D$35/'AEO Table 1'!$C$35 -> 1.1783687 | D71: ='AEO Table 1'!E$35/'AEO Table 1'!$C$35 -> 1.1864833 | E71: ='AEO Table 1'!F$35/'AEO Table 1'!$C$35 -> 1.2687304 | F71: ='AEO Table 1'!G$35/'AEO Table 1'!$C$35 -> 1.3579924 | G71: ='AEO Table 1'!H$35/'AEO Table 1'!$C$35 -> 1.4116898 | H71: ='AEO Table 1'!I$35/'AEO Table 1'!$C$35 -> 1.390329 | I71: ='AEO Table 1'!J$35/'AEO Table 1'!$C$35 -> 1.4427264 | ... AG71: ='AEO Table 1'!AH$35/'AEO Table 1'!$C$35 -> 1.4092271
A72: municipal solid waste | B72: 1 | C72: 1 | D72: 1 | E72: 1 | F72: 1 | G72: 1 | H72: 1 | I72: 1 | J72: 1 | K72: 1 | L72: 1 | M72: 1 | N72: 1 | O72: 1 | P72: 1 | Q72: 1 | R72: 1 | S72: 1 | T72: 1 | U72: 1 | V72: 1 | W72: 1 | X72: 1 | Y72: 1 | Z72: 1 | AA72: 1 | AB72: 1 | AC72: 1 | AD72: 1 | AE72: 1 | AF72: 1 | AG72: 1
A73: hydrogen | B73: 1 | C73: 1 | D73: 1 | E73: 1 | F73: 1 | G73: 1 | H73: 1 | I73: 1 | J73: 1 | K73: 1 | L73: 1 | M73: 1 | N73: 1 | O73: 1 | P73: 1 | Q73: 1 | R73: 1 | S73: 1 | T73: 1 | U73: 1 | V73: 1 | W73: 1 | X73: 1 | Y73: 1 | Z73: 1 | AA73: 1 | AB73: 1 | AC73: 1 | AD73: 1 | AE73: 1 | AF73: 1 | AG73: 1

Sheet BFPIaE-production
A1: Fuel (BTU) | B1: 2019 | C1: 2020 | D1: 2021 | E1: 2022 | F1: 2023 | G1: 2024 | H1: 2025 | I1: 2026 | J1: 2027 | K1: 2028 | L1: 2029 | M1: 2030 | N1: 2031 | O1: 2032 | P1: 2033 | Q1: 2034 | R1: 2035 | S1: 2036 | T1: 2037 | U1: 2038 | V1: 2039 | W1: 2040 | X1: 2041 | Y1: 2042 | Z1: 2043 | AA1: 2044 | AB1: 2045 | AC1: 2046 | AD1: 2047 | AE1: 2048 | AF1: 2049 | AG1: 2050 | AH1: 2051 | AI1: 2052 | AJ1: 2053 | AK1: 2054 | AL1: 2055 | AM1: 2056 | AN1: 2057 | AO1: 2058 | AP1: 2059 | AQ1: 2060 | AR1: 2061 | AS1: 2062 | AT1: 2063 | AU1: 2064 | AV1: 2065 | AW1: 2066 | AX1: 2067 | AY1: 2068 | AZ1: 2069 | BA1: 2070
A2: electricity (not used in this variable) | B2: ='Start Year Data'!B26 -> 0 | C2: =$B2*'Time Series Scaling Factors'!C3 -> 0 | D2: =$B2*'Time Series Scaling Factors'!D3 -> 0 | E2: =$B2*'Time Series Scaling Factors'!E3 -> 0 | F2: =$B2*'Time Series Scaling Factors'!F3 -> 0 | G2: =$B2*'Time Series Scaling Factors'!G3 -> 0 | H2: =$B2*'Time Series Scaling Factors'!H3 -> 0 | I2: =$B2*'Time Series Scaling Factors'!I3 -> 0 | J2: =$B2*'Time Series Scaling Factors'!J3 -> 0 | ... AG2: =$B2*'Time Series Scaling Factors'!AG3 -> 0 | AH2: =AG2 -> 0 | AI2: =AH2 -> 0 | AJ2: =AI2 -> 0 | AK2: =AJ2 -> 0 | AL2: =AK2 -> 0 | AM2: =AL2 -> 0 | AN2: =AM2 -> 0 | AO2: =AN2 -> 0 | ... BA2: =AZ2 -> 0
A3: hard coal | B3: ='Start Year Data'!B27 -> 281759490896640 | C3: =$B3*'Time Series Scaling Factors'!C4 -> 2.5587148e+14 | D3: =$B3*'Time Series Scaling Factors'!D4 -> 2.4077849e+14 | E3: =$B3*'Time Series Scaling Factors'!E4 -> 2.3665514e+14 | F3: =$B3*'Time Series Scaling Factors'!F4 -> 2.2394334e+14 | G3: =$B3*'Time Series Scaling Factors'!G4 -> 2.1728736e+14 | H3: =$B3*'Time Series Scaling Factors'!H4 -> 1.9575582e+14 | I3: =$B3*'Time Series Scaling Factors'!I4 -> 1.9955534e+14 | J3: =$B3*'Time Series Scaling Factors'!J4 -> 1.9860413e+14 | ... AG3: =$B3*'Time Series Scaling Factors'!AG4 -> 1.7508019e+14 | AH3: =AG3 -> 1.7508019e+14 | AI3: =AH3 -> 1.7508019e+14 | AJ3: =AI3 -> 1.7508019e+14 | AK3: =AJ3 -> 1.7508019e+14 | AL3: =AK3 -> 1.7508019e+14 | AM3: =AL3 -> 1.7508019e+14 | AN3: =AM3 -> 1.7508019e+14 | AO3: =AN3 -> 1.7508019e+14 | ... BA3: =AZ3 -> 1.7508019e+14
A4: natural gas | B4: ='Start Year Data'!B28 -> 1.389534e+15 | C4: =$B4*'Time Series Scaling Factors'!C5 -> 1.4192235e+15 | D4: =$B4*'Time Series Scaling Factors'!D5 -> 1.4946463e+15 | E4: =$B4*'Time Series Scaling Factors'!E5 -> 1.5205242e+15 | F4: =$B4*'Time Series Scaling Factors'!F5 -> 1.5390764e+15 | G4: =$B4*'Time Series Scaling Factors'!G5 -> 1.564227e+15 | H4: =$B4*'Time Series Scaling Factors'!H5 -> 1.6190287e+15 | I4: =$B4*'Time Series Scaling Factors'!I5 -> 1.673404e+15 | J4: =$B4*'Time Series Scaling Factors'!J5 -> 1.7063074e+15 | ... AG4: =$B4*'Time Series Scaling Factors'!AG5 -> 2.1931793e+15 | AH4: =AG4 -> 2.1931793e+15 | AI4: =AH4 -> 2.1931793e+15 | AJ4: =AI4 -> 2.1931793e+15 | AK4: =AJ4 -> 2.1931793e+15 | AL4: =AK4 -> 2.1931793e+15 | AM4: =AL4 -> 2.1931793e+15 | AN4: =AM4 -> 2.1931793e+15 | AO4: =AN4 -> 2.1931793e+15 | ... BA4: =AZ4 -> 2.1931793e+15
A5: nuclear | B5: ='Start Year Data'!B29 -> 118303689467040 | C5: =$B5*'Time Series Scaling Factors'!C6 -> 1.1618961e+14 | D5: =$B5*'Time Series Scaling Factors'!D6 -> 1.1426961e+14 | E5: =$B5*'Time Series Scaling Factors'!E6 -> 1.1213901e+14 | F5: =$B5*'Time Series Scaling Factors'!F6 -> 1.1247171e+14 | G5: =$B5*'Time Series Scaling Factors'!G6 -> 1.1290598e+14 | H5: =$B5*'Time Series Scaling Factors'!H6 -> 1.1082895e+14 | I5: =$B5*'Time Series Scaling Factors'!I6 -> 9.2163218e+13 | J5: =$B5*'Time Series Scaling Factors'!J6 -> 8.5606402e+13 | ... AG5: =$B5*'Time Series Scaling Factors'!AG6 -> 5.5112592e+13 | AH5: =AG5 -> 5.5112592e+13 | AI5: =AH5 -> 5.5112592e+13 | AJ5: =AI5 -> 5.5112592e+13 | AK5: =AJ5 -> 5.5112592e+13 | AL5: =AK5 -> 5.5112592e+13 | AM5: =AL5 -> 5.5112592e+13 | AN5: =AM5 -> 5.5112592e+13 | AO5: =AN5 -> 5.5112592e+13 | ... BA5: =AZ5 -> 5.5112592e+13
A6: hydro (is not a fuel) | B6: ='Start Year Data'!B30 -> 0 | C6: =$B6*'Time Series Scaling Factors'!C7 -> 0 | D6: =$B6*'Time Series Scaling Factors'!D7 -> 0 | E6: =$B6*'Time Series Scaling Factors'!E7 -> 0 | F6: =$B6*'Time Series Scaling Factors'!F7 -> 0 | G6: =$B6*'Time Series Scaling Factors'!G7 -> 0 | H6: =$B6*'Time Series Scaling Factors'!H7 -> 0 | I6: =$B6*'Time Series Scaling Factors'!I7 -> 0 | J6: =$B6*'Time Series Scaling Factors'!J7 -> 0 | ... AG6: =$B6*'Time Series Scaling Factors'!AG7 -> 0 | AH6: =AG6 -> 0 | AI6: =AH6 -> 0 | AJ6: =AI6 -> 0 | AK6: =AJ6 -> 0 | AL6: =AK6 -> 0 | AM6: =AL6 -> 0 | AN6: =AM6 -> 0 | AO6: =AN6 -> 0 | ... BA6: =AZ6 -> 0
A7: wind (is not a fuel) | B7: ='Start Year Data'!B31 -> 0 | C7: =$B7*'Time Series Scaling Factors'!C8 -> 0 | D7: =$B7*'Time Series Scaling Factors'!D8 -> 0 | E7: =$B7*'Time Series Scaling Factors'!E8 -> 0 | F7: =$B7*'Time Series Scaling Factors'!F8 -> 0 | G7: =$B7*'Time Series Scaling Factors'!G8 -> 0 | H7: =$B7*'Time Series Scaling Factors'!H8 -> 0 | I7: =$B7*'Time Series Scaling Factors'!I8 -> 0 | J7: =$B7*'Time Series Scaling Factors'!J8 -> 0 | ... AG7: =$B7*'Time Series Scaling Factors'!AG8 -> 0 | AH7: =AG7 -> 0 | AI7: =AH7 -> 0 | AJ7: =AI7 -> 0 | AK7: =AJ7 -> 0 | AL7: =AK7 -> 0 | AM7: =AL7 -> 0 | AN7: =AM7 -> 0 | AO7: =AN7 -> 0 | ... BA7: =AZ7 -> 0
A8: solar (is not a fuel) | B8: ='Start Year Data'!B32 -> 0 | C8: =$B8*'Time Series Scaling Factors'!C9 -> 0 | D8: =$B8*'Time Series Scaling Factors'!D9 -> 0 | E8: =$B8*'Time Series Scaling Factors'!E9 -> 0 | F8: =$B8*'Time Series Scaling Factors'!F9 -> 0 | G8: =$B8*'Time Series Scaling Factors'!G9 -> 0 | H8: =$B8*'Time Series Scaling Factors'!H9 -> 0 | I8: =$B8*'Time Series Scaling Factors'!I9 -> 0 | J8: =$B8*'Time Series Scaling Factors'!J9 -> 0 | ... AG8: =$B8*'Time Series Scaling Factors'!AG9 -> 0 | AH8: =AG8 -> 0 | AI8: =AH8 -> 0 | AJ8: =AI8 -> 0 | AK8: =AJ8 -> 0 | AL8: =AK8 -> 0 | AM8: =AL8 -> 0 | AN8: =AM8 -> 0 | AO8: =AN8 -> 0 | ... BA8: =AZ8 -> 0
A9: biomass | B9: ='Start Year Data'!B33 -> 342321213596160 | C9: =$B9*'Time Series Scaling Factors'!C10 -> 3.3818279e+14 | D9: =$B9*'Time Series Scaling Factors'!D10 -> 3.4242408e+14 | E9: =$B9*'Time Series Scaling Factors'!E10 -> 3.4700669e+14 | F9: =$B9*'Time Series Scaling Factors'!F10 -> 3.4895746e+14 | G9: =$B9*'Time Series Scaling Factors'!G10 -> 3.5118519e+14 | H9: =$B9*'Time Series Scaling Factors'!H10 -> 3.5331559e+14 | I9: =$B9*'Time Series Scaling Factors'!I10 -> 3.5525324e+14 | J9: =$B9*'Time Series Scaling Factors'!J10 -> 3.5784783e+14 | ... AG9: =$B9*'Time Series Scaling Factors'!AG10 -> 3.9719904e+14 | AH9: =AG9 -> 3.9719904e+14 | AI9: =AH9 -> 3.9719904e+14 | AJ9: =AI9 -> 3.9719904e+14 | AK9: =AJ9 -> 3.9719904e+14 | AL9: =AK9 -> 3.9719904e+14 | AM9: =AL9 -> 3.9719904e+14 | AN9: =AM9 -> 3.9719904e+14 | AO9: =AN9 -> 3.9719904e+14 | ... BA9: =AZ9 -> 3.9719904e+14
A10: petroleum gasoline | B10: ='Start Year Data'!B34 -> 451136305874880 | C10: =$B10*'Time Series Scaling Factors'!C11 -> 5.1126628e+14 | D10: =$B10*'Time Series Scaling Factors'!D11 -> 566402787426456 | E10: =$B10*'Time Series Scaling Factors'!E11 -> 6.0015701e+14 | F10: =$B10*'Time Series Scaling Factors'!F11 -> 6.1561072e+14 | G10: =$B10*'Time Series Scaling Factors'!G11 -> 6.3040293e+14 | H10: =$B10*'Time Series Scaling Factors'!H11 -> 6.3876038e+14 | I10: =$B10*'Time Series Scaling Factors'!I11 -> 6.4804028e+14 | J10: =$B10*'Time Series Scaling Factors'!J11 -> 652639700390321 | ... AG10: =$B10*'Time Series Scaling Factors'!AG11 -> 6.9692607e+14 | AH10: =AG10 -> 6.9692607e+14 | AI10: =AH10 -> 6.9692607e+14 | AJ10: =AI10 -> 6.9692607e+14 | AK10: =AJ10 -> 6.9692607e+14 | AL10: =AK10 -> 6.9692607e+14 | AM10: =AL10 -> 6.9692607e+14 | AN10: =AM10 -> 6.9692607e+14 | AO10: =AN10 -> 6.9692607e+14 | ... BA10: =AZ10 -> 6.9692607e+14
A11: petroleum diesel | B11: ='Start Year Data'!B35 -> 208414558699680 | C11: =$B11*'Time Series Scaling Factors'!C12 -> 2.3619322e+14 | D11: =$B11*'Time Series Scaling Factors'!D12 -> 2.6166501e+14 | E11: =$B11*'Time Series Scaling Factors'!E12 -> 2.7725868e+14 | F11: =$B11*'Time Series Scaling Factors'!F12 -> 2.8439794e+14 | G11: =$B11*'Time Series Scaling Factors'!G12 -> 2.912316e+14 | H11: =$B11*'Time Series Scaling Factors'!H12 -> 2.9509255e+14 | I11: =$B11*'Time Series Scaling Factors'!I12 -> 2.9937965e+14 | J11: =$B11*'Time Series Scaling Factors'!J12 -> 3.0150448e+14 | ... AG11: =$B11*'Time Series Scaling Factors'!AG12 -> 3.2196376e+14 | AH11: =AG11 -> 3.2196376e+14 | AI11: =AH11 -> 3.2196376e+14 | AJ11: =AI11 -> 3.2196376e+14 | AK11: =AJ11 -> 3.2196376e+14 | AL11: =AK11 -> 3.2196376e+14 | AM11: =AL11 -> 3.2196376e+14 | AN11: =AM11 -> 3.2196376e+14 | AO11: =AN11 -> 3.2196376e+14 | ... BA11: =AZ11 -> 3.2196376e+14
A12: biofuel gasoline | B12: ='Start Year Data'!B36 -> 0 | C12: =$B12*'Time Series Scaling Factors'!C13 -> 0 | D12: =$B12*'Time Series Scaling Factors'!D13 -> 0 | E12: =$B12*'Time Series Scaling Factors'!E13 -> 0 | F12: =$B12*'Time Series Scaling Factors'!F13 -> 0 | G12: =$B12*'Time Series Scaling Factors'!G13 -> 0 | H12: =$B12*'Time Series Scaling Factors'!H13 -> 0 | I12: =$B12*'Time Series Scaling Factors'!I13 -> 0 | J12: =$B12*'Time Series Scaling Factors'!J13 -> 0 | ... AG12: =$B12*'Time Series Scaling Factors'!AG13 -> 0 | AH12: =AG12 -> 0 | AI12: =AH12 -> 0 | AJ12: =AI12 -> 0 | AK12: =AJ12 -> 0 | AL12: =AK12 -> 0 | AM12: =AL12 -> 0 | AN12: =AM12 -> 0 | AO12: =AN12 -> 0 | ... BA12: =AZ12 -> 0
A13: biofuel diesel | B13: ='Start Year Data'!B37 -> 0 | C13: =$B13*'Time Series Scaling Factors'!C14 -> 0 | D13: =$B13*'Time Series Scaling Factors'!D14 -> 0 | E13: =$B13*'Time Series Scaling Factors'!E14 -> 0 | F13: =$B13*'Time Series Scaling Factors'!F14 -> 0 | G13: =$B13*'Time Series Scaling Factors'!G14 -> 0 | H13: =$B13*'Time Series Scaling Factors'!H14 -> 0 | I13: =$B13*'Time Series Scaling Factors'!I14 -> 0 | J13: =$B13*'Time Series Scaling Factors'!J14 -> 0 | ... AG13: =$B13*'Time Series Scaling Factors'!AG14 -> 0 | AH13: =AG13 -> 0 | AI13: =AH13 -> 0 | AJ13: =AI13 -> 0 | AK13: =AJ13 -> 0 | AL13: =AK13 -> 0 | AM13: =AL13 -> 0 | AN13: =AM13 -> 0 | AO13: =AN13 -> 0 | ... BA13: =AZ13 -> 0
... A22: hydrogen | B22: ='Start Year Data'!B46 -> 0 | C22: =$B22*'Time Series Scaling Factors'!C23 -> 0 | D22: =$B22*'Time Series Scaling Factors'!D23 -> 0 | E22: =$B22*'Time Series Scaling Factors'!E23 -> 0 | F22: =$B22*'Time Series Scaling Factors'!F23 -> 0 | G22: =$B22*'Time Series Scaling Factors'!G23 -> 0 | H22: =$B22*'Time Series Scaling Factors'!H23 -> 0 | I22: =$B22*'Time Series Scaling Factors'!I23 -> 0 | J22: =$B22*'Time Series Scaling Factors'!J23 -> 0 | ... AG22: =$B22*'Time Series Scaling Factors'!AG23 -> 0 | AH22: =AG22 -> 0 | AI22: =AH22 -> 0 | AJ22: =AI22 -> 0 | AK22: =AJ22 -> 0 | AL22: =AK22 -> 0 | AM22: =AL22 -> 0 | AN22: =AM22 -> 0 | AO22: =AN22 -> 0 | ... BA22: =AZ22 -> 0

Sheet BFPIaE-imports
A1: Fuel (BTU) | B1: 2019 | C1: 2020 | D1: 2021 | E1: 2022 | F1: 2023 | G1: 2024 | H1: 2025 | I1: 2026 | J1: 2027 | K1: 2028 | L1: 2029 | M1: 2030 | N1: 2031 | O1: 2032 | P1: 2033 | Q1: 2034 | R1: 2035 | S1: 2036 | T1: 2037 | U1: 2038 | V1: 2039 | W1: 2040 | X1: 2041 | Y1: 2042 | Z1: 2043 | AA1: 2044 | AB1: 2045 | AC1: 2046 | AD1: 2047 | AE1: 2048 | AF1: 2049 | AG1: 2050 | AH1: 2051 | AI1: 2052 | AJ1: 2053 | AK1: 2054 | AL1: 2055 | AM1: 2056 | AN1: 2057 | AO1: 2058 | AP1: 2059 | AQ1: 2060 | AR1: 2061 | AS1: 2062 | AT1: 2063 | AU1: 2064 | AV1: 2065 | AW1: 2066 | AX1: 2067 | AY1: 2068 | AZ1: 2069 | BA1: 2070
A2: electricity (not used in this variable) | B2: ='Start Year Data'!C26 -> 0 | C2: =$B2*'Time Series Scaling Factors'!C28 -> 0 | D2: =$B2*'Time Series Scaling Factors'!D28 -> 0 | E2: =$B2*'Time Series Scaling Factors'!E28 -> 0 | F2: =$B2*'Time Series Scaling Factors'!F28 -> 0 | G2: =$B2*'Time Series Scaling Factors'!G28 -> 0 | H2: =$B2*'Time Series Scaling Factors'!H28 -> 0 | I2: =$B2*'Time Series Scaling Factors'!I28 -> 0 | J2: =$B2*'Time Series Scaling Factors'!J28 -> 0 | ... AG2: =$B2*'Time Series Scaling Factors'!AG28 -> 0 | AH2: =AG2 -> 0 | AI2: =AH2 -> 0 | AJ2: =AI2 -> 0 | AK2: =AJ2 -> 0 | AL2: =AK2 -> 0 | AM2: =AL2 -> 0 | AN2: =AM2 -> 0 | AO2: =AN2 -> 0 | ... BA2: =AZ2 -> 0
A3: hard coal | B3: ='Start Year Data'!C27 -> 4.0250381e+14 | C3: =$B3*'Time Series Scaling Factors'!C29 -> 4.2992846e+14 | D3: =$B3*'Time Series Scaling Factors'!D29 -> 2.7398562e+14 | E3: =$B3*'Time Series Scaling Factors'!E29 -> 2.6077021e+14 | F3: =$B3*'Time Series Scaling Factors'!F29 -> 2.5525436e+14 | G3: =$B3*'Time Series Scaling Factors'!G29 -> 2.598302e+14 | H3: =$B3*'Time Series Scaling Factors'!H29 -> 2.4508952e+14 | I3: =$B3*'Time Series Scaling Factors'!I29 -> 2.5267588e+14 | J3: =$B3*'Time Series Scaling Factors'!J29 -> 2.7247828e+14 | ... AG3: =$B3*'Time Series Scaling Factors'!AG29 -> 2.6426938e+14 | AH3: =AG3 -> 2.6426938e+14 | AI3: =AH3 -> 2.6426938e+14 | AJ3: =AI3 -> 2.6426938e+14 | AK3: =AJ3 -> 2.6426938e+14 | AL3: =AK3 -> 2.6426938e+14 | AM3: =AL3 -> 2.6426938e+14 | AN3: =AM3 -> 2.6426938e+14 | AO3: =AN3 -> 2.6426938e+14 | ... BA3: =AZ3 -> 2.6426938e+14
A4: natural gas | B4: ='Start Year Data'!C28 -> 0 | C4: =$B4*'Time Series Scaling Factors'!C30 -> 0 | D4: =$B4*'Time Series Scaling Factors'!D30 -> 0 | E4: =$B4*'Time Series Scaling Factors'!E30 -> 0 | F4: =$B4*'Time Series Scaling Factors'!F30 -> 0 | G4: =$B4*'Time Series Scaling Factors'!G30 -> 0 | H4: =$B4*'Time Series Scaling Factors'!H30 -> 0 | I4: =$B4*'Time Series Scaling Factors'!I30 -> 0 | J4: =$B4*'Time Series Scaling Factors'!J30 -> 0 | ... AG4: =$B4*'Time Series Scaling Factors'!AG30 -> 0 | AH4: =AG4 -> 0 | AI4: =AH4 -> 0 | AJ4: =AI4 -> 0 | AK4: =AJ4 -> 0 | AL4: =AK4 -> 0 | AM4: =AL4 -> 0 | AN4: =AM4 -> 0 | AO4: =AN4 -> 0 | ... BA4: =AZ4 -> 0
A5: nuclear | B5: ='Start Year Data'!C29 -> 0 | C5: =$B5*'Time Series Scaling Factors'!C31 -> 0 | D5: =$B5*'Time Series Scaling Factors'!D31 -> 0 | E5: =$B5*'Time Series Scaling Factors'!E31 -> 0 | F5: =$B5*'Time Series Scaling Factors'!F31 -> 0 | G5: =$B5*'Time Series Scaling Factors'!G31 -> 0 | H5: =$B5*'Time Series Scaling Factors'!H31 -> 0 | I5: =$B5*'Time Series Scaling Factors'!I31 -> 0 | J5: =$B5*'Time Series Scaling Factors'!J31 -> 0 | ... AG5: =$B5*'Time Series Scaling Factors'!AG31 -> 0 | AH5: =AG5 -> 0 | AI5: =AH5 -> 0 | AJ5: =AI5 -> 0 | AK5: =AJ5 -> 0 | AL5: =AK5 -> 0 | AM5: =AL5 -> 0 | AN5: =AM5 -> 0 | AO5: =AN5 -> 0 | ... BA5: =AZ5 -> 0
A6: hydro (is not a fuel) | B6: ='Start Year Data'!C30 -> 0 | C6: =$B6*'Time Series Scaling Factors'!C32 -> 0 | D6: =$B6*'Time Series Scaling Factors'!D32 -> 0 | E6: =$B6*'Time Series Scaling Factors'!E32 -> 0 | F6: =$B6*'Time Series Scaling Factors'!F32 -> 0 | G6: =$B6*'Time Series Scaling Factors'!G32 -> 0 | H6: =$B6*'Time Series Scaling Factors'!H32 -> 0 | I6: =$B6*'Time Series Scaling Factors'!I32 -> 0 | J6: =$B6*'Time Series Scaling Factors'!J32 -> 0 | ... AG6: =$B6*'Time Series Scaling Factors'!AG32 -> 0 | AH6: =AG6 -> 0 | AI6: =AH6 -> 0 | AJ6: =AI6 -> 0 | AK6: =AJ6 -> 0 | AL6: =AK6 -> 0 | AM6: =AL6 -> 0 | AN6: =AM6 -> 0 | AO6: =AN6 -> 0 | ... BA6: =AZ6 -> 0
A7: wind (is not a fuel) | B7: ='Start Year Data'!C31 -> 0 | C7: =$B7*'Time Series Scaling Factors'!C33 -> 0 | D7: =$B7*'Time Series Scaling Factors'!D33 -> 0 | E7: =$B7*'Time Series Scaling Factors'!E33 -> 0 | F7: =$B7*'Time Series Scaling Factors'!F33 -> 0 | G7: =$B7*'Time Series Scaling Factors'!G33 -> 0 | H7: =$B7*'Time Series Scaling Factors'!H33 -> 0 | I7: =$B7*'Time Series Scaling Factors'!I33 -> 0 | J7: =$B7*'Time Series Scaling Factors'!J33 -> 0 | ... AG7: =$B7*'Time Series Scaling Factors'!AG33 -> 0 | AH7: =AG7 -> 0 | AI7: =AH7 -> 0 | AJ7: =AI7 -> 0 | AK7: =AJ7 -> 0 | AL7: =AK7 -> 0 | AM7: =AL7 -> 0 | AN7: =AM7 -> 0 | AO7: =AN7 -> 0 | ... BA7: =AZ7 -> 0
A8: solar (is not a fuel) | B8: ='Start Year Data'!C32 -> 0 | C8: =$B8*'Time Series Scaling Factors'!C34 -> 0 | D8: =$B8*'Time Series Scaling Factors'!D34 -> 0 | E8: =$B8*'Time Series Scaling Factors'!E34 -> 0 | F8: =$B8*'Time Series Scaling Factors'!F34 -> 0 | G8: =$B8*'Time Series Scaling Factors'!G34 -> 0 | H8: =$B8*'Time Series Scaling Factors'!H34 -> 0 | I8: =$B8*'Time Series Scaling Factors'!I34 -> 0 | J8: =$B8*'Time Series Scaling Factors'!J34 -> 0 | ... AG8: =$B8*'Time Series Scaling Factors'!AG34 -> 0 | AH8: =AG8 -> 0 | AI8: =AH8 -> 0 | AJ8: =AI8 -> 0 | AK8: =AJ8 -> 0 | AL8: =AK8 -> 0 | AM8: =AL8 -> 0 | AN8: =AM8 -> 0 | AO8: =AN8 -> 0 | ... BA8: =AZ8 -> 0
A9: biomass | B9: ='Start Year Data'!C33 -> 0 | C9: =$B9*'Time Series Scaling Factors'!C35 -> 0 | D9: =$B9*'Time Series Scaling Factors'!D35 -> 0 | E9: =$B9*'Time Series Scaling Factors'!E35 -> 0 | F9: =$B9*'Time Series Scaling Factors'!F35 -> 0 | G9: =$B9*'Time Series Scaling Factors'!G35 -> 0 | H9: =$B9*'Time Series Scaling Factors'!H35 -> 0 | I9: =$B9*'Time Series Scaling Factors'!I35 -> 0 | J9: =$B9*'Time Series Scaling Factors'!J35 -> 0 | ... AG9: =$B9*'Time Series Scaling Factors'!AG35 -> 0 | AH9: =AG9 -> 0 | AI9: =AH9 -> 0 | AJ9: =AI9 -> 0 | AK9: =AJ9 -> 0 | AL9: =AK9 -> 0 | AM9: =AL9 -> 0 | AN9: =AM9 -> 0 | AO9: =AN9 -> 0 | ... BA9: =AZ9 -> 0
A10: petroleum gasoline | B10: ='Start Year Data'!C34 -> 1.0692183e+15 | C10: =$B10*'Time Series Scaling Factors'!C36 -> 9.3248098e+14 | D10: =$B10*'Time Series Scaling Factors'!D36 -> 944095361908093 | E10: =$B10*'Time Series Scaling Factors'!E36 -> 9.6392474e+14 | F10: =$B10*'Time Series Scaling Factors'!F36 -> 9.563392e+14 | G10: =$B10*'Time Series Scaling Factors'!G36 -> 9.329203e+14 | H10: =$B10*'Time Series Scaling Factors'!H36 -> 8.9889257e+14 | I10: =$B10*'Time Series Scaling Factors'!I36 -> 8.2889723e+14 | J10: =$B10*'Time Series Scaling Factors'!J36 -> 8.338553e+14 | ... AG10: =$B10*'Time Series Scaling Factors'!AG36 -> 8.1942707e+14 | AH10: =AG10 -> 8.1942707e+14 | AI10: =AH10 -> 8.1942707e+14 | AJ10: =AI10 -> 8.1942707e+14 | AK10: =AJ10 -> 8.1942707e+14 | AL10: =AK10 -> 8.1942707e+14 | AM10: =AL10 -> 8.1942707e+14 | AN10: =AM10 -> 8.1942707e+14 | AO10: =AN10 -> 8.1942707e+14 | ... BA10: =AZ10 -> 8.1942707e+14
A11: petroleum diesel | B11: ='Start Year Data'!C35 -> 5.4220826e+14 | C11: =$B11*'Time Series Scaling Factors'!C37 -> 472867800016611 | D11: =$B11*'Time Series Scaling Factors'!D37 -> 4.7875753e+14 | E11: =$B11*'Time Series Scaling Factors'!E37 -> 4.8881315e+14 | F11: =$B11*'Time Series Scaling Factors'!F37 -> 4.8496647e+14 | G11: =$B11*'Time Series Scaling Factors'!G37 -> 4.7309058e+14 | H11: =$B11*'Time Series Scaling Factors'!H37 -> 4.5583487e+14 | I11: =$B11*'Time Series Scaling Factors'!I37 -> 4.2033974e+14 | J11: =$B11*'Time Series Scaling Factors'!J37 -> 4.2285401e+14 | ... AG11: =$B11*'Time Series Scaling Factors'!AG37 -> 4.1553735e+14 | AH11: =AG11 -> 4.1553735e+14 | AI11: =AH11 -> 4.1553735e+14 | AJ11: =AI11 -> 4.1553735e+14 | AK11: =AJ11 -> 4.1553735e+14 | AL11: =AK11 -> 4.1553735e+14 | AM11: =AL11 -> 4.1553735e+14 | AN11: =AM11 -> 4.1553735e+14 | AO11: =AN11 -> 4.1553735e+14 | ... BA11: =AZ11 -> 4.1553735e+14
A12: biofuel gasoline | B12: ='Start Year Data'!C36 -> 0 | C12: =$B12*'Time Series Scaling Factors'!C38 -> 0 | D12: =$B12*'Time Series Scaling Factors'!D38 -> 0 | E12: =$B12*'Time Series Scaling Factors'!E38 -> 0 | F12: =$B12*'Time Series Scaling Factors'!F38 -> 0 | G12: =$B12*'Time Series Scaling Factors'!G38 -> 0 | H12: =$B12*'Time Series Scaling Factors'!H38 -> 0 | I12: =$B12*'Time Series Scaling Factors'!I38 -> 0 | J12: =$B12*'Time Series Scaling Factors'!J38 -> 0 | ... AG12: =$B12*'Time Series Scaling Factors'!AG38 -> 0 | AH12: =AG12 -> 0 | AI12: =AH12 -> 0 | AJ12: =AI12 -> 0 | AK12: =AJ12 -> 0 | AL12: =AK12 -> 0 | AM12: =AL12 -> 0 | AN12: =AM12 -> 0 | AO12: =AN12 -> 0 | ... BA12: =AZ12 -> 0
A13: biofuel diesel | B13: ='Start Year Data'!C37 -> 0 | C13: =$B13*'Time Series Scaling Factors'!C39 -> 0 | D13: =$B13*'Time Series Scaling Factors'!D39 -> 0 | E13: =$B13*'Time Series Scaling Factors'!E39 -> 0 | F13: =$B13*'Time Series Scaling Factors'!F39 -> 0 | G13: =$B13*'Time Series Scaling Factors'!G39 -> 0 | H13: =$B13*'Time Series Scaling Factors'!H39 -> 0 | I13: =$B13*'Time Series Scaling Factors'!I39 -> 0 | J13: =$B13*'Time Series Scaling Factors'!J39 -> 0 | ... AG13: =$B13*'Time Series Scaling Factors'!AG39 -> 0 | AH13: =AG13 -> 0 | AI13: =AH13 -> 0 | AJ13: =AI13 -> 0 | AK13: =AJ13 -> 0 | AL13: =AK13 -> 0 | AM13: =AL13 -> 0 | AN13: =AM13 -> 0 | AO13: =AN13 -> 0 | ... BA13: =AZ13 -> 0
... A22: hydrogen | B22: ='Start Year Data'!C46 -> 0 | C22: =$B22*'Time Series Scaling Factors'!C48 -> 0 | D22: =$B22*'Time Series Scaling Factors'!D48 -> 0 | E22: =$B22*'Time Series Scaling Factors'!E48 -> 0 | F22: =$B22*'Time Series Scaling Factors'!F48 -> 0 | G22: =$B22*'Time Series Scaling Factors'!G48 -> 0 | H22: =$B22*'Time Series Scaling Factors'!H48 -> 0 | I22: =$B22*'Time Series Scaling Factors'!I48 -> 0 | J22: =$B22*'Time Series Scaling Factors'!J48 -> 0 | ... AG22: =$B22*'Time Series Scaling Factors'!AG48 -> 0 | AH22: =AG22 -> 0 | AI22: =AH22 -> 0 | AJ22: =AI22 -> 0 | AK22: =AJ22 -> 0 | AL22: =AK22 -> 0 | AM22: =AL22 -> 0 | AN22: =AM22 -> 0 | AO22: =AN22 -> 0 | ... BA22: =AZ22 -> 0

Sheet BFPIaE-exports
A1: Fuel (BTU) | B1: 2019 | C1: 2020 | D1: 2021 | E1: 2022 | F1: 2023 | G1: 2024 | H1: 2025 | I1: 2026 | J1: 2027 | K1: 2028 | L1: 2029 | M1: 2030 | N1: 2031 | O1: 2032 | P1: 2033 | Q1: 2034 | R1: 2035 | S1: 2036 | T1: 2037 | U1: 2038 | V1: 2039 | W1: 2040 | X1: 2041 | Y1: 2042 | Z1: 2043 | AA1: 2044 | AB1: 2045 | AC1: 2046 | AD1: 2047 | AE1: 2048 | AF1: 2049 | AG1: 2050 | AH1: 2051 | AI1: 2052 | AJ1: 2053 | AK1: 2054 | AL1: 2055 | AM1: 2056 | AN1: 2057 | AO1: 2058 | AP1: 2059 | AQ1: 2060 | AR1: 2061 | AS1: 2062 | AT1: 2063 | AU1: 2064 | AV1: 2065 | AW1: 2066 | AX1: 2067 | AY1: 2068 | AZ1: 2069 | BA1: 2070
A2: electricity (not used in this variable) | B2: ='Start Year Data'!D26 -> 0 | C2: =$B2*'Time Series Scaling Factors'!C53 -> 0 | D2: =$B2*'Time Series Scaling Factors'!D53 -> 0 | E2: =$B2*'Time Series Scaling Factors'!E53 -> 0 | F2: =$B2*'Time Series Scaling Factors'!F53 -> 0 | G2: =$B2*'Time Series Scaling Factors'!G53 -> 0 | H2: =$B2*'Time Series Scaling Factors'!H53 -> 0 | I2: =$B2*'Time Series Scaling Factors'!I53 -> 0 | J2: =$B2*'Time Series Scaling Factors'!J53 -> 0 | ... AG2: =$B2*'Time Series Scaling Factors'!AG53 -> 0 | AH2: =AG2 -> 0 | AI2: =AH2 -> 0 | AJ2: =AI2 -> 0 | AK2: =AJ2 -> 0 | AL2: =AK2 -> 0 | AM2: =AL2 -> 0 | AN2: =AM2 -> 0 | AO2: =AN2 -> 0 | ... BA2: =AZ2 -> 0
A3: hard coal | B3: ='Start Year Data'!D27 -> 220841388960 | C3: =$B3*'Time Series Scaling Factors'!C54 -> 1.9329137e+11 | D3: =$B3*'Time Series Scaling Factors'!D54 -> 2.0547548e+11 | E3: =$B3*'Time Series Scaling Factors'!E54 -> 2.5309327e+11 | F3: =$B3*'Time Series Scaling Factors'!F54 -> 2.5456527e+11 | G3: =$B3*'Time Series Scaling Factors'!G54 -> 2.5609311e+11 | H3: =$B3*'Time Series Scaling Factors'!H54 -> 2.5780588e+11 | I3: =$B3*'Time Series Scaling Factors'!I54 -> 2.5920241e+11 | J3: =$B3*'Time Series Scaling Factors'!J54 -> 2.5896878e+11 | ... AG3: =$B3*'Time Series Scaling Factors'!AG54 -> 2.5052301e+11 | AH3: =AG3 -> 2.5052301e+11 | AI3: =AH3 -> 2.5052301e+11 | AJ3: =AI3 -> 2.5052301e+11 | AK3: =AJ3 -> 2.5052301e+11 | AL3: =AK3 -> 2.5052301e+11 | AM3: =AL3 -> 2.5052301e+11 | AN3: =AM3 -> 2.5052301e+11 | AO3: =AN3 -> 2.5052301e+11 | ... BA3: =AZ3 -> 2.5052301e+11
A4: natural gas | B4: ='Start Year Data'!D28 -> 0 | C4: =$B4*'Time Series Scaling Factors'!C55 -> 0 | D4: =$B4*'Time Series Scaling Factors'!D55 -> 0 | E4: =$B4*'Time Series Scaling Factors'!E55 -> 0 | F4: =$B4*'Time Series Scaling Factors'!F55 -> 0 | G4: =$B4*'Time Series Scaling Factors'!G55 -> 0 | H4: =$B4*'Time Series Scaling Factors'!H55 -> 0 | I4: =$B4*'Time Series Scaling Factors'!I55 -> 0 | J4: =$B4*'Time Series Scaling Factors'!J55 -> 0 | ... AG4: =$B4*'Time Series Scaling Factors'!AG55 -> 0 | AH4: =AG4 -> 0 | AI4: =AH4 -> 0 | AJ4: =AI4 -> 0 | AK4: =AJ4 -> 0 | AL4: =AK4 -> 0 | AM4: =AL4 -> 0 | AN4: =AM4 -> 0 | AO4: =AN4 -> 0 | ... BA4: =AZ4 -> 0
A5: nuclear | B5: ='Start Year Data'!D29 -> 0 | C5: =$B5*'Time Series Scaling Factors'!C56 -> 0 | D5: =$B5*'Time Series Scaling Factors'!D56 -> 0 | E5: =$B5*'Time Series Scaling Factors'!E56 -> 0 | F5: =$B5*'Time Series Scaling Factors'!F56 -> 0 | G5: =$B5*'Time Series Scaling Factors'!G56 -> 0 | H5: =$B5*'Time Series Scaling Factors'!H56 -> 0 | I5: =$B5*'Time Series Scaling Factors'!I56 -> 0 | J5: =$B5*'Time Series Scaling Factors'!J56 -> 0 | ... AG5: =$B5*'Time Series Scaling Factors'!AG56 -> 0 | AH5: =AG5 -> 0 | AI5: =AH5 -> 0 | AJ5: =AI5 -> 0 | AK5: =AJ5 -> 0 | AL5: =AK5 -> 0 | AM5: =AL5 -> 0 | AN5: =AM5 -> 0 | AO5: =AN5 -> 0 | ... BA5: =AZ5 -> 0
A6: hydro (is not a fuel) | B6: ='Start Year Data'!D30 -> 0 | C6: =$B6*'Time Series Scaling Factors'!C57 -> 0 | D6: =$B6*'Time Series Scaling Factors'!D57 -> 0 | E6: =$B6*'Time Series Scaling Factors'!E57 -> 0 | F6: =$B6*'Time Series Scaling Factors'!F57 -> 0 | G6: =$B6*'Time Series Scaling Factors'!G57 -> 0 | H6: =$B6*'Time Series Scaling Factors'!H57 -> 0 | I6: =$B6*'Time Series Scaling Factors'!I57 -> 0 | J6: =$B6*'Time Series Scaling Factors'!J57 -> 0 | ... AG6: =$B6*'Time Series Scaling Factors'!AG57 -> 0 | AH6: =AG6 -> 0 | AI6: =AH6 -> 0 | AJ6: =AI6 -> 0 | AK6: =AJ6 -> 0 | AL6: =AK6 -> 0 | AM6: =AL6 -> 0 | AN6: =AM6 -> 0 | AO6: =AN6 -> 0 | ... BA6: =AZ6 -> 0
A7: wind (is not a fuel) | B7: ='Start Year Data'!D31 -> 0 | C7: =$B7*'Time Series Scaling Factors'!C58 -> 0 | D7: =$B7*'Time Series Scaling Factors'!D58 -> 0 | E7: =$B7*'Time Series Scaling Factors'!E58 -> 0 | F7: =$B7*'Time Series Scaling Factors'!F58 -> 0 | G7: =$B7*'Time Series Scaling Factors'!G58 -> 0 | H7: =$B7*'Time Series Scaling Factors'!H58 -> 0 | I7: =$B7*'Time Series Scaling Factors'!I58 -> 0 | J7: =$B7*'Time Series Scaling Factors'!J58 -> 0 | ... AG7: =$B7*'Time Series Scaling Factors'!AG58 -> 0 | AH7: =AG7 -> 0 | AI7: =AH7 -> 0 | AJ7: =AI7 -> 0 | AK7: =AJ7 -> 0 | AL7: =AK7 -> 0 | AM7: =AL7 -> 0 | AN7: =AM7 -> 0 | AO7: =AN7 -> 0 | ... BA7: =AZ7 -> 0
A8: solar (is not a fuel) | B8: ='Start Year Data'!D32 -> 0 | C8: =$B8*'Time Series Scaling Factors'!C59 -> 0 | D8: =$B8*'Time Series Scaling Factors'!D59 -> 0 | E8: =$B8*'Time Series Scaling Factors'!E59 -> 0 | F8: =$B8*'Time Series Scaling Factors'!F59 -> 0 | G8: =$B8*'Time Series Scaling Factors'!G59 -> 0 | H8: =$B8*'Time Series Scaling Factors'!H59 -> 0 | I8: =$B8*'Time Series Scaling Factors'!I59 -> 0 | J8: =$B8*'Time Series Scaling Factors'!J59 -> 0 | ... AG8: =$B8*'Time Series Scaling Factors'!AG59 -> 0 | AH8: =AG8 -> 0 | AI8: =AH8 -> 0 | AJ8: =AI8 -> 0 | AK8: =AJ8 -> 0 | AL8: =AK8 -> 0 | AM8: =AL8 -> 0 | AN8: =AM8 -> 0 | AO8: =AN8 -> 0 | ... BA8: =AZ8 -> 0
A9: biomass | B9: ='Start Year Data'!D33 -> 0 | C9: =$B9*'Time Series Scaling Factors'!C60 -> 0 | D9: =$B9*'Time Series Scaling Factors'!D60 -> 0 | E9: =$B9*'Time Series Scaling Factors'!E60 -> 0 | F9: =$B9*'Time Series Scaling Factors'!F60 -> 0 | G9: =$B9*'Time Series Scaling Factors'!G60 -> 0 | H9: =$B9*'Time Series Scaling Factors'!H60 -> 0 | I9: =$B9*'Time Series Scaling Factors'!I60 -> 0 | J9: =$B9*'Time Series Scaling Factors'!J60 -> 0 | ... AG9: =$B9*'Time Series Scaling Factors'!AG60 -> 0 | AH9: =AG9 -> 0 | AI9: =AH9 -> 0 | AJ9: =AI9 -> 0 | AK9: =AJ9 -> 0 | AL9: =AK9 -> 0 | AM9: =AL9 -> 0 | AN9: =AM9 -> 0 | AO9: =AN9 -> 0 | ... BA9: =AZ9 -> 0
A10: petroleum gasoline | B10: ='Start Year Data'!D34 -> 61302915687360 | C10: =$B10*'Time Series Scaling Factors'!C61 -> 7.2237436e+13 | D10: =$B10*'Time Series Scaling Factors'!D61 -> 7.2734889e+13 | E10: =$B10*'Time Series Scaling Factors'!E61 -> 7.7776874e+13 | F10: =$B10*'Time Series Scaling Factors'!F61 -> 8.3248893e+13 | G10: =$B10*'Time Series Scaling Factors'!G61 -> 8.6540699e+13 | H10: =$B10*'Time Series Scaling Factors'!H61 -> 8.5231223e+13 | I10: =$B10*'Time Series Scaling Factors'!I61 -> 8.8443332e+13 | J10: =$B10*'Time Series Scaling Factors'!J61 -> 8.9183414e+13 | ... AG10: =$B10*'Time Series Scaling Factors'!AG61 -> 8.6389732e+13 | AH10: =AG10 -> 8.6389732e+13 | AI10: =AH10 -> 8.6389732e+13 | AJ10: =AI10 -> 8.6389732e+13 | AK10: =AJ10 -> 8.6389732e+13 | AL10: =AK10 -> 8.6389732e+13 | AM10: =AL10 -> 8.6389732e+13 | AN10: =AM10 -> 8.6389732e+13 | AO10: =AN10 -> 8.6389732e+13 | ... BA10: =AZ10 -> 8.6389732e+13
A11: petroleum diesel | B11: ='Start Year Data'!D35 -> 25712382831360 | C11: =$B11*'Time Series Scaling Factors'!C62 -> 3.0298667e+13 | D11: =$B11*'Time Series Scaling Factors'!D62 -> 3.0507314e+13 | E11: =$B11*'Time Series Scaling Factors'!E62 -> 3.2622082e+13 | F11: =$B11*'Time Series Scaling Factors'!F62 -> 3.491722e+13 | G11: =$B11*'Time Series Scaling Factors'!G62 -> 3.6297908e+13 | H11: =$B11*'Time Series Scaling Factors'!H62 -> 3.5748672e+13 | I11: =$B11*'Time Series Scaling Factors'!I62 -> 3.7095932e+13 | J11: =$B11*'Time Series Scaling Factors'!J62 -> 3.7406346e+13 | ... AG11: =$B11*'Time Series Scaling Factors'!AG62 -> 3.6234588e+13 | AH11: =AG11 -> 3.6234588e+13 | AI11: =AH11 -> 3.6234588e+13 | AJ11: =AI11 -> 3.6234588e+13 | AK11: =AJ11 -> 3.6234588e+13 | AL11: =AK11 -> 3.6234588e+13 | AM11: =AL11 -> 3.6234588e+13 | AN11: =AM11 -> 3.6234588e+13 | AO11: =AN11 -> 3.6234588e+13 | ... BA11: =AZ11 -> 3.6234588e+13
A12: biofuel gasoline | B12: ='Start Year Data'!D36 -> 0 | C12: =$B12*'Time Series Scaling Factors'!C63 -> 0 | D12: =$B12*'Time Series Scaling Factors'!D63 -> 0 | E12: =$B12*'Time Series Scaling Factors'!E63 -> 0 | F12: =$B12*'Time Series Scaling Factors'!F63 -> 0 | G12: =$B12*'Time Series Scaling Factors'!G63 -> 0 | H12: =$B12*'Time Series Scaling Factors'!H63 -> 0 | I12: =$B12*'Time Series Scaling Factors'!I63 -> 0 | J12: =$B12*'Time Series Scaling Factors'!J63 -> 0 | ... AG12: =$B12*'Time Series Scaling Factors'!AG63 -> 0 | AH12: =AG12 -> 0 | AI12: =AH12 -> 0 | AJ12: =AI12 -> 0 | AK12: =AJ12 -> 0 | AL12: =AK12 -> 0 | AM12: =AL12 -> 0 | AN12: =AM12 -> 0 | AO12: =AN12 -> 0 | ... BA12: =AZ12 -> 0
A13: biofuel diesel | B13: ='Start Year Data'!D37 -> 0 | C13: =$B13*'Time Series Scaling Factors'!C64 -> 0 | D13: =$B13*'Time Series Scaling Factors'!D64 -> 0 | E13: =$B13*'Time Series Scaling Factors'!E64 -> 0 | F13: =$B13*'Time Series Scaling Factors'!F64 -> 0 | G13: =$B13*'Time Series Scaling Factors'!G64 -> 0 | H13: =$B13*'Time Series Scaling Factors'!H64 -> 0 | I13: =$B13*'Time Series Scaling Factors'!I64 -> 0 | J13: =$B13*'Time Series Scaling Factors'!J64 -> 0 | ... AG13: =$B13*'Time Series Scaling Factors'!AG64 -> 0 | AH13: =AG13 -> 0 | AI13: =AH13 -> 0 | AJ13: =AI13 -> 0 | AK13: =AJ13 -> 0 | AL13: =AK13 -> 0 | AM13: =AL13 -> 0 | AN13: =AM13 -> 0 | AO13: =AN13 -> 0 | ... BA13: =AZ13 -> 0
... A22: hydrogen | B22: ='Start Year Data'!D46 -> 0 | C22: =$B22*'Time Series Scaling Factors'!C73 -> 0 | D22: =$B22*'Time Series Scaling Factors'!D73 -> 0 | E22: =$B22*'Time Series Scaling Factors'!E73 -> 0 | F22: =$B22*'Time Series Scaling Factors'!F73 -> 0 | G22: =$B22*'Time Series Scaling Factors'!G73 -> 0 | H22: =$B22*'Time Series Scaling Factors'!H73 -> 0 | I22: =$B22*'Time Series Scaling Factors'!I73 -> 0 | J22: =$B22*'Time Series Scaling Factors'!J73 -> 0 | ... AG22: =$B22*'Time Series Scaling Factors'!AG73 -> 0 | AH22: =AG22 -> 0 | AI22: =AH22 -> 0 | AJ22: =AI22 -> 0 | AK22: =AJ22 -> 0 | AL22: =AK22 -> 0 | AM22: =AL22 -> 0 | AN22: =AM22 -> 0 | AO22: =AN22 -> 0 | ... BA22: =AZ22 -> 0
