Workbook
Name gal_per_barrel: [1]About!$A$63

Sheet About
A1: BFPIaE BAU Fuel Production
A2: BFPIaE BAU Fuel Imports
A3: BFPIaE BAU Fuel Exports
A5: Source: | B5: Petroleum-based fuels, biofuels
B6: U.S. Energy Information Administration
B7: 2019
B8: Petroleum & Other Liquids: Supply and Disposition
B9: https://www.eia.gov/dnav/pet/pet_sum_snd_d_nus_mbbl_a_cur.htm
B10: Area: US, Period: Annual 2017
B12: Nuclear Fuel (Uranium)
B13: U.S. Energy Information Administration
B14: 2018
B15: U.S. uranium imports continue as domestic production remains at historical lows
B16: https://www.eia.gov/todayinenergy/detail.php?id=37192
B17: Paragraph 1
B19: Hard Coal, Lignite
B20: U.S. Energy Information Administration
B21: 2019
B22: Coal Explained: Where Our Coal Comes From
B23: https://www.eia.gov/energyexplained/index.php?page=coal_where
B24: https://www.eia.gov/energyexplained/index.php?page=coal_imports
B25: https://www.eia.gov/energyexplained/index.php?page=coal_prices
B27: Biomass Production and Exports
B28: U.S. Energy Information Administration
B29: 2020
B30: Monthly Densified Biomass Fuel Report
B31: https://www.eia.gov/biofuels/biomass/?year=2020&month=12#table_data
B32: Tables 4 and 8
B34: Biomass Imports and Exports (for Import to Export Ratio)
B35: U.S. International Trade Administration
B36: 2017
B37: 2016 Top Markets Report Renewable Fuels Sector Snapshot: Biomass Wood Pellets
B38: https://www.trade.gov/topmarkets/pdf/Renewable_Fuels_Biomass_Wood_Pellets.pdf
B39: Tables 2 and 3a
B41: Natural Gas, Time Series Scaling Factors
B42: U.S. Energy Information Administration
B43: 2020, 2022
B44: Annual Energy Outlook 2020, Annual Energy Outlook 2022
B45: https://www.eia.gov/outlooks/aeo/tables_ref.php
B46: Table 1
B48: Municipal Solid Waste
B49: U.S. Environmental Protection Agency
B50: 2016
B51: National Overview: Facts and Figures on Materials, Wastes and Recycling
B52: https://www.epa.gov/facts-and-figures-about-materials-waste-and-recycling/national-overview-facts-and-figures-materials
B54: Hydrogen
B55: U.S. Department of Energy
B56: 2018
B57: Fact of the Month May 2018: 10 Million Metric Tons of Hydrogen Produced Annually in the United States
B58: https://www.energy.gov/eere/fuelcells/fact-month-may-2018-10-million-metric-tons-hydrogen-produced-annually-united-states
B60: Unit Conversions for hard coal, natural gas, petroleum fuels, liquid biofuels
B61: Energy Information Administration
B62: 2021
B63: Annual Energy Outlook 2021
B64: http://www.eia.gov/forecasts/aeo/supplement/excel/suptab_73.xlsx
B65: AEO2021 Table 71
B67: Unit Conversions for Lignite, Biomass, LPG, municipal solid waste, hydrogen
B68: Argonne National Laboratory
B69: 2019
B70: GREET1 2019
B71: https://greet.es.anl.gov/
B72: Tab "Fuel_Specs"
B74: Unit Conversion for Uranium (U3O8)
B75: TradeTech
B76: 2019
B77: Uranium Primer - Price & Unit Conversion Calculator & Table
B78: https://www.uranium.info/unit_conversion_table.php
A80: Notes
A82: Collect Export, Import, and Production Data for Each Fuel
A83: The consolidated data in this variable (production, imports, exports, and domestic use of each fuel)
A84: is used in the variable fuels/CiFIaEpUDFS. Therefore, even though this variable only outputs
A85: production and exports, you should also collect data on fuel imports. (Domestic use data
A86: can be calculated from production, imports, and exports. We ignore changes in fuel stocks,
A87: which should average to zero over multi-year timeframes.)
A89: Time Series
A90: This variable contains time series data.
A91: However, only data from the first year are used in variable fuels/CiFIaEpUDFS.
A92: In the future, fuels/CiFIaEpUDFS may be replaced with internal Vensim calculations,
A93: making those values sensitive to changes over time.
... A107: or exported in bulk, so is included here.

Sheet Petroleum and Biofuel Data
B1: Area: US | C1: Period: 2017 (Annual) | E1: Unit: Thousand Barrels
C2: Supply | I2: Disposition | M2: Ending Stocks
C3: Field Production | D3: Renewable Fuels & Oxygenate Plant Net Production | E3: Refinery & Blender Net Production | F3: Imports | G3: Net Receipts | H3: Adjust- ments | I3: Stock Change | J3: Refinery & Blender Net Inputs | K3: Exports | L3: Products Supplied
A4: =TRIM(B4) -> Crude Oil & Petroleum Products | B4: Crude Oil & Petroleum Products | C4: 4794078 | D4: 437131 | E4: 7408771 | F4: 3702640 | H4: 137262 | I4: -135002 | J4: 7003159 | K4: 2327156 | L4: 7284569 | M4: 1894570
A5: =TRIM(B5) -> Crude Oil | B5: Crude Oil | C5: 4083494 | D5: - - | E5: - - | F5: 2230000 | H5: 194916 | I5: -108241 | J5: 5529012 | K5: 1087638 | L5: 0 | M5: 1015102
A6: =TRIM(B6) -> Hydrocarbon Gas Liquids | B6: Hydrocarbon Gas Liquids | C6: 1970031 | D6: -7941 | E6: 225172 | F6: 63125 | H6: - - | I6: -40797 | J6: 198527 | K6: 848015 | L6: 1244642 | M6: 188360
A7: =TRIM(B7) -> Natural Gas Liquids | B7: Natural Gas Liquids | C7: 1970031 | D7: -7941 | E7: 120757 | F7: 57128 | H7: - - | I7: -40636 | J7: 198527 | K7: 848015 | L7: 1134069 | M7: 186272
A8: =TRIM(B8) -> Ethane | B8: Ethane | C8: 781560 | D8: - - | E8: 1505 | F8: - | H8: - - | I8: -9779 | K8: 147584 | L8: 645260 | M8: 59821
A9: =TRIM(B9) -> Propane | B9: Propane | C9: 632906 | D9: - - | E9: 101344 | F9: 41465 | H9: - - | I9: -8358 | K9: 477616 | L9: 306457 | M9: 62077
A10: =TRIM(B10) -> Normal Butane | B10: Normal Butane | C10: 180543 | D10: - | E10: 20998 | F10: 13237 | H10: - - | I10: -7626 | J10: 66056 | K10: 149693 | L10: 6655 | M10: 34017
A11: =TRIM(B11) -> Isobutane | B11: Isobutane | C11: 153863 | D11: - | E11: -3090 | F11: 2358 | H11: - - | I11: -2667 | J11: 71652 | K11: 1181 | L11: 82965 | M11: 9674
A12: =TRIM(B12) -> Natural Gasoline | B12: Natural Gasoline | C12: 221159 | D12: -7941 | F12: 68 | H12: - - | I12: -12206 | J12: 60819 | K12: 71941 | L12: 92732 | M12: 20683
A13: =TRIM(B13) -> Refinery Olefins | B13: Refinery Olefins | C13: - - | D13: - - | E13: 104415 | F13: 5997 | H13: - - | I13: -161 | J13: - - | K13: - - | L13: 110573 | M13: 2088
A14: =TRIM(B14) -> Ethylene | B14: Ethylene | C14: - - | D14: - - | E14: 277 | F14: - | H14: - - | I14: 0 | J14: - - | K14: - - | L14: 277 | M14: 0
A15: =TRIM(B15) -> Propylene | B15: Propylene | C15: - - | D15: - - | E15: 106126 | F15: 5243 | H15: - - | I15: -90 | J15: - - | K15: - - | L15: 111459 | M15: 1397
A16: =TRIM(B16) -> Normal Butylene | B16: Normal Butylene | C16: - - | D16: - - | E16: -2397 | F16: 2433 | H16: - - | I16: -1165 | J16: - - | K16: - - | L16: 1201 | M16: 1204
A17: =TRIM(B17) -> Isobutylene | B17: Isobutylene | C17: - - | D17: - - | E17: 286 | F17: - | H17: - - | I17: 6 | J17: - - | K17: - - | L17: 280 | M17: 30
A18: =TRIM(B18) -> Other Liquids | B18: Other Liquids | C18: - - | D18: 443737 | E18: - - | F18: 471784 | H18: 19117 | I18: 8685 | J18: 741289 | K18: 171592 | L18: 13072 | M18: 328230
A19: =TRIM(B19) -> Hydrogen/Oxygenates/Renewables/Other Hydrocarbons | B19: Hydrogen/Oxygenates/Renewables/Other Hydrocarbons | C19: - - | D19: 443788 | E19: - - | F19: 19778 | H19: 36824 | I19: 577 | J19: 439078 | K19: 60735 | L19: 0 | M19: 29585
A20: =TRIM(B20) -> Hydrogen | B20: Hydrogen | C20: - - | D20: - - | E20: - - | H20: 81091 | I20: - - | J20: 81091 | L20: 0 | M20: - -
A21: =TRIM(B21) -> Oxygenates (excl. Fuel Ethanol) | B21: Oxygenates (excl. Fuel Ethanol) | C21: - - | D21: 26360 | E21: - - | F21: 3835 | H21: -4811 | I21: -31 | J21: - | K21: 25415 | L21: 0 | M21: 1446
A22: =TRIM(B22) -> Renewable Fuels (incl. Fuel Ethanol) | B22: Renewable Fuels (incl. Fuel Ethanol) | C22: - - | D22: 417428 | E22: - - | F22: 15707 | H22: -39640 | I22: 578 | J22: 357597 | K22: 35320 | L22: 0 | M22: 28092
A23: =TRIM(B23) -> Fuel Ethanol | B23: Fuel Ethanol | C23: - - | D23: 379435 | E23: - - | F23: 1824 | H23: -9859 | I23: 3285 | J23: 335023 | K23: 33092 | L23: 0 | M23: 23043
A24: =TRIM(B24) -> Renewable Fuels Except Fuel Ethanol | B24: Renewable Fuels Except Fuel Ethanol | C24: - - | D24: 37993 | E24: - - | F24: 13883 | H24: -29781 | I24: -2707 | J24: 22574 | K24: 2228 | L24: 0 | M24: 5049
A25: =TRIM(B25) -> Other Hydrocarbons | B25: Other Hydrocarbons | C25: - - | D25: - - | E25: - - | F25: 236 | H25: 184 | I25: 30 | J25: 390 | L25: 0 | M25: 47
A26: =TRIM(B26) -> Unfinished Oils | B26: Unfinished Oils | C26: - - | D26: - - | E26: - - | F26: 231478 | H26: - - | I26: 6013 | J26: 129406 | K26: 82949 | L26: 13110 | M26: 86337
A27: =TRIM(B27) -> Motor Gasoline Blend. Comp. | B27: Motor Gasoline Blend. Comp. | C27: - - | D27: -51 | E27: - - | F27: 220528 | H27: -17707 | I27: 2089 | J27: 172773 | K27: 27908 | L27: 0 | M27: 212293
A28: =TRIM(B28) -> Reformulated | B28: Reformulated | C28: - - | D28: -3 | E28: - - | F28: 76948 | H28: 65150 | I28: 1299 | J28: 140697 | K28: 99 | L28: 0 | M28: 53447
A29: =TRIM(B29) -> Conventional | B29: Conventional | C29: - - | D29: -48 | E29: - - | F29: 143580 | H29: -82856 | I29: 790 | J29: 32076 | K29: 27810 | L29: 0 | M29: 158846
A30: =TRIM(B30) -> Aviation Gasoline Blend. Comp. | B30: Aviation Gasoline Blend. Comp. | C30: - - | D30: - - | E30: - - | F30: - | H30: - - | I30: 6 | J30: 32 | K30: - | L30: -38 | M30: 15
A31: =TRIM(B31) -> Finished Petroleum Products | B31: Finished Petroleum Products | C31: - - | D31: 1336 | E31: 7179380 | F31: 250759 | H31: 57659 | I31: -38269 | J31: - - | K31: 1220551 | L31: 6306852 | M31: 291859
A32: =TRIM(B32) -> Finished Motor Gasoline | B32: Finished Motor Gasoline | C32: - - | D32: 1336 | E32: 3633123 | F32: 11784 | H32: 27566 | I32: -3860 | J32: - - | K32: 273483 | L32: 3404186 | M32: 24523
A33: =TRIM(B33) -> Reformulated | B33: Reformulated | C33: - - | E33: 1187104 | F33: - | H33: -59342 | I33: -7 | J33: - - | K33: - | L33: 1127769 | M33: 40
A34: =TRIM(B34) -> Conventional | B34: Conventional | C34: - - | D34: 1336 | E34: 2446019 | F34: 11784 | H34: 86908 | I34: -3853 | J34: - - | K34: 273483 | L34: 2276417 | M34: 24483
A35: =TRIM(B35) -> Finished Aviation Gasoline | B35: Finished Aviation Gasoline | C35: - - | D35: - - | E35: 4032 | F35: 165 | H35: - - | I35: 47 | J35: - - | K35: - | L35: 4150 | M35: 1041
A36: =TRIM(B36) -> Kerosene-Type Jet Fuel | B36: Kerosene-Type Jet Fuel | C36: - - | D36: - - | E36: 621176 | F36: 58273 | H36: - - | I36: -1706 | J36: - - | K36: 67161 | L36: 613994 | M36: 41304
A37: =TRIM(B37) -> Kerosene | B37: Kerosene | C37: - - | D37: - - | E37: 2738 | F37: 1429 | H37: - - | I37: 10 | J37: - - | K37: 2267 | L37: 1890 | M37: 2138
A38: =TRIM(B38) -> Distillate Fuel Oil | B38: Distillate Fuel Oil | C38: - - | D38: - - | E38: 1833879 | F38: 54975 | H38: 30093 | I38: -20457 | J38: - - | K38: 504155 | L38: 1435249 | M38: 145638
A39: =TRIM(B39) -> 15 ppm Sulfur and Under | B39: 15 ppm Sulfur and Under | C39: - - | D39: - - | E39: 1713652 | F39: 37012 | H39: 30093 | I39: -16256 | J39: - - | K39: 423862 | L39: 1373151 | M39: 128016
A40: =TRIM(B40) -> Greater than 15 to 500 ppm Sulfur | B40: Greater than 15 to 500 ppm Sulfur | C40: - - | D40: - - | E40: 42167 | F40: 759 | H40: - | I40: -929 | J40: - - | K40: 41645 | L40: 2210 | M40: 7480
A41: =TRIM(B41) -> Greater than 500 ppm Sulfur | B41: Greater than 500 ppm Sulfur | C41: - - | D41: - - | E41: 78060 | F41: 17204 | H41: - - | I41: -3272 | J41: - - | K41: 38648 | L41: 59888 | M41: 10142
A42: =TRIM(B42) -> Residual Fuel Oil | B42: Residual Fuel Oil | C42: - - | D42: - - | E42: 155851 | F42: 69015 | H42: - - | I42: -12098 | J42: - - | K42: 112240 | L42: 124724 | M42: 29377
A43: =TRIM(B43) -> Less than 0.31% Sulfur | B43: Less than 0.31% Sulfur | C43: - - | D43: - - | E43: 18946 | F43: 4112 | H43: - - | I43: -2600 | J43: - - | K43: NA | L43: NA | M43: 1928
A44: =TRIM(B44) -> 0.31 to 1.00% Sulfur | B44: 0.31 to 1.00% Sulfur | C44: - - | D44: - - | E44: 19577 | F44: 7295 | H44: - - | I44: -1119 | J44: - - | K44: NA | L44: NA | M44: 6822
A45: =TRIM(B45) -> Greater than 1.00% Sulfur | B45: Greater than 1.00% Sulfur | C45: - - | D45: - - | E45: 117328 | F45: 57608 | H45: - - | I45: -8379 | J45: - - | K45: NA | L45: NA | M45: 20621
A46: =TRIM(B46) -> Petrochemical Feedstocks | B46: Petrochemical Feedstocks | C46: - - | D46: - - | E46: 112198 | F46: 15696 | H46: - - | I46: -357 | J46: - - | K46: - | L46: 128251 | M46: 2883
A47: =TRIM(B47) -> Naphtha for Petro. Feed. Use | B47: Naphtha for Petro. Feed. Use | C47: - - | D47: - - | E47: 71578 | F47: 11373 | H47: - - | I47: -162 | J47: - - | K47: - | L47: 83113 | M47: 1849
A48: =TRIM(B48) -> Other Oils for Petro. Feed. Use | B48: Other Oils for Petro. Feed. Use | C48: - - | D48: - - | E48: 40620 | F48: 4323 | H48: - - | I48: -195 | J48: - - | K48: - | L48: 45138 | M48: 1034
A49: =TRIM(B49) -> Special Naphthas | B49: Special Naphthas | C49: - - | D49: - - | E49: 13688 | F49: 5405 | H49: - - | I49: -26 | J49: - - | K49: - | L49: 19119 | M49: 1192
A50: =TRIM(B50) -> Lubricants | B50: Lubricants | C50: - - | D50: - - | E50: 64970 | F50: 14901 | H50: - - | I50: -347 | J50: - - | K50: 36215 | L50: 44003 | M50: 12021
A51: =TRIM(B51) -> Waxes | B51: Waxes | C51: - - | D51: - - | E51: 1774 | F51: 1724 | H51: - - | I51: 184 | J51: - - | K51: 1479 | L51: 1835 | M51: 855
A52: =TRIM(B52) -> Petroleum Coke | B52: Petroleum Coke | C52: - - | D52: - - | E52: 329170 | F52: 3662 | H52: - - | I52: 1536 | J52: - - | K52: 215873 | L52: 115423 | M52: 8519
A53: =TRIM(B53) -> Marketable | B53: Marketable | C53: - - | D53: - - | E53: 245213 | F53: 3662 | H53: - - | I53: 1536 | J53: - - | K53: 215873 | L53: 31466 | M53: 8519
A54: =TRIM(B54) -> Catalyst | B54: Catalyst | C54: - - | D54: - - | E54: 83957 | F54: - - | G54: - - | H54: - - | I54: - - | J54: - - | K54: - - | L54: 83957 | M54: - -
A55: =TRIM(B55) -> Asphalt and Road Oil | B55: Asphalt and Road Oil | C55: - - | D55: - - | E55: 120515 | F55: 13666 | H55: - - | I55: -1184 | J55: - - | K55: 7399 | L55: 127966 | M55: 21697
A56: =TRIM(B56) -> Still Gas | B56: Still Gas | C56: - - | D56: - - | E56: 251761 | F56: - - | G56: - - | H56: - - | I56: - - | J56: - - | K56: - - | L56: 251761 | M56: - -
A57: =TRIM(B57) -> Miscellaneous Products | B57: Miscellaneous Products | C57: - - | D57: - - | E57: 34505 | F57: 64 | H57: - - | I57: -11 | J57: - - | K57: 279 | L57: 34301 | M57: 671

Sheet Biomass Data
A1: Table 4. Production of densified biomass fuel, 2020 (tons)
A2: Region | B2: Month | C2: Wood Pellets, premium/standard | D2: Wood Pellets Utility
A3: U.S. Total
B4: 1 | C4: 184451 | D4: 589367
B5: 2 | C5: 168559 | D5: 535088
B6: 3 | C6: 158633 | D6: 613798
B7: 4 | C7: 122820 | D7: 592364
B8: 5 | C8: 143019 | D8: 608837
B9: 6 | C9: 157357 | D9: 575481
B10: 7 | C10: 174016 | D10: 581260
B11: 8 | C11: 178391 | D11: 664441
B12: 9 | C12: 173333 | D12: 629927
B13: 10 | C13: 193711 | D13: 658237
B14: 11 | C14: 172601 | D14: 635793
B15: 12 | C15: 161979 | D15: 599576
A17: Table 8. Export sales and average price of densified biomass fuel, 2020
A18: Month | B18: Quantity (tons) | C18: Average Price (USD per ton)
A19: 1 | B19: 465014 | C19: 167.75
A20: 2 | B20: 532014 | C20: 163.39
A21: 3 | B21: 655441 | C21: 167.92
A22: 4 | B22: 548340 | C22: 164.43
A23: 5 | B23: 525716 | C23: 166.38
A24: 6 | B24: 627529 | C24: 159.44
A25: 7 | B25: 466871 | C25: 159.27
A26: 8 | B26: 557048 | C26: 169.81
A27: 9 | B27: 658081 | C27: 165.88
A28: 10 | B28: 572569 | C28: 166.42
A29: 11 | B29: 579346 | C29: 171.17
A30: 12 | B30: 761935 | C30: 172.44
A32: Total wood pellet production
A33: =SUM(C4:D15) -> 9273039 | B33: tons
A35: Total wood pellet exports
A36: =SUM(B19:B30) -> 6949904 | B36: tons
A38: We don't have biomass import data from EIA, but we do have some from the International Trade Administration (trade.gov).
A39: It uses different units and shows much higher wood pellet quantities than the EIA data, and it lacks production data.
A40: Accordingly, we only use it to establish a ratio of exports to imports, and apply that ratio to the EIA export data to
A41: estimate wood pellet imports (which are small compared to exports).
B43: Imports | C43: Exports | D43: Unit
A44: 2015 | B44: 207171527 | C44: 4668774792 | D44: kg
A46: Import to Export Ratio
A47: =B44/C44 -> 0.044373853
A49: Total wood pellet imports
A50: =A36*A47 -> 308394.02 | B50: tons

Sheet Uranium, Coal, MSW, Hydrogen
A1: Uranium
B2: Production | C2: Imports | D2: Exports | E2: Unit
A3: 2017 | B3: 3 | C3: 40 | D3: 0 | E3: million pounds U3O8
A5: Hard Coal and Lignite
A6: 0.09 | B6: of U.S. coal production was lignite in 2017
A7: 775 | B7: million short tons of coal produced (of all types) in 2017
A8: 97 | B8: million short tons of coal exported in 2017
A9: 6 | B9: million short tons of coal imported in 2017
A10: We assume that all imported and exported coal was hard coal, while all lignite produced was used domestically.
B12: Production | C12: Imports | D12: Exports | E12: Unit
A13: Hard Coal | B13: =A7*(1-A6) -> 705.25 | C13: =A9 -> 6 | D13: =A8 -> 97 | E13: million short tons
A14: Lignite | B14: =A6*A7 -> 69.75 | C14: 0 | D14: 0 | E14: million short tons
A16: Municipal Solid Waste
A17: MSW Tonnage Data for Year 2015
A18: 262.4 | B18: U.S. MSW generated (million tons)
A19: 33.57 | B19: U.S. MSW burned with energy recovery (million tons)
A20: 67.8 | B20: U.S. MSW recycled (million tons)
A21: 23.4 | B21: U.S. MSW composted (million tons)
A22: 137.7 | B22: U.S. MSW landfilled (million tons)
A24: Although the U.S. exports waste to other countries,
A25: it is difficult to find statistics for waste exports other than plastic waste.
A26: (Plastic waste exports to other countries in 2018 were
A27: 1.07 million metric tons in 2018.) | D27: https://www.plasticpollutioncoalition.org/pft/2019/3/6/157000-shipping-containers-of-us-plastic-waste-exported-to-countries-with-poor-waste-management-in-2018
A30: In this model, we are only concerned about MSW that is burned as a
A31: fuel. We will assume that a negligible amount of exported waste
A32: is used as a fuel.
A34: Hydrogen
A35: 10 | B35: million metric tons
A36: produced in 2018
A38: We assume none was imported or exported.

Sheet AEO 2022 Table 1
B1: ref2022.d011222a | C1: 2021 | D1: 2022 | E1: 2023 | F1: 2024 | G1: 2025 | H1: 2026 | I1: 2027 | J1: 2028 | K1: 2029 | L1: 2030 | M1: 2031 | N1: 2032 | O1: 2033 | P1: 2034 | Q1: 2035 | R1: 2036 | S1: 2037 | T1: 2038 | U1: 2039 | V1: 2040 | W1: 2041 | X1: 2042 | Y1: 2043 | Z1: 2044 | AA1: 2045 | AB1: 2046 | AC1: 2047 | AD1: 2048 | AE1: 2049 | AF1: 2050
C3: Report | D3: Annual Energy Outlook 2022
C4: Scenario | D4: ref2022 | G4: Reference
C5: Datekey | D5: d011222a
C6: Release Date | E6: March 2022
A10: SUP000 | B10: 1. Total Energy Supply, Disposition, and Price Summary | AG10: Average
B11: (quadrillion Btu, unless otherwise noted) | AG11: Annual
AG12: Change
B13: Supply, Disposition, and Prices | C13: 2021 | D13: 2022 | E13: 2023 | F13: 2024 | G13: 2025 | H13: 2026 | I13: 2027 | J13: 2028 | K13: 2029 | L13: 2030 | M13: 2031 | N13: 2032 | O13: 2033 | P13: 2034 | Q13: 2035 | R13: 2036 | S13: 2037 | T13: 2038 | U13: 2039 | V13: 2040 | W13: 2041 | X13: 2042 | Y13: 2043 | Z13: 2044 | AA13: 2045 | AB13: 2046 | AC13: 2047 | AD13: 2048 | AE13: 2049 | AF13: 2050 | AG13: 2021–2050
B15: Production
A16: SUP000:ba_CrudeOilLease | B16: Crude Oil and Lease Condensate | C16: 23.173487 | D16: 24.717472 | E16: 25.494104 | F16: 26.154642 | G16: 27.054277 | H16: 27.435596 | I16: 27.342155 | J16: 27.686852 | K16: 27.633852 | L16: 27.555265 | M16: 27.280258 | N16: 27.009712 | O16: 27.003248 | P16: 26.646475 | Q16: 26.47743 | R16: 26.305445 | S16: 26.016472 | T16: 25.819599 | U16: 25.821352 | V16: 25.902487 | W16: 25.722721 | X16: 25.635948 | Y16: 25.63641 | Z16: 25.47831 | AA16: 25.779816 | AB16: 25.951448 | AC16: 25.981897 | AD16: 25.859144 | AE16: 25.553583 | AF16: 26.234585 | AG16: 0.004287
A17: SUP000:ba_NaturalGasPla | B17: Natural Gas Plant Liquids | C17: 7.006215 | D17: 7.552815 | E17: 7.883783 | F17: 8.023396 | G17: 8.163991 | H17: 8.108202 | I17: 8.041482 | J17: 8.029618 | K17: 8.082181 | L17: 8.155948 | M17: 8.184832 | N17: 8.259987 | O17: 8.235239 | P17: 8.250072 | Q17: 8.27844 | R17: 8.210117 | S17: 8.17472 | T17: 8.172275 | U17: 8.222511 | V17: 8.267702 | W17: 8.281703 | X17: 8.384741 | Y17: 8.490253 | Z17: 8.476263 | AA17: 8.579662 | AB17: 8.612893 | AC17: 8.634458 | AD17: 8.644827 | AE17: 8.650251 | AF17: 8.701235 | AG17: 0.007499
A18: SUP000:ba_DryNaturalGas | B18: Dry Natural Gas | C18: 35.682777 | D18: 36.629646 | E18: 36.922058 | F18: 37.131554 | G18: 37.233967 | H18: 37.210548 | I18: 37.134987 | J18: 37.74691 | K18: 38.012238 | L18: 38.079895 | M18: 38.334229 | N18: 38.609394 | O18: 38.861305 | P18: 38.688675 | Q18: 38.547447 | R18: 38.495739 | S18: 38.611137 | T18: 38.832619 | U18: 39.095234 | V18: 39.377579 | W18: 39.502232 | X18: 39.69487 | Y18: 40.037334 | Z18: 40.361305 | AA18: 40.596077 | AB18: 40.848938 | AC18: 41.134644 | AD18: 41.335979 | AE18: 41.513866 | AF18: 41.894924 | AG18: 0.00555
A19: SUP000:ba_Coal | B19: Coal 1/ | C19: 13.089978 | D19: 12.741252 | E19: 12.812081 | F19: 11.346849 | G19: 10.919338 | H19: 10.890395 | I19: 10.594276 | J19: 10.517385 | K19: 10.477952 | L19: 10.320335 | M19: 10.278054 | N19: 10.186623 | O19: 10.161192 | P19: 9.840708 | Q19: 9.568752 | R19: 9.414873 | S19: 9.287329 | T19: 9.301336 | U19: 9.227633 | V19: 9.145965 | W19: 9.122682 | X19: 9.086012 | Y19: 8.961373 | Z19: 8.89466 | AA19: 8.785145 | AB19: 8.720604 | AC19: 8.623024 | AD19: 8.544412 | AE19: 8.507181 | AF19: 8.572097 | AG19: -0.014492
A20: SUP000:ba_NuclearPower | B20: Nuclear / Uranium 2/ | C20: 8.12115 | D20: 8.183111 | E20: 8.202579 | F20: 8.239058 | G20: 8.163899 | H20: 8.075755 | I20: 7.930267 | J20: 7.368946 | K20: 7.299504 | L20: 7.307006 | M20: 7.318423 | N20: 7.326343 | O20: 6.808416 | P20: 6.815667 | Q20: 6.747447 | R20: 6.758354 | S20: 6.760554 | T20: 6.762659 | U20: 6.762759 | V20: 6.766273 | W20: 6.77936 | X20: 6.788805 | Y20: 6.797936 | Z20: 6.805902 | AA20: 6.814445 | AB20: 6.818903 | AC20: 6.823349 | AD20: 6.826119 | AE20: 6.829472 | AF20: 6.834313 | AG20: -0.005931
A21: SUP000:ba_Hydropower | B21: Conventional Hydroelectric Power | C21: 2.288529 | D21: 2.39653 | E21: 2.520376 | F21: 2.607582 | G21: 2.562303 | H21: 2.533515 | I21: 2.5148 | J21: 2.494481 | K21: 2.48263 | L21: 2.471396 | M21: 2.456771 | N21: 2.450083 | O21: 2.436512 | P21: 2.4271 | Q21: 2.410605 | R21: 2.397023 | S21: 2.392663 | T21: 2.381657 | U21: 2.376802 | V21: 2.37014 | W21: 2.362096 | X21: 2.354189 | Y21: 2.3427 | Z21: 2.33699 | AA21: 2.32513 | AB21: 2.318443 | AC21: 2.309026 | AD21: 2.304834 | AE21: 2.295233 | AF21: 2.274688 | AG21: -0.000209
A22: SUP000:ba_Biomass | B22: Biomass 3/ | C22: 4.70119 | D22: 4.833665 | E22: 4.736951 | F22: 4.731843 | G22: 4.751482 | H22: 4.740038 | I22: 4.728146 | J22: 4.706775 | K22: 4.708263 | L22: 4.6997 | M22: 4.688527 | N22: 4.681827 | O22: 4.666749 | P22: 4.654086 | Q22: 4.648972 | R22: 4.641438 | S22: 4.63418 | T22: 4.638316 | U22: 4.647457 | V22: 4.683486 | W22: 4.705445 | X22: 4.722157 | Y22: 4.748343 | Z22: 4.791994 | AA22: 4.814004 | AB22: 4.843565 | AC22: 4.876688 | AD22: 4.909999 | AE22: 4.942437 | AF22: 4.984637 | AG22: 0.002021
A23: SUP000:ba_RenewableEner | B23: Other Renewable Energy 4/ | C23: 4.839005 | D23: 5.544484 | E23: 6.085557 | F23: 6.989227 | G23: 7.561359 | H23: 7.846316 | I23: 8.347466 | J23: 8.5777 | K23: 8.787159 | L23: 9.155986 | M23: 9.41178 | N23: 9.649215 | O23: 9.910384 | P23: 10.464489 | Q23: 11.17978 | R23: 11.560812 | S23: 11.709242 | T23: 11.735645 | U23: 11.787336 | V23: 11.864063 | W23: 11.965893 | X23: 12.084974 | Y23: 12.202391 | Z23: 12.369851 | AA23: 12.586577 | AB23: 12.70438 | AC23: 12.871214 | AD23: 13.03612 | AE23: 13.182046 | AF23: 13.273847 | AG23: 0.035408
A24: SUP000:ba_Other | B24: Other 5/ | C24: 2.133576 | D24: 1.012973 | E24: 0.879855 | F24: 0.894946 | G24: 0.774271 | H24: 0.88321 | I24: 0.8699 | J24: 0.796129 | K24: 0.770551 | L24: 0.770231 | M24: 0.768565 | N24: 0.632673 | O24: 0.631935 | P24: 0.640565 | Q24: 0.637551 | R24: 0.647367 | S24: 0.651814 | T24: 0.653633 | U24: 0.651491 | V24: 0.642037 | W24: 0.639621 | X24: 0.634056 | Y24: 0.627797 | Z24: 0.632698 | AA24: 0.626717 | AB24: 0.618566 | AC24: 0.61455 | AD24: 0.621078 | AE24: 0.628376 | AF24: 0.623335 | AG24: -0.041542
A25: SUP000:ba_Total | B25: Total | C25: 101.0359 | D25: 103.61195 | E25: 105.53733 | F25: 106.1191 | G25: 107.18489 | H25: 107.72357 | I25: 107.50348 | J25: 107.9248 | K25: 108.25434 | L25: 108.51576 | M25: 108.72144 | N25: 108.80585 | O25: 108.71499 | P25: 108.42783 | Q25: 108.49642 | R25: 108.43117 | S25: 108.23811 | T25: 108.29774 | U25: 108.59257 | V25: 109.01973 | W25: 109.08175 | X25: 109.38576 | Y25: 109.84454 | Z25: 110.14797 | AA25: 110.90757 | AB25: 111.43774 | AC25: 111.86885 | AD25: 112.08251 | AE25: 112.10244 | AF25: 113.39367 | AG25: 0.003987
B27: Imports
A28: SUP000:ca_CrudeOil | B28: Crude Oil | C28: 13.849983 | D28: 16.37085 | E28: 16.629141 | F28: 15.971055 | G28: 15.230758 | H28: 14.679036 | I28: 14.643375 | J28: 14.357627 | K28: 14.264916 | L28: 14.200821 | M28: 14.399286 | N28: 14.778255 | O28: 14.611301 | P28: 14.955673 | Q28: 15.036996 | R28: 15.363056 | S28: 15.527345 | T28: 15.740888 | U28: 15.813135 | V28: 15.458242 | W28: 15.443821 | X28: 15.243117 | Y28: 14.882616 | Z28: 15.204732 | AA28: 14.507174 | AB28: 14.091373 | AC28: 13.903984 | AD28: 14.131474 | AE28: 14.48548 | AF28: 13.759513 | AG28: -0.000226
A29: SUP000:ca_PetroleumProd | B29: Petroleum and Other Liquids 6/ | C29: 4.715964 | D29: 4.470991 | E29: 3.845002 | F29: 3.923882 | G29: 4.01288 | H29: 3.965475 | I29: 3.914824 | J29: 3.83206 | K29: 3.720322 | L29: 3.693734 | M29: 3.634232 | N29: 3.635437 | O29: 3.59495 | P29: 3.562899 | Q29: 3.543973 | R29: 3.497625 | S29: 3.494834 | T29: 3.505317 | U29: 3.501205 | V29: 3.483078 | W29: 3.503401 | X29: 3.506699 | Y29: 3.514882 | Z29: 3.52966 | AA29: 3.55301 | AB29: 3.566257 | AC29: 3.599412 | AD29: 3.686488 | AE29: 3.677653 | AF29: 3.64243 | AG29: -0.008867
A30: SUP000:ca_NaturalGas | B30: Natural Gas | C30: 2.798295 | D30: 2.540921 | E30: 2.459869 | F30: 2.356853 | G30: 2.282891 | H30: 2.256741 | I30: 2.221225 | J30: 2.170627 | K30: 2.036805 | L30: 1.983411 | M30: 1.890747 | N30: 1.878801 | O30: 1.924771 | P30: 1.886512 | Q30: 1.844462 | R30: 1.839028 | S30: 1.873339 | T30: 1.870136 | U30: 1.839986 | V30: 1.805083 | W30: 1.780095 | X30: 1.772161 | Y30: 1.710783 | Z30: 1.587325 | AA30: 1.509457 | AB30: 1.489166 | AC30: 1.460802 | AD30: 1.464388 | AE30: 1.431648 | AF30: 1.387205 | AG30: -0.023907
A31: SUP000:ca_OtherImports | B31: Other 7/ | C31: 0.290388 | D31: 0.22012 | E31: 0.1165 | F31: 0.120814 | G31: 0.110212 | H31: 0.115351 | I31: 0.128298 | J31: 0.136961 | K31: 0.138309 | L31: 0.145788 | M31: 0.137366 | N31: 0.141914 | O31: 0.134995 | P31: 0.140072 | Q31: 0.137182 | R31: 0.136788 | S31: 0.131592 | T31: 0.13375 | U31: 0.134478 | V31: 0.136204 | W31: 0.131303 | X31: 0.131657 | Y31: 0.139108 | Z31: 0.138671 | AA31: 0.134569 | AB31: 0.134666 | AC31: 0.134403 | AD31: 0.13461 | AE31: 0.13483 | AF31: 0.135472 | AG31: -0.025949
A32: SUP000:ca_Total | B32: Total | C32: 21.654629 | D32: 23.602882 | E32: 23.05051 | F32: 22.372604 | G32: 21.63674 | H32: 21.016602 | I32: 20.907722 | J32: 20.497274 | K32: 20.160353 | L32: 20.023756 | M32: 20.06163 | N32: 20.434408 | O32: 20.266016 | P32: 20.545156 | Q32: 20.562613 | R32: 20.836498 | S32: 21.027109 | T32: 21.250092 | U32: 21.288803 | V32: 20.882607 | W32: 20.85862 | X32: 20.653633 | Y32: 20.247391 | Z32: 20.460388 | AA32: 19.70421 | AB32: 19.281464 | AC32: 19.098602 | AD32: 19.41696 | AE32: 19.729612 | AF32: 18.92462 | AG32: -0.004636
B34: Exports
A35: SUP000:da_Petroleum | B35: Petroleum and Other Liquids 8/ | C35: 16.73385 | D35: 18.356298 | E35: 19.182388 | F35: 19.602926 | G35: 19.941938 | H35: 19.903315 | I35: 19.849981 | J35: 19.863663 | K35: 19.811287 | L35: 19.834377 | M35: 19.808157 | N35: 19.842936 | O35: 19.662491 | P35: 19.775711 | Q35: 19.81488 | R35: 19.950239 | S35: 19.816631 | T35: 19.884661 | U35: 19.983006 | V35: 19.83169 | W35: 19.682125 | X35: 19.486174 | Y35: 19.221823 | Z35: 19.413261 | AA35: 19.138691 | AB35: 18.841377 | AC35: 18.655954 | AD35: 18.810968 | AE35: 18.771133 | AF35: 18.527115 | AG35: 0.003517
A36: SUP000:da_NaturalGas | B36: Natural Gas | C36: 6.809672 | D36: 7.579476 | E36: 7.788739 | F36: 7.875538 | G36: 8.095082 | H36: 8.109738 | I36: 8.24765 | J36: 8.540207 | K36: 8.791788 | L36: 9.023255 | M36: 9.300149 | N36: 9.552501 | O36: 9.670875 | P36: 9.714972 | Q36: 9.777483 | R36: 9.799871 | S36: 9.798469 | T36: 9.820782 | U36: 9.84569 | V36: 9.881186 | W36: 9.868215 | X36: 9.885421 | Y36: 9.895191 | Z36: 9.93121 | AA36: 9.928005 | AB36: 9.911631 | AC36: 9.899729 | AD36: 9.904961 | AE36: 9.876596 | AF36: 9.8705 | AG36: 0.012882
A37: SUP000:da_Coal | B37: Coal | C37: 2.253399 | D37: 2.300418 | E37: 2.924233 | F37: 2.806449 | G37: 2.745555 | H37: 2.878079 | I37: 2.822221 | J37: 2.814723 | K37: 2.789355 | L37: 2.781176 | M37: 2.809537 | N37: 2.864769 | O37: 2.790718 | P37: 2.767172 | Q37: 2.793478 | R37: 2.759903 | S37: 2.751223 | T37: 2.785581 | U37: 2.726024 | V37: 2.735147 | W37: 2.71931 | X37: 2.734332 | Y37: 2.698877 | Z37: 2.698676 | AA37: 2.712163 | AB37: 2.696237 | AC37: 2.690248 | AD37: 2.71199 | AE37: 2.722844 | AF37: 2.737185 | AG37: 0.006729
A38: SUP000:da_Total | B38: Total | C38: 25.796921 | D38: 28.236191 | E38: 29.895359 | F38: 30.284914 | G38: 30.782578 | H38: 30.891132 | I38: 30.919853 | J38: 31.218594 | K38: 31.392429 | L38: 31.638807 | M38: 31.917843 | N38: 32.260204 | O38: 32.124084 | P38: 32.257858 | Q38: 32.385841 | R38: 32.510014 | S38: 32.366325 | T38: 32.491024 | U38: 32.554718 | V38: 32.448021 | W38: 32.26965 | X38: 32.105927 | Y38: 31.815891 | Z38: 32.043148 | AA38: 31.778858 | AB38: 31.449245 | AC38: 31.245932 | AD38: 31.427919 | AE38: 31.370575 | AF38: 31.1348 | AG38: 0.006506
A40: SUP000:ea_Discrepancy | B40: Discrepancy 9/ | C40: -0.09956 | D40: 1.014343 | E40: 0.351906 | F40: 0.371489 | G40: 0.341177 | H40: 0.382046 | I40: 0.381279 | J40: 0.35734 | K40: 0.386271 | L40: 0.381487 | M40: 0.400639 | N40: 0.433743 | O40: 0.415009 | P40: 0.413139 | Q40: 0.417732 | R40: 0.407967 | S40: 0.411499 | T40: 0.408596 | U40: 0.402512 | V40: 0.377655 | W40: 0.373608 | X40: 0.358025 | Y40: 0.344402 | Z40: 0.348759 | AA40: 0.320744 | AB40: 0.279781 | AC40: 0.300562 | AD40: 0.304501 | AE40: 0.307432 | AF40: 0.309587 | AG40: --
B42: Consumption
A43: SUP000:fa_PetroleumProd | B43: Petroleum and Other Liquids 10/ | C43: 36.03891 | D43: 36.753876 | E43: 37.164867 | F43: 37.008743 | G43: 36.993271 | H43: 36.890812 | I43: 36.698307 | J43: 36.579685 | K43: 36.420643 | L43: 36.309967 | M43: 36.218292 | N43: 36.215271 | O43: 36.163837 | P43: 36.030983 | Q43: 35.914291 | R43: 35.832382 | S43: 35.810936 | T43: 35.784924 | U43: 35.813648 | V43: 35.779423 | W43: 35.801689 | X43: 35.841454 | Y43: 35.887527 | Z43: 35.903362 | AA43: 35.944035 | AB43: 36.088379 | AC43: 36.201035 | AD43: 36.273766 | AE43: 36.392872 | AF43: 36.628178 | AG43: 0.000559
A44: SUP000:fa_NaturalGas | B44: Natural Gas | C44: 31.361422 | D44: 31.199945 | E44: 31.177605 | F44: 31.16921 | G44: 30.965534 | H44: 30.880772 | I44: 30.613737 | J44: 30.871202 | K44: 30.754141 | L44: 30.537725 | M44: 30.416206 | N44: 30.414434 | O44: 30.607912 | P44: 30.353966 | Q44: 30.106274 | R44: 30.03334 | S44: 30.184532 | T44: 30.381096 | U44: 30.592625 | V44: 30.803253 | W44: 30.909266 | X44: 31.077223 | Y44: 31.346886 | Z44: 31.509253 | AA44: 31.678867 | AB44: 31.934574 | AC44: 32.173542 | AD44: 32.373512 | AE44: 32.546021 | AF44: 32.886066 | AG44: 0.001638
A45: SUP000:fa_Coal | B45: Coal 11/ | C45: 10.883375 | D45: 10.484755 | E45: 9.873912 | F45: 8.510278 | G45: 8.140191 | H45: 7.937951 | I45: 7.705096 | J45: 7.669232 | K45: 7.61521 | L45: 7.464706 | M45: 7.393437 | N45: 7.246166 | O45: 7.293676 | P45: 6.99925 | Q45: 6.700851 | R45: 6.583507 | S45: 6.461794 | T45: 6.44173 | U45: 6.426641 | V45: 6.337152 | W45: 6.326757 | X45: 6.277361 | Y45: 6.194617 | Z45: 6.127982 | AA45: 6.00381 | AB45: 5.957881 | AC45: 5.866497 | AD45: 5.765072 | AE45: 5.717658 | AF45: 5.766378 | AG45: -0.021665
A46: SUP000:fa_NuclearPower | B46: Nuclear / Uranium 2/ | C46: 8.12115 | D46: 8.183111 | E46: 8.202579 | F46: 8.239058 | G46: 8.163899 | H46: 8.075755 | I46: 7.930267 | J46: 7.368946 | K46: 7.299504 | L46: 7.307006 | M46: 7.318423 | N46: 7.326343 | O46: 6.808416 | P46: 6.815667 | Q46: 6.747447 | R46: 6.758354 | S46: 6.760554 | T46: 6.762659 | U46: 6.762759 | V46: 6.766273 | W46: 6.77936 | X46: 6.788805 | Y46: 6.797936 | Z46: 6.805902 | AA46: 6.814445 | AB46: 6.818903 | AC46: 6.823349 | AD46: 6.826119 | AE46: 6.829472 | AF46: 6.834313 | AG46: -0.005931
A47: SUP000:fa_Hydropower | B47: Conventional Hydroelectric Power | C47: 2.288529 | D47: 2.39653 | E47: 2.520376 | F47: 2.607582 | G47: 2.562303 | H47: 2.533515 | I47: 2.5148 | J47: 2.494481 | K47: 2.48263 | L47: 2.471396 | M47: 2.456771 | N47: 2.450083 | O47: 2.436512 | P47: 2.4271 | Q47: 2.410605 | R47: 2.397023 | S47: 2.392663 | T47: 2.381657 | U47: 2.376802 | V47: 2.37014 | W47: 2.362096 | X47: 2.354189 | Y47: 2.3427 | Z47: 2.33699 | AA47: 2.32513 | AB47: 2.318443 | AC47: 2.309026 | AD47: 2.304834 | AE47: 2.295233 | AF47: 2.274688 | AG47: -0.000209
A48: SUP000:fa_Biomass | B48: Biomass 12/ | C48: 3.124412 | D48: 3.124567 | E48: 3.05355 | F48: 3.045954 | G48: 3.05583 | H48: 3.041447 | I48: 3.026574 | J48: 3.002259 | K48: 2.992482 | L48: 2.980528 | M48: 2.965883 | N48: 2.956268 | O48: 2.939253 | P48: 2.923384 | Q48: 2.911871 | R48: 2.900167 | S48: 2.888609 | T48: 2.879169 | U48: 2.882052 | V48: 2.872139 | W48: 2.872755 | X48: 2.872178 | Y48: 2.879459 | Z48: 2.883198 | AA48: 2.883371 | AB48: 2.891699 | AC48: 2.900502 | AD48: 2.911157 | AE48: 2.913831 | AF48: 2.933004 | AG48: -0.002178
A49: SUP000:fa_RenewableEner | B49: Other Renewable Energy 4/ | C49: 4.839005 | D49: 5.544484 | E49: 6.085557 | F49: 6.989227 | G49: 7.561359 | H49: 7.846316 | I49: 8.347466 | J49: 8.5777 | K49: 8.787159 | L49: 9.155986 | M49: 9.41178 | N49: 9.649215 | O49: 9.910384 | P49: 10.464489 | Q49: 11.17978 | R49: 11.560812 | S49: 11.709242 | T49: 11.735645 | U49: 11.787336 | V49: 11.864063 | W49: 11.965893 | X49: 12.084974 | Y49: 12.202391 | Z49: 12.369851 | AA49: 12.586577 | AB49: 12.70438 | AC49: 12.871214 | AD49: 13.03612 | AE49: 13.182046 | AF49: 13.273847 | AG49: 0.035408
A50: SUP000:fa_Other | B50: Other 13/ | C50: 0.336373 | D50: 0.277024 | E50: 0.26214 | F50: 0.265242 | G50: 0.255492 | H50: 0.260431 | I50: 0.273827 | J50: 0.282621 | K50: 0.284219 | L50: 0.291907 | M50: 0.28379 | N50: 0.288546 | O50: 0.281913 | P50: 0.287158 | Q50: 0.284342 | R50: 0.284106 | S50: 0.279065 | T50: 0.281331 | U50: 0.282285 | V50: 0.284222 | W50: 0.2793 | X50: 0.27926 | Y50: 0.280125 | Z50: 0.279916 | AA50: 0.275945 | AB50: 0.27593 | AC50: 0.275795 | AD50: 0.276476 | AE50: 0.276908 | AF50: 0.27742 | AG50: -0.006622
A51: SUP000:fa_Total | B51: Total | C51: 96.993172 | D51: 97.964294 | E51: 98.340576 | F51: 97.835297 | G51: 97.697876 | H51: 97.466995 | I51: 97.110069 | J51: 96.846138 | K51: 96.635994 | L51: 96.519226 | M51: 96.464584 | N51: 96.546318 | O51: 96.44191 | P51: 96.301994 | Q51: 96.255463 | R51: 96.349693 | S51: 96.487396 | T51: 96.648209 | U51: 96.924149 | V51: 97.07666 | W51: 97.297112 | X51: 97.575439 | Y51: 97.931641 | Z51: 98.216454 | AA51: 98.512177 | AB51: 98.990181 | AC51: 99.420959 | AD51: 99.767052 | AE51: 100.15404 | AF51: 100.8739 | AG51: 0.001354
B53: Prices (2021 dollars per unit)
A54: SUP000:ha_WorldOilPrice | B54: Brent Spot Price (dollars per barrel) | C54: 71.587997 | D54: 69.66571 | E54: 60.115009 | F54: 65.487526 | G54: 66.944946 | H54: 68.336487 | I54: 70.188248 | J54: 71.247108 | K54: 72.276756 | L54: 73.089027 | M54: 74.201714 | N54: 75.693771 | O54: 76.516808 | P54: 77.011726 | Q54: 77.511917 | R54: 77.914551 | S54: 79.12043 | T54: 79.949265 | U54: 80.107307 | V54: 81.746223 | W54: 82.892479 | X54: 83.244728 | Y54: 84.953598 | Z54: 86.823944 | AA54: 87.048103 | AB54: 88.261673 | AC54: 88.154121 | AD54: 88.15358 | AE54: 88.626503 | AF54: 88.049568 | AG54: 0.007163
A55: SUP000:ha_ForLowSulfLit | B55: West Texas Intermediate Spot Price (dollars per barrel | C55: 69.023003 | D55: 66.150894 | E55: 58.565804 | F55: 63.481312 | G55: 64.71344 | H55: 65.889473 | I55: 67.33989 | J55: 68.79483 | K55: 69.806862 | L55: 70.71656 | M55: 71.664322 | N55: 73.149719 | O55: 74.028023 | P55: 74.299271 | Q55: 74.585869 | R55: 74.74485 | S55: 75.858505 | T55: 76.686295 | U55: 76.795464 | V55: 78.57148 | W55: 79.729446 | X55: 80.188103 | Y55: 81.850861 | Z55: 83.591797 | AA55: 84.018883 | AB55: 85.136871 | AC55: 85.34671 | AD55: 85.364227 | AE55: 85.855141 | AF55: 85.23468 | AG55: 0.007301
A56: SUP000:ha_GasPriceHenry | B56: Natural Gas at Henry Hub (dollars per mmBtu) | C56: 4.115437 | D56: 3.837557 | E56: 3.471147 | F56: 3.126585 | G56: 2.953741 | H56: 2.906966 | I56: 2.954549 | J56: 3.136157 | K56: 3.292231 | L56: 3.388971 | M56: 3.454448 | N56: 3.491858 | O56: 3.59329 | P56: 3.594153 | Q56: 3.524364 | R56: 3.485305 | S56: 3.48693 | T56: 3.51827 | U56: 3.545613 | V56: 3.577658 | W56: 3.63465 | X56: 3.652029 | Y56: 3.589562 | Z56: 3.561126 | AA56: 3.469676 | AB56: 3.425366 | AC56: 3.400315 | AD56: 3.392432 | AE56: 3.403568 | AF56: 3.409512 | AG56: -0.006468
A57: SUP000:ha_CoalMinemouth | B57: Coal, Minemouth (dollars per ton) 14/ | C57: 36.126965 | D57: 33.048691 | E57: 33.697308 | F57: 34.915207 | G57: 33.191757 | H57: 31.716324 | I57: 31.066441 | J57: 30.505335 | K57: 30.725069 | L57: 30.714941 | M57: 30.711941 | N57: 30.82056 | O57: 31.028635 | P57: 31.325903 | Q57: 31.308147 | R57: 31.61187 | S57: 32.129681 | T57: 32.22797 | U57: 32.280781 | V57: 32.69191 | W57: 32.910851 | X57: 32.751488 | Y57: 33.197136 | Z57: 33.294754 | AA57: 33.901966 | AB57: 34.154438 | AC57: 34.402786 | AD57: 34.352524 | AE57: 34.457165 | AF57: 34.526253 | AG57: -0.001562
A58: SUP000:ha_CoalMineBtu | B58: Coal, Minemouth (dollars per million Btu) 14/ | C58: 1.753047 | D58: 1.605396 | E58: 1.612716 | F58: 1.644811 | G58: 1.57868 | H58: 1.524597 | I58: 1.498204 | J58: 1.483403 | K58: 1.4923 | L58: 1.492875 | M58: 1.493347 | N58: 1.493653 | O58: 1.496539 | P58: 1.510248 | Q58: 1.511186 | R58: 1.522797 | S58: 1.536004 | T58: 1.543051 | U58: 1.547495 | V58: 1.564056 | W58: 1.574198 | X58: 1.569195 | Y58: 1.586313 | Z58: 1.590278 | AA58: 1.607756 | AB58: 1.618476 | AC58: 1.629431 | AD58: 1.629268 | AE58: 1.634834 | AF58: 1.639391 | AG58: -0.002309
A59: SUP000:ha_CoalDelivered | B59: Coal, Delivered (dollars per million Btu) 15/ | C59: 2.229239 | D59: 2.108559 | E59: 2.109313 | F59: 2.118861 | G59: 2.072601 | H59: 2.05201 | I59: 2.039511 | J59: 2.031738 | K59: 2.042039 | L59: 2.041963 | M59: 2.03813 | N59: 2.033941 | O59: 2.027794 | P59: 2.031424 | Q59: 2.01707 | R59: 2.01048 | S59: 2.012397 | T59: 2.00864 | U59: 2.008059 | V59: 2.010775 | W59: 2.014587 | X59: 2.002263 | Y59: 2.00309 | Z59: 2.000369 | AA59: 2.000631 | AB59: 2.001826 | AC59: 1.997227 | AD59: 1.985802 | AE59: 1.98377 | AF59: 1.981437 | AG59: -0.004055
A60: SUP000:ha_Electricity(c | B60: Electricity (cents per kilowatthour) | C60: 11.09206 | D60: 10.975097 | E60: 10.752557 | F60: 10.540874 | G60: 10.475073 | H60: 10.501468 | I60: 10.507842 | J60: 10.52357 | K60: 10.553371 | L60: 10.551203 | M60: 10.580885 | N60: 10.611277 | O60: 10.653981 | P60: 10.67311 | Q60: 10.574654 | R60: 10.500532 | S60: 10.454601 | T60: 10.40737 | U60: 10.364239 | V60: 10.379671 | W60: 10.349372 | X60: 10.349371 | Y60: 10.292791 | Z60: 10.252166 | AA60: 10.25128 | AB60: 10.175208 | AC60: 10.157688 | AD60: 10.123593 | AE60: 10.092719 | AF60: 10.021296 | AG60: -0.003494
B63: Prices (nominal dollars per unit)
A64: SUP000:nom_ImportRACost | B64: Brent Spot Price (dollars per barrel) | C64: 71.587997 | D64: 71.908997 | E64: 63.61998 | F64: 71.373055 | G64: 75.273743 | H64: 79.457573 | I64: 84.49556 | J64: 88.816948 | K64: 93.240852 | L64: 97.461693 | M64: 102.24275 | N64: 107.67736 | O64: 112.40005 | P64: 116.90786 | Q64: 121.68389 | R64: 126.52406 | S64: 132.93751 | T64: 138.98383 | U64: 144.0029 | V64: 152.01515 | W64: 159.44214 | X64: 165.62906 | Y64: 174.78682 | Z64: 184.65153 | AA64: 191.32927 | AB64: 200.49499 | AC64: 206.9554 | AD64: 213.82344 | AE64: 221.99219 | AF64: 227.62056 | AG64: 0.040694
A65: SUP000:nom_ForLowSulfLi | B65: West Texas Intermediate Spot Price (dollars per barrel | C65: 69.023003 | D65: 68.280998 | E65: 61.980446 | F65: 69.186539 | G65: 72.76461 | H65: 76.612328 | I65: 81.066589 | J65: 85.759926 | K65: 90.05455 | L65: 94.298096 | M65: 98.746475 | N65: 104.05834 | O65: 108.74414 | P65: 112.79021 | Q65: 117.09036 | R65: 121.37684 | S65: 127.45686 | T65: 133.31148 | U65: 138.04945 | V65: 146.11139 | W65: 153.35812 | X65: 159.54741 | Y65: 168.40314 | Z65: 177.7776 | AA65: 184.67111 | AB65: 193.3967 | AC65: 200.36456 | AD65: 207.05765 | AE65: 215.05046 | AF65: 220.34367 | AG65: 0.040838
A66: SUP000:nom_Gas@HenryHub | B66: Natural Gas at Henry Hub (dollars per mmBtu) | C66: 4.115437 | D66: 3.961129 | E66: 3.67353 | F66: 3.407579 | G66: 3.321223 | H66: 3.380046 | I66: 3.55681 | J66: 3.909547 | K66: 4.247153 | L66: 4.519075 | M66: 4.759894 | N66: 4.967306 | O66: 5.278396 | P66: 5.456114 | Q66: 5.532805 | R66: 5.659725 | S66: 5.858712 | T66: 6.116162 | U66: 6.373682 | V66: 6.653007 | W66: 6.991181 | X66: 7.266311 | Y66: 7.385303 | Z66: 7.573573 | AA66: 7.62625 | AB66: 7.781052 | AC66: 7.982764 | AD66: 8.228611 | AE66: 8.525277 | AF66: 8.814068 | AG66: 0.02661
A67: SUP000:nom_CoalMinemout | B67: Coal, Minemouth (dollars per ton) 14/ | C67: 36.126965 | D67: 34.112881 | E67: 35.66201 | F67: 38.053123 | G67: 37.321236 | H67: 36.877842 | I67: 37.399086 | J67: 38.02808 | K67: 39.636967 | L67: 40.957314 | M67: 42.318069 | N67: 43.843456 | O67: 45.579796 | P67: 47.554371 | Q67: 49.149826 | R67: 51.333954 | S67: 53.984035 | T67: 56.025112 | U67: 58.02874 | V67: 60.793827 | W67: 63.30341 | X67: 65.164467 | Y67: 68.301071 | Z67: 70.80912 | AA67: 74.515556 | AB67: 77.585136 | AC67: 80.765846 | AD67: 83.324745 | AE67: 86.30851 | AF67: 89.255226 | AG67: 0.03168
A68: SUP000:nom_CoalMineBtu | B68: Coal, Minemouth (dollars per million Btu) 14/ | C68: 1.753047 | D68: 1.65709 | E68: 1.706745 | F68: 1.792635 | G68: 1.775088 | H68: 1.77271 | I68: 1.803601 | J68: 1.849217 | K68: 1.925146 | L68: 1.990697 | M68: 2.057687 | N68: 2.124779 | O68: 2.198354 | P68: 2.292636 | Q68: 2.37237 | R68: 2.472843 | S68: 2.580781 | T68: 2.68244 | U68: 2.781816 | V68: 2.908517 | W68: 3.02794 | X68: 3.122171 | Y68: 3.263741 | Z68: 3.3821 | AA68: 3.533802 | AB68: 3.676526 | AC68: 3.825341 | AD68: 3.951918 | AE68: 4.094942 | AF68: 4.238058 | AG68: 0.030908
A69: SUP000:nom_CoalDeliverd | B69: Coal, Delivered (dollars per million Btu) 15/ | C69: 2.229239 | D69: 2.176456 | E69: 2.232296 | F69: 2.309288 | G69: 2.330459 | H69: 2.385954 | I69: 2.455249 | J69: 2.532773 | K69: 2.634339 | L69: 2.722887 | M69: 2.808344 | N69: 2.89336 | O69: 2.978747 | P69: 3.083808 | Q69: 3.166544 | R69: 3.264783 | S69: 3.381214 | T69: 3.491821 | U69: 3.609737 | V69: 3.739234 | W69: 3.875021 | X69: 3.98383 | Y69: 4.121235 | Z69: 4.254254 | AA69: 4.397331 | AB69: 4.547344 | AC69: 4.688799 | AD69: 4.81672 | AE69: 4.968959 | AF69: 5.122294 | AG69: 0.029103
A70: SUP000:nom_Electricity | B70: Electricity (cents per kilowatthour) | C70: 11.09206 | D70: 11.328503 | E70: 11.379478 | F70: 11.48821 | G70: 11.778304 | H70: 12.210477 | I70: 12.649781 | J70: 13.118728 | K70: 13.614408 | L70: 14.069665 | M70: 14.579432 | N70: 15.094956 | O70: 15.650263 | P70: 16.202343 | Q70: 16.600866 | R70: 17.051628 | S70: 17.565737 | T70: 18.092175 | U70: 18.631014 | V70: 19.302019 | W70: 19.906824 | X70: 20.591772 | Y70: 21.176786 | Z70: 21.803642 | AA70: 22.532022 | AB70: 23.113977 | AC70: 23.846741 | AD70: 24.555573 | AE70: 25.280302 | AF70: 25.906462 | AG70: 0.029682
B72: 1/ Includes waste coal.
B73: 2/ These values represent the energy obtained from uranium when it is used in light water reactors. The total energy content of uranium
B74: is much larger, but alternative processes are required to take advantage of it.
B75: 3/ Includes grid-connected electricity from wood and wood waste; biomass, such as corn, used for liquid fuels production; and nonelectric
B76: energy demand from wood. Refer to Table 17 for details.
B77: 4/ Includes grid-connected electricity from landfill gas; biogenic municipal waste; wind; photovoltaic and solar thermal sources; and
B78: nonelectric energy from renewable sources, such as active and passive solar systems. Excludes electricity imports using renewable sources
B79: and nonmarketed renewable energy. See Table 17 for selected nonmarketed residential and commercial renewable energy data.
B80: 5/ Includes non-biogenic municipal waste, hydrogen, methanol, and some domestic inputs to refineries.
B81: 6/ Includes imports of finished petroleum products, unfinished oils, alcohols, ethers, blending components, and renewable fuels such as ethanol.
B82: 7/ Includes coal, coal coke (net), and electricity (net). Excludes imports of fuel used in nuclear power plants.
B83: 8/ Includes crude oil, petroleum products, ethanol, and biodiesel.
... B100: National Energy Modeling System run ref2022.d011222a. Projections: EIA, AEO2022 National Energy Modeling System run ref2022.d011222a.

Sheet AEO 2023 Table 1
B1: ref2023.d020623a | C1: 2022 | D1: 2023 | E1: 2024 | F1: 2025 | G1: 2026 | H1: 2027 | I1: 2028 | J1: 2029 | K1: 2030 | L1: 2031 | M1: 2032 | N1: 2033 | O1: 2034 | P1: 2035 | Q1: 2036 | R1: 2037 | S1: 2038 | T1: 2039 | U1: 2040 | V1: 2041 | W1: 2042 | X1: 2043 | Y1: 2044 | Z1: 2045 | AA1: 2046 | AB1: 2047 | AC1: 2048 | AD1: 2049 | AE1: 2050
C3: Report | D3: Annual Energy Outlook 2023
C4: Scenario | D4: ref2023 | G4: Reference
C5: Datekey | D5: d020623a
C6: Release Date | E6: March 2023
A10: SUP000 | B10: 1. Total Energy Supply, Disposition, and Price Summary | AF10: Average
B11: (quadrillion Btu, unless otherwise noted) | AF11: Annual
AF12: Change
B13: Supply, Disposition, and Prices | C13: 2022 | D13: 2023 | E13: 2024 | F13: 2025 | G13: 2026 | H13: 2027 | I13: 2028 | J13: 2029 | K13: 2030 | L13: 2031 | M13: 2032 | N13: 2033 | O13: 2034 | P13: 2035 | Q13: 2036 | R13: 2037 | S13: 2038 | T13: 2039 | U13: 2040 | V13: 2041 | W13: 2042 | X13: 2043 | Y13: 2044 | Z13: 2045 | AA13: 2046 | AB13: 2047 | AC13: 2048 | AD13: 2049 | AE13: 2050 | AF13: 2022–2050
B15: Production
A16: SUP000:ba_CrudeOilLease | B16: Crude Oil and Lease Condensate | C16: 24.586992 | D16: 25.571161 | E16: 26.28504 | F16: 26.689157 | G16: 27.061613 | H16: 27.276854 | I16: 27.645002 | J16: 27.607613 | K16: 27.657637 | L16: 27.504726 | M16: 27.566185 | N16: 27.626516 | O16: 27.525274 | P16: 27.454479 | Q16: 27.324806 | R16: 27.286285 | S16: 27.180134 | T16: 27.06955 | U16: 26.857201 | V16: 26.565493 | W16: 26.618496 | X16: 26.76222 | Y16: 27.042204 | Z16: 27.108969 | AA16: 27.167717 | AB16: 26.948446 | AC16: 27.031092 | AD16: 27.320032 | AE16: 27.390823 | AF16: 0.003864
A17: SUP000:ba_NaturalGasPla | B17: Natural Gas Plant Liquids | C17: 7.768493 | D17: 8.169656 | E17: 8.33212 | F17: 8.311151 | G17: 8.472385 | H17: 8.339916 | I17: 8.228629 | J17: 8.126106 | K17: 8.05903 | L17: 8.040661 | M17: 8.113167 | N17: 8.167894 | O17: 8.280707 | P17: 8.339736 | Q17: 8.463762 | R17: 8.517173 | S17: 8.518053 | T17: 8.645661 | U17: 8.632603 | V17: 8.691146 | W17: 8.843096 | X17: 8.967008 | Y17: 9.032116 | Z17: 9.079972 | AA17: 9.143809 | AB17: 9.19521 | AC17: 9.236042 | AD17: 9.282736 | AE17: 9.310446 | AF17: 0.006487
A18: SUP000:ba_DryNaturalGas | B18: Dry Natural Gas | C18: 37.814274 | D18: 37.835823 | E18: 36.882996 | F18: 37.047318 | G18: 37.522251 | H18: 37.473186 | I18: 37.786018 | J18: 38.036835 | K18: 38.406055 | L18: 38.853168 | M18: 39.378105 | N18: 39.977421 | O18: 40.490608 | P18: 40.958794 | Q18: 41.332081 | R18: 41.707432 | S18: 41.989216 | T18: 42.240601 | U18: 42.38311 | V18: 42.506451 | W18: 42.687958 | X18: 42.804451 | Y18: 42.884609 | Z18: 43.041492 | AA18: 42.870251 | AB18: 43.082157 | AC18: 43.152935 | AD18: 43.235588 | AE18: 43.621796 | AF18: 0.005116
A19: SUP000:ba_Coal | B19: Coal 1/ | C19: 11.789563 | D19: 11.071955 | E19: 12.067057 | F19: 11.332017 | G19: 10.370732 | H19: 9.303524 | I19: 8.355421 | J19: 7.463985 | K19: 7.094864 | L19: 7.063365 | M19: 7.113411 | N19: 7.082268 | O19: 7.01697 | P19: 7.068785 | Q19: 6.985933 | R19: 6.801968 | S19: 6.692012 | T19: 6.533113 | U19: 6.437759 | V19: 6.442639 | W19: 6.454122 | X19: 6.36397 | Y19: 6.262532 | Z19: 6.188755 | AA19: 6.119871 | AB19: 6.087613 | AC19: 6.069883 | AD19: 6.032045 | AE19: 5.945596 | AF19: -0.024152
A20: SUP000:ba_NuclearPower | B20: Nuclear / Uranium 2/ | C20: 8.064654 | D20: 8.187211 | E20: 8.246629 | F20: 8.171966 | G20: 8.092857 | H20: 8.092719 | I20: 7.997469 | J20: 7.99734 | K20: 7.918744 | L20: 7.918797 | M20: 7.918885 | N20: 7.47281 | O20: 7.403218 | P20: 7.313933 | Q20: 7.145817 | R20: 7.031636 | S20: 6.837198 | T20: 6.734248 | U20: 6.533641 | V20: 6.535408 | W20: 6.538529 | X20: 6.541202 | Y20: 6.544166 | Z20: 6.544192 | AA20: 6.541663 | AB20: 6.539629 | AC20: 6.530636 | AD20: 6.531871 | AE20: 6.527707 | AF20: -0.007523
A21: SUP000:ba_Hydropower | B21: Conventional Hydroelectric Power | C21: 2.453454 | D21: 2.458462 | E21: 2.502563 | F21: 2.588684 | G21: 2.579723 | H21: 2.556826 | I21: 2.515381 | J21: 2.486196 | K21: 2.457424 | L21: 2.43646 | M21: 2.419676 | N21: 2.422381 | O21: 2.426406 | P21: 2.429998 | Q21: 2.435315 | R21: 2.423512 | S21: 2.41015 | T21: 2.386208 | U21: 2.381421 | V21: 2.366141 | W21: 2.369409 | X21: 2.362637 | Y21: 2.357599 | Z21: 2.354464 | AA21: 2.343242 | AB21: 2.336414 | AC21: 2.334075 | AD21: 2.320942 | AE21: 2.309024 | AF21: -0.002164
A22: SUP000:ba_Biomass | B22: Biomass 3/ | C22: 4.838805 | D22: 5.032741 | E22: 4.964215 | F22: 4.912142 | G22: 4.886052 | H22: 4.875721 | I22: 4.769737 | J22: 4.767001 | K22: 4.765035 | L22: 4.767915 | M22: 4.773014 | N22: 4.782948 | O22: 4.793034 | P22: 4.817472 | Q22: 4.818559 | R22: 4.826615 | S22: 4.834418 | T22: 4.844079 | U22: 4.857975 | V22: 4.892778 | W22: 4.909179 | X22: 4.92593 | Y22: 4.924026 | Z22: 4.93202 | AA22: 4.970815 | AB22: 5.019265 | AC22: 5.10552 | AD22: 5.154455 | AE22: 5.188916 | AF22: 0.002498
A23: SUP000:ba_RenewableEner | B23: Other Renewable Energy 4/ | C23: 5.622848 | D23: 6.12555 | E23: 6.742159 | F23: 8.173244 | G23: 9.907674 | H23: 11.653165 | I23: 13.154488 | J23: 14.209772 | K23: 15.128234 | L23: 15.78889 | M23: 16.442295 | N23: 17.189573 | O23: 17.791294 | P23: 18.262888 | Q23: 18.746868 | R23: 19.110622 | S23: 19.414564 | T23: 19.60931 | U23: 19.90523 | V23: 20.063116 | W23: 20.302187 | X23: 20.584305 | Y23: 20.993839 | Z23: 21.370592 | AA23: 21.805227 | AB23: 22.17202 | AC23: 22.539532 | AD23: 22.84026 | AE23: 23.283979 | AF23: 0.052057
A24: SUP000:ba_Other | B24: Other 5/ | C24: 1.82513 | D24: 1.234037 | E24: 0.928669 | F24: 0.803857 | G24: 0.909898 | H24: 0.90237 | I24: 0.841003 | J24: 0.828401 | K24: 0.836635 | L24: 0.837526 | M24: 0.71289 | N24: 0.708538 | O24: 0.71509 | P24: 0.709654 | Q24: 0.706237 | R24: 0.703952 | S24: 0.704838 | T24: 0.704036 | U24: 0.700627 | V24: 0.702727 | W24: 0.700445 | X24: 0.699926 | Y24: 0.700781 | Z24: 0.700645 | AA24: 0.677574 | AB24: 0.674621 | AC24: 0.677692 | AD24: 0.678272 | AE24: 0.675773 | AF24: -0.034862
A25: SUP000:ba_Total | B25: Total | C25: 104.76421 | D25: 105.6866 | E25: 106.95145 | F25: 108.02953 | G25: 109.80318 | H25: 110.47428 | I25: 111.29315 | J25: 111.52324 | K25: 112.32366 | L25: 113.21151 | M25: 114.43762 | N25: 115.43036 | O25: 116.4426 | P25: 117.35574 | Q25: 117.95938 | R25: 118.4092 | S25: 118.58059 | T25: 118.76679 | U25: 118.68956 | V25: 118.76591 | W25: 119.42342 | X25: 120.01164 | Y25: 120.74187 | Z25: 121.3211 | AA25: 121.64017 | AB25: 122.05538 | AC25: 122.67742 | AD25: 123.39619 | AE25: 124.25407 | AF25: 0.006112
B27: Imports
A28: SUP000:ca_CrudeOil | B28: Crude Oil | C28: 13.824968 | D28: 14.777425 | E28: 15.446031 | F28: 15.30518 | G28: 15.0045 | H28: 15.261106 | I28: 15.230433 | J28: 15.49168 | K28: 15.589063 | L28: 15.686406 | M28: 15.720078 | N28: 15.538974 | O28: 15.709466 | P28: 15.851457 | Q28: 15.843707 | R28: 15.807153 | S28: 15.874156 | T28: 15.984639 | U28: 16.045517 | V28: 16.390509 | W28: 16.327881 | X28: 16.155361 | Y28: 15.890744 | Z28: 15.766374 | AA28: 15.490686 | AB28: 15.523278 | AC28: 15.392778 | AD28: 15.059613 | AE28: 14.806977 | AF28: 0.002454
A29: SUP000:ca_PetroleumProd | B29: Petroleum and Other Liquids 6/ | C29: 4.758858 | D29: 4.839342 | E29: 4.030089 | F29: 4.034095 | G29: 4.035874 | H29: 3.992856 | I29: 3.913863 | J29: 3.837766 | K29: 3.804423 | L29: 3.806296 | M29: 3.740932 | N29: 3.718116 | O29: 3.68477 | P29: 3.681871 | Q29: 3.670537 | R29: 3.681304 | S29: 3.685072 | T29: 3.692872 | U29: 3.702409 | V29: 3.723368 | W29: 3.718675 | X29: 3.725362 | Y29: 3.717126 | Z29: 3.747543 | AA29: 3.722438 | AB29: 3.744125 | AC29: 3.816768 | AD29: 3.836668 | AE29: 3.767644 | AF29: -0.008307
A30: SUP000:ca_NaturalGas | B30: Natural Gas | C30: 2.981649 | D30: 2.808482 | E30: 2.461069 | F30: 2.35087 | G30: 2.25211 | H30: 2.184048 | I30: 2.073739 | J30: 2.040553 | K30: 2.072865 | L30: 2.06794 | M30: 2.11868 | N30: 2.137902 | O30: 2.141702 | P30: 2.125696 | Q30: 2.080384 | R30: 2.079351 | S30: 2.136969 | T30: 2.11006 | U30: 2.231398 | V30: 2.256781 | W30: 2.269709 | X30: 2.318002 | Y30: 2.40196 | Z30: 2.477401 | AA30: 2.508059 | AB30: 2.53545 | AC30: 2.582582 | AD30: 2.599269 | AE30: 2.627204 | AF30: -0.00451
A31: SUP000:ca_OtherImports | B31: Other 7/ | C31: 0.25367 | D31: 0.337121 | E31: 0.14549 | F31: 0.130841 | G31: 0.141319 | H31: 0.155275 | I31: 0.177303 | J31: 0.169148 | K31: 0.176284 | L31: 0.166932 | M31: 0.170314 | N31: 0.169336 | O31: 0.170398 | P31: 0.165942 | Q31: 0.164005 | R31: 0.163859 | S31: 0.167017 | T31: 0.16908 | U31: 0.170614 | V31: 0.166044 | W31: 0.165721 | X31: 0.163252 | Y31: 0.161465 | Z31: 0.158517 | AA31: 0.155057 | AB31: 0.154695 | AC31: 0.157649 | AD31: 0.15918 | AE31: 0.157261 | AF31: -0.016931
A32: SUP000:ca_Total | B32: Total | C32: 21.819145 | D32: 22.762371 | E32: 22.08268 | F32: 21.820986 | G32: 21.433804 | H32: 21.593285 | I32: 21.395336 | J32: 21.539146 | K32: 21.642633 | L32: 21.727573 | M32: 21.750002 | N32: 21.564329 | O32: 21.706337 | P32: 21.824965 | Q32: 21.758633 | R32: 21.731667 | S32: 21.863213 | T32: 21.956652 | U32: 22.149939 | V32: 22.536701 | W32: 22.481985 | X32: 22.361977 | Y32: 22.171295 | Z32: 22.149836 | AA32: 21.876242 | AB32: 21.957548 | AC32: 21.949778 | AD32: 21.654732 | AE32: 21.359085 | AF32: -0.000761
B34: Exports
A35: SUP000:da_Petroleum | B35: Petroleum and Other Liquids 8/ | C35: 18.53616 | D35: 19.04047 | E35: 20.328047 | F35: 20.57988 | G35: 21.071783 | H35: 21.489708 | I35: 21.636562 | J35: 21.880472 | K35: 22.202881 | L35: 22.327625 | M35: 22.464676 | N35: 22.515352 | O35: 22.756023 | P35: 22.978777 | Q35: 23.076605 | R35: 23.112068 | S35: 23.121672 | T35: 23.267797 | U35: 23.053844 | V35: 23.139196 | W35: 23.210157 | X35: 23.236942 | Y35: 23.218386 | Z35: 23.136253 | AA35: 22.799206 | AB35: 22.53091 | AC35: 22.513948 | AD35: 22.402639 | AE35: 21.931286 | AF35: 0.006025
A36: SUP000:da_NaturalGas | B36: Natural Gas | C36: 7.157014 | D36: 7.945881 | E36: 7.943815 | F36: 8.33703 | G36: 8.842743 | H36: 9.263846 | I36: 9.664758 | J36: 10.022476 | K36: 10.671082 | L36: 11.372363 | M36: 12.069704 | N36: 12.747917 | O36: 13.325287 | P36: 13.720263 | Q36: 13.973807 | R36: 14.186524 | S36: 14.301539 | T36: 14.335634 | U36: 14.360343 | V36: 14.349729 | W36: 14.358644 | X36: 14.365799 | Y36: 14.408306 | Z36: 14.392715 | AA36: 14.375298 | AB36: 14.355018 | AC36: 14.358721 | AD36: 14.323404 | AE36: 14.304577 | AF36: 0.02504
A37: SUP000:da_Coal | B37: Coal | C37: 2.154573 | D37: 2.143556 | E37: 2.779966 | F37: 2.715976 | G37: 2.848135 | H37: 2.810707 | I37: 2.822736 | J37: 2.808787 | K37: 2.810107 | L37: 2.838428 | M37: 2.89129 | N37: 2.819009 | O37: 2.79456 | P37: 2.821391 | Q37: 2.784587 | R37: 2.726998 | S37: 2.770777 | T37: 2.712615 | U37: 2.722989 | V37: 2.708216 | W37: 2.723382 | X37: 2.690624 | Y37: 2.694831 | Z37: 2.703859 | AA37: 2.688675 | AB37: 2.682404 | AC37: 2.70565 | AD37: 2.707865 | AE37: 2.723995 | AF37: 0.00841
A38: SUP000:da_Total | B38: Total | C38: 27.847746 | D38: 29.129908 | E38: 31.051828 | F38: 31.632887 | G38: 32.762661 | H38: 33.564262 | I38: 34.124054 | J38: 34.711735 | K38: 35.684071 | L38: 36.538418 | M38: 37.425667 | N38: 38.082275 | O38: 38.87587 | P38: 39.520432 | Q38: 39.834999 | R38: 40.025589 | S38: 40.193985 | T38: 40.316048 | U38: 40.137177 | V38: 40.197144 | W38: 40.292183 | X38: 40.293365 | Y38: 40.321526 | Z38: 40.232826 | AA38: 39.863178 | AB38: 39.568333 | AC38: 39.57832 | AD38: 39.43391 | AE38: 38.959858 | AF38: 0.012064
A40: SUP000:ea_Discrepancy | B40: Discrepancy 9/ | C40: -0.457861 | D40: 0.97529 | E40: 0.423643 | F40: 0.464403 | G40: 0.459312 | H40: 0.424484 | I40: 0.430447 | J40: 0.294971 | K40: 0.325535 | L40: 0.400856 | M40: 0.449509 | N40: 0.447327 | O40: 0.453705 | P40: 0.532143 | Q40: 0.48624 | R40: 0.46405 | S40: 0.455482 | T40: 0.450829 | U40: 0.450035 | V40: 0.45557 | W40: 0.44809 | X40: 0.438515 | Y40: 0.440971 | Z40: 0.547066 | AA40: 0.476925 | AB40: 0.612675 | AC40: 0.563404 | AD40: 0.513699 | AE40: 0.713924 | AF40: --
B42: Consumption
A43: SUP000:fa_PetroleumProd | B43: Petroleum and Other Liquids 10/ | C43: 36.816776 | D43: 36.981636 | E43: 36.540516 | F43: 36.38258 | G43: 36.236435 | H43: 36.093872 | I43: 35.925087 | J43: 35.71246 | K43: 35.460438 | L43: 35.244152 | M43: 35.085304 | N43: 34.948364 | O43: 34.86829 | P43: 34.774864 | Q43: 34.660748 | R43: 34.614304 | S43: 34.581387 | T43: 34.574551 | U43: 34.635841 | V43: 34.700855 | W43: 34.772816 | X43: 34.84396 | Y43: 34.938004 | Z43: 35.050571 | AA43: 35.202904 | AB43: 35.394215 | AC43: 35.548607 | AD43: 35.727844 | AE43: 35.995079 | AF43: -0.000806
A44: SUP000:fa_NaturalGas | B44: Natural Gas | C44: 33.183849 | D44: 31.975372 | E44: 30.744192 | F44: 30.454859 | G44: 30.362862 | H44: 29.860353 | I44: 29.690903 | J44: 29.540802 | K44: 29.285072 | L44: 29.002975 | M44: 28.86751 | N44: 28.778568 | O44: 28.707445 | P44: 28.712893 | Q44: 28.819685 | R44: 28.978542 | S44: 29.210226 | T44: 29.397072 | U44: 29.632147 | V44: 29.788446 | W44: 29.983868 | X44: 30.153929 | Y44: 30.279633 | Z44: 30.429348 | AA44: 30.410452 | AB44: 30.539183 | AC44: 30.747511 | AD44: 30.902693 | AE44: 31.130543 | AF44: -0.002279
A45: SUP000:fa_Coal | B45: Coal 11/ | C45: 9.694483 | D45: 9.040522 | E45: 9.411029 | F45: 8.647058 | G45: 7.516863 | H45: 6.501535 | I45: 5.529372 | J45: 4.801684 | K45: 4.396944 | L45: 4.30778 | M45: 4.272085 | N45: 4.338585 | O45: 4.299617 | P45: 4.302522 | Q45: 4.260971 | R45: 4.161004 | S45: 4.002717 | T45: 3.909357 | U45: 3.806856 | V45: 3.824085 | W45: 3.815112 | X45: 3.763251 | Y45: 3.645989 | Z45: 3.548136 | AA45: 3.463649 | AB45: 3.422932 | AC45: 3.33322 | AD45: 3.31122 | AE45: 3.208326 | AF45: -0.038723
A46: SUP000:fa_NuclearPower | B46: Nuclear / Uranium 2/ | C46: 8.064654 | D46: 8.187211 | E46: 8.246629 | F46: 8.171966 | G46: 8.092857 | H46: 8.092719 | I46: 7.997469 | J46: 7.99734 | K46: 7.918744 | L46: 7.918797 | M46: 7.918885 | N46: 7.47281 | O46: 7.403218 | P46: 7.313933 | Q46: 7.145817 | R46: 7.031636 | S46: 6.837198 | T46: 6.734248 | U46: 6.533641 | V46: 6.535408 | W46: 6.538529 | X46: 6.541202 | Y46: 6.544166 | Z46: 6.544192 | AA46: 6.541663 | AB46: 6.539629 | AC46: 6.530636 | AD46: 6.531871 | AE46: 6.527707 | AF46: -0.007523
A47: SUP000:fa_Hydropower | B47: Conventional Hydroelectric Power | C47: 2.453454 | D47: 2.458462 | E47: 2.502563 | F47: 2.588684 | G47: 2.579723 | H47: 2.556826 | I47: 2.515381 | J47: 2.486196 | K47: 2.457424 | L47: 2.43646 | M47: 2.419676 | N47: 2.422381 | O47: 2.426406 | P47: 2.429998 | Q47: 2.435315 | R47: 2.423512 | S47: 2.41015 | T47: 2.386208 | U47: 2.381421 | V47: 2.366141 | W47: 2.369409 | X47: 2.362637 | Y47: 2.357599 | Z47: 2.354464 | AA47: 2.343242 | AB47: 2.336414 | AC47: 2.334075 | AD47: 2.320942 | AE47: 2.309024 | AF47: -0.002164
A48: SUP000:fa_Biomass | B48: Biomass 12/ | C48: 3.086376 | D48: 3.275092 | E48: 3.097149 | F48: 3.077337 | G48: 3.057139 | H48: 3.045216 | I48: 3.037763 | J48: 3.031368 | K48: 3.025933 | L48: 3.025459 | M48: 3.027686 | N48: 3.034011 | O48: 3.040862 | P48: 3.052712 | Q48: 3.050264 | R48: 3.054543 | S48: 3.058388 | T48: 3.063898 | U48: 3.073415 | V48: 3.092868 | W48: 3.104291 | X48: 3.115824 | Y48: 3.11755 | Z48: 3.122586 | AA48: 3.141141 | AB48: 3.159971 | AC48: 3.182918 | AD48: 3.200994 | AE48: 3.21923 | AF48: 0.001506
A49: SUP000:fa_RenewableEner | B49: Other Renewable Energy 4/ | C49: 5.622848 | D49: 6.12555 | E49: 6.742159 | F49: 8.173244 | G49: 9.907674 | H49: 11.653165 | I49: 13.154488 | J49: 14.209772 | K49: 15.128234 | L49: 15.78889 | M49: 16.442295 | N49: 17.189573 | O49: 17.791294 | P49: 18.262888 | Q49: 18.746868 | R49: 19.110622 | S49: 19.414564 | T49: 19.60931 | U49: 19.90523 | V49: 20.063116 | W49: 20.302187 | X49: 20.584305 | Y49: 20.993839 | Z49: 21.370592 | AA49: 21.805227 | AB49: 22.17202 | AC49: 22.539532 | AD49: 22.84026 | AE49: 23.283979 | AF49: 0.052057
A50: SUP000:fa_Other | B50: Other 13/ | C50: 0.271036 | D50: 0.299924 | E50: 0.274433 | F50: 0.257492 | G50: 0.26147 | H50: 0.275129 | I50: 0.283526 | J50: 0.276055 | K50: 0.28389 | L50: 0.275291 | M50: 0.27901 | N50: 0.280792 | O50: 0.282222 | P50: 0.278324 | Q50: 0.277099 | R50: 0.277055 | S50: 0.279712 | T50: 0.281933 | U50: 0.283737 | V50: 0.278974 | W50: 0.278928 | X50: 0.276634 | Y50: 0.273885 | Z50: 0.271158 | AA50: 0.268038 | AB50: 0.26756 | AC50: 0.268972 | AD50: 0.267478 | AE50: 0.265471 | AF50: -0.000741
A51: SUP000:fa_Total | B51: Total | C51: 99.193466 | D51: 98.343773 | E51: 97.558655 | F51: 97.75322 | G51: 98.015015 | H51: 98.078819 | I51: 98.133987 | J51: 98.055679 | K51: 97.956688 | L51: 97.999809 | M51: 98.312447 | N51: 98.465088 | O51: 98.819359 | P51: 99.128128 | Q51: 99.396774 | R51: 99.65123 | S51: 99.794334 | T51: 99.956566 | U51: 100.25229 | V51: 100.6499 | W51: 101.16514 | X51: 101.64174 | Y51: 102.15067 | Z51: 102.69104 | AA51: 103.17632 | AB51: 103.83192 | AC51: 104.48547 | AD51: 105.10331 | AE51: 105.93937 | AF51: 0.002353
B53: Prices (2022 dollars per unit)
A54: SUP000:ha_WorldOilPrice | B54: Brent Spot Price (dollars per barrel) | C54: 102.13 | D54: 91.544693 | E54: 92.531395 | F54: 87.048607 | G54: 87.88282 | H54: 88.306427 | I54: 88.879097 | J54: 89.470894 | K54: 90.163071 | L54: 90.724144 | M54: 91.546387 | N54: 92.007187 | O54: 92.694916 | P54: 93.55275 | Q54: 94.142883 | R54: 94.796173 | S54: 95.331741 | T54: 95.867317 | U54: 96.392181 | V54: 96.938461 | W54: 97.381508 | X54: 97.758682 | Y54: 98.241776 | Z54: 98.596687 | AA54: 99.377373 | AB54: 99.794151 | AC54: 100.38441 | AD54: 101.06876 | AE54: 101.34071 | AF54: -0.000277
A55: SUP000:ha_ForLowSulfLit | B55: West Texas Intermediate Spot Price (dollars per barrel) | C55: 95.875999 | D55: 85.782883 | E55: 91.164047 | F55: 85.233162 | G55: 85.255096 | H55: 85.532898 | I55: 86.264732 | J55: 86.738144 | K55: 87.188271 | L55: 87.748749 | M55: 88.512123 | N55: 88.937447 | O55: 89.608727 | P55: 90.03215 | Q55: 90.825806 | R55: 91.434029 | S55: 91.807198 | T55: 92.341896 | U55: 92.759918 | V55: 93.263626 | W55: 93.719948 | X55: 94.111893 | Y55: 94.517479 | Z55: 94.856956 | AA55: 95.591454 | AB55: 96.024887 | AC55: 96.717949 | AD55: 97.444786 | AE55: 97.681374 | AF55: 0.000666
A56: SUP000:ha_GasPriceHenry | B56: Natural Gas at Henry Hub (dollars per mmBtu) | C56: 6.523997 | D56: 5.266376 | E56: 4.072381 | F56: 3.489514 | G56: 3.065508 | H56: 2.853001 | I56: 2.799904 | J56: 2.825097 | K56: 2.91248 | L56: 3.043758 | M56: 3.208004 | N56: 3.416918 | O56: 3.56943 | P56: 3.681824 | Q56: 3.694155 | R56: 3.737596 | S56: 3.866561 | T56: 3.78878 | U56: 3.938065 | V56: 4.022155 | W56: 4.014737 | X56: 3.950616 | Y56: 3.913768 | Z56: 3.910706 | AA56: 3.907083 | AB56: 3.870706 | AC56: 3.849094 | AD56: 3.783895 | AE56: 3.771015 | AF56: -0.019386
A57: SUP000:ha_CoalMinemouth | B57: Coal, Minemouth (dollars per ton) 14/ | C57: 37.847488 | D57: 37.282368 | E57: 40.075565 | F57: 40.7808 | G57: 43.636292 | H57: 47.361679 | I57: 49.855022 | J57: 50.434628 | K57: 52.797508 | L57: 55.776047 | M57: 53.310043 | N57: 53.457973 | O57: 53.443798 | P57: 53.327934 | Q57: 54.118721 | R57: 55.130642 | S57: 57.305939 | T57: 57.80991 | U57: 59.124004 | V57: 58.977062 | W57: 59.08213 | X57: 60.30798 | Y57: 61.433601 | Z57: 62.543072 | AA57: 63.485416 | AB57: 63.976109 | AC57: 64.145096 | AD57: 64.784264 | AE57: 65.411858 | AF57: 0.019733
A58: SUP000:ha_CoalMineBtu | B58: Coal, Minemouth (dollars per million Btu) 14/ | C58: 1.853989 | D58: 1.835992 | E58: 1.949069 | F58: 1.971774 | G58: 2.075296 | H58: 2.208372 | I58: 2.306122 | J58: 2.357656 | K58: 2.457956 | L58: 2.593634 | M58: 2.477518 | N58: 2.476679 | O58: 2.486898 | P58: 2.488834 | Q58: 2.523628 | R58: 2.575216 | S58: 2.63626 | T58: 2.656385 | U58: 2.708991 | V58: 2.70876 | W58: 2.716106 | X58: 2.761281 | Y58: 2.804768 | Z58: 2.847011 | AA58: 2.88458 | AB58: 2.905447 | AC58: 2.918446 | AD58: 2.943681 | AE58: 2.976179 | AF58: 0.017047
A59: SUP000:ha_CoalDelivered | B59: Coal, Delivered (dollars per million Btu) 15/ | C59: 2.326422 | D59: 2.26747 | E59: 2.266108 | F59: 2.271228 | G59: 2.283574 | H59: 2.312538 | I59: 2.349293 | J59: 2.399381 | K59: 2.446105 | L59: 2.451144 | M59: 2.441114 | N59: 2.425828 | O59: 2.431217 | P59: 2.429012 | Q59: 2.432617 | R59: 2.450752 | S59: 2.493669 | T59: 2.501265 | U59: 2.519032 | V59: 2.516981 | W59: 2.520107 | X59: 2.529351 | Y59: 2.54457 | Z59: 2.558418 | AA59: 2.576957 | AB59: 2.584111 | AC59: 2.597035 | AD59: 2.60517 | AE59: 2.631093 | AF59: 0.004405
A60: SUP000:ha_Electricity(c | B60: Electricity (cents per kilowatthour) | C60: 12.224998 | D60: 11.913273 | E60: 11.471824 | F60: 11.030275 | G60: 10.768831 | H60: 10.582514 | I60: 10.45016 | J60: 10.399552 | K60: 10.413742 | L60: 10.447019 | M60: 10.475133 | N60: 10.629589 | O60: 10.729555 | P60: 10.73074 | Q60: 10.793545 | R60: 10.871433 | S60: 10.987963 | T60: 11.078531 | U60: 11.155383 | V60: 11.217563 | W60: 11.243109 | X60: 11.258493 | Y60: 11.271253 | Z60: 11.281693 | AA60: 11.247436 | AB60: 11.196383 | AC60: 11.178801 | AD60: 11.117008 | AE60: 11.024078 | AF60: -0.003686
B63: Prices (nominal dollars per unit)
A64: SUP000:nom_ImportRACost | B64: Brent Spot Price (dollars per barrel) | C64: 102.13 | D64: 95.329002 | E64: 98.708405 | F64: 94.878891 | G64: 97.830475 | H64: 100.42555 | I64: 103.26054 | J64: 106.22783 | K64: 109.43919 | L64: 112.63979 | M64: 116.26587 | N64: 119.61838 | O64: 123.39955 | P64: 127.45785 | Q64: 131.21597 | R64: 135.08392 | S64: 138.85072 | T64: 142.6973 | U64: 146.67824 | V64: 150.81691 | W64: 154.92827 | X64: 159.09348 | Y64: 163.57149 | Z64: 167.98759 | AA64: 173.31236 | AB64: 178.17406 | AC64: 183.52431 | AD64: 189.21034 | AE64: 194.29927 | AF64: 0.023236
A65: SUP000:nom_ForLowSulfLi | B65: West Texas Intermediate Spot Price (dollars per barrel) | C65: 95.875999 | D65: 89.329002 | E65: 97.249779 | F65: 92.900146 | G65: 94.905304 | H65: 97.271385 | I65: 100.22316 | J65: 102.98327 | K65: 105.82841 | L65: 108.94564 | M65: 112.41229 | N65: 115.62741 | O65: 119.29108 | P65: 122.66132 | Q65: 126.59264 | R65: 130.29289 | S65: 133.71722 | T65: 137.44975 | U65: 141.15109 | V65: 145.09961 | W65: 149.10294 | X65: 153.15866 | Y65: 157.37058 | Z65: 161.61589 | AA65: 166.70979 | AB65: 171.44435 | AC65: 176.82123 | AD65: 182.42593 | AE65: 187.28326 | AF65: 0.024201
A66: SUP000:nom_Gas@HenryHub | B66: Natural Gas at Henry Hub (dollars per mmBtu) | C66: 6.523997 | D66: 5.48408 | E66: 4.344237 | F66: 3.803406 | G66: 3.4125 | H66: 3.244545 | I66: 3.252955 | J66: 3.354208 | K66: 3.535144 | L66: 3.779019 | M66: 4.074234 | N66: 4.442329 | O66: 4.751782 | P66: 5.016179 | Q66: 5.148898 | R66: 5.326049 | S66: 5.631648 | T66: 5.639552 | U66: 5.992483 | V66: 6.257671 | W66: 6.387211 | X66: 6.429273 | Y66: 6.516381 | Z66: 6.663004 | AA66: 6.813882 | AB66: 6.910819 | AC66: 7.036972 | AD66: 7.083812 | AE66: 7.230118 | AF66: 0.003677
A67: SUP000:nom_CoalMinemout | B67: Coal, Minemouth (dollars per ton) 14/ | C67: 37.847488 | D67: 38.823559 | E67: 42.750843 | F67: 44.449158 | G67: 48.575581 | H67: 53.861572 | I67: 57.92202 | J67: 59.880493 | K67: 64.085182 | L67: 69.249504 | M67: 67.704903 | N67: 69.50061 | O67: 71.146736 | P67: 72.654884 | Q67: 75.430458 | R67: 78.560806 | S67: 83.466125 | T67: 86.049324 | U67: 89.967934 | V67: 91.756546 | W67: 93.996201 | X67: 98.145828 | Y67: 102.28628 | Z67: 106.55997 | AA67: 110.71743 | AB67: 114.22395 | AC67: 117.27104 | AD67: 121.28231 | AE67: 125.41332 | AF67: 0.043716
A68: SUP000:nom_CoalMineBtu | B68: Coal, Minemouth (dollars per million Btu) 14/ | C68: 1.853989 | D68: 1.911889 | E68: 2.079181 | F68: 2.149142 | G68: 2.310204 | H68: 2.511448 | I68: 2.679273 | J68: 2.799219 | K68: 2.983446 | L68: 3.220161 | M68: 3.146501 | N68: 3.219926 | O68: 3.310668 | P68: 3.39083 | Q68: 3.517423 | R68: 3.669666 | S68: 3.839715 | T68: 3.953995 | U68: 4.122222 | V68: 4.21429 | W68: 4.321165 | X68: 4.493738 | Y68: 4.669909 | Z68: 4.850696 | AA68: 5.030655 | AB68: 5.187432 | AC68: 5.335547 | AD68: 5.51085 | AE68: 5.70619 | AF68: 0.040967
A69: SUP000:nom_CoalDeliverd | B69: Coal, Delivered (dollars per million Btu) 15/ | C69: 2.326422 | D69: 2.361203 | E69: 2.417383 | F69: 2.475532 | G69: 2.542057 | H69: 2.62991 | I69: 2.72943 | J69: 2.848759 | K69: 2.969062 | L69: 3.043251 | M69: 3.100267 | N69: 3.153815 | O69: 3.236543 | P69: 3.309328 | Q69: 3.390572 | R69: 3.492306 | S69: 3.63203 | T69: 3.723102 | U69: 3.833166 | V69: 3.915921 | W69: 4.009342 | X69: 4.116291 | Y69: 4.236682 | Z69: 4.358995 | AA69: 4.494166 | AB69: 4.613713 | AC69: 4.74794 | AD69: 4.877126 | AE69: 5.044562 | AF69: 0.028028
A70: SUP000:nom_Electricity | B70: Electricity (cents per kilowatthour) | C70: 12.224998 | D70: 12.405747 | E70: 12.237636 | F70: 12.022483 | G70: 11.987779 | H70: 12.034852 | I70: 12.141092 | J70: 12.347277 | K70: 12.640115 | L70: 12.970637 | M70: 13.303643 | N70: 13.81951 | O70: 14.283655 | P70: 14.619742 | Q70: 15.044 | R70: 15.49172 | S70: 16.003973 | T70: 16.490255 | U70: 16.974945 | V70: 17.452291 | W70: 17.887127 | X70: 18.322187 | Y70: 18.766512 | Z70: 19.221584 | AA70: 19.615328 | AB70: 19.990198 | AC70: 20.437254 | AD70: 20.812099 | AE70: 21.136326 | AF70: 0.019746
B72: 1/ Includes waste coal.
B73: 2/ These values represent the energy obtained from uranium when it is used in light water reactors. The total energy content of uranium
B74: is much larger, but alternative processes are required to take advantage of it.
B75: 3/ Includes grid-connected electricity from wood and wood waste; biomass, such as corn, used for liquid fuels production; and non-electric
B76: energy demand from wood. Refer to Table 17 for details on biomass use by sector.
B77: 4/ Includes grid-connected electricity from landfill gas; biogenic municipal waste; wind; photovoltaic and solar thermal sources; and
B78: non-electric energy from renewable sources, such as active and passive solar systems. Excludes electricity imports using renewable sources
B79: and nonmarketed renewable energy. See Table 17 for selected nonmarketed residential and commercial renewable energy data.
B80: 5/ Includes non-biogenic municipal waste, hydrogen, methanol, and some domestic inputs to refineries.
B81: 6/ Includes imports of finished petroleum products, unfinished oils, alcohols, ethers, blending components, and renewable fuels such as ethanol.
B82: 7/ Includes coal, coal coke (net), and electricity (net). Excludes imports of fuel used in nuclear power plants.
B83: 8/ Includes crude oil, petroleum products, ethanol, and biodiesel.
... B100: National Energy Modeling System run ref2023.d020623a. Projections: EIA, AEO2023 National Energy Modeling System run ref2023.d020623a.

Sheet AEO 2023 Table 71
B1: ref2023.d020623a | C1: 2022 | D1: 2023 | E1: 2024 | F1: 2025 | G1: 2026 | H1: 2027 | I1: 2028 | J1: 2029 | K1: 2030 | L1: 2031 | M1: 2032 | N1: 2033 | O1: 2034 | P1: 2035 | Q1: 2036 | R1: 2037 | S1: 2038 | T1: 2039 | U1: 2040 | V1: 2041 | W1: 2042 | X1: 2043 | Y1: 2044 | Z1: 2045 | AA1: 2046 | AB1: 2047 | AC1: 2048 | AD1: 2049 | AE1: 2050
C3: Report | D3: Annual Energy Outlook 2023
C4: Scenario | D4: ref2023 | G4: Reference
C5: Datekey | D5: d020623a
C6: Release Date | E6: March 2023
A10: CNV000:convert_cbob | B10: 68. Conversion Factors | AF10: Annual
A11: CNV000:convert_rbob | B11: (from physical units to million Btu) | AF11: Change
A12: CNV000:aa_PentanesPlus | AF12: 2022–2050
A13: CNV000:aa_OtherPetroleu | C13: 2022 | D13: 2023 | E13: 2024 | F13: 2025 | G13: 2026 | H13: 2027 | I13: 2028 | J13: 2029 | K13: 2030 | L13: 2031 | M13: 2032 | N13: 2033 | O13: 2034 | P13: 2035 | Q13: 2036 | R13: 2037 | S13: 2038 | T13: 2039 | U13: 2040 | V13: 2041 | W13: 2042 | X13: 2043 | Y13: 2044 | Z13: 2045 | AA13: 2046 | AB13: 2047 | AC13: 2048 | AD13: 2049 | AE13: 2050 | AF13: 2050
A14: CNV000:aa_PetrochemFeed | B14: Petroleum and Other Liquids
A15: CNV000:aa_PetroleumCoke | B15: (million Btu per barrel)
A16: CNV000:aa_ResidualFuel | B16: Asphalt and Road Oil | C16: 6.636 | D16: 6.636 | E16: 6.636 | F16: 6.636 | G16: 6.636 | H16: 6.636 | I16: 6.636 | J16: 6.636 | K16: 6.636 | L16: 6.636 | M16: 6.636 | N16: 6.636 | O16: 6.636 | P16: 6.636 | Q16: 6.636 | R16: 6.636 | S16: 6.636 | T16: 6.636 | U16: 6.636 | V16: 6.636 | W16: 6.636 | X16: 6.636 | Y16: 6.636 | Z16: 6.636 | AA16: 6.636 | AB16: 6.636 | AC16: 6.636 | AD16: 6.636 | AE16: 6.636 | AF16: 0
A17: CNV000:aa_StillGas | B17: Aviation Gasoline | C17: 5.048 | D17: 5.048 | E17: 5.048 | F17: 5.048 | G17: 5.048 | H17: 5.048 | I17: 5.048 | J17: 5.048 | K17: 5.048 | L17: 5.048 | M17: 5.048 | N17: 5.048 | O17: 5.048 | P17: 5.048 | Q17: 5.048 | R17: 5.048 | S17: 5.048 | T17: 5.048 | U17: 5.048 | V17: 5.048 | W17: 5.048 | X17: 5.048 | Y17: 5.048 | Z17: 5.048 | AA17: 5.048 | AB17: 5.048 | AC17: 5.048 | AD17: 5.048 | AE17: 5.048 | AF17: 0
A18: CNV000:aa_UnfinishOilIm | B18: Biodiesel | C18: 5.359 | D18: 5.359 | E18: 5.359 | F18: 5.359 | G18: 5.359 | H18: 5.359 | I18: 5.359 | J18: 5.359 | K18: 5.359 | L18: 5.359 | M18: 5.359 | N18: 5.359 | O18: 5.359 | P18: 5.359 | Q18: 5.359 | R18: 5.359 | S18: 5.359 | T18: 5.359 | U18: 5.359 | V18: 5.359 | W18: 5.359 | X18: 5.359 | Y18: 5.359 | Z18: 5.359 | AA18: 5.359 | AB18: 5.359 | AC18: 5.359 | AD18: 5.359 | AE18: 5.359 | AF18: 0
A19: CNV000:aa_TotalPetroleu | B19: Distillate Fuel Oil | C19: 5.825 | D19: 5.825 | E19: 5.825 | F19: 5.825 | G19: 5.825 | H19: 5.825 | I19: 5.825 | J19: 5.825 | K19: 5.825 | L19: 5.825 | M19: 5.825 | N19: 5.825 | O19: 5.825 | P19: 5.825 | Q19: 5.825 | R19: 5.825 | S19: 5.825 | T19: 5.825 | U19: 5.825 | V19: 5.825 | W19: 5.825 | X19: 5.825 | Y19: 5.825 | Z19: 5.825 | AA19: 5.825 | AB19: 5.825 | AC19: 5.825 | AD19: 5.825 | AE19: 5.825 | AF19: 0
A20: CNV000:aa_Imports | B20: Residential | C20: 5.775621 | D20: 5.775648 | E20: 5.776083 | F20: 5.776062 | G20: 5.776467 | H20: 5.777218 | I20: 5.776948 | J20: 5.776953 | K20: 5.776798 | L20: 5.776974 | M20: 5.776898 | N20: 5.77701 | O20: 5.776805 | P20: 5.776956 | Q20: 5.776839 | R20: 5.776862 | S20: 5.776748 | T20: 5.776711 | U20: 5.776654 | V20: 5.776614 | W20: 5.776632 | X20: 5.776631 | Y20: 5.776552 | Z20: 5.776594 | AA20: 5.776409 | AB20: 5.776283 | AC20: 5.77638 | AD20: 5.776386 | AE20: 5.776234 | AF20: 4e-06
A21: CNV000:aa_Exports | B21: Commercial | C21: 5.775621 | D21: 5.775648 | E21: 5.776083 | F21: 5.776062 | G21: 5.776467 | H21: 5.777218 | I21: 5.776948 | J21: 5.776953 | K21: 5.776798 | L21: 5.776974 | M21: 5.776898 | N21: 5.77701 | O21: 5.776805 | P21: 5.776956 | Q21: 5.776839 | R21: 5.776862 | S21: 5.776748 | T21: 5.776711 | U21: 5.776654 | V21: 5.776614 | W21: 5.776632 | X21: 5.776631 | Y21: 5.776552 | Z21: 5.776594 | AA21: 5.776409 | AB21: 5.776283 | AC21: 5.77638 | AD21: 5.776386 | AE21: 5.776234 | AF21: 4e-06
B22: Transportation | C22: 5.775621 | D22: 5.775648 | E22: 5.776083 | F22: 5.776062 | G22: 5.776467 | H22: 5.777218 | I22: 5.776948 | J22: 5.776953 | K22: 5.776798 | L22: 5.776974 | M22: 5.776898 | N22: 5.77701 | O22: 5.776805 | P22: 5.776956 | Q22: 5.776839 | R22: 5.776862 | S22: 5.776748 | T22: 5.776711 | U22: 5.776654 | V22: 5.776614 | W22: 5.776632 | X22: 5.776631 | Y22: 5.776552 | Z22: 5.776594 | AA22: 5.776409 | AB22: 5.776283 | AC22: 5.77638 | AD22: 5.776386 | AE22: 5.776234 | AF22: 4e-06
A23: CNV000:aa_CrudeOilProdu | B23: Industrial | C23: 5.775621 | D23: 5.775648 | E23: 5.776083 | F23: 5.776062 | G23: 5.776467 | H23: 5.777218 | I23: 5.776948 | J23: 5.776953 | K23: 5.776798 | L23: 5.776974 | M23: 5.776898 | N23: 5.77701 | O23: 5.776805 | P23: 5.776956 | Q23: 5.776839 | R23: 5.776862 | S23: 5.776748 | T23: 5.776711 | U23: 5.776654 | V23: 5.776614 | W23: 5.776632 | X23: 5.776631 | Y23: 5.776552 | Z23: 5.776594 | AA23: 5.776409 | AB23: 5.776283 | AC23: 5.77638 | AD23: 5.776386 | AE23: 5.776234 | AF23: 4e-06
A24: CNV000:aa_CrudeOilImpor | B24: Electric Power | C24: 5.775621 | D24: 5.775648 | E24: 5.776083 | F24: 5.776062 | G24: 5.776467 | H24: 5.777218 | I24: 5.776948 | J24: 5.776953 | K24: 5.776798 | L24: 5.776974 | M24: 5.776898 | N24: 5.77701 | O24: 5.776805 | P24: 5.776956 | Q24: 5.776839 | R24: 5.776862 | S24: 5.776748 | T24: 5.776711 | U24: 5.776654 | V24: 5.776614 | W24: 5.776632 | X24: 5.776631 | Y24: 5.776552 | Z24: 5.776594 | AA24: 5.776409 | AB24: 5.776283 | AC24: 5.77638 | AD24: 5.776386 | AE24: 5.776234 | AF24: 4e-06
A25: CNV000:aa_CrudeOilExpor | B25: Total Distillate | C25: 5.775621 | D25: 5.775648 | E25: 5.776083 | F25: 5.776062 | G25: 5.776467 | H25: 5.777218 | I25: 5.776948 | J25: 5.776953 | K25: 5.776799 | L25: 5.776974 | M25: 5.776899 | N25: 5.77701 | O25: 5.776805 | P25: 5.776956 | Q25: 5.776838 | R25: 5.776862 | S25: 5.776748 | T25: 5.776711 | U25: 5.776654 | V25: 5.776614 | W25: 5.776632 | X25: 5.776631 | Y25: 5.776552 | Z25: 5.776594 | AA25: 5.776409 | AB25: 5.776284 | AC25: 5.77638 | AD25: 5.776386 | AE25: 5.776234 | AF25: 4e-06
A26: CNV000:aa_NaturalGasPla | B26: Distillate Fuel Oil - Low Sulfur Diesel | C26: 5.817 | D26: 5.817 | E26: 5.817 | F26: 5.817 | G26: 5.817 | H26: 5.817 | I26: 5.817 | J26: 5.817 | K26: 5.817 | L26: 5.817 | M26: 5.817 | N26: 5.817 | O26: 5.817 | P26: 5.817 | Q26: 5.817 | R26: 5.817 | S26: 5.817 | T26: 5.817 | U26: 5.817 | V26: 5.817 | W26: 5.817 | X26: 5.817 | Y26: 5.817 | Z26: 5.817 | AA26: 5.817 | AB26: 5.817 | AC26: 5.817 | AD26: 5.817 | AE26: 5.817 | AF26: 0
B27: Distillate Fuel Oil - Ultra Low Sulfur Diesel | C27: 5.77 | D27: 5.77 | E27: 5.77 | F27: 5.77 | G27: 5.77 | H27: 5.77 | I27: 5.77 | J27: 5.77 | K27: 5.77 | L27: 5.77 | M27: 5.77 | N27: 5.77 | O27: 5.77 | P27: 5.77 | Q27: 5.77 | R27: 5.77 | S27: 5.77 | T27: 5.77 | U27: 5.77 | V27: 5.77 | W27: 5.77 | X27: 5.77 | Y27: 5.77 | Z27: 5.77 | AA27: 5.77 | AB27: 5.77 | AC27: 5.77 | AD27: 5.77 | AE27: 5.77 | AF27: 0
B28: Ethanol including denaturant | C28: 3.563 | D28: 3.563 | E28: 3.563 | F28: 3.563 | G28: 3.563 | H28: 3.563 | I28: 3.563 | J28: 3.563 | K28: 3.563 | L28: 3.563 | M28: 3.563 | N28: 3.563 | O28: 3.563 | P28: 3.563 | Q28: 3.563 | R28: 3.563 | S28: 3.563 | T28: 3.563 | U28: 3.563 | V28: 3.563 | W28: 3.563 | X28: 3.563 | Y28: 3.563 | Z28: 3.563 | AA28: 3.563 | AB28: 3.563 | AC28: 3.563 | AD28: 3.563 | AE28: 3.563 | AF28: 0
A29: CNV000:ba_Consumption | B29: E85 1/ | C29: 3.994413 | D29: 3.994413 | E29: 3.994413 | F29: 3.994413 | G29: 3.994413 | H29: 3.994413 | I29: 3.994413 | J29: 3.994413 | K29: 3.994413 | L29: 3.994413 | M29: 3.994413 | N29: 3.994413 | O29: 3.994413 | P29: 3.994413 | Q29: 3.994413 | R29: 3.994413 | S29: 3.994413 | T29: 3.994413 | U29: 3.994413 | V29: 3.994413 | W29: 3.994413 | X29: 3.994413 | Y29: 3.994413 | Z29: 3.994413 | AA29: 3.994413 | AB29: 3.994413 | AC29: 3.994413 | AD29: 3.994413 | AE29: 3.994413 | AF29: 0
A30: CNV000:ba_Utility | B30: Jet Fuel - Kerosene | C30: 5.67 | D30: 5.67 | E30: 5.67 | F30: 5.67 | G30: 5.67 | H30: 5.67 | I30: 5.67 | J30: 5.67 | K30: 5.67 | L30: 5.67 | M30: 5.67 | N30: 5.67 | O30: 5.67 | P30: 5.67 | Q30: 5.67 | R30: 5.67 | S30: 5.67 | T30: 5.67 | U30: 5.67 | V30: 5.67 | W30: 5.67 | X30: 5.67 | Y30: 5.67 | Z30: 5.67 | AA30: 5.67 | AB30: 5.67 | AC30: 5.67 | AD30: 5.67 | AE30: 5.67 | AF30: 0
A31: CNV000:ba_Nonutility | B31: Lubricants | C31: 6.065 | D31: 6.065 | E31: 6.065 | F31: 6.065 | G31: 6.065 | H31: 6.065 | I31: 6.065 | J31: 6.065 | K31: 6.065 | L31: 6.065 | M31: 6.065 | N31: 6.065 | O31: 6.065 | P31: 6.065 | Q31: 6.065 | R31: 6.065 | S31: 6.065 | T31: 6.065 | U31: 6.065 | V31: 6.065 | W31: 6.065 | X31: 6.065 | Y31: 6.065 | Z31: 6.065 | AA31: 6.065 | AB31: 6.065 | AC31: 6.065 | AD31: 6.065 | AE31: 6.065 | AF31: 0
A32: CNV000:ba_Production | B32: Motor Gasoline Average | C32: 5.051711 | D32: 5.050536 | E32: 5.049363 | F32: 5.048181 | G32: 5.046995 | H32: 5.045806 | I32: 5.044614 | J32: 5.043417 | K32: 5.042216 | L32: 5.041012 | M32: 5.039805 | N32: 5.038594 | O32: 5.037381 | P32: 5.036164 | Q32: 5.03513 | R32: 5.034097 | S32: 5.033101 | T32: 5.032113 | U32: 5.031125 | V32: 5.030226 | W32: 5.029317 | X32: 5.028415 | Y32: 5.02752 | Z32: 5.02663 | AA32: 5.025746 | AB32: 5.024862 | AC32: 5.023974 | AD32: 5.023084 | AE32: 5.0222 | AF32: -0.000209
A33: CNV000:ba_Imports | B33: Conventional Motor Gasoline | C33: 5.051239 | D33: 5.049952 | E33: 5.048665 | F33: 5.047375 | G33: 5.046085 | H33: 5.044794 | I33: 5.043502 | J33: 5.042209 | K33: 5.040914 | L33: 5.039618 | M33: 5.038322 | N33: 5.037026 | O33: 5.03573 | P33: 5.034434 | Q33: 5.033323 | R33: 5.032218 | S33: 5.03115 | T33: 5.030091 | U33: 5.029032 | V33: 5.028083 | W33: 5.027124 | X33: 5.026171 | Y33: 5.025226 | Z33: 5.024285 | AA33: 5.023351 | AB33: 5.022417 | AC33: 5.021479 | AD33: 5.020539 | AE33: 5.019606 | AF33: -0.000224
A34: CNV000:ba_Exports | B34: Reformulated Motor Gasoline | C34: 5.050956 | D34: 5.04961 | E34: 5.048264 | F34: 5.046918 | G34: 5.045574 | H34: 5.04423 | I34: 5.042888 | J34: 5.041545 | K34: 5.040203 | L34: 5.038862 | M34: 5.037521 | N34: 5.036182 | O34: 5.034844 | P34: 5.033506 | Q34: 5.032413 | R34: 5.031326 | S34: 5.030284 | T34: 5.029252 | U34: 5.028219 | V34: 5.027245 | W34: 5.026256 | X34: 5.025273 | Y34: 5.024298 | Z34: 5.023329 | AA34: 5.022367 | AB34: 5.021404 | AC34: 5.020434 | AD34: 5.019461 | AE34: 5.018494 | AF34: -0.00023
A35: CNV000:ba_CompressedNat | B35: Conventional before Blending | C35: 5.22228 | D35: 5.22228 | E35: 5.22228 | F35: 5.22228 | G35: 5.22228 | H35: 5.22228 | I35: 5.22228 | J35: 5.22228 | K35: 5.22228 | L35: 5.22228 | M35: 5.22228 | N35: 5.22228 | O35: 5.22228 | P35: 5.22228 | Q35: 5.22228 | R35: 5.22228 | S35: 5.22228 | T35: 5.22228 | U35: 5.22228 | V35: 5.22228 | W35: 5.22228 | X35: 5.22228 | Y35: 5.22228 | Z35: 5.22228 | AA35: 5.22228 | AB35: 5.22228 | AC35: 5.22228 | AD35: 5.22228 | AE35: 5.22228 | AF35: 0
B36: Reformulated before Blending | C36: 5.22228 | D36: 5.22228 | E36: 5.22228 | F36: 5.22228 | G36: 5.22228 | H36: 5.22228 | I36: 5.22228 | J36: 5.22228 | K36: 5.22228 | L36: 5.22228 | M36: 5.22228 | N36: 5.22228 | O36: 5.22228 | P36: 5.22228 | Q36: 5.22228 | R36: 5.22228 | S36: 5.22228 | T36: 5.22228 | U36: 5.22228 | V36: 5.22228 | W36: 5.22228 | X36: 5.22228 | Y36: 5.22228 | Z36: 5.22228 | AA36: 5.22228 | AB36: 5.22228 | AC36: 5.22228 | AD36: 5.22228 | AE36: 5.22228 | AF36: 0
B37: Natural Gasoline | C37: 4.638 | D37: 4.638 | E37: 4.638 | F37: 4.638 | G37: 4.638 | H37: 4.638 | I37: 4.638 | J37: 4.638 | K37: 4.638 | L37: 4.638 | M37: 4.638 | N37: 4.638 | O37: 4.638 | P37: 4.638 | Q37: 4.638 | R37: 4.638 | S37: 4.638 | T37: 4.638 | U37: 4.638 | V37: 4.638 | W37: 4.638 | X37: 4.638 | Y37: 4.638 | Z37: 4.638 | AA37: 4.638 | AB37: 4.638 | AC37: 4.638 | AD37: 4.638 | AE37: 4.638 | AF37: 0
A38: CNV000:ca_Production | B38: Other Petroleum | C38: 5.8 | D38: 5.8 | E38: 5.8 | F38: 5.8 | G38: 5.8 | H38: 5.8 | I38: 5.8 | J38: 5.8 | K38: 5.8 | L38: 5.8 | M38: 5.8 | N38: 5.8 | O38: 5.8 | P38: 5.8 | Q38: 5.8 | R38: 5.8 | S38: 5.8 | T38: 5.8 | U38: 5.8 | V38: 5.8 | W38: 5.8 | X38: 5.8 | Y38: 5.8 | Z38: 5.8 | AA38: 5.8 | AB38: 5.8 | AC38: 5.8 | AD38: 5.8 | AE38: 5.8 | AF38: 0
A39: CNV000:ca_EastoftheMiss | B39: Petrochemical Feedstocks | C39: 5.448283 | D39: 5.448283 | E39: 5.448283 | F39: 5.448283 | G39: 5.448283 | H39: 5.448283 | I39: 5.448283 | J39: 5.448283 | K39: 5.448283 | L39: 5.448283 | M39: 5.448283 | N39: 5.448283 | O39: 5.448283 | P39: 5.448283 | Q39: 5.448283 | R39: 5.448283 | S39: 5.448283 | T39: 5.448283 | U39: 5.448283 | V39: 5.448283 | W39: 5.448283 | X39: 5.448283 | Y39: 5.448283 | Z39: 5.448283 | AA39: 5.448283 | AB39: 5.448283 | AC39: 5.448283 | AD39: 5.448283 | AE39: 5.448283 | AF39: 0
A40: CNV000:ca_WestoftheMiss | B40: Petroleum Coke | C40: 6.287 | D40: 6.287 | E40: 6.287 | F40: 6.287 | G40: 6.287 | H40: 6.287 | I40: 6.287 | J40: 6.287 | K40: 6.287 | L40: 6.287 | M40: 6.287 | N40: 6.287 | O40: 6.287 | P40: 6.287 | Q40: 6.287 | R40: 6.287 | S40: 6.287 | T40: 6.287 | U40: 6.287 | V40: 6.287 | W40: 6.287 | X40: 6.287 | Y40: 6.287 | Z40: 6.287 | AA40: 6.287 | AB40: 6.287 | AC40: 6.287 | AD40: 6.287 | AE40: 6.287 | AF40: 0
A41: CNV000:ca_Consumption | B41: Residual Fuel | C41: 6.287 | D41: 6.287 | E41: 6.287 | F41: 6.287 | G41: 6.287 | H41: 6.287 | I41: 6.287 | J41: 6.287 | K41: 6.287 | L41: 6.287 | M41: 6.287 | N41: 6.287 | O41: 6.287 | P41: 6.287 | Q41: 6.287 | R41: 6.287 | S41: 6.287 | T41: 6.287 | U41: 6.287 | V41: 6.287 | W41: 6.287 | X41: 6.287 | Y41: 6.287 | Z41: 6.287 | AA41: 6.287 | AB41: 6.287 | AC41: 6.287 | AD41: 6.287 | AE41: 6.287 | AF41: 0
A42: CNV000:ca_Residentialan | B42: Still Gas | C42: 6.287 | D42: 6.287 | E42: 6.287 | F42: 6.287 | G42: 6.287 | H42: 6.287 | I42: 6.287 | J42: 6.287 | K42: 6.287 | L42: 6.287 | M42: 6.287 | N42: 6.287 | O42: 6.287 | P42: 6.287 | Q42: 6.287 | R42: 6.287 | S42: 6.287 | T42: 6.287 | U42: 6.287 | V42: 6.287 | W42: 6.287 | X42: 6.287 | Y42: 6.287 | Z42: 6.287 | AA42: 6.287 | AB42: 6.287 | AC42: 6.287 | AD42: 6.287 | AE42: 6.287 | AF42: 0
A43: CNV000:ca_Industrial | B43: Unfinished Oils | C43: 6.191736 | D43: 6.192239 | E43: 6.193067 | F43: 6.163516 | G43: 6.155307 | H43: 6.161367 | I43: 6.16242 | J43: 6.163478 | K43: 6.164545 | L43: 6.160776 | M43: 6.166696 | N43: 6.167782 | O43: 6.168875 | P43: 6.169975 | Q43: 6.171082 | R43: 6.172197 | S43: 6.173318 | T43: 6.174447 | U43: 6.175582 | V43: 6.176932 | W43: 6.178004 | X43: 6.179245 | Y43: 6.180129 | Z43: 6.181304 | AA43: 6.182486 | AB43: 6.183676 | AC43: 6.184874 | AD43: 6.18608 | AE43: 6.187586 | AF43: -2.4e-05
A44: CNV000:ca_Coking | B44: Total Petroleum Consumption | C44: 5.067464 | D44: 5.059147 | E44: 5.022825 | F44: 5.01719 | G44: 5.000348 | H44: 4.985026 | I44: 4.974782 | J44: 4.967464 | K44: 4.961115 | L44: 4.957813 | M44: 4.952669 | N44: 4.947966 | O44: 4.942125 | P44: 4.937525 | Q44: 4.932009 | R44: 4.929103 | S44: 4.927769 | T44: 4.92266 | U44: 4.920143 | V44: 4.916678 | W44: 4.910859 | X44: 4.90548 | Y44: 4.903147 | Z44: 4.901598 | AA44: 4.899264 | AB44: 4.896852 | AC44: 4.895994 | AD44: 4.893797 | AE44: 4.891023 | AF44: -0.001265
A45: CNV000:ca_ElectricPower | B45: Petroleum Product Imports | C45: 5.892745 | D45: 5.789976 | E45: 5.795176 | F45: 5.783333 | G45: 5.778988 | H45: 5.799472 | I45: 5.80944 | J45: 5.820918 | K45: 5.826458 | L45: 5.833271 | M45: 5.836474 | N45: 5.845973 | O45: 5.848357 | P45: 5.858846 | Q45: 5.855556 | R45: 5.857804 | S45: 5.858994 | T45: 5.86145 | U45: 5.860619 | V45: 5.859704 | W45: 5.858002 | X45: 5.856611 | Y45: 5.854544 | Z45: 5.854034 | AA45: 5.846951 | AB45: 5.844751 | AC45: 5.839046 | AD45: 5.836578 | AE45: 5.833464 | AF45: -0.000361
A46: CNV000:ca_Imports | B46: Petroleum Product Exports | C46: 5.045286 | D46: 5.103044 | E46: 5.064793 | F46: 5.065934 | G46: 5.095077 | H46: 5.175824 | I46: 5.22638 | J46: 5.263233 | K46: 5.273697 | L46: 5.297207 | M46: 5.295012 | N46: 5.294183 | O46: 5.284441 | P46: 5.28901 | Q46: 5.274773 | R46: 5.276637 | S46: 5.279346 | T46: 5.27027 | U46: 5.2766 | V46: 5.276398 | W46: 5.263596 | X46: 5.257178 | Y46: 5.254526 | Z46: 5.25268 | AA46: 5.250132 | AB46: 5.249116 | AC46: 5.250511 | AD46: 5.251673 | AE46: 5.252563 | AF46: 0.001439
A47: CNV000:ca_Exports | B47: Crude Oil
A48: CNV000:ca_CoaltoLiquids | B48: Production | C48: 5.694899 | D48: 5.687719 | E48: 5.684641 | F48: 5.685889 | G48: 5.685311 | H48: 5.685627 | I48: 5.691115 | J48: 5.691816 | K48: 5.692057 | L48: 5.691126 | M48: 5.689834 | N48: 5.688972 | O48: 5.687781 | P48: 5.686316 | Q48: 5.68428 | R48: 5.682676 | S48: 5.680431 | T48: 5.678968 | U48: 5.676489 | V48: 5.672715 | W48: 5.67099 | X48: 5.670876 | Y48: 5.671312 | Z48: 5.670749 | AA48: 5.669248 | AB48: 5.665374 | AC48: 5.668751 | AD48: 5.669958 | AE48: 5.66872 | AF48: -0.000165
A49: CNV000:ca_WasteCoal | B49: Imports | C49: 6.037077 | D49: 5.997051 | E49: 6.035549 | F49: 6.040228 | G49: 6.057789 | H49: 6.049477 | I49: 6.061068 | J49: 6.060353 | K49: 6.06164 | L49: 6.070837 | M49: 6.079952 | N49: 6.078108 | O49: 6.089023 | P49: 6.089758 | Q49: 6.089698 | R49: 6.099061 | S49: 6.098973 | T49: 6.099608 | U49: 6.101254 | V49: 6.098327 | W49: 6.097382 | X49: 6.101766 | Y49: 6.104531 | Z49: 6.105972 | AA49: 6.100702 | AB49: 6.100448 | AC49: 6.09999 | AD49: 6.100516 | AE49: 6.10035 | AF49: 0.000372
B50: Exports | C50: 5.572606 | D50: 5.597443 | E50: 5.595406 | F50: 5.595317 | G50: 5.595244 | H50: 5.595073 | I50: 5.594945 | J50: 5.594821 | K50: 5.594671 | L50: 5.594597 | M50: 5.594531 | N50: 5.59447 | O50: 5.594379 | P50: 5.594272 | Q50: 5.59422 | R50: 5.594141 | S50: 5.594086 | T50: 5.593991 | U50: 5.593964 | V50: 5.593852 | W50: 5.593757 | X50: 5.593641 | Y50: 5.593558 | Z50: 5.59345 | AA50: 5.593437 | AB50: 5.593347 | AC50: 5.594541 | AD50: 5.593982 | AE50: 5.593036 | AF50: 0.000131
B51: Natural Gas Plant Liquids | C51: 3.565097 | D51: 3.554502 | E51: 3.549132 | F51: 3.54179 | G51: 3.539737 | H51: 3.540236 | I51: 3.541674 | J51: 3.54206 | K51: 3.541894 | L51: 3.541105 | M51: 3.540758 | N51: 3.540197 | O51: 3.538921 | P51: 3.537422 | Q51: 3.537616 | R51: 3.538247 | S51: 3.537914 | T51: 3.537523 | U51: 3.53428 | V51: 3.532229 | W51: 3.52957 | X51: 3.528002 | Y51: 3.528308 | Z51: 3.528638 | AA51: 3.52914 | AB51: 3.529557 | AC51: 3.530749 | AD51: 3.531657 | AE51: 3.53116 | AF51: -0.000342
A53: CNV000:da_Electricity | B53: Natural Gas (thousand Btu per cubic foot)
A54: CNV000:fossil_hr_us | B54: Consumption | C54: 1.037 | D54: 1.037 | E54: 1.037 | F54: 1.037 | G54: 1.037 | H54: 1.037 | I54: 1.037 | J54: 1.037 | K54: 1.037 | L54: 1.037 | M54: 1.037 | N54: 1.037 | O54: 1.037 | P54: 1.037 | Q54: 1.037 | R54: 1.037 | S54: 1.037 | T54: 1.037 | U54: 1.037 | V54: 1.037 | W54: 1.037 | X54: 1.037 | Y54: 1.037 | Z54: 1.037 | AA54: 1.037 | AB54: 1.037 | AC54: 1.037 | AD54: 1.037 | AE54: 1.037 | AF54: 0
B55: Electric Power Sector 2/ | C55: 1.034 | D55: 1.034 | E55: 1.034 | F55: 1.034 | G55: 1.034 | H55: 1.034 | I55: 1.034 | J55: 1.034 | K55: 1.034 | L55: 1.034 | M55: 1.034 | N55: 1.034 | O55: 1.034 | P55: 1.034 | Q55: 1.034 | R55: 1.034 | S55: 1.034 | T55: 1.034 | U55: 1.034 | V55: 1.034 | W55: 1.034 | X55: 1.034 | Y55: 1.034 | Z55: 1.034 | AA55: 1.034 | AB55: 1.034 | AC55: 1.034 | AD55: 1.034 | AE55: 1.034 | AF55: 0
B56: End-use Sector | C56: 1.039 | D56: 1.039 | E56: 1.039 | F56: 1.039 | G56: 1.039 | H56: 1.039 | I56: 1.039 | J56: 1.039 | K56: 1.039 | L56: 1.039 | M56: 1.039 | N56: 1.039 | O56: 1.039 | P56: 1.039 | Q56: 1.039 | R56: 1.039 | S56: 1.039 | T56: 1.039 | U56: 1.039 | V56: 1.039 | W56: 1.039 | X56: 1.039 | Y56: 1.039 | Z56: 1.039 | AA56: 1.039 | AB56: 1.039 | AC56: 1.039 | AD56: 1.039 | AE56: 1.039 | AF56: 0
B57: Production | C57: 1.037 | D57: 1.037 | E57: 1.037 | F57: 1.037 | G57: 1.037 | H57: 1.037 | I57: 1.037 | J57: 1.037 | K57: 1.037 | L57: 1.037 | M57: 1.037 | N57: 1.037 | O57: 1.037 | P57: 1.037 | Q57: 1.037 | R57: 1.037 | S57: 1.037 | T57: 1.037 | U57: 1.037 | V57: 1.037 | W57: 1.037 | X57: 1.037 | Y57: 1.037 | Z57: 1.037 | AA57: 1.037 | AB57: 1.037 | AC57: 1.037 | AD57: 1.037 | AE57: 1.037 | AF57: 0
B58: Imports | C58: 1.025 | D58: 1.025 | E58: 1.025 | F58: 1.025 | G58: 1.025 | H58: 1.025 | I58: 1.025 | J58: 1.025 | K58: 1.025 | L58: 1.025 | M58: 1.025 | N58: 1.025 | O58: 1.025 | P58: 1.025 | Q58: 1.025 | R58: 1.025 | S58: 1.025 | T58: 1.025 | U58: 1.025 | V58: 1.025 | W58: 1.025 | X58: 1.025 | Y58: 1.025 | Z58: 1.025 | AA58: 1.025 | AB58: 1.025 | AC58: 1.025 | AD58: 1.025 | AE58: 1.025 | AF58: 0
B59: Exports | C59: 1.009 | D59: 1.009 | E59: 1.009 | F59: 1.009 | G59: 1.009 | H59: 1.009 | I59: 1.009 | J59: 1.009 | K59: 1.009 | L59: 1.009 | M59: 1.009 | N59: 1.009 | O59: 1.009 | P59: 1.009 | Q59: 1.009 | R59: 1.009 | S59: 1.009 | T59: 1.009 | U59: 1.009 | V59: 1.009 | W59: 1.009 | X59: 1.009 | Y59: 1.009 | Z59: 1.009 | AA59: 1.009 | AB59: 1.009 | AC59: 1.009 | AD59: 1.009 | AE59: 1.009 | AF59: 0
B60: Compressed/Liquefied Natural Gas | C60: 0.96 | D60: 0.96 | E60: 0.96 | F60: 0.96 | G60: 0.96 | H60: 0.96 | I60: 0.96 | J60: 0.96 | K60: 0.96 | L60: 0.96 | M60: 0.96 | N60: 0.96 | O60: 0.96 | P60: 0.96 | Q60: 0.96 | R60: 0.96 | S60: 0.96 | T60: 0.96 | U60: 0.96 | V60: 0.96 | W60: 0.96 | X60: 0.96 | Y60: 0.96 | Z60: 0.96 | AA60: 0.96 | AB60: 0.96 | AC60: 0.96 | AD60: 0.96 | AE60: 0.96 | AF60: 0
B62: Coal (million Btu per short ton)
B63: Production | C63: 20.414087 | D63: 20.306387 | E63: 20.561386 | F63: 20.682283 | G63: 21.026535 | H63: 21.446421 | I63: 21.618557 | J63: 21.391855 | K63: 21.480253 | L63: 21.504978 | M63: 21.517519 | N63: 21.584536 | O63: 21.490145 | P63: 21.426874 | Q63: 21.444807 | R63: 21.408159 | S63: 21.737587 | T63: 21.762627 | U63: 21.825102 | V63: 21.77272 | W63: 21.752516 | X63: 21.840578 | Y63: 21.903273 | Z63: 21.967976 | AA63: 22.008549 | AB63: 22.019365 | AC63: 21.979197 | AD63: 22.007912 | AE63: 21.97847 | AF63: 0.002641
B64: East of the Mississippi | C64: 25.150553 | D64: 25.16258 | E64: 25.277229 | F64: 25.196438 | G64: 25.173244 | H64: 25.253006 | I64: 25.375315 | J64: 25.881294 | K64: 25.949392 | L64: 25.919323 | M64: 25.917715 | N64: 26.122444 | O64: 26.104872 | P64: 26.092716 | Q64: 26.109541 | R64: 26.115759 | S64: 26.111366 | T64: 26.064837 | U64: 26.097258 | V64: 26.119198 | W64: 26.115305 | X64: 26.109867 | Y64: 26.134989 | Z64: 26.120363 | AA64: 26.130583 | AB64: 26.147619 | AC64: 26.167906 | AD64: 26.162901 | AE64: 26.183289 | AF64: 0.001438
B65: West of the Mississippi | C65: 17.359545 | D65: 17.333267 | E65: 17.469742 | F65: 17.421644 | G65: 17.439486 | H65: 17.491636 | I65: 17.459488 | J65: 17.634378 | K65: 17.574055 | L65: 17.584854 | M65: 17.592421 | N65: 17.594152 | O65: 17.563728 | P65: 17.529621 | Q65: 17.516928 | R65: 17.304117 | S65: 17.516291 | T65: 17.500505 | U65: 17.477858 | V65: 17.479235 | W65: 17.47102 | X65: 17.484035 | Y65: 17.490488 | Z65: 17.495975 | AA65: 17.492517 | AB65: 17.48987 | AC65: 17.478798 | AD65: 17.460386 | AE65: 17.475588 | AF65: 0.000238
B66: Consumption | C66: 19.658428 | D66: 19.54789 | E66: 19.530924 | F66: 19.656338 | G66: 20.110069 | H66: 20.51845 | I66: 20.575666 | J66: 20.0931 | K66: 19.986597 | L66: 20.045502 | M66: 20.072807 | N66: 20.139336 | O66: 20.012087 | P66: 19.954887 | Q66: 19.927517 | R66: 20.046503 | S66: 20.41361 | T66: 20.439775 | U66: 20.443367 | V66: 20.372391 | W66: 20.360712 | X66: 20.399227 | Y66: 20.438107 | Z66: 20.498695 | AA66: 20.521355 | AB66: 20.524982 | AC66: 20.513655 | AD66: 20.569065 | AE66: 20.506569 | AF66: 0.00151
B67: Commercial and Institutional | C67: 18.006001 | D67: 18.076195 | E67: 18.050531 | F67: 17.893633 | G67: 17.823393 | H67: 17.884933 | I67: 17.960043 | J67: 18.007738 | K67: 18.045809 | L67: 18.149769 | M67: 18.107817 | N67: 18.119068 | O67: 18.106014 | P67: 18.099829 | Q67: 18.068781 | R67: 17.983765 | S67: 17.92384 | T67: 17.901514 | U67: 17.88397 | V67: 17.863047 | W67: 17.841541 | X67: 17.809853 | Y67: 17.789932 | Z67: 17.759554 | AA67: 17.740721 | AB67: 17.717068 | AC67: 17.692871 | AD67: 17.692043 | AE67: 17.690735 | AF67: -0.000631
B68: Industrial 3/ | C68: 18.783617 | D68: 18.841715 | E68: 19.240131 | F68: 19.234219 | G68: 19.213202 | H68: 19.209591 | I68: 19.205172 | J68: 19.192945 | K68: 19.182035 | L68: 19.171402 | M68: 19.160555 | N68: 19.138552 | O68: 19.129539 | P68: 19.110559 | Q68: 19.098141 | R68: 19.08354 | S68: 19.066294 | T68: 19.059637 | U68: 19.057035 | V68: 19.053011 | W68: 19.047277 | X68: 19.039465 | Y68: 19.03443 | Z68: 19.027761 | AA68: 19.017918 | AB68: 19.012091 | AC68: 19.021603 | AD68: 19.003336 | AE68: 18.998146 | AF68: 0.000406
B69: Coking | C69: 28.414658 | D69: 28.420496 | E69: 28.564054 | F69: 28.563307 | G69: 28.564709 | H69: 28.561665 | I69: 28.424852 | J69: 28.42708 | K69: 28.424328 | L69: 28.424635 | M69: 28.425568 | N69: 28.425659 | O69: 28.423475 | P69: 28.424204 | Q69: 28.424822 | R69: 28.423916 | S69: 28.423409 | T69: 28.418621 | U69: 28.418154 | V69: 28.416595 | W69: 28.418688 | X69: 28.417397 | Y69: 28.418079 | Z69: 28.415937 | AA69: 28.41695 | AB69: 28.417501 | AC69: 28.414228 | AD69: 28.414782 | AE69: 28.414515 | AF69: 0
B70: Electric Power 2/ | C70: 19.261753 | D70: 19.094007 | E70: 19.073429 | F70: 19.172199 | G70: 19.601582 | H70: 19.981222 | I70: 19.951309 | J70: 19.245697 | K70: 19.029951 | L70: 19.089005 | M70: 19.111488 | N70: 19.224411 | O70: 19.066448 | P70: 19.00494 | Q70: 18.96826 | R70: 19.093117 | S70: 19.521412 | T70: 19.550014 | U70: 19.53932 | V70: 19.461977 | W70: 19.446018 | X70: 19.485048 | Y70: 19.506826 | Z70: 19.564098 | AA70: 19.57564 | AB70: 19.57551 | AC70: 19.545101 | AD70: 19.618681 | AE70: 19.498875 | AF70: 0.000437
B71: Imports | C71: 23.859665 | D71: 23.823355 | E71: 24.306349 | F71: 24.259813 | G71: 24.157303 | H71: 24.166779 | I71: 24.34152 | J71: 24.34701 | K71: 24.354691 | L71: 24.360081 | M71: 24.36758 | N71: 24.405735 | O71: 24.413681 | P71: 24.419716 | Q71: 24.42701 | R71: 24.434261 | S71: 24.42054 | T71: 24.426121 | U71: 24.427452 | V71: 24.428066 | W71: 24.430658 | X71: 24.43626 | Y71: 24.411711 | Z71: 24.416954 | AA71: 24.419678 | AB71: 24.413704 | AC71: 24.385359 | AD71: 24.329634 | AE71: 24.333668 | AF71: 0.000703
B72: Exports | C72: 25.334827 | D72: 25.104584 | E72: 25.440268 | F72: 25.260695 | G72: 24.183857 | H72: 24.143476 | I72: 24.205839 | J72: 24.216169 | K72: 24.54221 | L72: 24.411135 | M72: 24.344088 | N72: 24.484596 | O72: 24.493073 | P72: 24.428741 | Q72: 24.565546 | R72: 24.314209 | S72: 24.333239 | T72: 24.333513 | U72: 24.421448 | V72: 24.449455 | W72: 24.400551 | X72: 24.57086 | Y72: 24.596798 | Z72: 24.58979 | AA72: 24.643402 | AB72: 24.656141 | AC72: 24.537497 | AD72: 24.472775 | AE72: 24.429749 | AF72: -0.001298
B73: Coal to Liquids | C73: -- | D73: -- | E73: -- | F73: -- | G73: -- | H73: -- | I73: -- | J73: -- | K73: -- | L73: -- | M73: -- | N73: -- | O73: -- | P73: -- | Q73: -- | R73: -- | S73: -- | T73: -- | U73: -- | V73: -- | W73: -- | X73: -- | Y73: -- | Z73: -- | AA73: -- | AB73: -- | AC73: -- | AD73: -- | AE73: -- | AF73: -- | AG73: -- | AH73: -- | AI73: -- | AJ73: -- | AK73: -- | AL73: -- | AM73: -- | AN73: -- | AO73: -- | AP73: -- | AQ73: -- | AR73: -- | AS73: -- | AT73: -- | AU73: -- | AV73: -- | AW73: -- | AX73: -- | AY73: -- | AZ73: -- | BA73: --
B74: Waste Coal | C74: 12.525999 | D74: 12.526001 | E74: 12.525999 | F74: 12.526 | G74: 12.526001 | H74: 12.526 | I74: 12.526 | J74: 12.526001 | K74: 12.526001 | L74: 12.526 | M74: 12.526 | N74: 12.525999 | O74: 12.526 | P74: 12.526 | Q74: 12.526 | R74: 12.526 | S74: 12.526 | T74: 12.526 | U74: 12.526 | V74: 12.526 | W74: 12.525999 | X74: 12.526 | Y74: 12.525999 | Z74: 12.526 | AA74: 12.526001 | AB74: 12.526001 | AC74: 12.525999 | AD74: 12.526001 | AE74: 12.526 | AF74: 0
B76: Approximate Heat Rates and Heat Content
B77: (Btu per kilowatthour)
B78: Electricity Heat Content | C78: 3412 | D78: 3412 | E78: 3412 | F78: 3412 | G78: 3412 | H78: 3412 | I78: 3412 | J78: 3412 | K78: 3412 | L78: 3412 | M78: 3412 | N78: 3412 | O78: 3412 | P78: 3412 | Q78: 3412 | R78: 3412 | S78: 3412 | T78: 3412 | U78: 3412 | V78: 3412 | W78: 3412 | X78: 3412 | Y78: 3412 | Z78: 3412 | AA78: 3412 | AB78: 3412 | AC78: 3412 | AD78: 3412 | AE78: 3412 | AF78: 0
B79: Fossil Fuel Heat Rate | C79: 8704.7637 | D79: 8578.2412 | E79: 8637.2559 | F79: 8588.4531 | G79: 8512.0645 | H79: 8435.9893 | I79: 8346.5156 | J79: 8291.6826 | K79: 8261.0889 | L79: 8271.4092 | M79: 8287.583 | N79: 8311.3779 | O79: 8325.2793 | P79: 8337.6533 | Q79: 8327.502 | R79: 8296.8252 | S79: 8242.873 | T79: 8227.127 | U79: 8192.457 | V79: 8198.7402 | W79: 8188.8389 | X79: 8173.1421 | Y79: 8166.9146 | Z79: 8150.8018 | AA79: 8133.8296 | AB79: 8130.3311 | AC79: 8101.1709 | AD79: 8098.4907 | AE79: 8065.7134 | AF79: -0.002719
B80: 1/ E85 refers to a blend of 85 percent ethanol (renewable) and 15 percent motor gasoline (nonrenewable). To address cold starting issues,
B81: the percentage of ethanol varies seasonally. The annual average ethanol content of 74% is used for these projections.
B82: 2/ Includes all electricity-only and combined-heat-and-power plants that have a regulatory status.
B83: 3/ Includes combined-heat-and-power plants that have a non-regulatory status and small on-site generating systems.
B84: Btu = British Thermal Unit.
B85: - - = Not applicable.
B86: Data source: 2022: U.S. Energy Information Administration (EIA), Short-Term Energy Outlook, November 2022 and EIA,
B87: AEO2023 National Energy Modeling System run ref2023.d020623a. Projections: EIA, AEO2023 National Energy Modeling System run ref2023.d020623a.
A135: PPC001
A141: PPC001:ba_End-UserPrice
A142: PPC001:ba_FederalTaxes
A143: PPC001:ba_StateTaxes
A144: PPC001:Diesel_Tax_Allow
A145: PPC001:ba_DistributionC
A146: PPC001:ba_WholesalePric
A149: PPC001:ca_End-UserPrice
A150: PPC001:ca_FederalTaxes
A151: PPC001:ca_StateTaxes
A152: PPC001:MoGas_Tax_Allow
A153: PPC001:ca_DistributionC
... A158: PPC001:da_FederalTaxes
A159: PPC001:da_StateTaxes | AF159: Average

Sheet AEO 2023 Table 58 Raw
A1: Table 58. Lower 48 Crude Oil Production and Wellhead Prices by Supply Region
A2: https://www.eia.gov/outlooks/aeo/data/browser/#/?id=71-AEO2023&cases=ref2023&sourcekey=0
A3: Thu Apr 13 2023 09:30:41 GMT-0400 (Eastern Daylight Time)
A4: Source: U.S. Energy Information Administration
B5: full name | C5: api key | D5: units | E5: 2021 | F5: 2022 | G5: 2023 | H5: 2024 | I5: 2025 | J5: 2026 | K5: 2027 | L5: 2028 | M5: 2029 | N5: 2030 | O5: 2031 | P5: 2032 | Q5: 2033 | R5: 2034 | S5: 2035 | T5: 2036 | U5: 2037 | V5: 2038 | W5: 2039 | X5: 2040 | Y5: 2041 | Z5: 2042 | AA5: 2043 | AB5: 2044 | AC5: 2045 | AD5: 2046 | AE5: 2047 | AF5: 2048 | AG5: 2049 | AH5: 2050 | AI5: Growth (2022-2050)
A8: Production
A9: (million barrels per day)
A10: Lower 48 Total | B10: Crude Oil: Production: Lower 48 Total: Reference case | C10: AEO.2023.REF2023.PRD_NA_NA_NA_CR_NA_L48_MILLBRLPDY.A | D10: MMb/d | F10: 11.391961 | G10: 11.911623 | H10: 12.286136 | I10: 12.405836 | J10: 12.564268 | K10: 12.638444 | L10: 12.756742 | M10: 12.72641 | N10: 12.711927 | O10: 12.640687 | P10: 12.643459 | Q10: 12.650594 | R10: 12.649631 | S10: 12.664894 | T10: 12.608809 | U10: 12.553323 | V10: 12.463748 | W10: 12.381916 | X10: 12.31338 | Y10: 12.207516 | Z10: 12.241076 | AA10: 12.313479 | AB10: 12.393143 | AC10: 12.39796 | AD10: 12.389208 | AE10: 12.286963 | AF10: 12.299672 | AG10: 12.441811 | AH10: 12.510002 | AI10: 0.003
A11: Lower 48 Onshore | B11: Crude Oil: Production: Lower 48 Onshore: Reference case | C11: AEO.2023.REF2023.PRD_NA_ONS_NA_CR_NA_L48_MILLBRLPDY.A | D11: MMb/d | F11: 9.588554 | G11: 10.055934 | H11: 10.358483 | I11: 10.399044 | J11: 10.477204 | K11: 10.4938 | L11: 10.500588 | M11: 10.464238 | N11: 10.505914 | O11: 10.499349 | P11: 10.566035 | Q11: 10.61991 | R11: 10.63835 | S11: 10.668874 | T11: 10.704992 | U11: 10.735191 | V11: 10.759776 | W11: 10.788214 | X11: 10.798835 | Y11: 10.850989 | Z11: 10.894673 | AA11: 10.890308 | AB11: 10.938 | AC11: 10.994806 | AD11: 11.054777 | AE11: 11.106519 | AF11: 11.092963 | AG11: 11.133082 | AH11: 11.17417 | AI11: 0.005
A12: East | B12: Crude Oil: Production: Lower 48 Onshore: East: Reference case | C12: AEO.2023.REF2023.PRD_NA_ONS_NA_CR_NA_EST_MILLBRLPDY.A | D12: MMb/d | F12: 0.171888 | G12: 0.225764 | H12: 0.242261 | I12: 0.257118 | J12: 0.264548 | K12: 0.268981 | L12: 0.272477 | M12: 0.273717 | N12: 0.275452 | O12: 0.277022 | P12: 0.279275 | Q12: 0.278753 | R12: 0.278364 | S12: 0.27689 | T12: 0.275561 | U12: 0.273968 | V12: 0.271229 | W12: 0.269941 | X12: 0.269826 | Y12: 0.269375 | Z12: 0.271509 | AA12: 0.273072 | AB12: 0.28428 | AC12: 0.289666 | AD12: 0.292248 | AE12: 0.295728 | AF12: 0.29759 | AG12: 0.297977 | AH12: 0.298551 | AI12: 0.02
A13: Gulf Coast | B13: Crude Oil: Production: Lower 48 Onshore: Gulf Coast: Reference case | C13: AEO.2023.REF2023.PRD_NA_ONS_NA_CR_NA_GLFCT_MILLBRLPDY.A | D13: MMb/d | F13: 1.383148 | G13: 1.393971 | H13: 1.491083 | I13: 1.497238 | J13: 1.510162 | K13: 1.50666 | L13: 1.498164 | M13: 1.486872 | N13: 1.483546 | O13: 1.477908 | P13: 1.475312 | Q13: 1.480861 | R13: 1.480134 | S13: 1.489117 | T13: 1.508624 | U13: 1.520391 | V13: 1.528175 | W13: 1.537055 | X13: 1.546359 | Y13: 1.552486 | Z13: 1.562674 | AA13: 1.57283 | AB13: 1.578892 | AC13: 1.588323 | AD13: 1.60924 | AE13: 1.626181 | AF13: 1.64815 | AG13: 1.675383 | AH13: 1.697799 | AI13: 0.007
A14: Midcontinent | B14: Crude Oil: Production: Lower 48 Onshore: Midcontinent: Reference case | C14: AEO.2023.REF2023.PRD_NA_ONS_NA_CR_NA_MDCN_MILLBRLPDY.A | D14: MMb/d | F14: 0.526722 | G14: 0.511171 | H14: 0.417996 | I14: 0.432177 | J14: 0.439193 | K14: 0.442596 | L14: 0.449386 | M14: 0.456035 | N14: 0.474379 | O14: 0.480582 | P14: 0.485917 | Q14: 0.493996 | R14: 0.507221 | S14: 0.525307 | T14: 0.538106 | U14: 0.544989 | V14: 0.559187 | W14: 0.573562 | X14: 0.593468 | Y14: 0.608891 | Z14: 0.611587 | AA14: 0.609151 | AB14: 0.599706 | AC14: 0.591146 | AD14: 0.579808 | AE14: 0.569749 | AF14: 0.557094 | AG14: 0.549621 | AH14: 0.537407 | AI14: 0.001
A15: Southwest | B15: Crude Oil: Production: Lower 48 Onshore: Southwest: Reference case | C15: AEO.2023.REF2023.PRD_NA_ONS_NA_CR_NA_SW_MILLBRLPDY.A | D15: MMb/d | F15: 5.304413 | G15: 5.662721 | H15: 5.683052 | I15: 5.68033 | J15: 5.657163 | K15: 5.62552 | L15: 5.596425 | M15: 5.550232 | N15: 5.533936 | O15: 5.512948 | P15: 5.484202 | Q15: 5.477047 | R15: 5.46115 | S15: 5.423452 | T15: 5.403023 | U15: 5.403068 | V15: 5.403019 | W15: 5.394019 | X15: 5.370687 | Y15: 5.389072 | Z15: 5.412901 | AA15: 5.420758 | AB15: 5.439835 | AC15: 5.473671 | AD15: 5.499067 | AE15: 5.507268 | AF15: 5.495934 | AG15: 5.510453 | AH15: 5.512559 | AI15: 0.001
A16: Rocky Mountain | B16: Crude Oil: Production: Lower 48 Onshore: Rocky Mountain: Reference case | C16: AEO.2023.REF2023.PRD_NA_ONS_NA_CR_NA_RKYMTN_MILLBRLPDY.A | D16: MMb/d | F16: 0.791088 | G16: 0.820605 | H16: 0.901864 | I16: 0.913898 | J16: 0.947742 | K16: 0.95678 | L16: 0.958889 | M16: 0.962294 | N16: 0.964335 | O16: 0.965127 | P16: 1.00554 | Q16: 1.02466 | R16: 1.034453 | S16: 1.044982 | T16: 1.054448 | U16: 1.066194 | V16: 1.076688 | W16: 1.093658 | X16: 1.102297 | Y16: 1.10769 | Z16: 1.106416 | AA16: 1.109191 | AB16: 1.14141 | AC16: 1.152717 | AD16: 1.15582 | AE16: 1.160883 | AF16: 1.164491 | AG16: 1.169268 | AH16: 1.175559 | AI16: 0.014
A17: Northern Great Plains | B17: Crude Oil: Production: Lower 48 Onshore: Northern Great Plains: Reference case | C17: AEO.2023.REF2023.PRD_NA_ONS_NA_CR_NA_NOGP_MILLBRLPDY.A | D17: MMb/d | F17: 1.11074 | G17: 1.17498 | H17: 1.346333 | I17: 1.344669 | J17: 1.383713 | K17: 1.41899 | L17: 1.451118 | M17: 1.462647 | N17: 1.503288 | O17: 1.516634 | P17: 1.567483 | Q17: 1.601777 | R17: 1.621531 | S17: 1.665682 | T17: 1.694413 | U17: 1.707527 | V17: 1.714422 | W17: 1.72256 | X17: 1.728105 | Y17: 1.74456 | Z17: 1.760825 | AA17: 1.745668 | AB17: 1.741162 | AC17: 1.752758 | AD17: 1.775987 | AE17: 1.807755 | AF17: 1.794247 | AG17: 1.799285 | AH17: 1.824435 | AI17: 0.018
A18: West Coast | B18: Crude Oil: Production: Lower 48 Onshore: West Coast: Reference case | C18: AEO.2023.REF2023.PRD_NA_ONS_NA_CR_NA_WETCOT_MILLBRLPDY.A | D18: MMb/d | F18: 0.300553 | G18: 0.266723 | H18: 0.275893 | I18: 0.273616 | J18: 0.274683 | K18: 0.274274 | L18: 0.27413 | M18: 0.272441 | N18: 0.270979 | O18: 0.269128 | P18: 0.268306 | Q18: 0.262816 | R18: 0.255498 | S18: 0.243443 | T18: 0.230817 | U18: 0.219053 | V18: 0.207056 | W18: 0.197419 | X18: 0.188092 | Y18: 0.178916 | Z18: 0.168761 | AA18: 0.159638 | AB18: 0.152716 | AC18: 0.146526 | AD18: 0.142607 | AE18: 0.138954 | AF18: 0.135458 | AG18: 0.131095 | AH18: 0.12786 | AI18: -0.03
A19: Lower 48 Offshore | B19: Crude Oil: Production: Lower 48 Offshore: Reference case | C19: AEO.2023.REF2023.PRD_NA_OFS_NA_CR_NA_L48_MILLBRLPDY.A | D19: MMb/d | F19: 1.803407 | G19: 1.855688 | H19: 1.927653 | I19: 2.006793 | J19: 2.087064 | K19: 2.144644 | L19: 2.256153 | M19: 2.262172 | N19: 2.206013 | O19: 2.141338 | P19: 2.077424 | Q19: 2.030683 | R19: 2.011281 | S19: 1.996021 | T19: 1.903816 | U19: 1.818131 | V19: 1.703971 | W19: 1.593702 | X19: 1.514545 | Y19: 1.356526 | Z19: 1.346402 | AA19: 1.423172 | AB19: 1.455143 | AC19: 1.403154 | AD19: 1.334431 | AE19: 1.180445 | AF19: 1.206709 | AG19: 1.308728 | AH19: 1.335832 | AI19: -0.011
A20: Gulf | B20: Crude Oil: Production: Lower 48 Offshore: Gulf of Mexico: Reference case | C20: AEO.2023.REF2023.PRD_NA_OFS_NA_CR_NA_GOM_MILLBRLPDY.A | D20: MMb/d | F20: 1.769407 | G20: 1.822009 | H20: 1.906318 | I20: 1.987362 | J20: 2.069212 | K20: 2.128122 | L20: 2.121645 | M20: 2.107655 | N20: 2.019549 | O20: 1.944442 | P20: 1.877414 | Q20: 1.827506 | R20: 1.803886 | S20: 1.793289 | T20: 1.700344 | U20: 1.623243 | V20: 1.526606 | W20: 1.402897 | X20: 1.327631 | Y20: 1.157386 | Z20: 1.148999 | AA20: 1.234328 | AB20: 1.257517 | AC20: 1.185771 | AD20: 1.123478 | AE20: 0.983353 | AF20: 0.915748 | AG20: 1.012054 | AH20: 1.060987 | AI20: -0.018
A21: Shallow (State) | B21: less than 200 meters | C21: Crude Oil: Production: Lower 48 Offshore: Gulf of Mexico: Shallow (State): Reference case | D21: AEO.2023.REF2023.PRD_NA_OFS_SHOF_CR_ST_GOM_MILLBRLPDY.A | E21: MMb/d | G21: 0.009697 | H21: 0.008353 | I21: 0.007345 | J21: 0.006561 | K21: 0.005934 | L21: 0.005421 | M21: 0.004993 | N21: 0.004631 | O21: 0.004321 | P21: 0.004052 | Q21: 0.003817 | R21: 0.00361 | S21: 0.003425 | T21: 0.00326 | U21: 0.003112 | V21: 0.002977 | W21: 0.002855 | X21: 0.002744 | Y21: 0.002641 | Z21: 0.002547 | AA21: 0.00246 | AB21: 0.00238 | AC21: 0.002305 | AD21: 0.002236 | AE21: 0.002171 | AF21: 0.00211 | AG21: 0.002053 | AH21: 0.002 | AI21: 0.00195 | AJ21: -0.056
A22: Shallow (Federal) | B22: less than 200 meters | C22: Crude Oil: Production: Lower 48 Offshore: Gulf of Mexico: Shallow (Federal): Reference case | D22: AEO.2023.REF2023.PRD_NA_OFS_SHOF_CR_FED_GOM_MILLBRLPDY.A | E22: MMb/d | G22: 0.085136 | H22: 0.079364 | I22: 0.072546 | J22: 0.064921 | K22: 0.058893 | L22: 0.053896 | M22: 0.049768 | N22: 0.0464 | O22: 0.04355 | P22: 0.041003 | Q22: 0.038834 | R22: 0.03687 | S22: 0.035072 | T22: 0.038409 | U22: 0.043032 | V22: 0.041975 | W22: 0.051547 | X22: 0.055216 | Y22: 0.054596 | Z22: 0.053894 | AA22: 0.05567 | AB22: 0.057559 | AC22: 0.056937 | AD22: 0.065226 | AE22: 0.069948 | AF22: 0.069535 | AG22: 0.072605 | AH22: 0.071707 | AI22: 0.072537 | AJ22: -0.006
A23: Deep (Federal) | B23: Crude Oil: Production: Lower 48 Offshore: Gulf of Mexico: Deep: Reference case | C23: AEO.2023.REF2023.PRD_NA_OFS_DPO_CR_FED_GOM_MILLBRLPDY.A | D23: MMb/d | F23: 1.674574 | G23: 1.734292 | H23: 1.826427 | I23: 1.915881 | J23: 2.004385 | K23: 2.068805 | L23: 2.066884 | M23: 2.056624 | N23: 1.971678 | O23: 1.899387 | P23: 1.834762 | Q23: 1.787026 | R23: 1.765389 | S23: 1.75162 | T23: 1.654201 | U23: 1.578291 | V23: 1.472204 | W23: 1.344937 | X23: 1.270393 | Y23: 1.100944 | Z23: 1.090869 | AA23: 1.174389 | AB23: 1.198274 | AC23: 1.118309 | AD23: 1.051359 | AE23: 0.911708 | AF23: 0.84109 | AG23: 0.938347 | AH23: 0.9865 | AI23: -0.019
A24: Pacific | B24: Crude Oil: Production: Lower 48 Offshore: Pacific: Reference case | C24: AEO.2023.REF2023.PRD_NA_OFS_NA_CR_NA_PCF_MILLBRLPDY.A | D24: MMb/d | F24: 0.034 | G24: 0.03368 | H24: 0.021335 | I24: 0.01943 | J24: 0.017852 | K24: 0.016523 | L24: 0.134508 | M24: 0.154518 | N24: 0.186464 | O24: 0.196896 | P24: 0.20001 | Q24: 0.203177 | R24: 0.207395 | S24: 0.202732 | T24: 0.203472 | U24: 0.194888 | V24: 0.177365 | W24: 0.190805 | X24: 0.186914 | Y24: 0.19914 | Z24: 0.197403 | AA24: 0.188844 | AB24: 0.197626 | AC24: 0.217383 | AD24: 0.210953 | AE24: 0.197092 | AF24: 0.290961 | AG24: 0.296674 | AH24: 0.274845 | AI24: 0.077
A25: State | B25: Crude Oil: Production: Lower 48 Offshore: Pacific: State: Reference case | C25: AEO.2023.REF2023.PRD_NA_OFS_NA_CR_ST_PCF_MILLBRLPDY.A | D25: MMb/d | F25: 0.022985 | G25: 0.020434 | H25: 0.018411 | I25: 0.016767 | J25: 0.015405 | K25: 0.014258 | L25: 0.013279 | M25: 0.012433 | N25: 0.011696 | O25: 0.011047 | P25: 0.010471 | Q25: 0.009957 | R25: 0.009495 | S25: 0.009078 | T25: 0.0087 | U25: 0.008355 | V25: 0.008039 | W25: 0.007748 | X25: 0.007481 | Y25: 0.007233 | Z25: 0.007003 | AA25: 0.006789 | AB25: 0.00659 | AC25: 0.006404 | AD25: 0.006229 | AE25: 0.006065 | AF25: 0.005911 | AG25: 0.005766 | AH25: 0.005629 | AI25: -0.049
A26: Federal | B26: Crude Oil: Production: Lower 48 Offshore: Pacific: Federal: Reference case | C26: AEO.2023.REF2023.PRD_NA_OFS_NA_CR_FED_PCF_MILLBRLPDY.A | D26: MMb/d | F26: 0.011015 | G26: 0.013245 | H26: 0.002924 | I26: 0.002663 | J26: 0.002447 | K26: 0.002264 | L26: 0.121229 | M26: 0.142084 | N26: 0.174768 | O26: 0.185849 | P26: 0.189539 | Q26: 0.19322 | R26: 0.1979 | S26: 0.193654 | T26: 0.194773 | U26: 0.186534 | V26: 0.169327 | W26: 0.183057 | X26: 0.179434 | Y26: 0.191907 | Z26: 0.1904 | AA26: 0.182055 | AB26: 0.191036 | AC26: 0.210979 | AD26: 0.204723 | AE26: 0.191027 | AF26: 0.285049 | AG26: 0.290908 | AH26: 0.269216 | AI26: 0.121
A27: Atlantic | B27: Crude Oil: Production: Lower 48 Offshore: Atlantic: Reference case | C27: AEO.2023.REF2023.PRD_NA_OFS_NA_CR_NA_ATLN_MILLBRLPDY.A | D27: MMb/d | F27: 0 | G27: 0 | H27: 0 | I27: 0 | J27: 0 | K27: 0 | L27: 0 | M27: 0 | N27: 0 | O27: 0 | P27: 0 | Q27: 0 | R27: 0 | S27: 0 | T27: 0 | U27: 0 | V27: 0 | W27: 0 | X27: 0 | Y27: 0 | Z27: 0 | AA27: 0 | AB27: 0 | AC27: 0 | AD27: 0 | AE27: 0 | AF27: 0 | AG27: 0 | AH27: 0 | AI27: - -
A28: State | B28: Crude Oil: Production: Lower 48 Offshore: Atlantic: State: Reference case | C28: AEO.2023.REF2023.PRD_NA_OFS_NA_CR_ST_ATLN_MILLBRLPDY.A | D28: MMb/d | F28: 0 | G28: 0 | H28: 0 | I28: 0 | J28: 0 | K28: 0 | L28: 0 | M28: 0 | N28: 0 | O28: 0 | P28: 0 | Q28: 0 | R28: 0 | S28: 0 | T28: 0 | U28: 0 | V28: 0 | W28: 0 | X28: 0 | Y28: 0 | Z28: 0 | AA28: 0 | AB28: 0 | AC28: 0 | AD28: 0 | AE28: 0 | AF28: 0 | AG28: 0 | AH28: 0 | AI28: - -
A29: Federal | B29: Crude Oil: Production: Lower 48 Offshore: Atlantic: Federal: Reference case | C29: AEO.2023.REF2023.PRD_NA_OFS_NA_CR_FED_ATLN_MILLBRLPDY.A | D29: MMb/d | F29: 0 | G29: 0 | H29: 0 | I29: 0 | J29: 0 | K29: 0 | L29: 0 | M29: 0 | N29: 0 | O29: 0 | P29: 0 | Q29: 0 | R29: 0 | S29: 0 | T29: 0 | U29: 0 | V29: 0 | W29: 0 | X29: 0 | Y29: 0 | Z29: 0 | AA29: 0 | AB29: 0 | AC29: 0 | AD29: 0 | AE29: 0 | AF29: 0 | AG29: 0 | AH29: 0 | AI29: - -
A30: Wellhead Prices (2022 dollars per barrel)
A31: Lower 48 Average | B31: Crude Oil: Wellhead Prices: Lower 48 Average: Reference case | C31: AEO.2023.REF2023.PRCE_NA_NA_NA_CR_WLHD_L48_Y13DLRPBBL.A | D31: 2022 $/b | F31: 93.56955 | G31: 90.688019 | H31: 89.880753 | I31: 84.382957 | J31: 85.041725 | K31: 85.383301 | L31: 86.061264 | M31: 86.621979 | N31: 87.183044 | O31: 87.73774 | P31: 88.503822 | Q31: 88.924881 | R31: 89.668983 | S31: 90.255951 | T31: 90.907585 | U31: 91.408783 | V31: 91.902 | W31: 92.410072 | X31: 92.865814 | Y31: 93.327019 | Z31: 93.728691 | AA31: 94.147247 | AB31: 94.59536 | AC31: 94.925362 | AD31: 95.628647 | AE31: 95.99221 | AF31: 96.60643 | AG31: 97.285225 | AH31: 97.564827 | AI31: 0.001
A32: Lower 48 Onshore
A33: East | B33: Crude Oil: Wellhead Prices: Lower 48 Onshore: East: Reference case | C33: AEO.2023.REF2023.PRCE_NA_ONS_NA_CR_WLHD_EST_Y13DLRPBBL.A | D33: 2022 $/b | F33: 88.857887 | G33: 99.212326 | H33: 94.988663 | I33: 89.303764 | J33: 89.54892 | K33: 89.768143 | L33: 90.547218 | M33: 91.051865 | N33: 91.577278 | O33: 92.153046 | P33: 92.960587 | Q33: 93.412354 | R33: 94.127029 | S33: 94.47036 | T33: 95.220528 | U33: 95.801323 | V33: 96.284996 | W33: 96.854927 | X33: 97.344398 | Y33: 97.794792 | Z33: 98.245575 | AA33: 98.603348 | AB33: 99.192467 | AC33: 99.519241 | AD33: 100.30509 | AE33: 100.73212 | AF33: 101.41887 | AG33: 102.11453 | AH33: 102.3551 | AI33: 0.005
A34: Gulf Coast | B34: Crude Oil: Wellhead Prices: Lower 48 Onshore: Gulf Coast: Reference case | C34: AEO.2023.REF2023.PRCE_NA_ONS_NA_CR_WLHD_GLFCT_Y13DLRPBBL.A | D34: 2022 $/b | F34: 95.68544 | G34: 95.794312 | H34: 95.883911 | I34: 90.399498 | J34: 91.131546 | K34: 91.528313 | L34: 92.118324 | M34: 92.703568 | N34: 93.309517 | O34: 93.948669 | P34: 94.75354 | Q34: 95.190857 | R34: 95.845398 | S34: 96.49588 | T34: 97.17115 | U34: 97.71431 | V34: 98.33326 | W34: 98.926674 | X34: 99.474213 | Y34: 100.06269 | Z34: 100.45379 | AA34: 100.80462 | AB34: 101.2124 | AC34: 101.61681 | AD34: 102.3689 | AE34: 102.92178 | AF34: 103.49346 | AG34: 104.01952 | AH34: 104.26901 | AI34: 0.003
A35: Midcontinent | B35: Crude Oil: Wellhead Prices: Lower 48 Onshore: Midcontinent: Reference case | C35: AEO.2023.REF2023.PRCE_NA_ONS_NA_CR_WLHD_MDCN_Y13DLRPBBL.A | D35: 2022 $/b | F35: 98.130981 | G35: 94.383713 | H35: 90.740181 | I35: 84.768532 | J35: 84.886436 | K35: 85.133736 | L35: 85.873611 | M35: 86.350456 | N35: 86.822617 | O35: 87.440727 | P35: 88.191132 | Q35: 88.665749 | R35: 89.437965 | S35: 89.86866 | T35: 90.594017 | U35: 91.177994 | V35: 91.598381 | W35: 92.125458 | X35: 92.554054 | Y35: 93.055801 | Z35: 93.488914 | AA35: 93.91423 | AB35: 94.329201 | AC35: 94.675751 | AD35: 95.389282 | AE35: 95.815422 | AF35: 96.491089 | AG35: 97.212631 | AH35: 97.388603 | AI35: 0
A36: Southwest | B36: Crude Oil: Wellhead Prices: Lower 48 Onshore: Southwest: Reference case | C36: AEO.2023.REF2023.PRCE_NA_ONS_NA_CR_WLHD_SW_Y13DLRPBBL.A | D36: 2022 $/b | F36: 93.60923 | G36: 86.461113 | H36: 86.292458 | I36: 80.893379 | J36: 81.731491 | K36: 82.064789 | L36: 82.69149 | M36: 83.278709 | N36: 83.977737 | O36: 84.534981 | P36: 85.362259 | Q36: 85.825188 | R36: 86.492241 | S36: 87.179733 | T36: 87.881134 | U36: 88.41288 | V36: 89.023674 | W36: 89.591354 | X36: 90.093422 | Y36: 90.656464 | Z36: 91.054466 | AA36: 91.388397 | AB36: 91.799225 | AC36: 92.156898 | AD36: 92.970673 | AE36: 93.36068 | AF36: 93.968765 | AG36: 94.543152 | AH36: 94.848755 | AI36: 0
A37: Rocky Mountain | B37: Crude Oil: Wellhead Prices: Lower 48 Onshore: Rocky Mountain: Reference case | C37: AEO.2023.REF2023.PRCE_NA_ONS_NA_CR_WLHD_RKYMTN_Y13DLRPBBL.A | D37: 2022 $/b | F37: 87.180954 | G37: 92.036903 | H37: 88.479485 | I37: 82.607307 | J37: 82.661804 | K37: 82.822685 | L37: 83.559486 | M37: 84.041298 | N37: 84.512459 | O37: 85.110909 | P37: 85.915985 | Q37: 86.400414 | R37: 87.534592 | S37: 87.931038 | T37: 88.644226 | U37: 89.200996 | V37: 89.598732 | W37: 90.137314 | X37: 90.58091 | Y37: 91.09137 | Z37: 91.540482 | AA37: 91.967644 | AB37: 92.4179 | AC37: 92.766388 | AD37: 93.501015 | AE37: 93.951088 | AF37: 94.641335 | AG37: 95.371826 | AH37: 95.549522 | AI37: 0.003
A38: Northern Great Plains | B38: Crude Oil: Wellhead Prices: Lower 48 Onshore: Northern Great Plains: Reference case | C38: AEO.2023.REF2023.PRCE_NA_ONS_NA_CR_WLHD_NOGP_Y13DLRPBBL.A | D38: 2022 $/b | F38: 87.180954 | G38: 92.036903 | H38: 88.479485 | I38: 82.607307 | J38: 82.661804 | K38: 82.822685 | L38: 83.559486 | M38: 84.041298 | N38: 84.512459 | O38: 85.110909 | P38: 85.915985 | Q38: 86.400414 | R38: 87.534592 | S38: 87.931038 | T38: 88.644226 | U38: 89.200996 | V38: 89.598732 | W38: 90.137314 | X38: 90.58091 | Y38: 91.09137 | Z38: 91.540482 | AA38: 91.967644 | AB38: 92.4179 | AC38: 92.766388 | AD38: 93.501015 | AE38: 93.951088 | AF38: 94.641335 | AG38: 95.371826 | AH38: 95.549522 | AI38: 0.003
A39: West Coast | B39: Crude Oil: Wellhead Prices: Lower 48 Onshore: West Coast: Reference case | C39: AEO.2023.REF2023.PRCE_NA_ONS_NA_CR_WLHD_WETCOT_Y13DLRPBBL.A | D39: 2022 $/b | F39: 100.23714 | G39: 94.045677 | H39: 95.09832 | I39: 89.280617 | J39: 89.667526 | K39: 90.015343 | L39: 90.526176 | M39: 90.989204 | N39: 91.176765 | O39: 91.68502 | P39: 92.435165 | Q39: 92.69014 | R39: 93.147789 | S39: 93.708275 | T39: 94.256104 | U39: 94.817665 | V39: 95.323364 | W39: 96.041557 | X39: 96.44149 | Y39: 97.234436 | Z39: 97.643051 | AA39: 98.205544 | AB39: 99.080917 | AC39: 99.543686 | AD39: 99.042709 | AE39: 99.467789 | AF39: 99.620308 | AG39: 100.3074 | AH39: 100.51384 | AI39: 0
A40: Lower 48 Offshore
A41: Gulf | B41: Crude Oil: Wellhead Prices: Lower 48 Offshore: Gulf: Reference case | C41: AEO.2023.REF2023.PRCE_NA_OFS_NA_CR_WLHD_GOM_Y13DLRPBBL.A | D41: 2022 $/b | F41: 97.072922 | G41: 95.794312 | H41: 95.883911 | I41: 90.399498 | J41: 91.131546 | K41: 91.528313 | L41: 92.118324 | M41: 92.703568 | N41: 93.309517 | O41: 93.948669 | P41: 94.75354 | Q41: 95.190857 | R41: 95.845398 | S41: 96.49588 | T41: 97.17115 | U41: 97.71431 | V41: 98.33326 | W41: 98.926674 | X41: 99.474213 | Y41: 100.06269 | Z41: 100.45379 | AA41: 100.80462 | AB41: 101.2124 | AC41: 101.61681 | AD41: 102.3689 | AE41: 102.92178 | AF41: 103.49346 | AG41: 104.01952 | AH41: 104.26901 | AI41: 0.003
A42: Pacific | B42: Crude Oil: Wellhead Prices: Lower 48 Offshore: Pacific: Reference case | C42: AEO.2023.REF2023.PRCE_NA_OFS_NA_CR_WLHD_PCF_Y13DLRPBBL.A | D42: 2022 $/b | F42: 70.551292 | G42: 94.045677 | H42: 95.09832 | I42: 89.280617 | J42: 89.667526 | K42: 90.015343 | L42: 90.526176 | M42: 90.989204 | N42: 91.176765 | O42: 91.68502 | P42: 92.435165 | Q42: 92.69014 | R42: 93.147789 | S42: 93.708275 | T42: 94.256104 | U42: 94.817665 | V42: 95.323364 | W42: 96.041557 | X42: 96.44149 | Y42: 97.234436 | Z42: 97.643051 | AA42: 98.205544 | AB42: 99.080917 | AC42: 99.543686 | AD42: 99.042709 | AE42: 99.467789 | AF42: 99.620308 | AG42: 100.3074 | AH42: 100.51384 | AI42: 0.013
A43: Atlantic | B43: Crude Oil: Wellhead Prices: Lower 48 Offshore: Atlantic: Reference case | C43: AEO.2023.REF2023.PRCE_NA_OFS_NA_CR_WLHD_ATLN_Y13DLRPBBL.A | D43: 2022 $/b | F43: 0 | G43: 95.169678 | H43: 93.930977 | I43: 88.551704 | J43: 89.145035 | K43: 89.56546 | L43: 90.069565 | M43: 90.752197 | N43: 91.383827 | O43: 91.704681 | P43: 92.557144 | Q43: 92.936287 | R43: 93.634666 | S43: 94.611748 | T43: 95.246399 | U43: 95.927979 | V43: 96.400688 | W43: 96.986427 | X43: 97.520164 | Y43: 97.897842 | Z43: 98.306686 | AA43: 98.543892 | AB43: 99.086693 | AC43: 99.2836 | AD43: 100.08094 | AE43: 100.54139 | AF43: 101.20822 | AG43: 101.78192 | AH43: 102.01014 | AI43: - -

Sheet AEO 2023 Table 58
B1: ref2022.d011222a | C1: 2022 | D1: 2023 | E1: 2024 | F1: 2025 | G1: 2026 | H1: 2027 | I1: 2028 | J1: 2029 | K1: 2030 | L1: 2031 | M1: 2032 | N1: 2033 | O1: 2034 | P1: 2035 | Q1: 2036 | R1: 2037 | S1: 2038 | T1: 2039 | U1: 2040 | V1: 2041 | W1: 2042 | X1: 2043 | Y1: 2044 | Z1: 2045 | AA1: 2046 | AB1: 2047 | AC1: 2048 | AD1: 2049 | AE1: 2050
C3: Report | D3: Annual Energy Outlook 2022
C4: Scenario | D4: ref2022 | G4: Reference
C5: Datekey | D5: d011222a
C6: Release Date | E6: March 2022
A10: COP000 | B10: 58. Lower 48 Crude Oil Production and Wellhead Prices by Supply Region | AF10: Average
AF11: Annual
AF12: Change
B13: Region | C13: 2022 | D13: 2023 | E13: 2024 | F13: 2025 | G13: 2026 | H13: 2027 | I13: 2028 | J13: 2029 | K13: 2030 | L13: 2031 | M13: 2032 | N13: 2033 | O13: 2034 | P13: 2035 | Q13: 2036 | R13: 2037 | S13: 2038 | T13: 2039 | U13: 2040 | V13: 2041 | W13: 2042 | X13: 2043 | Y13: 2044 | Z13: 2045 | AA13: 2046 | AB13: 2047 | AC13: 2048 | AD13: 2049 | AE13: 2050 | AF13: 2021–2050
B15: Production 1/
B16: (million barrels per day) | C16: =C17*10^6*'AEO 2023 Table 71'!C48*10^6*365 -> 2.3679765e+16 | D16: =D17*10^6*'AEO 2023 Table 71'!D48*10^6*365 -> 2.4728737e+16 | E16: =E17*10^6*'AEO 2023 Table 71'!E48*10^6*365 -> 2.5492429e+16 | F16: =F17*10^6*'AEO 2023 Table 71'!F48*10^6*365 -> 2.5746445e+16 | G16: =G17*10^6*'AEO 2023 Table 71'!G48*10^6*365 -> 2.6072596e+16 | H16: =H17*10^6*'AEO 2023 Table 71'!H48*10^6*365 -> 2.622798e+16 | I16: =I17*10^6*'AEO 2023 Table 71'!I48*10^6*365 -> 2.6499031e+16 | J16: =J17*10^6*'AEO 2023 Table 71'!J48*10^6*365 -> 2.643928e+16 | ... AE16: =AE17*10^6*'AEO 2023 Table 71'!AE48*10^6*365 -> 2.588423e+16
A17: COP000:ba_Lower48Total | B17: Lower 48 Total | C17: ='AEO 2023 Table 58 Raw'!F10 -> 11.391961 | D17: ='AEO 2023 Table 58 Raw'!G10 -> 11.911623 | E17: ='AEO 2023 Table 58 Raw'!H10 -> 12.286136 | F17: ='AEO 2023 Table 58 Raw'!I10 -> 12.405836 | G17: ='AEO 2023 Table 58 Raw'!J10 -> 12.564268 | H17: ='AEO 2023 Table 58 Raw'!K10 -> 12.638444 | I17: ='AEO 2023 Table 58 Raw'!L10 -> 12.756742 | J17: ='AEO 2023 Table 58 Raw'!M10 -> 12.72641 | ... AF17: ='AEO 2023 Table 58 Raw'!AI10 -> 0.003
A19: COP000:ca_Low48Onshore | B19: Lower 48 Onshore | C19: ='AEO 2023 Table 58 Raw'!F11 -> 9.588554 | D19: ='AEO 2023 Table 58 Raw'!G11 -> 10.055934 | E19: ='AEO 2023 Table 58 Raw'!H11 -> 10.358483 | F19: ='AEO 2023 Table 58 Raw'!I11 -> 10.399044 | G19: ='AEO 2023 Table 58 Raw'!J11 -> 10.477204 | H19: ='AEO 2023 Table 58 Raw'!K11 -> 10.4938 | I19: ='AEO 2023 Table 58 Raw'!L11 -> 10.500588 | J19: ='AEO 2023 Table 58 Raw'!M11 -> 10.464238 | ... AF19: ='AEO 2023 Table 58 Raw'!AI11 -> 0.005
A20: COP000:ca_Northeast | B20: East | C20: ='AEO 2023 Table 58 Raw'!F12 -> 0.171888 | D20: ='AEO 2023 Table 58 Raw'!G12 -> 0.225764 | E20: ='AEO 2023 Table 58 Raw'!H12 -> 0.242261 | F20: ='AEO 2023 Table 58 Raw'!I12 -> 0.257118 | G20: ='AEO 2023 Table 58 Raw'!J12 -> 0.264548 | H20: ='AEO 2023 Table 58 Raw'!K12 -> 0.268981 | I20: ='AEO 2023 Table 58 Raw'!L12 -> 0.272477 | J20: ='AEO 2023 Table 58 Raw'!M12 -> 0.273717 | ... AF20: ='AEO 2023 Table 58 Raw'!AI12 -> 0.02
A21: COP000:ca_GulfCoast | B21: Gulf Coast | C21: ='AEO 2023 Table 58 Raw'!F13 -> 1.383148 | D21: ='AEO 2023 Table 58 Raw'!G13 -> 1.393971 | E21: ='AEO 2023 Table 58 Raw'!H13 -> 1.491083 | F21: ='AEO 2023 Table 58 Raw'!I13 -> 1.497238 | G21: ='AEO 2023 Table 58 Raw'!J13 -> 1.510162 | H21: ='AEO 2023 Table 58 Raw'!K13 -> 1.50666 | I21: ='AEO 2023 Table 58 Raw'!L13 -> 1.498164 | J21: ='AEO 2023 Table 58 Raw'!M13 -> 1.486872 | ... AF21: ='AEO 2023 Table 58 Raw'!AI13 -> 0.007
A22: COP000:ca_Midcontinent | B22: Midcontinent | C22: ='AEO 2023 Table 58 Raw'!F14 -> 0.526722 | D22: ='AEO 2023 Table 58 Raw'!G14 -> 0.511171 | E22: ='AEO 2023 Table 58 Raw'!H14 -> 0.417996 | F22: ='AEO 2023 Table 58 Raw'!I14 -> 0.432177 | G22: ='AEO 2023 Table 58 Raw'!J14 -> 0.439193 | H22: ='AEO 2023 Table 58 Raw'!K14 -> 0.442596 | I22: ='AEO 2023 Table 58 Raw'!L14 -> 0.449386 | J22: ='AEO 2023 Table 58 Raw'!M14 -> 0.456035 | ... AF22: ='AEO 2023 Table 58 Raw'!AI14 -> 0.001
A23: COP000:ca_Southwest | B23: Southwest | C23: ='AEO 2023 Table 58 Raw'!F15 -> 5.304413 | D23: ='AEO 2023 Table 58 Raw'!G15 -> 5.662721 | E23: ='AEO 2023 Table 58 Raw'!H15 -> 5.683052 | F23: ='AEO 2023 Table 58 Raw'!I15 -> 5.68033 | G23: ='AEO 2023 Table 58 Raw'!J15 -> 5.657163 | H23: ='AEO 2023 Table 58 Raw'!K15 -> 5.62552 | I23: ='AEO 2023 Table 58 Raw'!L15 -> 5.596425 | J23: ='AEO 2023 Table 58 Raw'!M15 -> 5.550232 | ... AF23: ='AEO 2023 Table 58 Raw'!AI15 -> 0.001
A24: COP000:ca_RockyMountain | B24: Rocky Mountain | C24: ='AEO 2023 Table 58 Raw'!F16 -> 0.791088 | D24: ='AEO 2023 Table 58 Raw'!G16 -> 0.820605 | E24: ='AEO 2023 Table 58 Raw'!H16 -> 0.901864 | F24: ='AEO 2023 Table 58 Raw'!I16 -> 0.913898 | G24: ='AEO 2023 Table 58 Raw'!J16 -> 0.947742 | H24: ='AEO 2023 Table 58 Raw'!K16 -> 0.95678 | I24: ='AEO 2023 Table 58 Raw'!L16 -> 0.958889 | J24: ='AEO 2023 Table 58 Raw'!M16 -> 0.962294 | ... AF24: ='AEO 2023 Table 58 Raw'!AI16 -> 0.014
A25: COP000:ca_NoGreatPlains | B25: Northern Great Plains | C25: ='AEO 2023 Table 58 Raw'!F17 -> 1.11074 | D25: ='AEO 2023 Table 58 Raw'!G17 -> 1.17498 | E25: ='AEO 2023 Table 58 Raw'!H17 -> 1.346333 | F25: ='AEO 2023 Table 58 Raw'!I17 -> 1.344669 | G25: ='AEO 2023 Table 58 Raw'!J17 -> 1.383713 | H25: ='AEO 2023 Table 58 Raw'!K17 -> 1.41899 | I25: ='AEO 2023 Table 58 Raw'!L17 -> 1.451118 | J25: ='AEO 2023 Table 58 Raw'!M17 -> 1.462647 | ... AF25: ='AEO 2023 Table 58 Raw'!AI17 -> 0.018
A26: COP000:ca_WestCoast | B26: West Coast | C26: ='AEO 2023 Table 58 Raw'!F18 -> 0.300553 | D26: ='AEO 2023 Table 58 Raw'!G18 -> 0.266723 | E26: ='AEO 2023 Table 58 Raw'!H18 -> 0.275893 | F26: ='AEO 2023 Table 58 Raw'!I18 -> 0.273616 | G26: ='AEO 2023 Table 58 Raw'!J18 -> 0.274683 | H26: ='AEO 2023 Table 58 Raw'!K18 -> 0.274274 | I26: ='AEO 2023 Table 58 Raw'!L18 -> 0.27413 | J26: ='AEO 2023 Table 58 Raw'!M18 -> 0.272441 | ... AF26: ='AEO 2023 Table 58 Raw'!AI18 -> -0.03
A28: COP000:da_Low48Offshore | B28: Lower 48 Offshore | C28: ='AEO 2023 Table 58 Raw'!F19 -> 1.803407 | D28: ='AEO 2023 Table 58 Raw'!G19 -> 1.855688 | E28: ='AEO 2023 Table 58 Raw'!H19 -> 1.927653 | F28: ='AEO 2023 Table 58 Raw'!I19 -> 2.006793 | G28: ='AEO 2023 Table 58 Raw'!J19 -> 2.087064 | H28: ='AEO 2023 Table 58 Raw'!K19 -> 2.144644 | I28: ='AEO 2023 Table 58 Raw'!L19 -> 2.256153 | J28: ='AEO 2023 Table 58 Raw'!M19 -> 2.262172 | ... AF28: ='AEO 2023 Table 58 Raw'!AI19 -> -0.011
A29: COP000:da_Gulf | B29: Gulf | C29: ='AEO 2023 Table 58 Raw'!F20 -> 1.769407 | D29: ='AEO 2023 Table 58 Raw'!G20 -> 1.822009 | E29: ='AEO 2023 Table 58 Raw'!H20 -> 1.906318 | F29: ='AEO 2023 Table 58 Raw'!I20 -> 1.987362 | G29: ='AEO 2023 Table 58 Raw'!J20 -> 2.069212 | H29: ='AEO 2023 Table 58 Raw'!K20 -> 2.128122 | I29: ='AEO 2023 Table 58 Raw'!L20 -> 2.121645 | J29: ='AEO 2023 Table 58 Raw'!M20 -> 2.107655 | ... AF29: ='AEO 2023 Table 58 Raw'!AI20 -> -0.018
A30: COP000:da_Shallow | B30: Shallow (State), less than 200 meters | C30: ='AEO 2023 Table 58 Raw'!F21 -> 0 | D30: ='AEO 2023 Table 58 Raw'!G21 -> 0.009697 | E30: ='AEO 2023 Table 58 Raw'!H21 -> 0.008353 | F30: ='AEO 2023 Table 58 Raw'!I21 -> 0.007345 | G30: ='AEO 2023 Table 58 Raw'!J21 -> 0.006561 | H30: ='AEO 2023 Table 58 Raw'!K21 -> 0.005934 | I30: ='AEO 2023 Table 58 Raw'!L21 -> 0.005421 | J30: ='AEO 2023 Table 58 Raw'!M21 -> 0.004993 | ... AF30: ='AEO 2023 Table 58 Raw'!AI21 -> 0.00195
A31: COP000:da_shallowfed | B31: Shallow (Federal), less than 200 meters | C31: ='AEO 2023 Table 58 Raw'!F22 -> 0 | D31: ='AEO 2023 Table 58 Raw'!G22 -> 0.085136 | E31: ='AEO 2023 Table 58 Raw'!H22 -> 0.079364 | F31: ='AEO 2023 Table 58 Raw'!I22 -> 0.072546 | G31: ='AEO 2023 Table 58 Raw'!J22 -> 0.064921 | H31: ='AEO 2023 Table 58 Raw'!K22 -> 0.058893 | I31: ='AEO 2023 Table 58 Raw'!L22 -> 0.053896 | J31: ='AEO 2023 Table 58 Raw'!M22 -> 0.049768 | ... AF31: ='AEO 2023 Table 58 Raw'!AI22 -> 0.072537
A32: COP000:da_Deep | B32: Deep (Federal) | C32: ='AEO 2023 Table 58 Raw'!F23 -> 1.674574 | D32: ='AEO 2023 Table 58 Raw'!G23 -> 1.734292 | E32: ='AEO 2023 Table 58 Raw'!H23 -> 1.826427 | F32: ='AEO 2023 Table 58 Raw'!I23 -> 1.915881 | G32: ='AEO 2023 Table 58 Raw'!J23 -> 2.004385 | H32: ='AEO 2023 Table 58 Raw'!K23 -> 2.068805 | I32: ='AEO 2023 Table 58 Raw'!L23 -> 2.066884 | J32: ='AEO 2023 Table 58 Raw'!M23 -> 2.056624 | ... AF32: ='AEO 2023 Table 58 Raw'!AI23 -> -0.019
A33: COP000:da_Pacific | B33: Pacific | C33: ='AEO 2023 Table 58 Raw'!F24 -> 0.034 | D33: ='AEO 2023 Table 58 Raw'!G24 -> 0.03368 | E33: ='AEO 2023 Table 58 Raw'!H24 -> 0.021335 | F33: ='AEO 2023 Table 58 Raw'!I24 -> 0.01943 | G33: ='AEO 2023 Table 58 Raw'!J24 -> 0.017852 | H33: ='AEO 2023 Table 58 Raw'!K24 -> 0.016523 | I33: ='AEO 2023 Table 58 Raw'!L24 -> 0.134508 | J33: ='AEO 2023 Table 58 Raw'!M24 -> 0.154518 | ... AF33: ='AEO 2023 Table 58 Raw'!AI24 -> 0.077
A34: COP000:da_Pacificstate | B34: State | C34: ='AEO 2023 Table 58 Raw'!F25 -> 0.022985 | D34: ='AEO 2023 Table 58 Raw'!G25 -> 0.020434 | E34: ='AEO 2023 Table 58 Raw'!H25 -> 0.018411 | F34: ='AEO 2023 Table 58 Raw'!I25 -> 0.016767 | G34: ='AEO 2023 Table 58 Raw'!J25 -> 0.015405 | H34: ='AEO 2023 Table 58 Raw'!K25 -> 0.014258 | I34: ='AEO 2023 Table 58 Raw'!L25 -> 0.013279 | J34: ='AEO 2023 Table 58 Raw'!M25 -> 0.012433 | ... AF34: ='AEO 2023 Table 58 Raw'!AI25 -> -0.049
A35: COP000:da_Pacificfed | B35: Federal | C35: ='AEO 2023 Table 58 Raw'!F26 -> 0.011015 | D35: ='AEO 2023 Table 58 Raw'!G26 -> 0.013245 | E35: ='AEO 2023 Table 58 Raw'!H26 -> 0.002924 | F35: ='AEO 2023 Table 58 Raw'!I26 -> 0.002663 | G35: ='AEO 2023 Table 58 Raw'!J26 -> 0.002447 | H35: ='AEO 2023 Table 58 Raw'!K26 -> 0.002264 | I35: ='AEO 2023 Table 58 Raw'!L26 -> 0.121229 | J35: ='AEO 2023 Table 58 Raw'!M26 -> 0.142084 | ... AF35: ='AEO 2023 Table 58 Raw'!AI26 -> 0.121
A36: COP000:da_Atlantic | B36: Atlantic | C36: ='AEO 2023 Table 58 Raw'!F27 -> 0 | D36: ='AEO 2023 Table 58 Raw'!G27 -> 0 | E36: ='AEO 2023 Table 58 Raw'!H27 -> 0 | F36: ='AEO 2023 Table 58 Raw'!I27 -> 0 | G36: ='AEO 2023 Table 58 Raw'!J27 -> 0 | H36: ='AEO 2023 Table 58 Raw'!K27 -> 0 | I36: ='AEO 2023 Table 58 Raw'!L27 -> 0 | J36: ='AEO 2023 Table 58 Raw'!M27 -> 0 | ... AF36: ='AEO 2023 Table 58 Raw'!AI27 -> - -
A37: COP000:da_Atlanticstate | B37: State | C37: ='AEO 2023 Table 58 Raw'!F28 -> 0 | D37: ='AEO 2023 Table 58 Raw'!G28 -> 0 | E37: ='AEO 2023 Table 58 Raw'!H28 -> 0 | F37: ='AEO 2023 Table 58 Raw'!I28 -> 0 | G37: ='AEO 2023 Table 58 Raw'!J28 -> 0 | H37: ='AEO 2023 Table 58 Raw'!K28 -> 0 | I37: ='AEO 2023 Table 58 Raw'!L28 -> 0 | J37: ='AEO 2023 Table 58 Raw'!M28 -> 0 | ... AF37: ='AEO 2023 Table 58 Raw'!AI28 -> - -
A38: COP000:da_Atlanticfed | B38: Federal | C38: ='AEO 2023 Table 58 Raw'!F29 -> 0 | D38: ='AEO 2023 Table 58 Raw'!G29 -> 0 | E38: ='AEO 2023 Table 58 Raw'!H29 -> 0 | F38: ='AEO 2023 Table 58 Raw'!I29 -> 0 | G38: ='AEO 2023 Table 58 Raw'!J29 -> 0 | H38: ='AEO 2023 Table 58 Raw'!K29 -> 0 | I38: ='AEO 2023 Table 58 Raw'!L29 -> 0 | J38: ='AEO 2023 Table 58 Raw'!M29 -> 0 | ... AF38: ='AEO 2023 Table 58 Raw'!AI29 -> - -
B41: Wellhead Prices (2021 dollars per barrel)
A43: COP000:fa_Lower48Averag | B43: Lower 48 Average 2/ | C43: ='AEO 2023 Table 58 Raw'!F31 -> 93.56955 | D43: ='AEO 2023 Table 58 Raw'!G31 -> 90.688019 | E43: ='AEO 2023 Table 58 Raw'!H31 -> 89.880753 | F43: ='AEO 2023 Table 58 Raw'!I31 -> 84.382957 | G43: ='AEO 2023 Table 58 Raw'!J31 -> 85.041725 | H43: ='AEO 2023 Table 58 Raw'!K31 -> 85.383301 | I43: ='AEO 2023 Table 58 Raw'!L31 -> 86.061264 | J43: ='AEO 2023 Table 58 Raw'!M31 -> 86.621979 | ... AF43: ='AEO 2023 Table 58 Raw'!AI31 -> 0.001
B45: Lower 48 Onshore
A46: COP000:ga_Northeast | B46: East | C46: ='AEO 2023 Table 58 Raw'!F33 -> 88.857887 | D46: ='AEO 2023 Table 58 Raw'!G33 -> 99.212326 | E46: ='AEO 2023 Table 58 Raw'!H33 -> 94.988663 | F46: ='AEO 2023 Table 58 Raw'!I33 -> 89.303764 | G46: ='AEO 2023 Table 58 Raw'!J33 -> 89.54892 | H46: ='AEO 2023 Table 58 Raw'!K33 -> 89.768143 | I46: ='AEO 2023 Table 58 Raw'!L33 -> 90.547218 | J46: ='AEO 2023 Table 58 Raw'!M33 -> 91.051865 | ... AF46: ='AEO 2023 Table 58 Raw'!AI33 -> 0.005
A47: COP000:ga_GulfCoast | B47: Gulf Coast | C47: ='AEO 2023 Table 58 Raw'!F34 -> 95.68544 | D47: ='AEO 2023 Table 58 Raw'!G34 -> 95.794312 | E47: ='AEO 2023 Table 58 Raw'!H34 -> 95.883911 | F47: ='AEO 2023 Table 58 Raw'!I34 -> 90.399498 | G47: ='AEO 2023 Table 58 Raw'!J34 -> 91.131546 | H47: ='AEO 2023 Table 58 Raw'!K34 -> 91.528313 | I47: ='AEO 2023 Table 58 Raw'!L34 -> 92.118324 | J47: ='AEO 2023 Table 58 Raw'!M34 -> 92.703568 | ... AF47: ='AEO 2023 Table 58 Raw'!AI34 -> 0.003
A48: COP000:ga_Midcontinent | B48: Midcontinent | C48: ='AEO 2023 Table 58 Raw'!F35 -> 98.130981 | D48: ='AEO 2023 Table 58 Raw'!G35 -> 94.383713 | E48: ='AEO 2023 Table 58 Raw'!H35 -> 90.740181 | F48: ='AEO 2023 Table 58 Raw'!I35 -> 84.768532 | G48: ='AEO 2023 Table 58 Raw'!J35 -> 84.886436 | H48: ='AEO 2023 Table 58 Raw'!K35 -> 85.133736 | I48: ='AEO 2023 Table 58 Raw'!L35 -> 85.873611 | J48: ='AEO 2023 Table 58 Raw'!M35 -> 86.350456 | ... AF48: ='AEO 2023 Table 58 Raw'!AI35 -> 0
A49: COP000:ga_Southwest | B49: Southwest | C49: ='AEO 2023 Table 58 Raw'!F36 -> 93.60923 | D49: ='AEO 2023 Table 58 Raw'!G36 -> 86.461113 | E49: ='AEO 2023 Table 58 Raw'!H36 -> 86.292458 | F49: ='AEO 2023 Table 58 Raw'!I36 -> 80.893379 | G49: ='AEO 2023 Table 58 Raw'!J36 -> 81.731491 | H49: ='AEO 2023 Table 58 Raw'!K36 -> 82.064789 | I49: ='AEO 2023 Table 58 Raw'!L36 -> 82.69149 | J49: ='AEO 2023 Table 58 Raw'!M36 -> 83.278709 | ... AF49: ='AEO 2023 Table 58 Raw'!AI36 -> 0
A50: COP000:ga_RockyMountain | B50: Rocky Mountain | C50: ='AEO 2023 Table 58 Raw'!F37 -> 87.180954 | D50: ='AEO 2023 Table 58 Raw'!G37 -> 92.036903 | E50: ='AEO 2023 Table 58 Raw'!H37 -> 88.479485 | F50: ='AEO 2023 Table 58 Raw'!I37 -> 82.607307 | G50: ='AEO 2023 Table 58 Raw'!J37 -> 82.661804 | H50: ='AEO 2023 Table 58 Raw'!K37 -> 82.822685 | I50: ='AEO 2023 Table 58 Raw'!L37 -> 83.559486 | J50: ='AEO 2023 Table 58 Raw'!M37 -> 84.041298 | ... AF50: ='AEO 2023 Table 58 Raw'!AI37 -> 0.003
A51: COP000:ga_NoGreatPlains | B51: Northern Great Plains | C51: ='AEO 2023 Table 58 Raw'!F38 -> 87.180954 | D51: ='AEO 2023 Table 58 Raw'!G38 -> 92.036903 | E51: ='AEO 2023 Table 58 Raw'!H38 -> 88.479485 | F51: ='AEO 2023 Table 58 Raw'!I38 -> 82.607307 | G51: ='AEO 2023 Table 58 Raw'!J38 -> 82.661804 | H51: ='AEO 2023 Table 58 Raw'!K38 -> 82.822685 | I51: ='AEO 2023 Table 58 Raw'!L38 -> 83.559486 | J51: ='AEO 2023 Table 58 Raw'!M38 -> 84.041298 | ... AF51: ='AEO 2023 Table 58 Raw'!AI38 -> 0.003
A52: COP000:ga_WestCoast | B52: West Coast | C52: ='AEO 2023 Table 58 Raw'!F39 -> 100.23714 | D52: ='AEO 2023 Table 58 Raw'!G39 -> 94.045677 | E52: ='AEO 2023 Table 58 Raw'!H39 -> 95.09832 | F52: ='AEO 2023 Table 58 Raw'!I39 -> 89.280617 | G52: ='AEO 2023 Table 58 Raw'!J39 -> 89.667526 | H52: ='AEO 2023 Table 58 Raw'!K39 -> 90.015343 | I52: ='AEO 2023 Table 58 Raw'!L39 -> 90.526176 | J52: ='AEO 2023 Table 58 Raw'!M39 -> 90.989204 | ... AF52: ='AEO 2023 Table 58 Raw'!AI39 -> 0
B54: Lower 48 Offshore
A55: COP000:ha_Gulf | B55: Gulf | C55: ='AEO 2023 Table 58 Raw'!F41 -> 97.072922 | D55: ='AEO 2023 Table 58 Raw'!G41 -> 95.794312 | E55: ='AEO 2023 Table 58 Raw'!H41 -> 95.883911 | F55: ='AEO 2023 Table 58 Raw'!I41 -> 90.399498 | G55: ='AEO 2023 Table 58 Raw'!J41 -> 91.131546 | H55: ='AEO 2023 Table 58 Raw'!K41 -> 91.528313 | I55: ='AEO 2023 Table 58 Raw'!L41 -> 92.118324 | J55: ='AEO 2023 Table 58 Raw'!M41 -> 92.703568 | ... AF55: ='AEO 2023 Table 58 Raw'!AI41 -> 0.003
A56: COP000:ha_Pacific | B56: Pacific | C56: ='AEO 2023 Table 58 Raw'!F42 -> 70.551292 | D56: ='AEO 2023 Table 58 Raw'!G42 -> 94.045677 | E56: ='AEO 2023 Table 58 Raw'!H42 -> 95.09832 | F56: ='AEO 2023 Table 58 Raw'!I42 -> 89.280617 | G56: ='AEO 2023 Table 58 Raw'!J42 -> 89.667526 | H56: ='AEO 2023 Table 58 Raw'!K42 -> 90.015343 | I56: ='AEO 2023 Table 58 Raw'!L42 -> 90.526176 | J56: ='AEO 2023 Table 58 Raw'!M42 -> 90.989204 | ... AF56: ='AEO 2023 Table 58 Raw'!AI42 -> 0.013
A57: COP000:ha_Atlantic | B57: Atlantic | C57: ='AEO 2023 Table 58 Raw'!F43 -> 0 | D57: ='AEO 2023 Table 58 Raw'!G43 -> 95.169678 | E57: ='AEO 2023 Table 58 Raw'!H43 -> 93.930977 | F57: ='AEO 2023 Table 58 Raw'!I43 -> 88.551704 | G57: ='AEO 2023 Table 58 Raw'!J43 -> 89.145035 | H57: ='AEO 2023 Table 58 Raw'!K43 -> 89.56546 | I57: ='AEO 2023 Table 58 Raw'!L43 -> 90.069565 | J57: ='AEO 2023 Table 58 Raw'!M43 -> 90.752197 | ... AF57: ='AEO 2023 Table 58 Raw'!AI43 -> - -
B59: Tight Oil Plays
B60: Bakken | C60: ='AEO 2023 Table 58 Raw'!F45 -> 0 | D60: 1.284764 | E60: 1.458055 | F60: 1.590817 | G60: 1.613765 | H60: 1.600968 | I60: 1.599423 | J60: 1.578719 | K60: 1.549718 | L60: 1.504085 | M60: 1.491626 | N60: 1.486892 | O60: 1.487927 | P60: 1.487207 | Q60: 1.48733 | R60: 1.483563 | S60: 1.479458 | T60: 1.514265 | U60: 1.534134 | V60: 1.555008 | W60: 1.561783 | X60: 1.550906 | Y60: 1.535994 | Z60: 1.521108 | AA60: 1.513464 | AB60: 1.494211 | AC60: 1.477779 | AD60: 1.485681 | AE60: 1.486883 | AF60: 0.0099432857
B61: Eagle Ford | C61: ='AEO 2023 Table 58 Raw'!F46 -> 0 | D61: 1.028032 | E61: 1.031465 | F61: 1.140107 | G61: 1.183199 | H61: 1.191396 | I61: 1.191763 | J61: 1.183924 | K61: 1.174589 | L61: 1.160303 | M61: 1.151423 | N61: 1.140229 | O61: 1.099218 | P61: 1.080407 | Q61: 1.064877 | R61: 1.054148 | S61: 1.043394 | T61: 1.03764 | U61: 1.022488 | V61: 1.016957 | W61: 1.006644 | X61: 0.997128 | Y61: 0.984891 | Z61: 0.976349 | AA61: 0.966554 | AB61: 0.959038 | AC61: 0.950075 | AD61: 0.94273 | AE61: 0.934578 | AF61: -0.0026385794
B62: Woodford | C62: ='AEO 2023 Table 58 Raw'!F47 -> 0 | D62: 0.09094 | E62: 0.091294 | F62: 0.088377 | G62: 0.084128 | H62: 0.080048 | I62: 0.08199 | J62: 0.082497 | K62: 0.082003 | L62: 0.083749 | M62: 0.084532 | N62: 0.084377 | O62: 0.08342 | P62: 0.082952 | Q62: 0.081758 | R62: 0.085082 | S62: 0.086193 | T62: 0.086422 | U62: 0.087248 | V62: 0.087849 | W62: 0.087977 | X62: 0.087927 | Y62: 0.087833 | Z62: 0.088201 | AA62: 0.09068 | AB62: 0.091795 | AC62: 0.092543 | AD62: 0.093478 | AE62: 0.094022 | AF62: -0.0010746698
B63: Austin Chalk | C63: ='AEO 2023 Table 58 Raw'!F48 -> 0 | D63: 0.108209 | E63: 0.119158 | F63: 0.131342 | G63: 0.135725 | H63: 0.138256 | I63: 0.14231 | J63: 0.164 | K63: 0.171424 | L63: 0.174058 | M63: 0.178415 | N63: 0.182324 | O63: 0.186021 | P63: 0.187887 | Q63: 0.200777 | R63: 0.21139 | S63: 0.217522 | T63: 0.224642 | U63: 0.230035 | V63: 0.234136 | W63: 0.23627 | X63: 0.239323 | Y63: 0.245171 | Z63: 0.252609 | AA63: 0.259579 | AB63: 0.264745 | AC63: 0.268286 | AD63: 0.272506 | AE63: 0.274566 | AF63: 0.034735127
B64: Spraberry | C64: ='AEO 2023 Table 58 Raw'!F49 -> 0 | D64: 0.936898 | E64: 0.914626 | F64: 0.900527 | G64: 0.840661 | H64: 0.813808 | I64: 0.78795 | J64: 0.774315 | K64: 0.760199 | L64: 0.740554 | M64: 0.715742 | N64: 0.689881 | O64: 0.666623 | P64: 0.643481 | Q64: 0.621175 | R64: 0.599821 | S64: 0.578784 | T64: 0.55893 | U64: 0.54042 | V64: 0.523859 | W64: 0.504357 | X64: 0.488753 | Y64: 0.471661 | Z64: 0.456539 | AA64: 0.441076 | AB64: 0.427339 | AC64: 0.413761 | AD64: 0.402283 | AE64: 0.390766 | AF64: -0.028691932
B65: Niobrara | C65: ='AEO 2023 Table 58 Raw'!F50 -> 0 | D65: 0.57192 | E65: 0.589178 | F65: 0.635555 | G65: 0.647064 | H65: 0.654841 | I65: 0.658678 | J65: 0.658895 | K65: 0.654917 | L65: 0.650329 | M65: 0.648838 | N65: 0.646147 | O65: 0.648552 | P65: 0.645647 | Q65: 0.64165 | R65: 0.639808 | S65: 0.637416 | T65: 0.635988 | U65: 0.637546 | V65: 0.634853 | W65: 0.633713 | X65: 0.630362 | Y65: 0.629605 | Z65: 0.62828 | AA65: 0.63242 | AB65: 0.630288 | AC65: 0.627316 | AD65: 0.624646 | AE65: 0.621324 | AF65: 0.011970318
B66: Avalon/Bone Springs | C66: ='AEO 2023 Table 58 Raw'!F51 -> 0 | D66: 0.662599 | E66: 0.714036 | F66: 0.746142 | G66: 0.815727 | H66: 0.85283 | I66: 0.876076 | J66: 0.883181 | K66: 0.888943 | L66: 0.894158 | M66: 0.910679 | N66: 0.915315 | O66: 0.921982 | P66: 0.924463 | Q66: 0.925103 | R66: 0.922752 | S66: 0.919678 | T66: 0.934144 | U66: 0.933344 | V66: 0.92922 | W66: 0.925184 | X66: 0.920802 | Y66: 0.904876 | Z66: 0.913078 | AA66: 0.912508 | AB66: 0.911659 | AC66: 0.910346 | AD66: 0.90982 | AE66: 0.908154 | AF66: 0.017125886
B67: Monterey | C67: ='AEO 2023 Table 58 Raw'!F52 -> 0 | D67: 0.024515 | E67: 0.023675 | F67: 0.022865 | G67: 0.022083 | H67: 0.021328 | I67: 0.020599 | J67: 0.019896 | K67: 0.019217 | L67: 0.018562 | M67: 0.017929 | N67: 0.017319 | O67: 0.016729 | P67: 0.016161 | Q67: 0.015306 | R67: 0.014787 | S67: 0.014285 | T67: 0.013801 | U67: 0.013334 | V67: 0.012883 | W67: 0.012447 | X67: 0.01201 | Y67: 0.011605 | Z67: 0.011213 | AA67: 0.010835 | AB67: 0.01047 | AC67: 0.010106 | AD67: 0.009766 | AE67: 0.009438 | AF67: -0.034339724
B68: Wolfcamp | C68: ='AEO 2023 Table 58 Raw'!F53 -> 0 | D68: 2.953266 | E68: 2.965916 | F68: 2.955796 | G68: 2.966785 | H68: 2.897201 | I68: 2.838486 | J68: 2.777276 | K68: 2.718389 | L68: 2.659629 | M68: 2.630852 | N68: 2.590855 | O68: 2.566443 | P68: 2.568752 | Q68: 2.55597 | R68: 2.585652 | S68: 2.59788 | T68: 2.623691 | U68: 2.628755 | V68: 2.622619 | W68: 2.618176 | X68: 2.610916 | Y68: 2.608633 | Z68: 2.632223 | AA68: 2.636291 | AB68: 2.641968 | AC68: 2.64919 | AD68: 2.654824 | AE68: 2.664979 | AF68: 0.0015354898
B69: Utica | C69: ='AEO 2023 Table 58 Raw'!F54 -> 0 | D69: 0.085125 | E69: 0.084968 | F69: 0.080169 | G69: 0.075577 | H69: 0.070812 | I69: 0.06967 | J69: 0.067444 | K69: 0.063024 | L69: 0.059396 | M69: 0.056012 | N69: 0.053796 | O69: 0.052447 | P69: 0.05097 | Q69: 0.050594 | R69: 0.054174 | S69: 0.054212 | T69: 0.067062 | U69: 0.071487 | V69: 0.073588 | W69: 0.074077 | X69: 0.074184 | Y69: 0.074565 | Z69: 0.075391 | AA69: 0.078283 | AB69: 0.080938 | AC69: 0.082483 | AD69: 0.084104 | AE69: 0.085532 | AF69: 0.012300764
B70: Other | C70: ='AEO 2023 Table 58 Raw'!F55 -> 0 | D70: 0.880444 | E70: 0.908875 | F70: 0.97579 | G70: 0.987594 | H70: 0.992203 | I70: 0.9952 | J70: 0.997181 | K70: 0.995118 | L70: 0.992045 | M70: 0.996773 | N70: 1.056262 | O70: 1.091962 | P70: 1.128754 | Q70: 1.155376 | R70: 1.186167 | S70: 1.21501 | T70: 1.241271 | U70: 1.329676 | V70: 1.38167 | W70: 1.415396 | X70: 1.442509 | Y70: 1.47836 | Z70: 1.506077 | AA70: 1.531763 | AB70: 1.553811 | AC70: 1.587568 | AD70: 1.617103 | AE70: 1.668501 | AF70: 0.033873339
B71: Total | C71: ='AEO 2023 Table 58 Raw'!F56 -> 0 | D71: 8.626714 | E71: 8.901247 | F71: 9.267487 | G71: 9.372309 | H71: 9.31369 | I71: 9.262145 | J71: 9.187327 | K71: 9.077542 | L71: 8.936868 | M71: 8.88282 | N71: 8.863394 | O71: 8.821326 | P71: 8.816681 | Q71: 8.799916 | R71: 8.837342 | S71: 8.843831 | T71: 8.937856 | U71: 9.028466 | V71: 9.07264 | W71: 9.076026 | X71: 9.054821 | Y71: 9.033194 | Z71: 9.061068 | AA71: 9.073453 | AB71: 9.066263 | AC71: 9.069452 | AD71: 9.096942 | AE71: 9.138742 | AF71: 0.006847004
B74: 1/ Includes lease condensate.
B75: 2/ Represents lower 48 onshore and offshore supplies.
B76: - - = Not applicable.
B77: Note: Oil and Gas Supply Model regions are defined in Assumptions to the Annual Energy Outlook. Totals may not equal sum of components
B78: due to independent rounding.
B79: Sources: 2021: U.S. Energy Information Administration (EIA), Short-Term Energy Outlook, November 2021 and EIA, AEO2022
B80: National Energy Modeling System run ref2022.d011222a. Projections: EIA, AEO2022 National Energy Modeling System run ref2022.d011222a.

Sheet AEO 2023 Table 59 Raw
A1: Table 59. Lower 48 Natural Gas Production and Supply Prices by Supply Region
A2: https://www.eia.gov/outlooks/aeo/data/browser/#/?id=72-AEO2023&cases=ref2023&sourcekey=0
A3: Thu Apr 13 2023 09:35:30 GMT-0400 (Eastern Daylight Time)
A4: Source: U.S. Energy Information Administration
B5: full name | C5: api key | D5: units | E5: 2021 | F5: 2022 | G5: 2023 | H5: 2024 | I5: 2025 | J5: 2026 | K5: 2027 | L5: 2028 | M5: 2029 | N5: 2030 | O5: 2031 | P5: 2032 | Q5: 2033 | R5: 2034 | S5: 2035 | T5: 2036 | U5: 2037 | V5: 2038 | W5: 2039 | X5: 2040 | Y5: 2041 | Z5: 2042 | AA5: 2043 | AB5: 2044 | AC5: 2045 | AD5: 2046 | AE5: 2047 | AF5: 2048 | AG5: 2049 | AH5: 2050 | AI5: Growth (2022-2050)
A8: Dry Production (trillion cubic feet)
A9: Lower 48 Total | B9: Natural Gas: Dry Production: Lower 48 Total: Reference case | C9: AEO.2023.REF2023.PRD_NA_NA_NA_NG_NA_L48_TRLCF.A | D9: Tcf | F9: 36.11721 | G9: 36.160473 | H9: 35.236458 | I9: 35.385082 | J9: 35.842361 | K9: 35.789593 | L9: 36.084969 | M9: 36.326553 | N9: 36.675777 | O9: 37.108833 | P9: 37.608639 | Q9: 38.184341 | R9: 38.686111 | S9: 39.140957 | T9: 39.498707 | U9: 39.854 | V9: 40.120361 | W9: 40.358707 | X9: 40.50095 | Y9: 40.620884 | Z9: 40.794956 | AA9: 40.90696 | AB9: 40.974735 | AC9: 41.124126 | AD9: 40.952206 | AE9: 41.157238 | AF9: 41.220951 | AG9: 41.302063 | AH9: 41.677505 | AI9: 0.005
A10: Lower 48 Onshore | B10: Natural Gas: Dry Production: Lower 48 Onshore: Reference case | C10: AEO.2023.REF2023.PRD_NA_ONS_NA_NG_NA_L48_TRLCF.A | D10: Tcf | F10: 35.046551 | G10: 35.336418 | H10: 34.441242 | I10: 34.503323 | J10: 34.879745 | K10: 34.711132 | L10: 34.854389 | M10: 35.019588 | N10: 35.347614 | O10: 35.780499 | P10: 36.265156 | Q10: 36.855312 | R10: 37.36681 | S10: 37.837582 | T10: 38.213299 | U10: 38.579849 | V10: 38.861893 | W10: 39.162666 | X10: 39.335423 | Y10: 39.544559 | Z10: 39.670769 | AA10: 39.661568 | AB10: 39.646687 | AC10: 39.801342 | AD10: 39.645775 | AE10: 39.963863 | AF10: 39.982841 | AG10: 39.924835 | AH10: 40.241112 | AI10: 0.005
A11: East | B11: Natural Gas: Dry Production: Lower 48 Onshore: East: Reference case | C11: AEO.2023.REF2023.PRD_NA_ONS_NA_NG_NA_EST_TRLCF.A | D11: Tcf | F11: 15.131968 | G11: 13.514215 | H11: 12.409004 | I11: 12.356494 | J11: 12.315032 | K11: 12.338302 | L11: 12.570937 | M11: 12.812769 | N11: 13.143781 | O11: 13.462552 | P11: 13.766328 | Q11: 14.026499 | R11: 14.216332 | S11: 14.421331 | T11: 14.398188 | U11: 14.399078 | V11: 14.592781 | W11: 14.478137 | X11: 14.673953 | Y11: 14.80999 | Z11: 14.946556 | AA11: 14.964318 | AB11: 15.028558 | AC11: 15.185709 | AD11: 15.102778 | AE11: 15.243244 | AF11: 15.234793 | AG11: 15.235981 | AH11: 15.51906 | AI11: 0.001
A12: Gulf Coast | B12: Natural Gas: Dry Production: Lower 48 Onshore: Gulf Coast: Reference case | C12: AEO.2023.REF2023.PRD_NA_ONS_NA_NG_NA_GLFCT_TRLCF.A | D12: Tcf | F12: 7.228662 | G12: 8.55634 | H12: 9.373387 | I12: 9.430349 | J12: 9.471944 | K12: 9.277282 | L12: 9.185096 | M12: 9.166778 | N12: 9.178074 | O12: 9.33682 | P12: 9.53478 | Q12: 9.819237 | R12: 10.124263 | S12: 10.378657 | T12: 10.682348 | U12: 10.90027 | V12: 11.017419 | W12: 11.257378 | X12: 11.210609 | Y12: 11.234081 | Z12: 11.1992 | AA12: 11.143196 | AB12: 10.985036 | AC12: 10.95787 | AD12: 10.843297 | AE12: 10.943599 | AF12: 10.983875 | AG12: 10.947719 | AH12: 10.954504 | AI12: 0.015
A13: Midcontinent | B13: Natural Gas: Dry Production: Lower 48 Onshore: Midcontinent: Reference case | C13: AEO.2023.REF2023.PRD_NA_ONS_NA_NG_NA_MDCN_TRLCF.A | D13: Tcf | F13: 2.765047 | G13: 2.85201 | H13: 2.59163 | I13: 2.584664 | J13: 2.606673 | K13: 2.558037 | L13: 2.511741 | M13: 2.455868 | N13: 2.424041 | O13: 2.370743 | P13: 2.342753 | Q13: 2.315938 | R13: 2.291161 | S13: 2.262149 | T13: 2.256484 | U13: 2.238439 | V13: 2.196423 | W13: 2.207939 | X13: 2.190404 | Y13: 2.186232 | Z13: 2.195779 | AA13: 2.194933 | AB13: 2.184463 | AC13: 2.175076 | AD13: 2.152232 | AE13: 2.192416 | AF13: 2.17778 | AG13: 2.151856 | AH13: 2.132941 | AI13: -0.009
A14: Southwest | B14: Natural Gas: Dry Production: Lower 48 Onshore: Southwest: Reference case | C14: AEO.2023.REF2023.PRD_NA_ONS_NA_NG_NA_SW_TRLCF.A | D14: Tcf | F14: 4.914759 | G14: 6.044238 | H14: 5.808331 | I14: 5.764486 | J14: 6.037246 | K14: 6.044762 | L14: 6.045456 | M14: 6.023058 | N14: 6.037135 | O14: 6.071146 | P14: 6.139278 | Q14: 6.232044 | R14: 6.34437 | S14: 6.430139 | T14: 6.466352 | U14: 6.61659 | V14: 6.603184 | W14: 6.765916 | X14: 6.75592 | Y14: 6.815601 | Z14: 6.864169 | AA14: 6.937812 | AB14: 7.02853 | AC14: 7.120607 | AD14: 7.225514 | AE14: 7.280244 | AF14: 7.318533 | AG14: 7.363565 | AH14: 7.424009 | AI14: 0.015
A15: Rocky Mountain | B15: Natural Gas: Dry Production: Lower 48 Onshore: Rocky Mountain: Reference case | C15: AEO.2023.REF2023.PRD_NA_ONS_NA_NG_NA_RKYMTN_TRLCF.A | D15: Tcf | F15: 4.080968 | G15: 3.429896 | H15: 3.364925 | I15: 3.491153 | J15: 3.57061 | K15: 3.616507 | L15: 3.665931 | M15: 3.691127 | N15: 3.699205 | O15: 3.679139 | P15: 3.615395 | Q15: 3.591738 | R15: 3.525626 | S15: 3.478284 | T15: 3.542527 | U15: 3.563337 | V15: 3.596846 | W15: 3.599293 | X15: 3.652844 | Y15: 3.648354 | Z15: 3.618313 | AA15: 3.590814 | AB15: 3.598248 | AC15: 3.543151 | AD15: 3.50279 | AE15: 3.481233 | AF15: 3.450871 | AG15: 3.409222 | AH15: 3.389066 | AI15: -0.007
A16: Northern Great Plains | B16: Natural Gas: Dry Production: Lower 48 Onshore: Northern Great Plains: Reference case | C16: AEO.2023.REF2023.PRD_NA_ONS_NA_NG_NA_NOGP_TRLCF.A | D16: Tcf | F16: 0.758008 | G16: 0.813158 | H16: 0.788122 | I16: 0.776183 | J16: 0.787115 | K16: 0.792252 | L16: 0.797109 | M16: 0.797164 | N16: 0.797788 | O16: 0.795638 | P16: 0.805806 | Q16: 0.811677 | R16: 0.810845 | S16: 0.815814 | T16: 0.81936 | U16: 0.816824 | V16: 0.812283 | W16: 0.808585 | X16: 0.805369 | Y16: 0.805459 | Z16: 0.805774 | AA16: 0.792521 | AB16: 0.785659 | AC16: 0.784072 | AD16: 0.785451 | AE16: 0.790393 | AF16: 0.785353 | AG16: 0.785941 | AH16: 0.792016 | AI16: 0.002
A17: West Coast | B17: Natural Gas: Dry Production: Lower 48 Onshore: West Coast: Reference case | C17: AEO.2023.REF2023.PRD_NA_ONS_NA_NG_NA_WETCOT_TRLCF.A | D17: Tcf | F17: 0.167141 | G17: 0.126558 | H17: 0.105848 | I17: 0.099993 | J17: 0.091125 | K17: 0.08399 | L17: 0.078121 | M17: 0.072828 | N17: 0.067596 | O17: 0.064461 | P17: 0.060816 | Q17: 0.058181 | R17: 0.054211 | S17: 0.051209 | T17: 0.048042 | U17: 0.04532 | V17: 0.042956 | W17: 0.04542 | X17: 0.046322 | Y17: 0.044842 | Z17: 0.040979 | AA17: 0.037977 | AB17: 0.036195 | AC17: 0.034857 | AD17: 0.033712 | AE17: 0.032733 | AF17: 0.031639 | AG17: 0.030551 | AH17: 0.029518 | AI17: -0.06
A18: Lower 48 Offshore | B18: Natural Gas: Dry Production: Lower 48 Offshore: Reference case | C18: AEO.2023.REF2023.PRD_NA_OFS_NA_NG_NA_L48_TRLCF.A | D18: Tcf | F18: 1.070656 | G18: 0.824057 | H18: 0.795216 | I18: 0.881762 | J18: 0.962611 | K18: 1.078455 | L18: 1.230578 | M18: 1.306956 | N18: 1.328158 | O18: 1.328338 | P18: 1.343482 | Q18: 1.32903 | R18: 1.319305 | S18: 1.303373 | T18: 1.285405 | U18: 1.274144 | V18: 1.258471 | W18: 1.196043 | X18: 1.165528 | Y18: 1.076319 | Z18: 1.124182 | AA18: 1.245389 | AB18: 1.328045 | AC18: 1.322789 | AD18: 1.306431 | AE18: 1.193373 | AF18: 1.238106 | AG18: 1.37723 | AH18: 1.43639 | AI18: 0.011
A19: Gulf | B19: Natural Gas: Dry Production: Lower 48 Offshore: Gulf of Mexico: Reference case | C19: AEO.2023.REF2023.PRD_NA_OFS_NA_NG_NA_GOM_TRLCF.A | D19: Tcf | F19: 1.06135 | G19: 0.820089 | H19: 0.791535 | I19: 0.878328 | J19: 0.95939 | K19: 1.07542 | L19: 1.103616 | M19: 1.115855 | N19: 1.111558 | O19: 1.098036 | P19: 1.107808 | Q19: 1.090719 | R19: 1.084312 | S19: 1.083777 | T19: 1.05672 | U19: 1.054063 | V19: 1.059612 | W19: 0.985578 | X19: 0.950471 | Y19: 0.844999 | Z19: 0.899971 | AA19: 1.036117 | AB19: 1.108361 | AC19: 1.092072 | AD19: 1.09266 | AE19: 0.992129 | AF19: 0.969224 | AG19: 1.108598 | AH19: 1.187927 | AI19: 0.004
A20: Shallow (State) | B20: less than 200 meters | C20: Natural Gas: Dry Production: Lower 48 Offshore: Gulf: Shallow (State): Reference case | D20: AEO.2023.REF2023.PRD_NA_OFS_SHOF_NG_ST_GOM_TRLCF.A | E20: Tcf | G20: 0.068782 | H20: 0.04114 | I20: 0.032001 | J20: 0.02993 | K20: 0.026898 | L20: 0.025101 | M20: 0.023499 | N20: 0.021878 | O20: 0.020369 | P20: 0.019035 | Q20: 0.01782 | R20: 0.01683 | S20: 0.015732 | T20: 0.014828 | U20: 0.013899 | V20: 0.013306 | W20: 0.012813 | X20: 0.01196 | Y20: 0.011762 | Z20: 0.011226 | AA20: 0.010688 | AB20: 0.010236 | AC20: 0.009908 | AD20: 0.009635 | AE20: 0.009328 | AF20: 0.009005 | AG20: 0.008753 | AH20: 0.00847 | AI20: 0.008303 | AJ20: -0.073
A21: Shallow (Federal) | B21: less than 200 meters | C21: Natural Gas: Dry Production: Lower 48 Offshore: Gulf: Shallow (Federal): Reference case | D21: AEO.2023.REF2023.PRD_NA_OFS_SHOF_NG_FED_GOM_TRLCF.A | E21: Tcf | G21: 0.11572 | H21: 0.092628 | I21: 0.071989 | J21: 0.068006 | K21: 0.061444 | L21: 0.057699 | M21: 0.054343 | N21: 0.05084 | O21: 0.04767 | P21: 0.044853 | Q21: 0.042416 | R21: 0.040592 | S21: 0.038177 | T21: 0.046589 | U21: 0.057213 | V21: 0.056628 | W21: 0.0788 | X21: 0.085582 | Y21: 0.087631 | Z21: 0.086256 | AA21: 0.089688 | AB21: 0.093801 | AC21: 0.093535 | AD21: 0.112123 | AE21: 0.122999 | AF21: 0.122162 | AG21: 0.129296 | AH21: 0.129042 | AI21: 0.133118 | AJ21: 0.005
A22: Deep (Federal) | B22: Natural Gas: Dry Production: Lower 48 Offshore: Gulf: Deep: Reference case | C22: AEO.2023.REF2023.PRD_NA_OFS_DPO_NG_FED_GOM_TRLCF.A | D22: Tcf | F22: 0.603061 | G22: 0.688524 | H22: 0.68941 | I22: 0.78201 | J22: 0.872479 | K22: 0.993904 | L22: 1.02694 | M22: 1.044204 | N22: 1.044504 | O22: 1.035065 | P22: 1.048428 | Q22: 1.034101 | R22: 1.031162 | S22: 1.023077 | T22: 0.98629 | U22: 0.984779 | V22: 0.968619 | W22: 0.88863 | X22: 0.851649 | Y22: 0.748065 | Z22: 0.800124 | AA22: 0.93259 | AB22: 1.00541 | AC22: 0.97079 | AD22: 0.960794 | AE22: 0.861409 | AF22: 0.83161 | AG22: 0.971509 | AH22: 1.046917 | AI22: 0.02
A23: Pacific | B23: Natural Gas: Dry Production: Lower 48 Offshore: Pacific: Reference case | C23: AEO.2023.REF2023.PRD_NA_OFS_NA_NG_NA_PCF_TRLCF.A | D23: Tcf | F23: 0.009306 | G23: 0.003967 | H23: 0.00368 | I23: 0.003434 | J23: 0.003221 | K23: 0.003034 | L23: 0.126962 | M23: 0.191101 | N23: 0.2166 | O23: 0.230302 | P23: 0.235674 | Q23: 0.238311 | R23: 0.234994 | S23: 0.219596 | T23: 0.228685 | U23: 0.220081 | V23: 0.198859 | W23: 0.210465 | X23: 0.215057 | Y23: 0.23132 | Z23: 0.224211 | AA23: 0.209272 | AB23: 0.219684 | AC23: 0.230716 | AD23: 0.213772 | AE23: 0.201244 | AF23: 0.268882 | AG23: 0.268632 | AH23: 0.248463 | AI23: 0.124
A24: State | B24: Natural Gas: Dry Production: Lower 48 Offshore: Pacific: State: Reference case | C24: AEO.2023.REF2023.PRD_NA_OFS_NA_NG_ST_PCF_TRLCF.A | D24: Tcf | F24: 0.003229 | G24: 0.003038 | H24: 0.002819 | I24: 0.00263 | J24: 0.002467 | K24: 0.002324 | L24: 0.002198 | M24: 0.002086 | N24: 0.001985 | O24: 0.001895 | P24: 0.001814 | Q24: 0.001739 | R24: 0.001672 | S24: 0.001609 | T24: 0.001552 | U24: 0.0015 | V24: 0.001451 | W24: 0.001405 | X24: 0.001363 | Y24: 0.001324 | Z24: 0.001287 | AA24: 0.001252 | AB24: 0.00122 | AC24: 0.001189 | AD24: 0.00116 | AE24: 0.001133 | AF24: 0.001107 | AG24: 0.001083 | AH24: 0.00106 | AI24: -0.039
A25: Federal | B25: Natural Gas: Dry Production: Lower 48 Offshore: Pacific: Federal: Reference case | C25: AEO.2023.REF2023.PRD_NA_OFS_NA_NG_FED_PCF_TRLCF.A | D25: Tcf | F25: 0.006077 | G25: 0.000929 | H25: 0.000862 | I25: 0.000804 | J25: 0.000754 | K25: 0.000711 | L25: 0.124764 | M25: 0.189015 | N25: 0.214615 | O25: 0.228407 | P25: 0.23386 | Q25: 0.236571 | R25: 0.233322 | S25: 0.217987 | T25: 0.227133 | U25: 0.218582 | V25: 0.197408 | W25: 0.20906 | X25: 0.213694 | Y25: 0.229996 | Z25: 0.222924 | AA25: 0.208019 | AB25: 0.218465 | AC25: 0.229527 | AD25: 0.212611 | AE25: 0.200111 | AF25: 0.267774 | AG25: 0.267549 | AH25: 0.247403 | AI25: 0.142
A26: Atlantic | B26: Natural Gas: Dry Production: Lower 48 Offshore: Atlantic: Reference case | C26: AEO.2023.REF2023.PRD_NA_OFS_NA_NG_NA_ATLN_TRLCF.A | D26: Tcf | F26: 0 | G26: 0 | H26: 0 | I26: 0 | J26: 0 | K26: 0 | L26: 0 | M26: 0 | N26: 0 | O26: 0 | P26: 0 | Q26: 0 | R26: 0 | S26: 0 | T26: 0 | U26: 0 | V26: 0 | W26: 0 | X26: 0 | Y26: 0 | Z26: 0 | AA26: 0 | AB26: 0 | AC26: 0 | AD26: 0 | AE26: 0 | AF26: 0 | AG26: 0 | AH26: 0 | AI26: - -
A27: State | B27: Natural Gas: Dry Production: Lower 48 Offshore: Atlantic: State: Reference case | C27: AEO.2023.REF2023.PRD_NA_OFS_NA_NG_ST_ATLN_TRLCF.A | D27: Tcf | F27: 0 | G27: 0 | H27: 0 | I27: 0 | J27: 0 | K27: 0 | L27: 0 | M27: 0 | N27: 0 | O27: 0 | P27: 0 | Q27: 0 | R27: 0 | S27: 0 | T27: 0 | U27: 0 | V27: 0 | W27: 0 | X27: 0 | Y27: 0 | Z27: 0 | AA27: 0 | AB27: 0 | AC27: 0 | AD27: 0 | AE27: 0 | AF27: 0 | AG27: 0 | AH27: 0 | AI27: - -
A28: Federal | B28: Natural Gas: Dry Production: Lower 48 Offshore: Atlantic: Federal: Reference case | C28: AEO.2023.REF2023.PRD_NA_OFS_NA_NG_FED_ATLN_TRLCF.A | D28: Tcf | F28: 0 | G28: 0 | H28: 0 | I28: 0 | J28: 0 | K28: 0 | L28: 0 | M28: 0 | N28: 0 | O28: 0 | P28: 0 | Q28: 0 | R28: 0 | S28: 0 | T28: 0 | U28: 0 | V28: 0 | W28: 0 | X28: 0 | Y28: 0 | Z28: 0 | AA28: 0 | AB28: 0 | AC28: 0 | AD28: 0 | AE28: 0 | AF28: 0 | AG28: 0 | AH28: 0 | AI28: - -
A29: Supply Prices
A30: (2022 dollars per million Btu)
A31: Henry Hub Spot Price | B31: Natural Gas: Supply Prices: Henry Hub Spot: Reference case | C31: AEO.2023.REF2023.PRCE_SUP_NA_NA_NG_NA_HHUB_Y13DLRPMMBTU.A | D31: 2022 $/MMBtu | F31: 6.523997 | G31: 5.266376 | H31: 4.072381 | I31: 3.489514 | J31: 3.065508 | K31: 2.853001 | L31: 2.799904 | M31: 2.825097 | N31: 2.91248 | O31: 3.043758 | P31: 3.208004 | Q31: 3.416918 | R31: 3.56943 | S31: 3.681824 | T31: 3.694155 | U31: 3.737596 | V31: 3.866561 | W31: 3.78878 | X31: 3.938065 | Y31: 4.022155 | Z31: 4.014737 | AA31: 3.950616 | AB31: 3.913768 | AC31: 3.910706 | AD31: 3.907083 | AE31: 3.870706 | AF31: 3.849094 | AG31: 3.783895 | AH31: 3.771015 | AI31: -0.019
A32: Lower 48 Average Price | B32: Natural Gas: Supply Prices: Lower 48 Average: Reference case | C32: AEO.2023.REF2023.PRCE_SUP_NA_NA_NG_NA_L48_Y13DLRPMMBTU.A | D32: 2022 $/MMBtu | F32: 5.108581 | G32: 4.496722 | H32: 3.469988 | I32: 2.892442 | J32: 2.459758 | K32: 2.225519 | L32: 2.133026 | M32: 2.115468 | N32: 2.156652 | O32: 2.240563 | P32: 2.33826 | Q32: 2.463977 | R32: 2.575345 | S32: 2.676528 | T32: 2.713635 | U32: 2.761968 | V32: 2.867161 | W32: 2.848468 | X32: 2.940892 | Y32: 2.988464 | Z32: 2.962466 | AA32: 2.906876 | AB32: 2.867534 | AC32: 2.843702 | AD32: 2.817131 | AE32: 2.777319 | AF32: 2.742738 | AG32: 2.693233 | AH32: 2.676029 | AI32: -0.023
A33: (2022 dollars per thousand cubic feet)
A34: Lower 48 Average Price | B34: Natural Gas: Supply Prices: Lower 48 Average: Reference case | C34: AEO.2023.REF2023.PRCE_SUP_NA_NA_NG_NA_L48_Y13DLRPMCF.A | D34: 2022 $/Mcf | F34: 5.297598 | G34: 4.6631 | H34: 3.598378 | I34: 2.999462 | J34: 2.550768 | K34: 2.307863 | L34: 2.211948 | M34: 2.19374 | N34: 2.236448 | O34: 2.323464 | P34: 2.424776 | Q34: 2.555144 | R34: 2.670632 | S34: 2.775559 | T34: 2.81404 | U34: 2.864161 | V34: 2.973246 | W34: 2.953861 | X34: 3.049704 | Y34: 3.099037 | Z34: 3.072077 | AA34: 3.01443 | AB34: 2.973633 | AC34: 2.948918 | AD34: 2.921365 | AE34: 2.88008 | AF34: 2.844219 | AG34: 2.792883 | AH34: 2.775042 | AI34: -0.023
A35: Lower 48 Onshore Price
A36: East | B36: Natural Gas: Supply Prices: Lower 48 Onshore: East: Reference case | C36: AEO.2023.REF2023.PRCE_SUP_NA_NA_NG_NA_EST_Y13DLRPMCF.A | D36: 2022 $/Mcf | F36: 4.495963 | G36: 4.408257 | H36: 3.439742 | I36: 2.828316 | J36: 2.367009 | K36: 2.105921 | L36: 1.970865 | M36: 1.903738 | N36: 1.88818 | O36: 1.908919 | P36: 1.952179 | Q36: 2.013541 | R36: 2.084761 | S36: 2.159367 | T36: 2.213028 | U36: 2.271686 | V36: 2.354753 | W36: 2.391489 | X36: 2.433505 | Y36: 2.447776 | Z36: 2.404809 | AA36: 2.351671 | AB36: 2.319847 | AC36: 2.281933 | AD36: 2.246254 | AE36: 2.198399 | AF36: 2.148588 | AG36: 2.104743 | AH36: 2.081049 | AI36: -0.027
A37: Gulf Coast | B37: Natural Gas: Supply Prices: Lower 48 Onshore: Gulf Coast: Reference case | C37: AEO.2023.REF2023.PRCE_SUP_NA_NA_NG_NA_GLFCT_Y13DLRPMCF.A | D37: 2022 $/Mcf | F37: 6.342973 | G37: 5.063886 | H37: 3.842494 | I37: 3.246102 | J37: 2.813074 | K37: 2.59683 | L37: 2.544311 | M37: 2.572556 | N37: 2.671812 | O37: 2.818912 | P37: 2.982175 | Q37: 3.184034 | R37: 3.339914 | S37: 3.467139 | T37: 3.478095 | U37: 3.514131 | V37: 3.648592 | W37: 3.564691 | X37: 3.717124 | Y37: 3.801028 | Z37: 3.792323 | AA37: 3.725607 | AB37: 3.687238 | AC37: 3.68379 | AD37: 3.678917 | AE37: 3.639425 | AF37: 3.615878 | AG37: 3.547849 | AH37: 3.533859 | AI37: -0.021
A38: Midcontinent | B38: Natural Gas: Supply Prices: Lower 48 Onshore: Midcontinent: Reference case | C38: AEO.2023.REF2023.PRCE_SUP_NA_NA_NG_NA_MDCN_Y13DLRPMCF.A | D38: 2022 $/Mcf | F38: 5.891514 | G38: 4.685303 | H38: 3.587715 | I38: 3.005321 | J38: 2.556094 | K38: 2.317663 | L38: 2.240961 | M38: 2.263006 | N38: 2.360847 | O38: 2.495367 | P38: 2.626106 | Q38: 2.793201 | R38: 2.928839 | S38: 3.049093 | T38: 3.063851 | U38: 3.095169 | V38: 3.226722 | W38: 3.154944 | X38: 3.295776 | Y38: 3.377325 | Z38: 3.368104 | AA38: 3.312332 | AB38: 3.264743 | AC38: 3.245367 | AD38: 3.225416 | AE38: 3.187302 | AF38: 3.166051 | AG38: 3.120948 | AH38: 3.115168 | AI38: -0.023
A39: Southwest | B39: Natural Gas: Supply Prices: Lower 48 Onshore: Southwest: Reference case | C39: AEO.2023.REF2023.PRCE_SUP_NA_NA_NG_NA_SW_Y13DLRPMCF.A | D39: 2022 $/Mcf | F39: 6.005493 | G39: 4.693 | H39: 3.529354 | I39: 2.956786 | J39: 2.519996 | K39: 2.293305 | L39: 2.226445 | M39: 2.248604 | N39: 2.354171 | O39: 2.520651 | P39: 2.678705 | Q39: 2.854002 | R39: 2.995707 | S39: 3.12826 | T39: 3.145562 | U39: 3.165577 | V39: 3.298712 | W39: 3.222145 | X39: 3.374846 | Y39: 3.458428 | Z39: 3.451305 | AA39: 3.397575 | AB39: 3.355302 | AC39: 3.335531 | AD39: 3.315635 | AE39: 3.282599 | AF39: 3.264709 | AG39: 3.215299 | AH39: 3.208428 | AI39: -0.022
A40: Rocky Mountain | B40: Natural Gas: Supply Prices: Lower 48 Onshore: Rocky Mountain: Reference case | C40: AEO.2023.REF2023.PRCE_SUP_NA_NA_NG_NA_RKYMTN_Y13DLRPMCF.A | D40: 2022 $/Mcf | F40: 5.742832 | G40: 4.626787 | H40: 3.54197 | I40: 2.958944 | J40: 2.511465 | K40: 2.263142 | L40: 2.176153 | M40: 2.184029 | N40: 2.271296 | O40: 2.41635 | P40: 2.55462 | Q40: 2.72116 | R40: 2.868438 | S40: 3.004475 | T40: 3.02449 | U40: 3.054317 | V40: 3.189528 | W40: 3.123179 | X40: 3.263659 | Y40: 3.350009 | Z40: 3.351562 | AA40: 3.305258 | AB40: 3.257014 | AC40: 3.244544 | AD40: 3.217094 | AE40: 3.189258 | AF40: 3.169464 | AG40: 3.134983 | AH40: 3.133789 | AI40: -0.021
A41: Northern Great Plains | B41: Natural Gas: Supply Prices: Lower 48 Onshore: Northern Great Plains: Reference case | C41: AEO.2023.REF2023.PRCE_SUP_NA_NA_NG_NA_NOGP_Y13DLRPMCF.A | D41: 2022 $/Mcf | F41: 6.959198 | G41: 5.646724 | H41: 4.429469 | I41: 3.909585 | J41: 3.500575 | K41: 3.22762 | L41: 3.110677 | M41: 3.086089 | N41: 3.094053 | O41: 3.193303 | P41: 3.277823 | Q41: 3.470813 | R41: 3.636553 | S41: 3.793429 | T41: 3.8334 | U41: 3.891849 | V41: 4.066804 | W41: 3.995746 | X41: 4.138037 | Y41: 4.225255 | Z41: 4.244837 | AA41: 4.219415 | AB41: 4.159546 | AC41: 4.160259 | AD41: 4.074099 | AE41: 4.068096 | AF41: 4.016241 | AG41: 4.016356 | AH41: 4.047671 | AI41: -0.019
A42: West Coast | B42: Natural Gas: Supply Prices: Lower 48 Onshore: West Coast: Reference case | C42: AEO.2023.REF2023.PRCE_SUP_NA_NA_NG_NA_WETCOT_Y13DLRPMCF.A | D42: 2022 $/Mcf | F42: 4.86809 | G42: 4.041528 | H42: 3.370783 | I42: 2.855986 | J42: 2.466662 | K42: 2.248124 | L42: 2.187892 | M42: 2.198744 | N42: 2.246313 | O42: 2.339305 | P42: 2.420661 | Q42: 2.556879 | R42: 2.663852 | S42: 2.763424 | T42: 2.790686 | U42: 2.837048 | V42: 2.936753 | W42: 2.894342 | X42: 2.989807 | Y42: 3.06079 | Z42: 3.0476 | AA42: 2.98941 | AB42: 2.919872 | AC42: 2.873728 | AD42: 2.83302 | AE42: 2.789794 | AF42: 2.744407 | AG42: 2.702146 | AH42: 2.6863 | AI42: -0.021
A43: Lower 48 Offshore Price
A44: Gulf | B44: Natural Gas: Supply Prices: Lower 48 Offshore: Gulf: Reference case | C44: AEO.2023.REF2023.#NAME?.A | D44: 2022 $/Mcf | F44: 6.426492 | G44: 5.110907 | H44: 3.87916 | I44: 3.278244 | J44: 2.838944 | K44: 2.61611 | L44: 2.561345 | M44: 2.588378 | N44: 2.681772 | O44: 2.822094 | P44: 2.988642 | Q44: 3.197995 | R44: 3.355494 | S44: 3.477199 | T44: 3.489903 | U44: 3.53088 | V44: 3.661503 | W44: 3.580137 | X44: 3.735213 | Y44: 3.821392 | Z44: 3.811334 | AA44: 3.747378 | AB44: 3.707001 | AC44: 3.703826 | AD44: 3.699356 | AE44: 3.660956 | AF44: 3.638313 | AG44: 3.563657 | AH44: 3.547059 | AI44: -0.021
A45: Pacific | B45: Natural Gas: Supply Prices: Lower 48 Offshore: Pacific: Reference case | C45: AEO.2023.REF2023.#NAME?.A | D45: 2022 $/Mcf | F45: 6.005988 | G45: 6.005988 | H45: 6.005988 | I45: 6.005988 | J45: 6.005988 | K45: 6.005988 | L45: 3.115042 | M45: 3.088059 | N45: 3.094053 | O45: 3.193303 | P45: 3.277823 | Q45: 3.470813 | R45: 3.636553 | S45: 3.793429 | T45: 3.8334 | U45: 3.89185 | V45: 4.066804 | W45: 3.995746 | X45: 4.138037 | Y45: 4.225256 | Z45: 4.244837 | AA45: 4.219415 | AB45: 4.159546 | AC45: 4.160259 | AD45: 4.074099 | AE45: 4.068096 | AF45: 4.016241 | AG45: 4.016356 | AH45: 4.047671 | AI45: -0.014
A46: Atlantic | B46: Natural Gas: Supply Prices: Lower 48 Offshore: Atlantic: Reference case | C46: AEO.2023.REF2023.#NAME?.A | D46: 2022 $/Mcf | F46: - - | G46: - - | H46: - - | I46: - - | J46: - - | K46: - - | L46: - - | M46: - - | N46: - - | O46: - - | P46: - - | Q46: - - | R46: - - | S46: - - | T46: - - | U46: - - | V46: - - | W46: - - | X46: - - | Y46: - - | Z46: - - | AA46: - - | AB46: - - | AC46: - - | AD46: - - | AE46: - - | AF46: - - | AG46: - - | AH46: - - | AI46: - -

Sheet AEO 2023 Table 59
B1: ref2022.d011222a | C1: 2022 | D1: 2023 | E1: 2024 | F1: 2025 | G1: 2026 | H1: 2027 | I1: 2028 | J1: 2029 | K1: 2030 | L1: 2031 | M1: 2032 | N1: 2033 | O1: 2034 | P1: 2035 | Q1: 2036 | R1: 2037 | S1: 2038 | T1: 2039 | U1: 2040 | V1: 2041 | W1: 2042 | X1: 2043 | Y1: 2044 | Z1: 2045 | AA1: 2046 | AB1: 2047 | AC1: 2048 | AD1: 2049 | AE1: 2050
C3: Report | D3: Annual Energy Outlook 2022
C4: Scenario | D4: ref2022 | G4: Reference
C5: Datekey | D5: d011222a
C6: Release Date | E6: March 2022
A10: L48000 | B10: 59. Lower 48 Natural Gas Production and Supply Prices by Supply Region | AF10: Average
AF11: Annual
AF12: Change
B13: Region | C13: 2022 | D13: 2023 | E13: 2024 | F13: 2025 | G13: 2026 | H13: 2027 | I13: 2028 | J13: 2029 | K13: 2030 | L13: 2031 | M13: 2032 | N13: 2033 | O13: 2034 | P13: 2035 | Q13: 2036 | R13: 2037 | S13: 2038 | T13: 2039 | U13: 2040 | V13: 2041 | W13: 2042 | X13: 2043 | Y13: 2044 | Z13: 2045 | AA13: 2046 | AB13: 2047 | AC13: 2048 | AD13: 2049 | AE13: 2050 | AF13: 2021–2050
B15: Dry Production (trillion cubic feet) 1/
A16: L48000:ba_Lower48Total | B16: Lower 48 Total | C16: ='AEO 2023 Table 59 Raw'!F9 -> 36.11721 | D16: ='AEO 2023 Table 59 Raw'!G9 -> 36.160473 | E16: ='AEO 2023 Table 59 Raw'!H9 -> 35.236458 | F16: ='AEO 2023 Table 59 Raw'!I9 -> 35.385082 | G16: ='AEO 2023 Table 59 Raw'!J9 -> 35.842361 | H16: ='AEO 2023 Table 59 Raw'!K9 -> 35.789593 | I16: ='AEO 2023 Table 59 Raw'!L9 -> 36.084969 | J16: ='AEO 2023 Table 59 Raw'!M9 -> 36.326553 | ... AF16: ='AEO 2023 Table 59 Raw'!AI9 -> 0.005
A18: L48000:ca_Low48Onshore | B18: Lower 48 Onshore | C18: ='AEO 2023 Table 59 Raw'!F10 -> 35.046551 | D18: ='AEO 2023 Table 59 Raw'!G10 -> 35.336418 | E18: ='AEO 2023 Table 59 Raw'!H10 -> 34.441242 | F18: ='AEO 2023 Table 59 Raw'!I10 -> 34.503323 | G18: ='AEO 2023 Table 59 Raw'!J10 -> 34.879745 | H18: ='AEO 2023 Table 59 Raw'!K10 -> 34.711132 | I18: ='AEO 2023 Table 59 Raw'!L10 -> 34.854389 | J18: ='AEO 2023 Table 59 Raw'!M10 -> 35.019588 | ... AF18: ='AEO 2023 Table 59 Raw'!AI10 -> 0.005
A19: L48000:ca_Northeast | B19: East | C19: ='AEO 2023 Table 59 Raw'!F11 -> 15.131968 | D19: ='AEO 2023 Table 59 Raw'!G11 -> 13.514215 | E19: ='AEO 2023 Table 59 Raw'!H11 -> 12.409004 | F19: ='AEO 2023 Table 59 Raw'!I11 -> 12.356494 | G19: ='AEO 2023 Table 59 Raw'!J11 -> 12.315032 | H19: ='AEO 2023 Table 59 Raw'!K11 -> 12.338302 | I19: ='AEO 2023 Table 59 Raw'!L11 -> 12.570937 | J19: ='AEO 2023 Table 59 Raw'!M11 -> 12.812769 | ... AF19: ='AEO 2023 Table 59 Raw'!AI11 -> 0.001
A20: L48000:ca_GulfCoast | B20: Gulf Coast | C20: ='AEO 2023 Table 59 Raw'!F12 -> 7.228662 | D20: ='AEO 2023 Table 59 Raw'!G12 -> 8.55634 | E20: ='AEO 2023 Table 59 Raw'!H12 -> 9.373387 | F20: ='AEO 2023 Table 59 Raw'!I12 -> 9.430349 | G20: ='AEO 2023 Table 59 Raw'!J12 -> 9.471944 | H20: ='AEO 2023 Table 59 Raw'!K12 -> 9.277282 | I20: ='AEO 2023 Table 59 Raw'!L12 -> 9.185096 | J20: ='AEO 2023 Table 59 Raw'!M12 -> 9.166778 | ... AF20: ='AEO 2023 Table 59 Raw'!AI12 -> 0.015
A21: L48000:ca_Midcontinent | B21: Midcontinent | C21: ='AEO 2023 Table 59 Raw'!F13 -> 2.765047 | D21: ='AEO 2023 Table 59 Raw'!G13 -> 2.85201 | E21: ='AEO 2023 Table 59 Raw'!H13 -> 2.59163 | F21: ='AEO 2023 Table 59 Raw'!I13 -> 2.584664 | G21: ='AEO 2023 Table 59 Raw'!J13 -> 2.606673 | H21: ='AEO 2023 Table 59 Raw'!K13 -> 2.558037 | I21: ='AEO 2023 Table 59 Raw'!L13 -> 2.511741 | J21: ='AEO 2023 Table 59 Raw'!M13 -> 2.455868 | ... AF21: ='AEO 2023 Table 59 Raw'!AI13 -> -0.009
A22: L48000:ca_Southwest | B22: Southwest | C22: ='AEO 2023 Table 59 Raw'!F14 -> 4.914759 | D22: ='AEO 2023 Table 59 Raw'!G14 -> 6.044238 | E22: ='AEO 2023 Table 59 Raw'!H14 -> 5.808331 | F22: ='AEO 2023 Table 59 Raw'!I14 -> 5.764486 | G22: ='AEO 2023 Table 59 Raw'!J14 -> 6.037246 | H22: ='AEO 2023 Table 59 Raw'!K14 -> 6.044762 | I22: ='AEO 2023 Table 59 Raw'!L14 -> 6.045456 | J22: ='AEO 2023 Table 59 Raw'!M14 -> 6.023058 | ... AF22: ='AEO 2023 Table 59 Raw'!AI14 -> 0.015
A23: L48000:ca_RockyMountain | B23: Rocky Mountain | C23: ='AEO 2023 Table 59 Raw'!F15 -> 4.080968 | D23: ='AEO 2023 Table 59 Raw'!G15 -> 3.429896 | E23: ='AEO 2023 Table 59 Raw'!H15 -> 3.364925 | F23: ='AEO 2023 Table 59 Raw'!I15 -> 3.491153 | G23: ='AEO 2023 Table 59 Raw'!J15 -> 3.57061 | H23: ='AEO 2023 Table 59 Raw'!K15 -> 3.616507 | I23: ='AEO 2023 Table 59 Raw'!L15 -> 3.665931 | J23: ='AEO 2023 Table 59 Raw'!M15 -> 3.691127 | ... AF23: ='AEO 2023 Table 59 Raw'!AI15 -> -0.007
A24: L48000:ca_NoGreatPlains | B24: Northern Great Plains | C24: ='AEO 2023 Table 59 Raw'!F16 -> 0.758008 | D24: ='AEO 2023 Table 59 Raw'!G16 -> 0.813158 | E24: ='AEO 2023 Table 59 Raw'!H16 -> 0.788122 | F24: ='AEO 2023 Table 59 Raw'!I16 -> 0.776183 | G24: ='AEO 2023 Table 59 Raw'!J16 -> 0.787115 | H24: ='AEO 2023 Table 59 Raw'!K16 -> 0.792252 | I24: ='AEO 2023 Table 59 Raw'!L16 -> 0.797109 | J24: ='AEO 2023 Table 59 Raw'!M16 -> 0.797164 | ... AF24: ='AEO 2023 Table 59 Raw'!AI16 -> 0.002
A25: L48000:ca_WestCoast | B25: West Coast | C25: ='AEO 2023 Table 59 Raw'!F17 -> 0.167141 | D25: ='AEO 2023 Table 59 Raw'!G17 -> 0.126558 | E25: ='AEO 2023 Table 59 Raw'!H17 -> 0.105848 | F25: ='AEO 2023 Table 59 Raw'!I17 -> 0.099993 | G25: ='AEO 2023 Table 59 Raw'!J17 -> 0.091125 | H25: ='AEO 2023 Table 59 Raw'!K17 -> 0.08399 | I25: ='AEO 2023 Table 59 Raw'!L17 -> 0.078121 | J25: ='AEO 2023 Table 59 Raw'!M17 -> 0.072828 | ... AF25: ='AEO 2023 Table 59 Raw'!AI17 -> -0.06
A27: L48000:da_Low48Offshore | B27: Lower 48 Offshore | C27: ='AEO 2023 Table 59 Raw'!F18 -> 1.070656 | D27: ='AEO 2023 Table 59 Raw'!G18 -> 0.824057 | E27: ='AEO 2023 Table 59 Raw'!H18 -> 0.795216 | F27: ='AEO 2023 Table 59 Raw'!I18 -> 0.881762 | G27: ='AEO 2023 Table 59 Raw'!J18 -> 0.962611 | H27: ='AEO 2023 Table 59 Raw'!K18 -> 1.078455 | I27: ='AEO 2023 Table 59 Raw'!L18 -> 1.230578 | J27: ='AEO 2023 Table 59 Raw'!M18 -> 1.306956 | ... AF27: ='AEO 2023 Table 59 Raw'!AI18 -> 0.011
A28: L48000:da_Gulf | B28: Gulf | C28: ='AEO 2023 Table 59 Raw'!F19 -> 1.06135 | D28: ='AEO 2023 Table 59 Raw'!G19 -> 0.820089 | E28: ='AEO 2023 Table 59 Raw'!H19 -> 0.791535 | F28: ='AEO 2023 Table 59 Raw'!I19 -> 0.878328 | G28: ='AEO 2023 Table 59 Raw'!J19 -> 0.95939 | H28: ='AEO 2023 Table 59 Raw'!K19 -> 1.07542 | I28: ='AEO 2023 Table 59 Raw'!L19 -> 1.103616 | J28: ='AEO 2023 Table 59 Raw'!M19 -> 1.115855 | ... AF28: ='AEO 2023 Table 59 Raw'!AI19 -> 0.004
A29: L48000:da_Shallow | B29: Shallow (State), less than 200 meters | C29: ='AEO 2023 Table 59 Raw'!F20 -> 0 | D29: ='AEO 2023 Table 59 Raw'!G20 -> 0.068782 | E29: ='AEO 2023 Table 59 Raw'!H20 -> 0.04114 | F29: ='AEO 2023 Table 59 Raw'!I20 -> 0.032001 | G29: ='AEO 2023 Table 59 Raw'!J20 -> 0.02993 | H29: ='AEO 2023 Table 59 Raw'!K20 -> 0.026898 | I29: ='AEO 2023 Table 59 Raw'!L20 -> 0.025101 | J29: ='AEO 2023 Table 59 Raw'!M20 -> 0.023499 | ... AF29: ='AEO 2023 Table 59 Raw'!AI20 -> 0.008303
A30: L48000:da_shallowfed | B30: Shallow (Federal), less than 200 meters | C30: ='AEO 2023 Table 59 Raw'!F21 -> 0 | D30: ='AEO 2023 Table 59 Raw'!G21 -> 0.11572 | E30: ='AEO 2023 Table 59 Raw'!H21 -> 0.092628 | F30: ='AEO 2023 Table 59 Raw'!I21 -> 0.071989 | G30: ='AEO 2023 Table 59 Raw'!J21 -> 0.068006 | H30: ='AEO 2023 Table 59 Raw'!K21 -> 0.061444 | I30: ='AEO 2023 Table 59 Raw'!L21 -> 0.057699 | J30: ='AEO 2023 Table 59 Raw'!M21 -> 0.054343 | ... AF30: ='AEO 2023 Table 59 Raw'!AI21 -> 0.133118
A31: L48000:da_Deep | B31: Deep (Federal) | C31: ='AEO 2023 Table 59 Raw'!F22 -> 0.603061 | D31: ='AEO 2023 Table 59 Raw'!G22 -> 0.688524 | E31: ='AEO 2023 Table 59 Raw'!H22 -> 0.68941 | F31: ='AEO 2023 Table 59 Raw'!I22 -> 0.78201 | G31: ='AEO 2023 Table 59 Raw'!J22 -> 0.872479 | H31: ='AEO 2023 Table 59 Raw'!K22 -> 0.993904 | I31: ='AEO 2023 Table 59 Raw'!L22 -> 1.02694 | J31: ='AEO 2023 Table 59 Raw'!M22 -> 1.044204 | ... AF31: ='AEO 2023 Table 59 Raw'!AI22 -> 0.02
A32: L48000:da_Pacific | B32: Pacific | C32: ='AEO 2023 Table 59 Raw'!F23 -> 0.009306 | D32: ='AEO 2023 Table 59 Raw'!G23 -> 0.003967 | E32: ='AEO 2023 Table 59 Raw'!H23 -> 0.00368 | F32: ='AEO 2023 Table 59 Raw'!I23 -> 0.003434 | G32: ='AEO 2023 Table 59 Raw'!J23 -> 0.003221 | H32: ='AEO 2023 Table 59 Raw'!K23 -> 0.003034 | I32: ='AEO 2023 Table 59 Raw'!L23 -> 0.126962 | J32: ='AEO 2023 Table 59 Raw'!M23 -> 0.191101 | ... AF32: ='AEO 2023 Table 59 Raw'!AI23 -> 0.124
A33: L48000:da_Pacificstate | B33: State | C33: ='AEO 2023 Table 59 Raw'!F24 -> 0.003229 | D33: ='AEO 2023 Table 59 Raw'!G24 -> 0.003038 | E33: ='AEO 2023 Table 59 Raw'!H24 -> 0.002819 | F33: ='AEO 2023 Table 59 Raw'!I24 -> 0.00263 | G33: ='AEO 2023 Table 59 Raw'!J24 -> 0.002467 | H33: ='AEO 2023 Table 59 Raw'!K24 -> 0.002324 | I33: ='AEO 2023 Table 59 Raw'!L24 -> 0.002198 | J33: ='AEO 2023 Table 59 Raw'!M24 -> 0.002086 | ... AF33: ='AEO 2023 Table 59 Raw'!AI24 -> -0.039
A34: L48000:da_Pacificfed | B34: Federal | C34: ='AEO 2023 Table 59 Raw'!F25 -> 0.006077 | D34: ='AEO 2023 Table 59 Raw'!G25 -> 0.000929 | E34: ='AEO 2023 Table 59 Raw'!H25 -> 0.000862 | F34: ='AEO 2023 Table 59 Raw'!I25 -> 0.000804 | G34: ='AEO 2023 Table 59 Raw'!J25 -> 0.000754 | H34: ='AEO 2023 Table 59 Raw'!K25 -> 0.000711 | I34: ='AEO 2023 Table 59 Raw'!L25 -> 0.124764 | J34: ='AEO 2023 Table 59 Raw'!M25 -> 0.189015 | ... AF34: ='AEO 2023 Table 59 Raw'!AI25 -> 0.142
A35: L48000:da_Atlantic | B35: Atlantic | C35: ='AEO 2023 Table 59 Raw'!F26 -> 0 | D35: ='AEO 2023 Table 59 Raw'!G26 -> 0 | E35: ='AEO 2023 Table 59 Raw'!H26 -> 0 | F35: ='AEO 2023 Table 59 Raw'!I26 -> 0 | G35: ='AEO 2023 Table 59 Raw'!J26 -> 0 | H35: ='AEO 2023 Table 59 Raw'!K26 -> 0 | I35: ='AEO 2023 Table 59 Raw'!L26 -> 0 | J35: ='AEO 2023 Table 59 Raw'!M26 -> 0 | ... AF35: ='AEO 2023 Table 59 Raw'!AI26 -> - -
A36: L48000:da_Atlanticstate | B36: State | C36: ='AEO 2023 Table 59 Raw'!F27 -> 0 | D36: ='AEO 2023 Table 59 Raw'!G27 -> 0 | E36: ='AEO 2023 Table 59 Raw'!H27 -> 0 | F36: ='AEO 2023 Table 59 Raw'!I27 -> 0 | G36: ='AEO 2023 Table 59 Raw'!J27 -> 0 | H36: ='AEO 2023 Table 59 Raw'!K27 -> 0 | I36: ='AEO 2023 Table 59 Raw'!L27 -> 0 | J36: ='AEO 2023 Table 59 Raw'!M27 -> 0 | ... AF36: ='AEO 2023 Table 59 Raw'!AI27 -> - -
A37: L48000:da_Atlanticfed | B37: Federal | C37: ='AEO 2023 Table 59 Raw'!F28 -> 0 | D37: ='AEO 2023 Table 59 Raw'!G28 -> 0 | E37: ='AEO 2023 Table 59 Raw'!H28 -> 0 | F37: ='AEO 2023 Table 59 Raw'!I28 -> 0 | G37: ='AEO 2023 Table 59 Raw'!J28 -> 0 | H37: ='AEO 2023 Table 59 Raw'!K28 -> 0 | I37: ='AEO 2023 Table 59 Raw'!L28 -> 0 | J37: ='AEO 2023 Table 59 Raw'!M28 -> 0 | ... AF37: ='AEO 2023 Table 59 Raw'!AI28 -> - -
B40: Supply Prices
B41: (2021 dollars per million Btu)
A42: L48000:fa_HenryHub | B42: Henry Hub Spot Price | C42: ='AEO 2023 Table 59 Raw'!F31 -> 6.523997 | D42: ='AEO 2023 Table 59 Raw'!G31 -> 5.266376 | E42: ='AEO 2023 Table 59 Raw'!H31 -> 4.072381 | F42: ='AEO 2023 Table 59 Raw'!I31 -> 3.489514 | G42: ='AEO 2023 Table 59 Raw'!J31 -> 3.065508 | H42: ='AEO 2023 Table 59 Raw'!K31 -> 2.853001 | I42: ='AEO 2023 Table 59 Raw'!L31 -> 2.799904 | J42: ='AEO 2023 Table 59 Raw'!M31 -> 2.825097 | ... AF42: ='AEO 2023 Table 59 Raw'!AI31 -> -0.019
A43: L48000:fa_Lower48AveBtu | B43: Lower 48 Average Price | C43: ='AEO 2023 Table 59 Raw'!F32 -> 5.108581 | D43: ='AEO 2023 Table 59 Raw'!G32 -> 4.496722 | E43: ='AEO 2023 Table 59 Raw'!H32 -> 3.469988 | F43: ='AEO 2023 Table 59 Raw'!I32 -> 2.892442 | G43: ='AEO 2023 Table 59 Raw'!J32 -> 2.459758 | H43: ='AEO 2023 Table 59 Raw'!K32 -> 2.225519 | I43: ='AEO 2023 Table 59 Raw'!L32 -> 2.133026 | J43: ='AEO 2023 Table 59 Raw'!M32 -> 2.115468 | ... AF43: ='AEO 2023 Table 59 Raw'!AI32 -> -0.023
B45: (2021 dollars per thousand cubic feet)
A46: L48000:fa_Lower48Averag | B46: Lower 48 Average Price | C46: ='AEO 2023 Table 59 Raw'!F34 -> 5.297598 | D46: ='AEO 2023 Table 59 Raw'!G34 -> 4.6631 | E46: ='AEO 2023 Table 59 Raw'!H34 -> 3.598378 | F46: ='AEO 2023 Table 59 Raw'!I34 -> 2.999462 | G46: ='AEO 2023 Table 59 Raw'!J34 -> 2.550768 | H46: ='AEO 2023 Table 59 Raw'!K34 -> 2.307863 | I46: ='AEO 2023 Table 59 Raw'!L34 -> 2.211948 | J46: ='AEO 2023 Table 59 Raw'!M34 -> 2.19374 | ... AF46: ='AEO 2023 Table 59 Raw'!AI34 -> -0.023
B48: Lower 48 Onshore Price
A49: L48000:ga_Northeast | B49: East | C49: ='AEO 2023 Table 59 Raw'!F36 -> 4.495963 | D49: ='AEO 2023 Table 59 Raw'!G36 -> 4.408257 | E49: ='AEO 2023 Table 59 Raw'!H36 -> 3.439742 | F49: ='AEO 2023 Table 59 Raw'!I36 -> 2.828316 | G49: ='AEO 2023 Table 59 Raw'!J36 -> 2.367009 | H49: ='AEO 2023 Table 59 Raw'!K36 -> 2.105921 | I49: ='AEO 2023 Table 59 Raw'!L36 -> 1.970865 | J49: ='AEO 2023 Table 59 Raw'!M36 -> 1.903738 | ... AF49: ='AEO 2023 Table 59 Raw'!AI36 -> -0.027
A50: L48000:ga_GulfCoast | B50: Gulf Coast | C50: ='AEO 2023 Table 59 Raw'!F37 -> 6.342973 | D50: ='AEO 2023 Table 59 Raw'!G37 -> 5.063886 | E50: ='AEO 2023 Table 59 Raw'!H37 -> 3.842494 | F50: ='AEO 2023 Table 59 Raw'!I37 -> 3.246102 | G50: ='AEO 2023 Table 59 Raw'!J37 -> 2.813074 | H50: ='AEO 2023 Table 59 Raw'!K37 -> 2.59683 | I50: ='AEO 2023 Table 59 Raw'!L37 -> 2.544311 | J50: ='AEO 2023 Table 59 Raw'!M37 -> 2.572556 | ... AF50: ='AEO 2023 Table 59 Raw'!AI37 -> -0.021
A51: L48000:ga_Midcontinent | B51: Midcontinent | C51: ='AEO 2023 Table 59 Raw'!F38 -> 5.891514 | D51: ='AEO 2023 Table 59 Raw'!G38 -> 4.685303 | E51: ='AEO 2023 Table 59 Raw'!H38 -> 3.587715 | F51: ='AEO 2023 Table 59 Raw'!I38 -> 3.005321 | G51: ='AEO 2023 Table 59 Raw'!J38 -> 2.556094 | H51: ='AEO 2023 Table 59 Raw'!K38 -> 2.317663 | I51: ='AEO 2023 Table 59 Raw'!L38 -> 2.240961 | J51: ='AEO 2023 Table 59 Raw'!M38 -> 2.263006 | ... AF51: ='AEO 2023 Table 59 Raw'!AI38 -> -0.023
A52: L48000:ga_Southwest | B52: Southwest | C52: ='AEO 2023 Table 59 Raw'!F39 -> 6.005493 | D52: ='AEO 2023 Table 59 Raw'!G39 -> 4.693 | E52: ='AEO 2023 Table 59 Raw'!H39 -> 3.529354 | F52: ='AEO 2023 Table 59 Raw'!I39 -> 2.956786 | G52: ='AEO 2023 Table 59 Raw'!J39 -> 2.519996 | H52: ='AEO 2023 Table 59 Raw'!K39 -> 2.293305 | I52: ='AEO 2023 Table 59 Raw'!L39 -> 2.226445 | J52: ='AEO 2023 Table 59 Raw'!M39 -> 2.248604 | ... AF52: ='AEO 2023 Table 59 Raw'!AI39 -> -0.022
A53: L48000:ga_RockyMountain | B53: Rocky Mountain | C53: ='AEO 2023 Table 59 Raw'!F40 -> 5.742832 | D53: ='AEO 2023 Table 59 Raw'!G40 -> 4.626787 | E53: ='AEO 2023 Table 59 Raw'!H40 -> 3.54197 | F53: ='AEO 2023 Table 59 Raw'!I40 -> 2.958944 | G53: ='AEO 2023 Table 59 Raw'!J40 -> 2.511465 | H53: ='AEO 2023 Table 59 Raw'!K40 -> 2.263142 | I53: ='AEO 2023 Table 59 Raw'!L40 -> 2.176153 | J53: ='AEO 2023 Table 59 Raw'!M40 -> 2.184029 | ... AF53: ='AEO 2023 Table 59 Raw'!AI40 -> -0.021
A54: L48000:ga_NoGreatPlains | B54: Northern Great Plains | C54: ='AEO 2023 Table 59 Raw'!F41 -> 6.959198 | D54: ='AEO 2023 Table 59 Raw'!G41 -> 5.646724 | E54: ='AEO 2023 Table 59 Raw'!H41 -> 4.429469 | F54: ='AEO 2023 Table 59 Raw'!I41 -> 3.909585 | G54: ='AEO 2023 Table 59 Raw'!J41 -> 3.500575 | H54: ='AEO 2023 Table 59 Raw'!K41 -> 3.22762 | I54: ='AEO 2023 Table 59 Raw'!L41 -> 3.110677 | J54: ='AEO 2023 Table 59 Raw'!M41 -> 3.086089 | ... AF54: ='AEO 2023 Table 59 Raw'!AI41 -> -0.019
A55: L48000:ga_WestCoast | B55: West Coast | C55: ='AEO 2023 Table 59 Raw'!F42 -> 4.86809 | D55: ='AEO 2023 Table 59 Raw'!G42 -> 4.041528 | E55: ='AEO 2023 Table 59 Raw'!H42 -> 3.370783 | F55: ='AEO 2023 Table 59 Raw'!I42 -> 2.855986 | G55: ='AEO 2023 Table 59 Raw'!J42 -> 2.466662 | H55: ='AEO 2023 Table 59 Raw'!K42 -> 2.248124 | I55: ='AEO 2023 Table 59 Raw'!L42 -> 2.187892 | J55: ='AEO 2023 Table 59 Raw'!M42 -> 2.198744 | ... AF55: ='AEO 2023 Table 59 Raw'!AI42 -> -0.021
B57: Lower 48 Offshore Price
A58: L48000:ha_Gulf | B58: Gulf | C58: ='AEO 2023 Table 59 Raw'!F44 -> 6.426492 | D58: ='AEO 2023 Table 59 Raw'!G44 -> 5.110907 | E58: ='AEO 2023 Table 59 Raw'!H44 -> 3.87916 | F58: ='AEO 2023 Table 59 Raw'!I44 -> 3.278244 | G58: ='AEO 2023 Table 59 Raw'!J44 -> 2.838944 | H58: ='AEO 2023 Table 59 Raw'!K44 -> 2.61611 | I58: ='AEO 2023 Table 59 Raw'!L44 -> 2.561345 | J58: ='AEO 2023 Table 59 Raw'!M44 -> 2.588378 | ... AF58: ='AEO 2023 Table 59 Raw'!AI44 -> -0.021
A59: L48000:ha_Pacific | B59: Pacific | C59: ='AEO 2023 Table 59 Raw'!F45 -> 6.005988 | D59: ='AEO 2023 Table 59 Raw'!G45 -> 6.005988 | E59: ='AEO 2023 Table 59 Raw'!H45 -> 6.005988 | F59: ='AEO 2023 Table 59 Raw'!I45 -> 6.005988 | G59: ='AEO 2023 Table 59 Raw'!J45 -> 6.005988 | H59: ='AEO 2023 Table 59 Raw'!K45 -> 6.005988 | I59: ='AEO 2023 Table 59 Raw'!L45 -> 3.115042 | J59: ='AEO 2023 Table 59 Raw'!M45 -> 3.088059 | ... AF59: ='AEO 2023 Table 59 Raw'!AI45 -> -0.014
A60: L48000:ha_Atlantic | B60: Atlantic | C60: ='AEO 2023 Table 59 Raw'!F46 -> - - | D60: ='AEO 2023 Table 59 Raw'!G46 -> - - | E60: ='AEO 2023 Table 59 Raw'!H46 -> - - | F60: ='AEO 2023 Table 59 Raw'!I46 -> - - | G60: ='AEO 2023 Table 59 Raw'!J46 -> - - | H60: ='AEO 2023 Table 59 Raw'!K46 -> - - | I60: ='AEO 2023 Table 59 Raw'!L46 -> - - | J60: ='AEO 2023 Table 59 Raw'!M46 -> - - | ... AF60: ='AEO 2023 Table 59 Raw'!AI46 -> - -
B62: Shale Gas Plays
B63: Barnett | C63: 0.602709 | D63: 0.515749 | E63: 0.45862 | F63: 0.421902 | G63: 0.389087 | H63: 0.355368 | I63: 0.31897 | J63: 0.279774 | K63: 0.247751 | L63: 0.219258 | M63: 0.192589 | N63: 0.17217 | O63: 0.150776 | P63: 0.134399 | Q63: 0.119792 | R63: 0.106633 | S63: 0.094436 | T63: 0.083187 | U63: 0.074682 | V63: 0.065289 | W63: 0.056792 | X63: 0.051069 | Y63: 0.042814 | Z63: 0.03853 | AA63: 0.050213 | AB63: 0.052223 | AC63: 0.053956 | AD63: 0.057516 | AE63: 0.06485 | AF63: -0.074114985
B64: Haynesville/Bossier | C64: 5.082581 | D64: 5.666948 | E64: 5.771996 | F64: 5.665076 | G64: 5.552168 | H64: 5.523814 | I64: 5.595086 | J64: 5.644664 | K64: 5.674849 | L64: 5.795424 | M64: 5.850874 | N64: 5.701812 | O64: 5.621414 | P64: 5.561186 | Q64: 5.489774 | R64: 5.406096 | S64: 5.308152 | T64: 5.190531 | U64: 5.092913 | V64: 5.005298 | W64: 4.865066 | X64: 4.739606 | Y64: 4.564822 | Z64: 4.425786 | AA64: 4.306918 | AB64: 4.216811 | AC64: 4.141778 | AD64: 4.067255 | AE64: 4.002763 | AF64: 0.0038081429
B65: Fayetteville | C65: 0.389257 | D65: 0.373596 | E65: 0.362119 | F65: 0.355016 | G65: 0.346505 | H65: 0.337825 | I65: 0.328251 | J65: 0.317772 | K65: 0.307938 | L65: 0.298499 | M65: 0.288996 | N65: 0.280546 | O65: 0.271018 | P65: 0.263556 | Q65: 0.255731 | R65: 0.248114 | S65: 0.240661 | T65: 0.23333 | U65: 0.226501 | V65: 0.219544 | W65: 0.21273 | X65: 0.206532 | Y65: 0.199859 | Z65: 0.194017 | AA65: 0.188268 | AB65: 0.182612 | AC65: 0.177263 | AD65: 0.171695 | AE65: 0.166632 | AF65: -0.029238623
B66: Woodford | C66: 0.949789 | D66: 0.839754 | E66: 0.830345 | F66: 0.820068 | G66: 0.810369 | H66: 0.805098 | I66: 0.81403 | J66: 0.797237 | K66: 0.780796 | L66: 0.773373 | M66: 0.771632 | N66: 0.767671 | O66: 0.744561 | P66: 0.726607 | Q66: 0.70906 | R66: 0.736259 | S66: 0.742999 | T66: 0.737676 | U66: 0.749985 | V66: 0.787694 | W66: 0.818863 | X66: 0.833139 | Y66: 0.827254 | Z66: 0.825882 | AA66: 0.8778 | AB66: 0.901156 | AC66: 0.914868 | AD66: 0.930785 | AE66: 0.960517 | AF66: -0.0016966053
B67: Eagle Ford | C67: 1.504324 | D67: 1.581611 | E67: 1.617322 | F67: 1.736254 | G67: 1.799061 | H67: 1.851364 | I67: 1.920302 | J67: 1.983822 | K67: 2.049443 | L67: 2.092327 | M67: 2.113713 | N67: 2.073844 | O67: 1.998679 | P67: 1.969679 | Q67: 1.947011 | R67: 1.930375 | S67: 1.913574 | T67: 1.896845 | U67: 1.880102 | V67: 1.858191 | W67: 1.825808 | X67: 1.800479 | Y67: 1.756254 | Z67: 1.748397 | AA67: 1.730729 | AB67: 1.714616 | AC67: 1.676909 | AD67: 1.641407 | AE67: 1.617366 | AF67: 0.0030652681
B68: Antrim | C68: 0.040036 | D68: 0.033991 | E68: 0.035609 | F68: 0.037323 | G68: 0.037736 | H68: 0.037662 | I68: 0.037335 | J68: 0.036817 | K68: 0.036674 | L68: 0.036711 | M68: 0.036654 | N68: 0.036949 | O68: 0.037225 | P68: 0.03764 | Q68: 0.037946 | R68: 0.038248 | S68: 0.038574 | T68: 0.03895 | U68: 0.039374 | V68: 0.039859 | W68: 0.04034 | X68: 0.040859 | Y68: 0.041308 | Z68: 0.041719 | AA68: 0.042128 | AB68: 0.042575 | AC68: 0.042997 | AD68: 0.043485 | AE68: 0.043992 | AF68: -0.010644213
B69: Marcellus | C69: 9.882874 | D69: 9.682184 | E69: 9.466339 | F69: 9.210995 | G69: 9.168756 | H69: 9.18716 | I69: 9.34754 | J69: 9.564765 | K69: 9.669225 | L69: 9.60283 | M69: 9.66012 | N69: 9.733713 | O69: 9.851462 | P69: 9.82138 | Q69: 9.951206 | R69: 10.028527 | S69: 10.108671 | T69: 10.19431 | U69: 10.310494 | V69: 10.442215 | W69: 10.56158 | X69: 10.54293 | Y69: 10.506332 | Z69: 10.556562 | AA69: 10.61714 | AB69: 10.603475 | AC69: 10.634814 | AD69: 10.655152 | AE69: 10.70049 | AF69: 0.0073624955
B70: Bakken | C70: 0.729813 | D70: 0.739442 | E70: 0.752427 | F70: 0.80099 | G70: 0.810604 | H70: 0.810857 | I70: 0.813417 | J70: 0.808258 | K70: 0.799534 | L70: 0.783041 | M70: 0.775679 | N70: 0.769711 | O70: 0.766743 | P70: 0.763155 | Q70: 0.758029 | R70: 0.751599 | S70: 0.746067 | T70: 0.748871 | U70: 0.747613 | V70: 0.749618 | W70: 0.748495 | X70: 0.73975 | Y70: 0.72936 | Z70: 0.718389 | AA70: 0.71018 | AB70: 0.697016 | AC70: 0.684914 | AD70: 0.675216 | AE70: 0.66457 | AF70: -0.00079115526
B71: Utica | C71: 2.970921 | D71: 3.060587 | E71: 2.873947 | F71: 2.714928 | G71: 2.613579 | H71: 2.588693 | I71: 2.580542 | J71: 2.506026 | K71: 2.379374 | L71: 2.623072 | M71: 2.743765 | N71: 2.824784 | O71: 3.051888 | P71: 3.097809 | Q71: 3.143046 | R71: 3.289969 | S71: 3.347322 | T71: 3.452139 | U71: 3.571692 | V71: 3.656769 | W71: 3.684707 | X71: 3.908351 | Y71: 4.126873 | Z71: 4.185009 | AA71: 4.231706 | AB71: 4.483768 | AC71: 4.645783 | AD71: 4.696206 | AE71: 4.776205 | AF71: 0.018585317
B72: Other | C72: 5.010411 | D72: 5.32651 | E72: 6.066134 | F72: 6.605976 | G72: 7.067448 | H72: 7.431614 | I72: 7.772848 | J72: 8.008885 | K72: 8.188647 | L72: 8.284155 | M72: 8.443089 | N72: 8.565622 | O72: 8.593579 | P72: 8.596869 | Q72: 8.654397 | R72: 8.726677 | S72: 8.83795 | T72: 9.002231 | U72: 9.159966 | V72: 9.243934 | W72: 9.433949 | X72: 9.628787 | Y72: 9.904388 | Z72: 10.075343 | AA72: 10.232612 | AB72: 10.339174 | AC72: 10.486917 | AD72: 10.584052 | AE72: 10.671181 | AF72: 0.02220982
B73: Total | C73: 27.162714 | D73: 27.82037 | E73: 28.234859 | F73: 28.368526 | G73: 28.595314 | H73: 28.929455 | I73: 29.52832 | J73: 29.948021 | K73: 30.134232 | L73: 30.50869 | M73: 30.87711 | N73: 30.926821 | O73: 31.087345 | P73: 30.972282 | Q73: 31.06599 | R73: 31.262495 | S73: 31.378407 | T73: 31.578072 | U73: 31.853321 | V73: 32.068413 | W73: 32.248333 | X73: 32.491501 | Y73: 32.699265 | Z73: 32.809635 | AA73: 32.987694 | AB73: 33.233425 | AC73: 33.460197 | AD73: 33.522774 | AE73: 33.668564 | AF73: 0.010448501
B78: 1/ Marketed production (wet) minus extraction losses.
B79: - - = Not applicable.
B80: Note: Oil and Gas Supply Model regions are defined in Assumptions to the Annual Energy Outlook. Totals may not equal sum of
B81: components due to independent rounding.
B82: Sources: 2021: U.S. Energy Information Administration (EIA), Short-Term Energy Outlook, November 2021 and EIA, AEO2022
B83: National Energy Modeling System run ref2022.d011222a. Projections: EIA, AEO2022 National Energy Modeling System run ref2022.d011222a.

Sheet GREET1 Fuel_Specs
A1: Specifications of Fuels, Global Warming Potentials of Greenhouse Gases, and Carbon and Sulfur Ratios of Pollutants
A2: 1) Specifications of Fuels
A3: Fuel | B3: Heating Value | E3: Density | F3: C ratio | G3: S ratio | H3: S ratio
B4: Calculation: LHV | C4: LHV | D4: HHV | F4: (% by wt) | G4: (ppm by wt) | H4: Actual ratio by wt | I4: LHV/HHV
A5: Use LHV or HHV in calculations? | B5: 1 | C5: 1 -- LHV; 2 -- HHV
A6: Liquid Fuels: | B6: Btu/gal | C6: Btu/gal | D6: Btu/gal | E6: grams/gal
A7: Crude oil | B7: 129670 | C7: 129670 | D7: 138350 | E7: 3205 | F7: 0.853 | G7: 16000 | H7: 0.016 | I7: 0.93726057
A8: Synthetic crude oil (SCO) | B8: 135084.91 | C8: 135084.91 | D8: 144475.84 | E8: 3266 | F8: 0.85562069 | G8: 1800 | H8: 0.0018 | I8: 0.935
A9: Bitumen | B9: 152370.9 | C9: 152370.9 | D9: 162963.53 | E9: 3839.6821 | F9: 0.83 | G9: 48000 | H9: 0.048 | I9: 0.935
A10: Dilbit (After Recovery) | B10: 152370.9 | C10: 152370.9 | D10: 162963.53 | E10: 3839.6821 | F10: 0.83 | G10: 48000 | H10: 0.048 | I10: 0.935
A11: Dilbit (Before Recovery) | B11: 145194.19 | C11: 145194.19 | D11: 155287.9 | E11: 3500.4775 | F11: 0.83245886 | G11: 37227.39 | H11: 0.03722739 | I11: 0.935
A12: Diluent | B12: 128448.53 | C12: 128448.53 | D12: 137378.1 | E12: 2709 | F12: 0.84059084 | G12: 1600 | H12: 0.0016 | I12: 0.935
A13: Shale Oil (Bakken) | B13: 125600.91 | C13: 125600.91 | D13: 134008.53 | E13: 3087.2372 | F13: 0.853 | G13: 16000 | H13: 0.016 | I13: 0.93726057
A14: Shale Oil (Eagle Ford) | B14: 122492.61 | C14: 122492.61 | D14: 130692.16 | E14: 2984.0427 | F14: 0.853 | G14: 16000 | H14: 0.016 | I14: 0.93726057
A15: Gasoline blendstock | B15: 116090 | C15: 116090 | D15: 124340 | E15: 2819 | F15: 0.863 | G15: 10 | H15: 1e-05 | I15: 0.93364967
A16: Gasoline | B16: 112193.52 | C16: 112193.52 | D16: 120438.62 | E16: 2835.562 | F16: 0.82778547 | G16: 9.0261788 | H16: 9.0261788e-06 | I16: 0.93154106
A17: CA gasoline | B17: 112193.52 | C17: 112193.52 | D17: 120438.62 | E17: 2835.562 | F17: 0.82778547 | G17: 9.0261788 | H17: 9.0261788e-06 | I17: 0.93154106
A18: High Octane Fuel (E25) | B18: 106150 | C18: 106150 | D18: 114387.5 | E18: 2861.25 | F18: 0.77775 | G18: 7.6425 | H18: 7.6425e-06 | I18: 0.92798601
... A20: U.S. conventional diesel | B20: 128450 | C20: 128450 | D20: 137380 | E20: 3167 | F20: 0.865 | G20: 200 | H20: 0.0002 | I20: 0.93499782
A21: CA diesel | B21: 129487.85 | C21: 129487.85 | D21: 138490 | E21: 3206 | F21: 0.871 | G21: 11 | H21: 1.1e-05
A22: Diesel for non-road engines | B22: 128450 | C22: 128450 | D22: 137380 | E22: 3167 | F22: 0.865 | G22: 11 | H22: 1.1e-05 | I22: 0.93499782
A23: Low-sulfur diesel | B23: 129487.85 | C23: 129487.85 | D23: 138490 | E23: 3206 | F23: 0.871 | G23: 11 | H23: 1.1e-05 | I23: 0.93499782
A24: Petroleum naphtha | B24: 116920 | C24: 116920 | D24: 125080 | E24: 2745 | F24: 0.85 | G24: 1 | H24: 1e-06 | I24: 0.93476175
A25: Low Octane Gasoline-Like Fuel (LOF) | B25: 118237.43 | C25: 118237.43 | D25: 126586.16 | E25: 2833.857 | F25: 0.85315639 | G25: 10 | H25: 1e-05 | I25: 0.93404711
A26: Conventional Jet Fuel | B26: 124307.03 | C26: 124307.03 | D26: 132948.69 | E26: 3035.8996 | F26: 0.862 | G26: 700 | H26: 0.0007 | I26: 0.93500004
A27: ULS Jet Fuel | B27: 123041.23 | C27: 123041.23 | D27: 131594.89 | E27: 2998.0455 | F27: 0.86 | G27: 11 | H27: 1.1e-05 | I27: 0.93500004
A28: NG-based FT naphtha | B28: 111520 | C28: 111520 | D28: 119740 | E28: 2651 | F28: 0.842 | G28: 0 | H28: 0 | I28: 0.93135126
A29: Residual oil | B29: 140352.52 | C29: 140352.52 | D29: 150110 | E29: 3752 | F29: 0.868 | G29: 5000 | H29: 0.005 | I29: 0.93499782
A30: Bunker fuel for ocean tanker | B30: 140352.52 | C30: 140352.52 | D30: 150110 | E30: 3752 | F30: 0.868 | G30: 27000 | H30: 0.027 | I30: 0.93499782
A31: Methanol | B31: 57250 | C31: 57250 | D31: 65200 | E31: 3006 | F31: 0.375 | G31: 0 | H31: 0 | I31: 0.87806748
A32: Ethanol | B32: 76330 | C32: 76330 | D32: 84530 | E32: 2988 | F32: 0.522 | G32: 0.57000011 | H32: 5.7000011e-07 | I32: 0.90299302
A33: Butanol | B33: 99837 | C33: 99837 | D33: 108458 | E33: 3065 | F33: 0.6486 | G33: 0 | H33: 0 | I33: 0.92051301
... A56: Propane | B56: 84250 | C56: 84250 | D56: 91420 | E56: 1920 | F56: 0.818 | G56: 0 | H56: 0 | I56: 0.92157077
A57: Natural gas liquids | B57: 83686.112 | C57: 83686.112 | D57: 90050 | E57: 2532 | G57: 0 | H57: 0 | I57: 0.9293294
A58: n-Hexane | B58: 105124.8 | C58: 105124.8 | D58: 112166.3 | E58: 2478.7 | F58: 0.836251 | G58: 0 | H58: 0 | I58: 0.93722268
A59: Gaseous Fuels (at 32F and 1atm): | B59: Btu/ft3 | C59: Btu/ft3 | D59: Btu/ft3 | E59: gms/ft3 | I59: LHV/HHV
A60: Natural gas | B60: 983 | C60: 983 | D60: 1089 | E60: 22 | F60: 0.724 | G60: 6 | H60: 6e-06 | I60: 0.90266299
A61: Pure Methane | B61: 962.18505 | C61: 962.18505 | D61: 1068.0254 | E61: 20.303179 | F61: 0.75 | G61: 0 | H61: 0 | I61: 0.9009009
A62: Gaseous hydrogen | B62: 290 | C62: 290 | D62: 343 | E62: 2.55 | F62: 0 | G62: 0 | H62: 0 | I62: 0.84548105
A63: Carbon Dioxide | E63: 55.97783 | F63: 0.27272727 | G63: 0 | H63: 0
A64: Still gas (in refineries) | B64: 1159.2737 | C64: 1159.2737 | D64: 1279.7381 | E64: 25.019852 | F64: 0.76981386 | G64: 6 | H64: 6e-06 | I64: 0.9058679
A65: Solid Fuels: | B65: Btu/ton | C65: Btu/ton | D65: Btu/ton | I65: LHV/HHV
A66: Coal Mix for Electricity Generation | B66: 19474169 | C66: 19474169 | D66: 20673610 | F66: 0.5857111 | G66: 10455.988 | H66: 0.010455988
A67: Bituminous coal | B67: 22639320 | C67: 22639320 | D67: 23633493 | F67: 0.612 | G67: 15352.093 | H67: 0.015352093 | I67: 0.95793373
A68: Subbituminous coal | B68: 16085444 | C68: 16085444 | D68: 17449320 | F68: 0.537 | G68: 3568.2537 | H68: 0.0035682537 | I68: 0.92183789
A69: Lignite coal | B69: 10805183 | C69: 10805183 | D69: 12992302 | F69: 0.491 | G69: 9064.2347 | H69: 0.0090642347 | I69: 0.83166038
A70: Synthetic coal | B70: 22639320 | C70: 22639320 | D70: 23633493 | F70: 0.8064205 | G70: 16142.739 | H70: 0.016142739 | I70: 0.95793373
A71: Waste coal | B71: 9945646.3 | C71: 9945646.3 | D71: 11958783 | F71: 0.32642858 | G71: 9064.2347 | H71: 0.0090642347 | I71: 0.83166038
A72: Pet Coke | B72: 26949429 | C72: 26949429 | D72: 28595925 | F72: 0.8667 | G72: 45137.714 | H72: 0.045137714 | I72: 0.94242199
A73: Tire Derived Fuel | B73: 26664354 | C73: 26664354 | D73: 28293434 | F73: 0.48798697 | G73: 45137.714 | H73: 0.045137714 | I73: 0.94242199
A74: Coking coal | B74: 24599422 | C74: 24599422 | D74: 25679670 | F74: 0.747 | G74: 11800 | H74: 0.0118 | I74: 0.95793373
A75: Catalyst Coke | B75: 28385750 | C75: 28385750 | D75: 30120000 | F75: 0.86413234 | G75: 45137.714 | H75: 0.045137714 | I75: 0.94242199
A76: Willow | B76: 15396000 | C76: 15396000 | D76: 16524000 | F76: 0.487 | G76: 500 | H76: 0.0005 | I76: 0.93173566
A77: Poplar | B77: 15929000 | C77: 15929000 | D77: 17062000 | F77: 0.501 | G77: 200 | H77: 0.0002 | I77: 0.93359512
A78: Switchgrass | B78: 14447000 | C78: 14447000 | D78: 15583000 | F78: 0.466 | G78: 1100 | H78: 0.0011 | I78: 0.92710004
... A82: Clean Pine | B82: 15929000 | C82: 15929000 | D82: 17062000 | F82: 0.501 | G82: 200 | H82: 0.0002 | I82: 0.93359512
A83: Yard trimming waste | B83: 15000000 | C83: 15000000 | F83: 0.478 | G83: 400 | H83: 0.0004
A84: Sugarcane straw | B84: 13454049 | C84: 13454049 | D84: 15774000 | F84: 0.5 | I84: 0.85292563
A85: Sugarcane bagasse | B85: 12381771 | C85: 12381771 | D85: 14062678 | F85: 0.463 | I85: 0.88047037
A86: Bio-char | B86: 18916911 | C86: 18916911 | D86: 18916911 | F86: 0.512 | G86: 0 | H86: 0 | I86: 1
A87: Grain sorghum bagasse | B87: 12781599 | C87: 12781599 | D87: 14131556 | F87: 0.3934 | G87: 0 | H87: 0 | I87: 0.90447216
A88: Sweet sorghum bagasse | B88: 14409931 | C88: 14409931 | D88: 15305245 | F88: 0.41985 | G88: 0 | H88: 0 | I88: 0.94150281
A89: Forage sorghum bagasse | B89: 14409931 | C89: 14409931 | D89: 15305245 | F89: 0.41985 | G89: 0 | H89: 0 | I89: 0.94150281
A90: Municipal solid waste (defined by EISA) | B90: 11209639 | C90: 11209639 | D90: 13583445 | F90: 0.49161518 | G90: 1765.2251 | H90: 0.0017652251 | I90: 0.82524272
A91: Convertible municipal solid waste | B91: 14155275 | C91: 14155275 | D91: 16144033 | F91: 0.5049151 | G91: 1787.3101 | H91: 0.0017873101 | I91: 0.87681159
A92: Asphalt | B92: 152370.9 | C92: 152370.9 | D92: 162963.53 | E92: 3839.6821 | F92: 0.83 | G92: 48000 | H92: 0.048 | I92: 0.935
A93: Lubricants | B93: 144230 | E93: 3785.411 | F93: 0.80800504 | G93: 3510
A95: 2) Global Warming Potentials of Greenhouse Gases: relative to CO2
A96: Metrics for Carbon Dioxide, Methane, Nitrous Oxide
A97: AR Edition/Type | B97: AR5/GWP | C97: AR5/GWP | D97: AR5/GWP | E97: AR5/GTP | F97: AR5/GTP | G97: AR4/GWP | H97: AR4/GWP | I97: AR3/GWP | J97: AR3/GWP | K97: AR2/GWP | L97: AR2/GWP | M97: AR1/GWP | N97: AR1/GWP
A98: Time Horizon (YR) | B98: 100 | C98: 100 | D98: 20 | E98: 100 | F98: 20 | G98: 100 | H98: 20 | I98: 100 | J98: 20 | K98: 100 | L98: 20 | M98: 100 | N98: 20
