Workbook

Sheet About
A1: AVIC Annual Vehicle Insurance Cost
A3: Source: | B3: Passenger LDVs
B4: Asociación Mexicana de Instituciones de seguros AMIS
B5: 2022
B6: https://centroestadisticoamis.mx/finanzas-reportes-en-excel/
B8: Freight LDVs
B9: Car and Driver magazine
B10: 2021
B11: Commercial Auto Insurance Cost: Everything You Need to Know
B12: https://www.caranddriver.com/car-insurance/a36232977/commercial-auto-insurance-cost/
B14: Freight HDVs
B15: Progressive Commercial
B16: undated
B17: What does commercial truck insurance cost?
B18: https://www.progressivecommercial.com/commercial-auto-insurance/truck-insurance/commercial-truck-insurance-cost/
B20: Passenger HDVs (buses)
B21: Bus Insurance HQ
B22: undated
B23: https://www.businsurancehq.com/bus-insurance-cost/
B25: Passenger Motorbikes
B26: Cotizador.com
B27: 2022
B28: Average Cost of Motorcycle Insurance (2022)
B29: https://cotizator.com/seguros-para-motos/
A31: Notes
A32: Data on insurnace costs for LDVs is available online.
A33: Freight and HDV costs derived from US price ratios.
A35: Insurance costs for rail, commercial airlines, and freight shipping is harder to come by. It appears these firms
A36: often buy policies covering a broader share of company operations, not just individual vehicles. For instance,
A37: a railroad's insurance might cover up to $X million in damages/liability from covered causes across the railroad's
A38: entire system, and would include things like damage caused by spills, collisions, etc.
A39: It appears that per-vehicle insurance may not be the correct way to price insurance costs for commercial
A40: airlines, rail, or freight shipping, so we leave those values set to zero in this variable.
A42: Currency Conversion from CPI
A44: 0.89805482 | B44: 2019 to 2012 USD
A45: 0.88711067 | B45: 2020 to 2012 USD
A46: 0.84730413 | B46: 2021 to 2012 USD
A47: 0.78452102 | B47: 2022 to 2012 USD

Sheet Data
A1: Passenger LDVs | J1: 2020 | K1: 2021 | L1: 2022 | N1: Primas
I2: Parque | J2: 50347569 | K2: 53115396 | L2: 55167421 | N2: 2022 | O2: 2021 | P2: 2022 | Q2: 2021 | R2: 2022 | S2: 2021 | T2: 2022 | U2: 2021
A3: Data from AMIS: | B3: https://centroestadisticoamis.mx/finanzas-reportes-en-excel/ | I3: Asegurados | J3: 14386107 | K3: 15011246 | L3: 15353091 | M3: =L3/L2 -> 0.27829996 | N3: Q4 | O3: Q4 | P3: Q3 | Q3: Q3 | R3: Q2 | S3: Q2 | T3: Q1 | U3: Q1
J4: Primas total | K4: =O4+Q4+S4+U4 -> 1.4690054e+09 | L4: =N4+P4+R4+T4 -> 1.5565527e+09 | N4: 6.6694023e+08 | O4: =633397048.49517 -> 6.3339705e+08 | P4: 5.1413196e+08 | Q4: 4.793301e+08 | R4: 3.5056095e+08 | S4: 3.3585245e+08 | T4: 24919511 | U4: =T4/1.22 -> 20425829
A5: =L6*1000 -> 8448.6389 | B5: $ / yr (2022 Mexican pesos) | K5: =K4/K3 -> 97.860326 | L5: =L4/L3 -> 101.38367
A6: 20.125 | B6: MXN/USD FIX 2022 | K6: =K5/12 -> 8.1550272 | L6: =L5/12 -> 8.4486389 | M6: =L6/K6-1 -> 0.036003761
A7: =A5/A6 -> 419.80815 | B7: USD 2022
E8: US Ref
A9: Passenger LDV | B9: =A7*About!$A$47 -> 329.34832 | C9: $/yr (2012 USD) | E9: 1194
A10: Freight multipier | B10: =D18/E9 -> 3.9782245
A11: Freight LDVs
A13: Using data from Car and Driver magazine (2021):
B15: Low | C15: High | D15: Simple Avg
A16: standard car used for business purposes | B16: 600 | C16: 2400 | D16: =AVERAGE(B16:C16) -> 1500 | E16: $/yr (2021 USD)
A17: Limousine | B17: 4000 | C17: 10000 | D17: =AVERAGE(B17:C17) -> 7000 | E17: $/yr (2021 USD)
A18: Cargo or delivery van | B18: 3300 | C18: 6200 | D18: =AVERAGE(B18:C18) -> 4750 | E18: $/yr (2021 USD)
A19: Taxi | B19: 5000 | C19: 10000 | D19: =AVERAGE(B19:C19) -> 7500 | E19: $/yr (2021 USD)
A20: Semi-truck | B20: 8000 | C20: 12500 | D20: =AVERAGE(B20:C20) -> 10250 | E20: $/yr (2021 USD)
A22: For freight LDVs, the value for "cargo or delivery van" is most appropriate.
A24: Freight HDVs
A26: Avg. for specialty truckers | B26: 640 | C26: $/mth
A27: Avg. for transport truckers | B27: 982 | C27: $/mth
A28: Overall simple average | B28: =AVERAGE(B26:B27) -> 811 | C28: $/mth
A29: Annualized | B29: =B28*12 -> 9732 | C29: $/yr
A31: Likely includes primary liability insurance, physical damage insurance, occupational accident coverage, and general liability insurance.
A32: For more on these insurance types, see https://www.caranddriver.com/car-insurance/a36320549/truck-insurance-cost/
A34: Passenger HDVs (buses)
A36: 50-state average | B36: 9420 | C36: $/yr
A38: Passenger Motorbikes
F39: Aseguradora | G39: R.C. | H39: Limitada | I39: Amplia
A40: https://cotizator.com/seguros-para-motos/ | C40: (2022) | F40: Quálitas | G40: 3879.75 | H40: 5029.91 | I40: 5741.5
A41: =AVERAGE(H40:H42) -> 4031.47 | B41: $ / yr (2022 Mexican pesos) | F41: GNP | G41: 3184.2 | H41: 3703.85 | I41: 4940.21
A42: 20.125 | B42: MXN/USD FIX 2022 | F42: Mapfre | G42: 2803.5 | H42: 3360.65 | I42: 4468.25
A43: =A41/A42 -> 200.32149 | B43: USD 2022
A45: Motorbikes | B45: =A43*About!$A$47 -> 157.15642 | C45: $/yr (2021 USD)

Sheet AVIC
A1: 2012 USD/year | B1: passenger | C1: freight
A2: LDVs | B2: =Data!B9 -> 329.34832 | C2: =B2*Data!B10 -> 1310.2215
A3: HDVs | B3: =Data!B9*Data!B36/Data!E9 -> 2598.3762 | C3: =Data!B9*Data!B29/Data!E9 -> 2684.437
A4: aircraft | B4: 0 | C4: 0
A5: rail | B5: 0 | C5: 0
A6: ships | B6: 0 | C6: 0
A7: motorbikes | B7: =Data!B45*About!A46 -> 133.15929 | C7: =B7 -> 133.15929
