Workbook

Sheet About

Sheet CO2e Emissions
A1: Time (Year) | B1: BAU | C1: Expert | D1: CAS
A2: 2020 | B2: 551.292 | C2: 551.292 | D2: 551.292
A3: 2021 | B3: 571.186 | C3: 571.186 | D3: 571.186
A4: 2022 | B4: 587.302 | C4: 587.302 | D4: 587.302
A5: 2023 | B5: 594.024 | C5: 594.024 | D5: 594.024
A6: 2024 | B6: 602.923 | C6: 602.923 | D6: 602.923
A7: 2025 | B7: 614.923 | C7: 614.923 | D7: 614.923
A8: 2026 | B8: 624.397 | C8: 623.941 | D8: 610.115
A9: 2027 | B9: 631.592 | C9: 630.135 | D9: 600.575
A10: 2028 | B10: 639.76 | C10: 637.555 | D10: 569.329
A11: 2029 | B11: 648.691 | C11: 645.225 | D11: 553.22
A12: 2030 | B12: 659.618 | C12: 654.99 | D12: 543.001
A13: 2031 | B13: 668.669 | C13: 662.726 | D13: 535.76
... A32: 2050 | B32: 878.094 | C32: 767.135 | D32: 199.885

Sheet CO2e Emissions (LULUCF excl)
A1: Time (Year) | B1: BAU | C1: Expert | D1: CAS
A2: 2020 | B2: 533.676 | C2: 533.676 | D2: 533.676
A3: 2021 | B3: 553.667 | C3: 553.667 | D3: 553.667
A4: 2022 | B4: 569.98 | C4: 569.98 | D4: 569.98
A5: 2023 | B5: 576.799 | C5: 576.799 | D5: 576.799
A6: 2024 | B6: 585.894 | C6: 585.894 | D6: 585.894
A7: 2025 | B7: 598.091 | C7: 598.091 | D7: 598.091
A8: 2026 | B8: 607.672 | C8: 607.311 | D8: 593.833
A9: 2027 | B9: 615.019 | C9: 613.848 | D9: 585.233
A10: 2028 | B10: 623.338 | C10: 621.707 | D10: 555.115
A11: 2029 | B11: 632.421 | C11: 629.912 | D11: 540.523
A12: 2030 | B12: 643.5 | C12: 640.307 | D12: 532.224
A13: 2031 | B13: 652.703 | C13: 648.769 | D13: 526.861
... A32: 2050 | B32: 865.014 | C32: 785.147 | D32: 284.091

Sheet CO2e Emissions by Sector-BAU
A1: Time (Year) | B1: Transportation | C1: Electricity | D1: Residential Buildings | E1: Commercial Buildings | F1: Industry | G1: District Heat and Hydrogen | H1: LULUCF | I1: Agriculture | J1: Water and Waste
A2: 2020 | B2: 149.838 | C2: 109.612 | D2: 16.5474 | E2: 4.16586 | F2: 124.17 | G2: 0 | H2: 17.6158 | I2: 79.9983 | J2: 49.3445
A3: 2021 | B3: 153.605 | C3: 118.194 | D3: 16.5469 | E3: 4.18492 | F3: 130.483 | G3: 5.23e-06 | H3: 17.5193 | I3: 80.494 | J3: 50.1587
A4: 2022 | B4: 157.844 | C4: 126.295 | D4: 16.5328 | E4: 4.19914 | F4: 133.136 | G4: 1.0418e-05 | H4: 17.3223 | I4: 80.9725 | J4: 51.0008
A5: 2023 | B5: 162.543 | C5: 124.52 | D5: 16.506 | E5: 4.20967 | F5: 135.757 | G5: 1.5708e-05 | H5: 17.2256 | I5: 81.4487 | J5: 51.815
A6: 2024 | B6: 167.322 | C6: 124.958 | D6: 16.4862 | E6: 4.22107 | F6: 138.353 | G6: 2.0934e-05 | H6: 17.0292 | I6: 81.9246 | J6: 52.629
A7: 2025 | B7: 172.32 | C7: 128.293 | D7: 16.4683 | E7: 4.2316 | F7: 140.933 | G7: 4.2048e-05 | H7: 16.8325 | I7: 82.4025 | J7: 53.443
A8: 2026 | B8: 177.392 | C8: 126.825 | D8: 16.4548 | E8: 4.24362 | F8: 142.916 | G8: 6.324e-05 | H8: 16.7357 | I8: 82.8242 | J8: 54.226
A9: 2027 | B9: 182.716 | C9: 125.095 | D9: 16.4473 | E9: 4.2543 | F9: 145.436 | G9: 0.000100598 | H9: 16.539 | I9: 83.2178 | J9: 54.9809
A10: 2028 | B10: 188.315 | C10: 124.493 | D10: 16.4366 | E10: 4.26632 | F10: 147.301 | G10: 0.00014941 | H10: 16.4426 | I10: 83.6129 | J10: 55.7634
A11: 2029 | B11: 194.222 | C11: 124.45 | D11: 16.4425 | E11: 4.27762 | F11: 149.201 | G11: 0.000226214 | H11: 16.2456 | I11: 84.034 | J11: 56.5458
A12: 2030 | B12: 200.134 | C12: 126.496 | D12: 16.4347 | E12: 4.28892 | F12: 151.107 | G12: 0.000335664 | H12: 16.1491 | I12: 84.4287 | J12: 57.3282
A13: 2031 | B13: 206.045 | C13: 127.323 | D13: 16.3948 | E13: 4.28753 | F13: 152.245 | G13: 0.000484092 | H13: 15.9524 | I13: 84.7136 | J13: 58.0516
... A32: 2050 | B32: 343.926 | C32: 140.919 | D32: 17.0271 | E32: 5.68998 | F32: 193.228 | G32: 0.0163694 | H32: 13.115 | I32: 88.2033 | J32: 71.3637

Sheet CO2e Emissions by Sector-Expert
A1: Time (Year) | B1: Transportation | C1: Electricity | D1: Residential Buildings | E1: Commercial Buildings | F1: Industry | G1: District Heat and Hydrogen | H1: LULUCF | I1: Agriculture | J1: Water and Waste
A2: 2020 | B2: 151.84 | C2: 109.596 | D2: 16.5471 | E2: 4.16604 | F2: 124.17 | G2: 0 | H2: 17.637 | I2: 79.9858 | J2: 49.3557
A3: 2021 | B3: 155.694 | C3: 118.146 | D3: 16.5497 | E3: 4.18505 | F3: 130.491 | G3: 5.23e-06 | H3: 17.4851 | I3: 80.4863 | J3: 50.172
A4: 2022 | B4: 160.041 | C4: 126.305 | D4: 16.5303 | E4: 4.1993 | F4: 133.137 | G4: 1.0418e-05 | H4: 17.3332 | I4: 80.9681 | J4: 50.9886
A5: 2023 | B5: 164.875 | C5: 124.487 | D5: 16.5055 | E5: 4.20939 | F5: 135.736 | G5: 1.5708e-05 | H5: 17.1813 | I5: 81.4491 | J5: 51.8052
A6: 2024 | B6: 169.809 | C6: 124.909 | D6: 16.4831 | E6: 4.22127 | F6: 138.338 | G6: 2.0934e-05 | H6: 17.0294 | I6: 81.9298 | J6: 52.6217
A7: 2025 | B7: 174.966 | C7: 128.225 | D7: 16.4684 | E7: 4.23137 | F7: 140.935 | G7: 4.2048e-05 | H7: 16.8776 | I7: 82.4111 | J7: 53.4379
A8: 2026 | B8: 180.166 | C8: 126.595 | D8: 16.4555 | E8: 4.24216 | F8: 142.778 | G8: 0.0723507 | H8: 16.63 | I8: 82.7865 | J8: 54.2148
A9: 2027 | B9: 185.508 | C9: 124.239 | D9: 16.4395 | E9: 4.25087 | F9: 145.11 | G9: 0.147015 | H9: 16.2868 | I9: 83.1621 | J9: 54.9933
A10: 2028 | B10: 191.148 | C10: 123.607 | D10: 16.4323 | E10: 4.26258 | F10: 146.728 | G10: 0.224075 | H10: 15.8479 | I10: 83.5384 | J10: 55.7698
A11: 2029 | B11: 197.009 | C11: 123.056 | D11: 16.4296 | E11: 4.27191 | F11: 148.383 | G11: 0.303271 | H11: 15.3133 | I11: 83.9159 | J11: 56.5487
A12: 2030 | B12: 202.847 | C12: 124.726 | D12: 16.4213 | E12: 4.28281 | F12: 150.03 | G12: 0.385231 | H12: 14.6831 | I12: 84.2958 | J12: 57.3256
A13: 2031 | B13: 208.631 | C13: 125.451 | D13: 16.3808 | E13: 4.28013 | F13: 150.95 | G13: 0.467149 | H13: 13.9572 | I13: 84.552 | J13: 58.0661
... A32: 2050 | B32: 331.943 | C32: 123.358 | D32: 16.9384 | E32: 5.62032 | F32: 150.621 | G32: 2.46149 | H32: -18.0119 | I32: 87.321 | J32: 66.8564

Sheet CO2e Emissions by Sector-CAS
A1: Time (Year) | B1: Transportation | C1: Electricity | D1: Residential Buildings | E1: Commercial Buildings | F1: Industry | G1: District Heat and Hydrogen | H1: LULUCF | I1: Agriculture | J1: Water and Waste
A2: 2020 | B2: 149.838 | C2: 109.612 | D2: 16.5474 | E2: 4.16586 | F2: 124.17 | G2: 0 | H2: 17.6158 | I2: 79.9983 | J2: 49.3445
A3: 2021 | B3: 153.605 | C3: 118.194 | D3: 16.5469 | E3: 4.18492 | F3: 130.483 | G3: 5.23e-06 | H3: 17.5193 | I3: 80.494 | J3: 50.1587
A4: 2022 | B4: 157.844 | C4: 126.295 | D4: 16.5328 | E4: 4.19914 | F4: 133.136 | G4: 1.0418e-05 | H4: 17.3223 | I4: 80.9725 | J4: 51.0008
A5: 2023 | B5: 162.543 | C5: 124.52 | D5: 16.506 | E5: 4.20967 | F5: 135.757 | G5: 1.5708e-05 | H5: 17.2256 | I5: 81.4487 | J5: 51.815
A6: 2024 | B6: 167.322 | C6: 124.958 | D6: 16.4862 | E6: 4.22107 | F6: 138.353 | G6: 2.0934e-05 | H6: 17.0292 | I6: 81.9246 | J6: 52.629
A7: 2025 | B7: 172.32 | C7: 128.293 | D7: 16.4683 | E7: 4.2316 | F7: 140.933 | G7: 4.1098e-05 | H7: 16.8325 | I7: 82.4025 | J7: 53.443
A8: 2026 | B8: 174.763 | C8: 122.763 | D8: 16.3485 | E8: 4.21369 | F8: 140.821 | G8: 0.286704 | H8: 16.2815 | I8: 82.0507 | J8: 53.1661
A9: 2027 | B9: 176.855 | C9: 113.992 | D9: 16.1516 | E9: 4.17433 | F9: 140.288 | G9: 0.613581 | H9: 15.342 | I9: 81.7227 | J9: 52.8137
A10: 2028 | B10: 178.618 | C10: 102.621 | D10: 15.9564 | E10: 4.1379 | F10: 124.122 | G10: 0.910543 | H10: 14.2141 | I10: 81.3199 | J10: 49.9559
A11: 2029 | B11: 180.119 | C11: 89.3126 | D11: 15.7236 | E11: 4.08595 | F11: 124.22 | G11: 1.22233 | H11: 12.6973 | I11: 81.0389 | J11: 49.466
A12: 2030 | B12: 181.139 | C12: 81.5904 | D12: 15.4767 | E12: 4.03317 | F12: 122.879 | G12: 1.52112 | H12: 10.9924 | I12: 80.7333 | J12: 48.9118
A13: 2031 | B13: 181.65 | C13: 78.3354 | D13: 15.1946 | E13: 3.96472 | F13: 120.629 | G13: 1.80989 | H13: 8.89864 | I13: 80.3303 | J13: 48.4032
... A32: 2050 | B32: 114.92 | C32: 19.5245 | D32: 4.99224 | E32: 1.40346 | F32: 43.7204 | G32: 7.95181 | H32: -84.8058 | I32: 70.6767 | J32: 33.1888

Sheet EG-BAU
A1: Time (Year) | B1: 2020 | C1: 2021 | D1: 2022 | E1: 2023 | F1: 2024 | G1: 2025 | H1: 2026 | I1: 2027 | J1: 2028 | K1: 2029 | L1: 2030 | M1: 2031 | N1: 2032 | O1: 2033 | P1: 2034 | Q1: 2035 | R1: 2036 | S1: 2037 | T1: 2038 | U1: 2039 | V1: 2040 | W1: 2041 | X1: 2042 | Y1: 2043 | Z1: 2044 | AA1: 2045 | AB1: 2046 | AC1: 2047 | AD1: 2048 | AE1: 2049 | AF1: 2050
A2: Output Electricity Generation by Type[hard coal es] : BAU-Adjusted | B2: 13.5351 | C2: 29.6539 | D2: 18.7252 | E2: 19.1984 | F2: 20.0296 | G2: 22.6687 | H2: 21.2581 | I2: 19.7476 | J2: 19.5031 | K2: 17.8576 | L2: 18.6575 | M2: 18.861 | N2: 18.5388 | O2: 19.3929 | P2: 19.4336 | Q2: 19.5589 | R2: 18.3841 | S2: 18.0046 | T2: 17.2068 | U2: 15.6631 | V2: 15.458 | W2: 15.5039 | X2: 15.6555 | Y2: 14.3024 | Z2: 14.5304 | AA2: 14.3677 | AB2: 14.2142 | AC2: 13.0944 | AD2: 12.8953 | AE2: 12.5366 | AF2: 12.6872
A3: Output Electricity Generation by Type[natural gas nonpeaker es] : BAU-Adjusted | B3: 179.7 | C3: 183.099 | D3: 170.429 | E3: 173.272 | F3: 172.278 | G3: 172.529 | H3: 180.411 | I3: 187.443 | J3: 185.317 | K3: 183.805 | L3: 183.257 | M3: 182.439 | N3: 181.749 | O3: 180.829 | P3: 181.029 | Q3: 181.464 | R3: 182.432 | S3: 182.754 | T3: 183.322 | U3: 184.654 | V3: 185.058 | W3: 186.24 | X3: 186.591 | Y3: 187.097 | Z3: 187.15 | AA3: 188.14 | AB3: 188.766 | AC3: 189.193 | AD3: 190.688 | AE3: 193.083 | AF3: 192.497
A4: Output Electricity Generation by Type[nuclear es] : BAU-Adjusted | B4: 10.8829 | C4: 10.8829 | D4: 10.8829 | E4: 10.8829 | F4: 10.8829 | G4: 10.8829 | H4: 10.8829 | I4: 10.8829 | J4: 10.8829 | K4: 10.8829 | L4: 10.8829 | M4: 10.8829 | N4: 10.8829 | O4: 10.8829 | P4: 10.8829 | Q4: 10.8829 | R4: 10.8829 | S4: 10.8829 | T4: 10.8829 | U4: 10.8829 | V4: 10.8829 | W4: 10.8829 | X4: 10.8829 | Y4: 10.8829 | Z4: 10.8829 | AA4: 10.8829 | AB4: 10.8829 | AC4: 10.8829 | AD4: 10.8829 | AE4: 10.8829 | AF4: 10.8829
A5: Output Electricity Generation by Type[hydro es] : BAU-Adjusted | B5: 31.3059 | C5: 31.3059 | D5: 31.3059 | E5: 31.3059 | F5: 31.3059 | G5: 31.3059 | H5: 31.3059 | I5: 31.3059 | J5: 31.3059 | K5: 31.3059 | L5: 31.3059 | M5: 31.3059 | N5: 31.3059 | O5: 31.3059 | P5: 31.3059 | Q5: 31.3059 | R5: 31.3059 | S5: 31.3059 | T5: 31.3059 | U5: 31.3059 | V5: 31.3059 | W5: 31.3059 | X5: 31.3059 | Y5: 31.3059 | Z5: 31.3059 | AA5: 31.3059 | AB5: 31.3059 | AC5: 31.3059 | AD5: 31.3059 | AE5: 31.3059 | AF5: 31.3059
A6: Output Electricity Generation by Type[onshore wind es] : BAU-Adjusted | B6: 34.7425 | C6: 37.0479 | D6: 38.3117 | E6: 41.4758 | F6: 44.2909 | G6: 46.0838 | H6: 48.0974 | I6: 50.3763 | J6: 53.6497 | K6: 56.5985 | L6: 58.9756 | M6: 61.1427 | N6: 63.0284 | O6: 64.54 | P6: 66.4125 | Q6: 68.3366 | R6: 70.4886 | S6: 72.4773 | T6: 74.3177 | U6: 76.2013 | V6: 77.9249 | W6: 79.5108 | X6: 81.3105 | Y6: 83.5657 | Z6: 85.2527 | AA6: 87.191 | AB6: 89.1797 | AC6: 91.3238 | AD6: 93.2856 | AE6: 95.1645 | AF6: 97.2988
A7: Output Electricity Generation by Type[solar PV es] : BAU-Adjusted | B7: 31.2231 | C7: 34.6821 | D7: 36.8137 | E7: 42.06 | F7: 47.4985 | G7: 50.3693 | H7: 54.3434 | I7: 59.2108 | J7: 66.8133 | K7: 74.1178 | L7: 80.3783 | M7: 85.9159 | N7: 91.3523 | O7: 95.8045 | P7: 101.382 | Q7: 107.143 | R7: 113.6 | S7: 119.565 | T7: 125.403 | U7: 131.534 | V7: 137.276 | W7: 142.625 | X7: 148.644 | Y7: 156.064 | Z7: 161.794 | AA7: 168.301 | AB7: 174.949 | AC7: 182.094 | AD7: 188.686 | AE7: 195.049 | AF7: 202.131
A8: Output Electricity Generation by Type[solar thermal es] : BAU-Adjusted | B8: 0 | C8: 0 | D8: 0 | E8: 0 | F8: 0 | G8: 0 | H8: 0 | I8: 0 | J8: 0 | K8: 0 | L8: 0 | M8: 0 | N8: 0 | O8: 0 | P8: 0 | Q8: 0 | R8: 0 | S8: 0 | T8: 0 | U8: 0 | V8: 0 | W8: 0 | X8: 0 | Y8: 0 | Z8: 0 | AA8: 0 | AB8: 0 | AC8: 0 | AD8: 0 | AE8: 0 | AF8: 0
A9: Output Electricity Generation by Type[biomass es] : BAU-Adjusted | B9: 6.62644 | C9: 6.76283 | D9: 6.76283 | E9: 6.89922 | F9: 7.03562 | G9: 7.03562 | H9: 7.03562 | I9: 7.03562 | J9: 7.03562 | K9: 7.03562 | L9: 7.03562 | M9: 7.03562 | N9: 7.03562 | O9: 7.03562 | P9: 7.03562 | Q9: 7.03562 | R9: 7.03562 | S9: 7.03562 | T9: 7.03562 | U9: 7.03562 | V9: 7.03562 | W9: 7.03562 | X9: 7.03562 | Y9: 7.03562 | Z9: 7.03562 | AA9: 7.03562 | AB9: 7.03562 | AC9: 7.03562 | AD9: 7.03562 | AE9: 7.03562 | AF9: 7.03562
A10: Output Electricity Generation by Type[geothermal es] : BAU-Adjusted | B10: 6.26634 | C10: 6.41554 | D10: 6.49014 | E10: 6.63933 | F10: 6.63933 | G10: 6.63933 | H10: 6.63933 | I10: 6.63933 | J10: 6.63933 | K10: 6.63933 | L10: 6.63933 | M10: 6.63933 | N10: 6.63933 | O10: 6.63933 | P10: 6.63933 | Q10: 6.63933 | R10: 6.63933 | S10: 6.63933 | T10: 6.63933 | U10: 6.63933 | V10: 6.63933 | W10: 6.63933 | X10: 6.63933 | Y10: 6.63933 | Z10: 6.63933 | AA10: 6.63933 | AB10: 6.63933 | AC10: 6.63933 | AD10: 6.63933 | AE10: 6.63933 | AF10: 6.63933
A11: Output Electricity Generation by Type[petroleum es] : BAU-Adjusted | B11: 0 | C11: 0 | D11: 0 | E11: 0.00569261 | F11: 0.0170778 | G11: 0.0227704 | H11: 0.0284631 | I11: 0.0341557 | J11: 0.0398483 | K11: 0.0455409 | L11: 0.0512335 | M11: 0.0512335 | N11: 0.0512335 | O11: 0.0512335 | P11: 0.0512335 | Q11: 0.0512335 | R11: 0.0569261 | S11: 0.318786 | T11: 0.643265 | U11: 1.02467 | V11: 1.3833 | W11: 1.69071 | X11: 2.01518 | Y11: 2.42505 | Z11: 2.74384 | AA11: 3.06832 | AB11: 3.40987 | AC11: 3.78559 | AD11: 4.13284 | AE11: 4.43454 | AF11: 4.78179
A12: Output Electricity Generation by Type[natural gas peaker es] : BAU-Adjusted | B12: 7.75487 | C12: 7.07172 | D12: 6.84401 | E12: 6.38858 | F12: 6.51382 | G12: 6.51382 | H12: 6.51382 | I12: 6.51382 | J12: 6.63906 | K12: 6.63906 | L12: 6.63906 | M12: 6.63906 | N12: 6.63906 | O12: 6.63906 | P12: 6.63906 | Q12: 6.63906 | R12: 6.63906 | S12: 8.01675 | T12: 9.64492 | U12: 11.6488 | V12: 13.5275 | W12: 15.1556 | X12: 16.9091 | Y12: 19.1635 | Z12: 20.9169 | AA12: 22.6703 | AB12: 24.5489 | AC12: 26.6781 | AD12: 28.682 | AE12: 30.4354 | AF12: 32.4393
... A18: Output Distributed Solar PV Output : BAU-Adjusted | B18: 2.39514 | C18: 3.13657 | D18: 4.06081 | E18: 5.191 | F18: 6.11952 | G18: 7.28498 | H18: 8.45044 | I18: 9.61589 | J18: 10.7814 | K18: 11.8237 | L18: 12.866 | M18: 13.9083 | N18: 14.9506 | O18: 15.9929 | P18: 16.8311 | Q18: 17.6692 | R18: 18.5074 | S18: 19.3456 | T18: 20.1838 | U18: 20.7908 | V18: 21.3978 | W18: 22.0049 | X18: 22.6119 | Y18: 23.2189 | Z18: 23.5858 | AA18: 23.9528 | AB18: 24.3197 | AC18: 24.6866 | AD18: 25.0535 | AE18: 25.1772 | AF18: 25.301
A22: =A1 -> Time (Year) | B22: =B1 -> 2020 | C22: =C1 -> 2021 | D22: =D1 -> 2022 | E22: =E1 -> 2023 | F22: =F1 -> 2024 | G22: =G1 -> 2025 | H22: =H1 -> 2026 | ... AF22: =AF1 -> 2050
A23: Coal | B23: =B2 -> 13.5351 | C23: =C2 -> 29.6539 | D23: =D2 -> 18.7252 | E23: =E2 -> 19.1984 | F23: =F2 -> 20.0296 | G23: =G2 -> 22.6687 | H23: =H2 -> 21.2581 | I23: =I2 -> 19.7476 | ... AF23: =AF2 -> 12.6872
A24: Natural Gas | B24: =B3+B12 -> 187.45487 | C24: =C3+C12 -> 190.17072 | D24: =D3+D12 -> 177.27301 | E24: =E3+E12 -> 179.66058 | F24: =F3+F12 -> 178.79182 | G24: =G3+G12 -> 179.04282 | H24: =H3+H12 -> 186.92482 | I24: =I3+I12 -> 193.95682 | ... AF24: =AF3+AF12 -> 224.9363
A25: Solar | B25: =B7+B8+B18 -> 33.61824 | C25: =C7+C8+C18 -> 37.81867 | D25: =D7+D8+D18 -> 40.87451 | E25: =E7+E8+E18 -> 47.251 | F25: =F7+F8+F18 -> 53.61802 | G25: =G7+G8+G18 -> 57.65428 | H25: =H7+H8+H18 -> 62.79384 | I25: =I7+I8+I18 -> 68.82669 | ... AF25: =AF7+AF8+AF18 -> 227.432
A26: Wind | B26: =B6+B14 -> 35.345636 | C26: =C6+C14 -> 37.741274 | D26: =D6+D14 -> 39.051769 | E26: =E6+E14 -> 42.349698 | F26: =F6+F14 -> 45.29902 | G26: =G6+G14 -> 47.18254 | H26: =H6+H14 -> 49.30888 | I26: =I6+I14 -> 51.72279 | ... AF26: =AF6+AF14 -> 102.4973
A27: Hydro | B27: =B5 -> 31.3059 | C27: =C5 -> 31.3059 | D27: =D5 -> 31.3059 | E27: =E5 -> 31.3059 | F27: =F5 -> 31.3059 | G27: =G5 -> 31.3059 | H27: =H5 -> 31.3059 | I27: =I5 -> 31.3059 | ... AF27: =AF5 -> 31.3059
A28: Oil | B28: =B11+B15+B16 -> 29.3437 | C28: =C11+C15+C16 -> 18.6715 | D28: =D11+D15+D16 -> 48.5079 | E28: =E11+E15+E16 -> 44.090193 | F28: =F11+F15+F16 -> 43.346178 | G28: =G11+G15+G16 -> 43.67767 | H28: =H11+H15+H16 -> 39.637263 | I28: =I11+I15+I16 -> 35.630856 | ... AF28: =AF11+AF15+AF16 -> 40.16619
A29: Other | B29: =B4+B9+B10+B13+B17 -> 23.77568 | C29: =C4+C9+C10+C13+C17 -> 24.06127 | D29: =D4+D9+D10+D13+D17 -> 24.13587 | E29: =E4+E9+E10+E13+E17 -> 25.120498 | F29: =F4+F9+F10+F13+F17 -> 26.07245 | G29: =G4+G9+G10+G13+G17 -> 26.53849 | H29: =H4+H9+H10+H13+H17 -> 27.00452 | I29: =I4+I9+I10+I13+I17 -> 27.47055 | ... AF29: =AF4+AF9+AF10+AF13+AF17 -> 33.52897

Sheet EG-BAU-2030
A1: Type | B1: EG
A2: Coal | B2: ='EG-BAU'!L23 -> 18.6575
A3: Natural Gas | B3: ='EG-BAU'!L24 -> 189.89606
A4: Solar | B4: ='EG-BAU'!L25 -> 93.2443
A5: Wind | B5: ='EG-BAU'!L26 -> 60.86173
A6: Hydro | B6: ='EG-BAU'!L27 -> 31.3059
A7: Oil | B7: ='EG-BAU'!L28 -> 39.209333
A8: Other (Biomass, Lignite, Waste, Nuclear, and Geothermal) | B8: ='EG-BAU'!L29 -> 29.10166

Sheet EG-BAU-2050
A1: Type | B1: EG
A2: Coal | B2: ='EG-BAU'!AF23 -> 12.6872
A3: Natural Gas | B3: ='EG-BAU'!AF24 -> 224.9363
A4: Solar | B4: ='EG-BAU'!AF25 -> 227.432
A5: Wind | B5: ='EG-BAU'!AF26 -> 102.4973
A6: Hydro | B6: ='EG-BAU'!AF27 -> 31.3059
A7: Oil | B7: ='EG-BAU'!AF28 -> 40.16619
A8: Other (Biomass, Lignite, Waste, Nuclear, and Geothermal) | B8: ='EG-BAU'!AF29 -> 33.52897

Sheet EG-Expert
A1: Time (Year) | B1: 2020 | C1: 2021 | D1: 2022 | E1: 2023 | F1: 2024 | G1: 2025 | H1: 2026 | I1: 2027 | J1: 2028 | K1: 2029 | L1: 2030 | M1: 2031 | N1: 2032 | O1: 2033 | P1: 2034 | Q1: 2035 | R1: 2036 | S1: 2037 | T1: 2038 | U1: 2039 | V1: 2040 | W1: 2041 | X1: 2042 | Y1: 2043 | Z1: 2044 | AA1: 2045 | AB1: 2046 | AC1: 2047 | AD1: 2048 | AE1: 2049 | AF1: 2050
A2: Output Electricity Generation by Type[hard coal es] : Expert-Adjusted | B2: 13.5351 | C2: 29.6539 | D2: 18.7252 | E2: 19.1984 | F2: 20.0296 | G2: 22.6687 | H2: 21.2524 | I2: 19.6304 | J2: 19.3667 | K2: 17.6104 | L2: 18.2828 | M2: 18.3322 | N2: 17.9726 | O2: 18.6292 | P2: 18.5236 | Q2: 18.5314 | R2: 17.351 | S2: 16.8789 | T2: 16.0118 | U2: 14.4489 | V2: 14.1485 | W2: 14.015 | X2: 13.9665 | Y2: 12.524 | Z2: 12.5691 | AA2: 12.2573 | AB2: 11.9088 | AC2: 10.753 | AD2: 10.378 | AE2: 9.90359 | AF2: 9.82705
A3: Output Electricity Generation by Type[natural gas nonpeaker es] : Expert-Adjusted | B3: 179.7 | C3: 183.099 | D3: 170.429 | E3: 173.272 | F3: 172.278 | G3: 172.529 | H3: 179.739 | I3: 185.974 | J3: 183.549 | K3: 181.354 | L3: 180.615 | M3: 179.999 | N3: 179.156 | O3: 177.884 | P3: 177.994 | Q3: 178.279 | R3: 178.914 | S3: 179.33 | T3: 179.659 | U3: 180.636 | V3: 180.93 | W3: 181.929 | X3: 182.025 | Y3: 181.455 | Z3: 179.945 | AA3: 179.615 | AB3: 179.272 | AC3: 178.518 | AD3: 178.614 | AE3: 179.536 | AF3: 177.823
A4: Output Electricity Generation by Type[nuclear es] : Expert-Adjusted | B4: 10.8829 | C4: 10.8829 | D4: 10.8829 | E4: 10.8829 | F4: 10.8829 | G4: 10.8829 | H4: 10.8829 | I4: 10.8829 | J4: 10.8829 | K4: 10.8829 | L4: 10.8829 | M4: 10.8829 | N4: 10.8829 | O4: 10.8829 | P4: 10.8829 | Q4: 10.8829 | R4: 10.8829 | S4: 10.8829 | T4: 10.8829 | U4: 10.8829 | V4: 10.8829 | W4: 10.8829 | X4: 10.8829 | Y4: 10.8829 | Z4: 10.8829 | AA4: 10.8829 | AB4: 10.8829 | AC4: 10.8829 | AD4: 10.8829 | AE4: 10.8829 | AF4: 10.8829
A5: Output Electricity Generation by Type[hydro es] : Expert-Adjusted | B5: 31.3059 | C5: 31.3059 | D5: 31.3059 | E5: 31.3059 | F5: 31.3059 | G5: 31.3059 | H5: 31.3059 | I5: 31.3059 | J5: 31.3059 | K5: 31.3059 | L5: 31.3059 | M5: 31.3059 | N5: 31.3059 | O5: 31.3059 | P5: 31.3059 | Q5: 31.3059 | R5: 31.3059 | S5: 31.3059 | T5: 31.3059 | U5: 31.3059 | V5: 31.3059 | W5: 31.3059 | X5: 31.3059 | Y5: 31.3059 | Z5: 31.3059 | AA5: 31.3059 | AB5: 31.3059 | AC5: 31.3059 | AD5: 31.3059 | AE5: 31.3059 | AF5: 31.3059
A6: Output Electricity Generation by Type[onshore wind es] : Expert-Adjusted | B6: 34.7425 | C6: 37.0479 | D6: 38.3117 | E6: 41.4758 | F6: 44.2909 | G6: 46.0838 | H6: 48.2008 | I6: 50.6151 | J6: 53.9449 | K6: 57.0122 | L6: 59.4331 | M6: 61.5264 | N6: 63.3398 | O6: 64.9292 | P6: 66.7948 | Q6: 68.6098 | R6: 70.6398 | S6: 72.6402 | T6: 74.5796 | U6: 76.5547 | V6: 78.339 | W6: 80.0355 | X6: 82.2308 | Y6: 85.2746 | Z6: 87.908 | AA6: 90.1025 | AB6: 92.3148 | AC6: 94.7475 | AD6: 97.0994 | AE6: 99.3351 | AF6: 101.827
A7: Output Electricity Generation by Type[solar PV es] : Expert-Adjusted | B7: 31.2231 | C7: 34.6821 | D7: 36.8137 | E7: 42.06 | F7: 47.4985 | G7: 50.3693 | H7: 54.5846 | I7: 59.761 | J7: 67.5105 | K7: 75.1613 | L7: 81.5514 | M7: 86.9154 | N7: 92.2106 | O7: 96.9665 | P7: 102.617 | Q7: 108.174 | R7: 114.407 | S7: 120.584 | T7: 126.716 | U7: 133.123 | V7: 139.06 | W7: 144.741 | X7: 151.964 | Y7: 161.834 | Z7: 170.517 | AA7: 177.832 | AB7: 185.239 | AC7: 193.283 | AD7: 201.075 | AE7: 208.555 | AF7: 216.775
A8: Output Electricity Generation by Type[solar thermal es] : Expert-Adjusted | B8: 0 | C8: 0 | D8: 0 | E8: 0 | F8: 0 | G8: 0 | H8: 0 | I8: 0 | J8: 0 | K8: 0 | L8: 0 | M8: 0 | N8: 0 | O8: 0 | P8: 0 | Q8: 0 | R8: 0 | S8: 0 | T8: 0 | U8: 0 | V8: 0 | W8: 0 | X8: 0 | Y8: 0 | Z8: 0 | AA8: 0 | AB8: 0 | AC8: 0 | AD8: 0 | AE8: 0 | AF8: 0
A9: Output Electricity Generation by Type[biomass es] : Expert-Adjusted | B9: 6.62644 | C9: 6.76283 | D9: 6.76283 | E9: 6.89922 | F9: 7.03562 | G9: 7.03562 | H9: 7.03562 | I9: 7.03562 | J9: 7.03562 | K9: 7.03562 | L9: 7.03562 | M9: 7.03562 | N9: 7.03562 | O9: 7.03562 | P9: 7.03562 | Q9: 7.03562 | R9: 7.03562 | S9: 7.03562 | T9: 7.03562 | U9: 7.03562 | V9: 7.03562 | W9: 7.03562 | X9: 5.67168 | Y9: 3.21661 | Z9: 0.0795627 | AA9: 0.0795627 | AB9: 0.0795627 | AC9: 0.0795627 | AD9: 0.0795627 | AE9: 0.0795627 | AF9: 0.0795627
A10: Output Electricity Generation by Type[geothermal es] : Expert-Adjusted | B10: 6.26634 | C10: 6.41554 | D10: 6.49014 | E10: 6.63933 | F10: 6.63933 | G10: 6.63933 | H10: 6.71393 | I10: 6.71393 | J10: 6.71393 | K10: 6.71393 | L10: 6.71393 | M10: 6.71393 | N10: 6.71393 | O10: 6.71393 | P10: 6.71393 | Q10: 6.71393 | R10: 6.71393 | S10: 6.71393 | T10: 6.71393 | U10: 6.71393 | V10: 6.71393 | W10: 6.71393 | X10: 6.71393 | Y10: 6.71393 | Z10: 6.71393 | AA10: 6.71393 | AB10: 6.71393 | AC10: 6.71393 | AD10: 6.71393 | AE10: 6.71393 | AF10: 6.71393
A11: Output Electricity Generation by Type[petroleum es] : Expert-Adjusted | B11: 0 | C11: 0 | D11: 0 | E11: 0.00569261 | F11: 0.0170778 | G11: 0.0227704 | H11: 0.0284631 | I11: 0.0341557 | J11: 0.0398483 | K11: 0.0455409 | L11: 0.0455409 | M11: 0.0455409 | N11: 0.0455409 | O11: 0.0455409 | P11: 0.0455409 | Q11: 0.0455409 | R11: 0.0455409 | S11: 0.153701 | T11: 0.387098 | U11: 0.671728 | V11: 0.91651 | W11: 1.09867 | X11: 1.33207 | Y11: 1.72486 | Z11: 2.0778 | AA11: 2.35674 | AB11: 2.59014 | AC11: 2.84061 | AD11: 3.06262 | AE11: 3.2334 | AF11: 3.43264
A12: Output Electricity Generation by Type[natural gas peaker es] : Expert-Adjusted | B12: 7.75487 | C12: 7.07172 | D12: 6.84401 | E12: 6.38858 | F12: 6.51382 | G12: 6.51382 | H12: 6.51382 | I12: 6.51382 | J12: 6.51382 | K12: 6.51382 | L12: 6.51382 | M12: 6.51382 | N12: 6.51382 | O12: 6.51382 | P12: 6.51382 | Q12: 6.51382 | R12: 6.51382 | S12: 7.0148 | T12: 8.14199 | U12: 9.64492 | V12: 10.8974 | W12: 11.7741 | X12: 13.0265 | Y12: 15.1556 | Z12: 17.0343 | AA12: 18.5372 | AB12: 19.7897 | AC12: 21.1674 | AD12: 22.4198 | AE12: 23.4217 | AF12: 24.5489
... A18: Output Distributed Solar PV Output : Expert-Adjusted | B18: 2.39514 | C18: 3.13657 | D18: 4.06081 | E18: 5.191 | F18: 6.11952 | G18: 7.28498 | H18: 8.45044 | I18: 9.61589 | J18: 10.7814 | K18: 11.8237 | L18: 12.866 | M18: 13.9083 | N18: 14.9506 | O18: 15.9929 | P18: 16.8311 | Q18: 17.6692 | R18: 18.5074 | S18: 19.3456 | T18: 20.1838 | U18: 20.7908 | V18: 21.3978 | W18: 22.0049 | X18: 22.6119 | Y18: 23.2189 | Z18: 23.5858 | AA18: 23.9528 | AB18: 24.3197 | AC18: 24.6866 | AD18: 25.0535 | AE18: 25.1772 | AF18: 25.301
A22: =A1 -> Time (Year) | B22: =B1 -> 2020 | C22: =C1 -> 2021 | D22: =D1 -> 2022 | E22: =E1 -> 2023 | F22: =F1 -> 2024 | G22: =G1 -> 2025 | H22: =H1 -> 2026 | ... AF22: =AF1 -> 2050
A23: Coal | B23: =B2 -> 13.5351 | C23: =C2 -> 29.6539 | D23: =D2 -> 18.7252 | E23: =E2 -> 19.1984 | F23: =F2 -> 20.0296 | G23: =G2 -> 22.6687 | H23: =H2 -> 21.2524 | I23: =I2 -> 19.6304 | ... AF23: =AF2 -> 9.82705
A24: Natural Gas | B24: =B3+B12 -> 187.45487 | C24: =C3+C12 -> 190.17072 | D24: =D3+D12 -> 177.27301 | E24: =E3+E12 -> 179.66058 | F24: =F3+F12 -> 178.79182 | G24: =G3+G12 -> 179.04282 | H24: =H3+H12 -> 186.25282 | I24: =I3+I12 -> 192.48782 | ... AF24: =AF3+AF12 -> 202.3719
A25: Solar | B25: =B7+B8+B18 -> 33.61824 | C25: =C7+C8+C18 -> 37.81867 | D25: =D7+D8+D18 -> 40.87451 | E25: =E7+E8+E18 -> 47.251 | F25: =F7+F8+F18 -> 53.61802 | G25: =G7+G8+G18 -> 57.65428 | H25: =H7+H8+H18 -> 63.03504 | I25: =I7+I8+I18 -> 69.37689 | ... AF25: =AF7+AF8+AF18 -> 242.076
A26: Wind | B26: =B6+B14 -> 35.345636 | C26: =C6+C14 -> 37.741274 | D26: =D6+D14 -> 39.051769 | E26: =E6+E14 -> 42.349698 | F26: =F6+F14 -> 45.29902 | G26: =G6+G14 -> 47.18254 | H26: =H6+H14 -> 49.41228 | I26: =I6+I14 -> 51.96159 | ... AF26: =AF6+AF14 -> 107.45494
A27: Hydro | B27: =B5 -> 31.3059 | C27: =C5 -> 31.3059 | D27: =D5 -> 31.3059 | E27: =E5 -> 31.3059 | F27: =F5 -> 31.3059 | G27: =G5 -> 31.3059 | H27: =H5 -> 31.3059 | I27: =I5 -> 31.3059 | ... AF27: =AF5 -> 31.3059
A28: Oil | B28: =B11+B15+B16 -> 29.3437 | C28: =C11+C15+C16 -> 18.6715 | D28: =D11+D15+D16 -> 48.5079 | E28: =E11+E15+E16 -> 44.090193 | F28: =F11+F15+F16 -> 43.346178 | G28: =G11+G15+G16 -> 43.67767 | H28: =H11+H15+H16 -> 39.777563 | I28: =I11+I15+I16 -> 35.620056 | ... AF28: =AF11+AF15+AF16 -> 35.89444
A29: Other (Biomass, Lignite, Waste, Nuclear, and Geothermal) | B29: =B4+B9+B10+B13+B17 -> 23.77568 | C29: =C4+C9+C10+C13+C17 -> 24.06127 | D29: =D4+D9+D10+D13+D17 -> 24.13587 | E29: =E4+E9+E10+E13+E17 -> 25.120498 | F29: =F4+F9+F10+F13+F17 -> 26.07245 | G29: =G4+G9+G10+G13+G17 -> 26.53849 | H29: =H4+H9+H10+H13+H17 -> 26.96261 | I29: =I4+I9+I10+I13+I17 -> 27.42864 | ... AF29: =AF4+AF9+AF10+AF13+AF17 -> 25.715443

Sheet EG-Expert-2030
A1: Type | B1: EG
A2: Coal | B2: ='EG-Expert'!L23 -> 18.2828
A3: Natural Gas | B3: ='EG-Expert'!L24 -> 187.12882
A4: Solar | B4: ='EG-Expert'!L25 -> 94.4174
A5: Wind | B5: ='EG-Expert'!L26 -> 61.34142
A6: Hydro | B6: ='EG-Expert'!L27 -> 31.3059
A7: Oil | B7: ='EG-Expert'!L28 -> 39.157041
A8: Other (Biomass, Lignite, Waste, Nuclear, and Geothermal) | B8: ='EG-Expert'!L29 -> 28.94325

Sheet EG-Expert-2050
A1: Type | B1: EG
A2: Coal | B2: ='EG-Expert'!AF23 -> 9.82705
A3: Natural Gas | B3: ='EG-Expert'!AF24 -> 202.3719
A4: Solar | B4: ='EG-Expert'!AF25 -> 242.076
A5: Wind | B5: ='EG-Expert'!AF26 -> 107.45494
A6: Hydro | B6: ='EG-Expert'!AF27 -> 31.3059
A7: Oil | B7: ='EG-Expert'!AF28 -> 35.89444
A8: Other (Biomass, Lignite, Waste, Nuclear, and Geothermal) | B8: ='EG-Expert'!AF29 -> 25.715443

Sheet EG-CAS
A1: Time (Year) | B1: 2020 | C1: 2021 | D1: 2022 | E1: 2023 | F1: 2024 | G1: 2025 | H1: 2026 | I1: 2027 | J1: 2028 | K1: 2029 | L1: 2030 | M1: 2031 | N1: 2032 | O1: 2033 | P1: 2034 | Q1: 2035 | R1: 2036 | S1: 2037 | T1: 2038 | U1: 2039 | V1: 2040 | W1: 2041 | X1: 2042 | Y1: 2043 | Z1: 2044 | AA1: 2045 | AB1: 2046 | AC1: 2047 | AD1: 2048 | AE1: 2049 | AF1: 2050
A2: Output Electricity Generation by Type[hard coal es] : CAS-Adjusted | B2: 13.5351 | C2: 29.6539 | D2: 18.7252 | E2: 19.1984 | F2: 20.0296 | G2: 22.6687 | H2: 18.5773 | I2: 14.095 | J2: 8.51865 | K2: 0 | L2: 0 | M2: 0 | N2: 0 | O2: 0 | P2: 0 | Q2: 0 | R2: 0 | S2: 0 | T2: 0 | U2: 0 | V2: 0 | W2: 0 | X2: 0 | Y2: 0 | Z2: 0 | AA2: 0 | AB2: 0 | AC2: 0 | AD2: 0 | AE2: 0 | AF2: 0
A3: Output Electricity Generation by Type[natural gas nonpeaker es] : CAS-Adjusted | B3: 179.7 | C3: 183.099 | D3: 170.429 | E3: 173.272 | F3: 172.278 | G3: 172.529 | H3: 174.733 | I3: 171.025 | J3: 152.067 | K3: 105.807 | L3: 101.575 | M3: 100.704 | N3: 102.722 | O3: 105.08 | P3: 109.01 | Q3: 111.08 | R3: 111.226 | S3: 110.957 | T3: 110.353 | U3: 110.404 | V3: 108.807 | W3: 106.042 | X3: 100.49 | Y3: 93.8507 | Z3: 85.9789 | AA3: 76.9081 | AB3: 65.0689 | AC3: 51.0204 | AD3: 35.2405 | AE3: 17.3862 | AF3: 5.62561
A4: Output Electricity Generation by Type[nuclear es] : CAS-Adjusted | B4: 10.8829 | C4: 10.8829 | D4: 10.8829 | E4: 10.8829 | F4: 10.8829 | G4: 10.8829 | H4: 10.8829 | I4: 10.8829 | J4: 10.8829 | K4: 10.8829 | L4: 10.8829 | M4: 10.8829 | N4: 10.8829 | O4: 10.8829 | P4: 10.8829 | Q4: 10.8829 | R4: 10.8829 | S4: 10.8829 | T4: 10.8829 | U4: 10.8829 | V4: 10.8829 | W4: 10.8829 | X4: 10.8829 | Y4: 10.8829 | Z4: 10.8829 | AA4: 10.8829 | AB4: 10.8829 | AC4: 10.8829 | AD4: 10.8829 | AE4: 10.8829 | AF4: 10.8829
A5: Output Electricity Generation by Type[hydro es] : CAS-Adjusted | B5: 31.3059 | C5: 31.3059 | D5: 31.3059 | E5: 31.3059 | F5: 31.3059 | G5: 31.3059 | H5: 31.3059 | I5: 31.3059 | J5: 31.3059 | K5: 31.3059 | L5: 31.3059 | M5: 31.3059 | N5: 31.3059 | O5: 31.3059 | P5: 31.3059 | Q5: 31.3059 | R5: 31.3059 | S5: 31.3059 | T5: 31.3059 | U5: 31.3059 | V5: 31.3059 | W5: 31.3059 | X5: 31.3059 | Y5: 31.3059 | Z5: 31.3059 | AA5: 31.3059 | AB5: 31.3059 | AC5: 31.3059 | AD5: 31.3059 | AE5: 31.3059 | AF5: 31.3059
A6: Output Electricity Generation by Type[onshore wind es] : CAS-Adjusted | B6: 34.7425 | C6: 37.0479 | D6: 38.3117 | E6: 41.4758 | F6: 44.2909 | G6: 46.0838 | H6: 49.6799 | I6: 54.7509 | J6: 65.2654 | K6: 77.5192 | L6: 78.2345 | M6: 78.7225 | N6: 78.8511 | O6: 79.0012 | P6: 79.1216 | Q6: 79.6702 | R6: 80.9211 | S6: 82.805 | T6: 84.7208 | U6: 86.622 | V6: 88.9806 | W6: 92.2524 | X6: 96.5069 | Y6: 101.443 | Z6: 106.608 | AA6: 112.717 | AB6: 119.87 | AC6: 127.938 | AD6: 136.802 | AE6: 145.973 | AF6: 153.867
A7: Output Electricity Generation by Type[solar PV es] : CAS-Adjusted | B7: 31.2231 | C7: 34.6821 | D7: 36.8137 | E7: 42.06 | F7: 47.4985 | G7: 50.3693 | H7: 57.6086 | I7: 68.5051 | J7: 92.6597 | K7: 121.36 | L7: 123.307 | M7: 124.323 | N7: 125.164 | O7: 126.149 | P7: 126.952 | Q7: 128.967 | R7: 132.938 | S7: 138.661 | T7: 144.459 | U7: 150.25 | V7: 157.736 | W7: 166.875 | X7: 179.085 | Y7: 193.073 | Z7: 207.594 | AA7: 224.556 | AB7: 244.172 | AC7: 265.994 | AD7: 289.661 | AE7: 313.877 | AF7: 334.625
A8: Output Electricity Generation by Type[solar thermal es] : CAS-Adjusted | B8: 0 | C8: 0 | D8: 0 | E8: 0 | F8: 0 | G8: 0 | H8: 0 | I8: 0 | J8: 0 | K8: 0 | L8: 0 | M8: 0 | N8: 0 | O8: 0 | P8: 0 | Q8: 0 | R8: 0 | S8: 0 | T8: 0 | U8: 0 | V8: 0 | W8: 0 | X8: 0 | Y8: 0 | Z8: 0 | AA8: 0 | AB8: 0 | AC8: 0 | AD8: 0 | AE8: 0 | AF8: 0
A9: Output Electricity Generation by Type[biomass es] : CAS-Adjusted | B9: 6.62644 | C9: 6.76283 | D9: 6.76283 | E9: 6.89922 | F9: 7.03562 | G9: 7.03562 | H9: 7.17201 | I9: 7.3084 | J9: 1.3071 | K9: 1.44349 | L9: 1.44349 | M9: 1.44349 | N9: 1.44349 | O9: 1.44349 | P9: 1.44349 | Q9: 1.44349 | R9: 1.44349 | S9: 1.44349 | T9: 1.44349 | U9: 1.44349 | V9: 1.44349 | W9: 1.44349 | X9: 1.44349 | Y9: 1.44349 | Z9: 1.44349 | AA9: 1.44349 | AB9: 1.44349 | AC9: 1.44349 | AD9: 1.44349 | AE9: 1.44349 | AF9: 0.0795627
A10: Output Electricity Generation by Type[geothermal es] : CAS-Adjusted | B10: 6.26634 | C10: 6.41554 | D10: 6.49014 | E10: 6.63933 | F10: 6.63933 | G10: 6.63933 | H10: 6.71393 | I10: 6.71393 | J10: 6.71393 | K10: 6.71393 | L10: 6.71393 | M10: 6.71393 | N10: 6.71393 | O10: 6.71393 | P10: 6.71393 | Q10: 6.71393 | R10: 6.71393 | S10: 6.71393 | T10: 6.71393 | U10: 6.71393 | V10: 6.71393 | W10: 6.71393 | X10: 6.71393 | Y10: 6.71393 | Z10: 6.71393 | AA10: 6.71393 | AB10: 6.71393 | AC10: 6.71393 | AD10: 6.71393 | AE10: 6.71393 | AF10: 6.71393
A11: Output Electricity Generation by Type[petroleum es] : CAS-Adjusted | B11: 0 | C11: 0 | D11: 0 | E11: 0.00569261 | F11: 0.0170778 | G11: 0.0227704 | H11: 0.0341557 | I11: 0.0455409 | J11: 1.56547 | K11: 32.2202 | L11: 35.7838 | M11: 35.9318 | N11: 36.3359 | O11: 36.3986 | P11: 36.3815 | Q11: 36.3587 | R11: 36.3359 | S11: 36.3132 | T11: 36.2847 | U11: 36.2562 | V11: 36.2221 | W11: 36.1879 | X11: 36.1538 | Y11: 36.1139 | Z11: 36.0741 | AA11: 36.0285 | AB11: 35.983 | AC11: 35.9375 | AD11: 35.8862 | AE11: 35.835 | AF11: 35.7781
A12: Output Electricity Generation by Type[natural gas peaker es] : CAS-Adjusted | B12: 7.75487 | C12: 7.07172 | D12: 6.84401 | E12: 6.38858 | F12: 6.51382 | G12: 6.51382 | H12: 6.51382 | I12: 6.51382 | J12: 6.51382 | K12: 6.51382 | L12: 6.51382 | M12: 7.26528 | N12: 9.39443 | O12: 9.77016 | P12: 9.77016 | Q12: 9.77016 | R12: 9.77016 | S12: 9.77016 | T12: 9.77016 | U12: 9.77016 | V12: 9.77016 | W12: 9.77016 | X12: 9.77016 | Y12: 9.77016 | Z12: 9.77016 | AA12: 9.77016 | AB12: 9.77016 | AC12: 9.77016 | AD12: 9.77016 | AE12: 9.77016 | AF12: 9.77016
... A18: Output Distributed Solar PV Output : CAS-Adjusted | B18: 2.39514 | C18: 3.13657 | D18: 4.06081 | E18: 5.191 | F18: 6.11952 | G18: 7.28498 | H18: 8.45044 | I18: 9.61589 | J18: 10.7814 | K18: 11.8237 | L18: 12.866 | M18: 13.9083 | N18: 14.9506 | O18: 15.9929 | P18: 17.1237 | Q18: 19.2837 | R18: 21.4441 | S18: 23.6851 | T18: 26.0509 | U18: 28.4596 | V18: 30.975 | W18: 33.5775 | X18: 36.3076 | Y18: 39.1434 | Z18: 42.1449 | AA18: 45.2117 | AB18: 48.4724 | AC18: 51.8685 | AD18: 55.421 | AE18: 59.1825 | AF18: 63.0552
A22: =A1 -> Time (Year) | B22: =B1 -> 2020 | C22: =C1 -> 2021 | D22: =D1 -> 2022 | E22: =E1 -> 2023 | F22: =F1 -> 2024 | G22: =G1 -> 2025 | H22: =H1 -> 2026 | ... AF22: =AF1 -> 2050
A23: Coal | B23: =B2 -> 13.5351 | C23: =C2 -> 29.6539 | D23: =D2 -> 18.7252 | E23: =E2 -> 19.1984 | F23: =F2 -> 20.0296 | G23: =G2 -> 22.6687 | H23: =H2 -> 18.5773 | I23: =I2 -> 14.095 | ... AF23: =AF2 -> 0
A24: Natural Gas | B24: =B3+B12 -> 187.45487 | C24: =C3+C12 -> 190.17072 | D24: =D3+D12 -> 177.27301 | E24: =E3+E12 -> 179.66058 | F24: =F3+F12 -> 178.79182 | G24: =G3+G12 -> 179.04282 | H24: =H3+H12 -> 181.24682 | I24: =I3+I12 -> 177.53882 | ... AF24: =AF3+AF12 -> 15.39577
A25: Solar | B25: =B7+B8+B18 -> 33.61824 | C25: =C7+C8+C18 -> 37.81867 | D25: =D7+D8+D18 -> 40.87451 | E25: =E7+E8+E18 -> 47.251 | F25: =F7+F8+F18 -> 53.61802 | G25: =G7+G8+G18 -> 57.65428 | H25: =H7+H8+H18 -> 66.05904 | I25: =I7+I8+I18 -> 78.12099 | ... AF25: =AF7+AF8+AF18 -> 397.6802
A26: Wind | B26: =B6+B14 -> 35.345636 | C26: =C6+C14 -> 37.741274 | D26: =D6+D14 -> 39.051769 | E26: =E6+E14 -> 42.349698 | F26: =F6+F14 -> 45.29902 | G26: =G6+G14 -> 47.18254 | H26: =H6+H14 -> 50.97949 | I26: =I6+I14 -> 56.36227 | ... AF26: =AF6+AF14 -> 162.84007
A27: Hydro | B27: =B5 -> 31.3059 | C27: =C5 -> 31.3059 | D27: =D5 -> 31.3059 | E27: =E5 -> 31.3059 | F27: =F5 -> 31.3059 | G27: =G5 -> 31.3059 | H27: =H5 -> 31.3059 | I27: =I5 -> 31.3059 | ... AF27: =AF5 -> 31.3059
A28: Oil | B28: =B11+B15+B16 -> 29.3437 | C28: =C11+C15+C16 -> 18.6715 | D28: =D11+D15+D16 -> 48.5079 | E28: =E11+E15+E16 -> 44.090193 | F28: =F11+F15+F16 -> 43.346178 | G28: =G11+G15+G16 -> 43.67767 | H28: =H11+H15+H16 -> 39.656556 | I28: =I11+I15+I16 -> 34.719741 | ... AF28: =AF11+AF15+AF16 -> 37.12223
A29: Other (Biomass, Lignite, Waste, Nuclear, and Geothermal) | B29: =B4+B9+B10+B13+B17 -> 23.77568 | C29: =C4+C9+C10+C13+C17 -> 24.06127 | D29: =D4+D9+D10+D13+D17 -> 24.13587 | E29: =E4+E9+E10+E13+E17 -> 25.120498 | F29: =F4+F9+F10+F13+F17 -> 26.07245 | G29: =G4+G9+G10+G13+G17 -> 26.53849 | H29: =H4+H9+H10+H13+H17 -> 27.56503 | I29: =I4+I9+I10+I13+I17 -> 28.63349 | ... AF29: =AF4+AF9+AF10+AF13+AF17 -> 24.899893

Sheet EG-CAS-2030
A1: Type | B1: EG
A2: Coal | B2: ='EG-CAS'!L23 -> 0
A3: Natural Gas | B3: ='EG-CAS'!L24 -> 108.08882
A4: Solar | B4: ='EG-CAS'!L25 -> 136.173
A5: Wind | B5: ='EG-CAS'!L26 -> 81.38545
A6: Hydro | B6: ='EG-CAS'!L27 -> 31.3059
A7: Oil | B7: ='EG-CAS'!L28 -> 59.6564
A8: Other (Biomass, Lignite, Waste, Nuclear, and Geothermal) | B8: ='EG-CAS'!L29 -> 26.26382

Sheet EG-CAS-2050
A1: Type | B1: EG
A2: Coal | B2: ='EG-CAS'!AF23 -> 0
A3: Natural Gas | B3: ='EG-CAS'!AF24 -> 15.39577
A4: Solar | B4: ='EG-CAS'!AF25 -> 397.6802
A5: Wind | B5: ='EG-CAS'!AF26 -> 162.84007
A6: Hydro | B6: ='EG-CAS'!AF27 -> 31.3059
A7: Oil | B7: ='EG-CAS'!AF28 -> 37.12223
A8: Other (Biomass, Lignite, Waste, Nuclear, and Geothermal) | B8: ='EG-CAS'!AF29 -> 24.899893

Sheet EGC-PENP-BAU
A1: Time (Year) | B1: Coal | C1: Fossil Fuels
A2: 2020 | B2: 5463 | C2: 10156
A3: 2021 | B3: 5463 | C3: 9836
A4: 2022 | B4: 5463 | C4: 8946
A5: 2023 | B5: 5463 | C5: 7886
A6: 2024 | B6: 5463 | C6: 6896
A7: 2025 | B7: 5463 | C7: 6896
A8: 2026 | B8: 5463 | C8: 6896
A9: 2027 | B9: 5463 | C9: 6556
A10: 2028 | B10: 4947 | C10: 6556
A11: 2029 | B11: 4173 | C11: 6556
A12: 2030 | B12: 4173 | C12: 6556
A13: 2031 | B13: 4173 | C13: 6556
... A32: 2050 | B32: 2883 | C32: 6556

Sheet EGC-PENP-Expert
A1: Time (Year) | B1: Coal | C1: Fossil Fuels
A2: 2020 | B2: 5463 | C2: 10156
A3: 2021 | B3: 5463 | C3: 9836
A4: 2022 | B4: 5463 | C4: 8946
A5: 2023 | B5: 5463 | C5: 7886
A6: 2024 | B6: 5463 | C6: 6896
A7: 2025 | B7: 5463 | C7: 6896
A8: 2026 | B8: 5463 | C8: 6876
A9: 2027 | B9: 5463 | C9: 6506
A10: 2028 | B10: 4947 | C10: 6446
A11: 2029 | B11: 4173 | C11: 6426
A12: 2030 | B12: 4173 | C12: 6366
A13: 2031 | B13: 4173 | C13: 6336
... A32: 2050 | B32: 2883 | C32: 4376

Sheet EGC-PENP-CAS
A1: Time (Year) | B1: Coal | C1: Fossil Fuels
A2: 2020 | B2: 5463 | C2: 10156
A3: 2021 | B3: 5463 | C3: 9836
A4: 2022 | B4: 5463 | C4: 8946
A5: 2023 | B5: 5463 | C5: 7886
A6: 2024 | B6: 5463 | C6: 6896
A7: 2025 | B7: 5463 | C7: 6896
A8: 2026 | B8: 4947 | C8: 6336
A9: 2027 | B9: 4173 | C9: 4986
A10: 2028 | B10: 2367 | C10: 3476
A11: 2029 | B11: 0 | C11: 1296
A12: 2030 | B12: 0 | C12: 0
A13: 2031 | B13: 0 | C13: 0
... A32: 2050 | B32: 0 | C32: 0

Sheet ECG-BAU
A1: Time (Year) | B1: 2020 | C1: 2021 | D1: 2022 | E1: 2023 | F1: 2024 | G1: 2025 | H1: 2026 | I1: 2027 | J1: 2028 | K1: 2029 | L1: 2030 | M1: 2031 | N1: 2032 | O1: 2033 | P1: 2034 | Q1: 2035 | R1: 2036 | S1: 2037 | T1: 2038 | U1: 2039 | V1: 2040 | W1: 2041 | X1: 2042 | Y1: 2043 | Z1: 2044 | AA1: 2045 | AB1: 2046 | AC1: 2047 | AD1: 2048 | AE1: 2049 | AF1: 2050
A2: Coal | B2: 5463 | C2: 5463 | D2: 5463 | E2: 5463 | F2: 5463 | G2: 5463 | H2: 5463 | I2: 5463 | J2: 4947 | K2: 4173 | L2: 4173 | M2: 4173 | N2: 3915 | O2: 3915 | P2: 3915 | Q2: 3915 | R2: 3657 | S2: 3657 | T2: 3657 | U2: 3399 | V2: 3399 | W2: 3399 | X2: 3399 | Y2: 3141 | Z2: 3141 | AA2: 3141 | AB2: 3141 | AC2: 2883 | AD2: 2883 | AE2: 2883 | AF2: 2883
A3: Natural Gas | B3: 33653.5 | C3: 32891.5 | D3: 32637.5 | E3: 33053.5 | F3: 33873.5 | G3: 34335.5 | H3: 34797.5 | I3: 35259.5 | J3: 35463.5 | K3: 35925.5 | L3: 36233.5 | M3: 36387.5 | N3: 36541.5 | O3: 36695.5 | P3: 36695.5 | Q3: 36695.5 | R3: 37003.5 | S3: 37553.5 | T3: 38203.5 | U3: 39157.5 | V3: 39907.5 | W3: 40711.5 | X3: 41411.5 | Y3: 42311.5 | Z3: 43165.5 | AA3: 43865.5 | AB3: 44615.5 | AC3: 45619.5 | AD3: 46419.5 | AE3: 47273.5 | AF3: 48073.5
A4: Solar | B4: 13334 | C4: 14784 | D4: 15630 | E4: 17770 | F4: 19846 | G4: 21190 | H4: 22764 | I4: 24698 | J4: 27780 | K4: 30724 | L4: 33226 | M4: 35446 | N4: 37596 | O4: 39324 | P4: 41460 | Q4: 43666 | R4: 46164 | S4: 48458 | T4: 50524 | U4: 52646 | V4: 54574 | W4: 56342 | X4: 58374 | Y4: 60938 | Z4: 62820 | AA4: 64992 | AB4: 67214 | AC4: 69606 | AD4: 71768 | AE4: 73824 | AF4: 76142
A5: Wind | B5: 11740 | C5: 12520 | D5: 12940 | E5: 13935 | F5: 14820 | G5: 15365 | H5: 15960 | I5: 16635 | J5: 17630 | K5: 18505 | L5: 19190 | M5: 19795 | N5: 20380 | O5: 20845 | P5: 21425 | Q5: 22020 | R5: 22690 | S5: 23310 | T5: 23865 | U5: 24430 | V5: 24940 | W5: 25410 | X5: 25950 | Y5: 26635 | Z5: 27135 | AA5: 27720 | AB5: 28320 | AC5: 28970 | AD5: 29560 | AE5: 30125 | AF5: 30770
A6: Hydro | B6: 12612 | C6: 12612 | D6: 12612 | E6: 12612 | F6: 12612 | G6: 12612 | H6: 12612 | I6: 12612 | J6: 12612 | K6: 12612 | L6: 12612 | M6: 12612 | N6: 12612 | O6: 12612 | P6: 12612 | Q6: 12612 | R6: 12612 | S6: 12612 | T6: 12612 | U6: 12612 | V6: 12612 | W6: 12612 | X6: 12612 | Y6: 12612 | Z6: 12612 | AA6: 12612 | AB6: 12612 | AC6: 12612 | AD6: 12612 | AE6: 12612 | AF6: 12612
A7: Oil | B7: 10156 | C7: 9836 | D7: 8946 | E7: 7887 | F7: 6899 | G7: 6900 | H7: 6901 | I7: 6562 | J7: 6563 | K7: 6564 | L7: 6565 | M7: 6565 | N7: 6565 | O7: 6565 | P7: 6565 | Q7: 6565 | R7: 6566 | S7: 6612 | T7: 6669 | U7: 6736 | V7: 6799 | W7: 6853 | X7: 6910 | Y7: 6982 | Z7: 7038 | AA7: 7095 | AB7: 7155 | AC7: 7221 | AD7: 7282 | AE7: 7335 | AF7: 7396
A8: Other (Biomass, Lignite, Waste, Nuclear, and Geothermal) | B8: 3401.5 | C8: 3439.5 | D8: 3449.5 | E8: 3571.5 | F8: 3687.5 | G8: 3743.5 | H8: 3799.5 | I8: 3855.5 | J8: 3939.5 | K8: 4009.5 | L8: 4051.5 | M8: 4093.5 | N8: 4135.5 | O8: 4163.5 | P8: 4191.5 | Q8: 4219.5 | R8: 4261.5 | S8: 4289.5 | T8: 4317.5 | U8: 4345.5 | V8: 4373.5 | W8: 4387.5 | X8: 4415.5 | Y8: 4443.5 | Z8: 4457.5 | AA8: 4485.5 | AB8: 4513.5 | AC8: 4541.5 | AD8: 4555.5 | AE8: 4569.5 | AF8: 4583.5

Sheet EGC-BAU-2020
A1: Type | B1: EGC
A2: Coal | B2: ='ECG-BAU'!B2 -> 5463
A3: Natural Gas | B3: ='ECG-BAU'!B3 -> 33653.5
A4: Solar | B4: ='ECG-BAU'!B4 -> 13334
A5: Wind | B5: ='ECG-BAU'!B5 -> 11740
A6: Hydro | B6: ='ECG-BAU'!B6 -> 12612
A7: Oil | B7: ='ECG-BAU'!B7 -> 10156
A8: Other (Biomass, Lignite, Waste, Nuclear, and Geothermal) | B8: ='ECG-BAU'!B8 -> 3401.5

Sheet EGC-BAU-2030
A1: Type | B1: EGC
A2: Coal | B2: ='ECG-BAU'!L2 -> 4173
A3: Natural Gas | B3: ='ECG-BAU'!L3 -> 36233.5
A4: Solar | B4: ='ECG-BAU'!L4 -> 33226
A5: Wind | B5: ='ECG-BAU'!L5 -> 19190
A6: Hydro | B6: ='ECG-BAU'!L6 -> 12612
A7: Oil | B7: ='ECG-BAU'!L7 -> 6565
A8: Other (Biomass, Lignite, Waste, Nuclear, and Geothermal) | B8: ='ECG-BAU'!L8 -> 4051.5

Sheet EGC-BAU-2050
A1: Type | B1: EGC
A2: Coal | B2: ='ECG-BAU'!AF2 -> 2883
A3: Natural Gas | B3: ='ECG-BAU'!AF3 -> 48073.5
A4: Solar | B4: ='ECG-BAU'!AF4 -> 76142
A5: Wind | B5: ='ECG-BAU'!AF5 -> 30770
A6: Hydro | B6: ='ECG-BAU'!AF6 -> 12612
A7: Oil | B7: ='ECG-BAU'!AF7 -> 7396
A8: Other (Biomass, Lignite, Waste, Nuclear, and Geothermal) | B8: ='ECG-BAU'!AF8 -> 4583.5

Sheet EGC-Expert
A1: Time (Year) | B1: 2020 | C1: 2021 | D1: 2022 | E1: 2023 | F1: 2024 | G1: 2025 | H1: 2026 | I1: 2027 | J1: 2028 | K1: 2029 | L1: 2030 | M1: 2031 | N1: 2032 | O1: 2033 | P1: 2034 | Q1: 2035 | R1: 2036 | S1: 2037 | T1: 2038 | U1: 2039 | V1: 2040 | W1: 2041 | X1: 2042 | Y1: 2043 | Z1: 2044 | AA1: 2045 | AB1: 2046 | AC1: 2047 | AD1: 2048 | AE1: 2049 | AF1: 2050
A2: Coal | B2: 5463 | C2: 5463 | D2: 5463 | E2: 5463 | F2: 5463 | G2: 5463 | H2: 5463 | I2: 5463 | J2: 4947 | K2: 4173 | L2: 4173 | M2: 4173 | N2: 3915 | O2: 3915 | P2: 3915 | Q2: 3915 | R2: 3657 | S2: 3657 | T2: 3657 | U2: 3399 | V2: 3399 | W2: 3399 | X2: 3399 | Y2: 3141 | Z2: 3141 | AA2: 3141 | AB2: 3141 | AC2: 2883 | AD2: 2883 | AE2: 2883 | AF2: 2883
A3: Natural Gas | B3: 33653.5 | C3: 32891.5 | D3: 32637.5 | E3: 33053.5 | F3: 33873.5 | G3: 34335.5 | H3: 34643.5 | I3: 35105.5 | J3: 35105.5 | K3: 35567.5 | L3: 35875.5 | M3: 36029.5 | N3: 36029.5 | O3: 36183.5 | P3: 36183.5 | Q3: 36183.5 | R3: 36337.5 | S3: 36537.5 | T3: 36987.5 | U3: 37741.5 | V3: 38241.5 | W3: 38745.5 | X3: 39245.5 | Y3: 40095.5 | Z3: 40691.5 | AA3: 41137.5 | AB3: 41483.5 | AC3: 42033.5 | AD3: 42379.5 | AE3: 42779.5 | AF3: 43075.5
A4: Solar | B4: 13334 | C4: 14784 | D4: 15630 | E4: 17770 | F4: 19846 | G4: 21190 | H4: 22856 | I4: 24910 | J4: 28042 | K4: 31120 | L4: 33656 | M4: 35786 | N4: 37846 | O4: 39660 | P4: 41792 | Q4: 43890 | R4: 46242 | S4: 48564 | T4: 50792 | U4: 53046 | V4: 55064 | W4: 56980 | X4: 59504 | Y4: 63024 | Z4: 66036 | AA4: 68508 | AB4: 70998 | AC4: 73726 | AD4: 76326 | AE4: 78806 | AF4: 81540
A5: Wind | B5: 11740 | C5: 12520 | D5: 12940 | E5: 13935 | F5: 14820 | G5: 15365 | H5: 15990 | I5: 16705 | J5: 17715 | K5: 18630 | L5: 19325 | M5: 19905 | N5: 20465 | O5: 20950 | P5: 21525 | Q5: 22090 | R5: 22720 | S5: 23340 | T5: 23930 | U5: 24525 | V5: 25060 | W5: 25565 | X5: 26235 | Y5: 27170 | Z5: 27975 | AA5: 28640 | AB5: 29310 | AC5: 30050 | AD5: 30760 | AE5: 31440 | AF5: 32195
A6: Hydro | B6: 12612 | C6: 12612 | D6: 12612 | E6: 12612 | F6: 12612 | G6: 12612 | H6: 12612 | I6: 12612 | J6: 12612 | K6: 12612 | L6: 12612 | M6: 12612 | N6: 12612 | O6: 12612 | P6: 12612 | Q6: 12612 | R6: 12612 | S6: 12612 | T6: 12612 | U6: 12612 | V6: 12612 | W6: 12612 | X6: 12612 | Y6: 12612 | Z6: 12612 | AA6: 12612 | AB6: 12612 | AC6: 12612 | AD6: 12612 | AE6: 12612 | AF6: 12612
A7: Oil | B7: 10156 | C7: 9836 | D7: 8946 | E7: 7887 | F7: 6899 | G7: 6900 | H7: 6881 | I7: 6512 | J7: 6453 | K7: 6434 | L7: 6374 | M7: 6344 | N7: 6324 | O7: 6314 | P7: 6254 | Q7: 6214 | R7: 6174 | S7: 6173 | T7: 6144 | U7: 6124 | V7: 6087 | W7: 6019 | X7: 5960 | Y7: 5898 | Z7: 5770 | AA7: 5639 | AB7: 5519 | AC7: 5403 | AD7: 5272 | AE7: 5122 | AF7: 4977
A8: Other (Biomass, Lignite, Waste, Nuclear, and Geothermal) | B8: 3401.5 | C8: 3439.5 | D8: 3449.5 | E8: 3571.5 | F8: 3687.5 | G8: 3743.5 | H8: 3795.5 | I8: 3851.5 | J8: 3921.5 | K8: 3991.5 | L8: 4033.5 | M8: 4061.5 | N8: 4089.5 | O8: 4117.5 | P8: 4145.5 | Q8: 4173.5 | R8: 4201.5 | S8: 4229.5 | T8: 4257.5 | U8: 4285.5 | V8: 4299.5 | W8: 4313.5 | X8: 4161.5 | Y8: 3865.5 | Z8: 3479.5 | AA8: 3493.5 | AB8: 3507.5 | AC8: 3521.5 | AD8: 3535.5 | AE8: 3549.5 | AF8: 3563.5

Sheet EGC-Expert-2030
A1: Type | B1: EGC
A2: Coal | B2: ='EGC-Expert'!L2 -> 4173
A3: Natural Gas | B3: ='EGC-Expert'!L3 -> 35875.5
A4: Solar | B4: ='EGC-Expert'!L4 -> 33656
A5: Wind | B5: ='EGC-Expert'!L5 -> 19325
A6: Hydro | B6: ='EGC-Expert'!L6 -> 12612
A7: Oil | B7: ='EGC-Expert'!L7 -> 6374
A8: Other (Biomass, Lignite, Waste, Nuclear, and Geothermal) | B8: ='EGC-Expert'!L8 -> 4033.5

Sheet EGC-Expert-2050
A1: Type | B1: EGC
A2: Coal | B2: ='EGC-Expert'!AF2 -> 2883
A3: Natural Gas | B3: ='EGC-Expert'!AF3 -> 43075.5
A4: Solar | B4: ='EGC-Expert'!AF4 -> 81540
A5: Wind | B5: ='EGC-Expert'!AF5 -> 32195
A6: Hydro | B6: ='EGC-Expert'!AF6 -> 12612
A7: Oil | B7: ='EGC-Expert'!AF7 -> 4977
A8: Other (Biomass, Lignite, Waste, Nuclear, and Geothermal) | B8: ='EGC-Expert'!AF8 -> 3563.5

Sheet EGC-CAS
A1: Time (Year) | B1: 2020 | C1: 2021 | D1: 2022 | E1: 2023 | F1: 2024 | G1: 2025 | H1: 2026 | I1: 2027 | J1: 2028 | K1: 2029 | L1: 2030 | M1: 2031 | N1: 2032 | O1: 2033 | P1: 2034 | Q1: 2035 | R1: 2036 | S1: 2037 | T1: 2038 | U1: 2039 | V1: 2040 | W1: 2041 | X1: 2042 | Y1: 2043 | Z1: 2044 | AA1: 2045 | AB1: 2046 | AC1: 2047 | AD1: 2048 | AE1: 2049 | AF1: 2050
A2: Coal | B2: 5463 | C2: 5463 | D2: 5463 | E2: 5463 | F2: 5463 | G2: 5463 | H2: 4947 | I2: 4173 | J2: 2367 | K2: 0 | L2: 0 | M2: 0 | N2: 0 | O2: 0 | P2: 0 | Q2: 0 | R2: 0 | S2: 0 | T2: 0 | U2: 0 | V2: 0 | W2: 0 | X2: 0 | Y2: 0 | Z2: 0 | AA2: 0 | AB2: 0 | AC2: 0 | AD2: 0 | AE2: 0 | AF2: 0
A3: Natural Gas | B3: 33653.5 | C3: 32891.5 | D3: 32637.5 | E3: 33053.5 | F3: 33873.5 | G3: 34335.5 | H3: 34643.5 | I3: 34847.5 | J3: 34435.5 | K3: 37381.5 | L3: 38513.5 | M3: 38607.5 | N3: 38587.5 | O3: 38587.5 | P3: 38433.5 | Q3: 38279.5 | R3: 37971.5 | S3: 37355.5 | T3: 36431.5 | U3: 35507.5 | V3: 34275.5 | W3: 32581.5 | X3: 30425.5 | Y3: 28115.5 | Z3: 25805.5 | AA3: 23341.5 | AB3: 20261.5 | AC3: 18105.5 | AD3: 16719.5 | AE3: 15641.5 | AF3: 14409.5
A4: Solar | B4: 13334 | C4: 14784 | D4: 15630 | E4: 17770 | F4: 19846 | G4: 21190 | H4: 23804 | I4: 27652 | J4: 34666 | K4: 46462 | L4: 53692 | M4: 55932 | N4: 56648 | O4: 57614 | P4: 59506 | Q4: 61598 | R4: 64272 | S4: 67998 | T4: 72158 | U4: 76466 | V4: 81422 | W4: 87300 | X4: 94018 | Y4: 101260 | Z4: 108384 | AA4: 115992 | AB4: 124570 | AC4: 132030 | AD4: 138464 | AE4: 145534 | AF4: 151984
A5: Wind | B5: 11740 | C5: 12520 | D5: 12940 | E5: 13935 | F5: 14820 | G5: 15365 | H5: 16350 | I5: 17695 | J5: 19980 | K5: 23595 | L5: 25655 | M5: 26265 | N5: 26455 | O5: 26710 | P5: 27205 | Q5: 27745 | R5: 28435 | S5: 29395 | T5: 30470 | U5: 31575 | V5: 32845 | W5: 34360 | X5: 36090 | Y5: 37960 | Z5: 39810 | AA5: 41795 | AB5: 44045 | AC5: 46010 | AD5: 47710 | AE5: 49595 | AF5: 51330
A6: Hydro | B6: 12612 | C6: 12612 | D6: 12612 | E6: 12612 | F6: 12612 | G6: 12612 | H6: 12612 | I6: 12612 | J6: 12612 | K6: 12612 | L6: 12612 | M6: 12612 | N6: 12612 | O6: 12612 | P6: 12612 | Q6: 12612 | R6: 12612 | S6: 12612 | T6: 12612 | U6: 12612 | V6: 12612 | W6: 12612 | X6: 12612 | Y6: 12612 | Z6: 12612 | AA6: 12612 | AB6: 12612 | AC6: 12612 | AD6: 12612 | AE6: 12612 | AF6: 12612
A7: Oil | B7: 10156 | C7: 9836 | D7: 8946 | E7: 7887 | F7: 6899 | G7: 6900 | H7: 6337 | I7: 4987 | J7: 3479 | K7: 1537 | L7: 302 | M7: 188 | N7: 63 | O7: 0 | P7: 0 | Q7: 0 | R7: 0 | S7: 0 | T7: 0 | U7: 0 | V7: 0 | W7: 0 | X7: 0 | Y7: 0 | Z7: 0 | AA7: 0 | AB7: 0 | AC7: 0 | AD7: 0 | AE7: 0 | AF7: 0
A8: Other (Biomass, Lignite, Waste, Nuclear, and Geothermal) | B8: 3401.5 | C8: 3439.5 | D8: 3449.5 | E8: 3571.5 | F8: 3687.5 | G8: 3743.5 | H8: 3813.5 | I8: 3901.5 | J8: 4045.5 | K8: 3435.5 | L8: 3357.5 | M8: 3353.5 | N8: 3353.5 | O8: 3353.5 | P8: 3353.5 | Q8: 3353.5 | R8: 3367.5 | S8: 3381.5 | T8: 3395.5 | U8: 3409.5 | V8: 3423.5 | W8: 3437.5 | X8: 3451.5 | Y8: 3465.5 | Z8: 3479.5 | AA8: 3479.5 | AB8: 3479.5 | AC8: 3479.5 | AD8: 3479.5 | AE8: 2749.5 | AF8: 2589.5
A11: Time (Year) | B11: Bau | C11: Natural Gas
A12: 2020 | B12: 33653.5 | C12: 33653.5
A13: 2021 | B13: 32891.5 | C13: 32891.5
A14: 2022 | B14: 32637.5 | C14: 32637.5
A15: 2023 | B15: 33053.5 | C15: 33053.5
A16: 2024 | B16: 33873.5 | C16: 33873.5
A17: 2025 | B17: 34335.5 | C17: 34335.5
A18: 2026 | B18: 34797.5 | C18: 34643.5
A19: 2027 | B19: 35259.5 | C19: 34847.5
A20: 2028 | B20: 35463.5 | C20: 34435.5
A21: 2029 | B21: 35925.5 | C21: 37381.5
A22: 2030 | B22: 36233.5 | C22: 38513.5
A23: 2031 | B23: 36387.5 | C23: 38607.5
... A42: 2050 | B42: 48073.5 | C42: 14409.5

Sheet EGC-CAS-2030
A1: Type | B1: EGC
A2: Coal | B2: ='EGC-CAS'!L2 -> 0
A3: Natural Gas | B3: ='EGC-CAS'!L3 -> 38513.5
A4: Solar | B4: ='EGC-CAS'!L4 -> 53692
A5: Wind | B5: ='EGC-CAS'!L5 -> 25655
A6: Hydro | B6: ='EGC-CAS'!L6 -> 12612
A7: Oil | B7: ='EGC-CAS'!L7 -> 302
A8: Other (Biomass, Lignite, Waste, Nuclear, and Geothermal) | B8: ='EGC-CAS'!L8 -> 3357.5

Sheet EGC-CAS-2050
A1: Type | B1: EGC
A2: Coal | B2: ='EGC-CAS'!AF2 -> 0
A3: Natural Gas | B3: ='EGC-CAS'!AF3 -> 14409.5
A4: Solar | B4: ='EGC-CAS'!AF4 -> 151984
A5: Wind | B5: ='EGC-CAS'!AF5 -> 51330
A6: Hydro | B6: ='EGC-CAS'!AF6 -> 12612
A7: Oil | B7: ='EGC-CAS'!AF7 -> 0
A8: Other (Biomass, Lignite, Waste, Nuclear, and Geothermal) | B8: ='EGC-CAS'!AF8 -> 2589.5

Sheet GDP
A1: Time (Year) | B1: BAU | C1: Expert | D1: CAS
A2: 2020 | B2: 0 | C2: 0 | D2: 0
A3: 2021 | B3: 0 | C3: 0 | D3: 0
A4: 2022 | B4: 0 | C4: 0 | D4: 0
A5: 2023 | B5: 0 | C5: 0 | D5: 0
A6: 2024 | B6: 0 | C6: 0 | D6: 0
A7: 2025 | B7: 0 | C7: 0 | D7: 0
A8: 2026 | B8: 0 | C8: 0.103657 | D8: 0.6398
A9: 2027 | B9: 0 | C9: 0.365529 | D9: 2.16838
A10: 2028 | B10: 0 | C10: 0.413142 | D10: 2.66335
A11: 2029 | B11: 0 | C11: 0.505392 | D11: 2.91878
A12: 2030 | B12: 0 | C12: 0.562429 | D12: 3.57197
A13: 2031 | B13: 0 | C13: 0.656663 | D13: 5.39316
... A32: 2050 | B32: 0 | C32: 3.80904 | D32: 32.4185

Sheet Debt
A1: Time (Year) | B1: BAU | C1: Expert | D1: CAS
A2: 2020 | B2: 0 | C2: 0 | D2: 0
A3: 2021 | B3: 0 | C3: 0 | D3: 0
A4: 2022 | B4: 0 | C4: 0 | D4: 0
A5: 2023 | B5: 0 | C5: 0 | D5: 0
A6: 2024 | B6: 0 | C6: 0 | D6: 0
A7: 2025 | B7: 0 | C7: 0 | D7: 0
A8: 2026 | B8: 0 | C8: -0.0111352 | D8: -0.305104
A9: 2027 | B9: 0 | C9: -0.0285061 | D9: -0.89126
A10: 2028 | B10: 0 | C10: -0.0632478 | D10: -1.77272
A11: 2029 | B11: 0 | C11: -0.106007 | D11: -2.95394
A12: 2030 | B12: 0 | C12: -0.160792 | D12: -4.40819
A13: 2031 | B13: 0 | C13: -0.221813 | D13: -6.18626
... A32: 2050 | B32: 0 | C32: -4.6554 | D32: -107.9

Sheet Jobs
A1: Time (Year) | B1: BAU | C1: Expert | D1: CAS
A2: 2020 | B2: 0 | C2: 0 | D2: 0
A3: 2021 | B3: 0 | C3: 0 | D3: 0
A4: 2022 | B4: 0 | C4: 0 | D4: 0
A5: 2023 | B5: 0 | C5: 0 | D5: 0
A6: 2024 | B6: 0 | C6: 0 | D6: 0
A7: 2025 | B7: 0 | C7: 0 | D7: 0
A8: 2026 | B8: 0 | C8: 3665 | D8: 11238
A9: 2027 | B9: 0 | C9: 5960 | D9: 29863
A10: 2028 | B10: 0 | C10: 8943 | D10: 41096
A11: 2029 | B11: 0 | C11: 11388 | D11: 45198
A12: 2030 | B12: 0 | C12: 15542 | D12: 87487
A13: 2031 | B13: 0 | C13: 18638 | D13: 127339
... A32: 2050 | B32: 0 | C32: 198992 | D32: 1325060

Sheet EPS Outputs
A1: =GDP!A1 -> Time (Year) | B1: Total GHG-BAU | C1: Total GHG-Expert | D1: Total GHG-CAS | E1: Total GHGeLULUCF-BAU | F1: Total GHGeLULUCF-Expert | G1: Total GHGeLULUCF-CAS | H1: GHGS1BAU | I1: GHGS2BAU | J1: GHGS3BAU | K1: GHGS4BAU | L1: GHGS5BAU | M1: GHGS6BAU | N1: GHGS7BAU | O1: GHGS8BAU | P1: GHGS9BAU | Q1: GHGS1EXPERT | R1: GHGS2EXPERT | S1: GHGS3EXPERT | T1: GHGS4EXPERT | U1: GHGS5EXPERT | V1: GHGS6EXPERT | W1: GHGS7EXPERT | X1: GHGS8EXPERT | Y1: GHGS9EXPERT | Z1: GHGS1CAS | AA1: GHGS2CAS | AB1: GHGS3CAS | AC1: GHGS4CAS | AD1: GHGS5CAS | AE1: GHGS6CAS | AF1: GHGS7CAS | AG1: GHGS8CAS | AH1: GHGS9CAS | AI1: Type | AJ1: BAU2030 | AK1: BAU2050 | AL1: EXPERT2030 | AM1: EXPERT2050 | AN1: CAS2030 | AO1: CAS2050 | AP1: GDPBAU | AQ1: GDPEXPERT | AR1: GDPCAS | AS1: JOBBAU | AT1: JOBEXPERT | AU1: JOBCAS | AV1: DEBTBAU | AW1: DEBTEXPERT | AX1: DEBTCAS | AY1: CTREXPERT | AZ1: FTREXPERT | BA1: EVSEXPERT | BB1: EGSEXPERT | BC1: ECCSEXPERT | BD1: DSSEXPERT | BE1: FSEXPERT | BF1: NDIEXPERT | BG1: REXPERT | BH1: CTRCAS | BI1: FTRCAS | BJ1: EVSCAS | BK1: EGSCAS | BL1: ECCSCAS | BM1: DSSCAS | BN1: FSCAS | BO1: NDICAS | BP1: RCAS
A2: =GDP!A2 -> 2020 | B2: ='CO2e Emissions'!B2 -> 551.292 | C2: ='CO2e Emissions'!C2 -> 551.292 | D2: ='CO2e Emissions'!D2 -> 551.292 | E2: ='CO2e Emissions (LULUCF excl)'!B2 -> 533.676 | F2: ='CO2e Emissions (LULUCF excl)'!C2 -> 533.676 | G2: ='CO2e Emissions (LULUCF excl)'!D2 -> 533.676 | H2: ='CO2e Emissions by Sector-BAU'!B2 -> 149.838 | I2: ='CO2e Emissions by Sector-BAU'!C2 -> 109.612 | J2: ='CO2e Emissions by Sector-BAU'!D2 -> 16.5474 | K2: ='CO2e Emissions by Sector-BAU'!E2 -> 4.16586 | L2: ='CO2e Emissions by Sector-BAU'!F2 -> 124.17 | M2: ='CO2e Emissions by Sector-BAU'!G2 -> 0 | N2: ='CO2e Emissions by Sector-BAU'!H2 -> 17.6158 | O2: ='CO2e Emissions by Sector-BAU'!I2 -> 79.9983 | P2: ='CO2e Emissions by Sector-BAU'!J2 -> 49.3445 | Q2: ='CO2e Emissions by Sector-Expert'!B2 -> 151.84 | R2: ='CO2e Emissions by Sector-Expert'!C2 -> 109.596 | S2: ='CO2e Emissions by Sector-Expert'!D2 -> 16.5471 | T2: ='CO2e Emissions by Sector-Expert'!E2 -> 4.16604 | U2: ='CO2e Emissions by Sector-Expert'!F2 -> 124.17 | V2: ='CO2e Emissions by Sector-Expert'!G2 -> 0 | W2: ='CO2e Emissions by Sector-Expert'!H2 -> 17.637 | X2: ='CO2e Emissions by Sector-Expert'!I2 -> 79.9858 | Y2: ='CO2e Emissions by Sector-Expert'!J2 -> 49.3557 | Z2: ='CO2e Emissions by Sector-CAS'!B2 -> 149.838 | AA2: ='CO2e Emissions by Sector-CAS'!C2 -> 109.612 | AB2: ='CO2e Emissions by Sector-CAS'!D2 -> 16.5474 | AC2: ='CO2e Emissions by Sector-CAS'!E2 -> 4.16586 | AD2: ='CO2e Emissions by Sector-CAS'!F2 -> 124.17 | AE2: ='CO2e Emissions by Sector-CAS'!G2 -> 0 | AF2: ='CO2e Emissions by Sector-CAS'!H2 -> 17.6158 | AG2: ='CO2e Emissions by Sector-CAS'!I2 -> 79.9983 | AH2: ='CO2e Emissions by Sector-CAS'!J2 -> 49.3445 | AI2: ='EG-BAU'!A23 -> Coal | AJ2: ='EG-BAU-2030'!B2 -> 18.6575 | AK2: ='EG-BAU-2050'!B2 -> 12.6872 | AL2: ='EG-Expert-2030'!B2 -> 18.2828 | AM2: ='EG-Expert-2050'!B2 -> 9.82705 | AN2: ='EG-CAS-2030'!B2 -> 0 | AO2: ='EG-CAS-2050'!B2 -> 0 | AP2: =GDP!B2 -> 0 | AQ2: =GDP!C2 -> 0 | AR2: =GDP!D2 -> 0 | AS2: =Jobs!B2 -> 0 | AT2: =Jobs!C2 -> 0 | AU2: =Jobs!D2 -> 0 | AV2: =Debt!B2 -> 0 | AW2: =Debt!C2 -> 0 | AX2: =Debt!D2 -> 0 | AY2: ='GCF-Expert'!B2 -> 0 | AZ2: ='GCF-Expert'!C2 -> 0 | BA2: ='GCF-Expert'!D2 -> 0 | BB2: ='GCF-Expert'!E2 -> 0 | BC2: ='GCF-Expert'!F2 -> 0 | BD2: ='GCF-Expert'!G2 -> 0 | BE2: ='GCF-Expert'!H2 -> 0 | BF2: ='GCF-Expert'!I2 -> 0 | BG2: ='GCF-Expert'!J2 -> 0 | BH2: ='GCF-CAS'!B2 -> 0 | BI2: ='GCF-CAS'!C2 -> 0 | BJ2: ='GCF-CAS'!D2 -> 0 | BK2: ='GCF-CAS'!E2 -> 0 | BL2: ='GCF-CAS'!F2 -> 0 | BM2: ='GCF-CAS'!G2 -> 0 | BN2: ='GCF-CAS'!H2 -> 0 | BO2: ='GCF-CAS'!I2 -> 0 | BP2: ='GCF-CAS'!J2 -> 0
A3: =GDP!A3 -> 2021 | B3: ='CO2e Emissions'!B3 -> 571.186 | C3: ='CO2e Emissions'!C3 -> 571.186 | D3: ='CO2e Emissions'!D3 -> 571.186 | E3: ='CO2e Emissions (LULUCF excl)'!B3 -> 553.667 | F3: ='CO2e Emissions (LULUCF excl)'!C3 -> 553.667 | G3: ='CO2e Emissions (LULUCF excl)'!D3 -> 553.667 | H3: ='CO2e Emissions by Sector-BAU'!B3 -> 153.605 | I3: ='CO2e Emissions by Sector-BAU'!C3 -> 118.194 | J3: ='CO2e Emissions by Sector-BAU'!D3 -> 16.5469 | K3: ='CO2e Emissions by Sector-BAU'!E3 -> 4.18492 | L3: ='CO2e Emissions by Sector-BAU'!F3 -> 130.483 | M3: ='CO2e Emissions by Sector-BAU'!G3 -> 5.23e-06 | N3: ='CO2e Emissions by Sector-BAU'!H3 -> 17.5193 | O3: ='CO2e Emissions by Sector-BAU'!I3 -> 80.494 | P3: ='CO2e Emissions by Sector-BAU'!J3 -> 50.1587 | Q3: ='CO2e Emissions by Sector-Expert'!B3 -> 155.694 | R3: ='CO2e Emissions by Sector-Expert'!C3 -> 118.146 | S3: ='CO2e Emissions by Sector-Expert'!D3 -> 16.5497 | T3: ='CO2e Emissions by Sector-Expert'!E3 -> 4.18505 | U3: ='CO2e Emissions by Sector-Expert'!F3 -> 130.491 | V3: ='CO2e Emissions by Sector-Expert'!G3 -> 5.23e-06 | W3: ='CO2e Emissions by Sector-Expert'!H3 -> 17.4851 | X3: ='CO2e Emissions by Sector-Expert'!I3 -> 80.4863 | Y3: ='CO2e Emissions by Sector-Expert'!J3 -> 50.172 | Z3: ='CO2e Emissions by Sector-CAS'!B3 -> 153.605 | AA3: ='CO2e Emissions by Sector-CAS'!C3 -> 118.194 | AB3: ='CO2e Emissions by Sector-CAS'!D3 -> 16.5469 | AC3: ='CO2e Emissions by Sector-CAS'!E3 -> 4.18492 | AD3: ='CO2e Emissions by Sector-CAS'!F3 -> 130.483 | AE3: ='CO2e Emissions by Sector-CAS'!G3 -> 5.23e-06 | AF3: ='CO2e Emissions by Sector-CAS'!H3 -> 17.5193 | AG3: ='CO2e Emissions by Sector-CAS'!I3 -> 80.494 | AH3: ='CO2e Emissions by Sector-CAS'!J3 -> 50.1587 | AI3: ='EG-BAU'!A24 -> Natural Gas | AJ3: ='EG-BAU-2030'!B3 -> 189.89606 | AK3: ='EG-BAU-2050'!B3 -> 224.9363 | AL3: ='EG-Expert-2030'!B3 -> 187.12882 | AM3: ='EG-Expert-2050'!B3 -> 202.3719 | AN3: ='EG-CAS-2030'!B3 -> 108.08882 | AO3: ='EG-CAS-2050'!B3 -> 15.39577 | AP3: =GDP!B3 -> 0 | AQ3: =GDP!C3 -> 0 | AR3: =GDP!D3 -> 0 | AS3: =Jobs!B3 -> 0 | AT3: =Jobs!C3 -> 0 | AU3: =Jobs!D3 -> 0 | AV3: =Debt!B3 -> 0 | AW3: =Debt!C3 -> 0 | AX3: =Debt!D3 -> 0 | AY3: ='GCF-Expert'!B3 -> 0 | AZ3: ='GCF-Expert'!C3 -> 0 | BA3: ='GCF-Expert'!D3 -> 0 | BB3: ='GCF-Expert'!E3 -> 0 | BC3: ='GCF-Expert'!F3 -> 0 | BD3: ='GCF-Expert'!G3 -> 0 | BE3: ='GCF-Expert'!H3 -> 0 | BF3: ='GCF-Expert'!I3 -> 0 | BG3: ='GCF-Expert'!J3 -> 0 | BH3: ='GCF-CAS'!B3 -> 0 | BI3: ='GCF-CAS'!C3 -> 0 | BJ3: ='GCF-CAS'!D3 -> 0 | BK3: ='GCF-CAS'!E3 -> 0 | BL3: ='GCF-CAS'!F3 -> 0 | BM3: ='GCF-CAS'!G3 -> 0 | BN3: ='GCF-CAS'!H3 -> 0 | BO3: ='GCF-CAS'!I3 -> 0 | BP3: ='GCF-CAS'!J3 -> 0
A4: =GDP!A4 -> 2022 | B4: ='CO2e Emissions'!B4 -> 587.302 | C4: ='CO2e Emissions'!C4 -> 587.302 | D4: ='CO2e Emissions'!D4 -> 587.302 | E4: ='CO2e Emissions (LULUCF excl)'!B4 -> 569.98 | F4: ='CO2e Emissions (LULUCF excl)'!C4 -> 569.98 | G4: ='CO2e Emissions (LULUCF excl)'!D4 -> 569.98 | H4: ='CO2e Emissions by Sector-BAU'!B4 -> 157.844 | I4: ='CO2e Emissions by Sector-BAU'!C4 -> 126.295 | J4: ='CO2e Emissions by Sector-BAU'!D4 -> 16.5328 | K4: ='CO2e Emissions by Sector-BAU'!E4 -> 4.19914 | L4: ='CO2e Emissions by Sector-BAU'!F4 -> 133.136 | M4: ='CO2e Emissions by Sector-BAU'!G4 -> 1.0418e-05 | N4: ='CO2e Emissions by Sector-BAU'!H4 -> 17.3223 | O4: ='CO2e Emissions by Sector-BAU'!I4 -> 80.9725 | P4: ='CO2e Emissions by Sector-BAU'!J4 -> 51.0008 | Q4: ='CO2e Emissions by Sector-Expert'!B4 -> 160.041 | R4: ='CO2e Emissions by Sector-Expert'!C4 -> 126.305 | S4: ='CO2e Emissions by Sector-Expert'!D4 -> 16.5303 | T4: ='CO2e Emissions by Sector-Expert'!E4 -> 4.1993 | U4: ='CO2e Emissions by Sector-Expert'!F4 -> 133.137 | V4: ='CO2e Emissions by Sector-Expert'!G4 -> 1.0418e-05 | W4: ='CO2e Emissions by Sector-Expert'!H4 -> 17.3332 | X4: ='CO2e Emissions by Sector-Expert'!I4 -> 80.9681 | Y4: ='CO2e Emissions by Sector-Expert'!J4 -> 50.9886 | Z4: ='CO2e Emissions by Sector-CAS'!B4 -> 157.844 | AA4: ='CO2e Emissions by Sector-CAS'!C4 -> 126.295 | AB4: ='CO2e Emissions by Sector-CAS'!D4 -> 16.5328 | AC4: ='CO2e Emissions by Sector-CAS'!E4 -> 4.19914 | AD4: ='CO2e Emissions by Sector-CAS'!F4 -> 133.136 | AE4: ='CO2e Emissions by Sector-CAS'!G4 -> 1.0418e-05 | AF4: ='CO2e Emissions by Sector-CAS'!H4 -> 17.3223 | AG4: ='CO2e Emissions by Sector-CAS'!I4 -> 80.9725 | AH4: ='CO2e Emissions by Sector-CAS'!J4 -> 51.0008 | AI4: ='EG-BAU'!A25 -> Solar | AJ4: ='EG-BAU-2030'!B4 -> 93.2443 | AK4: ='EG-BAU-2050'!B4 -> 227.432 | AL4: ='EG-Expert-2030'!B4 -> 94.4174 | AM4: ='EG-Expert-2050'!B4 -> 242.076 | AN4: ='EG-CAS-2030'!B4 -> 136.173 | AO4: ='EG-CAS-2050'!B4 -> 397.6802 | AP4: =GDP!B4 -> 0 | AQ4: =GDP!C4 -> 0 | AR4: =GDP!D4 -> 0 | AS4: =Jobs!B4 -> 0 | AT4: =Jobs!C4 -> 0 | AU4: =Jobs!D4 -> 0 | AV4: =Debt!B4 -> 0 | AW4: =Debt!C4 -> 0 | AX4: =Debt!D4 -> 0 | AY4: ='GCF-Expert'!B4 -> 0 | AZ4: ='GCF-Expert'!C4 -> 0 | BA4: ='GCF-Expert'!D4 -> 0 | BB4: ='GCF-Expert'!E4 -> 0 | BC4: ='GCF-Expert'!F4 -> 0 | BD4: ='GCF-Expert'!G4 -> 0 | BE4: ='GCF-Expert'!H4 -> 0 | BF4: ='GCF-Expert'!I4 -> 0 | BG4: ='GCF-Expert'!J4 -> 0 | BH4: ='GCF-CAS'!B4 -> 0 | BI4: ='GCF-CAS'!C4 -> 0 | BJ4: ='GCF-CAS'!D4 -> 0 | BK4: ='GCF-CAS'!E4 -> 0 | BL4: ='GCF-CAS'!F4 -> 0 | BM4: ='GCF-CAS'!G4 -> 0 | BN4: ='GCF-CAS'!H4 -> 0 | BO4: ='GCF-CAS'!I4 -> 0 | BP4: ='GCF-CAS'!J4 -> 0
A5: =GDP!A5 -> 2023 | B5: ='CO2e Emissions'!B5 -> 594.024 | C5: ='CO2e Emissions'!C5 -> 594.024 | D5: ='CO2e Emissions'!D5 -> 594.024 | E5: ='CO2e Emissions (LULUCF excl)'!B5 -> 576.799 | F5: ='CO2e Emissions (LULUCF excl)'!C5 -> 576.799 | G5: ='CO2e Emissions (LULUCF excl)'!D5 -> 576.799 | H5: ='CO2e Emissions by Sector-BAU'!B5 -> 162.543 | I5: ='CO2e Emissions by Sector-BAU'!C5 -> 124.52 | J5: ='CO2e Emissions by Sector-BAU'!D5 -> 16.506 | K5: ='CO2e Emissions by Sector-BAU'!E5 -> 4.20967 | L5: ='CO2e Emissions by Sector-BAU'!F5 -> 135.757 | M5: ='CO2e Emissions by Sector-BAU'!G5 -> 1.5708e-05 | N5: ='CO2e Emissions by Sector-BAU'!H5 -> 17.2256 | O5: ='CO2e Emissions by Sector-BAU'!I5 -> 81.4487 | P5: ='CO2e Emissions by Sector-BAU'!J5 -> 51.815 | Q5: ='CO2e Emissions by Sector-Expert'!B5 -> 164.875 | R5: ='CO2e Emissions by Sector-Expert'!C5 -> 124.487 | S5: ='CO2e Emissions by Sector-Expert'!D5 -> 16.5055 | T5: ='CO2e Emissions by Sector-Expert'!E5 -> 4.20939 | U5: ='CO2e Emissions by Sector-Expert'!F5 -> 135.736 | V5: ='CO2e Emissions by Sector-Expert'!G5 -> 1.5708e-05 | W5: ='CO2e Emissions by Sector-Expert'!H5 -> 17.1813 | X5: ='CO2e Emissions by Sector-Expert'!I5 -> 81.4491 | Y5: ='CO2e Emissions by Sector-Expert'!J5 -> 51.8052 | Z5: ='CO2e Emissions by Sector-CAS'!B5 -> 162.543 | AA5: ='CO2e Emissions by Sector-CAS'!C5 -> 124.52 | AB5: ='CO2e Emissions by Sector-CAS'!D5 -> 16.506 | AC5: ='CO2e Emissions by Sector-CAS'!E5 -> 4.20967 | AD5: ='CO2e Emissions by Sector-CAS'!F5 -> 135.757 | AE5: ='CO2e Emissions by Sector-CAS'!G5 -> 1.5708e-05 | AF5: ='CO2e Emissions by Sector-CAS'!H5 -> 17.2256 | AG5: ='CO2e Emissions by Sector-CAS'!I5 -> 81.4487 | AH5: ='CO2e Emissions by Sector-CAS'!J5 -> 51.815 | AI5: ='EG-BAU'!A26 -> Wind | AJ5: ='EG-BAU-2030'!B5 -> 60.86173 | AK5: ='EG-BAU-2050'!B5 -> 102.4973 | AL5: ='EG-Expert-2030'!B5 -> 61.34142 | AM5: ='EG-Expert-2050'!B5 -> 107.45494 | AN5: ='EG-CAS-2030'!B5 -> 81.38545 | AO5: ='EG-CAS-2050'!B5 -> 162.84007 | AP5: =GDP!B5 -> 0 | AQ5: =GDP!C5 -> 0 | AR5: =GDP!D5 -> 0 | AS5: =Jobs!B5 -> 0 | AT5: =Jobs!C5 -> 0 | AU5: =Jobs!D5 -> 0 | AV5: =Debt!B5 -> 0 | AW5: =Debt!C5 -> 0 | AX5: =Debt!D5 -> 0 | AY5: ='GCF-Expert'!B5 -> 0 | AZ5: ='GCF-Expert'!C5 -> 0 | BA5: ='GCF-Expert'!D5 -> 0 | BB5: ='GCF-Expert'!E5 -> 0 | BC5: ='GCF-Expert'!F5 -> 0 | BD5: ='GCF-Expert'!G5 -> 0 | BE5: ='GCF-Expert'!H5 -> 0 | BF5: ='GCF-Expert'!I5 -> 0 | BG5: ='GCF-Expert'!J5 -> 0 | BH5: ='GCF-CAS'!B5 -> 0 | BI5: ='GCF-CAS'!C5 -> 0 | BJ5: ='GCF-CAS'!D5 -> 0 | BK5: ='GCF-CAS'!E5 -> 0 | BL5: ='GCF-CAS'!F5 -> 0 | BM5: ='GCF-CAS'!G5 -> 0 | BN5: ='GCF-CAS'!H5 -> 0 | BO5: ='GCF-CAS'!I5 -> 0 | BP5: ='GCF-CAS'!J5 -> 0
A6: =GDP!A6 -> 2024 | B6: ='CO2e Emissions'!B6 -> 602.923 | C6: ='CO2e Emissions'!C6 -> 602.923 | D6: ='CO2e Emissions'!D6 -> 602.923 | E6: ='CO2e Emissions (LULUCF excl)'!B6 -> 585.894 | F6: ='CO2e Emissions (LULUCF excl)'!C6 -> 585.894 | G6: ='CO2e Emissions (LULUCF excl)'!D6 -> 585.894 | H6: ='CO2e Emissions by Sector-BAU'!B6 -> 167.322 | I6: ='CO2e Emissions by Sector-BAU'!C6 -> 124.958 | J6: ='CO2e Emissions by Sector-BAU'!D6 -> 16.4862 | K6: ='CO2e Emissions by Sector-BAU'!E6 -> 4.22107 | L6: ='CO2e Emissions by Sector-BAU'!F6 -> 138.353 | M6: ='CO2e Emissions by Sector-BAU'!G6 -> 2.0934e-05 | N6: ='CO2e Emissions by Sector-BAU'!H6 -> 17.0292 | O6: ='CO2e Emissions by Sector-BAU'!I6 -> 81.9246 | P6: ='CO2e Emissions by Sector-BAU'!J6 -> 52.629 | Q6: ='CO2e Emissions by Sector-Expert'!B6 -> 169.809 | R6: ='CO2e Emissions by Sector-Expert'!C6 -> 124.909 | S6: ='CO2e Emissions by Sector-Expert'!D6 -> 16.4831 | T6: ='CO2e Emissions by Sector-Expert'!E6 -> 4.22127 | U6: ='CO2e Emissions by Sector-Expert'!F6 -> 138.338 | V6: ='CO2e Emissions by Sector-Expert'!G6 -> 2.0934e-05 | W6: ='CO2e Emissions by Sector-Expert'!H6 -> 17.0294 | X6: ='CO2e Emissions by Sector-Expert'!I6 -> 81.9298 | Y6: ='CO2e Emissions by Sector-Expert'!J6 -> 52.6217 | Z6: ='CO2e Emissions by Sector-CAS'!B6 -> 167.322 | AA6: ='CO2e Emissions by Sector-CAS'!C6 -> 124.958 | AB6: ='CO2e Emissions by Sector-CAS'!D6 -> 16.4862 | AC6: ='CO2e Emissions by Sector-CAS'!E6 -> 4.22107 | AD6: ='CO2e Emissions by Sector-CAS'!F6 -> 138.353 | AE6: ='CO2e Emissions by Sector-CAS'!G6 -> 2.0934e-05 | AF6: ='CO2e Emissions by Sector-CAS'!H6 -> 17.0292 | AG6: ='CO2e Emissions by Sector-CAS'!I6 -> 81.9246 | AH6: ='CO2e Emissions by Sector-CAS'!J6 -> 52.629 | AI6: ='EG-BAU'!A27 -> Hydro | AJ6: ='EG-BAU-2030'!B6 -> 31.3059 | AK6: ='EG-BAU-2050'!B6 -> 31.3059 | AL6: ='EG-Expert-2030'!B6 -> 31.3059 | AM6: ='EG-Expert-2050'!B6 -> 31.3059 | AN6: ='EG-CAS-2030'!B6 -> 31.3059 | AO6: ='EG-CAS-2050'!B6 -> 31.3059 | AP6: =GDP!B6 -> 0 | AQ6: =GDP!C6 -> 0 | AR6: =GDP!D6 -> 0 | AS6: =Jobs!B6 -> 0 | AT6: =Jobs!C6 -> 0 | AU6: =Jobs!D6 -> 0 | AV6: =Debt!B6 -> 0 | AW6: =Debt!C6 -> 0 | AX6: =Debt!D6 -> 0 | AY6: ='GCF-Expert'!B6 -> 0 | AZ6: ='GCF-Expert'!C6 -> 0 | BA6: ='GCF-Expert'!D6 -> 0 | BB6: ='GCF-Expert'!E6 -> 0 | BC6: ='GCF-Expert'!F6 -> 0 | BD6: ='GCF-Expert'!G6 -> 0 | BE6: ='GCF-Expert'!H6 -> 0 | BF6: ='GCF-Expert'!I6 -> 0 | BG6: ='GCF-Expert'!J6 -> 0 | BH6: ='GCF-CAS'!B6 -> 0 | BI6: ='GCF-CAS'!C6 -> 0 | BJ6: ='GCF-CAS'!D6 -> 0 | BK6: ='GCF-CAS'!E6 -> 0 | BL6: ='GCF-CAS'!F6 -> 0 | BM6: ='GCF-CAS'!G6 -> 0 | BN6: ='GCF-CAS'!H6 -> 0 | BO6: ='GCF-CAS'!I6 -> 0 | BP6: ='GCF-CAS'!J6 -> 0
A7: =GDP!A7 -> 2025 | B7: ='CO2e Emissions'!B7 -> 614.923 | C7: ='CO2e Emissions'!C7 -> 614.923 | D7: ='CO2e Emissions'!D7 -> 614.923 | E7: ='CO2e Emissions (LULUCF excl)'!B7 -> 598.091 | F7: ='CO2e Emissions (LULUCF excl)'!C7 -> 598.091 | G7: ='CO2e Emissions (LULUCF excl)'!D7 -> 598.091 | H7: ='CO2e Emissions by Sector-BAU'!B7 -> 172.32 | I7: ='CO2e Emissions by Sector-BAU'!C7 -> 128.293 | J7: ='CO2e Emissions by Sector-BAU'!D7 -> 16.4683 | K7: ='CO2e Emissions by Sector-BAU'!E7 -> 4.2316 | L7: ='CO2e Emissions by Sector-BAU'!F7 -> 140.933 | M7: ='CO2e Emissions by Sector-BAU'!G7 -> 4.2048e-05 | N7: ='CO2e Emissions by Sector-BAU'!H7 -> 16.8325 | O7: ='CO2e Emissions by Sector-BAU'!I7 -> 82.4025 | P7: ='CO2e Emissions by Sector-BAU'!J7 -> 53.443 | Q7: ='CO2e Emissions by Sector-Expert'!B7 -> 174.966 | R7: ='CO2e Emissions by Sector-Expert'!C7 -> 128.225 | S7: ='CO2e Emissions by Sector-Expert'!D7 -> 16.4684 | T7: ='CO2e Emissions by Sector-Expert'!E7 -> 4.23137 | U7: ='CO2e Emissions by Sector-Expert'!F7 -> 140.935 | V7: ='CO2e Emissions by Sector-Expert'!G7 -> 4.2048e-05 | W7: ='CO2e Emissions by Sector-Expert'!H7 -> 16.8776 | X7: ='CO2e Emissions by Sector-Expert'!I7 -> 82.4111 | Y7: ='CO2e Emissions by Sector-Expert'!J7 -> 53.4379 | Z7: ='CO2e Emissions by Sector-CAS'!B7 -> 172.32 | AA7: ='CO2e Emissions by Sector-CAS'!C7 -> 128.293 | AB7: ='CO2e Emissions by Sector-CAS'!D7 -> 16.4683 | AC7: ='CO2e Emissions by Sector-CAS'!E7 -> 4.2316 | AD7: ='CO2e Emissions by Sector-CAS'!F7 -> 140.933 | AE7: ='CO2e Emissions by Sector-CAS'!G7 -> 4.1098e-05 | AF7: ='CO2e Emissions by Sector-CAS'!H7 -> 16.8325 | AG7: ='CO2e Emissions by Sector-CAS'!I7 -> 82.4025 | AH7: ='CO2e Emissions by Sector-CAS'!J7 -> 53.443 | AI7: ='EG-BAU'!A28 -> Oil | AJ7: ='EG-BAU-2030'!B7 -> 39.209333 | AK7: ='EG-BAU-2050'!B7 -> 40.16619 | AL7: ='EG-Expert-2030'!B7 -> 39.157041 | AM7: ='EG-Expert-2050'!B7 -> 35.89444 | AN7: ='EG-CAS-2030'!B7 -> 59.6564 | AO7: ='EG-CAS-2050'!B7 -> 37.12223 | AP7: =GDP!B7 -> 0 | AQ7: =GDP!C7 -> 0 | AR7: =GDP!D7 -> 0 | AS7: =Jobs!B7 -> 0 | AT7: =Jobs!C7 -> 0 | AU7: =Jobs!D7 -> 0 | AV7: =Debt!B7 -> 0 | AW7: =Debt!C7 -> 0 | AX7: =Debt!D7 -> 0 | AY7: ='GCF-Expert'!B7 -> 0 | AZ7: ='GCF-Expert'!C7 -> 0 | BA7: ='GCF-Expert'!D7 -> 0 | BB7: ='GCF-Expert'!E7 -> 0 | BC7: ='GCF-Expert'!F7 -> 0 | BD7: ='GCF-Expert'!G7 -> 0 | BE7: ='GCF-Expert'!H7 -> 0 | BF7: ='GCF-Expert'!I7 -> 0 | BG7: ='GCF-Expert'!J7 -> 0 | BH7: ='GCF-CAS'!B7 -> 0 | BI7: ='GCF-CAS'!C7 -> 0 | BJ7: ='GCF-CAS'!D7 -> 0 | BK7: ='GCF-CAS'!E7 -> 0 | BL7: ='GCF-CAS'!F7 -> 0 | BM7: ='GCF-CAS'!G7 -> 0 | BN7: ='GCF-CAS'!H7 -> 0 | BO7: ='GCF-CAS'!I7 -> 0 | BP7: ='GCF-CAS'!J7 -> 0
A8: =GDP!A8 -> 2026 | B8: ='CO2e Emissions'!B8 -> 624.397 | C8: ='CO2e Emissions'!C8 -> 623.941 | D8: ='CO2e Emissions'!D8 -> 610.115 | E8: ='CO2e Emissions (LULUCF excl)'!B8 -> 607.672 | F8: ='CO2e Emissions (LULUCF excl)'!C8 -> 607.311 | G8: ='CO2e Emissions (LULUCF excl)'!D8 -> 593.833 | H8: ='CO2e Emissions by Sector-BAU'!B8 -> 177.392 | I8: ='CO2e Emissions by Sector-BAU'!C8 -> 126.825 | J8: ='CO2e Emissions by Sector-BAU'!D8 -> 16.4548 | K8: ='CO2e Emissions by Sector-BAU'!E8 -> 4.24362 | L8: ='CO2e Emissions by Sector-BAU'!F8 -> 142.916 | M8: ='CO2e Emissions by Sector-BAU'!G8 -> 6.324e-05 | N8: ='CO2e Emissions by Sector-BAU'!H8 -> 16.7357 | O8: ='CO2e Emissions by Sector-BAU'!I8 -> 82.8242 | P8: ='CO2e Emissions by Sector-BAU'!J8 -> 54.226 | Q8: ='CO2e Emissions by Sector-Expert'!B8 -> 180.166 | R8: ='CO2e Emissions by Sector-Expert'!C8 -> 126.595 | S8: ='CO2e Emissions by Sector-Expert'!D8 -> 16.4555 | T8: ='CO2e Emissions by Sector-Expert'!E8 -> 4.24216 | U8: ='CO2e Emissions by Sector-Expert'!F8 -> 142.778 | V8: ='CO2e Emissions by Sector-Expert'!G8 -> 0.0723507 | W8: ='CO2e Emissions by Sector-Expert'!H8 -> 16.63 | X8: ='CO2e Emissions by Sector-Expert'!I8 -> 82.7865 | Y8: ='CO2e Emissions by Sector-Expert'!J8 -> 54.2148 | Z8: ='CO2e Emissions by Sector-CAS'!B8 -> 174.763 | AA8: ='CO2e Emissions by Sector-CAS'!C8 -> 122.763 | AB8: ='CO2e Emissions by Sector-CAS'!D8 -> 16.3485 | AC8: ='CO2e Emissions by Sector-CAS'!E8 -> 4.21369 | AD8: ='CO2e Emissions by Sector-CAS'!F8 -> 140.821 | AE8: ='CO2e Emissions by Sector-CAS'!G8 -> 0.286704 | AF8: ='CO2e Emissions by Sector-CAS'!H8 -> 16.2815 | AG8: ='CO2e Emissions by Sector-CAS'!I8 -> 82.0507 | AH8: ='CO2e Emissions by Sector-CAS'!J8 -> 53.1661 | AI8: ='EG-BAU'!A29 -> Other | AJ8: ='EG-BAU-2030'!B8 -> 29.10166 | AK8: ='EG-BAU-2050'!B8 -> 33.52897 | AL8: ='EG-Expert-2030'!B8 -> 28.94325 | AM8: ='EG-Expert-2050'!B8 -> 25.715443 | AN8: ='EG-CAS-2030'!B8 -> 26.26382 | AO8: ='EG-CAS-2050'!B8 -> 24.899893 | AP8: =GDP!B8 -> 0 | AQ8: =GDP!C8 -> 0.103657 | AR8: =GDP!D8 -> 0.6398 | AS8: =Jobs!B8 -> 0 | AT8: =Jobs!C8 -> 3665 | AU8: =Jobs!D8 -> 11238 | AV8: =Debt!B8 -> 0 | AW8: =Debt!C8 -> -0.0111352 | AX8: =Debt!D8 -> -0.305104 | AY8: ='GCF-Expert'!B8 -> 0.122377 | AZ8: ='GCF-Expert'!C8 -> -0.00225562 | BA8: ='GCF-Expert'!D8 -> 0 | BB8: ='GCF-Expert'!E8 -> 0 | BC8: ='GCF-Expert'!F8 -> 0 | BD8: ='GCF-Expert'!G8 -> 0 | BE8: ='GCF-Expert'!H8 -> 0.000374575 | BF8: ='GCF-Expert'!I8 -> 0 | BG8: ='GCF-Expert'!J8 -> -0.01048 | BH8: ='GCF-CAS'!B8 -> 1.38372 | BI8: ='GCF-CAS'!C8 -> -0.212177 | BJ8: ='GCF-CAS'!D8 -> 0 | BK8: ='GCF-CAS'!E8 -> 0 | BL8: ='GCF-CAS'!F8 -> 0 | BM8: ='GCF-CAS'!G8 -> 0 | BN8: ='GCF-CAS'!H8 -> 0.214247 | BO8: ='GCF-CAS'!I8 -> 0 | BP8: ='GCF-CAS'!J8 -> -0.0330909
A9: =GDP!A9 -> 2027 | B9: ='CO2e Emissions'!B9 -> 631.592 | C9: ='CO2e Emissions'!C9 -> 630.135 | D9: ='CO2e Emissions'!D9 -> 600.575 | E9: ='CO2e Emissions (LULUCF excl)'!B9 -> 615.019 | F9: ='CO2e Emissions (LULUCF excl)'!C9 -> 613.848 | G9: ='CO2e Emissions (LULUCF excl)'!D9 -> 585.233 | H9: ='CO2e Emissions by Sector-BAU'!B9 -> 182.716 | I9: ='CO2e Emissions by Sector-BAU'!C9 -> 125.095 | J9: ='CO2e Emissions by Sector-BAU'!D9 -> 16.4473 | K9: ='CO2e Emissions by Sector-BAU'!E9 -> 4.2543 | L9: ='CO2e Emissions by Sector-BAU'!F9 -> 145.436 | M9: ='CO2e Emissions by Sector-BAU'!G9 -> 0.000100598 | N9: ='CO2e Emissions by Sector-BAU'!H9 -> 16.539 | O9: ='CO2e Emissions by Sector-BAU'!I9 -> 83.2178 | P9: ='CO2e Emissions by Sector-BAU'!J9 -> 54.9809 | Q9: ='CO2e Emissions by Sector-Expert'!B9 -> 185.508 | R9: ='CO2e Emissions by Sector-Expert'!C9 -> 124.239 | S9: ='CO2e Emissions by Sector-Expert'!D9 -> 16.4395 | T9: ='CO2e Emissions by Sector-Expert'!E9 -> 4.25087 | U9: ='CO2e Emissions by Sector-Expert'!F9 -> 145.11 | V9: ='CO2e Emissions by Sector-Expert'!G9 -> 0.147015 | W9: ='CO2e Emissions by Sector-Expert'!H9 -> 16.2868 | X9: ='CO2e Emissions by Sector-Expert'!I9 -> 83.1621 | Y9: ='CO2e Emissions by Sector-Expert'!J9 -> 54.9933 | Z9: ='CO2e Emissions by Sector-CAS'!B9 -> 176.855 | AA9: ='CO2e Emissions by Sector-CAS'!C9 -> 113.992 | AB9: ='CO2e Emissions by Sector-CAS'!D9 -> 16.1516 | AC9: ='CO2e Emissions by Sector-CAS'!E9 -> 4.17433 | AD9: ='CO2e Emissions by Sector-CAS'!F9 -> 140.288 | AE9: ='CO2e Emissions by Sector-CAS'!G9 -> 0.613581 | AF9: ='CO2e Emissions by Sector-CAS'!H9 -> 15.342 | AG9: ='CO2e Emissions by Sector-CAS'!I9 -> 81.7227 | AH9: ='CO2e Emissions by Sector-CAS'!J9 -> 52.8137 | AP9: =GDP!B9 -> 0 | AQ9: =GDP!C9 -> 0.365529 | AR9: =GDP!D9 -> 2.16838 | AS9: =Jobs!B9 -> 0 | AT9: =Jobs!C9 -> 5960 | AU9: =Jobs!D9 -> 29863 | AV9: =Debt!B9 -> 0 | AW9: =Debt!C9 -> -0.0285061 | AX9: =Debt!D9 -> -0.89126 | AY9: ='GCF-Expert'!B9 -> 0.246512 | AZ9: ='GCF-Expert'!C9 -> -0.021866 | BA9: ='GCF-Expert'!D9 -> 0 | BB9: ='GCF-Expert'!E9 -> 0 | BC9: ='GCF-Expert'!F9 -> 0 | BD9: ='GCF-Expert'!G9 -> 0 | BE9: ='GCF-Expert'!H9 -> 0.00154327 | BF9: ='GCF-Expert'!I9 -> 0.000768773 | BG9: ='GCF-Expert'!J9 -> -0.0220216 | BH9: ='GCF-CAS'!B9 -> 2.72209 | BI9: ='GCF-CAS'!C9 -> -0.546468 | BJ9: ='GCF-CAS'!D9 -> 0 | BK9: ='GCF-CAS'!E9 -> 0 | BL9: ='GCF-CAS'!F9 -> 0 | BM9: ='GCF-CAS'!G9 -> 0 | BN9: ='GCF-CAS'!H9 -> 0.456358 | BO9: ='GCF-CAS'!I9 -> 0.0210644 | BP9: ='GCF-CAS'!J9 -> -0.0837514
A10: =GDP!A10 -> 2028 | B10: ='CO2e Emissions'!B10 -> 639.76 | C10: ='CO2e Emissions'!C10 -> 637.555 | D10: ='CO2e Emissions'!D10 -> 569.329 | E10: ='CO2e Emissions (LULUCF excl)'!B10 -> 623.338 | F10: ='CO2e Emissions (LULUCF excl)'!C10 -> 621.707 | G10: ='CO2e Emissions (LULUCF excl)'!D10 -> 555.115 | H10: ='CO2e Emissions by Sector-BAU'!B10 -> 188.315 | I10: ='CO2e Emissions by Sector-BAU'!C10 -> 124.493 | J10: ='CO2e Emissions by Sector-BAU'!D10 -> 16.4366 | K10: ='CO2e Emissions by Sector-BAU'!E10 -> 4.26632 | L10: ='CO2e Emissions by Sector-BAU'!F10 -> 147.301 | M10: ='CO2e Emissions by Sector-BAU'!G10 -> 0.00014941 | N10: ='CO2e Emissions by Sector-BAU'!H10 -> 16.4426 | O10: ='CO2e Emissions by Sector-BAU'!I10 -> 83.6129 | P10: ='CO2e Emissions by Sector-BAU'!J10 -> 55.7634 | Q10: ='CO2e Emissions by Sector-Expert'!B10 -> 191.148 | R10: ='CO2e Emissions by Sector-Expert'!C10 -> 123.607 | S10: ='CO2e Emissions by Sector-Expert'!D10 -> 16.4323 | T10: ='CO2e Emissions by Sector-Expert'!E10 -> 4.26258 | U10: ='CO2e Emissions by Sector-Expert'!F10 -> 146.728 | V10: ='CO2e Emissions by Sector-Expert'!G10 -> 0.224075 | W10: ='CO2e Emissions by Sector-Expert'!H10 -> 15.8479 | X10: ='CO2e Emissions by Sector-Expert'!I10 -> 83.5384 | Y10: ='CO2e Emissions by Sector-Expert'!J10 -> 55.7698 | Z10: ='CO2e Emissions by Sector-CAS'!B10 -> 178.618 | AA10: ='CO2e Emissions by Sector-CAS'!C10 -> 102.621 | AB10: ='CO2e Emissions by Sector-CAS'!D10 -> 15.9564 | AC10: ='CO2e Emissions by Sector-CAS'!E10 -> 4.1379 | AD10: ='CO2e Emissions by Sector-CAS'!F10 -> 124.122 | AE10: ='CO2e Emissions by Sector-CAS'!G10 -> 0.910543 | AF10: ='CO2e Emissions by Sector-CAS'!H10 -> 14.2141 | AG10: ='CO2e Emissions by Sector-CAS'!I10 -> 81.3199 | AH10: ='CO2e Emissions by Sector-CAS'!J10 -> 49.9559 | AP10: =GDP!B10 -> 0 | AQ10: =GDP!C10 -> 0.413142 | AR10: =GDP!D10 -> 2.66335 | AS10: =Jobs!B10 -> 0 | AT10: =Jobs!C10 -> 8943 | AU10: =Jobs!D10 -> 41096 | AV10: =Debt!B10 -> 0 | AW10: =Debt!C10 -> -0.0632478 | AX10: =Debt!D10 -> -1.77272 | AY10: ='GCF-Expert'!B10 -> 0.373398 | AZ10: ='GCF-Expert'!C10 -> -0.0270766 | BA10: ='GCF-Expert'!D10 -> 0 | BB10: ='GCF-Expert'!E10 -> 0 | BC10: ='GCF-Expert'!F10 -> 0 | BD10: ='GCF-Expert'!G10 -> 0 | BE10: ='GCF-Expert'!H10 -> 0.00434702 | BF10: ='GCF-Expert'!I10 -> 0.00196806 | BG10: ='GCF-Expert'!J10 -> -0.0208821 | BH10: ='GCF-CAS'!B10 -> 3.80419 | BI10: ='GCF-CAS'!C10 -> -0.983384 | BJ10: ='GCF-CAS'!D10 -> 0 | BK10: ='GCF-CAS'!E10 -> 0 | BL10: ='GCF-CAS'!F10 -> 0 | BM10: ='GCF-CAS'!G10 -> 0 | BN10: ='GCF-CAS'!H10 -> 0.768218 | BO10: ='GCF-CAS'!I10 -> 0.0615326 | BP10: ='GCF-CAS'!J10 -> -0.102529
A11: =GDP!A11 -> 2029 | B11: ='CO2e Emissions'!B11 -> 648.691 | C11: ='CO2e Emissions'!C11 -> 645.225 | D11: ='CO2e Emissions'!D11 -> 553.22 | E11: ='CO2e Emissions (LULUCF excl)'!B11 -> 632.421 | F11: ='CO2e Emissions (LULUCF excl)'!C11 -> 629.912 | G11: ='CO2e Emissions (LULUCF excl)'!D11 -> 540.523 | H11: ='CO2e Emissions by Sector-BAU'!B11 -> 194.222 | I11: ='CO2e Emissions by Sector-BAU'!C11 -> 124.45 | J11: ='CO2e Emissions by Sector-BAU'!D11 -> 16.4425 | K11: ='CO2e Emissions by Sector-BAU'!E11 -> 4.27762 | L11: ='CO2e Emissions by Sector-BAU'!F11 -> 149.201 | M11: ='CO2e Emissions by Sector-BAU'!G11 -> 0.000226214 | N11: ='CO2e Emissions by Sector-BAU'!H11 -> 16.2456 | O11: ='CO2e Emissions by Sector-BAU'!I11 -> 84.034 | P11: ='CO2e Emissions by Sector-BAU'!J11 -> 56.5458 | Q11: ='CO2e Emissions by Sector-Expert'!B11 -> 197.009 | R11: ='CO2e Emissions by Sector-Expert'!C11 -> 123.056 | S11: ='CO2e Emissions by Sector-Expert'!D11 -> 16.4296 | T11: ='CO2e Emissions by Sector-Expert'!E11 -> 4.27191 | U11: ='CO2e Emissions by Sector-Expert'!F11 -> 148.383 | V11: ='CO2e Emissions by Sector-Expert'!G11 -> 0.303271 | W11: ='CO2e Emissions by Sector-Expert'!H11 -> 15.3133 | X11: ='CO2e Emissions by Sector-Expert'!I11 -> 83.9159 | Y11: ='CO2e Emissions by Sector-Expert'!J11 -> 56.5487 | Z11: ='CO2e Emissions by Sector-CAS'!B11 -> 180.119 | AA11: ='CO2e Emissions by Sector-CAS'!C11 -> 89.3126 | AB11: ='CO2e Emissions by Sector-CAS'!D11 -> 15.7236 | AC11: ='CO2e Emissions by Sector-CAS'!E11 -> 4.08595 | AD11: ='CO2e Emissions by Sector-CAS'!F11 -> 124.22 | AE11: ='CO2e Emissions by Sector-CAS'!G11 -> 1.22233 | AF11: ='CO2e Emissions by Sector-CAS'!H11 -> 12.6973 | AG11: ='CO2e Emissions by Sector-CAS'!I11 -> 81.0389 | AH11: ='CO2e Emissions by Sector-CAS'!J11 -> 49.466 | AP11: =GDP!B11 -> 0 | AQ11: =GDP!C11 -> 0.505392 | AR11: =GDP!D11 -> 2.91878 | AS11: =Jobs!B11 -> 0 | AT11: =Jobs!C11 -> 11388 | AU11: =Jobs!D11 -> 45198 | AV11: =Debt!B11 -> 0 | AW11: =Debt!C11 -> -0.106007 | AX11: =Debt!D11 -> -2.95394 | AY11: ='GCF-Expert'!B11 -> 0.504233 | AZ11: ='GCF-Expert'!C11 -> -0.0516046 | BA11: ='GCF-Expert'!D11 -> 0 | BB11: ='GCF-Expert'!E11 -> 0 | BC11: ='GCF-Expert'!F11 -> 0 | BD11: ='GCF-Expert'!G11 -> 0 | BE11: ='GCF-Expert'!H11 -> 0.00822467 | BF11: ='GCF-Expert'!I11 -> 0.00436663 | BG11: ='GCF-Expert'!J11 -> -0.0334625 | BH11: ='GCF-CAS'!B11 -> 4.96878 | BI11: ='GCF-CAS'!C11 -> -1.48229 | BJ11: ='GCF-CAS'!D11 -> 0 | BK11: ='GCF-CAS'!E11 -> 0 | BL11: ='GCF-CAS'!F11 -> 0 | BM11: ='GCF-CAS'!G11 -> 0 | BN11: ='GCF-CAS'!H11 -> 1.11408 | BO11: ='GCF-CAS'!I11 -> 0.122389 | BP11: ='GCF-CAS'!J11 -> -0.179292
A12: =GDP!A12 -> 2030 | B12: ='CO2e Emissions'!B12 -> 659.618 | C12: ='CO2e Emissions'!C12 -> 654.99 | D12: ='CO2e Emissions'!D12 -> 543.001 | E12: ='CO2e Emissions (LULUCF excl)'!B12 -> 643.5 | F12: ='CO2e Emissions (LULUCF excl)'!C12 -> 640.307 | G12: ='CO2e Emissions (LULUCF excl)'!D12 -> 532.224 | H12: ='CO2e Emissions by Sector-BAU'!B12 -> 200.134 | I12: ='CO2e Emissions by Sector-BAU'!C12 -> 126.496 | J12: ='CO2e Emissions by Sector-BAU'!D12 -> 16.4347 | K12: ='CO2e Emissions by Sector-BAU'!E12 -> 4.28892 | L12: ='CO2e Emissions by Sector-BAU'!F12 -> 151.107 | M12: ='CO2e Emissions by Sector-BAU'!G12 -> 0.000335664 | N12: ='CO2e Emissions by Sector-BAU'!H12 -> 16.1491 | O12: ='CO2e Emissions by Sector-BAU'!I12 -> 84.4287 | P12: ='CO2e Emissions by Sector-BAU'!J12 -> 57.3282 | Q12: ='CO2e Emissions by Sector-Expert'!B12 -> 202.847 | R12: ='CO2e Emissions by Sector-Expert'!C12 -> 124.726 | S12: ='CO2e Emissions by Sector-Expert'!D12 -> 16.4213 | T12: ='CO2e Emissions by Sector-Expert'!E12 -> 4.28281 | U12: ='CO2e Emissions by Sector-Expert'!F12 -> 150.03 | V12: ='CO2e Emissions by Sector-Expert'!G12 -> 0.385231 | W12: ='CO2e Emissions by Sector-Expert'!H12 -> 14.6831 | X12: ='CO2e Emissions by Sector-Expert'!I12 -> 84.2958 | Y12: ='CO2e Emissions by Sector-Expert'!J12 -> 57.3256 | Z12: ='CO2e Emissions by Sector-CAS'!B12 -> 181.139 | AA12: ='CO2e Emissions by Sector-CAS'!C12 -> 81.5904 | AB12: ='CO2e Emissions by Sector-CAS'!D12 -> 15.4767 | AC12: ='CO2e Emissions by Sector-CAS'!E12 -> 4.03317 | AD12: ='CO2e Emissions by Sector-CAS'!F12 -> 122.879 | AE12: ='CO2e Emissions by Sector-CAS'!G12 -> 1.52112 | AF12: ='CO2e Emissions by Sector-CAS'!H12 -> 10.9924 | AG12: ='CO2e Emissions by Sector-CAS'!I12 -> 80.7333 | AH12: ='CO2e Emissions by Sector-CAS'!J12 -> 48.9118 | AP12: =GDP!B12 -> 0 | AQ12: =GDP!C12 -> 0.562429 | AR12: =GDP!D12 -> 3.57197 | AS12: =Jobs!B12 -> 0 | AT12: =Jobs!C12 -> 15542 | AU12: =Jobs!D12 -> 87487 | AV12: =Debt!B12 -> 0 | AW12: =Debt!C12 -> -0.160792 | AX12: =Debt!D12 -> -4.40819 | AY12: ='GCF-Expert'!B12 -> 0.640311 | AZ12: ='GCF-Expert'!C12 -> -0.0702768 | BA12: ='GCF-Expert'!D12 -> 0 | BB12: ='GCF-Expert'!E12 -> 0 | BC12: ='GCF-Expert'!F12 -> 0 | BD12: ='GCF-Expert'!G12 -> 0 | BE12: ='GCF-Expert'!H12 -> 0.0130708 | BF12: ='GCF-Expert'!I12 -> 0.00731872 | BG12: ='GCF-Expert'!J12 -> -0.0446305 | BH12: ='GCF-CAS'!B12 -> 6.12988 | BI12: ='GCF-CAS'!C12 -> -2.00274 | BJ12: ='GCF-CAS'!D12 -> 0 | BK12: ='GCF-CAS'!E12 -> 0 | BL12: ='GCF-CAS'!F12 -> 0 | BM12: ='GCF-CAS'!G12 -> 0 | BN12: ='GCF-CAS'!H12 -> 1.44475 | BO12: ='GCF-CAS'!I12 -> 0.20394 | BP12: ='GCF-CAS'!J12 -> -0.266588
A13: =GDP!A13 -> 2031 | B13: ='CO2e Emissions'!B13 -> 668.669 | C13: ='CO2e Emissions'!C13 -> 662.726 | D13: ='CO2e Emissions'!D13 -> 535.76 | E13: ='CO2e Emissions (LULUCF excl)'!B13 -> 652.703 | F13: ='CO2e Emissions (LULUCF excl)'!C13 -> 648.769 | G13: ='CO2e Emissions (LULUCF excl)'!D13 -> 526.861 | H13: ='CO2e Emissions by Sector-BAU'!B13 -> 206.045 | I13: ='CO2e Emissions by Sector-BAU'!C13 -> 127.323 | J13: ='CO2e Emissions by Sector-BAU'!D13 -> 16.3948 | K13: ='CO2e Emissions by Sector-BAU'!E13 -> 4.28753 | L13: ='CO2e Emissions by Sector-BAU'!F13 -> 152.245 | M13: ='CO2e Emissions by Sector-BAU'!G13 -> 0.000484092 | N13: ='CO2e Emissions by Sector-BAU'!H13 -> 15.9524 | O13: ='CO2e Emissions by Sector-BAU'!I13 -> 84.7136 | P13: ='CO2e Emissions by Sector-BAU'!J13 -> 58.0516 | Q13: ='CO2e Emissions by Sector-Expert'!B13 -> 208.631 | R13: ='CO2e Emissions by Sector-Expert'!C13 -> 125.451 | S13: ='CO2e Emissions by Sector-Expert'!D13 -> 16.3808 | T13: ='CO2e Emissions by Sector-Expert'!E13 -> 4.28013 | U13: ='CO2e Emissions by Sector-Expert'!F13 -> 150.95 | V13: ='CO2e Emissions by Sector-Expert'!G13 -> 0.467149 | W13: ='CO2e Emissions by Sector-Expert'!H13 -> 13.9572 | X13: ='CO2e Emissions by Sector-Expert'!I13 -> 84.552 | Y13: ='CO2e Emissions by Sector-Expert'!J13 -> 58.0661 | Z13: ='CO2e Emissions by Sector-CAS'!B13 -> 181.65 | AA13: ='CO2e Emissions by Sector-CAS'!C13 -> 78.3354 | AB13: ='CO2e Emissions by Sector-CAS'!D13 -> 15.1946 | AC13: ='CO2e Emissions by Sector-CAS'!E13 -> 3.96472 | AD13: ='CO2e Emissions by Sector-CAS'!F13 -> 120.629 | AE13: ='CO2e Emissions by Sector-CAS'!G13 -> 1.80989 | AF13: ='CO2e Emissions by Sector-CAS'!H13 -> 8.89864 | AG13: ='CO2e Emissions by Sector-CAS'!I13 -> 80.3303 | AH13: ='CO2e Emissions by Sector-CAS'!J13 -> 48.4032 | AP13: =GDP!B13 -> 0 | AQ13: =GDP!C13 -> 0.656663 | AR13: =GDP!D13 -> 5.39316 | AS13: =Jobs!B13 -> 0 | AT13: =Jobs!C13 -> 18638 | AU13: =Jobs!D13 -> 127339 | AV13: =Debt!B13 -> 0 | AW13: =Debt!C13 -> -0.221813 | AX13: =Debt!D13 -> -6.18626 | AY13: ='GCF-Expert'!B13 -> 0.749245 | AZ13: ='GCF-Expert'!C13 -> -0.0898262 | BA13: ='GCF-Expert'!D13 -> 0 | BB13: ='GCF-Expert'!E13 -> 0 | BC13: ='GCF-Expert'!F13 -> 0 | BD13: ='GCF-Expert'!G13 -> 0 | BE13: ='GCF-Expert'!H13 -> 0.0181135 | BF13: ='GCF-Expert'!I13 -> 0.0111011 | BG13: ='GCF-Expert'!J13 -> -0.0623136 | BH13: ='GCF-CAS'!B13 -> 7.03298 | BI13: ='GCF-CAS'!C13 -> -2.40367 | BJ13: ='GCF-CAS'!D13 -> 0 | BK13: ='GCF-CAS'!E13 -> 0 | BL13: ='GCF-CAS'!F13 -> 0 | BM13: ='GCF-CAS'!G13 -> 0 | BN13: ='GCF-CAS'!H13 -> 1.83254 | BO13: ='GCF-CAS'!I13 -> 0.304342 | BP13: ='GCF-CAS'!J13 -> -0.395863
A14: =GDP!A14 -> 2032 | B14: ='CO2e Emissions'!B14 -> 676.8 | C14: ='CO2e Emissions'!C14 -> 669.683 | D14: ='CO2e Emissions'!D14 -> 530.88 | E14: ='CO2e Emissions (LULUCF excl)'!B14 -> 660.986 | F14: ='CO2e Emissions (LULUCF excl)'!C14 -> 656.547 | G14: ='CO2e Emissions (LULUCF excl)'!D14 -> 524.264 | H14: ='CO2e Emissions by Sector-BAU'!B14 -> 211.873 | I14: ='CO2e Emissions by Sector-BAU'!C14 -> 127.491 | J14: ='CO2e Emissions by Sector-BAU'!D14 -> 16.4177 | K14: ='CO2e Emissions by Sector-BAU'!E14 -> 4.35188 | L14: ='CO2e Emissions by Sector-BAU'!F14 -> 153.392 | M14: ='CO2e Emissions by Sector-BAU'!G14 -> 0.000676716 | N14: ='CO2e Emissions by Sector-BAU'!H14 -> 15.8554 | O14: ='CO2e Emissions by Sector-BAU'!I14 -> 84.9995 | P14: ='CO2e Emissions by Sector-BAU'!J14 -> 58.8026 | Q14: ='CO2e Emissions by Sector-Expert'!B14 -> 214.292 | R14: ='CO2e Emissions by Sector-Expert'!C14 -> 125.415 | S14: ='CO2e Emissions by Sector-Expert'!D14 -> 16.4 | T14: ='CO2e Emissions by Sector-Expert'!E14 -> 4.3437 | U14: ='CO2e Emissions by Sector-Expert'!F14 -> 151.946 | V14: ='CO2e Emissions by Sector-Expert'!G14 -> 0.551485 | W14: ='CO2e Emissions by Sector-Expert'!H14 -> 13.1356 | X14: ='CO2e Emissions by Sector-Expert'!I14 -> 84.8028 | Y14: ='CO2e Emissions by Sector-Expert'!J14 -> 58.8053 | Z14: ='CO2e Emissions by Sector-CAS'!B14 -> 181.632 | AA14: ='CO2e Emissions by Sector-CAS'!C14 -> 77.5093 | AB14: ='CO2e Emissions by Sector-CAS'!D14 -> 14.9565 | AC14: ='CO2e Emissions by Sector-CAS'!E14 -> 3.9485 | AD14: ='CO2e Emissions by Sector-CAS'!F14 -> 119.182 | AE14: ='CO2e Emissions by Sector-CAS'!G14 -> 2.09836 | AF14: ='CO2e Emissions by Sector-CAS'!H14 -> 6.6161 | AG14: ='CO2e Emissions by Sector-CAS'!I14 -> 79.9141 | AH14: ='CO2e Emissions by Sector-CAS'!J14 -> 47.8805 | AP14: =GDP!B14 -> 0 | AQ14: =GDP!C14 -> 0.738001 | AR14: =GDP!D14 -> 6.9272 | AS14: =Jobs!B14 -> 0 | AT14: =Jobs!C14 -> 22220 | AU14: =Jobs!D14 -> 163524 | AV14: =Debt!B14 -> 0 | AW14: =Debt!C14 -> -0.292632 | AX14: =Debt!D14 -> -8.3937 | AY14: ='GCF-Expert'!B14 -> 0.862261 | AZ14: ='GCF-Expert'!C14 -> -0.106012 | BA14: ='GCF-Expert'!D14 -> 0 | BB14: ='GCF-Expert'!E14 -> 0 | BC14: ='GCF-Expert'!F14 -> 0 | BD14: ='GCF-Expert'!G14 -> 0 | BE14: ='GCF-Expert'!H14 -> 0.0258986 | BF14: ='GCF-Expert'!I14 -> 0.015314 | BG14: ='GCF-Expert'!J14 -> -0.0819249 | BH14: ='GCF-CAS'!B14 -> 7.96316 | BI14: ='GCF-CAS'!C14 -> -2.74207 | BJ14: ='GCF-CAS'!D14 -> 0 | BK14: ='GCF-CAS'!E14 -> 0 | BL14: ='GCF-CAS'!F14 -> 0 | BM14: ='GCF-CAS'!G14 -> 0 | BN14: ='GCF-CAS'!H14 -> 2.29198 | BO14: ='GCF-CAS'!I14 -> 0.427099 | BP14: ='GCF-CAS'!J14 -> -0.496454
A15: =GDP!A15 -> 2033 | B15: ='CO2e Emissions'!B15 -> 686.696 | C15: ='CO2e Emissions'!C15 -> 677.727 | D15: ='CO2e Emissions'!D15 -> 513.489 | E15: ='CO2e Emissions (LULUCF excl)'!B15 -> 671.034 | F15: ='CO2e Emissions (LULUCF excl)'!C15 -> 665.509 | G15: ='CO2e Emissions (LULUCF excl)'!D15 -> 509.544 | H15: ='CO2e Emissions by Sector-BAU'!B15 -> 217.752 | I15: ='CO2e Emissions by Sector-BAU'!C15 -> 129.253 | J15: ='CO2e Emissions by Sector-BAU'!D15 -> 16.4365 | K15: ='CO2e Emissions by Sector-BAU'!E15 -> 4.41701 | L15: ='CO2e Emissions by Sector-BAU'!F15 -> 154.541 | M15: ='CO2e Emissions by Sector-BAU'!G15 -> 0.000912572 | N15: ='CO2e Emissions by Sector-BAU'!H15 -> 15.659 | O15: ='CO2e Emissions by Sector-BAU'!I15 -> 85.285 | P15: ='CO2e Emissions by Sector-BAU'!J15 -> 59.5254 | Q15: ='CO2e Emissions by Sector-Expert'!B15 -> 219.924 | R15: ='CO2e Emissions by Sector-Expert'!C15 -> 126.62 | S15: ='CO2e Emissions by Sector-Expert'!D15 -> 16.4188 | T15: ='CO2e Emissions by Sector-Expert'!E15 -> 4.40771 | U15: ='CO2e Emissions by Sector-Expert'!F15 -> 152.91 | V15: ='CO2e Emissions by Sector-Expert'!G15 -> 0.637006 | W15: ='CO2e Emissions by Sector-Expert'!H15 -> 12.2184 | X15: ='CO2e Emissions by Sector-Expert'!I15 -> 85.0548 | Y15: ='CO2e Emissions by Sector-Expert'!J15 -> 59.5445 | Z15: ='CO2e Emissions by Sector-CAS'!B15 -> 181.244 | AA15: ='CO2e Emissions by Sector-CAS'!C15 -> 77.7064 | AB15: ='CO2e Emissions by Sector-CAS'!D15 -> 14.7221 | AC15: ='CO2e Emissions by Sector-CAS'!E15 -> 3.92838 | AD15: ='CO2e Emissions by Sector-CAS'!F15 -> 106.557 | AE15: ='CO2e Emissions by Sector-CAS'!G15 -> 2.38113 | AF15: ='CO2e Emissions by Sector-CAS'!H15 -> 3.94556 | AG15: ='CO2e Emissions by Sector-CAS'!I15 -> 79.486 | AH15: ='CO2e Emissions by Sector-CAS'!J15 -> 45.8847 | AP15: =GDP!B15 -> 0 | AQ15: =GDP!C15 -> 0.810909 | AR15: =GDP!D15 -> 7.87896 | AS15: =Jobs!B15 -> 0 | AT15: =Jobs!C15 -> 25322 | AU15: =Jobs!D15 -> 193092 | AV15: =Debt!B15 -> 0 | AW15: =Debt!C15 -> -0.369242 | AX15: =Debt!D15 -> -10.9757 | AY15: ='GCF-Expert'!B15 -> 0.976981 | AZ15: ='GCF-Expert'!C15 -> -0.138957 | BA15: ='GCF-Expert'!D15 -> 0 | BB15: ='GCF-Expert'!E15 -> 0 | BC15: ='GCF-Expert'!F15 -> 0 | BD15: ='GCF-Expert'!G15 -> 0 | BE15: ='GCF-Expert'!H15 -> 0.0352083 | BF15: ='GCF-Expert'!I15 -> 0.0202033 | BG15: ='GCF-Expert'!J15 -> -0.102758 | BH15: ='GCF-CAS'!B15 -> 8.62861 | BI15: ='GCF-CAS'!C15 -> -3.08195 | BJ15: ='GCF-CAS'!D15 -> 0 | BK15: ='GCF-CAS'!E15 -> 0 | BL15: ='GCF-CAS'!F15 -> 0 | BM15: ='GCF-CAS'!G15 -> 0 | BN15: ='GCF-CAS'!H15 -> 2.72878 | BO15: ='GCF-CAS'!I15 -> 0.579501 | BP15: ='GCF-CAS'!J15 -> -0.593665
A16: =GDP!A16 -> 2034 | B16: ='CO2e Emissions'!B16 -> 695.22 | C16: ='CO2e Emissions'!C16 -> 684.477 | D16: ='CO2e Emissions'!D16 -> 507.35 | E16: ='CO2e Emissions (LULUCF excl)'!B16 -> 679.709 | F16: ='CO2e Emissions (LULUCF excl)'!C16 -> 673.272 | G16: ='CO2e Emissions (LULUCF excl)'!D16 -> 506.364 | H16: ='CO2e Emissions by Sector-BAU'!B16 -> 223.682 | I16: ='CO2e Emissions by Sector-BAU'!C16 -> 129.699 | J16: ='CO2e Emissions by Sector-BAU'!D16 -> 16.456 | K16: ='CO2e Emissions by Sector-BAU'!E16 -> 4.48403 | L16: ='CO2e Emissions by Sector-BAU'!F16 -> 155.685 | M16: ='CO2e Emissions by Sector-BAU'!G16 -> 0.00121451 | N16: ='CO2e Emissions by Sector-BAU'!H16 -> 15.4622 | O16: ='CO2e Emissions by Sector-BAU'!I16 -> 85.5711 | P16: ='CO2e Emissions by Sector-BAU'!J16 -> 60.2763 | Q16: ='CO2e Emissions by Sector-Expert'!B16 -> 225.571 | R16: ='CO2e Emissions by Sector-Expert'!C16 -> 126.655 | S16: ='CO2e Emissions by Sector-Expert'!D16 -> 16.4405 | T16: ='CO2e Emissions by Sector-Expert'!E16 -> 4.47297 | U16: ='CO2e Emissions by Sector-Expert'!F16 -> 153.823 | V16: ='CO2e Emissions by Sector-Expert'!G16 -> 0.725403 | W16: ='CO2e Emissions by Sector-Expert'!H16 -> 11.2055 | X16: ='CO2e Emissions by Sector-Expert'!I16 -> 85.3085 | Y16: ='CO2e Emissions by Sector-Expert'!J16 -> 60.2832 | Z16: ='CO2e Emissions by Sector-CAS'!B16 -> 180.514 | AA16: ='CO2e Emissions by Sector-CAS'!C16 -> 76.6506 | AB16: ='CO2e Emissions by Sector-CAS'!D16 -> 14.3405 | AC16: ='CO2e Emissions by Sector-CAS'!E16 -> 3.87239 | AD16: ='CO2e Emissions by Sector-CAS'!F16 -> 105.887 | AE16: ='CO2e Emissions by Sector-CAS'!G16 -> 2.66071 | AF16: ='CO2e Emissions by Sector-CAS'!H16 -> 0.986203 | AG16: ='CO2e Emissions by Sector-CAS'!I16 -> 79.0452 | AH16: ='CO2e Emissions by Sector-CAS'!J16 -> 45.3565 | AP16: =GDP!B16 -> 0 | AQ16: =GDP!C16 -> 0.845627 | AR16: =GDP!D16 -> 8.34269 | AS16: =Jobs!B16 -> 0 | AT16: =Jobs!C16 -> 29795 | AU16: =Jobs!D16 -> 221974 | AV16: =Debt!B16 -> 0 | AW16: =Debt!C16 -> -0.45387 | AX16: =Debt!D16 -> -13.9078 | AY16: ='GCF-Expert'!B16 -> 1.09276 | AZ16: ='GCF-Expert'!C16 -> -0.167332 | BA16: ='GCF-Expert'!D16 -> 0 | BB16: ='GCF-Expert'!E16 -> 0 | BC16: ='GCF-Expert'!F16 -> 0 | BD16: ='GCF-Expert'!G16 -> 0 | BE16: ='GCF-Expert'!H16 -> 0.0448302 | BF16: ='GCF-Expert'!I16 -> 0.0254925 | BG16: ='GCF-Expert'!J16 -> -0.122889 | BH16: ='GCF-CAS'!B16 -> 9.50815 | BI16: ='GCF-CAS'!C16 -> -3.46531 | BJ16: ='GCF-CAS'!D16 -> 0 | BK16: ='GCF-CAS'!E16 -> 0 | BL16: ='GCF-CAS'!F16 -> 0 | BM16: ='GCF-CAS'!G16 -> 0 | BN16: ='GCF-CAS'!H16 -> 3.17304 | BO16: ='GCF-CAS'!I16 -> 0.757764 | BP16: ='GCF-CAS'!J16 -> -0.821825
A17: =GDP!A17 -> 2035 | B17: ='CO2e Emissions'!B17 -> 704.083 | C17: ='CO2e Emissions'!C17 -> 691.501 | D17: ='CO2e Emissions'!D17 -> 500.187 | E17: ='CO2e Emissions (LULUCF excl)'!B17 -> 688.725 | F17: ='CO2e Emissions (LULUCF excl)'!C17 -> 681.404 | G17: ='CO2e Emissions (LULUCF excl)'!D17 -> 502.349 | H17: ='CO2e Emissions by Sector-BAU'!B17 -> 229.784 | I17: ='CO2e Emissions by Sector-BAU'!C17 -> 129.815 | J17: ='CO2e Emissions by Sector-BAU'!D17 -> 16.4831 | K17: ='CO2e Emissions by Sector-BAU'!E17 -> 4.55125 | L17: ='CO2e Emissions by Sector-BAU'!F17 -> 157.258 | M17: ='CO2e Emissions by Sector-BAU'!G17 -> 0.00157734 | N17: ='CO2e Emissions by Sector-BAU'!H17 -> 15.3655 | O17: ='CO2e Emissions by Sector-BAU'!I17 -> 85.8554 | P17: ='CO2e Emissions by Sector-BAU'!J17 -> 60.9986 | Q17: ='CO2e Emissions by Sector-Expert'!B17 -> 231.337 | R17: ='CO2e Emissions by Sector-Expert'!C17 -> 126.535 | S17: ='CO2e Emissions by Sector-Expert'!D17 -> 16.4617 | T17: ='CO2e Emissions by Sector-Expert'!E17 -> 4.53854 | U17: ='CO2e Emissions by Sector-Expert'!F17 -> 155.135 | V17: ='CO2e Emissions by Sector-Expert'!G17 -> 0.816476 | W17: ='CO2e Emissions by Sector-Expert'!H17 -> 10.0969 | X17: ='CO2e Emissions by Sector-Expert'!I17 -> 85.5633 | Y17: ='CO2e Emissions by Sector-Expert'!J17 -> 61.0225 | Z17: ='CO2e Emissions by Sector-CAS'!B17 -> 179.486 | AA17: ='CO2e Emissions by Sector-CAS'!C17 -> 75.3471 | AB17: ='CO2e Emissions by Sector-CAS'!D17 -> 13.9168 | AC17: ='CO2e Emissions by Sector-CAS'!E17 -> 3.79667 | AD17: ='CO2e Emissions by Sector-CAS'!F17 -> 105.222 | AE17: ='CO2e Emissions by Sector-CAS'!G17 -> 3.06026 | AF17: ='CO2e Emissions by Sector-CAS'!H17 -> -2.16172 | AG17: ='CO2e Emissions by Sector-CAS'!I17 -> 78.6247 | AH17: ='CO2e Emissions by Sector-CAS'!J17 -> 44.7707 | AP17: =GDP!B17 -> 0 | AQ17: =GDP!C17 -> 0.936389 | AR17: =GDP!D17 -> 9.01423 | AS17: =Jobs!B17 -> 0 | AT17: =Jobs!C17 -> 34623 | AU17: =Jobs!D17 -> 255936 | AV17: =Debt!B17 -> 0 | AW17: =Debt!C17 -> -0.544287 | AX17: =Debt!D17 -> -17.2493 | AY17: ='GCF-Expert'!B17 -> 1.21195 | AZ17: ='GCF-Expert'!C17 -> -0.198531 | BA17: ='GCF-Expert'!D17 -> 0 | BB17: ='GCF-Expert'!E17 -> 0 | BC17: ='GCF-Expert'!F17 -> 0 | BD17: ='GCF-Expert'!G17 -> 0 | BE17: ='GCF-Expert'!H17 -> 0.0565736 | BF17: ='GCF-Expert'!I17 -> 0.0313352 | BG17: ='GCF-Expert'!J17 -> -0.153655 | BH17: ='GCF-CAS'!B17 -> 10.3594 | BI17: ='GCF-CAS'!C17 -> -3.83613 | BJ17: ='GCF-CAS'!D17 -> 0 | BK17: ='GCF-CAS'!E17 -> 0 | BL17: ='GCF-CAS'!F17 -> 0 | BM17: ='GCF-CAS'!G17 -> 0 | BN17: ='GCF-CAS'!H17 -> 3.67419 | BO17: ='GCF-CAS'!I17 -> 0.960197 | BP17: ='GCF-CAS'!J17 -> -1.04611
A18: =GDP!A18 -> 2036 | B18: ='CO2e Emissions'!B18 -> 712.751 | C18: ='CO2e Emissions'!C18 -> 698.36 | D18: ='CO2e Emissions'!D18 -> 489.227 | E18: ='CO2e Emissions (LULUCF excl)'!B18 -> 697.544 | F18: ='CO2e Emissions (LULUCF excl)'!C18 -> 689.467 | G18: ='CO2e Emissions (LULUCF excl)'!D18 -> 494.925 | H18: ='CO2e Emissions by Sector-BAU'!B18 -> 235.916 | I18: ='CO2e Emissions by Sector-BAU'!C18 -> 128.811 | J18: ='CO2e Emissions by Sector-BAU'!D18 -> 16.5048 | K18: ='CO2e Emissions by Sector-BAU'!E18 -> 4.6192 | L18: ='CO2e Emissions by Sector-BAU'!F18 -> 159.486 | M18: ='CO2e Emissions by Sector-BAU'!G18 -> 0.00200562 | N18: ='CO2e Emissions by Sector-BAU'!H18 -> 15.1688 | O18: ='CO2e Emissions by Sector-BAU'!I18 -> 86.0859 | P18: ='CO2e Emissions by Sector-BAU'!J18 -> 61.7182 | Q18: ='CO2e Emissions by Sector-Expert'!B18 -> 237.094 | R18: ='CO2e Emissions by Sector-Expert'!C18 -> 125.74 | S18: ='CO2e Emissions by Sector-Expert'!D18 -> 16.4849 | T18: ='CO2e Emissions by Sector-Expert'!E18 -> 4.60498 | U18: ='CO2e Emissions by Sector-Expert'!F18 -> 157.138 | V18: ='CO2e Emissions by Sector-Expert'!G18 -> 0.909964 | W18: ='CO2e Emissions by Sector-Expert'!H18 -> 8.89264 | X18: ='CO2e Emissions by Sector-Expert'!I18 -> 85.759 | Y18: ='CO2e Emissions by Sector-Expert'!J18 -> 61.7356 | Z18: ='CO2e Emissions by Sector-CAS'!B18 -> 177.986 | AA18: ='CO2e Emissions by Sector-CAS'!C18 -> 73.606 | AB18: ='CO2e Emissions by Sector-CAS'!D18 -> 13.4331 | AC18: ='CO2e Emissions by Sector-CAS'!E18 -> 3.69721 | AD18: ='CO2e Emissions by Sector-CAS'!F18 -> 102.685 | AE18: ='CO2e Emissions by Sector-CAS'!G18 -> 3.35182 | AF18: ='CO2e Emissions by Sector-CAS'!H18 -> -5.69817 | AG18: ='CO2e Emissions by Sector-CAS'!I18 -> 78.1765 | AH18: ='CO2e Emissions by Sector-CAS'!J18 -> 44.1641 | AP18: =GDP!B18 -> 0 | AQ18: =GDP!C18 -> 1.07328 | AR18: =GDP!D18 -> 11.7798 | AS18: =Jobs!B18 -> 0 | AT18: =Jobs!C18 -> 40982 | AU18: =Jobs!D18 -> 341794 | AV18: =Debt!B18 -> 0 | AW18: =Debt!C18 -> -0.651631 | AX18: =Debt!D18 -> -21.0517 | AY18: ='GCF-Expert'!B18 -> 1.39888 | AZ18: ='GCF-Expert'!C18 -> -0.227204 | BA18: ='GCF-Expert'!D18 -> 0 | BB18: ='GCF-Expert'!E18 -> 0 | BC18: ='GCF-Expert'!F18 -> 0 | BD18: ='GCF-Expert'!G18 -> 0 | BE18: ='GCF-Expert'!H18 -> 0.0706643 | BF18: ='GCF-Expert'!I18 -> 0.0375776 | BG18: ='GCF-Expert'!J18 -> -0.186163 | BH18: ='GCF-CAS'!B18 -> 11.684 | BI18: ='GCF-CAS'!C18 -> -4.27857 | BJ18: ='GCF-CAS'!D18 -> 0 | BK18: ='GCF-CAS'!E18 -> 0 | BL18: ='GCF-CAS'!F18 -> 0 | BM18: ='GCF-CAS'!G18 -> 0 | BN18: ='GCF-CAS'!H18 -> 4.20896 | BO18: ='GCF-CAS'!I18 -> 1.19089 | BP18: ='GCF-CAS'!J18 -> -1.32122
A19: =GDP!A19 -> 2037 | B19: ='CO2e Emissions'!B19 -> 721.951 | C19: ='CO2e Emissions'!C19 -> 705.113 | D19: ='CO2e Emissions'!D19 -> 476.999 | E19: ='CO2e Emissions (LULUCF excl)'!B19 -> 706.897 | F19: ='CO2e Emissions (LULUCF excl)'!C19 -> 697.52 | G19: ='CO2e Emissions (LULUCF excl)'!D19 -> 486.422 | H19: ='CO2e Emissions by Sector-BAU'!B19 -> 241.758 | I19: ='CO2e Emissions by Sector-BAU'!C19 -> 129.323 | J19: ='CO2e Emissions by Sector-BAU'!D19 -> 16.5339 | K19: ='CO2e Emissions by Sector-BAU'!E19 -> 4.68854 | L19: ='CO2e Emissions by Sector-BAU'!F19 -> 161.706 | M19: ='CO2e Emissions by Sector-BAU'!G19 -> 0.00253801 | N19: ='CO2e Emissions by Sector-BAU'!H19 -> 15.0724 | O19: ='CO2e Emissions by Sector-BAU'!I19 -> 86.3151 | P19: ='CO2e Emissions by Sector-BAU'!J19 -> 62.4375 | Q19: ='CO2e Emissions by Sector-Expert'!B19 -> 242.44 | R19: ='CO2e Emissions by Sector-Expert'!C19 -> 125.363 | S19: ='CO2e Emissions by Sector-Expert'!D19 -> 16.509 | T19: ='CO2e Emissions by Sector-Expert'!E19 -> 4.67223 | U19: ='CO2e Emissions by Sector-Expert'!F19 -> 159.125 | V19: ='CO2e Emissions by Sector-Expert'!G19 -> 1.00526 | W19: ='CO2e Emissions by Sector-Expert'!H19 -> 7.59273 | X19: ='CO2e Emissions by Sector-Expert'!I19 -> 85.9558 | Y19: ='CO2e Emissions by Sector-Expert'!J19 -> 62.4494 | Z19: ='CO2e Emissions by Sector-CAS'!B19 -> 175.502 | AA19: ='CO2e Emissions by Sector-CAS'!C19 -> 71.9944 | AB19: ='CO2e Emissions by Sector-CAS'!D19 -> 12.8939 | AC19: ='CO2e Emissions by Sector-CAS'!E19 -> 3.57585 | AD19: ='CO2e Emissions by Sector-CAS'!F19 -> 100.048 | AE19: ='CO2e Emissions by Sector-CAS'!G19 -> 3.6699 | AF19: ='CO2e Emissions by Sector-CAS'!H19 -> -9.4229 | AG19: ='CO2e Emissions by Sector-CAS'!I19 -> 77.746 | AH19: ='CO2e Emissions by Sector-CAS'!J19 -> 43.5327 | AP19: =GDP!B19 -> 0 | AQ19: =GDP!C19 -> 1.20372 | AR19: =GDP!D19 -> 13.2944 | AS19: =Jobs!B19 -> 0 | AT19: =Jobs!C19 -> 47197 | AU19: =Jobs!D19 -> 398577 | AV19: =Debt!B19 -> 0 | AW19: =Debt!C19 -> -0.773227 | AX19: =Debt!D19 -> -25.2029 | AY19: ='GCF-Expert'!B19 -> 1.5894 | AZ19: ='GCF-Expert'!C19 -> -0.276798 | BA19: ='GCF-Expert'!D19 -> 0 | BB19: ='GCF-Expert'!E19 -> 0 | BC19: ='GCF-Expert'!F19 -> 0 | BD19: ='GCF-Expert'!G19 -> 0 | BE19: ='GCF-Expert'!H19 -> 0.0879875 | BF19: ='GCF-Expert'!I19 -> 0.0449886 | BG19: ='GCF-Expert'!J19 -> -0.217859 | BH19: ='GCF-CAS'!B19 -> 12.921 | BI19: ='GCF-CAS'!C19 -> -4.76451 | BJ19: ='GCF-CAS'!D19 -> 0 | BK19: ='GCF-CAS'!E19 -> 0 | BL19: ='GCF-CAS'!F19 -> 0 | BM19: ='GCF-CAS'!G19 -> 0 | BN19: ='GCF-CAS'!H19 -> 4.64632 | BO19: ='GCF-CAS'!I19 -> 1.45341 | BP19: ='GCF-CAS'!J19 -> -1.56504
A20: =GDP!A20 -> 2038 | B20: ='CO2e Emissions'!B20 -> 731.223 | C20: ='CO2e Emissions'!C20 -> 711.708 | D20: ='CO2e Emissions'!D20 -> 460.871 | E20: ='CO2e Emissions (LULUCF excl)'!B20 -> 716.32 | F20: ='CO2e Emissions (LULUCF excl)'!C20 -> 705.51 | G20: ='CO2e Emissions (LULUCF excl)'!D20 -> 474.408 | H20: ='CO2e Emissions by Sector-BAU'!B20 -> 247.809 | I20: ='CO2e Emissions by Sector-BAU'!C20 -> 129.4 | J20: ='CO2e Emissions by Sector-BAU'!D20 -> 16.5644 | K20: ='CO2e Emissions by Sector-BAU'!E20 -> 4.75859 | L20: ='CO2e Emissions by Sector-BAU'!F20 -> 163.937 | M20: ='CO2e Emissions by Sector-BAU'!G20 -> 0.00314495 | N20: ='CO2e Emissions by Sector-BAU'!H20 -> 14.8754 | O20: ='CO2e Emissions by Sector-BAU'!I20 -> 86.5189 | P20: ='CO2e Emissions by Sector-BAU'!J20 -> 63.1565 | Q20: ='CO2e Emissions by Sector-Expert'!B20 -> 247.92 | R20: ='CO2e Emissions by Sector-Expert'!C20 -> 124.828 | S20: ='CO2e Emissions by Sector-Expert'!D20 -> 16.5354 | T20: ='CO2e Emissions by Sector-Expert'!E20 -> 4.74057 | U20: ='CO2e Emissions by Sector-Expert'!F20 -> 161.067 | V20: ='CO2e Emissions by Sector-Expert'!G20 -> 1.10353 | W20: ='CO2e Emissions by Sector-Expert'!H20 -> 6.19715 | X20: ='CO2e Emissions by Sector-Expert'!I20 -> 86.1523 | Y20: ='CO2e Emissions by Sector-Expert'!J20 -> 63.163 | Z20: ='CO2e Emissions by Sector-CAS'!B20 -> 172.68 | AA20: ='CO2e Emissions by Sector-CAS'!C20 -> 69.3858 | AB20: ='CO2e Emissions by Sector-CAS'!D20 -> 12.2682 | AC20: ='CO2e Emissions by Sector-CAS'!E20 -> 3.43391 | AD20: ='CO2e Emissions by Sector-CAS'!F20 -> 95.6541 | AE20: ='CO2e Emissions by Sector-CAS'!G20 -> 3.97462 | AF20: ='CO2e Emissions by Sector-CAS'!H20 -> -13.5367 | AG20: ='CO2e Emissions by Sector-CAS'!I20 -> 77.2366 | AH20: ='CO2e Emissions by Sector-CAS'!J20 -> 42.6883 | AP20: =GDP!B20 -> 0 | AQ20: =GDP!C20 -> 1.26621 | AR20: =GDP!D20 -> 14.5567 | AS20: =Jobs!B20 -> 0 | AT20: =Jobs!C20 -> 53764 | AU20: =Jobs!D20 -> 451554 | AV20: =Debt!B20 -> 0 | AW20: =Debt!C20 -> -0.910858 | AX20: =Debt!D20 -> -29.7541 | AY20: ='GCF-Expert'!B20 -> 1.78236 | AZ20: ='GCF-Expert'!C20 -> -0.32717 | BA20: ='GCF-Expert'!D20 -> 0 | BB20: ='GCF-Expert'!E20 -> 0 | BC20: ='GCF-Expert'!F20 -> 0 | BD20: ='GCF-Expert'!G20 -> 0 | BE20: ='GCF-Expert'!H20 -> 0.108043 | BF20: ='GCF-Expert'!I20 -> 0.0533836 | BG20: ='GCF-Expert'!J20 -> -0.252109 | BH20: ='GCF-CAS'!B20 -> 13.999 | BI20: ='GCF-CAS'!C20 -> -5.31035 | BJ20: ='GCF-CAS'!D20 -> 0 | BK20: ='GCF-CAS'!E20 -> 0 | BL20: ='GCF-CAS'!F20 -> 0 | BM20: ='GCF-CAS'!G20 -> 0 | BN20: ='GCF-CAS'!H20 -> 5.2052 | BO20: ='GCF-CAS'!I20 -> 1.74001 | BP20: ='GCF-CAS'!J20 -> -1.90032
... A32: =GDP!A32 -> 2050 | B32: ='CO2e Emissions'!B32 -> 878.094 | C32: ='CO2e Emissions'!C32 -> 767.135 | D32: ='CO2e Emissions'!D32 -> 199.885 | E32: ='CO2e Emissions (LULUCF excl)'!B32 -> 865.014 | F32: ='CO2e Emissions (LULUCF excl)'!C32 -> 785.147 | G32: ='CO2e Emissions (LULUCF excl)'!D32 -> 284.091 | H32: ='CO2e Emissions by Sector-BAU'!B32 -> 343.926 | I32: ='CO2e Emissions by Sector-BAU'!C32 -> 140.919 | J32: ='CO2e Emissions by Sector-BAU'!D32 -> 17.0271 | K32: ='CO2e Emissions by Sector-BAU'!E32 -> 5.68998 | L32: ='CO2e Emissions by Sector-BAU'!F32 -> 193.228 | M32: ='CO2e Emissions by Sector-BAU'!G32 -> 0.0163694 | N32: ='CO2e Emissions by Sector-BAU'!H32 -> 13.115 | O32: ='CO2e Emissions by Sector-BAU'!I32 -> 88.2033 | P32: ='CO2e Emissions by Sector-BAU'!J32 -> 71.3637 | Q32: ='CO2e Emissions by Sector-Expert'!B32 -> 331.943 | R32: ='CO2e Emissions by Sector-Expert'!C32 -> 123.358 | S32: ='CO2e Emissions by Sector-Expert'!D32 -> 16.9384 | T32: ='CO2e Emissions by Sector-Expert'!E32 -> 5.62032 | U32: ='CO2e Emissions by Sector-Expert'!F32 -> 150.621 | V32: ='CO2e Emissions by Sector-Expert'!G32 -> 2.46149 | W32: ='CO2e Emissions by Sector-Expert'!H32 -> -18.0119 | X32: ='CO2e Emissions by Sector-Expert'!I32 -> 87.321 | Y32: ='CO2e Emissions by Sector-Expert'!J32 -> 66.8564 | Z32: ='CO2e Emissions by Sector-CAS'!B32 -> 114.92 | AA32: ='CO2e Emissions by Sector-CAS'!C32 -> 19.5245 | AB32: ='CO2e Emissions by Sector-CAS'!D32 -> 4.99224 | AC32: ='CO2e Emissions by Sector-CAS'!E32 -> 1.40346 | AD32: ='CO2e Emissions by Sector-CAS'!F32 -> 43.7204 | AE32: ='CO2e Emissions by Sector-CAS'!G32 -> 7.95181 | AF32: ='CO2e Emissions by Sector-CAS'!H32 -> -84.8058 | AG32: ='CO2e Emissions by Sector-CAS'!I32 -> 70.6767 | AH32: ='CO2e Emissions by Sector-CAS'!J32 -> 33.1888 | AP32: =GDP!B32 -> 0 | AQ32: =GDP!C32 -> 3.80904 | AR32: =GDP!D32 -> 32.4185 | AS32: =Jobs!B32 -> 0 | AT32: =Jobs!C32 -> 198992 | AU32: =Jobs!D32 -> 1325060 | AV32: =Debt!B32 -> 0 | AW32: =Debt!C32 -> -4.6554 | AX32: =Debt!D32 -> -107.9 | AY32: ='GCF-Expert'!B32 -> 6.24743 | AZ32: ='GCF-Expert'!C32 -> -1.43202 | BA32: ='GCF-Expert'!D32 -> 0 | BB32: ='GCF-Expert'!E32 -> 0 | BC32: ='GCF-Expert'!F32 -> 0 | BD32: ='GCF-Expert'!G32 -> 0 | BE32: ='GCF-Expert'!H32 -> 0.540291 | BF32: ='GCF-Expert'!I32 -> 0.283339 | BG32: ='GCF-Expert'!J32 -> -0.876805 | BH32: ='GCF-CAS'!B32 -> 27.0816 | BI32: ='GCF-CAS'!C32 -> -15.0609 | BJ32: ='GCF-CAS'!D32 -> 0 | BK32: ='GCF-CAS'!E32 -> 0 | BL32: ='GCF-CAS'!F32 -> 0 | BM32: ='GCF-CAS'!G32 -> 0 | BN32: ='GCF-CAS'!H32 -> 12.6544 | BO32: ='GCF-CAS'!I32 -> 6.91757 | BP32: ='GCF-CAS'!J32 -> -9.94744

Sheet GCF-Expert
A1: Time (Year) | B1: Carbon Tax Revenue | C1: Fuel Tax Revenue | D1: Electric Vehicle Subsidy | E1: Electricity Generation Subsidy | F1: Electricity Capacity Construction Subsidy | G1: Distributed Solar Subsidy | H1: Fuel Subsidy | I1: National Debt Interest | J1: Remainder
A2: 2020 | B2: 0 | C2: 0 | D2: 0 | E2: 0 | F2: 0 | G2: 0 | H2: 0 | I2: 0 | J2: 0
A3: 2021 | B3: 0 | C3: 0 | D3: 0 | E3: 0 | F3: 0 | G3: 0 | H3: 0 | I3: 0 | J3: 0
A4: 2022 | B4: 0 | C4: 0 | D4: 0 | E4: 0 | F4: 0 | G4: 0 | H4: 0 | I4: 0 | J4: 0
A5: 2023 | B5: 0 | C5: 0 | D5: 0 | E5: 0 | F5: 0 | G5: 0 | H5: 0 | I5: 0 | J5: 0
A6: 2024 | B6: 0 | C6: 0 | D6: 0 | E6: 0 | F6: 0 | G6: 0 | H6: 0 | I6: 0 | J6: 0
A7: 2025 | B7: 0 | C7: 0 | D7: 0 | E7: 0 | F7: 0 | G7: 0 | H7: 0 | I7: 0 | J7: 0
A8: 2026 | B8: 0.122377 | C8: -0.00225562 | D8: 0 | E8: 0 | F8: 0 | G8: 0 | H8: 0.000374575 | I8: 0 | J8: -0.01048
A9: 2027 | B9: 0.246512 | C9: -0.021866 | D9: 0 | E9: 0 | F9: 0 | G9: 0 | H9: 0.00154327 | I9: 0.000768773 | J9: -0.0220216
A10: 2028 | B10: 0.373398 | C10: -0.0270766 | D10: 0 | E10: 0 | F10: 0 | G10: 0 | H10: 0.00434702 | I10: 0.00196806 | J10: -0.0208821
A11: 2029 | B11: 0.504233 | C11: -0.0516046 | D11: 0 | E11: 0 | F11: 0 | G11: 0 | H11: 0.00822467 | I11: 0.00436663 | J11: -0.0334625
A12: 2030 | B12: 0.640311 | C12: -0.0702768 | D12: 0 | E12: 0 | F12: 0 | G12: 0 | H12: 0.0130708 | I12: 0.00731872 | J12: -0.0446305
A13: 2031 | B13: 0.749245 | C13: -0.0898262 | D13: 0 | E13: 0 | F13: 0 | G13: 0 | H13: 0.0181135 | I13: 0.0111011 | J13: -0.0623136
... A32: 2050 | B32: 6.24743 | C32: -1.43202 | D32: 0 | E32: 0 | F32: 0 | G32: 0 | H32: 0.540291 | I32: 0.283339 | J32: -0.876805

Sheet GCF-CAS
A1: Time (Year) | B1: Carbon Tax Revenue | C1: Fuel Tax Revenue | D1: Electric Vehicle Subsidy | E1: Electricity Generation Subsidy | F1: Electricity Capacity Construction Subsidy | G1: Distributed Solar Subsidy | H1: Fuel Subsidy | I1: National Debt Interest | J1: Remainder
A2: 2020 | B2: 0 | C2: 0 | D2: 0 | E2: 0 | F2: 0 | G2: 0 | H2: 0 | I2: 0 | J2: 0
A3: 2021 | B3: 0 | C3: 0 | D3: 0 | E3: 0 | F3: 0 | G3: 0 | H3: 0 | I3: 0 | J3: 0
A4: 2022 | B4: 0 | C4: 0 | D4: 0 | E4: 0 | F4: 0 | G4: 0 | H4: 0 | I4: 0 | J4: 0
A5: 2023 | B5: 0 | C5: 0 | D5: 0 | E5: 0 | F5: 0 | G5: 0 | H5: 0 | I5: 0 | J5: 0
A6: 2024 | B6: 0 | C6: 0 | D6: 0 | E6: 0 | F6: 0 | G6: 0 | H6: 0 | I6: 0 | J6: 0
A7: 2025 | B7: 0 | C7: 0 | D7: 0 | E7: 0 | F7: 0 | G7: 0 | H7: 0 | I7: 0 | J7: 0
A8: 2026 | B8: 1.38372 | C8: -0.212177 | D8: 0 | E8: 0 | F8: 0 | G8: 0 | H8: 0.214247 | I8: 0 | J8: -0.0330909
A9: 2027 | B9: 2.72209 | C9: -0.546468 | D9: 0 | E9: 0 | F9: 0 | G9: 0 | H9: 0.456358 | I9: 0.0210644 | J9: -0.0837514
A10: 2028 | B10: 3.80419 | C10: -0.983384 | D10: 0 | E10: 0 | F10: 0 | G10: 0 | H10: 0.768218 | I10: 0.0615326 | J10: -0.102529
A11: 2029 | B11: 4.96878 | C11: -1.48229 | D11: 0 | E11: 0 | F11: 0 | G11: 0 | H11: 1.11408 | I11: 0.122389 | J11: -0.179292
A12: 2030 | B12: 6.12988 | C12: -2.00274 | D12: 0 | E12: 0 | F12: 0 | G12: 0 | H12: 1.44475 | I12: 0.20394 | J12: -0.266588
A13: 2031 | B13: 7.03298 | C13: -2.40367 | D13: 0 | E13: 0 | F13: 0 | G13: 0 | H13: 1.83254 | I13: 0.304342 | J13: -0.395863
... A32: 2050 | B32: 27.0816 | C32: -15.0609 | D32: 0 | E32: 0 | F32: 0 | G32: 0 | H32: 12.6544 | I32: 6.91757 | J32: -9.94744

Sheet Expert
A1: Time (Year) | B1: Expert: CAPEXP | C1: Expert: OMEXP | D1: CAPEXP: BAU | E1: OMEXP: BAU
A2: 2020 | B2: 0 | C2: 0 | D2: 0 | E2: 0
A3: 2021 | B3: 0 | C3: 0 | D3: 0 | E3: 0
A4: 2022 | B4: 0 | C4: 0 | D4: 0 | E4: 0
A5: 2023 | B5: 0 | C5: 0 | D5: 0 | E5: 0
A6: 2024 | B6: 0 | C6: 0 | D6: 0 | E6: 0
A7: 2025 | B7: 0 | C7: 0 | D7: 0 | E7: 0
A8: 2026 | B8: 0.323366 | C8: 0.00271698 | D8: 0 | E8: 0
A9: 2027 | B9: 0.375478 | C9: 0.00414229 | D9: 0 | E9: 0
A10: 2028 | B10: 0.461887 | C10: 0.0048104 | D10: 0 | E10: 0
A11: 2029 | B11: 0.491729 | C11: 0.00227158 | D11: 0 | E11: 0
A12: 2030 | B12: 0.583483 | C12: 0.0187071 | D12: 0 | E12: 0
A13: 2031 | B13: 0.646286 | C13: 0.0521126 | D13: 0 | E13: 0
... A32: 2050 | B32: 3.09113 | C32: 2.81319 | D32: 0 | E32: 0

Sheet CAS
A1: Time (Year) | B1: CAS:CAPEXP | C1: CAS:OMEXP | D1: CAPEXP: BAU | E1: OMEXP: BAU
A2: 2020 | B2: 0 | C2: 0 | D2: 0 | E2: 0
A3: 2021 | B3: 0 | C3: 0 | D3: 0 | E3: 0
A4: 2022 | B4: 0 | C4: 0 | D4: 0 | E4: 0
A5: 2023 | B5: 0 | C5: 0 | D5: 0 | E5: 0
A6: 2024 | B6: 0 | C6: 0 | D6: 0 | E6: 0
A7: 2025 | B7: 0 | C7: 0 | D7: 0 | E7: 0
A8: 2026 | B8: 0.96876 | C8: -0.289069 | D8: 0 | E8: 0
A9: 2027 | B9: 1.48721 | C9: -0.626688 | D9: 0 | E9: 0
A10: 2028 | B10: 2.15889 | C10: -0.909076 | D10: 0 | E10: 0
A11: 2029 | B11: 2.79894 | C11: -1.32108 | D11: 0 | E11: 0
A12: 2030 | B12: 4.65361 | C12: -2.10945 | D12: 0 | E12: 0
A13: 2031 | B13: 5.01261 | C13: -2.76152 | D13: 0 | E13: 0
... A32: 2050 | B32: -26.5627 | C32: -38.8426 | D32: 0 | E32: 0

Sheet Savings-Expert
A1: Time (Year) | B1: Economic Benefit from Avoided Climate Damages | C1: Household Savings | D1: Social Benefits from Emissions Reduction | E1: Monetized Benefit from Avoided Premature Mortality | F1: Total Savings
A2: 2020 | B2: 0 | C2: 0 | D2: 0 | E2: 0 | F2: =SUM(B2:E2) -> 0
A3: 2021 | B3: 0 | C3: 0 | D3: 0 | E3: 0 | F3: =SUM(B3:E3) -> 0
A4: 2022 | B4: 0 | C4: 0 | D4: 0 | E4: 0 | F4: =SUM(B4:E4) -> 0
A5: 2023 | B5: 0 | C5: 0 | D5: 0 | E5: 0 | F5: =SUM(B5:E5) -> 0
A6: 2024 | B6: 0 | C6: 0 | D6: 0 | E6: 0 | F6: =SUM(B6:E6) -> 0
A7: 2025 | B7: 0 | C7: 0 | D7: 0 | E7: 0 | F7: =SUM(B7:E7) -> 0
A8: 2026 | B8: 0.0238016 | C8: -0.00223261 | D8: 0.0204 | E8: -0.00303495 | F8: =SUM(B8:E8) -> 0.03893404
A9: 2027 | B9: 0.0775752 | C9: -0.00905946 | D9: 0.0764 | E9: -0.00101165 | F9: =SUM(B9:E9) -> 0.14390409
A10: 2028 | B10: 0.119811 | C10: -0.00996578 | D10: 0.1124 | E10: -0.00708156 | F10: =SUM(B10:E10) -> 0.21516366
A11: 2029 | B11: 0.188333 | C11: -0.0096335 | D11: 0.182 | E11: -0.0060699 | F11: =SUM(B11:E11) -> 0.3546296
A12: 2030 | B12: 0.25661 | C12: -0.00498947 | D12: 0.2472 | E12: -0.00910486 | F12: =SUM(B12:E12) -> 0.48971567
A13: 2031 | B13: 0.336101 | C13: 0.00133124 | D13: 0.328 | E13: -0.00809321 | F13: =SUM(B13:E13) -> 0.65733903
... A32: 2050 | B32: 8.4907 | C32: 1.89894 | D32: 8.4836 | E32: -0.00708156 | F32: =SUM(B32:E32) -> 18.866158

Sheet Savings-CAS
A1: Time (Year) | B1: Economic Benefit from Avoided Climate Damages | C1: Household Savings | D1: Social Benefits from Emissions Reduction | E1: Monetized Benefit from Avoided Premature Mortality | F1: Total Savings
A2: 2020 | B2: 0 | C2: 0 | D2: 0 | E2: 0 | F2: =B2+C2+D2 -> 0
A3: 2021 | B3: 0 | C3: 0 | D3: 0 | E3: 0 | F3: =B3+C3+D3 -> 0
A4: 2022 | B4: 0 | C4: 0 | D4: 0 | E4: 0 | F4: =B4+C4+D4 -> 0
A5: 2023 | B5: 0 | C5: 0 | D5: 0 | E5: 0 | F5: =B5+C5+D5 -> 0
A6: 2024 | B6: 0 | C6: 0 | D6: 0 | E6: 0 | F6: =B6+C6+D6 -> 0
A7: 2025 | B7: 0 | C7: 0 | D7: 0 | E7: 0 | F7: =B7+C7+D7 -> 0
A8: 2026 | B8: 0.569136 | C8: 0.0952386 | D8: 0.6124 | E8: 0.043501 | F8: =B8+C8+D8 -> 1.2767746
A9: 2027 | B9: 1.42217 | C9: 0.216033 | D9: 1.5484 | E9: 0.126456 | F9: =B9+C9+D9 -> 3.186603
A10: 2028 | B10: 3.51703 | C10: 0.366514 | D10: 3.7496 | E10: 0.23268 | F10: =B10+C10+D10 -> 7.633144
A11: 2029 | B11: 4.75268 | C11: 0.5653 | D11: 5.152 | E11: 0.399602 | F11: =B11+C11+D11 -> 10.46998
A12: 2030 | B12: 6.0539 | C12: 0.819883 | D12: 6.596 | E12: 0.542245 | F12: =B12+C12+D12 -> 13.469783
A13: 2031 | B13: 7.11923 | C13: 1.06308 | D13: 7.7704 | E13: 0.651503 | F13: =B13+C13+D13 -> 15.95271
... A32: 2050 | B32: 50.6191 | C32: 14.4798 | D32: 54.3548 | E32: 3.73603 | F32: =B32+C32+D32 -> 119.4537

Sheet Avoided Deaths
A1: Time (Year) | B1: Expert | C1: CAS
A2: 2020 | B2: 0 | C2: =0 -> 0
A3: 2021 | B3: 0 | C3: =0 -> 0
A4: 2022 | B4: 0 | C4: =0 -> 0
A5: 2023 | B5: 0 | C5: =0 -> 0
A6: 2024 | B6: 0 | C6: =0 -> 0
A7: 2025 | B7: 0 | C7: =0 -> 0
A8: 2026 | B8: 0 | C8: 43
A9: 2027 | B9: -3 | C9: 168
A10: 2028 | B10: -4 | C10: 398
A11: 2029 | B11: -11 | C11: 793
A12: 2030 | B12: -17 | C12: 1329
A13: 2031 | B13: -26 | C13: 1973
A14: 2032 | B14: -34 | C14: 2695
A15: 2033 | B15: -47 | C15: 3494
A16: 2034 | B16: -58 | C16: 4376
A17: 2035 | B17: -70 | C17: 5344
A18: 2036 | B18: -85 | C18: 6399
A19: 2037 | B19: -106 | C19: 7556
... A32: 2050 | B32: -373 | C32: 39333

Sheet GDP-Sector-Expert
A1: Time (Year) | B1: Agriculture, forestry and fishing [ISIC 01T03] | C1: Oil and gas extraction [ISIC 06] | D1: Coke and refined petroleum products [ISIC 19] | E1: Iron and steel mills and ferroalloy manufacturing [ISIC 241] | F1: Motor vehicles, trailers and semi-trailers [ISIC 29] | G1: Electric power generation, transmission and distribution [ISIC 351]
A2: 2020 | B2: 0 | C2: 0 | D2: 0 | E2: 0 | F2: 0 | G2: 0
A3: 2021 | B3: 0 | C3: 0 | D3: 0 | E3: 0 | F3: 0 | G3: 0
A4: 2022 | B4: 0 | C4: 0 | D4: 0 | E4: 0 | F4: 0 | G4: 0
A5: 2023 | B5: 0 | C5: 0 | D5: 0 | E5: 0 | F5: 0 | G5: 0
A6: 2024 | B6: 0 | C6: 0 | D6: 0 | E6: 0 | F6: 0 | G6: 0
A7: 2025 | B7: 0 | C7: 0 | D7: 0 | E7: 0 | F7: 0 | G7: 0
A8: 2026 | B8: -0.0096 | C8: 0.0004 | D8: -0.0004 | E8: 0 | F8: 0.0076 | G8: -0.004
A9: 2027 | B9: -0.006 | C9: 0.0068 | D9: -0.0044 | E9: -0.002 | F9: 0.0156 | G9: 0.0968
A10: 2028 | B10: -0.002 | C10: 0.01 | D10: -0.006 | E10: -0.0068 | F10: 0.0244 | G10: 0.0632
A11: 2029 | B11: 0.028 | C11: 0.0168 | D11: -0.0124 | E11: -0.0112 | F11: 0.0336 | G11: 0.08
A12: 2030 | B12: 0.066 | C12: 0.022 | D12: -0.0188 | E12: -0.0164 | F12: 0.0424 | G12: 0.0344
A13: 2031 | B13: 0.0912 | C13: 0.0296 | D13: -0.0276 | E13: -0.0204 | F13: 0.0512 | G13: 0.0344
... A32: 2050 | B32: 1.768 | C32: 0.7152 | D32: -0.5216 | E32: -0.2416 | F32: 0.3788 | G32: -1.2648

Sheet GDP-Sector-CAS
A1: Time (Year) | B1: Oil and gas extraction [ISIC 06] | C1: Food products, beverages and tobacco [ISIC 10T12] | D1: Real estate activities [ISIC 68] | E1: Coke and refined petroleum products [ISIC 19] | F1: Motor vehicles, trailers and semi-trailers [ISIC 29] | G1: Electric power generation, transmission and distribution [ISIC 351]
A2: 2020 | B2: 0 | C2: 0 | D2: 0 | E2: 0 | F2: 0 | G2: 0
A3: 2021 | B3: 0 | C3: 0 | D3: 0 | E3: 0 | F3: 0 | G3: 0
A4: 2022 | B4: 0 | C4: 0 | D4: 0 | E4: 0 | F4: 0 | G4: 0
A5: 2023 | B5: 0 | C5: 0 | D5: 0 | E5: 0 | F5: 0 | G5: 0
A6: 2024 | B6: 0 | C6: 0 | D6: 0 | E6: 0 | F6: 0 | G6: 0
A7: 2025 | B7: 0 | C7: 0 | D7: 0 | E7: 0 | F7: 0 | G7: 0
A8: 2026 | B8: 0.154619 | C8: 0.209204 | D8: 0.11066 | E8: -0.217146 | F8: -0.0375623 | G8: -0.165091
A9: 2027 | B9: 0.347184 | C9: 0.587506 | D9: 0.227774 | E9: -0.600345 | F9: 0.0460992 | G9: 0.140387
A10: 2028 | B10: 0.559006 | C10: 1.0135 | D10: 0.376703 | E10: -1.18281 | F10: 0.0563435 | G10: -0.0765201
A11: 2029 | B11: 0.858049 | C11: 1.50345 | D11: 0.568974 | E11: -1.94921 | F11: -0.0580509 | G11: -0.36091
A12: 2030 | B12: 1.16955 | C12: 2.09421 | D12: 0.84839 | E12: -2.8229 | F12: -0.336354 | G12: -0.974878
A13: 2031 | B13: 1.49125 | C13: 2.74242 | D13: 1.13195 | E13: -3.76812 | F13: -0.667585 | G13: -0.614571
... A32: 2050 | B32: 13.475 | C32: 29.694 | D32: 15.9792 | E32: -40.2104 | F32: -23.8538 | G32: -6.32044

Sheet Jobs-Sector-Expert
A1: Time (Year) | B1: Agriculture, forestry and fishing [ISIC 01T03] | C1: Coal mining [ISIC 05] | D1: Coke and refined petroleum products [ISIC 19] | E1: Electric power generation, transmission and distribution [ISIC 351] | F1: Other business sector services [ISIC 69T82] | G1: Public services [ISIC 84]
A2: 2020 | B2: 0 | C2: 0 | D2: 0 | E2: 0 | F2: 0 | G2: 0
A3: 2021 | B3: 0 | C3: 0 | D3: 0 | E3: 0 | F3: 0 | G3: 0
A4: 2022 | B4: 0 | C4: 0 | D4: 0 | E4: 0 | F4: 0 | G4: 0
A5: 2023 | B5: 0 | C5: 0 | D5: 0 | E5: 0 | F5: 0 | G5: 0
A6: 2024 | B6: 0 | C6: 0 | D6: 0 | E6: 0 | F6: 0 | G6: 0
A7: 2025 | B7: 0 | C7: 0 | D7: 0 | E7: 0 | F7: 0 | G7: 0
A8: 2026 | B8: -594 | C8: 46 | D8: -3 | E8: -39 | F8: 2764 | G8: 460
A9: 2027 | B9: -868 | C9: -100 | D9: -21 | E9: 859 | F9: 2974 | G9: 945
A10: 2028 | B10: -372 | C10: 100 | D10: -31 | E10: 559 | F10: 3532 | G10: 1555
A11: 2029 | B11: 1254 | C11: -224 | D11: -60 | E11: 706 | F11: 3508 | G11: 2037
A12: 2030 | B12: 3610 | C12: -408 | D12: -89 | E12: 301 | F12: 4149 | G12: 2625
A13: 2031 | B13: 5472 | C13: -741 | D13: -129 | E13: 299 | F13: 4429 | G13: 3019
... A32: 2050 | B32: 117498 | C32: -5279 | D32: -2365 | E32: -11301 | F32: 22930 | G32: 24677

Sheet Jobs-Sector-CAS
A1: Time (Year) | B1: Agriculture, forestry and fishing [ISIC 01T03] | C1: Other business sector services [ISIC 69T82] | D1: Private households with employed persons [ISIC 97T98] | E1: Coke and refined petroleum products [ISIC 19] | F1: Motor vehicles, trailers and semi-trailers [ISIC 29] | G1: Electric power generation, transmission and distribution [ISIC 351]
A2: 2020 | B2: 0 | C2: 0 | D2: 0 | E2: 0 | F2: 0 | G2: 0
A3: 2021 | B3: 0 | C3: 0 | D3: 0 | E3: 0 | F3: 0 | G3: 0
A4: 2022 | B4: 0 | C4: 0 | D4: 0 | E4: 0 | F4: 0 | G4: 0
A5: 2023 | B5: 0 | C5: 0 | D5: 0 | E5: 0 | F5: 0 | G5: 0
A6: 2024 | B6: 0 | C6: 0 | D6: 0 | E6: 0 | F6: 0 | G6: 0
A7: 2025 | B7: 0 | C7: 0 | D7: 0 | E7: 0 | F7: 0 | G7: 0
A8: 2026 | B8: -7648 | C8: 8923 | D8: 2402 | E8: -155 | F8: -151 | G8: -987
A9: 2027 | B9: -9674 | C9: 12081 | D9: 5320 | E9: -432 | F9: 185 | G9: 811
A10: 2028 | B10: -9006 | C10: 20194 | D10: 9223 | E10: -845 | F10: 242 | G10: -484
A11: 2029 | B11: -10049 | C11: 24946 | D11: 14441 | E11: -1385 | F11: -208 | G11: -2174
A12: 2030 | B12: -2442 | C12: 39668 | D12: 21297 | E12: -1993 | F12: -1295 | G12: -5823
A13: 2031 | B13: 5154 | C13: 50168 | D13: 28248 | E13: -2661 | F13: -2632 | G13: -3694
... A32: 2050 | B32: 610036 | C32: 324345 | D32: 432066 | E32: -27463 | F32: -95274 | G32: -39555
