Workbook
Name lignite_multiplier: '[1]Hard Coal and Lig Multipliers'!$N$16
Name nonlignite_multiplier: '[1]Hard Coal and Lig Multipliers'!$N$17

Sheet About
A1: EIaE BAU Imported Electricity
A2: EIaE BAU Exported Electricity
A3: EIaE Imported Electricity Price
A4: EIaE BAU Exported Electricity Price
A6: Source: | B6: Import and export | C6: Data 2022 and 2023
B7: Energy Ministry (SENER)
B8: 2024
B9: National Energy Balance 2023
B10: https://www.gob.mx/cms/uploads/attachment/file/947752/BALANCE_NACIONAL_DE_ENERG_A_PRELIMINAR_2023.pdf
B13: National council of humanities, sciences and technologies | C13: Data 2020 and 2021
B14: 2024
B15: Energy futures for Mexico by 2050 The path to a just and sustainable energy transition
B16: https://conahcyt.mx/wp-content/uploads/pronaces/micrositios/energia_y_cambio_climatico/energia/cuadernos_tematicos/Cuaderno_9.pdf
B17: Statistical annex
B18: https://docs.google.com/spreadsheets/d/1_RmvJpDh5CUSkNj1lKf5HorV8Rx0YtOkXj6PAuzNAF4/edit?gid=2140732780#gid=2140732780
B19: imp and exp sheets
B21: Imported and Exported Electricity Prices
B22: Energy Information Administration
B23: 2021 and 2022
B24: Annual Energy Outlook 2021 and 2022
B25: https://www.eia.gov/outlooks/aeo/tables_side.php
B26: Table 3
A35: Notes
A36: We need to know the mix of imported electricity types if we will be including
A37: pollutant emissions associated with imported electricity into the totals, which
A38: is managed by a control lever. If these emissions will not be included in the
A39: emissions totals, the breakdown is unimportant, and you may assign all
A40: imported electricity emissions to any one electricity source, if you prefer.
A42: Electricity exports are supplied by power plants in the modeled region and
A43: hence do not need their electricity source to be specified here.
A45: Since electricity imported to the U.S. comes overwhelmingly from Canada,
A46: we use Canada's electricity generation mix to approximate the mix
A47: of all imported electricity.
A49: All Canadian natural gas was assigned to the "natural gas nonpeaker" plant type
... A58: Conversion Factors
A59: 2.931e-07 | B59: MWh/BTU
A60: 0.88711067 | B60: 2012 USD/2020 USD
A61: 0.84730413 | B61: 2012 USD/2021 USD

Sheet AEO Table 3 2023
B1: ref2023.d020623a | C1: 2022 | D1: 2023 | E1: 2024 | F1: 2025 | G1: 2026 | H1: 2027 | I1: 2028 | J1: 2029 | K1: 2030 | L1: 2031 | M1: 2032 | N1: 2033 | O1: 2034 | P1: 2035 | Q1: 2036 | R1: 2037 | S1: 2038 | T1: 2039 | U1: 2040 | V1: 2041 | W1: 2042 | X1: 2043 | Y1: 2044 | Z1: 2045 | AA1: 2046 | AB1: 2047 | AC1: 2048 | AD1: 2049 | AE1: 2050
C3: Report | D3: Annual Energy Outlook 2023
C4: Scenario | D4: ref2023 | G4: Reference
C5: Datekey | D5: d020623a
C6: Release Date | E6: March 2023
A10: PRC000 | B10: 3. Energy Prices by Sector and Source | AF10: Average
B11: (2022 dollars per million Btu, unless otherwise noted) | AF11: Annual
AF12: Change
B13: Sector and Source | C13: 2022 | D13: 2023 | E13: 2024 | F13: 2025 | G13: 2026 | H13: 2027 | I13: 2028 | J13: 2029 | K13: 2030 | L13: 2031 | M13: 2032 | N13: 2033 | O13: 2034 | P13: 2035 | Q13: 2036 | R13: 2037 | S13: 2038 | T13: 2039 | U13: 2040 | V13: 2041 | W13: 2042 | X13: 2043 | Y13: 2044 | Z13: 2045 | AA13: 2046 | AB13: 2047 | AC13: 2048 | AD13: 2049 | AE13: 2050 | AF13: 2022–2050
B15: Residential
A16: PRC000:ba_LiquefiedPetr | B16: Propane | C16: 29.133368 | D16: 31.306763 | E16: 31.488976 | F16: 30.414381 | G16: 29.316694 | H16: 28.432261 | I16: 27.927179 | J16: 27.736774 | K16: 27.826454 | L16: 28.114607 | M16: 28.577341 | N16: 29.166182 | O16: 29.755032 | P16: 30.227194 | Q16: 30.581852 | R16: 30.898972 | S16: 31.307201 | T16: 31.50728 | U16: 31.831757 | V16: 32.150085 | W16: 32.377548 | X16: 32.495739 | Y16: 32.527752 | Z16: 32.601685 | AA16: 32.818344 | AB16: 32.85873 | AC16: 32.944168 | AD16: 32.974564 | AE16: 32.963577 | AF16: 0.004421
A17: PRC000:ba_DistillateFue | B17: Distillate Fuel Oil | C17: 35.242496 | D17: 32.825691 | E17: 31.613775 | F17: 29.971098 | G17: 29.506725 | H17: 29.058901 | I17: 28.775816 | J17: 28.863544 | K17: 28.871641 | L17: 29.047983 | M17: 29.134987 | N17: 29.251019 | O17: 29.296843 | P17: 29.470129 | Q17: 29.486605 | R17: 29.608255 | S17: 29.697092 | T17: 29.738928 | U17: 29.786015 | V17: 29.942484 | W17: 29.935656 | X17: 30.04907 | Y17: 29.954853 | Z17: 29.998642 | AA17: 30.208778 | AB17: 30.235264 | AC17: 30.267241 | AD17: 30.332973 | AE17: 30.333071 | AF17: -0.005343
A18: PRC000:ba_NaturalGas | B18: Natural Gas | C18: 14.293921 | D18: 14.064584 | E18: 12.820667 | F18: 12.096767 | G18: 11.4904 | H18: 11.084416 | I18: 10.822556 | J18: 10.873314 | K18: 10.916109 | L18: 11.018429 | M18: 11.109651 | N18: 11.256351 | O18: 11.376831 | P18: 11.484237 | Q18: 11.535565 | R18: 11.619214 | S18: 11.759008 | T18: 11.765636 | U18: 11.858184 | V18: 11.954752 | W18: 11.979805 | X18: 11.966863 | Y18: 11.924366 | Z18: 11.983916 | AA18: 12.29451 | AB18: 12.278927 | AC18: 12.246208 | AD18: 12.250841 | AE18: 12.285347 | AF18: -0.005394
A19: PRC000:ba_Electricity | B19: Electricity | C19: 42.669247 | D19: 41.433243 | E19: 40.553883 | F19: 39.341568 | G19: 38.636055 | H19: 38.098618 | I19: 37.73653 | J19: 37.638126 | K19: 37.737511 | L19: 37.934017 | M19: 38.113976 | N19: 38.685684 | O19: 39.125294 | P19: 39.167233 | Q19: 39.408443 | R19: 39.708202 | S19: 40.126545 | T19: 40.421806 | U19: 40.716976 | V19: 40.952396 | W19: 41.084854 | X19: 41.174622 | Y19: 41.248722 | Z19: 41.3391 | AA19: 41.270775 | AB19: 41.153133 | AC19: 41.092045 | AD19: 40.90506 | AE19: 40.599277 | AF19: -0.001774
B21: Commercial
A22: PRC000:ca_LiquefiedGas | B22: Propane | C22: 27.825644 | D22: 26.750048 | E22: 24.895067 | F22: 22.915489 | G22: 21.863068 | H22: 21.29063 | I22: 21.16449 | J22: 21.271128 | K22: 21.567476 | L22: 21.957167 | M22: 22.450293 | N22: 22.999268 | O22: 23.455528 | P22: 23.727991 | Q22: 23.893875 | R22: 24.081245 | S22: 24.430447 | T22: 24.450624 | U22: 24.742603 | V22: 24.982395 | W22: 25.090612 | X22: 25.093864 | Y22: 25.044073 | Z22: 25.106045 | AA22: 25.32711 | AB22: 25.361147 | AC22: 25.452358 | AD22: 25.443525 | AE22: 25.401167 | AF22: -0.003251
A23: PRC000:ca_DistillateFue | B23: Distillate Fuel Oil | C23: 35.263695 | D23: 32.981144 | E23: 30.614763 | F23: 27.813896 | G23: 26.172981 | H23: 24.57275 | I23: 23.124897 | J23: 23.207827 | K23: 23.210224 | L23: 23.375801 | M23: 23.469553 | N23: 23.574059 | O23: 23.628925 | P23: 23.780882 | Q23: 23.807659 | R23: 23.920523 | S23: 24.003952 | T23: 24.045341 | U23: 24.092535 | V23: 24.247444 | W23: 24.240576 | X23: 24.354948 | Y23: 24.264793 | Z23: 24.334454 | AA23: 24.855766 | AB23: 24.870148 | AC23: 24.901745 | AD23: 24.972281 | AE23: 24.973919 | AF23: -0.012247
A24: PRC000:ca_ResidualFuel | B24: Residual Fuel Oil | C24: 12.628995 | D24: 7.865066 | E24: 9.434374 | F24: 9.738273 | G24: 11.133956 | H24: 12.534562 | I24: 14.025284 | J24: 14.102822 | K24: 14.186954 | L24: 14.294547 | M24: 14.392586 | N24: 14.48232 | O24: 14.582383 | P24: 14.694341 | Q24: 14.783643 | R24: 14.88051 | S24: 14.985899 | T24: 15.052875 | U24: 15.137448 | V24: 15.264226 | W24: 15.277987 | X24: 15.347211 | Y24: 15.376574 | Z24: 15.433166 | AA24: 15.594908 | AB24: 15.594114 | AC24: 15.714553 | AD24: 15.804392 | AE24: 15.873075 | AF24: 0.008199
A25: PRC000:ca_NaturalGas | B25: Natural Gas | C25: 10.986808 | D25: 10.325419 | E25: 9.325422 | F25: 8.846206 | G25: 8.456365 | H25: 8.24514 | I25: 8.153749 | J25: 8.191227 | K25: 8.216532 | L25: 8.296233 | M25: 8.367693 | N25: 8.499839 | O25: 8.600746 | P25: 8.688319 | Q25: 8.723988 | R25: 8.792732 | S25: 8.916448 | T25: 8.913137 | U25: 8.995551 | V25: 9.080802 | W25: 9.096286 | X25: 9.076388 | Y25: 9.030754 | Z25: 9.079571 | AA25: 9.276369 | AB25: 9.235811 | AC25: 9.192889 | AD25: 9.192929 | AE25: 9.224361 | AF25: -0.006225
A26: PRC000:ca_Electricity | B26: Electricity | C26: 36.670883 | D26: 35.900337 | E26: 34.342381 | F26: 32.872684 | G26: 32.054314 | H26: 31.460438 | I26: 30.960938 | J26: 30.716866 | K26: 30.680281 | L26: 30.663637 | M26: 30.632755 | N26: 30.980528 | O26: 31.210361 | P26: 31.136457 | Q26: 31.231977 | R26: 31.342302 | S26: 31.591194 | T26: 31.754965 | U26: 31.889711 | V26: 31.993582 | W26: 32.010456 | X26: 32.017532 | Y26: 31.980669 | Z26: 31.929119 | AA26: 31.752293 | AB26: 31.48889 | AC26: 31.376942 | AD26: 31.126701 | AE26: 30.802555 | AF26: -0.006209
B28: Industrial 1/
A29: PRC000:da_LiquefiedPetr | B29: Propane | C29: 23.43502 | D29: 21.469131 | E29: 19.205515 | F29: 17.003975 | G29: 15.9326 | H29: 15.36812 | I29: 15.270111 | J29: 15.401594 | K29: 15.727974 | L29: 16.148449 | M29: 16.682365 | N29: 17.278715 | O29: 17.769476 | P29: 18.054674 | Q29: 18.227863 | R29: 18.434586 | S29: 18.832411 | T29: 18.834532 | U29: 19.175161 | V29: 19.442755 | W29: 19.555237 | X29: 19.550402 | Y29: 19.489828 | Z29: 19.551672 | AA29: 19.545284 | AB29: 19.586832 | AC29: 19.694736 | AD29: 19.679703 | AE29: 19.63002 | AF29: -0.006308
A30: PRC000:da_DistillateFue | B30: Distillate Fuel Oil | C30: 35.187302 | D30: 32.80463 | E30: 30.476191 | F30: 27.636358 | G30: 25.955219 | H30: 24.321341 | I30: 22.837069 | J30: 22.933369 | K30: 22.940443 | L30: 23.109438 | M30: 23.21262 | N30: 23.333881 | O30: 23.39049 | P30: 23.561224 | Q30: 23.589087 | R30: 23.713947 | S30: 23.804403 | T30: 23.853134 | U30: 23.908232 | V30: 24.072897 | W30: 24.073511 | X30: 24.198322 | Y30: 24.118036 | Z30: 24.174662 | AA30: 24.400406 | AB30: 24.425331 | AC30: 24.465715 | AD30: 24.54307 | AE30: 24.550739 | AF30: -0.012773
A31: PRC000:da_ResidualFuel | B31: Residual Fuel Oil | C31: 13.34515 | D31: 8.496145 | E31: 10.168447 | F31: 10.736027 | G31: 12.278802 | H31: 13.923551 | I31: 15.540428 | J31: 15.624061 | K31: 15.728378 | L31: 15.850405 | M31: 15.970654 | N31: 16.084974 | O31: 16.205595 | P31: 16.335403 | Q31: 16.434 | R31: 16.537802 | S31: 16.65823 | T31: 16.734859 | U31: 16.83429 | V31: 16.971537 | W31: 16.992592 | X31: 17.066227 | Y31: 17.056499 | Z31: 17.117035 | AA31: 17.292305 | AB31: 17.297117 | AC31: 17.411476 | AD31: 17.497351 | AE31: 17.570717 | AF31: 0.009873
A32: PRC000:da_NaturalGas | B32: Natural Gas 2/ | C32: 7.330917 | D32: 6.270033 | E32: 5.16042 | F32: 4.592026 | G32: 4.159236 | H32: 3.920227 | I32: 3.836974 | J32: 3.852003 | K32: 3.910489 | L32: 4.015809 | M32: 4.126628 | N32: 4.284631 | O32: 4.410897 | P32: 4.522078 | Q32: 4.541005 | R32: 4.585563 | S32: 4.709835 | T32: 4.654778 | U32: 4.774618 | V32: 4.851438 | W32: 4.845424 | X32: 4.794214 | Y32: 4.744589 | Z32: 4.742186 | AA32: 4.706445 | AB32: 4.671878 | AC32: 4.638087 | AD32: 4.596459 | AE32: 4.592654 | AF32: -0.016563
A33: PRC000:da_Metallurgical | B33: Metallurgical Coal | C33: 5.430425 | D33: 5.446697 | E33: 5.679083 | F33: 5.676692 | G33: 5.706998 | H33: 5.757409 | I33: 5.79744 | J33: 5.843367 | K33: 5.947584 | L33: 6.009778 | M33: 6.110779 | N33: 6.182961 | O33: 6.250663 | P33: 6.325945 | Q33: 6.403143 | R33: 6.495366 | S33: 6.56843 | T33: 6.639044 | U33: 6.709926 | V33: 6.759548 | W33: 6.8068 | X33: 6.856149 | Y33: 6.908331 | Z33: 6.965621 | AA33: 7.01844 | AB33: 7.069538 | AC33: 7.122657 | AD33: 7.171206 | AE33: 7.226233 | AF33: 0.010256
A34: PRC000:da_SteamCoal | B34: Other Industrial Coal | C34: 2.799599 | D34: 2.739652 | E34: 2.81602 | F34: 2.878773 | G34: 2.87116 | H34: 2.854581 | I34: 2.836225 | J34: 2.826388 | K34: 2.820199 | L34: 2.815378 | M34: 2.808907 | N34: 2.808419 | O34: 2.809438 | P34: 2.811175 | Q34: 2.815027 | R34: 2.825727 | S34: 2.838923 | T34: 2.847067 | U34: 2.84949 | V34: 2.85175 | W34: 2.851687 | X34: 2.85427 | Y34: 2.853814 | Z34: 2.857372 | AA34: 2.860795 | AB34: 2.865016 | AC34: 2.870122 | AD34: 2.866868 | AE34: 2.867251 | AF34: 0.000853
A35: PRC000:da_CoaltoLiquids | B35: Coal to Liquids | C35: -- | D35: -- | E35: -- | F35: -- | G35: -- | H35: -- | I35: -- | J35: -- | K35: -- | L35: -- | M35: -- | N35: -- | O35: -- | P35: -- | Q35: -- | R35: -- | S35: -- | T35: -- | U35: -- | V35: -- | W35: -- | X35: -- | Y35: -- | Z35: -- | AA35: -- | AB35: -- | AC35: -- | AD35: -- | AE35: -- | AF35: -- | AG35: --
A36: PRC000:da_Electricity | B36: Electricity | C36: 24.421028 | D36: 23.969261 | E36: 22.165068 | F36: 20.957455 | G36: 20.154661 | H36: 19.591454 | I36: 19.228178 | J36: 19.033813 | K36: 18.984463 | L36: 18.977394 | M36: 18.98955 | N36: 19.311668 | O36: 19.408781 | P36: 19.357767 | Q36: 19.480951 | R36: 19.64303 | S36: 19.909723 | T36: 20.139053 | U36: 20.302843 | V36: 20.438232 | W36: 20.447336 | X36: 20.409019 | Y36: 20.401766 | Z36: 20.352793 | AA36: 20.226259 | AB36: 20.095247 | AC36: 20.023176 | AD36: 19.89432 | AE36: 19.708027 | AF36: -0.007629
B38: Transportation
A39: PRC000:ea_LiquefiedPetr | B39: Propane | C39: 25.673756 | D39: 24.128675 | E39: 22.471951 | F39: 20.815958 | G39: 19.998926 | H39: 19.561989 | I39: 19.492157 | J39: 19.602236 | K39: 19.865448 | L39: 20.198456 | M39: 20.616091 | N39: 21.075577 | O39: 21.446709 | P39: 21.658113 | Q39: 21.785759 | R39: 21.940096 | S39: 22.238503 | T39: 22.234596 | U39: 22.490118 | V39: 22.68578 | W39: 22.765638 | X39: 22.760218 | Y39: 22.715187 | Z39: 22.775301 | AA39: 23.024887 | AB39: 23.057398 | AC39: 23.138636 | AD39: 23.127609 | AE39: 23.092308 | AF39: -0.003778
A40: PRC000:ea_Ethanol(E85) | B40: E85 3/ | C40: 38.155422 | D40: 33.744049 | E40: 32.413799 | F40: 30.254673 | G40: 29.96781 | H40: 29.806168 | I40: 29.845123 | J40: 29.921642 | K40: 30.057253 | L40: 30.034431 | M40: 30.226929 | N40: 30.330379 | O40: 30.467768 | P40: 30.563356 | Q40: 30.925976 | R40: 30.996416 | S40: 31.117224 | T40: 31.273573 | U40: 31.334126 | V40: 31.351469 | W40: 31.450729 | X40: 31.335976 | Y40: 31.554224 | Z40: 31.580019 | AA40: 32.420742 | AB40: 32.430134 | AC40: 32.712605 | AD40: 32.812477 | AE40: 33.119743 | AF40: -0.005042
A41: PRC000:ea_MotorGasoline | B41: Motor Gasoline 4/ | C41: 34.785816 | D41: 30.5009 | E41: 27.654461 | F41: 25.814499 | G41: 25.540665 | H41: 25.387987 | I41: 25.40008 | J41: 25.444729 | K41: 25.533381 | L41: 25.497232 | M41: 25.631807 | N41: 25.694864 | O41: 25.783964 | P41: 25.841785 | Q41: 26.121752 | R41: 26.161154 | S41: 26.242393 | T41: 26.358507 | U41: 26.395033 | V41: 26.397087 | W41: 26.466999 | X41: 26.361927 | Y41: 26.536808 | Z41: 26.548639 | AA41: 27.288559 | AB41: 27.287636 | AC41: 27.511337 | AD41: 27.584213 | AE41: 27.827412 | AF41: -0.007939
A42: PRC000:ea_JetFuel | B42: Jet Fuel 5/ | C42: 26.739815 | D42: 22.567797 | E42: 21.658487 | F42: 20.17568 | G42: 19.946627 | H42: 19.713881 | I42: 19.619631 | J42: 19.732992 | K42: 19.754887 | L42: 19.972422 | M42: 20.131733 | N42: 20.218672 | O42: 20.368309 | P42: 20.522896 | Q42: 20.622114 | R42: 20.746122 | S42: 20.869146 | T42: 20.96678 | U42: 21.087648 | V42: 21.294411 | W42: 21.343142 | X42: 21.507015 | Y42: 21.467026 | Z42: 21.622814 | AA42: 21.944468 | AB42: 21.990461 | AC42: 22.051092 | AD42: 22.151415 | AE42: 22.180281 | AF42: -0.006655
A43: PRC000:ea_DistillateFue | B43: Diesel Fuel (distillate fuel oil) 6/ | C43: 37.123703 | D43: 32.857502 | E43: 31.169697 | F43: 29.060146 | G43: 28.13373 | H43: 27.197218 | I43: 26.424463 | J43: 26.52013 | K43: 26.545546 | L43: 26.701553 | M43: 26.827372 | N43: 26.946201 | O43: 26.99394 | P43: 27.20031 | Q43: 27.206823 | R43: 27.345297 | S43: 27.446815 | T43: 27.489861 | U43: 27.537863 | V43: 27.708595 | W43: 27.718977 | X43: 27.838846 | Y43: 27.744848 | Z43: 27.80047 | AA43: 28.387547 | AB43: 28.413376 | AC43: 28.46122 | AD43: 28.524797 | AE43: 28.533144 | AF43: -0.009356
A44: PRC000:ea_ResidualFuel | B44: Residual Fuel Oil | C44: 15.39181 | D44: 15.551938 | E44: 17.300776 | F44: 16.409485 | G44: 16.427687 | H44: 16.502735 | I44: 16.535357 | J44: 16.614216 | K44: 16.714342 | L44: 16.791964 | M44: 16.89019 | N44: 16.984158 | O44: 17.077217 | P44: 17.192131 | Q44: 17.249979 | R44: 17.340448 | S44: 17.439604 | T44: 17.511599 | U44: 17.576931 | V44: 17.686035 | W44: 17.712141 | X44: 17.789486 | Y44: 17.786716 | Z44: 17.831644 | AA44: 18.012905 | AB44: 18.00956 | AC44: 18.112957 | AD44: 18.199448 | AE44: 18.28933 | AF44: 0.006179
A45: PRC000:ea_NaturalGas | B45: Natural Gas 7/ | C45: 17.54928 | D45: 16.298449 | E45: 14.88739 | F45: 14.304173 | G45: 13.609575 | H45: 13.258362 | I45: 13.009375 | J45: 12.877625 | K45: 12.804221 | L45: 12.79319 | M45: 12.772279 | N45: 12.814316 | O45: 12.811182 | P45: 12.783017 | Q45: 12.651464 | R45: 12.542599 | S45: 12.536258 | T45: 12.333598 | U45: 12.31179 | V45: 12.251882 | W45: 12.115541 | X45: 11.941437 | Y45: 11.766513 | Z45: 11.69476 | AA45: 12.298188 | AB45: 12.136044 | AC45: 11.981798 | AD45: 11.858985 | AE45: 11.776169 | AF45: -0.014147
A46: PRC000:ea_Electricity | B46: Electricity | C46: 42.503979 | D46: 44.014454 | E46: 42.699257 | F46: 40.270164 | G46: 39.897511 | H46: 39.828831 | I46: 39.741402 | J46: 39.72414 | K46: 39.732391 | L46: 39.929424 | M46: 40.166943 | N46: 40.565945 | O46: 40.854523 | P46: 41.05629 | Q46: 41.06863 | R46: 41.392082 | S46: 41.665051 | T46: 42.074825 | U46: 42.285225 | V46: 42.527729 | W46: 42.529423 | X46: 42.497456 | Y46: 42.464611 | Z46: 42.516262 | AA46: 42.623566 | AB46: 42.482262 | AC46: 42.484821 | AD46: 42.022789 | AE46: 41.658325 | AF46: -0.000717
B48: Electric Power 8/
A49: PRC000:ga_DistillateFue | B49: Distillate Fuel Oil | C49: 35.259407 | D49: 32.908623 | E49: 30.715006 | F49: 27.876041 | G49: 26.264648 | H49: 24.649519 | I49: 23.123522 | J49: 23.303953 | K49: 23.443438 | L49: 23.430513 | M49: 23.544266 | N49: 23.535339 | O49: 23.673569 | P49: 23.769455 | Q49: 23.84054 | R49: 23.890585 | S49: 23.930655 | T49: 24.005789 | U49: 24.099161 | V49: 24.257807 | W49: 24.249802 | X49: 24.362133 | Y49: 24.304323 | Z49: 24.419262 | AA49: 24.659782 | AB49: 24.697874 | AC49: 24.74641 | AD49: 24.866106 | AE49: 24.873064 | AF49: -0.012385
A50: PRC000:ga_ResidualFuel | B50: Residual Fuel Oil | C50: 21.746656 | D50: 18.583588 | E50: 18.437738 | F50: 17.426687 | G50: 17.396133 | H50: 17.45089 | I50: 17.445499 | J50: 17.50403 | K50: 17.585358 | L50: 17.627741 | M50: 17.713676 | N50: 17.789324 | O50: 17.860552 | P50: 17.979301 | Q50: 18.031912 | R50: 18.093887 | S50: 18.164892 | T50: 18.222368 | U50: 18.234999 | V50: 18.210297 | W50: 18.106007 | X50: 17.987822 | Y50: 17.796373 | Z50: 17.579773 | AA50: 17.799135 | AB50: 17.826294 | AC50: 17.931381 | AD50: 18.026842 | AE50: 18.092518 | AF50: -0.006549
A51: PRC000:ga_NaturalGas | B51: Natural Gas | C51: 7.020061 | D51: 5.62185 | E51: 4.482505 | F51: 3.86762 | G51: 3.385019 | H51: 3.086035 | I51: 2.967777 | J51: 2.962992 | K51: 2.999907 | L51: 3.071391 | M51: 3.152358 | N51: 3.281944 | O51: 3.391262 | P51: 3.511152 | Q51: 3.546355 | R51: 3.593677 | S51: 3.73342 | T51: 3.704462 | U51: 3.844075 | V51: 3.917639 | W51: 3.898643 | X51: 3.847106 | Y51: 3.778374 | Z51: 3.770119 | AA51: 3.746305 | AB51: 3.714029 | AC51: 3.697487 | AD51: 3.642601 | AE51: 3.64077 | AF51: -0.023176
A52: PRC000:ga_SteamCoal | B52: Steam Coal | C52: 2.134762 | D52: 2.057127 | E52: 2.05386 | F52: 2.037131 | G52: 2.008164 | H52: 1.988704 | I52: 1.964183 | J52: 1.952749 | K52: 1.954107 | L52: 1.947204 | M52: 1.91757 | N52: 1.906071 | O52: 1.904636 | P52: 1.897833 | Q52: 1.891512 | R52: 1.889286 | S52: 1.914712 | T52: 1.91035 | U52: 1.912446 | V52: 1.911104 | W52: 1.909412 | X52: 1.909024 | Y52: 1.903793 | Z52: 1.899784 | AA52: 1.900499 | AB52: 1.895365 | AC52: 1.886729 | AD52: 1.890216 | AE52: 1.88728 | AF52: -0.004391
A53: PRC000:ga_uranium | B53: Uranium | C53: 0.710872 | D53: 0.7108 | E53: 0.710739 | F53: 0.710677 | G53: 0.710606 | H53: 0.710544 | I53: 0.710483 | J53: 0.710411 | K53: 0.710349 | L53: 0.710277 | M53: 0.710216 | N53: 0.710154 | O53: 0.710083 | P53: 0.710021 | Q53: 0.709949 | R53: 0.709888 | S53: 0.709826 | T53: 0.709755 | U53: 0.709693 | V53: 0.709631 | W53: 0.70956 | X53: 0.709498 | Y53: 0.709426 | Z53: 0.709365 | AA53: 0.709303 | AB53: 0.709232 | AC53: 0.70917 | AD53: 0.709108 | AE53: 0.709037 | AF53: -9.2e-05
B56: Average Price to All Users 9/
A57: PRC000:ha_LiquefiedPetr | B57: Propane | C57: 28.079664 | D57: 28.863071 | E57: 27.577629 | F57: 26.031885 | G57: 24.921839 | H57: 24.151785 | I57: 23.797935 | J57: 23.714777 | K57: 23.87669 | L57: 24.191362 | M57: 24.642891 | N57: 25.197872 | O57: 25.706682 | P57: 26.062887 | Q57: 26.30707 | R57: 26.53977 | S57: 26.90296 | T57: 26.989214 | U57: 27.284809 | V57: 27.549026 | W57: 27.698435 | X57: 27.740465 | Y57: 27.713034 | Z57: 27.764099 | AA57: 27.921663 | AB57: 27.942894 | AC57: 28.018711 | AD57: 28.013481 | AE57: 27.968328 | AF57: -0.000142
A58: PRC000:ha_Ethanol(E85) | B58: E85 3/ | C58: 38.155422 | D58: 33.744049 | E58: 32.413799 | F58: 30.254673 | G58: 29.96781 | H58: 29.806168 | I58: 29.845123 | J58: 29.921642 | K58: 30.057253 | L58: 30.034431 | M58: 30.226929 | N58: 30.330379 | O58: 30.467768 | P58: 30.563356 | Q58: 30.925976 | R58: 30.996416 | S58: 31.117224 | T58: 31.273573 | U58: 31.334126 | V58: 31.351469 | W58: 31.450729 | X58: 31.335976 | Y58: 31.554224 | Z58: 31.580019 | AA58: 32.420742 | AB58: 32.430134 | AC58: 32.712605 | AD58: 32.812477 | AE58: 33.119743 | AF58: -0.005042
A59: PRC000:ha_MotorGasoline | B59: Motor Gasoline 4/ | C59: 34.782677 | D59: 30.452633 | E59: 27.655825 | F59: 25.83893 | G59: 25.571243 | H59: 25.414442 | I59: 25.417324 | J59: 25.462954 | K59: 25.552574 | L59: 25.517675 | M59: 25.653202 | N59: 25.717319 | O59: 25.807234 | P59: 25.865997 | Q59: 26.146042 | R59: 26.186483 | S59: 26.268536 | T59: 26.385166 | U59: 26.422464 | V59: 26.425398 | W59: 26.495975 | X59: 26.391788 | Y59: 26.567183 | Z59: 26.58003 | AA59: 27.324665 | AB59: 27.324312 | AC59: 27.548143 | AD59: 27.62151 | AE59: 27.864849 | AF59: -0.007888
A60: PRC000:ha_JetFuel | B60: Jet Fuel 5/ | C60: 26.739815 | D60: 22.567797 | E60: 21.658487 | F60: 20.17568 | G60: 19.946627 | H60: 19.713881 | I60: 19.619631 | J60: 19.732992 | K60: 19.754887 | L60: 19.972422 | M60: 20.131733 | N60: 20.218672 | O60: 20.368309 | P60: 20.522896 | Q60: 20.622114 | R60: 20.746122 | S60: 20.869146 | T60: 20.96678 | U60: 21.087648 | V60: 21.294411 | W60: 21.343142 | X60: 21.507015 | Y60: 21.467026 | Z60: 21.622814 | AA60: 21.944468 | AB60: 21.990461 | AC60: 22.051092 | AD60: 22.151415 | AE60: 22.180281 | AF60: -0.006655
A61: PRC000:ha_DistillateFue | B61: Distillate Fuel Oil | C61: 36.67762 | D61: 32.847237 | E61: 31.066772 | F61: 28.850601 | G61: 27.806213 | H61: 26.772062 | I61: 25.893951 | J61: 25.991577 | K61: 26.00194 | L61: 26.168556 | M61: 26.275074 | N61: 26.402332 | O61: 26.447607 | P61: 26.633846 | Q61: 26.645639 | R61: 26.773325 | S61: 26.862782 | T61: 26.907473 | U61: 26.957165 | V61: 27.116112 | W61: 27.111334 | X61: 27.231009 | Y61: 27.144974 | Z61: 27.202578 | AA61: 27.69154 | AB61: 27.715929 | AC61: 27.750174 | AD61: 27.821075 | AE61: 27.823706 | AF61: -0.009819
A62: PRC000:ha_ResidualFuel | B62: Residual Fuel Oil | C62: 15.551993 | D62: 15.007058 | E62: 16.830484 | F62: 16.090752 | G62: 16.222122 | H62: 16.403404 | I62: 16.530327 | J62: 16.608894 | K62: 16.708054 | L62: 16.785976 | M62: 16.884041 | N62: 16.976837 | O62: 17.068817 | P62: 17.183195 | Q62: 17.241272 | R62: 17.328798 | S62: 17.425045 | T62: 17.495161 | U62: 17.557133 | V62: 17.656975 | W62: 17.672941 | X62: 17.738798 | Y62: 17.726212 | Z62: 17.761419 | AA62: 17.944437 | AB62: 17.942337 | AC62: 18.046041 | AD62: 18.132389 | AE62: 18.218988 | AF62: 0.005669
A63: PRC000:ha_NaturalGas | B63: Natural Gas | C63: 8.881388 | D63: 7.976063 | E63: 6.852537 | F63: 6.29388 | G63: 5.852363 | H63: 5.624272 | I63: 5.525674 | J63: 5.566098 | K63: 5.641952 | L63: 5.765839 | M63: 5.879462 | N63: 6.039192 | O63: 6.168878 | P63: 6.280257 | Q63: 6.306401 | R63: 6.349401 | S63: 6.456745 | T63: 6.411808 | U63: 6.503413 | V63: 6.57014 | W63: 6.553286 | X63: 6.502223 | Y63: 6.443989 | Z63: 6.448259 | AA63: 6.519228 | AB63: 6.479012 | AC63: 6.437845 | AD63: 6.398898 | AE63: 6.392191 | AF63: -0.011677
A64: PRC000:ha_Metallugical | B64: Metallurgical Coal | C64: 5.430425 | D64: 5.446697 | E64: 5.679083 | F64: 5.676692 | G64: 5.706998 | H64: 5.757409 | I64: 5.79744 | J64: 5.843367 | K64: 5.947584 | L64: 6.009778 | M64: 6.110779 | N64: 6.182961 | O64: 6.250663 | P64: 6.325945 | Q64: 6.403143 | R64: 6.495366 | S64: 6.56843 | T64: 6.639044 | U64: 6.709926 | V64: 6.759548 | W64: 6.8068 | X64: 6.856149 | Y64: 6.908331 | Z64: 6.965621 | AA64: 7.01844 | AB64: 7.069538 | AC64: 7.122657 | AD64: 7.171206 | AE64: 7.226233 | AF64: 0.010256
A65: PRC000:ha_Coal | B65: Other Coal | C65: 2.175554 | D65: 2.099087 | E65: 2.095512 | F65: 2.086296 | G65: 2.066263 | H65: 2.056357 | I65: 2.044493 | J65: 2.044922 | K65: 2.053573 | L65: 2.046573 | M65: 2.018765 | N65: 2.004686 | O65: 2.002431 | P65: 1.994464 | Q65: 1.987976 | R65: 1.987349 | S65: 2.013478 | T65: 2.010947 | U65: 2.014595 | V65: 2.011747 | W65: 2.008997 | X65: 2.008635 | Y65: 2.005536 | Z65: 2.003703 | AA65: 2.007817 | AB65: 2.005845 | AC65: 2.003943 | AD65: 2.007061 | AE65: 2.007241 | AF65: -0.002872
A66: PRC000:ha_CoaltoLiquids | B66: Coal to Liquids | C66: -- | D66: -- | E66: -- | F66: -- | G66: -- | H66: -- | I66: -- | J66: -- | K66: -- | L66: -- | M66: -- | N66: -- | O66: -- | P66: -- | Q66: -- | R66: -- | S66: -- | T66: -- | U66: -- | V66: -- | W66: -- | X66: -- | Y66: -- | Z66: -- | AA66: -- | AB66: -- | AC66: -- | AD66: -- | AE66: -- | AF66: -- | AG66: --
A67: PRC000:ha_Electricity | B67: Electricity | C67: 35.829422 | D67: 34.915806 | E67: 33.621994 | F67: 32.327888 | G67: 31.56164 | H67: 31.015574 | I67: 30.627668 | J67: 30.479345 | K67: 30.520933 | L67: 30.61846 | M67: 30.700859 | N67: 31.153543 | O67: 31.446527 | P67: 31.449999 | Q67: 31.634071 | R67: 31.862349 | S67: 32.203876 | T67: 32.469318 | U67: 32.694557 | V67: 32.876797 | W67: 32.951668 | X67: 32.996758 | Y67: 33.034153 | Z67: 33.064751 | AA67: 32.964348 | AB67: 32.81472 | AC67: 32.763191 | AD67: 32.582088 | AE67: 32.309727 | AF67: -0.003686
B69: Non-Renewable Energy Expenditures by Sector
B70: (billion 2022 dollars)
A71: PRC000:ia_Residential | B71: Residential | C71: 322.79446 | D71: 311.10562 | E71: 296.58255 | F71: 287.51538 | G71: 281.89728 | H71: 278.237 | I71: 276.01395 | J71: 276.53046 | K71: 277.74963 | L71: 279.73901 | M71: 281.66983 | N71: 286.21335 | O71: 289.80994 | P71: 291.72476 | Q71: 294.61844 | R71: 298.18088 | S71: 302.58005 | T71: 305.62888 | U71: 309.17578 | V71: 312.54153 | W71: 315.099 | X71: 317.38449 | Y71: 319.51975 | Z71: 322.40082 | AA71: 325.77969 | AB71: 327.3389 | AC71: 329.25366 | AD71: 330.65851 | AE71: 331.64893 | AF71: 0.000967
A72: PRC000:ia_Commercial | B72: Commercial | C72: 237.58575 | D72: 225.87795 | E72: 213.01193 | F72: 203.11526 | G72: 197.8513 | H72: 193.91623 | I72: 191.97257 | J72: 191.99533 | K72: 192.80859 | L72: 194.00732 | M72: 195.20189 | N72: 198.03673 | O72: 200.05309 | P72: 200.73555 | Q72: 201.89059 | R72: 203.22679 | S72: 205.25421 | T72: 206.31689 | U72: 207.71613 | V72: 209.11646 | W72: 209.91202 | X72: 210.61569 | Y72: 211.14548 | Z72: 212.0106 | AA72: 213.26053 | AB72: 212.95163 | AC72: 213.52231 | AD72: 213.60996 | AE72: 213.53391 | AF72: -0.003805
A73: PRC000:ia_Industrial | B73: Industrial 1/ | C73: 310.1033 | D73: 282.26938 | E73: 252.55199 | F73: 234.86604 | G73: 226.70996 | H73: 221.57541 | I73: 219.73885 | J73: 221.3373 | K73: 224.22203 | L73: 228.29579 | M73: 233.62683 | N73: 240.33781 | O73: 245.94324 | P73: 250.18936 | Q73: 253.30142 | R73: 257.26852 | S73: 262.92703 | T73: 265.25409 | U73: 271.08899 | V73: 276.17294 | W73: 279.27426 | X73: 280.34839 | Y73: 281.26077 | Z73: 283.24661 | AA73: 285.4295 | AB73: 287.5195 | AC73: 289.11874 | AD73: 290.22354 | AE73: 292.79837 | AF73: -0.002049
A74: PRC000:ia_Transportatio | B74: Transportation | C74: 881.96179 | D74: 779.21692 | E74: 718.76898 | F74: 663.46997 | G74: 647.39758 | H74: 634.12219 | I74: 624.34558 | J74: 620.4953 | K74: 615.71277 | L74: 611.47125 | M74: 610.01404 | N74: 608.5733 | O74: 607.87622 | P74: 607.89911 | Q74: 609.51086 | R74: 609.85699 | S74: 611.14374 | T74: 612.75714 | U74: 614.47162 | V74: 617.21283 | W74: 619.52008 | X74: 620.98688 | Y74: 624.36005 | Z74: 627.82812 | AA74: 645.26947 | AB74: 649.33063 | AC74: 656.65985 | AD74: 662.27075 | AE74: 670.698 | AF74: -0.009732
A75: PRC000:ia_TotalNon-Rene | B75: Total Non-Renewable Expenditures | C75: 1752.4453 | D75: 1598.4698 | E75: 1480.9155 | F75: 1388.9667 | G75: 1353.8562 | H75: 1327.8508 | I75: 1312.0709 | J75: 1310.3584 | K75: 1310.493 | L75: 1313.5134 | M75: 1320.5126 | N75: 1333.1611 | O75: 1343.6825 | P75: 1350.5488 | Q75: 1359.3213 | R75: 1368.5332 | S75: 1381.905 | T75: 1389.957 | U75: 1402.4525 | V75: 1415.0437 | W75: 1423.8054 | X75: 1429.3354 | Y75: 1436.2861 | Z75: 1445.4862 | AA75: 1469.7393 | AB75: 1477.1406 | AC75: 1488.5547 | AD75: 1496.7627 | AE75: 1508.6792 | AF75: -0.005335
A76: PRC000:ja_Transportatio | B76: Transportation Renewable Expenditures | C76: 1.289994 | D76: 1.153556 | E76: 1.040157 | F76: 0.967007 | G76: 0.934007 | H76: 0.903224 | I76: 0.873027 | J76: 0.840123 | K76: 0.806767 | L76: 0.769688 | M76: 0.738783 | N76: 0.70919 | O76: 0.683297 | P76: 0.659391 | Q76: 0.642216 | R76: 0.625333 | S76: 0.614081 | T76: 0.607816 | U76: 0.60403 | V76: 0.601727 | W76: 0.603247 | X76: 0.603687 | Y76: 0.610925 | Z76: 0.615965 | AA76: 0.636548 | AB76: 0.644462 | AC76: 0.6571 | AD76: 0.668256 | AE76: 0.683259 | AF76: -0.022441
A77: PRC000:ja_TotalExpendit | B77: Total Expenditures | C77: 1753.7354 | D77: 1599.6234 | E77: 1481.9557 | F77: 1389.9337 | G77: 1354.7902 | H77: 1328.754 | I77: 1312.944 | J77: 1311.1985 | K77: 1311.2998 | L77: 1314.2831 | M77: 1321.2513 | N77: 1333.8704 | O77: 1344.3658 | P77: 1351.2083 | Q77: 1359.9635 | R77: 1369.1586 | S77: 1382.5192 | T77: 1390.5648 | U77: 1403.0565 | V77: 1415.6454 | W77: 1424.4087 | X77: 1429.9391 | Y77: 1436.8971 | Z77: 1446.1022 | AA77: 1470.3759 | AB77: 1477.785 | AC77: 1489.2118 | AD77: 1497.4309 | AE77: 1509.3624 | AF77: -0.005345
B80: Prices in Nominal Dollars
B81: Residential
A82: PRC000:nom_R_LiquefiedP | B82: Propane | C82: 29.133368 | D82: 32.600933 | E82: 33.591049 | F82: 33.150249 | G82: 32.635117 | H82: 32.33429 | I82: 32.446053 | J82: 32.931576 | K82: 33.77552 | L82: 34.906071 | M82: 36.293835 | N82: 37.9189 | O82: 39.611206 | P82: 41.182041 | Q82: 42.624863 | R82: 44.03083 | S82: 45.598953 | T82: 46.898193 | U82: 48.437809 | V82: 50.019119 | W82: 51.510777 | X82: 52.8839 | Y82: 54.158352 | Z82: 55.546276 | AA82: 57.234604 | AB82: 58.666496 | AC82: 60.229031 | AD82: 61.731525 | AE82: 63.200649 | AF82: 0.028044
A83: PRC000:nom_R_Distillate | B83: Distillate Fuel Oil | C83: 35.242496 | D83: 34.182652 | E83: 33.724178 | F83: 32.667091 | G83: 32.846657 | H83: 33.046928 | I83: 33.432007 | J83: 34.269375 | K83: 35.044159 | L83: 36.064919 | M83: 37.002056 | N83: 38.029194 | O83: 39.001244 | P83: 40.150604 | Q83: 41.098312 | R83: 42.19157 | S83: 43.25383 | T83: 44.266022 | U83: 45.324841 | V83: 46.584534 | W83: 47.62587 | X83: 48.902164 | Y83: 49.874504 | Z83: 51.111248 | AA83: 52.683567 | AB83: 53.982517 | AC83: 55.33503 | AD83: 56.786217 | AE83: 58.157211 | AF83: 0.01805
A84: PRC000:nom_R_NaturalGas | B84: Natural Gas | C84: 14.293921 | D84: 14.64599 | E84: 13.676522 | F84: 13.184909 | G84: 12.791023 | H84: 12.605636 | I84: 12.573746 | J84: 12.909769 | K84: 13.249883 | L84: 13.680079 | M84: 14.109493 | N84: 14.63436 | O84: 15.145339 | P84: 15.646319 | Q84: 16.078226 | R84: 16.557304 | S84: 17.127001 | T84: 17.513002 | U84: 18.044384 | V84: 18.599209 | W84: 19.059166 | X84: 19.474995 | Y84: 19.853939 | Z84: 20.418022 | AA84: 21.441404 | AB84: 21.922989 | AC84: 22.388704 | AD84: 22.934742 | AE84: 23.554539 | AF84: 0.017999
A85: PRC000:nom_R_Electricit | B85: Electricity | C85: 42.669247 | D85: 43.146023 | E85: 43.261093 | F85: 42.880463 | G85: 43.009357 | H85: 43.327248 | I85: 43.842648 | J85: 44.68734 | K85: 45.805477 | L85: 47.097492 | M85: 48.405567 | N85: 50.295189 | O85: 52.085312 | P85: 53.362103 | Q85: 54.92733 | R85: 56.583927 | S85: 58.444336 | T85: 60.167355 | U85: 61.95829 | V85: 63.713764 | W85: 65.363594 | X85: 67.008003 | Y85: 68.678673 | Z85: 70.432961 | AA85: 71.975487 | AB85: 73.475456 | AC85: 75.125107 | AD85: 76.578171 | AE85: 77.840477 | AF85: 0.021703
B87: Commercial
A88: PRC000:nom_C_LiquefiedG | B88: Propane | C88: 27.825644 | D88: 27.85585 | E88: 26.556959 | F88: 24.976807 | G88: 24.337795 | H88: 24.212545 | I88: 24.589096 | J88: 25.254982 | K88: 26.178425 | L88: 27.261217 | M88: 28.512354 | N88: 29.901306 | O88: 31.225031 | P88: 32.327419 | Q88: 33.303188 | R88: 34.315617 | S88: 35.582958 | T88: 36.394447 | U88: 37.650372 | V88: 38.867626 | W88: 39.91769 | X88: 40.838013 | Y88: 41.698109 | Z88: 42.775314 | AA88: 44.170029 | AB88: 45.28019 | AC88: 46.532391 | AD88: 47.632702 | AE88: 48.701336 | AF88: 0.020192
A89: PRC000:nom_C_Distillate | B89: Distillate Fuel Oil | C89: 35.263695 | D89: 34.344528 | E89: 32.658478 | F89: 30.315842 | G89: 29.135559 | H89: 27.945101 | I89: 26.866716 | J89: 27.554403 | K89: 28.172379 | L89: 29.022541 | M89: 29.806835 | N89: 30.64859 | O89: 31.455866 | P89: 32.399479 | Q89: 33.183022 | R89: 34.086586 | S89: 34.961765 | T89: 35.791187 | U89: 36.661175 | V89: 37.72419 | W89: 38.565331 | X89: 39.63549 | Y89: 40.40062 | Z89: 41.460686 | AA89: 43.348011 | AB89: 44.403557 | AC89: 45.525749 | AD89: 46.750488 | AE89: 47.882179 | AF89: 0.010985
A90: PRC000:nom_C_ResidualFu | B90: Residual Fuel Oil | C90: 12.628995 | D90: 8.190194 | E90: 10.064173 | F90: 10.614261 | G90: 12.394233 | H90: 14.254799 | I90: 16.294704 | J90: 16.744129 | K90: 17.220007 | L90: 17.747589 | M90: 18.278893 | N90: 18.828438 | O90: 19.41271 | P90: 20.019819 | Q90: 20.605381 | R90: 21.20463 | S90: 21.826969 | T90: 22.406015 | U90: 23.034382 | V90: 23.748093 | W90: 24.306381 | X90: 24.97621 | Y90: 25.601828 | Z90: 26.294802 | AA90: 27.197239 | AB90: 27.841978 | AC90: 28.729586 | AD90: 29.587326 | AE90: 30.433245 | AF90: 0.031911
A91: PRC000:nom_C_NaturalGas | B91: Natural Gas | C91: 10.986808 | D91: 10.752255 | E91: 9.947948 | F91: 9.641949 | G91: 9.413559 | H91: 9.376698 | I91: 9.473101 | J91: 9.725355 | K91: 9.973158 | L91: 10.300301 | M91: 10.62715 | N91: 11.050625 | O91: 11.449692 | P91: 11.837113 | Q91: 12.159459 | R91: 12.529586 | S91: 12.986811 | T91: 13.267094 | U91: 13.688367 | V91: 14.127917 | W91: 14.471656 | X91: 14.771008 | Y91: 15.036107 | Z91: 15.46964 | AA91: 16.177822 | AB91: 16.489763 | AC91: 16.806581 | AD91: 17.210039 | AE91: 17.685751 | AF91: 0.017148
A92: PRC000:nom_C_Electricit | B92: Electricity | C92: 36.670883 | D92: 37.384396 | E92: 36.634933 | F92: 35.829681 | G92: 35.682613 | H92: 35.778049 | I92: 35.970699 | J92: 36.469803 | K92: 37.239471 | L92: 38.070854 | M92: 38.904255 | N92: 40.277725 | O92: 41.548607 | P92: 42.420837 | Q92: 43.531006 | R92: 44.662575 | S92: 46.012589 | T92: 47.266869 | U92: 48.525997 | V92: 49.775635 | W92: 50.926758 | X92: 52.105659 | Y92: 53.247463 | Z92: 54.400368 | AA92: 55.375427 | AB92: 56.22076 | AC92: 57.363804 | AD92: 58.272152 | AE92: 59.05735 | AF92: 0.017164
B94: Industrial 1/
A95: PRC000:nom_I_LiquefiedP | B95: Propane | C95: 23.43502 | D95: 22.35663 | E95: 20.487595 | F95: 18.533535 | G95: 17.736046 | H95: 17.477232 | I95: 17.740955 | J95: 18.286146 | K95: 19.090485 | L95: 20.049326 | M95: 21.186962 | N95: 22.464025 | O95: 23.655508 | P95: 24.597996 | Q95: 25.405924 | R95: 26.269163 | S95: 27.429415 | T95: 28.034966 | U95: 29.178497 | V95: 30.24905 | W95: 31.111233 | X95: 31.816525 | Y95: 32.450352 | Z95: 33.311852 | AA95: 34.086624 | AB95: 34.970642 | AC95: 36.006218 | AD95: 36.842278 | AE95: 37.636387 | AF95: 0.017063
A96: PRC000:nom_I_Distillate | B96: Distillate Fuel Oil | C96: 35.187302 | D96: 34.160721 | E96: 32.510654 | F96: 30.122334 | G96: 28.893148 | H96: 27.659189 | I96: 26.532314 | J96: 27.228542 | K96: 27.844921 | L96: 28.691835 | M96: 29.480526 | N96: 30.336336 | O96: 31.138449 | P96: 32.100212 | Q96: 32.878376 | R96: 33.792221 | S96: 34.671124 | T96: 35.505093 | U96: 36.380726 | V96: 37.452629 | W96: 38.299541 | X96: 39.3806 | Y96: 40.156269 | Z96: 41.188438 | AA96: 42.553871 | AB96: 43.609371 | AC96: 44.728596 | AD96: 45.946964 | AE96: 47.07082 | AF96: 0.010446
A97: PRC000:nom_I_ResidualFu | B97: Residual Fuel Oil | C97: 13.34515 | D97: 8.847362 | E97: 10.847251 | F97: 11.701765 | G97: 13.668666 | H97: 15.834412 | I97: 18.055012 | J97: 18.55028 | K97: 19.090975 | L97: 19.679285 | M97: 20.283073 | N97: 20.912045 | O97: 21.573601 | P97: 22.25563 | Q97: 22.905643 | R97: 23.566257 | S97: 24.26272 | T97: 24.90963 | U97: 25.616434 | V97: 26.404327 | W97: 27.034216 | X97: 27.773752 | Y97: 28.398886 | Z97: 29.163754 | AA97: 30.157469 | AB97: 30.882547 | AC97: 31.831926 | AD97: 32.756706 | AE97: 33.688114 | AF97: 0.033624
A98: PRC000:nom_I_NaturalGas | B98: Natural Gas 2/ | C98: 7.330917 | D98: 6.529226 | E98: 5.504909 | F98: 5.005093 | G98: 4.630029 | H98: 4.458237 | I98: 4.457832 | J98: 4.573442 | K98: 4.746519 | L98: 4.985881 | M98: 5.240906 | N98: 5.570441 | O98: 5.87198 | P98: 6.160956 | Q98: 6.329235 | R98: 6.534397 | S98: 6.859877 | T98: 6.928579 | U98: 7.26545 | V98: 7.547869 | W98: 7.708785 | X98: 7.802154 | Y98: 7.899689 | Z98: 8.079667 | AA98: 8.207956 | AB98: 8.341245 | AC98: 8.479423 | AD98: 8.605009 | AE98: 8.805438 | AF98: 0.006567
A99: PRC000:nom_I_Metallurgi | B99: Metallurgical Coal | C99: 5.430425 | D99: 5.671855 | E99: 6.058195 | F99: 6.187327 | G99: 6.352985 | H99: 6.547553 | I99: 6.735518 | J99: 6.937766 | K99: 7.219128 | L99: 7.461522 | M99: 7.76082 | N99: 8.038456 | O99: 8.321158 | P99: 8.618576 | Q99: 8.924676 | R99: 9.255854 | S99: 9.566922 | T99: 9.882133 | U99: 10.210374 | V99: 10.516509 | W99: 10.82922 | X99: 11.157767 | Y99: 11.502296 | Z99: 11.867923 | AA99: 12.240033 | AB99: 12.622065 | AC99: 13.02175 | AD99: 13.425182 | AE99: 13.854766 | AF99: 0.034016
A100: PRC000:nom_I_SteamCoal | B100: Other Industrial Coal | C100: 2.799599 | D100: 2.852905 | E100: 3.004005 | F100: 3.137727 | G100: 3.196153 | H100: 3.246342 | I100: 3.295152 | J100: 3.35574 | K100: 3.423134 | L100: 3.495471 | M100: 3.567373 | N100: 3.65122 | O100: 3.740048 | P100: 3.829993 | Q100: 3.923573 | R100: 4.026642 | S100: 4.134892 | T100: 4.237823 | U100: 4.336017 | V100: 4.436754 | W100: 4.536867 | X100: 4.645069 | Y100: 4.751569 | Z100: 4.868348 | AA100: 4.989175 | AB100: 5.115244 | AC100: 5.247201 | AD100: 5.36705 | AE100: 5.497344 | AF100: 0.024392
A101: PRC000:nom_I_CoaltoLiqu | B101: Coal to Liquids | C101: -- | D101: -- | E101: -- | F101: -- | G101: -- | H101: -- | I101: -- | J101: -- | K101: -- | L101: -- | M101: -- | N101: -- | O101: -- | P101: -- | Q101: -- | R101: -- | S101: -- | T101: -- | U101: -- | V101: -- | W101: -- | X101: -- | Y101: -- | Z101: -- | AA101: -- | AB101: -- | AC101: -- | AD101: -- | AE101: -- | AF101: -- | AG101: --
A102: PRC000:nom_I_Electricit | B102: Electricity | C102: 24.421028 | D102: 24.96011 | E102: 23.644716 | F102: 22.842644 | G102: 22.436012 | H102: 22.280174 | I102: 22.339474 | J102: 22.598642 | K102: 23.043182 | L102: 23.56164 | M102: 24.117136 | N102: 25.107063 | O102: 25.837824 | P102: 26.37335 | Q102: 27.152472 | R102: 27.991188 | S102: 28.998522 | T102: 29.97673 | U102: 30.89447 | V102: 31.797815 | W102: 32.53051 | X102: 33.213848 | Y102: 33.968719 | Z102: 34.676792 | AA102: 35.274235 | AB102: 35.878372 | AC102: 36.606674 | AD102: 37.244061 | AE102: 37.78595 | AF102: 0.015711
B105: Transportation
A106: PRC000:nom_T_LiquefiedP | B106: Propane | C106: 25.673756 | D106: 25.126116 | E106: 23.972084 | F106: 22.688417 | G106: 22.262648 | H106: 22.246664 | I106: 22.646168 | J106: 23.273523 | K106: 24.112516 | L106: 25.077665 | M106: 26.182877 | N106: 27.400318 | O106: 28.550802 | P106: 29.507381 | Q106: 30.364902 | R106: 31.264492 | S106: 32.390388 | T106: 33.095917 | U106: 34.222809 | V106: 35.294552 | W106: 36.218792 | X106: 37.040211 | Y106: 37.820538 | Z106: 38.804226 | AA106: 40.154991 | AB106: 41.167042 | AC106: 42.302406 | AD106: 43.297089 | AE106: 44.274586 | AF106: 0.019653
A107: PRC000:nom_T_Ethan(E85) | B107: E85 3/ | C107: 38.155422 | D107: 35.138969 | E107: 34.57761 | F107: 32.976173 | G107: 33.359932 | H107: 33.896748 | I107: 34.674335 | J107: 35.525642 | K107: 36.483246 | L107: 37.289654 | M107: 38.388847 | N107: 39.432472 | O107: 40.560032 | P107: 41.640038 | Q107: 43.1045 | R107: 44.169689 | S107: 45.32225 | T107: 46.55032 | U107: 47.680573 | V107: 48.776634 | W107: 50.036263 | X107: 50.99649 | Y107: 52.537441 | Z107: 53.805576 | AA107: 56.541191 | AB107: 57.901272 | AC107: 59.805683 | AD107: 61.428082 | AE107: 63.500065 | AF107: 0.018358
A108: PRC000:nom_T_MotorGasol | B108: Motor Gasoline 4/ | C108: 34.785816 | D108: 31.761757 | E108: 29.500557 | F108: 28.136593 | G108: 28.431669 | H108: 28.872221 | I108: 29.510046 | J108: 30.210253 | K108: 30.992207 | L108: 31.656433 | M108: 32.552944 | N108: 33.405846 | O108: 34.324749 | P108: 35.207287 | Q108: 36.408394 | R108: 37.279472 | S108: 38.222057 | T108: 39.234306 | U108: 40.164845 | V108: 41.068604 | W108: 42.107441 | X108: 42.901672 | Y108: 44.183495 | Z108: 45.233185 | AA108: 47.590759 | AB108: 48.719776 | AC108: 50.296646 | AD108: 51.640278 | AE108: 53.353146 | AF108: 0.015393
A109: PRC000:nom_T_JetFuel | B109: Jet Fuel 5/ | C109: 26.739815 | D109: 23.500711 | E109: 23.104317 | F109: 21.990543 | G109: 22.20443 | H109: 22.419403 | I109: 22.794266 | J109: 23.428768 | K109: 23.978319 | L109: 24.797031 | M109: 25.567732 | N109: 26.286257 | O109: 27.115189 | P109: 27.960741 | Q109: 28.743019 | R109: 29.563089 | S109: 30.395922 | T109: 31.20879 | U109: 32.088696 | V109: 33.129856 | W109: 33.955685 | X109: 35.00074 | Y109: 35.742363 | Z109: 36.840633 | AA109: 38.270756 | AB109: 39.262115 | AC109: 40.31414 | AD109: 41.469559 | AE109: 42.52597 | AF109: 0.016708
A110: PRC000:nom_T_Distillate | B110: Diesel Fuel (distillate fuel oil) 6/ | C110: 37.123703 | D110: 34.215778 | E110: 33.250454 | F110: 31.674196 | G110: 31.318249 | H110: 30.929749 | I110: 30.700182 | J110: 31.487066 | K110: 32.220764 | L110: 33.151676 | M110: 34.071335 | N110: 35.032707 | O110: 35.93552 | P110: 37.058163 | Q110: 37.920761 | R110: 38.966869 | S110: 39.976299 | T110: 40.918312 | U110: 41.90387 | V110: 43.109047 | W110: 44.099266 | X110: 45.305222 | Y110: 46.194874 | Z110: 47.366039 | AA110: 49.507374 | AB110: 50.729691 | AC110: 52.033237 | AD110: 53.401138 | AE110: 54.706234 | AF110: 0.013944
A111: PRC000:nom_T_ResidualFu | B111: Residual Fuel Oil | C111: 15.39181 | D111: 16.19483 | E111: 18.455704 | F111: 17.885569 | G111: 18.287172 | H111: 18.767561 | I111: 19.210928 | J111: 19.72588 | K111: 20.287731 | L111: 20.848289 | M111: 21.450903 | N111: 22.081072 | O111: 22.733944 | P111: 23.422852 | Q111: 24.042952 | R111: 24.710026 | S111: 25.400791 | T111: 26.065796 | U111: 26.746498 | V111: 27.515944 | W111: 28.178976 | X111: 28.950792 | Y111: 29.614689 | Z111: 30.381294 | AA111: 31.414185 | AB111: 32.154549 | AC111: 33.114384 | AD111: 34.071102 | AE111: 35.065899 | AF111: 0.029844
A112: PRC000:nom_T_NaturalGas | B112: Natural Gas 7/ | C112: 17.54928 | D112: 16.9722 | E112: 15.88121 | F112: 15.590877 | G112: 15.150073 | H112: 15.077931 | I112: 15.11441 | J112: 15.289466 | K112: 15.541657 | L112: 15.883558 | M112: 16.221067 | N112: 16.659868 | O112: 17.05481 | P112: 17.4158 | Q112: 17.633558 | R112: 17.873119 | S112: 18.259066 | T112: 18.358406 | U112: 18.734629 | V112: 19.061485 | W112: 19.275114 | X112: 19.433617 | Y112: 19.591116 | Z112: 19.925364 | AA112: 21.447821 | AB112: 21.667885 | AC112: 21.905306 | AD112: 22.201149 | AE112: 22.5783 | AF112: 0.00904
A113: PRC000:nom_T_Electricit | B113: Electricity | C113: 42.503979 | D113: 45.833939 | E113: 45.549683 | F113: 43.89259 | G113: 44.413597 | H113: 45.294914 | I113: 46.171925 | J113: 47.164043 | K113: 48.226849 | L113: 49.574917 | M113: 51.012875 | N113: 52.739712 | O113: 54.387337 | P113: 55.935787 | Q113: 57.241295 | R113: 58.983448 | S113: 60.685165 | T113: 62.62785 | U113: 64.344666 | V113: 66.164665 | W113: 67.661812 | X113: 69.160797 | Y113: 70.703117 | Z113: 72.438583 | AA113: 74.33474 | AB113: 75.848503 | AC113: 77.671402 | AD113: 78.67067 | AE113: 79.870979 | AF113: 0.022785
B115: Electric Power 8/
A116: PRC000:nom_E_Distillate | B116: Distillate Fuel Oil | C116: 35.259407 | D116: 34.269009 | E116: 32.765411 | F116: 30.383577 | G116: 29.2376 | H116: 28.032406 | I116: 26.86512 | J116: 27.668533 | K116: 28.45545 | L116: 29.090471 | M116: 29.901722 | N116: 30.598249 | O116: 31.515295 | P116: 32.383911 | Q116: 33.228851 | R116: 34.043926 | S116: 34.855011 | T116: 35.732315 | U116: 36.671261 | V116: 37.740311 | W116: 38.580009 | X116: 39.647186 | Y116: 40.466434 | Z116: 41.605183 | AA116: 43.006218 | AB116: 44.095974 | AC116: 45.241764 | AD116: 46.55172 | AE116: 47.688812 | AF116: 0.010843
A117: PRC000:nom_E_ResidualFu | B117: Residual Fuel Oil | C117: 21.746656 | D117: 19.351803 | E117: 19.668566 | F117: 18.99427 | G117: 19.36524 | H117: 19.84584 | I117: 20.268341 | J117: 20.782347 | K117: 21.344961 | L117: 21.88596 | M117: 22.496748 | N117: 23.127867 | O117: 23.776752 | P117: 24.495306 | Q117: 25.132807 | R117: 25.78367 | S117: 26.457172 | T117: 27.123766 | U117: 27.747868 | V117: 28.331589 | W117: 28.805592 | X117: 29.273563 | Y117: 29.630768 | Z117: 29.95216 | AA117: 31.041374 | AB117: 31.827347 | AC117: 32.782425 | AD117: 33.747967 | AE117: 34.688557 | AF117: 0.016817
A118: PRC000:nom_E_NaturalGas | B118: Natural Gas | C118: 7.020061 | D118: 5.854248 | E118: 4.781738 | F118: 4.215524 | G118: 3.768177 | H118: 3.509561 | I118: 3.44799 | J118: 3.517929 | K118: 3.641263 | L118: 3.813327 | M118: 4.003562 | N118: 4.26685 | O118: 4.514597 | P118: 4.783653 | Q118: 4.942896 | R118: 5.120965 | S118: 5.437727 | T118: 5.514046 | U118: 5.84946 | V118: 6.095066 | W118: 6.202512 | X118: 6.260819 | Y118: 6.290952 | Z118: 6.423474 | AA118: 6.533488 | AB118: 6.631086 | AC118: 6.759801 | AD118: 6.819296 | AE118: 6.980403 | AF118: -0.000202
A119: PRC000:nom_E_SteamCoal | B119: Steam Coal | C119: 2.134762 | D119: 2.142165 | E119: 2.190968 | F119: 2.220377 | G119: 2.235473 | H119: 2.261633 | I119: 2.282006 | J119: 2.318478 | K119: 2.371879 | L119: 2.417578 | M119: 2.435354 | N119: 2.478079 | O119: 2.535536 | P119: 2.58564 | Q119: 2.636382 | R119: 2.692221 | S119: 2.788779 | T119: 2.843532 | U119: 2.910135 | V119: 2.973297 | W119: 3.037762 | X119: 3.106765 | Y119: 3.169794 | Z119: 3.236824 | AA119: 3.314437 | AB119: 3.384014 | AC119: 3.449347 | AD119: 3.538665 | AE119: 3.618458 | AF119: 0.019025
...

Sheet AEO Table 3 2022
B1: ref2022.d011222a | C1: 2021 | D1: 2022 | E1: 2023 | F1: 2024 | G1: 2025 | H1: 2026 | I1: 2027 | J1: 2028 | K1: 2029 | L1: 2030 | M1: 2031 | N1: 2032 | O1: 2033 | P1: 2034 | Q1: 2035 | R1: 2036 | S1: 2037 | T1: 2038 | U1: 2039 | V1: 2040 | W1: 2041 | X1: 2042 | Y1: 2043 | Z1: 2044 | AA1: 2045 | AB1: 2046 | AC1: 2047 | AD1: 2048 | AE1: 2049 | AF1: 2050
C3: Report | D3: Annual Energy Outlook 2022
C4: Scenario | D4: ref2022 | G4: Reference
C5: Datekey | D5: d011222a
C6: Release Date | E6: March 2022
A10: PRC000 | B10: 3. Energy Prices by Sector and Source | AG10: Average
B11: (2021 dollars per million Btu, unless otherwise noted) | AG11: Annual
AG12: Change
B13: Sector and Source | C13: 2021 | D13: 2022 | E13: 2023 | F13: 2024 | G13: 2025 | H13: 2026 | I13: 2027 | J13: 2028 | K13: 2029 | L13: 2030 | M13: 2031 | N13: 2032 | O13: 2033 | P13: 2034 | Q13: 2035 | R13: 2036 | S13: 2037 | T13: 2038 | U13: 2039 | V13: 2040 | W13: 2041 | X13: 2042 | Y13: 2043 | Z13: 2044 | AA13: 2045 | AB13: 2046 | AC13: 2047 | AD13: 2048 | AE13: 2049 | AF13: 2050 | AG13: 2021–2050
B15: Residential
A16: PRC000:ba_LiquefiedPetr | B16: Propane | C16: 21.519539 | D16: 23.171989 | E16: 22.882879 | F16: 22.879547 | G16: 22.81468 | H16: 22.860277 | I16: 23.090302 | J16: 23.526861 | K16: 24.041061 | L16: 24.518085 | M16: 24.986616 | N16: 25.594236 | O16: 26.029459 | P16: 26.333237 | Q16: 26.526838 | R16: 26.637016 | S16: 26.823605 | T16: 27.044893 | U16: 27.215189 | V16: 27.495535 | W16: 27.787014 | X16: 28.060249 | Y16: 28.415535 | Z16: 28.739542 | AA16: 28.873835 | AB16: 28.852163 | AC16: 28.765711 | AD16: 28.699755 | AE16: 28.682411 | AF16: 28.628248 | AG16: 0.009891
A17: PRC000:ba_DistillateFue | B17: Distillate Fuel Oil | C17: 21.74482 | D17: 22.068129 | E17: 21.495361 | F17: 22.810974 | G17: 23.416267 | H17: 23.953699 | I17: 24.605654 | J17: 24.700975 | K17: 24.801643 | L17: 24.726501 | M17: 24.89443 | N17: 25.006918 | O17: 25.06778 | P17: 25.021008 | Q17: 25.012953 | R17: 25.030716 | S17: 25.173168 | T17: 25.266403 | U17: 25.26918 | V17: 25.488142 | W17: 25.65202 | X17: 25.722313 | Y17: 25.994267 | Z17: 26.257401 | AA17: 26.239376 | AB17: 26.421463 | AC17: 26.39146 | AD17: 26.301579 | AE17: 26.37286 | AF17: 26.23348 | AG17: 0.006492
A18: PRC000:ba_NaturalGas | B18: Natural Gas | C18: 11.714767 | D18: 12.151939 | E18: 11.530189 | F18: 11.049291 | G18: 10.738748 | H18: 10.557094 | I18: 10.430874 | J18: 10.569336 | K18: 10.733542 | L18: 10.824615 | M18: 10.916719 | N18: 11.249624 | O18: 11.388998 | P18: 11.442094 | Q18: 11.442281 | R18: 11.411037 | S18: 11.449186 | T18: 11.482208 | U18: 11.520953 | V18: 11.549916 | W18: 11.630534 | X18: 11.626328 | Y18: 11.591697 | Z18: 11.577318 | AA18: 11.548356 | AB18: 11.546086 | AC18: 11.550601 | AD18: 11.556095 | AE18: 11.593725 | AF18: 11.616578 | AG18: -0.00029
A19: PRC000:ba_Electricity | B19: Electricity | C19: 38.76239 | D19: 38.520023 | E19: 38.213291 | F19: 37.571396 | G19: 37.389545 | H19: 37.544312 | I19: 37.608688 | J19: 37.67712 | K19: 37.800606 | L19: 37.826485 | M19: 37.95697 | N19: 38.120724 | O19: 38.280704 | P19: 38.361744 | Q19: 38.052212 | R19: 37.810265 | S19: 37.659115 | T19: 37.508751 | U19: 37.363533 | V19: 37.418816 | W19: 37.32682 | X19: 37.339638 | Y19: 37.170746 | Z19: 37.042542 | AA19: 37.059158 | AB19: 36.817814 | AC19: 36.777477 | AD19: 36.656681 | AE19: 36.538506 | AF19: 36.290455 | AG19: -0.00227
B21: Commercial
A22: PRC000:ca_LiquefiedGas | B22: Propane | C22: 18.82229 | D22: 19.715876 | E22: 18.120464 | F22: 18.024939 | G22: 17.919872 | H22: 18.009079 | I22: 18.3034 | J22: 18.778172 | K22: 19.233488 | L22: 19.571339 | M22: 19.902462 | N22: 20.432222 | O22: 20.743967 | P22: 20.877277 | Q22: 20.929077 | R22: 20.949825 | S22: 21.118494 | T22: 21.305202 | U22: 21.400408 | V22: 21.663759 | W22: 21.891474 | X22: 22.078979 | Y22: 22.382664 | Z22: 22.604012 | AA22: 22.578735 | AB22: 22.440573 | AC22: 22.312597 | AD22: 22.263029 | AE22: 22.278421 | AF22: 22.221497 | AG22: 0.005741
A23: PRC000:ca_DistillateFue | B23: Distillate Fuel Oil | C23: 21.823187 | D23: 22.151241 | E23: 20.410337 | F23: 20.680359 | G23: 20.203226 | H23: 19.669413 | I23: 19.257957 | J23: 19.355928 | K23: 19.454554 | L23: 19.407745 | M23: 19.577158 | N23: 20.015388 | O23: 20.072495 | P23: 20.03583 | Q23: 20.077394 | R23: 20.092907 | S23: 20.242428 | T23: 20.340593 | U23: 20.341209 | V23: 20.574266 | W23: 20.738567 | X23: 20.811586 | Y23: 21.077398 | Z23: 21.340584 | AA23: 21.334831 | AB23: 21.519756 | AC23: 21.496529 | AD23: 21.407711 | AE23: 21.483562 | AF23: 21.350731 | AG23: -0.000754
A24: PRC000:ca_ResidualFuel | B24: Residual Fuel Oil | C24: 6.510058 | D24: 7.557132 | E24: 7.507626 | F24: 8.768214 | G24: 9.385942 | H24: 9.938887 | I24: 10.723703 | J24: 10.872849 | K24: 10.957002 | L24: 11.106604 | M24: 11.208329 | N24: 11.39804 | O24: 11.494227 | P24: 11.57103 | Q24: 11.59597 | R24: 11.640589 | S24: 11.60836 | T24: 11.717171 | U24: 11.650704 | V24: 12.228127 | W24: 12.351459 | X24: 12.376053 | Y24: 12.620767 | Z24: 12.870325 | AA24: 12.911318 | AB24: 13.078762 | AC24: 13.098419 | AD24: 13.071736 | AE24: 13.146095 | AF24: 13.070272 | AG24: 0.024325
A25: PRC000:ca_NaturalGas | B25: Natural Gas | C25: 8.442578 | D25: 8.81864 | E25: 8.497001 | F25: 8.180623 | G25: 8.017892 | H25: 7.970574 | I25: 7.962804 | J25: 8.083815 | K25: 8.223901 | L25: 8.293325 | M25: 8.363929 | N25: 8.57109 | O25: 8.670591 | P25: 8.698514 | Q25: 8.671237 | R25: 8.627092 | S25: 8.651712 | T25: 8.673417 | U25: 8.701211 | V25: 8.720324 | W25: 8.789293 | X25: 8.774185 | Y25: 8.728896 | Z25: 8.705806 | AA25: 8.668962 | AB25: 8.657973 | AC25: 8.654889 | AD25: 8.653486 | AE25: 8.683637 | AF25: 8.700233 | AG25: 0.001037
A26: PRC000:ca_Electricity | B26: Electricity | C26: 33.23053 | D26: 32.918514 | E26: 32.008312 | F26: 31.329121 | G26: 31.108648 | H26: 31.226942 | I26: 31.192585 | J26: 31.205448 | K26: 31.239994 | L26: 31.164198 | M26: 31.207338 | N26: 31.252337 | O26: 31.384094 | P26: 31.392914 | Q26: 31.002916 | R26: 30.702438 | S26: 30.551657 | T26: 30.342772 | U26: 30.176033 | V26: 30.204935 | W26: 30.056618 | X26: 30.057528 | Y26: 29.873531 | Z26: 29.691975 | AA26: 29.655783 | AB26: 29.391348 | AC26: 29.304863 | AD26: 29.157902 | AE26: 29.036934 | AF26: 28.768715 | AG26: -0.004959
B28: Industrial 1/
A29: PRC000:da_LiquefiedPetr | B29: Propane | C29: 13.663833 | D29: 14.357594 | E29: 12.540752 | F29: 12.504602 | G29: 12.409207 | H29: 12.512104 | I29: 12.822186 | J29: 13.316794 | K29: 13.784143 | L29: 14.126072 | M29: 14.469291 | N29: 14.76237 | O29: 15.093699 | P29: 15.225082 | Q29: 15.235613 | R29: 15.257844 | S29: 15.447799 | T29: 15.651039 | U29: 15.74879 | V29: 16.04315 | W29: 16.289669 | X29: 16.49139 | Y29: 16.830481 | Z29: 17.069897 | AA29: 17.026379 | AB29: 16.866844 | AC29: 16.727716 | AD29: 16.679976 | AE29: 16.703079 | AF29: 16.638475 | AG29: 0.006815
A30: PRC000:da_DistillateFue | B30: Distillate Fuel Oil | C30: 21.75238 | D30: 22.07209 | E30: 20.410429 | F30: 20.646559 | G30: 20.162947 | H30: 19.615082 | I30: 19.183277 | J30: 19.286734 | K30: 19.397879 | L30: 19.367228 | M30: 19.537781 | N30: 19.664978 | O30: 19.740728 | P30: 19.7083 | Q30: 19.713743 | R30: 19.732658 | S30: 19.883741 | T30: 19.985138 | U30: 19.992161 | V30: 20.237799 | W30: 20.408806 | X30: 20.488091 | Y30: 20.759394 | Z30: 21.023619 | AA30: 21.028748 | AB30: 21.221027 | AC30: 21.206429 | AD30: 21.123951 | AE30: 21.206486 | AF30: 21.081644 | AG30: -0.001079
A31: PRC000:da_ResidualFuel | B31: Residual Fuel Oil | C31: 7.09223 | D31: 8.293962 | E31: 8.453308 | F31: 9.941956 | G31: 10.752403 | H31: 11.551449 | I31: 12.545612 | J31: 12.71112 | K31: 12.829576 | L31: 12.988939 | M31: 13.118169 | N31: 13.329255 | O31: 13.446094 | P31: 13.510265 | Q31: 13.572783 | R31: 13.618667 | S31: 13.563599 | T31: 13.682616 | U31: 13.633999 | V31: 14.207245 | W31: 14.34065 | X31: 14.376684 | Y31: 14.61781 | Z31: 14.86674 | AA31: 14.907736 | AB31: 15.082319 | AC31: 15.10018 | AD31: 15.080288 | AE31: 15.156901 | AF31: 15.086491 | AG31: 0.026369
A32: PRC000:da_NaturalGas | B32: Natural Gas 2/ | C32: 5.071276 | D32: 4.843464 | E32: 4.512031 | F32: 4.155407 | G32: 3.980554 | H32: 3.926305 | I32: 3.957039 | J32: 4.114555 | K32: 4.261919 | L32: 4.348165 | M32: 4.405538 | N32: 4.405082 | O32: 4.501796 | P32: 4.506782 | Q32: 4.436007 | R32: 4.385244 | S32: 4.383933 | T32: 4.405835 | U32: 4.426479 | V32: 4.448872 | W32: 4.503239 | X32: 4.510521 | Y32: 4.447511 | Z32: 4.412628 | AA32: 4.339705 | AB32: 4.309629 | AC32: 4.291151 | AD32: 4.285682 | AE32: 4.295768 | AF32: 4.30372 | AG32: -0.005643
A33: PRC000:da_Metallurgical | B33: Metallurgical Coal | C33: 3.927859 | D33: 3.518811 | E33: 3.347698 | F33: 3.188333 | G33: 3.098164 | H33: 3.037497 | I33: 3.009427 | J33: 3.004971 | K33: 3.016198 | L33: 3.040812 | M33: 3.063208 | N33: 3.094111 | O33: 3.112654 | P33: 3.12921 | Q33: 3.151268 | R33: 3.173285 | S33: 3.199473 | T33: 3.221655 | U33: 3.243439 | V33: 3.268032 | W33: 3.287717 | X33: 3.306536 | Y33: 3.33003 | Z33: 3.356462 | AA33: 3.383151 | AB33: 3.410095 | AC33: 3.436724 | AD33: 3.458919 | AE33: 3.483504 | AF33: 3.508619 | AG33: -0.003885
A34: PRC000:da_SteamCoal | B34: Other Industrial Coal | C34: 2.729489 | D34: 2.681275 | E34: 2.690543 | F34: 2.694087 | G34: 2.695647 | H34: 2.689396 | I34: 2.677643 | J34: 2.675602 | K34: 2.675394 | L34: 2.676888 | M34: 2.677192 | N34: 2.681719 | O34: 2.687179 | P34: 2.68689 | Q34: 2.675991 | R34: 2.671342 | S34: 2.666051 | T34: 2.66399 | U34: 2.670385 | V34: 2.672748 | W34: 2.678431 | X34: 2.677164 | Y34: 2.67528 | Z34: 2.679811 | AA34: 2.682535 | AB34: 2.685032 | AC34: 2.684788 | AD34: 2.68338 | AE34: 2.684288 | AF34: 2.68431 | AG34: -0.000575
A35: PRC000:da_CoaltoLiquids | B35: Coal to Liquids | C35: -- | D35: -- | E35: -- | F35: -- | G35: -- | H35: -- | I35: -- | J35: -- | K35: -- | L35: -- | M35: -- | N35: -- | O35: -- | P35: -- | Q35: -- | R35: -- | S35: -- | T35: -- | U35: -- | V35: -- | W35: -- | X35: -- | Y35: -- | Z35: -- | AA35: -- | AB35: -- | AC35: -- | AD35: -- | AE35: -- | AF35: -- | AG35: --
A36: PRC000:da_Electricity | B36: Electricity | C36: 21.954327 | D36: 21.585382 | E36: 20.592312 | F36: 19.991262 | G36: 19.767326 | H36: 19.610733 | I36: 19.56032 | J36: 19.572056 | K36: 19.607359 | L36: 19.590822 | M36: 19.607412 | N36: 19.627659 | O36: 19.631359 | P36: 19.629396 | Q36: 19.42919 | R36: 19.290569 | S36: 19.131826 | T36: 19.040081 | U36: 18.93644 | V36: 18.923027 | W36: 18.863256 | X36: 18.807621 | Y36: 18.641674 | Z36: 18.541803 | AA36: 18.475939 | AB36: 18.302622 | AC36: 18.235422 | AD36: 18.142365 | AE36: 18.062515 | AF36: 17.956863 | AG36: -0.006907
B38: Transportation
A39: PRC000:ea_LiquefiedPetr | B39: Propane | C39: 17.771591 | D39: 18.268835 | E39: 16.727415 | F39: 16.714048 | G39: 16.63475 | H39: 16.724779 | I39: 16.989109 | J39: 17.403635 | K39: 17.787142 | L39: 18.062943 | M39: 18.338911 | N39: 18.912962 | O39: 19.174692 | P39: 19.274258 | Q39: 19.327059 | R39: 19.342785 | S39: 19.492384 | T39: 19.649984 | U39: 19.722977 | V39: 19.951733 | W39: 20.139431 | X39: 20.291405 | Y39: 20.549433 | Z39: 20.727776 | AA39: 20.689186 | AB39: 20.564272 | AC39: 20.45661 | AD39: 20.419739 | AE39: 20.436655 | AF39: 20.384317 | AG39: 0.004741
A40: PRC000:ea_Ethanol(E85) | B40: E85 3/ | C40: 25.787903 | D40: 25.761244 | E40: 25.495865 | F40: 25.212345 | G40: 24.975626 | H40: 25.043127 | I40: 25.355228 | J40: 25.594719 | K40: 25.777565 | L40: 26.200195 | M40: 26.276876 | N40: 27.198093 | O40: 27.413271 | P40: 27.550776 | Q40: 27.680271 | R40: 27.711462 | S40: 27.855463 | T40: 28.059765 | U40: 28.008661 | V40: 28.442335 | W40: 28.682402 | X40: 28.964655 | Y40: 29.315157 | Z40: 29.494404 | AA40: 29.595737 | AB40: 29.879946 | AC40: 29.952457 | AD40: 30.036066 | AE40: 30.150232 | AF40: 29.900158 | AG40: 0.005115
A41: PRC000:ea_MotorGasoline | B41: Motor Gasoline 4/ | C41: 25.885534 | D41: 24.823555 | E41: 21.931265 | F41: 21.752617 | G41: 21.573097 | H41: 21.630323 | I41: 21.882795 | J41: 22.068708 | K41: 22.206301 | L41: 22.537537 | M41: 22.59231 | N41: 23.553766 | O41: 23.718866 | P41: 23.814569 | Q41: 23.936171 | R41: 23.943441 | S41: 24.047487 | T41: 24.204655 | U41: 24.154181 | V41: 24.491938 | W41: 24.685377 | X41: 24.854437 | Y41: 25.146194 | Z41: 25.343546 | AA41: 25.424524 | AB41: 25.671301 | AC41: 25.718651 | AD41: 25.792084 | AE41: 25.879534 | AF41: 25.666084 | AG41: -0.000294
A42: PRC000:ea_JetFuel | B42: Jet Fuel 5/ | C42: 14.720805 | D42: 15.38822 | E42: 14.073745 | F42: 15.179766 | G42: 15.292542 | H42: 15.463751 | I42: 15.70466 | J42: 15.898726 | K42: 16.05232 | L42: 16.046509 | M42: 16.330721 | N42: 16.697517 | O42: 16.757906 | P42: 16.780107 | Q42: 16.810595 | R42: 16.876972 | S42: 17.097425 | T42: 17.235626 | U42: 17.279207 | V42: 17.533007 | W42: 17.728834 | X42: 17.813095 | Y42: 18.115818 | Z42: 18.40634 | AA42: 18.427332 | AB42: 18.612141 | AC42: 18.622166 | AD42: 18.579237 | AE42: 18.690105 | AF42: 18.608126 | AG42: 0.008113
A43: PRC000:ea_DistillateFue | B43: Diesel Fuel (distillate fuel oil) 6/ | C43: 23.750263 | D43: 22.843327 | E43: 21.93634 | F43: 22.651623 | G43: 22.721119 | H43: 22.675623 | I43: 22.731689 | J43: 22.822958 | K43: 22.936224 | L43: 22.910614 | M43: 23.069981 | N43: 23.535149 | O43: 23.617865 | P43: 23.558996 | Q43: 23.605259 | R43: 23.598024 | S43: 23.764229 | T43: 23.864792 | U43: 23.869284 | V43: 24.107859 | W43: 24.278906 | X43: 24.369808 | Y43: 24.638464 | Z43: 24.907894 | AA43: 24.912159 | AB43: 25.116587 | AC43: 25.106068 | AD43: 25.002657 | AE43: 25.088144 | AF43: 24.951025 | AG43: 0.001702
A44: PRC000:ea_ResidualFuel | B44: Residual Fuel Oil | C44: 12.357966 | D44: 10.441763 | E44: 12.662357 | F44: 13.544412 | G44: 13.756763 | H44: 13.919001 | I44: 14.270379 | J44: 14.384391 | K44: 14.458046 | L44: 14.603832 | M44: 14.679204 | N44: 14.933182 | O44: 15.015419 | P44: 15.044872 | Q44: 15.107331 | R44: 15.142351 | S44: 15.144779 | T44: 15.235153 | U44: 15.196106 | V44: 15.646362 | W44: 15.738945 | X44: 15.785649 | Y44: 15.987934 | Z44: 16.203949 | AA44: 16.243937 | AB44: 16.391148 | AC44: 16.410231 | AD44: 16.386232 | AE44: 16.43816 | AF44: 16.369478 | AG44: 0.009741
A45: PRC000:ea_NaturalGas | B45: Natural Gas 7/ | C45: 14.654003 | D45: 14.619699 | E45: 13.872672 | F45: 13.306766 | G45: 12.89931 | H45: 12.541728 | I45: 12.263359 | J45: 12.130099 | K45: 12.005839 | L45: 11.846902 | M45: 11.685585 | N45: 12.332364 | O45: 12.244666 | P45: 12.103299 | Q45: 11.998527 | R45: 11.817566 | S45: 11.702035 | T45: 11.61793 | U45: 11.537097 | V45: 11.515666 | W45: 11.50357 | X45: 11.440135 | Y45: 11.341637 | Z45: 11.270406 | AA45: 11.16805 | AB45: 11.113301 | AC45: 11.064749 | AD45: 11.018502 | AE45: 10.993929 | AF45: 10.952426 | AG45: -0.00999
A46: PRC000:ea_Electricity | B46: Electricity | C46: 39.115726 | D46: 39.616028 | E46: 38.115593 | F46: 37.093182 | G46: 37.086498 | H46: 37.542118 | I46: 37.558929 | J46: 37.560974 | K46: 37.509598 | L46: 37.302563 | M46: 37.30394 | N46: 37.330086 | O46: 37.461796 | P46: 37.336975 | Q46: 36.881054 | R46: 36.467251 | S46: 36.202427 | T46: 35.905403 | U46: 35.639503 | V46: 35.46138 | W46: 35.281731 | X46: 35.079762 | Y46: 34.771469 | Z46: 34.571163 | AA46: 34.483639 | AB46: 34.241879 | AC46: 34.021767 | AD46: 33.821972 | AE46: 33.614403 | AF46: 33.397739 | AG46: -0.005435
B48: Electric Power 8/
A49: PRC000:ga_DistillateFue | B49: Distillate Fuel Oil | C49: 21.749472 | D49: 22.063303 | E49: 20.153975 | F49: 20.553831 | G49: 19.961508 | H49: 19.321976 | I49: 18.867052 | J49: 18.963041 | K49: 19.071278 | L49: 19.038746 | M49: 19.098368 | N49: 19.294424 | O49: 19.321995 | P49: 19.367441 | Q49: 19.355671 | R49: 19.394863 | S49: 19.574009 | T49: 19.640402 | U49: 19.645767 | V49: 19.901247 | W49: 20.06513 | X49: 20.117165 | Y49: 20.384939 | Z49: 20.628145 | AA49: 20.629406 | AB49: 20.826429 | AC49: 20.826172 | AD49: 20.740261 | AE49: 20.844084 | AF49: 20.736099 | AG49: -0.001644
A50: PRC000:ga_ResidualFuel | B50: Residual Fuel Oil | C50: 13.006465 | D50: 13.345431 | E50: 12.638397 | F50: 13.540524 | G50: 13.744135 | H50: 13.901823 | I50: 14.324615 | J50: 14.413228 | K50: 14.473246 | L50: 14.597926 | M50: 14.66163 | N50: 14.952104 | O50: 15.023062 | P50: 15.028744 | Q50: 15.100775 | R50: 15.121873 | S50: 15.147896 | T50: 15.209865 | U50: 15.144525 | V50: 15.53472 | W50: 15.481628 | X50: 15.415256 | Y50: 15.467604 | Z50: 15.479861 | AA50: 15.233349 | AB50: 15.422539 | AC50: 15.494015 | AD50: 15.477424 | AE50: 15.574907 | AF50: 15.574647 | AG50: 0.006233
A51: PRC000:ga_NaturalGas | B51: Natural Gas | C51: 5.157501 | D51: 4.041245 | E51: 3.758129 | F51: 3.430388 | G51: 3.266725 | H51: 3.232515 | I51: 3.270525 | J51: 3.439616 | K51: 3.567562 | L51: 3.640071 | M51: 3.682663 | N51: 3.699922 | O51: 3.792077 | P51: 3.7758 | Q51: 3.673566 | R51: 3.626955 | S51: 3.621633 | T51: 3.644042 | U51: 3.668771 | V51: 3.703752 | W51: 3.75456 | X51: 3.753616 | Y51: 3.678001 | Z51: 3.641202 | AA51: 3.570948 | AB51: 3.545763 | AC51: 3.530404 | AD51: 3.534259 | AE51: 3.53999 | AF51: 3.56578 | AG51: -0.012646
A52: PRC000:ga_SteamCoal | B52: Steam Coal | C52: 2.11768 | D52: 2.002686 | E52: 2.003769 | F52: 2.008078 | G52: 1.956206 | H52: 1.931614 | I52: 1.916737 | J52: 1.908257 | K52: 1.920629 | L52: 1.917488 | M52: 1.911739 | N52: 1.90225 | O52: 1.895574 | P52: 1.892647 | Q52: 1.86805 | R52: 1.856108 | S52: 1.853899 | T52: 1.847783 | U52: 1.844928 | V52: 1.844842 | W52: 1.846852 | X52: 1.828859 | Y52: 1.824401 | Z52: 1.81727 | AA52: 1.811768 | AB52: 1.808238 | AC52: 1.797737 | AD52: 1.78178 | AE52: 1.777986 | AF52: 1.775739 | AG52: -0.006054
A53: PRC000:ga_uranium | B53: Uranium | C53: 0.717811 | D53: 0.718863 | E53: 0.720964 | F53: 0.722015 | G53: 0.724117 | H53: 0.725168 | I53: 0.72727 | J53: 0.728321 | K53: 0.730423 | L53: 0.732525 | M53: 0.733576 | N53: 0.735678 | O53: 0.73778 | P53: 0.738831 | Q53: 0.740933 | R53: 0.743035 | S53: 0.744086 | T53: 0.746188 | U53: 0.74829 | V53: 0.750391 | W53: 0.752494 | X53: 0.754595 | Y53: 0.756697 | Z53: 0.758799 | AA53: 0.760901 | AB53: 0.763003 | AC53: 0.765105 | AD53: 0.767207 | AE53: 0.769309 | AF53: 0.771411 | AG53: 0.002486
B56: Average Price to All Users 9/
A57: PRC000:ha_LiquefiedPetr | B57: Propane | C57: 19.520824 | D57: 20.92996 | E57: 20.082417 | F57: 20.050674 | G57: 19.965826 | H57: 20.02533 | I57: 20.268194 | J57: 20.706121 | K57: 21.177542 | L57: 21.577402 | M57: 21.969906 | N57: 22.476595 | O57: 22.83824 | P57: 23.050047 | Q57: 23.159853 | R57: 23.215166 | S57: 23.376358 | T57: 23.562716 | U57: 23.67705 | V57: 23.936489 | W57: 24.185408 | X57: 24.404106 | Y57: 24.725622 | Z57: 24.990145 | AA57: 25.032494 | AB57: 24.937096 | AC57: 24.814219 | AD57: 24.741323 | AE57: 24.724777 | AF57: 24.650307 | AG57: 0.008078
A58: PRC000:ha_Ethanol(E85) | B58: E85 3/ | C58: 25.787903 | D58: 25.761244 | E58: 25.495865 | F58: 25.212345 | G58: 24.975626 | H58: 25.043127 | I58: 25.355228 | J58: 25.594719 | K58: 25.777565 | L58: 26.200195 | M58: 26.276876 | N58: 27.198093 | O58: 27.413271 | P58: 27.550776 | Q58: 27.680271 | R58: 27.711462 | S58: 27.855463 | T58: 28.059765 | U58: 28.008661 | V58: 28.442335 | W58: 28.682402 | X58: 28.964655 | Y58: 29.315157 | Z58: 29.494404 | AA58: 29.595737 | AB58: 29.879946 | AC58: 29.952457 | AD58: 30.036066 | AE58: 30.150232 | AF58: 29.900158 | AG58: 0.005115
A59: PRC000:ha_MotorGasoline | B59: Motor Gasoline 4/ | C59: 25.875973 | D59: 24.818628 | E59: 21.957455 | F59: 21.790281 | G59: 21.608536 | H59: 21.654921 | I59: 21.892027 | J59: 22.07807 | K59: 22.215803 | L59: 22.54702 | M59: 22.602013 | N59: 23.561117 | O59: 23.726307 | P59: 23.822149 | Q59: 23.943626 | R59: 23.951033 | S59: 24.055145 | T59: 24.212412 | U59: 24.161999 | V59: 24.499897 | W59: 24.693489 | X59: 24.862711 | Y59: 25.154669 | Z59: 25.352127 | AA59: 25.433323 | AB59: 25.680344 | AC59: 25.727892 | AD59: 25.801403 | AE59: 25.888937 | AF59: 25.675623 | AG59: -0.000268
A60: PRC000:ha_JetFuel | B60: Jet Fuel 5/ | C60: 14.720805 | D60: 15.38822 | E60: 14.073745 | F60: 15.179766 | G60: 15.292542 | H60: 15.463751 | I60: 15.70466 | J60: 15.898726 | K60: 16.05232 | L60: 16.046509 | M60: 16.330721 | N60: 16.697517 | O60: 16.757906 | P60: 16.780107 | Q60: 16.810595 | R60: 16.876972 | S60: 17.097425 | T60: 17.235626 | U60: 17.279207 | V60: 17.533007 | W60: 17.728834 | X60: 17.813095 | Y60: 18.115818 | Z60: 18.40634 | AA60: 18.427332 | AB60: 18.612141 | AC60: 18.622166 | AD60: 18.579237 | AE60: 18.690105 | AF60: 18.608126 | AG60: 0.008113
A61: PRC000:ha_DistillateFue | B61: Distillate Fuel Oil | C61: 23.276806 | D61: 22.657784 | E61: 21.509951 | F61: 22.159214 | G61: 22.12748 | H61: 22.01108 | I61: 22.010616 | J61: 22.090155 | K61: 22.191229 | L61: 22.147449 | M61: 22.299383 | N61: 22.668865 | O61: 22.730412 | P61: 22.678328 | Q61: 22.711632 | R61: 22.719547 | S61: 22.852823 | T61: 22.942526 | U61: 22.941147 | V61: 23.172098 | W61: 23.334955 | X61: 23.412827 | Y61: 23.677961 | Z61: 23.933039 | AA61: 23.931978 | AB61: 24.119179 | AC61: 24.097599 | AD61: 24.005205 | AE61: 24.077518 | AF61: 23.943972 | AG61: 0.000975
A62: PRC000:ha_ResidualFuel | B62: Residual Fuel Oil | C62: 12.032716 | D62: 10.461782 | E62: 12.369011 | F62: 13.310703 | G62: 13.567265 | H62: 13.763799 | I62: 14.156386 | J62: 14.267786 | K62: 14.339729 | L62: 14.481854 | M62: 14.557441 | N62: 14.810274 | O62: 14.891078 | P62: 14.92039 | Q62: 14.983093 | R62: 15.017566 | S62: 15.015263 | T62: 15.104892 | U62: 15.061521 | V62: 15.516302 | W62: 15.603861 | X62: 15.644531 | Y62: 15.845129 | Z62: 16.058098 | AA62: 16.091763 | AB62: 16.24157 | AC62: 16.261566 | AD62: 16.237041 | AE62: 16.292362 | AF62: 16.22451 | AG62: 0.01036
A63: PRC000:ha_NaturalGas | B63: Natural Gas | C63: 6.727046 | D63: 6.398545 | E63: 6.007559 | F63: 5.653534 | G63: 5.487725 | H63: 5.429889 | I63: 5.454965 | J63: 5.59216 | K63: 5.741125 | L63: 5.837134 | M63: 5.907144 | N63: 6.005502 | O63: 6.090653 | P63: 6.117626 | Q63: 6.076823 | R63: 6.04059 | S63: 6.036061 | T63: 6.044491 | U63: 6.054013 | V63: 6.068184 | W63: 6.11861 | X63: 6.106076 | Y63: 6.030046 | Z63: 5.991965 | AA63: 5.9233 | AB63: 5.887187 | AC63: 5.860796 | AD63: 5.847686 | AE63: 5.85101 | AF63: 5.847811 | AG63: -0.004818
A64: PRC000:ha_Metallugical | B64: Metallurgical Coal | C64: 3.927859 | D64: 3.518811 | E64: 3.347698 | F64: 3.188333 | G64: 3.098164 | H64: 3.037497 | I64: 3.009427 | J64: 3.004971 | K64: 3.016198 | L64: 3.040812 | M64: 3.063208 | N64: 3.094111 | O64: 3.112654 | P64: 3.12921 | Q64: 3.151268 | R64: 3.173285 | S64: 3.199473 | T64: 3.221655 | U64: 3.243439 | V64: 3.268032 | W64: 3.287717 | X64: 3.306536 | Y64: 3.33003 | Z64: 3.356462 | AA64: 3.383151 | AB64: 3.410095 | AC64: 3.436724 | AD64: 3.458919 | AE64: 3.483504 | AF64: 3.508619 | AG64: -0.003885
A65: PRC000:ha_Coal | B65: Other Coal | C65: 2.151859 | D65: 2.041804 | E65: 2.044459 | F65: 2.05539 | G65: 2.009318 | H65: 1.987594 | I65: 1.974667 | J65: 1.966878 | K65: 1.978533 | L65: 1.976764 | M65: 1.971833 | N65: 1.964469 | O65: 1.958048 | P65: 1.957809 | Q65: 1.937612 | R65: 1.927672 | S65: 1.926794 | T65: 1.921452 | U65: 1.920618 | V65: 1.921497 | W65: 1.924581 | X65: 1.908737 | Y65: 1.905591 | Z65: 1.900162 | AA65: 1.896935 | AB65: 1.894529 | AC65: 1.886219 | AD65: 1.872889 | AE65: 1.869953 | AF65: 1.866915 | AG65: -0.004886
A66: PRC000:ha_CoaltoLiquids | B66: Coal to Liquids | C66: -- | D66: -- | E66: -- | F66: -- | G66: -- | H66: -- | I66: -- | J66: -- | K66: -- | L66: -- | M66: -- | N66: -- | O66: -- | P66: -- | Q66: -- | R66: -- | S66: -- | T66: -- | U66: -- | V66: -- | W66: -- | X66: -- | Y66: -- | Z66: -- | AA66: -- | AB66: -- | AC66: -- | AD66: -- | AE66: -- | AF66: -- | AG66: --
A67: PRC000:ha_Electricity | B67: Electricity | C67: 32.508968 | D67: 32.166168 | E67: 31.513943 | F67: 30.893538 | G67: 30.700684 | H67: 30.778042 | I67: 30.796724 | J67: 30.842819 | K67: 30.930162 | L67: 30.923807 | M67: 31.010801 | N67: 31.099874 | O67: 31.225035 | P67: 31.281097 | Q67: 30.992538 | R67: 30.775299 | S67: 30.640684 | T67: 30.502256 | U67: 30.375847 | V67: 30.421076 | W67: 30.332275 | X67: 30.332272 | Y67: 30.166447 | Z67: 30.047379 | AA67: 30.044783 | AB67: 29.821831 | AC67: 29.770481 | AD67: 29.670555 | AE67: 29.580069 | AF67: 29.370739 | AG67: -0.003494
B69: Non-Renewable Energy Expenditures by Sector
B70: (billion 2021 dollars)
A71: PRC000:ia_Residential | B71: Residential | C71: 275.19543 | D71: 274.69827 | E71: 272.04227 | F71: 268.02911 | G71: 266.8042 | H71: 267.53424 | I71: 267.90832 | J71: 269.61636 | K71: 271.74518 | L71: 272.91385 | M71: 274.75326 | N71: 278.11163 | O71: 280.4754 | P71: 281.95062 | Q71: 281.42996 | R71: 281.35779 | S71: 282.30389 | T71: 283.22006 | U71: 284.15469 | V71: 286.06439 | W71: 287.36847 | X71: 288.87006 | Y71: 289.41064 | Z71: 290.36166 | AA71: 291.91492 | AB71: 292.26712 | AC71: 293.7171 | AD71: 294.71783 | AE71: 295.96994 | AF71: 296.49973 | AG71: 0.002575
A72: PRC000:ia_Commercial | B72: Commercial | C72: 198.23921 | D72: 201.05307 | E72: 194.74181 | F72: 190.23673 | G72: 188.21303 | H72: 187.65823 | I72: 187.63826 | J72: 188.45783 | K72: 189.38261 | L72: 189.44869 | M72: 190.23714 | N72: 192.08362 | O72: 193.46835 | P72: 194.11852 | Q72: 193.13898 | R72: 192.45633 | S72: 192.71271 | T72: 192.80084 | U72: 192.95999 | V72: 194.02557 | W72: 194.53627 | X72: 195.41013 | Y72: 195.60156 | Z72: 195.9108 | AA72: 196.69556 | AB72: 196.62048 | AC72: 197.383 | AD72: 197.89435 | AE72: 198.69301 | AF72: 198.65846 | AG72: 7.3e-05
A73: PRC000:ia_Industrial | B73: Industrial 1/ | C73: 208.20412 | D73: 210.05396 | E73: 199.0141 | F73: 195.01041 | G73: 193.97601 | H73: 194.498 | I73: 196.37509 | J73: 201.22051 | K73: 205.68648 | L73: 208.69907 | M73: 212.24527 | N73: 216.80934 | O73: 221.01056 | P73: 221.60986 | Q73: 220.98859 | R73: 220.6508 | S73: 222.12486 | T73: 224.47987 | U73: 225.4944 | V73: 228.34744 | W73: 231.27826 | X73: 233.87386 | Y73: 235.76959 | Z73: 236.9698 | AA73: 236.51178 | AB73: 237.4744 | AC73: 237.51184 | AD73: 236.39203 | AE73: 236.96558 | AF73: 238.35934 | AG73: 0.004675
A74: PRC000:ia_Transportatio | B74: Transportation | C74: 609.53595 | D74: 598.28845 | E74: 547.89264 | F74: 551.61621 | G74: 547.54291 | H74: 545.69781 | I74: 546.7984 | J74: 547.26239 | K74: 546.77887 | L74: 548.69134 | M74: 548.89294 | N74: 565.02356 | O74: 565.95117 | P74: 564.18976 | Q74: 563.7074 | R74: 561.88098 | S74: 563.49658 | T74: 565.8255 | U74: 565.11725 | V74: 572.72223 | W74: 577.58527 | X74: 581.76526 | Y74: 589.78558 | Z74: 596.39648 | AA74: 599.4906 | AB74: 607.73554 | AC74: 611.27429 | AD74: 614.31207 | AE74: 619.45441 | AF74: 619.66425 | AG74: 0.000568
A75: PRC000:ia_TotalNon-Rene | B75: Total Non-Renewable Expenditures | C75: 1291.1747 | D75: 1284.0938 | E75: 1213.6908 | F75: 1204.8925 | G75: 1196.5361 | H75: 1195.3883 | I75: 1198.72 | J75: 1206.5571 | K75: 1213.5931 | L75: 1219.7529 | M75: 1226.1287 | N75: 1252.0281 | O75: 1260.9055 | P75: 1261.8688 | Q75: 1259.2649 | R75: 1256.3459 | S75: 1260.6381 | T75: 1266.3263 | U75: 1267.7263 | V75: 1281.1597 | W75: 1290.7683 | X75: 1299.9193 | Y75: 1310.5674 | Z75: 1319.6387 | AA75: 1324.6128 | AB75: 1334.0975 | AC75: 1339.8862 | AD75: 1343.3163 | AE75: 1351.083 | AF75: 1353.1819 | AG75: 0.001619
A76: PRC000:ja_Transportatio | B76: Transportation Renewable Expenditures | C76: 0.793518 | D76: 0.855206 | E76: 0.882733 | F76: 0.86548 | G76: 0.844213 | H76: 0.825758 | I76: 0.80896 | J76: 0.789201 | K76: 0.767372 | L76: 0.751337 | M76: 0.727102 | N76: 0.724035 | O76: 0.705781 | P76: 0.686639 | Q76: 0.670417 | R76: 0.655405 | S76: 0.646374 | T76: 0.641782 | U76: 0.638807 | V76: 0.645006 | W76: 0.650856 | X76: 0.650637 | Y76: 0.662279 | Z76: 0.680016 | AA76: 0.689701 | AB76: 0.704812 | AC76: 0.715713 | AD76: 0.729132 | AE76: 0.742763 | AF76: 0.751202 | AG76: -0.001888
A77: PRC000:ja_TotalExpendit | B77: Total Expenditures | C77: 1291.9681 | D77: 1284.949 | E77: 1214.5735 | F77: 1205.7579 | G77: 1197.3804 | H77: 1196.2141 | I77: 1199.5289 | J77: 1207.3463 | K77: 1214.3605 | L77: 1220.5043 | M77: 1226.8557 | N77: 1252.7521 | O77: 1261.6113 | P77: 1262.5554 | Q77: 1259.9353 | R77: 1257.0013 | S77: 1261.2844 | T77: 1266.968 | U77: 1268.3651 | V77: 1281.8047 | W77: 1291.4192 | X77: 1300.5699 | Y77: 1311.2296 | Z77: 1320.3187 | AA77: 1325.3025 | AB77: 1334.8024 | AC77: 1340.6019 | AD77: 1344.0454 | AE77: 1351.8258 | AF77: 1353.9331 | AG77: 0.001617
B80: Prices in Nominal Dollars
B81: Residential
A82: PRC000:nom_R_LiquefiedP | B82: Propane | C82: 21.519539 | D82: 23.918144 | E82: 24.217051 | F82: 24.935791 | G82: 25.653114 | H82: 26.580561 | I82: 27.797075 | J82: 29.328686 | K82: 31.014244 | L82: 32.694023 | M82: 34.429127 | N82: 36.408802 | O82: 38.23621 | P82: 39.975243 | Q82: 41.643776 | R82: 43.255379 | S82: 45.06881 | T82: 47.014851 | U82: 48.922707 | V82: 51.130653 | W82: 53.447807 | X82: 55.830475 | Y82: 58.463219 | Z82: 61.121395 | AA82: 63.463867 | AB82: 65.540504 | AC82: 67.531944 | AD82: 69.613518 | AE82: 71.843872 | AF82: 74.008057 | AG82: 0.043514
A83: PRC000:nom_R_Distillate | B83: Distillate Fuel Oil | C83: 21.74482 | D83: 22.778738 | E83: 22.748636 | F83: 24.861053 | G83: 26.329546 | H83: 27.851925 | I83: 29.621317 | J83: 30.792341 | K83: 31.995436 | L83: 32.971935 | M83: 34.302105 | N83: 35.573318 | O83: 36.823544 | P83: 37.983208 | Q83: 39.267166 | R83: 40.646938 | S83: 42.295757 | T83: 43.923122 | U83: 45.424511 | V83: 47.397709 | W83: 49.341187 | X83: 51.178768 | Y83: 53.481609 | Z83: 55.842537 | AA83: 57.673405 | AB83: 60.018929 | AC83: 61.958023 | AD83: 63.796551 | AE83: 66.058899 | AF83: 67.817245 | AG83: 0.040001
A84: PRC000:nom_R_NaturalGas | B84: Natural Gas | C84: 11.714767 | D84: 12.543241 | E84: 12.202449 | F84: 12.042318 | G84: 12.074784 | H84: 12.275156 | I84: 12.557124 | J84: 13.175778 | K84: 13.846839 | L84: 14.43425 | M84: 15.042178 | N84: 16.003031 | O84: 16.729973 | P84: 17.369701 | Q84: 17.962931 | R84: 18.53018 | S84: 19.236832 | T84: 19.960674 | U84: 20.710352 | V84: 21.478207 | W84: 22.371119 | X84: 23.13249 | Y84: 23.849205 | Z84: 24.621889 | AA84: 25.382959 | AB84: 26.228062 | AC84: 27.116817 | AD84: 28.030218 | AE84: 29.04003 | AF84: 30.030491 | AG84: 0.032993
A85: PRC000:nom_R_Electricit | B85: Electricity | C85: 38.76239 | D85: 39.760395 | E85: 40.441296 | F85: 40.948036 | G85: 42.041279 | H85: 43.654278 | I85: 45.274918 | J85: 46.968456 | K85: 48.764786 | L85: 50.440311 | M85: 52.301014 | N85: 54.228222 | O85: 56.232788 | P85: 58.235149 | Q85: 59.737148 | R85: 61.399422 | S85: 63.274548 | T85: 65.205223 | U85: 67.165619 | V85: 69.583977 | W85: 71.797447 | X85: 74.293343 | Y85: 76.476524 | Z85: 78.779671 | AA85: 81.454979 | AB85: 83.635262 | AC85: 86.340797 | AD85: 88.913673 | AE85: 91.521866 | AF85: 93.815933 | AG85: 0.030948
B87: Commercial
A88: PRC000:nom_C_LiquefiedG | B88: Propane | C88: 18.82229 | D88: 20.35074 | E88: 19.176968 | F88: 19.644886 | G88: 20.149332 | H88: 20.939877 | I88: 22.034401 | J88: 23.408949 | K88: 24.81222 | L88: 26.097706 | M88: 27.423658 | N88: 29.065638 | O88: 30.472038 | P88: 31.692806 | Q88: 32.855999 | R88: 34.02005 | S88: 35.483128 | T88: 37.036972 | U88: 38.469906 | V88: 40.285892 | W88: 42.107845 | X88: 43.92976 | Y88: 46.050961 | Z88: 48.072746 | AA88: 49.627422 | AB88: 50.975948 | AC88: 52.382263 | AD88: 54.000732 | AE88: 55.80312 | AF88: 57.445702 | AG88: 0.039226
A89: PRC000:nom_C_Distillate | B89: Distillate Fuel Oil | C89: 21.823187 | D89: 22.864527 | E89: 21.600349 | F89: 22.538956 | G89: 22.716763 | H89: 22.870413 | I89: 23.183537 | J89: 24.129183 | K89: 25.097404 | L89: 25.879559 | M89: 26.97542 | N89: 28.472673 | O89: 29.485674 | P89: 30.415445 | Q89: 31.518965 | R89: 32.628517 | S89: 34.011166 | T89: 35.360092 | U89: 36.565868 | V89: 38.259872 | W89: 39.890251 | X89: 41.40807 | Y89: 43.365456 | Z89: 45.385769 | AA89: 46.893353 | AB89: 48.884224 | AC89: 50.466415 | AD89: 51.926086 | AE89: 53.812157 | AF89: 55.194649 | AG89: 0.032514
A90: PRC000:nom_C_ResidualFu | B90: Residual Fuel Oil | C90: 6.510058 | D90: 7.800477 | E90: 7.945353 | F90: 9.556235 | G90: 10.553672 | H90: 11.556342 | I90: 12.909644 | J90: 13.55414 | K90: 14.135114 | L90: 14.810273 | M90: 15.443988 | N90: 16.214159 | O90: 16.88455 | P90: 17.565434 | Q90: 18.204203 | R90: 18.902946 | S90: 19.504274 | T90: 20.369133 | U90: 20.943598 | V90: 22.739405 | W90: 23.757801 | X90: 24.624191 | Y90: 25.966454 | Z90: 27.371773 | AA90: 28.37871 | AB90: 29.709684 | AC90: 30.750561 | AD90: 31.706526 | AE90: 32.928417 | AF90: 33.788494 | AG90: 0.058429
A91: PRC000:nom_C_NaturalGas | B91: Natural Gas | C91: 8.442578 | D91: 9.102607 | E91: 8.992414 | F91: 8.915836 | G91: 9.015419 | H91: 9.267706 | I91: 9.585958 | J91: 10.077318 | K91: 10.609268 | L91: 11.058864 | M91: 11.524681 | N91: 12.192711 | O91: 12.736744 | P91: 13.204803 | Q91: 13.612744 | R91: 14.009382 | S91: 14.536539 | T91: 15.07787 | U91: 15.641514 | V91: 16.216299 | W91: 16.906044 | X91: 17.457684 | Y91: 17.959169 | Z91: 18.514944 | AA91: 19.054134 | AB91: 19.667431 | AC91: 20.318686 | AD91: 20.989712 | AE91: 21.750826 | AF91: 22.491329 | AG91: 0.034365
A92: PRC000:nom_C_Electricit | B92: Electricity | C92: 33.23053 | D92: 33.978516 | E92: 33.874538 | F92: 34.144749 | G92: 34.978958 | H92: 36.308815 | I92: 37.550941 | J92: 38.900845 | K92: 40.301247 | L92: 41.556381 | M92: 43.000675 | N92: 44.457672 | O92: 46.101952 | P92: 47.656097 | Q92: 48.67065 | R92: 49.857143 | S92: 51.332649 | T92: 52.747883 | U92: 54.245193 | V92: 56.169052 | W92: 57.813347 | X92: 59.804386 | Y92: 61.462963 | Z92: 63.146969 | AA92: 65.182571 | AB92: 66.765312 | AC92: 68.797684 | AD92: 70.724792 | AE92: 72.73188 | AF92: 74.371185 | AG92: 0.028169
B94: Industrial 1/
A95: PRC000:nom_I_LiquefiedP | B95: Propane | C95: 13.663833 | D95: 14.819919 | E95: 13.271934 | F95: 13.628423 | G95: 13.95307 | H95: 14.548325 | I95: 15.435884 | J95: 16.600773 | K95: 17.782276 | L95: 18.83663 | M95: 19.937275 | N95: 21.00005 | O95: 22.172026 | P95: 23.112478 | Q95: 23.917982 | R95: 24.776943 | S95: 25.955269 | T95: 27.207771 | U95: 28.310419 | V95: 29.833817 | W95: 31.332878 | X95: 32.812332 | Y95: 34.627686 | Z95: 36.30315 | AA95: 37.4235 | AB95: 38.314682 | AC95: 39.270897 | AD95: 40.458591 | AE95: 41.837971 | AF95: 43.012806 | AG95: 0.040335
A96: PRC000:nom_I_Distillate | B96: Distillate Fuel Oil | C96: 21.75238 | D96: 22.782827 | E96: 21.600447 | F96: 22.502117 | G96: 22.671473 | H96: 22.807241 | I96: 23.093634 | J96: 24.042925 | K96: 25.024292 | L96: 25.825529 | M96: 26.921162 | N96: 27.974201 | O96: 28.998323 | P96: 29.918238 | Q96: 30.948078 | R96: 32.043514 | S96: 33.408504 | T96: 34.742168 | U96: 35.938408 | V96: 37.634182 | W96: 39.255959 | X96: 40.764423 | Y96: 42.711178 | Z96: 44.71167 | AA96: 46.220592 | AB96: 48.205631 | AC96: 49.785362 | AD96: 51.237804 | AE96: 53.11813 | AF96: 54.499023 | AG96: 0.032178
A97: PRC000:nom_I_ResidualFu | B97: Residual Fuel Oil | C97: 7.09223 | D97: 8.561032 | E97: 8.946173 | F97: 10.835464 | G97: 12.090138 | H97: 13.431333 | I97: 15.102934 | J97: 15.845736 | K97: 16.550835 | L97: 17.320303 | M97: 18.075562 | N97: 18.961388 | O97: 19.75176 | P97: 20.509295 | Q97: 21.30755 | R97: 22.115112 | S97: 22.789452 | T97: 23.785866 | U97: 24.508816 | V97: 26.419771 | W97: 27.583975 | X97: 28.604774 | Y97: 30.075249 | Z97: 31.617619 | AA97: 32.766781 | AB97: 34.26096 | AC97: 35.450001 | AD97: 36.578426 | AE97: 37.965096 | AF97: 39.000706 | AG97: 0.06054
A98: PRC000:nom_I_NaturalGas | B98: Natural Gas 2/ | C98: 5.071276 | D98: 4.999427 | E98: 4.775102 | F98: 4.528864 | G98: 4.475785 | H98: 4.565272 | I98: 4.763649 | J98: 5.129222 | K98: 5.498101 | L98: 5.798128 | M98: 6.070403 | N98: 6.266402 | O98: 6.612955 | P98: 6.841533 | Q98: 6.963968 | R98: 7.12112 | S98: 7.365849 | T98: 7.659105 | U98: 7.957149 | V98: 8.273115 | W98: 8.661897 | X98: 8.974422 | Y98: 9.150481 | Z98: 9.384491 | AA98: 9.538548 | AB98: 9.789742 | AC98: 10.074139 | AD98: 10.39526 | AE98: 10.760066 | AF98: 11.125721 | AG98: 0.027462
A99: PRC000:nom_I_Metallurgi | B99: Metallurgical Coal | C99: 3.927859 | D99: 3.632119 | E99: 3.542883 | F99: 3.474877 | G99: 3.483614 | H99: 3.53182 | I99: 3.622874 | J99: 3.746009 | K99: 3.891056 | L99: 4.054818 | M99: 4.220803 | N99: 4.401494 | O99: 4.572361 | P99: 4.750306 | Q99: 4.947092 | R99: 5.15304 | S99: 5.375729 | T99: 5.600526 | U99: 5.830487 | V99: 6.077228 | W99: 6.323863 | X99: 6.578897 | Y99: 6.851333 | Z99: 7.138305 | AA99: 7.436069 | AB99: 7.746365 | AC99: 8.06824 | AD99: 8.38988 | AE99: 8.725502 | AF99: 9.070274 | AG99: 0.029279
A100: PRC000:nom_I_SteamCoal | B100: Other Industrial Coal | C100: 2.729489 | D100: 2.767614 | E100: 2.847413 | F100: 2.936212 | G100: 3.031019 | H100: 3.127068 | I100: 3.223459 | J100: 3.335417 | K100: 3.451401 | L100: 3.569537 | M100: 3.688911 | N100: 3.814851 | O100: 3.947356 | P100: 4.07884 | Q100: 4.200966 | R100: 4.337944 | S100: 4.479478 | T100: 4.631082 | U100: 4.800351 | V100: 4.970238 | W100: 5.151912 | X100: 5.326657 | Y100: 5.504225 | Z100: 5.699249 | AA100: 5.896136 | AB100: 6.099313 | AC100: 6.302955 | AD100: 6.50875 | AE100: 6.72362 | AF100: 6.93932 | AG100: 0.032699
A101: PRC000:nom_I_CoaltoLiqu | B101: Coal to Liquids | C101: -- | D101: -- | E101: -- | F101: -- | G101: -- | H101: -- | I101: -- | J101: -- | K101: -- | L101: -- | M101: -- | N101: -- | O101: -- | P101: -- | Q101: -- | R101: -- | S101: -- | T101: -- | U101: -- | V101: -- | W101: -- | X101: -- | Y101: -- | Z101: -- | AA101: -- | AB101: -- | AC101: -- | AD101: -- | AE101: -- | AF101: -- | AG101: --
A102: PRC000:nom_I_Electricit | B102: Electricity | C102: 21.954327 | D102: 22.280447 | E102: 21.792934 | F102: 21.787928 | G102: 22.226633 | H102: 22.802185 | I102: 23.547533 | J102: 24.398607 | K102: 25.294533 | L102: 26.123686 | M102: 27.017107 | N102: 27.921112 | O102: 28.837664 | P102: 29.798458 | Q102: 30.501366 | R102: 31.325613 | S102: 32.145142 | T102: 33.099281 | U102: 34.040619 | V102: 35.189232 | W102: 36.283123 | X102: 37.420853 | Y102: 38.354103 | Z102: 39.433506 | AA102: 40.609592 | AB102: 41.576191 | AC102: 42.810467 | AD102: 44.005733 | AE102: 45.243095 | AF102: 46.421021 | AG102: 0.026157
B105: Transportation
A106: PRC000:nom_T_LiquefiedP | B106: Propane | C106: 17.771591 | D106: 18.857105 | E106: 17.702696 | F106: 18.216183 | G106: 18.704325 | H106: 19.446571 | I106: 20.452202 | J106: 21.695446 | K106: 22.946356 | L106: 24.086309 | M106: 25.269236 | N106: 26.904428 | O106: 28.166838 | P106: 29.259338 | Q106: 30.341032 | R106: 31.410406 | S106: 32.75095 | T106: 34.159538 | U106: 35.454517 | V106: 37.102211 | W106: 38.73782 | X106: 40.373085 | Y106: 42.279198 | Z106: 44.082489 | AA106: 45.474243 | AB106: 46.713749 | AC106: 48.025043 | AD106: 49.529682 | AE106: 51.189854 | AF106: 52.696335 | AG106: 0.038192
A107: PRC000:nom_T_Ethan(E85) | B107: E85 3/ | C107: 25.787903 | D107: 26.590775 | E107: 26.982386 | F107: 27.478241 | G107: 28.082909 | H107: 29.118649 | I107: 30.523687 | J107: 31.906485 | K107: 33.254425 | L107: 34.937057 | M107: 36.206982 | N107: 38.690353 | O107: 40.268974 | P107: 41.823528 | Q107: 43.454517 | R107: 45.000153 | S107: 46.802525 | T107: 48.779102 | U107: 50.349072 | V107: 52.891319 | W107: 55.170071 | X107: 57.62994 | Y107: 60.314137 | Z107: 62.726788 | AA107: 65.050591 | AB107: 67.875214 | AC107: 70.318016 | AD107: 72.854843 | AE107: 75.520477 | AF107: 77.296127 | AG107: 0.038579
A108: PRC000:nom_T_MotorGasol | B108: Motor Gasoline 4/ | C108: 25.885534 | D108: 25.62289 | E108: 23.209953 | F108: 23.707579 | G108: 24.257063 | H108: 25.150444 | I108: 26.343428 | J108: 27.510944 | K108: 28.647305 | L108: 30.053028 | M108: 31.130007 | N108: 33.506157 | O108: 34.842045 | P108: 36.151772 | Q108: 37.576756 | R108: 38.881332 | S108: 40.404396 | T108: 42.077377 | U108: 43.420158 | V108: 45.54517 | W108: 47.481865 | X108: 49.451988 | Y108: 51.736752 | Z108: 53.89901 | AA108: 55.882385 | AB108: 58.314865 | AC108: 60.378498 | AD108: 62.56073 | AE108: 64.823204 | AF108: 66.350449 | AG108: 0.03299
A109: PRC000:nom_T_JetFuel | B109: Jet Fuel 5/ | C109: 14.720805 | D109: 15.883732 | E109: 14.894306 | F109: 16.54401 | G109: 17.195129 | H109: 17.980322 | I109: 18.90593 | J109: 19.81942 | K109: 20.708345 | L109: 21.397467 | M109: 22.502146 | N109: 23.752871 | O109: 24.616678 | P109: 25.473087 | Q109: 26.390503 | R109: 27.406216 | S109: 28.726957 | T109: 29.962418 | U109: 31.061535 | V109: 32.604355 | W109: 34.101086 | X109: 35.442081 | Y109: 37.272186 | Z109: 39.145409 | AA109: 40.50275 | AB109: 42.279293 | AC109: 43.718407 | AD109: 45.065403 | AE109: 46.815086 | AF109: 48.104626 | AG109: 0.041677
A110: PRC000:nom_T_Distillate | B110: Diesel Fuel (distillate fuel oil) 6/ | C110: 23.750263 | D110: 23.578897 | E110: 23.215324 | F110: 24.687382 | G110: 25.547915 | H110: 26.365854 | I110: 27.365362 | J110: 28.451197 | K110: 29.588945 | L110: 30.550512 | M110: 31.788191 | N110: 33.479671 | O110: 34.693676 | P110: 35.763798 | Q110: 37.057266 | R110: 38.320412 | S110: 39.928471 | T110: 41.486561 | U110: 42.90802 | V110: 44.830936 | W110: 46.700027 | X110: 48.487736 | Y110: 50.692127 | Z110: 52.972492 | AA110: 54.756222 | AB110: 57.054775 | AC110: 58.940365 | AD110: 60.645912 | AE110: 62.840931 | AF110: 64.501915 | AG110: 0.035052
A111: PRC000:nom_T_ResidualFu | B111: Residual Fuel Oil | C111: 12.357966 | D111: 10.777995 | E111: 13.400628 | F111: 14.761683 | G111: 15.468278 | H111: 16.184179 | I111: 17.179281 | J111: 17.931643 | K111: 18.651646 | L111: 19.473707 | M111: 20.226515 | N111: 21.243036 | O111: 22.057035 | P111: 22.838909 | Q111: 23.716595 | R111: 24.589396 | S111: 25.446138 | T111: 26.484795 | U111: 27.3169 | V111: 29.095949 | W111: 30.273571 | X111: 31.408142 | Y111: 32.894196 | Z111: 34.461506 | AA111: 35.703712 | AB111: 37.234089 | AC111: 38.525547 | AD111: 39.746098 | AE111: 41.1744 | AF111: 42.31741 | AG111: 0.043358
A112: PRC000:nom_T_NaturalGas | B112: Natural Gas 7/ | C112: 14.654003 | D112: 15.090463 | E112: 14.68151 | F112: 14.502679 | G112: 14.504148 | H112: 14.582769 | I112: 14.763145 | J112: 15.121434 | K112: 15.48817 | L112: 15.797434 | M112: 16.101601 | N112: 17.54327 | O112: 17.986914 | P112: 18.373447 | Q112: 18.836166 | R112: 19.190336 | S112: 19.661667 | T112: 20.196613 | U112: 20.739374 | V112: 21.414515 | W112: 22.126902 | X112: 22.76203 | Y112: 23.334723 | Z112: 23.969168 | AA112: 24.547056 | AB112: 25.244947 | AC112: 25.976206 | AD112: 26.726246 | AE112: 27.537659 | AF112: 28.313566 | AG112: 0.022971
A113: PRC000:nom_T_Electricit | B113: Electricity | C113: 39.115726 | D113: 40.891689 | E113: 40.337898 | F113: 40.426842 | G113: 41.700527 | H113: 43.651726 | I113: 45.215015 | J113: 46.823669 | K113: 48.38937 | L113: 49.74168 | M113: 51.401199 | N113: 53.103508 | O113: 55.02985 | P113: 56.679493 | Q113: 57.898582 | R113: 59.218525 | S113: 60.827026 | T113: 62.417961 | U113: 64.066467 | V113: 65.943932 | W113: 67.863762 | X113: 69.796951 | Y113: 71.540169 | Z113: 73.523705 | AA113: 75.79406 | AB113: 77.783768 | AC113: 79.871346 | AD113: 82.037857 | AE113: 84.197556 | AF113: 86.33786 | AG113: 0.027678
B115: Electric Power 8/
A116: PRC000:nom_E_Distillate | B116: Distillate Fuel Oil | C116: 21.749472 | D116: 22.773756 | E116: 21.329041 | F116: 22.401056 | G116: 22.444971 | H116: 22.466434 | I116: 22.712948 | J116: 23.639408 | K116: 24.602959 | L116: 25.38751 | M116: 26.315695 | N116: 27.447075 | O116: 28.383221 | P116: 29.400795 | Q116: 30.385952 | R116: 31.494976 | S116: 32.888092 | T116: 34.142879 | U116: 35.315723 | V116: 37.008327 | W116: 38.59491 | X116: 40.026405 | Y116: 41.940762 | Z116: 43.870602 | AA116: 45.34285 | AB116: 47.309265 | AC116: 48.892651 | AD116: 50.30714 | AE116: 52.210384 | AF116: 53.605736 | AG116: 0.031595
A117: PRC000:nom_E_ResidualFu | B117: Residual Fuel Oil | C117: 13.006465 | D117: 13.775164 | E117: 13.375271 | F117: 14.757445 | G117: 15.454079 | H117: 16.164206 | I117: 17.244572 | J117: 17.96759 | K117: 18.671255 | L117: 19.465832 | M117: 20.202301 | N117: 21.269953 | O117: 22.068264 | P117: 22.814425 | Q117: 23.706303 | R117: 24.556141 | S117: 25.451374 | T117: 26.440834 | U117: 27.224174 | V117: 28.888342 | W117: 29.778625 | X117: 30.671183 | Y117: 31.823647 | Z117: 32.921566 | AA117: 33.482468 | AB117: 35.033802 | AC117: 36.374592 | AD117: 37.54171 | AE117: 39.012119 | AF117: 40.262657 | AG117: 0.039734
A118: PRC000:nom_E_NaturalGas | B118: Natural Gas | C118: 5.157501 | D118: 4.171376 | E118: 3.977244 | F118: 3.738685 | G118: 3.673146 | H118: 3.758575 | I118: 3.937195 | J118: 4.287839 | K118: 4.602344 | L118: 4.853909 | M118: 5.074351 | N118: 5.263284 | O118: 5.570406 | P118: 5.731863 | Q118: 5.767033 | R118: 5.889748 | S118: 6.085039 | T118: 6.334803 | U118: 6.595075 | V118: 6.887491 | W118: 7.221827 | X118: 7.468435 | Y118: 7.567262 | Z118: 7.743873 | AA118: 7.848843 | AB118: 8.054547 | AC118: 8.288168 | AD118: 8.572623 | AE118: 8.866986 | AF118: 9.218044 | AG118: 0.020226
A119: PRC000:nom_E_SteamCoal | B119: Steam Coal | C119: 2.11768 | D119: 2.067174 | E119: 2.120597 | F119: 2.188549 | G119: 2.199583 | H119: 2.245965 | I119: 2.307448 | J119: 2.378841 | K119: 2.477713 | L119: 2.556904 | M119: 2.63419 | N119: 2.706025 | O119: 2.784521 | P119: 2.873138 | Q119: 2.932602 | R119: 3.014101 | S119: 3.114906 | T119: 3.212186 | U119: 3.316489 | V119: 3.430665 | W119: 3.552385 | X119: 3.638816 | Y119: 3.753593 | Z119: 3.864852 | AA119: 3.982215 | AB119: 4.10759 | AC119: 4.220465 | AD119: 4.321849 | AE119: 4.453509 | AF119: 4.590535 | AG119: 0.027038
...

Sheet AEO Table 3 2021
B1: highogs.d120120a | C1: 2020 | D1: 2021 | E1: 2022 | F1: 2023 | G1: 2024 | H1: 2025 | I1: 2026 | J1: 2027 | K1: 2028 | L1: 2029 | M1: 2030 | N1: 2031 | O1: 2032 | P1: 2033 | Q1: 2034 | R1: 2035 | S1: 2036 | T1: 2037 | U1: 2038 | V1: 2039 | W1: 2040 | X1: 2041 | Y1: 2042 | Z1: 2043 | AA1: 2044 | AB1: 2045 | AC1: 2046 | AD1: 2047 | AE1: 2048 | AF1: 2049 | AG1: 2050
C3: Report | D3: Annual Energy Outlook 2021
C4: Scenario | D4: ref2021 | G4: Reference case
C5: Datekey | D5: d113020a
C6: Release Date | E6: January 2021
A10: PRC000 | B10: 3. Energy Prices by Sector and Source | AH10: Compound
B11: (2020 dollars per million Btu, unless otherwise noted) | AH11: Growth
AH12: 2020-2050
B13: Sector and Source | C13: 2020 | D13: 2021 | E13: 2022 | F13: 2023 | G13: 2024 | H13: 2025 | I13: 2026 | J13: 2027 | K13: 2028 | L13: 2029 | M13: 2030 | N13: 2031 | O13: 2032 | P13: 2033 | Q13: 2034 | R13: 2035 | S13: 2036 | T13: 2037 | U13: 2038 | V13: 2039 | W13: 2040 | X13: 2041 | Y13: 2042 | Z13: 2043 | AA13: 2044 | AB13: 2045 | AC13: 2046 | AD13: 2047 | AE13: 2048 | AF13: 2049 | AG13: 2050 | AH13: (percent)
B15: Residential
A16: PRC000:ba_LiquefiedPetr | B16: Propane | C16: 17.296467 | D16: 17.183254 | E16: 17.386812 | F16: 17.278086 | G16: 17.282633 | H16: 17.365963 | I16: 17.281719 | J16: 17.232769 | K16: 17.352678 | L16: 17.525156 | M16: 18.105442 | N16: 18.397449 | O16: 18.665577 | P16: 18.88686 | Q16: 19.101889 | R16: 19.23711 | S16: 19.41116 | T16: 19.712313 | U16: 19.979467 | V16: 20.173357 | W16: 20.375391 | X16: 20.580265 | Y16: 20.773108 | Z16: 20.871334 | AA16: 21.039562 | AB16: 21.186533 | AC16: 21.38179 | AD16: 21.587627 | AE16: 21.790129 | AF16: 22.029543 | AG16: 22.264086 | AH16: 0.008451
A17: PRC000:ba_DistillateFue | B17: Distillate Fuel Oil | C17: 17.748362 | D17: 17.778864 | E17: 18.840994 | F17: 20.194542 | G17: 20.900642 | H17: 21.347786 | I17: 21.95985 | J17: 22.37348 | K17: 22.572247 | L17: 22.803102 | M17: 23.134237 | N17: 23.233164 | O17: 23.457367 | P17: 23.595133 | Q17: 23.692457 | R17: 23.53126 | S17: 23.427431 | T17: 23.58984 | U17: 23.769676 | V17: 23.632313 | W17: 24.000732 | X17: 24.13143 | Y17: 24.220469 | Z17: 24.344158 | AA17: 24.51425 | AB17: 24.754841 | AC17: 24.880373 | AD17: 24.974497 | AE17: 25.016258 | AF17: 25.183065 | AG17: 25.323921 | AH17: 0.011919
A18: PRC000:ba_NaturalGas | B18: Natural Gas | C18: 10.141716 | D18: 10.51412 | E18: 10.202188 | F18: 9.913226 | G18: 9.649481 | H18: 9.660916 | I18: 9.737484 | J18: 9.850092 | K18: 9.923312 | L18: 10.06601 | M18: 10.422234 | N18: 10.498061 | O18: 10.580394 | P18: 10.658723 | Q18: 10.693798 | R18: 10.700832 | S18: 10.715192 | T18: 10.731378 | U18: 10.724482 | V18: 10.712461 | W18: 10.708804 | X18: 10.731961 | Y18: 10.757458 | Z18: 10.775259 | AA18: 10.802486 | AB18: 10.823374 | AC18: 10.832982 | AD18: 10.843533 | AE18: 10.825556 | AF18: 10.832339 | AG18: 10.859445 | AH18: 0.002282
A19: PRC000:ba_Electricity | B19: Electricity | C19: 35.768967 | D19: 36.572845 | E19: 36.200897 | F19: 35.847927 | G19: 35.555779 | H19: 35.370304 | I19: 35.271217 | J19: 35.232407 | K19: 35.179947 | L19: 35.13731 | M19: 35.114113 | N19: 35.213707 | O19: 35.215427 | P19: 35.186943 | Q19: 35.111835 | R19: 34.965027 | S19: 34.841293 | T19: 34.730331 | U19: 34.648323 | V19: 34.567348 | W19: 34.484665 | X19: 34.428879 | Y19: 34.354916 | Z19: 34.264565 | AA19: 34.180298 | AB19: 34.138596 | AC19: 34.02042 | AD19: 33.894436 | AE19: 33.717102 | AF19: 33.468891 | AG19: 33.255077 | AH19: -0.002426
B21: Commercial
A22: PRC000:ca_LiquefiedGas | B22: Propane | C22: 12.770181 | D22: 13.596351 | E22: 14.132167 | F22: 13.946478 | G22: 13.993322 | H22: 14.10978 | I22: 13.959495 | J22: 13.925439 | K22: 14.114777 | L22: 14.294835 | M22: 14.966532 | N22: 15.145463 | O22: 15.316516 | P22: 15.455637 | Q22: 15.603415 | R22: 15.65097 | S22: 15.789752 | T22: 16.088108 | U22: 16.278292 | V22: 16.373463 | W22: 16.514631 | X22: 16.663309 | Y22: 16.795403 | Z22: 16.807695 | AA22: 16.958042 | AB22: 17.057177 | AC22: 17.22489 | AD22: 17.38492 | AE22: 17.530947 | AF22: 17.725052 | AG22: 17.895052 | AH22: 0.011311
A23: PRC000:ca_DistillateFue | B23: Distillate Fuel Oil | C23: 17.825056 | D23: 17.90453 | E23: 17.917162 | F23: 18.273129 | G23: 17.977633 | H23: 17.420301 | I23: 17.035746 | J23: 17.45133 | K23: 17.649296 | L23: 17.881008 | M23: 18.477827 | N23: 18.582241 | O23: 18.841583 | P23: 18.984005 | Q23: 19.086586 | R23: 18.923241 | S23: 18.824066 | T23: 18.987247 | U23: 19.171539 | V23: 19.037495 | W23: 19.410124 | X23: 19.543423 | Y23: 19.633228 | Z23: 19.766468 | AA23: 19.946016 | AB23: 20.19311 | AC23: 20.325541 | AD23: 20.426331 | AE23: 20.483273 | AF23: 20.656473 | AG23: 20.796879 | AH23: 0.005153
A24: PRC000:ca_ResidualFuel | B24: Residual Fuel Oil | C24: 5.24652 | D24: 4.094263 | E24: 5.155511 | F24: 6.388786 | G24: 7.417715 | H24: 8.084204 | I24: 8.797711 | J24: 9.271342 | K24: 9.380152 | L24: 9.630754 | M24: 9.977427 | N24: 10.056496 | O24: 10.322896 | P24: 10.494815 | Q24: 10.659212 | R24: 10.565108 | S24: 10.57521 | T24: 10.757941 | U24: 10.935437 | V24: 10.928781 | W24: 11.256635 | X24: 11.39807 | Y24: 11.526395 | Z24: 11.652904 | AA24: 11.895937 | AB24: 12.079579 | AC24: 12.28236 | AD24: 12.398063 | AE24: 12.434026 | AF24: 12.576524 | AG24: 12.679845 | AH24: 0.029852
A25: PRC000:ca_NaturalGas | B25: Natural Gas | C25: 7.227466 | D25: 7.757176 | E25: 7.758438 | F25: 7.432969 | G25: 7.15386 | H25: 7.140882 | I25: 7.187162 | J25: 7.262215 | K25: 7.303709 | L25: 7.416845 | M25: 7.668393 | N25: 7.709173 | O25: 7.756773 | P25: 7.814415 | Q25: 7.83147 | R25: 7.823295 | S25: 7.823662 | T25: 7.825634 | U25: 7.805791 | V25: 7.781954 | W25: 7.768893 | X25: 7.783077 | Y25: 7.799472 | Z25: 7.808736 | AA25: 7.828284 | AB25: 7.841544 | AC25: 7.844315 | AD25: 7.846509 | AE25: 7.819409 | AF25: 7.816325 | AG25: 7.833879 | AH25: 0.002689
A26: PRC000:ca_Electricity | B26: Electricity | C26: 31.322283 | D26: 31.751371 | E26: 31.36965 | F26: 30.770927 | G26: 30.355267 | H26: 30.114548 | I26: 29.891642 | J26: 29.798216 | K26: 29.668579 | L26: 29.54162 | M26: 29.447769 | N26: 29.516174 | O26: 29.407202 | P26: 29.362705 | Q26: 29.207033 | R26: 29.013252 | S26: 28.80307 | T26: 28.61985 | U26: 28.475729 | V26: 28.334457 | W26: 28.186321 | X26: 28.052315 | Y26: 27.894957 | Z26: 27.748571 | AA26: 27.573784 | AB26: 27.437696 | AC26: 27.26679 | AD26: 27.07099 | AE26: 26.838396 | AF26: 26.563028 | AG26: 26.336115 | AH26: -0.005763
B28: Industrial 1/
A29: PRC000:da_LiquefiedPetr | B29: Propane | C29: 7.622427 | D29: 8.496119 | E29: 8.995164 | F29: 8.791455 | G29: 8.841549 | H29: 8.954068 | I29: 8.804231 | J29: 8.777181 | K29: 8.962337 | L29: 9.129627 | M29: 9.562165 | N29: 9.718732 | O29: 9.847404 | P29: 9.979259 | Q29: 10.120852 | R29: 10.16201 | S29: 10.299414 | T29: 10.596047 | U29: 10.776484 | V29: 10.863864 | W29: 11.003838 | X29: 11.150719 | Y29: 11.280413 | Z29: 11.286859 | AA29: 11.442306 | AB29: 11.53952 | AC29: 11.710324 | AD29: 11.870821 | AE29: 12.016953 | AF29: 12.215362 | AG29: 12.386859 | AH29: 0.016316
A30: PRC000:da_DistillateFue | B30: Distillate Fuel Oil | C30: 17.750837 | D30: 17.784218 | E30: 17.832458 | F30: 18.255758 | G30: 17.965652 | H30: 17.418257 | I30: 17.043358 | J30: 17.464336 | K30: 17.665487 | L30: 17.90383 | M30: 18.228374 | N30: 18.345335 | O30: 18.564774 | P30: 18.711565 | Q30: 18.823149 | R30: 18.657301 | S30: 18.557192 | T30: 18.721062 | U30: 18.906944 | V30: 18.769888 | W30: 19.141384 | X30: 19.276993 | Y30: 19.368721 | Z30: 19.507063 | AA30: 19.688093 | AB30: 19.940121 | AC30: 20.075132 | AD30: 20.18284 | AE30: 20.246756 | AF30: 20.426596 | AG30: 20.570137 | AH30: 0.004926
A31: PRC000:da_ResidualFuel | B31: Residual Fuel Oil | C31: 5.42274 | D31: 4.431344 | E31: 5.806646 | F31: 7.352966 | G31: 8.604152 | H31: 9.588043 | I31: 10.678126 | J31: 11.122404 | K31: 11.319104 | L31: 11.560951 | M31: 11.886529 | N31: 11.988492 | O31: 12.214651 | P31: 12.396055 | Q31: 12.54118 | R31: 12.441391 | S31: 12.436083 | T31: 12.619387 | U31: 12.817525 | V31: 12.799622 | W31: 13.127106 | X31: 13.276533 | Y31: 13.38976 | Z31: 13.499092 | AA31: 13.732372 | AB31: 13.936438 | AC31: 14.088271 | AD31: 14.181102 | AE31: 14.234844 | AF31: 14.370006 | AG31: 14.531082 | AH31: 0.033402
A32: PRC000:da_NaturalGas | B32: Natural Gas 2/ | C32: 3.058431 | D32: 4.045059 | E32: 3.979237 | F32: 3.564088 | G32: 3.222769 | H32: 3.167117 | I32: 3.19632 | J32: 3.294182 | K32: 3.358054 | L32: 3.462901 | M32: 3.516128 | N32: 3.544856 | O32: 3.567816 | P32: 3.613658 | Q32: 3.614324 | R32: 3.59441 | S32: 3.587867 | T32: 3.575028 | U32: 3.557224 | V32: 3.53187 | W32: 3.511744 | X32: 3.512166 | Y32: 3.514958 | Z32: 3.50462 | AA32: 3.517149 | AB32: 3.499087 | AC32: 3.486105 | AD32: 3.499511 | AE32: 3.469027 | AF32: 3.445241 | AG32: 3.461729 | AH32: 0.004137
A33: PRC000:da_Metallurgical | B33: Metallurgical Coal | C33: 4.0174 | D33: 3.598935 | E33: 3.356058 | F33: 3.207879 | G33: 3.117534 | H33: 3.070951 | I33: 3.029583 | J33: 3.01361 | K33: 3.014059 | L33: 3.036777 | M33: 3.066812 | N33: 3.102134 | O33: 3.137037 | P33: 3.169176 | Q33: 3.199574 | R33: 3.23061 | S33: 3.261404 | T33: 3.294469 | U33: 3.328295 | V33: 3.36151 | W33: 3.395033 | X33: 3.429636 | Y33: 3.466346 | Z33: 3.505546 | AA33: 3.545559 | AB33: 3.58672 | AC33: 3.624724 | AD33: 3.661516 | AE33: 3.699104 | AF33: 3.737599 | AG33: 3.780184 | AH33: -0.002027
A34: PRC000:da_SteamCoal | B34: Other Industrial Coal | C34: 2.815477 | D34: 2.827866 | E34: 2.884658 | F34: 2.873684 | G34: 2.873563 | H34: 2.861837 | I34: 2.849145 | J34: 2.837385 | K34: 2.825764 | L34: 2.820652 | M34: 2.830257 | N34: 2.828997 | O34: 2.815725 | P34: 2.816442 | Q34: 2.817086 | R34: 2.821201 | S34: 2.823316 | T34: 2.827811 | U34: 2.827212 | V34: 2.82924 | W34: 2.837649 | X34: 2.840635 | Y34: 2.844644 | Z34: 2.84973 | AA34: 2.846455 | AB34: 2.857904 | AC34: 2.860906 | AD34: 2.869795 | AE34: 2.879357 | AF34: 2.888515 | AG34: 2.900779 | AH34: 0.000995
A35: PRC000:da_CoaltoLiquids | B35: Coal to Liquids | C35: -- | D35: -- | E35: -- | F35: -- | G35: -- | H35: -- | I35: -- | J35: -- | K35: -- | L35: -- | M35: -- | N35: -- | O35: -- | P35: -- | Q35: -- | R35: -- | S35: -- | T35: -- | U35: -- | V35: -- | W35: -- | X35: -- | Y35: -- | Z35: -- | AA35: -- | AB35: -- | AC35: -- | AD35: -- | AE35: -- | AF35: -- | AG35: -- | AH35: --
A36: PRC000:da_Electricity | B36: Electricity | C36: 20.703951 | D36: 20.963264 | E36: 20.467888 | F36: 19.783636 | G36: 19.357731 | H36: 19.106281 | I36: 18.963926 | J36: 18.841095 | K36: 18.735588 | L36: 18.663567 | M36: 18.617512 | N36: 18.676767 | O36: 18.634558 | P36: 18.5455 | Q36: 18.446602 | R36: 18.351669 | S36: 18.23979 | T36: 18.124399 | U36: 18.044464 | V36: 17.939983 | W36: 17.836859 | X36: 17.750677 | Y36: 17.663349 | Z36: 17.552032 | AA36: 17.48848 | AB36: 17.401014 | AC36: 17.289835 | AD36: 17.180754 | AE36: 17.048691 | AF36: 16.892347 | AG36: 16.778522 | AH36: -0.006983
B38: Transportation
A39: PRC000:ea_LiquefiedPetr | B39: Propane | C39: 11.989126 | D39: 12.919199 | E39: 13.387474 | F39: 13.175584 | G39: 13.226618 | H39: 13.334444 | I39: 13.185479 | J39: 13.161032 | K39: 13.340968 | L39: 13.497202 | M39: 14.332111 | N39: 14.464104 | O39: 14.634573 | P39: 14.748526 | Q39: 14.872234 | R39: 14.902267 | S39: 15.02397 | T39: 15.289154 | U39: 15.443079 | V39: 15.51417 | W39: 15.635192 | X39: 15.760916 | Y39: 15.870314 | Z39: 15.87043 | AA39: 16.006077 | AB39: 16.086893 | AC39: 16.233223 | AD39: 16.368509 | AE39: 16.490398 | AF39: 16.657537 | AG39: 16.799364 | AH39: 0.011308
A40: PRC000:ea_Ethanol(E85) | B40: E85 3/ | C40: 21.197994 | D40: 22.2544 | E40: 23.610071 | F40: 23.112133 | G40: 22.835497 | H40: 22.609148 | I40: 22.527273 | J40: 23.046518 | K40: 23.283846 | L40: 23.639156 | M40: 24.640181 | N40: 24.558275 | O40: 24.877409 | P40: 25.090036 | Q40: 25.61343 | R40: 25.3027 | S40: 25.378855 | T40: 25.66387 | U40: 25.927429 | V40: 25.975618 | W40: 26.159891 | X40: 26.357864 | Y40: 26.34479 | Z40: 26.476631 | AA40: 26.680527 | AB40: 26.959341 | AC40: 27.088846 | AD40: 27.212555 | AE40: 27.351645 | AF40: 27.548573 | AG40: 27.76218 | AH40: 0.009033
A41: PRC000:ea_MotorGasoline | B41: Motor Gasoline 4/ | C41: 18.753328 | D41: 19.581623 | E41: 19.852089 | F41: 19.731396 | G41: 19.549955 | H41: 19.404346 | I41: 19.369587 | J41: 19.802027 | K41: 19.986061 | L41: 20.267641 | M41: 21.249949 | N41: 21.156803 | O41: 21.426884 | P41: 21.582792 | Q41: 22.004717 | R41: 21.723974 | S41: 21.772913 | T41: 22.005011 | U41: 22.215183 | V41: 22.246717 | W41: 22.394073 | X41: 22.54735 | Y41: 22.523794 | Z41: 22.623035 | AA41: 22.783686 | AB41: 22.996141 | AC41: 23.074652 | AD41: 23.173857 | AE41: 23.260544 | AF41: 23.427748 | AG41: 23.597351 | AH41: 0.007688
A42: PRC000:ea_JetFuel | B42: Jet Fuel 5/ | C42: 9.568654 | D42: 10.382089 | E42: 11.359349 | F42: 12.190462 | G42: 12.696321 | H42: 12.90303 | I42: 13.260797 | J42: 13.761744 | K42: 14.027101 | L42: 14.319986 | M42: 14.720232 | N42: 14.946351 | O42: 15.259788 | P42: 15.467662 | Q42: 15.60177 | R42: 15.515354 | S42: 15.477219 | T42: 15.705438 | U42: 15.944727 | V42: 15.870375 | W42: 16.294031 | X42: 16.474258 | Y42: 16.612787 | Z42: 16.803795 | AA42: 17.055935 | AB42: 17.333384 | AC42: 17.508017 | AD42: 17.640877 | AE42: 17.718878 | AF42: 17.919552 | AG42: 18.07815 | AH42: 0.021433
A43: PRC000:ea_DistillateFue | B43: Diesel Fuel (distillate fuel oil) 6/ | C43: 18.329231 | D43: 18.273304 | E43: 19.018625 | F43: 20.184969 | G43: 20.458481 | H43: 20.666317 | I43: 20.773323 | J43: 21.303528 | K43: 21.534609 | L43: 21.744459 | M43: 22.445812 | N43: 22.594145 | O43: 22.867039 | P43: 23.024622 | Q43: 23.134773 | R43: 22.871685 | S43: 22.789751 | T43: 22.977484 | U43: 23.1539 | V43: 23.013912 | W43: 23.353069 | X43: 23.471916 | Y43: 23.546528 | Z43: 23.659164 | AA43: 23.822613 | AB43: 24.034845 | AC43: 24.17654 | AD43: 24.286657 | AE43: 24.364197 | AF43: 24.512602 | AG43: 24.657568 | AH43: 0.009935
A44: PRC000:ea_ResidualFuel | B44: Residual Fuel Oil | C44: 9.208066 | D44: 6.989611 | E44: 7.144215 | F44: 8.188413 | G44: 9.349967 | H44: 9.375696 | I44: 9.64027 | J44: 10.126381 | K44: 10.226327 | L44: 10.968683 | M44: 11.327226 | N44: 11.050945 | O44: 11.334099 | P44: 11.461785 | Q44: 11.880727 | R44: 11.526117 | S44: 11.641574 | T44: 11.783689 | U44: 11.978284 | V44: 12.118925 | W44: 12.296306 | X44: 12.352102 | Y44: 12.596483 | Z44: 12.935369 | AA44: 13.238238 | AB44: 13.200082 | AC44: 13.803732 | AD44: 13.884045 | AE44: 13.935925 | AF44: 14.105252 | AG44: 14.331807 | AH44: 0.014856
A45: PRC000:ea_NaturalGas | B45: Natural Gas 7/ | C45: 12.999203 | D45: 13.612721 | E45: 13.962173 | F45: 13.394044 | G45: 12.701125 | H45: 12.45573 | I45: 12.231554 | J45: 12.004652 | K45: 11.749408 | L45: 11.559972 | M45: 12.03606 | N45: 11.756859 | O45: 11.637913 | P45: 11.466904 | Q45: 11.297943 | R45: 11.07862 | S45: 10.936546 | T45: 10.797911 | U45: 10.667474 | V45: 10.546729 | W45: 10.458061 | X45: 10.372773 | Y45: 10.336288 | Z45: 10.268269 | AA45: 10.251918 | AB45: 10.198373 | AC45: 10.155938 | AD45: 10.137851 | AE45: 10.073518 | AF45: 10.031018 | AG45: 10.035291 | AH45: -0.008589
A46: PRC000:ea_Electricity | B46: Electricity | C46: 34.881683 | D46: 36.432148 | E46: 35.38266 | F46: 34.505398 | G46: 33.776939 | H46: 33.571579 | I46: 33.493298 | J46: 33.46344 | K46: 33.426533 | L46: 33.43816 | M46: 33.332623 | N46: 33.562084 | O46: 33.609898 | P46: 33.642971 | Q46: 33.577801 | R46: 33.383286 | S46: 33.236187 | T46: 33.11697 | U46: 32.992996 | V46: 32.848633 | W46: 32.697342 | X46: 32.558189 | Y46: 32.407673 | Z46: 32.201775 | AA46: 32.01421 | AB46: 31.856125 | AC46: 31.64279 | AD46: 31.444817 | AE46: 31.182276 | AF46: 30.867584 | AG46: 30.581863 | AH46: -0.004376
B48: Electric Power 8/
A49: PRC000:ga_DistillateFue | B49: Distillate Fuel Oil | C49: 17.708588 | D49: 17.73579 | E49: 17.772367 | F49: 17.757168 | G49: 17.440514 | H49: 16.906563 | I49: 16.321712 | J49: 16.740919 | K49: 16.886805 | L49: 17.092268 | M49: 17.428493 | N49: 17.382967 | O49: 17.607697 | P49: 17.75326 | Q49: 17.881567 | R49: 17.759588 | S49: 17.726187 | T49: 17.89739 | U49: 17.993275 | V49: 17.910707 | W49: 18.34079 | X49: 18.489763 | Y49: 18.573277 | Z49: 18.707031 | AA49: 18.910122 | AB49: 19.160456 | AC49: 19.33226 | AD49: 19.448906 | AE49: 19.543753 | AF49: 19.758375 | AG49: 19.904821 | AH49: 0.003905
A50: PRC000:ga_ResidualFuel | B50: Residual Fuel Oil | C50: 8.29073 | D50: 8.853661 | E50: 9.720617 | F50: 10.69387 | G50: 11.372703 | H50: 11.701245 | I50: 12.102871 | J50: 12.510105 | K50: 12.626429 | L50: 12.84155 | M50: 13.156911 | N50: 13.264642 | O50: 13.461685 | P50: 13.653866 | Q50: 13.733962 | R50: 13.649095 | S50: 13.591269 | T50: 13.757905 | U50: 13.930717 | V50: 13.97852 | W50: 14.261134 | X50: 14.30029 | Y50: 14.296969 | Z50: 14.277529 | AA50: 14.328882 | AB50: 14.239768 | AC50: 14.427329 | AD50: 14.57197 | AE50: 14.66136 | AF50: 14.848315 | AG50: 15.050549 | AH50: 0.020075
A51: PRC000:ga_NaturalGas | B51: Natural Gas | C51: 2.447536 | D51: 3.537754 | E51: 3.433262 | F51: 3.015679 | G51: 2.684941 | H51: 2.64967 | I51: 2.674637 | J51: 2.749986 | K51: 2.804769 | L51: 2.901679 | M51: 2.961337 | N51: 2.994839 | O51: 3.013569 | P51: 3.046341 | Q51: 3.039761 | R51: 3.019435 | S51: 3.015147 | T51: 2.99057 | U51: 2.965697 | V51: 2.937553 | W51: 2.921646 | X51: 2.922298 | Y51: 2.923243 | Z51: 2.907824 | AA51: 2.925534 | AB51: 2.901988 | AC51: 2.885729 | AD51: 2.888961 | AE51: 2.848796 | AF51: 2.809709 | AG51: 2.824214 | AH51: 0.004783
A52: PRC000:ga_SteamCoal | B52: Steam Coal | C52: 1.91399 | D52: 1.992829 | E52: 1.997653 | F52: 1.922558 | G52: 1.888824 | H52: 1.808135 | I52: 1.788723 | J52: 1.771312 | K52: 1.730594 | L52: 1.724651 | M52: 1.720315 | N52: 1.724638 | O52: 1.700455 | P52: 1.685458 | Q52: 1.680244 | R52: 1.665702 | S52: 1.655894 | T52: 1.654502 | U52: 1.667736 | V52: 1.664871 | W52: 1.663831 | X52: 1.66272 | Y52: 1.657685 | Z52: 1.656195 | AA52: 1.653838 | AB52: 1.64913 | AC52: 1.647008 | AD52: 1.644727 | AE52: 1.634284 | AF52: 1.631901 | AG52: 1.630677 | AH52: -0.005326
A53: PRC000:ga_uranium | B53: Uranium | C53: 0.686123 | D53: 0.687129 | E53: 0.688135 | F53: 0.690147 | G53: 0.691153 | H53: 0.693165 | I53: 0.694171 | J53: 0.696183 | K53: 0.697189 | L53: 0.699201 | M53: 0.701213 | N53: 0.702219 | O53: 0.704231 | P53: 0.706243 | Q53: 0.70725 | R53: 0.709262 | S53: 0.711274 | T53: 0.71228 | U53: 0.714292 | V53: 0.716304 | W53: 0.718316 | X53: 0.720328 | Y53: 0.72234 | Z53: 0.724352 | AA53: 0.726364 | AB53: 0.728376 | AC53: 0.730389 | AD53: 0.732401 | AE53: 0.734413 | AF53: 0.736425 | AG53: 0.738437 | AH53: 0.002452
B56: Average Price to All Users 9/
A57: PRC000:ha_LiquefiedPetr | B57: Propane | C57: 14.345899 | D57: 14.713685 | E57: 15.243047 | F57: 14.460915 | G57: 14.47782 | H57: 14.54909 | I57: 14.412589 | J57: 14.35487 | K57: 14.495398 | L57: 14.655359 | M57: 15.206007 | N57: 15.418427 | O57: 15.603514 | P57: 15.762777 | Q57: 15.921435 | R57: 15.985692 | S57: 16.117588 | T57: 16.395573 | U57: 16.597931 | V57: 16.714836 | W57: 16.862282 | X57: 17.012253 | Y57: 17.148232 | Z57: 17.174129 | AA57: 17.31028 | AB57: 17.405563 | AC57: 17.561203 | AD57: 17.719315 | AE57: 17.866386 | AF57: 18.056528 | AG57: 18.22818 | AH57: 0.008015
A58: PRC000:ha_Ethanol(E85) | B58: E85 3/ | C58: 21.197994 | D58: 22.2544 | E58: 23.610071 | F58: 23.112133 | G58: 22.835497 | H58: 22.609148 | I58: 22.527273 | J58: 23.046518 | K58: 23.283846 | L58: 23.639156 | M58: 24.640181 | N58: 24.558275 | O58: 24.877409 | P58: 25.090036 | Q58: 25.61343 | R58: 25.3027 | S58: 25.378855 | T58: 25.66387 | U58: 25.927429 | V58: 25.975618 | W58: 26.159891 | X58: 26.357864 | Y58: 26.34479 | Z58: 26.476631 | AA58: 26.680527 | AB58: 26.959341 | AC58: 27.088846 | AD58: 27.212555 | AE58: 27.351645 | AF58: 27.548573 | AG58: 27.76218 | AH58: 0.009033
A59: PRC000:ha_MotorGasoline | B59: Motor Gasoline 4/ | C59: 18.741726 | D59: 19.573618 | E59: 19.847181 | F59: 19.73012 | G59: 19.552361 | H59: 19.410414 | I59: 19.379324 | J59: 19.811895 | K59: 19.996117 | L59: 20.277868 | M59: 21.256985 | N59: 21.163912 | O59: 21.433542 | P59: 21.589588 | Q59: 22.011629 | R59: 21.731033 | S59: 21.780111 | T59: 22.01232 | U59: 22.22261 | V59: 22.25421 | W59: 22.401754 | X59: 22.55514 | Y59: 22.531652 | Z59: 22.631084 | AA59: 22.79184 | AB59: 23.004425 | AC59: 23.083075 | AD59: 23.182411 | AE59: 23.269247 | AF59: 23.436558 | AG59: 23.606295 | AH59: 0.007722
A60: PRC000:ha_JetFuel | B60: Jet Fuel 5/ | C60: 9.568654 | D60: 10.382089 | E60: 11.359349 | F60: 12.190462 | G60: 12.696321 | H60: 12.90303 | I60: 13.260797 | J60: 13.761744 | K60: 14.027101 | L60: 14.319986 | M60: 14.720232 | N60: 14.946351 | O60: 15.259788 | P60: 15.467662 | Q60: 15.60177 | R60: 15.515354 | S60: 15.477219 | T60: 15.705438 | U60: 15.944727 | V60: 15.870375 | W60: 16.294031 | X60: 16.474258 | Y60: 16.612787 | Z60: 16.803795 | AA60: 17.055935 | AB60: 17.333384 | AC60: 17.508017 | AD60: 17.640877 | AE60: 17.718878 | AF60: 17.919552 | AG60: 18.07815 | AH60: 0.021433
A61: PRC000:ha_DistillateFue | B61: Distillate Fuel Oil | C61: 18.18478 | D61: 18.15044 | E61: 18.691107 | F61: 19.695511 | G61: 19.908745 | H61: 19.860836 | I61: 19.983017 | J61: 20.39817 | K61: 20.586687 | L61: 20.817989 | M61: 21.381784 | N61: 21.479427 | O61: 21.722721 | P61: 21.850819 | Q61: 21.951105 | R61: 21.765625 | S61: 21.643816 | T61: 21.794834 | U61: 21.965029 | V61: 21.811846 | W61: 22.161392 | X61: 22.2794 | Y61: 22.364939 | Z61: 22.489794 | AA61: 22.653406 | AB61: 22.892004 | AC61: 23.013697 | AD61: 23.111158 | AE61: 23.160799 | AF61: 23.327538 | AG61: 23.461897 | AH61: 0.008529
A62: PRC000:ha_ResidualFuel | B62: Residual Fuel Oil | C62: 8.844019 | D62: 6.948499 | E62: 7.206591 | F62: 8.25698 | G62: 9.405904 | H62: 9.492084 | I62: 9.799534 | J62: 10.292654 | K62: 10.398303 | L62: 11.087937 | M62: 11.440717 | N62: 11.198093 | O62: 11.482384 | P62: 11.61646 | Q62: 12.002509 | R62: 11.670424 | S62: 11.776406 | T62: 11.921858 | U62: 12.109484 | V62: 12.24009 | W62: 12.432967 | X62: 12.48371 | Y62: 12.711926 | Z62: 13.016186 | AA62: 13.303496 | AB62: 13.280558 | AC62: 13.835614 | AD62: 13.919657 | AE62: 13.972843 | AF62: 14.140263 | AG62: 14.360459 | AH62: 0.016289
A63: PRC000:ha_NaturalGas | B63: Natural Gas | C63: 4.530272 | D63: 5.529237 | E63: 5.402839 | F63: 4.962407 | G63: 4.613622 | H63: 4.517911 | I63: 4.519835 | J63: 4.582997 | K63: 4.636856 | L63: 4.725906 | M63: 4.861133 | N63: 4.885196 | O63: 4.905554 | P63: 4.944284 | Q63: 4.935405 | R63: 4.914975 | S63: 4.904593 | T63: 4.873412 | U63: 4.838724 | V63: 4.80314 | W63: 4.778995 | X63: 4.771886 | Y63: 4.765336 | Z63: 4.737822 | AA63: 4.729506 | AB63: 4.70147 | AC63: 4.684419 | AD63: 4.685564 | AE63: 4.644473 | AF63: 4.617917 | AG63: 4.625296 | AH63: 0.000692
A64: PRC000:ha_Metallugical | B64: Metallurgical Coal | C64: 4.0174 | D64: 3.598935 | E64: 3.356058 | F64: 3.207879 | G64: 3.117534 | H64: 3.070951 | I64: 3.029583 | J64: 3.01361 | K64: 3.014059 | L64: 3.036777 | M64: 3.066812 | N64: 3.102134 | O64: 3.137037 | P64: 3.169176 | Q64: 3.199574 | R64: 3.23061 | S64: 3.261404 | T64: 3.294469 | U64: 3.328295 | V64: 3.36151 | W64: 3.395033 | X64: 3.429636 | Y64: 3.466346 | Z64: 3.505546 | AA64: 3.545559 | AB64: 3.58672 | AC64: 3.624724 | AD64: 3.661516 | AE64: 3.699104 | AF64: 3.737599 | AG64: 3.780184 | AH64: -0.002027
A65: PRC000:ha_Coal | B65: Other Coal | C65: 1.973834 | D65: 2.037621 | E65: 2.043919 | F65: 1.983716 | G65: 1.96444 | H65: 1.912539 | I65: 1.892117 | J65: 1.877834 | K65: 1.838427 | L65: 1.831164 | M65: 1.826424 | N65: 1.831034 | O65: 1.809595 | P65: 1.795457 | Q65: 1.792116 | R65: 1.78228 | S65: 1.775267 | T65: 1.77634 | U65: 1.791125 | V65: 1.789499 | W65: 1.790528 | X65: 1.791391 | Y65: 1.789991 | Z65: 1.79127 | AA65: 1.792075 | AB65: 1.793719 | AC65: 1.794313 | AD65: 1.794798 | AE65: 1.789883 | AF65: 1.791704 | AG65: 1.792621 | AH65: -0.003205
A66: PRC000:ha_CoaltoLiquids | B66: Coal to Liquids | C66: -- | D66: -- | E66: -- | F66: -- | G66: -- | H66: -- | I66: -- | J66: -- | K66: -- | L66: -- | M66: -- | N66: -- | O66: -- | P66: -- | Q66: -- | R66: -- | S66: -- | T66: -- | U66: -- | V66: -- | W66: -- | X66: -- | Y66: -- | Z66: -- | AA66: -- | AB66: -- | AC66: -- | AD66: -- | AE66: -- | AF66: -- | AG66: -- | AH66: --
A67: PRC000:ha_Electricity | B67: Electricity | C67: 30.523893 | D67: 31.073757 | E67: 30.6444 | F67: 30.064251 | G67: 29.625053 | H67: 29.354122 | I67: 29.175064 | J67: 29.083216 | K67: 28.98082 | L67: 28.902288 | M67: 28.841974 | N67: 28.919064 | O67: 28.86585 | P67: 28.82501 | Q67: 28.718842 | R67: 28.568573 | S67: 28.42029 | T67: 28.288023 | U67: 28.189095 | V67: 28.082899 | W67: 27.978746 | X67: 27.888968 | Y67: 27.78153 | Z67: 27.658247 | AA67: 27.550392 | AB67: 27.461987 | AC67: 27.334007 | AD67: 27.199772 | AE67: 27.024487 | AF67: 26.797375 | AG67: 26.609512 | AH67: -0.004564
B69: Non-Renewable Energy Expenditures by Sector
B70: (billion 2020 dollars)
A71: PRC000:ia_Residential | B71: Residential | C71: 246.6207 | D71: 253.13023 | E71: 252.01663 | F71: 249.83353 | G71: 248.12788 | H71: 248.28451 | I71: 249.34052 | J71: 250.65616 | K71: 251.75119 | L71: 253.27866 | M71: 256.01141 | N71: 257.78015 | O71: 259.22812 | P71: 260.54663 | Q71: 261.63565 | R71: 262.25629 | S71: 263.1326 | T71: 264.25726 | U71: 265.39078 | V71: 266.38806 | W71: 267.52377 | X71: 268.83185 | Y71: 270.06149 | Z71: 271.15643 | AA71: 272.41125 | AB71: 273.90283 | AC71: 274.91461 | AD71: 275.87061 | AE71: 276.51178 | AF71: 276.92877 | AG71: 277.66956 | AH71: 0.00396
A72: PRC000:ia_Commercial | B72: Commercial | C72: 173.48148 | D72: 181.11337 | E72: 182.81439 | F72: 182.45297 | G72: 182.73657 | H72: 184.55039 | I72: 184.2793 | J72: 184.96017 | K72: 185.21028 | L72: 185.74585 | M72: 187.11746 | N72: 187.96493 | O72: 188.46733 | P72: 189.285 | Q72: 189.63022 | R72: 189.46245 | S72: 189.41785 | T72: 189.78436 | U72: 190.24286 | V72: 190.58105 | W72: 191.09221 | X72: 191.86337 | Y72: 192.50102 | Z72: 193.29668 | AA72: 194.11905 | AB72: 195.20566 | AC72: 196.03664 | AD72: 196.9303 | AE72: 197.60815 | AF72: 198.31926 | AG72: 199.38541 | AH72: 0.00465
A73: PRC000:ia_Industrial | B73: Industrial 1/ | C73: 151.84804 | D73: 165.11462 | E73: 170.16429 | F73: 170.95889 | G73: 172.68074 | H73: 175.70645 | I73: 177.85625 | J73: 181.78732 | K73: 185.88344 | L73: 190.06396 | M73: 195.25731 | N73: 199.51869 | O73: 203.37735 | P73: 206.16083 | Q73: 209.28558 | R73: 212.13353 | S73: 214.53505 | T73: 218.42818 | U73: 221.85586 | V73: 223.43198 | W73: 226.55086 | X73: 230.10513 | Y73: 233.68272 | Z73: 237.01584 | AA73: 241.07835 | AB73: 245.14499 | AC73: 248.45346 | AD73: 251.57375 | AE73: 254.08211 | AF73: 258.03217 | AG73: 262.57321 | AH73: 0.018423
A74: PRC000:ia_Transportatio | B74: Transportation | C74: 411.84992 | D74: 447.95297 | E74: 465.37207 | F74: 477.4696 | G74: 482.10873 | H74: 482.54916 | I74: 484.44397 | J74: 494.09119 | K74: 497.25134 | L74: 502.08032 | M74: 520.23267 | N74: 517.75806 | O74: 523.00543 | P74: 525.63324 | Q74: 532.64874 | R74: 527.36926 | S74: 527.97565 | T74: 533.87903 | U74: 539.88324 | V74: 540.74921 | W74: 548.76001 | X74: 554.73199 | Y74: 558.28699 | Z74: 564.58496 | AA74: 571.83954 | AB74: 580.52154 | AC74: 586.19775 | AD74: 591.22278 | AE74: 595.93066 | AF74: 603.30054 | AG74: 610.66248 | AH74: 0.013216
A75: PRC000:ia_TotalNon-Rene | B75: Total Non-Renewable Expenditures | C75: 983.80011 | D75: 1047.3112 | E75: 1070.3674 | F75: 1080.715 | G75: 1085.6539 | H75: 1091.0906 | I75: 1095.92 | J75: 1111.4949 | K75: 1120.0962 | L75: 1131.1688 | M75: 1158.6189 | N75: 1163.0219 | O75: 1174.0781 | P75: 1181.6257 | Q75: 1193.2002 | R75: 1191.2216 | S75: 1195.0612 | T75: 1206.3489 | U75: 1217.3728 | V75: 1221.1504 | W75: 1233.9268 | X75: 1245.5323 | Y75: 1254.5322 | Z75: 1266.054 | AA75: 1279.4482 | AB75: 1294.775 | AC75: 1305.6024 | AD75: 1315.5974 | AE75: 1324.1327 | AF75: 1336.5808 | AG75: 1350.2906 | AH75: 0.010611
A76: PRC000:ja_Transportatio | B76: Transportation Renewable Expenditures | C76: 0.641505 | D76: 0.724327 | E76: 0.7319 | F76: 0.747163 | G76: 0.737895 | H76: 0.725906 | I76: 0.715617 | J76: 0.718177 | K76: 0.711925 | L76: 0.708562 | M76: 0.724556 | N76: 0.711187 | O76: 0.709875 | P76: 0.707981 | Q76: 0.71608 | R76: 0.707236 | S76: 0.709616 | T76: 0.719833 | U76: 0.73005 | V76: 0.738035 | W76: 0.751175 | X76: 0.765134 | Y76: 0.774439 | Z76: 0.787946 | AA76: 0.804366 | AB76: 0.821308 | AC76: 0.834072 | AD76: 0.850394 | AE76: 0.864071 | AF76: 0.884526 | AG76: 0.904505 | AH76: 0.011518
A77: PRC000:ja_TotalExpendit | B77: Total Expenditures | C77: 984.44159 | D77: 1048.0355 | E77: 1071.0994 | F77: 1081.4622 | G77: 1086.3918 | H77: 1091.8165 | I77: 1096.6356 | J77: 1112.213 | K77: 1120.8081 | L77: 1131.8774 | M77: 1159.3435 | N77: 1163.733 | O77: 1174.788 | P77: 1182.3337 | Q77: 1193.9163 | R77: 1191.9288 | S77: 1195.7708 | T77: 1207.0687 | U77: 1218.1029 | V77: 1221.8884 | W77: 1234.678 | X77: 1246.2975 | Y77: 1255.3066 | Z77: 1266.8419 | AA77: 1280.2526 | AB77: 1295.5963 | AC77: 1306.4365 | AD77: 1316.4478 | AE77: 1324.9967 | AF77: 1337.4653 | AG77: 1351.1952 | AH77: 0.010612
B80: Prices in Nominal Dollars
B81: Residential
A82: PRC000:nom_R_LiquefiedP | B82: Propane | C82: 17.296467 | D82: 17.364542 | E82: 17.773216 | F82: 17.895594 | G82: 18.20512 | H82: 18.688913 | I82: 19.072323 | J82: 19.563379 | K82: 20.288092 | L82: 21.121529 | M82: 22.49015 | N82: 23.541407 | O82: 24.573856 | P82: 25.557503 | Q82: 26.52951 | R82: 27.389929 | S82: 28.309729 | T82: 29.424145 | U82: 30.513109 | V82: 31.49655 | W82: 32.537384 | X82: 33.617428 | Y82: 34.722183 | Z82: 35.721493 | AA82: 36.903725 | AB82: 38.092831 | AC82: 39.457756 | AD82: 40.901833 | AE82: 42.397968 | AF82: 44.048859 | AG82: 45.773941 | AH82: 0.032972
A83: PRC000:nom_R_Distillate | B83: Distillate Fuel Oil | C83: 17.748362 | D83: 17.966434 | E83: 19.259716 | F83: 20.916285 | G83: 22.016247 | H83: 22.974073 | I83: 24.235168 | J83: 25.399334 | K83: 26.390614 | L83: 27.482574 | M83: 28.736801 | N83: 29.729197 | O83: 30.882408 | P83: 31.928686 | Q83: 32.905087 | R83: 33.503971 | S83: 34.16716 | T83: 35.212048 | U83: 36.301605 | V83: 36.896996 | W83: 38.326675 | X83: 39.418179 | Y83: 40.484432 | Z83: 41.665268 | AA83: 42.998383 | AB83: 44.508553 | AC83: 45.914009 | AD83: 47.318893 | AE83: 48.675186 | AF83: 50.354439 | AG83: 52.064827 | AH83: 0.036524
A84: PRC000:nom_R_NaturalGas | B84: Natural Gas | C84: 10.141716 | D84: 10.625046 | E84: 10.428921 | F84: 10.267519 | G84: 10.164536 | H84: 10.396891 | I84: 10.74641 | J84: 11.182247 | K84: 11.60196 | L84: 12.131678 | M84: 12.946251 | N84: 13.433338 | O84: 13.929442 | P84: 14.423272 | Q84: 14.851999 | R84: 15.235919 | S84: 15.627309 | T84: 16.018497 | U84: 16.378679 | V84: 16.725304 | W84: 17.100847 | X84: 17.530432 | Y84: 17.981056 | Z84: 18.441963 | AA84: 18.947731 | AB84: 19.460142 | AC84: 19.991085 | AD84: 20.545118 | AE84: 21.06374 | AF84: 21.659649 | AG84: 22.326521 | AH84: 0.026653
A85: PRC000:nom_R_Electricit | B85: Electricity | C85: 35.768967 | D85: 36.958694 | E85: 37.005428 | F85: 37.129112 | G85: 37.453621 | H85: 38.064835 | I85: 38.925762 | J85: 39.997341 | K85: 41.131058 | L85: 42.347912 | M85: 43.61792 | N85: 45.059521 | O85: 46.362289 | P85: 47.614605 | Q85: 48.764801 | R85: 49.783447 | S85: 50.813431 | T85: 51.841217 | U85: 52.915726 | V85: 53.969807 | W85: 55.068424 | X85: 56.238846 | Y85: 57.424133 | Z85: 58.644146 | AA85: 59.952782 | AB85: 61.380295 | AC85: 62.780964 | AD85: 64.219398 | AE85: 65.604782 | AF85: 66.922249 | AG85: 68.370926 | AH85: 0.02183
B87: Commercial
A88: PRC000:nom_C_LiquefiedG | B88: Propane | C88: 12.770181 | D88: 13.739795 | E88: 14.44624 | F88: 14.444918 | G88: 14.740237 | H88: 15.184672 | I88: 15.405874 | J88: 15.808756 | K88: 16.50246 | L88: 17.228308 | M88: 18.59107 | N88: 19.380161 | O88: 20.164705 | P88: 20.914408 | Q88: 21.670685 | R88: 22.283958 | S88: 23.028175 | T88: 24.014372 | U88: 24.860586 | V88: 25.563795 | W88: 26.37215 | X88: 27.21916 | Y88: 28.073462 | Z88: 28.766537 | AA88: 29.744673 | AB88: 30.668356 | AC88: 31.78665 | AD88: 32.939011 | AE88: 34.110699 | AF88: 35.441875 | AG88: 36.791409 | AH88: 0.035901
A89: PRC000:nom_C_Distillate | B89: Distillate Fuel Oil | C89: 17.825056 | D89: 18.093426 | E89: 18.315351 | F89: 18.926201 | G89: 18.937216 | H89: 18.747389 | I89: 18.800863 | J89: 19.811499 | K89: 20.634888 | L89: 21.550406 | M89: 22.952717 | N89: 23.777868 | O89: 24.805574 | P89: 25.688957 | Q89: 26.508257 | R89: 26.943041 | S89: 27.453497 | T89: 28.341854 | U89: 29.279222 | V89: 29.723133 | W89: 30.995951 | X89: 31.923767 | Y89: 32.816875 | Z89: 33.830505 | AA89: 34.985626 | AB89: 36.306683 | AC89: 37.50856 | AD89: 38.701534 | AE89: 39.855164 | AF89: 41.30336 | AG89: 42.757435 | AH89: 0.029594
A90: PRC000:nom_C_ResidualFu | B90: Residual Fuel Oil | C90: 5.24652 | D90: 4.137457 | E90: 5.270087 | F90: 6.617117 | G90: 7.813646 | H90: 8.700063 | I90: 9.709266 | J90: 10.525226 | K90: 10.966917 | L90: 11.607101 | M90: 12.393723 | N90: 12.86831 | O90: 13.590438 | P90: 14.201473 | Q90: 14.803964 | R90: 15.042674 | S90: 15.423155 | T90: 16.058147 | U90: 16.700855 | V90: 17.063044 | W90: 17.975677 | X90: 18.618505 | Y90: 19.266331 | Z90: 19.944061 | AA90: 20.865662 | AB90: 21.718767 | AC90: 22.665752 | AD90: 23.490469 | AE90: 24.193407 | AF90: 25.147209 | AG90: 26.069181 | AH90: 0.054893
A91: PRC000:nom_C_NaturalGas | B91: Natural Gas | C91: 7.227466 | D91: 7.839015 | E91: 7.930861 | F91: 7.698619 | G91: 7.535708 | H91: 7.684878 | I91: 7.931843 | J91: 8.244377 | K91: 8.539219 | L91: 8.93887 | M91: 9.525496 | N91: 9.864672 | O91: 10.212051 | P91: 10.574384 | Q91: 10.876677 | R91: 11.138861 | S91: 11.410228 | T91: 11.681154 | U91: 11.921187 | V91: 12.14992 | W91: 12.406116 | X91: 12.713491 | Y91: 13.036792 | Z91: 13.364729 | AA91: 13.730934 | AB91: 14.098891 | AC91: 14.475825 | AD91: 14.866691 | AE91: 15.214554 | AF91: 15.629021 | AG91: 16.106098 | AH91: 0.02707
A92: PRC000:nom_C_Electricit | B92: Electricity | C92: 31.322283 | D92: 32.086353 | E92: 32.066811 | F92: 31.870663 | G92: 31.975525 | H92: 32.408691 | I92: 32.988792 | J92: 33.828213 | K92: 34.687374 | L92: 35.603916 | M92: 36.579319 | N92: 37.768948 | O92: 38.715565 | P92: 39.733307 | Q92: 40.563961 | R92: 41.309269 | S92: 42.00713 | T92: 42.720234 | U92: 43.488796 | V92: 44.238426 | W92: 45.010628 | X92: 45.822861 | Y92: 46.626328 | Z92: 47.491955 | AA92: 48.364853 | AB92: 49.332256 | AC92: 50.317883 | AD92: 51.291096 | AE92: 52.220596 | AF92: 53.113724 | AG92: 54.145847 | AH92: 0.018412
B94: Industrial 1/
A95: PRC000:nom_I_LiquefiedP | B95: Propane | C95: 7.622427 | D95: 8.585755 | E95: 9.195073 | F95: 9.105658 | G95: 9.31348 | H95: 9.636194 | I95: 9.716459 | J95: 9.964232 | K95: 10.478424 | L95: 11.003137 | M95: 11.877894 | N95: 12.436106 | O95: 12.964437 | P95: 13.503829 | Q95: 14.056269 | R95: 14.46874 | S95: 15.020927 | T95: 15.816492 | U95: 16.458099 | V95: 16.961691 | W95: 17.571985 | X95: 18.214462 | Y95: 18.855173 | Z95: 19.31757 | AA95: 20.069984 | AB95: 20.747753 | AC95: 21.610123 | AD95: 22.491508 | AE95: 23.381889 | AF95: 24.425053 | AG95: 25.466816 | AH95: 0.041029
A96: PRC000:nom_I_Distillate | B96: Distillate Fuel Oil | C96: 17.750837 | D96: 17.971844 | E96: 18.228767 | F96: 18.908209 | G96: 18.924597 | H96: 18.74519 | I96: 18.809263 | J96: 19.826265 | K96: 20.653816 | L96: 21.577911 | M96: 22.642855 | N96: 23.474722 | O96: 24.441145 | P96: 25.320295 | Q96: 26.142385 | R96: 26.564394 | S96: 27.064281 | T96: 27.944525 | U96: 28.875128 | V96: 29.305321 | W96: 30.566803 | X96: 31.488558 | Y96: 32.374752 | Z96: 33.386532 | AA96: 34.533226 | AB96: 35.851814 | AC96: 37.046463 | AD96: 38.240196 | AE96: 39.394962 | AF96: 40.843708 | AG96: 42.29126 | AH96: 0.029361
A97: PRC000:nom_I_ResidualFu | B97: Residual Fuel Oil | C97: 5.42274 | D97: 4.478096 | E97: 5.935693 | F97: 7.615757 | G97: 9.063412 | H97: 10.318466 | I97: 11.784514 | J97: 12.62663 | K97: 13.233867 | L97: 13.933397 | M97: 14.765164 | N97: 15.340495 | O97: 16.080996 | P97: 16.774212 | Q97: 17.417721 | R97: 17.714138 | S97: 18.1371 | T97: 18.836687 | U97: 19.575224 | V97: 19.983976 | W97: 20.962624 | X97: 21.686935 | Y97: 22.380941 | Z97: 23.10383 | AA97: 24.086798 | AB97: 25.05735 | AC97: 25.998363 | AD97: 26.868773 | AE97: 27.697334 | AF97: 28.733341 | AG97: 29.87524 | AH97: 0.05853
A98: PRC000:nom_I_NaturalGas | B98: Natural Gas 2/ | C98: 3.058431 | D98: 4.087736 | E98: 4.067672 | F98: 3.691466 | G98: 3.394789 | H98: 3.40839 | I98: 3.527498 | J98: 3.739697 | K98: 3.926109 | L98: 4.17353 | M98: 4.36765 | N98: 4.536004 | O98: 4.69715 | P98: 4.889965 | Q98: 5.019726 | R98: 5.117745 | S98: 5.232636 | T98: 5.336368 | U98: 5.432676 | V98: 5.514288 | W98: 5.60789 | X98: 5.737049 | Y98: 5.875242 | Z98: 5.998192 | AA98: 6.169134 | AB98: 6.291267 | AC98: 6.433225 | AD98: 6.630484 | AE98: 6.74983 | AF98: 6.888884 | AG98: 7.117157 | AH98: 0.028554
A99: PRC000:nom_I_Metallurgi | B99: Metallurgical Coal | C99: 4.0174 | D99: 3.636905 | E99: 3.430643 | F99: 3.322526 | G99: 3.283937 | H99: 3.304898 | I99: 3.343487 | J99: 3.42118 | K99: 3.523924 | L99: 3.65996 | M99: 3.809521 | N99: 3.969496 | O99: 4.130013 | P99: 4.288495 | Q99: 4.443704 | R99: 4.599765 | S99: 4.756515 | T99: 4.917583 | U99: 5.08305 | V99: 5.248307 | W99: 5.421515 | X99: 5.602237 | Y99: 5.793986 | Z99: 5.999776 | AA99: 6.218966 | AB99: 6.448829 | AC99: 6.689032 | AD99: 6.937432 | AE99: 7.197502 | AF99: 7.473462 | AG99: 7.771885 | AH99: 0.02224
A100: PRC000:nom_I_SteamCoal | B100: Other Industrial Coal | C100: 2.815477 | D100: 2.8577 | E100: 2.948766 | F100: 2.976388 | G100: 3.026943 | H100: 3.079853 | I100: 3.144352 | J100: 3.221121 | K100: 3.303776 | L100: 3.399484 | M100: 3.515678 | N100: 3.61999 | O100: 3.706996 | P100: 3.811179 | Q100: 3.912488 | R100: 4.016845 | S100: 4.117596 | T100: 4.221014 | U100: 4.317785 | V100: 4.417277 | W100: 4.53143 | X100: 4.640117 | Y100: 4.754814 | Z100: 4.877342 | AA100: 4.992728 | AB100: 5.138436 | AC100: 5.279489 | AD100: 5.437367 | AE100: 5.602487 | AF100: 5.77569 | AG100: 5.963869 | AH100: 0.025335
A101: PRC000:nom_I_CoaltoLiqu | B101: Coal to Liquids | C101: -- | D101: -- | E101: -- | F101: -- | G101: -- | H101: -- | I101: -- | J101: -- | K101: -- | L101: -- | M101: -- | N101: -- | O101: -- | P101: -- | Q101: -- | R101: -- | S101: -- | T101: -- | U101: -- | V101: -- | W101: -- | X101: -- | Y101: -- | Z101: -- | AA101: -- | AB101: -- | AC101: -- | AD101: -- | AE101: -- | AF101: -- | AG101: -- | AH101: --
A102: PRC000:nom_I_Electricit | B102: Electricity | C102: 20.703951 | D102: 21.184431 | E102: 20.922766 | F102: 20.490692 | G102: 20.390978 | H102: 20.56181 | I102: 20.928827 | J102: 21.389219 | K102: 21.904938 | L102: 22.493555 | M102: 23.126232 | N102: 23.898823 | O102: 24.533018 | P102: 25.095577 | Q102: 25.619421 | R102: 26.129232 | S102: 26.601374 | T102: 27.053902 | U102: 27.557926 | V102: 28.009596 | W102: 28.483612 | X102: 28.995356 | Y102: 29.524231 | Z102: 30.04048 | AA102: 30.675072 | AB102: 31.286566 | AC102: 31.906498 | AD102: 32.552177 | AE102: 33.172356 | AF102: 33.776855 | AG102: 34.495876 | AH102: 0.017163
B105: Transportation
A106: PRC000:nom_T_LiquefiedP | B106: Propane | C106: 11.989126 | D106: 13.055498 | E106: 13.684998 | F106: 13.646472 | G106: 13.932609 | H106: 14.35027 | I106: 14.551661 | J106: 14.940968 | K106: 15.597754 | L106: 16.266991 | M106: 17.803009 | N106: 18.508293 | O106: 19.266905 | P106: 19.95755 | Q106: 20.655188 | R106: 21.217951 | S106: 21.911341 | T106: 22.821793 | U106: 23.585032 | V106: 24.222187 | W106: 24.967777 | X106: 25.745121 | Y106: 26.527178 | Z106: 27.162399 | AA106: 28.074911 | AB106: 28.923811 | AC106: 29.956638 | AD106: 31.013227 | AE106: 32.086063 | AF106: 33.307343 | AG106: 34.538723 | AH106: 0.035899
A107: PRC000:nom_T_Ethan(E85) | B107: E85 3/ | C107: 21.197994 | D107: 22.489187 | E107: 24.134783 | F107: 23.938148 | G107: 24.054377 | H107: 24.331526 | I107: 24.861383 | J107: 26.163397 | K107: 27.222589 | L107: 28.490194 | M107: 30.607447 | N107: 31.424812 | O107: 32.751942 | P107: 33.951576 | Q107: 35.573013 | R107: 36.026157 | S107: 37.013168 | T107: 38.307907 | U107: 39.596973 | V107: 40.555588 | W107: 41.774628 | X107: 43.055012 | Y107: 44.035229 | Z107: 45.315018 | AA107: 46.798065 | AB107: 48.472187 | AC107: 49.989506 | AD107: 51.559319 | AE107: 53.219242 | AF107: 55.084354 | AG107: 57.077778 | AH107: 0.033568
A108: PRC000:nom_T_MotorGasol | B108: Motor Gasoline 4/ | C108: 18.753328 | D108: 19.788212 | E108: 20.293282 | F108: 20.436584 | G108: 20.593464 | H108: 20.882582 | I108: 21.37652 | J108: 22.48011 | K108: 23.366943 | L108: 24.426805 | M108: 26.396181 | N108: 27.072281 | O108: 28.209209 | P108: 29.205608 | Q108: 30.561083 | R108: 30.930744 | S108: 31.754171 | T108: 32.846405 | U108: 33.927547 | V108: 34.733677 | W108: 35.761009 | X108: 36.83062 | Y108: 37.648449 | Z108: 38.719551 | AA108: 39.962944 | AB108: 41.346458 | AC108: 42.581745 | AD108: 43.907246 | AE108: 45.259014 | AF108: 46.84462 | AG108: 48.515076 | AH108: 0.032191
A109: PRC000:nom_T_JetFuel | B109: Jet Fuel 5/ | C109: 9.568654 | D109: 10.491621 | E109: 11.611799 | F109: 12.626143 | G109: 13.374006 | H109: 13.885991 | I109: 14.634782 | J109: 15.622922 | K109: 16.399954 | L109: 17.258619 | M109: 18.285124 | N109: 19.125378 | O109: 20.090021 | P109: 20.930677 | Q109: 21.668398 | R109: 22.090868 | S109: 22.572369 | T109: 23.443169 | U109: 24.351158 | V109: 24.778328 | W109: 26.019875 | X109: 26.910351 | Y109: 27.768221 | Z109: 28.759863 | AA109: 29.916378 | AB109: 31.164968 | AC109: 32.309132 | AD109: 33.423969 | AE109: 34.476364 | AF109: 35.830788 | AG109: 37.16785 | AH109: 0.04627
A110: PRC000:nom_T_Distillate | B110: Diesel Fuel (distillate fuel oil) 6/ | C110: 18.329231 | D110: 18.466091 | E110: 19.441296 | F110: 20.906368 | G110: 21.550484 | H110: 22.240688 | I110: 22.925701 | J110: 24.184679 | K110: 25.177448 | L110: 26.206684 | M110: 27.881655 | N110: 28.911507 | O110: 30.105221 | P110: 31.156677 | Q110: 32.130554 | R110: 32.564861 | S110: 33.237152 | T110: 34.297997 | U110: 35.361176 | V110: 35.931492 | W110: 37.292427 | X110: 38.340878 | Y110: 39.357944 | Z110: 40.492893 | AA110: 41.785236 | AB110: 43.21402 | AC110: 44.615162 | AD110: 46.015656 | AE110: 47.406441 | AF110: 49.013824 | AG110: 50.694832 | AH110: 0.034492
A111: PRC000:nom_T_ResidualFu | B111: Residual Fuel Oil | C111: 9.208066 | D111: 7.063352 | E111: 7.302988 | F111: 8.481062 | G111: 9.849035 | H111: 10.089943 | I111: 10.639123 | J111: 11.495901 | K111: 11.956233 | L111: 13.219588 | M111: 14.070412 | N111: 14.140808 | O111: 14.921721 | P111: 15.509969 | Q111: 16.500456 | R111: 16.410965 | S111: 16.978367 | T111: 17.589258 | U111: 18.293514 | V111: 18.921209 | W111: 19.635923 | X111: 20.176897 | Y111: 21.054981 | Z111: 22.139013 | AA111: 23.220079 | AB111: 23.7334 | AC111: 25.473278 | AD111: 26.305943 | AE111: 27.115713 | AF111: 28.203957 | AG111: 29.465542 | AH111: 0.039533
A112: PRC000:nom_T_NaturalGas | B112: Natural Gas 7/ | C112: 12.999203 | D112: 13.756338 | E112: 14.272468 | F112: 13.87274 | G112: 13.379067 | H112: 13.404615 | I112: 13.498897 | J112: 13.628196 | K112: 13.736962 | L112: 13.932218 | M112: 14.950909 | N112: 15.044097 | O112: 15.321702 | P112: 15.516894 | Q112: 15.691061 | R112: 15.773815 | S112: 15.950137 | T112: 16.117809 | U112: 16.291615 | V112: 16.466549 | W112: 16.700438 | X112: 16.943705 | Y112: 17.277073 | Z112: 17.574244 | AA112: 17.982027 | AB112: 18.336407 | AC112: 18.741673 | AD112: 19.208071 | AE112: 19.600466 | AF112: 20.057381 | AG112: 20.632099 | AH112: 0.015518
A113: PRC000:nom_T_Electricit | B113: Electricity | C113: 34.881683 | D113: 36.816513 | E113: 36.169003 | F113: 35.738602 | G113: 35.579834 | H113: 36.129082 | I113: 36.963623 | J113: 37.989132 | K113: 39.081032 | L113: 40.300076 | M113: 41.404995 | N113: 42.946102 | O113: 44.248558 | P113: 45.525314 | Q113: 46.634274 | R113: 47.531353 | S113: 48.4725 | T113: 49.432987 | U113: 50.387676 | V113: 51.286388 | W113: 52.21426 | X113: 53.183109 | Y113: 54.169323 | Z113: 55.113655 | AA113: 56.153427 | AB113: 57.276478 | AC113: 58.393307 | AD113: 59.57814 | AE113: 60.672661 | AF113: 61.72084 | AG113: 62.874916 | AH113: 0.019834
B115: Electric Power 8/
A116: PRC000:nom_E_Distillate | B116: Distillate Fuel Oil | C116: 17.708588 | D116: 17.922907 | E116: 18.167339 | F116: 18.391798 | G116: 18.371428 | H116: 18.194515 | I116: 18.012846 | J116: 19.005011 | K116: 19.743412 | L116: 20.599808 | M116: 21.649261 | N116: 22.243275 | O116: 23.181122 | P116: 24.023527 | Q116: 24.834677 | R116: 25.286222 | S116: 25.852322 | T116: 26.715048 | U116: 27.47975 | V116: 27.963886 | W116: 29.288336 | X116: 30.202635 | Y116: 31.045172 | Z116: 32.017269 | AA116: 33.168652 | AB116: 34.449997 | AC116: 35.675571 | AD116: 36.849621 | AE116: 38.0271 | AF116: 39.507576 | AG116: 40.923405 | AH116: 0.028315
A117: PRC000:nom_E_ResidualFu | B117: Residual Fuel Oil | C117: 8.29073 | D117: 8.947068 | E117: 9.936648 | F117: 11.076062 | G117: 11.979738 | H117: 12.592653 | I117: 13.356881 | J117: 14.202008 | K117: 14.762341 | L117: 15.47679 | M117: 16.343203 | N117: 16.973457 | O117: 17.722759 | P117: 18.476269 | Q117: 19.074306 | R117: 19.433674 | S117: 19.821852 | T117: 20.536129 | U117: 21.275314 | V117: 21.824587 | W117: 22.77355 | X117: 23.359221 | Y117: 23.897337 | Z117: 24.436132 | AA117: 25.133085 | AB117: 25.60273 | AC117: 26.62406 | AD117: 27.609346 | AE117: 28.527224 | AF117: 29.689737 | AG117: 30.943239 | AH117: 0.044878
A118: PRC000:nom_E_NaturalGas | B118: Natural Gas | C118: 2.447536 | D118: 3.575078 | E118: 3.509563 | F118: 3.123458 | G118: 2.828254 | H118: 2.851523 | I118: 2.951763 | J118: 3.121902 | K118: 3.279229 | L118: 3.497139 | M118: 3.678502 | N118: 3.832201 | O118: 3.967464 | P118: 4.122277 | Q118: 4.221748 | R118: 4.299093 | S118: 4.397367 | T118: 4.46396 | U118: 4.529282 | V118: 4.586386 | W118: 4.665565 | X118: 4.773511 | Y118: 4.886192 | Z118: 4.97677 | AA118: 5.131433 | AB118: 5.217699 | AC118: 5.325298 | AD118: 5.473681 | AE118: 5.543022 | AF118: 5.618113 | AG118: 5.806455 | AH118: 0.029215
A119: PRC000:nom_E_SteamCoal | B119: Steam Coal | C119: 1.91399 | D119: 2.013854 | E119: 2.042048 | F119: 1.991269 | G119: 1.989643 | H119: 1.94588 | I119: 1.974057 | J119: 2.01087 | K119: 2.023345 | L119: 2.078571 | M119: 2.136934 | N119: 2.206849 | O119: 2.238706 | P119: 2.280745 | Q119: 2.333594 | R119: 2.371638 | S119: 2.414998 | T119: 2.46964 | U119: 2.547005 | V119: 2.599354 | W119: 2.656965 | X119: 2.716018 | Y119: 2.770816 | Z119: 2.834594 | AA119: 2.900858 | AB119: 2.965092 | AC119: 3.039372 | AD119: 3.116245 | AE119: 3.179896 | AF119: 3.263045 | AG119: 3.352597 | AH119: 0.01886
...

Sheet BNE
B2: 2022 | C2: 2023
A3: Importación | B3: 7.73 | C3: 7.47
A4: Exportación | B4: -8.72 | C4: -11.2

Sheet Conahcyt
B2: 2020 | C2: 2021
A3: Importación | B3: 35.87 | C3: 6.25
A4: Exportación | B4: -21.44 | C4: -9.7

Sheet Calculations
B2: 2020 | C2: 2021 | D2: 2022 | E2: 2023
A3: Importación | B3: =Conahcyt!B3 -> 35.87 | C3: =Conahcyt!C3 -> 6.25 | D3: =BNE!B3 -> 7.73 | E3: =BNE!C3 -> 7.47
A4: Exportación | B4: =Conahcyt!B4 -> -21.44 | C4: =Conahcyt!C4 -> -9.7 | D4: =BNE!B4 -> -8.72 | E4: =BNE!C4 -> -11.2
A7: Importación | B7: =B3/0.0000036 -> 9963888.9 | C7: =C3/0.0000036 -> 1736111.1 | D7: =D3/0.0000036 -> 2147222.2 | E7: =E3/0.0000036 -> 2075000
A8: Exportación | B8: =-B4/0.0000036 -> 5955555.6 | C8: =-C4/0.0000036 -> 2694444.4 | D8: =-D4/0.0000036 -> 2422222.2 | E8: =-E4/0.0000036 -> 3111111.1

Sheet EIaE-BIE
A1: Imported Electricity (MW*hour) | B1: 2020 | C1: 2021 | D1: 2022 | E1: 2023 | F1: 2024 | G1: 2025 | H1: 2026 | I1: 2027 | J1: 2028 | K1: 2029 | L1: 2030 | M1: 2031 | N1: 2032 | O1: 2033 | P1: 2034 | Q1: 2035 | R1: 2036 | S1: 2037 | T1: 2038 | U1: 2039 | V1: 2040 | W1: 2041 | X1: 2042 | Y1: 2043 | Z1: 2044 | AA1: 2045 | AB1: 2046 | AC1: 2047 | AD1: 2048 | AE1: 2049 | AF1: 2050 | AG1: 2051 | AH1: 2052 | AI1: 2053 | AJ1: 2054 | AK1: 2055 | AL1: 2056 | AM1: 2057 | AN1: 2058 | AO1: 2059 | AP1: 2060 | AQ1: 2061 | AR1: 2062 | AS1: 2063 | AT1: 2064 | AU1: 2065 | AV1: 2066 | AW1: 2067 | AX1: 2068 | AY1: 2069 | AZ1: 2070
A2: hard coal | B2: 0 | C2: 0 | D2: 0 | E2: 0 | F2: 0 | G2: 0 | H2: 0 | I2: 0 | J2: 0 | K2: 0 | L2: 0 | M2: 0 | N2: 0 | O2: 0 | P2: 0 | Q2: 0 | R2: 0 | S2: 0 | T2: 0 | U2: 0 | V2: 0 | W2: 0 | X2: 0 | Y2: 0 | Z2: 0 | AA2: 0 | AB2: 0 | AC2: 0 | AD2: 0 | AE2: 0 | AF2: 0 | AG2: 0 | AH2: 0 | AI2: 0 | AJ2: 0 | AK2: 0 | AL2: 0 | AM2: 0 | AN2: 0 | AO2: 0 | AP2: 0 | AQ2: 0 | AR2: 0 | AS2: 0 | AT2: 0 | AU2: 0 | AV2: 0 | AW2: 0 | AX2: 0 | AY2: 0 | AZ2: 0
A3: natural gas steam turbine | B3: =0.2*Calculations!B$7 -> 1992777.8 | C3: =0.2*Calculations!C$7 -> 347222.22 | D3: =0.2*Calculations!D$7 -> 429444.44 | E3: =0.2*Calculations!E$7 -> 415000 | F3: =AVERAGE($B3:$E3) -> 796111.11 | G3: =AVERAGE($B3:$E3) -> 796111.11 | H3: =AVERAGE($B3:$E3) -> 796111.11 | I3: =AVERAGE($B3:$E3) -> 796111.11 | J3: =AVERAGE($B3:$E3) -> 796111.11 | K3: =AVERAGE($B3:$E3) -> 796111.11 | L3: =AVERAGE($B3:$E3) -> 796111.11 | M3: =AVERAGE($B3:$E3) -> 796111.11 | ... AZ3: =AVERAGE($B3:$E3) -> 796111.11
A4: natural gas combined cycle | B4: =0.2*Calculations!B$7 -> 1992777.8 | C4: =0.2*Calculations!C$7 -> 347222.22 | D4: =0.2*Calculations!D$7 -> 429444.44 | E4: =0.2*Calculations!E$7 -> 415000 | F4: =AVERAGE($B4:$E4) -> 796111.11 | G4: =AVERAGE($B4:$E4) -> 796111.11 | H4: =AVERAGE($B4:$E4) -> 796111.11 | I4: =AVERAGE($B4:$E4) -> 796111.11 | J4: =AVERAGE($B4:$E4) -> 796111.11 | K4: =AVERAGE($B4:$E4) -> 796111.11 | L4: =AVERAGE($B4:$E4) -> 796111.11 | M4: =AVERAGE($B4:$E4) -> 796111.11 | ... AZ4: =AVERAGE($B4:$E4) -> 796111.11
A5: nuclear | B5: 0 | C5: 0 | D5: 0 | E5: 0 | F5: 0 | G5: 0 | H5: 0 | I5: 0 | J5: 0 | K5: 0 | L5: 0 | M5: 0 | N5: 0 | O5: 0 | P5: 0 | Q5: 0 | R5: 0 | S5: 0 | T5: 0 | U5: 0 | V5: 0 | W5: 0 | X5: 0 | Y5: 0 | Z5: 0 | AA5: 0 | AB5: 0 | AC5: 0 | AD5: 0 | AE5: 0 | AF5: 0 | AG5: 0 | AH5: 0 | AI5: 0 | AJ5: 0 | AK5: 0 | AL5: 0 | AM5: 0 | AN5: 0 | AO5: 0 | AP5: 0 | AQ5: 0 | AR5: 0 | AS5: 0 | AT5: 0 | AU5: 0 | AV5: 0 | AW5: 0 | AX5: 0 | AY5: 0 | AZ5: 0
A6: hydro | B6: 0 | C6: 0 | D6: 0 | E6: 0 | F6: 0 | G6: 0 | H6: 0 | I6: 0 | J6: 0 | K6: 0 | L6: 0 | M6: 0 | N6: 0 | O6: 0 | P6: 0 | Q6: 0 | R6: 0 | S6: 0 | T6: 0 | U6: 0 | V6: 0 | W6: 0 | X6: 0 | Y6: 0 | Z6: 0 | AA6: 0 | AB6: 0 | AC6: 0 | AD6: 0 | AE6: 0 | AF6: 0 | AG6: 0 | AH6: 0 | AI6: 0 | AJ6: 0 | AK6: 0 | AL6: 0 | AM6: 0 | AN6: 0 | AO6: 0 | AP6: 0 | AQ6: 0 | AR6: 0 | AS6: 0 | AT6: 0 | AU6: 0 | AV6: 0 | AW6: 0 | AX6: 0 | AY6: 0 | AZ6: 0
A7: onshore wind | B7: =0.2*Calculations!B$7 -> 1992777.8 | C7: =0.2*Calculations!C$7 -> 347222.22 | D7: =0.2*Calculations!D$7 -> 429444.44 | E7: =0.2*Calculations!E$7 -> 415000 | F7: =AVERAGE($B7:$E7) -> 796111.11 | G7: =AVERAGE($B7:$E7) -> 796111.11 | H7: =AVERAGE($B7:$E7) -> 796111.11 | I7: =AVERAGE($B7:$E7) -> 796111.11 | J7: =AVERAGE($B7:$E7) -> 796111.11 | K7: =AVERAGE($B7:$E7) -> 796111.11 | L7: =AVERAGE($B7:$E7) -> 796111.11 | M7: =AVERAGE($B7:$E7) -> 796111.11 | ... AZ7: =AVERAGE($B7:$E7) -> 796111.11
A8: solar PV | B8: =0.2*Calculations!B$7 -> 1992777.8 | C8: =0.2*Calculations!C$7 -> 347222.22 | D8: =0.2*Calculations!D$7 -> 429444.44 | E8: =0.2*Calculations!E$7 -> 415000 | F8: =AVERAGE($B8:$E8) -> 796111.11 | G8: =AVERAGE($B8:$E8) -> 796111.11 | H8: =AVERAGE($B8:$E8) -> 796111.11 | I8: =AVERAGE($B8:$E8) -> 796111.11 | J8: =AVERAGE($B8:$E8) -> 796111.11 | K8: =AVERAGE($B8:$E8) -> 796111.11 | L8: =AVERAGE($B8:$E8) -> 796111.11 | M8: =AVERAGE($B8:$E8) -> 796111.11 | ... AZ8: =AVERAGE($B8:$E8) -> 796111.11
A9: solar thermal | B9: 0 | C9: 0 | D9: 0 | E9: 0 | F9: 0 | G9: 0 | H9: 0 | I9: 0 | J9: 0 | K9: 0 | L9: 0 | M9: 0 | N9: 0 | O9: 0 | P9: 0 | Q9: 0 | R9: 0 | S9: 0 | T9: 0 | U9: 0 | V9: 0 | W9: 0 | X9: 0 | Y9: 0 | Z9: 0 | AA9: 0 | AB9: 0 | AC9: 0 | AD9: 0 | AE9: 0 | AF9: 0 | AG9: 0 | AH9: 0 | AI9: 0 | AJ9: 0 | AK9: 0 | AL9: 0 | AM9: 0 | AN9: 0 | AO9: 0 | AP9: 0 | AQ9: 0 | AR9: 0 | AS9: 0 | AT9: 0 | AU9: 0 | AV9: 0 | AW9: 0 | AX9: 0 | AY9: 0 | AZ9: 0
A10: biomass | B10: 0 | C10: 0 | D10: 0 | E10: 0 | F10: 0 | G10: 0 | H10: 0 | I10: 0 | J10: 0 | K10: 0 | L10: 0 | M10: 0 | N10: 0 | O10: 0 | P10: 0 | Q10: 0 | R10: 0 | S10: 0 | T10: 0 | U10: 0 | V10: 0 | W10: 0 | X10: 0 | Y10: 0 | Z10: 0 | AA10: 0 | AB10: 0 | AC10: 0 | AD10: 0 | AE10: 0 | AF10: 0 | AG10: 0 | AH10: 0 | AI10: 0 | AJ10: 0 | AK10: 0 | AL10: 0 | AM10: 0 | AN10: 0 | AO10: 0 | AP10: 0 | AQ10: 0 | AR10: 0 | AS10: 0 | AT10: 0 | AU10: 0 | AV10: 0 | AW10: 0 | AX10: 0 | AY10: 0 | AZ10: 0
A11: geothermal | B11: 0 | C11: 0 | D11: 0 | E11: 0 | F11: 0 | G11: 0 | H11: 0 | I11: 0 | J11: 0 | K11: 0 | L11: 0 | M11: 0 | N11: 0 | O11: 0 | P11: 0 | Q11: 0 | R11: 0 | S11: 0 | T11: 0 | U11: 0 | V11: 0 | W11: 0 | X11: 0 | Y11: 0 | Z11: 0 | AA11: 0 | AB11: 0 | AC11: 0 | AD11: 0 | AE11: 0 | AF11: 0 | AG11: 0 | AH11: 0 | AI11: 0 | AJ11: 0 | AK11: 0 | AL11: 0 | AM11: 0 | AN11: 0 | AO11: 0 | AP11: 0 | AQ11: 0 | AR11: 0 | AS11: 0 | AT11: 0 | AU11: 0 | AV11: 0 | AW11: 0 | AX11: 0 | AY11: 0 | AZ11: 0
A12: petroleum | B12: 0 | C12: 0 | D12: 0 | E12: 0 | F12: 0 | G12: 0 | H12: 0 | I12: 0 | J12: 0 | K12: 0 | L12: 0 | M12: 0 | N12: 0 | O12: 0 | P12: 0 | Q12: 0 | R12: 0 | S12: 0 | T12: 0 | U12: 0 | V12: 0 | W12: 0 | X12: 0 | Y12: 0 | Z12: 0 | AA12: 0 | AB12: 0 | AC12: 0 | AD12: 0 | AE12: 0 | AF12: 0 | AG12: 0 | AH12: 0 | AI12: 0 | AJ12: 0 | AK12: 0 | AL12: 0 | AM12: 0 | AN12: 0 | AO12: 0 | AP12: 0 | AQ12: 0 | AR12: 0 | AS12: 0 | AT12: 0 | AU12: 0 | AV12: 0 | AW12: 0 | AX12: 0 | AY12: 0 | AZ12: 0
A13: natural gas peaker | B13: =0.2*Calculations!B$7 -> 1992777.8 | C13: =0.2*Calculations!C$7 -> 347222.22 | D13: =0.2*Calculations!D$7 -> 429444.44 | E13: =0.2*Calculations!E$7 -> 415000 | F13: =AVERAGE($B13:$E13) -> 796111.11 | G13: =AVERAGE($B13:$E13) -> 796111.11 | H13: =AVERAGE($B13:$E13) -> 796111.11 | I13: =AVERAGE($B13:$E13) -> 796111.11 | J13: =AVERAGE($B13:$E13) -> 796111.11 | K13: =AVERAGE($B13:$E13) -> 796111.11 | L13: =AVERAGE($B13:$E13) -> 796111.11 | M13: =AVERAGE($B13:$E13) -> 796111.11 | ... AZ13: =AVERAGE($B13:$E13) -> 796111.11
A14: lignite | B14: 0 | C14: 0 | D14: 0 | E14: 0 | F14: 0 | G14: 0 | H14: 0 | I14: 0 | J14: 0 | K14: 0 | L14: 0 | M14: 0 | N14: 0 | O14: 0 | P14: 0 | Q14: 0 | R14: 0 | S14: 0 | T14: 0 | U14: 0 | V14: 0 | W14: 0 | X14: 0 | Y14: 0 | Z14: 0 | AA14: 0 | AB14: 0 | AC14: 0 | AD14: 0 | AE14: 0 | AF14: 0 | AG14: 0 | AH14: 0 | AI14: 0 | AJ14: 0 | AK14: 0 | AL14: 0 | AM14: 0 | AN14: 0 | AO14: 0 | AP14: 0 | AQ14: 0 | AR14: 0 | AS14: 0 | AT14: 0 | AU14: 0 | AV14: 0 | AW14: 0 | AX14: 0 | AY14: 0 | AZ14: 0
A15: offshore wind | B15: 0 | C15: 0 | D15: 0 | E15: 0 | F15: 0 | G15: 0 | H15: 0 | I15: 0 | J15: 0 | K15: 0 | L15: 0 | M15: 0 | N15: 0 | O15: 0 | P15: 0 | Q15: 0 | R15: 0 | S15: 0 | T15: 0 | U15: 0 | V15: 0 | W15: 0 | X15: 0 | Y15: 0 | Z15: 0 | AA15: 0 | AB15: 0 | AC15: 0 | AD15: 0 | AE15: 0 | AF15: 0 | AG15: 0 | AH15: 0 | AI15: 0 | AJ15: 0 | AK15: 0 | AL15: 0 | AM15: 0 | AN15: 0 | AO15: 0 | AP15: 0 | AQ15: 0 | AR15: 0 | AS15: 0 | AT15: 0 | AU15: 0 | AV15: 0 | AW15: 0 | AX15: 0 | AY15: 0 | AZ15: 0
A16: crude oil | B16: 0 | C16: 0 | D16: 0 | E16: 0 | F16: 0 | G16: 0 | H16: 0 | I16: 0 | J16: 0 | K16: 0 | L16: 0 | M16: 0 | N16: 0 | O16: 0 | P16: 0 | Q16: 0 | R16: 0 | S16: 0 | T16: 0 | U16: 0 | V16: 0 | W16: 0 | X16: 0 | Y16: 0 | Z16: 0 | AA16: 0 | AB16: 0 | AC16: 0 | AD16: 0 | AE16: 0 | AF16: 0 | AG16: 0 | AH16: 0 | AI16: 0 | AJ16: 0 | AK16: 0 | AL16: 0 | AM16: 0 | AN16: 0 | AO16: 0 | AP16: 0 | AQ16: 0 | AR16: 0 | AS16: 0 | AT16: 0 | AU16: 0 | AV16: 0 | AW16: 0 | AX16: 0 | AY16: 0 | AZ16: 0
A17: heavy or residual fuel oil | B17: 0 | C17: 0 | D17: 0 | E17: 0 | F17: 0 | G17: 0 | H17: 0 | I17: 0 | J17: 0 | K17: 0 | L17: 0 | M17: 0 | N17: 0 | O17: 0 | P17: 0 | Q17: 0 | R17: 0 | S17: 0 | T17: 0 | U17: 0 | V17: 0 | W17: 0 | X17: 0 | Y17: 0 | Z17: 0 | AA17: 0 | AB17: 0 | AC17: 0 | AD17: 0 | AE17: 0 | AF17: 0 | AG17: 0 | AH17: 0 | AI17: 0 | AJ17: 0 | AK17: 0 | AL17: 0 | AM17: 0 | AN17: 0 | AO17: 0 | AP17: 0 | AQ17: 0 | AR17: 0 | AS17: 0 | AT17: 0 | AU17: 0 | AV17: 0 | AW17: 0 | AX17: 0 | AY17: 0 | AZ17: 0
A18: municipal solid waste | B18: 0 | C18: 0 | D18: 0 | E18: 0 | F18: 0 | G18: 0 | H18: 0 | I18: 0 | J18: 0 | K18: 0 | L18: 0 | M18: 0 | N18: 0 | O18: 0 | P18: 0 | Q18: 0 | R18: 0 | S18: 0 | T18: 0 | U18: 0 | V18: 0 | W18: 0 | X18: 0 | Y18: 0 | Z18: 0 | AA18: 0 | AB18: 0 | AC18: 0 | AD18: 0 | AE18: 0 | AF18: 0 | AG18: 0 | AH18: 0 | AI18: 0 | AJ18: 0 | AK18: 0 | AL18: 0 | AM18: 0 | AN18: 0 | AO18: 0 | AP18: 0 | AQ18: 0 | AR18: 0 | AS18: 0 | AT18: 0 | AU18: 0 | AV18: 0 | AW18: 0 | AX18: 0 | AY18: 0 | AZ18: 0
A19: hard coal w CCS | B19: 0 | C19: 0 | D19: 0 | E19: 0 | F19: 0 | G19: 0 | H19: 0 | I19: 0 | J19: 0 | K19: 0 | L19: 0 | M19: 0 | N19: 0 | O19: 0 | P19: 0 | Q19: 0 | R19: 0 | S19: 0 | T19: 0 | U19: 0 | V19: 0 | W19: 0 | X19: 0 | Y19: 0 | Z19: 0 | AA19: 0 | AB19: 0 | AC19: 0 | AD19: 0 | AE19: 0 | AF19: 0 | AG19: 0 | AH19: 0 | AI19: 0 | AJ19: 0 | AK19: 0 | AL19: 0 | AM19: 0 | AN19: 0 | AO19: 0 | AP19: 0 | AQ19: 0 | AR19: 0 | AS19: 0 | AT19: 0 | AU19: 0 | AV19: 0 | AW19: 0 | AX19: 0 | AY19: 0 | AZ19: 0
A20: natural gas combined cycle w CCS | B20: 0 | C20: 0 | D20: 0 | E20: 0 | F20: 0 | G20: 0 | H20: 0 | I20: 0 | J20: 0 | K20: 0 | L20: 0 | M20: 0 | N20: 0 | O20: 0 | P20: 0 | Q20: 0 | R20: 0 | S20: 0 | T20: 0 | U20: 0 | V20: 0 | W20: 0 | X20: 0 | Y20: 0 | Z20: 0 | AA20: 0 | AB20: 0 | AC20: 0 | AD20: 0 | AE20: 0 | AF20: 0 | AG20: 0 | AH20: 0 | AI20: 0 | AJ20: 0 | AK20: 0 | AL20: 0 | AM20: 0 | AN20: 0 | AO20: 0 | AP20: 0 | AQ20: 0 | AR20: 0 | AS20: 0 | AT20: 0 | AU20: 0 | AV20: 0 | AW20: 0 | AX20: 0 | AY20: 0 | AZ20: 0
A21: biomass w CCS | B21: 0 | C21: 0 | D21: 0 | E21: 0 | F21: 0 | G21: 0 | H21: 0 | I21: 0 | J21: 0 | K21: 0 | L21: 0 | M21: 0 | N21: 0 | O21: 0 | P21: 0 | Q21: 0 | R21: 0 | S21: 0 | T21: 0 | U21: 0 | V21: 0 | W21: 0 | X21: 0 | Y21: 0 | Z21: 0 | AA21: 0 | AB21: 0 | AC21: 0 | AD21: 0 | AE21: 0 | AF21: 0 | AG21: 0 | AH21: 0 | AI21: 0 | AJ21: 0 | AK21: 0 | AL21: 0 | AM21: 0 | AN21: 0 | AO21: 0 | AP21: 0 | AQ21: 0 | AR21: 0 | AS21: 0 | AT21: 0 | AU21: 0 | AV21: 0 | AW21: 0 | AX21: 0 | AY21: 0 | AZ21: 0
A22: lignite w CCS | B22: 0 | C22: 0 | D22: 0 | E22: 0 | F22: 0 | G22: 0 | H22: 0 | I22: 0 | J22: 0 | K22: 0 | L22: 0 | M22: 0 | N22: 0 | O22: 0 | P22: 0 | Q22: 0 | R22: 0 | S22: 0 | T22: 0 | U22: 0 | V22: 0 | W22: 0 | X22: 0 | Y22: 0 | Z22: 0 | AA22: 0 | AB22: 0 | AC22: 0 | AD22: 0 | AE22: 0 | AF22: 0 | AG22: 0 | AH22: 0 | AI22: 0 | AJ22: 0 | AK22: 0 | AL22: 0 | AM22: 0 | AN22: 0 | AO22: 0 | AP22: 0 | AQ22: 0 | AR22: 0 | AS22: 0 | AT22: 0 | AU22: 0 | AV22: 0 | AW22: 0 | AX22: 0 | AY22: 0 | AZ22: 0
A23: small modular reactor | B23: 0 | C23: 0 | D23: 0 | E23: 0 | F23: 0 | G23: 0 | H23: 0 | I23: 0 | J23: 0 | K23: 0 | L23: 0 | M23: 0 | N23: 0 | O23: 0 | P23: 0 | Q23: 0 | R23: 0 | S23: 0 | T23: 0 | U23: 0 | V23: 0 | W23: 0 | X23: 0 | Y23: 0 | Z23: 0 | AA23: 0 | AB23: 0 | AC23: 0 | AD23: 0 | AE23: 0 | AF23: 0 | AG23: 0 | AH23: 0 | AI23: 0 | AJ23: 0 | AK23: 0 | AL23: 0 | AM23: 0 | AN23: 0 | AO23: 0 | AP23: 0 | AQ23: 0 | AR23: 0 | AS23: 0 | AT23: 0 | AU23: 0 | AV23: 0 | AW23: 0 | AX23: 0 | AY23: 0 | AZ23: 0
A24: hydrogen combustion turbine | B24: 0 | C24: 0 | D24: 0 | E24: 0 | F24: 0 | G24: 0 | H24: 0 | I24: 0 | J24: 0 | K24: 0 | L24: 0 | M24: 0 | N24: 0 | O24: 0 | P24: 0 | Q24: 0 | R24: 0 | S24: 0 | T24: 0 | U24: 0 | V24: 0 | W24: 0 | X24: 0 | Y24: 0 | Z24: 0 | AA24: 0 | AB24: 0 | AC24: 0 | AD24: 0 | AE24: 0 | AF24: 0 | AG24: 0 | AH24: 0 | AI24: 0 | AJ24: 0 | AK24: 0 | AL24: 0 | AM24: 0 | AN24: 0 | AO24: 0 | AP24: 0 | AQ24: 0 | AR24: 0 | AS24: 0 | AT24: 0 | AU24: 0 | AV24: 0 | AW24: 0 | AX24: 0 | AY24: 0 | AZ24: 0
A25: hydrogen combined cycle | B25: 0 | C25: 0 | D25: 0 | E25: 0 | F25: 0 | G25: 0 | H25: 0 | I25: 0 | J25: 0 | K25: 0 | L25: 0 | M25: 0 | N25: 0 | O25: 0 | P25: 0 | Q25: 0 | R25: 0 | S25: 0 | T25: 0 | U25: 0 | V25: 0 | W25: 0 | X25: 0 | Y25: 0 | Z25: 0 | AA25: 0 | AB25: 0 | AC25: 0 | AD25: 0 | AE25: 0 | AF25: 0 | AG25: 0 | AH25: 0 | AI25: 0 | AJ25: 0 | AK25: 0 | AL25: 0 | AM25: 0 | AN25: 0 | AO25: 0 | AP25: 0 | AQ25: 0 | AR25: 0 | AS25: 0 | AT25: 0 | AU25: 0 | AV25: 0 | AW25: 0 | AX25: 0 | AY25: 0 | AZ25: 0

Sheet EIaE-BEE
A1: Exported Electricity (MW*hour) | B1: 2020 | C1: 2021 | D1: 2022 | E1: 2023 | F1: 2024 | G1: 2025 | H1: 2026 | I1: 2027 | J1: 2028 | K1: 2029 | L1: 2030 | M1: 2031 | N1: 2032 | O1: 2033 | P1: 2034 | Q1: 2035 | R1: 2036 | S1: 2037 | T1: 2038 | U1: 2039 | V1: 2040 | W1: 2041 | X1: 2042 | Y1: 2043 | Z1: 2044 | AA1: 2045 | AB1: 2046 | AC1: 2047 | AD1: 2048 | AE1: 2049 | AF1: 2050 | AG1: 2051 | AH1: 2052 | AI1: 2053 | AJ1: 2054 | AK1: 2055 | AL1: 2056 | AM1: 2057 | AN1: 2058 | AO1: 2059 | AP1: 2060 | AQ1: 2061 | AR1: 2062 | AS1: 2063 | AT1: 2064 | AU1: 2065 | AV1: 2066 | AW1: 2067 | AX1: 2068 | AY1: 2069 | AZ1: 2070
A2: Electricity Exports (MWh) | B2: =Calculations!B8 -> 5955555.6 | C2: =Calculations!C8 -> 2694444.4 | D2: =Calculations!D8 -> 2422222.2 | E2: =Calculations!E8 -> 3111111.1 | F2: =AVERAGE($B2:$E2) -> 3545833.3 | G2: =AVERAGE($B2:$E2) -> 3545833.3 | H2: =AVERAGE($B2:$E2) -> 3545833.3 | I2: =AVERAGE($B2:$E2) -> 3545833.3 | J2: =AVERAGE($B2:$E2) -> 3545833.3 | K2: =AVERAGE($B2:$E2) -> 3545833.3 | L2: =AVERAGE($B2:$E2) -> 3545833.3 | M2: =AVERAGE($B2:$E2) -> 3545833.3 | ... AZ2: =AVERAGE($B2:$E2) -> 3545833.3

Sheet EIaE-IEP
A1: Unit: 2012 USD/MWh | B1: 2020 | C1: 2021 | D1: 2022 | E1: 2023 | F1: 2024 | G1: 2025 | H1: 2026 | I1: 2027 | J1: 2028 | K1: 2029 | L1: 2030 | M1: 2031 | N1: 2032 | O1: 2033 | P1: 2034 | Q1: 2035 | R1: 2036 | S1: 2037 | T1: 2038 | U1: 2039 | V1: 2040 | W1: 2041 | X1: 2042 | Y1: 2043 | Z1: 2044 | AA1: 2045 | AB1: 2046 | AC1: 2047 | AD1: 2048 | AE1: 2049 | AF1: 2050 | AG1: 2051 | AH1: 2052 | AI1: 2053 | AJ1: 2054 | AK1: 2055 | AL1: 2056 | AM1: 2057 | AN1: 2058 | AO1: 2059 | AP1: 2060 | AQ1: 2061 | AR1: 2062 | AS1: 2063 | AT1: 2064 | AU1: 2065 | AV1: 2066 | AW1: 2067 | AX1: 2068 | AY1: 2069 | AZ1: 2070
A2: Imported Electricity Price | B2: =INDEX('AEO Table 3 2021'!67:67,MATCH(B1,'AEO Table 3 2021'!1:1,0))/10^6*About!$A$60/About!$A$59 -> 92.385095 | C2: =INDEX('AEO Table 3 2022'!67:67,MATCH(C1,'AEO Table 3 2022'!1:1,0))/10^6*About!$A$61/About!$A$59 -> 93.978106 | D2: =INDEX('AEO Table 3 2023'!67:67,MATCH(D1,'AEO Table 3 2023'!1:1,0))/10^6*About!$A$61/About!$A$59 -> 103.57699 | E2: =INDEX('AEO Table 3 2023'!67:67,MATCH(E1,'AEO Table 3 2023'!1:1,0))/10^6*About!$A$61/About!$A$59 -> 100.93588 | F2: =INDEX('AEO Table 3 2023'!67:67,MATCH(F1,'AEO Table 3 2023'!1:1,0))/10^6*About!$A$61/About!$A$59 -> 97.195682 | G2: =INDEX('AEO Table 3 2023'!67:67,MATCH(G1,'AEO Table 3 2023'!1:1,0))/10^6*About!$A$61/About!$A$59 -> 93.454633 | H2: =INDEX('AEO Table 3 2023'!67:67,MATCH(H1,'AEO Table 3 2023'!1:1,0))/10^6*About!$A$61/About!$A$59 -> 91.239536 | I2: =INDEX('AEO Table 3 2023'!67:67,MATCH(I1,'AEO Table 3 2023'!1:1,0))/10^6*About!$A$61/About!$A$59 -> 89.660948 | J2: =INDEX('AEO Table 3 2023'!67:67,MATCH(J1,'AEO Table 3 2023'!1:1,0))/10^6*About!$A$61/About!$A$59 -> 88.539575 | K2: =INDEX('AEO Table 3 2023'!67:67,MATCH(K1,'AEO Table 3 2023'!1:1,0))/10^6*About!$A$61/About!$A$59 -> 88.110798 | ... AF2: =INDEX('AEO Table 3 2023'!67:67,MATCH(AF1,'AEO Table 3 2023'!1:1,0))/10^6*About!$A$61/About!$A$59 -> 93.402133 | AG2: =AF2 -> 93.402133 | AH2: =AG2 -> 93.402133 | AI2: =AH2 -> 93.402133 | AJ2: =AI2 -> 93.402133 | AK2: =AJ2 -> 93.402133 | AL2: =AK2 -> 93.402133 | AM2: =AL2 -> 93.402133 | AN2: =AM2 -> 93.402133 | ... AZ2: =AY2 -> 93.402133

Sheet EIaE-BEEP
A1: Unit: 2012 USD/MWh | B1: 2020 | C1: 2021 | D1: 2022 | E1: 2023 | F1: 2024 | G1: 2025 | H1: 2026 | I1: 2027 | J1: 2028 | K1: 2029 | L1: 2030 | M1: 2031 | N1: 2032 | O1: 2033 | P1: 2034 | Q1: 2035 | R1: 2036 | S1: 2037 | T1: 2038 | U1: 2039 | V1: 2040 | W1: 2041 | X1: 2042 | Y1: 2043 | Z1: 2044 | AA1: 2045 | AB1: 2046 | AC1: 2047 | AD1: 2048 | AE1: 2049 | AF1: 2050 | AG1: 2051 | AH1: 2052 | AI1: 2053 | AJ1: 2054 | AK1: 2055 | AL1: 2056 | AM1: 2057 | AN1: 2058 | AO1: 2059 | AP1: 2060 | AQ1: 2061 | AR1: 2062 | AS1: 2063 | AT1: 2064 | AU1: 2065 | AV1: 2066 | AW1: 2067 | AX1: 2068 | AY1: 2069 | AZ1: 2070
A2: Exported Electricity Price | B2: =INDEX('AEO Table 3 2021'!67:67,MATCH(B1,'AEO Table 3 2021'!1:1,0))/10^6*About!$A$60/About!$A$59 -> 92.385095 | C2: =INDEX('AEO Table 3 2022'!67:67,MATCH(C1,'AEO Table 3 2022'!1:1,0))/10^6*About!$A$61/About!$A$59 -> 93.978106 | D2: =INDEX('AEO Table 3 2023'!67:67,MATCH(D1,'AEO Table 3 2023'!1:1,0))/10^6*About!$A$61/About!$A$59 -> 103.57699 | E2: =INDEX('AEO Table 3 2023'!67:67,MATCH(E1,'AEO Table 3 2023'!1:1,0))/10^6*About!$A$61/About!$A$59 -> 100.93588 | F2: =INDEX('AEO Table 3 2023'!67:67,MATCH(F1,'AEO Table 3 2023'!1:1,0))/10^6*About!$A$61/About!$A$59 -> 97.195682 | G2: =INDEX('AEO Table 3 2023'!67:67,MATCH(G1,'AEO Table 3 2023'!1:1,0))/10^6*About!$A$61/About!$A$59 -> 93.454633 | H2: =INDEX('AEO Table 3 2023'!67:67,MATCH(H1,'AEO Table 3 2023'!1:1,0))/10^6*About!$A$61/About!$A$59 -> 91.239536 | I2: =INDEX('AEO Table 3 2023'!67:67,MATCH(I1,'AEO Table 3 2023'!1:1,0))/10^6*About!$A$61/About!$A$59 -> 89.660948 | J2: =INDEX('AEO Table 3 2023'!67:67,MATCH(J1,'AEO Table 3 2023'!1:1,0))/10^6*About!$A$61/About!$A$59 -> 88.539575 | K2: =INDEX('AEO Table 3 2023'!67:67,MATCH(K1,'AEO Table 3 2023'!1:1,0))/10^6*About!$A$61/About!$A$59 -> 88.110798 | ... AF2: =INDEX('AEO Table 3 2023'!67:67,MATCH(AF1,'AEO Table 3 2023'!1:1,0))/10^6*About!$A$61/About!$A$59 -> 93.402133 | AG2: =AF2 -> 93.402133 | AH2: =AG2 -> 93.402133 | AI2: =AH2 -> 93.402133 | AJ2: =AI2 -> 93.402133 | AK2: =AJ2 -> 93.402133 | AL2: =AK2 -> 93.402133 | AM2: =AL2 -> 93.402133 | AN2: =AM2 -> 93.402133 | ... AZ2: =AY2 -> 93.402133
