Workbook

Sheet About
A1: DACD Direct Air Capture Potential
A2: DACD Direct Air Capture Energy Intensity
A3: DACD Direct Air Capture Amortized CapEx and OM
A5: Sources: | B5: Potential
B6: Fuhrman et al.
B7: 2023
B8: Diverse carbon dioxide removal approaches could reduce impacts on the energy-water-land system
B9: https://www.nature.com/articles/s41558-023-01604-9
B10: Supplemental information, Figure 9
B12: Energy Intensity and CapEx Data
B13: Realmonte et al.
B14: 2019
B15: An inter-model assessment of the role of direct air capture in deep mitigation pathways
B16: https://www.nature.com/articles/s41467-019-10842-5
B17: Table 2
B18: https://static-content.springer.com/esm/art%3A10.1038%2Fs41467-019-10842-5/MediaObjects/41467_2019_10842_MOESM1_ESM.pdf
B19: Supplementary materials, Fig 3
A21: Notes
A22: We use the US Long-Term Strategy to project DAC potential and a
A23: separate source for energy intensity and CapEx calculations.
A25: Amortized CapEx and OM Cost Notes
A26: CapEx here should include the cost of equipment, maintenance, and labor.
A27: Energy costs are calculated separately in the model and should not be included here.

Sheet Data
A1: DAC Technologies Considered
A2: DAC1 = hydroxide sorbent-based technology, most mature technology, used for large-scale plants, requires high heat (>800C)
A3: DAC2 = amine-based technology, less mature, can be small modular units, can accept waste heat (temp 85-120C)
A5: According to the source paper, DAC1 heat is provided by natural gas, and DAC2 heat is provided by waste heat.
A6: However, the largest currently operating DAC facilities use solid sorbent systems and utilize non-fossil resources at low heat (80-120 C),
A7: see: https://www.wri.org/insights/direct-air-capture-resource-considerations-and-costs-carbon-removal, Status of the Leading DAC Companies.
A8: Therefore, we take the heat input specified for DAC1 plants and convert to the amount of electricity needed
A9: if supplied by a heat pump.
A11: Capital Cost per Ton CO2 Captured (amortized over lifetime of equipment)
A12: The paper indicates these costs include equipment, maintenance, and labor. Energy costs are not included.
A13: $/ton CO2 | B13: DAC1 | C13: DAC2
A14: High | B14: 300 | C14: 350
A15: Low | B15: 180 | C15: 200
A16: Floor | B16: 100 | C16: 50
A18: Electricity Required per Ton CO2 Captured
A19: GJ/ton CO2 | B19: DAC1 | C19: DAC2
A20: High | B20: 1.8 | C20: 1.1
A21: Low | B21: 1.3 | C21: 0.6
A22: Floor
A24: Heat Input Required per Ton CO2 Captured
A25: GJ/ton CO2 | B25: DAC1 | C25: DAC2
A26: High | B26: 8.1 | C26: 7.2
A27: Low | B27: 5.3 | C27: 4.4
A28: Floor
A30: Percent Reduction in Fuel Use with Heat Pump | B30: 0.67 | D30: Source: indst/PIFURfE
A32: Heat Input Required per Ton CO2 Captured, Converted to Electricity
A33: GJ/ton CO2 | B33: DAC1 | C33: DAC2
A34: High | B34: =B26*(1-$B$30) -> 2.673 | C34: =C26*(1-$B$30) -> 2.376
A35: Low | B35: =B27*(1-$B$30) -> 1.749 | C35: =C27*(1-$B$30) -> 1.452
A37: Technology Shares (Supplement Fig 3)
A38: Very little DAC of any sort is deployed before 2045-2050. DAC1 is dominant
A39: until after 2080. Therefore, for the EPS, which extends only to 2050, we
A40: assume the only relevant DAC technology is DAC1.
A62: Global DAC Potential
A63: We will use the 1.5-degree C pathway as our outer potential bound (100% lever setting),
A64: since it is the more aggressive of the two scenarios.
A65: We will measure deployment in specific years to the pixel, since the data are not
A66: provided in tabular form:
B68: 2045 | C68: 2050 | D68: 2060 | E68: 2070 | F68: 2080 | G68: 2090 | H68: 2100
A69: DAC1 (pixels, high zoom) | B69: 0 | C69: 5 | D69: 20 | E69: 122 | F69: 388 | G69: 384 | H69: 379
A70: DAC2 (pixels, high zoom) | B70: 0 | C70: 0 | D70: 0 | E70: 5 | F70: 30 | G70: 35 | H70: 40
A72: Scale (pixels/(30 Gt/yr)) | B72: 420
B74: 2045 | C74: 2050 | D74: 2060 | E74: 2070 | F74: 2080 | G74: 2090 | H74: 2100
A75: DAC1 (Gt/yr) | B75: =B69/$B$72*30 -> 0 | C75: =C69/$B$72*30 -> 0.35714286 | D75: =D69/$B$72*30 -> 1.4285714 | E75: =E69/$B$72*30 -> 8.7142857 | F75: =F69/$B$72*30 -> 27.714286 | G75: =G69/$B$72*30 -> 27.428571 | H75: =H69/$B$72*30 -> 27.071429
A76: DAC2 (Gt/yr) | B76: =B70/$B$72*30 -> 0 | C76: =C70/$B$72*30 -> 0 | D76: =D70/$B$72*30 -> 0 | E76: =E70/$B$72*30 -> 0.35714286 | F76: =F70/$B$72*30 -> 2.1428571 | G76: =G70/$B$72*30 -> 2.5 | H76: =H70/$B$72*30 -> 2.8571429
A78: Assigning Country-Specific Share
A79: The totals above are global. We assign DAC expenditures proportionally to current GDP, which
A80: reflects both a country's ability to pay and, to a rough degree, its responsibility for historical emissions
A81: to date.
A83: U.S. GDP | B83: 19.39 | C83: trillion USD | D83: 2017
A84: World GDP | B84: 80 | C84: trillion UDS | D84: 2017
A85: US GDP share | B85: =B83/B84 -> 0.242375
A87: U.S. DAC potential
B88: 2045 | C88: 2050 | D88: 2060 | E88: 2070 | F88: 2080 | G88: 2090 | H88: 2100
A89: DAC1 (Gt/yr) | B89: =B75*$B$85 -> 0 | C89: =C75*$B$85 -> 0.0865625 | D89: =D75*$B$85 -> 0.34625 | E89: =E75*$B$85 -> 2.112125 | F89: =F75*$B$85 -> 6.71725 | G89: =G75*$B$85 -> 6.648 | H89: =H75*$B$85 -> 6.5614375
A90: DAC2 (Gt/yr) | B90: =B76*$B$85 -> 0 | C90: =C76*$B$85 -> 0 | D90: =D76*$B$85 -> 0 | E90: =E76*$B$85 -> 0.0865625 | F90: =F76*$B$85 -> 0.519375 | G90: =G76*$B$85 -> 0.6059375 | H90: =H76*$B$85 -> 0.6925
A92: Converting to metric tons:
B93: 2045 | C93: 2050 | D93: 2060 | E93: 2070 | F93: 2080 | G93: 2090 | H93: 2100
A94: DAC1 (t/yr) | B94: =B89*10^9 -> 0 | C94: =C89*10^9 -> 86562500 | D94: =D89*10^9 -> 3.4625e+08 | E94: =E89*10^9 -> 2.112125e+09 | F94: =F89*10^9 -> 6.71725e+09 | G94: =G89*10^9 -> 6648000000 | H94: =H89*10^9 -> 6561437500
A95: DAC2 (t/yr) | B95: =B90*10^9 -> 0 | C95: =C90*10^9 -> 0 | D95: =D90*10^9 -> 0 | E95: =E90*10^9 -> 86562500 | F95: =F90*10^9 -> 5.19375e+08 | G95: =G90*10^9 -> 605937500 | H95: =H90*10^9 -> 6.925e+08
A97: Electricity and Heat Intensity, Costs
A98: Due to the fact that the EPS model run ends at 2050, and deployment of DAC1 may only begin in 2046 (and DAC2 can't
A99: begin during the model run at all), we assume there will not be sufficient time to progress from the high toward the
A100: low intensity or cost values. Therefore, we take the high values as constant over the period 2046-2050, when deployment
A101: is just barely beginning.
A103: BTU/GJ | B103: 947086
A105: In this variable, we use BTU for all energy sources, including electricity. This is a strict unit conversion, not a heat rate.

Sheet Fuhrman data
A1: Total potential | B1: 90

Sheet DACD-potential
A1: metric tons/yr | B1: 2017 | C1: 2018 | D1: 2019 | E1: 2020 | F1: 2021 | G1: 2022 | H1: 2023 | I1: 2024 | J1: 2025 | K1: 2026 | L1: 2027 | M1: 2028 | N1: 2029 | O1: 2030 | P1: 2031 | Q1: 2032 | R1: 2033 | S1: 2034 | T1: 2035 | U1: 2036 | V1: 2037 | W1: 2038 | X1: 2039 | Y1: 2040 | Z1: 2041 | AA1: 2042 | AB1: 2043 | AC1: 2044 | AD1: 2045 | AE1: 2046 | AF1: 2047 | AG1: 2048 | AH1: 2049 | AI1: 2050 | AJ1: 2051 | AK1: 2052 | AL1: 2053 | AM1: 2054 | AN1: 2055 | AO1: 2056 | AP1: 2057 | AQ1: 2058 | AR1: 2059 | AS1: 2060 | AT1: 2061 | AU1: 2062 | AV1: 2063 | AW1: 2064 | AX1: 2065 | AY1: 2066 | AZ1: 2067 | BA1: 2068 | BB1: 2069 | BC1: 2070
A2: DAC Potential | B2: 0 | C2: 0 | D2: 0 | E2: 0 | F2: 0 | G2: 0 | H2: 0 | I2: =H2 -> 0 | J2: {=TREND($O$2-$I$2)/COUNT($J$1:$O$1)+I2} -> 15000000 | K2: {=TREND($O$2-$I$2)/COUNT($J$1:$O$1)+J2} -> 30000000 | L2: {=TREND($O$2-$I$2)/COUNT($J$1:$O$1)+K2} -> 45000000 | M2: {=TREND($O$2-$I$2)/COUNT($J$1:$O$1)+L2} -> 60000000 | N2: {=TREND($O$2-$I$2)/COUNT($J$1:$O$1)+M2} -> 75000000 | O2: ='Fuhrman data'!$B$1*10^6 -> 90000000 | P2: ='Fuhrman data'!$B$1*10^6 -> 90000000 | Q2: ='Fuhrman data'!$B$1*10^6 -> 90000000 | R2: ='Fuhrman data'!$B$1*10^6 -> 90000000 | S2: ='Fuhrman data'!$B$1*10^6 -> 90000000 | T2: ='Fuhrman data'!$B$1*10^6 -> 90000000 | U2: ='Fuhrman data'!$B$1*10^6 -> 90000000 | V2: ='Fuhrman data'!$B$1*10^6 -> 90000000 | ... BC2: ='Fuhrman data'!$B$1*10^6 -> 90000000

Sheet DACD-energyintensity
A1: BTU/metric ton CO2 | B1: 2017 | C1: 2018 | D1: 2019 | E1: 2020 | F1: 2021 | G1: 2022 | H1: 2023 | I1: 2024 | J1: 2025 | K1: 2026 | L1: 2027 | M1: 2028 | N1: 2029 | O1: 2030 | P1: 2031 | Q1: 2032 | R1: 2033 | S1: 2034 | T1: 2035 | U1: 2036 | V1: 2037 | W1: 2038 | X1: 2039 | Y1: 2040 | Z1: 2041 | AA1: 2042 | AB1: 2043 | AC1: 2044 | AD1: 2045 | AE1: 2046 | AF1: 2047 | AG1: 2048 | AH1: 2049 | AI1: 2050
A2: electricity | B2: =(Data!B20+Data!B34)*Data!B103 -> 4236315.7 | C2: =$B2 -> 4236315.7 | D2: =$B2 -> 4236315.7 | E2: =$B2 -> 4236315.7 | F2: =$B2 -> 4236315.7 | G2: =$B2 -> 4236315.7 | H2: =$B2 -> 4236315.7 | I2: =$B2 -> 4236315.7 | J2: =$B2 -> 4236315.7 | ... AI2: =$B2 -> 4236315.7
A3: coal | B3: 0 | C3: =$B3 -> 0 | D3: =$B3 -> 0 | E3: =$B3 -> 0 | F3: =$B3 -> 0 | G3: =$B3 -> 0 | H3: =$B3 -> 0 | I3: =$B3 -> 0 | J3: =$B3 -> 0 | ... AI3: =$B3 -> 0
A4: natural gas | B4: 0 | C4: =$B4 -> 0 | D4: =$B4 -> 0 | E4: =$B4 -> 0 | F4: =$B4 -> 0 | G4: =$B4 -> 0 | H4: =$B4 -> 0 | I4: =$B4 -> 0 | J4: =$B4 -> 0 | ... AI4: =$B4 -> 0
A5: biomass | B5: 0 | C5: =$B5 -> 0 | D5: =$B5 -> 0 | E5: =$B5 -> 0 | F5: =$B5 -> 0 | G5: =$B5 -> 0 | H5: =$B5 -> 0 | I5: =$B5 -> 0 | J5: =$B5 -> 0 | ... AI5: =$B5 -> 0
A6: petroleum diesel | B6: 0 | C6: =$B6 -> 0 | D6: =$B6 -> 0 | E6: =$B6 -> 0 | F6: =$B6 -> 0 | G6: =$B6 -> 0 | H6: =$B6 -> 0 | I6: =$B6 -> 0 | J6: =$B6 -> 0 | ... AI6: =$B6 -> 0
A7: heat | B7: 0 | C7: =$B7 -> 0 | D7: =$B7 -> 0 | E7: =$B7 -> 0 | F7: =$B7 -> 0 | G7: =$B7 -> 0 | H7: =$B7 -> 0 | I7: =$B7 -> 0 | J7: =$B7 -> 0 | ... AI7: =$B7 -> 0
A8: crude oil | B8: 0 | C8: =$B8 -> 0 | D8: =$B8 -> 0 | E8: =$B8 -> 0 | F8: =$B8 -> 0 | G8: =$B8 -> 0 | H8: =$B8 -> 0 | I8: =$B8 -> 0 | J8: =$B8 -> 0 | ... AI8: =$B8 -> 0
A9: heavy or residual fuel oil | B9: 0 | C9: =$B9 -> 0 | D9: =$B9 -> 0 | E9: =$B9 -> 0 | F9: =$B9 -> 0 | G9: =$B9 -> 0 | H9: =$B9 -> 0 | I9: =$B9 -> 0 | J9: =$B9 -> 0 | ... AI9: =$B9 -> 0
A10: LPG propane or butane | B10: 0 | C10: =$B10 -> 0 | D10: =$B10 -> 0 | E10: =$B10 -> 0 | F10: =$B10 -> 0 | G10: =$B10 -> 0 | H10: =$B10 -> 0 | I10: =$B10 -> 0 | J10: =$B10 -> 0 | ... AI10: =$B10 -> 0
A11: hydrogen | B11: 0 | C11: =$B11 -> 0 | D11: =$B11 -> 0 | E11: =$B11 -> 0 | F11: =$B11 -> 0 | G11: =$B11 -> 0 | H11: =$B11 -> 0 | I11: =$B11 -> 0 | J11: =$B11 -> 0 | ... AI11: =$B11 -> 0

Sheet DACD-capex
A1: $/metric ton CO2 | B1: 2017 | C1: 2018 | D1: 2019 | E1: 2020 | F1: 2021 | G1: 2022 | H1: 2023 | I1: 2024 | J1: 2025 | K1: 2026 | L1: 2027 | M1: 2028 | N1: 2029 | O1: 2030 | P1: 2031 | Q1: 2032 | R1: 2033 | S1: 2034 | T1: 2035 | U1: 2036 | V1: 2037 | W1: 2038 | X1: 2039 | Y1: 2040 | Z1: 2041 | AA1: 2042 | AB1: 2043 | AC1: 2044 | AD1: 2045 | AE1: 2046 | AF1: 2047 | AG1: 2048 | AH1: 2049 | AI1: 2050
A2: amortized CapEx | B2: =Data!B14 -> 300 | C2: =$B2 -> 300 | D2: =$B2 -> 300 | E2: =$B2 -> 300 | F2: =$B2 -> 300 | G2: =$B2 -> 300 | H2: =$B2 -> 300 | I2: =$B2 -> 300 | J2: =$B2 -> 300 | ... AI2: =$B2 -> 300
