Workbook
Name BARRILES: 6.28982
Name calorcarbonII: 5164.3
Name calordiesel: 9243.22
Name Calorgas: 8967.6
Name calorpeta: 6389.256
Name calorrio: 3900.6
Name calorvacio: 13700
Name corr: 1
Name Eno_TM: #REF!
Name Eno_Tons: #REF!
Name ft: 35.31466
Name GWP: 21
Name iva: 1.15
Name joules: 4186.8402
Name litros: 158.987
Name NTS_YR: #REF!
Name Sum_T2: #REF!
Name Sum_TTM: #REF!
Name ti_tbl_50: #REF!
Name ti_tbl_69: #REF!
Name tonelada: 907.185

Sheet About
A1: AVL Avg Vehicle Lifetime
A3: Sources: | B3: LDV Lifetimes
B4: Calibrated
A6: Sources: | B6: On-road fleet by type of vehicle and technology
B7: Updated Transport Model Data Base (2024), self-analysis with data from INEGI
B8: 2024
B10: LDVs: Market Shares of Cars and Light Trucks
B11: INEGI -
B12: 2016
B13: National Transportation Statistics 2015
B14: http://www.rita.dot.gov/bts/sites/rita.dot.gov.bts/files/publications/national_transportation_statistics/index.html
B15: Table 1-20
B17: aircraft
B18: Secretaria de comunicaciones y transportes
B19: 2024
B20: Estadísticas de flota
B21: https://www.gob.mx/cms/uploads/attachment/file/970059/flota-reg-2024-4-trim-27012025.pdf
B22: Slide 2
B24: rail and ships
B25: California State Controller's Office
B26: 1992 (but still current)
B27: Audit Guidelines and Uniform Accounting Systems: Special Districts
B28: http://www.sco.ca.gov/ard_local_rep_uas_special_dist.html
B29: Appendix A: Suggested Useful Lives of Fixed Assets
A31: US, not used | B31: Freight HDVs
B32: Oak Ridge National Laboratory
B33: 2015
B34: Transportation Energy Data Book Ed. 34
B35: http://cta.ornl.gov/data/tedb34/Spreadsheets/Table3_14.xls
B36: Table 3-14, Row 43
A38: US, not used | B38: Passenger HDVs (Buses)
B39: ThoughtCo
B40: 2019
B41: How Long Do Buses and Other Transit Vehicles Last?
B42: https://www.thoughtco.com/buses-and-other-transit-lifetime-2798844
A44: US, not used | B44: motorbikes
B45: Bureau of Transportation Statistics
B46: 2009
B47: Motorcycle Trends in the United States
B48: http://www.rita.dot.gov/bts/sites/rita.dot.gov.bts/files/publications/special_reports_and_issue_briefs/special_report/2009_05_14/pdf/entire.pdf
B49: Page 3, Table 1
A51: About
A52: The model requires the lifetime to be an integer, so we round to the nearest integer.
A54: We calibrate the value for passenger LDVs to match annual passenger LDV sales in the model, which were roughly 15 million in 2021.
A56: We assume passenger and freight modes are the same for aircraft, rail, and ships.
A58: There are no freight motorbikes in the U.S. EPS, so we arbitrarily set their lifetime equal to passenger motorbikes.
A60: MexNotes
A61: We consider average lifetime, the age where 1/2 (50%) of the vehicles are still used
A62: We have no data for rail & ships so US data with an adjustment is made.
A63: Ajustment
A64: 1.33 | B64: Guided by LDV lifetime ratio Mex/US

Sheet Mexico Road Fleet
B1: Registered Vehicles INEGI | D1: 1980 | E1: 1981 | F1: 1982 | G1: 1983 | H1: 1984 | I1: 1985 | J1: 1986 | K1: 1987 | L1: 1988 | M1: 1989 | N1: 1990 | O1: 1991 | P1: 1992 | Q1: 1993 | R1: 1994 | S1: 1995 | T1: 1996 | U1: 1997 | V1: 1998 | W1: 1999 | X1: 2000 | Y1: 2001 | Z1: 2002 | AA1: 2003 | AB1: 2004 | AC1: 2005 | AD1: 2006 | AE1: 2007 | AF1: 2008 | AG1: 2009 | AH1: 2010 | AI1: 2011 | AJ1: 2012 | AK1: 2013 | AL1: 2014 | AM1: 2015 | AN1: 2016 | AO1: 2017 | AP1: 2018 | AQ1: 2019 | AR1: 2020 | AS1: 2021 | AT1: 2022 | AU1: 2023 | AV1: 2024 | BW1: . | CC1: .
B2: Automóviles | C2: Units | D2: 3950042 | E2: 4341363 | F2: 4616897 | G2: 4726236 | H2: 4970526 | I2: 5281842 | J2: 5202922 | K2: 5336228 | L2: 5597735 | M2: 6003532 | N2: 6555550 | O2: 6950708 | P2: 7399178 | Q2: 7715951 | R2: 7217732 | S2: 7469504 | T2: 7830864 | U2: 8402995 | V2: 9086209 | W2: 9582796 | X2: 10176179 | Y2: 11351982 | Z2: 12254910 | AA2: 12742049 | AB2: 13388011 | AC2: 14300380 | AD2: 16411813 | AE2: 17696623 | AF2: 19420942 | AG2: 20519224 | AH2: 21152773 | AI2: 22374326 | AJ2: 23569623 | AK2: 24819922 | AL2: 25543908 | AM2: 26907994 | AN2: 28664295 | AO2: 30696542 | AP2: 31552351 | AQ2: 32316144 | AR2: 32848577 | AS2: 33368689 | AT2: 33855651 | AU2: 34453866 | AV2: 35090355 | AX2: =(AV2/AP2)^(1/($AV$1-$AP$1))-1 -> 0.01787084 | BW2: . | CC2: .
B3: Camiones para pasajeros | C3: Units | D3: 60388 | E3: 64973 | F3: 69233 | G3: 71326 | H3: 76517 | I3: 79028 | J3: 83373 | K3: 84364 | L3: 85229 | M3: 90150 | N3: 93275 | O3: 96910 | P3: 95179 | Q3: 85941 | R3: 114577 | S3: 120497 | T3: 96933 | U3: 125445 | V3: 176443 | W3: 200357 | X3: 202396 | Y3: 273536 | Z3: 299365 | AA3: 308101 | AB3: 264585 | AC3: 268817 | AD3: 310189 | AE3: 322078 | AF3: 333287 | AG3: 337465 | AH3: 312738 | AI3: 327565 | AJ3: 338520 | AK3: 347144 | AL3: 347720 | AM3: 357452 | AN3: 367772 | AO3: 398584 | AP3: 440470 | AQ3: 450423 | AR3: 457620 | AS3: 456923 | AT3: 465103 | AU3: 484157 | AV3: 485698 | AX3: =(AV3/AP3)^(1/($AV$1-$AP$1))-1 -> 0.0164242 | BW3: . | CC3: .
B4: Camiones y camionetas para carga | C4: Units | D4: 1470816 | E4: 1636899 | F4: 1751799 | G4: 1893206 | H4: 2009875 | I4: 2114395 | J4: 2213025 | K4: 2292078 | L4: 2424025 | M4: 2691551 | N4: 2964736 | O4: 3293414 | P4: 3492416 | Q4: 3592977 | R4: 3613808 | S4: 3598685 | T4: 3645672 | U4: 3878581 | V4: 4078068 | W4: 4340112 | X4: 4939417 | Y4: 5394206 | Z4: 5860797 | AA4: 6317293 | AB4: 6707535 | AC4: 6980738 | AD4: 7462918 | AE4: 7849491 | AF4: 8453601 | AG4: 8835194 | AH4: 9015356 | AI4: 9260456 | AJ4: 9385466 | AK4: 9704131 | AL4: 9863980 | AM4: 10073288 | AN4: 10384621 | AO4: 10806605 | AP4: 11409902 | AQ4: 11998035 | AR4: 12439548 | AS4: 12961227 | AT4: 13603884 | AU4: 14413656 | AV4: 15324327 | AX4: =(AV4/AP4)^(1/($AV$1-$AP$1))-1 -> 0.050388398 | BW4: . | CC4: .
B5: Motocicletas | C5: Units | D5: 277084 | E5: 296601 | F5: 257235 | G5: 250484 | H5: 248148 | I5: 250358 | J5: 232692 | K5: 221059 | L5: 217898 | M5: 223815 | N5: 248547 | O5: 261111 | P5: 273411 | Q5: 198209 | R5: 214972 | S5: 128960 | T5: 176559 | U5: 178166 | V5: 222100 | W5: 262599 | X5: 293924 | Y5: 280806 | Z5: 369522 | AA5: 439517 | AB5: 518307 | AC5: 588543 | AD5: 722309 | AE5: 879005 | AF5: 1080073 | AG5: 1198253 | AH5: 1154145 | AI5: 1313122 | AJ5: 1582228 | AK5: 1873641 | AL5: 2271563 | AM5: 2637264 | AN5: 3037577 | AO5: 3574402 | AP5: 4135368 | AQ5: 4616977 | AR5: 5326447 | AS5: 5821035 | AT5: 6472998 | AU5: 7349263 | AV5: 8307284.5 | AX5: =(AV5/AP5)^(1/($AV$1-$AP$1))-1 -> 0.12328723 | BW5: .
B6: High | BW6: . | CC6: .
B7: Med | S7: 114785 | T7: 120868 | U7: 97716 | V7: 126892 | W7: 177674 | X7: 202140 | Y7: 205214 | Z7: 275459 | AA7: 301034 | AB7: 309753 | AC7: 266501 | AD7: 270606 | AE7: 311560 | AF7: 324102 | AG7: 334075 | AH7: 338486 | AI7: 314264 | AJ7: 328867 | AK7: 340200 | AL7: 348870 | AM7: 348891 | AN7: 359010 | AO7: 369436 | AP7: 400270 | AQ7: 442262 | AR7: 450973 | AS7: 458162 | AT7: 457667 | AU7: 466564 | AV7: 485698 | BW7: . | CC7: .
B8: Low | AO8: . | BW8: . | CC8: .
B9: Choose Growth Rate = | C9: High | AO9: . | BW9: . | CC9: .
AO10: . | BW10: .
B11: Future car fleet | D11: 2010 | E11: 2015 | F11: 2020 | G11: 2030 | H11: 2040 | I11: 2050 | AO11: . | BW11: .
B12: Car fleet growth | C12: Million vehicles | D12: =AH43/10^6 -> 16.525114 | E12: =AM44/10^6 -> 20.339859 | F12: =AR44/10^6 -> 25.226119 | G12: =BB44/10^6 -> 38.802117 | H12: =BL44/10^6 -> 59.684342 | I12: =BV44/10^6 -> 91.804802 | BW12: .
B13: Motorisation rate growth | C13: Million vehicles | D13: =AH43/10^6 -> 16.525114 | E13: =AM44/10^6 -> 20.339859 | F13: =AR45/10^6 -> 24.170076 | G13: =BB45/10^6 -> 33.469053 | H13: =BL45/10^6 -> 45.315848 | I13: =BV45/10^6 -> 60.17088 | BW13: .
B14: Car registration growth | C14: Million vehicles | D14: =AH43/10^6 -> 16.525114 | E14: =AM46/10^6 -> 20.339859 | F14: =AR46/10^6 -> 21.219673 | G14: =BB46/10^6 -> 24.576986 | H14: =BL46/10^6 -> 31.195879 | I14: =BV46/10^6 -> 42.433952 | BW14: .
BW15: .
BW16: .
BW17: .
BW18: .
BW19: .
BW20: .
BW21: .
BW22: .
BW23: .
BW24: .
BW25: .
BW26: .
... BW31: .
B32: Estimations of Actual Fleets 2015 | BW32: .
BW33: .
B34: Modelling vehicle & motorcycle retirement | BW34: .
B35: Age of car | C35: years | D35: 0 | E35: 5 | F35: 10 | G35: 15 | H35: 20 | I35: 25 | J35: 30 | K35: 35 | L35: 40 | M35: 45 | N35: 50 | O35: 55 | P35: 60 | Q35: 65 | R35: 70 | BW35: .
B36: Percent survival per age | C36: % | D36: 1 | E36: 0.99 | F36: 0.96 | G36: 0.85 | H36: 0.67 | I36: 0.48 | J36: 0.32 | K36: 0.21 | L36: 0.13 | M36: 0.08 | N36: 0.045 | O36: 0.025 | P36: 0.01 | Q36: 0.004 | R36: 0 | BW36: .
B37: Adapted (with "a lag" to the Mexican context) from: Fridstrøm, L., Østli, V. & Johansen, K.W. Eur. Transp. Res. Rev. (2016) 8: 22. https://doi.org/10.1007/s12544-016-0210-z | BW37: .
BW38: .
B39: Age of car | C39: years | D39: 0 | E39: 1 | F39: 2 | G39: 3 | H39: 4 | I39: 5 | J39: 6 | K39: 7 | L39: 8 | M39: 9 | N39: 10 | O39: 11 | P39: 12 | Q39: 13 | R39: 14 | S39: 15 | T39: 16 | U39: 17 | V39: 18 | W39: 19 | X39: 20 | Y39: 21 | Z39: 22 | AA39: 23 | AB39: 24 | AC39: 25 | AD39: 26 | AE39: 27 | AF39: 28 | AG39: 29 | AH39: 30 | AI39: 31 | AJ39: 32 | AK39: 33 | AL39: 34 | AM39: 35 | AN39: 36 | AO39: 37 | AP39: 38 | AQ39: 39 | AR39: 40 | AS39: 41 | AT39: 42 | AU39: 43 | AV39: 44 | AW39: 45 | AX39: 46 | AY39: 47 | AZ39: 48 | BA39: 49 | BB39: 50 | BC39: 51 | BD39: 52 | BE39: 53 | BF39: 54 | BG39: 55 | BH39: 56 | BI39: 57 | BJ39: 58 | BK39: 59 | BL39: 60 | BM39: 61 | BN39: 62 | BO39: 63 | BP39: 64 | BQ39: 65 | BR39: 66 | BS39: 67 | BT39: 68 | BU39: 69 | BV39: 70 | BW39: .
B40: Percent survival per age | C40: % | D40: =D36 -> 1 | E40: =($I40-$D40)/($I$39-$D$39)+D40 -> 0.998 | F40: =($I40-$D40)/($I$39-$D$39)+E40 -> 0.996 | G40: =($I40-$D40)/($I$39-$D$39)+F40 -> 0.994 | H40: =($I40-$D40)/($I$39-$D$39)+G40 -> 0.992 | I40: =E36 -> 0.99 | J40: =($N40-$I40)/($N$39-$I$39)+I40 -> 0.984 | K40: =($N40-$I40)/($N$39-$I$39)+J40 -> 0.978 | L40: =($N40-$I40)/($N$39-$I$39)+K40 -> 0.972 | M40: =($N40-$I40)/($N$39-$I$39)+L40 -> 0.966 | N40: =F36 -> 0.96 | O40: =($S40-$N40)/($S$39-$N$39)+N40 -> 0.938 | P40: =($S40-$N40)/($S$39-$N$39)+O40 -> 0.916 | Q40: =($S40-$N40)/($S$39-$N$39)+P40 -> 0.894 | R40: =($S40-$N40)/($S$39-$N$39)+Q40 -> 0.872 | S40: =G36 -> 0.85 | T40: =($X40-$S40)/($X$39-$S$39)+S40 -> 0.814 | U40: =($X40-$S40)/($X$39-$S$39)+T40 -> 0.778 | V40: =($X40-$S40)/($X$39-$S$39)+U40 -> 0.742 | W40: =($X40-$S40)/($X$39-$S$39)+V40 -> 0.706 | X40: =H36 -> 0.67 | Y40: =($AC40-$X40)/($AC$39-$X$39)+X40 -> 0.632 | Z40: =($AC40-$X40)/($AC$39-$X$39)+Y40 -> 0.594 | AA40: =($AC40-$X40)/($AC$39-$X$39)+Z40 -> 0.556 | AB40: =($AC40-$X40)/($AC$39-$X$39)+AA40 -> 0.518 | AC40: =I36 -> 0.48 | AD40: =($AH40-$AC40)/($AH$39-$AC$39)+AC40 -> 0.448 | AE40: =($AH40-$AC40)/($AH$39-$AC$39)+AD40 -> 0.416 | AF40: =($AH40-$AC40)/($AH$39-$AC$39)+AE40 -> 0.384 | AG40: =($AH40-$AC40)/($AH$39-$AC$39)+AF40 -> 0.352 | AH40: =J36 -> 0.32 | AI40: =($AM40-$AH40)/($AM$39-$AH$39)+AH40 -> 0.298 | AJ40: =($AM40-$AH40)/($AM$39-$AH$39)+AI40 -> 0.276 | AK40: =($AM40-$AH40)/($AM$39-$AH$39)+AJ40 -> 0.254 | AL40: =($AM40-$AH40)/($AM$39-$AH$39)+AK40 -> 0.232 | AM40: =K36 -> 0.21 | AN40: =($AR40-$AM40)/($AR$39-$AM$39)+AM40 -> 0.194 | AO40: =($AR40-$AM40)/($AR$39-$AM$39)+AN40 -> 0.178 | AP40: =($AR40-$AM40)/($AR$39-$AM$39)+AO40 -> 0.162 | AQ40: =($AR40-$AM40)/($AR$39-$AM$39)+AP40 -> 0.146 | AR40: =L36 -> 0.13 | AS40: =($AW40-$AR40)/($AW$39-$AR$39)+AR40 -> 0.12 | AT40: =($AW40-$AR40)/($AW$39-$AR$39)+AS40 -> 0.11 | AU40: =($AW40-$AR40)/($AW$39-$AR$39)+AT40 -> 0.1 | AV40: =($AW40-$AR40)/($AW$39-$AR$39)+AU40 -> 0.09 | AW40: =M36 -> 0.08 | AX40: =($BB40-$AW40)/($BB$39-$AW$39)+AW40 -> 0.073 | AY40: =($BB40-$AW40)/($BB$39-$AW$39)+AX40 -> 0.066 | AZ40: =($BB40-$AW40)/($BB$39-$AW$39)+AY40 -> 0.059 | BA40: =($BB40-$AW40)/($BB$39-$AW$39)+AZ40 -> 0.052 | BB40: =N36 -> 0.045 | BC40: =($BG40-$BB40)/($BG$39-$BB$39)+BB40 -> 0.041 | BD40: =($BG40-$BB40)/($BG$39-$BB$39)+BC40 -> 0.037 | BE40: =($BG40-$BB40)/($BG$39-$BB$39)+BD40 -> 0.033 | BF40: =($BG40-$BB40)/($BG$39-$BB$39)+BE40 -> 0.029 | BG40: =O36 -> 0.025 | BH40: =($BL40-$BG40)/($BL$39-$BG$39)+BG40 -> 0.022 | BI40: =($BL40-$BG40)/($BL$39-$BG$39)+BH40 -> 0.019 | BJ40: =($BL40-$BG40)/($BL$39-$BG$39)+BI40 -> 0.016 | BK40: =($BL40-$BG40)/($BL$39-$BG$39)+BJ40 -> 0.013 | BL40: =P36 -> 0.01 | BM40: =($BQ40-$BL40)/($BQ$39-$BL$39)+BL40 -> 0.0088 | BN40: =($BQ40-$BL40)/($BQ$39-$BL$39)+BM40 -> 0.0076 | BO40: =($BQ40-$BL40)/($BQ$39-$BL$39)+BN40 -> 0.0064 | BP40: =($BQ40-$BL40)/($BQ$39-$BL$39)+BO40 -> 0.0052 | BQ40: =Q36 -> 0.004 | BR40: =($BV40-$BQ40)/($BV$39-$BQ$39)+BQ40 -> 0.0032 | BS40: =($BV40-$BQ40)/($BV$39-$BQ$39)+BR40 -> 0.0024 | BT40: =($BV40-$BQ40)/($BV$39-$BQ$39)+BS40 -> 0.0016 | BU40: =($BV40-$BQ40)/($BV$39-$BQ$39)+BT40 -> 0.0008 | BV40: =R36 -> 0 | BW40: .
BW41: .
D42: 1980 | E42: 1981 | F42: 1982 | G42: 1983 | H42: 1984 | I42: 1985 | J42: 1986 | K42: 1987 | L42: 1988 | M42: 1989 | N42: 1990 | O42: 1991 | P42: 1992 | Q42: 1993 | R42: 1994 | S42: 1995 | T42: 1996 | U42: 1997 | V42: 1998 | W42: 1999 | X42: 2000 | Y42: 2001 | Z42: 2002 | AA42: 2003 | AB42: 2004 | AC42: 2005 | AD42: 2006 | AE42: 2007 | AF42: 2008 | AG42: 2009 | AH42: 2010 | AI42: 2011 | AJ42: 2012 | AK42: 2013 | AL42: 2014 | AM42: 2015 | AN42: 2016 | AO42: 2017 | AP42: 2018 | AQ42: 2019 | AR42: 2020 | AS42: 2021 | AT42: 2022 | AU42: 2023 | AV42: 2024 | AW42: 2025 | AX42: 2026 | AY42: 2027 | AZ42: 2028 | BA42: 2029 | BB42: 2030 | BC42: 2031 | BD42: 2032 | BE42: 2033 | BF42: 2034 | BG42: 2035 | BH42: 2036 | BI42: 2037 | BJ42: 2038 | BK42: 2039 | BL42: 2040 | BM42: 2041 | BN42: 2042 | BO42: 2043 | BP42: 2044 | BQ42: 2045 | BR42: 2046 | BS42: 2047 | BT42: 2048 | BU42: 2049 | BV42: 2050 | BW42: .
B43: TOTAL CAR FLEET | C43: Units | D43: =D55 -> 4298190.1 | E43: =E55 -> 4680898.9 | F43: =F55 -> 4947038.1 | G43: =G55 -> 5046431.2 | H43: =H55 -> 5280556.6 | I43: =I55 -> 5565419.3 | J43: =J55 -> 5457999.2 | K43: =K55 -> 5561239.7 | ... AV43: =AV55 -> 23298996 | BW43: .
B44: Average age real fleet (2024) | C44: Years | D44: =BE55/BD55 -> 12.99737 | L44: Milion vehicles in 2050: | AL44: Projected fleet based on its own growth trends >> | AM44: =$AM$55 -> 20339859 | AN44: =AM44*(1+$E$46) -> 21234813 | AO44: =AN44*(1+$E$46) -> 22169145 | AP44: =AO44*(1+$E$46) -> 23144587 | AQ44: =AP44*(1+$E$46) -> 24162949 | AR44: =AQ44*(1+$E$46) -> 25226119 | AS44: =AR44*(1+$E$46) -> 26336068 | AT44: =AS44*(1+$E$46) -> 27494855 | AU44: =AT44*(1+$E$46) -> 28704629 | ... BV44: =BU44*(1+$E$46) -> 91804802 | BW44: .
B45: Fleet in 2015 | C45: Million vehicles | D45: =AM44/10^6 -> 20.339859 | L45: =BV44/10^6 -> 91.804802 | M45: Based on fleet's own growth trends (4.4% annual 2015-2050) | AL45: Projected fleet based on trends of motorisation rates (vehicles / people) 2.5% annual >> | AM45: =$AM$55 -> 20339859 | AN45: =AN50*(AN$49*10^3) -> 21058064 | AO45: =AO50*(AO$49*10^3) -> 21799466 | AP45: =AP50*(AP$49*10^3) -> 22564777 | AQ45: =AQ50*(AQ$49*10^3) -> 23354730 | AR45: =AR50*(AR$49*10^3) -> 24170076 | AS45: =AS50*(AS$49*10^3) -> 24988458 | AT45: =AT50*(AT$49*10^3) -> 25832653 | AU45: =AU50*(AU$49*10^3) -> 26703440 | ... BV45: =BV50*(BV$49*10^3) -> 60170880 | BW45: .
B46: Actual CAGR (2000-2015) | C46: % | D46: =(AM44/D43)^(1/(AM42-D42))-1 -> 0.045412034 | E46: 0.044 | L46: =BV45/10^6 -> 60.17088 | M46: Based on trends of motorisation rates (vehicles/people, 2.5% annual 2015-2050) | AL46: Projected fleet based on annual variation of registration >> | AM46: =$AM$55 -> 20339859 | AN46: =(678.8*(AN42-$AM42)^2)+((AN42-$AM42)*11573)+133777+AM46 -> 20485888 | AO46: =((AO42-$AM42)^2*678.8)+((AO42-$AM42)*11573)+133777+AN46 -> 20645526 | AP46: =((AP42-$AM42)^2*678.8)+((AP42-$AM42)*11573)+133777+AO46 -> 20820132 | AQ46: =((AQ42-$AM42)^2*678.8)+((AQ42-$AM42)*11573)+133777+AP46 -> 21011061 | AR46: =((AR42-$AM42)^2*678.8)+((AR42-$AM42)*11573)+133777+AQ46 -> 21219673 | AS46: =((AS42-$AM42)^2*678.8)+((AS42-$AM42)*11573)+133777+AR46 -> 21447325 | AT46: =((AT42-$AM42)^2*678.8)+((AT42-$AM42)*11573)+133777+AS46 -> 21695374 | AU46: =((AU42-$AM42)^2*678.8)+((AU42-$AM42)*11573)+133777+AT46 -> 21965179 | AV46: =((AV42-$AM42)^2*678.8)+((AV42-$AM42)*11573)+133777+AU46 -> 22258095 | ... BV46: =((BV42-$AM42)^2*678.8)+((BV42-$AM42)*11573)+133777+BU46 -> 42433952 | BW46: .
L47: =BV46/10^6 -> 42.433952 | M47: Based on trends of annual variation of vehicle registration (2.1 % annual 2015-2050) | BW47: .
BW48: .
B49: Population | C49: million people | D49: 68.163974 | E49: 69.507067 | F49: 70.876625 | G49: 72.273168 | H49: 73.697228 | I49: 75.149348 | J49: 76.63008 | K49: 78.139989 | L49: 79.679648 | M49: 81.249645 | N49: 83.141224 | O49: 85.07684 | P49: 87.05752 | Q49: 89.084312 | R49: 91.15829 | S49: 92.389599 | T49: 93.637539 | U49: 94.902336 | V49: 96.184216 | W49: 97.483412 | X49: 98.612927 | Y49: 99.75553 | Z49: 100.91137 | AA49: 102.08061 | AB49: 103.26339 | AC49: 105.01741 | AD49: 106.80123 | AE49: 108.61534 | AF49: 110.46027 | AG49: 112.33654 | AH49: 114.25556 | AI49: 115.60561 | AJ49: 116.95566 | AK49: 118.30571 | AL49: 119.65576 | AM49: 121.00582 | AN49: 122.22298 | AO49: 123.44015 | AP49: 124.65731 | AQ49: 125.87448 | AR49: 127.09164 | AS49: 128.19012 | AT49: 129.28861 | AU49: 130.38709 | AV49: 131.48557 | AW49: 132.58405 | AX49: 133.56351 | AY49: 134.54297 | AZ49: 135.52242 | BA49: 136.50188 | BB49: 137.48134 | BC49: 138.33645 | BD49: 139.19157 | BE49: 140.04669 | BF49: 140.9018 | BG49: 141.75692 | BH49: 142.48871 | BI49: 143.2205 | BJ49: 143.95228 | BK49: 144.68407 | BL49: 145.41586 | BM49: 146.02289 | BN49: 146.62993 | BO49: 147.23696 | BP49: 147.844 | BQ49: 148.45103 | BR49: 148.92833 | BS49: 149.40563 | BT49: 149.88292 | BU49: 150.36022 | BV49: 150.83752 | BW49: .
B50: Motorisation rate | C50: vehicles / 1000 people | D50: =D43/(D49*10^3) -> 63.056625 | E50: =E43/(E49*10^3) -> 67.344216 | F50: =F43/(F49*10^3) -> 69.797879 | G50: =G43/(G49*10^3) -> 69.824409 | H50: =H43/(H49*10^3) -> 71.652038 | I50: =I43/(I49*10^3) -> 74.058118 | J50: =J43/(J49*10^3) -> 71.225283 | K50: =K43/(K49*10^3) -> 71.170214 | ... AL50: =AL43/(AL49*10^3) -> 162.0616 | AM50: =AM44/(AM49*10^3) -> 168.08993 | AN50: =AM50*(1+$E51) -> 172.29218 | AO50: =AN50*(1+$E51) -> 176.59949 | AP50: =AO50*(1+$E51) -> 181.01447 | AQ50: =AP50*(1+$E51) -> 185.53983 | AR50: =AQ50*(1+$E51) -> 190.17833 | AS50: =AR50*(1+$E51) -> 194.93279 | AT50: =AS50*(1+$E51) -> 199.80611 | AU50: =AT50*(1+$E51) -> 204.80126 | ... BV50: =BU50*(1+$E51) -> 398.9119 | BW50: .
B51: CAGR motorisation 1980-2015 | C51: % | D51: =(AM50/D50)^(1/(AM42-D42))-1 -> 0.028409378 | E51: 0.025 | G51: =BV45/10^6 -> 60.17088 | H51: milion veicles in 2050 | AR51: =(AR45-AH43)/(10*0.96) -> 796350.21 | BB51: =(BB45-AR45)/(10*0.96) -> 968643.43 | BL51: =(BL45-BB45)/(10*0.96) -> 1234041.1 | BV51: =(BV45-BL45)/(10*0.96) -> 1547399.2 | BW51: .
BE52: Avg age | BW52: .
B53: Annually registered cars | C53: Units/yr | D53: =D2*(E53/E2) -> 356048.18 | E53: =E2-D2 -> 391321 | F53: =F2-E2 -> 275534 | G53: =G2-F2 -> 109339 | H53: =H2-G2 -> 244290 | I53: =I2-H2 -> 311316 | J53: =J2-I2 -> -78920 | K53: =K2-J2 -> 133306 | L53: =L2-K2 -> 261507 | ... AV53: =AV2-AU2 -> 636489 | BC53: En 2024 | BE53: =BE55/BD55 -> 12.99737 | BW53: .
AR54: . | AU54: TACC 12-24 | AV54: =(AV55/AJ55)^(1/(AV$1-AJ$1))-1 -> 0.020631534 | BA54: Age (chart) | BB54: Million cars (chart) | BC54: Edad | BD54: Unidades | BE54: Años totales | BG54: Salieron de circulacion | BW54: .
B55: Surviving CAR fleet by year-model | C55: =SUM(C56:C101) -> 3950042 | D55: =SUM(D56:D101) -> 4298190.1 | E55: =SUM(E56:E101) -> 4680898.9 | F55: =SUM(F56:F101) -> 4947038.1 | G55: =SUM(G56:G101) -> 5046431.2 | H55: =SUM(H56:H101) -> 5280556.6 | I55: =SUM(I56:I101) -> 5565419.3 | J55: =SUM(J56:J101) -> 5457999.2 | ... AV55: =SUM(AV56:AV101) -> 23298996 | BD55: =SUM(BD56:BD101) -> 23298996 | BE55: =SUM(BE56:BE101) -> 3.0282567e+08 | BG55: =AV55-AU55 -> -86228.445 | BW55: .
B56: Older than 1980 | C56: =D2 -> 3950042 | D56: =$C56*E$40 -> 3942141.9 | E56: =$C56*F$40 -> 3934241.8 | F56: =$C56*G$40 -> 3926341.7 | G56: =$C56*H$40 -> 3918441.7 | H56: =$C56*I$40 -> 3910541.6 | I56: =$C56*J$40 -> 3886841.3 | J56: =$C56*K$40 -> 3863141.1 | K56: =$C56*L$40 -> 3839440.8 | ... AV56: =$C56*AW$40 -> 316003.36 | BA56: =-BC56 -> -45 | BB56: =(IF(BD56>0,BD56,0))/10^6 -> 0.31600336 | BC56: 45 | BD56: =AV56 -> 316003.36 | BE56: =BC56*BD56 -> 14220151 | BG56: =AV56-AU56 -> -39500.42 | BW56: .
B57: 1980 | D57: =D53 -> 356048.18 | E57: =$D57*E$40 -> 355336.08 | F57: =$D57*F$40 -> 354623.99 | G57: =$D57*G$40 -> 353911.89 | H57: =$D57*H$40 -> 353199.79 | I57: =$D57*I$40 -> 352487.7 | J57: =$D57*J$40 -> 350351.41 | K57: =$D57*K$40 -> 348215.12 | L57: =$D57*L$40 -> 346078.83 | ... AV57: =$D57*AV$40 -> 32044.336 | BA57: -44 | BB57: =(IF(BD57>0,BD57,0))/10^6 -> 0.032044336 | BC57: 44 | BD57: =AV57 -> 32044.336 | BE57: =BC57*BD57 -> 1409950.8 | BG57: =AV57-AU57 -> -3560.4818 | BW57: .
B58: 1981 | E58: =E53 -> 391321 | F58: =$E58*E$40 -> 390538.36 | G58: =$E58*F$40 -> 389755.72 | H58: =$E58*G$40 -> 388973.07 | I58: =$E58*H$40 -> 388190.43 | J58: =$E58*I$40 -> 387407.79 | K58: =$E58*J$40 -> 385059.86 | L58: =$E58*K$40 -> 382711.94 | M58: =$E58*L$40 -> 380364.01 | ... AV58: =$E58*AU$40 -> 39132.1 | BA58: -43 | BB58: =(IF(BD58>0,BD58,0))/10^6 -> 0.0391321 | BC58: 43 | BD58: =AV58 -> 39132.1 | BE58: =BC58*BD58 -> 1682680.3 | BG58: =AV58-AU58 -> -3913.21 | BW58: .
B59: 1982 | F59: =F53 -> 275534 | G59: =$F59*E$40 -> 274982.93 | H59: =$F59*F$40 -> 274431.86 | I59: =$F59*G$40 -> 273880.8 | J59: =$F59*H$40 -> 273329.73 | K59: =$F59*I$40 -> 272778.66 | L59: =$F59*J$40 -> 271125.46 | M59: =$F59*K$40 -> 269472.25 | N59: =$F59*L$40 -> 267819.05 | ... AV59: =$F59*AT$40 -> 30308.74 | BA59: -42 | BB59: =(IF(BD59>0,BD59,0))/10^6 -> 0.03030874 | BC59: 42 | BD59: =AV59 -> 30308.74 | BE59: =BC59*BD59 -> 1272967.1 | BG59: =AV59-AU59 -> -2755.34 | BW59: .
B60: 1983 | G60: =G53 -> 109339 | H60: =$G60*E$40 -> 109120.32 | I60: =$G60*F$40 -> 108901.64 | J60: =$G60*G$40 -> 108682.97 | K60: =$G60*H$40 -> 108464.29 | L60: =$G60*I$40 -> 108245.61 | M60: =$G60*J$40 -> 107589.58 | N60: =$G60*K$40 -> 106933.54 | O60: =$G60*L$40 -> 106277.51 | ... AV60: =$G60*AS$40 -> 13120.68 | BA60: -41 | BB60: =(IF(BD60>0,BD60,0))/10^6 -> 0.01312068 | BC60: 41 | BD60: =AV60 -> 13120.68 | BE60: =BC60*BD60 -> 537947.88 | BG60: =AV60-AU60 -> -1093.39 | BW60: .
B61: 1984 | H61: =H53 -> 244290 | I61: =$H61*E$40 -> 243801.42 | J61: =$H61*F$40 -> 243312.84 | K61: =$H61*G$40 -> 242824.26 | L61: =$H61*H$40 -> 242335.68 | M61: =$H61*I$40 -> 241847.1 | N61: =$H61*J$40 -> 240381.36 | O61: =$H61*K$40 -> 238915.62 | P61: =$H61*L$40 -> 237449.88 | ... AV61: =$H61*AR$40 -> 31757.7 | BA61: -40 | BB61: =(IF(BD61>0,BD61,0))/10^6 -> 0.0317577 | BC61: 40 | BD61: =AV61 -> 31757.7 | BE61: =BC61*BD61 -> 1270308 | BG61: =AV61-AU61 -> -3908.64 | BW61: .
B62: 1985 | I62: =I53 -> 311316 | J62: =$I62*E$40 -> 310693.37 | K62: =$I62*F$40 -> 310070.74 | L62: =$I62*G$40 -> 309448.1 | M62: =$I62*H$40 -> 308825.47 | N62: =$I62*I$40 -> 308202.84 | O62: =$I62*J$40 -> 306334.94 | P62: =$I62*K$40 -> 304467.05 | Q62: =$I62*L$40 -> 302599.15 | ... AV62: =$I62*AQ$40 -> 45452.136 | BA62: -39 | BB62: =(IF(BD62>0,BD62,0))/10^6 -> 0.045452136 | BC62: 39 | BD62: =AV62 -> 45452.136 | BE62: =BC62*BD62 -> 1772633.3 | BG62: =AV62-AU62 -> -4981.056 | BW62: .
B63: 1986 | J63: =J53 -> -78920 | K63: =J63 -> -78920 | L63: =K63 -> -78920 | M63: =L63 -> -78920 | N63: =M63 -> -78920 | O63: =N63 -> -78920 | P63: =O63 -> -78920 | Q63: =P63 -> -78920 | R63: =Q63 -> -78920 | ... AV63: =AU63 -> -78920 | AW63: terremoto | BA63: -38 | BB63: =(IF(BD63>0,BD63,0))/10^6 -> 0 | BC63: 38 | BD63: =AV63 -> -78920 | BE63: =BC63*BD63 -> -2998960 | BG63: =AV63-AU63 -> 0 | BW63: .
B64: 1987 | K64: =K53 -> 133306 | L64: =$K64*E$40 -> 133039.39 | M64: =$K64*F$40 -> 132772.78 | N64: =$K64*G$40 -> 132506.16 | O64: =$K64*H$40 -> 132239.55 | P64: =$K64*I$40 -> 131972.94 | Q64: =$K64*J$40 -> 131173.1 | R64: =$K64*K$40 -> 130373.27 | S64: =$K64*L$40 -> 129573.43 | ... AV64: =$K64*AO$40 -> 23728.468 | BA64: -37 | BB64: =(IF(BD64>0,BD64,0))/10^6 -> 0.023728468 | BC64: 37 | BD64: =AV64 -> 23728.468 | BE64: =BC64*BD64 -> 877953.32 | BG64: =AV64-AU64 -> -2132.896 | BW64: .
B65: 1988 | L65: =L53 -> 261507 | M65: =$L65*E$40 -> 260983.99 | N65: =$L65*F$40 -> 260460.97 | O65: =$L65*G$40 -> 259937.96 | P65: =$L65*H$40 -> 259414.94 | Q65: =$L65*I$40 -> 258891.93 | R65: =$L65*J$40 -> 257322.89 | S65: =$L65*K$40 -> 255753.85 | T65: =$L65*L$40 -> 254184.8 | ... AV65: =$L65*AN$40 -> 50732.358 | BA65: -36 | BB65: =(IF(BD65>0,BD65,0))/10^6 -> 0.050732358 | BC65: 36 | BD65: =AV65 -> 50732.358 | BE65: =BC65*BD65 -> 1826364.9 | BG65: =AV65-AU65 -> -4184.112 | BW65: .
B66: 1989 | M66: =M53 -> 405797 | N66: =$M66*E$40 -> 404985.41 | O66: =$M66*F$40 -> 404173.81 | P66: =$M66*G$40 -> 403362.22 | Q66: =$M66*H$40 -> 402550.62 | R66: =$M66*I$40 -> 401739.03 | S66: =$M66*J$40 -> 399304.25 | T66: =$M66*K$40 -> 396869.47 | U66: =$M66*L$40 -> 394434.68 | ... AV66: =$M66*AM$40 -> 85217.37 | BA66: =-BC66 -> -35 | BB66: =(IF(BD66>0,BD66,0))/10^6 -> 0.08521737 | BC66: 35 | BD66: =AV66 -> 85217.37 | BE66: =BC66*BD66 -> 2982607.9 | BG66: =AV66-AU66 -> -8927.534 | BW66: .
B67: 1990 | N67: =N53 -> 552018 | O67: =$N67*E$40 -> 550913.96 | P67: =$N67*F$40 -> 549809.93 | Q67: =$N67*G$40 -> 548705.89 | R67: =$N67*H$40 -> 547601.86 | S67: =$N67*I$40 -> 546497.82 | T67: =$N67*J$40 -> 543185.71 | U67: =$N67*K$40 -> 539873.6 | V67: =$N67*L$40 -> 536561.5 | ... AV67: =$N67*AL$40 -> 128068.18 | BA67: =-BC67 -> -34 | BB67: =(IF(BD67>0,BD67,0))/10^6 -> 0.12806818 | BC67: 34 | BD67: =AV67 -> 128068.18 | BE67: =BC67*BD67 -> 4354318 | BG67: =AV67-AU67 -> -12144.396 | BW67: .
B68: 1991 | O68: =O53 -> 395158 | P68: =$O68*E$40 -> 394367.68 | Q68: =$O68*F$40 -> 393577.37 | R68: =$O68*G$40 -> 392787.05 | S68: =$O68*H$40 -> 391996.74 | T68: =$O68*I$40 -> 391206.42 | U68: =$O68*J$40 -> 388835.47 | V68: =$O68*K$40 -> 386464.52 | W68: =$O68*L$40 -> 384093.58 | ... AV68: =$O68*AK$40 -> 100370.13 | BA68: =-BC68 -> -33 | BB68: =(IF(BD68>0,BD68,0))/10^6 -> 0.10037013 | BC68: 33 | BD68: =AV68 -> 100370.13 | BE68: =BC68*BD68 -> 3312214.4 | BG68: =AV68-AU68 -> -8693.476 | BW68: .
B69: 1992 | P69: =P53 -> 448470 | Q69: =$P69*E$40 -> 447573.06 | R69: =$P69*F$40 -> 446676.12 | S69: =$P69*G$40 -> 445779.18 | T69: =$P69*H$40 -> 444882.24 | U69: =$P69*I$40 -> 443985.3 | V69: =$P69*J$40 -> 441294.48 | W69: =$P69*K$40 -> 438603.66 | X69: =$P69*L$40 -> 435912.84 | ... AV69: =$P69*AJ$40 -> 123777.72 | BA69: =-BC69 -> -32 | BB69: =(IF(BD69>0,BD69,0))/10^6 -> 0.12377772 | BC69: 32 | BD69: =AV69 -> 123777.72 | BE69: =BC69*BD69 -> 3960887 | BG69: =AV69-AU69 -> -9866.34 | BW69: .
B70: 1993 | Q70: =Q53 -> 316773 | R70: =$Q70*E$40 -> 316139.45 | S70: =$Q70*F$40 -> 315505.91 | T70: =$Q70*G$40 -> 314872.36 | U70: =$Q70*H$40 -> 314238.82 | V70: =$Q70*I$40 -> 313605.27 | W70: =$Q70*J$40 -> 311704.63 | X70: =$Q70*K$40 -> 309803.99 | Y70: =$Q70*L$40 -> 307903.36 | ... AV70: =$Q70*AI$40 -> 94398.354 | BA70: =-BC70 -> -31 | BB70: =(IF(BD70>0,BD70,0))/10^6 -> 0.094398354 | BC70: 31 | BD70: =AV70 -> 94398.354 | BE70: =BC70*BD70 -> 2926349 | BG70: =AV70-AU70 -> -6969.006 | BW70: .
B71: 1994 | R71: =R53 -> -498219 | S71: =R71 -> -498219 | T71: =S71 -> -498219 | U71: =T71 -> -498219 | V71: =U71 -> -498219 | W71: =V71 -> -498219 | X71: =W71 -> -498219 | Y71: =X71 -> -498219 | Z71: =Y71 -> -498219 | ... AV71: =AU71 -> -498219 | AW71: Hoy No Circula | BA71: =-BC71 -> -30 | BB71: =(IF(BD71>0,BD71,0))/10^6 -> 0 | BC71: 30 | BD71: =AV71 -> -498219 | BE71: =BC71*BD71 -> -14946570 | BG71: =AV71-AU71 -> 0 | BW71: .
B72: 1995 | S72: =S53 -> 251772 | T72: =$S72*E$40 -> 251268.46 | U72: =$S72*F$40 -> 250764.91 | V72: =$S72*G$40 -> 250261.37 | W72: =$S72*H$40 -> 249757.82 | X72: =$S72*I$40 -> 249254.28 | Y72: =$S72*J$40 -> 247743.65 | Z72: =$S72*K$40 -> 246233.02 | AA72: =$S72*L$40 -> 244722.38 | ... AV72: =$S72*AG$40 -> 88623.744 | BA72: =-BC72 -> -29 | BB72: =(IF(BD72>0,BD72,0))/10^6 -> 0.088623744 | BC72: 29 | BD72: =AV72 -> 88623.744 | BE72: =BC72*BD72 -> 2570088.6 | BG72: =AV72-AU72 -> -8056.704 | BW72: .
B73: 1996 | T73: =T53 -> 361360 | U73: =$T73*E$40 -> 360637.28 | V73: =$T73*F$40 -> 359914.56 | W73: =$T73*G$40 -> 359191.84 | X73: =$T73*H$40 -> 358469.12 | Y73: =$T73*I$40 -> 357746.4 | Z73: =$T73*J$40 -> 355578.24 | AA73: =$T73*K$40 -> 353410.08 | AB73: =$T73*L$40 -> 351241.92 | ... AV73: =$T73*AF$40 -> 138762.24 | BA73: =-BC73 -> -28 | BB73: =(IF(BD73>0,BD73,0))/10^6 -> 0.13876224 | BC73: 28 | BD73: =AV73 -> 138762.24 | BE73: =BC73*BD73 -> 3885342.7 | BG73: =AV73-AU73 -> -11563.52 | BW73: .
B74: 1997 | U74: =U53 -> 572131 | V74: =$U74*E$40 -> 570986.74 | W74: =$U74*F$40 -> 569842.48 | X74: =$U74*G$40 -> 568698.21 | Y74: =$U74*H$40 -> 567553.95 | Z74: =$U74*I$40 -> 566409.69 | AA74: =$U74*J$40 -> 562976.9 | AB74: =$U74*K$40 -> 559544.12 | AC74: =$U74*L$40 -> 556111.33 | ... AV74: =$U74*AE$40 -> 238006.5 | BA74: =-BC74 -> -27 | BB74: =(IF(BD74>0,BD74,0))/10^6 -> 0.2380065 | BC74: 27 | BD74: =AV74 -> 238006.5 | BE74: =BC74*BD74 -> 6426175.4 | BG74: =AV74-AU74 -> -18308.192 | BW74: .
B75: 1998 | V75: =V53 -> 683214 | W75: =$V75*E$40 -> 681847.57 | X75: =$V75*F$40 -> 680481.14 | Y75: =$V75*G$40 -> 679114.72 | Z75: =$V75*H$40 -> 677748.29 | AA75: =$V75*I$40 -> 676381.86 | AB75: =$V75*J$40 -> 672282.58 | AC75: =$V75*K$40 -> 668183.29 | AD75: =$V75*L$40 -> 664084.01 | ... AV75: =$V75*AD$40 -> 306079.87 | BA75: =-BC75 -> -26 | BB75: =(IF(BD75>0,BD75,0))/10^6 -> 0.30607987 | BC75: 26 | BD75: =AV75 -> 306079.87 | BE75: =BC75*BD75 -> 7958076.7 | BG75: =AV75-AU75 -> -21862.848 | BW75: .
B76: 1999 | W76: =W53 -> 496587 | X76: =$W76*E$40 -> 495593.83 | Y76: =$W76*F$40 -> 494600.65 | Z76: =$W76*G$40 -> 493607.48 | AA76: =$W76*H$40 -> 492614.3 | AB76: =$W76*I$40 -> 491621.13 | AC76: =$W76*J$40 -> 488641.61 | AD76: =$W76*K$40 -> 485662.09 | AE76: =$W76*L$40 -> 482682.56 | ... AV76: =$W76*AC$40 -> 238361.76 | BA76: =-BC76 -> -25 | BB76: =(IF(BD76>0,BD76,0))/10^6 -> 0.23836176 | BC76: 25 | BD76: =AV76 -> 238361.76 | BE76: =BC76*BD76 -> 5959044 | BG76: =AV76-AU76 -> -18870.306 | BW76: .
B77: 2000 | X77: =X53 -> 593383 | Y77: =$X77*E$40 -> 592196.23 | Z77: =$X77*F$40 -> 591009.47 | AA77: =$X77*G$40 -> 589822.7 | AB77: =$X77*H$40 -> 588635.94 | AC77: =$X77*I$40 -> 587449.17 | AD77: =$X77*J$40 -> 583888.87 | AE77: =$X77*K$40 -> 580328.57 | AF77: =$X77*L$40 -> 576768.28 | ... AV77: =$X77*AB$40 -> 307372.39 | BA77: =-BC77 -> -24 | BB77: =(IF(BD77>0,BD77,0))/10^6 -> 0.30737239 | BC77: 24 | BD77: =AV77 -> 307372.39 | BE77: =BC77*BD77 -> 7376937.5 | BG77: =AV77-AU77 -> -22548.554 | BW77: .
B78: 2001 | Y78: =Y53 -> 1175803 | Z78: =$Y78*E$40 -> 1173451.4 | AA78: =$Y78*F$40 -> 1171099.8 | AB78: =$Y78*G$40 -> 1168748.2 | AC78: =$Y78*H$40 -> 1166396.6 | AD78: =$Y78*I$40 -> 1164045 | AE78: =$Y78*J$40 -> 1156990.2 | AF78: =$Y78*K$40 -> 1149935.3 | AG78: =$Y78*L$40 -> 1142880.5 | ... AV78: =$Y78*AA$40 -> 653746.47 | BA78: =-BC78 -> -23 | BB78: =(IF(BD78>0,BD78,0))/10^6 -> 0.65374647 | BC78: 23 | BD78: =AV78 -> 653746.47 | BE78: =BC78*BD78 -> 15036169 | BG78: =AV78-AU78 -> -44680.514 | BW78: .
B79: 2002 | Z79: =Z53 -> 902928 | AA79: =$Z79*E$40 -> 901122.14 | AB79: =$Z79*F$40 -> 899316.29 | AC79: =$Z79*G$40 -> 897510.43 | AD79: =$Z79*H$40 -> 895704.58 | AE79: =$Z79*I$40 -> 893898.72 | AF79: =$Z79*J$40 -> 888481.15 | AG79: =$Z79*K$40 -> 883063.58 | AH79: =$Z79*L$40 -> 877646.02 | ... AV79: =$Z79*Z$40 -> 536339.23 | BA79: =-BC79 -> -22 | BB79: =(IF(BD79>0,BD79,0))/10^6 -> 0.53633923 | BC79: 22 | BD79: =AV79 -> 536339.23 | BE79: =BC79*BD79 -> 11799463 | BG79: =AV79-AU79 -> -34311.264 | BW79: .
B80: 2003 | AA80: =AA53 -> 487139 | AB80: =$AA80*E$40 -> 486164.72 | AC80: =$AA80*F$40 -> 485190.44 | AD80: =$AA80*G$40 -> 484216.17 | AE80: =$AA80*H$40 -> 483241.89 | AF80: =$AA80*I$40 -> 482267.61 | AG80: =$AA80*J$40 -> 479344.78 | AH80: =$AA80*K$40 -> 476421.94 | AI80: =$AA80*L$40 -> 473499.11 | ... AV80: =$AA80*Y$40 -> 307871.85 | BA80: =-BC80 -> -21 | BB80: =(IF(BD80>0,BD80,0))/10^6 -> 0.30787185 | BC80: 21 | BD80: =AV80 -> 307871.85 | BE80: =BC80*BD80 -> 6465308.8 | BG80: =AV80-AU80 -> -18511.282 | BW80: .
B81: 2004 | AB81: =AB53 -> 645962 | AC81: =$AB81*E$40 -> 644670.08 | AD81: =$AB81*F$40 -> 643378.15 | AE81: =$AB81*G$40 -> 642086.23 | AF81: =$AB81*H$40 -> 640794.3 | AG81: =$AB81*I$40 -> 639502.38 | AH81: =$AB81*J$40 -> 635626.61 | AI81: =$AB81*K$40 -> 631750.84 | AJ81: =$AB81*L$40 -> 627875.06 | ... AV81: =$AB81*X$40 -> 432794.54 | BA81: =-BC81 -> -20 | BB81: =(IF(BD81>0,BD81,0))/10^6 -> 0.43279454 | BC81: 20 | BD81: =AV81 -> 432794.54 | BE81: =BC81*BD81 -> 8655890.8 | BG81: =AV81-AU81 -> -23254.632 | BW81: .
B82: 2005 | AC82: =AC53 -> 912369 | AD82: =$AC82*E$40 -> 910544.26 | AE82: =$AC82*F$40 -> 908719.52 | AF82: =$AC82*G$40 -> 906894.79 | AG82: =$AC82*H$40 -> 905070.05 | AH82: =$AC82*I$40 -> 903245.31 | AI82: =$AC82*J$40 -> 897771.1 | AJ82: =$AC82*K$40 -> 892296.88 | AK82: =$AC82*L$40 -> 886822.67 | ... AV82: =$AC82*W$40 -> 644132.51 | BA82: =-BC82 -> -19 | BB82: =(IF(BD82>0,BD82,0))/10^6 -> 0.64413251 | BC82: 19 | BD82: =AV82 -> 644132.51 | BE82: =BC82*BD82 -> 12238518 | BG82: =AV82-AU82 -> -32845.284 | BW82: .
B83: 2006 | AD83: =AD53 -> 2111433 | AE83: =$AD83*E$40 -> 2107210.1 | AF83: =$AD83*F$40 -> 2102987.3 | AG83: =$AD83*G$40 -> 2098764.4 | AH83: =$AD83*H$40 -> 2094541.5 | AI83: =$AD83*I$40 -> 2090318.7 | AJ83: =$AD83*J$40 -> 2077650.1 | AK83: =$AD83*K$40 -> 2064981.5 | AL83: =$AD83*L$40 -> 2052312.9 | ... AV83: =$AD83*V$40 -> 1566683.3 | BA83: =-BC83 -> -18 | BB83: =(IF(BD83>0,BD83,0))/10^6 -> 1.5666833 | BC83: 18 | BD83: =AV83 -> 1566683.3 | BE83: =BC83*BD83 -> 28200299 | BG83: =AV83-AU83 -> -76011.588 | BW83: .
B84: 2007 | AE84: =AE53 -> 1284810 | AF84: =$AE84*E$40 -> 1282240.4 | AG84: =$AE84*F$40 -> 1279670.8 | AH84: =$AE84*G$40 -> 1277101.1 | AI84: =$AE84*H$40 -> 1274531.5 | AJ84: =$AE84*I$40 -> 1271961.9 | AK84: =$AE84*J$40 -> 1264253 | AL84: =$AE84*K$40 -> 1256544.2 | AM84: =$AE84*L$40 -> 1248835.3 | ... AV84: =$AE84*U$40 -> 999582.18 | BA84: =-BC84 -> -17 | BB84: =(IF(BD84>0,BD84,0))/10^6 -> 0.99958218 | BC84: 17 | BD84: =AV84 -> 999582.18 | BE84: =BC84*BD84 -> 16992897 | BG84: =AV84-AU84 -> -46253.16 | BW84: .
B85: 2008 | AF85: =AF53 -> 1724319 | AG85: =$AF85*E$40 -> 1720870.4 | AH85: =$AF85*F$40 -> 1717421.7 | AI85: =$AF85*G$40 -> 1713973.1 | AJ85: =$AF85*H$40 -> 1710524.4 | AK85: =$AF85*I$40 -> 1707075.8 | AL85: =$AF85*J$40 -> 1696729.9 | AM85: =$AF85*K$40 -> 1686384 | AN85: =$AF85*L$40 -> 1676038.1 | ... AV85: =$AF85*T$40 -> 1403595.7 | BA85: =-BC85 -> -16 | BB85: =(IF(BD85>0,BD85,0))/10^6 -> 1.4035957 | BC85: 16 | BD85: =AV85 -> 1403595.7 | BE85: =BC85*BD85 -> 22457531 | BG85: =AV85-AU85 -> -62075.484 | BW85: .
B86: 2009 | AG86: =AG53 -> 1098282 | AH86: =$AG86*E$40 -> 1096085.4 | AI86: =$AG86*F$40 -> 1093888.9 | AJ86: =$AG86*G$40 -> 1091692.3 | AK86: =$AG86*H$40 -> 1089495.7 | AL86: =$AG86*I$40 -> 1087299.2 | AM86: =$AG86*J$40 -> 1080709.5 | AN86: =$AG86*K$40 -> 1074119.8 | AO86: =$AG86*L$40 -> 1067530.1 | ... AV86: =$AG86*S$40 -> 933539.7 | BA86: =-BC86 -> -15 | BB86: =(IF(BD86>0,BD86,0))/10^6 -> 0.9335397 | BC86: 15 | BD86: =AV86 -> 933539.7 | BE86: =BC86*BD86 -> 14003096 | BG86: =AV86-AU86 -> -24162.204 | BW86: .
B87: 2010 | AH87: =AH53 -> 633549 | AI87: =$AH87*E$40 -> 632281.9 | AJ87: =$AH87*F$40 -> 631014.8 | AK87: =$AH87*G$40 -> 629747.71 | AL87: =$AH87*H$40 -> 628480.61 | AM87: =$AH87*I$40 -> 627213.51 | AN87: =$AH87*J$40 -> 623412.22 | AO87: =$AH87*K$40 -> 619610.92 | AP87: =$AH87*L$40 -> 615809.63 | ... AV87: =$AH87*R$40 -> 552454.73 | BA87: =-BC87 -> -14 | BB87: =(IF(BD87>0,BD87,0))/10^6 -> 0.55245473 | BC87: 14 | BD87: =AV87 -> 552454.73 | BE87: =BC87*BD87 -> 7734366.2 | BG87: =AV87-AU87 -> -13938.078 | BW87: .
B88: 2011 | AI88: =AI53 -> 1221553 | AJ88: =$AI88*E$40 -> 1219109.9 | AK88: =$AI88*F$40 -> 1216666.8 | AL88: =$AI88*G$40 -> 1214223.7 | AM88: =$AI88*H$40 -> 1211780.6 | AN88: =$AI88*I$40 -> 1209337.5 | AO88: =$AI88*J$40 -> 1202008.2 | AP88: =$AI88*K$40 -> 1194678.8 | AQ88: =$AI88*L$40 -> 1187349.5 | ... AV88: =$AI88*Q$40 -> 1092068.4 | BA88: =-BC88 -> -13 | BB88: =(IF(BD88>0,BD88,0))/10^6 -> 1.0920684 | BC88: 13 | BD88: =AV88 -> 1092068.4 | BE88: =BC88*BD88 -> 14196889 | BG88: =AV88-AU88 -> -26874.166 | BW88: .
B89: 2012 | AJ89: =AJ53 -> 1195297 | AK89: =$AJ89*E$40 -> 1192906.4 | AL89: =$AJ89*F$40 -> 1190515.8 | AM89: =$AJ89*G$40 -> 1188125.2 | AN89: =$AJ89*H$40 -> 1185734.6 | AO89: =$AJ89*I$40 -> 1183344 | AP89: =$AJ89*J$40 -> 1176172.2 | AQ89: =$AJ89*K$40 -> 1169000.5 | AR89: =$AJ89*L$40 -> 1161828.7 | ... AV89: =$AJ89*P$40 -> 1094892.1 | BA89: =-BC89 -> -12 | BB89: =(IF(BD89>0,BD89,0))/10^6 -> 1.0948921 | BC89: 12 | BD89: =AV89 -> 1094892.1 | BE89: =BC89*BD89 -> 13138705 | BG89: =AV89-AU89 -> -26296.534 | BW89: .
B90: 2013 | AK90: =AK53 -> 1250299 | AL90: =$AK90*E$40 -> 1247798.4 | AM90: =$AK90*F$40 -> 1245297.8 | AN90: =$AK90*G$40 -> 1242797.2 | AO90: =$AK90*H$40 -> 1240296.6 | AP90: =$AK90*I$40 -> 1237796 | AQ90: =$AK90*J$40 -> 1230294.2 | AR90: =$AK90*K$40 -> 1222792.4 | AS90: =$AK90*L$40 -> 1215290.6 | ... AV90: =$AK90*O$40 -> 1172780.5 | BA90: =-BC90 -> -11 | BB90: =(IF(BD90>0,BD90,0))/10^6 -> 1.1727805 | BC90: 11 | BD90: =AV90 -> 1172780.5 | BE90: =BC90*BD90 -> 12900585 | BG90: =AV90-AU90 -> -27506.578 | BW90: .
B91: 2014 | AL91: =AL53 -> 723986 | AM91: =$AL91*E$40 -> 722538.03 | AN91: =$AL91*F$40 -> 721090.06 | AO91: =$AL91*G$40 -> 719642.08 | AP91: =$AL91*H$40 -> 718194.11 | AQ91: =$AL91*I$40 -> 716746.14 | AR91: =$AL91*J$40 -> 712402.22 | AS91: =$AL91*K$40 -> 708058.31 | AT91: =$AL91*L$40 -> 703714.39 | ... AV91: =$AL91*N$40 -> 695026.56 | BA91: =-BC91 -> -10 | BB91: =(IF(BD91>0,BD91,0))/10^6 -> 0.69502656 | BC91: 10 | BD91: =AV91 -> 695026.56 | BE91: =BC91*BD91 -> 6950265.6 | BG91: =AV91-AU91 -> -4343.916 | BW91: .
B92: 2015 | AM92: =AM53 -> 1364086 | AN92: =$AM92*E$40 -> 1361357.8 | AO92: =$AM92*F$40 -> 1358629.7 | AP92: =$AM92*G$40 -> 1355901.5 | AQ92: =$AM92*H$40 -> 1353173.3 | AR92: =$AM92*I$40 -> 1350445.1 | AS92: =$AM92*J$40 -> 1342260.6 | AT92: =$AM92*K$40 -> 1334076.1 | AU92: =$AM92*L$40 -> 1325891.6 | AV92: =$AM92*M$40 -> 1317707.1 | BA92: =-BC92 -> -9 | BB92: =(IF(BD92>0,BD92,0))/10^6 -> 1.3177071 | BC92: 9 | BD92: =AV92 -> 1317707.1 | BE92: =BC92*BD92 -> 11859364 | BG92: =AV92-AU92 -> -8184.516 | BW92: .
B93: 2016 | AN93: =AN53 -> 1756301 | AO93: =$AN93*E$40 -> 1752788.4 | AP93: =$AN93*F$40 -> 1749275.8 | AQ93: =$AN93*G$40 -> 1745763.2 | AR93: =$AN93*H$40 -> 1742250.6 | AS93: =$AN93*I$40 -> 1738738 | AT93: =$AN93*J$40 -> 1728200.2 | AU93: =$AN93*K$40 -> 1717662.4 | AV93: =$AN93*L$40 -> 1707124.6 | BA93: =-BC93 -> -8 | BB93: =(IF(BD93>0,BD93,0))/10^6 -> 1.7071246 | BC93: 8 | BD93: =AV93 -> 1707124.6 | BE93: =BC93*BD93 -> 13656997 | BG93: =AV93-AU93 -> -10537.806 | BW93: .
B94: 2017 | AO94: =AO53 -> 2032247 | AP94: =$AO94*E$40 -> 2028182.5 | AQ94: =$AO94*F$40 -> 2024118 | AR94: =$AO94*G$40 -> 2020053.5 | AS94: =$AO94*H$40 -> 2015989 | AT94: =$AO94*I$40 -> 2011924.5 | AU94: =$AO94*J$40 -> 1999731 | AV94: =$AO94*K$40 -> 1987537.6 | BA94: =-BC94 -> -7 | BB94: =(IF(BD94>0,BD94,0))/10^6 -> 1.9875376 | BC94: 7 | BD94: =AV94 -> 1987537.6 | BE94: =BC94*BD94 -> 13912763 | BG94: =AV94-AU94 -> -12193.482 | BW94: .
B95: 2018 | AP95: =AP53 -> 855809 | AQ95: =$AP95*E$40 -> 854097.38 | AR95: =$AP95*F$40 -> 852385.76 | AS95: =$AP95*G$40 -> 850674.15 | AT95: =$AP95*H$40 -> 848962.53 | AU95: =$AP95*I$40 -> 847250.91 | AV95: =$AP95*J$40 -> 842116.06 | BA95: =-BC95 -> -6 | BB95: =(IF(BD95>0,BD95,0))/10^6 -> 0.84211606 | BC95: 6 | BD95: =AV95 -> 842116.06 | BE95: =BC95*BD95 -> 5052696.3 | BG95: =AV95-AU95 -> -5134.854 | BW95: .
B96: 2019 | AQ96: =AQ$53 -> 763793 | AR96: =AQ96*E$40 -> 762265.41 | AS96: =AR96*F$40 -> 759216.35 | AT96: =AS96*G$40 -> 754661.05 | AU96: =AT96*H$40 -> 748623.77 | AV96: =AU96*I$40 -> 741137.53 | BA96: =-BC96 -> -5 | BB96: =(IF(BD96>0,BD96,0))/10^6 -> 0.74113753 | BC96: 5 | BD96: =AV96 -> 741137.53 | BE96: =BC96*BD96 -> 3705687.6 | BG96: =AV96-AU96 -> -7486.2377 | BW96: .
B97: 2020 | AR97: =AR$53 -> 532433 | AS97: =$AR97*E$40 -> 531368.13 | AT97: =$AR97*F$40 -> 530303.27 | AU97: =$AR97*G$40 -> 529238.4 | AV97: =$AR97*H$40 -> 528173.54 | BA97: =-BC97 -> -4 | BB97: =(IF(BD97>0,BD97,0))/10^6 -> 0.52817354 | BC97: 4 | BD97: =AV97 -> 528173.54 | BE97: =BC97*BD97 -> 2112694.1 | BG97: =AV97-AU97 -> -1064.866 | BW97: .
B98: 2021 | AS98: =AS$53 -> 520112 | AT98: =$AS98*E$40 -> 519071.78 | AU98: =$AS98*F$40 -> 518031.55 | AV98: =$AS98*G$40 -> 516991.33 | BA98: =-BC98 -> -3 | BB98: =(IF(BD98>0,BD98,0))/10^6 -> 0.51699133 | BC98: 3 | BD98: =AV98 -> 516991.33 | BE98: =BC98*BD98 -> 1550974 | BG98: =AV98-AU98 -> -1040.224 | BW98: .
B99: 2022 | AT99: =AT$53 -> 486962 | AU99: =$AT99*E$40 -> 485988.08 | AV99: =$AT99*F$40 -> 485014.15 | BA99: =-BC99 -> -2 | BB99: =(IF(BD99>0,BD99,0))/10^6 -> 0.48501415 | BC99: 2 | BD99: =AV99 -> 485014.15 | BE99: =BC99*BD99 -> 970028.3 | BG99: =AV99-AU99 -> -973.924 | BW99: .
B100: 2023 | AU100: =AU$53 -> 598215 | AV100: =$AU100*E$40 -> 597018.57 | BA100: =-BC100 -> -1 | BB100: =(IF(BD100>0,BD100,0))/10^6 -> 0.59701857 | BC100: 1 | BD100: =AV100 -> 597018.57 | BE100: =BC100*BD100 -> 597018.57 | BG100: =AV100-AU100 -> -1196.43 | BW100: .
B101: 2024 | AV101: =AV$53 -> 636489 | BA101: =-BC101 -> 0 | BB101: =(IF(BD101>0,BD101,0))/10^6 -> 0.636489 | BC101: 0 | BD101: =AV101 -> 636489 | BE101: =BC101*BD101 -> 0 | BG101: =AV101-AU101 -> 636489 | BW101: .
BW102: .
B103: Future motorcycle fleet | D103: 2010 | E103: 2020 | F103: 2030 | G103: 2040 | H103: 2050 | BW103: .
B104: Motorcycles | C104: Million vehicles | D104: =AH112/10^6 -> 0.91170878 | E104: =AR112/10^6 -> 4.8025736 | F104: =BB112/10^6 -> 9.6137636 | G104: =BL112/10^6 -> 13.256798 | H104: =BV112/10^6 -> 16.954392 | BW104: .
...

Sheet Mexico AirFleet
B26: Age of air fleet in 2022
B27: 7.7
B29: Lifetime estimated at twice the average age
B30: =B27*2 -> 15.4

Sheet Table_38._Light-Duty_Vehicle_Sa
A1: Table 38. Light-Duty Vehicle Sales by Technology Type
A2: https://www.eia.gov/outlooks/aeo/data/browser/#/?id=48-AEO2022&cases=lowmacro&sourcekey=0
A3: Fri Dec 09 2022 10:03:54 GMT-0500 (Eastern Standard Time)
A4: Source: U.S. Energy Information Administration
B5: full name | C5: api key | D5: units | E5: 2020 | F5: 2021 | G5: 2022 | H5: 2023 | I5: 2024 | J5: 2025 | K5: 2026 | L5: 2027 | M5: 2028 | N5: 2029 | O5: 2030 | P5: 2031 | Q5: 2032 | R5: 2033 | S5: 2034 | T5: 2035 | U5: 2036 | V5: 2037 | W5: 2038 | X5: 2039 | Y5: 2040 | Z5: 2041 | AA5: 2042 | AB5: 2043 | AC5: 2044 | AD5: 2045 | AE5: 2046 | AF5: 2047 | AG5: 2048 | AH5: 2049 | AI5: 2050 | AJ5: Growth (2021-2050)
A6: New Car Sales
A7: Conventional Cars
A8: Gasoline ICE Vehicles | B8: Light-Duty Vehicle Sales: Conventional Cars: Gasoline: Low economic growth | C8: AEO.2022.LOWMACRO.ECI_SAL_TRN_CAR_GSL_NA_NA_TH.A | D8: thousands | F8: 4708.5171 | G8: 4027.0447 | H8: 3831.8833 | I8: 3672.634 | J8: 3461.1855 | K8: 3333.5042 | L8: 3228.2043 | M8: 3174.7429 | N8: 3117.6521 | O8: 3060.6807 | P8: 2996.7515 | Q8: 3020.3459 | R8: 3005.4482 | S8: 2916.3523 | T8: 2828.9541 | U8: 2771.4673 | V8: 2742.8406 | W8: 2741.3857 | X8: 2738.3291 | Y8: 2743.7698 | Z8: 2718.2727 | AA8: 2685.4128 | AB8: 2655.9783 | AC8: 2617.8574 | AD8: 2571.8245 | AE8: 2557.7061 | AF8: 2528.2446 | AG8: 2487.0168 | AH8: 2470.873 | AI8: 2424.7546 | AJ8: -0.023
A9: TDI Diesel ICE | B9: Light-Duty Vehicle Sales: Conventional Cars: TDI Diesel: Low economic growth | C9: AEO.2022.LOWMACRO.ECI_SAL_TRN_CAR_TDS_NA_NA_TH.A | D9: thousands | F9: 0.055604 | G9: 0.052588 | H9: 0.052776 | I9: 0.047209 | J9: 0.043953 | K9: 0.043103 | L9: 0.042453 | M9: 0.042038 | N9: 0.041436 | O9: 0.04163 | P9: 0.040842 | Q9: 0.04214 | R9: 0.042788 | S9: 0.042154 | T9: 0.041222 | U9: 0.040598 | V9: 0.04015 | W9: 0.040506 | X9: 0.040439 | Y9: 0.040958 | Z9: 0.040855 | AA9: 0.040838 | AB9: 0.040575 | AC9: 0.039879 | AD9: 0.039518 | AE9: 0.039347 | AF9: 0.039286 | AG9: 0.039098 | AH9: 0.038984 | AI9: 0.038242 | AJ9: -0.013
A10: Total Conventional Cars | B10: Light-Duty Vehicle Sales: Conventional Cars: Total: Low economic growth | C10: AEO.2022.LOWMACRO.ECI_SAL_TRN_CAR_CNV_NA_NA_TH.A | D10: thousands | F10: 4708.5728 | G10: 4027.0972 | H10: 3831.936 | I10: 3672.6812 | J10: 3461.2295 | K10: 3333.5474 | L10: 3228.2468 | M10: 3174.7849 | N10: 3117.6936 | O10: 3060.7224 | P10: 2996.7922 | Q10: 3020.3882 | R10: 3005.491 | S10: 2916.3945 | T10: 2828.9954 | U10: 2771.5078 | V10: 2742.8806 | W10: 2741.4263 | X10: 2738.3696 | Y10: 2743.8108 | Z10: 2718.3135 | AA10: 2685.4536 | AB10: 2656.0188 | AC10: 2617.8972 | AD10: 2571.864 | AE10: 2557.7454 | AF10: 2528.2839 | AG10: 2487.0559 | AH10: 2470.9121 | AI10: 2424.793 | AJ10: -0.023
A11: Alternative-Fuel Cars
A12: Ethanol-Flex Fuel ICE | B12: Light-Duty Vehicle Sales: Alternative-Fuel Cars: Ethanol-Flex Fuel ICE: Low economic growth | C12: AEO.2022.LOWMACRO.ECI_SAL_TRN_CAR_EFFI_NA_NA_TH.A | D12: thousands | F12: 70.343307 | G12: 60.549362 | H12: 58.041054 | I12: 55.635876 | J12: 52.402313 | K12: 50.446724 | L12: 48.850254 | M12: 48.098244 | N12: 47.30896 | O12: 46.54229 | P12: 45.684765 | Q12: 46.060051 | R12: 46.024467 | S12: 44.769226 | T12: 43.527195 | U12: 42.754539 | V12: 42.415855 | W12: 42.501331 | X12: 42.568268 | Y12: 42.744873 | Z12: 42.494694 | AA12: 42.101707 | AB12: 41.76836 | AC12: 41.300838 | AD12: 40.689476 | AE12: 40.579243 | AF12: 40.234856 | AG12: 39.691223 | AH12: 39.541573 | AI12: 38.713806 | AJ12: -0.02
A13: 100 Mile Electric Vehicle | B13: Light-Duty Vehicle Sales: Alternative-Fuel Cars: 100 Mile Electric Vehicle: Low economic growth | C13: AEO.2022.LOWMACRO.ECI_SAL_TRN_CAR_100EV_NA_NA_TH.A | D13: thousands | F13: 1.889388 | G13: 1.853578 | H13: 2.010953 | I13: 2.130904 | J13: 2.194248 | K13: 2.286907 | L13: 2.380218 | M13: 2.512388 | N13: 2.639935 | O13: 2.764761 | P13: 2.882028 | Q13: 3.07301 | R13: 3.249978 | S13: 3.330011 | T13: 3.404459 | U13: 3.509104 | V13: 3.645464 | W13: 3.819031 | X13: 3.995179 | Y13: 4.179914 | Z13: 4.331512 | AA13: 4.463648 | AB13: 4.601828 | AC13: 4.724389 | AD13: 4.825278 | AE13: 4.984514 | AF13: 5.115482 | AG13: 5.218546 | AH13: 5.371593 | AI13: 5.454651 | AJ13: 0.037
A14: 200 Mile Electric Vehicle | B14: Light-Duty Vehicle Sales: Alternative-Fuel Cars: 200 Mile Electric Vehicle: Low economic growth | C14: AEO.2022.LOWMACRO.ECI_SAL_TRN_CAR_200EV_NA_NA_TH.A | D14: thousands | F14: 23.375469 | G14: 25.162935 | H14: 26.887745 | I14: 28.182169 | J14: 27.906448 | K14: 28.487347 | L14: 29.056843 | M14: 30.245136 | N14: 31.850908 | O14: 33.557735 | P14: 35.134197 | Q14: 38.987633 | R14: 41.828842 | S14: 43.608128 | T14: 45.457848 | U14: 47.45253 | V14: 49.824116 | W14: 52.774906 | X14: 55.452347 | Y14: 58.692047 | Z14: 61.099415 | AA14: 63.306271 | AB14: 65.701378 | AC14: 67.526718 | AD14: 68.845268 | AE14: 71.151718 | AF14: 72.830406 | AG14: 74.05481 | AH14: 76.02253 | AI14: 76.51194 | AJ14: 0.042
A15: 300 Mile Electric Vehicle | B15: Light-Duty Vehicle Sales: Alternative-Fuel Cars: 300 Mile Electric Vehicle: Low economic growth | C15: AEO.2022.LOWMACRO.ECI_SAL_TRN_CAR_300EV_NA_NA_TH.A | D15: thousands | F15: 147.40178 | G15: 155.99675 | H15: 171.69786 | I15: 181.12497 | J15: 175.2215 | K15: 171.76187 | L15: 168.80046 | M15: 169.34013 | N15: 172.23846 | O15: 179.98 | P15: 184.51266 | Q15: 199.95792 | R15: 212.35974 | S15: 218.05942 | T15: 224.15056 | U15: 230.9104 | V15: 239.59773 | W15: 251.35535 | X15: 262.51718 | Y15: 275.64163 | Z15: 286.47797 | AA15: 296.27103 | AB15: 307.46561 | AC15: 316.62567 | AD15: 323.55627 | AE15: 335.51575 | AF15: 345.19446 | AG15: 353.00534 | AH15: 364.80512 | AI15: 370.38699 | AJ15: 0.032
A16: Plug-in 20 Gasoline Hybrid | B16: Light-Duty Vehicle Sales: Alternative-Fuel Cars: Plug-in 20 Gasoline Hybrid: Low economic growth | C16: AEO.2022.LOWMACRO.#N/A.A | D16: thousands | F16: 46.07452 | G16: 41.307823 | H16: 35.311195 | I16: 33.157207 | J16: 32.668339 | K16: 31.887579 | L16: 31.637594 | M16: 31.960209 | N16: 32.534397 | O16: 33.628281 | P16: 34.726852 | Q16: 38.217216 | R16: 40.075108 | S16: 40.901299 | T16: 41.703312 | U16: 42.683685 | V16: 44.039829 | W16: 45.875614 | X16: 47.390827 | Y16: 49.550098 | Z16: 50.653801 | AA16: 51.584179 | AB16: 52.619587 | AC16: 53.227955 | AD16: 53.513435 | AE16: 54.554977 | AF16: 55.090519 | AG16: 55.30695 | AH16: 56.10244 | AI16: 55.769161 | AJ16: 0.007
A17: Plug-in 50 Gasoline Hybrid | B17: Light-Duty Vehicle Sales: Alternative-Fuel Cars: Plug-in 50 Gasoline Hybrid: Low economic growth | C17: AEO.2022.LOWMACRO.#N/A.A | D17: thousands | F17: 2.051092 | G17: 1.980519 | H17: 2.072338 | I17: 2.267704 | J17: 2.410676 | K17: 2.600569 | L17: 2.797372 | M17: 3.04156 | N17: 3.288033 | O17: 3.549641 | P17: 3.802512 | Q17: 4.214235 | R17: 4.552578 | S17: 4.759618 | T17: 4.9583 | U17: 5.187163 | V17: 5.460164 | W17: 5.792198 | X17: 6.113984 | Y17: 6.475055 | Z17: 6.761046 | AA17: 7.020243 | AB17: 7.293337 | AC17: 7.528407 | AD17: 7.722812 | AE17: 8.01825 | AF17: 8.25815 | AG17: 8.451497 | AH17: 8.728467 | AI17: 8.870539 | AJ17: 0.052
A18: Electric-Diesel Hybrid | B18: Light-Duty Vehicle Sales: Alternative-Fuel Cars: Electric-Diesel Hybrid: Low economic growth | C18: AEO.2022.LOWMACRO.ECI_SAL_TRN_CAR_EDH_NA_NA_TH.A | D18: thousands | F18: 0 | G18: 0 | H18: 0 | I18: 0 | J18: 0 | K18: 0 | L18: 0 | M18: 0 | N18: 0 | O18: 0 | P18: 0 | Q18: 0 | R18: 0 | S18: 0 | T18: 0 | U18: 0 | V18: 0 | W18: 0 | X18: 0 | Y18: 0 | Z18: 0 | AA18: 0 | AB18: 0 | AC18: 0 | AD18: 0 | AE18: 0 | AF18: 0 | AG18: 0 | AH18: 0 | AI18: 0 | AJ18: - -
A19: Electric-Gasoline Hybrid | B19: Light-Duty Vehicle Sales: Alternative-Fuel Cars: Electric-Gasoline Hybrid: Low economic growth | C19: AEO.2022.LOWMACRO.ECI_SAL_TRN_CAR_EGH_NA_NA_TH.A | D19: thousands | F19: 332.48666 | G19: 337.24652 | H19: 365.72226 | I19: 361.76471 | J19: 343.10757 | K19: 337.5228 | L19: 334.77814 | M19: 336.78854 | N19: 337.88992 | O19: 339.16202 | P19: 338.97922 | Q19: 350.40442 | R19: 355.52737 | S19: 350.95868 | T19: 346.27304 | U19: 344.43457 | V19: 346.00168 | W19: 351.18692 | X19: 355.50055 | Y19: 362.08258 | Z19: 366.14453 | AA19: 367.11215 | AB19: 368.55566 | AC19: 368.23932 | AD19: 366.31882 | AE19: 369.05972 | AF19: 369.16357 | AG19: 367.36792 | AH19: 369.24075 | AI19: 365.6044 | AJ19: 0.003
A20: Natural Gas ICE | B20: Light-Duty Vehicle Sales: Alternative-Fuel Cars: Natural Gas ICE: Low economic growth | C20: AEO.2022.LOWMACRO.ECI_SAL_TRN_CAR_NGI_NA_NA_TH.A | D20: thousands | F20: 0.125795 | G20: 0.137188 | H20: 0.16456 | I20: 0.178194 | J20: 0.178977 | K20: 0.17513 | L20: 0.169911 | M20: 0.166769 | N20: 0.16133 | O20: 0.157814 | P20: 0.155445 | Q20: 0.153072 | R20: 0.154532 | S20: 0.150304 | T20: 0.145904 | U20: 0.143305 | V20: 0.141849 | W20: 0.142148 | X20: 0.142495 | Y20: 0.142984 | Z20: 0.143385 | AA20: 0.143712 | AB20: 0.144666 | AC20: 0.144943 | AD20: 0.143982 | AE20: 0.144406 | AF20: 0.144026 | AG20: 0.142705 | AH20: 0.142891 | AI20: 0.141464 | AJ20: 0.004
A21: Natural Gas Bi-fuel | B21: Light-Duty Vehicle Sales: Alternative-Fuel Cars: Natural Gas Bi-fuel: Low economic growth | C21: AEO.2022.LOWMACRO.ECI_SAL_TRN_CAR_NBF_NA_NA_TH.A | D21: thousands | F21: 0.08721 | G21: 0.083797 | H21: 0.086701 | I21: 0.082955 | J21: 0.077557 | K21: 0.07438 | L21: 0.072463 | M21: 0.071962 | N21: 0.071043 | O21: 0.070278 | P21: 0.069926 | Q21: 0.068586 | R21: 0.070636 | S21: 0.069626 | T21: 0.068207 | U21: 0.067855 | V21: 0.067926 | W21: 0.068939 | X21: 0.069968 | Y21: 0.071117 | Z21: 0.072263 | AA21: 0.073052 | AB21: 0.074277 | AC21: 0.075227 | AD21: 0.075636 | AE21: 0.076905 | AF21: 0.077803 | AG21: 0.078107 | AH21: 0.079107 | AI21: 0.079022 | AJ21: -0.003
A22: Propane ICE | B22: Light-Duty Vehicle Sales: Alternative-Fuel Cars: Propane: Low economic growth | C22: AEO.2022.LOWMACRO.ECI_SAL_TRN_CAR_PROP_NA_NA_TH.A | D22: thousands | F22: 0.05824 | G22: 0.083935 | H22: 0.102234 | I22: 0.100122 | J22: 0.094563 | K22: 0.091009 | L22: 0.088827 | M22: 0.088865 | N22: 0.088482 | O22: 0.08789 | P22: 0.088635 | Q22: 0.089944 | R22: 0.095838 | S22: 0.095839 | T22: 0.095929 | U22: 0.097352 | V22: 0.098851 | W22: 0.10141 | X22: 0.105067 | Y22: 0.106972 | Z22: 0.110404 | AA22: 0.112637 | AB22: 0.114746 | AC22: 0.11737 | AD22: 0.119959 | AE22: 0.124351 | AF22: 0.128778 | AG22: 0.132005 | AH22: 0.136136 | AI22: 0.139824 | AJ22: 0.031
A23: Propane Bi-fuel | B23: Light-Duty Vehicle Sales: Alternative-Fuel Cars: Propane: Low economic growth | C23: AEO.2022.LOWMACRO.ECI_SAL_TRN_CAR_PBF_NA_NA_TH.A | D23: thousands | F23: 0.034324 | G23: 0.03163 | H23: 0.032664 | I23: 0.031067 | J23: 0.028989 | K23: 0.027804 | L23: 0.026821 | M23: 0.026294 | N23: 0.025703 | O23: 0.025183 | P23: 0.024775 | Q23: 0.025119 | R23: 0.025592 | S23: 0.025025 | T23: 0.024549 | U23: 0.024303 | V23: 0.024152 | W23: 0.024312 | X23: 0.024516 | Y23: 0.024692 | Z23: 0.024848 | AA23: 0.02486 | AB23: 0.024879 | AC23: 0.024869 | AD23: 0.024892 | AE23: 0.025346 | AF23: 0.025631 | AG23: 0.025672 | AH23: 0.025926 | AI23: 0.025838 | AJ23: -0.01
A24: Fuel Cell Methanol | B24: Light-Duty Vehicle Sales: Alternative-Fuel Cars: Fuel Cell Methanol: Low economic growth | C24: AEO.2022.LOWMACRO.ECI_SAL_TRN_CAR_FCLMTH_NA_NA_TH.A | D24: thousands | F24: 0 | G24: 0 | H24: 0 | I24: 0 | J24: 0 | K24: 0 | L24: 0 | M24: 0 | N24: 0 | O24: 0 | P24: 0 | Q24: 0 | R24: 0 | S24: 0 | T24: 0 | U24: 0 | V24: 0 | W24: 0 | X24: 0 | Y24: 0 | Z24: 0 | AA24: 0 | AB24: 0 | AC24: 0 | AD24: 0 | AE24: 0 | AF24: 0 | AG24: 0 | AH24: 0 | AI24: 0 | AJ24: - -
A25: Fuel Cell Hydrogen | B25: Light-Duty Vehicle Sales: Alternative-Fuel cars: Fuel Cell Hydrogen: Low economic growth | C25: AEO.2022.LOWMACRO.ECI_SAL_TRN_CAR_FCH_NA_NA_TH.A | D25: thousands | F25: 2.810565 | G25: 2.579295 | H25: 2.900511 | I25: 3.099156 | J25: 3.365274 | K25: 3.752151 | L25: 4.085079 | M25: 4.495492 | N25: 4.871282 | O25: 5.194482 | P25: 5.450906 | Q25: 5.798769 | R25: 6.174509 | S25: 6.189462 | T25: 6.141377 | U25: 6.097211 | V25: 6.046902 | W25: 6.255177 | X25: 6.485738 | Y25: 6.689171 | Z25: 6.886049 | AA25: 7.010755 | AB25: 7.137501 | AC25: 7.23891 | AD25: 7.278145 | AE25: 7.388267 | AF25: 7.455015 | AG25: 7.461854 | AH25: 7.526855 | AI25: 7.509429 | AJ25: 0.034
A26: Total Alternative Cars | B26: Light-Duty Vehicle Sales: Alternative-Fuel Cars: Total: Low economic growth | C26: AEO.2022.LOWMACRO.ECI_SAL_TRN_CAR_ALT_NA_NA_TH.A | D26: thousands | F26: 626.73834 | G26: 627.01331 | H26: 665.03003 | I26: 667.75507 | J26: 639.65643 | K26: 629.11426 | L26: 622.74402 | M26: 626.83557 | N26: 632.96844 | O26: 644.72034 | P26: 651.51196 | Q26: 687.04999 | R26: 710.13922 | S26: 712.91663 | T26: 715.95062 | U26: 723.362 | V26: 737.36444 | W26: 759.8974 | X26: 780.36609 | Y26: 806.40118 | Z26: 825.19989 | AA26: 839.22424 | AB26: 855.50189 | AC26: 866.7746 | AD26: 873.11395 | AE26: 891.62335 | AF26: 903.71875 | AG26: 910.93671 | AH26: 927.72333 | AI26: 929.20703 | AJ26: 0.014
A27: Percent Alternative Car Sales | B27: Light-Duty Vehicle Sales: Percent Alternative Car: Low economic growth | C27: AEO.2022.LOWMACRO.ECI_SAL_TRN_CAR_ALT_NA_NA_PCT.A | D27: percent | F27: 11.746987 | G27: 13.472249 | H27: 14.788416 | I27: 15.384516 | J27: 15.598006 | K27: 15.876053 | L27: 16.171009 | M27: 16.488642 | N27: 16.876179 | O27: 17.399279 | P27: 17.857939 | Q27: 18.531664 | R27: 19.112215 | S27: 19.643305 | T27: 20.196375 | U27: 20.697823 | V27: 21.187141 | W27: 21.703146 | X27: 22.177456 | Y27: 22.71417 | Z27: 23.287619 | AA27: 23.809956 | AB27: 24.362717 | AC27: 24.873922 | AD27: 25.344545 | AE27: 25.848886 | AF27: 26.332109 | AG27: 26.808083 | AH27: 27.296936 | AI27: 27.704445 | AJ27: 0.03
A28: Total New Car Sales | B28: Light-Duty Vehicle Sales: Total New Car: Low economic growth | C28: AEO.2022.LOWMACRO.ECI_SAL_TRN_CAR_TOT_NA_NA_TH.A | D28: thousands | F28: 5335.311 | G28: 4654.1104 | H28: 4496.9658 | I28: 4340.436 | J28: 4100.8857 | K28: 3962.6616 | L28: 3850.9907 | M28: 3801.6206 | N28: 3750.6621 | O28: 3705.4429 | P28: 3648.3042 | Q28: 3707.4382 | R28: 3715.6301 | S28: 3629.311 | T28: 3544.946 | U28: 3494.8699 | V28: 3480.2451 | W28: 3501.3237 | X28: 3518.7358 | Y28: 3550.2119 | Z28: 3543.5134 | AA28: 3524.6777 | AB28: 3511.5208 | AC28: 3484.6719 | AD28: 3444.978 | AE28: 3449.3687 | AF28: 3432.0027 | AG28: 3397.9927 | AH28: 3398.6355 | AI28: 3354 | AJ28: -0.016
A29: New Light Truck Sales
A30: Conventional Light Trucks
A31: Gasoline ICE Vehicles | B31: Light-Duty Vehicle Sales: Conventional Light Trucks: Gasoline: Low economic growth | C31: AEO.2022.LOWMACRO.ECI_SAL_TRN_LTK_GSL_NA_NA_TH.A | D31: thousands | F31: 8724.5283 | G31: 7939.5649 | H31: 8116.8813 | I31: 8314.5391 | J31: 8323.5039 | K31: 8322.1758 | L31: 8213.2363 | M31: 8182.4932 | N31: 8148.5396 | O31: 8039.1226 | P31: 7956.1636 | Q31: 7892.4268 | R31: 7877.8208 | S31: 7680.5063 | T31: 7491.6279 | U31: 7401.8281 | V31: 7379.4507 | W31: 7421.5366 | X31: 7516.1909 | Y31: 7545.4082 | Z31: 7531.5078 | AA31: 7480.3242 | AB31: 7421.3354 | AC31: 7365.7759 | AD31: 7297.77 | AE31: 7308.1538 | AF31: 7296.1382 | AG31: 7261.7114 | AH31: 7295.6362 | AI31: 7308.436 | AJ31: -0.006
A32: TDI Diesel ICE | B32: Light-Duty Vehicle Sales: Conventional Light Trucks: TDI Diesel: Low economic growth | C32: AEO.2022.LOWMACRO.ECI_SAL_TRN_LTK_DSL_NA_NA_TH.A | D32: thousands | F32: 46.41877 | G32: 51.253639 | H32: 54.700764 | I32: 52.197567 | J32: 51.239521 | K32: 51.580734 | L32: 51.742249 | M32: 52.058838 | N32: 51.945 | O32: 52.957184 | P32: 52.219421 | Q32: 53.612389 | R32: 54.034382 | S32: 53.363277 | T32: 52.099304 | U32: 51.40202 | V32: 50.977821 | W32: 51.689278 | X32: 51.969776 | Y32: 53.049381 | Z32: 53.070942 | AA32: 53.386406 | AB32: 53.157028 | AC32: 52.364655 | AD32: 52.270599 | AE32: 52.341469 | AF32: 52.742237 | AG32: 53.071175 | AH32: 53.468132 | AI32: 53.209236 | AJ32: 0.005
A33: Total Conventional Light Trucks | B33: Light-Duty Vehicle Sales: Conventional Light Trucks: Total: Low economic growth | C33: AEO.2022.LOWMACRO.ECI_SAL_TRN_LTK_CNV_NA_NA_TH.A | D33: thousands | F33: 8770.9473 | G33: 7990.8184 | H33: 8171.582 | I33: 8366.7363 | J33: 8374.7432 | K33: 8373.7568 | L33: 8264.9785 | M33: 8234.5518 | N33: 8200.4844 | O33: 8092.0796 | P33: 8008.3828 | Q33: 7946.0391 | R33: 7931.855 | S33: 7733.8696 | T33: 7543.7271 | U33: 7453.23 | V33: 7430.4287 | W33: 7473.2261 | X33: 7568.1606 | Y33: 7598.4575 | Z33: 7584.5786 | AA33: 7533.7104 | AB33: 7474.4927 | AC33: 7418.1406 | AD33: 7350.0405 | AE33: 7360.4951 | AF33: 7348.8804 | AG33: 7314.7827 | AH33: 7349.1045 | AI33: 7361.6455 | AJ33: -0.006
A34: Alternative-Fuel Light Trucks
A35: Ethanol-Flex Fuel ICE | B35: Light-Duty Vehicle Sales: Alternative-Fuel Light Trucks: Ethanol-Flex Fuel ICE: Low economic growth | C35: AEO.2022.LOWMACRO.ECI_SAL_TRN_LTK_EFFI_NA_NA_TH.A | D35: thousands | F35: 596.271 | G35: 546.36578 | H35: 560.06812 | I35: 574.92841 | J35: 576.18988 | K35: 576.79669 | L35: 569.94995 | M35: 568.57684 | N35: 566.88086 | O35: 560.06952 | P35: 554.92859 | Q35: 552.00311 | R35: 551.68054 | S35: 538.38373 | T35: 525.73877 | U35: 519.98261 | V35: 519.21204 | W35: 522.88904 | X35: 529.97516 | Y35: 532.82471 | Z35: 532.42767 | AA35: 529.45483 | AB35: 525.90851 | AC35: 522.56659 | AD35: 518.38086 | AE35: 519.85077 | AF35: 519.60535 | AG35: 517.68317 | AH35: 520.55609 | AI35: 521.65747 | AJ35: -0.005
A36: 100 Mile Electric Vehicle | B36: Light-Duty Vehicle Sales: Alternative-Fuel Light Trucks: 100 Mile Electric Vehicle: Low economic growth | C36: AEO.2022.LOWMACRO.ECI_SAL_TRN_LTK_100EV_NA_NA_TH.A | D36: thousands | F36: 0.093778 | G36: 0.084562 | H36: 0.083867 | I36: 0.082934 | J36: 0.079843 | K36: 0.076699 | L36: 0.072665 | M36: 0.069366 | N36: 0.066088 | O36: 0.062316 | P36: 0.05875 | Q36: 0.05555 | R36: 0.052556 | S36: 0.048386 | T36: 0.044404 | U36: 0.041074 | V36: 0.038148 | W36: 0.035541 | X36: 0.033077 | Y36: 0.030316 | Z36: 0.027324 | AA36: 0.024208 | AB36: 0.021095 | AC36: 0.018 | AD36: 0.014901 | AE36: 0.011975 | AF36: 0.008991 | AG36: 0.005981 | AH36: 0.003012 | AI36: 0 | AJ36: - -
A37: 200 Mile Electric Vehicle | B37: Light-Duty Vehicle Sales: Alternative-Fuel Light Trucks: 200 Mile Electric Vehicle: Low economic growth | C37: AEO.2022.LOWMACRO.ECI_SAL_TRN_LTK_200EV_NA_NA_TH.A | D37: thousands | F37: 28.579189 | G37: 37.799797 | H37: 46.339046 | I37: 54.261101 | J37: 58.176041 | K37: 61.65593 | L37: 64.917702 | M37: 68.914391 | N37: 73.443619 | O37: 78.091064 | P37: 80.645233 | Q37: 85.000328 | R37: 88.585281 | S37: 89.981232 | T37: 91.31456 | U37: 93.395668 | V37: 96.163765 | W37: 99.826248 | X37: 103.86043 | Y37: 107.46287 | Z37: 110.17909 | AA37: 112.39967 | AB37: 114.57875 | AC37: 116.57037 | AD37: 118.28721 | AE37: 121.47288 | AF37: 124.27996 | AG37: 126.7664 | AH37: 130.59279 | AI37: 133.89475 | AJ37: 0.055
A38: 300 Mile Electric Vehicle | B38: Light-Duty Vehicle Sales: Alternative-Fuel Light Trucks: 300 Mile Electric Vehicle: Low economic growth | C38: AEO.2022.LOWMACRO.ECI_SAL_TRN_LTK_300EV_NA_NA_TH.A | D38: thousands | F38: 116.33713 | G38: 128.26813 | H38: 155.00763 | I38: 182.8981 | J38: 195.78984 | K38: 205.34196 | L38: 213.27428 | M38: 223.44061 | N38: 236.34247 | O38: 247.95653 | P38: 258.8595 | Q38: 282.15915 | R38: 301.43454 | S38: 312.80041 | T38: 324.20505 | U38: 337.03262 | V38: 352.85297 | W38: 373.2952 | X38: 393.44055 | Y38: 416.24756 | Z38: 434.52277 | AA38: 451.46811 | AB38: 469.5571 | AC38: 484.46344 | AD38: 496.07871 | AE38: 515.07562 | AF38: 530.70703 | AG38: 543.75415 | AH38: 562.82434 | AI38: 573.33344 | AJ38: 0.057
A39: Plug-in 20 Gasoline Hybrid | B39: Light-Duty Vehicle Sales: Alternative-Fuel Light Trucks: Plug-in 20 Gasoline Hybrid: Low economic growth | C39: AEO.2022.LOWMACRO.#N/A.A | D39: thousands | F39: 55.057671 | G39: 53.127327 | H39: 53.622997 | I39: 53.152264 | J39: 51.774372 | K39: 51.00499 | L39: 50.355652 | M39: 50.621254 | N39: 51.208557 | O39: 52.072277 | P39: 53.217651 | Q39: 55.713207 | R39: 57.525776 | S39: 58.145058 | T39: 58.647335 | U39: 59.694374 | V39: 61.187141 | W39: 63.272671 | X39: 65.54245 | Y39: 67.744652 | Z39: 69.149834 | AA39: 70.186066 | AB39: 71.208481 | AC39: 71.972328 | AD39: 72.425598 | AE39: 73.737701 | AF39: 74.667358 | AG39: 75.298149 | AH39: 76.662216 | AI39: 77.354256 | AJ39: 0.012
A40: Plug-in 50 Gasoline Hybrid | B40: Light-Duty Vehicle Sales: Alternative-Fuel Light Trucks: Plug-in 50 Gasoline Hybrid: Low economic growth | C40: AEO.2022.LOWMACRO.#N/A.A | D40: thousands | F40: 36.218811 | G40: 154.58676 | H40: 190.44367 | I40: 194.14935 | J40: 189.67104 | K40: 186.11908 | L40: 182.59335 | M40: 182.38986 | N40: 183.34767 | O40: 185.21614 | P40: 188.22492 | Q40: 195.50043 | R40: 201.6022 | S40: 202.48445 | T40: 203.07191 | U40: 205.48602 | V40: 209.44359 | W40: 215.51012 | X40: 222.27899 | Y40: 228.56625 | Z40: 232.79988 | AA40: 235.78497 | AB40: 238.74777 | AC40: 241.03796 | AD40: 242.18599 | AE40: 246.25104 | AF40: 249.1515 | AG40: 250.96053 | AH40: 255.1868 | AI40: 257.30136 | AJ40: 0.07
A41: Electric-Diesel Hybrid | B41: Light-Duty Vehicle Sales: Alternative-Fuel Light Trucks: Electric-Diesel Hybrid: Low economic growth | C41: AEO.2022.LOWMACRO.ECI_SAL_TRN_LTK_EDH_NA_NA_TH.A | D41: thousands | F41: 0 | G41: 0 | H41: 0 | I41: 0 | J41: 0 | K41: 0 | L41: 0 | M41: 0 | N41: 0 | O41: 0 | P41: 0 | Q41: 0 | R41: 0 | S41: 0 | T41: 0 | U41: 0 | V41: 0 | W41: 0 | X41: 0 | Y41: 0 | Z41: 0 | AA41: 0 | AB41: 0 | AC41: 0 | AD41: 0 | AE41: 0 | AF41: 0 | AG41: 0 | AH41: 0 | AI41: 0 | AJ41: - -
A42: Electric-Gasoline Hybrid | B42: Light-Duty Vehicle Sales: Alternative-Fuel Light Trucks: Electric-Gasoline Hybrid: Low economic growth | C42: AEO.2022.LOWMACRO.ECI_SAL_TRN_LTK_EGH_NA_NA_TH.A | D42: thousands | F42: 458.01428 | G42: 501.93494 | H42: 547.27466 | I42: 565.82758 | J42: 565.51459 | K42: 565.17664 | L42: 560.31372 | M42: 561.88214 | N42: 563.1698 | O42: 562.63098 | P42: 562.89172 | Q42: 570.48767 | R42: 576.23822 | S42: 567.89606 | T42: 558.948 | U42: 556.03162 | V42: 558.46686 | W42: 566.62964 | X42: 576.86871 | Y42: 585.97894 | Z42: 589.79346 | AA42: 590.86481 | AB42: 591.52167 | AC42: 591.03229 | AD42: 588.61328 | AE42: 593.19031 | AF42: 595.05341 | AG42: 594.78009 | AH42: 600.26404 | AI42: 601.24219 | AJ42: 0.009
A43: Natural Gas ICE | B43: Light-Duty Vehicle Sales: Alternative-Fuel Light Trucks: Natural Gas ICE: Low economic growth | C43: AEO.2022.LOWMACRO.ECI_SAL_TRN_LTK_NGI_NA_NA_TH.A | D43: thousands | F43: 0.110323 | G43: 0.137763 | H43: 0.183253 | I43: 0.233282 | J43: 0.259284 | K43: 0.269482 | L43: 0.270297 | M43: 0.268545 | N43: 0.261866 | O43: 0.261643 | P43: 0.25868 | Q43: 0.262902 | R43: 0.262595 | S43: 0.258141 | T43: 0.253383 | U43: 0.250794 | V43: 0.251176 | W43: 0.254957 | X43: 0.258006 | Y43: 0.265225 | Z43: 0.266884 | AA43: 0.271629 | AB43: 0.277702 | AC43: 0.2806 | AD43: 0.281397 | AE43: 0.285592 | AF43: 0.287317 | AG43: 0.287753 | AH43: 0.291969 | AI43: 0.291154 | AJ43: 0.034
A44: Natural Gas Bi-fuel | B44: Light-Duty Vehicle Sales: Alternative-Fuel Light Trucks: Natural Gas Bi-fuel: Low economic growth | C44: AEO.2022.LOWMACRO.ECI_SAL_TRN_LTK_NBF_NA_NA_TH.A | D44: thousands | F44: 0.021523 | G44: 0.022523 | H44: 0.023245 | I44: 0.024621 | J44: 0.025133 | K44: 0.025956 | L44: 0.026794 | M44: 0.027444 | N44: 0.027904 | O44: 0.028843 | P44: 0.029156 | Q44: 0.030004 | R44: 0.030705 | S44: 0.030901 | T44: 0.031073 | U44: 0.031643 | V44: 0.032498 | W44: 0.033939 | X44: 0.034953 | Y44: 0.037253 | Z44: 0.038561 | AA44: 0.040196 | AB44: 0.042287 | AC44: 0.043835 | AD44: 0.045184 | AE44: 0.047343 | AF44: 0.049065 | AG44: 0.050527 | AH44: 0.052707 | AI44: 0.053216 | AJ44: 0.032
A45: Propane ICE | B45: Light-Duty Vehicle Sales: Alternative-Fuel Light Trucks: Propane ICE: Low economic growth | C45: AEO.2022.LOWMACRO.ECI_SAL_TRN_LTK_PROP_NA_NA_TH.A | D45: thousands | F45: 0.454287 | G45: 0.619532 | H45: 0.697917 | I45: 0.731946 | J45: 0.749887 | K45: 0.771736 | L45: 0.785443 | M45: 0.797604 | N45: 0.807218 | O45: 0.821994 | P45: 0.828952 | Q45: 0.862679 | R45: 0.882488 | S45: 0.889684 | T45: 0.899373 | U45: 0.917832 | V45: 0.944113 | W45: 0.984376 | X45: 1.026566 | Y45: 1.076635 | Z45: 1.114979 | AA45: 1.153714 | AB45: 1.190774 | AC45: 1.225661 | AD45: 1.271202 | AE45: 1.348631 | AF45: 1.423801 | AG45: 1.489571 | AH45: 1.572449 | AI45: 1.632918 | AJ45: 0.045
A46: Propane Bi-fuel | B46: Light-Duty Vehicle Sales: Alternative-Fuel Light Trucks: Propane Bi-fuel: Low economic growth | C46: AEO.2022.LOWMACRO.ECI_SAL_TRN_LTK_PBF_NA_NA_TH.A | D46: thousands | F46: 0.005835 | G46: 0.005803 | H46: 0.006486 | I46: 0.006671 | J46: 0.006728 | K46: 0.006819 | L46: 0.006837 | M46: 0.006778 | N46: 0.006707 | O46: 0.006742 | P46: 0.006667 | Q46: 0.007034 | R46: 0.007056 | S46: 0.007006 | T46: 0.007014 | U46: 0.007062 | V46: 0.007123 | W46: 0.007305 | X46: 0.00745 | Y46: 0.007735 | Z46: 0.007876 | AA46: 0.008041 | AB46: 0.008189 | AC46: 0.008291 | AD46: 0.008498 | AE46: 0.008951 | AF46: 0.009304 | AG46: 0.009556 | AH46: 0.00992 | AI46: 0.010041 | AJ46: 0.019
A47: Fuel Cell Methanol | B47: Light-Duty Vehicle Sales: Alternative-Fuel Light Trucks: Fuel Cell Methanol: Low economic growth | C47: AEO.2022.LOWMACRO.ECI_SAL_TRN_LTK_FCLMTH_NA_NA_TH.A | D47: thousands | F47: 0 | G47: 0 | H47: 0 | I47: 0 | J47: 0 | K47: 0 | L47: 0 | M47: 0 | N47: 0 | O47: 0 | P47: 0 | Q47: 0 | R47: 0 | S47: 0 | T47: 0 | U47: 0 | V47: 0 | W47: 0 | X47: 0 | Y47: 0 | Z47: 0 | AA47: 0 | AB47: 0 | AC47: 0 | AD47: 0 | AE47: 0 | AF47: 0 | AG47: 0 | AH47: 0 | AI47: 0 | AJ47: - -
A48: Fuel Cell Hydrogen | B48: Light-Duty Vehicle Sales: Alternative-Fuel Light Trucks: Fuel Cell Hydrogen: Low economic growth | C48: AEO.2022.LOWMACRO.ECI_SAL_TRN_LTK_FCH_NA_NA_TH.A | D48: thousands | F48: 0.000631 | G48: 0.003924 | H48: 0.007607 | I48: 0.011663 | J48: 0.016934 | K48: 0.02146 | L48: 0.025975 | M48: 0.031001 | N48: 0.036346 | O48: 0.041801 | P48: 0.047445 | Q48: 0.054152 | R48: 0.06115 | S48: 0.066989 | T48: 0.073029 | U48: 0.08017 | V48: 0.088482 | W48: 0.098235 | X48: 0.108999 | Y48: 0.120353 | Z48: 0.13121 | AA48: 0.142038 | AB48: 0.153393 | AC48: 0.164783 | AD48: 0.176149 | AE48: 0.190062 | AF48: 0.203503 | AG48: 0.216376 | AH48: 0.232098 | AI48: 0.245919 | AJ48: 0.228
A49: Total Alternative Light Trucks | B49: Light-Duty Vehicle Sales: Alternative-Fuel Light Trucks: Total: Low economic growth | C49: AEO.2022.LOWMACRO.ECI_SAL_TRN_LTK_ALT_NA_NA_TH.A | D49: thousands | F49: 1291.1644 | G49: 1422.957 | H49: 1553.7583 | I49: 1626.308 | J49: 1638.2535 | K49: 1647.2676 | L49: 1642.5927 | M49: 1657.0259 | N49: 1675.5991 | O49: 1687.2598 | P49: 1699.9974 | Q49: 1742.1364 | R49: 1778.3632 | S49: 1770.9921 | T49: 1763.234 | U49: 1772.9515 | V49: 1798.6879 | W49: 1842.8373 | X49: 1893.4354 | Y49: 1940.3625 | Z49: 1970.4596 | AA49: 1991.7983 | AB49: 2013.2158 | AC49: 2029.3843 | AD49: 2037.769 | AE49: 2071.4707 | AF49: 2095.4468 | AG49: 2111.3022 | AH49: 2148.2485 | AI49: 2167.0166 | AJ49: 0.018
A50: Percent Alternative Light Truck Sales | B50: Light-Duty Vehicle Sales: Percent Alternative Light Truck Sales: Low economic growth | C50: AEO.2022.LOWMACRO.ECI_SAL_TRN_LTK_ALT_NA_NA_PCT.A | D50: percent | F50: 12.831943 | G50: 15.115688 | H50: 15.97639 | I50: 16.274401 | J50: 16.361271 | K50: 16.438116 | L50: 16.579166 | M50: 16.751884 | N50: 16.96623 | O50: 17.253309 | P50: 17.51062 | Q50: 17.982088 | R50: 18.314348 | S50: 18.632486 | T50: 18.945324 | U50: 19.216526 | V50: 19.489275 | W50: 19.781286 | X50: 20.011797 | Y50: 20.341745 | Z50: 20.622206 | AA50: 20.910151 | AB50: 21.219198 | AC50: 21.480591 | AD50: 21.706543 | AE50: 21.962238 | AF50: 22.187359 | AG50: 22.398506 | AH50: 22.619444 | AI50: 22.742086 | AJ50: 0.02
A51: Total New Light Truck Sales | B51: Light-Duty Vehicle Sales: Total New Truck: Low economic growth | C51: AEO.2022.LOWMACRO.ECI_SAL_TRN_LTK_NA_NA_NA_TH.A | D51: thousands | F51: 10062.111 | G51: 9413.7754 | H51: 9725.3398 | I51: 9993.0439 | J51: 10012.997 | K51: 10021.024 | L51: 9907.5713 | M51: 9891.5781 | N51: 9876.084 | O51: 9779.3398 | P51: 9708.3799 | Q51: 9688.1758 | R51: 9710.2178 | S51: 9504.8613 | T51: 9306.9609 | U51: 9226.1816 | V51: 9229.1162 | W51: 9316.0635 | X51: 9461.5957 | Y51: 9538.8203 | Z51: 9555.0381 | AA51: 9525.5088 | AB51: 9487.709 | AC51: 9447.5254 | AD51: 9387.8096 | AE51: 9431.9658 | AF51: 9444.3271 | AG51: 9426.085 | AH51: 9497.3535 | AI51: 9528.6621 | AJ51: -0.002
A52: Percent Total Alternative Sales | B52: Light-Duty Vehicle Sales: Percent Total Alternative Sales: Low economic growth | C52: AEO.2022.LOWMACRO.ECI_SAL_TRN_LDTY_ALT_NA_NA_PCT.A | D52: percent | F52: 12.455999 | G52: 14.571984 | H52: 15.600765 | I52: 16.004927 | J52: 16.139498 | K52: 16.278839 | L52: 16.464922 | M52: 16.678802 | N52: 16.941446 | O52: 17.293423 | P52: 17.605484 | Q52: 18.134192 | R52: 18.535164 | S52: 18.911802 | T52: 19.290403 | U52: 19.623487 | V52: 19.95421 | W52: 20.306282 | X52: 20.598869 | Y52: 20.985233 | Z52: 21.343271 | AA52: 21.693348 | AB52: 22.068369 | AC52: 22.394947 | AD52: 22.683172 | AE52: 23.003008 | AF52: 23.292082 | AG52: 23.56691 | AH52: 23.852163 | AI52: 24.034039 | AJ52: 0.023
A53: EPACT Legislative Alternative Sales | B53: Light-Duty Vehicle Sales: EPACT Legislative Alternative Sales: Low economic growth | C53: AEO.2022.LOWMACRO.ECI_SAL_TRN_LDTY_EPACLEGI_NA_NA_TH.A | D53: thousands | F53: 74.063698 | G53: 70.525612 | H53: 74.440796 | I53: 77.914856 | J53: 79.591187 | K53: 81.828644 | L53: 83.563957 | M53: 86.347923 | N53: 89.081993 | O53: 91.337914 | P53: 93.610977 | Q53: 97.19944 | R53: 100.75716 | S53: 101.64602 | T53: 102.49258 | U53: 104.42773 | V53: 107.30495 | W53: 111.21426 | X53: 115.60329 | Y53: 119.62868 | Z53: 122.81091 | AA53: 125.41865 | AB53: 128.01065 | AC53: 130.39082 | AD53: 132.36084 | AE53: 135.84607 | AF53: 138.75171 | AG53: 141.09642 | AH53: 144.8008 | AI53: 147.26543 | AJ53: 0.024
A54: ZEVP Legislative Alternative Sales | B54: Light-Duty Vehicle Sales: ZEVP Legislative Alternative Sales: Low economic growth | C54: AEO.2022.LOWMACRO.ECI_SAL_TRN_LDTY_ZVPLG_NA_NA_TH.A | D54: thousands | F54: 0 | G54: 0 | H54: 0 | I54: 0 | J54: 0 | K54: 0 | L54: 0 | M54: 0 | N54: 0 | O54: 0 | P54: 0 | Q54: 0 | R54: 0 | S54: 0 | T54: 0 | U54: 0 | V54: 0 | W54: 0 | X54: 0 | Y54: 0 | Z54: 0 | AA54: 0 | AB54: 0 | AC54: 0 | AD54: 0 | AE54: 0 | AF54: 0 | AG54: 0 | AH54: 0 | AI54: 0 | AJ54: - -
A55: Total Sales | B55: Cars and Light Trucks
A56: Conventional Gasoline | B56: Light-Duty Vehicle Sales: Total Sales, Cars and Light Trucks: Conventional Gasoline: Low economic growth | C56: AEO.2022.LOWMACRO.ECI_SAL_TRN_LDTY_CVG_NA_NA_TH.A | D56: thousands | F56: 13433.045 | G56: 11966.61 | H56: 11948.765 | I56: 11987.173 | J56: 11784.688 | K56: 11655.68 | L56: 11441.44 | M56: 11357.236 | N56: 11266.191 | O56: 11099.803 | P56: 10952.915 | Q56: 10912.773 | R56: 10883.27 | S56: 10596.859 | T56: 10320.581 | U56: 10173.296 | V56: 10122.292 | W56: 10162.922 | X56: 10254.521 | Y56: 10289.178 | Z56: 10249.78 | AA56: 10165.737 | AB56: 10077.313 | AC56: 9983.6328 | AD56: 9869.5947 | AE56: 9865.8604 | AF56: 9824.3828 | AG56: 9748.7285 | AH56: 9766.5088 | AI56: 9733.1904 | AJ56: -0.011
A57: TDI Diesel | B57: Light-Duty Vehicle Sales: Total Sales, Cars and Light Trucks: TDI Diesel: Low economic growth | C57: AEO.2022.LOWMACRO.ECI_SAL_TRN_LDTY_TDS_NA_NA_TH.A | D57: thousands | F57: 46.474377 | G57: 51.306229 | H57: 54.75354 | I57: 52.244778 | J57: 51.28347 | K57: 51.623837 | L57: 51.784702 | M57: 52.100876 | N57: 51.986439 | O57: 52.998814 | P57: 52.260265 | Q57: 53.65453 | R57: 54.077171 | S57: 53.405434 | T57: 52.140526 | U57: 51.442619 | V57: 51.017975 | W57: 51.729782 | X57: 52.010216 | Y57: 53.09034 | Z57: 53.111794 | AA57: 53.427242 | AB57: 53.197605 | AC57: 52.404533 | AD57: 52.310116 | AE57: 52.380814 | AF57: 52.781521 | AG57: 53.110271 | AH57: 53.507114 | AI57: 53.247482 | AJ57: 0.005
A58: Flex-Fuel | B58: Light-Duty Vehicle Sales: Total Sales, Cars and Light Trucks: Flex-Fuel: Low economic growth | C58: AEO.2022.LOWMACRO.ECI_SAL_TRN_LDTY_FXF_NA_NA_TH.A | D58: thousands | F58: 666.61432 | G58: 606.91516 | H58: 618.10919 | I58: 630.56427 | J58: 628.59216 | K58: 627.24347 | L58: 618.80017 | M58: 616.67511 | N58: 614.18988 | O58: 606.61182 | P58: 600.61334 | Q58: 598.06311 | R58: 597.70502 | S58: 583.15295 | T58: 569.26599 | U58: 562.73712 | V58: 561.62787 | W58: 565.39032 | X58: 572.54346 | Y58: 575.56958 | Z58: 574.92236 | AA58: 571.55652 | AB58: 567.67688 | AC58: 563.86743 | AD58: 559.07037 | AE58: 560.43005 | AF58: 559.84021 | AG58: 557.37433 | AH58: 560.09772 | AI58: 560.37128 | AJ58: -0.006
A59: Electric | B59: Light-Duty Vehicle Sales: Total Sales, Cars and Light Trucks: Electric: Low economic growth | C59: AEO.2022.LOWMACRO.ECI_SAL_TRN_LDTY_ELE_NA_NA_TH.A | D59: thousands | F59: 317.67673 | G59: 349.16574 | H59: 402.0271 | I59: 448.68018 | J59: 459.36792 | K59: 469.61072 | L59: 478.50217 | M59: 494.52203 | N59: 516.58148 | O59: 542.41242 | P59: 562.09228 | Q59: 609.23364 | R59: 647.51093 | S59: 667.82764 | T59: 688.5769 | U59: 712.34137 | V59: 742.12219 | W59: 781.10626 | X59: 819.29877 | Y59: 862.25433 | Z59: 896.63806 | AA59: 927.93292 | AB59: 961.92572 | AC59: 989.92859 | AD59: 1011.6077 | AE59: 1048.2125 | AF59: 1078.1364 | AG59: 1102.8053 | AH59: 1139.6194 | AI59: 1159.5818 | AJ59: 0.046
A60: Plug-in Electric Hybrid | B60: Light-Duty Vehicle Sales: Total Sales, Cars and Light Trucks: Plug-in Electric Hybrid: Low economic growth | C60: AEO.2022.LOWMACRO.ECI_SAL_TRN_LDTY_PIE_NA_NA_TH.A | D60: thousands | F60: 139.40208 | G60: 251.00243 | H60: 281.45023 | I60: 282.72653 | J60: 276.52441 | K60: 271.61221 | L60: 267.384 | M60: 268.01288 | N60: 270.37866 | O60: 274.46634 | P60: 279.97192 | Q60: 293.64508 | R60: 303.75568 | S60: 306.29041 | T60: 308.38086 | U60: 313.05124 | V60: 320.13071 | W60: 330.45059 | X60: 341.32626 | Y60: 352.33606 | Z60: 359.36456 | AA60: 364.57547 | AB60: 369.86917 | AC60: 373.76666 | AD60: 375.84781 | AE60: 382.56198 | AF60: 387.16751 | AG60: 390.01712 | AH60: 396.6799 | AI60: 399.29532 | AJ60: 0.037
A61: Electric Hybrid | B61: Light-Duty Vehicle Sales: Total Sales, Cars and Light Trucks: Electric Hybrid: Low economic growth | C61: AEO.2022.LOWMACRO.ECI_SAL_TRN_LDTY_EHY_NA_NA_TH.A | D61: thousands | F61: 790.50092 | G61: 839.1814 | H61: 912.99689 | I61: 927.59228 | J61: 908.62213 | K61: 902.6994 | L61: 895.09186 | M61: 898.67065 | N61: 901.05969 | O61: 901.79303 | P61: 901.87097 | Q61: 920.89209 | R61: 931.76556 | S61: 918.85474 | T61: 905.22101 | U61: 900.46619 | V61: 904.46851 | W61: 917.81659 | X61: 932.36926 | Y61: 948.06146 | Z61: 955.93799 | AA61: 957.97693 | AB61: 960.07733 | AC61: 959.27154 | AD61: 954.93207 | AE61: 962.25 | AF61: 964.21698 | AG61: 962.14801 | AH61: 969.50476 | AI61: 966.84656 | AJ61: 0.007
A62: Gaseous (Propane and Natural Gas) | B62: Light-Duty Vehicle Sales: Total Sales, Cars and Light Trucks: Gaseous: Low economic growth | C62: AEO.2022.LOWMACRO.ECI_SAL_TRN_LDTY_GSU_NA_NA_TH.A | D62: thousands | F62: 0.897537 | G62: 1.122171 | H62: 1.297062 | I62: 1.388858 | J62: 1.421118 | K62: 1.442317 | L62: 1.447393 | M62: 1.454261 | N62: 1.450253 | O62: 1.460388 | P62: 1.462236 | Q62: 1.499341 | R62: 1.529442 | S62: 1.526526 | T62: 1.525431 | U62: 1.540147 | V62: 1.567688 | W62: 1.617386 | X62: 1.669021 | Y62: 1.732613 | Z62: 1.7792 | AA62: 1.827841 | AB62: 1.87752 | AC62: 1.920797 | AD62: 1.970749 | AE62: 2.061524 | AF62: 2.145725 | AG62: 2.215896 | AH62: 2.311106 | AI62: 2.373477 | AJ62: 0.034
A63: Fuel Cell | B63: Light-Duty Vehicle Sales: Total Sales, Cars and Light Trucks: Fuel Cell: Low economic growth | C63: AEO.2022.LOWMACRO.ECI_SAL_TRN_LDTY_FUC_NA_NA_TH.A | D63: thousands | F63: 2.811197 | G63: 2.583219 | H63: 2.908118 | I63: 3.110819 | J63: 3.382208 | K63: 3.773611 | L63: 4.111054 | M63: 4.526493 | N63: 4.907628 | O63: 5.236283 | P63: 5.498351 | Q63: 5.852921 | R63: 6.235659 | S63: 6.256451 | T63: 6.214406 | U63: 6.177381 | V63: 6.135384 | W63: 6.353412 | X63: 6.594737 | Y63: 6.809524 | Z63: 7.01726 | AA63: 7.152792 | AB63: 7.290894 | AC63: 7.403693 | AD63: 7.454294 | AE63: 7.578329 | AF63: 7.658518 | AG63: 7.678229 | AH63: 7.758953 | AI63: 7.755348 | AJ63: 0.036
A64: Total Vehicles Sales | B64: Light-Duty Vehicle Sales: Total Vehicles Sales: Low economic growth | C64: AEO.2022.LOWMACRO.ECI_SAL_TRN_LDTY_NA_NA_NA_TH.A | D64: thousands | F64: 15397.422 | G64: 14067.886 | H64: 14222.306 | I64: 14333.48 | J64: 14113.883 | K64: 13983.686 | L64: 13758.562 | M64: 13693.199 | N64: 13626.746 | O64: 13484.783 | P64: 13356.684 | Q64: 13395.614 | R64: 13425.848 | S64: 13134.172 | T64: 12851.907 | U64: 12721.052 | V64: 12709.361 | W64: 12817.387 | X64: 12980.332 | Y64: 13089.032 | Z64: 13098.552 | AA64: 13050.187 | AB64: 12999.229 | AC64: 12932.197 | AD64: 12832.787 | AE64: 12881.334 | AF64: 12876.33 | AG64: 12824.078 | AH64: 12895.989 | AI64: 12882.662 | AJ64: -0.006
A65: Conventional Gasoline Microhybrids | B65: Light-Duty Vehicle Sales: Microhybrids: Conventional Gasoline: Low economic growth | C65: AEO.2022.LOWMACRO.ECI_SAL_TRN_MCHY_CVG_NA_NA_TH.A | D65: thousands | F65: 4953.1133 | G65: 4668.9976 | H65: 4958.145 | I65: 5404.3682 | J65: 5500.1509 | K65: 5639.5771 | L65: 5625.3179 | M65: 5668.8452 | N65: 5678.7173 | O65: 5624.5156 | P65: 5562.1196 | Q65: 5547.9023 | R65: 5531.2271 | S65: 5383.1025 | T65: 5267.1528 | U65: 5226.7104 | V65: 5235.1162 | W65: 5280.4731 | X65: 5356.3335 | Y65: 5373.9346 | Z65: 5357.4409 | AA65: 5315.6724 | AB65: 5287.2612 | AC65: 5251.5776 | AD65: 5206.2437 | AE65: 5220.0103 | AF65: 5220.5039 | AG65: 5181.395 | AH65: 5202.6357 | AI65: 5189.8833 | AJ65: 0.002
A66: TDI Diesel Microhybrids | B66: Light-Duty Vehicle Sales: Microhybrids: TDI Diesel: Low economic growth | C66: AEO.2022.LOWMACRO.ECI_SAL_TRN_MCHY_TDS_NA_NA_TH.A | D66: thousands | F66: 0 | G66: 0 | H66: 0 | I66: 0 | J66: 0 | K66: 0 | L66: 0 | M66: 0 | N66: 0 | O66: 0 | P66: 0 | Q66: 0 | R66: 0 | S66: 0 | T66: 0 | U66: 0 | V66: 0 | W66: 0 | X66: 0 | Y66: 0 | Z66: 0 | AA66: 0 | AB66: 0 | AC66: 0 | AD66: 0 | AE66: 0 | AF66: 0 | AG66: 0 | AH66: 0 | AI66: 0 | AJ66: - -
A67: Total Alternative-Fueled Vehicle Sales | B67: Light-Duty Vehicle Sales: Alternative-Fueled Vehicles: Low economic growth | C67: AEO.2022.LOWMACRO.ECI_SAL_TRN_LDTY_NA_NA_NA_TH.A | D67: thousands | F67: 6917.4902 | G67: 6770.2744 | H67: 7231.6865 | I67: 7750.6748 | J67: 7829.3447 | K67: 7967.582 | L67: 7942.4385 | M67: 8004.8066 | N67: 8039.2715 | O67: 8009.4941 | P67: 7965.8896 | Q67: 8030.7422 | R67: 8073.8066 | S67: 7920.416 | T67: 7798.4775 | U67: 7774.4658 | V67: 7822.1865 | W67: 7934.9375 | X67: 8082.1455 | Y67: 8173.7871 | Z67: 8206.2119 | AA67: 8200.1221 | AB67: 8209.1768 | AC67: 8200.1406 | AD67: 8169.4365 | AE67: 8235.4854 | AF67: 8272.4512 | AG67: 8256.7441 | AH67: 8332.1143 | AI67: 8339.3545 | AJ67: 0.006

Sheet Table 44
A1: ref2023.d020623a | B1: 2022 | C1: 2023 | D1: 2024 | E1: 2025 | F1: 2026 | G1: 2027 | H1: 2028 | I1: 2029 | J1: 2030 | K1: 2031 | L1: 2032 | M1: 2033 | N1: 2034 | O1: 2035 | P1: 2036 | Q1: 2037 | R1: 2038 | S1: 2039 | T1: 2040 | U1: 2041 | V1: 2042 | W1: 2043 | X1: 2044 | Y1: 2045 | Z1: 2046 | AA1: 2047 | AB1: 2048 | AC1: 2049 | AD1: 2050
B3: Report | C3: Annual Energy Outlook 2023
B4: Scenario | C4: ref2023 | F4: Reference
B5: Datekey | C5: d020623a
B6: Release Date | D6: March 2023
A10: 44. Transportation Fleet Car and Truck Sales by Type and Technology | AE10: Annual
A11: (thousands) | AE11: Change
AE12: 2022–2050
A13: Technology Type | B13: 2022 | C13: 2023 | D13: 2024 | E13: 2025 | F13: 2026 | G13: 2027 | H13: 2028 | I13: 2029 | J13: 2030 | K13: 2031 | L13: 2032 | M13: 2033 | N13: 2034 | O13: 2035 | P13: 2036 | Q13: 2037 | R13: 2038 | S13: 2039 | T13: 2040 | U13: 2041 | V13: 2042 | W13: 2043 | X13: 2044 | Y13: 2045 | Z13: 2046 | AA13: 2047 | AB13: 2048 | AC13: 2049 | AD13: 2050 | AE13: 2050
A15: New Car Sales 1/
A16: Conventional Cars
A17: Gasoline ICE Vehicles | B17: 745.48859 | C17: 752.84778 | D17: 752.35828 | E17: 735.73346 | F17: 714.39777 | G17: 699.98785 | H17: 685.04047 | I17: 673.87494 | J17: 663.85052 | K17: 653.93219 | L17: 646.67609 | M17: 638 | N17: 632.65363 | O17: 629.94421 | P17: 630.54657 | Q17: 627.93366 | R17: 625.11896 | S17: 622.16144 | T17: 618.44098 | U17: 611.17291 | V17: 603.78058 | W17: 594.08051 | X17: 586.63452 | Y17: 582.1673 | Z17: 581.98822 | AA17: 575.44702 | AB17: 569.67371 | AC17: 564.75281 | AD17: 561.18835 | AE17: -0.010091
A18: TDI Diesel ICE | B18: 0 | C18: 0 | D18: 0 | E18: 0 | F18: 0 | G18: 0 | H18: 0 | I18: 0 | J18: 0 | K18: 0 | L18: 0 | M18: 0 | N18: 0 | O18: 0 | P18: 0 | Q18: 0 | R18: 0 | S18: 0 | T18: 0 | U18: 0 | V18: 0 | W18: 0 | X18: 0 | Y18: 0 | Z18: 0 | AA18: 0 | AB18: 0 | AC18: 0 | AD18: 0 | AE18: --
A19: Total Conventional Cars | B19: 745.48859 | C19: 752.84778 | D19: 752.35828 | E19: 735.73346 | F19: 714.39777 | G19: 699.98785 | H19: 685.04047 | I19: 673.87494 | J19: 663.85052 | K19: 653.93219 | L19: 646.67609 | M19: 638 | N19: 632.65363 | O19: 629.94421 | P19: 630.54657 | Q19: 627.93366 | R19: 625.11896 | S19: 622.16144 | T19: 618.44098 | U19: 611.17291 | V19: 603.78058 | W19: 594.08051 | X19: 586.63452 | Y19: 582.1673 | Z19: 581.98822 | AA19: 575.44702 | AB19: 569.67371 | AC19: 564.75281 | AD19: 561.18835 | AE19: -0.010091
A21: Alternative-Fuel Cars
A22: Ethanol-Flex Fuel ICE | B22: 27.701494 | C22: 28.161213 | D22: 28.336246 | E22: 27.930389 | F22: 27.360483 | G22: 27.062561 | H22: 26.745171 | I22: 26.574789 | J22: 26.450092 | K22: 26.327152 | L22: 26.309853 | M22: 26.236437 | N22: 26.300083 | O22: 26.476437 | P22: 26.802656 | Q22: 26.993179 | R22: 27.175011 | S22: 27.3564 | T22: 27.506229 | U22: 27.497744 | V22: 27.48558 | W22: 27.36544 | X22: 27.347322 | Y22: 27.466482 | Z22: 27.77367 | AA22: 27.796991 | AB22: 27.862095 | AC22: 27.968414 | AD22: 27.940855 | AE22: 0.000307
A23: 100-Mile Electric Vehicle | B23: 1.733732 | C23: 2.015718 | D23: 2.282101 | E23: 2.494302 | F23: 2.678695 | G23: 2.879138 | H23: 3.07065 | I23: 3.273858 | J23: 3.479208 | K23: 3.682477 | L23: 3.899189 | M23: 4.106014 | N23: 4.333928 | O23: 4.58201 | P23: 4.858603 | Q23: 5.115785 | R23: 5.375243 | S23: 5.636921 | T23: 5.89505 | U23: 6.120733 | V23: 6.344616 | W23: 6.542595 | X23: 6.763642 | Y23: 7.019996 | Z23: 7.332982 | AA23: 7.569391 | AB23: 7.816744 | AC23: 8.077607 | AD23: 8.358113 | AE23: 0.057785
A24: 200-Mile Electric Vehicle | B24: 2.34727 | C24: 4.423422 | D24: 6.51033 | E24: 8.447515 | F24: 10.260118 | G24: 12.106405 | H24: 13.894964 | I24: 15.720405 | J24: 17.546631 | K24: 19.353251 | L24: 21.224617 | M24: 23.038656 | N24: 24.968584 | O24: 27.018316 | P24: 29.246431 | Q24: 31.364456 | R24: 33.500416 | S24: 35.655449 | T24: 37.791504 | U24: 39.719631 | V24: 41.633911 | W24: 43.373734 | X24: 45.262123 | Y24: 47.386185 | Z24: 49.898258 | AA24: 51.892063 | AB24: 53.95982 | AC24: 56.121365 | AD24: 58.420788 | AE24: 0.12165
A25: 300-Mile Electric Vehicle | B25: 16.660831 | C25: 19.503101 | D25: 22.200615 | E25: 24.367395 | F25: 26.25774 | G25: 28.301954 | H25: 30.256197 | I25: 32.324257 | J25: 34.412506 | K25: 36.479725 | L25: 38.679714 | M25: 40.781128 | N25: 43.091831 | O25: 45.603497 | P25: 48.399467 | Q25: 51.002945 | R25: 53.629681 | S25: 56.278992 | T25: 58.893322 | U25: 61.18375 | V25: 63.455978 | W25: 65.468964 | X25: 67.712502 | Y25: 70.309715 | Z25: 73.47554 | AA25: 75.873489 | AB25: 78.380974 | AC25: 81.024094 | AD25: 83.864441 | AE25: 0.059418
A26: Plug-in 20 Gasoline Hybrid | B26: 2.416381 | C26: 2.779324 | D26: 3.120898 | E26: 3.388887 | F26: 3.61952 | G26: 3.871928 | H26: 4.112279 | I26: 4.368149 | J26: 4.626535 | K26: 4.881974 | L26: 5.155017 | M26: 5.414467 | N26: 5.701344 | O26: 6.014175 | P26: 6.363098 | Q26: 6.686507 | R26: 7.012915 | S26: 7.341406 | T26: 7.665002 | U26: 7.946321 | V26: 8.224556 | W26: 8.469109 | X26: 8.743222 | Y26: 9.063097 | Z26: 9.459611 | AA26: 9.753787 | AB26: 10.060923 | AC26: 10.385608 | AD26: 10.734817 | AE26: 0.054702
A27: Plug-in 50 Gasoline Hybrid | B27: 0.85057 | C27: 1.23013 | D27: 1.607591 | E27: 1.947863 | F27: 2.261849 | G27: 2.585001 | H27: 2.896867 | I27: 3.217093 | J27: 3.53761 | K27: 3.854425 | L27: 4.184191 | M27: 4.502318 | N27: 4.842849 | O27: 5.205986 | P27: 5.601945 | Q27: 5.976532 | R27: 6.354444 | S27: 6.735092 | T27: 7.111816 | U27: 7.449342 | V27: 7.783675 | W27: 8.085442 | X27: 8.414771 | Y27: 8.788048 | Z27: 9.236242 | AA27: 9.585274 | AB27: 9.946996 | AC27: 10.326148 | AD27: 10.729992 | AE27: 0.094756
A28: Electric-Diesel Hybrid | B28: 0 | C28: 0 | D28: 0 | E28: 0 | F28: 0 | G28: 0 | H28: 0 | I28: 0 | J28: 0 | K28: 0 | L28: 0 | M28: 0 | N28: 0 | O28: 0 | P28: 0 | Q28: 0 | R28: 0 | S28: 0 | T28: 0 | U28: 0 | V28: 0 | W28: 0 | X28: 0 | Y28: 0 | Z28: 0 | AA28: 0 | AB28: 0 | AC28: 0 | AD28: 0 | AE28: --
A29: Electric-Gasoline Hybrid | B29: 32.527454 | C29: 34.683559 | D29: 36.517467 | E29: 37.527821 | F29: 38.211796 | G29: 39.194439 | H29: 40.098598 | I29: 41.186401 | J29: 42.318878 | K29: 43.439339 | L29: 44.725349 | M29: 45.902386 | N29: 47.315739 | O29: 48.939678 | P29: 50.848152 | Q29: 52.535007 | R29: 54.232723 | S29: 55.940033 | T29: 57.601685 | U29: 58.942471 | V29: 60.265564 | W29: 61.346802 | X29: 62.647991 | Y29: 64.274544 | Z29: 66.418465 | AA29: 67.85157 | AB29: 69.378136 | AC29: 71.021629 | AD29: 72.830383 | AE29: 0.029206
A30: Natural Gas ICE | B30: 0 | C30: 0 | D30: 0 | E30: 0 | F30: 0 | G30: 0 | H30: 0 | I30: 0 | J30: 0 | K30: 0 | L30: 0 | M30: 0 | N30: 0 | O30: 0 | P30: 0 | Q30: 0 | R30: 0 | S30: 0 | T30: 0 | U30: 0 | V30: 0 | W30: 0 | X30: 0 | Y30: 0 | Z30: 0 | AA30: 0 | AB30: 0 | AC30: 0 | AD30: 0 | AE30: --
A31: Natural Gas Bi-fuel | B31: 0 | C31: 0 | D31: 0 | E31: 0 | F31: 0 | G31: 0 | H31: 0 | I31: 0 | J31: 0 | K31: 0 | L31: 0 | M31: 0 | N31: 0 | O31: 0 | P31: 0 | Q31: 0 | R31: 0 | S31: 0 | T31: 0 | U31: 0 | V31: 0 | W31: 0 | X31: 0 | Y31: 0 | Z31: 0 | AA31: 0 | AB31: 0 | AC31: 0 | AD31: 0 | AE31: --
A32: Propane ICE | B32: 0 | C32: 0 | D32: 0 | E32: 0 | F32: 0 | G32: 0 | H32: 0 | I32: 0 | J32: 0 | K32: 0 | L32: 0 | M32: 0 | N32: 0 | O32: 0 | P32: 0 | Q32: 0 | R32: 0 | S32: 0 | T32: 0 | U32: 0 | V32: 0 | W32: 0 | X32: 0 | Y32: 0 | Z32: 0 | AA32: 0 | AB32: 0 | AC32: 0 | AD32: 0 | AE32: --
A33: Propane Bi-fuel | B33: 0 | C33: 0 | D33: 0 | E33: 0 | F33: 0 | G33: 0 | H33: 0 | I33: 0 | J33: 0 | K33: 0 | L33: 0 | M33: 0 | N33: 0 | O33: 0 | P33: 0 | Q33: 0 | R33: 0 | S33: 0 | T33: 0 | U33: 0 | V33: 0 | W33: 0 | X33: 0 | Y33: 0 | Z33: 0 | AA33: 0 | AB33: 0 | AC33: 0 | AD33: 0 | AE33: --
A34: Fuel Cell Methanol | B34: 0 | C34: 0 | D34: 0 | E34: 0 | F34: 0 | G34: 0 | H34: 0 | I34: 0 | J34: 0 | K34: 0 | L34: 0 | M34: 0 | N34: 0 | O34: 0 | P34: 0 | Q34: 0 | R34: 0 | S34: 0 | T34: 0 | U34: 0 | V34: 0 | W34: 0 | X34: 0 | Y34: 0 | Z34: 0 | AA34: 0 | AB34: 0 | AC34: 0 | AD34: 0 | AE34: --
A35: Fuel Cell Hydrogen | B35: 0.048113 | C35: 0.092384 | D35: 0.137451 | E35: 0.179425 | F35: 0.218551 | G35: 0.258121 | H35: 0.29623 | I35: 0.334905 | J35: 0.373342 | K35: 0.411207 | L35: 0.450298 | M35: 0.487883 | N35: 0.527722 | O35: 0.569856 | P35: 0.615191 | Q35: 0.65825 | R35: 0.701748 | S35: 0.745306 | T35: 0.78838 | U35: 0.827084 | V35: 0.865125 | W35: 0.89946 | X35: 0.936702 | Y35: 0.978884 | Z35: 1.03084 | AA35: 1.070397 | AB35: 1.110929 | AC35: 1.153482 | AD35: 1.19854 | AE35: 0.121686
A36: Total Alternative Cars | B36: 84.285843 | C36: 92.888847 | D36: 100.7127 | E36: 106.28359 | F36: 110.86876 | G36: 116.25954 | H36: 121.37095 | I36: 126.99986 | J36: 132.7448 | K36: 138.42955 | L36: 144.62823 | M36: 150.46928 | N36: 157.08208 | O36: 164.40996 | P36: 172.73555 | Q36: 180.33266 | R36: 187.98219 | S36: 195.68961 | T36: 203.25299 | U36: 209.68707 | V36: 216.05902 | W36: 221.55154 | X36: 227.82828 | Y36: 235.28696 | Z36: 244.62561 | AA36: 251.39296 | AB36: 258.51663 | AC36: 266.07834 | AD36: 274.07794 | AE36: 0.043014
A38: Percent Alternative Car Sales | B38: 10.157681 | C38: 10.983189 | D38: 11.8059 | E38: 12.622499 | F38: 13.434297 | G38: 14.243176 | H38: 15.050748 | I38: 15.857643 | J38: 16.664019 | K38: 17.470499 | L38: 18.277195 | M38: 19.083721 | N38: 19.890461 | O38: 20.697311 | P38: 21.503721 | Q38: 22.311045 | R38: 23.119165 | S38: 23.92729 | T38: 24.735849 | U38: 25.544804 | V38: 26.353815 | W38: 27.163172 | X38: 27.97283 | Y38: 28.782892 | Z38: 29.5937 | AA38: 30.404064 | AB38: 31.214642 | AC38: 32.025562 | AD38: 32.813244 | AE38: 0.042768
A39: Total New Car Sales | B39: 829.77441 | C39: 845.73663 | D39: 853.07098 | E39: 842.01703 | F39: 825.26654 | G39: 816.24738 | H39: 806.41144 | I39: 800.87482 | J39: 796.59534 | K39: 792.36176 | L39: 791.30432 | M39: 788.4693 | N39: 789.73572 | O39: 794.35419 | P39: 803.2821 | Q39: 808.2663 | R39: 813.10113 | S39: 817.85107 | T39: 821.69397 | U39: 820.85999 | V39: 819.8396 | W39: 815.63208 | X39: 814.46277 | Y39: 817.45422 | Z39: 826.61383 | AA39: 826.83997 | AB39: 828.19031 | AC39: 830.83118 | AD39: 835.2663 | AE39: 0.000236
A41: New Light Truck Sales 1/
A42: Conventional Light Trucks
A43: Gasoline ICE Vehicles | B43: 1139.8827 | C43: 1177.5922 | D43: 1225.1962 | E43: 1266.6293 | F43: 1280.5264 | G43: 1273.6564 | H43: 1266.3192 | I43: 1266.3704 | J43: 1255.4795 | K43: 1247.1234 | L43: 1238.2233 | M43: 1229.917 | N43: 1228.6764 | O43: 1234.7007 | P43: 1240.9656 | Q43: 1247.8655 | R43: 1256.8419 | S43: 1264.0477 | T43: 1273.665 | U43: 1276.9398 | V43: 1280.7981 | W43: 1284.9028 | X43: 1287.0942 | Y43: 1296.9729 | Z43: 1299.4546 | AA43: 1304.3114 | AB43: 1303.999 | AC43: 1310.5312 | AD43: 1318.3575 | AE43: 0.005209
A44: TDI Diesel ICE | B44: 0.042834 | C44: 0.0448 | D44: 0.047137 | E44: 0.049205 | F44: 0.050164 | G44: 0.05028 | H44: 0.050354 | I44: 0.050707 | J44: 0.050606 | K44: 0.050601 | L44: 0.050573 | M44: 0.05056 | N44: 0.050837 | O44: 0.051416 | P44: 0.051999 | Q44: 0.052623 | R44: 0.053332 | S44: 0.053966 | T44: 0.054716 | U44: 0.055203 | V44: 0.05572 | W44: 0.056254 | X44: 0.056709 | Y44: 0.057515 | Z44: 0.058032 | AA44: 0.058632 | AB44: 0.058999 | AC44: 0.059676 | AD44: 0.06041 | AE44: 0.012355
A45: Total Conventional Light Trucks | B45: 1139.9255 | C45: 1177.637 | D45: 1225.2433 | E45: 1266.6785 | F45: 1280.5765 | G45: 1273.7067 | H45: 1266.3696 | I45: 1266.421 | J45: 1255.5302 | K45: 1247.1741 | L45: 1238.2738 | M45: 1229.9675 | N45: 1228.7272 | O45: 1234.7521 | P45: 1241.0176 | Q45: 1247.9181 | R45: 1256.8953 | S45: 1264.1017 | T45: 1273.7197 | U45: 1276.995 | V45: 1280.8538 | W45: 1284.9591 | X45: 1287.151 | Y45: 1297.0304 | Z45: 1299.5126 | AA45: 1304.37 | AB45: 1304.058 | AC45: 1310.5909 | AD45: 1318.418 | AE45: 0.005209
A47: Alternative-Fuel Light Trucks
A48: Ethanol-Flex Fuel ICE | B48: 97.975632 | C48: 102.39687 | D48: 107.67007 | E48: 112.33575 | F48: 114.48013 | G48: 114.70761 | H48: 114.84385 | I48: 115.61748 | J48: 115.36041 | K48: 115.32437 | L48: 115.23352 | M48: 115.18002 | N48: 115.78656 | O48: 117.08218 | P48: 118.38756 | Q48: 119.78483 | R48: 121.37783 | S48: 122.8025 | T48: 124.48741 | U48: 125.57402 | V48: 126.72716 | W48: 127.91966 | X48: 128.93149 | Y48: 130.74116 | Z48: 131.88454 | AA48: 133.22308 | AB48: 134.03351 | AC48: 135.54968 | AD48: 137.19547 | AE48: 0.012097
A49: 100-Mile Electric Vehicle | B49: 0.077187 | C49: 0.076893 | D49: 0.07708 | E49: 0.076725 | F49: 0.074614 | G49: 0.071291 | H49: 0.067977 | I49: 0.065073 | J49: 0.061625 | K49: 0.058332 | L49: 0.055036 | M49: 0.051793 | N49: 0.048852 | O49: 0.046172 | P49: 0.043459 | Q49: 0.040714 | R49: 0.037982 | S49: 0.035139 | T49: 0.0323 | U49: 0.029246 | V49: 0.026166 | W49: 0.02305 | X49: 0.019861 | Y49: 0.016736 | Z49: 0.013458 | AA49: 0.010167 | AB49: 0.006801 | AC49: 0.00343 | AD49: 0 | AE49: --
A50: 200-Mile Electric Vehicle | B50: 3.626619 | C50: 7.114282 | D50: 10.936429 | E50: 14.991846 | F50: 18.91403 | G50: 22.581854 | H50: 26.231239 | I50: 30.04413 | J50: 33.597034 | K50: 37.19194 | L50: 40.750645 | M50: 44.308708 | N50: 48.125023 | O50: 52.274918 | P50: 56.508244 | Q50: 60.848198 | R50: 65.376472 | S50: 69.901756 | T50: 74.653328 | U50: 79.114174 | V50: 83.673813 | W50: 88.316002 | X50: 92.888107 | Y50: 98.097862 | Z50: 102.83463 | AA50: 107.82616 | AB50: 112.44904 | AC50: 117.72791 | AD50: 123.21871 | AE50: 0.134187
A51: 300-Mile Electric Vehicle | B51: 1.540752 | C51: 2.054901 | D51: 2.625191 | E51: 3.223209 | F51: 3.778698 | G51: 4.280706 | H51: 4.780124 | I51: 5.309176 | J51: 5.792547 | K51: 6.284184 | L51: 6.770445 | M51: 7.25732 | N51: 7.786545 | O51: 8.368753 | P51: 8.962948 | Q51: 9.572627 | R51: 10.210526 | S51: 10.846562 | T51: 11.516315 | U51: 12.140107 | V51: 12.778309 | W51: 13.428332 | X51: 14.067024 | Y51: 14.801416 | Z51: 15.463592 | AA51: 16.163538 | AB51: 16.80772 | AC51: 17.549417 | AD51: 18.321917 | AE51: 0.09245
A52: Plug-in 20 Gasoline Hybrid | B52: 4.744301 | C52: 5.045507 | D52: 5.402499 | E52: 5.747861 | F52: 5.979481 | G52: 6.117843 | H52: 6.254298 | I52: 6.428265 | J52: 6.547184 | K52: 6.678004 | L52: 6.80469 | M52: 6.933836 | N52: 7.102757 | O52: 7.315749 | P52: 7.534082 | Q52: 7.758972 | R52: 8.001135 | S52: 8.236279 | T52: 8.490767 | U52: 8.706131 | V52: 8.928126 | W52: 9.154455 | X52: 9.369674 | Y52: 9.643818 | Z52: 9.863976 | AA52: 10.107215 | AB52: 10.313154 | AC52: 10.576284 | AD52: 10.854796 | AE52: 0.030001
A53: Plug-in 50 Gasoline Hybrid | B53: 0.346853 | C53: 0.685489 | D53: 1.054651 | E53: 1.445064 | F53: 1.821794 | G53: 2.173277 | H53: 2.522332 | I53: 2.886506 | J53: 3.225218 | K53: 3.567282 | L53: 3.905131 | M53: 4.242438 | N53: 4.603806 | O53: 4.996414 | P53: 5.396834 | Q53: 5.806306 | R53: 6.233519 | S53: 6.660077 | T53: 7.107193 | U53: 7.525671 | V53: 7.952894 | W53: 8.387099 | X53: 8.813905 | Y53: 9.299941 | Z53: 9.737713 | AA53: 10.201078 | AB53: 10.629158 | AC53: 11.11884 | AD53: 11.628694 | AE53: 0.133648
A54: Electric-Diesel Hybrid | B54: 0 | C54: 0 | D54: 0 | E54: 0 | F54: 0 | G54: 0 | H54: 0 | I54: 0 | J54: 0 | K54: 0 | L54: 0 | M54: 0 | N54: 0 | O54: 0 | P54: 0 | Q54: 0 | R54: 0 | S54: 0 | T54: 0 | U54: 0 | V54: 0 | W54: 0 | X54: 0 | Y54: 0 | Z54: 0 | AA54: 0 | AB54: 0 | AC54: 0 | AD54: 0 | AE54: --
A55: Electric-Gasoline Hybrid | B55: 37.296288 | C55: 39.102524 | D55: 41.305428 | E55: 43.376812 | F55: 44.561203 | G55: 45.045021 | H55: 45.519054 | I55: 46.267311 | J55: 46.621571 | K55: 47.067921 | L55: 47.492344 | M55: 47.939545 | N55: 48.665665 | O55: 49.692074 | P55: 50.747635 | Q55: 51.84573 | R55: 53.052174 | S55: 54.205021 | T55: 55.481575 | U55: 56.500191 | V55: 57.560112 | W55: 58.646866 | X55: 59.661129 | Y55: 61.050877 | Z55: 62.110481 | AA55: 63.303482 | AB55: 64.26046 | AC55: 65.571259 | AD55: 66.969986 | AE55: 0.021125
A56: Natural Gas ICE | B56: 0 | C56: 0 | D56: 0 | E56: 0 | F56: 0 | G56: 0 | H56: 0 | I56: 0 | J56: 0 | K56: 0 | L56: 0 | M56: 0 | N56: 0 | O56: 0 | P56: 0 | Q56: 0 | R56: 0 | S56: 0 | T56: 0 | U56: 0 | V56: 0 | W56: 0 | X56: 0 | Y56: 0 | Z56: 0 | AA56: 0 | AB56: 0 | AC56: 0 | AD56: 0 | AE56: --
A57: Natural Gas Bi-fuel | B57: 0 | C57: 0 | D57: 0 | E57: 0 | F57: 0 | G57: 0 | H57: 0 | I57: 0 | J57: 0 | K57: 0 | L57: 0 | M57: 0 | N57: 0 | O57: 0 | P57: 0 | Q57: 0 | R57: 0 | S57: 0 | T57: 0 | U57: 0 | V57: 0 | W57: 0 | X57: 0 | Y57: 0 | Z57: 0 | AA57: 0 | AB57: 0 | AC57: 0 | AD57: 0 | AE57: --
A58: Propane ICE | B58: 0 | C58: 0 | D58: 0 | E58: 0 | F58: 0 | G58: 0 | H58: 0 | I58: 0 | J58: 0 | K58: 0 | L58: 0 | M58: 0 | N58: 0 | O58: 0 | P58: 0 | Q58: 0 | R58: 0 | S58: 0 | T58: 0 | U58: 0 | V58: 0 | W58: 0 | X58: 0 | Y58: 0 | Z58: 0 | AA58: 0 | AB58: 0 | AC58: 0 | AD58: 0 | AE58: --
A59: Propane Bi-fuel | B59: 0 | C59: 0 | D59: 0 | E59: 0 | F59: 0 | G59: 0 | H59: 0 | I59: 0 | J59: 0 | K59: 0 | L59: 0 | M59: 0 | N59: 0 | O59: 0 | P59: 0 | Q59: 0 | R59: 0 | S59: 0 | T59: 0 | U59: 0 | V59: 0 | W59: 0 | X59: 0 | Y59: 0 | Z59: 0 | AA59: 0 | AB59: 0 | AC59: 0 | AD59: 0 | AE59: --
A60: Fuel Cell Methanol | B60: 0 | C60: 0 | D60: 0 | E60: 0 | F60: 0 | G60: 0 | H60: 0 | I60: 0 | J60: 0 | K60: 0 | L60: 0 | M60: 0 | N60: 0 | O60: 0 | P60: 0 | Q60: 0 | R60: 0 | S60: 0 | T60: 0 | U60: 0 | V60: 0 | W60: 0 | X60: 0 | Y60: 0 | Z60: 0 | AA60: 0 | AB60: 0 | AC60: 0 | AD60: 0 | AE60: --
A61: Fuel Cell Hydrogen | B61: 0.002034 | C61: 0.004225 | D61: 0.006628 | E61: 0.00918 | F61: 0.011653 | G61: 0.013968 | H61: 0.016271 | I61: 0.018672 | J61: 0.020911 | K61: 0.023173 | L61: 0.025411 | M61: 0.027647 | N61: 0.030044 | O61: 0.032647 | P61: 0.035303 | Q61: 0.038024 | R61: 0.040864 | S61: 0.043703 | T61: 0.046681 | U61: 0.049475 | V61: 0.052331 | W61: 0.055236 | X61: 0.058096 | Y61: 0.061352 | Z61: 0.064302 | AA61: 0.067422 | AB61: 0.070311 | AC61: 0.073611 | AD61: 0.077048 | AE61: 0.138607
A62: Total Alternative Light Trucks | B62: 145.60967 | C62: 156.48068 | D62: 169.07797 | E62: 181.20645 | F62: 189.62161 | G62: 194.99156 | H62: 200.23515 | I62: 206.63663 | J62: 211.22647 | K62: 216.19522 | L62: 221.03722 | M62: 225.94132 | N62: 232.14925 | O62: 239.80893 | P62: 247.61607 | Q62: 255.6954 | R62: 264.33047 | S62: 272.73105 | T62: 281.81561 | U62: 289.63901 | V62: 297.69894 | W62: 305.93072 | X62: 313.8093 | Y62: 323.71317 | Z62: 331.97269 | AA62: 340.90216 | AB62: 348.57013 | AC62: 358.17044 | AD62: 368.26666 | AE62: 0.033694
A64: Percent Alternative Light Truck Sales | B64: 11.326775 | C64: 11.729152 | D64: 12.126184 | E64: 12.515253 | F64: 12.897691 | G64: 13.276489 | H64: 13.652973 | I64: 14.027736 | J64: 14.400922 | K64: 14.773798 | L64: 15.146683 | M64: 15.518919 | N64: 15.891093 | O64: 16.263073 | P64: 16.633781 | Q64: 17.005394 | R64: 17.37615 | S64: 17.746307 | T64: 18.116953 | U64: 18.487982 | V64: 18.85898 | W64: 19.230164 | X64: 19.601316 | Y64: 19.973127 | Z64: 20.347881 | AA64: 20.720106 | AB64: 21.091866 | AC64: 21.463251 | AD64: 21.833759 | AE64: 0.023716
A65: Total New Light Truck Sales | B65: 1285.5352 | C65: 1334.1177 | D65: 1394.3213 | E65: 1447.8849 | F65: 1470.1981 | G65: 1468.6982 | H65: 1466.6047 | I65: 1473.0576 | J65: 1466.7566 | K65: 1463.3693 | L65: 1459.311 | M65: 1455.9088 | N65: 1460.8765 | O65: 1474.561 | P65: 1488.6337 | Q65: 1503.6135 | R65: 1521.2257 | S65: 1536.8328 | T65: 1555.5354 | U65: 1566.634 | V65: 1578.5527 | W65: 1590.8899 | X65: 1600.9603 | Y65: 1620.7435 | Z65: 1631.4852 | AA65: 1645.2722 | AB65: 1652.6282 | AC65: 1668.7614 | AD65: 1686.6846 | AE65: 0.009747
A67: Total Fleet Vehicles | B67: 2115.3096 | C67: 2179.8542 | D67: 2247.3923 | E67: 2289.9019 | F67: 2295.4646 | G67: 2284.9456 | H67: 2273.0161 | I67: 2273.9324 | J67: 2263.3521 | K67: 2255.731 | L67: 2250.6152 | M67: 2244.3782 | N67: 2250.6123 | O67: 2268.9153 | P67: 2291.9158 | Q67: 2311.8799 | R67: 2334.3269 | S67: 2354.6838 | T67: 2377.2295 | U67: 2387.4941 | V67: 2398.3923 | W67: 2406.522 | X67: 2415.4231 | Y67: 2438.1978 | Z67: 2458.0991 | AA67: 2472.1123 | AB67: 2480.8184 | AC67: 2499.5925 | AD67: 2521.9509 | AE67: 0.006299
A69: Commercial Light Truck Sales 2/
A70: Motor Gasoline | B70: 410.29077 | C70: 411.8602 | D70: 422.08719 | E70: 427.93866 | F70: 425.80893 | G70: 420.11331 | H70: 414.63776 | I70: 410.57367 | J70: 405.62149 | K70: 400.92529 | L70: 396.54636 | M70: 391.28879 | N70: 387.86078 | O70: 386.62799 | P70: 386.7623 | Q70: 386.57773 | R70: 387.32144 | S70: 387.70996 | T70: 388.84601 | U70: 388.04797 | V70: 387.54559 | W70: 386.55063 | X70: 386.34116 | Y70: 388.39728 | Z70: 390.78958 | AA70: 393.30301 | AB70: 393.95352 | AC70: 395.85947 | AD70: 398.83917 | AE70: -0.00101
A71: Diesel | B71: 201.5527 | C71: 203.64354 | D71: 209.87985 | E71: 213.99391 | F71: 214.05772 | G71: 212.22472 | H71: 210.50501 | I71: 209.42543 | J71: 207.82423 | K71: 206.28252 | L71: 205.66522 | M71: 205.2451 | N71: 205.64667 | O71: 207.12898 | P71: 209.04892 | Q71: 210.68805 | R71: 212.59926 | S71: 214.24075 | T71: 216.09015 | U71: 216.77892 | V71: 217.4895 | W71: 217.91325 | X71: 218.44653 | Y71: 220.21542 | Z71: 221.82936 | AA71: 223.04495 | AB71: 223.58778 | AC71: 225.01088 | AD71: 226.82165 | AE71: 0.004227
A72: Propane | B72: 0 | C72: 0.426189 | D72: 0.443802 | E72: 0.452902 | F72: 0.472858 | G72: 0.495123 | H72: 0.522636 | I72: 0.559383 | J72: 0.606095 | K72: 0.666157 | L72: 0.739718 | M72: 0.82662 | N72: 0.930666 | O72: 1.058675 | P72: 1.215913 | Q72: 1.400357 | R72: 1.611812 | S72: 1.853485 | T72: 2.121979 | U72: 2.4104 | V72: 2.716785 | W72: 3.048225 | X72: 3.396039 | Y72: 3.774491 | Z72: 4.156269 | AA72: 4.525984 | AB72: 4.863328 | AC72: 5.19646 | AD72: 5.514914 | AE72: --
A73: Compressed/Liquefied Natural Gas | B73: 0 | C73: 0 | D73: 0 | E73: 0 | F73: 0 | G73: 0 | H73: 0 | I73: 0 | J73: 0 | K73: 0 | L73: 0 | M73: 0 | N73: 0 | O73: 0 | P73: 0 | Q73: 0 | R73: 0 | S73: 0 | T73: 0 | U73: 0 | V73: 0 | W73: 0 | X73: 0 | Y73: 0 | Z73: 0 | AA73: 0 | AB73: 0 | AC73: 0 | AD73: 0 | AE73: --
A74: Ethanol-Flex Fuel | B74: 30.450521 | C74: 34.585701 | D74: 41.047306 | E74: 45.537777 | F74: 49.499519 | G74: 53.91124 | H74: 56.826736 | I74: 60.335323 | J74: 64.028458 | K74: 68.345497 | L74: 72.455597 | M74: 76.482697 | N74: 80.193878 | O74: 84.221336 | P74: 87.631432 | Q74: 90.807678 | R74: 93.597557 | S74: 96.278252 | T74: 98.649979 | U74: 100.45418 | V74: 102.04842 | W74: 103.66414 | X74: 104.52655 | Y74: 105.99032 | Z74: 106.50535 | AA74: 105.59877 | AB74: 105.57081 | AC74: 106.51856 | AD74: 107.08038 | AE74: 0.045934
A75: Electric | B75: 0 | C75: 0 | D75: 0 | E75: 0 | F75: 0 | G75: 0 | H75: 0 | I75: 0 | J75: 0 | K75: 0 | L75: 0 | M75: 0 | N75: 0 | O75: 0 | P75: 0 | Q75: 0 | R75: 0 | S75: 0 | T75: 0 | U75: 0 | V75: 0 | W75: 0 | X75: 0 | Y75: 0 | Z75: 0 | AA75: 0 | AB75: 0 | AC75: 0 | AD75: 0 | AE75: --
A76: Plug-in Gasoline Hybrid | B76: 0 | C76: 0.787767 | D76: 0.800162 | E76: 0.80873 | F76: 0.811863 | G76: 0.818902 | H76: 0.83272 | I76: 0.857921 | J76: 0.888965 | K76: 0.926874 | L76: 0.975346 | M76: 1.032321 | N76: 1.10005 | O76: 1.182309 | P76: 1.282668 | Q76: 1.396122 | R76: 1.526245 | S76: 1.669053 | T76: 1.825708 | U76: 1.981003 | V76: 2.139786 | W76: 2.294503 | X76: 2.443944 | Y76: 2.598308 | Z76: 2.739717 | AA76: 2.862724 | AB76: 2.963504 | AC76: 3.063527 | AD76: 3.154913 | AE76: --
A77: Plug-in Diesel Hybrid | B77: 0 | C77: 0.855433 | D77: 0.878329 | E77: 0.872768 | F77: 0.866021 | G77: 0.860978 | H77: 0.859267 | I77: 0.870182 | J77: 0.892912 | K77: 0.931418 | L77: 0.984099 | M77: 1.050674 | N77: 1.131704 | O77: 1.236498 | P77: 1.359498 | Q77: 1.501473 | R77: 1.662221 | S77: 1.841707 | T77: 2.037043 | U77: 2.23404 | V77: 2.435504 | W77: 2.635596 | X77: 2.821458 | Y77: 3.013784 | Z77: 3.179278 | AA77: 3.327742 | AB77: 3.442774 | AC77: 3.561341 | AD77: 3.662281 | AE77: --
A78: Fuel Cell | B78: 0 | C78: 0 | D78: 0 | E78: 0 | F78: 0 | G78: 0 | H78: 0 | I78: 0 | J78: 0 | K78: 0 | L78: 0 | M78: 0 | N78: 0 | O78: 0 | P78: 0 | Q78: 0 | R78: 0 | S78: 0 | T78: 0 | U78: 0 | V78: 0 | W78: 0 | X78: 0 | Y78: 0 | Z78: 0 | AA78: 0 | AB78: 0 | AC78: 0 | AD78: 0 | AE78: --
A79: Total Commercial Light Truck Sales | B79: 642.29395 | C79: 652.15881 | D79: 675.13666 | E79: 689.60468 | F79: 691.51691 | G79: 688.42426 | H79: 684.18414 | I79: 682.62189 | J79: 679.86218 | K79: 678.07776 | L79: 677.36639 | M79: 675.92621 | N79: 676.86371 | O79: 681.45581 | P79: 687.30078 | Q79: 692.37146 | R79: 698.3186 | S79: 703.5932 | T79: 709.57092 | U79: 711.90656 | V79: 714.37567 | W79: 716.10638 | X79: 717.97565 | Y79: 723.98962 | Z79: 729.19946 | AA79: 732.66321 | AB79: 734.38165 | AC79: 739.21014 | AD79: 745.07336 | AE79: 0.005315
A81: 1/ Includes all fleets of 10 or more.
A82: 2/ Commercial trucks from 8,501 to 10,000 pounds.
A83: ICE = Internal combustion engine.
A84: TDI = Turbocharged direct injection
A85: - - = Not Applicable.
A86: Note: Totals may not equal sum of components due to independent rounding.
A87: Data source: U.S. Energy Information Administration, AEO2023 National Energy Modeling System run ref2023.d020623a.

Sheet Table 45
A1: ref2023.d020623a | B1: 2022 | C1: 2023 | D1: 2024 | E1: 2025 | F1: 2026 | G1: 2027 | H1: 2028 | I1: 2029 | J1: 2030 | K1: 2031 | L1: 2032 | M1: 2033 | N1: 2034 | O1: 2035 | P1: 2036 | Q1: 2037 | R1: 2038 | S1: 2039 | T1: 2040 | U1: 2041 | V1: 2042 | W1: 2043 | X1: 2044 | Y1: 2045 | Z1: 2046 | AA1: 2047 | AB1: 2048 | AC1: 2049 | AD1: 2050
B3: Report | C3: Annual Energy Outlook 2023
B4: Scenario | C4: ref2023 | F4: Reference
B5: Datekey | C5: d020623a
B6: Release Date | D6: March 2023
A10: 45. Transportation Fleet Car and Truck Stock by Type and Technology | AE10: Annual
A11: (thousands) | AE11: Change
AE12: 2022–2050
A13: Technology Type | B13: 2022 | C13: 2023 | D13: 2024 | E13: 2025 | F13: 2026 | G13: 2027 | H13: 2028 | I13: 2029 | J13: 2030 | K13: 2031 | L13: 2032 | M13: 2033 | N13: 2034 | O13: 2035 | P13: 2036 | Q13: 2037 | R13: 2038 | S13: 2039 | T13: 2040 | U13: 2041 | V13: 2042 | W13: 2043 | X13: 2044 | Y13: 2045 | Z13: 2046 | AA13: 2047 | AB13: 2048 | AC13: 2049 | AD13: 2050 | AE13: 2050
A15: Car Stock 1/
A16: Conventional Cars
A17: Gasoline ICE Vehicles | B17: 5006.5488 | C17: 4623.4966 | D17: 4322.0991 | E17: 4050.3804 | F17: 3798.4448 | G17: 3573.9875 | H17: 3375.2903 | I17: 3201.9536 | J17: 3049.9338 | K17: 2915.8713 | L17: 2799.1982 | M17: 2695.3247 | N17: 2605.9509 | O17: 2531.2725 | P17: 2471.8772 | Q17: 2420.7988 | R17: 2375.9214 | S17: 2335.8723 | T17: 2299.6143 | U17: 2263.064 | V17: 2226.7246 | W17: 2188.9048 | X17: 2153.0828 | Y17: 2121.8831 | Z17: 2098.4036 | AA17: 2073.5654 | AB17: 2048.2012 | AC17: 2023.4009 | AD17: 2001.2681 | AE17: -0.032218
A18: TDI Diesel ICE | B18: 16.267254 | C18: 14.041601 | D18: 12.078984 | E18: 10.34063 | F18: 8.810128 | G18: 7.452874 | H18: 6.247537 | I18: 5.194445 | J18: 4.291502 | K18: 3.527866 | L18: 2.892869 | M18: 2.376716 | N18: 1.965617 | O18: 1.6438 | P18: 1.393396 | Q18: 1.198524 | R18: 1.047394 | S18: 0.928337 | T18: 0.828804 | U18: 0.742408 | V18: 0.667005 | W18: 0.600459 | X18: 0.541114 | Y18: 0.488003 | Z18: 0.440443 | AA18: 0.39783 | AB18: 0.359624 | AC18: 0.325348 | AD18: 0.294577 | AE18: -0.133474
A19: Total Conventional Cars | B19: 5022.8159 | C19: 4637.5381 | D19: 4334.1782 | E19: 4060.7209 | F19: 3807.2549 | G19: 3581.4404 | H19: 3381.5378 | I19: 3207.1479 | J19: 3054.2253 | K19: 2919.3992 | L19: 2802.0911 | M19: 2697.7014 | N19: 2607.9165 | O19: 2532.9163 | P19: 2473.2705 | Q19: 2421.9973 | R19: 2376.9688 | S19: 2336.8005 | T19: 2300.4431 | U19: 2263.8064 | V19: 2227.3916 | W19: 2189.5051 | X19: 2153.6238 | Y19: 2122.3711 | Z19: 2098.844 | AA19: 2073.9634 | AB19: 2048.5608 | AC19: 2023.7262 | AD19: 2001.5626 | AE19: -0.032325
A21: Alternative-Fuel Cars
A22: Ethanol-Flex Fuel ICE | B22: 260.40921 | C22: 233.98811 | D22: 209.63817 | E22: 186.64131 | F22: 165.97789 | G22: 147.82109 | H22: 132.07271 | I22: 118.78522 | J22: 107.73377 | K22: 98.722214 | L22: 91.63073 | M22: 86.220879 | N22: 82.223007 | O22: 79.438202 | P22: 77.735916 | Q22: 76.54174 | R22: 75.666542 | S22: 75.034683 | T22: 74.555443 | U22: 74.032272 | V22: 73.489876 | W22: 72.862831 | X22: 72.320984 | Y22: 71.990898 | Z22: 72.008469 | AA22: 71.941269 | AB22: 71.822685 | AC22: 71.715027 | AD22: 71.534599 | AE22: -0.045097
A23: 100-Mile Electric Vehicle | B23: 11.328024 | C23: 11.751799 | D23: 12.242356 | E23: 12.619924 | F23: 12.897101 | G23: 13.181957 | H23: 13.471307 | I23: 13.783559 | J23: 14.123207 | K23: 14.488546 | L23: 14.888898 | M23: 15.317131 | N23: 15.79207 | O23: 16.327549 | P23: 16.936695 | Q23: 17.57663 | R23: 18.235157 | S23: 18.903063 | T23: 19.57601 | U23: 20.217279 | V23: 20.833857 | W23: 21.407917 | X23: 21.97821 | Y23: 22.581919 | Z23: 23.266811 | AA23: 23.926888 | AB23: 24.574036 | AC23: 25.223347 | AD23: 25.902096 | AE23: 0.029978
A24: 200-Mile Electric Vehicle | B24: 17.462101 | C24: 18.744711 | D24: 21.541321 | E24: 25.222059 | F24: 29.118896 | G24: 33.20546 | H24: 37.426132 | I24: 41.846264 | J24: 46.466694 | K24: 51.259415 | L24: 56.27491 | M24: 61.416988 | N24: 66.797653 | O24: 72.494194 | P24: 78.615685 | Q24: 84.929886 | R24: 91.387436 | S24: 97.968834 | T24: 104.64284 | U24: 111.18373 | V24: 117.62488 | W24: 123.84116 | X24: 130.07907 | Y24: 136.56813 | Z24: 143.62234 | AA24: 150.50897 | AB24: 157.30911 | AC24: 164.12808 | AD24: 171.15567 | AE24: 0.084934
A25: 300-Mile Electric Vehicle | B25: 55.467815 | C25: 63.862431 | D25: 72.749718 | E25: 81.883339 | F25: 90.405708 | G25: 98.471451 | H25: 106.06701 | I25: 113.40288 | J25: 120.48434 | K25: 127.29469 | L25: 133.98381 | M25: 140.44589 | N25: 146.91003 | O25: 153.54129 | P25: 160.5623 | Q25: 167.61523 | R25: 174.68607 | S25: 181.77106 | T25: 188.8676 | U25: 195.65595 | V25: 202.22496 | W25: 208.40951 | X25: 214.59907 | Y25: 221.16119 | Z25: 228.55313 | AA25: 235.69231 | AB25: 242.69841 | AC25: 249.72317 | AD25: 257.04065 | AE25: 0.056293
A26: Plug-in 20 Gasoline Hybrid | B26: 18.620897 | C26: 18.742386 | D26: 19.225786 | E26: 19.769812 | F26: 20.255058 | G26: 20.684639 | H26: 21.07461 | I26: 21.458031 | J26: 21.848562 | K26: 22.249832 | L26: 22.686924 | M26: 23.151102 | N26: 23.674931 | O26: 24.288008 | P26: 25.015554 | Q26: 25.810991 | R26: 26.663719 | S26: 27.561453 | T26: 28.491934 | U26: 29.406263 | V26: 30.308496 | W26: 31.167662 | X26: 32.028728 | Y26: 32.935436 | Z26: 33.948967 | AA26: 34.930641 | AB26: 35.897713 | AC26: 36.868179 | AD26: 37.873577 | AE26: 0.02568
A27: Plug-in 50 Gasoline Hybrid | B27: 9.18985 | C27: 9.232191 | D27: 9.513065 | E27: 9.890547 | F27: 10.297814 | G27: 10.742392 | H27: 11.226655 | I27: 11.782159 | J27: 12.41293 | K27: 13.113447 | L27: 13.8957 | M27: 14.741248 | N27: 15.667826 | O27: 16.685068 | P27: 17.809175 | Q27: 18.991947 | R27: 20.221149 | S27: 21.486172 | T27: 22.775742 | U27: 24.045906 | V27: 25.302801 | W27: 26.519762 | X27: 27.738804 | Y27: 29.00321 | Z27: 30.374689 | AA27: 31.715918 | AB27: 33.043564 | AC27: 34.375633 | AD27: 35.743801 | AE27: 0.049706
A28: Electric-Diesel Hybrid | B28: 0 | C28: 0 | D28: 0 | E28: 0 | F28: 0 | G28: 0 | H28: 0 | I28: 0 | J28: 0 | K28: 0 | L28: 0 | M28: 0 | N28: 0 | O28: 0 | P28: 0 | Q28: 0 | R28: 0 | S28: 0 | T28: 0 | U28: 0 | V28: 0 | W28: 0 | X28: 0 | Y28: 0 | Z28: 0 | AA28: 0 | AB28: 0 | AC28: 0 | AD28: 0 | AE28: --
A29: Electric-Gasoline Hybrid | B29: 223.61549 | C29: 216.07962 | D29: 210.16901 | E29: 203.94279 | F29: 198.138 | G29: 193.12856 | H29: 188.94823 | I29: 185.78183 | J29: 183.58957 | K29: 182.24689 | L29: 181.81209 | M29: 182.02373 | N29: 183.03459 | O29: 184.91509 | P29: 187.75081 | Q29: 191.07138 | R29: 194.74928 | S29: 198.696 | T29: 202.83295 | U29: 206.79274 | V29: 210.62627 | W29: 214.1521 | X29: 217.71721 | Y29: 221.63664 | Z29: 226.31955 | AA29: 230.77928 | AB29: 235.12669 | AC29: 239.49492 | AD29: 244.11679 | AE29: 0.003138
A30: Natural Gas ICE | B30: 11.524047 | C30: 10.680966 | D30: 9.790733 | E30: 8.885427 | F30: 7.990345 | G30: 7.103336 | H30: 6.237593 | I30: 5.428048 | J30: 4.758622 | K30: 4.129239 | L30: 3.577585 | M30: 3.107362 | N30: 2.721086 | O30: 2.399466 | P30: 2.138429 | Q30: 1.966115 | R30: 1.819323 | S30: 1.697581 | T30: 1.589439 | U30: 1.488186 | V30: 1.393384 | W30: 1.30462 | X30: 1.221511 | Y30: 1.143696 | Z30: 1.070839 | AA30: 1.002622 | AB30: 0.938752 | AC30: 0.87895 | AD30: 0.822958 | AE30: -0.089954
A31: Natural Gas Bi-fuel | B31: 0.307861 | C31: 0.264919 | D31: 0.239802 | E31: 0.224525 | F31: 0.210222 | G31: 0.19683 | H31: 0.184292 | I31: 0.172551 | J31: 0.161559 | K31: 0.151267 | L31: 0.141631 | M31: 0.132609 | N31: 0.124161 | O31: 0.116252 | P31: 0.108846 | Q31: 0.101912 | R31: 0.09542 | S31: 0.089341 | T31: 0.08365 | U31: 0.078321 | V31: 0.073332 | W31: 0.06866 | X31: 0.064286 | Y31: 0.060191 | Z31: 0.056357 | AA31: 0.052767 | AB31: 0.049405 | AC31: 0.046258 | AD31: 0.043311 | AE31: -0.067647
A32: Propane ICE | B32: 2.087991 | C32: 1.784609 | D32: 1.535312 | E32: 1.333347 | F32: 1.206512 | G32: 1.127065 | H32: 1.055267 | I32: 0.988043 | J32: 0.925101 | K32: 0.866168 | L32: 0.810991 | M32: 0.759328 | N32: 0.710956 | O32: 0.665665 | P32: 0.62326 | Q32: 0.583556 | R32: 0.546381 | S32: 0.511575 | T32: 0.478986 | U32: 0.448473 | V32: 0.419903 | W32: 0.393154 | X32: 0.368109 | Y32: 0.344659 | Z32: 0.322703 | AA32: 0.302145 | AB32: 0.282898 | AC32: 0.264876 | AD32: 0.248003 | AE32: -0.073267
A33: Propane Bi-fuel | B33: 4.082679 | C33: 3.480398 | D33: 2.97779 | E33: 2.565041 | F33: 2.283806 | G33: 2.108607 | H33: 1.959856 | I33: 1.835006 | J33: 1.718109 | K33: 1.60866 | L33: 1.506182 | M33: 1.410233 | N33: 1.320396 | O33: 1.236282 | P33: 1.157526 | Q33: 1.083788 | R33: 1.014747 | S33: 0.950104 | T33: 0.889579 | U33: 0.832909 | V33: 0.77985 | W33: 0.730171 | X33: 0.683656 | Y33: 0.640105 | Z33: 0.599328 | AA33: 0.561149 | AB33: 0.525401 | AC33: 0.491931 | AD33: 0.460594 | AE33: -0.074969
A34: Fuel Cell Methanol | B34: 0 | C34: 0 | D34: 0 | E34: 0 | F34: 0 | G34: 0 | H34: 0 | I34: 0 | J34: 0 | K34: 0 | L34: 0 | M34: 0 | N34: 0 | O34: 0 | P34: 0 | Q34: 0 | R34: 0 | S34: 0 | T34: 0 | U34: 0 | V34: 0 | W34: 0 | X34: 0 | Y34: 0 | Z34: 0 | AA34: 0 | AB34: 0 | AC34: 0 | AD34: 0 | AE34: --
A35: Fuel Cell Hydrogen | B35: 0.695658 | C35: 0.693525 | D35: 0.730931 | E35: 0.79699 | F35: 0.88554 | G35: 0.9894 | H35: 1.10531 | I35: 1.234237 | J35: 1.374475 | K35: 1.524476 | L35: 1.685228 | M35: 1.854181 | N35: 2.033293 | O35: 2.223712 | P35: 2.427094 | Q35: 2.639039 | R35: 2.858608 | S35: 3.08428 | T35: 3.314411 | U35: 3.544198 | V35: 3.773129 | W35: 3.997288 | X35: 4.220754 | Y35: 4.448301 | Z35: 4.688444 | AA35: 4.925473 | AB35: 5.161976 | AC35: 5.399414 | AD35: 5.639956 | AE35: 0.077606
A36: Total Alternative Cars | B36: 614.79175 | C36: 589.30566 | D36: 570.354 | E36: 553.77508 | F36: 539.66693 | G36: 528.7608 | H36: 520.82898 | I36: 516.4978 | J36: 515.59692 | K36: 517.65485 | L36: 522.89471 | M36: 530.58075 | N36: 541.01001 | O36: 554.33075 | P36: 570.88135 | Q36: 588.91223 | R36: 607.94379 | S36: 627.75415 | T36: 648.09857 | U36: 667.7262 | V36: 686.85071 | W36: 704.85486 | X36: 723.02039 | Y36: 742.51434 | Z36: 764.8316 | AA36: 786.33948 | AB36: 807.43066 | AC36: 828.60986 | AD36: 850.58197 | AE36: 0.011662
A38: Total Car Stock | B38: 5637.6074 | C38: 5226.8438 | D38: 4904.5322 | E38: 4614.4961 | F38: 4346.9219 | G38: 4110.2012 | H38: 3902.3667 | I38: 3723.6458 | J38: 3569.8223 | K38: 3437.054 | L38: 3324.9858 | M38: 3228.2822 | N38: 3148.9265 | O38: 3087.2471 | P38: 3044.1519 | Q38: 3010.9097 | R38: 2984.9126 | S38: 2964.5547 | T38: 2948.5417 | U38: 2931.5327 | V38: 2914.2422 | W38: 2894.3599 | X38: 2876.644 | Y38: 2864.8855 | Z38: 2863.6755 | AA38: 2860.3027 | AB38: 2855.9915 | AC38: 2852.3359 | AD38: 2852.1445 | AE38: -0.024042
A40: Light Truck Stock 1/
A41: Conventional Light Trucks
A42: Gasoline ICE Vehicles | B42: 7639.083 | C42: 7655.0962 | D42: 7760.314 | E42: 7895.3628 | F42: 8023.1143 | G42: 8127.6328 | H42: 8212.9814 | I42: 8290.5889 | J42: 8349.9736 | K42: 8394.4512 | L42: 8423.9824 | M42: 8440.4258 | N42: 8451.6865 | O42: 8465.3477 | P42: 8480.6543 | Q42: 8497.1035 | R42: 8516.1016 | S42: 8536.0273 | T42: 8559.6494 | U42: 8580.2031 | V42: 8599.4805 | W42: 8618.3643 | X42: 8635.5254 | Y42: 8659.0557 | Z42: 8680.4678 | AA42: 8702.9229 | AB42: 8720.7891 | AC42: 8742.2803 | AD42: 8768.0771 | AE42: 0.004935
A43: TDI Diesel ICE | B43: 60.55452 | C43: 54.813412 | D43: 48.998947 | E43: 43.883667 | F43: 39.715416 | G43: 35.790714 | H43: 32.023296 | I43: 28.420086 | J43: 24.994423 | K43: 21.770369 | L43: 18.758324 | M43: 15.995414 | N43: 13.487585 | O43: 11.270679 | P43: 9.33564 | Q43: 7.682456 | R43: 6.313601 | S43: 5.195662 | T43: 4.315732 | U43: 3.636456 | V43: 3.103021 | W43: 2.68296 | X43: 2.347914 | Y43: 2.093235 | Z43: 1.89311 | AA43: 1.714415 | AB43: 1.55453 | AC43: 1.411821 | AD43: 1.284441 | AE43: -0.128566
A44: Total Conventional Light Trucks | B44: 7699.6377 | C44: 7709.9097 | D44: 7809.313 | E44: 7939.2466 | F44: 8062.8296 | G44: 8163.4233 | H44: 8245.0049 | I44: 8319.0088 | J44: 8374.9678 | K44: 8416.2217 | L44: 8442.7412 | M44: 8456.4209 | N44: 8465.1738 | O44: 8476.6182 | P44: 8489.9902 | Q44: 8504.7861 | R44: 8522.415 | S44: 8541.2227 | T44: 8563.9648 | U44: 8583.8398 | V44: 8602.583 | W44: 8621.0469 | X44: 8637.873 | Y44: 8661.1484 | Z44: 8682.3613 | AA44: 8704.6377 | AB44: 8722.3438 | AC44: 8743.6924 | AD44: 8769.3613 | AE44: 0.004657
A46: Alternative-Fuel Light Trucks
A47: Ethanol-Flex Fuel ICE | B47: 1218.5098 | C47: 1120.8608 | D47: 1037.9226 | E47: 953.25147 | F47: 874.38513 | G47: 799.1477 | H47: 728.95618 | I47: 665.63318 | J47: 608.78552 | K47: 558.96545 | L47: 515.91949 | M47: 479.58041 | N47: 449.99478 | O47: 427.03122 | P47: 409.60956 | Q47: 396.73981 | R47: 387.82333 | S47: 381.65939 | T47: 377.57605 | U47: 374.55402 | V47: 372.48346 | W47: 371.24045 | X47: 370.60294 | Y47: 371.13873 | Z47: 371.85049 | AA47: 372.85184 | AB47: 373.50031 | AC47: 374.77466 | AD47: 376.6777 | AE47: -0.041062
A48: 100-Mile Electric Vehicle | B48: 0.402784 | C48: 0.424502 | D48: 0.4509 | E48: 0.475507 | F48: 0.495525 | G48: 0.511744 | H48: 0.524131 | I48: 0.533375 | J48: 0.539227 | K48: 0.542153 | L48: 0.542259 | M48: 0.539481 | N48: 0.534017 | O48: 0.526224 | P48: 0.516212 | Q48: 0.50371 | R48: 0.488581 | S48: 0.471082 | T48: 0.451541 | U48: 0.430114 | V48: 0.407183 | W48: 0.383066 | X48: 0.357975 | Y48: 0.33221 | Z48: 0.305866 | AA48: 0.279164 | AB48: 0.252075 | AC48: 0.224646 | AD48: 0.196857 | AE48: -0.025244
A49: 200-Mile Electric Vehicle | B49: 7.412667 | C49: 13.531482 | D49: 22.335041 | E49: 33.406113 | F49: 46.353321 | G49: 60.676521 | H49: 76.242645 | I49: 93.138985 | J49: 110.99479 | K49: 129.77493 | L49: 149.34218 | M49: 169.6248 | N49: 190.79437 | O49: 213.05165 | P49: 236.29544 | Q49: 260.44391 | R49: 285.51135 | S49: 311.33316 | T49: 338.00738 | U49: 365.09576 | V49: 392.64249 | W49: 420.65604 | X49: 449.01431 | Y49: 478.30362 | Z49: 507.88632 | AA49: 537.97443 | AB49: 568.08893 | AC49: 598.92822 | AD49: 630.58472 | AE49: 0.17198
A50: 300-Mile Electric Vehicle | B50: 4.682086 | C50: 6.222938 | D50: 8.134543 | E50: 10.340325 | F50: 12.714148 | G50: 15.219875 | H50: 17.849283 | I50: 20.622627 | J50: 23.482182 | K50: 26.428581 | L50: 29.444866 | M50: 32.522842 | N50: 35.698284 | O50: 39.007183 | P50: 42.437012 | Q50: 45.980495 | R50: 49.641651 | S50: 53.398613 | T50: 57.268452 | U50: 61.18808 | V50: 65.168549 | W50: 69.211052 | X50: 73.297386 | Y50: 77.51741 | Z50: 81.776482 | AA50: 86.10894 | AB50: 90.443428 | AC50: 94.884018 | AD50: 99.444466 | AE50: 0.115316
A51: Plug-in 20 Gasoline Hybrid | B51: 19.925865 | C51: 21.544413 | D51: 23.247982 | E51: 26.570223 | F51: 29.872574 | G51: 33.027237 | H51: 36.027607 | I51: 38.916355 | J51: 41.642071 | K51: 44.229752 | L51: 46.675167 | M51: 48.98344 | N51: 51.200951 | O51: 53.372917 | P51: 55.503918 | Q51: 57.604095 | R51: 59.697903 | S51: 61.78006 | T51: 63.879299 | U51: 65.963066 | V51: 68.048286 | W51: 70.14286 | X51: 72.239494 | Y51: 74.405258 | Z51: 76.580681 | AA51: 78.79007 | AB51: 80.991341 | AC51: 83.242905 | AD51: 85.554489 | AE51: 0.053418
A52: Plug-in 50 Gasoline Hybrid | B52: 1.216323 | C52: 1.800487 | D52: 2.66213 | E52: 3.815796 | F52: 5.275611 | G52: 6.958508 | H52: 8.842771 | I52: 10.92844 | J52: 13.17403 | K52: 15.571791 | L52: 18.100981 | M52: 20.747391 | N52: 23.521433 | O52: 26.438812 | P52: 29.488754 | Q52: 32.663853 | R52: 35.966309 | S52: 39.37788 | T52: 42.906147 | U52: 46.508396 | V52: 50.184578 | W52: 53.931499 | X52: 57.733253 | Y52: 61.64463 | Z52: 65.605125 | AA52: 69.635689 | AB52: 73.692322 | AC52: 77.833954 | AD52: 82.071625 | AE52: 0.162322
A53: Electric-Diesel Hybrid | B53: 0 | C53: 0 | D53: 0 | E53: 0 | F53: 0 | G53: 0 | H53: 0 | I53: 0 | J53: 0 | K53: 0 | L53: 0 | M53: 0 | N53: 0 | O53: 0 | P53: 0 | Q53: 0 | R53: 0 | S53: 0 | T53: 0 | U53: 0 | V53: 0 | W53: 0 | X53: 0 | Y53: 0 | Z53: 0 | AA53: 0 | AB53: 0 | AC53: 0 | AD53: 0 | AE53: --
A54: Electric-Gasoline Hybrid | B54: 135.86803 | C54: 160.33597 | D54: 184.47356 | E54: 209.81908 | F54: 234.51753 | G54: 257.46469 | H54: 278.54953 | I54: 298.11563 | J54: 315.83499 | K54: 331.87372 | L54: 346.20721 | M54: 358.90128 | N54: 370.3175 | O54: 380.79077 | P54: 390.40115 | Q54: 399.24509 | R54: 407.54202 | S54: 415.3074 | T54: 422.79144 | U54: 429.82556 | V54: 436.56516 | W54: 443.10947 | X54: 449.46088 | Y54: 456.09204 | Z54: 462.64462 | AA54: 469.25632 | AB54: 475.66361 | AC54: 482.26096 | AD54: 489.10043 | AE54: 0.046808
A55: Natural Gas ICE | B55: 2.839469 | C55: 2.640239 | D55: 2.471421 | E55: 2.307671 | F55: 2.148902 | G55: 1.994446 | H55: 1.851924 | I55: 1.735058 | J55: 1.626692 | K55: 1.521126 | L55: 1.420394 | M55: 1.324712 | N55: 1.23502 | O55: 1.150507 | P55: 1.071948 | Q55: 1.010057 | R55: 0.950586 | S55: 0.898791 | T55: 0.849829 | U55: 0.803543 | V55: 0.759786 | W55: 0.718421 | X55: 0.679315 | Y55: 0.642346 | Z55: 0.607395 | AA55: 0.574352 | AB55: 0.543113 | AC55: 0.513579 | AD55: 0.485657 | AE55: -0.061119
A56: Natural Gas Bi-fuel | B56: 2.185251 | C56: 2.015078 | D56: 1.904845 | E56: 1.800663 | F56: 1.702199 | G56: 1.609138 | H56: 1.521183 | I56: 1.438052 | J56: 1.35948 | K56: 1.285217 | L56: 1.215024 | M56: 1.148678 | N56: 1.085968 | O56: 1.026693 | P56: 0.970665 | Q56: 0.917705 | R56: 0.867645 | S56: 0.820325 | T56: 0.775595 | U56: 0.733312 | V56: 0.693342 | W56: 0.655559 | X56: 0.619842 | Y56: 0.586077 | Z56: 0.554158 | AA56: 0.523983 | AB56: 0.495457 | AC56: 0.468489 | AD56: 0.442995 | AE56: -0.055404
A57: Propane ICE | B57: 5.754653 | C57: 5.170995 | D57: 4.633657 | E57: 4.204803 | F57: 3.890476 | G57: 3.661827 | H57: 3.461627 | I57: 3.272411 | J57: 3.093574 | K57: 2.924544 | L57: 2.764783 | M57: 2.61378 | N57: 2.471052 | O57: 2.336146 | P57: 2.208631 | Q57: 2.0881 | R57: 1.97417 | S57: 1.866478 | T57: 1.764681 | U57: 1.668455 | V57: 1.577494 | W57: 1.49151 | X57: 1.410229 | Y57: 1.333392 | Z57: 1.260757 | AA57: 1.192091 | AB57: 1.127179 | AC57: 1.065813 | AD57: 1.0078 | AE57: -0.060327
A58: Propane Bi-fuel | B58: 5.126245 | C58: 4.726759 | D58: 4.468183 | E58: 4.223802 | F58: 3.992835 | G58: 3.774542 | H58: 3.568225 | I58: 3.373224 | J58: 3.188919 | K58: 3.014719 | L58: 2.850067 | M58: 2.69444 | N58: 2.547341 | O58: 2.4083 | P58: 2.276875 | Q58: 2.152647 | R58: 2.035221 | S58: 1.924223 | T58: 1.819299 | U58: 1.720117 | V58: 1.62636 | W58: 1.537732 | X58: 1.45395 | Y58: 1.374748 | Z58: 1.299876 | AA58: 1.229095 | AB58: 1.162182 | AC58: 1.098925 | AD58: 1.039122 | AE58: -0.055406
A59: Fuel Cell Methanol | B59: 0 | C59: 0 | D59: 0 | E59: 0 | F59: 0 | G59: 0 | H59: 0 | I59: 0 | J59: 0 | K59: 0 | L59: 0 | M59: 0 | N59: 0 | O59: 0 | P59: 0 | Q59: 0 | R59: 0 | S59: 0 | T59: 0 | U59: 0 | V59: 0 | W59: 0 | X59: 0 | Y59: 0 | Z59: 0 | AA59: 0 | AB59: 0 | AC59: 0 | AD59: 0 | AE59: --
A60: Fuel Cell Hydrogen | B60: 0.002034 | C60: 0.006205 | D60: 0.012722 | E60: 0.0217 | F60: 0.033009 | G60: 0.046429 | H60: 0.061843 | I60: 0.079235 | J60: 0.098309 | K60: 0.118946 | L60: 0.140962 | M60: 0.164185 | N60: 0.188612 | O60: 0.214285 | P60: 0.241124 | Q60: 0.269074 | R60: 0.298147 | S60: 0.328241 | T60: 0.359404 | U60: 0.391358 | V60: 0.424089 | W60: 0.45757 | X60: 0.491682 | Y60: 0.526757 | Z60: 0.562411 | AA60: 0.598777 | AB60: 0.635567 | AC60: 0.67315 | AD60: 0.711608 | AE60: 0.232694
A61: Total Alternative Light Trucks | B61: 1403.9254 | C61: 1339.2802 | D61: 1292.7174 | E61: 1250.2372 | F61: 1215.3812 | G61: 1184.0927 | H61: 1157.457 | I61: 1137.7867 | J61: 1123.8199 | K61: 1116.2509 | L61: 1114.6233 | M61: 1118.8455 | N61: 1129.5892 | O61: 1147.3549 | P61: 1171.0212 | Q61: 1199.6185 | R61: 1232.7968 | S61: 1269.1655 | T61: 1308.4491 | U61: 1348.8818 | V61: 1390.5808 | W61: 1433.535 | X61: 1477.3615 | Y61: 1523.8972 | Z61: 1570.9343 | AA61: 1619.0146 | AB61: 1666.5957 | AC61: 1715.9692 | AD61: 1767.3174 | AE61: 0.008255
A63: Total Light Truck Stock | B63: 9103.5635 | C63: 9049.1895 | D63: 9102.0303 | E63: 9189.4834 | F63: 9278.2109 | G63: 9347.5156 | H63: 9402.4619 | I63: 9456.7959 | J63: 9498.7881 | K63: 9532.4727 | L63: 9557.3643 | M63: 9575.2666 | N63: 9594.7627 | O63: 9623.9727 | P63: 9661.0117 | Q63: 9704.4043 | R63: 9755.2119 | S63: 9810.3887 | T63: 9872.4141 | U63: 9932.7217 | V63: 9993.1641 | W63: 10054.582 | X63: 10115.234 | Y63: 10185.046 | Z63: 10253.296 | AA63: 10323.652 | AB63: 10388.939 | AC63: 10459.662 | AD63: 10536.679 | AE63: 0.005235
A65: Total Fleet Vehicles | B65: 14741.171 | C65: 14276.033 | D65: 14006.562 | E65: 13803.979 | F65: 13625.133 | G65: 13457.717 | H65: 13304.828 | I65: 13180.441 | J65: 13068.61 | K65: 12969.526 | L65: 12882.35 | M65: 12803.549 | N65: 12743.689 | O65: 12711.22 | P65: 12705.164 | Q65: 12715.314 | R65: 12740.125 | S65: 12774.943 | T65: 12820.956 | U65: 12864.254 | V65: 12907.406 | W65: 12948.941 | X65: 12991.879 | Y65: 13049.932 | Z65: 13116.972 | AA65: 13183.955 | AB65: 13244.931 | AC65: 13311.998 | AD65: 13388.823 | AE65: -0.003431
A67: Commercial Light Truck Stock 2/
A68: Motor Gasoline | B68: 8031.3188 | C68: 7940.3721 | D68: 7903.7354 | E68: 7909.8018 | F68: 7940.8301 | G68: 7987.8506 | H68: 8042.6831 | I68: 8101.8809 | J68: 8168.1221 | K68: 8235.2178 | L68: 8306.8525 | M68: 8373.7109 | N68: 8435.4941 | O68: 8494.0547 | P68: 8552.7588 | Q68: 8606.1826 | R68: 8658.1016 | S68: 8711.0576 | T68: 8762.5674 | U68: 8814.5947 | V68: 8864.6865 | W68: 8916.5879 | X68: 8972.7021 | Y68: 9027.6074 | Z68: 9080.1377 | AA68: 9132.8711 | AB68: 9182.998 | AC68: 9228.2012 | AD68: 9269.6211 | AE68: 0.005134
A69: Diesel | B69: 5201.8086 | C69: 5250.897 | D69: 5302.2627 | E69: 5353.2271 | F69: 5399.2612 | G69: 5437.2954 | H69: 5468.6099 | I69: 5492.0894 | J69: 5507.6777 | K69: 5512.2534 | L69: 5521.1802 | M69: 5519.0474 | N69: 5513.2485 | O69: 5500.6274 | P69: 5486.0024 | Q69: 5469.0234 | R69: 5449.0186 | S69: 5431.8198 | T69: 5414.2065 | U69: 5406.397 | V69: 5405.3071 | W69: 5420.1104 | X69: 5445.6807 | Y69: 5472.603 | Z69: 5500.2749 | AA69: 5530.6382 | AB69: 5561.6924 | AC69: 5585.7549 | AD69: 5608.0508 | AE69: 0.002689
A70: Propane | B70: 0.0272 | C70: 0.446405 | D70: 0.885205 | E70: 1.334503 | F70: 1.804604 | G70: 2.297728 | H70: 2.818901 | I70: 3.37659 | J70: 3.979535 | K70: 4.63974 | L70: 5.36918 | M70: 6.179323 | N70: 7.085126 | O70: 8.108479 | P70: 9.276356 | Q70: 10.613518 | R70: 12.144465 | S70: 13.896809 | T70: 15.894682 | U70: 18.155231 | V70: 20.693428 | W70: 23.531113 | X70: 26.681091 | Y70: 30.170033 | Z70: 33.996666 | AA70: 38.143761 | AB70: 42.573021 | AC70: 47.273495 | AD70: 52.222855 | AE70: 0.309968
A71: Compressed/Liquefied Natural Gas | B71: 12.657215 | C71: 12.253946 | D71: 11.837053 | E71: 11.405747 | F71: 10.958616 | G71: 10.497103 | H71: 10.004997 | I71: 9.502007 | J71: 8.96981 | K71: 8.417904 | L71: 7.827207 | M71: 7.176929 | N71: 6.57033 | O71: 6.001122 | P71: 5.468161 | Q71: 4.972802 | R71: 4.512303 | S71: 4.093148 | T71: 3.71057 | U71: 3.361499 | V71: 3.043814 | W71: 2.755612 | X71: 2.494757 | Y71: 2.250751 | Z71: 1.967801 | AA71: 1.629623 | AB71: 1.333248 | AC71: 1.052214 | AD71: 0.836617 | AE71: -0.092464
A72: Ethanol-Flex Fuel | B72: 1568.9006 | C72: 1592.0657 | D72: 1617.6141 | E72: 1642.8894 | F72: 1666.8478 | G72: 1689.6023 | H72: 1709.5068 | I72: 1727.177 | J72: 1742.9712 | K72: 1757.8314 | L72: 1771.9937 | M72: 1785.913 | N72: 1799.8901 | O72: 1814.8966 | P72: 1830.9843 | Q72: 1848.5692 | R72: 1867.8733 | S72: 1889.3264 | T72: 1913.0802 | U72: 1938.9139 | V72: 1966.855 | W72: 1997.0092 | X72: 2025.7972 | Y72: 2053.8918 | Z72: 2081.9648 | AA72: 2106.8191 | AB72: 2130.8447 | AC72: 2151.365 | AD72: 2171.7822 | AE72: 0.011681
A73: Electric | B73: 0 | C73: 0 | D73: 0 | E73: 0 | F73: 0 | G73: 0 | H73: 0 | I73: 0 | J73: 0 | K73: 0 | L73: 0 | M73: 0 | N73: 0 | O73: 0 | P73: 0 | Q73: 0 | R73: 0 | S73: 0 | T73: 0 | U73: 0 | V73: 0 | W73: 0 | X73: 0 | Y73: 0 | Z73: 0 | AA73: 0 | AB73: 0 | AC73: 0 | AD73: 0 | AE73: --
A74: Plug-in Gasoline Hybrid | B74: 0 | C74: 0.787767 | D74: 1.587929 | E74: 2.39666 | F74: 3.208523 | G74: 4.027426 | H74: 4.860145 | I74: 5.716928 | J74: 6.601765 | K74: 7.519146 | L74: 8.476849 | M74: 9.480237 | N74: 10.536694 | O74: 11.657214 | P74: 12.856302 | Q74: 14.143478 | R74: 15.531952 | S74: 17.031109 | T74: 18.651724 | U74: 20.389593 | V74: 22.245596 | W74: 24.213247 | X74: 26.284992 | Y74: 28.463531 | Z74: 30.733688 | AA74: 33.074711 | AB74: 35.461926 | AC74: 37.891819 | AD74: 40.35284 | AE74: --
A75: Plug-in Diesel Hybrid | B75: 0 | C75: 0.855433 | D75: 1.733762 | E75: 2.60653 | F75: 3.472551 | G75: 4.333529 | H75: 5.192794 | I75: 6.061743 | J75: 6.950156 | K75: 7.87124 | L75: 8.836157 | M75: 9.855454 | N75: 10.940022 | O75: 12.10994 | P75: 13.379708 | Q75: 14.764685 | R75: 16.280159 | S75: 17.941574 | T75: 19.761744 | U75: 21.739498 | V75: 23.87665 | W75: 26.169352 | X75: 28.600906 | Y75: 31.175287 | Z75: 33.863022 | AA75: 36.644165 | AB75: 39.482059 | AC75: 42.376591 | AD75: 45.30611 | AE75: --
A76: Fuel Cell | B76: 0 | C76: 0 | D76: 0 | E76: 0 | F76: 0 | G76: 0 | H76: 0 | I76: 0 | J76: 0 | K76: 0 | L76: 0 | M76: 0 | N76: 0 | O76: 0 | P76: 0 | Q76: 0 | R76: 0 | S76: 0 | T76: 0 | U76: 0 | V76: 0 | W76: 0 | X76: 0 | Y76: 0 | Z76: 0 | AA76: 0 | AB76: 0 | AC76: 0 | AD76: 0 | AE76: --
A77: Total Commercial Light Truck Stock | B77: 14814.712 | C77: 14797.679 | D77: 14839.655 | E77: 14923.662 | F77: 15026.385 | G77: 15135.905 | H77: 15243.677 | I77: 15345.805 | J77: 15445.272 | K77: 15533.75 | L77: 15630.535 | M77: 15711.363 | N77: 15783.765 | O77: 15847.455 | P77: 15910.727 | Q77: 15968.27 | R77: 16023.463 | S77: 16085.165 | T77: 16147.872 | U77: 16223.552 | V77: 16306.708 | W77: 16410.377 | X77: 16528.242 | Y77: 16646.162 | Z77: 16762.939 | AA77: 16879.82 | AB77: 16994.387 | AC77: 17093.916 | AD77: 17188.174 | AE77: 0.005321
A79: 1/ Includes all fleets of 10 or more.
A80: 2/ Commercial trucks from 8,501 to 10,000 pounds.
A81: ICE = Internal combustion engine.
A82: TDI = Turbocharged direct injection
A83: - - = Not applicable.
A84: Note: Totals may not equal sum of components due to independent rounding.
A85: Data source: U.S. Energy Information Administration, AEO2023 National Energy Modeling System run ref2023.d020623a.
AE109: Average

Sheet Table 49
B1: ref2023.d020623a | C1: 2022 | D1: 2023 | E1: 2024 | F1: 2025 | G1: 2026 | H1: 2027 | I1: 2028 | J1: 2029 | K1: 2030 | L1: 2031 | M1: 2032 | N1: 2033 | O1: 2034 | P1: 2035 | Q1: 2036 | R1: 2037 | S1: 2038 | T1: 2039 | U1: 2040 | V1: 2041 | W1: 2042 | X1: 2043 | Y1: 2044 | Z1: 2045 | AA1: 2046 | AB1: 2047 | AC1: 2048 | AD1: 2049 | AE1: 2050
C3: Report | D3: Annual Energy Outlook 2023
C4: Scenario | D4: ref2023 | G4: Reference
C5: Datekey | D5: d020623a
C6: Release Date | E6: March 2023
A10: FTE000 | B10: 49. Freight Transportation Energy Use | AF10: Annual
AF11: Change
AF12: 2022–2050
B13: Technology and Fuel Type | C13: 2022 | D13: 2023 | E13: 2024 | F13: 2025 | G13: 2026 | H13: 2027 | I13: 2028 | J13: 2029 | K13: 2030 | L13: 2031 | M13: 2032 | N13: 2033 | O13: 2034 | P13: 2035 | Q13: 2036 | R13: 2037 | S13: 2038 | T13: 2039 | U13: 2040 | V13: 2041 | W13: 2042 | X13: 2043 | Y13: 2044 | Z13: 2045 | AA13: 2046 | AB13: 2047 | AC13: 2048 | AD13: 2049 | AE13: 2050 | AF13: 2050
B15: Freight Truck Stock by Size Class 1/
B17: Vehicle Miles Traveled (billion miles)
B18: Light Medium
A19: FTE000:lm_vmt_stk_Dies | B19: Diesel | C19: 54.392624 | D19: 53.187412 | E19: 52.529724 | F19: 52.479733 | G19: 52.720959 | H19: 52.851051 | I19: 52.993168 | J19: 53.175175 | K19: 53.566818 | L19: 54.220245 | M19: 55.079853 | N19: 55.840675 | O19: 56.638935 | P19: 57.504395 | Q19: 58.304447 | R19: 59.176174 | S19: 60.063702 | T19: 61.000946 | U19: 62.044392 | V19: 63.120777 | W19: 64.186768 | X19: 65.249405 | Y19: 66.318535 | Z19: 67.468948 | AA19: 68.816582 | AB19: 70.243614 | AC19: 71.603302 | AD19: 73.056641 | AE19: 74.77961 | AF19: 0.011433
A20: FTE000:lm_vmt_stk_Gas | B20: Motor Gasoline | C20: 16.846205 | D20: 17.761892 | E20: 18.76346 | F20: 19.899122 | G20: 21.083855 | H20: 22.151054 | I20: 23.138805 | J20: 24.075592 | K20: 25.031351 | L20: 26.026825 | M20: 27.096857 | N20: 28.109198 | O20: 29.09211 | P20: 30.063576 | Q20: 30.988947 | R20: 31.943773 | S20: 32.87841 | T20: 33.782879 | U20: 34.707161 | V20: 35.65567 | W20: 36.558773 | X20: 37.368587 | Y20: 38.121651 | Z20: 38.871418 | AA20: 39.695541 | AB20: 40.532322 | AC20: 41.299179 | AD20: 42.100204 | AE20: 43.049957 | AF20: 0.034076
A21: FTE000:lm_vmt_stk_Liq | B21: Propane | C21: 0.000585 | D21: 0.007631 | E21: 0.014685 | F21: 0.021224 | G21: 0.027498 | H21: 0.033387 | I21: 0.038968 | J21: 0.044345 | K21: 0.049704 | L21: 0.055248 | M21: 0.061056 | N21: 0.066844 | O21: 0.072697 | P21: 0.078774 | Q21: 0.085074 | R21: 0.091911 | S21: 0.099268 | T21: 0.107287 | U21: 0.116186 | V21: 0.125999 | W21: 0.136618 | X21: 0.148055 | Y21: 0.160189 | Z21: 0.173373 | AA21: 0.188008 | AB21: 0.203789 | AC21: 0.220242 | AD21: 0.237737 | AE21: 0.256857 | AF21: 0.242756
A22: FTE000:lm_vmt_stk_NGas | B22: Compressed/Liquefied Natural Gas | C22: 0.015418 | D22: 0.013986 | E22: 0.012747 | F22: 0.011705 | G22: 0.010794 | H22: 0.00993 | I22: 0.00913 | J22: 0.008393 | K22: 0.007732 | L22: 0.007146 | M22: 0.006624 | N22: 0.006093 | O22: 0.005543 | P22: 0.004963 | Q22: 0.004369 | R22: 0.003744 | S22: 0.003165 | T22: 0.002637 | U22: 0.002105 | V22: 0.001683 | W22: 0.001373 | X22: 0.001147 | Y22: 0.001 | Z22: 0.000899 | AA22: 0.00082 | AB22: 0.000769 | AC22: 0.000703 | AD22: 0.000625 | AE22: 0.000529 | AF22: -0.113488
A23: FTE000:lm_vmt_stk_eff | B23: Ethanol-Flex Fuel | C23: 3.793104 | D23: 3.733989 | E23: 3.701197 | F23: 3.694834 | G23: 3.705554 | H23: 3.713322 | I23: 3.722355 | J23: 3.737602 | K23: 3.763645 | L23: 3.807043 | M23: 3.864232 | N23: 3.914667 | O23: 3.947316 | P23: 3.968468 | Q23: 3.971855 | R23: 3.975454 | S23: 3.964083 | T23: 3.953435 | U23: 3.955495 | V23: 3.973439 | W23: 4.000788 | X23: 4.04146 | Y23: 4.095368 | Z23: 4.15557 | AA23: 4.225757 | AB23: 4.299688 | AC23: 4.36784 | AD23: 4.436968 | AE23: 4.51719 | AF23: 0.006259
A24: FTE000:lm_vmt_stk_elec | B24: Electric | C24: 0.000803 | D24: 0.000726 | E24: 0.000665 | F24: 0.000618 | G24: 0.000584 | H24: 0.000557 | I24: 0.000536 | J24: 0.000504 | K24: 0.000463 | L24: 0.000425 | M24: 0.000392 | N24: 0.00033 | O24: 0.00026 | P24: 0.000205 | Q24: 0.000161 | R24: 0.000126 | S24: 9.9e-05 | T24: 7.7e-05 | U24: 6.9e-05 | V24: 6.7e-05 | W24: 6.6e-05 | X24: 6.4e-05 | Y24: 5.2e-05 | Z24: 3.6e-05 | AA24: 2.6e-05 | AB24: 1.8e-05 | AC24: 1.3e-05 | AD24: 9e-06 | AE24: 6e-06 | AF24: -0.159098
A25: FTE000:lm_vmt_stk_pidh | B25: Plug-in Diesel Hybrid | C25: 0 | D25: 0.005791 | E25: 0.011641 | F25: 0.017745 | G25: 0.024024 | H25: 0.030277 | I25: 0.036508 | J25: 0.042765 | K25: 0.049185 | L25: 0.055924 | M25: 0.063112 | N25: 0.070484 | O25: 0.078226 | P25: 0.086534 | Q25: 0.095422 | R25: 0.105274 | S25: 0.116181 | T25: 0.128332 | U25: 0.142063 | V25: 0.157389 | W25: 0.174051 | X25: 0.191836 | Y25: 0.210715 | Z25: 0.230889 | AA25: 0.252466 | AB25: 0.274962 | AC25: 0.297693 | AD25: 0.321199 | AE25: 0.346224 | AF25: --
A26: FTE000:lm_vmt_stk_pigh | B26: Plug-in Gasoline Hybrid | C26: 0 | D26: 0.006025 | E26: 0.012129 | F26: 0.018395 | G26: 0.024749 | H26: 0.030966 | I26: 0.037011 | J26: 0.042946 | K26: 0.048956 | L26: 0.055274 | M26: 0.06205 | N26: 0.069098 | O26: 0.076634 | P26: 0.084903 | Q26: 0.093932 | R26: 0.104143 | S26: 0.115635 | T26: 0.12865 | U26: 0.143532 | V26: 0.160333 | W26: 0.178793 | X26: 0.198736 | Y26: 0.21998 | Z26: 0.242805 | AA26: 0.267198 | AB26: 0.292703 | AC26: 0.318521 | AD26: 0.345285 | AE26: 0.373702 | AF26: --
A27: FTE000:lm_vmt_stk_cell | B27: Fuel Cell | C27: 0 | D27: 0 | E27: 2e-06 | F27: 4e-06 | G27: 6e-06 | H27: 8e-06 | I27: 1e-05 | J27: 1.1e-05 | K27: 1.3e-05 | L27: 1.5e-05 | M27: 1.7e-05 | N27: 1.8e-05 | O27: 2e-05 | P27: 2.1e-05 | Q27: 2.2e-05 | R27: 2.3e-05 | S27: 2.4e-05 | T27: 2.5e-05 | U27: 2.6e-05 | V27: 2.7e-05 | W27: 2.8e-05 | X27: 2.8e-05 | Y27: 2.8e-05 | Z27: 2.9e-05 | AA27: 2.9e-05 | AB27: 2.8e-05 | AC27: 2.8e-05 | AD27: 2.7e-05 | AE27: 2.7e-05 | AF27: --
A28: FTE000:lm_vmt_stk_total | B28: Light Medium Subtotal | C28: 75.048714 | D28: 74.717514 | E28: 75.046082 | F28: 76.143509 | G28: 77.598 | H28: 78.820419 | I28: 79.976402 | J28: 81.127167 | K28: 82.517715 | L28: 84.228111 | M28: 86.234123 | N28: 88.07753 | O28: 89.911659 | P28: 91.791748 | Q28: 93.544197 | R28: 95.400566 | S28: 97.240463 | T28: 99.104271 | U28: 101.111 | V28: 103.19528 | W28: 105.2371 | X28: 107.19923 | Y28: 109.12768 | Z28: 111.1437 | AA28: 113.44614 | AB28: 115.84798 | AC28: 118.10761 | AD28: 120.49865 | AE28: 123.32388 | AF28: 0.017897
B29: Medium
A30: FTE000:ca_Diesel | B30: Diesel | C30: 39.558544 | D30: 39.337627 | E30: 39.299656 | F30: 39.581608 | G30: 40.110664 | H30: 40.671707 | I30: 41.263809 | J30: 41.765324 | K30: 42.233723 | L30: 42.75589 | M30: 43.429985 | N30: 44.019016 | O30: 44.583286 | P30: 45.18047 | Q30: 45.736732 | R30: 46.355183 | S30: 46.957836 | T30: 47.563808 | U30: 48.222565 | V30: 48.907677 | W30: 49.5737 | X30: 50.240974 | Y30: 50.887699 | Z30: 51.487984 | AA30: 52.142113 | AB30: 52.823296 | AC30: 53.454895 | AD30: 54.11842 | AE30: 54.955475 | AF30: 0.01181
A31: FTE000:ca_Gasoline | B31: Motor Gasoline | C31: 19.487116 | D31: 19.215473 | E31: 19.072891 | F31: 19.059853 | G31: 19.182478 | H31: 19.313581 | I31: 19.47892 | J31: 19.629051 | K31: 19.775127 | L31: 19.949099 | M31: 20.21559 | N31: 20.442692 | O31: 20.670752 | P31: 20.9112 | Q31: 21.112675 | R31: 21.367302 | S31: 21.576696 | T31: 21.845287 | U31: 22.11479 | V31: 22.415617 | W31: 22.714939 | X31: 23.016796 | Y31: 23.311953 | Z31: 23.583118 | AA31: 23.878855 | AB31: 24.179132 | AC31: 24.450663 | AD31: 24.739687 | AE31: 25.09705 | AF31: 0.009077
A32: FTE000:ca_LiquefiedPetr | B32: Propane | C32: 0.035519 | D32: 0.036849 | E32: 0.0383 | F32: 0.039928 | G32: 0.041891 | H32: 0.043984 | I32: 0.046242 | J32: 0.048501 | K32: 0.050945 | L32: 0.053743 | M32: 0.057158 | N32: 0.061107 | O32: 0.065479 | P32: 0.069911 | Q32: 0.074638 | R32: 0.079953 | S32: 0.085782 | T32: 0.092219 | U32: 0.099416 | V32: 0.107424 | W32: 0.115934 | X32: 0.124888 | Y32: 0.134116 | Z32: 0.143486 | AA32: 0.153252 | AB32: 0.163224 | AC32: 0.173081 | AD32: 0.182492 | AE32: 0.192533 | AF32: 0.062223
A33: FTE000:ca_CompressedNat | B33: Compressed/Liquefied Natural Gas | C33: 0.040711 | D33: 0.038744 | E33: 0.036801 | F33: 0.035049 | G33: 0.033437 | H33: 0.031726 | I33: 0.030068 | J33: 0.028327 | K33: 0.026554 | L33: 0.024896 | M33: 0.023395 | N33: 0.021886 | O33: 0.020384 | P33: 0.018924 | Q33: 0.017501 | R33: 0.01624 | S33: 0.015091 | T33: 0.014094 | U33: 0.01316 | V33: 0.012222 | W33: 0.01138 | X33: 0.010424 | Y33: 0.00945 | Z33: 0.008636 | AA33: 0.007954 | AB33: 0.007266 | AC33: 0.006568 | AD33: 0.005938 | AE33: 0.005415 | AF33: -0.069514
A34: FTE000:ca_ethanolflex | B34: Ethanol-Flex Fuel | C34: 0.567986 | D34: 0.597828 | E34: 0.637764 | F34: 0.685371 | G34: 0.742963 | H34: 0.808578 | I34: 0.879891 | J34: 0.955174 | K34: 1.036787 | L34: 1.129257 | M34: 1.237243 | N34: 1.355722 | O34: 1.486297 | P34: 1.627784 | Q34: 1.769562 | R34: 1.919661 | S34: 2.070964 | T34: 2.223877 | U34: 2.384504 | V34: 2.545784 | W34: 2.705446 | X34: 2.862837 | Y34: 3.012749 | Z34: 3.155075 | AA34: 3.292932 | AB34: 3.426188 | AC34: 3.547679 | AD34: 3.667386 | AE34: 3.793095 | AF34: 0.070168
A35: FTE000:ca_electric | B35: Electric | C35: 0.004799 | D35: 0.005708 | E35: 0.006401 | F35: 0.006945 | G35: 0.007371 | H35: 0.007662 | I35: 0.007837 | J35: 0.007902 | K35: 0.007887 | L35: 0.007822 | M35: 0.007727 | N35: 0.007575 | O35: 0.007374 | P35: 0.00716 | Q35: 0.006879 | R35: 0.006576 | S35: 0.006319 | T35: 0.006056 | U35: 0.005758 | V35: 0.005468 | W35: 0.005185 | X35: 0.00491 | Y35: 0.004645 | Z35: 0.004391 | AA35: 0.004158 | AB35: 0.003937 | AC35: 0.003723 | AD35: 0.003516 | AE35: 0.003332 | AF35: -0.012949
A36: FTE000:ca_plugindiesel | B36: Plug-in Diesel Hybrid | C36: 0 | D36: 0 | E36: 0.00483 | F36: 0.009332 | G36: 0.013625 | H36: 0.017784 | I36: 0.021821 | J36: 0.025634 | K36: 0.029242 | L36: 0.032781 | M36: 0.03644 | N36: 0.040144 | O36: 0.043931 | P36: 0.047813 | Q36: 0.051763 | R36: 0.055931 | S36: 0.060281 | T36: 0.064887 | U36: 0.06992 | V36: 0.075448 | W36: 0.081417 | X36: 0.087566 | Y36: 0.094056 | Z36: 0.100833 | AA36: 0.108103 | AB36: 0.115766 | AC36: 0.123626 | AD36: 0.131829 | AE36: 0.140711 | AF36: --
A37: FTE000:ca_plugingasolin | B37: Plug-in Gasoline Hybrid | C37: 0 | D37: 0 | E37: 0.004699 | F37: 0.008982 | G37: 0.013004 | H37: 0.016833 | I37: 0.020468 | J37: 0.023865 | K37: 0.027097 | L37: 0.030357 | M37: 0.033845 | N37: 0.037534 | O37: 0.041471 | P37: 0.045675 | Q37: 0.050146 | R37: 0.055067 | S37: 0.060408 | T37: 0.066288 | U37: 0.07291 | V37: 0.080391 | W37: 0.088689 | X37: 0.097593 | Y37: 0.107179 | Z37: 0.117361 | AA37: 0.128284 | AB37: 0.139872 | AC37: 0.151817 | AD37: 0.164304 | AE37: 0.177619 | AF37: --
A38: FTE000:ca_fuelcell | B38: Fuel Cell | C38: 0 | D38: 0 | E38: 0.008078 | F38: 0.015645 | G38: 0.022989 | H38: 0.030179 | I38: 0.037161 | J38: 0.043795 | K38: 0.050102 | L38: 0.056295 | M38: 0.06264 | N38: 0.068956 | O38: 0.075354 | P38: 0.081949 | Q38: 0.088664 | R38: 0.095808 | S38: 0.103379 | T38: 0.111517 | U38: 0.120537 | V38: 0.130567 | W38: 0.141523 | X38: 0.152972 | Y38: 0.165171 | Z38: 0.178007 | AA38: 0.191833 | AB38: 0.206467 | AC38: 0.221546 | AD38: 0.23731 | AE38: 0.254356 | AF38: --
A39: FTE000:ca_MediumSubtota | B39: Medium Subtotal | C39: 59.694576 | D39: 59.232098 | E39: 59.109398 | F39: 59.442654 | G39: 60.168362 | H39: 60.942036 | I39: 61.78616 | J39: 62.527435 | K39: 63.237366 | L39: 64.040108 | M39: 65.104019 | N39: 66.054314 | O39: 66.994217 | P39: 67.990768 | Q39: 68.908279 | R39: 69.951363 | S39: 70.936752 | T39: 71.987885 | U39: 73.103226 | V39: 74.280495 | W39: 75.437996 | X39: 76.598991 | Y39: 77.726692 | Z39: 78.778595 | AA39: 79.907219 | AB39: 81.064888 | AC39: 82.133057 | AD39: 83.250366 | AE39: 84.619041 | AF39: 0.012539
B40: Heavy
A41: FTE000:da_Diesel | B41: Diesel | C41: 184.85648 | D41: 184.3631 | E41: 184.53233 | F41: 185.92311 | G41: 188.09622 | H41: 189.92868 | I41: 191.46675 | J41: 192.31586 | K41: 192.75873 | L41: 193.26146 | M41: 194.18498 | N41: 194.74161 | O41: 195.21269 | P41: 195.78941 | Q41: 196.09772 | R41: 196.64531 | S41: 197.17789 | T41: 197.58701 | U41: 198.11809 | V41: 198.71742 | W41: 199.2968 | X41: 199.71181 | Y41: 199.91617 | Z41: 199.88377 | AA41: 199.97646 | AB41: 200.03841 | AC41: 199.82256 | AD41: 199.67621 | AE41: 200.11252 | AF41: 0.002836
A42: FTE000:da_Gasoline | B42: Motor Gasoline | C42: 0.177811 | D42: 0.177786 | E42: 0.180963 | F42: 0.186843 | G42: 0.196174 | H42: 0.207373 | I42: 0.219367 | J42: 0.231142 | K42: 0.243587 | L42: 0.255892 | M42: 0.268135 | N42: 0.279295 | O42: 0.289438 | P42: 0.298673 | Q42: 0.30595 | R42: 0.31252 | S42: 0.317911 | T42: 0.322673 | U42: 0.327547 | V42: 0.332211 | W42: 0.335203 | X42: 0.337378 | Y42: 0.339952 | Z42: 0.342462 | AA42: 0.345487 | AB42: 0.348537 | AC42: 0.351078 | AD42: 0.353734 | AE42: 0.357393 | AF42: 0.025246
A43: FTE000:da_LiquefiedPetr | B43: Propane | C43: 0.027641 | D43: 0.030197 | E43: 0.032636 | F43: 0.034937 | G43: 0.037206 | H43: 0.039183 | I43: 0.040809 | J43: 0.041921 | K43: 0.042711 | L43: 0.043318 | M43: 0.043885 | N43: 0.044439 | O43: 0.045072 | P43: 0.045765 | Q43: 0.046311 | R43: 0.046866 | S43: 0.047248 | T43: 0.047567 | U43: 0.047885 | V43: 0.048297 | W43: 0.048665 | X43: 0.048979 | Y43: 0.049225 | Z43: 0.049414 | AA43: 0.049661 | AB43: 0.04992 | AC43: 0.050113 | AD43: 0.050276 | AE43: 0.05053 | AF43: 0.021778
A44: FTE000:da_CompressedNat | B44: Compressed/Liquefied Natural Gas | C44: 2.145453 | D44: 2.194808 | E44: 2.238753 | F44: 2.28101 | G44: 2.317616 | H44: 2.333008 | I44: 2.330277 | J44: 2.307991 | K44: 2.27358 | L44: 2.243996 | M44: 2.231564 | N44: 2.234868 | O44: 2.258435 | P44: 2.300837 | Q44: 2.354893 | R44: 2.425728 | S44: 2.508595 | T44: 2.603091 | U44: 2.713572 | V44: 2.839585 | W44: 2.975951 | X44: 3.121336 | Y44: 3.273978 | Z44: 3.43134 | AA44: 3.599105 | AB44: 3.776055 | AC44: 3.954944 | AD44: 4.142594 | AE44: 4.352327 | AF44: 0.025585
A45: FTE000:da_ethanolflex | B45: Ethanol-Flex Fuel | C45: 0 | D45: 0 | E45: 0 | F45: 0 | G45: 0 | H45: 0 | I45: 0 | J45: 0 | K45: 0 | L45: 0 | M45: 0 | N45: 0 | O45: 0 | P45: 0 | Q45: 0 | R45: 0 | S45: 0 | T45: 0 | U45: 0 | V45: 0 | W45: 0 | X45: 0 | Y45: 0 | Z45: 0 | AA45: 0 | AB45: 0 | AC45: 0 | AD45: 0 | AE45: 0 | AF45: --
A46: FTE000:da_electric | B46: Electric | C46: 0.004264 | D46: 0.004962 | E46: 0.005559 | F46: 0.006088 | G46: 0.006551 | H46: 0.006912 | I46: 0.007172 | J46: 0.007324 | K46: 0.007383 | L46: 0.007367 | M46: 0.007284 | N46: 0.007108 | O46: 0.006863 | P46: 0.006574 | Q46: 0.006244 | R46: 0.005922 | S46: 0.005604 | T46: 0.005244 | U46: 0.004876 | V46: 0.00456 | W46: 0.004299 | X46: 0.00403 | Y46: 0.003785 | Z46: 0.00356 | AA46: 0.003357 | AB46: 0.00317 | AC46: 0.002991 | AD46: 0.002826 | AE46: 0.002681 | AF46: -0.016431
A47: FTE000:da_plugindiesel | B47: Plug-in Diesel Hybrid | C47: 0 | D47: 0 | E47: 0.001246 | F47: 0.00243 | G47: 0.0036 | H47: 0.004779 | I47: 0.00597 | J47: 0.007146 | K47: 0.00831 | L47: 0.009483 | M47: 0.010697 | N47: 0.011908 | O47: 0.013111 | P47: 0.014297 | Q47: 0.015442 | R47: 0.016583 | S47: 0.017702 | T47: 0.018821 | U47: 0.019993 | V47: 0.021249 | W47: 0.022599 | X47: 0.024009 | Y47: 0.025467 | Z47: 0.027013 | AA47: 0.028766 | AB47: 0.030682 | AC47: 0.032723 | AD47: 0.034948 | AE47: 0.037459 | AF47: --
A48: FTE000:da_plugingasolin | B48: Plug-in Gasoline Hybrid | C48: 0 | D48: 0 | E48: 0.002763 | F48: 0.005341 | G48: 0.007861 | H48: 0.010367 | I48: 0.012849 | J48: 0.015255 | K48: 0.017602 | L48: 0.01995 | M48: 0.02235 | N48: 0.02471 | O48: 0.027016 | P48: 0.029253 | Q48: 0.031359 | R48: 0.033412 | S48: 0.035376 | T48: 0.037299 | U48: 0.039282 | V48: 0.041389 | W48: 0.043634 | X48: 0.045939 | Y48: 0.048251 | Z48: 0.050642 | AA48: 0.053319 | AB48: 0.056164 | AC48: 0.05907 | AD48: 0.06213 | AE48: 0.065482 | AF48: --
A49: FTE000:da_fuelcell | B49: Fuel Cell | C49: 0 | D49: 0 | E49: 0.00678 | F49: 0.013259 | G49: 0.019751 | H49: 0.026344 | I49: 0.03299 | J49: 0.039546 | K49: 0.045989 | L49: 0.052423 | M49: 0.058965 | N49: 0.065316 | O49: 0.071456 | P49: 0.07736 | Q49: 0.082834 | R49: 0.088063 | S49: 0.092967 | T49: 0.097629 | U49: 0.102295 | V49: 0.107098 | W49: 0.112072 | X49: 0.117018 | Y49: 0.121867 | Z49: 0.126833 | AA49: 0.132515 | AB49: 0.138672 | AC49: 0.145142 | AD49: 0.152234 | AE49: 0.160418 | AF49: --
A50: FTE000:da_HeavySubtotal | B50: Heavy Subtotal | C50: 187.21161 | D50: 186.77066 | E50: 187.00078 | F50: 188.45283 | G50: 190.68486 | H50: 192.55638 | I50: 194.11635 | J50: 194.96588 | K50: 195.39752 | L50: 195.89365 | M50: 196.82713 | N50: 197.40904 | O50: 197.92372 | P50: 198.56163 | Q50: 198.94003 | R50: 199.57364 | S50: 200.20254 | T50: 200.71848 | U50: 201.37273 | V50: 202.11119 | W50: 202.83833 | X50: 203.40926 | Y50: 203.7776 | Z50: 203.91367 | AA50: 204.18713 | AB50: 204.44009 | AC50: 204.41753 | AD50: 204.47378 | AE50: 205.13785 | AF50: 0.003271
A51: FTE000:da_TotalVehicleM | B51: Total Vehicle Miles Traveled | C51: 321.95383 | D51: 320.71957 | E51: 321.15537 | F51: 324.03748 | G51: 328.44952 | H51: 332.31747 | I51: 335.87714 | J51: 338.61987 | K51: 341.15076 | L51: 344.15997 | M51: 348.16452 | N51: 351.53851 | O51: 354.82727 | P51: 358.34311 | Q51: 361.3916 | R51: 364.92499 | S51: 368.37805 | T51: 371.80917 | U51: 375.58542 | V51: 379.58304 | W51: 383.51111 | X51: 387.20508 | Y51: 390.63013 | Z51: 393.8345 | AA51: 397.53842 | AB51: 401.35025 | AC51: 404.65439 | AD51: 408.2189 | AE51: 413.07754 | AF51: 0.008941
B53: Consumption (trillion Btu)
B54: Light Medium
A55: FTE000:lm_use_stk_Dies | B55: Diesel | C55: 503.23831 | D55: 484.80926 | E55: 470.10184 | F55: 459.78449 | G55: 451.87814 | H55: 443.24606 | I55: 435.43274 | J55: 428.57593 | K55: 424.18491 | L55: 422.56686 | M55: 423.05704 | N55: 423.25711 | O55: 424.28409 | P55: 426.25699 | Q55: 428.07437 | R55: 430.74142 | S55: 433.84168 | T55: 437.7146 | U55: 442.6882 | V55: 448.15237 | W55: 453.8429 | X55: 459.89023 | Y55: 466.2998 | Z55: 473.53125 | AA55: 482.34018 | AB55: 491.8963 | AC55: 501.23676 | AD55: 511.31162 | AE55: 523.31238 | AF55: 0.001398
A56: FTE000:lm_use_stk_Gas | B56: Motor Gasoline | C56: 196.41988 | D56: 201.42117 | E56: 206.93259 | F56: 213.4828 | G56: 220.53224 | H56: 226.21765 | I56: 231.3105 | J56: 235.95909 | K56: 241.0206 | L56: 246.62308 | M56: 253.2693 | N56: 259.5228 | O56: 265.59988 | P56: 271.63849 | Q56: 277.3645 | R56: 283.4436 | S56: 289.37485 | T56: 295.02786 | U56: 300.90585 | V56: 307.12256 | W56: 313.00485 | X56: 318.11237 | Y56: 322.94775 | Z56: 327.87622 | AA56: 333.5806 | AB56: 339.54462 | AC56: 345.05283 | AD56: 350.95578 | AE56: 358.22073 | AF56: 0.021693
A57: FTE000:lm_use_stk_Liq | B57: Propane | C57: 0.008824 | D57: 0.079078 | E57: 0.148368 | F57: 0.211796 | G57: 0.27223 | H57: 0.328085 | I57: 0.380416 | J57: 0.429704 | K57: 0.477469 | L57: 0.525701 | M57: 0.575181 | N57: 0.623545 | O57: 0.671896 | P57: 0.722093 | Q57: 0.774258 | R57: 0.831293 | S57: 0.893031 | T57: 0.960705 | U57: 1.036213 | V57: 1.11984 | W57: 1.210605 | X57: 1.308586 | Y57: 1.412456 | Z57: 1.525402 | AA57: 1.65115 | AB57: 1.786922 | AC57: 1.928594 | AD57: 2.079436 | AE57: 2.244543 | AF57: 0.218738
A58: FTE000:lm_use_stk_NGas | B58: Compressed/Liquefied Natural Gas | C58: 0.192116 | D58: 0.174257 | E58: 0.158799 | F58: 0.145806 | G58: 0.134438 | H58: 0.123654 | I58: 0.113679 | J58: 0.104485 | K58: 0.096244 | L58: 0.088943 | M58: 0.082427 | N58: 0.075773 | O58: 0.068822 | P58: 0.061432 | Q58: 0.053884 | R58: 0.045974 | S58: 0.038685 | T58: 0.032133 | U58: 0.025619 | V58: 0.020525 | W58: 0.016807 | X58: 0.014122 | Y58: 0.012398 | Z58: 0.011208 | AA58: 0.010267 | AB58: 0.009607 | AC58: 0.008735 | AD58: 0.007734 | AE58: 0.00649 | AF58: -0.113962
A59: FTE000:lm_use_stk_flex | B59: Ethanol-Flex Fuel | C59: 45.964245 | D59: 44.611794 | E59: 43.499821 | F59: 42.670467 | G59: 42.056103 | H59: 41.41785 | I59: 40.858673 | J59: 40.401375 | K59: 40.094643 | L59: 39.995682 | M59: 40.077168 | N59: 40.08778 | O59: 39.881618 | P59: 39.530632 | Q59: 38.979153 | R59: 38.427227 | S59: 37.705452 | T59: 37.000896 | U59: 36.440113 | V59: 36.08366 | W59: 35.872028 | X59: 35.852295 | Y59: 36.018429 | Z59: 36.285957 | AA59: 36.676159 | AB59: 37.130253 | AC59: 37.561069 | AD59: 38.004097 | AE59: 38.549274 | AF59: -0.006263
A60: FTE000:lm_use_stk_elect | B60: Electric | C60: 0.004618 | D60: 0.004177 | E60: 0.003821 | F60: 0.003554 | G60: 0.003357 | H60: 0.0032 | I60: 0.003084 | J60: 0.002899 | K60: 0.002664 | L60: 0.002446 | M60: 0.002253 | N60: 0.001897 | O60: 0.001495 | P60: 0.001176 | Q60: 0.000923 | R60: 0.000724 | S60: 0.000568 | T60: 0.000444 | U60: 0.000396 | V60: 0.000387 | W60: 0.000378 | X60: 0.000368 | Y60: 0.000298 | Z60: 0.000209 | AA60: 0.000147 | AB60: 0.000103 | AC60: 7.3e-05 | AD60: 5.1e-05 | AE60: 3.6e-05 | AF60: -0.159099
A61: FTE000:lm_use_stk_plugd | B61: Plug-in Diesel Hybrid | C61: 0 | D61: 0.034697 | E61: 0.06879 | F61: 0.10379 | G61: 0.139219 | H61: 0.173667 | I61: 0.207235 | J61: 0.239813 | K61: 0.272039 | L61: 0.304685 | M61: 0.338422 | N61: 0.372229 | O61: 0.407349 | P61: 0.444994 | Q61: 0.485266 | R61: 0.530182 | S61: 0.580241 | T61: 0.636407 | U61: 0.700343 | V61: 0.772136 | W61: 0.85035 | X61: 0.933939 | Y61: 1.022764 | Z61: 1.117797 | AA61: 1.219284 | AB61: 1.324989 | AC61: 1.431711 | AD61: 1.542152 | AE61: 1.659889 | AF61: --
A62: FTE000:lm_use_stk_plugg | B62: Plug-in Gasoline Hybrid | C62: 0 | D62: 0.039742 | E62: 0.079436 | F62: 0.119691 | G62: 0.160329 | H62: 0.199692 | I62: 0.237663 | J62: 0.27446 | K62: 0.311191 | L62: 0.349268 | M62: 0.389597 | N62: 0.431086 | O62: 0.475127 | P62: 0.523366 | Q62: 0.575913 | R62: 0.635429 | S62: 0.702605 | T62: 0.7789 | U62: 0.866414 | V62: 0.965463 | W62: 1.074376 | X62: 1.192066 | Y62: 1.317839 | Z62: 1.452814 | AA62: 1.596785 | AB62: 1.746942 | AC62: 1.89845 | AD62: 2.054983 | AE62: 2.220644 | AF62: --
A63: FTE000:lm_use_stk_sell | B63: Fuel Cell | C63: 0 | D63: 0 | E63: 1.4e-05 | F63: 3e-05 | G63: 4.7e-05 | H63: 6.3e-05 | I63: 8e-05 | J63: 9.5e-05 | K63: 0.00011 | L63: 0.000125 | M63: 0.00014 | N63: 0.000153 | O63: 0.000166 | P63: 0.000177 | Q63: 0.000188 | R63: 0.000197 | S63: 0.000206 | T63: 0.000215 | U63: 0.000222 | V63: 0.000229 | W63: 0.000235 | X63: 0.000239 | Y63: 0.000241 | Z63: 0.000243 | AA63: 0.000243 | AB63: 0.000241 | AC63: 0.000238 | AD63: 0.000232 | AE63: 0.000226 | AF63: --
A64: FTE000:lm_use_stk_total | B64: Light Medium Subtotal | C64: 745.828 | D64: 731.17419 | E64: 720.99335 | F64: 716.5227 | G64: 715.17602 | H64: 711.70978 | I64: 708.54401 | J64: 705.98767 | K64: 706.45978 | L64: 710.45648 | M64: 717.79108 | N64: 724.37238 | O64: 731.39026 | P64: 739.17914 | Q64: 746.30835 | R64: 754.65625 | S64: 763.13678 | T64: 772.15192 | U64: 782.66351 | V64: 794.237 | W64: 805.87268 | X64: 817.30414 | Y64: 829.03204 | Z64: 841.80078 | AA64: 857.07452 | AB64: 873.44 | AC64: 889.11823 | AD64: 905.95587 | AE64: 926.21387 | AF64: 0.007766
B65: Medium
A66: FTE000:ea_Diesel | B66: Diesel | C66: 596.79718 | D66: 582.57031 | E66: 570.54584 | F66: 562.60992 | G66: 557.47638 | H66: 552.10059 | I66: 547.56726 | J66: 541.8349 | K66: 535.99304 | L66: 531.10577 | M66: 528.55798 | N66: 525.62 | O66: 523.05524 | P66: 521.63513 | Q66: 520.47327 | R66: 520.68817 | S66: 521.26672 | T66: 522.35956 | U66: 524.42358 | V66: 527.08154 | W66: 529.90253 | X66: 533.3006 | Y66: 536.98975 | Z66: 540.51788 | AA66: 544.76953 | AB66: 549.50623 | AC66: 553.8952 | AD66: 558.68854 | AE66: 565.29273 | AF66: -0.001935
A67: FTE000:ea_Gasoline | B67: Motor Gasoline | C67: 361.09714 | D67: 352.45267 | E67: 345.87949 | F67: 341.19531 | G67: 338.49741 | H67: 335.44928 | I67: 333.12943 | J67: 330.41745 | K67: 327.60516 | L67: 325.20841 | M67: 324.38138 | N67: 322.96948 | O67: 321.80856 | P67: 321.0246 | Q67: 319.85523 | R67: 319.80576 | S67: 319.18863 | T67: 319.81021 | U67: 320.5246 | V67: 321.91736 | W67: 323.47983 | X67: 325.35474 | Y67: 327.38092 | Z67: 329.19855 | AA67: 331.44745 | AB67: 333.82504 | AC67: 335.92966 | AD67: 338.38473 | AE67: 341.7948 | AF67: -0.00196
A68: FTE000:ea_LiquefiedPetr | B68: Propane | C68: 0.665595 | D68: 0.682733 | E68: 0.700859 | F68: 0.720756 | G68: 0.744488 | H68: 0.767789 | I68: 0.792564 | J68: 0.815042 | K68: 0.838861 | L68: 0.866507 | M68: 0.902205 | N68: 0.944946 | O68: 0.993298 | P68: 1.040652 | Q68: 1.091984 | R68: 1.151901 | S68: 1.219368 | T68: 1.295874 | U68: 1.383652 | V68: 1.483504 | W68: 1.590991 | X68: 1.705203 | Y68: 1.823792 | Z68: 1.944942 | AA68: 2.071958 | AB68: 2.202169 | AC68: 2.33111 | AD68: 2.451528 | AE68: 2.581014 | AF68: 0.049592
A69: FTE000:ea_CompressedNat | B69: Compressed/Liquefied Natural Gas | C69: 0.761944 | D69: 0.718699 | E69: 0.676321 | F69: 0.637992 | G69: 0.602869 | H69: 0.56657 | I69: 0.532462 | J69: 0.497576 | K69: 0.462788 | L69: 0.430828 | M69: 0.402386 | N69: 0.374433 | O69: 0.346945 | P69: 0.320598 | Q69: 0.295219 | R69: 0.273016 | S69: 0.253025 | T69: 0.235997 | U69: 0.220233 | V69: 0.204292 | W69: 0.190149 | X69: 0.173557 | Y69: 0.156469 | Z69: 0.142422 | AA69: 0.130806 | AB69: 0.118887 | AC69: 0.106766 | AD69: 0.095869 | AE69: 0.086903 | AF69: -0.074609
A70: FTE000:ea_ethanolflex | B70: Ethanol-Flex Fuel | C70: 10.331885 | D70: 10.758182 | E70: 11.321586 | F70: 11.975374 | G70: 12.744726 | H70: 13.587193 | I70: 14.506134 | J70: 15.44483 | K70: 16.450348 | L70: 17.581884 | M70: 18.915562 | N70: 20.372982 | O70: 22.01041 | P70: 23.794563 | Q70: 25.57753 | R70: 27.489719 | S70: 29.423685 | T70: 31.3827 | U70: 33.47094 | V70: 35.564487 | W70: 37.641945 | X70: 39.69342 | Y70: 41.6465 | Z70: 43.501041 | AA70: 45.296207 | AB70: 47.027523 | AC70: 48.595695 | AD70: 50.145443 | AE70: 51.783787 | AF70: 0.059255
A71: FTE000:ea_electric | B71: Electric | C71: 0.038242 | D71: 0.045435 | E71: 0.050754 | F71: 0.054753 | G71: 0.057684 | H71: 0.059468 | I71: 0.060365 | J71: 0.060383 | K71: 0.05979 | L71: 0.058834 | M71: 0.057679 | N71: 0.056149 | O71: 0.054414 | P71: 0.052583 | Q71: 0.050235 | R71: 0.047787 | S71: 0.045778 | T71: 0.043761 | U71: 0.041476 | V71: 0.03928 | W71: 0.037174 | X71: 0.035144 | Y71: 0.033201 | Z71: 0.031363 | AA71: 0.029679 | AB71: 0.02809 | AC71: 0.026553 | AD71: 0.025127 | AE71: 0.02381 | AF71: -0.01678
A72: FTE000:ea_plugindiesel | B72: Plug-in Diesel Hybrid | C72: 0 | D72: 0 | E72: 0.046031 | F72: 0.087364 | G72: 0.125998 | H72: 0.162359 | I72: 0.196929 | J72: 0.228566 | K72: 0.257603 | L72: 0.285156 | M72: 0.312729 | N72: 0.339615 | O72: 0.36633 | P72: 0.393577 | Q72: 0.420733 | R72: 0.449286 | S72: 0.47926 | T72: 0.511257 | U72: 0.546639 | V72: 0.585939 | W72: 0.62877 | X72: 0.672651 | Y72: 0.719311 | Z72: 0.768308 | AA72: 0.821181 | AB72: 0.877112 | AC72: 0.934619 | AD72: 0.994792 | AE72: 1.060159 | AF72: --
A73: FTE000:ea_plugingasolin | B73: Plug-in Gasoline Hybrid | C73: 0 | D73: 0 | E73: 0.055973 | F73: 0.105385 | G73: 0.151093 | H73: 0.193687 | I73: 0.233462 | J73: 0.26947 | K73: 0.302646 | L73: 0.335016 | M73: 0.368535 | N73: 0.40277 | O73: 0.438283 | P73: 0.476151 | Q73: 0.515752 | R73: 0.559245 | S73: 0.606796 | T73: 0.659627 | U73: 0.719741 | V73: 0.788289 | W73: 0.864886 | X73: 0.946915 | Y73: 1.035699 | Z73: 1.130374 | AA73: 1.23231 | AB73: 1.340697 | AC73: 1.452583 | AD73: 1.569724 | AE73: 1.695413 | AF73: --
A74: FTE000:ea_fuelcell | B74: Fuel Cell | C74: 0 | D74: 0 | E74: 0.097282 | F74: 0.188421 | G74: 0.276858 | H74: 0.363454 | I74: 0.447537 | J74: 0.527429 | K74: 0.603393 | L74: 0.677971 | M74: 0.75438 | N74: 0.830451 | O74: 0.907503 | P74: 0.98692 | Q74: 1.067797 | R74: 1.153837 | S74: 1.245005 | T74: 1.34302 | U74: 1.451644 | V74: 1.572443 | W74: 1.704381 | X74: 1.842259 | Y74: 1.989176 | Z74: 2.143766 | AA74: 2.310273 | AB74: 2.48651 | AC74: 2.668105 | AD74: 2.857946 | AE74: 3.063244 | AF74: --
A75: FTE000:ea_MediumSubtota | B75: Medium Subtotal | C75: 969.6922 | D75: 947.2279 | E75: 929.3739 | F75: 917.57489 | G75: 910.67767 | H75: 903.25073 | I75: 897.46606 | J75: 890.09558 | K75: 882.57385 | L75: 876.55035 | M75: 874.65283 | N75: 871.91071 | O75: 869.9809 | P75: 869.72479 | Q75: 869.34753 | R75: 871.61847 | S75: 873.72821 | T75: 877.64209 | U75: 882.78265 | V75: 889.23706 | W75: 896.04047 | X75: 903.72449 | Y75: 911.77454 | Z75: 919.37824 | AA75: 928.10968 | AB75: 937.41242 | AC75: 945.94019 | AD75: 955.21375 | AE75: 967.38214 | AF75: -8.5e-05
B76: Heavy
A77: FTE000:fa_Diesel | B77: Diesel | C77: 4152.2949 | D77: 4082.8315 | E77: 4021.4512 | F77: 3982.2764 | G77: 3955.9531 | H77: 3919.7483 | I77: 3881.1033 | J77: 3831.7788 | K77: 3778.5308 | L77: 3730.3296 | M77: 3694.2207 | N77: 3656.8643 | O77: 3623.7571 | P77: 3598.0146 | Q77: 3572.1406 | R77: 3555.0132 | S77: 3541.657 | T77: 3529.0093 | U77: 3520.9712 | V77: 3515.9072 | W77: 3513.189 | X77: 3509.6179 | Y77: 3504.0908 | Z77: 3495.7058 | AA77: 3490.0081 | AB77: 3484.0903 | AC77: 3473.502 | AD77: 3463.9399 | AE77: 3464.1235 | AF77: -0.006451
A78: FTE000:fa_Gasoline | B78: Motor Gasoline | C78: 3.967448 | D78: 3.91121 | E78: 3.927975 | F78: 4.003333 | G78: 4.154909 | H78: 4.346583 | I78: 4.555941 | J78: 4.758452 | K78: 4.97601 | L78: 5.18817 | M78: 5.395782 | N78: 5.579236 | O78: 5.743181 | P78: 5.890036 | Q78: 5.998426 | R78: 6.094069 | S78: 6.16721 | T78: 6.22837 | U78: 6.292622 | V78: 6.356681 | W78: 6.389575 | X78: 6.407103 | Y78: 6.434031 | Z78: 6.465653 | AA78: 6.509548 | AB78: 6.555473 | AC78: 6.592998 | AD78: 6.633256 | AE78: 6.692633 | AF78: 0.01885
A79: FTE000:fa_LiquefiedPetr | B79: Propane | C79: 0.570847 | D79: 0.624367 | E79: 0.675653 | F79: 0.723456 | G79: 0.769549 | H79: 0.807832 | I79: 0.837598 | J79: 0.854943 | K79: 0.864169 | L79: 0.868258 | M79: 0.870423 | N79: 0.871982 | O79: 0.876027 | P79: 0.882238 | Q79: 0.886164 | R79: 0.890656 | S79: 0.892193 | T79: 0.893006 | U79: 0.894043 | V79: 0.897259 | W79: 0.900476 | X79: 0.903219 | Y79: 0.905168 | Z79: 0.906542 | AA79: 0.909339 | AB79: 0.912656 | AC79: 0.914926 | AD79: 0.916513 | AE79: 0.919479 | AF79: 0.01717
A80: FTE000:fa_CompressedNat | B80: Compressed/Liquefied Natural Gas | C80: 50.390869 | D80: 50.880238 | E80: 51.130661 | F80: 51.278004 | G80: 51.2663 | H80: 50.76376 | I80: 49.941105 | J80: 48.755848 | K80: 47.376194 | L80: 46.136257 | M80: 45.289948 | N80: 44.81562 | O80: 44.797993 | P80: 45.188122 | Q80: 45.832714 | R80: 46.829082 | S80: 48.081806 | T80: 49.582222 | U80: 51.412018 | V80: 53.560184 | W80: 55.921677 | X80: 58.465366 | Y80: 61.153961 | Z80: 63.935596 | AA80: 66.919731 | AB80: 70.06723 | AC80: 73.232262 | AD80: 76.543907 | AE80: 80.243095 | AF80: 0.016755
A81: FTE000:fa_ethanolflex | B81: Ethanol-Flex Fuel | C81: 0 | D81: 0 | E81: 0 | F81: 0 | G81: 0 | H81: 0 | I81: 0 | J81: 0 | K81: 0 | L81: 0 | M81: 0 | N81: 0 | O81: 0 | P81: 0 | Q81: 0 | R81: 0 | S81: 0 | T81: 0 | U81: 0 | V81: 0 | W81: 0 | X81: 0 | Y81: 0 | Z81: 0 | AA81: 0 | AB81: 0 | AC81: 0 | AD81: 0 | AE81: 0 | AF81: --
A82: FTE000:fa_electric | B82: Electric | C82: 0.047272 | D82: 0.056366 | E82: 0.064063 | F82: 0.070822 | G82: 0.076726 | H82: 0.081383 | I82: 0.08483 | J82: 0.086958 | K82: 0.087952 | L82: 0.088013 | M82: 0.08725 | N82: 0.085333 | O82: 0.082536 | P82: 0.079114 | Q82: 0.075204 | R82: 0.071353 | S82: 0.067467 | T82: 0.063056 | U82: 0.058637 | V82: 0.054799 | W82: 0.051537 | X82: 0.048206 | Y82: 0.045224 | Z82: 0.042496 | AA82: 0.040057 | AB82: 0.037804 | AC82: 0.035659 | AD82: 0.033694 | AE82: 0.031963 | AF82: -0.013879
A83: FTE000:fa_plugindiesel | B83: Plug-in Diesel Hybrid | C83: 0 | D83: 0 | E83: 0.111749 | F83: 0.126518 | G83: 0.142694 | H83: 0.15934 | I83: 0.176213 | J83: 0.192228 | K83: 0.207245 | L83: 0.221401 | M83: 0.234888 | N83: 0.246569 | O83: 0.256597 | P83: 0.265207 | Q83: 0.272052 | R83: 0.278225 | S83: 0.283998 | T83: 0.29018 | U83: 0.298065 | V83: 0.30863 | W83: 0.322564 | X83: 0.334818 | Y83: 0.346776 | Z83: 0.362276 | AA83: 0.384801 | AB83: 0.407429 | AC83: 0.431705 | AD83: 0.458424 | AE83: 0.488884 | AF83: --
A84: FTE000:fa_plugingasolin | B84: Plug-in Gasoline Hybrid | C84: 0 | D84: 0 | E84: 0.234144 | F84: 0.262736 | G84: 0.294181 | H84: 0.326345 | I84: 0.358361 | J84: 0.388214 | K84: 0.415743 | L84: 0.441347 | M84: 0.465224 | N84: 0.485016 | O84: 0.500979 | P84: 0.513628 | Q84: 0.522262 | R84: 0.52909 | S84: 0.534693 | T84: 0.540743 | U84: 0.549724 | V84: 0.563565 | W84: 0.583643 | X84: 0.599231 | Y84: 0.613008 | Z84: 0.632858 | AA84: 0.665276 | AB84: 0.695484 | AC84: 0.726562 | AD84: 0.759665 | AE84: 0.796416 | AF84: --
A85: FTE000:fa_fuelcell | B85: Fuel Cell | C85: 0 | D85: 0 | E85: 0.132431 | F85: 0.258802 | G85: 0.385407 | H85: 0.513998 | I85: 0.643633 | J85: 0.771512 | K85: 0.897175 | L85: 1.022669 | M85: 1.150256 | N85: 1.274112 | O85: 1.393794 | P85: 1.508843 | Q85: 1.615412 | R85: 1.717117 | S85: 1.812324 | T85: 1.902677 | U85: 1.992978 | V85: 2.085901 | W85: 2.182155 | X85: 2.277899 | Y85: 2.371854 | Z85: 2.468158 | AA85: 2.57848 | AB85: 2.69808 | AC85: 2.823772 | AD85: 2.961604 | AE85: 3.12061 | AF85: --
A86: FTE000:fa_HeavySubtotal | B86: Heavy Subtotal | C86: 4207.2734 | D86: 4138.3027 | E86: 4077.7275 | F86: 4039.0002 | G86: 4013.043 | H86: 3976.7485 | I86: 3937.7007 | J86: 3887.5862 | K86: 3833.3564 | L86: 3784.2959 | M86: 3747.7146 | N86: 3710.2214 | O86: 3677.4077 | P86: 3652.3428 | Q86: 3627.3423 | R86: 3611.4219 | S86: 3599.4954 | T86: 3588.5098 | U86: 3582.4688 | V86: 3579.7346 | W86: 3579.541 | X86: 3578.6531 | Y86: 3575.9612 | Z86: 3570.5195 | AA86: 3568.0159 | AB86: 3565.4648 | AC86: 3558.2588 | AD86: 3552.2461 | AE86: 3556.4155 | AF86: -0.005984
B87: Light Medium, Medium, and Heavy Total
A88: FTE000:ga_Diesel | B88: Diesel | C88: 5252.3306 | D88: 5150.2109 | E88: 5062.0986 | F88: 5004.6709 | G88: 4965.3076 | H88: 4915.0947 | I88: 4864.1035 | J88: 4802.1895 | K88: 4738.709 | L88: 4684.002 | M88: 4645.8359 | N88: 4605.7412 | O88: 4571.0967 | P88: 4545.9067 | Q88: 4520.6885 | R88: 4506.4429 | S88: 4496.7656 | T88: 4489.0835 | U88: 4488.083 | V88: 4491.1411 | W88: 4496.9346 | X88: 4502.8086 | Y88: 4507.3804 | Z88: 4509.7549 | AA88: 4517.1177 | AB88: 4525.4932 | AC88: 4528.6338 | AD88: 4533.9399 | AE88: 4552.7285 | AF88: -0.005092
A89: FTE000:ga_Gasoline | B89: Motor Gasoline | C89: 561.4845 | D89: 557.78503 | E89: 556.74005 | F89: 558.68146 | G89: 563.18457 | H89: 566.01349 | I89: 568.99591 | J89: 571.13495 | K89: 573.60175 | L89: 577.01965 | M89: 583.04651 | N89: 588.07153 | O89: 593.15161 | P89: 598.5531 | Q89: 603.21814 | R89: 609.34344 | S89: 614.73071 | T89: 621.06647 | U89: 627.72302 | V89: 635.39661 | W89: 642.87427 | X89: 649.87421 | Y89: 656.7627 | Z89: 663.5404 | AA89: 671.5376 | AB89: 679.92511 | AC89: 687.5755 | AD89: 695.97375 | AE89: 706.70813 | AF89: 0.008249
A90: FTE000:ga_LiquefiedPetr | B90: Propane | C90: 1.245265 | D90: 1.386178 | E90: 1.52488 | F90: 1.656008 | G90: 1.786266 | H90: 1.903707 | I90: 2.010578 | J90: 2.099688 | K90: 2.180499 | L90: 2.260466 | M90: 2.347808 | N90: 2.440473 | O90: 2.541221 | P90: 2.644983 | Q90: 2.752405 | R90: 2.873849 | S90: 3.004591 | T90: 3.149585 | U90: 3.313908 | V90: 3.500602 | W90: 3.702072 | X90: 3.917007 | Y90: 4.141415 | Z90: 4.376886 | AA90: 4.632447 | AB90: 4.901746 | AC90: 5.174631 | AD90: 5.447477 | AE90: 5.745036 | AF90: 0.056125
A91: FTE000:ga_CompressedNat | B91: Compressed/Liquefied Natural Gas | C91: 51.344929 | D91: 51.773193 | E91: 51.965782 | F91: 52.061802 | G91: 52.003609 | H91: 51.453983 | I91: 50.587246 | J91: 49.35791 | K91: 47.935226 | L91: 46.656029 | M91: 45.774761 | N91: 45.265827 | O91: 45.21376 | P91: 45.570152 | Q91: 46.181816 | R91: 47.148071 | S91: 48.373516 | T91: 49.850353 | U91: 51.657871 | V91: 53.785004 | W91: 56.128632 | X91: 58.653046 | Y91: 61.32283 | Z91: 64.089226 | AA91: 67.060806 | AB91: 70.195724 | AC91: 73.347763 | AD91: 76.647514 | AE91: 80.336487 | AF91: 0.016116
A92: FTE000:ga_ethanolflex | B92: Ethanol-Flex Fuel | C92: 56.296131 | D92: 55.369976 | E92: 54.821407 | F92: 54.645844 | G92: 54.800827 | H92: 55.005043 | I92: 55.364807 | J92: 55.846207 | K92: 56.544991 | L92: 57.577568 | M92: 58.992729 | N92: 60.460762 | O92: 61.892029 | P92: 63.325195 | Q92: 64.556686 | R92: 65.916946 | S92: 67.129135 | T92: 68.383598 | U92: 69.911057 | V92: 71.648148 | W92: 73.513977 | X92: 75.545715 | Y92: 77.664932 | Z92: 79.787003 | AA92: 81.972366 | AB92: 84.157776 | AC92: 86.156769 | AD92: 88.149536 | AE92: 90.333061 | AF92: 0.017032
A93: FTE000:ga_electric | B93: Electric | C93: 0.090132 | D93: 0.105979 | E93: 0.118638 | F93: 0.129129 | G93: 0.137766 | H93: 0.144051 | I93: 0.148279 | J93: 0.15024 | K93: 0.150405 | L93: 0.149294 | M93: 0.147183 | N93: 0.143379 | O93: 0.138445 | P93: 0.132873 | Q93: 0.126362 | R93: 0.119864 | S93: 0.113812 | T93: 0.107261 | U93: 0.100509 | V93: 0.094466 | W93: 0.089089 | X93: 0.083718 | Y93: 0.078723 | Z93: 0.074068 | AA93: 0.069883 | AB93: 0.065998 | AC93: 0.062285 | AD93: 0.058872 | AE93: 0.055809 | AF93: -0.016974
A94: FTE000:ga_plugindiesel | B94: Plug-in Diesel Hybrid | C94: 0 | D94: 0.034697 | E94: 0.22657 | F94: 0.317672 | G94: 0.40791 | H94: 0.495367 | I94: 0.580377 | J94: 0.660607 | K94: 0.736886 | L94: 0.811243 | M94: 0.886039 | N94: 0.958413 | O94: 1.030276 | P94: 1.103778 | Q94: 1.178052 | R94: 1.257694 | S94: 1.343499 | T94: 1.437844 | U94: 1.545047 | V94: 1.666705 | W94: 1.801683 | X94: 1.941409 | Y94: 2.088851 | Z94: 2.248381 | AA94: 2.425267 | AB94: 2.60953 | AC94: 2.798035 | AD94: 2.995368 | AE94: 3.208932 | AF94: --
A95: FTE000:ga_plugingasolin | B95: Plug-in Gasoline Hybrid | C95: 0 | D95: 0.039742 | E95: 0.369553 | F95: 0.487812 | G95: 0.605603 | H95: 0.719725 | I95: 0.829486 | J95: 0.932144 | K95: 1.02958 | L95: 1.12563 | M95: 1.223357 | N95: 1.318871 | O95: 1.414389 | P95: 1.513145 | Q95: 1.613927 | R95: 1.723764 | S95: 1.844094 | T95: 1.979271 | U95: 2.13588 | V95: 2.317318 | W95: 2.522904 | X95: 2.738211 | Y95: 2.966547 | Z95: 3.216047 | AA95: 3.49437 | AB95: 3.783123 | AC95: 4.077595 | AD95: 4.384372 | AE95: 4.712472 | AF95: --
A96: FTE000:ga_fuelcell | B96: Fuel Cell | C96: 0 | D96: 0 | E96: 0.229727 | F96: 0.447252 | G96: 0.662312 | H96: 0.877515 | I96: 1.09125 | J96: 1.299036 | K96: 1.500679 | L96: 1.700765 | M96: 1.904776 | N96: 2.104716 | O96: 2.301462 | P96: 2.49594 | Q96: 2.683397 | R96: 2.871152 | S96: 3.057536 | T96: 3.245911 | U96: 3.444844 | V96: 3.658573 | W96: 3.886771 | X96: 4.120397 | Y96: 4.361271 | Z96: 4.612166 | AA96: 4.888996 | AB96: 5.184831 | AC96: 5.492115 | AD96: 5.819783 | AE96: 6.18408 | AF96: --
A97: FTE000:ga_Total | B97: Total Consumption | C97: 5922.7944 | D97: 5816.7051 | E97: 5728.0957 | F97: 5673.0986 | G97: 5638.8975 | H97: 5591.7061 | I97: 5543.71 | J97: 5483.6724 | K97: 5422.3882 | L97: 5371.3042 | M97: 5340.1577 | N97: 5306.5059 | O97: 5278.7812 | P97: 5261.2451 | Q97: 5243.0034 | R97: 5237.6968 | S97: 5236.3604 | T97: 5238.3047 | U97: 5247.9136 | V97: 5263.2056 | W97: 5281.4531 | X97: 5299.6841 | Y97: 5316.7676 | Z97: 5331.7002 | AA97: 5353.1963 | AB97: 5376.3159 | AC97: 5393.3193 | AD97: 5413.417 | AE97: 5450.0137 | AF97: -0.002967
B99: Fuel Efficiency (miles per gallon)
B100: Light Medium
A101: FTE000:lm_mpg_stk_Dies | B101: Diesel | C101: 14.991418 | D101: 15.216496 | E101: 15.498507 | F101: 15.831193 | G101: 16.182243 | H101: 16.538082 | I101: 16.880116 | J101: 17.209087 | K101: 17.515287 | L101: 17.796841 | M101: 18.05801 | N101: 18.298815 | O101: 18.515478 | P101: 18.711391 | Q101: 18.891172 | R101: 19.054907 | S101: 19.202492 | T101: 19.329569 | U101: 19.439314 | V101: 19.535429 | W101: 19.61628 | X101: 19.678816 | Y101: 19.72633 | Z101: 19.762045 | AA101: 19.788633 | AB101: 19.806604 | AC101: 19.813744 | AD101: 19.817585 | AE101: 19.819794 | AF101: 0.010021
A102: FTE000:lm_mpg_stk_Gas | B102: Motor Gasoline | C102: 10.726876 | D102: 11.029115 | E102: 11.340722 | F102: 11.658097 | G102: 11.957341 | H102: 12.246843 | I102: 12.511288 | J102: 12.761357 | K102: 12.989336 | L102: 13.199086 | M102: 13.38113 | N102: 13.546596 | O102: 13.699472 | P102: 13.842229 | Q102: 13.973739 | R102: 14.095364 | S102: 14.210415 | T102: 14.321558 | U102: 14.425992 | V102: 14.520219 | W102: 14.608215 | X102: 14.692059 | Y102: 14.763736 | Z102: 14.827796 | AA102: 14.883237 | AB102: 14.930063 | AC102: 14.969678 | AD102: 15.003341 | AE102: 15.030684 | AF102: 0.012121
A103: FTE000:lm_mpg_stk_Liq | B103: Propane | C103: 8.287116 | D103: 12.070017 | E103: 12.378905 | F103: 12.533067 | G103: 12.633637 | H103: 12.727521 | I103: 12.811732 | J103: 12.9071 | K103: 13.019794 | L103: 13.144209 | M103: 13.276356 | N103: 13.407525 | O103: 13.532327 | P103: 13.644149 | Q103: 13.742635 | R103: 13.828311 | S103: 13.902666 | T103: 13.967391 | U103: 14.023659 | V103: 14.072396 | W103: 14.11443 | X103: 14.150719 | Y103: 14.184551 | Z103: 14.215186 | AA103: 14.241229 | AB103: 14.26371 | AC103: 14.282851 | AD103: 14.299067 | AE103: 14.312678 | AF103: 0.019708
A104: FTE000:lm_mpg_stk_NGas | B104: Compressed/Liquefied Natural Gas | C104: 10.037065 | D104: 10.03825 | E104: 10.039481 | F104: 10.04076 | G104: 10.04208 | H104: 10.043437 | I104: 10.044827 | J104: 10.046251 | K104: 10.047701 | L104: 10.049176 | M104: 10.050672 | N104: 10.057157 | O104: 10.073521 | P104: 10.105247 | Q104: 10.140972 | R104: 10.185604 | S104: 10.231821 | T104: 10.265868 | U104: 10.275093 | V104: 10.25789 | W104: 10.216537 | X104: 10.1613 | Y104: 10.092754 | Z104: 10.027177 | AA104: 9.99404 | AB104: 10.014455 | AC104: 10.061934 | AD104: 10.114001 | AE104: 10.188727 | AF104: 0.000536
A105: FTE000:lm_mpg_stk_fleck | B105: Ethanol-Flex Fuel | C105: 10.321225 | D105: 10.468386 | E105: 10.641707 | F105: 10.829888 | G105: 11.019979 | H105: 11.213248 | I105: 11.394366 | J105: 11.570538 | K105: 11.740291 | L105: 11.905053 | M105: 12.059313 | N105: 12.21348 | O105: 12.379014 | P105: 12.555837 | Q105: 12.744346 | R105: 12.939108 | S105: 13.149075 | T105: 13.363464 | U105: 13.576193 | V105: 13.772496 | W105: 13.949099 | X105: 14.098662 | Y105: 14.220824 | Z105: 14.323482 | AA105: 14.410444 | AB105: 14.483241 | AC105: 14.544046 | AD105: 14.60201 | AE105: 14.655778 | AF105: 0.012601
A106: FTE000:lm_mpg_stk_eleck | B106: Electric | C106: 24.120544 | D106: 24.120651 | E106: 24.120832 | F106: 24.121077 | G106: 24.121357 | H106: 24.121647 | I106: 24.121906 | J106: 24.1206 | K106: 24.120342 | L106: 24.120312 | M106: 24.120283 | N106: 24.116169 | O106: 24.116142 | P106: 24.116114 | Q106: 24.116087 | R106: 24.116058 | S106: 24.11603 | T106: 24.116003 | U106: 24.12192 | V106: 24.121895 | W106: 24.121872 | X106: 24.121847 | Y106: 24.121847 | Z106: 24.121847 | AA106: 24.121847 | AB106: 24.121847 | AC106: 24.121847 | AD106: 24.121847 | AE106: 24.121849 | AF106: 2e-06
A107: FTE000:lm_mpg_stk_diehy | B107: Plug-in Diesel Hybrid | C107: 0 | D107: 23.149469 | E107: 23.472181 | F107: 23.713379 | G107: 23.934065 | H107: 24.180559 | I107: 24.434351 | J107: 24.733727 | K107: 25.076927 | L107: 25.458097 | M107: 25.866047 | N107: 26.26355 | O107: 26.63553 | P107: 26.97172 | Q107: 27.273853 | R107: 27.540438 | S107: 27.771664 | T107: 27.968973 | U107: 28.134949 | V107: 28.272074 | W107: 28.389307 | X107: 28.489752 | Y107: 28.575668 | Z107: 28.649502 | AA107: 28.719357 | AB107: 28.78302 | AC107: 28.839659 | AD107: 28.888365 | AE107: 28.930431 | AF107: --
A108: FTE000:lm_mpg_stk_gashy | B108: Plug-in Gasoline Hybrid | C108: 0 | D108: 18.959843 | E108: 19.097799 | F108: 19.221861 | G108: 19.306705 | H108: 19.394665 | I108: 19.477266 | J108: 19.57037 | K108: 19.676134 | L108: 19.793497 | M108: 19.919716 | N108: 20.047338 | O108: 20.172951 | P108: 20.289747 | Q108: 20.399185 | R108: 20.498297 | S108: 20.584267 | T108: 20.657764 | U108: 20.719555 | V108: 20.770308 | W108: 20.813774 | X108: 20.851307 | Y108: 20.877443 | Z108: 20.902786 | AA108: 20.928736 | AB108: 20.955839 | AC108: 20.984339 | AD108: 21.01486 | AE108: 21.047607 | AF108: --
...

Sheet Sheet1

Sheet NTS 1-20
A1: Table 1-20: Productions, Production Shares, and Production-Weighted Fuel Economies of New Domestic and Imported Automobiles (Thousands of vehicles)
B2: 1980 | C2: 1985 | D2: 1990 | E2: 1991 | F2: 1992 | G2: 1993 | H2: 1994 | I2: 1995 | J2: 1996 | K2: 1997 | L2: 1998 | M2: 1999 | N2: 2000 | O2: 2001 | P2: 2002 | Q2: 2003 | R2: 2004 | S2: 2005 | T2: 2006 | U2: 2007 | V2: 2008 | W2: 2009 | X2: 2010 | Y2: 2011 | Z2: 2012 | AA2: 2013 | AB2: 2014
A3: TOTAL productions | B3: 11306 | C3: 14460 | D3: 12615 | E3: 12573 | F3: 12172 | G3: 13211 | H3: 14125 | I3: 15145 | J3: 13144 | K3: 14458 | L3: 14456 | M3: 15215 | N3: 16571 | O3: 15605 | P3: 16115 | Q3: 15773 | R3: 15709 | S3: 15892 | T3: 15104 | U3: 15276 | V3: 13898 | W3: 9316 | X3: 11110 | Y3: 12003 | Z3: 13438 | AA3: 14846 | AB3: N
A4: Car | B4: 9443 | C4: 10791 | D4: 8810 | E4: 8524 | F4: 8108 | G4: 8456 | H4: 8415 | I4: 9396 | J4: 7890 | K4: 8334 | L4: 7971 | M4: 8376 | N4: 9125 | O4: 8405 | P4: 8301 | Q4: 7921 | R4: 7537 | S4: 8027 | T4: 7993 | U4: 8082 | V4: 7319 | W4: 5636 | X4: 6055 | Y4: 5728 | Z4: 7379 | AA4: 7907 | AB4: N
A5: Car SUV | B5: 0 | C5: 88 | D5: 65 | E5: 224 | F5: 243 | G5: 473 | H5: 332 | I5: 220 | J5: 287 | K5: 361 | L5: 454 | M5: 488 | N5: 617 | O5: 743 | P5: 603 | Q5: 575 | R5: 639 | S5: 813 | T5: 751 | U5: 919 | V5: 924 | W5: 608 | X5: 915 | Y5: 1207 | Z5: 1269 | AA5: 1470 | AB5: N
A6: Pickup | B6: 1437 | C6: 2078 | D6: 1835 | E6: 1920 | F6: 1840 | G6: 2002 | H6: 2669 | I6: 2271 | J6: 1955 | K6: 2408 | L6: 2415 | M6: 2544 | N6: 2612 | O6: 2519 | P6: 2380 | Q6: 2474 | R6: 2505 | S6: 2300 | T6: 2188 | U6: 2113 | V6: 1794 | W6: 989 | X6: 1276 | Y6: 1479 | Z6: 1357 | AA6: 1577 | AB6: N
A7: Van | B7: 242 | C7: 855 | D7: 1262 | E7: 1034 | F7: 1221 | G7: 1441 | H7: 1418 | I7: 1662 | J7: 1409 | K7: 1265 | L7: 1489 | M7: 1463 | N7: 1691 | O7: 1232 | P7: 1243 | Q7: 1232 | R7: 953 | S7: 1481 | T7: 1166 | U7: 847 | V7: 790 | W7: 368 | X7: 559 | Y7: 521 | Z7: 661 | AA7: 571 | AB7: N
A8: Truck SUV | B8: 184 | C8: 648 | D8: 643 | E8: 871 | F8: 761 | G8: 838 | H8: 1291 | I8: 1596 | J8: 1603 | K8: 2089 | L8: 2127 | M8: 2342 | N8: 2526 | O8: 2707 | P8: 3588 | Q8: 3571 | R8: 4075 | S8: 3272 | T8: 3006 | U8: 3314 | V8: 3072 | W8: 1713 | X8: 2305 | Y8: 3069 | Z8: 2773 | AA8: 3321 | AB8: N
A9: Market share, percent
A10: Car | B10: =B4/B$3*100 -> 83.522024 | C10: =C4/C$3*100 -> 74.626556 | D10: 69.8 | E10: 67.8 | F10: 66.6 | G10: 64 | H10: 59.6 | I10: 62 | J10: 60 | K10: 57.6 | L10: 55.1 | M10: 55.1 | N10: 55.1 | O10: 53.9 | P10: 51.5 | Q10: 50.2 | R10: 48 | S10: 50.5 | T10: 52.9 | U10: 52.9 | V10: 52.7 | W10: 60.5 | X10: 54.5 | Y10: 47.7 | Z10: 54.9 | AA10: 53.3 | AB10: 51.3
A11: Car SUV | B11: 0 | C11: 0.6 | D11: 0.5 | E11: 1.8 | F11: 2 | G11: 3.6 | H11: 2.3 | I11: 1.5 | J11: 2.2 | K11: 2.5 | L11: 3.1 | M11: 3.2 | N11: 3.7 | O11: 4.8 | P11: 3.7 | Q11: 3.6 | R11: 4.1 | S11: 5.1 | T11: 5 | U11: 6 | V11: 6.6 | W11: 6.5 | X11: 8.2 | Y11: 10.1 | Z11: 9.4 | AA11: 9.9 | AB11: 10
A12: Pickup | B12: 12.7 | C12: 14.4 | D12: 14.5 | E12: 15.3 | F12: 15.1 | G12: 15.2 | H12: 18.9 | I12: 15 | J12: 14.9 | K12: 16.7 | L12: 16.7 | M12: 16.7 | N12: 15.8 | O12: 16.1 | P12: 14.8 | Q12: 15.7 | R12: 15.9 | S12: 14.5 | T12: 14.5 | U12: 13.8 | V12: 12.9 | W12: 10.6 | X12: 11.5 | Y12: 12.3 | Z12: 10.1 | AA12: 10.6 | AB12: 11.5
A13: Van | B13: 2.1 | C13: 5.9 | D13: 10 | E13: 8.2 | F13: 10 | G13: 10.9 | H13: 10 | I13: 11 | J13: 10.7 | K13: 8.8 | L13: 10.3 | M13: 9.6 | N13: 10.2 | O13: 7.9 | P13: 7.7 | Q13: 7.8 | R13: 6.1 | S13: 9.3 | T13: 7.7 | U13: 5.5 | V13: 5.7 | W13: 4 | X13: 5 | Y13: 4.3 | Z13: 4.9 | AA13: 3.8 | AB13: 3.9
A14: Truck SUV | B14: 1.6 | C14: 4.5 | D14: 5.1 | E14: 6.9 | F14: 6.2 | G14: 6.3 | H14: 9.1 | I14: 10.5 | J14: 12.2 | K14: 14.5 | L14: 14.7 | M14: 15.4 | N14: 15.2 | O14: 17.3 | P14: 22.3 | Q14: 22.6 | R14: 25.9 | S14: 20.6 | T14: 19.9 | U14: 21.7 | V14: 22.1 | W14: 18.4 | X14: 20.8 | Y14: 25.6 | Z14: 20.6 | AA14: 22.4 | AB14: 23.3
A15: Fuel economy, mpg
A16: Car | B16: 20 | C16: 23 | D16: 23.3 | E16: 23.4 | F16: 23.1 | G16: 23.5 | H16: 23.3 | I16: 23.4 | J16: 23.3 | K16: 23.4 | L16: 23.4 | M16: 23 | N16: 22.9 | O16: 23 | P16: 23.1 | Q16: 23.3 | R16: 23.1 | S16: 23.5 | T16: 23.3 | U16: 24.1 | V16: 24.3 | W16: 25.3 | X16: 26.2 | Y16: 26 | Z16: 27.8 | AA16: 28.3 | AB16: 28.7
A17: Car SUV | B17: 14.6 | C17: 20.1 | D17: 18.8 | E17: 18.2 | F17: 17.8 | G17: 17 | H17: 18 | I17: 17.8 | J17: 18.4 | K17: 19.2 | L17: 18.2 | M17: 18.5 | N17: 17.9 | O17: 18.8 | P17: 19.3 | Q17: 19.9 | R17: 20 | S17: 20.2 | T17: 20.5 | U17: 20.6 | V17: 21.2 | W17: 22 | X17: 23 | Y17: 23.6 | Z17: 23.4 | AA17: 24.5 | AB17: 24.3
A18: Pickup | B18: 16.5 | C18: 18.2 | D18: 17.4 | E18: 18.2 | F18: 17.5 | G18: 17.6 | H18: 17.4 | I18: 16.9 | J18: 17.1 | K18: 16.8 | L18: 17 | M18: 16.3 | N18: 16.7 | O18: 16 | P18: 15.8 | Q18: 16.1 | R18: 15.7 | S18: 15.8 | T18: 16.1 | U18: 16.2 | V18: 16.5 | W18: 16.9 | X18: 16.9 | Y18: 17.2 | Z18: 17.2 | AA18: 17.4 | AB18: 18
A19: Van | B19: 14.1 | C19: 16.5 | D19: 17.8 | E19: 17.9 | F19: 17.9 | G19: 18.2 | H19: 17.8 | I19: 18.1 | J19: 18.3 | K19: 18.2 | L19: 18.7 | M19: 18.3 | N19: 18.6 | O19: 18 | P19: 18.7 | Q19: 19 | R19: 19.2 | S19: 19.3 | T19: 19.5 | U19: 19.5 | V19: 19.8 | W19: 20.1 | X19: 20.1 | Y19: 21 | Z19: 21.4 | AA19: 21.1 | AB19: 21.2
A20: Truck SUV | B20: 13.2 | C20: 16.5 | D20: 16.4 | E20: 16.7 | F20: 16.2 | G20: 16.3 | H20: 16 | I20: 16 | J20: 16.2 | K20: 16.1 | L20: 16.2 | M20: 16.1 | N20: 16 | O20: 16.4 | P20: 16.3 | Q20: 16.4 | R20: 16.5 | S20: 16.7 | T20: 17.2 | U20: 17.7 | V20: 18.2 | W20: 19.3 | X20: 19.7 | Y20: 19.8 | Z20: 20 | AA20: 20.9 | AB20: 21.2
A21: KEY: mpg = miles per gallon; N = data are not available; R = revised; SUV = sport utility vehicle.
A23: NOTES
A24: Numbers may not add to totals due to rounding.
A25: This table is not comparable to previous publication's tables due to changes in the source data.
A26: The Environmental Protection Agency changed the vehicle classifications, combining wagons with the rest of the cars and dropping the small, medium, large categories of cars, pickups, sport-utilities, and vans. The fuel economy displayed in those tables has been adjusted to provide the best estimate of real-world performance.
A28: SOURCE
A29: U.S. Department of Energy, Office of Energy Efficiency and Renewable Energy, Transportation Energy Data Book, Edition 33, tables 4.7, table 4.9 and table 4.11 (Oak Ridge, TN), available at http://cta.ornl.gov/data/index.shtml as of Dec. 8, 2015.

Sheet Calculations
A1: LDVs
A2: Car Avg Lifetime, years (Page 22, Table 7) | B2: Light Truck Avg Lifetime, years (Page 25, Table 8) | C2: Avg Car Sales from 2010-2013, thousands of vehicles (Table 1-20, Rows 4-5) | D2: Avg Light Truck Sales from 2010-2013, thousands of vehicles (Table 1-20, Rows 6-8) | E2: Market Share-Weighted Average LDV Lifetime
A3: 13 | B3: 14 | C3: =AVERAGE(SUM('NTS 1-20'!X4:X5),SUM('NTS 1-20'!Y4:Y5),SUM('NTS 1-20'!Z4:Z5),SUM('NTS 1-20'!AA4:AA5)) -> 7982.5 | D3: =AVERAGE(SUM('NTS 1-20'!X6:X8),SUM('NTS 1-20'!Y6:Y8),SUM('NTS 1-20'!Z6:Z8),SUM('NTS 1-20'!AA6:AA8)) -> 4867.25 | E3: =(A3*C3+B3*D3)/(C3+D3) -> 13.378782
A5: HDVs
A6: Heavy Truck Avg Lifetime, years (Table 3-14, Row 43) | B6: Heavy Truck Start Year Vehicles | C6: Bus Lifetime | D6: Bus Start Year Vehicle
A7: 28 | B7: 11932239 | C7: 23 | D7: 1007829.3
A10: aircraft
A11: Exhibits 1-3 illustrate roughly the same results.
A12: Exhibit 1: | B12: Non-dotted lines (aircraft in service) have been constant at 23-24 years for the last 15 years.
A13: Exhibit 2: | B13: Non-dashed lines (aircraft age when they leave service) has been 22-26 for Pax (passengers) and 31-36 for freighters over the last 15 years.
A14: Exhibit 3: | B14: The curves for all aircraft except the 707 Pax and the 737-100/200 Pax cross or are on track to cross 50% survival around age 23-24.
A15: Value selected for use in model
A16: 24
A18: rail
A19: Table | B19: CA Asset Type | C19: Lifetime (years)
A20: 2000 - Water Utility | B20: railroads | C20: 33
A21: 5000 - Transit | B21: locomotives, electric | C21: 35
B22: Value selected for use in model | C22: 34
A23: Neither of these asset types is exactly what I'd prefer (which would be something like "locomotives, diesel"
A24: or "locomotives, freight"), but they seem like reasonable values and are close to each other.
A26: ships
A27: Table | B27: CA Asset Type | C27: Lifetime (years)
A28: 3000 - Harbor & Port | B28: Motor vessels - diesel, ocean | C28: 33
A30: motorbikes
A31: Year | B31: Registered Motorcycles | C31: Motorcycles sold (new) | D31: Retiring Motorcycles | E31: Percentage of Fleet That Retired This Year
A32: 1997 | B32: 3826373 | C32: 260000
A33: 1998 | B33: 3879450 | C33: 311000 | D33: =C33-(B33-B32) -> 257923 | E33: =D33/B33 -> 0.066484424
A34: 1999 | B34: 4152433 | C34: 394000 | D34: =C34-(B34-B33) -> 121017 | E34: =D34/B34 -> 0.029143637
A35: 2000 | B35: 4346068 | C35: 490000 | D35: =C35-(B35-B34) -> 296365 | E35: =D35/B35 -> 0.068191524
A36: 2001 | B36: 4903056 | C36: 577000 | D36: =C36-(B36-B35) -> 20012 | E36: =D36/B36 -> 0.0040815361
A37: 2002 | B37: 5004156 | C37: 640000 | D37: =C37-(B37-B36) -> 538900 | E37: =D37/B37 -> 0.10769049
A38: 2003 | B38: 5370035 | C38: 683000 | D38: =C38-(B38-B37) -> 317121 | E38: =D38/B38 -> 0.059053805
A39: 2004 | B39: 5780870 | C39: 750000 | D39: =C39-(B39-B38) -> 339165 | E39: =D39/B39 -> 0.058670235
A40: 2005 | B40: 6227146 | C40: 831000 | D40: =C40-(B40-B39) -> 384724 | E40: =D40/B40 -> 0.061781754
A41: 2006 | B41: 6678958 | C41: 892000 | D41: =C41-(B41-B40) -> 440188 | E41: =D41/B41 -> 0.065906688
A42: 2007 | B42: 7138476 | C42: 885000 | D42: =C42-(B42-B41) -> 425482 | E42: =D42/B42 -> 0.059604039
A44: Average Percent Fleet Retirement per Year
A45: =AVERAGE(E33:E42) -> 0.058060813
A47: Estimated Lifetime of Motorcycle (years)
A48: =1/A45 -> 17.223321

Sheet Freight and Buses
A2: commercial truck sales | B2: ='Table 44'!B79*1000 -> 642293.95
A3: commercial truck stock | B3: ='Table 45'!B77*1000 -> 14814712
A4: Average replacement time | B4: =1/(B2/B3) -> 23.065315
A7: LDV/MDV sales | B7: =SUM('Table 49'!C220,'Table 49'!C231)*1000 -> 432742.8
A8: LDV/MDV stock | B8: =SUM('Table 49'!C146,'Table 49'!C157)*10^6 -> 8342662
A9: Average replacement time | B9: =1/(B7/B8) -> 19.278569
A11: HDV sales | B11: ='Table 49'!C242*1000 -> 279162.05
A12: HDV stock | B12: ='Table 49'!C168*10^6 -> 5303351
A13: Average replacement time | B13: =1/(B11/B12) -> 18.997393
A15: BNEF, bus sales 2021 | B15: 6000
A16: BNEF, bus fleet 2021 | B16: 73000
A17: average replacement time | B17: =1/(B15/B16) -> 12.166667
A19: BNEF, LDV sales 2021 (M) | B19: 14
A20: BNEF, LDV fleet 2021 (M) | B20: 237
A21: average replacement time | B21: =1/(B19/B20) -> 16.928571

Sheet AVL
A1: Vehicle Lifetime (years) | B1: Passenger | C1: Freight
A2: LDVs | B2: =ROUND('Mexico Road Fleet'!AB39,0) -> 24 | C2: =B2 -> 24
A3: HDVs | B3: =ROUND('Mexico Road Fleet'!AC194,0) -> 25 | C3: =B3*About!A64 -> 33.25
A4: aircraft | B4: =ROUND('Mexico AirFleet'!B30,0) -> 15 | C4: =B4 -> 15
A5: rail | B5: =ROUND(Calculations!C22*About!$A$64,0) -> 45 | C5: =B5 -> 45
A6: ships | B6: =ROUND(Calculations!C28*About!$A$64,0) -> 44 | C6: =B6 -> 44
A7: motorbikes | B7: =ROUND('Mexico Road Fleet'!BE118*2,0) -> 11 | C7: =B7 -> 11
